Workbook
Name formatResults: [1]ResultsEXR10!$A$50

Sheet Carbontax
A1: _date_ | B1: 42005 | C1: 42370 | D1: 42736 | E1: 43101 | F1: 43466 | G1: 43831 | H1: 44197 | I1: 44562 | J1: 44927 | K1: 45292 | L1: 45658 | M1: 46023 | N1: 46388 | O1: 46753 | P1: 47119 | Q1: 47484 | R1: 47849 | S1: 48214 | T1: 48580 | U1: 48945 | V1: 49310 | W1: 49675 | X1: 50041 | Y1: 50406 | Z1: 50771 | AA1: 51136 | AB1: 51502 | AC1: 51867 | AD1: 52232 | AE1: 52597 | AF1: 52963 | AG1: 53328 | AH1: 53693 | AI1: 54058 | AJ1: 54424 | AK1: 54789
A2: t2val_ch_0 | B2: 1732.612 | C2: 2615.9682 | D2: 3567.279 | E2: 5115.5759 | F2: 5079.1745 | G2: 5103.7755 | H2: 5088.7002 | I2: 5092.551 | J2: 5104.2054 | K2: 5119.6797 | L2: 5139.079 | M2: 5158.9579 | N2: 5179.4906 | O2: 5200.7738 | P2: 5222.8373 | Q2: 5245.6711 | R2: 5269.128 | S2: 5293.0858 | T2: 5317.4671 | U2: 5342.2313 | V2: 5366.1609 | W2: 5390.9612 | X2: 5416.2398 | Y2: 5441.8279 | Z2: 5467.6651 | AA2: 5490.416 | AB2: 5512.7592 | AC2: 5534.1483 | AD2: 5554.4468 | AE2: 5573.7078 | AF2: 5592.0235 | AG2: 5609.8116 | AH2: 5627.3254 | AI2: 5644.6615 | AJ2: 5661.8296 | AK2: 5678.7958
A3: t2val_ch_2 | B3: 1732.612 | C3: 2615.9682 | D3: 3567.279 | E3: 5115.5759 | F3: 5079.1745 | G3: 5103.7755 | H3: 5088.7002 | I3: 7569.3917 | J3: 11232.675 | K3: 16626.621 | L3: 24553.672 | M3: 25943.06 | N3: 27525.443 | O3: 29261.495 | P3: 31132.872 | Q3: 33132.955 | R3: 36030.744 | S3: 39171.85 | T3: 42577.353 | U3: 46268.496 | V3: 50259.165 | W3: 53371.886 | X3: 56675.216 | Y3: 60176.658 | Z3: 63884.785 | AA3: 67769.06 | AB3: 70975.096 | AC3: 74304.815 | AD3: 77757.164 | AE3: 81333.863 | AF3: 85037.703 | AG3: 88175.325 | AH3: 91401.968 | AI3: 94718.504 | AJ3: 98124.613 | AK3: 101801.73
A4: t2val_sec_0 | B4: 3328.339 | C4: 5086.0564 | D4: 7054.7083 | E4: 10266.712 | F4: 10317.322 | G4: 10570.625 | H4: 10817.961 | I4: 11090.341 | J4: 11377.461 | K4: 11677.661 | L4: 11993.69 | M4: 12356.342 | N4: 12735.048 | O4: 13134.253 | P4: 13556.495 | Q4: 14003.657 | R4: 14461.317 | S4: 14946.603 | T4: 15461.335 | U4: 16006.121 | V4: 16580.456 | W4: 17170.369 | X4: 17788.902 | Y4: 18440.863 | Z4: 19129.968 | AA4: 19855.695 | AB4: 20346.596 | AC4: 20761.778 | AD4: 21161.291 | AE4: 21563.552 | AF4: 21973.051 | AG4: 22445.551 | AH4: 22943.686 | AI4: 23458.204 | AJ4: 23986.036 | AK4: 24525.729
A5: t2val_sec_2 | B5: 3328.339 | C5: 5086.0564 | D5: 7054.7083 | E5: 10266.712 | F5: 10317.322 | G5: 10570.625 | H5: 10817.961 | I5: 16482.564 | J5: 24994.223 | K5: 37711.025 | L5: 56623.026 | M5: 60740.82 | N5: 65481.389 | O5: 70904.953 | P5: 77048.047 | Q5: 83948.931 | R5: 93507.094 | S5: 104268.45 | T5: 116380.64 | U5: 130285.81 | V5: 145958.22 | W5: 159927.29 | X5: 175446.15 | Y5: 192713.42 | Z5: 211935.18 | AA5: 233293.15 | AB5: 250582.3 | AC5: 268194.86 | AD5: 286844 | AE5: 306794.65 | AF5: 328154.74 | AG5: 349115.54 | AH5: 371685.79 | AI5: 395780.87 | AJ5: 421401.23 | AK5: 436882.71
A6: t2val_ci_0 | B6: 3107.2095 | C6: 4745.8395 | D6: 6576.6065 | E6: 9558.8397 | F6: 9599.7992 | G6: 9840.4362 | H6: 10073.275 | I6: 10330.234 | J6: 10601.328 | K6: 10884.974 | L6: 11183.822 | M6: 11528.886 | N6: 11889.519 | O6: 12270.088 | P6: 12673.08 | Q6: 13100.338 | R6: 13538.176 | S6: 14003.218 | T6: 14497.141 | U6: 15020.477 | V6: 15572.723 | W6: 16140.569 | X6: 16736.531 | Y6: 17365.244 | Z6: 18030.32 | AA6: 18731.32 | AB6: 19201.48 | AC6: 19597.629 | AD6: 19978.969 | AE6: 20363.469 | AF6: 20755.365 | AG6: 21207.996 | AH6: 21685.297 | AI6: 22178.317 | AJ6: 22684.092 | AK6: 23201.225
A7: t2val_ci_2 | B7: 3107.2095 | C7: 4745.8395 | D7: 6576.6065 | E7: 9558.8397 | F7: 9599.7992 | G7: 9840.4362 | H7: 10073.275 | I7: 15347.6 | J7: 23264.727 | K7: 35076.698 | L7: 52611.943 | M7: 56411.066 | N7: 60805.749 | O7: 65852.021 | P7: 71583.309 | Q7: 78035.161 | R7: 86968.562 | S7: 97038.66 | T7: 108385.3 | U7: 121441.53 | V7: 136173.04 | W7: 149349.36 | X7: 164010.36 | Y7: 180347.27 | Z7: 198559.01 | AA7: 218821.88 | AB7: 235182.91 | AC7: 251836.64 | AD7: 269483.79 | AE7: 288381.23 | AF7: 308630.66 | AG7: 328544.47 | AH7: 349999.96 | AI7: 372913.66 | AJ7: 397284.21 | AK7: 411844.07
A8: t2val_y_0 | B8: 0.39940733 | C8: 0.61402327 | D8: 0.86245259 | E8: 1.2779238 | F8: 1.2979382 | G8: 1.3256723 | H8: 1.3570559 | I8: 1.3899691 | J8: 1.42405 | K8: 1.4593064 | L8: 1.4961536 | M8: 1.5338708 | N8: 1.5726651 | O8: 1.6125847 | P8: 1.6536551 | Q8: 1.6958998 | R8: 1.7371325 | S8: 1.7789729 | T8: 1.8215694 | U8: 1.8650131 | V8: 1.9091191 | W8: 1.952158 | X8: 1.9957285 | Y8: 2.0400009 | Z8: 2.0850911 | AA8: 2.1303202 | AB8: 2.1657651 | AC8: 2.1990519 | AD8: 2.2309505 | AE8: 2.2619533 | AF8: 2.2924594 | AG8: 2.3291372 | AH8: 2.3675359 | AI8: 2.4074213 | AJ8: 2.4486711 | AK8: 2.4911493
A9: t2val_y_2 | B9: 0.39940733 | C9: 0.61402327 | D9: 0.86245259 | E9: 1.2779238 | F9: 1.2979382 | G9: 1.3256723 | H9: 1.3570559 | I9: 2.0774205 | J9: 3.1823131 | K9: 4.878051 | L9: 7.4854706 | M9: 8.1317442 | N9: 8.8323143 | O9: 9.5968132 | P9: 10.431185 | Q9: 11.340456 | R9: 12.588035 | S9: 13.969563 | T9: 15.499567 | U9: 17.195955 | V9: 19.073631 | W9: 20.655085 | X9: 22.361292 | Y9: 24.20467 | Z9: 26.197195 | AA9: 28.341364 | AB9: 30.124594 | AC9: 31.976948 | AD9: 33.912893 | AE9: 35.943905 | AF9: 38.080927 | AG9: 40.119652 | AH9: 42.286947 | AI9: 44.586451 | AJ9: 47.023247 | AK9: 48.752627
A10: t2val_mat_0 | B10: 220.73011 | C10: 339.60287 | D10: 477.23928 | E10: 706.5943 | F10: 716.22479 | G10: 728.86362 | H10: 743.32846 | I10: 758.71717 | J10: 774.70902 | K10: 791.22737 | L10: 808.37269 | M10: 825.92163 | N10: 843.95679 | O10: 862.55245 | P10: 881.76126 | Q10: 901.623 | R10: 921.40365 | S10: 941.6057 | T10: 962.37312 | U10: 983.77919 | V10: 1005.8233 | W10: 1027.8479 | X10: 1050.3756 | Y10: 1073.5792 | Z10: 1097.5625 | AA10: 1122.2441 | AB10: 1142.9504 | AC10: 1161.9491 | AD10: 1180.0916 | AE10: 1197.8216 | AF10: 1215.3937 | AG10: 1235.2265 | AH10: 1256.0215 | AI10: 1277.4793 | AJ10: 1299.4955 | AK10: 1322.0129
A11: t2val_mat_2 | B11: 220.73011 | C11: 339.60287 | D11: 477.23928 | E11: 706.5943 | F11: 716.22479 | G11: 728.86362 | H11: 743.32846 | I11: 1132.8865 | J11: 1726.3136 | K11: 2629.4491 | L11: 4003.5976 | M11: 4321.6217 | N11: 4666.8071 | O11: 5043.3352 | P11: 5454.3065 | Q11: 5902.4296 | R11: 6525.9434 | S11: 7215.8197 | T11: 7979.8406 | U11: 8827.0896 | V11: 9766.1064 | W11: 10557.272 | X11: 11413.43 | Y11: 12341.95 | Z11: 13349.966 | AA11: 14442.931 | AB11: 15369.256 | AC11: 16326.247 | AD11: 17326.295 | AE11: 18377.469 | AF11: 19485.995 | AG11: 20530.955 | AH11: 21643.544 | AI11: 22822.623 | AJ11: 24069.997 | AK11: 24989.888

Sheet Production
A1: _date_ | B1: 42005 | C1: 42370 | D1: 42736 | E1: 43101 | F1: 43466 | G1: 43831 | H1: 44197 | I1: 44562 | J1: 44927 | K1: 45292 | L1: 45658 | M1: 46023 | N1: 46388 | O1: 46753 | P1: 47119 | Q1: 47484 | R1: 47849 | S1: 48214 | T1: 48580 | U1: 48945 | V1: 49310 | W1: 49675 | X1: 50041 | Y1: 50406 | Z1: 50771 | AA1: 51136 | AB1: 51502 | AC1: 51867 | AD1: 52232 | AE1: 52597 | AF1: 52963 | AG1: 53328 | AH1: 53693 | AI1: 54058 | AJ1: 54424 | AK1: 54789
A2: y_2 | B2: 3853313.2 | C2: 3912706 | D2: 3969876.1 | E2: 4024755.4 | F2: 4088145.3 | G2: 4171936.6 | H2: 4263906.9 | I2: 4360824.3 | J2: 4461076 | K2: 4565013.1 | L2: 4674461.5 | M2: 4781173.6 | N2: 4890805.7 | O2: 5004952.2 | P2: 5123593.1 | Q2: 5246404.6 | R2: 5368117.6 | S2: 5492305 | T2: 5619415 | U2: 5750622.7 | V2: 5885076.1 | W2: 6017792 | X2: 6153485 | Y2: 6293015 | Z2: 6436916.3 | AA2: 6583901.6 | AB2: 6695256.5 | AC2: 6797288.4 | AD2: 6895125 | AE2: 6991049.2 | AF2: 7086276.5 | AG2: 7197899.2 | AH2: 7314531 | AI2: 7435183.8 | AJ2: 7559355.3 | AK2: 7559353.5
A3: y_0 | B3: 3853313.2 | C3: 3912706 | D3: 3969876.1 | E3: 4024755.4 | F3: 4088145.3 | G3: 4171936.6 | H3: 4263906.9 | I3: 4359618.4 | J3: 4458308.3 | K3: 4560188.1 | L3: 4666440.2 | M3: 4774219.1 | N3: 4885003.3 | O3: 4999232.4 | P3: 5117103.2 | Q3: 5238762.4 | R3: 5358927.1 | S3: 5481621.1 | T3: 5607373.8 | U3: 5736558.1 | V3: 5868910.1 | W3: 5999989.6 | X3: 6134079.6 | Y3: 6271945.2 | Z3: 6414179.7 | AA3: 6559560.4 | AB3: 6669485 | AC3: 6770186.9 | AD3: 6866708.2 | AE3: 6961277.5 | AF3: 7055088.6 | AG3: 7165409.7 | AH3: 7280680.5 | AI3: 7399900.6 | AJ3: 7522622.6 | AK3: 7648512.4
A4: y_sagr_2 | B4: 81781.721 | C4: 82864.854 | D4: 83954.428 | E4: 85070.368 | F4: 86402.711 | G4: 88248.951 | H4: 90338.128 | I4: 92595.975 | J4: 94974.047 | K4: 97477.126 | L4: 100154.35 | M4: 102717.07 | N4: 105327.47 | O4: 108044.43 | P4: 110870.8 | Q4: 113794.76 | R4: 116674.3 | S4: 119598.47 | T4: 122571.03 | U4: 125608.81 | V4: 128692.33 | W4: 131684.09 | X4: 134707.01 | Y4: 137777.88 | Z4: 140903.6 | AA4: 144037.33 | AB4: 146493.83 | AC4: 148791.8 | AD4: 150990.86 | AE4: 153128.11 | AF4: 155231.91 | AG4: 157741.17 | AH4: 160364.66 | AI4: 163087.12 | AJ4: 165899.01 | AK4: 165898.95
A5: y_sagr_0 | B5: 81781.721 | C5: 82864.854 | D5: 83954.428 | E5: 85070.368 | F5: 86402.711 | G5: 88248.951 | H5: 90338.128 | I5: 92529.136 | J5: 94797.872 | K5: 97144.867 | L5: 99597.754 | M5: 102108.56 | N5: 104691.06 | O5: 107348.48 | P5: 110082.5 | Q5: 112894.7 | R5: 115639.53 | S5: 118424.81 | T5: 121260.42 | U5: 124152.44 | V5: 127088.54 | W5: 129953.6 | X5: 132854.06 | Y5: 135801.23 | Z5: 138802.85 | AA5: 141813.72 | AB5: 144173.26 | AC5: 146389.13 | AD5: 148512.59 | AE5: 150576.43 | AF5: 152607.2 | AG5: 155048.81 | AH5: 157604.98 | AI5: 160260.12 | AJ5: 163006.08 | AK5: 165833.82
A6: y_sfor_2 | B6: 6531.7299 | C6: 6471.6699 | D6: 6414.2951 | E6: 6352.2464 | F6: 6321.1321 | G6: 6312.5703 | H6: 6348.7268 | I6: 6364.7174 | J6: 6364.3128 | K6: 6349.7594 | L6: 6325.3963 | M6: 6361.02 | N6: 6428.9781 | O6: 6518.0724 | P6: 6622.3473 | Q6: 6739.3596 | R6: 6881.3153 | S6: 7037.6455 | T6: 7206.9837 | U6: 7389.5563 | V6: 7583.8257 | W6: 7787.4116 | X6: 8004.6625 | Y6: 8236.9784 | Z6: 8486.048 | AA6: 8748.8769 | AB6: 8842.7354 | AC6: 8889.9437 | AD6: 8928.8483 | AE6: 8970.0067 | AF6: 9015.322 | AG6: 9080.9683 | AH6: 9153.7639 | AI6: 9231.3991 | AJ6: 9312.8699 | AK6: 9312.7457
A7: y_sfor_0 | B7: 6531.7299 | C7: 6471.6699 | D7: 6414.2951 | E7: 6352.2464 | F7: 6321.1321 | G7: 6312.5703 | H7: 6348.7268 | I7: 6399.2089 | J7: 6458.8663 | K7: 6526.5421 | L7: 6605.0143 | M7: 6685.6809 | N7: 6771.9759 | O7: 6866.9722 | P7: 6971.9881 | Q7: 7087.9427 | R7: 7230.8427 | S7: 7389.0387 | T7: 7560.5856 | U7: 7745.3059 | V7: 7941.4866 | W7: 8147.2778 | X7: 8366.9599 | Y7: 8601.959 | Z7: 8854.0556 | AA7: 9120.0677 | AB7: 9214.8756 | AC7: 9261.199 | AD7: 9298.0476 | AE7: 9336.3971 | AF7: 9378.3678 | AG7: 9440.672 | AH7: 9509.6481 | AI7: 9582.8133 | AJ7: 9659.1426 | AK7: 9738.1991
A8: y_sfoo_2 | B8: 157757.79 | C8: 160031.53 | D8: 162244.69 | E8: 164513.46 | F8: 167179.37 | G8: 170803.28 | H8: 174784.15 | I8: 179103.98 | J8: 183677.79 | K8: 188533.26 | L8: 193791.51 | M8: 198723.72 | N8: 203709.39 | O8: 208867.45 | P8: 214204.15 | Q8: 219700.25 | R8: 225149.14 | S8: 230673.29 | T8: 236277.04 | U8: 242005.2 | V8: 247804.84 | W8: 253459.86 | X8: 259165.21 | Y8: 264949.42 | Z8: 270826.85 | AA8: 276691.04 | AB8: 281470.6 | AC8: 285938.96 | AD8: 290191.08 | AE8: 294303.16 | AF8: 298336.74 | AG8: 302991.16 | AH8: 307851.93 | AI8: 312906.93 | AJ8: 318138.25 | AK8: 318138.21
A9: y_sfoo_0 | B9: 157757.79 | C9: 160031.53 | D9: 162244.69 | E9: 164513.46 | F9: 167179.37 | G9: 170803.28 | H9: 174784.15 | I9: 178926.43 | J9: 183198.6 | K9: 187608.26 | L9: 192218.52 | M9: 196926.61 | N9: 201759.32 | O9: 206722.29 | P9: 211818.46 | Q9: 217050.84 | R9: 222191.11 | S9: 227399.51 | T9: 232690.11 | U9: 238074.92 | V9: 243525.16 | W9: 248881.16 | X9: 254298.19 | Y9: 259793.4 | Z9: 265382.42 | AA9: 270961.92 | AB9: 275520.12 | AC9: 279801.16 | AD9: 283880.48 | AE9: 287824.13 | AF9: 291689.11 | AG9: 296186.85 | AH9: 300891.14 | AI9: 305789.5 | AJ9: 310867.16 | AK9: 316104.64
A10: y_sveh_2 | B10: 125590.98 | C10: 129264.51 | D10: 132710.97 | E10: 135743.06 | F10: 139439.99 | G10: 144264.85 | H10: 148517.26 | I10: 152606.8 | J10: 156674.94 | K10: 160798.26 | L10: 165016.16 | M10: 169583.22 | N10: 174440.45 | O10: 179465.37 | P10: 184606.04 | Q10: 189854.03 | R10: 194682.17 | S10: 199588.04 | T10: 204610.02 | U10: 209744.08 | V10: 215006.12 | W10: 219944.43 | X10: 224995.11 | Y10: 230158.05 | Z10: 235433.62 | AA10: 240792.36 | AB10: 243878.08 | AC10: 246891.77 | AD10: 249898.22 | AE10: 252923.81 | AF10: 255980.44 | AG10: 260550.78 | AH10: 265271 | AI10: 270102.5 | AJ10: 275032.27 | AK10: 275032.21
A11: y_sveh_0 | B11: 125590.98 | C11: 129264.51 | D11: 132710.97 | E11: 135743.06 | F11: 139439.99 | G11: 144264.85 | H11: 148517.26 | I11: 152698.56 | J11: 156934.22 | K11: 161281.18 | L11: 165785.3 | M11: 170377.87 | N11: 175112.56 | O11: 179994.16 | P11: 185024.79 | Q11: 190206.93 | R11: 195026.46 | S11: 199953.98 | T11: 205005.85 | U11: 210190.35 | V11: 215501.7 | W11: 220461.57 | X11: 225524.75 | Y11: 230705.43 | Z11: 236010.23 | AA11: 241411 | AB11: 244541.84 | AC11: 247608.69 | AD11: 250677.1 | AE11: 253771.49 | AF11: 256901.22 | AG11: 261539.42 | AH11: 266324.86 | AI11: 271221.33 | AJ11: 276216.81 | AK11: 281306.77
A12: y_sgla_2 | B12: 22090.808 | C12: 22423.532 | D12: 22739.387 | E12: 23022.685 | F12: 23348.847 | G12: 23806.982 | H12: 24335.49 | I12: 24888.024 | J12: 25443.202 | K12: 25992.842 | L12: 26538.068 | M12: 27084.731 | N12: 27661.836 | O12: 28280.151 | P12: 28940.143 | Q12: 29638.772 | R12: 30336.083 | S12: 31055.07 | T12: 31797.682 | U12: 32569.135 | V12: 33366.655 | W12: 34160.223 | X12: 34979.338 | Y12: 35829.356 | Z12: 36713.537 | AA12: 37628.024 | AB12: 38357.943 | AC12: 39032.274 | AD12: 39676.663 | AE12: 40306.103 | AF12: 40929.327 | AG12: 41656.034 | AH12: 42414.172 | AI12: 43197.392 | AJ12: 44002.454 | AK12: 44002.406
... A67: y_seot_0 | B67: 109.60567 | C67: 110.5762 | D67: 111.04269 | E67: 111.41278 | F67: 111.98891 | G67: 113.20091 | H67: 115.73033 | I67: 119.06262 | J67: 122.70921 | K67: 126.59096 | L67: 130.7574 | M67: 135.64191 | N67: 140.57961 | O67: 145.86704 | P67: 151.58976 | Q67: 157.79219 | R67: 163.73257 | S67: 170.17575 | T67: 177.1992 | U67: 184.9351 | V67: 193.52184 | W67: 203.00727 | X67: 213.69682 | Y67: 225.84724 | Z67: 239.72962 | AA67: 255.57415 | AB67: 261.83088 | AC67: 264.80886 | AD67: 267.15077 | AE67: 269.57115 | AF67: 272.20373 | AG67: 275.59797 | AH67: 279.3564 | AI67: 283.32845 | AJ67: 287.44867 | AK67: 291.68791

Sheet Capital
A1: _date_ | B1: 42005 | C1: 42370 | D1: 42736 | E1: 43101 | F1: 43466 | G1: 43831 | H1: 44197 | I1: 44562 | J1: 44927 | K1: 45292 | L1: 45658 | M1: 46023 | N1: 46388 | O1: 46753 | P1: 47119 | Q1: 47484 | R1: 47849 | S1: 48214 | T1: 48580 | U1: 48945 | V1: 49310 | W1: 49675 | X1: 50041 | Y1: 50406 | Z1: 50771 | AA1: 51136 | AB1: 51502 | AC1: 51867 | AD1: 52232 | AE1: 52597 | AF1: 52963 | AG1: 53328 | AH1: 53693 | AI1: 54058 | AJ1: 54424 | AK1: 54789
A2: f_k_2 | B2: 5223356.6 | C2: 5284516.8 | D2: 5346672.5 | E2: 5408276.4 | F2: 5470776.1 | G2: 5538263.2 | H2: 5610936 | I2: 5688588.3 | J2: 5770561.2 | K2: 5856073.1 | L2: 5944430.8 | M2: 6035909.5 | N2: 6131056 | O2: 6230528 | P2: 6334926.3 | Q2: 6444738 | R2: 6559870.1 | S2: 6680353 | T2: 6806295.8 | U2: 6937856.9 | V2: 7075194.1 | W2: 7218151.5 | X2: 7366806.3 | Y2: 7521365.5 | Z2: 7682100.2 | AA2: 7849189.6 | AB2: 8019780.3 | AC2: 8192058.4 | AD2: 8365016.4 | AE2: 8538123.5 | AF2: 8711119.3 | AG2: 8885212.5 | AH2: 9061119.1 | AI2: 9239284.2 | AJ2: 9420016.1 | AK2: 9591419.1
A3: f_k_0 | B3: 5223356.6 | C3: 5284516.8 | D3: 5346672.5 | E3: 5408276.4 | F3: 5470776.1 | G3: 5538263.2 | H3: 5610936 | I3: 5689113.8 | J3: 5772827.9 | K3: 5862074.2 | L3: 5956965.9 | M3: 6057471.7 | N3: 6163606.9 | O3: 6275447.8 | P3: 6393111.7 | Q3: 6516742.8 | R3: 6646081.9 | S3: 6781084.5 | T3: 6921828 | U3: 7068456.7 | V3: 7221108.1 | W3: 7379556.6 | X3: 7543817.3 | Y3: 7714049.9 | Z3: 7890501.9 | AA3: 8073340.2 | AB3: 8259602.1 | AC3: 8447412.6 | AD3: 8635742.4 | AE3: 8824063.6 | AF3: 9012131.8 | AG3: 9201193.4 | AH3: 9391971.5 | AI3: 9584902.6 | AJ3: 9780286.2 | AK3: 9978349.5
A4: f_k_sagr_2 | B4: 47210.231 | C4: 47758.923 | D4: 48311.58 | E4: 48860.241 | F4: 49420.185 | G4: 50030.867 | H4: 50697.565 | I4: 51423.148 | J4: 52206.101 | K4: 53043.828 | L4: 53935.194 | M4: 54879.384 | N4: 55878.062 | O4: 56935.165 | P4: 58054.767 | Q4: 59240.027 | R4: 60487.805 | S4: 61796.4 | T4: 63164.751 | U4: 64592.432 | V4: 66078.555 | W4: 67617.895 | X4: 69208.047 | Y4: 70848.074 | Z4: 72537.618 | AA4: 74274.646 | AB4: 76032.515 | AC4: 77796.316 | AD4: 79557.621 | AE4: 81311.462 | AF4: 83055.005 | AG4: 84802.289 | AH4: 86561.246 | AI4: 88336.913 | AJ4: 90132.962 | AK4: 91834.34
A5: f_k_sagr_0 | B5: 47210.231 | C5: 47758.923 | D5: 48311.58 | E5: 48860.241 | F5: 49420.185 | G5: 50030.867 | H5: 50697.565 | I5: 51425.216 | J5: 52215.028 | K5: 53067.419 | L5: 53983.791 | M5: 54964.123 | N5: 56008.555 | O5: 57117.414 | P5: 58291.127 | Q5: 59530.176 | R5: 60829.856 | S5: 62187.888 | T5: 63603.212 | U5: 65075.346 | V5: 66603.457 | W5: 68182.425 | X5: 69809.833 | Y5: 71484.609 | Z5: 73206.329 | AA5: 74972.955 | AB5: 76757.872 | AC5: 78546.692 | AD5: 80331.509 | AE5: 82107.784 | AF5: 83873.055 | AG5: 85641.982 | AH5: 87422.754 | AI5: 89220.522 | AJ5: 91039.102 | AK5: 92881.509
A6: f_k_sfor_2 | B6: 1844.3596 | C6: 1862.9368 | D6: 1878.0952 | E6: 1889.0726 | F6: 1897.012 | G6: 1903.8069 | H6: 1909.9698 | I6: 1915.1641 | J6: 1918.771 | K6: 1920.1725 | L6: 1918.8639 | M6: 1916.2022 | N6: 1913.3473 | O6: 1911.1252 | P6: 1910.1044 | Q6: 1910.6956 | R6: 1913.3912 | S6: 1918.5374 | T6: 1926.3985 | U6: 1937.1995 | V6: 1951.124 | W6: 1968.3433 | X6: 1989.0662 | Y6: 2013.5226 | Z6: 2041.9633 | AA6: 2074.5869 | AB6: 2108.739 | AC6: 2142.8078 | AD6: 2176.1872 | AE6: 2208.7647 | AF6: 2240.6071 | AG6: 2272.0944 | AH6: 2303.4692 | AI6: 2334.8819 | AJ6: 2366.434 | AK6: 2396.3514
A7: f_k_sfor_0 | B7: 1844.3596 | C7: 1862.9368 | D7: 1878.0952 | E7: 1889.0726 | F7: 1897.012 | G7: 1903.8069 | H7: 1909.9698 | I7: 1916.0534 | J7: 1922.3459 | K7: 1929.0489 | L7: 1936.3928 | M7: 1944.4666 | N7: 1953.378 | O7: 1963.2924 | P7: 1974.4104 | Q7: 1986.9532 | R7: 2001.4157 | S7: 2018.1719 | T7: 2037.5125 | U7: 2059.6904 | V7: 2084.9088 | W7: 2113.3221 | X7: 2145.1377 | Y7: 2180.5973 | Z7: 2219.9748 | AA7: 2263.4893 | AB7: 2308.2106 | AC7: 2352.3444 | AD7: 2395.208 | AE7: 2436.6722 | AF7: 2476.8148 | AG7: 2516.0475 | AH7: 2554.6294 | AI7: 2592.7176 | AJ7: 2630.4181 | AK7: 2667.8136
A8: f_k_sfoo_2 | B8: 74516.296 | C8: 75380.546 | D8: 76245.432 | E8: 77097.683 | F8: 77967.119 | G8: 78919.202 | H8: 79956.673 | I8: 81080.568 | J8: 82285.343 | K8: 83564.155 | L8: 84912.794 | M8: 86330.893 | N8: 87822.296 | O8: 89394.204 | P8: 91053.572 | Q8: 92805.593 | R8: 94646.924 | S8: 96575.56 | T8: 98590.113 | U8: 100690.38 | V8: 102875.13 | W8: 105138.33 | X8: 107477.41 | Y8: 109891.62 | Z8: 112380.85 | AA8: 114941.85 | AB8: 117541.42 | AC8: 120160 | AD8: 122785.75 | AE8: 125411.35 | AF8: 128032.55 | AG8: 130666.39 | AH8: 133323.33 | AI8: 136010.73 | AJ8: 138734.26 | AK8: 141315.64
A9: f_k_sfoo_0 | B9: 74516.296 | C9: 75380.546 | D9: 76245.432 | E9: 77097.683 | F9: 77967.119 | G9: 78919.202 | H9: 79956.673 | I9: 81084.988 | J9: 82304.365 | K9: 83614.42 | L9: 85016.961 | M9: 86511.437 | N9: 88097.672 | O9: 89775.852 | P9: 91546.371 | Q9: 93409.754 | R9: 95360.103 | S9: 97394.478 | T9: 99511.43 | U9: 101710.29 | V9: 103989.66 | W9: 106343.33 | X9: 108768.44 | Y9: 111263.73 | Z9: 113828.78 | AA9: 116460.1 | AB9: 119124.25 | AC9: 121802.28 | AD9: 124483 | AE9: 127159.6 | AF9: 129828.3 | AG9: 132507 | AH9: 135206.42 | AI9: 137934.02 | AJ9: 140695.67 | AK9: 143496.1
A10: f_k_sveh_2 | B10: 401516.46 | C10: 406575.73 | D10: 412173.26 | E10: 418188.34 | F10: 424751.47 | G10: 432188.8 | H10: 440398.75 | I10: 449272.21 | J10: 458722.59 | K10: 468688.5 | L10: 479125.39 | M10: 490099.35 | N10: 501680.89 | O10: 513910.99 | P10: 526805.92 | Q10: 540369.36 | R10: 554488.29 | S10: 569117.54 | T10: 584243.41 | U10: 599860.31 | V10: 615968.53 | W10: 632479.25 | X10: 649366.43 | Y10: 666624.87 | Z10: 684255 | AA10: 702251.87 | AB10: 720115.27 | AC10: 737665.57 | AD10: 754849.15 | AE10: 771657.73 | AF10: 788099.88 | AG10: 804504.24 | AH10: 820999.96 | AI10: 837638.9 | AJ10: 854445.65 | AK10: 870309.58
A11: f_k_sveh_0 | B11: 401516.46 | C11: 406575.73 | D11: 412173.26 | E11: 418188.34 | F11: 424751.47 | G11: 432188.8 | H11: 440398.75 | I11: 449312.62 | J11: 458889.49 | K11: 469111.44 | L11: 479978.65 | M11: 491482.86 | N11: 503624.56 | O11: 516407.85 | P11: 529837.94 | Q11: 543920.36 | R11: 558554.13 | S11: 573703.98 | T11: 589360.68 | U11: 605524.47 | V11: 622196.57 | W11: 639277.58 | X11: 656734.26 | Y11: 674559.07 | Z11: 692753.45 | AA11: 711314.61 | AB11: 729734.96 | AC11: 747834.11 | AD11: 765560.87 | AE11: 782910.22 | AF11: 799893.73 | AG11: 816844.01 | AH11: 833890.74 | AI11: 851085.67 | AJ11: 868453.42 | AK11: 886009.08
A12: f_k_sgla_2 | B12: 16080.628 | C12: 16265.327 | D12: 16450.515 | E12: 16632.22 | F12: 16815.306 | G12: 17012.677 | H12: 17226.436 | I12: 17456.184 | J12: 17699.289 | K12: 17952.155 | L12: 18211.041 | M12: 18477.243 | N12: 18753.224 | O12: 19041.946 | P12: 19346.225 | Q12: 19668.449 | R12: 20008.659 | S12: 20367.26 | T12: 20744.852 | U12: 21142.254 | V12: 21560.224 | W12: 21998.519 | X12: 22457.712 | Y12: 22938.811 | Z12: 23443.021 | AA12: 23971.356 | AB12: 24515.536 | AC12: 25070.178 | AD12: 25632.14 | AE12: 26199.656 | AF12: 26771.76 | AG12: 27352.727 | AH12: 27944.969 | AI12: 28549.878 | AJ12: 29168.333 | AK12: 29758.135
... A67: f_k_seot_0 | B67: 65.167563 | C67: 65.909608 | D67: 66.627414 | E67: 67.307164 | F67: 67.958237 | G67: 68.612931 | H67: 69.320547 | I67: 70.125007 | J67: 71.047373 | K67: 72.098366 | L67: 73.287308 | M67: 74.639551 | N67: 76.160003 | O67: 77.857679 | P67: 79.745994 | Q67: 81.841046 | R67: 84.131611 | S67: 86.62643 | T67: 89.343617 | U67: 92.308713 | V67: 95.5542 | W67: 99.116085 | X67: 103.04261 | Y67: 107.39513 | Z67: 112.24878 | AA67: 117.69081 | AB67: 123.35009 | AC67: 128.95549 | AD67: 134.38849 | AE67: 139.6135 | AF67: 144.62836 | AG67: 149.4644 | AH67: 154.14672 | AI67: 158.6919 | AJ67: 163.1113 | AK67: 167.41361

Sheet Results
A1: NB : on crée ici une liste : - globale, qui fusionne les sorties des reportings 1, 2 et 3 - "rationalisée" : suppression des doublons, et regroupements par thématique On continue par la suite à avoir 2 Excels de reporting (un "energie", fusion des reportings 1 et 2), et un "économie" (reporting 3)), dans lesquels on copiera cet onglet "results" (généré automatiquement par EViews). --> puis voir à la fin si on peut pas importer les graphs et tableaux dans l'excel automatiquement généré (éviterait les copiés collés, mais à voir si ça prend trop de temps, et si c'est pas trop gros comme excel)
A2: Nom du bloc de variables utilisé dans le code | B2: Sous-bloc de variables pour plus de lisibilité dans le Excel | E2: Year | F2: =date!B3 -> 2015 | G2: =date!C3 -> 2016 | H2: =date!D3 -> 2017 | I2: =date!E3 -> 2018 | J2: =date!F3 -> 2019 | K2: =date!G3 -> 2020 | L2: =date!H3 -> 2021 | M2: =date!I3 -> 2022 | ... AO2: =date!AK3 -> 2050
A3: HYBRID | B3: AUTOMOBILES (thousands) | C3: TOTAL STOCK SHOCK | E3: AUTO_2 | F3: =VLOOKUP($E3,Hybrid!$1:$1048576,MATCH(DATE(F$2,1,1),Hybrid!$A$1:$LI$1),FALSE) -> 32317.941 | G3: =VLOOKUP($E3,Hybrid!$1:$1048576,MATCH(DATE(G$2,1,1),Hybrid!$A$1:$LI$1),FALSE) -> 31989.266 | H3: =VLOOKUP($E3,Hybrid!$1:$1048576,MATCH(DATE(H$2,1,1),Hybrid!$A$1:$LI$1),FALSE) -> 31766.848 | I3: =VLOOKUP($E3,Hybrid!$1:$1048576,MATCH(DATE(I$2,1,1),Hybrid!$A$1:$LI$1),FALSE) -> 31556.566 | J3: =VLOOKUP($E3,Hybrid!$1:$1048576,MATCH(DATE(J$2,1,1),Hybrid!$A$1:$LI$1),FALSE) -> 31558.174 | K3: =VLOOKUP($E3,Hybrid!$1:$1048576,MATCH(DATE(K$2,1,1),Hybrid!$A$1:$LI$1),FALSE) -> 31942.005 | L3: =VLOOKUP($E3,Hybrid!$1:$1048576,MATCH(DATE(L$2,1,1),Hybrid!$A$1:$LI$1),FALSE) -> 32251.021 | M3: =VLOOKUP($E3,Hybrid!$1:$1048576,MATCH(DATE(M$2,1,1),Hybrid!$A$1:$LI$1),FALSE) -> 32560.604 | ... AO3: =VLOOKUP($E3,Hybrid!$1:$1048576,MATCH(DATE(AO$2,1,1),Hybrid!$A$1:$LI$1),FALSE) -> 44134.237
C4: OIL | E4: AUTO_cfut_2 | F4: =VLOOKUP($E4,Hybrid!$1:$1048576,MATCH(DATE(F$2,1,1),Hybrid!$A$1:$LI$1),FALSE) -> 32271.24 | G4: =VLOOKUP($E4,Hybrid!$1:$1048576,MATCH(DATE(G$2,1,1),Hybrid!$A$1:$LI$1),FALSE) -> 31924.248 | H4: =VLOOKUP($E4,Hybrid!$1:$1048576,MATCH(DATE(H$2,1,1),Hybrid!$A$1:$LI$1),FALSE) -> 31683.81 | I4: =VLOOKUP($E4,Hybrid!$1:$1048576,MATCH(DATE(I$2,1,1),Hybrid!$A$1:$LI$1),FALSE) -> 31454.989 | J4: =VLOOKUP($E4,Hybrid!$1:$1048576,MATCH(DATE(J$2,1,1),Hybrid!$A$1:$LI$1),FALSE) -> 31432.993 | K4: =VLOOKUP($E4,Hybrid!$1:$1048576,MATCH(DATE(K$2,1,1),Hybrid!$A$1:$LI$1),FALSE) -> 31788.805 | L4: =VLOOKUP($E4,Hybrid!$1:$1048576,MATCH(DATE(L$2,1,1),Hybrid!$A$1:$LI$1),FALSE) -> 32071.448 | M4: =VLOOKUP($E4,Hybrid!$1:$1048576,MATCH(DATE(M$2,1,1),Hybrid!$A$1:$LI$1),FALSE) -> 32354.504 | ... AO4: =VLOOKUP($E4,Hybrid!$1:$1048576,MATCH(DATE(AO$2,1,1),Hybrid!$A$1:$LI$1),FALSE) -> 39550.518
D5: class A | E5: AUTO_ca_cfut_2 | F5: =VLOOKUP($E5,Hybrid!$1:$1048576,MATCH(DATE(F$2,1,1),Hybrid!$A$1:$LI$1),FALSE) -> 7095.7005 | G5: =VLOOKUP($E5,Hybrid!$1:$1048576,MATCH(DATE(G$2,1,1),Hybrid!$A$1:$LI$1),FALSE) -> 7159.6915 | H5: =VLOOKUP($E5,Hybrid!$1:$1048576,MATCH(DATE(H$2,1,1),Hybrid!$A$1:$LI$1),FALSE) -> 7248.7731 | I5: =VLOOKUP($E5,Hybrid!$1:$1048576,MATCH(DATE(I$2,1,1),Hybrid!$A$1:$LI$1),FALSE) -> 7341.6733 | J5: =VLOOKUP($E5,Hybrid!$1:$1048576,MATCH(DATE(J$2,1,1),Hybrid!$A$1:$LI$1),FALSE) -> 7498.2843 | K5: =VLOOKUP($E5,Hybrid!$1:$1048576,MATCH(DATE(K$2,1,1),Hybrid!$A$1:$LI$1),FALSE) -> 7766.7593 | L5: =VLOOKUP($E5,Hybrid!$1:$1048576,MATCH(DATE(L$2,1,1),Hybrid!$A$1:$LI$1),FALSE) -> 8009.8192 | M5: =VLOOKUP($E5,Hybrid!$1:$1048576,MATCH(DATE(M$2,1,1),Hybrid!$A$1:$LI$1),FALSE) -> 8254.162 | ... AO5: =VLOOKUP($E5,Hybrid!$1:$1048576,MATCH(DATE(AO$2,1,1),Hybrid!$A$1:$LI$1),FALSE) -> 20603.905
D6: class B | E6: AUTO_cb_cfut_2 | F6: =VLOOKUP($E6,Hybrid!$1:$1048576,MATCH(DATE(F$2,1,1),Hybrid!$A$1:$LI$1),FALSE) -> 8251.2564 | G6: =VLOOKUP($E6,Hybrid!$1:$1048576,MATCH(DATE(G$2,1,1),Hybrid!$A$1:$LI$1),FALSE) -> 8200.0167 | H6: =VLOOKUP($E6,Hybrid!$1:$1048576,MATCH(DATE(H$2,1,1),Hybrid!$A$1:$LI$1),FALSE) -> 8180.1563 | I6: =VLOOKUP($E6,Hybrid!$1:$1048576,MATCH(DATE(I$2,1,1),Hybrid!$A$1:$LI$1),FALSE) -> 8168.7824 | J6: =VLOOKUP($E6,Hybrid!$1:$1048576,MATCH(DATE(J$2,1,1),Hybrid!$A$1:$LI$1),FALSE) -> 8221.3545 | K6: =VLOOKUP($E6,Hybrid!$1:$1048576,MATCH(DATE(K$2,1,1),Hybrid!$A$1:$LI$1),FALSE) -> 8384.8744 | L6: =VLOOKUP($E6,Hybrid!$1:$1048576,MATCH(DATE(L$2,1,1),Hybrid!$A$1:$LI$1),FALSE) -> 8529.766 | M6: =VLOOKUP($E6,Hybrid!$1:$1048576,MATCH(DATE(M$2,1,1),Hybrid!$A$1:$LI$1),FALSE) -> 8678.75 | ... AO6: =VLOOKUP($E6,Hybrid!$1:$1048576,MATCH(DATE(AO$2,1,1),Hybrid!$A$1:$LI$1),FALSE) -> 11614.849
D7: class C | E7: AUTO_cc_cfut_2 | F7: =VLOOKUP($E7,Hybrid!$1:$1048576,MATCH(DATE(F$2,1,1),Hybrid!$A$1:$LI$1),FALSE) -> 6777.6025 | G7: =VLOOKUP($E7,Hybrid!$1:$1048576,MATCH(DATE(G$2,1,1),Hybrid!$A$1:$LI$1),FALSE) -> 6658.6926 | H7: =VLOOKUP($E7,Hybrid!$1:$1048576,MATCH(DATE(H$2,1,1),Hybrid!$A$1:$LI$1),FALSE) -> 6566.988 | I7: =VLOOKUP($E7,Hybrid!$1:$1048576,MATCH(DATE(I$2,1,1),Hybrid!$A$1:$LI$1),FALSE) -> 6484.9391 | J7: =VLOOKUP($E7,Hybrid!$1:$1048576,MATCH(DATE(J$2,1,1),Hybrid!$A$1:$LI$1),FALSE) -> 6449.5485 | K7: =VLOOKUP($E7,Hybrid!$1:$1048576,MATCH(DATE(K$2,1,1),Hybrid!$A$1:$LI$1),FALSE) -> 6493.8251 | L7: =VLOOKUP($E7,Hybrid!$1:$1048576,MATCH(DATE(L$2,1,1),Hybrid!$A$1:$LI$1),FALSE) -> 6529.5432 | M7: =VLOOKUP($E7,Hybrid!$1:$1048576,MATCH(DATE(M$2,1,1),Hybrid!$A$1:$LI$1),FALSE) -> 6570.4856 | ... AO7: =VLOOKUP($E7,Hybrid!$1:$1048576,MATCH(DATE(AO$2,1,1),Hybrid!$A$1:$LI$1),FALSE) -> 5357.1708
D8: class D | E8: AUTO_cd_cfut_2 | F8: =VLOOKUP($E8,Hybrid!$1:$1048576,MATCH(DATE(F$2,1,1),Hybrid!$A$1:$LI$1),FALSE) -> 4159.6639 | G8: =VLOOKUP($E8,Hybrid!$1:$1048576,MATCH(DATE(G$2,1,1),Hybrid!$A$1:$LI$1),FALSE) -> 4061.0488 | H8: =VLOOKUP($E8,Hybrid!$1:$1048576,MATCH(DATE(H$2,1,1),Hybrid!$A$1:$LI$1),FALSE) -> 3977.3705 | I8: =VLOOKUP($E8,Hybrid!$1:$1048576,MATCH(DATE(I$2,1,1),Hybrid!$A$1:$LI$1),FALSE) -> 3897.1966 | J8: =VLOOKUP($E8,Hybrid!$1:$1048576,MATCH(DATE(J$2,1,1),Hybrid!$A$1:$LI$1),FALSE) -> 3839.5055 | K8: =VLOOKUP($E8,Hybrid!$1:$1048576,MATCH(DATE(K$2,1,1),Hybrid!$A$1:$LI$1),FALSE) -> 3822.0886 | L8: =VLOOKUP($E8,Hybrid!$1:$1048576,MATCH(DATE(L$2,1,1),Hybrid!$A$1:$LI$1),FALSE) -> 3799.3302 | M8: =VLOOKUP($E8,Hybrid!$1:$1048576,MATCH(DATE(M$2,1,1),Hybrid!$A$1:$LI$1),FALSE) -> 3776.8536 | ... AO8: =VLOOKUP($E8,Hybrid!$1:$1048576,MATCH(DATE(AO$2,1,1),Hybrid!$A$1:$LI$1),FALSE) -> 1140.7951
D9: class E | E9: AUTO_ce_cfut_2 | F9: =VLOOKUP($E9,Hybrid!$1:$1048576,MATCH(DATE(F$2,1,1),Hybrid!$A$1:$LI$1),FALSE) -> 2503.7292 | G9: =VLOOKUP($E9,Hybrid!$1:$1048576,MATCH(DATE(G$2,1,1),Hybrid!$A$1:$LI$1),FALSE) -> 2446.6199 | H9: =VLOOKUP($E9,Hybrid!$1:$1048576,MATCH(DATE(H$2,1,1),Hybrid!$A$1:$LI$1),FALSE) -> 2396.9821 | I9: =VLOOKUP($E9,Hybrid!$1:$1048576,MATCH(DATE(I$2,1,1),Hybrid!$A$1:$LI$1),FALSE) -> 2346.9867 | J9: =VLOOKUP($E9,Hybrid!$1:$1048576,MATCH(DATE(J$2,1,1),Hybrid!$A$1:$LI$1),FALSE) -> 2307.6163 | K9: =VLOOKUP($E9,Hybrid!$1:$1048576,MATCH(DATE(K$2,1,1),Hybrid!$A$1:$LI$1),FALSE) -> 2289.8168 | L9: =VLOOKUP($E9,Hybrid!$1:$1048576,MATCH(DATE(L$2,1,1),Hybrid!$A$1:$LI$1),FALSE) -> 2267.4709 | M9: =VLOOKUP($E9,Hybrid!$1:$1048576,MATCH(DATE(M$2,1,1),Hybrid!$A$1:$LI$1),FALSE) -> 2243.2053 | ... AO9: =VLOOKUP($E9,Hybrid!$1:$1048576,MATCH(DATE(AO$2,1,1),Hybrid!$A$1:$LI$1),FALSE) -> 476.7991
D10: class F | E10: AUTO_cf_cfut_2 | F10: =VLOOKUP($E10,Hybrid!$1:$1048576,MATCH(DATE(F$2,1,1),Hybrid!$A$1:$LI$1),FALSE) -> 1243.6668 | G10: =VLOOKUP($E10,Hybrid!$1:$1048576,MATCH(DATE(G$2,1,1),Hybrid!$A$1:$LI$1),FALSE) -> 1212.2229 | H10: =VLOOKUP($E10,Hybrid!$1:$1048576,MATCH(DATE(H$2,1,1),Hybrid!$A$1:$LI$1),FALSE) -> 1182.327 | I10: =VLOOKUP($E10,Hybrid!$1:$1048576,MATCH(DATE(I$2,1,1),Hybrid!$A$1:$LI$1),FALSE) -> 1149.3589 | J10: =VLOOKUP($E10,Hybrid!$1:$1048576,MATCH(DATE(J$2,1,1),Hybrid!$A$1:$LI$1),FALSE) -> 1117.9241 | K10: =VLOOKUP($E10,Hybrid!$1:$1048576,MATCH(DATE(K$2,1,1),Hybrid!$A$1:$LI$1),FALSE) -> 1092.9672 | L10: =VLOOKUP($E10,Hybrid!$1:$1048576,MATCH(DATE(L$2,1,1),Hybrid!$A$1:$LI$1),FALSE) -> 1064.6737 | M10: =VLOOKUP($E10,Hybrid!$1:$1048576,MATCH(DATE(M$2,1,1),Hybrid!$A$1:$LI$1),FALSE) -> 1033.7777 | ... AO10: =VLOOKUP($E10,Hybrid!$1:$1048576,MATCH(DATE(AO$2,1,1),Hybrid!$A$1:$LI$1),FALSE) -> 140.51472
D11: class G | E11: AUTO_cg_cfut_2 | F11: =VLOOKUP($E11,Hybrid!$1:$1048576,MATCH(DATE(F$2,1,1),Hybrid!$A$1:$LI$1),FALSE) -> 2239.6206 | G11: =VLOOKUP($E11,Hybrid!$1:$1048576,MATCH(DATE(G$2,1,1),Hybrid!$A$1:$LI$1),FALSE) -> 2185.9552 | H11: =VLOOKUP($E11,Hybrid!$1:$1048576,MATCH(DATE(H$2,1,1),Hybrid!$A$1:$LI$1),FALSE) -> 2131.2134 | I11: =VLOOKUP($E11,Hybrid!$1:$1048576,MATCH(DATE(I$2,1,1),Hybrid!$A$1:$LI$1),FALSE) -> 2066.0517 | J11: =VLOOKUP($E11,Hybrid!$1:$1048576,MATCH(DATE(J$2,1,1),Hybrid!$A$1:$LI$1),FALSE) -> 1998.7596 | K11: =VLOOKUP($E11,Hybrid!$1:$1048576,MATCH(DATE(K$2,1,1),Hybrid!$A$1:$LI$1),FALSE) -> 1938.4737 | L11: =VLOOKUP($E11,Hybrid!$1:$1048576,MATCH(DATE(L$2,1,1),Hybrid!$A$1:$LI$1),FALSE) -> 1870.8443 | M11: =VLOOKUP($E11,Hybrid!$1:$1048576,MATCH(DATE(M$2,1,1),Hybrid!$A$1:$LI$1),FALSE) -> 1797.2695 | ... AO11: =VLOOKUP($E11,Hybrid!$1:$1048576,MATCH(DATE(AO$2,1,1),Hybrid!$A$1:$LI$1),FALSE) -> 216.48413
C12: ELEC | E12: AUTO_cele_2 | F12: =VLOOKUP($E12,Hybrid!$1:$1048576,MATCH(DATE(F$2,1,1),Hybrid!$A$1:$LI$1),FALSE) -> 44.765 | G12: =VLOOKUP($E12,Hybrid!$1:$1048576,MATCH(DATE(G$2,1,1),Hybrid!$A$1:$LI$1),FALSE) -> 63.021127 | H12: =VLOOKUP($E12,Hybrid!$1:$1048576,MATCH(DATE(H$2,1,1),Hybrid!$A$1:$LI$1),FALSE) -> 80.977049 | I12: =VLOOKUP($E12,Hybrid!$1:$1048576,MATCH(DATE(I$2,1,1),Hybrid!$A$1:$LI$1),FALSE) -> 99.457266 | J12: =VLOOKUP($E12,Hybrid!$1:$1048576,MATCH(DATE(J$2,1,1),Hybrid!$A$1:$LI$1),FALSE) -> 122.9902 | K12: =VLOOKUP($E12,Hybrid!$1:$1048576,MATCH(DATE(K$2,1,1),Hybrid!$A$1:$LI$1),FALSE) -> 150.91049 | L12: =VLOOKUP($E12,Hybrid!$1:$1048576,MATCH(DATE(L$2,1,1),Hybrid!$A$1:$LI$1),FALSE) -> 177.19542 | M12: =VLOOKUP($E12,Hybrid!$1:$1048576,MATCH(DATE(M$2,1,1),Hybrid!$A$1:$LI$1),FALSE) -> 203.63756 | ... AO12: =VLOOKUP($E12,Hybrid!$1:$1048576,MATCH(DATE(AO$2,1,1),Hybrid!$A$1:$LI$1),FALSE) -> 4798.8813
D13: class A | E13: AUTO_ca_cele_2 | F13: =VLOOKUP($E13,Hybrid!$1:$1048576,MATCH(DATE(F$2,1,1),Hybrid!$A$1:$LI$1),FALSE) -> 9.8427899 | G13: =VLOOKUP($E13,Hybrid!$1:$1048576,MATCH(DATE(G$2,1,1),Hybrid!$A$1:$LI$1),FALSE) -> 15.157168 | H13: =VLOOKUP($E13,Hybrid!$1:$1048576,MATCH(DATE(H$2,1,1),Hybrid!$A$1:$LI$1),FALSE) -> 20.444627 | I13: =VLOOKUP($E13,Hybrid!$1:$1048576,MATCH(DATE(I$2,1,1),Hybrid!$A$1:$LI$1),FALSE) -> 26.028391 | J13: =VLOOKUP($E13,Hybrid!$1:$1048576,MATCH(DATE(J$2,1,1),Hybrid!$A$1:$LI$1),FALSE) -> 33.352976 | K13: =VLOOKUP($E13,Hybrid!$1:$1048576,MATCH(DATE(K$2,1,1),Hybrid!$A$1:$LI$1),FALSE) -> 42.139977 | L13: =VLOOKUP($E13,Hybrid!$1:$1048576,MATCH(DATE(L$2,1,1),Hybrid!$A$1:$LI$1),FALSE) -> 50.520577 | M13: =VLOOKUP($E13,Hybrid!$1:$1048576,MATCH(DATE(M$2,1,1),Hybrid!$A$1:$LI$1),FALSE) -> 59.100915 | ... AO13: =VLOOKUP($E13,Hybrid!$1:$1048576,MATCH(DATE(AO$2,1,1),Hybrid!$A$1:$LI$1),FALSE) -> 2712.0959
D14: class B | E14: AUTO_cb_cele_2 | F14: =VLOOKUP($E14,Hybrid!$1:$1048576,MATCH(DATE(F$2,1,1),Hybrid!$A$1:$LI$1),FALSE) -> 11.445717 | G14: =VLOOKUP($E14,Hybrid!$1:$1048576,MATCH(DATE(G$2,1,1),Hybrid!$A$1:$LI$1),FALSE) -> 16.461946 | H14: =VLOOKUP($E14,Hybrid!$1:$1048576,MATCH(DATE(H$2,1,1),Hybrid!$A$1:$LI$1),FALSE) -> 21.433349 | I14: =VLOOKUP($E14,Hybrid!$1:$1048576,MATCH(DATE(I$2,1,1),Hybrid!$A$1:$LI$1),FALSE) -> 26.683623 | J14: =VLOOKUP($E14,Hybrid!$1:$1048576,MATCH(DATE(J$2,1,1),Hybrid!$A$1:$LI$1),FALSE) -> 33.615652 | K14: =VLOOKUP($E14,Hybrid!$1:$1048576,MATCH(DATE(K$2,1,1),Hybrid!$A$1:$LI$1),FALSE) -> 41.934825 | L14: =VLOOKUP($E14,Hybrid!$1:$1048576,MATCH(DATE(L$2,1,1),Hybrid!$A$1:$LI$1),FALSE) -> 49.840932 | M14: =VLOOKUP($E14,Hybrid!$1:$1048576,MATCH(DATE(M$2,1,1),Hybrid!$A$1:$LI$1),FALSE) -> 57.904057 | ... AO14: =VLOOKUP($E14,Hybrid!$1:$1048576,MATCH(DATE(AO$2,1,1),Hybrid!$A$1:$LI$1),FALSE) -> 1421.4788
D15: class C | E15: AUTO_cc_cele_2 | F15: =VLOOKUP($E15,Hybrid!$1:$1048576,MATCH(DATE(F$2,1,1),Hybrid!$A$1:$LI$1),FALSE) -> 9.4015406 | G15: =VLOOKUP($E15,Hybrid!$1:$1048576,MATCH(DATE(G$2,1,1),Hybrid!$A$1:$LI$1),FALSE) -> 12.810382 | H15: =VLOOKUP($E15,Hybrid!$1:$1048576,MATCH(DATE(H$2,1,1),Hybrid!$A$1:$LI$1),FALSE) -> 16.175633 | I15: =VLOOKUP($E15,Hybrid!$1:$1048576,MATCH(DATE(I$2,1,1),Hybrid!$A$1:$LI$1),FALSE) -> 19.72907 | J15: =VLOOKUP($E15,Hybrid!$1:$1048576,MATCH(DATE(J$2,1,1),Hybrid!$A$1:$LI$1),FALSE) -> 24.449744 | K15: =VLOOKUP($E15,Hybrid!$1:$1048576,MATCH(DATE(K$2,1,1),Hybrid!$A$1:$LI$1),FALSE) -> 30.117195 | L15: =VLOOKUP($E15,Hybrid!$1:$1048576,MATCH(DATE(L$2,1,1),Hybrid!$A$1:$LI$1),FALSE) -> 35.483708 | M15: =VLOOKUP($E15,Hybrid!$1:$1048576,MATCH(DATE(M$2,1,1),Hybrid!$A$1:$LI$1),FALSE) -> 40.934695 | ... AO15: =VLOOKUP($E15,Hybrid!$1:$1048576,MATCH(DATE(AO$2,1,1),Hybrid!$A$1:$LI$1),FALSE) -> 588.56936
D16: class D | E16: AUTO_cd_cele_2 | F16: =VLOOKUP($E16,Hybrid!$1:$1048576,MATCH(DATE(F$2,1,1),Hybrid!$A$1:$LI$1),FALSE) -> 5.7700713 | G16: =VLOOKUP($E16,Hybrid!$1:$1048576,MATCH(DATE(G$2,1,1),Hybrid!$A$1:$LI$1),FALSE) -> 7.6228602 | H16: =VLOOKUP($E16,Hybrid!$1:$1048576,MATCH(DATE(H$2,1,1),Hybrid!$A$1:$LI$1),FALSE) -> 9.4510521 | I16: =VLOOKUP($E16,Hybrid!$1:$1048576,MATCH(DATE(I$2,1,1),Hybrid!$A$1:$LI$1),FALSE) -> 11.261629 | J16: =VLOOKUP($E16,Hybrid!$1:$1048576,MATCH(DATE(J$2,1,1),Hybrid!$A$1:$LI$1),FALSE) -> 13.387628 | K16: =VLOOKUP($E16,Hybrid!$1:$1048576,MATCH(DATE(K$2,1,1),Hybrid!$A$1:$LI$1),FALSE) -> 15.871449 | L16: =VLOOKUP($E16,Hybrid!$1:$1048576,MATCH(DATE(L$2,1,1),Hybrid!$A$1:$LI$1),FALSE) -> 18.187902 | M16: =VLOOKUP($E16,Hybrid!$1:$1048576,MATCH(DATE(M$2,1,1),Hybrid!$A$1:$LI$1),FALSE) -> 20.45637 | ... AO16: =VLOOKUP($E16,Hybrid!$1:$1048576,MATCH(DATE(AO$2,1,1),Hybrid!$A$1:$LI$1),FALSE) -> 52.604655
D17: class E | E17: AUTO_ce_cele_2 | F17: =VLOOKUP($E17,Hybrid!$1:$1048576,MATCH(DATE(F$2,1,1),Hybrid!$A$1:$LI$1),FALSE) -> 3.4730441 | G17: =VLOOKUP($E17,Hybrid!$1:$1048576,MATCH(DATE(G$2,1,1),Hybrid!$A$1:$LI$1),FALSE) -> 4.6091896 | H17: =VLOOKUP($E17,Hybrid!$1:$1048576,MATCH(DATE(H$2,1,1),Hybrid!$A$1:$LI$1),FALSE) -> 5.7149767 | I17: =VLOOKUP($E17,Hybrid!$1:$1048576,MATCH(DATE(I$2,1,1),Hybrid!$A$1:$LI$1),FALSE) -> 6.7928004 | J17: =VLOOKUP($E17,Hybrid!$1:$1048576,MATCH(DATE(J$2,1,1),Hybrid!$A$1:$LI$1),FALSE) -> 8.0398585 | K17: =VLOOKUP($E17,Hybrid!$1:$1048576,MATCH(DATE(K$2,1,1),Hybrid!$A$1:$LI$1),FALSE) -> 9.4759102 | L17: =VLOOKUP($E17,Hybrid!$1:$1048576,MATCH(DATE(L$2,1,1),Hybrid!$A$1:$LI$1),FALSE) -> 10.790746 | M17: =VLOOKUP($E17,Hybrid!$1:$1048576,MATCH(DATE(M$2,1,1),Hybrid!$A$1:$LI$1),FALSE) -> 12.050356 | ... AO17: =VLOOKUP($E17,Hybrid!$1:$1048576,MATCH(DATE(AO$2,1,1),Hybrid!$A$1:$LI$1),FALSE) -> 17.470553
D18: class F | E18: AUTO_cf_cele_2 | F18: =VLOOKUP($E18,Hybrid!$1:$1048576,MATCH(DATE(F$2,1,1),Hybrid!$A$1:$LI$1),FALSE) -> 1.7251505 | G18: =VLOOKUP($E18,Hybrid!$1:$1048576,MATCH(DATE(G$2,1,1),Hybrid!$A$1:$LI$1),FALSE) -> 2.2608175 | H18: =VLOOKUP($E18,Hybrid!$1:$1048576,MATCH(DATE(H$2,1,1),Hybrid!$A$1:$LI$1),FALSE) -> 2.7629561 | I18: =VLOOKUP($E18,Hybrid!$1:$1048576,MATCH(DATE(I$2,1,1),Hybrid!$A$1:$LI$1),FALSE) -> 3.2118073 | J18: =VLOOKUP($E18,Hybrid!$1:$1048576,MATCH(DATE(J$2,1,1),Hybrid!$A$1:$LI$1),FALSE) -> 3.6713826 | K18: =VLOOKUP($E18,Hybrid!$1:$1048576,MATCH(DATE(K$2,1,1),Hybrid!$A$1:$LI$1),FALSE) -> 4.1657074 | L18: =VLOOKUP($E18,Hybrid!$1:$1048576,MATCH(DATE(L$2,1,1),Hybrid!$A$1:$LI$1),FALSE) -> 4.5869138 | M18: =VLOOKUP($E18,Hybrid!$1:$1048576,MATCH(DATE(M$2,1,1),Hybrid!$A$1:$LI$1),FALSE) -> 4.9518074 | ... AO18: =VLOOKUP($E18,Hybrid!$1:$1048576,MATCH(DATE(AO$2,1,1),Hybrid!$A$1:$LI$1),FALSE) -> 2.8904074
D19: class G | E19: AUTO_cg_cele_2 | F19: =VLOOKUP($E19,Hybrid!$1:$1048576,MATCH(DATE(F$2,1,1),Hybrid!$A$1:$LI$1),FALSE) -> 3.1066862 | G19: =VLOOKUP($E19,Hybrid!$1:$1048576,MATCH(DATE(G$2,1,1),Hybrid!$A$1:$LI$1),FALSE) -> 4.0987638 | H19: =VLOOKUP($E19,Hybrid!$1:$1048576,MATCH(DATE(H$2,1,1),Hybrid!$A$1:$LI$1),FALSE) -> 4.9944538 | I19: =VLOOKUP($E19,Hybrid!$1:$1048576,MATCH(DATE(I$2,1,1),Hybrid!$A$1:$LI$1),FALSE) -> 5.7499462 | J19: =VLOOKUP($E19,Hybrid!$1:$1048576,MATCH(DATE(J$2,1,1),Hybrid!$A$1:$LI$1),FALSE) -> 6.4729559 | K19: =VLOOKUP($E19,Hybrid!$1:$1048576,MATCH(DATE(K$2,1,1),Hybrid!$A$1:$LI$1),FALSE) -> 7.205424 | L19: =VLOOKUP($E19,Hybrid!$1:$1048576,MATCH(DATE(L$2,1,1),Hybrid!$A$1:$LI$1),FALSE) -> 7.7846433 | M19: =VLOOKUP($E19,Hybrid!$1:$1048576,MATCH(DATE(M$2,1,1),Hybrid!$A$1:$LI$1),FALSE) -> 8.2393631 | ... AO19: =VLOOKUP($E19,Hybrid!$1:$1048576,MATCH(DATE(AO$2,1,1),Hybrid!$A$1:$LI$1),FALSE) -> 3.7716557
C20: GAS | E20: AUTO_cgas_2 | F20: =VLOOKUP($E20,Hybrid!$1:$1048576,MATCH(DATE(F$2,1,1),Hybrid!$A$1:$LI$1),FALSE) -> 1.936 | G20: =VLOOKUP($E20,Hybrid!$1:$1048576,MATCH(DATE(G$2,1,1),Hybrid!$A$1:$LI$1),FALSE) -> 1.9968324 | H20: =VLOOKUP($E20,Hybrid!$1:$1048576,MATCH(DATE(H$2,1,1),Hybrid!$A$1:$LI$1),FALSE) -> 2.060546 | I20: =VLOOKUP($E20,Hybrid!$1:$1048576,MATCH(DATE(I$2,1,1),Hybrid!$A$1:$LI$1),FALSE) -> 2.1196814 | J20: =VLOOKUP($E20,Hybrid!$1:$1048576,MATCH(DATE(J$2,1,1),Hybrid!$A$1:$LI$1),FALSE) -> 2.1910005 | K20: =VLOOKUP($E20,Hybrid!$1:$1048576,MATCH(DATE(K$2,1,1),Hybrid!$A$1:$LI$1),FALSE) -> 2.2894584 | L20: =VLOOKUP($E20,Hybrid!$1:$1048576,MATCH(DATE(L$2,1,1),Hybrid!$A$1:$LI$1),FALSE) -> 2.3779418 | M20: =VLOOKUP($E20,Hybrid!$1:$1048576,MATCH(DATE(M$2,1,1),Hybrid!$A$1:$LI$1),FALSE) -> 2.4627777 | ... AO20: =VLOOKUP($E20,Hybrid!$1:$1048576,MATCH(DATE(AO$2,1,1),Hybrid!$A$1:$LI$1),FALSE) -> 3.9314241
D21: class A | E21: AUTO_ca_cgas_2 | F21: =VLOOKUP($E21,Hybrid!$1:$1048576,MATCH(DATE(F$2,1,1),Hybrid!$A$1:$LI$1),FALSE) -> 0.4256817 | G21: =VLOOKUP($E21,Hybrid!$1:$1048576,MATCH(DATE(G$2,1,1),Hybrid!$A$1:$LI$1),FALSE) -> 0.45084295 | H21: =VLOOKUP($E21,Hybrid!$1:$1048576,MATCH(DATE(H$2,1,1),Hybrid!$A$1:$LI$1),FALSE) -> 0.47695788 | I21: =VLOOKUP($E21,Hybrid!$1:$1048576,MATCH(DATE(I$2,1,1),Hybrid!$A$1:$LI$1),FALSE) -> 0.50234383 | J21: =VLOOKUP($E21,Hybrid!$1:$1048576,MATCH(DATE(J$2,1,1),Hybrid!$A$1:$LI$1),FALSE) -> 0.53210293 | K21: =VLOOKUP($E21,Hybrid!$1:$1048576,MATCH(DATE(K$2,1,1),Hybrid!$A$1:$LI$1),FALSE) -> 0.57042379 | L21: =VLOOKUP($E21,Hybrid!$1:$1048576,MATCH(DATE(L$2,1,1),Hybrid!$A$1:$LI$1),FALSE) -> 0.60596968 | M21: =VLOOKUP($E21,Hybrid!$1:$1048576,MATCH(DATE(M$2,1,1),Hybrid!$A$1:$LI$1),FALSE) -> 0.64099082 | ... AO21: =VLOOKUP($E21,Hybrid!$1:$1048576,MATCH(DATE(AO$2,1,1),Hybrid!$A$1:$LI$1),FALSE) -> 1.9825822
D22: class B | E22: AUTO_cb_cgas_2 | F22: =VLOOKUP($E22,Hybrid!$1:$1048576,MATCH(DATE(F$2,1,1),Hybrid!$A$1:$LI$1),FALSE) -> 0.49500523 | G22: =VLOOKUP($E22,Hybrid!$1:$1048576,MATCH(DATE(G$2,1,1),Hybrid!$A$1:$LI$1),FALSE) -> 0.51370793 | H22: =VLOOKUP($E22,Hybrid!$1:$1048576,MATCH(DATE(H$2,1,1),Hybrid!$A$1:$LI$1),FALSE) -> 0.53354294 | I22: =VLOOKUP($E22,Hybrid!$1:$1048576,MATCH(DATE(I$2,1,1),Hybrid!$A$1:$LI$1),FALSE) -> 0.55272136 | J22: =VLOOKUP($E22,Hybrid!$1:$1048576,MATCH(DATE(J$2,1,1),Hybrid!$A$1:$LI$1),FALSE) -> 0.57599895 | K22: =VLOOKUP($E22,Hybrid!$1:$1048576,MATCH(DATE(K$2,1,1),Hybrid!$A$1:$LI$1),FALSE) -> 0.60748622 | L22: =VLOOKUP($E22,Hybrid!$1:$1048576,MATCH(DATE(L$2,1,1),Hybrid!$A$1:$LI$1),FALSE) -> 0.63650963 | M22: =VLOOKUP($E22,Hybrid!$1:$1048576,MATCH(DATE(M$2,1,1),Hybrid!$A$1:$LI$1),FALSE) -> 0.66501015 | ... AO22: =VLOOKUP($E22,Hybrid!$1:$1048576,MATCH(DATE(AO$2,1,1),Hybrid!$A$1:$LI$1),FALSE) -> 1.1632447
D23: class C | E23: AUTO_cc_cgas_2 | F23: =VLOOKUP($E23,Hybrid!$1:$1048576,MATCH(DATE(F$2,1,1),Hybrid!$A$1:$LI$1),FALSE) -> 0.40659852 | G23: =VLOOKUP($E23,Hybrid!$1:$1048576,MATCH(DATE(G$2,1,1),Hybrid!$A$1:$LI$1),FALSE) -> 0.41550713 | H23: =VLOOKUP($E23,Hybrid!$1:$1048576,MATCH(DATE(H$2,1,1),Hybrid!$A$1:$LI$1),FALSE) -> 0.42536707 | I23: =VLOOKUP($E23,Hybrid!$1:$1048576,MATCH(DATE(I$2,1,1),Hybrid!$A$1:$LI$1),FALSE) -> 0.43482241 | J23: =VLOOKUP($E23,Hybrid!$1:$1048576,MATCH(DATE(J$2,1,1),Hybrid!$A$1:$LI$1),FALSE) -> 0.44707018 | K23: =VLOOKUP($E23,Hybrid!$1:$1048576,MATCH(DATE(K$2,1,1),Hybrid!$A$1:$LI$1),FALSE) -> 0.46501401 | L23: =VLOOKUP($E23,Hybrid!$1:$1048576,MATCH(DATE(L$2,1,1),Hybrid!$A$1:$LI$1),FALSE) -> 0.48140681 | M23: =VLOOKUP($E23,Hybrid!$1:$1048576,MATCH(DATE(M$2,1,1),Hybrid!$A$1:$LI$1),FALSE) -> 0.49744747 | ... AO23: =VLOOKUP($E23,Hybrid!$1:$1048576,MATCH(DATE(AO$2,1,1),Hybrid!$A$1:$LI$1),FALSE) -> 0.55682411
D24: class D | E24: AUTO_cd_cgas_2 | F24: =VLOOKUP($E24,Hybrid!$1:$1048576,MATCH(DATE(F$2,1,1),Hybrid!$A$1:$LI$1),FALSE) -> 0.24954447 | G24: =VLOOKUP($E24,Hybrid!$1:$1048576,MATCH(DATE(G$2,1,1),Hybrid!$A$1:$LI$1),FALSE) -> 0.25285832 | H24: =VLOOKUP($E24,Hybrid!$1:$1048576,MATCH(DATE(H$2,1,1),Hybrid!$A$1:$LI$1),FALSE) -> 0.25657518 | I24: =VLOOKUP($E24,Hybrid!$1:$1048576,MATCH(DATE(I$2,1,1),Hybrid!$A$1:$LI$1),FALSE) -> 0.25980708 | J24: =VLOOKUP($E24,Hybrid!$1:$1048576,MATCH(DATE(J$2,1,1),Hybrid!$A$1:$LI$1),FALSE) -> 0.26420163 | K24: =VLOOKUP($E24,Hybrid!$1:$1048576,MATCH(DATE(K$2,1,1),Hybrid!$A$1:$LI$1),FALSE) -> 0.27132781 | L24: =VLOOKUP($E24,Hybrid!$1:$1048576,MATCH(DATE(L$2,1,1),Hybrid!$A$1:$LI$1),FALSE) -> 0.277446 | M24: =VLOOKUP($E24,Hybrid!$1:$1048576,MATCH(DATE(M$2,1,1),Hybrid!$A$1:$LI$1),FALSE) -> 0.28305668 | ... AO24: =VLOOKUP($E24,Hybrid!$1:$1048576,MATCH(DATE(AO$2,1,1),Hybrid!$A$1:$LI$1),FALSE) -> 0.13047409
D25: class E | E25: AUTO_ce_cgas_2 | F25: =VLOOKUP($E25,Hybrid!$1:$1048576,MATCH(DATE(F$2,1,1),Hybrid!$A$1:$LI$1),FALSE) -> 0.15020247 | G25: =VLOOKUP($E25,Hybrid!$1:$1048576,MATCH(DATE(G$2,1,1),Hybrid!$A$1:$LI$1),FALSE) -> 0.15238593 | H25: =VLOOKUP($E25,Hybrid!$1:$1048576,MATCH(DATE(H$2,1,1),Hybrid!$A$1:$LI$1),FALSE) -> 0.15468725 | I25: =VLOOKUP($E25,Hybrid!$1:$1048576,MATCH(DATE(I$2,1,1),Hybrid!$A$1:$LI$1),FALSE) -> 0.15649018 | J25: =VLOOKUP($E25,Hybrid!$1:$1048576,MATCH(DATE(J$2,1,1),Hybrid!$A$1:$LI$1),FALSE) -> 0.15874617 | K25: =VLOOKUP($E25,Hybrid!$1:$1048576,MATCH(DATE(K$2,1,1),Hybrid!$A$1:$LI$1),FALSE) -> 0.16241596 | L25: =VLOOKUP($E25,Hybrid!$1:$1048576,MATCH(DATE(L$2,1,1),Hybrid!$A$1:$LI$1),FALSE) -> 0.16535808 | M25: =VLOOKUP($E25,Hybrid!$1:$1048576,MATCH(DATE(M$2,1,1),Hybrid!$A$1:$LI$1),FALSE) -> 0.16780894 | ... AO25: =VLOOKUP($E25,Hybrid!$1:$1048576,MATCH(DATE(AO$2,1,1),Hybrid!$A$1:$LI$1),FALSE) -> 0.056121869
D26: class F | E26: AUTO_cf_cgas_2 | F26: =VLOOKUP($E26,Hybrid!$1:$1048576,MATCH(DATE(F$2,1,1),Hybrid!$A$1:$LI$1),FALSE) -> 0.074609436 | G26: =VLOOKUP($E26,Hybrid!$1:$1048576,MATCH(DATE(G$2,1,1),Hybrid!$A$1:$LI$1),FALSE) -> 0.075435583 | H26: =VLOOKUP($E26,Hybrid!$1:$1048576,MATCH(DATE(H$2,1,1),Hybrid!$A$1:$LI$1),FALSE) -> 0.076134567 | I26: =VLOOKUP($E26,Hybrid!$1:$1048576,MATCH(DATE(I$2,1,1),Hybrid!$A$1:$LI$1),FALSE) -> 0.076336312 | J26: =VLOOKUP($E26,Hybrid!$1:$1048576,MATCH(DATE(J$2,1,1),Hybrid!$A$1:$LI$1),FALSE) -> 0.076438727 | K26: =VLOOKUP($E26,Hybrid!$1:$1048576,MATCH(DATE(K$2,1,1),Hybrid!$A$1:$LI$1),FALSE) -> 0.076873442 | L26: =VLOOKUP($E26,Hybrid!$1:$1048576,MATCH(DATE(L$2,1,1),Hybrid!$A$1:$LI$1),FALSE) -> 0.076837512 | M26: =VLOOKUP($E26,Hybrid!$1:$1048576,MATCH(DATE(M$2,1,1),Hybrid!$A$1:$LI$1),FALSE) -> 0.076400208 | ... AO26: =VLOOKUP($E26,Hybrid!$1:$1048576,MATCH(DATE(AO$2,1,1),Hybrid!$A$1:$LI$1),FALSE) -> 0.016674178
D27: class G | E27: AUTO_cg_cgas_2 | F27: =VLOOKUP($E27,Hybrid!$1:$1048576,MATCH(DATE(F$2,1,1),Hybrid!$A$1:$LI$1),FALSE) -> 0.13435819 | G27: =VLOOKUP($E27,Hybrid!$1:$1048576,MATCH(DATE(G$2,1,1),Hybrid!$A$1:$LI$1),FALSE) -> 0.13609456 | H27: =VLOOKUP($E27,Hybrid!$1:$1048576,MATCH(DATE(H$2,1,1),Hybrid!$A$1:$LI$1),FALSE) -> 0.13728112 | I27: =VLOOKUP($E27,Hybrid!$1:$1048576,MATCH(DATE(I$2,1,1),Hybrid!$A$1:$LI$1),FALSE) -> 0.13716024 | J27: =VLOOKUP($E27,Hybrid!$1:$1048576,MATCH(DATE(J$2,1,1),Hybrid!$A$1:$LI$1),FALSE) -> 0.13644192 | K27: =VLOOKUP($E27,Hybrid!$1:$1048576,MATCH(DATE(K$2,1,1),Hybrid!$A$1:$LI$1),FALSE) -> 0.13591716 | L27: =VLOOKUP($E27,Hybrid!$1:$1048576,MATCH(DATE(L$2,1,1),Hybrid!$A$1:$LI$1),FALSE) -> 0.13441412 | M27: =VLOOKUP($E27,Hybrid!$1:$1048576,MATCH(DATE(M$2,1,1),Hybrid!$A$1:$LI$1),FALSE) -> 0.13206339 | ... AO27: =VLOOKUP($E27,Hybrid!$1:$1048576,MATCH(DATE(AO$2,1,1),Hybrid!$A$1:$LI$1),FALSE) -> 0.025503054
C28: TOTAL STOCK BASELINE | E28: AUTO_0 | F28: =VLOOKUP($E28,Hybrid!$1:$1048576,MATCH(DATE(F$2,1,1),Hybrid!$A$1:$LI$1),FALSE) -> 32317.941 | G28: =VLOOKUP($E28,Hybrid!$1:$1048576,MATCH(DATE(G$2,1,1),Hybrid!$A$1:$LI$1),FALSE) -> 31989.266 | H28: =VLOOKUP($E28,Hybrid!$1:$1048576,MATCH(DATE(H$2,1,1),Hybrid!$A$1:$LI$1),FALSE) -> 31766.848 | I28: =VLOOKUP($E28,Hybrid!$1:$1048576,MATCH(DATE(I$2,1,1),Hybrid!$A$1:$LI$1),FALSE) -> 31556.566 | J28: =VLOOKUP($E28,Hybrid!$1:$1048576,MATCH(DATE(J$2,1,1),Hybrid!$A$1:$LI$1),FALSE) -> 31558.174 | K28: =VLOOKUP($E28,Hybrid!$1:$1048576,MATCH(DATE(K$2,1,1),Hybrid!$A$1:$LI$1),FALSE) -> 31942.005 | L28: =VLOOKUP($E28,Hybrid!$1:$1048576,MATCH(DATE(L$2,1,1),Hybrid!$A$1:$LI$1),FALSE) -> 32251.021 | M28: =VLOOKUP($E28,Hybrid!$1:$1048576,MATCH(DATE(M$2,1,1),Hybrid!$A$1:$LI$1),FALSE) -> 32582.334 | ... AO28: =VLOOKUP($E28,Hybrid!$1:$1048576,MATCH(DATE(AO$2,1,1),Hybrid!$A$1:$LI$1),FALSE) -> 44584.282
C29: OIL | E29: AUTO_cfut_0 | F29: =VLOOKUP($E29,Hybrid!$1:$1048576,MATCH(DATE(F$2,1,1),Hybrid!$A$1:$LI$1),FALSE) -> 32271.24 | G29: =VLOOKUP($E29,Hybrid!$1:$1048576,MATCH(DATE(G$2,1,1),Hybrid!$A$1:$LI$1),FALSE) -> 31924.248 | H29: =VLOOKUP($E29,Hybrid!$1:$1048576,MATCH(DATE(H$2,1,1),Hybrid!$A$1:$LI$1),FALSE) -> 31683.81 | I29: =VLOOKUP($E29,Hybrid!$1:$1048576,MATCH(DATE(I$2,1,1),Hybrid!$A$1:$LI$1),FALSE) -> 31454.989 | J29: =VLOOKUP($E29,Hybrid!$1:$1048576,MATCH(DATE(J$2,1,1),Hybrid!$A$1:$LI$1),FALSE) -> 31432.993 | K29: =VLOOKUP($E29,Hybrid!$1:$1048576,MATCH(DATE(K$2,1,1),Hybrid!$A$1:$LI$1),FALSE) -> 31788.805 | L29: =VLOOKUP($E29,Hybrid!$1:$1048576,MATCH(DATE(L$2,1,1),Hybrid!$A$1:$LI$1),FALSE) -> 32071.448 | M29: =VLOOKUP($E29,Hybrid!$1:$1048576,MATCH(DATE(M$2,1,1),Hybrid!$A$1:$LI$1),FALSE) -> 32376.242 | ... AO29: =VLOOKUP($E29,Hybrid!$1:$1048576,MATCH(DATE(AO$2,1,1),Hybrid!$A$1:$LI$1),FALSE) -> 43277.168
D30: class A | E30: AUTO_ca_cfut_0 | F30: =VLOOKUP($E30,Hybrid!$1:$1048576,MATCH(DATE(F$2,1,1),Hybrid!$A$1:$LI$1),FALSE) -> 7095.7005 | G30: =VLOOKUP($E30,Hybrid!$1:$1048576,MATCH(DATE(G$2,1,1),Hybrid!$A$1:$LI$1),FALSE) -> 7159.6915 | H30: =VLOOKUP($E30,Hybrid!$1:$1048576,MATCH(DATE(H$2,1,1),Hybrid!$A$1:$LI$1),FALSE) -> 7248.7731 | I30: =VLOOKUP($E30,Hybrid!$1:$1048576,MATCH(DATE(I$2,1,1),Hybrid!$A$1:$LI$1),FALSE) -> 7341.6733 | J30: =VLOOKUP($E30,Hybrid!$1:$1048576,MATCH(DATE(J$2,1,1),Hybrid!$A$1:$LI$1),FALSE) -> 7498.2843 | K30: =VLOOKUP($E30,Hybrid!$1:$1048576,MATCH(DATE(K$2,1,1),Hybrid!$A$1:$LI$1),FALSE) -> 7766.7593 | L30: =VLOOKUP($E30,Hybrid!$1:$1048576,MATCH(DATE(L$2,1,1),Hybrid!$A$1:$LI$1),FALSE) -> 8009.8192 | M30: =VLOOKUP($E30,Hybrid!$1:$1048576,MATCH(DATE(M$2,1,1),Hybrid!$A$1:$LI$1),FALSE) -> 8259.9685 | ... AO30: =VLOOKUP($E30,Hybrid!$1:$1048576,MATCH(DATE(AO$2,1,1),Hybrid!$A$1:$LI$1),FALSE) -> 19071.974
D31: class B | E31: AUTO_cb_cfut_0 | F31: =VLOOKUP($E31,Hybrid!$1:$1048576,MATCH(DATE(F$2,1,1),Hybrid!$A$1:$LI$1),FALSE) -> 8251.2564 | G31: =VLOOKUP($E31,Hybrid!$1:$1048576,MATCH(DATE(G$2,1,1),Hybrid!$A$1:$LI$1),FALSE) -> 8200.0167 | H31: =VLOOKUP($E31,Hybrid!$1:$1048576,MATCH(DATE(H$2,1,1),Hybrid!$A$1:$LI$1),FALSE) -> 8180.1563 | I31: =VLOOKUP($E31,Hybrid!$1:$1048576,MATCH(DATE(I$2,1,1),Hybrid!$A$1:$LI$1),FALSE) -> 8168.7824 | J31: =VLOOKUP($E31,Hybrid!$1:$1048576,MATCH(DATE(J$2,1,1),Hybrid!$A$1:$LI$1),FALSE) -> 8221.3545 | K31: =VLOOKUP($E31,Hybrid!$1:$1048576,MATCH(DATE(K$2,1,1),Hybrid!$A$1:$LI$1),FALSE) -> 8384.8744 | L31: =VLOOKUP($E31,Hybrid!$1:$1048576,MATCH(DATE(L$2,1,1),Hybrid!$A$1:$LI$1),FALSE) -> 8529.766 | M31: =VLOOKUP($E31,Hybrid!$1:$1048576,MATCH(DATE(M$2,1,1),Hybrid!$A$1:$LI$1),FALSE) -> 8684.5805 | ... AO31: =VLOOKUP($E31,Hybrid!$1:$1048576,MATCH(DATE(AO$2,1,1),Hybrid!$A$1:$LI$1),FALSE) -> 13897.5
D32: class C | E32: AUTO_cc_cfut_0 | F32: =VLOOKUP($E32,Hybrid!$1:$1048576,MATCH(DATE(F$2,1,1),Hybrid!$A$1:$LI$1),FALSE) -> 6777.6025 | G32: =VLOOKUP($E32,Hybrid!$1:$1048576,MATCH(DATE(G$2,1,1),Hybrid!$A$1:$LI$1),FALSE) -> 6658.6926 | H32: =VLOOKUP($E32,Hybrid!$1:$1048576,MATCH(DATE(H$2,1,1),Hybrid!$A$1:$LI$1),FALSE) -> 6566.988 | I32: =VLOOKUP($E32,Hybrid!$1:$1048576,MATCH(DATE(I$2,1,1),Hybrid!$A$1:$LI$1),FALSE) -> 6484.9391 | J32: =VLOOKUP($E32,Hybrid!$1:$1048576,MATCH(DATE(J$2,1,1),Hybrid!$A$1:$LI$1),FALSE) -> 6449.5485 | K32: =VLOOKUP($E32,Hybrid!$1:$1048576,MATCH(DATE(K$2,1,1),Hybrid!$A$1:$LI$1),FALSE) -> 6493.8251 | L32: =VLOOKUP($E32,Hybrid!$1:$1048576,MATCH(DATE(L$2,1,1),Hybrid!$A$1:$LI$1),FALSE) -> 6529.5432 | M32: =VLOOKUP($E32,Hybrid!$1:$1048576,MATCH(DATE(M$2,1,1),Hybrid!$A$1:$LI$1),FALSE) -> 6574.6851 | ... AO32: =VLOOKUP($E32,Hybrid!$1:$1048576,MATCH(DATE(AO$2,1,1),Hybrid!$A$1:$LI$1),FALSE) -> 7516.2298
D33: class D | E33: AUTO_cd_cfut_0 | F33: =VLOOKUP($E33,Hybrid!$1:$1048576,MATCH(DATE(F$2,1,1),Hybrid!$A$1:$LI$1),FALSE) -> 4159.6639 | G33: =VLOOKUP($E33,Hybrid!$1:$1048576,MATCH(DATE(G$2,1,1),Hybrid!$A$1:$LI$1),FALSE) -> 4061.0488 | H33: =VLOOKUP($E33,Hybrid!$1:$1048576,MATCH(DATE(H$2,1,1),Hybrid!$A$1:$LI$1),FALSE) -> 3977.3705 | I33: =VLOOKUP($E33,Hybrid!$1:$1048576,MATCH(DATE(I$2,1,1),Hybrid!$A$1:$LI$1),FALSE) -> 3897.1966 | J33: =VLOOKUP($E33,Hybrid!$1:$1048576,MATCH(DATE(J$2,1,1),Hybrid!$A$1:$LI$1),FALSE) -> 3839.5055 | K33: =VLOOKUP($E33,Hybrid!$1:$1048576,MATCH(DATE(K$2,1,1),Hybrid!$A$1:$LI$1),FALSE) -> 3822.0886 | L33: =VLOOKUP($E33,Hybrid!$1:$1048576,MATCH(DATE(L$2,1,1),Hybrid!$A$1:$LI$1),FALSE) -> 3799.3302 | M33: =VLOOKUP($E33,Hybrid!$1:$1048576,MATCH(DATE(M$2,1,1),Hybrid!$A$1:$LI$1),FALSE) -> 3779.304 | ... AO33: =VLOOKUP($E33,Hybrid!$1:$1048576,MATCH(DATE(AO$2,1,1),Hybrid!$A$1:$LI$1),FALSE) -> 1739.6729
D34: class E | E34: AUTO_ce_cfut_0 | F34: =VLOOKUP($E34,Hybrid!$1:$1048576,MATCH(DATE(F$2,1,1),Hybrid!$A$1:$LI$1),FALSE) -> 2503.7292 | G34: =VLOOKUP($E34,Hybrid!$1:$1048576,MATCH(DATE(G$2,1,1),Hybrid!$A$1:$LI$1),FALSE) -> 2446.6199 | H34: =VLOOKUP($E34,Hybrid!$1:$1048576,MATCH(DATE(H$2,1,1),Hybrid!$A$1:$LI$1),FALSE) -> 2396.9821 | I34: =VLOOKUP($E34,Hybrid!$1:$1048576,MATCH(DATE(I$2,1,1),Hybrid!$A$1:$LI$1),FALSE) -> 2346.9867 | J34: =VLOOKUP($E34,Hybrid!$1:$1048576,MATCH(DATE(J$2,1,1),Hybrid!$A$1:$LI$1),FALSE) -> 2307.6163 | K34: =VLOOKUP($E34,Hybrid!$1:$1048576,MATCH(DATE(K$2,1,1),Hybrid!$A$1:$LI$1),FALSE) -> 2289.8168 | L34: =VLOOKUP($E34,Hybrid!$1:$1048576,MATCH(DATE(L$2,1,1),Hybrid!$A$1:$LI$1),FALSE) -> 2267.4709 | M34: =VLOOKUP($E34,Hybrid!$1:$1048576,MATCH(DATE(M$2,1,1),Hybrid!$A$1:$LI$1),FALSE) -> 2244.7587 | ... AO34: =VLOOKUP($E34,Hybrid!$1:$1048576,MATCH(DATE(AO$2,1,1),Hybrid!$A$1:$LI$1),FALSE) -> 660.47631
D35: class F | E35: AUTO_cf_cfut_0 | F35: =VLOOKUP($E35,Hybrid!$1:$1048576,MATCH(DATE(F$2,1,1),Hybrid!$A$1:$LI$1),FALSE) -> 1243.6668 | G35: =VLOOKUP($E35,Hybrid!$1:$1048576,MATCH(DATE(G$2,1,1),Hybrid!$A$1:$LI$1),FALSE) -> 1212.2229 | H35: =VLOOKUP($E35,Hybrid!$1:$1048576,MATCH(DATE(H$2,1,1),Hybrid!$A$1:$LI$1),FALSE) -> 1182.327 | I35: =VLOOKUP($E35,Hybrid!$1:$1048576,MATCH(DATE(I$2,1,1),Hybrid!$A$1:$LI$1),FALSE) -> 1149.3589 | J35: =VLOOKUP($E35,Hybrid!$1:$1048576,MATCH(DATE(J$2,1,1),Hybrid!$A$1:$LI$1),FALSE) -> 1117.9241 | K35: =VLOOKUP($E35,Hybrid!$1:$1048576,MATCH(DATE(K$2,1,1),Hybrid!$A$1:$LI$1),FALSE) -> 1092.9672 | L35: =VLOOKUP($E35,Hybrid!$1:$1048576,MATCH(DATE(L$2,1,1),Hybrid!$A$1:$LI$1),FALSE) -> 1064.6737 | M35: =VLOOKUP($E35,Hybrid!$1:$1048576,MATCH(DATE(M$2,1,1),Hybrid!$A$1:$LI$1),FALSE) -> 1034.4912 | ... AO35: =VLOOKUP($E35,Hybrid!$1:$1048576,MATCH(DATE(AO$2,1,1),Hybrid!$A$1:$LI$1),FALSE) -> 159.58538
D36: class G | E36: AUTO_cg_cfut_0 | F36: =VLOOKUP($E36,Hybrid!$1:$1048576,MATCH(DATE(F$2,1,1),Hybrid!$A$1:$LI$1),FALSE) -> 2239.6206 | G36: =VLOOKUP($E36,Hybrid!$1:$1048576,MATCH(DATE(G$2,1,1),Hybrid!$A$1:$LI$1),FALSE) -> 2185.9552 | H36: =VLOOKUP($E36,Hybrid!$1:$1048576,MATCH(DATE(H$2,1,1),Hybrid!$A$1:$LI$1),FALSE) -> 2131.2134 | I36: =VLOOKUP($E36,Hybrid!$1:$1048576,MATCH(DATE(I$2,1,1),Hybrid!$A$1:$LI$1),FALSE) -> 2066.0517 | J36: =VLOOKUP($E36,Hybrid!$1:$1048576,MATCH(DATE(J$2,1,1),Hybrid!$A$1:$LI$1),FALSE) -> 1998.7596 | K36: =VLOOKUP($E36,Hybrid!$1:$1048576,MATCH(DATE(K$2,1,1),Hybrid!$A$1:$LI$1),FALSE) -> 1938.4737 | L36: =VLOOKUP($E36,Hybrid!$1:$1048576,MATCH(DATE(L$2,1,1),Hybrid!$A$1:$LI$1),FALSE) -> 1870.8443 | M36: =VLOOKUP($E36,Hybrid!$1:$1048576,MATCH(DATE(M$2,1,1),Hybrid!$A$1:$LI$1),FALSE) -> 1798.4537 | ... AO36: =VLOOKUP($E36,Hybrid!$1:$1048576,MATCH(DATE(AO$2,1,1),Hybrid!$A$1:$LI$1),FALSE) -> 231.7298
C37: ELEC | E37: AUTO_cele_0 | F37: =VLOOKUP($E37,Hybrid!$1:$1048576,MATCH(DATE(F$2,1,1),Hybrid!$A$1:$LI$1),FALSE) -> 44.765 | G37: =VLOOKUP($E37,Hybrid!$1:$1048576,MATCH(DATE(G$2,1,1),Hybrid!$A$1:$LI$1),FALSE) -> 63.021127 | H37: =VLOOKUP($E37,Hybrid!$1:$1048576,MATCH(DATE(H$2,1,1),Hybrid!$A$1:$LI$1),FALSE) -> 80.977049 | I37: =VLOOKUP($E37,Hybrid!$1:$1048576,MATCH(DATE(I$2,1,1),Hybrid!$A$1:$LI$1),FALSE) -> 99.457266 | J37: =VLOOKUP($E37,Hybrid!$1:$1048576,MATCH(DATE(J$2,1,1),Hybrid!$A$1:$LI$1),FALSE) -> 122.9902 | K37: =VLOOKUP($E37,Hybrid!$1:$1048576,MATCH(DATE(K$2,1,1),Hybrid!$A$1:$LI$1),FALSE) -> 150.91049 | L37: =VLOOKUP($E37,Hybrid!$1:$1048576,MATCH(DATE(L$2,1,1),Hybrid!$A$1:$LI$1),FALSE) -> 177.19542 | M37: =VLOOKUP($E37,Hybrid!$1:$1048576,MATCH(DATE(M$2,1,1),Hybrid!$A$1:$LI$1),FALSE) -> 203.6274 | ... AO37: =VLOOKUP($E37,Hybrid!$1:$1048576,MATCH(DATE(AO$2,1,1),Hybrid!$A$1:$LI$1),FALSE) -> 1302.844
D38: class A | E38: AUTO_ca_cele_0 | F38: =VLOOKUP($E38,Hybrid!$1:$1048576,MATCH(DATE(F$2,1,1),Hybrid!$A$1:$LI$1),FALSE) -> 9.8427899 | G38: =VLOOKUP($E38,Hybrid!$1:$1048576,MATCH(DATE(G$2,1,1),Hybrid!$A$1:$LI$1),FALSE) -> 15.157168 | H38: =VLOOKUP($E38,Hybrid!$1:$1048576,MATCH(DATE(H$2,1,1),Hybrid!$A$1:$LI$1),FALSE) -> 20.444627 | I38: =VLOOKUP($E38,Hybrid!$1:$1048576,MATCH(DATE(I$2,1,1),Hybrid!$A$1:$LI$1),FALSE) -> 26.028391 | J38: =VLOOKUP($E38,Hybrid!$1:$1048576,MATCH(DATE(J$2,1,1),Hybrid!$A$1:$LI$1),FALSE) -> 33.352976 | K38: =VLOOKUP($E38,Hybrid!$1:$1048576,MATCH(DATE(K$2,1,1),Hybrid!$A$1:$LI$1),FALSE) -> 42.139977 | L38: =VLOOKUP($E38,Hybrid!$1:$1048576,MATCH(DATE(L$2,1,1),Hybrid!$A$1:$LI$1),FALSE) -> 50.520577 | M38: =VLOOKUP($E38,Hybrid!$1:$1048576,MATCH(DATE(M$2,1,1),Hybrid!$A$1:$LI$1),FALSE) -> 59.084801 | ... AO38: =VLOOKUP($E38,Hybrid!$1:$1048576,MATCH(DATE(AO$2,1,1),Hybrid!$A$1:$LI$1),FALSE) -> 587.20783
D39: class B | E39: AUTO_cb_cele_0 | F39: =VLOOKUP($E39,Hybrid!$1:$1048576,MATCH(DATE(F$2,1,1),Hybrid!$A$1:$LI$1),FALSE) -> 11.445717 | G39: =VLOOKUP($E39,Hybrid!$1:$1048576,MATCH(DATE(G$2,1,1),Hybrid!$A$1:$LI$1),FALSE) -> 16.461946 | H39: =VLOOKUP($E39,Hybrid!$1:$1048576,MATCH(DATE(H$2,1,1),Hybrid!$A$1:$LI$1),FALSE) -> 21.433349 | I39: =VLOOKUP($E39,Hybrid!$1:$1048576,MATCH(DATE(I$2,1,1),Hybrid!$A$1:$LI$1),FALSE) -> 26.683623 | J39: =VLOOKUP($E39,Hybrid!$1:$1048576,MATCH(DATE(J$2,1,1),Hybrid!$A$1:$LI$1),FALSE) -> 33.615652 | K39: =VLOOKUP($E39,Hybrid!$1:$1048576,MATCH(DATE(K$2,1,1),Hybrid!$A$1:$LI$1),FALSE) -> 41.934825 | L39: =VLOOKUP($E39,Hybrid!$1:$1048576,MATCH(DATE(L$2,1,1),Hybrid!$A$1:$LI$1),FALSE) -> 49.840932 | M39: =VLOOKUP($E39,Hybrid!$1:$1048576,MATCH(DATE(M$2,1,1),Hybrid!$A$1:$LI$1),FALSE) -> 57.888851 | ... AO39: =VLOOKUP($E39,Hybrid!$1:$1048576,MATCH(DATE(AO$2,1,1),Hybrid!$A$1:$LI$1),FALSE) -> 422.2625
D40: class C | E40: AUTO_cc_cele_0 | F40: =VLOOKUP($E40,Hybrid!$1:$1048576,MATCH(DATE(F$2,1,1),Hybrid!$A$1:$LI$1),FALSE) -> 9.4015406 | G40: =VLOOKUP($E40,Hybrid!$1:$1048576,MATCH(DATE(G$2,1,1),Hybrid!$A$1:$LI$1),FALSE) -> 12.810382 | H40: =VLOOKUP($E40,Hybrid!$1:$1048576,MATCH(DATE(H$2,1,1),Hybrid!$A$1:$LI$1),FALSE) -> 16.175633 | I40: =VLOOKUP($E40,Hybrid!$1:$1048576,MATCH(DATE(I$2,1,1),Hybrid!$A$1:$LI$1),FALSE) -> 19.72907 | J40: =VLOOKUP($E40,Hybrid!$1:$1048576,MATCH(DATE(J$2,1,1),Hybrid!$A$1:$LI$1),FALSE) -> 24.449744 | K40: =VLOOKUP($E40,Hybrid!$1:$1048576,MATCH(DATE(K$2,1,1),Hybrid!$A$1:$LI$1),FALSE) -> 30.117195 | L40: =VLOOKUP($E40,Hybrid!$1:$1048576,MATCH(DATE(L$2,1,1),Hybrid!$A$1:$LI$1),FALSE) -> 35.483708 | M40: =VLOOKUP($E40,Hybrid!$1:$1048576,MATCH(DATE(M$2,1,1),Hybrid!$A$1:$LI$1),FALSE) -> 40.924607 | ... AO40: =VLOOKUP($E40,Hybrid!$1:$1048576,MATCH(DATE(AO$2,1,1),Hybrid!$A$1:$LI$1),FALSE) -> 224.12872
D41: class D | E41: AUTO_cd_cele_0 | F41: =VLOOKUP($E41,Hybrid!$1:$1048576,MATCH(DATE(F$2,1,1),Hybrid!$A$1:$LI$1),FALSE) -> 5.7700713 | G41: =VLOOKUP($E41,Hybrid!$1:$1048576,MATCH(DATE(G$2,1,1),Hybrid!$A$1:$LI$1),FALSE) -> 7.6228602 | H41: =VLOOKUP($E41,Hybrid!$1:$1048576,MATCH(DATE(H$2,1,1),Hybrid!$A$1:$LI$1),FALSE) -> 9.4510521 | I41: =VLOOKUP($E41,Hybrid!$1:$1048576,MATCH(DATE(I$2,1,1),Hybrid!$A$1:$LI$1),FALSE) -> 11.261629 | J41: =VLOOKUP($E41,Hybrid!$1:$1048576,MATCH(DATE(J$2,1,1),Hybrid!$A$1:$LI$1),FALSE) -> 13.387628 | K41: =VLOOKUP($E41,Hybrid!$1:$1048576,MATCH(DATE(K$2,1,1),Hybrid!$A$1:$LI$1),FALSE) -> 15.871449 | L41: =VLOOKUP($E41,Hybrid!$1:$1048576,MATCH(DATE(L$2,1,1),Hybrid!$A$1:$LI$1),FALSE) -> 18.187902 | M41: =VLOOKUP($E41,Hybrid!$1:$1048576,MATCH(DATE(M$2,1,1),Hybrid!$A$1:$LI$1),FALSE) -> 20.466934 | ... AO41: =VLOOKUP($E41,Hybrid!$1:$1048576,MATCH(DATE(AO$2,1,1),Hybrid!$A$1:$LI$1),FALSE) -> 45.491795
D42: class E | E42: AUTO_ce_cele_0 | F42: =VLOOKUP($E42,Hybrid!$1:$1048576,MATCH(DATE(F$2,1,1),Hybrid!$A$1:$LI$1),FALSE) -> 3.4730441 | G42: =VLOOKUP($E42,Hybrid!$1:$1048576,MATCH(DATE(G$2,1,1),Hybrid!$A$1:$LI$1),FALSE) -> 4.6091896 | H42: =VLOOKUP($E42,Hybrid!$1:$1048576,MATCH(DATE(H$2,1,1),Hybrid!$A$1:$LI$1),FALSE) -> 5.7149767 | I42: =VLOOKUP($E42,Hybrid!$1:$1048576,MATCH(DATE(I$2,1,1),Hybrid!$A$1:$LI$1),FALSE) -> 6.7928004 | J42: =VLOOKUP($E42,Hybrid!$1:$1048576,MATCH(DATE(J$2,1,1),Hybrid!$A$1:$LI$1),FALSE) -> 8.0398585 | K42: =VLOOKUP($E42,Hybrid!$1:$1048576,MATCH(DATE(K$2,1,1),Hybrid!$A$1:$LI$1),FALSE) -> 9.4759102 | L42: =VLOOKUP($E42,Hybrid!$1:$1048576,MATCH(DATE(L$2,1,1),Hybrid!$A$1:$LI$1),FALSE) -> 10.790746 | M42: =VLOOKUP($E42,Hybrid!$1:$1048576,MATCH(DATE(M$2,1,1),Hybrid!$A$1:$LI$1),FALSE) -> 12.057285 | ... AO42: =VLOOKUP($E42,Hybrid!$1:$1048576,MATCH(DATE(AO$2,1,1),Hybrid!$A$1:$LI$1),FALSE) -> 16.619222
D43: class F | E43: AUTO_cf_cele_0 | F43: =VLOOKUP($E43,Hybrid!$1:$1048576,MATCH(DATE(F$2,1,1),Hybrid!$A$1:$LI$1),FALSE) -> 1.7251505 | G43: =VLOOKUP($E43,Hybrid!$1:$1048576,MATCH(DATE(G$2,1,1),Hybrid!$A$1:$LI$1),FALSE) -> 2.2608175 | H43: =VLOOKUP($E43,Hybrid!$1:$1048576,MATCH(DATE(H$2,1,1),Hybrid!$A$1:$LI$1),FALSE) -> 2.7629561 | I43: =VLOOKUP($E43,Hybrid!$1:$1048576,MATCH(DATE(I$2,1,1),Hybrid!$A$1:$LI$1),FALSE) -> 3.2118073 | J43: =VLOOKUP($E43,Hybrid!$1:$1048576,MATCH(DATE(J$2,1,1),Hybrid!$A$1:$LI$1),FALSE) -> 3.6713826 | K43: =VLOOKUP($E43,Hybrid!$1:$1048576,MATCH(DATE(K$2,1,1),Hybrid!$A$1:$LI$1),FALSE) -> 4.1657074 | L43: =VLOOKUP($E43,Hybrid!$1:$1048576,MATCH(DATE(L$2,1,1),Hybrid!$A$1:$LI$1),FALSE) -> 4.5869138 | M43: =VLOOKUP($E43,Hybrid!$1:$1048576,MATCH(DATE(M$2,1,1),Hybrid!$A$1:$LI$1),FALSE) -> 4.9568288 | ... AO43: =VLOOKUP($E43,Hybrid!$1:$1048576,MATCH(DATE(AO$2,1,1),Hybrid!$A$1:$LI$1),FALSE) -> 3.1251022
D44: class G | E44: AUTO_cg_cele_0 | F44: =VLOOKUP($E44,Hybrid!$1:$1048576,MATCH(DATE(F$2,1,1),Hybrid!$A$1:$LI$1),FALSE) -> 3.1066862 | G44: =VLOOKUP($E44,Hybrid!$1:$1048576,MATCH(DATE(G$2,1,1),Hybrid!$A$1:$LI$1),FALSE) -> 4.0987638 | H44: =VLOOKUP($E44,Hybrid!$1:$1048576,MATCH(DATE(H$2,1,1),Hybrid!$A$1:$LI$1),FALSE) -> 4.9944538 | I44: =VLOOKUP($E44,Hybrid!$1:$1048576,MATCH(DATE(I$2,1,1),Hybrid!$A$1:$LI$1),FALSE) -> 5.7499462 | J44: =VLOOKUP($E44,Hybrid!$1:$1048576,MATCH(DATE(J$2,1,1),Hybrid!$A$1:$LI$1),FALSE) -> 6.4729559 | K44: =VLOOKUP($E44,Hybrid!$1:$1048576,MATCH(DATE(K$2,1,1),Hybrid!$A$1:$LI$1),FALSE) -> 7.205424 | L44: =VLOOKUP($E44,Hybrid!$1:$1048576,MATCH(DATE(L$2,1,1),Hybrid!$A$1:$LI$1),FALSE) -> 7.7846433 | M44: =VLOOKUP($E44,Hybrid!$1:$1048576,MATCH(DATE(M$2,1,1),Hybrid!$A$1:$LI$1),FALSE) -> 8.2480923 | ... AO44: =VLOOKUP($E44,Hybrid!$1:$1048576,MATCH(DATE(AO$2,1,1),Hybrid!$A$1:$LI$1),FALSE) -> 4.0088262
C45: GAS | E45: AUTO_cgas_0 | F45: =VLOOKUP($E45,Hybrid!$1:$1048576,MATCH(DATE(F$2,1,1),Hybrid!$A$1:$LI$1),FALSE) -> 1.936 | G45: =VLOOKUP($E45,Hybrid!$1:$1048576,MATCH(DATE(G$2,1,1),Hybrid!$A$1:$LI$1),FALSE) -> 1.9968324 | H45: =VLOOKUP($E45,Hybrid!$1:$1048576,MATCH(DATE(H$2,1,1),Hybrid!$A$1:$LI$1),FALSE) -> 2.060546 | I45: =VLOOKUP($E45,Hybrid!$1:$1048576,MATCH(DATE(I$2,1,1),Hybrid!$A$1:$LI$1),FALSE) -> 2.1196814 | J45: =VLOOKUP($E45,Hybrid!$1:$1048576,MATCH(DATE(J$2,1,1),Hybrid!$A$1:$LI$1),FALSE) -> 2.1910005 | K45: =VLOOKUP($E45,Hybrid!$1:$1048576,MATCH(DATE(K$2,1,1),Hybrid!$A$1:$LI$1),FALSE) -> 2.2894584 | L45: =VLOOKUP($E45,Hybrid!$1:$1048576,MATCH(DATE(L$2,1,1),Hybrid!$A$1:$LI$1),FALSE) -> 2.3779418 | M45: =VLOOKUP($E45,Hybrid!$1:$1048576,MATCH(DATE(M$2,1,1),Hybrid!$A$1:$LI$1),FALSE) -> 2.4646039 | ... AO45: =VLOOKUP($E45,Hybrid!$1:$1048576,MATCH(DATE(AO$2,1,1),Hybrid!$A$1:$LI$1),FALSE) -> 4.2712199
D46: class A | E46: AUTO_ca_cgas_0 | F46: =VLOOKUP($E46,Hybrid!$1:$1048576,MATCH(DATE(F$2,1,1),Hybrid!$A$1:$LI$1),FALSE) -> 0.4256817 | G46: =VLOOKUP($E46,Hybrid!$1:$1048576,MATCH(DATE(G$2,1,1),Hybrid!$A$1:$LI$1),FALSE) -> 0.45084295 | H46: =VLOOKUP($E46,Hybrid!$1:$1048576,MATCH(DATE(H$2,1,1),Hybrid!$A$1:$LI$1),FALSE) -> 0.47695788 | I46: =VLOOKUP($E46,Hybrid!$1:$1048576,MATCH(DATE(I$2,1,1),Hybrid!$A$1:$LI$1),FALSE) -> 0.50234383 | J46: =VLOOKUP($E46,Hybrid!$1:$1048576,MATCH(DATE(J$2,1,1),Hybrid!$A$1:$LI$1),FALSE) -> 0.53210293 | K46: =VLOOKUP($E46,Hybrid!$1:$1048576,MATCH(DATE(K$2,1,1),Hybrid!$A$1:$LI$1),FALSE) -> 0.57042379 | L46: =VLOOKUP($E46,Hybrid!$1:$1048576,MATCH(DATE(L$2,1,1),Hybrid!$A$1:$LI$1),FALSE) -> 0.60596968 | M46: =VLOOKUP($E46,Hybrid!$1:$1048576,MATCH(DATE(M$2,1,1),Hybrid!$A$1:$LI$1),FALSE) -> 0.64147863 | ... AO46: =VLOOKUP($E46,Hybrid!$1:$1048576,MATCH(DATE(AO$2,1,1),Hybrid!$A$1:$LI$1),FALSE) -> 1.8414263
D47: class B | E47: AUTO_cb_cgas_0 | F47: =VLOOKUP($E47,Hybrid!$1:$1048576,MATCH(DATE(F$2,1,1),Hybrid!$A$1:$LI$1),FALSE) -> 0.49500523 | G47: =VLOOKUP($E47,Hybrid!$1:$1048576,MATCH(DATE(G$2,1,1),Hybrid!$A$1:$LI$1),FALSE) -> 0.51370793 | H47: =VLOOKUP($E47,Hybrid!$1:$1048576,MATCH(DATE(H$2,1,1),Hybrid!$A$1:$LI$1),FALSE) -> 0.53354294 | I47: =VLOOKUP($E47,Hybrid!$1:$1048576,MATCH(DATE(I$2,1,1),Hybrid!$A$1:$LI$1),FALSE) -> 0.55272136 | J47: =VLOOKUP($E47,Hybrid!$1:$1048576,MATCH(DATE(J$2,1,1),Hybrid!$A$1:$LI$1),FALSE) -> 0.57599895 | K47: =VLOOKUP($E47,Hybrid!$1:$1048576,MATCH(DATE(K$2,1,1),Hybrid!$A$1:$LI$1),FALSE) -> 0.60748622 | L47: =VLOOKUP($E47,Hybrid!$1:$1048576,MATCH(DATE(L$2,1,1),Hybrid!$A$1:$LI$1),FALSE) -> 0.63650963 | M47: =VLOOKUP($E47,Hybrid!$1:$1048576,MATCH(DATE(M$2,1,1),Hybrid!$A$1:$LI$1),FALSE) -> 0.66549998 | ... AO47: =VLOOKUP($E47,Hybrid!$1:$1048576,MATCH(DATE(AO$2,1,1),Hybrid!$A$1:$LI$1),FALSE) -> 1.3666867
D48: class C | E48: AUTO_cc_cgas_0 | F48: =VLOOKUP($E48,Hybrid!$1:$1048576,MATCH(DATE(F$2,1,1),Hybrid!$A$1:$LI$1),FALSE) -> 0.40659852 | G48: =VLOOKUP($E48,Hybrid!$1:$1048576,MATCH(DATE(G$2,1,1),Hybrid!$A$1:$LI$1),FALSE) -> 0.41550713 | H48: =VLOOKUP($E48,Hybrid!$1:$1048576,MATCH(DATE(H$2,1,1),Hybrid!$A$1:$LI$1),FALSE) -> 0.42536707 | I48: =VLOOKUP($E48,Hybrid!$1:$1048576,MATCH(DATE(I$2,1,1),Hybrid!$A$1:$LI$1),FALSE) -> 0.43482241 | J48: =VLOOKUP($E48,Hybrid!$1:$1048576,MATCH(DATE(J$2,1,1),Hybrid!$A$1:$LI$1),FALSE) -> 0.44707018 | K48: =VLOOKUP($E48,Hybrid!$1:$1048576,MATCH(DATE(K$2,1,1),Hybrid!$A$1:$LI$1),FALSE) -> 0.46501401 | L48: =VLOOKUP($E48,Hybrid!$1:$1048576,MATCH(DATE(L$2,1,1),Hybrid!$A$1:$LI$1),FALSE) -> 0.48140681 | M48: =VLOOKUP($E48,Hybrid!$1:$1048576,MATCH(DATE(M$2,1,1),Hybrid!$A$1:$LI$1),FALSE) -> 0.49780028 | ... AO48: =VLOOKUP($E48,Hybrid!$1:$1048576,MATCH(DATE(AO$2,1,1),Hybrid!$A$1:$LI$1),FALSE) -> 0.75325033
D49: class D | E49: AUTO_cd_cgas_0 | F49: =VLOOKUP($E49,Hybrid!$1:$1048576,MATCH(DATE(F$2,1,1),Hybrid!$A$1:$LI$1),FALSE) -> 0.24954447 | G49: =VLOOKUP($E49,Hybrid!$1:$1048576,MATCH(DATE(G$2,1,1),Hybrid!$A$1:$LI$1),FALSE) -> 0.25285832 | H49: =VLOOKUP($E49,Hybrid!$1:$1048576,MATCH(DATE(H$2,1,1),Hybrid!$A$1:$LI$1),FALSE) -> 0.25657518 | I49: =VLOOKUP($E49,Hybrid!$1:$1048576,MATCH(DATE(I$2,1,1),Hybrid!$A$1:$LI$1),FALSE) -> 0.25980708 | J49: =VLOOKUP($E49,Hybrid!$1:$1048576,MATCH(DATE(J$2,1,1),Hybrid!$A$1:$LI$1),FALSE) -> 0.26420163 | K49: =VLOOKUP($E49,Hybrid!$1:$1048576,MATCH(DATE(K$2,1,1),Hybrid!$A$1:$LI$1),FALSE) -> 0.27132781 | L49: =VLOOKUP($E49,Hybrid!$1:$1048576,MATCH(DATE(L$2,1,1),Hybrid!$A$1:$LI$1),FALSE) -> 0.277446 | M49: =VLOOKUP($E49,Hybrid!$1:$1048576,MATCH(DATE(M$2,1,1),Hybrid!$A$1:$LI$1),FALSE) -> 0.28326254 | ... AO49: =VLOOKUP($E49,Hybrid!$1:$1048576,MATCH(DATE(AO$2,1,1),Hybrid!$A$1:$LI$1),FALSE) -> 0.18867474
D50: class E | E50: AUTO_ce_cgas_0 | F50: =VLOOKUP($E50,Hybrid!$1:$1048576,MATCH(DATE(F$2,1,1),Hybrid!$A$1:$LI$1),FALSE) -> 0.15020247 | G50: =VLOOKUP($E50,Hybrid!$1:$1048576,MATCH(DATE(G$2,1,1),Hybrid!$A$1:$LI$1),FALSE) -> 0.15238593 | H50: =VLOOKUP($E50,Hybrid!$1:$1048576,MATCH(DATE(H$2,1,1),Hybrid!$A$1:$LI$1),FALSE) -> 0.15468725 | I50: =VLOOKUP($E50,Hybrid!$1:$1048576,MATCH(DATE(I$2,1,1),Hybrid!$A$1:$LI$1),FALSE) -> 0.15649018 | J50: =VLOOKUP($E50,Hybrid!$1:$1048576,MATCH(DATE(J$2,1,1),Hybrid!$A$1:$LI$1),FALSE) -> 0.15874617 | K50: =VLOOKUP($E50,Hybrid!$1:$1048576,MATCH(DATE(K$2,1,1),Hybrid!$A$1:$LI$1),FALSE) -> 0.16241596 | L50: =VLOOKUP($E50,Hybrid!$1:$1048576,MATCH(DATE(L$2,1,1),Hybrid!$A$1:$LI$1),FALSE) -> 0.16535808 | M50: =VLOOKUP($E50,Hybrid!$1:$1048576,MATCH(DATE(M$2,1,1),Hybrid!$A$1:$LI$1),FALSE) -> 0.16793944 | ... AO50: =VLOOKUP($E50,Hybrid!$1:$1048576,MATCH(DATE(AO$2,1,1),Hybrid!$A$1:$LI$1),FALSE) -> 0.075017242
D51: class F | E51: AUTO_cf_cgas_0 | F51: =VLOOKUP($E51,Hybrid!$1:$1048576,MATCH(DATE(F$2,1,1),Hybrid!$A$1:$LI$1),FALSE) -> 0.074609436 | G51: =VLOOKUP($E51,Hybrid!$1:$1048576,MATCH(DATE(G$2,1,1),Hybrid!$A$1:$LI$1),FALSE) -> 0.075435583 | H51: =VLOOKUP($E51,Hybrid!$1:$1048576,MATCH(DATE(H$2,1,1),Hybrid!$A$1:$LI$1),FALSE) -> 0.076134567 | I51: =VLOOKUP($E51,Hybrid!$1:$1048576,MATCH(DATE(I$2,1,1),Hybrid!$A$1:$LI$1),FALSE) -> 0.076336312 | J51: =VLOOKUP($E51,Hybrid!$1:$1048576,MATCH(DATE(J$2,1,1),Hybrid!$A$1:$LI$1),FALSE) -> 0.076438727 | K51: =VLOOKUP($E51,Hybrid!$1:$1048576,MATCH(DATE(K$2,1,1),Hybrid!$A$1:$LI$1),FALSE) -> 0.076873442 | L51: =VLOOKUP($E51,Hybrid!$1:$1048576,MATCH(DATE(L$2,1,1),Hybrid!$A$1:$LI$1),FALSE) -> 0.076837512 | M51: =VLOOKUP($E51,Hybrid!$1:$1048576,MATCH(DATE(M$2,1,1),Hybrid!$A$1:$LI$1),FALSE) -> 0.076460147 | ... AO51: =VLOOKUP($E51,Hybrid!$1:$1048576,MATCH(DATE(AO$2,1,1),Hybrid!$A$1:$LI$1),FALSE) -> 0.018854075
D52: class G | E52: AUTO_cg_cgas_0 | F52: =VLOOKUP($E52,Hybrid!$1:$1048576,MATCH(DATE(F$2,1,1),Hybrid!$A$1:$LI$1),FALSE) -> 0.13435819 | G52: =VLOOKUP($E52,Hybrid!$1:$1048576,MATCH(DATE(G$2,1,1),Hybrid!$A$1:$LI$1),FALSE) -> 0.13609456 | H52: =VLOOKUP($E52,Hybrid!$1:$1048576,MATCH(DATE(H$2,1,1),Hybrid!$A$1:$LI$1),FALSE) -> 0.13728112 | I52: =VLOOKUP($E52,Hybrid!$1:$1048576,MATCH(DATE(I$2,1,1),Hybrid!$A$1:$LI$1),FALSE) -> 0.13716024 | J52: =VLOOKUP($E52,Hybrid!$1:$1048576,MATCH(DATE(J$2,1,1),Hybrid!$A$1:$LI$1),FALSE) -> 0.13644192 | K52: =VLOOKUP($E52,Hybrid!$1:$1048576,MATCH(DATE(K$2,1,1),Hybrid!$A$1:$LI$1),FALSE) -> 0.13591716 | L52: =VLOOKUP($E52,Hybrid!$1:$1048576,MATCH(DATE(L$2,1,1),Hybrid!$A$1:$LI$1),FALSE) -> 0.13441412 | M52: =VLOOKUP($E52,Hybrid!$1:$1048576,MATCH(DATE(M$2,1,1),Hybrid!$A$1:$LI$1),FALSE) -> 0.13216288 | ... AO52: =VLOOKUP($E52,Hybrid!$1:$1048576,MATCH(DATE(AO$2,1,1),Hybrid!$A$1:$LI$1),FALSE) -> 0.02731051
C53: TOTAL SALES SHOCK | E53: NEWAUTO_2 | F53: =VLOOKUP($E53,Hybrid!$1:$1048576,MATCH(DATE(F$2,1,1),Hybrid!$A$1:$LI$1),FALSE) -> 1886.229 | G53: =VLOOKUP($E53,Hybrid!$1:$1048576,MATCH(DATE(G$2,1,1),Hybrid!$A$1:$LI$1),FALSE) -> 2184.6168 | H53: =VLOOKUP($E53,Hybrid!$1:$1048576,MATCH(DATE(H$2,1,1),Hybrid!$A$1:$LI$1),FALSE) -> 2264.6053 | I53: =VLOOKUP($E53,Hybrid!$1:$1048576,MATCH(DATE(I$2,1,1),Hybrid!$A$1:$LI$1),FALSE) -> 2258.7517 | J53: =VLOOKUP($E53,Hybrid!$1:$1048576,MATCH(DATE(J$2,1,1),Hybrid!$A$1:$LI$1),FALSE) -> 2453.578 | K53: =VLOOKUP($E53,Hybrid!$1:$1048576,MATCH(DATE(K$2,1,1),Hybrid!$A$1:$LI$1),FALSE) -> 2835.035 | L53: =VLOOKUP($E53,Hybrid!$1:$1048576,MATCH(DATE(L$2,1,1),Hybrid!$A$1:$LI$1),FALSE) -> 2789.0324 | M53: =VLOOKUP($E53,Hybrid!$1:$1048576,MATCH(DATE(M$2,1,1),Hybrid!$A$1:$LI$1),FALSE) -> 2812.6521 | ... AO53: =VLOOKUP($E53,Hybrid!$1:$1048576,MATCH(DATE(AO$2,1,1),Hybrid!$A$1:$LI$1),FALSE) -> 3266.3302
C54: OIL | E54: NEWAUTO_cfut_2 | F54: =VLOOKUP($E54,Hybrid!$1:$1048576,MATCH(DATE(F$2,1,1),Hybrid!$A$1:$LI$1),FALSE) -> 1868.672 | G54: =VLOOKUP($E54,Hybrid!$1:$1048576,MATCH(DATE(G$2,1,1),Hybrid!$A$1:$LI$1),FALSE) -> 2164.3883 | H54: =VLOOKUP($E54,Hybrid!$1:$1048576,MATCH(DATE(H$2,1,1),Hybrid!$A$1:$LI$1),FALSE) -> 2243.94 | I54: =VLOOKUP($E54,Hybrid!$1:$1048576,MATCH(DATE(I$2,1,1),Hybrid!$A$1:$LI$1),FALSE) -> 2236.8445 | J54: =VLOOKUP($E54,Hybrid!$1:$1048576,MATCH(DATE(J$2,1,1),Hybrid!$A$1:$LI$1),FALSE) -> 2425.863 | K54: =VLOOKUP($E54,Hybrid!$1:$1048576,MATCH(DATE(K$2,1,1),Hybrid!$A$1:$LI$1),FALSE) -> 2801.9597 | L54: =VLOOKUP($E54,Hybrid!$1:$1048576,MATCH(DATE(L$2,1,1),Hybrid!$A$1:$LI$1),FALSE) -> 2756.4794 | M54: =VLOOKUP($E54,Hybrid!$1:$1048576,MATCH(DATE(M$2,1,1),Hybrid!$A$1:$LI$1),FALSE) -> 2778.8887 | ... AO54: =VLOOKUP($E54,Hybrid!$1:$1048576,MATCH(DATE(AO$2,1,1),Hybrid!$A$1:$LI$1),FALSE) -> 2955.3149
D55: class A | E55: NEWAUTO_ca_cfut_2 | F55: =VLOOKUP($E55,Hybrid!$1:$1048576,MATCH(DATE(F$2,1,1),Hybrid!$A$1:$LI$1),FALSE) -> 528.64494 | G55: =VLOOKUP($E55,Hybrid!$1:$1048576,MATCH(DATE(G$2,1,1),Hybrid!$A$1:$LI$1),FALSE) -> 616.18553 | H55: =VLOOKUP($E55,Hybrid!$1:$1048576,MATCH(DATE(H$2,1,1),Hybrid!$A$1:$LI$1),FALSE) -> 646.25606 | I55: =VLOOKUP($E55,Hybrid!$1:$1048576,MATCH(DATE(I$2,1,1),Hybrid!$A$1:$LI$1),FALSE) -> 657.00705 | J55: =VLOOKUP($E55,Hybrid!$1:$1048576,MATCH(DATE(J$2,1,1),Hybrid!$A$1:$LI$1),FALSE) -> 727.94743 | K55: =VLOOKUP($E55,Hybrid!$1:$1048576,MATCH(DATE(K$2,1,1),Hybrid!$A$1:$LI$1),FALSE) -> 851.99909 | L55: =VLOOKUP($E55,Hybrid!$1:$1048576,MATCH(DATE(L$2,1,1),Hybrid!$A$1:$LI$1),FALSE) -> 847.47695 | M55: =VLOOKUP($E55,Hybrid!$1:$1048576,MATCH(DATE(M$2,1,1),Hybrid!$A$1:$LI$1),FALSE) -> 867.67507 | ... AO55: =VLOOKUP($E55,Hybrid!$1:$1048576,MATCH(DATE(AO$2,1,1),Hybrid!$A$1:$LI$1),FALSE) -> 2121.7146
D56: class B | E56: NEWAUTO_cb_cfut_2 | F56: =VLOOKUP($E56,Hybrid!$1:$1048576,MATCH(DATE(F$2,1,1),Hybrid!$A$1:$LI$1),FALSE) -> 507.52609 | G56: =VLOOKUP($E56,Hybrid!$1:$1048576,MATCH(DATE(G$2,1,1),Hybrid!$A$1:$LI$1),FALSE) -> 590.88139 | H56: =VLOOKUP($E56,Hybrid!$1:$1048576,MATCH(DATE(H$2,1,1),Hybrid!$A$1:$LI$1),FALSE) -> 618.27323 | I56: =VLOOKUP($E56,Hybrid!$1:$1048576,MATCH(DATE(I$2,1,1),Hybrid!$A$1:$LI$1),FALSE) -> 625.21413 | J56: =VLOOKUP($E56,Hybrid!$1:$1048576,MATCH(DATE(J$2,1,1),Hybrid!$A$1:$LI$1),FALSE) -> 688.275 | K56: =VLOOKUP($E56,Hybrid!$1:$1048576,MATCH(DATE(K$2,1,1),Hybrid!$A$1:$LI$1),FALSE) -> 803.31397 | L56: =VLOOKUP($E56,Hybrid!$1:$1048576,MATCH(DATE(L$2,1,1),Hybrid!$A$1:$LI$1),FALSE) -> 797.41103 | M56: =VLOOKUP($E56,Hybrid!$1:$1048576,MATCH(DATE(M$2,1,1),Hybrid!$A$1:$LI$1),FALSE) -> 812.77904 | ... AO56: =VLOOKUP($E56,Hybrid!$1:$1048576,MATCH(DATE(AO$2,1,1),Hybrid!$A$1:$LI$1),FALSE) -> 661.82908
D57: class C | E57: NEWAUTO_cc_cfut_2 | F57: =VLOOKUP($E57,Hybrid!$1:$1048576,MATCH(DATE(F$2,1,1),Hybrid!$A$1:$LI$1),FALSE) -> 351.30482 | G57: =VLOOKUP($E57,Hybrid!$1:$1048576,MATCH(DATE(G$2,1,1),Hybrid!$A$1:$LI$1),FALSE) -> 408.53004 | H57: =VLOOKUP($E57,Hybrid!$1:$1048576,MATCH(DATE(H$2,1,1),Hybrid!$A$1:$LI$1),FALSE) -> 426.4816 | I57: =VLOOKUP($E57,Hybrid!$1:$1048576,MATCH(DATE(I$2,1,1),Hybrid!$A$1:$LI$1),FALSE) -> 429.00078 | J57: =VLOOKUP($E57,Hybrid!$1:$1048576,MATCH(DATE(J$2,1,1),Hybrid!$A$1:$LI$1),FALSE) -> 469.27384 | K57: =VLOOKUP($E57,Hybrid!$1:$1048576,MATCH(DATE(K$2,1,1),Hybrid!$A$1:$LI$1),FALSE) -> 546.18706 | L57: =VLOOKUP($E57,Hybrid!$1:$1048576,MATCH(DATE(L$2,1,1),Hybrid!$A$1:$LI$1),FALSE) -> 541.07413 | M57: =VLOOKUP($E57,Hybrid!$1:$1048576,MATCH(DATE(M$2,1,1),Hybrid!$A$1:$LI$1),FALSE) -> 549.07802 | ... AO57: =VLOOKUP($E57,Hybrid!$1:$1048576,MATCH(DATE(AO$2,1,1),Hybrid!$A$1:$LI$1),FALSE) -> 169.25215
D58: class D | E58: NEWAUTO_cd_cfut_2 | F58: =VLOOKUP($E58,Hybrid!$1:$1048576,MATCH(DATE(F$2,1,1),Hybrid!$A$1:$LI$1),FALSE) -> 194.72089 | G58: =VLOOKUP($E58,Hybrid!$1:$1048576,MATCH(DATE(G$2,1,1),Hybrid!$A$1:$LI$1),FALSE) -> 225.09419 | H58: =VLOOKUP($E58,Hybrid!$1:$1048576,MATCH(DATE(H$2,1,1),Hybrid!$A$1:$LI$1),FALSE) -> 232.35655 | I58: =VLOOKUP($E58,Hybrid!$1:$1048576,MATCH(DATE(I$2,1,1),Hybrid!$A$1:$LI$1),FALSE) -> 229.34914 | J58: =VLOOKUP($E58,Hybrid!$1:$1048576,MATCH(DATE(J$2,1,1),Hybrid!$A$1:$LI$1),FALSE) -> 245.5927 | K58: =VLOOKUP($E58,Hybrid!$1:$1048576,MATCH(DATE(K$2,1,1),Hybrid!$A$1:$LI$1),FALSE) -> 281.37729 | L58: =VLOOKUP($E58,Hybrid!$1:$1048576,MATCH(DATE(L$2,1,1),Hybrid!$A$1:$LI$1),FALSE) -> 274.68038 | M58: =VLOOKUP($E58,Hybrid!$1:$1048576,MATCH(DATE(M$2,1,1),Hybrid!$A$1:$LI$1),FALSE) -> 273.1911 | ... AO58: =VLOOKUP($E58,Hybrid!$1:$1048576,MATCH(DATE(AO$2,1,1),Hybrid!$A$1:$LI$1),FALSE) -> 2.4435391
D59: class E | E59: NEWAUTO_ce_cfut_2 | F59: =VLOOKUP($E59,Hybrid!$1:$1048576,MATCH(DATE(F$2,1,1),Hybrid!$A$1:$LI$1),FALSE) -> 119.78434 | G59: =VLOOKUP($E59,Hybrid!$1:$1048576,MATCH(DATE(G$2,1,1),Hybrid!$A$1:$LI$1),FALSE) -> 137.73343 | H59: =VLOOKUP($E59,Hybrid!$1:$1048576,MATCH(DATE(H$2,1,1),Hybrid!$A$1:$LI$1),FALSE) -> 140.76063 | I59: =VLOOKUP($E59,Hybrid!$1:$1048576,MATCH(DATE(I$2,1,1),Hybrid!$A$1:$LI$1),FALSE) -> 136.54019 | J59: =VLOOKUP($E59,Hybrid!$1:$1048576,MATCH(DATE(J$2,1,1),Hybrid!$A$1:$LI$1),FALSE) -> 143.27439 | K59: =VLOOKUP($E59,Hybrid!$1:$1048576,MATCH(DATE(K$2,1,1),Hybrid!$A$1:$LI$1),FALSE) -> 161.78155 | L59: =VLOOKUP($E59,Hybrid!$1:$1048576,MATCH(DATE(L$2,1,1),Hybrid!$A$1:$LI$1),FALSE) -> 155.84999 | M59: =VLOOKUP($E59,Hybrid!$1:$1048576,MATCH(DATE(M$2,1,1),Hybrid!$A$1:$LI$1),FALSE) -> 152.1913 | ... AO59: =VLOOKUP($E59,Hybrid!$1:$1048576,MATCH(DATE(AO$2,1,1),Hybrid!$A$1:$LI$1),FALSE) -> 0.074831725
D60: class F | E60: NEWAUTO_cf_cfut_2 | F60: =VLOOKUP($E60,Hybrid!$1:$1048576,MATCH(DATE(F$2,1,1),Hybrid!$A$1:$LI$1),FALSE) -> 57.930882 | G60: =VLOOKUP($E60,Hybrid!$1:$1048576,MATCH(DATE(G$2,1,1),Hybrid!$A$1:$LI$1),FALSE) -> 65.339505 | H60: =VLOOKUP($E60,Hybrid!$1:$1048576,MATCH(DATE(H$2,1,1),Hybrid!$A$1:$LI$1),FALSE) -> 64.440466 | I60: =VLOOKUP($E60,Hybrid!$1:$1048576,MATCH(DATE(I$2,1,1),Hybrid!$A$1:$LI$1),FALSE) -> 59.041743 | J60: =VLOOKUP($E60,Hybrid!$1:$1048576,MATCH(DATE(J$2,1,1),Hybrid!$A$1:$LI$1),FALSE) -> 58.009481 | K60: =VLOOKUP($E60,Hybrid!$1:$1048576,MATCH(DATE(K$2,1,1),Hybrid!$A$1:$LI$1),FALSE) -> 62.041117 | L60: =VLOOKUP($E60,Hybrid!$1:$1048576,MATCH(DATE(L$2,1,1),Hybrid!$A$1:$LI$1),FALSE) -> 56.762331 | M60: =VLOOKUP($E60,Hybrid!$1:$1048576,MATCH(DATE(M$2,1,1),Hybrid!$A$1:$LI$1),FALSE) -> 51.957966 | ... AO60: =VLOOKUP($E60,Hybrid!$1:$1048576,MATCH(DATE(AO$2,1,1),Hybrid!$A$1:$LI$1),FALSE) -> 0.00042036833
D61: class G | E61: NEWAUTO_cg_cfut_2 | F61: =VLOOKUP($E61,Hybrid!$1:$1048576,MATCH(DATE(F$2,1,1),Hybrid!$A$1:$LI$1),FALSE) -> 108.76007 | G61: =VLOOKUP($E61,Hybrid!$1:$1048576,MATCH(DATE(G$2,1,1),Hybrid!$A$1:$LI$1),FALSE) -> 120.62416 | H61: =VLOOKUP($E61,Hybrid!$1:$1048576,MATCH(DATE(H$2,1,1),Hybrid!$A$1:$LI$1),FALSE) -> 115.37146 | I61: =VLOOKUP($E61,Hybrid!$1:$1048576,MATCH(DATE(I$2,1,1),Hybrid!$A$1:$LI$1),FALSE) -> 100.69141 | J61: =VLOOKUP($E61,Hybrid!$1:$1048576,MATCH(DATE(J$2,1,1),Hybrid!$A$1:$LI$1),FALSE) -> 93.490133 | K61: =VLOOKUP($E61,Hybrid!$1:$1048576,MATCH(DATE(K$2,1,1),Hybrid!$A$1:$LI$1),FALSE) -> 95.259594 | L61: =VLOOKUP($E61,Hybrid!$1:$1048576,MATCH(DATE(L$2,1,1),Hybrid!$A$1:$LI$1),FALSE) -> 83.224633 | M61: =VLOOKUP($E61,Hybrid!$1:$1048576,MATCH(DATE(M$2,1,1),Hybrid!$A$1:$LI$1),FALSE) -> 72.016196 | ... AO61: =VLOOKUP($E61,Hybrid!$1:$1048576,MATCH(DATE(AO$2,1,1),Hybrid!$A$1:$LI$1),FALSE) -> 0.00027029982
C62: ELEC | E62: NEWAUTO_cele_2 | F62: =VLOOKUP($E62,Hybrid!$1:$1048576,MATCH(DATE(F$2,1,1),Hybrid!$A$1:$LI$1),FALSE) -> 17.399981 | G62: =VLOOKUP($E62,Hybrid!$1:$1048576,MATCH(DATE(G$2,1,1),Hybrid!$A$1:$LI$1),FALSE) -> 20.046727 | H62: =VLOOKUP($E62,Hybrid!$1:$1048576,MATCH(DATE(H$2,1,1),Hybrid!$A$1:$LI$1),FALSE) -> 20.476767 | I62: =VLOOKUP($E62,Hybrid!$1:$1048576,MATCH(DATE(I$2,1,1),Hybrid!$A$1:$LI$1),FALSE) -> 21.719299 | J62: =VLOOKUP($E62,Hybrid!$1:$1048576,MATCH(DATE(J$2,1,1),Hybrid!$A$1:$LI$1),FALSE) -> 27.511221 | K62: =VLOOKUP($E62,Hybrid!$1:$1048576,MATCH(DATE(K$2,1,1),Hybrid!$A$1:$LI$1),FALSE) -> 32.839898 | L62: =VLOOKUP($E62,Hybrid!$1:$1048576,MATCH(DATE(L$2,1,1),Hybrid!$A$1:$LI$1),FALSE) -> 32.321355 | M62: =VLOOKUP($E62,Hybrid!$1:$1048576,MATCH(DATE(M$2,1,1),Hybrid!$A$1:$LI$1),FALSE) -> 33.529959 | ... AO62: =VLOOKUP($E62,Hybrid!$1:$1048576,MATCH(DATE(AO$2,1,1),Hybrid!$A$1:$LI$1),FALSE) -> 529.8608
D63: class A | E63: NEWAUTO_ca_cele_2 | F63: =VLOOKUP($E63,Hybrid!$1:$1048576,MATCH(DATE(F$2,1,1),Hybrid!$A$1:$LI$1),FALSE) -> 4.9248306 | G63: =VLOOKUP($E63,Hybrid!$1:$1048576,MATCH(DATE(G$2,1,1),Hybrid!$A$1:$LI$1),FALSE) -> 5.7080893 | H63: =VLOOKUP($E63,Hybrid!$1:$1048576,MATCH(DATE(H$2,1,1),Hybrid!$A$1:$LI$1),FALSE) -> 5.8937466 | I63: =VLOOKUP($E63,Hybrid!$1:$1048576,MATCH(DATE(I$2,1,1),Hybrid!$A$1:$LI$1),FALSE) -> 6.4015487 | J63: =VLOOKUP($E63,Hybrid!$1:$1048576,MATCH(DATE(J$2,1,1),Hybrid!$A$1:$LI$1),FALSE) -> 8.3657204 | K63: =VLOOKUP($E63,Hybrid!$1:$1048576,MATCH(DATE(K$2,1,1),Hybrid!$A$1:$LI$1),FALSE) -> 10.12112 | L63: =VLOOKUP($E63,Hybrid!$1:$1048576,MATCH(DATE(L$2,1,1),Hybrid!$A$1:$LI$1),FALSE) -> 10.0662 | M63: =VLOOKUP($E63,Hybrid!$1:$1048576,MATCH(DATE(M$2,1,1),Hybrid!$A$1:$LI$1),FALSE) -> 10.601161 | ... AO63: =VLOOKUP($E63,Hybrid!$1:$1048576,MATCH(DATE(AO$2,1,1),Hybrid!$A$1:$LI$1),FALSE) -> 358.56132
D64: class B | E64: NEWAUTO_cb_cele_2 | F64: =VLOOKUP($E64,Hybrid!$1:$1048576,MATCH(DATE(F$2,1,1),Hybrid!$A$1:$LI$1),FALSE) -> 4.7310662 | G64: =VLOOKUP($E64,Hybrid!$1:$1048576,MATCH(DATE(G$2,1,1),Hybrid!$A$1:$LI$1),FALSE) -> 5.4740577 | H64: =VLOOKUP($E64,Hybrid!$1:$1048576,MATCH(DATE(H$2,1,1),Hybrid!$A$1:$LI$1),FALSE) -> 5.6298808 | I64: =VLOOKUP($E64,Hybrid!$1:$1048576,MATCH(DATE(I$2,1,1),Hybrid!$A$1:$LI$1),FALSE) -> 6.1076074 | J64: =VLOOKUP($E64,Hybrid!$1:$1048576,MATCH(DATE(J$2,1,1),Hybrid!$A$1:$LI$1),FALSE) -> 7.9993744 | K64: =VLOOKUP($E64,Hybrid!$1:$1048576,MATCH(DATE(K$2,1,1),Hybrid!$A$1:$LI$1),FALSE) -> 9.6637987 | L64: =VLOOKUP($E64,Hybrid!$1:$1048576,MATCH(DATE(L$2,1,1),Hybrid!$A$1:$LI$1),FALSE) -> 9.5835001 | M64: =VLOOKUP($E64,Hybrid!$1:$1048576,MATCH(DATE(M$2,1,1),Hybrid!$A$1:$LI$1),FALSE) -> 10.056763 | ... AO64: =VLOOKUP($E64,Hybrid!$1:$1048576,MATCH(DATE(AO$2,1,1),Hybrid!$A$1:$LI$1),FALSE) -> 134.07727
D65: class C | E65: NEWAUTO_cc_cele_2 | F65: =VLOOKUP($E65,Hybrid!$1:$1048576,MATCH(DATE(F$2,1,1),Hybrid!$A$1:$LI$1),FALSE) -> 3.2767218 | G65: =VLOOKUP($E65,Hybrid!$1:$1048576,MATCH(DATE(G$2,1,1),Hybrid!$A$1:$LI$1),FALSE) -> 3.7849027 | H65: =VLOOKUP($E65,Hybrid!$1:$1048576,MATCH(DATE(H$2,1,1),Hybrid!$A$1:$LI$1),FALSE) -> 3.8776671 | I65: =VLOOKUP($E65,Hybrid!$1:$1048576,MATCH(DATE(I$2,1,1),Hybrid!$A$1:$LI$1),FALSE) -> 4.2004619 | J65: =VLOOKUP($E65,Hybrid!$1:$1048576,MATCH(DATE(J$2,1,1),Hybrid!$A$1:$LI$1),FALSE) -> 5.5098365 | K65: =VLOOKUP($E65,Hybrid!$1:$1048576,MATCH(DATE(K$2,1,1),Hybrid!$A$1:$LI$1),FALSE) -> 6.6454407 | L65: =VLOOKUP($E65,Hybrid!$1:$1048576,MATCH(DATE(L$2,1,1),Hybrid!$A$1:$LI$1),FALSE) -> 6.5712009 | M65: =VLOOKUP($E65,Hybrid!$1:$1048576,MATCH(DATE(M$2,1,1),Hybrid!$A$1:$LI$1),FALSE) -> 6.8703358 | ... AO65: =VLOOKUP($E65,Hybrid!$1:$1048576,MATCH(DATE(AO$2,1,1),Hybrid!$A$1:$LI$1),FALSE) -> 36.920829
D66: class D | E66: NEWAUTO_cd_cele_2 | F66: =VLOOKUP($E66,Hybrid!$1:$1048576,MATCH(DATE(F$2,1,1),Hybrid!$A$1:$LI$1),FALSE) -> 1.8078176 | G66: =VLOOKUP($E66,Hybrid!$1:$1048576,MATCH(DATE(G$2,1,1),Hybrid!$A$1:$LI$1),FALSE) -> 2.0835918 | H66: =VLOOKUP($E66,Hybrid!$1:$1048576,MATCH(DATE(H$2,1,1),Hybrid!$A$1:$LI$1),FALSE) -> 2.1331063 | I66: =VLOOKUP($E66,Hybrid!$1:$1048576,MATCH(DATE(I$2,1,1),Hybrid!$A$1:$LI$1),FALSE) -> 2.1886185 | J66: =VLOOKUP($E66,Hybrid!$1:$1048576,MATCH(DATE(J$2,1,1),Hybrid!$A$1:$LI$1),FALSE) -> 2.5764642 | K66: =VLOOKUP($E66,Hybrid!$1:$1048576,MATCH(DATE(K$2,1,1),Hybrid!$A$1:$LI$1),FALSE) -> 3.0193267 | L66: =VLOOKUP($E66,Hybrid!$1:$1048576,MATCH(DATE(L$2,1,1),Hybrid!$A$1:$LI$1),FALSE) -> 2.9513106 | M66: =VLOOKUP($E66,Hybrid!$1:$1048576,MATCH(DATE(M$2,1,1),Hybrid!$A$1:$LI$1),FALSE) -> 2.9959839 | ... AO66: =VLOOKUP($E66,Hybrid!$1:$1048576,MATCH(DATE(AO$2,1,1),Hybrid!$A$1:$LI$1),FALSE) -> 0.29311659
D67: class E | E67: NEWAUTO_ce_cele_2 | F67: =VLOOKUP($E67,Hybrid!$1:$1048576,MATCH(DATE(F$2,1,1),Hybrid!$A$1:$LI$1),FALSE) -> 1.1128791 | G67: =VLOOKUP($E67,Hybrid!$1:$1048576,MATCH(DATE(G$2,1,1),Hybrid!$A$1:$LI$1),FALSE) -> 1.2750673 | H67: =VLOOKUP($E67,Hybrid!$1:$1048576,MATCH(DATE(H$2,1,1),Hybrid!$A$1:$LI$1),FALSE) -> 1.2901547 | I67: =VLOOKUP($E67,Hybrid!$1:$1048576,MATCH(DATE(I$2,1,1),Hybrid!$A$1:$LI$1),FALSE) -> 1.3064227 | J67: =VLOOKUP($E67,Hybrid!$1:$1048576,MATCH(DATE(J$2,1,1),Hybrid!$A$1:$LI$1),FALSE) -> 1.5187702 | K67: =VLOOKUP($E67,Hybrid!$1:$1048576,MATCH(DATE(K$2,1,1),Hybrid!$A$1:$LI$1),FALSE) -> 1.7576461 | L67: =VLOOKUP($E67,Hybrid!$1:$1048576,MATCH(DATE(L$2,1,1),Hybrid!$A$1:$LI$1),FALSE) -> 1.6938725 | M67: =VLOOKUP($E67,Hybrid!$1:$1048576,MATCH(DATE(M$2,1,1),Hybrid!$A$1:$LI$1),FALSE) -> 1.6912399 | ... AO67: =VLOOKUP($E67,Hybrid!$1:$1048576,MATCH(DATE(AO$2,1,1),Hybrid!$A$1:$LI$1),FALSE) -> 0.0088551847
D68: class F | E68: NEWAUTO_cf_cele_2 | F68: =VLOOKUP($E68,Hybrid!$1:$1048576,MATCH(DATE(F$2,1,1),Hybrid!$A$1:$LI$1),FALSE) -> 0.5373497 | G68: =VLOOKUP($E68,Hybrid!$1:$1048576,MATCH(DATE(G$2,1,1),Hybrid!$A$1:$LI$1),FALSE) -> 0.60467305 | H68: =VLOOKUP($E68,Hybrid!$1:$1048576,MATCH(DATE(H$2,1,1),Hybrid!$A$1:$LI$1),FALSE) -> 0.59257126 | I68: =VLOOKUP($E68,Hybrid!$1:$1048576,MATCH(DATE(I$2,1,1),Hybrid!$A$1:$LI$1),FALSE) -> 0.55936948 | J68: =VLOOKUP($E68,Hybrid!$1:$1048576,MATCH(DATE(J$2,1,1),Hybrid!$A$1:$LI$1),FALSE) -> 0.58804758 | K68: =VLOOKUP($E68,Hybrid!$1:$1048576,MATCH(DATE(K$2,1,1),Hybrid!$A$1:$LI$1),FALSE) -> 0.64118008 | L68: =VLOOKUP($E68,Hybrid!$1:$1048576,MATCH(DATE(L$2,1,1),Hybrid!$A$1:$LI$1),FALSE) -> 0.5878347 | M68: =VLOOKUP($E68,Hybrid!$1:$1048576,MATCH(DATE(M$2,1,1),Hybrid!$A$1:$LI$1),FALSE) -> 0.54837017 | ... AO68: =VLOOKUP($E68,Hybrid!$1:$1048576,MATCH(DATE(AO$2,1,1),Hybrid!$A$1:$LI$1),FALSE) -> -0.00033543224
D69: class G | E69: NEWAUTO_cg_cele_2 | F69: =VLOOKUP($E69,Hybrid!$1:$1048576,MATCH(DATE(F$2,1,1),Hybrid!$A$1:$LI$1),FALSE) -> 1.0093163 | G69: =VLOOKUP($E69,Hybrid!$1:$1048576,MATCH(DATE(G$2,1,1),Hybrid!$A$1:$LI$1),FALSE) -> 1.1163451 | H69: =VLOOKUP($E69,Hybrid!$1:$1048576,MATCH(DATE(H$2,1,1),Hybrid!$A$1:$LI$1),FALSE) -> 1.0596405 | I69: =VLOOKUP($E69,Hybrid!$1:$1048576,MATCH(DATE(I$2,1,1),Hybrid!$A$1:$LI$1),FALSE) -> 0.95527055 | J69: =VLOOKUP($E69,Hybrid!$1:$1048576,MATCH(DATE(J$2,1,1),Hybrid!$A$1:$LI$1),FALSE) -> 0.95300756 | K69: =VLOOKUP($E69,Hybrid!$1:$1048576,MATCH(DATE(K$2,1,1),Hybrid!$A$1:$LI$1),FALSE) -> 0.9913864 | L69: =VLOOKUP($E69,Hybrid!$1:$1048576,MATCH(DATE(L$2,1,1),Hybrid!$A$1:$LI$1),FALSE) -> 0.86743627 | M69: =VLOOKUP($E69,Hybrid!$1:$1048576,MATCH(DATE(M$2,1,1),Hybrid!$A$1:$LI$1),FALSE) -> 0.76610548 | ... AO69: =VLOOKUP($E69,Hybrid!$1:$1048576,MATCH(DATE(AO$2,1,1),Hybrid!$A$1:$LI$1),FALSE) -> -0.00025161303
C70: GAS | E70: NEWAUTO_cgas_2 | F70: =VLOOKUP($E70,Hybrid!$1:$1048576,MATCH(DATE(F$2,1,1),Hybrid!$A$1:$LI$1),FALSE) -> 0.156989 | G70: =VLOOKUP($E70,Hybrid!$1:$1048576,MATCH(DATE(G$2,1,1),Hybrid!$A$1:$LI$1),FALSE) -> 0.18183241 | H70: =VLOOKUP($E70,Hybrid!$1:$1048576,MATCH(DATE(H$2,1,1),Hybrid!$A$1:$LI$1),FALSE) -> 0.18851563 | I70: =VLOOKUP($E70,Hybrid!$1:$1048576,MATCH(DATE(I$2,1,1),Hybrid!$A$1:$LI$1),FALSE) -> 0.18791953 | J70: =VLOOKUP($E70,Hybrid!$1:$1048576,MATCH(DATE(J$2,1,1),Hybrid!$A$1:$LI$1),FALSE) -> 0.20379916 | K70: =VLOOKUP($E70,Hybrid!$1:$1048576,MATCH(DATE(K$2,1,1),Hybrid!$A$1:$LI$1),FALSE) -> 0.23539542 | L70: =VLOOKUP($E70,Hybrid!$1:$1048576,MATCH(DATE(L$2,1,1),Hybrid!$A$1:$LI$1),FALSE) -> 0.23157458 | M70: =VLOOKUP($E70,Hybrid!$1:$1048576,MATCH(DATE(M$2,1,1),Hybrid!$A$1:$LI$1),FALSE) -> 0.23345721 | ... AO70: =VLOOKUP($E70,Hybrid!$1:$1048576,MATCH(DATE(AO$2,1,1),Hybrid!$A$1:$LI$1),FALSE) -> 0.24827895
D71: class A | E71: NEWAUTO_ca_cgas_2 | F71: =VLOOKUP($E71,Hybrid!$1:$1048576,MATCH(DATE(F$2,1,1),Hybrid!$A$1:$LI$1),FALSE) -> 0.044411988 | G71: =VLOOKUP($E71,Hybrid!$1:$1048576,MATCH(DATE(G$2,1,1),Hybrid!$A$1:$LI$1),FALSE) -> 0.05176636 | H71: =VLOOKUP($E71,Hybrid!$1:$1048576,MATCH(DATE(H$2,1,1),Hybrid!$A$1:$LI$1),FALSE) -> 0.054292615 | I71: =VLOOKUP($E71,Hybrid!$1:$1048576,MATCH(DATE(I$2,1,1),Hybrid!$A$1:$LI$1),FALSE) -> 0.055195817 | J71: =VLOOKUP($E71,Hybrid!$1:$1048576,MATCH(DATE(J$2,1,1),Hybrid!$A$1:$LI$1),FALSE) -> 0.061155588 | K71: =VLOOKUP($E71,Hybrid!$1:$1048576,MATCH(DATE(K$2,1,1),Hybrid!$A$1:$LI$1),FALSE) -> 0.071577291 | L71: =VLOOKUP($E71,Hybrid!$1:$1048576,MATCH(DATE(L$2,1,1),Hybrid!$A$1:$LI$1),FALSE) -> 0.071197382 | M71: =VLOOKUP($E71,Hybrid!$1:$1048576,MATCH(DATE(M$2,1,1),Hybrid!$A$1:$LI$1),FALSE) -> 0.072894246 | ... AO71: =VLOOKUP($E71,Hybrid!$1:$1048576,MATCH(DATE(AO$2,1,1),Hybrid!$A$1:$LI$1),FALSE) -> 0.17824736
D72: class B | E72: NEWAUTO_cb_cgas_2 | F72: =VLOOKUP($E72,Hybrid!$1:$1048576,MATCH(DATE(F$2,1,1),Hybrid!$A$1:$LI$1),FALSE) -> 0.042637772 | G72: =VLOOKUP($E72,Hybrid!$1:$1048576,MATCH(DATE(G$2,1,1),Hybrid!$A$1:$LI$1),FALSE) -> 0.049640534 | H72: =VLOOKUP($E72,Hybrid!$1:$1048576,MATCH(DATE(H$2,1,1),Hybrid!$A$1:$LI$1),FALSE) -> 0.05194175 | I72: =VLOOKUP($E72,Hybrid!$1:$1048576,MATCH(DATE(I$2,1,1),Hybrid!$A$1:$LI$1),FALSE) -> 0.052524862 | J72: =VLOOKUP($E72,Hybrid!$1:$1048576,MATCH(DATE(J$2,1,1),Hybrid!$A$1:$LI$1),FALSE) -> 0.057822668 | K72: =VLOOKUP($E72,Hybrid!$1:$1048576,MATCH(DATE(K$2,1,1),Hybrid!$A$1:$LI$1),FALSE) -> 0.067487206 | L72: =VLOOKUP($E72,Hybrid!$1:$1048576,MATCH(DATE(L$2,1,1),Hybrid!$A$1:$LI$1),FALSE) -> 0.066991295 | M72: =VLOOKUP($E72,Hybrid!$1:$1048576,MATCH(DATE(M$2,1,1),Hybrid!$A$1:$LI$1),FALSE) -> 0.068282376 | ... AO72: =VLOOKUP($E72,Hybrid!$1:$1048576,MATCH(DATE(AO$2,1,1),Hybrid!$A$1:$LI$1),FALSE) -> 0.05560092
D73: class C | E73: NEWAUTO_cc_cgas_2 | F73: =VLOOKUP($E73,Hybrid!$1:$1048576,MATCH(DATE(F$2,1,1),Hybrid!$A$1:$LI$1),FALSE) -> 0.029513467 | G73: =VLOOKUP($E73,Hybrid!$1:$1048576,MATCH(DATE(G$2,1,1),Hybrid!$A$1:$LI$1),FALSE) -> 0.034321016 | H73: =VLOOKUP($E73,Hybrid!$1:$1048576,MATCH(DATE(H$2,1,1),Hybrid!$A$1:$LI$1),FALSE) -> 0.035829144 | I73: =VLOOKUP($E73,Hybrid!$1:$1048576,MATCH(DATE(I$2,1,1),Hybrid!$A$1:$LI$1),FALSE) -> 0.036040783 | J73: =VLOOKUP($E73,Hybrid!$1:$1048576,MATCH(DATE(J$2,1,1),Hybrid!$A$1:$LI$1),FALSE) -> 0.039424162 | K73: =VLOOKUP($E73,Hybrid!$1:$1048576,MATCH(DATE(K$2,1,1),Hybrid!$A$1:$LI$1),FALSE) -> 0.045885719 | L73: =VLOOKUP($E73,Hybrid!$1:$1048576,MATCH(DATE(L$2,1,1),Hybrid!$A$1:$LI$1),FALSE) -> 0.045456176 | M73: =VLOOKUP($E73,Hybrid!$1:$1048576,MATCH(DATE(M$2,1,1),Hybrid!$A$1:$LI$1),FALSE) -> 0.046128591 | ... AO73: =VLOOKUP($E73,Hybrid!$1:$1048576,MATCH(DATE(AO$2,1,1),Hybrid!$A$1:$LI$1),FALSE) -> 0.014219042
D74: class D | E74: NEWAUTO_cd_cgas_2 | F74: =VLOOKUP($E74,Hybrid!$1:$1048576,MATCH(DATE(F$2,1,1),Hybrid!$A$1:$LI$1),FALSE) -> 0.016358695 | G74: =VLOOKUP($E74,Hybrid!$1:$1048576,MATCH(DATE(G$2,1,1),Hybrid!$A$1:$LI$1),FALSE) -> 0.018910387 | H74: =VLOOKUP($E74,Hybrid!$1:$1048576,MATCH(DATE(H$2,1,1),Hybrid!$A$1:$LI$1),FALSE) -> 0.019520505 | I74: =VLOOKUP($E74,Hybrid!$1:$1048576,MATCH(DATE(I$2,1,1),Hybrid!$A$1:$LI$1),FALSE) -> 0.019267849 | J74: =VLOOKUP($E74,Hybrid!$1:$1048576,MATCH(DATE(J$2,1,1),Hybrid!$A$1:$LI$1),FALSE) -> 0.020632487 | K74: =VLOOKUP($E74,Hybrid!$1:$1048576,MATCH(DATE(K$2,1,1),Hybrid!$A$1:$LI$1),FALSE) -> 0.023638786 | L74: =VLOOKUP($E74,Hybrid!$1:$1048576,MATCH(DATE(L$2,1,1),Hybrid!$A$1:$LI$1),FALSE) -> 0.023076172 | M74: =VLOOKUP($E74,Hybrid!$1:$1048576,MATCH(DATE(M$2,1,1),Hybrid!$A$1:$LI$1),FALSE) -> 0.022951056 | ... AO74: =VLOOKUP($E74,Hybrid!$1:$1048576,MATCH(DATE(AO$2,1,1),Hybrid!$A$1:$LI$1),FALSE) -> 0.00020528415
D75: class E | E75: NEWAUTO_ce_cgas_2 | F75: =VLOOKUP($E75,Hybrid!$1:$1048576,MATCH(DATE(F$2,1,1),Hybrid!$A$1:$LI$1),FALSE) -> 0.010063201 | G75: =VLOOKUP($E75,Hybrid!$1:$1048576,MATCH(DATE(G$2,1,1),Hybrid!$A$1:$LI$1),FALSE) -> 0.011571123 | H75: =VLOOKUP($E75,Hybrid!$1:$1048576,MATCH(DATE(H$2,1,1),Hybrid!$A$1:$LI$1),FALSE) -> 0.011825441 | I75: =VLOOKUP($E75,Hybrid!$1:$1048576,MATCH(DATE(I$2,1,1),Hybrid!$A$1:$LI$1),FALSE) -> 0.011470878 | J75: =VLOOKUP($E75,Hybrid!$1:$1048576,MATCH(DATE(J$2,1,1),Hybrid!$A$1:$LI$1),FALSE) -> 0.012036624 | K75: =VLOOKUP($E75,Hybrid!$1:$1048576,MATCH(DATE(K$2,1,1),Hybrid!$A$1:$LI$1),FALSE) -> 0.013591429 | L75: =VLOOKUP($E75,Hybrid!$1:$1048576,MATCH(DATE(L$2,1,1),Hybrid!$A$1:$LI$1),FALSE) -> 0.013093113 | M75: =VLOOKUP($E75,Hybrid!$1:$1048576,MATCH(DATE(M$2,1,1),Hybrid!$A$1:$LI$1),FALSE) -> 0.012785743 | ... AO75: =VLOOKUP($E75,Hybrid!$1:$1048576,MATCH(DATE(AO$2,1,1),Hybrid!$A$1:$LI$1),FALSE) -> 6.2866877e-06
D76: class F | E76: NEWAUTO_cf_cgas_2 | F76: =VLOOKUP($E76,Hybrid!$1:$1048576,MATCH(DATE(F$2,1,1),Hybrid!$A$1:$LI$1),FALSE) -> 0.0048668311 | G76: =VLOOKUP($E76,Hybrid!$1:$1048576,MATCH(DATE(G$2,1,1),Hybrid!$A$1:$LI$1),FALSE) -> 0.0054892368 | H76: =VLOOKUP($E76,Hybrid!$1:$1048576,MATCH(DATE(H$2,1,1),Hybrid!$A$1:$LI$1),FALSE) -> 0.0054137077 | I76: =VLOOKUP($E76,Hybrid!$1:$1048576,MATCH(DATE(I$2,1,1),Hybrid!$A$1:$LI$1),FALSE) -> 0.0049601556 | J76: =VLOOKUP($E76,Hybrid!$1:$1048576,MATCH(DATE(J$2,1,1),Hybrid!$A$1:$LI$1),FALSE) -> 0.0048734343 | K76: =VLOOKUP($E76,Hybrid!$1:$1048576,MATCH(DATE(K$2,1,1),Hybrid!$A$1:$LI$1),FALSE) -> 0.005212136 | L76: =VLOOKUP($E76,Hybrid!$1:$1048576,MATCH(DATE(L$2,1,1),Hybrid!$A$1:$LI$1),FALSE) -> 0.0047686599 | M76: =VLOOKUP($E76,Hybrid!$1:$1048576,MATCH(DATE(M$2,1,1),Hybrid!$A$1:$LI$1),FALSE) -> 0.0043650404 | ... AO76: =VLOOKUP($E76,Hybrid!$1:$1048576,MATCH(DATE(AO$2,1,1),Hybrid!$A$1:$LI$1),FALSE) -> 3.5315562e-08
D77: class G | E77: NEWAUTO_cg_cgas_2 | F77: =VLOOKUP($E77,Hybrid!$1:$1048576,MATCH(DATE(F$2,1,1),Hybrid!$A$1:$LI$1),FALSE) -> 0.0091370421 | G77: =VLOOKUP($E77,Hybrid!$1:$1048576,MATCH(DATE(G$2,1,1),Hybrid!$A$1:$LI$1),FALSE) -> 0.010133756 | H77: =VLOOKUP($E77,Hybrid!$1:$1048576,MATCH(DATE(H$2,1,1),Hybrid!$A$1:$LI$1),FALSE) -> 0.0096924715 | I77: =VLOOKUP($E77,Hybrid!$1:$1048576,MATCH(DATE(I$2,1,1),Hybrid!$A$1:$LI$1),FALSE) -> 0.008459186 | J77: =VLOOKUP($E77,Hybrid!$1:$1048576,MATCH(DATE(J$2,1,1),Hybrid!$A$1:$LI$1),FALSE) -> 0.0078541991 | K77: =VLOOKUP($E77,Hybrid!$1:$1048576,MATCH(DATE(K$2,1,1),Hybrid!$A$1:$LI$1),FALSE) -> 0.0080028533 | L77: =VLOOKUP($E77,Hybrid!$1:$1048576,MATCH(DATE(L$2,1,1),Hybrid!$A$1:$LI$1),FALSE) -> 0.0069917842 | M77: =VLOOKUP($E77,Hybrid!$1:$1048576,MATCH(DATE(M$2,1,1),Hybrid!$A$1:$LI$1),FALSE) -> 0.0060501523 | ... AO77: =VLOOKUP($E77,Hybrid!$1:$1048576,MATCH(DATE(AO$2,1,1),Hybrid!$A$1:$LI$1),FALSE) -> 2.2708157e-08
C78: TOTAL SALES BASELINE | E78: NEWAUTO_0 | F78: =VLOOKUP($E78,Hybrid!$1:$1048576,MATCH(DATE(F$2,1,1),Hybrid!$A$1:$LI$1),FALSE) -> 1886.229 | G78: =VLOOKUP($E78,Hybrid!$1:$1048576,MATCH(DATE(G$2,1,1),Hybrid!$A$1:$LI$1),FALSE) -> 2184.6168 | H78: =VLOOKUP($E78,Hybrid!$1:$1048576,MATCH(DATE(H$2,1,1),Hybrid!$A$1:$LI$1),FALSE) -> 2264.6053 | I78: =VLOOKUP($E78,Hybrid!$1:$1048576,MATCH(DATE(I$2,1,1),Hybrid!$A$1:$LI$1),FALSE) -> 2258.7517 | J78: =VLOOKUP($E78,Hybrid!$1:$1048576,MATCH(DATE(J$2,1,1),Hybrid!$A$1:$LI$1),FALSE) -> 2453.578 | K78: =VLOOKUP($E78,Hybrid!$1:$1048576,MATCH(DATE(K$2,1,1),Hybrid!$A$1:$LI$1),FALSE) -> 2835.035 | L78: =VLOOKUP($E78,Hybrid!$1:$1048576,MATCH(DATE(L$2,1,1),Hybrid!$A$1:$LI$1),FALSE) -> 2789.0324 | M78: =VLOOKUP($E78,Hybrid!$1:$1048576,MATCH(DATE(M$2,1,1),Hybrid!$A$1:$LI$1),FALSE) -> 2834.3818 | ... AO78: =VLOOKUP($E78,Hybrid!$1:$1048576,MATCH(DATE(AO$2,1,1),Hybrid!$A$1:$LI$1),FALSE) -> 3789.5313
C79: OIL | E79: NEWAUTO_cfut_0 | F79: =VLOOKUP($E79,Hybrid!$1:$1048576,MATCH(DATE(F$2,1,1),Hybrid!$A$1:$LI$1),FALSE) -> 1868.672 | G79: =VLOOKUP($E79,Hybrid!$1:$1048576,MATCH(DATE(G$2,1,1),Hybrid!$A$1:$LI$1),FALSE) -> 2164.3883 | H79: =VLOOKUP($E79,Hybrid!$1:$1048576,MATCH(DATE(H$2,1,1),Hybrid!$A$1:$LI$1),FALSE) -> 2243.94 | I79: =VLOOKUP($E79,Hybrid!$1:$1048576,MATCH(DATE(I$2,1,1),Hybrid!$A$1:$LI$1),FALSE) -> 2236.8445 | J79: =VLOOKUP($E79,Hybrid!$1:$1048576,MATCH(DATE(J$2,1,1),Hybrid!$A$1:$LI$1),FALSE) -> 2425.863 | K79: =VLOOKUP($E79,Hybrid!$1:$1048576,MATCH(DATE(K$2,1,1),Hybrid!$A$1:$LI$1),FALSE) -> 2801.9597 | L79: =VLOOKUP($E79,Hybrid!$1:$1048576,MATCH(DATE(L$2,1,1),Hybrid!$A$1:$LI$1),FALSE) -> 2756.4794 | M79: =VLOOKUP($E79,Hybrid!$1:$1048576,MATCH(DATE(M$2,1,1),Hybrid!$A$1:$LI$1),FALSE) -> 2800.6267 | ... AO79: =VLOOKUP($E79,Hybrid!$1:$1048576,MATCH(DATE(AO$2,1,1),Hybrid!$A$1:$LI$1),FALSE) -> 3671.3739
D80: class A | E80: NEWAUTO_ca_cfut_0 | F80: =VLOOKUP($E80,Hybrid!$1:$1048576,MATCH(DATE(F$2,1,1),Hybrid!$A$1:$LI$1),FALSE) -> 528.64494 | G80: =VLOOKUP($E80,Hybrid!$1:$1048576,MATCH(DATE(G$2,1,1),Hybrid!$A$1:$LI$1),FALSE) -> 616.18553 | H80: =VLOOKUP($E80,Hybrid!$1:$1048576,MATCH(DATE(H$2,1,1),Hybrid!$A$1:$LI$1),FALSE) -> 646.25606 | I80: =VLOOKUP($E80,Hybrid!$1:$1048576,MATCH(DATE(I$2,1,1),Hybrid!$A$1:$LI$1),FALSE) -> 657.00705 | J80: =VLOOKUP($E80,Hybrid!$1:$1048576,MATCH(DATE(J$2,1,1),Hybrid!$A$1:$LI$1),FALSE) -> 727.94743 | K80: =VLOOKUP($E80,Hybrid!$1:$1048576,MATCH(DATE(K$2,1,1),Hybrid!$A$1:$LI$1),FALSE) -> 851.99909 | L80: =VLOOKUP($E80,Hybrid!$1:$1048576,MATCH(DATE(L$2,1,1),Hybrid!$A$1:$LI$1),FALSE) -> 847.47695 | M80: =VLOOKUP($E80,Hybrid!$1:$1048576,MATCH(DATE(M$2,1,1),Hybrid!$A$1:$LI$1),FALSE) -> 873.48155 | ... AO80: =VLOOKUP($E80,Hybrid!$1:$1048576,MATCH(DATE(AO$2,1,1),Hybrid!$A$1:$LI$1),FALSE) -> 1967.8644
D81: class B | E81: NEWAUTO_cb_cfut_0 | F81: =VLOOKUP($E81,Hybrid!$1:$1048576,MATCH(DATE(F$2,1,1),Hybrid!$A$1:$LI$1),FALSE) -> 507.52609 | G81: =VLOOKUP($E81,Hybrid!$1:$1048576,MATCH(DATE(G$2,1,1),Hybrid!$A$1:$LI$1),FALSE) -> 590.88139 | H81: =VLOOKUP($E81,Hybrid!$1:$1048576,MATCH(DATE(H$2,1,1),Hybrid!$A$1:$LI$1),FALSE) -> 618.27323 | I81: =VLOOKUP($E81,Hybrid!$1:$1048576,MATCH(DATE(I$2,1,1),Hybrid!$A$1:$LI$1),FALSE) -> 625.21413 | J81: =VLOOKUP($E81,Hybrid!$1:$1048576,MATCH(DATE(J$2,1,1),Hybrid!$A$1:$LI$1),FALSE) -> 688.275 | K81: =VLOOKUP($E81,Hybrid!$1:$1048576,MATCH(DATE(K$2,1,1),Hybrid!$A$1:$LI$1),FALSE) -> 803.31397 | L81: =VLOOKUP($E81,Hybrid!$1:$1048576,MATCH(DATE(L$2,1,1),Hybrid!$A$1:$LI$1),FALSE) -> 797.41103 | M81: =VLOOKUP($E81,Hybrid!$1:$1048576,MATCH(DATE(M$2,1,1),Hybrid!$A$1:$LI$1),FALSE) -> 818.60958 | ... AO81: =VLOOKUP($E81,Hybrid!$1:$1048576,MATCH(DATE(AO$2,1,1),Hybrid!$A$1:$LI$1),FALSE) -> 1166.6646
D82: class C | E82: NEWAUTO_cc_cfut_0 | F82: =VLOOKUP($E82,Hybrid!$1:$1048576,MATCH(DATE(F$2,1,1),Hybrid!$A$1:$LI$1),FALSE) -> 351.30482 | G82: =VLOOKUP($E82,Hybrid!$1:$1048576,MATCH(DATE(G$2,1,1),Hybrid!$A$1:$LI$1),FALSE) -> 408.53004 | H82: =VLOOKUP($E82,Hybrid!$1:$1048576,MATCH(DATE(H$2,1,1),Hybrid!$A$1:$LI$1),FALSE) -> 426.4816 | I82: =VLOOKUP($E82,Hybrid!$1:$1048576,MATCH(DATE(I$2,1,1),Hybrid!$A$1:$LI$1),FALSE) -> 429.00078 | J82: =VLOOKUP($E82,Hybrid!$1:$1048576,MATCH(DATE(J$2,1,1),Hybrid!$A$1:$LI$1),FALSE) -> 469.27384 | K82: =VLOOKUP($E82,Hybrid!$1:$1048576,MATCH(DATE(K$2,1,1),Hybrid!$A$1:$LI$1),FALSE) -> 546.18706 | L82: =VLOOKUP($E82,Hybrid!$1:$1048576,MATCH(DATE(L$2,1,1),Hybrid!$A$1:$LI$1),FALSE) -> 541.07413 | M82: =VLOOKUP($E82,Hybrid!$1:$1048576,MATCH(DATE(M$2,1,1),Hybrid!$A$1:$LI$1),FALSE) -> 553.27757 | ... AO82: =VLOOKUP($E82,Hybrid!$1:$1048576,MATCH(DATE(AO$2,1,1),Hybrid!$A$1:$LI$1),FALSE) -> 502.32988
D83: class D | E83: NEWAUTO_cd_cfut_0 | F83: =VLOOKUP($E83,Hybrid!$1:$1048576,MATCH(DATE(F$2,1,1),Hybrid!$A$1:$LI$1),FALSE) -> 194.72089 | G83: =VLOOKUP($E83,Hybrid!$1:$1048576,MATCH(DATE(G$2,1,1),Hybrid!$A$1:$LI$1),FALSE) -> 225.09419 | H83: =VLOOKUP($E83,Hybrid!$1:$1048576,MATCH(DATE(H$2,1,1),Hybrid!$A$1:$LI$1),FALSE) -> 232.35655 | I83: =VLOOKUP($E83,Hybrid!$1:$1048576,MATCH(DATE(I$2,1,1),Hybrid!$A$1:$LI$1),FALSE) -> 229.34914 | J83: =VLOOKUP($E83,Hybrid!$1:$1048576,MATCH(DATE(J$2,1,1),Hybrid!$A$1:$LI$1),FALSE) -> 245.5927 | K83: =VLOOKUP($E83,Hybrid!$1:$1048576,MATCH(DATE(K$2,1,1),Hybrid!$A$1:$LI$1),FALSE) -> 281.37729 | L83: =VLOOKUP($E83,Hybrid!$1:$1048576,MATCH(DATE(L$2,1,1),Hybrid!$A$1:$LI$1),FALSE) -> 274.68038 | M83: =VLOOKUP($E83,Hybrid!$1:$1048576,MATCH(DATE(M$2,1,1),Hybrid!$A$1:$LI$1),FALSE) -> 275.64148 | ... AO83: =VLOOKUP($E83,Hybrid!$1:$1048576,MATCH(DATE(AO$2,1,1),Hybrid!$A$1:$LI$1),FALSE) -> 31.678052
D84: class E | E84: NEWAUTO_ce_cfut_0 | F84: =VLOOKUP($E84,Hybrid!$1:$1048576,MATCH(DATE(F$2,1,1),Hybrid!$A$1:$LI$1),FALSE) -> 119.78434 | G84: =VLOOKUP($E84,Hybrid!$1:$1048576,MATCH(DATE(G$2,1,1),Hybrid!$A$1:$LI$1),FALSE) -> 137.73343 | H84: =VLOOKUP($E84,Hybrid!$1:$1048576,MATCH(DATE(H$2,1,1),Hybrid!$A$1:$LI$1),FALSE) -> 140.76063 | I84: =VLOOKUP($E84,Hybrid!$1:$1048576,MATCH(DATE(I$2,1,1),Hybrid!$A$1:$LI$1),FALSE) -> 136.54019 | J84: =VLOOKUP($E84,Hybrid!$1:$1048576,MATCH(DATE(J$2,1,1),Hybrid!$A$1:$LI$1),FALSE) -> 143.27439 | K84: =VLOOKUP($E84,Hybrid!$1:$1048576,MATCH(DATE(K$2,1,1),Hybrid!$A$1:$LI$1),FALSE) -> 161.78155 | L84: =VLOOKUP($E84,Hybrid!$1:$1048576,MATCH(DATE(L$2,1,1),Hybrid!$A$1:$LI$1),FALSE) -> 155.84999 | M84: =VLOOKUP($E84,Hybrid!$1:$1048576,MATCH(DATE(M$2,1,1),Hybrid!$A$1:$LI$1),FALSE) -> 153.74472 | ... AO84: =VLOOKUP($E84,Hybrid!$1:$1048576,MATCH(DATE(AO$2,1,1),Hybrid!$A$1:$LI$1),FALSE) -> 2.8335042
D85: class F | E85: NEWAUTO_cf_cfut_0 | F85: =VLOOKUP($E85,Hybrid!$1:$1048576,MATCH(DATE(F$2,1,1),Hybrid!$A$1:$LI$1),FALSE) -> 57.930882 | G85: =VLOOKUP($E85,Hybrid!$1:$1048576,MATCH(DATE(G$2,1,1),Hybrid!$A$1:$LI$1),FALSE) -> 65.339505 | H85: =VLOOKUP($E85,Hybrid!$1:$1048576,MATCH(DATE(H$2,1,1),Hybrid!$A$1:$LI$1),FALSE) -> 64.440466 | I85: =VLOOKUP($E85,Hybrid!$1:$1048576,MATCH(DATE(I$2,1,1),Hybrid!$A$1:$LI$1),FALSE) -> 59.041743 | J85: =VLOOKUP($E85,Hybrid!$1:$1048576,MATCH(DATE(J$2,1,1),Hybrid!$A$1:$LI$1),FALSE) -> 58.009481 | K85: =VLOOKUP($E85,Hybrid!$1:$1048576,MATCH(DATE(K$2,1,1),Hybrid!$A$1:$LI$1),FALSE) -> 62.041117 | L85: =VLOOKUP($E85,Hybrid!$1:$1048576,MATCH(DATE(L$2,1,1),Hybrid!$A$1:$LI$1),FALSE) -> 56.762331 | M85: =VLOOKUP($E85,Hybrid!$1:$1048576,MATCH(DATE(M$2,1,1),Hybrid!$A$1:$LI$1),FALSE) -> 52.67143 | ... AO85: =VLOOKUP($E85,Hybrid!$1:$1048576,MATCH(DATE(AO$2,1,1),Hybrid!$A$1:$LI$1),FALSE) -> 0.0031945159
D86: class G | E86: NEWAUTO_cg_cfut_0 | F86: =VLOOKUP($E86,Hybrid!$1:$1048576,MATCH(DATE(F$2,1,1),Hybrid!$A$1:$LI$1),FALSE) -> 108.76007 | G86: =VLOOKUP($E86,Hybrid!$1:$1048576,MATCH(DATE(G$2,1,1),Hybrid!$A$1:$LI$1),FALSE) -> 120.62416 | H86: =VLOOKUP($E86,Hybrid!$1:$1048576,MATCH(DATE(H$2,1,1),Hybrid!$A$1:$LI$1),FALSE) -> 115.37146 | I86: =VLOOKUP($E86,Hybrid!$1:$1048576,MATCH(DATE(I$2,1,1),Hybrid!$A$1:$LI$1),FALSE) -> 100.69141 | J86: =VLOOKUP($E86,Hybrid!$1:$1048576,MATCH(DATE(J$2,1,1),Hybrid!$A$1:$LI$1),FALSE) -> 93.490133 | K86: =VLOOKUP($E86,Hybrid!$1:$1048576,MATCH(DATE(K$2,1,1),Hybrid!$A$1:$LI$1),FALSE) -> 95.259594 | L86: =VLOOKUP($E86,Hybrid!$1:$1048576,MATCH(DATE(L$2,1,1),Hybrid!$A$1:$LI$1),FALSE) -> 83.224633 | M86: =VLOOKUP($E86,Hybrid!$1:$1048576,MATCH(DATE(M$2,1,1),Hybrid!$A$1:$LI$1),FALSE) -> 73.20041 | ... AO86: =VLOOKUP($E86,Hybrid!$1:$1048576,MATCH(DATE(AO$2,1,1),Hybrid!$A$1:$LI$1),FALSE) -> 0.00018137866
C87: ELEC | E87: NEWAUTO_cele_0 | F87: =VLOOKUP($E87,Hybrid!$1:$1048576,MATCH(DATE(F$2,1,1),Hybrid!$A$1:$LI$1),FALSE) -> 17.399981 | G87: =VLOOKUP($E87,Hybrid!$1:$1048576,MATCH(DATE(G$2,1,1),Hybrid!$A$1:$LI$1),FALSE) -> 20.046727 | H87: =VLOOKUP($E87,Hybrid!$1:$1048576,MATCH(DATE(H$2,1,1),Hybrid!$A$1:$LI$1),FALSE) -> 20.476767 | I87: =VLOOKUP($E87,Hybrid!$1:$1048576,MATCH(DATE(I$2,1,1),Hybrid!$A$1:$LI$1),FALSE) -> 21.719299 | J87: =VLOOKUP($E87,Hybrid!$1:$1048576,MATCH(DATE(J$2,1,1),Hybrid!$A$1:$LI$1),FALSE) -> 27.511221 | K87: =VLOOKUP($E87,Hybrid!$1:$1048576,MATCH(DATE(K$2,1,1),Hybrid!$A$1:$LI$1),FALSE) -> 32.839898 | L87: =VLOOKUP($E87,Hybrid!$1:$1048576,MATCH(DATE(L$2,1,1),Hybrid!$A$1:$LI$1),FALSE) -> 32.321355 | M87: =VLOOKUP($E87,Hybrid!$1:$1048576,MATCH(DATE(M$2,1,1),Hybrid!$A$1:$LI$1),FALSE) -> 33.519794 | ... AO87: =VLOOKUP($E87,Hybrid!$1:$1048576,MATCH(DATE(AO$2,1,1),Hybrid!$A$1:$LI$1),FALSE) -> 117.84902
D88: class A | E88: NEWAUTO_ca_cele_0 | F88: =VLOOKUP($E88,Hybrid!$1:$1048576,MATCH(DATE(F$2,1,1),Hybrid!$A$1:$LI$1),FALSE) -> 4.9248306 | G88: =VLOOKUP($E88,Hybrid!$1:$1048576,MATCH(DATE(G$2,1,1),Hybrid!$A$1:$LI$1),FALSE) -> 5.7080893 | H88: =VLOOKUP($E88,Hybrid!$1:$1048576,MATCH(DATE(H$2,1,1),Hybrid!$A$1:$LI$1),FALSE) -> 5.8937466 | I88: =VLOOKUP($E88,Hybrid!$1:$1048576,MATCH(DATE(I$2,1,1),Hybrid!$A$1:$LI$1),FALSE) -> 6.4015487 | J88: =VLOOKUP($E88,Hybrid!$1:$1048576,MATCH(DATE(J$2,1,1),Hybrid!$A$1:$LI$1),FALSE) -> 8.3657204 | K88: =VLOOKUP($E88,Hybrid!$1:$1048576,MATCH(DATE(K$2,1,1),Hybrid!$A$1:$LI$1),FALSE) -> 10.12112 | L88: =VLOOKUP($E88,Hybrid!$1:$1048576,MATCH(DATE(L$2,1,1),Hybrid!$A$1:$LI$1),FALSE) -> 10.0662 | M88: =VLOOKUP($E88,Hybrid!$1:$1048576,MATCH(DATE(M$2,1,1),Hybrid!$A$1:$LI$1),FALSE) -> 10.585047 | ... AO88: =VLOOKUP($E88,Hybrid!$1:$1048576,MATCH(DATE(AO$2,1,1),Hybrid!$A$1:$LI$1),FALSE) -> 63.915714
D89: class B | E89: NEWAUTO_cb_cele_0 | F89: =VLOOKUP($E89,Hybrid!$1:$1048576,MATCH(DATE(F$2,1,1),Hybrid!$A$1:$LI$1),FALSE) -> 4.7310662 | G89: =VLOOKUP($E89,Hybrid!$1:$1048576,MATCH(DATE(G$2,1,1),Hybrid!$A$1:$LI$1),FALSE) -> 5.4740577 | H89: =VLOOKUP($E89,Hybrid!$1:$1048576,MATCH(DATE(H$2,1,1),Hybrid!$A$1:$LI$1),FALSE) -> 5.6298808 | I89: =VLOOKUP($E89,Hybrid!$1:$1048576,MATCH(DATE(I$2,1,1),Hybrid!$A$1:$LI$1),FALSE) -> 6.1076074 | J89: =VLOOKUP($E89,Hybrid!$1:$1048576,MATCH(DATE(J$2,1,1),Hybrid!$A$1:$LI$1),FALSE) -> 7.9993744 | K89: =VLOOKUP($E89,Hybrid!$1:$1048576,MATCH(DATE(K$2,1,1),Hybrid!$A$1:$LI$1),FALSE) -> 9.6637987 | L89: =VLOOKUP($E89,Hybrid!$1:$1048576,MATCH(DATE(L$2,1,1),Hybrid!$A$1:$LI$1),FALSE) -> 9.5835001 | M89: =VLOOKUP($E89,Hybrid!$1:$1048576,MATCH(DATE(M$2,1,1),Hybrid!$A$1:$LI$1),FALSE) -> 10.041557 | ... AO89: =VLOOKUP($E89,Hybrid!$1:$1048576,MATCH(DATE(AO$2,1,1),Hybrid!$A$1:$LI$1),FALSE) -> 37.204053
D90: class C | E90: NEWAUTO_cc_cele_0 | F90: =VLOOKUP($E90,Hybrid!$1:$1048576,MATCH(DATE(F$2,1,1),Hybrid!$A$1:$LI$1),FALSE) -> 3.2767218 | G90: =VLOOKUP($E90,Hybrid!$1:$1048576,MATCH(DATE(G$2,1,1),Hybrid!$A$1:$LI$1),FALSE) -> 3.7849027 | H90: =VLOOKUP($E90,Hybrid!$1:$1048576,MATCH(DATE(H$2,1,1),Hybrid!$A$1:$LI$1),FALSE) -> 3.8776671 | I90: =VLOOKUP($E90,Hybrid!$1:$1048576,MATCH(DATE(I$2,1,1),Hybrid!$A$1:$LI$1),FALSE) -> 4.2004619 | J90: =VLOOKUP($E90,Hybrid!$1:$1048576,MATCH(DATE(J$2,1,1),Hybrid!$A$1:$LI$1),FALSE) -> 5.5098365 | K90: =VLOOKUP($E90,Hybrid!$1:$1048576,MATCH(DATE(K$2,1,1),Hybrid!$A$1:$LI$1),FALSE) -> 6.6454407 | L90: =VLOOKUP($E90,Hybrid!$1:$1048576,MATCH(DATE(L$2,1,1),Hybrid!$A$1:$LI$1),FALSE) -> 6.5712009 | M90: =VLOOKUP($E90,Hybrid!$1:$1048576,MATCH(DATE(M$2,1,1),Hybrid!$A$1:$LI$1),FALSE) -> 6.8602479 | ... AO90: =VLOOKUP($E90,Hybrid!$1:$1048576,MATCH(DATE(AO$2,1,1),Hybrid!$A$1:$LI$1),FALSE) -> 15.605405
D91: class D | E91: NEWAUTO_cd_cele_0 | F91: =VLOOKUP($E91,Hybrid!$1:$1048576,MATCH(DATE(F$2,1,1),Hybrid!$A$1:$LI$1),FALSE) -> 1.8078176 | G91: =VLOOKUP($E91,Hybrid!$1:$1048576,MATCH(DATE(G$2,1,1),Hybrid!$A$1:$LI$1),FALSE) -> 2.0835918 | H91: =VLOOKUP($E91,Hybrid!$1:$1048576,MATCH(DATE(H$2,1,1),Hybrid!$A$1:$LI$1),FALSE) -> 2.1331063 | I91: =VLOOKUP($E91,Hybrid!$1:$1048576,MATCH(DATE(I$2,1,1),Hybrid!$A$1:$LI$1),FALSE) -> 2.1886185 | J91: =VLOOKUP($E91,Hybrid!$1:$1048576,MATCH(DATE(J$2,1,1),Hybrid!$A$1:$LI$1),FALSE) -> 2.5764642 | K91: =VLOOKUP($E91,Hybrid!$1:$1048576,MATCH(DATE(K$2,1,1),Hybrid!$A$1:$LI$1),FALSE) -> 3.0193267 | L91: =VLOOKUP($E91,Hybrid!$1:$1048576,MATCH(DATE(L$2,1,1),Hybrid!$A$1:$LI$1),FALSE) -> 2.9513106 | M91: =VLOOKUP($E91,Hybrid!$1:$1048576,MATCH(DATE(M$2,1,1),Hybrid!$A$1:$LI$1),FALSE) -> 3.0065479 | ... AO91: =VLOOKUP($E91,Hybrid!$1:$1048576,MATCH(DATE(AO$2,1,1),Hybrid!$A$1:$LI$1),FALSE) -> 1.0267072
D92: class E | E92: NEWAUTO_ce_cele_0 | F92: =VLOOKUP($E92,Hybrid!$1:$1048576,MATCH(DATE(F$2,1,1),Hybrid!$A$1:$LI$1),FALSE) -> 1.1128791 | G92: =VLOOKUP($E92,Hybrid!$1:$1048576,MATCH(DATE(G$2,1,1),Hybrid!$A$1:$LI$1),FALSE) -> 1.2750673 | H92: =VLOOKUP($E92,Hybrid!$1:$1048576,MATCH(DATE(H$2,1,1),Hybrid!$A$1:$LI$1),FALSE) -> 1.2901547 | I92: =VLOOKUP($E92,Hybrid!$1:$1048576,MATCH(DATE(I$2,1,1),Hybrid!$A$1:$LI$1),FALSE) -> 1.3064227 | J92: =VLOOKUP($E92,Hybrid!$1:$1048576,MATCH(DATE(J$2,1,1),Hybrid!$A$1:$LI$1),FALSE) -> 1.5187702 | K92: =VLOOKUP($E92,Hybrid!$1:$1048576,MATCH(DATE(K$2,1,1),Hybrid!$A$1:$LI$1),FALSE) -> 1.7576461 | L92: =VLOOKUP($E92,Hybrid!$1:$1048576,MATCH(DATE(L$2,1,1),Hybrid!$A$1:$LI$1),FALSE) -> 1.6938725 | M92: =VLOOKUP($E92,Hybrid!$1:$1048576,MATCH(DATE(M$2,1,1),Hybrid!$A$1:$LI$1),FALSE) -> 1.6981681 | ... AO92: =VLOOKUP($E92,Hybrid!$1:$1048576,MATCH(DATE(AO$2,1,1),Hybrid!$A$1:$LI$1),FALSE) -> 0.097002533
D93: class F | E93: NEWAUTO_cf_cele_0 | F93: =VLOOKUP($E93,Hybrid!$1:$1048576,MATCH(DATE(F$2,1,1),Hybrid!$A$1:$LI$1),FALSE) -> 0.5373497 | G93: =VLOOKUP($E93,Hybrid!$1:$1048576,MATCH(DATE(G$2,1,1),Hybrid!$A$1:$LI$1),FALSE) -> 0.60467305 | H93: =VLOOKUP($E93,Hybrid!$1:$1048576,MATCH(DATE(H$2,1,1),Hybrid!$A$1:$LI$1),FALSE) -> 0.59257126 | I93: =VLOOKUP($E93,Hybrid!$1:$1048576,MATCH(DATE(I$2,1,1),Hybrid!$A$1:$LI$1),FALSE) -> 0.55936948 | J93: =VLOOKUP($E93,Hybrid!$1:$1048576,MATCH(DATE(J$2,1,1),Hybrid!$A$1:$LI$1),FALSE) -> 0.58804758 | K93: =VLOOKUP($E93,Hybrid!$1:$1048576,MATCH(DATE(K$2,1,1),Hybrid!$A$1:$LI$1),FALSE) -> 0.64118008 | L93: =VLOOKUP($E93,Hybrid!$1:$1048576,MATCH(DATE(L$2,1,1),Hybrid!$A$1:$LI$1),FALSE) -> 0.5878347 | M93: =VLOOKUP($E93,Hybrid!$1:$1048576,MATCH(DATE(M$2,1,1),Hybrid!$A$1:$LI$1),FALSE) -> 0.55339157 | ... AO93: =VLOOKUP($E93,Hybrid!$1:$1048576,MATCH(DATE(AO$2,1,1),Hybrid!$A$1:$LI$1),FALSE) -> 0.00012509225
D94: class G | E94: NEWAUTO_cg_cele_0 | F94: =VLOOKUP($E94,Hybrid!$1:$1048576,MATCH(DATE(F$2,1,1),Hybrid!$A$1:$LI$1),FALSE) -> 1.0093163 | G94: =VLOOKUP($E94,Hybrid!$1:$1048576,MATCH(DATE(G$2,1,1),Hybrid!$A$1:$LI$1),FALSE) -> 1.1163451 | H94: =VLOOKUP($E94,Hybrid!$1:$1048576,MATCH(DATE(H$2,1,1),Hybrid!$A$1:$LI$1),FALSE) -> 1.0596405 | I94: =VLOOKUP($E94,Hybrid!$1:$1048576,MATCH(DATE(I$2,1,1),Hybrid!$A$1:$LI$1),FALSE) -> 0.95527055 | J94: =VLOOKUP($E94,Hybrid!$1:$1048576,MATCH(DATE(J$2,1,1),Hybrid!$A$1:$LI$1),FALSE) -> 0.95300756 | K94: =VLOOKUP($E94,Hybrid!$1:$1048576,MATCH(DATE(K$2,1,1),Hybrid!$A$1:$LI$1),FALSE) -> 0.9913864 | L94: =VLOOKUP($E94,Hybrid!$1:$1048576,MATCH(DATE(L$2,1,1),Hybrid!$A$1:$LI$1),FALSE) -> 0.86743627 | M94: =VLOOKUP($E94,Hybrid!$1:$1048576,MATCH(DATE(M$2,1,1),Hybrid!$A$1:$LI$1),FALSE) -> 0.77483475 | ... AO94: =VLOOKUP($E94,Hybrid!$1:$1048576,MATCH(DATE(AO$2,1,1),Hybrid!$A$1:$LI$1),FALSE) -> 7.5400472e-06
C95: GAS | E95: NEWAUTO_cgas_0 | F95: =VLOOKUP($E95,Hybrid!$1:$1048576,MATCH(DATE(F$2,1,1),Hybrid!$A$1:$LI$1),FALSE) -> 0.156989 | G95: =VLOOKUP($E95,Hybrid!$1:$1048576,MATCH(DATE(G$2,1,1),Hybrid!$A$1:$LI$1),FALSE) -> 0.18183241 | H95: =VLOOKUP($E95,Hybrid!$1:$1048576,MATCH(DATE(H$2,1,1),Hybrid!$A$1:$LI$1),FALSE) -> 0.18851563 | I95: =VLOOKUP($E95,Hybrid!$1:$1048576,MATCH(DATE(I$2,1,1),Hybrid!$A$1:$LI$1),FALSE) -> 0.18791953 | J95: =VLOOKUP($E95,Hybrid!$1:$1048576,MATCH(DATE(J$2,1,1),Hybrid!$A$1:$LI$1),FALSE) -> 0.20379916 | K95: =VLOOKUP($E95,Hybrid!$1:$1048576,MATCH(DATE(K$2,1,1),Hybrid!$A$1:$LI$1),FALSE) -> 0.23539542 | L95: =VLOOKUP($E95,Hybrid!$1:$1048576,MATCH(DATE(L$2,1,1),Hybrid!$A$1:$LI$1),FALSE) -> 0.23157458 | M95: =VLOOKUP($E95,Hybrid!$1:$1048576,MATCH(DATE(M$2,1,1),Hybrid!$A$1:$LI$1),FALSE) -> 0.23528344 | ... AO95: =VLOOKUP($E95,Hybrid!$1:$1048576,MATCH(DATE(AO$2,1,1),Hybrid!$A$1:$LI$1),FALSE) -> 0.30843577
D96: class A | E96: NEWAUTO_ca_cgas_0 | F96: =VLOOKUP($E96,Hybrid!$1:$1048576,MATCH(DATE(F$2,1,1),Hybrid!$A$1:$LI$1),FALSE) -> 0.044411988 | G96: =VLOOKUP($E96,Hybrid!$1:$1048576,MATCH(DATE(G$2,1,1),Hybrid!$A$1:$LI$1),FALSE) -> 0.05176636 | H96: =VLOOKUP($E96,Hybrid!$1:$1048576,MATCH(DATE(H$2,1,1),Hybrid!$A$1:$LI$1),FALSE) -> 0.054292615 | I96: =VLOOKUP($E96,Hybrid!$1:$1048576,MATCH(DATE(I$2,1,1),Hybrid!$A$1:$LI$1),FALSE) -> 0.055195817 | J96: =VLOOKUP($E96,Hybrid!$1:$1048576,MATCH(DATE(J$2,1,1),Hybrid!$A$1:$LI$1),FALSE) -> 0.061155588 | K96: =VLOOKUP($E96,Hybrid!$1:$1048576,MATCH(DATE(K$2,1,1),Hybrid!$A$1:$LI$1),FALSE) -> 0.071577291 | L96: =VLOOKUP($E96,Hybrid!$1:$1048576,MATCH(DATE(L$2,1,1),Hybrid!$A$1:$LI$1),FALSE) -> 0.071197382 | M96: =VLOOKUP($E96,Hybrid!$1:$1048576,MATCH(DATE(M$2,1,1),Hybrid!$A$1:$LI$1),FALSE) -> 0.073382055 | ... AO96: =VLOOKUP($E96,Hybrid!$1:$1048576,MATCH(DATE(AO$2,1,1),Hybrid!$A$1:$LI$1),FALSE) -> 0.16532225
D97: class B | E97: NEWAUTO_cb_cgas_0 | F97: =VLOOKUP($E97,Hybrid!$1:$1048576,MATCH(DATE(F$2,1,1),Hybrid!$A$1:$LI$1),FALSE) -> 0.042637772 | G97: =VLOOKUP($E97,Hybrid!$1:$1048576,MATCH(DATE(G$2,1,1),Hybrid!$A$1:$LI$1),FALSE) -> 0.049640534 | H97: =VLOOKUP($E97,Hybrid!$1:$1048576,MATCH(DATE(H$2,1,1),Hybrid!$A$1:$LI$1),FALSE) -> 0.05194175 | I97: =VLOOKUP($E97,Hybrid!$1:$1048576,MATCH(DATE(I$2,1,1),Hybrid!$A$1:$LI$1),FALSE) -> 0.052524862 | J97: =VLOOKUP($E97,Hybrid!$1:$1048576,MATCH(DATE(J$2,1,1),Hybrid!$A$1:$LI$1),FALSE) -> 0.057822668 | K97: =VLOOKUP($E97,Hybrid!$1:$1048576,MATCH(DATE(K$2,1,1),Hybrid!$A$1:$LI$1),FALSE) -> 0.067487206 | L97: =VLOOKUP($E97,Hybrid!$1:$1048576,MATCH(DATE(L$2,1,1),Hybrid!$A$1:$LI$1),FALSE) -> 0.066991295 | M97: =VLOOKUP($E97,Hybrid!$1:$1048576,MATCH(DATE(M$2,1,1),Hybrid!$A$1:$LI$1),FALSE) -> 0.068772206 | ... AO97: =VLOOKUP($E97,Hybrid!$1:$1048576,MATCH(DATE(AO$2,1,1),Hybrid!$A$1:$LI$1),FALSE) -> 0.098012657
D98: class C | E98: NEWAUTO_cc_cgas_0 | F98: =VLOOKUP($E98,Hybrid!$1:$1048576,MATCH(DATE(F$2,1,1),Hybrid!$A$1:$LI$1),FALSE) -> 0.029513467 | G98: =VLOOKUP($E98,Hybrid!$1:$1048576,MATCH(DATE(G$2,1,1),Hybrid!$A$1:$LI$1),FALSE) -> 0.034321016 | H98: =VLOOKUP($E98,Hybrid!$1:$1048576,MATCH(DATE(H$2,1,1),Hybrid!$A$1:$LI$1),FALSE) -> 0.035829144 | I98: =VLOOKUP($E98,Hybrid!$1:$1048576,MATCH(DATE(I$2,1,1),Hybrid!$A$1:$LI$1),FALSE) -> 0.036040783 | J98: =VLOOKUP($E98,Hybrid!$1:$1048576,MATCH(DATE(J$2,1,1),Hybrid!$A$1:$LI$1),FALSE) -> 0.039424162 | K98: =VLOOKUP($E98,Hybrid!$1:$1048576,MATCH(DATE(K$2,1,1),Hybrid!$A$1:$LI$1),FALSE) -> 0.045885719 | L98: =VLOOKUP($E98,Hybrid!$1:$1048576,MATCH(DATE(L$2,1,1),Hybrid!$A$1:$LI$1),FALSE) -> 0.045456176 | M98: =VLOOKUP($E98,Hybrid!$1:$1048576,MATCH(DATE(M$2,1,1),Hybrid!$A$1:$LI$1),FALSE) -> 0.046481399 | ... AO98: =VLOOKUP($E98,Hybrid!$1:$1048576,MATCH(DATE(AO$2,1,1),Hybrid!$A$1:$LI$1),FALSE) -> 0.042201233
D99: class D | E99: NEWAUTO_cd_cgas_0 | F99: =VLOOKUP($E99,Hybrid!$1:$1048576,MATCH(DATE(F$2,1,1),Hybrid!$A$1:$LI$1),FALSE) -> 0.016358695 | G99: =VLOOKUP($E99,Hybrid!$1:$1048576,MATCH(DATE(G$2,1,1),Hybrid!$A$1:$LI$1),FALSE) -> 0.018910387 | H99: =VLOOKUP($E99,Hybrid!$1:$1048576,MATCH(DATE(H$2,1,1),Hybrid!$A$1:$LI$1),FALSE) -> 0.019520505 | I99: =VLOOKUP($E99,Hybrid!$1:$1048576,MATCH(DATE(I$2,1,1),Hybrid!$A$1:$LI$1),FALSE) -> 0.019267849 | J99: =VLOOKUP($E99,Hybrid!$1:$1048576,MATCH(DATE(J$2,1,1),Hybrid!$A$1:$LI$1),FALSE) -> 0.020632487 | K99: =VLOOKUP($E99,Hybrid!$1:$1048576,MATCH(DATE(K$2,1,1),Hybrid!$A$1:$LI$1),FALSE) -> 0.023638786 | L99: =VLOOKUP($E99,Hybrid!$1:$1048576,MATCH(DATE(L$2,1,1),Hybrid!$A$1:$LI$1),FALSE) -> 0.023076172 | M99: =VLOOKUP($E99,Hybrid!$1:$1048576,MATCH(DATE(M$2,1,1),Hybrid!$A$1:$LI$1),FALSE) -> 0.023156915 | ... AO99: =VLOOKUP($E99,Hybrid!$1:$1048576,MATCH(DATE(AO$2,1,1),Hybrid!$A$1:$LI$1),FALSE) -> 0.0026613047
D100: class E | E100: NEWAUTO_ce_cgas_0 | F100: =VLOOKUP($E100,Hybrid!$1:$1048576,MATCH(DATE(F$2,1,1),Hybrid!$A$1:$LI$1),FALSE) -> 0.010063201 | G100: =VLOOKUP($E100,Hybrid!$1:$1048576,MATCH(DATE(G$2,1,1),Hybrid!$A$1:$LI$1),FALSE) -> 0.011571123 | H100: =VLOOKUP($E100,Hybrid!$1:$1048576,MATCH(DATE(H$2,1,1),Hybrid!$A$1:$LI$1),FALSE) -> 0.011825441 | I100: =VLOOKUP($E100,Hybrid!$1:$1048576,MATCH(DATE(I$2,1,1),Hybrid!$A$1:$LI$1),FALSE) -> 0.011470878 | J100: =VLOOKUP($E100,Hybrid!$1:$1048576,MATCH(DATE(J$2,1,1),Hybrid!$A$1:$LI$1),FALSE) -> 0.012036624 | K100: =VLOOKUP($E100,Hybrid!$1:$1048576,MATCH(DATE(K$2,1,1),Hybrid!$A$1:$LI$1),FALSE) -> 0.013591429 | L100: =VLOOKUP($E100,Hybrid!$1:$1048576,MATCH(DATE(L$2,1,1),Hybrid!$A$1:$LI$1),FALSE) -> 0.013093113 | M100: =VLOOKUP($E100,Hybrid!$1:$1048576,MATCH(DATE(M$2,1,1),Hybrid!$A$1:$LI$1),FALSE) -> 0.012916247 | ... AO100: =VLOOKUP($E100,Hybrid!$1:$1048576,MATCH(DATE(AO$2,1,1),Hybrid!$A$1:$LI$1),FALSE) -> 0.00023804551
...

Sheet date
A1: =Hybrid!A1 -> _date_ | B1: =Hybrid!B1 -> 42005 | C1: =Hybrid!C1 -> 42370 | D1: =Hybrid!D1 -> 42736 | E1: =Hybrid!E1 -> 43101 | F1: =Hybrid!F1 -> 43466 | G1: =Hybrid!G1 -> 43831 | H1: =Hybrid!H1 -> 44197 | ... AK1: =Hybrid!AK1 -> 54789
B2: =TEXT(B1,"jj mm aaaa") -> 01 01 2015 | C2: =TEXT(C1,"jj mm aaaa") -> 01 01 2016 | D2: =TEXT(D1,"jj mm aaaa") -> 01 01 2017 | E2: =TEXT(E1,"jj mm aaaa") -> 01 01 2018 | F2: =TEXT(F1,"jj mm aaaa") -> 01 01 2019 | G2: =TEXT(G1,"jj mm aaaa") -> 01 01 2020 | H2: =TEXT(H1,"jj mm aaaa") -> 01 01 2021 | I2: =TEXT(I1,"jj mm aaaa") -> 01 01 2022 | ... AK2: =TEXT(AK1,"jj mm aaaa") -> 01 01 2050
B3: =RIGHT(B2,4) -> 2015 | C3: =RIGHT(C2,4) -> 2016 | D3: =RIGHT(D2,4) -> 2017 | E3: =RIGHT(E2,4) -> 2018 | F3: =RIGHT(F2,4) -> 2019 | G3: =RIGHT(G2,4) -> 2020 | H3: =RIGHT(H2,4) -> 2021 | I3: =RIGHT(I2,4) -> 2022 | ... AK3: =RIGHT(AK2,4) -> 2050

Sheet Emissions
A1: _date_ | B1: 42005 | C1: 42370 | D1: 42736 | E1: 43101 | F1: 43466 | G1: 43831 | H1: 44197 | I1: 44562 | J1: 44927 | K1: 45292 | L1: 45658 | M1: 46023 | N1: 46388 | O1: 46753 | P1: 47119 | Q1: 47484 | R1: 47849 | S1: 48214 | T1: 48580 | U1: 48945 | V1: 49310 | W1: 49675 | X1: 50041 | Y1: 50406 | Z1: 50771 | AA1: 51136 | AB1: 51502 | AC1: 51867 | AD1: 52232 | AE1: 52597 | AF1: 52963 | AG1: 53328 | AH1: 53693 | AI1: 54058 | AJ1: 54424 | AK1: 54789
A2: ems_2 | B2: 468.75054 | C2: 471.19302 | D2: 470.67241 | E2: 468.61064 | F2: 470.55109 | G2: 479.10827 | H2: 486.86711 | I2: 494.01088 | J2: 499.8909 | K2: 504.37446 | L2: 507.56386 | M2: 513.61073 | N2: 521.55848 | O2: 531.14755 | P2: 542.08026 | Q2: 554.12133 | R2: 566.38506 | S2: 579.2542 | T2: 592.73215 | U2: 607.59992 | V2: 623.0926 | W2: 639.08116 | X2: 655.98463 | Y2: 673.89558 | Z2: 692.86688 | AA2: 712.73476 | AB2: 727.4013 | AC2: 740.64303 | AD2: 753.67307 | AE2: 766.83603 | AF2: 780.19083 | AG2: 795.45982 | AH2: 811.49637 | AI2: 828.03542 | AJ2: 844.94808 | AK2: 845.06799
A3: ems_ch_2 | B3: 129.15358 | C3: 128.5268 | D3: 126.48356 | E3: 124.12401 | F3: 123.23562 | G3: 123.74091 | H3: 123.35283 | I3: 122.84094 | J3: 122.05839 | K3: 120.99119 | L3: 119.6752 | M3: 119.34526 | N3: 119.48529 | O3: 119.85086 | P3: 120.31622 | Q3: 120.818 | R3: 121.29564 | S3: 121.74745 | T3: 122.17725 | U3: 122.58478 | V3: 122.94691 | W3: 123.31952 | X3: 123.69207 | Y3: 124.05655 | Z3: 124.40742 | AA3: 124.66542 | AB3: 124.89969 | AC3: 125.09387 | AD3: 125.24104 | AE3: 125.33942 | AF3: 125.38916 | AG3: 125.40501 | AH3: 125.38961 | AI3: 125.34286 | AJ3: 125.26328 | AK3: 125.35861
A4: ems_ch_2+ems_ci_2 | B4: 348.56175 | C4: 349.36355 | D4: 347.20381 | E4: 343.49624 | F4: 343.525 | G4: 349.52224 | H4: 354.40808 | I4: 358.47474 | J4: 361.13845 | K4: 362.26415 | L4: 361.89685 | M4: 364.50949 | N4: 368.95089 | O4: 374.89047 | P4: 382.02674 | Q4: 390.13839 | R4: 398.52252 | S4: 407.44771 | T4: 416.90958 | U4: 427.64542 | V4: 438.93497 | W4: 450.81847 | X4: 463.55988 | Y4: 477.22772 | Z4: 491.86403 | AA4: 507.3588 | AB4: 518.54197 | AC4: 528.5219 | AD4: 538.41722 | AE4: 548.51873 | AF4: 558.84797 | AG4: 570.56538 | AH4: 582.89391 | AI4: 595.59491 | AJ4: 608.55406 | AK4: 608.58705
A5: ems_ci_2 | B5: 219.40818 | C5: 220.83675 | D5: 220.72025 | E5: 219.37223 | F5: 220.28939 | G5: 225.78133 | H5: 231.05525 | I5: 235.6338 | J5: 239.08006 | K5: 241.27296 | L5: 242.22164 | M5: 245.16423 | N5: 249.4656 | O5: 255.03961 | P5: 261.71051 | Q5: 269.3204 | R5: 277.22688 | S5: 285.70026 | T5: 294.73232 | U5: 305.06063 | V5: 315.98806 | W5: 327.49896 | X5: 339.86781 | Y5: 353.17117 | Z5: 367.4566 | AA5: 382.69338 | AB5: 393.64228 | AC5: 403.42803 | AD5: 413.17618 | AE5: 423.17931 | AF5: 433.45881 | AG5: 445.16037 | AH5: 457.5043 | AI5: 470.25205 | AJ5: 483.29077 | AK5: 483.22845
A6: ems_mat_2 | B6: 27.948689 | C6: 28.318354 | D6: 28.68613 | E6: 29.040513 | F6: 29.422437 | G6: 29.888091 | H6: 30.402092 | I6: 30.939917 | J6: 31.487823 | K6: 32.041675 | L6: 32.604587 | M6: 33.164459 | N6: 33.740002 | O6: 34.340364 | P6: 34.966865 | Q6: 35.618003 | R6: 36.272073 | S6: 36.939137 | T6: 37.621755 | U6: 38.323493 | V6: 39.042678 | W6: 39.761575 | X6: 40.49485 | Y6: 41.247453 | Z6: 42.021839 | AA6: 42.814315 | AB6: 43.503661 | AC6: 44.149061 | AD6: 44.773285 | AE6: 45.388103 | AF6: 46.000308 | AG6: 46.673273 | AH6: 47.374836 | AI6: 48.097407 | AJ6: 48.838033 | AK6: 48.89847
A7: ems_y_2 | B7: 92.240103 | C7: 93.51112 | D7: 94.782465 | E7: 96.073889 | F7: 97.603648 | G7: 99.697945 | H7: 102.05693 | I7: 104.59623 | J7: 107.26463 | K7: 110.06863 | L7: 113.06243 | M7: 115.93678 | N7: 118.86759 | O7: 121.91671 | P7: 125.08666 | Q7: 128.36493 | R7: 131.59047 | S7: 134.86735 | T7: 138.20082 | U7: 141.63101 | V7: 145.11495 | W7: 148.50111 | X7: 151.9299 | Y7: 155.42041 | Z7: 158.98102 | AA7: 162.56164 | AB7: 165.35568 | AC7: 167.97207 | AD7: 170.48256 | AE7: 172.92919 | AF7: 175.34256 | AG7: 178.22117 | AH7: 181.22763 | AI7: 184.3431 | AJ7: 187.55599 | AK7: 187.58247
A8: ems_sec_2 | B8: 339.59697 | C8: 342.66622 | D8: 344.18885 | E8: 344.48664 | F8: 347.31547 | G8: 355.36736 | H8: 363.51428 | I8: 371.16995 | J8: 377.83251 | K8: 383.38327 | L8: 387.88866 | M8: 394.26547 | N8: 402.07319 | O8: 411.29668 | P8: 421.76404 | Q8: 433.30333 | R8: 445.08942 | S8: 457.50675 | T8: 470.5549 | U8: 485.01513 | V8: 500.14569 | W8: 515.76164 | X8: 532.29256 | Y8: 549.83903 | Z8: 568.45946 | AA8: 588.06934 | AB8: 602.50161 | AC8: 615.54916 | AD8: 628.43203 | AE8: 641.49661 | AF8: 654.80167 | AG8: 670.05481 | AH8: 686.10677 | AI8: 702.69255 | AJ8: 719.6848 | AK8: 719.70938
A9: ems_ets_2 | B9: 126.3106 | C9: 126.67165 | D9: 126.49932 | E9: 126.06373 | F9: 126.67739 | G9: 129.39713 | H9: 132.48287 | I9: 135.44448 | J9: 137.9489 | K9: 139.88302 | L9: 141.22032 | M9: 143.90323 | N9: 147.29536 | O9: 151.4142 | P9: 156.19721 | Q9: 161.57818 | R9: 167.16882 | S9: 173.20944 | T9: 179.68884 | U9: 187.37608 | V9: 195.5609 | W9: 204.21484 | X9: 213.55671 | Y9: 223.66576 | Z9: 234.6024 | AA9: 246.37899 | AB9: 254.21681 | AC9: 260.94088 | AD9: 267.61218 | AE9: 274.51014 | AF9: 281.65514 | AG9: 289.8315 | AH9: 298.46785 | AI9: 307.38017 | AJ9: 316.4769 | AK9: 316.49412
A10: ems_nets_2 | B10: 213.28637 | C10: 215.99457 | D10: 217.68953 | E10: 218.42291 | F10: 220.63808 | G10: 225.97023 | H10: 231.03141 | I10: 235.72546 | J10: 239.88361 | K10: 243.50025 | L10: 246.66833 | M10: 250.36224 | N10: 254.77784 | O10: 259.88249 | P10: 265.56682 | Q10: 271.72515 | R10: 277.9206 | S10: 284.29731 | T10: 290.86606 | U10: 297.63905 | V10: 304.5848 | W10: 311.5468 | X10: 318.73585 | Y10: 326.17327 | Z10: 333.85706 | AA10: 341.69034 | AB10: 348.28481 | AC10: 354.60829 | AD10: 360.81984 | AE10: 366.98647 | AF10: 373.14653 | AG10: 380.22332 | AH10: 387.63892 | AI10: 395.31239 | AJ10: 403.20789 | AK10: 403.21527
A11: ems_netsi_2 | B11: 25.497471 | C11: 25.767786 | D11: 25.854834 | E11: 25.803492 | F11: 26.025341 | G11: 26.731392 | H11: 27.365553 | I11: 27.913157 | J11: 28.338895 | K11: 28.633506 | L11: 28.801005 | M11: 29.085459 | N11: 29.504387 | O11: 30.044388 | P11: 30.685354 | Q11: 31.409435 | R11: 32.151726 | S11: 32.926686 | T11: 33.735618 | U11: 34.579505 | V11: 35.456073 | W11: 36.357918 | X11: 37.307924 | Y11: 38.308272 | Z11: 39.358722 | AA11: 40.449375 | AB11: 41.405843 | AC11: 42.33199 | AD11: 43.248577 | AE11: 44.164864 | AF11: 45.085594 | AG11: 46.127542 | AH11: 47.223535 | AI11: 48.361148 | AJ11: 49.534508 | AK11: 49.554416
A12: ems_trsp_2-ems_sair_2 | B12: 24.94373 | C12: 25.492854 | D12: 25.79787 | E12: 25.781879 | F12: 25.959213 | G12: 26.835108 | H12: 27.531693 | I12: 28.167055 | J12: 28.725178 | K12: 29.196698 | L12: 29.575097 | M12: 30.032698 | N12: 30.594835 | O12: 31.255246 | P12: 32.000382 | Q12: 32.817615 | R12: 33.636434 | S12: 34.485073 | T12: 35.36748 | U12: 36.277658 | V12: 37.214102 | W12: 38.150741 | X12: 39.121549 | Y12: 40.128843 | Z12: 41.170081 | AA12: 42.236285 | AB12: 43.097225 | AC12: 43.919402 | AD12: 44.728929 | AE12: 45.530064 | AF12: 46.323008 | AG12: 47.258178 | AH12: 48.229135 | AI12: 49.217823 | AJ12: 50.219931 | AK12: 50.219329
... A819: ems_ch_cbio_0+ems_ci_cbio_0 | B819: 31.867557 | C819: 31.51565 | D819: 31.145292 | E819: 30.713448 | F819: 30.462184 | G819: 30.324491 | H819: 30.234032 | I819: 30.168544 | J819: 30.11888 | K819: 30.080614 | L819: 30.066353 | M819: 30.051202 | N819: 30.039697 | O819: 30.033911 | P819: 30.03471 | Q819: 30.042438 | R819: 30.051656 | S819: 30.066233 | T819: 30.086979 | U819: 30.114145 | V819: 30.138148 | W819: 30.168686 | X819: 30.206708 | Y819: 30.251677 | Z819: 30.303249 | AA819: 30.33466 | AB819: 30.344377 | AC819: 30.351669 | AD819: 30.360767 | AE819: 30.372678 | AF819: 30.387606 | AG819: 30.422946 | AH819: 30.46648 | AI819: 30.51566 | AJ819: 30.569791 | AK819: 30.628574

Sheet Consumption
A1: _date_ | B1: 42005 | C1: 42370 | D1: 42736 | E1: 43101 | F1: 43466 | G1: 43831 | H1: 44197 | I1: 44562 | J1: 44927 | K1: 45292 | L1: 45658 | M1: 46023 | N1: 46388 | O1: 46753 | P1: 47119 | Q1: 47484 | R1: 47849 | S1: 48214 | T1: 48580 | U1: 48945 | V1: 49310 | W1: 49675 | X1: 50041 | Y1: 50406 | Z1: 50771 | AA1: 51136 | AB1: 51502 | AC1: 51867 | AD1: 52232 | AE1: 52597 | AF1: 52963 | AG1: 53328 | AH1: 53693 | AI1: 54058 | AJ1: 54424 | AK1: 54789
A2: ch_2 | B2: 1203404.4 | C2: 1222401.8 | D2: 1237530.9 | E2: 1250314.2 | F2: 1269299.9 | G2: 1301578.8 | H2: 1329002.4 | I2: 1357789.8 | J2: 1387968 | K2: 1420397.3 | L2: 1456675.4 | M2: 1490551.4 | N2: 1525239.1 | O2: 1561053.5 | P2: 1597644.8 | Q2: 1634733.8 | R2: 1672116.9 | S2: 1709541.7 | T2: 1747149 | U2: 1785132.6 | V2: 1823183 | W2: 1861114.2 | X2: 1899133.7 | Y2: 1937353.1 | Z2: 1975846.1 | AA2: 2013302 | AB2: 2048045.8 | AC2: 2079981.5 | AD2: 2109717.2 | AE2: 2137947 | AF2: 2165268.5 | AG2: 2193422.2 | AH2: 2223037.7 | AI2: 2254163.8 | AJ2: 2286656.1 | AK2: 2297320.9
A3: ch_0 | B3: 1203404.4 | C3: 1222401.8 | D3: 1237530.9 | E3: 1250314.2 | F3: 1269299.9 | G3: 1301578.8 | H3: 1329002.4 | I3: 1356254.9 | J3: 1383774.9 | K3: 1411981.7 | L3: 1441772.5 | M3: 1472142.8 | N3: 1503264.1 | O3: 1535161.6 | P3: 1567825.2 | Q3: 1601250.8 | R3: 1634975.6 | S3: 1668939.3 | T3: 1703203.2 | U3: 1737859.7 | V3: 1772524.4 | W3: 1807519.3 | X3: 1842726.3 | Y3: 1878229.8 | Z3: 1914151.8 | AA3: 1949218.4 | AB3: 1982363.8 | AC3: 2013174.8 | AD3: 2042046.8 | AE3: 2069540.4 | AF3: 2096170.5 | AG3: 2123738.6 | AH3: 2152753.4 | AI3: 2183263.1 | AJ3: 2215148 | AK3: 2248220.3
A4: pch_2 | B4: 1.0032468 | C4: 1.0221015 | D4: 1.0530567 | E4: 1.0930848 | F4: 1.1248208 | G4: 1.1430421 | H4: 1.1774681 | I4: 1.2174542 | J4: 1.2666522 | K4: 1.327428 | L4: 1.403201 | M4: 1.4808674 | N4: 1.5661788 | O4: 1.6604591 | P4: 1.7651164 | Q4: 1.8815755 | R4: 2.0121974 | S4: 2.1579742 | T4: 2.3205566 | U4: 2.502229 | V4: 2.7052337 | W4: 2.9298532 | X4: 3.1790131 | Y4: 3.455474 | Z4: 3.7624005 | AA4: 4.1040694 | AB4: 4.4789532 | AC4: 4.8885566 | AD4: 5.3344983 | AE4: 5.8186726 | AF4: 6.3430104 | AG4: 6.9113183 | AH4: 7.5277171 | AI4: 8.1956576 | AJ4: 8.9184683 | AK4: 8.9184681
A5: pch_0 | B5: 1.0032468 | C5: 1.0221015 | D5: 1.0530567 | E5: 1.0930848 | F5: 1.1248208 | G5: 1.1430421 | H5: 1.1774681 | I5: 1.2123348 | J5: 1.2509694 | K5: 1.2934343 | L5: 1.3398555 | M5: 1.3907473 | N5: 1.4464336 | O5: 1.5073934 | P5: 1.5741562 | Q5: 1.6472972 | R5: 1.7270942 | S5: 1.8139848 | T5: 1.9085346 | U5: 2.0114021 | V5: 2.1234679 | W5: 2.245088 | X5: 2.3768617 | Y5: 2.5195627 | Z5: 2.6741001 | AA5: 2.8420232 | AB5: 3.0215732 | AC5: 3.2118235 | AD5: 3.4122786 | AE5: 3.6226013 | AF5: 3.8424377 | AG5: 4.0732092 | AH5: 4.3156046 | AI5: 4.5699239 | AJ5: 4.8362696 | AK5: 5.1146469
A6: ch_cagr_2 | B6: 31664.106 | C6: 32092.395 | D6: 32446.991 | E6: 32747.935 | F6: 33161.041 | G6: 33919.129 | H6: 34698.843 | I6: 35537.006 | J6: 36404.354 | K6: 37308.665 | L6: 38284.013 | M6: 39161.114 | N6: 40068.091 | O6: 41033.933 | P6: 42051.441 | Q6: 43107.6 | R6: 44189.125 | S6: 45279.107 | T6: 46375.702 | U6: 47484.511 | V6: 48595.461 | W6: 49702.875 | X6: 50816.642 | Y6: 51941.28 | Z6: 53078.698 | AA6: 54195.316 | AB6: 55241.955 | AC6: 56213.439 | AD6: 57123.744 | AE6: 57990.417 | AF6: 58829.314 | AG6: 59688.213 | AH6: 60587.5 | AI6: 61529.819 | AJ6: 62511.273 | AK6: 63021.951
A7: ch_cagr_0 | B7: 31664.106 | C7: 32092.395 | D7: 32446.991 | E7: 32747.935 | F7: 33161.041 | G7: 33919.129 | H7: 34698.843 | I7: 35496.863 | J7: 36307.589 | K7: 37135.834 | L7: 38002.615 | M7: 38883.875 | N7: 39785.037 | O7: 40708.16 | P7: 41654.227 | Q7: 42623.99 | R7: 43605.365 | S7: 44596.235 | T7: 45597.995 | U7: 46613.119 | V7: 47632.111 | W7: 48662.085 | X7: 49699.702 | Y7: 50747.132 | Z7: 51807.823 | AA7: 52849.66 | AB7: 53840.038 | AC7: 54764.525 | AD7: 55632.312 | AE7: 56458.832 | AF7: 57259.032 | AG7: 58083.447 | AH7: 58948.585 | AI7: 59857.034 | AJ7: 60805.754 | AK7: 61789.386
A8: pch_cagr_2 | B8: 1.0028246 | C8: 1.0218946 | D8: 1.050828 | E8: 1.0914865 | F8: 1.1276977 | G8: 1.1482102 | H8: 1.1788854 | I8: 1.2172175 | J8: 1.2657517 | K8: 1.3272438 | L8: 1.4054961 | M8: 1.4884876 | N8: 1.5774749 | O8: 1.6740567 | P8: 1.7799524 | Q8: 1.8968828 | R8: 2.0274835 | S8: 2.1733207 | T8: 2.336099 | U8: 2.5180292 | V8: 2.7214199 | W8: 2.9464377 | X8: 3.1954563 | Y8: 3.4712458 | Z8: 3.7769572 | AA8: 4.1167156 | AB8: 4.4893962 | AC8: 4.8961931 | AD8: 5.3387323 | AE8: 5.8188608 | AF8: 6.338475 | AG8: 6.9009852 | AH8: 7.5101518 | AI8: 8.1694781 | AJ8: 8.8823573 | AK8: 8.8823583
A9: pch_cagr_0 | B9: 1.0028246 | C9: 1.0218946 | D9: 1.050828 | E9: 1.0914865 | F9: 1.1276977 | G9: 1.1482102 | H9: 1.1788854 | I9: 1.21249 | J9: 1.249859 | K9: 1.2912523 | L9: 1.3367917 | M9: 1.3868627 | N9: 1.4417792 | O9: 1.5019403 | P9: 1.5678171 | Q9: 1.6399439 | R9: 1.7185941 | S9: 1.8042003 | T9: 1.8973013 | U9: 1.9985213 | V9: 2.1086802 | W9: 2.2281615 | X9: 2.3575527 | Y9: 2.4975862 | Z9: 2.6491198 | AA9: 2.8135583 | AB9: 2.9895035 | AC9: 3.1761104 | AD9: 3.372808 | AE9: 3.5791565 | AF9: 3.7947303 | AG9: 4.0207312 | AH9: 4.2577773 | AI9: 4.5061933 | AJ9: 4.76613 | AK9: 5.0376315
A10: ch_cfoo_2 | B10: 175274.19 | C10: 177551.28 | D10: 179575.46 | E10: 181612.92 | F10: 184184.43 | G10: 188169.02 | H10: 192326.41 | I10: 196938.29 | J10: 201876.91 | K10: 207197.72 | L10: 213104.42 | M10: 218366.21 | N10: 223631.97 | O10: 229084.64 | P10: 234726.47 | Q10: 240523.53 | R10: 246448.3 | S10: 252423.89 | T10: 258443.92 | U10: 264542.06 | V10: 270658.53 | W10: 276733.57 | X10: 282818.82 | Y10: 288944.57 | Z10: 295128.2 | AA10: 301188.73 | AB10: 306836.9 | AC10: 312044.7 | AD10: 316897.47 | AE10: 321501.53 | AF10: 325952.19 | AG10: 330515.4 | AH10: 335308.11 | AI10: 340347.29 | AJ10: 345611.83 | AK10: 348384.66
A11: ch_cfoo_0 | B11: 175274.19 | C11: 177551.28 | D11: 179575.46 | E11: 181612.92 | F11: 184184.43 | G11: 188169.02 | H11: 192326.41 | I11: 196626.89 | J11: 201038.55 | K11: 205578.45 | L11: 210350.52 | M11: 215211.52 | N11: 220183.14 | O11: 225271.25 | P11: 230478.26 | Q11: 235807.03 | R11: 241189.21 | S11: 246612.82 | T11: 252086.23 | U11: 257624.19 | V11: 263175.43 | W11: 268779.03 | X11: 274416.82 | Y11: 280101.66 | Z11: 285853.78 | AA11: 291497.4 | AB11: 296846.4 | AC11: 301818.17 | AD11: 306464.62 | AE11: 310874.43 | AF11: 315134.1 | AG11: 319529.24 | AH11: 324154.83 | AI11: 329026.04 | AJ11: 334125.36 | AK11: 339421.91
A12: pch_cfoo_2 | B12: 1.0017356 | C12: 1.0228194 | D12: 1.0500197 | E12: 1.0845578 | F12: 1.1182405 | G12: 1.1445194 | H12: 1.176196 | I12: 1.2137038 | J12: 1.2594212 | K12: 1.31592 | L12: 1.3864947 | M12: 1.4647022 | N12: 1.5508523 | O12: 1.6458391 | P12: 1.7508802 | Q12: 1.8673652 | R12: 1.9972738 | S12: 2.1422015 | T12: 2.3038965 | U12: 2.4844971 | V12: 2.6863933 | W12: 2.9105687 | X12: 3.1592487 | Y12: 3.4350928 | Z12: 3.7411767 | AA12: 4.0815799 | AB12: 4.4560725 | AC12: 4.8657821 | AD12: 5.3122142 | AE12: 5.7970965 | AF12: 6.3222343 | AG12: 6.8912027 | AH12: 7.5075856 | AI12: 8.1748496 | AJ12: 8.8964224 | AK12: 8.896423
... A105: pch_cbio_0 | B105: 1.0609943 | C105: 1.1094858 | D105: 1.1692166 | E105: 1.2611558 | F105: 1.2938345 | G105: 1.3163405 | H105: 1.3479671 | I105: 1.3827258 | J105: 1.4209798 | K105: 1.4628444 | L105: 1.5084513 | M105: 1.5582171 | N105: 1.6125939 | O105: 1.6721393 | P105: 1.737451 | Q105: 1.8091484 | R105: 1.8878572 | S105: 1.9739767 | T105: 2.0679229 | U105: 2.1702301 | V105: 2.2816985 | W105: 2.4027471 | X105: 2.5340245 | Y105: 2.6763325 | Z105: 2.8305962 | AA105: 2.9983563 | AB105: 3.1756007 | AC105: 3.3618507 | AD105: 3.5581028 | AE105: 3.7651673 | AF105: 3.9831311 | AG105: 4.212981 | AH105: 4.4548905 | AI105: 4.7087023 | AJ105: 4.9742146 | AK105: 5.2512889

Sheet Value_Added
A1: _date_ | B1: 42005 | C1: 42370 | D1: 42736 | E1: 43101 | F1: 43466 | G1: 43831 | H1: 44197 | I1: 44562 | J1: 44927 | K1: 45292 | L1: 45658 | M1: 46023 | N1: 46388 | O1: 46753 | P1: 47119 | Q1: 47484 | R1: 47849 | S1: 48214 | T1: 48580 | U1: 48945 | V1: 49310 | W1: 49675 | X1: 50041 | Y1: 50406 | Z1: 50771 | AA1: 51136 | AB1: 51502 | AC1: 51867 | AD1: 52232 | AE1: 52597 | AF1: 52963 | AG1: 53328 | AH1: 53693 | AI1: 54058 | AJ1: 54424 | AK1: 54789
A2: va_2 | B2: 1966350.9 | C2: 1996530 | D2: 2025301.6 | E2: 2053628.2 | F2: 2086126.4 | G2: 2127752.1 | H2: 2171259.9 | I2: 2216945.8 | J2: 2264433.5 | K2: 2314086.1 | L2: 2366954 | M2: 2418352.4 | N2: 2470987.5 | O2: 2525377.6 | P2: 2581418.4 | Q2: 2638946.5 | R2: 2695415.5 | S2: 2752858.6 | T2: 2811311.4 | U2: 2871031 | V2: 2931671.7 | W2: 2990710 | X2: 3050604 | Y2: 3111452.1 | Z2: 3173342.7 | AA2: 3235398.6 | AB2: 3285576.4 | AC2: 3333986.3 | AD2: 3380752.9 | AE2: 3426422.1 | AF2: 3471507.2 | AG2: 3524284.1 | AH2: 3578587.5 | AI2: 3634593.8 | AJ2: 3692217 | AK2: 3687559.3
A3: va_0 | B3: 1966350.9 | C3: 1996530 | D3: 2025301.6 | E3: 2053628.2 | F3: 2086126.4 | G3: 2127752.1 | H3: 2171259.9 | I3: 2215904.9 | J3: 2261734 | K3: 2308925.4 | L3: 2358068.3 | M3: 2408402.7 | N3: 2460152.5 | O3: 2513325 | P3: 2567938.2 | Q3: 2624017.8 | R3: 2678799.1 | S3: 2734564.7 | T3: 2791356.9 | U3: 2849272.7 | V3: 2908077.4 | W3: 2965604.3 | X3: 3024050.8 | Y3: 3083476.8 | Z3: 3144000.3 | AA3: 3204770.1 | AB3: 3254291.2 | AC3: 3302390.3 | AD3: 3349024.6 | AE3: 3394648.4 | AF3: 3439722.5 | AG3: 3492584.7 | AH3: 3546975.2 | AI3: 3603055.5 | AJ3: 3660751 | AK3: 3719934.8
A4: va_sagr_2 | B4: 30825.379 | C4: 31230.579 | D4: 31670.696 | E4: 32165.133 | F4: 32722.727 | G4: 33403.467 | H4: 34186.039 | I4: 35045.968 | J4: 35972.867 | K4: 36975.072 | L4: 38075.985 | M4: 39101.588 | N4: 40136.92 | O4: 41201.609 | P4: 42295.465 | Q4: 43415.492 | R4: 44506.832 | S4: 45617.838 | T4: 46745.55 | U4: 47897.181 | V4: 49063.107 | W4: 50180.757 | X4: 51311.73 | Y4: 52456.857 | Z4: 53618.061 | AA4: 54775.083 | AB4: 55633.476 | AC4: 56458.49 | AD4: 57247.369 | AE4: 58010.558 | AF4: 58758.902 | AG4: 59678.078 | AH4: 60618.082 | AI4: 61589.958 | AJ4: 62593.264 | AK4: 62464.784
A5: va_sagr_0 | B5: 30825.379 | C5: 31230.579 | D5: 31670.696 | E5: 32165.133 | F5: 32722.727 | G5: 33403.467 | H5: 34186.039 | I5: 34997.337 | J5: 35836.991 | K5: 36707.236 | L5: 37619.308 | M5: 38550.553 | N5: 39508.903 | O5: 40494.463 | P5: 41507.193 | Q5: 42547.258 | R5: 43552.16 | S5: 44576.486 | T5: 45618.011 | U5: 46677.85 | V5: 47750.102 | W5: 48786.487 | X5: 49839.362 | Y5: 50907.329 | Z5: 51992.4 | AA5: 53074.746 | AB5: 53876.663 | AC5: 54653.871 | AD5: 55399.012 | AE5: 56120.222 | AF5: 56827.128 | AG5: 57706.681 | AH5: 58607.494 | AI5: 59540.554 | AJ5: 60505.781 | AK5: 61500.349
A6: va_sfor_2 | B6: 5287.6962 | C6: 5236.9216 | D6: 5192.2565 | E6: 5145.4329 | F6: 5122.8585 | G6: 5115.1548 | H6: 5144.882 | I6: 5157.934 | J6: 5158.7029 | K6: 5149.0677 | L6: 5132.5164 | M6: 5164.8715 | N6: 5222.0891 | O6: 5295.5467 | P6: 5380.7529 | Q6: 5475.9424 | R6: 5591.4608 | S6: 5718.3807 | T6: 5855.7645 | U6: 6003.8666 | V6: 6161.4083 | W6: 6326.3064 | X6: 6502.2114 | Y6: 6690.2231 | Z6: 6891.7252 | AA6: 7104.2196 | AB6: 7176.5835 | AC6: 7213.359 | AD6: 7244.1556 | AE6: 7276.7892 | AF6: 7312.6172 | AG6: 7364.9704 | AH6: 7422.7285 | AI6: 7484.2644 | AJ6: 7548.8495 | AK6: 7547.0539
A7: va_sfor_0 | B7: 5287.6962 | C7: 5236.9216 | D7: 5192.2565 | E7: 5145.4329 | F7: 5122.8585 | G7: 5115.1548 | H7: 5144.882 | I7: 5185.6001 | J7: 5233.6019 | K7: 5288.0835 | L7: 5351.3574 | M7: 5416.261 | N7: 5485.764 | O7: 5562.3339 | P7: 5646.984 | Q7: 5740.4363 | R7: 5855.8713 | S7: 5983.3731 | T7: 6121.5362 | U7: 6270.2717 | V7: 6428.1709 | W7: 6593.736 | X7: 6770.5273 | Y7: 6959.6365 | Z7: 7162.4958 | AA7: 7376.4434 | AB7: 7448.9991 | AC7: 7484.7456 | AD7: 7513.651 | AE7: 7543.7908 | AF7: 7576.668 | AG7: 7626.0548 | AH7: 7680.4558 | AI7: 7738.111 | AJ7: 7798.2751 | AK7: 7860.6263
A8: va_sfoo_2 | B8: 43707.442 | C8: 44380.276 | D8: 45032.564 | E8: 45716.665 | F8: 46502.571 | G8: 47538.334 | H8: 48639.88 | I8: 49843.819 | J8: 51131.91 | K8: 52522.149 | L8: 54055.444 | M8: 55443.012 | N8: 56860.97 | O8: 58327.195 | P8: 59834.698 | Q8: 61377.693 | R8: 62892.117 | S8: 64435.054 | T8: 66000.316 | U8: 67602 | V8: 69218.773 | W8: 70778.238 | X8: 72361.466 | Y8: 73965.285 | Z8: 75591.577 | AA8: 77203.588 | AB8: 78445.317 | AC8: 79652.58 | AD8: 80806.537 | AE8: 81921.248 | AF8: 83012.296 | AG8: 84310.501 | AH8: 85629.184 | AI8: 86992.709 | AJ8: 88400.42 | AK8: 88103.538
A9: va_sfoo_0 | B9: 43707.442 | C9: 44380.276 | D9: 45032.564 | E9: 45716.665 | F9: 46502.571 | G9: 47538.334 | H9: 48639.88 | I9: 49769.558 | J9: 50936.093 | K9: 52145.188 | L9: 53416.468 | M9: 54710.351 | N9: 56041.759 | O9: 57410.384 | P9: 58815.997 | Q9: 60258.887 | R9: 61661.833 | S9: 63094.256 | T9: 64549.898 | U9: 66030.332 | V9: 67524.701 | W9: 68981.377 | X9: 70463.656 | Y9: 71966.698 | Z9: 73493.531 | AA9: 75008.398 | AB9: 76179.216 | AC9: 77325.809 | AD9: 78423.616 | AE9: 79484.186 | AF9: 80521.884 | AG9: 81771.549 | AH9: 83042.264 | AI9: 84358.814 | AJ9: 85721.403 | AK9: 87125.616
A10: va_sveh_2 | B10: 29846.84 | C10: 30858.704 | D10: 31638.716 | E10: 32306.531 | F10: 33210.659 | G10: 34406.515 | H10: 35348.782 | I10: 36287.596 | J10: 37243.615 | K10: 38224.589 | L10: 39234.302 | M10: 40341.862 | N10: 41509.869 | O10: 42705.448 | P10: 43923.589 | Q10: 45166.894 | R10: 46279.121 | S10: 47448.126 | T10: 48649.552 | U10: 49875.707 | V10: 51131.46 | W10: 52280.756 | X10: 53487.669 | Y10: 54721.356 | Z10: 55979.202 | AA10: 57252.677 | AB10: 57840.7 | AC10: 58574.551 | AD10: 59317.652 | AE10: 60058.498 | AF10: 60799.395 | AG10: 61984.251 | AH10: 63098.207 | AI10: 64227.317 | AJ10: 65380.943 | AK10: 65069.24
A11: va_sveh_0 | B11: 29846.84 | C11: 30858.704 | D11: 31638.716 | E11: 32306.531 | F11: 33210.659 | G11: 34406.515 | H11: 35348.782 | I11: 36313.579 | J11: 37309.489 | K11: 38339.022 | L11: 39409.432 | M11: 40496.165 | N11: 41620.079 | O11: 42778.91 | P11: 43972.617 | Q11: 45201.833 | R11: 46312.986 | S11: 47484.951 | T11: 48689.028 | U11: 49923.155 | V11: 51184.984 | W11: 52332.573 | X11: 53537.594 | Y11: 54772.06 | Z11: 56033.931 | AA11: 57314.468 | AB11: 57910.805 | AC11: 58655.821 | AD11: 59412.652 | AE11: 60169.008 | AF11: 60926.479 | AG11: 62125.938 | AH11: 63254.334 | AI11: 64398.299 | AJ11: 65567.218 | AK11: 66761.146
A12: va_sgla_2 | B12: 7907.6322 | C12: 8052.3352 | D12: 8194.2115 | E12: 8327.2846 | F12: 8464.4666 | G12: 8630.7153 | H12: 8821.7832 | I12: 9027.196 | J12: 9243.9285 | K12: 9471.031 | L12: 9709.7604 | M12: 9940.8332 | N12: 10175.588 | O12: 10418.614 | P12: 10671.089 | Q12: 10933.061 | R12: 11190.489 | S12: 11456.109 | T12: 11729.647 | U12: 12013.114 | V12: 12304.97 | W12: 12590.91 | X12: 12885.255 | Y12: 13188.783 | Z12: 13502.596 | AA12: 13824.962 | AB12: 14064.982 | AC12: 14290.149 | AD12: 14504.252 | AE12: 14711.562 | AF12: 14915.079 | AG12: 15159.412 | AH12: 15408.288 | AI12: 15663.679 | AJ12: 15925.456 | AK12: 15890.135
... A79: va_ser_0 | B79: 1511595.7 | C79: 1534025.8 | D79: 1555666.3 | E79: 1577023.9 | F79: 1601502 | G79: 1633047.2 | H79: 1666133.9 | I79: 1700191 | J79: 1735144.8 | K79: 1771130 | L79: 1808612 | M79: 1846836.4 | N79: 1886067.7 | O79: 1926366.6 | P79: 1967757.7 | Q79: 2010263.4 | R79: 2052165.3 | S79: 2094744.3 | T79: 2138108.2 | U79: 2182345.6 | V79: 2227280 | W79: 2271630.9 | X79: 2316653.2 | Y79: 2362493.1 | Z79: 2409277.3 | AA79: 2456364.2 | AB79: 2495019.7 | AC79: 2531609.1 | AD79: 2566916.9 | AE79: 2601467 | AF79: 2635641.2 | AG79: 2674797.9 | AH79: 2715441.3 | AI79: 2757440.1 | AJ79: 2800691.5 | AK79: 2845082.4

Sheet INV
A1: _date_ | B1: 42005 | C1: 42370 | D1: 42736 | E1: 43101 | F1: 43466 | G1: 43831 | H1: 44197 | I1: 44562 | J1: 44927 | K1: 45292 | L1: 45658 | M1: 46023 | N1: 46388 | O1: 46753 | P1: 47119 | Q1: 47484 | R1: 47849 | S1: 48214 | T1: 48580 | U1: 48945 | V1: 49310 | W1: 49675 | X1: 50041 | Y1: 50406 | Z1: 50771 | AA1: 51136 | AB1: 51502 | AC1: 51867 | AD1: 52232 | AE1: 52597 | AF1: 52963 | AG1: 53328 | AH1: 53693 | AI1: 54058 | AJ1: 54424 | AK1: 54789
A2: ia_2 | B2: 472227.21 | C2: 479028.76 | D2: 484916.97 | E2: 489337.77 | F2: 495161.79 | G2: 505149.17 | H2: 515733.91 | I2: 526527.14 | J2: 537059.92 | K2: 547156.87 | L2: 556843.55 | M2: 567033.1 | N2: 578019.25 | O2: 589956.48 | P2: 602840.57 | Q2: 616605.82 | R2: 630711.17 | S2: 645272.5 | T2: 660371 | U2: 676064.79 | V2: 692365.74 | W2: 708972.88 | X2: 726106.93 | Y2: 743903.68 | Z2: 762444.04 | AA2: 781657.38 | AB2: 798525.83 | AC2: 813860.56 | AD2: 828322.67 | AE2: 842308.4 | AF2: 856045.65 | AG2: 870982.73 | AH2: 886723.63 | AI2: 903054.67 | AJ2: 919874.62 | AK2: 925004.26
A3: ia_0 | B3: 472227.21 | C3: 479028.76 | D3: 484916.97 | E3: 489337.77 | F3: 495161.79 | G3: 505149.17 | H3: 515733.91 | I3: 527052.68 | J3: 538843.18 | K3: 551072.52 | L3: 563857.6 | M3: 577063.16 | N3: 590732.87 | O3: 604929.44 | P3: 619699.73 | Q3: 635080.03 | R3: 650678.55 | S3: 666689.16 | T3: 683230.3 | U3: 700374.89 | V3: 718127.99 | W3: 736137.14 | X3: 754625.21 | Y3: 773737.93 | Z3: 793576.01 | AA3: 814078.46 | AB3: 832129.12 | AC3: 848578.66 | AD3: 864122.84 | AE3: 879180.59 | AF3: 893993.29 | AG3: 910032.15 | AH3: 926873.57 | AI3: 944288.84 | AJ3: 962175.8 | AK3: 980486.13
A4: ia_sagr_2 | B4: 4269.8683 | C4: 4325.5104 | D4: 4373.3704 | E4: 4413.5882 | F4: 4468.7632 | G4: 4564.2964 | H4: 4669.1675 | I4: 4781.3881 | J4: 4896.8044 | K4: 5014.2155 | L4: 5134.8724 | M4: 5259.0051 | N4: 5389.0288 | O4: 5527.3483 | P4: 5674.4152 | Q4: 5829.6411 | R4: 5986.9808 | S4: 6147.6187 | T4: 6312.0628 | U4: 6480.861 | V4: 6653.5181 | W4: 6825.6241 | X4: 6999.5835 | Y4: 7176.6715 | Z4: 7357.3897 | AA4: 7540.0377 | AB4: 7699.84 | AC4: 7846.402 | AD4: 7985.011 | AE4: 8118.4507 | AF4: 8248.4598 | AG4: 8391.684 | AH4: 8543.1404 | AI4: 8700.5669 | AJ4: 8863.0016 | AK4: 8912.0149
A5: ia_sagr_0 | B5: 4269.8683 | C5: 4325.5104 | D5: 4373.3704 | E5: 4413.5882 | F5: 4468.7632 | G5: 4564.2964 | H5: 4669.1675 | I5: 4783.4561 | J5: 4903.8292 | K5: 5029.5931 | L5: 5161.7655 | M5: 5299.0352 | N5: 5441.562 | O5: 5589.5436 | P5: 5743.1056 | Q5: 5902.3397 | R5: 6062.0938 | S5: 6224.4202 | T5: 6390.3558 | U5: 6560.3903 | V5: 6734.1391 | W5: 6907.2439 | X5: 7082.0026 | Y5: 7259.5621 | Z5: 7440.4887 | AA5: 7623.1327 | AB5: 7782.7536 | AC5: 7929.4498 | AD5: 8068.5519 | AE5: 8202.7963 | AF5: 8333.8938 | AG5: 8478.7714 | AH5: 8632.1304 | AI5: 8791.5882 | AJ5: 8956.2217 | AK5: 9125.5349
A6: ia_sfor_2 | B6: 166.59892 | C6: 166.12599 | D6: 164.19333 | E6: 161.22508 | F6: 159.0652 | G6: 158.55587 | H6: 158.46741 | I6: 157.99184 | J6: 156.82006 | K6: 154.90316 | L6: 152.30518 | M6: 150.84746 | N6: 150.44127 | O6: 150.84565 | P6: 151.86929 | Q6: 153.39952 | R6: 155.55122 | S6: 158.21748 | T6: 161.34416 | U6: 164.91285 | V6: 168.90044 | W6: 173.30928 | X6: 178.1903 | Y6: 183.58175 | Z6: 189.52248 | AA6: 195.9807 | AB6: 200.11905 | AC6: 202.76786 | AD6: 204.80407 | AE6: 206.6725 | AF6: 208.5435 | AG6: 210.73588 | AH6: 213.14238 | AI6: 215.69026 | AJ6: 218.34261 | AK6: 219.23215
A7: ia_sfor_0 | B7: 166.59892 | C7: 166.12599 | D7: 164.19333 | E7: 161.22508 | F7: 159.0652 | G7: 158.55587 | H7: 158.46741 | I7: 158.88121 | J7: 159.57671 | K7: 160.49075 | L7: 161.66779 | M7: 162.98518 | N7: 164.46878 | O7: 166.18461 | P7: 168.18144 | Q7: 170.49563 | R7: 173.41873 | S7: 176.86941 | T7: 180.79437 | U7: 185.1789 | V7: 189.99367 | W7: 195.20602 | X7: 200.88131 | Y7: 207.07063 | Z7: 213.82532 | AA7: 221.11251 | AB7: 225.80039 | AC7: 228.79067 | AD7: 231.05114 | AE7: 233.08081 | AF7: 235.07636 | AG7: 237.37792 | AH7: 239.86567 | AI7: 242.45858 | AJ7: 245.11795 | AK7: 247.82887
A8: ia_sfoo_2 | B8: 6738.5226 | C8: 6825.5538 | D8: 6895.3298 | E8: 6951.8855 | F8: 7037.251 | G8: 7189.4524 | H8: 7351.0069 | I8: 7520.4293 | J8: 7691.2196 | K8: 7861.6397 | L8: 8033.7718 | M8: 8211.1219 | N8: 8397.8744 | O8: 8597.6923 | P8: 8810.9044 | Q8: 9036.3063 | R8: 9265.7783 | S8: 9500.3906 | T8: 9740.597 | U8: 9987.4812 | V8: 10239.98 | W8: 10493.203 | X8: 10750.153 | Y8: 11012.397 | Z8: 11280.559 | AA8: 11551.474 | AB8: 11794.912 | AC8: 12021.895 | AD8: 12238.551 | AE8: 12448.465 | AF8: 12654.101 | AG8: 12876.45 | AH8: 13110.252 | AI8: 13353.263 | AJ8: 13604.385 | AK8: 13680.123
A9: ia_sfoo_0 | B9: 6738.5226 | C9: 6825.5538 | D9: 6895.3298 | E9: 6951.8855 | F9: 7037.251 | G9: 7189.4524 | H9: 7351.0069 | I9: 7524.8492 | J9: 7706.1762 | K9: 7894.4042 | L9: 8091.6945 | M9: 8295.833 | N9: 8507.1493 | O9: 8725.9945 | P9: 8952.5866 | Q9: 9187.093 | R9: 9423.1287 | S9: 9663.1838 | T9: 9908.5105 | U9: 10159.774 | V9: 10416.19 | W9: 10672.848 | X9: 10932.576 | Y9: 11196.759 | Z9: 11466.152 | AA9: 11737.624 | AB9: 11980.952 | AC9: 12207.976 | AD9: 12424.898 | AE9: 12635.247 | AF9: 12841.464 | AG9: 13064.966 | AH9: 13299.98 | AI9: 13544.111 | AJ9: 13796.369 | AK9: 14056.085
A10: ia_sveh_2 | B10: 36313.187 | C10: 37180.585 | D10: 38123.586 | E10: 38988.948 | F10: 40018.192 | G10: 41417.452 | H10: 42785.056 | I10: 44105.358 | J10: 45392.159 | K10: 46663.711 | L10: 47931.975 | M10: 49303.988 | N10: 50789.489 | O10: 52364.572 | P10: 54007.812 | Q10: 55707.908 | R10: 57348.482 | S10: 58988.31 | T10: 60655.271 | U10: 62356.372 | V10: 64097.052 | W10: 65788.197 | X10: 67485.525 | Y10: 69207.755 | Z10: 70960.121 | AA10: 72737.27 | AB10: 74043.541 | AC10: 75159.523 | AD10: 76196.828 | AE10: 77196.517 | AF10: 78174.765 | AG10: 79452.348 | AH10: 80856.062 | AI10: 82318.937 | AJ10: 83817.856 | AK10: 84219.584
A11: ia_sveh_0 | B11: 36313.187 | C11: 37180.585 | D11: 38123.586 | E11: 38988.948 | F11: 40018.192 | G11: 41417.452 | H11: 42785.056 | I11: 44145.767 | J11: 45521.88 | K11: 46933.114 | L11: 48396.117 | M11: 49902.504 | N11: 51460.327 | O11: 53073.258 | P11: 54742.719 | Q11: 56469.456 | R11: 58147.394 | S11: 59834.179 | T11: 61553.024 | U11: 63312.639 | V11: 65114.06 | W11: 66856.734 | X11: 68598.89 | Y11: 70363.553 | Z11: 72159.099 | AA11: 73981.441 | AB11: 75325.519 | AC11: 76477.949 | AD11: 77553.484 | AE11: 78594.223 | AF11: 79616.331 | AG11: 80941.77 | AH11: 82394.254 | AI11: 83906.191 | AJ11: 85454.597 | AK11: 87031.934
A12: ia_sgla_2 | B12: 1452.9754 | C12: 1471.1499 | D12: 1486.4143 | E12: 1497.7457 | F12: 1513.6638 | G12: 1542.5955 | H12: 1574.7727 | I12: 1607.8636 | J12: 1639.6 | K12: 1668.8082 | L12: 1695.0592 | M12: 1723.0851 | N12: 1754.1604 | O12: 1788.9799 | P12: 1827.6346 | Q12: 1869.922 | R12: 1913.6861 | S12: 1959.2938 | T12: 2006.9721 | U12: 2056.9906 | V12: 2109.3502 | W12: 2163.1129 | X12: 2219.0742 | Y12: 2277.7162 | Z12: 2339.3155 | AA12: 2403.7766 | AB12: 2461.888 | AC12: 2515.8853 | AD12: 2567.576 | AE12: 2618.087 | AF12: 2668.0769 | AG12: 2722.7076 | AH12: 2780.4605 | AI12: 2840.5066 | AJ12: 2902.445 | AK12: 2923.2685
... A79: ia_ser_0 | B79: 219274.86 | C79: 222317.38 | D79: 224800.39 | E79: 226624.71 | F79: 229257.49 | G79: 233929.02 | H79: 238657.87 | I79: 243611.77 | J79: 248678.17 | K79: 253858.22 | L79: 259220.27 | M79: 264720.19 | N79: 270375.67 | O79: 276203.48 | P79: 282214.05 | Q79: 288414.66 | R79: 294647.42 | S79: 300978.32 | T79: 307449.64 | U79: 314084.56 | V79: 320869.7 | W79: 327676.52 | X79: 334578.86 | Y79: 341622.95 | Z79: 348834.92 | AA79: 356150.44 | AB79: 362709.51 | AC79: 368808.28 | AD79: 374667.29 | AE79: 380414.38 | AF79: 386125.06 | AG79: 392337.19 | AH79: 398905.08 | AI79: 405741.14 | AJ79: 412806.09 | AK79: 420080.04

Sheet Labor
A1: _date_ | B1: 42005 | C1: 42370 | D1: 42736 | E1: 43101 | F1: 43466 | G1: 43831 | H1: 44197 | I1: 44562 | J1: 44927 | K1: 45292 | L1: 45658 | M1: 46023 | N1: 46388 | O1: 46753 | P1: 47119 | Q1: 47484 | R1: 47849 | S1: 48214 | T1: 48580 | U1: 48945 | V1: 49310 | W1: 49675 | X1: 50041 | Y1: 50406 | Z1: 50771 | AA1: 51136 | AB1: 51502 | AC1: 51867 | AD1: 52232 | AE1: 52597 | AF1: 52963 | AG1: 53328 | AH1: 53693 | AI1: 54058 | AJ1: 54424 | AK1: 54789
A2: f_l_2 | B2: 27382.109 | C2: 27473.907 | D2: 27601.825 | E2: 27763.415 | F2: 27938.864 | G2: 28130.929 | H2: 28371.543 | I2: 28663.39 | J2: 29004.227 | K2: 29394.337 | L2: 29841.203 | M2: 30279.006 | N2: 30692.327 | O2: 31083.119 | P2: 31456.562 | Q2: 31817.304 | R2: 32155.7 | S2: 32477.756 | T2: 32788.331 | U2: 33093.546 | V2: 33393.499 | W2: 33671.047 | X2: 33930.704 | Y2: 34177.951 | Z2: 34417.376 | AA2: 34647.073 | AB2: 34778.678 | AC2: 34825.022 | AD2: 34807.48 | AE2: 34745.433 | AF2: 34653.818 | AG2: 34583.097 | AH2: 34532.157 | AI2: 34496.58 | AJ2: 34471.601 | AK2: 34455.375
A3: f_l_0 | B3: 27382.109 | C3: 27473.907 | D3: 27601.825 | E3: 27763.415 | F3: 27938.864 | G3: 28130.929 | H3: 28371.543 | I3: 28643.753 | J3: 28936.646 | K3: 29243.93 | L3: 29565.106 | M3: 29892.074 | N3: 30222 | O3: 30554.051 | P3: 30887.885 | Q3: 31223.281 | R3: 31543.224 | S3: 31850.25 | T3: 32147.377 | U3: 32437.227 | V3: 32719.975 | W3: 32983.275 | X3: 33231.92 | Y3: 33470.553 | Z3: 33703 | AA3: 33927.003 | AB3: 34058.323 | AC3: 34108.848 | AD3: 34097.918 | AE3: 34043.061 | AF3: 33957.958 | AG3: 33893.038 | AH3: 33847.255 | AI3: 33816.229 | AJ3: 33795.326 | AK3: 33780.327
A4: f_l_sagr_2 | B4: 732.65441 | C4: 734.30782 | D4: 738.01937 | E4: 745.34771 | F4: 753.23977 | G4: 758.26529 | H4: 765.19009 | I4: 774.95496 | J4: 787.98398 | K4: 804.62575 | L4: 825.50305 | M4: 846.14513 | N4: 865.13736 | O4: 882.32299 | P4: 897.93201 | Q4: 912.26454 | R4: 925.19471 | S4: 937.15421 | T4: 948.41794 | U4: 959.25862 | V4: 969.70631 | W4: 978.8908 | X4: 986.99033 | Y4: 994.24548 | Z4: 1000.8664 | AA4: 1006.7959 | AB4: 1009.0006 | AC4: 1008.2468 | AD4: 1005.3432 | AE4: 1000.9776 | AF4: 995.69209 | AG4: 991.41841 | AH4: 988.00279 | AI4: 985.26956 | AJ4: 983.05551 | AK4: 982.18291
A5: f_l_sagr_0 | B5: 732.65441 | C5: 734.30782 | D5: 738.01937 | E5: 745.34771 | F5: 753.23977 | G5: 758.26529 | H5: 765.19009 | I5: 773.43822 | J5: 782.64288 | K5: 792.53713 | L5: 803.04368 | M5: 813.84891 | N5: 824.80463 | O5: 835.81874 | P5: 846.83105 | Q5: 857.80222 | R5: 868.03184 | S5: 877.6472 | T5: 886.76716 | U5: 895.48658 | V5: 903.80369 | W5: 911.22913 | X5: 917.97611 | Y5: 924.21732 | Z5: 930.0831 | AA5: 935.46546 | AB5: 937.67328 | AC5: 937.39284 | AD5: 935.27217 | AE5: 931.84535 | AF5: 927.53809 | AG5: 924.22209 | AH5: 921.74136 | AI5: 919.91134 | AJ5: 918.56463 | AK5: 917.54969
A6: f_l_sfor_2 | B6: 29.065872 | C6: 28.739653 | D6: 28.273549 | E6: 27.780878 | F6: 27.331544 | G6: 26.888808 | H6: 26.603102 | I6: 26.366861 | J6: 26.136116 | K6: 25.896009 | L6: 25.65297 | M6: 25.527659 | N6: 25.515175 | O6: 25.5867 | P6: 25.714553 | Q6: 25.880288 | R6: 26.10664 | S6: 26.380374 | T6: 26.69076 | U6: 27.032784 | V6: 27.399864 | W6: 27.77965 | X6: 28.175759 | Y6: 28.593408 | Z6: 29.038676 | AA6: 29.507994 | AB6: 29.630111 | AC6: 29.473225 | AD6: 29.164009 | AE6: 28.79395 | AF6: 28.41321 | AG6: 28.074268 | AH6: 27.775251 | AI6: 27.507808 | AJ6: 27.263583 | AK6: 23.615454
A7: f_l_sfor_0 | B7: 29.065872 | C7: 28.739653 | D7: 28.273549 | E7: 27.780878 | F7: 27.331544 | G7: 26.888808 | H7: 26.603102 | I7: 26.433158 | J7: 26.342032 | K7: 26.304841 | L7: 26.313491 | M7: 26.342113 | N7: 26.385051 | O7: 26.446399 | P7: 26.530876 | Q7: 26.642292 | R7: 26.817178 | S7: 27.045881 | T7: 27.317177 | U7: 27.623593 | V7: 27.956704 | W7: 28.307606 | X7: 28.680174 | Y7: 29.078747 | Z7: 29.508296 | AA7: 29.964015 | AB7: 30.080166 | AC7: 29.920909 | AD7: 29.60914 | AE7: 29.234317 | AF7: 28.845857 | AG7: 28.497254 | AH7: 28.186782 | AI7: 27.905877 | AJ7: 27.646049 | AK7: 27.400695
A8: f_l_sfoo_2 | B8: 618.6912 | C8: 621.19864 | D8: 624.72512 | E8: 629.19505 | F8: 633.9425 | G8: 639.3507 | H8: 646.26381 | I8: 654.88792 | J8: 665.20754 | K8: 677.29562 | L8: 691.49695 | M8: 705.21529 | N8: 717.95237 | O8: 729.83453 | P8: 741.06863 | Q8: 751.81685 | R8: 761.87679 | S8: 771.42048 | T8: 780.55804 | U8: 789.44635 | V8: 798.05277 | W8: 805.85628 | X8: 812.98911 | Y8: 819.60248 | Z8: 825.82104 | AA8: 831.5276 | AB8: 834.68088 | AC8: 835.70181 | AD8: 835.07278 | AE8: 833.24764 | AF8: 830.61047 | AG8: 828.52586 | AH8: 826.97578 | AI8: 825.89307 | AJ8: 825.17958 | AK8: 824.72328
A9: f_l_sfoo_0 | B9: 618.6912 | C9: 621.19864 | D9: 624.72512 | E9: 629.19505 | F9: 633.9425 | G9: 639.3507 | H9: 646.26381 | I9: 654.07942 | J9: 662.43988 | K9: 671.15018 | L9: 680.2181 | M9: 689.41989 | N9: 698.67519 | O9: 707.94299 | P9: 717.19962 | Q9: 726.4311 | R9: 735.16139 | S9: 743.46456 | T9: 751.41219 | U9: 759.06856 | V9: 766.41349 | W9: 773.13526 | X9: 779.37204 | Y9: 785.23541 | Z9: 790.81573 | AA9: 795.98023 | AB9: 798.86546 | AC9: 799.86758 | AD9: 799.39017 | AE9: 797.80856 | AF9: 795.4482 | AG9: 793.66242 | AH9: 792.42064 | AI9: 791.6467 | AJ9: 791.24101 | AK9: 791.09302
A10: f_l_sveh_2 | B10: 185.82756 | C10: 188.06781 | D10: 191.49728 | E10: 195.59318 | F10: 200.00831 | G10: 204.38057 | H10: 208.58546 | I10: 212.8206 | J10: 217.36524 | K10: 222.42993 | L10: 228.15159 | M10: 234.12452 | N10: 240.07902 | O10: 245.82676 | P10: 251.29524 | Q10: 256.49897 | R10: 261.08996 | S10: 265.30623 | T10: 269.31037 | U10: 273.19072 | V10: 276.99777 | W10: 280.35925 | X10: 283.42501 | Y10: 286.28581 | Z10: 288.99924 | AA10: 291.58267 | AB10: 292.28547 | AC10: 291.83046 | AD10: 290.68065 | AE10: 289.11941 | AF10: 287.31692 | AG10: 286.36655 | AH10: 285.89846 | AI10: 285.68666 | AJ10: 285.6 | AK10: 285.57616
A11: f_l_sveh_0 | B11: 185.82756 | C11: 188.06781 | D11: 191.49728 | E11: 195.59318 | F11: 200.00831 | G11: 204.38057 | H11: 208.58546 | I11: 212.6476 | J11: 216.70973 | K11: 220.872 | L11: 225.19182 | M11: 229.62066 | N11: 234.1526 | O11: 238.77244 | P11: 243.46209 | Q11: 248.2045 | R11: 252.57081 | S11: 256.69841 | T11: 260.67226 | U11: 264.54277 | V11: 268.33229 | W11: 271.68728 | X11: 274.76362 | Y11: 277.65755 | Z11: 280.42691 | AA11: 283.0882 | AB11: 283.94855 | AC11: 283.69668 | AD11: 282.76628 | AE11: 281.41911 | AF11: 279.81172 | AG11: 279.0091 | AH11: 278.65952 | AI11: 278.54888 | AJ11: 278.55176 | AK11: 278.59555
A12: f_l_sgla_2 | B12: 98.063283 | C12: 98.706573 | D12: 99.670911 | E12: 100.74194 | F12: 101.66164 | G12: 102.40138 | H12: 103.32961 | I12: 104.53961 | J12: 106.0541 | K12: 107.88501 | L12: 110.07219 | M12: 112.19736 | N12: 114.14445 | O12: 115.92072 | P12: 117.56771 | Q12: 119.12679 | R12: 120.57199 | S12: 121.951 | T12: 123.29521 | U12: 124.63356 | V12: 125.97133 | W12: 127.20715 | X12: 128.36368 | Y12: 129.47209 | Z12: 130.56032 | AA12: 131.63613 | AB12: 132.23494 | AC12: 132.41057 | AD12: 132.26904 | AE12: 131.91357 | AF12: 131.42552 | AG12: 131.05232 | AH12: 130.77927 | AI12: 130.58218 | AJ12: 130.43857 | AK12: 130.32984
... A79: f_l_ser_0 | B79: 21276.537 | C79: 21344.021 | D79: 21432.381 | E79: 21539.466 | F79: 21659.41 | G79: 21805.293 | H79: 21984.851 | I79: 22184.547 | J79: 22396.126 | K79: 22615.45 | L79: 22842.974 | M79: 23073.564 | N79: 23305.555 | O79: 23538.292 | P79: 23771.392 | Q79: 24004.565 | R79: 24226.138 | S79: 24437.423 | T79: 24640.362 | U79: 24836.72 | V79: 25026.39 | W79: 25201.321 | X79: 25364.499 | Y79: 25518.976 | Z79: 25667.275 | AA79: 25807.145 | AB79: 25886.646 | AC79: 25912.909 | AD79: 25898.01 | AE79: 25853.179 | AF79: 25787.433 | AG79: 25734.737 | AH79: 25695.269 | AI79: 25666.302 | AJ79: 25644.702 | AK79: 25627.496

Sheet Final_nrj
A1: _date_ | B1: 42005 | C1: 42370 | D1: 42736 | E1: 43101 | F1: 43466 | G1: 43831 | H1: 44197 | I1: 44562 | J1: 44927 | K1: 45292 | L1: 45658 | M1: 46023 | N1: 46388 | O1: 46753 | P1: 47119 | Q1: 47484 | R1: 47849 | S1: 48214 | T1: 48580 | U1: 48945 | V1: 49310 | W1: 49675 | X1: 50041 | Y1: 50406 | Z1: 50771 | AA1: 51136 | AB1: 51502 | AC1: 51867 | AD1: 52232 | AE1: 52597 | AF1: 52963 | AG1: 53328 | AH1: 53693 | AI1: 54058 | AJ1: 54424 | AK1: 54789
A2: cf_toe_2 | B2: 161.84534 | C2: 162.93754 | D2: 162.61509 | E2: 161.58507 | F2: 162.06763 | G2: 165.12013 | H2: 167.50705 | I2: 169.63119 | J2: 171.27484 | K2: 172.38746 | L2: 172.99643 | M2: 174.23649 | N2: 176.10071 | O2: 178.4863 | P2: 181.27931 | Q2: 184.38985 | R2: 187.52498 | S2: 190.75906 | T2: 194.10374 | U2: 197.55962 | V2: 201.1057 | W2: 204.69231 | X2: 208.44159 | Y2: 212.36603 | Z2: 216.45994 | AA2: 220.64143 | AB2: 224.16194 | AC2: 227.58007 | AD2: 231.00285 | AE2: 234.45072 | AF2: 237.92451 | AG2: 241.96205 | AH2: 246.20534 | AI2: 250.57894 | AJ2: 255.0583 | AK2: 255.17088
A3: ch_toe_2 | B3: 64.30144 | C3: 64.087087 | D3: 63.145851 | E3: 62.135601 | F3: 61.774544 | G3: 62.010107 | H3: 61.823056 | I3: 61.650653 | J3: 61.39911 | K3: 61.055072 | L3: 60.64456 | M3: 60.517275 | N3: 60.555633 | O3: 60.68965 | P3: 60.873072 | Q3: 61.079234 | R3: 61.288976 | S3: 61.492741 | T3: 61.689365 | U3: 61.878707 | V3: 62.046141 | W3: 62.219025 | X3: 62.398496 | Y3: 62.581473 | Z3: 62.765574 | AA3: 62.901996 | AB3: 63.037931 | AC3: 63.167814 | AD3: 63.288003 | AE3: 63.396626 | AF3: 63.492998 | AG3: 63.58131 | AH3: 63.664403 | AI3: 63.743245 | AJ3: 63.818 | AK3: 63.924186
A4: ch_hous_toe_2 | B4: 42520877 | C4: 42551548 | D4: 41785133 | E4: 40943659 | F4: 40614444 | G4: 40631366 | H4: 40275258 | I4: 39934769 | J4: 39520877 | K4: 39023356 | L4: 38470867 | M4: 38168274 | N4: 37996448 | O4: 37896811 | P4: 37832677 | Q4: 37783845 | R4: 37740208 | S4: 37693702 | T4: 37642588 | U4: 37589865 | V4: 37520778 | W4: 37457478 | X4: 37402403 | Y4: 37353971 | Z4: 37311029 | AA4: 37230472 | AB4: 37163437 | AC4: 37106761 | AD4: 37056716 | AE4: 37010560 | AF4: 36966549 | AG4: 36922257 | AH4: 36879018 | AI4: 36837445 | AJ4: 36797574 | AK4: 36903760
A5: ch_auto_toe_2 | B5: 21780563 | C5: 21535539 | D5: 21360718 | E5: 21191942 | F5: 21160100 | G5: 21378742 | H5: 21547798 | I5: 21715884 | J5: 21878233 | K5: 22031716 | L5: 22173694 | M5: 22349001 | N5: 22559185 | O5: 22792838 | P5: 23040396 | Q5: 23295389 | R5: 23548768 | S5: 23799039 | T5: 24046777 | U5: 24288842 | V5: 24525364 | W5: 24761546 | X5: 24996094 | Y5: 25227502 | Z5: 25454545 | AA5: 25671524 | AB5: 25874494 | AC5: 26061053 | AD5: 26231287 | AE5: 26386066 | AF5: 26526449 | AG5: 26659053 | AH5: 26785384 | AI5: 26905800 | AJ5: 27020426 | AK5: 27020426
A6: cf_toe_0 | B6: 161.84534 | C6: 162.93754 | D6: 162.61509 | E6: 161.58507 | F6: 162.06763 | G6: 165.12013 | H6: 167.50705 | I6: 170.18661 | J6: 173.01173 | K6: 175.95053 | L6: 179.0471 | M6: 182.21712 | N6: 185.49504 | O6: 188.90065 | P6: 192.4458 | Q6: 196.13914 | R6: 199.80761 | S6: 203.58236 | T6: 207.49386 | U6: 211.55436 | V6: 215.74344 | W6: 219.92993 | X6: 224.23824 | Y6: 228.69497 | Z6: 233.31001 | AA6: 238.00836 | AB6: 241.92765 | AC6: 245.68929 | AD6: 249.42884 | AE6: 253.18434 | AF6: 256.968 | AG6: 261.33666 | AH6: 265.90238 | AI6: 270.58947 | AJ6: 275.37827 | AK6: 280.26017
A7: ch_toe_0 | B7: 64.30144 | C7: 64.087087 | D7: 63.145851 | E7: 62.135601 | F7: 61.774544 | G7: 62.010107 | H7: 61.823056 | I7: 61.826135 | J7: 61.906119 | K7: 62.023991 | L7: 62.190572 | M7: 62.354583 | N7: 62.523056 | O7: 62.699007 | P7: 62.883492 | Q7: 63.076756 | R7: 63.277374 | S7: 63.484666 | T7: 63.698257 | U7: 63.917986 | V7: 64.125826 | W7: 64.348494 | X7: 64.580062 | Y7: 64.817832 | Z7: 65.060659 | AA7: 65.258558 | AB7: 65.458706 | AC7: 65.655011 | AD7: 65.844914 | AE7: 66.027705 | AF7: 66.203354 | AG7: 66.375221 | AH7: 66.545433 | AI7: 66.714907 | AJ7: 66.88393 | AK7: 67.052469
A8: ch_hous_toe_0 | B8: 42520877 | C8: 42551548 | D8: 41785133 | E8: 40943659 | F8: 40614444 | G8: 40631366 | H8: 40275258 | I8: 40095735 | J8: 39980641 | K8: 39892370 | L8: 39839697 | M8: 39775958 | N8: 39708999 | O8: 39642842 | P8: 39579588 | Q8: 39520390 | R8: 39466250 | S8: 39417355 | T8: 39373665 | U8: 39335142 | V8: 39285533 | W8: 39250762 | X8: 39225308 | Y8: 39206284 | Z8: 39192278 | AA8: 39137972 | AB8: 39094804 | AC8: 39058264 | AD8: 39025054 | AE8: 38993325 | AF8: 38961992 | AG8: 38929191 | AH8: 38895534 | AI8: 38861486 | AJ8: 38827207 | AK8: 38792747
A9: ch_auto_toe_0 | B9: 21780563 | C9: 21535539 | D9: 21360718 | E9: 21191942 | F9: 21160100 | G9: 21378742 | H9: 21547798 | I9: 21730400 | J9: 21925477 | K9: 22131621 | L9: 22350875 | M9: 22578625 | N9: 22814057 | O9: 23056165 | P9: 23303903 | Q9: 23556366 | R9: 23811124 | S9: 24067311 | T9: 24324593 | U9: 24582844 | V9: 24840293 | W9: 25097732 | X9: 25354754 | Y9: 25611549 | Z9: 25868381 | AA9: 26120586 | AB9: 26363901 | AC9: 26596748 | AD9: 26819860 | AE9: 27034380 | AF9: 27241361 | AG9: 27446030 | AH9: 27649898 | AI9: 27853421 | AJ9: 28056722 | AK9: 28259722
A10: cf_toe_ccoa_2 | B10: 5.4375075 | C10: 5.309642 | D10: 5.1957812 | E10: 5.1540109 | F10: 5.1631627 | G10: 5.2550689 | H10: 5.373918 | I10: 5.4820674 | J10: 5.5672436 | K10: 5.6244007 | L10: 5.6507325 | M10: 5.7067552 | N10: 5.7943915 | O10: 5.9094653 | P10: 6.047353 | Q10: 6.2042542 | R10: 6.3617402 | S10: 6.5264125 | T10: 6.6993842 | U10: 6.8812542 | V10: 7.0718602 | W10: 7.2663251 | X10: 7.4724914 | Y10: 7.691346 | Z10: 7.9227407 | AA10: 8.1657141 | AB10: 8.3654754 | AC10: 8.5607725 | AD10: 8.759249 | AE10: 8.9622945 | AF10: 9.1698415 | AG10: 9.4189218 | AH10: 9.6834766 | AI10: 9.957734 | AJ10: 10.239897 | AK10: 10.237031
A11: cf_toe_ccoa_0 | B11: 5.4375075 | C11: 5.309642 | D11: 5.1957812 | E11: 5.1540109 | F11: 5.1631627 | G11: 5.2550689 | H11: 5.373918 | I11: 5.5090331 | J11: 5.6538901 | K11: 5.8071915 | L11: 5.9693167 | M11: 6.1382576 | N11: 6.3151701 | O11: 6.5007372 | P11: 6.695436 | Q11: 6.8996791 | R11: 7.1014304 | S11: 7.3100453 | T11: 7.5276493 | U11: 7.7549813 | V11: 7.9921952 | W11: 8.2275936 | X11: 8.470516 | Y11: 8.7230906 | Z11: 8.9860657 | AA11: 9.2589951 | AB11: 9.4765544 | AC11: 9.6836147 | AD11: 9.890142 | AE11: 10.098736 | AF11: 10.310069 | AG11: 10.563089 | AH11: 10.829075 | AI11: 11.102214 | AJ11: 11.381134 | AK11: 11.665406
A12: cf_toe_ccoi_2 | B12: 0.084442038 | C12: 0.086397798 | D12: 0.086957266 | E12: 0.086216758 | F12: 0.08667557 | G12: 0.090389272 | H12: 0.092584884 | I12: 0.094510867 | J12: 0.095999796 | K12: 0.097017012 | L12: 0.097563915 | M12: 0.098596671 | N12: 0.10015403 | O12: 0.10217054 | P12: 0.10456529 | Q12: 0.10727118 | R12: 0.11002446 | S12: 0.11290133 | T12: 0.1159146 | U12: 0.1190744 | V12: 0.12237547 | W12: 0.12577879 | X12: 0.12938458 | Y12: 0.13320319 | Z12: 0.13723116 | AA12: 0.14143855 | AB12: 0.14511254 | AC12: 0.148748 | AD12: 0.15243901 | AE12: 0.15620581 | AF12: 0.16005113 | AG12: 0.16448962 | AH12: 0.1691889 | AI12: 0.1740779 | AJ12: 0.17913134 | AK12: 0.17200514
... A737: ci_toe_cfuel_ser_0 | B737: 2.8654882 | C737: 2.8967075 | D737: 2.9278608 | E737: 2.9597623 | F737: 2.9926616 | G737: 3.0265472 | H737: 3.0613249 | I737: 3.0968928 | J737: 3.1331649 | K737: 3.170076 | L737: 3.2075792 | M737: 3.2456425 | N737: 3.2842451 | O737: 3.3233755 | P737: 3.363028 | Q737: 3.4032016 | R737: 3.443898 | S737: 3.4851202 | T737: 3.5268716 | U737: 3.5691552 | V737: 3.6119734 | W737: 3.6553275 | X737: 3.6992182 | Y737: 3.7436452 | Z737: 3.7886078 | AA737: 3.8341054 | AB737: 3.8801368 | AC737: 3.9267016 | AD737: 3.9737996 | AE737: 4.021431 | AF737: 4.0695968 | AG737: 4.1182989 | AH737: 4.1675396 | AI737: 4.2173221 | AJ737: 4.2676504 | AK737: 4.3185291

Sheet Primary_nrj
A1: _date_ | B1: 42005 | C1: 42370 | D1: 42736 | E1: 43101 | F1: 43466 | G1: 43831 | H1: 44197 | I1: 44562 | J1: 44927 | K1: 45292 | L1: 45658 | M1: 46023 | N1: 46388 | O1: 46753 | P1: 47119 | Q1: 47484 | R1: 47849 | S1: 48214 | T1: 48580 | U1: 48945 | V1: 49310 | W1: 49675 | X1: 50041 | Y1: 50406 | Z1: 50771 | AA1: 51136 | AB1: 51502 | AC1: 51867 | AD1: 52232 | AE1: 52597 | AF1: 52963 | AG1: 53328 | AH1: 53693 | AI1: 54058 | AJ1: 54424 | AK1: 54789
A2: yg_toe_2 | B2: 148.40948 | C2: 149.34171 | D2: 150.0338 | E2: 150.4657 | F2: 151.23595 | G2: 152.84635 | H2: 156.58272 | I2: 160.66652 | J2: 164.79313 | K2: 168.8767 | L2: 172.90459 | M2: 176.62235 | N2: 180.68208 | O2: 185.26794 | P2: 190.39614 | Q2: 196.05076 | R2: 202.10658 | S2: 208.63111 | T2: 215.63029 | U2: 223.68147 | V2: 232.31507 | W2: 241.49568 | X2: 251.50294 | Y2: 262.48225 | Z2: 274.57188 | AA2: 287.84541 | AB2: 294.28434 | AC2: 298.96454 | AD2: 303.42174 | AE2: 308.04377 | AF2: 312.87438 | AG2: 318.57398 | AH2: 324.61366 | AI2: 330.84707 | AJ2: 337.2004 | AK2: 337.91644
A3: yg_toe_0 | B3: 148.40947 | C3: 149.34171 | D3: 150.0338 | E3: 150.4657 | F3: 151.23595 | G3: 152.84635 | H3: 156.58272 | I3: 160.81919 | J3: 165.35262 | K3: 170.15432 | L3: 175.28695 | M3: 180.15734 | N3: 185.19622 | O3: 190.55357 | P3: 196.28639 | Q3: 202.43214 | R3: 208.99939 | S3: 216.05584 | T3: 223.62996 | U3: 231.76867 | V3: 240.50853 | W3: 249.74517 | X3: 259.71728 | Y3: 270.55867 | Z3: 282.40788 | AA3: 295.3433 | AB3: 301.02595 | AC3: 304.68304 | AD3: 307.94114 | AE3: 311.24542 | AF3: 314.68291 | AG3: 318.95014 | AH3: 323.52264 | AI3: 328.27661 | AJ3: 333.16462 | AK3: 338.16617
A4: yg_toe_ccoa_2 | B4: 2.3808766 | C4: 2.2622534 | D4: 2.183104 | E4: 2.1653971 | F4: 2.1609971 | G4: 2.159258 | H4: 2.2421332 | I4: 2.3290858 | J4: 2.4130448 | K4: 2.4922242 | L4: 2.5647903 | M4: 2.5802567 | N4: 2.6031251 | O4: 2.6351612 | P4: 2.6746027 | Q4: 2.7197143 | R4: 2.755536 | S4: 2.7904612 | T4: 2.8257033 | U4: 2.8421521 | V4: 2.8596981 | W4: 2.8728264 | X4: 2.8837485 | Y4: 2.8924115 | Z4: 2.8982953 | AA4: 2.9007895 | AB4: 2.912238 | AC4: 2.9276209 | AD4: 2.9431333 | AE4: 2.9577989 | AF4: 2.9718379 | AG4: 2.9984912 | AH4: 3.0294971 | AI4: 3.0636299 | AJ4: 3.1010745 | AK4: 3.0975253
A5: yg_toe_ccoa_0 | B5: 2.3808766 | C5: 2.2622534 | D5: 2.183104 | E5: 2.1653971 | F5: 2.1609971 | G5: 2.159258 | H5: 2.2421332 | I5: 2.3395592 | J5: 2.4466687 | K5: 2.5633119 | L5: 2.6904344 | M5: 2.7509226 | N5: 2.8093688 | O5: 2.8696683 | P5: 2.9321296 | Q5: 2.9966837 | R5: 3.0529844 | S5: 3.1089095 | T5: 3.1658114 | U5: 3.2238959 | V5: 3.283099 | W5: 3.3387944 | X5: 3.3941529 | Y5: 3.4496526 | Z5: 3.5051045 | AA5: 3.5599705 | AB5: 3.6244613 | AC5: 3.6941333 | AD5: 3.7653037 | AE5: 3.836841 | AF5: 3.908592 | AG5: 3.9945991 | AH5: 4.0846705 | AI5: 4.1767383 | AJ5: 4.2704218 | AK5: 4.3656566
A6: yg_toe_ccoi_2 | B6: 1.0948709 | C6: 1.1043267 | D6: 1.1091211 | E6: 1.1082636 | F6: 1.1112959 | G6: 1.1252977 | H6: 1.1426121 | I6: 1.1611912 | J6: 1.178702 | K6: 1.1942376 | L6: 1.2063148 | M6: 1.2198125 | N6: 1.2359785 | O6: 1.2548682 | P6: 1.2761283 | Q6: 1.2993637 | R6: 1.3200016 | S6: 1.3406542 | T6: 1.3617044 | U6: 1.3637386 | V6: 1.3668816 | W6: 1.366976 | X6: 1.3645197 | Y6: 1.3596503 | Z6: 1.3524077 | AA6: 1.3427174 | AB6: 1.3233392 | AC6: 1.2992334 | AD6: 1.2724985 | AE6: 1.2441086 | AF6: 1.2147703 | AG6: 1.1883513 | AH6: 1.1634411 | AI6: 1.1401286 | AJ6: 1.1189031 | AK6: 1.1125833
A7: yg_toe_ccoi_0 | B7: 1.0948709 | C7: 1.1043267 | D7: 1.1091211 | E7: 1.1082636 | F7: 1.1112959 | G7: 1.1252977 | H7: 1.1426121 | I7: 1.162854 | J7: 1.1845383 | K7: 1.2072338 | L7: 1.2309712 | M7: 1.2553513 | N7: 1.2805009 | O7: 1.3066179 | P7: 1.3338099 | Q7: 1.3621474 | R7: 1.3901674 | S7: 1.4190615 | T7: 1.4491188 | U7: 1.4804028 | V7: 1.5128725 | W7: 1.5454149 | X7: 1.5788798 | Y7: 1.6135635 | Z7: 1.649608 | AA7: 1.6869042 | AB7: 1.7156152 | AC7: 1.7411893 | AD7: 1.7659677 | AE7: 1.7906984 | AF7: 1.8155816 | AG7: 1.8445683 | AH7: 1.8751542 | AI7: 1.9065845 | AJ7: 1.9386593 | AK7: 1.9713102
A8: yg_toe_cfut_2 | B8: 42.295972 | C8: 42.432119 | D8: 42.627777 | E8: 42.754462 | F8: 42.87116 | G8: 43.053382 | H8: 43.636145 | I8: 44.122338 | J8: 44.502381 | K8: 44.754231 | L8: 44.860719 | M8: 45.201108 | N8: 45.647236 | O8: 46.184511 | P8: 46.795946 | Q8: 47.464658 | R8: 48.054516 | S8: 48.671189 | T8: 49.315481 | U8: 50.594818 | V8: 51.919438 | W8: 53.334926 | X8: 54.876153 | Y8: 56.553789 | Z8: 58.371478 | AA8: 60.321065 | AB8: 62.227829 | AC8: 64.183221 | AD8: 66.198036 | AE8: 68.258537 | AF8: 70.341708 | AG8: 72.529339 | AH8: 74.737184 | AI8: 76.924009 | AJ8: 79.060851 | AK8: 79.044563
A9: yg_toe_cfut_0 | B9: 42.295972 | C9: 42.432119 | D9: 42.627777 | E9: 42.754462 | F9: 42.87116 | G9: 43.053382 | H9: 43.636145 | I9: 44.198572 | J9: 44.758306 | K9: 45.312038 | L9: 45.863787 | M9: 46.609715 | N9: 47.386329 | O9: 48.18464 | P9: 49.00534 | Q9: 49.849618 | R9: 50.605475 | S9: 51.395386 | T9: 52.224769 | U9: 53.088993 | V9: 53.981938 | W9: 54.876304 | X9: 55.789353 | Y9: 56.72481 | Z9: 57.684118 | AA9: 58.660737 | AB9: 59.473765 | AC9: 60.234906 | AD9: 60.976321 | AE9: 61.709095 | AF9: 62.437972 | AG9: 63.253105 | AH9: 64.098419 | AI9: 64.961924 | AJ9: 65.840362 | AK9: 66.732183
A10: yg_toe_cfuh_2 | B10: 7.9231223 | C10: 8.0390968 | D10: 8.0198843 | E10: 7.8810981 | F10: 7.8535874 | G10: 8.0365217 | H10: 8.1104827 | I10: 8.1927378 | J10: 8.2598364 | K10: 8.3031903 | L10: 8.3192312 | M10: 8.369274 | N10: 8.4489527 | O10: 8.5524734 | P10: 8.6747208 | Q10: 8.8118616 | R10: 8.9521294 | S10: 9.0978929 | T10: 9.2494763 | U10: 9.4054704 | V10: 9.5653255 | W10: 9.7283849 | X10: 9.8987022 | Y10: 10.076517 | Z10: 10.261334 | AA10: 10.448767 | AB10: 10.609474 | AC10: 10.763706 | AD10: 10.915922 | AE10: 11.067177 | AF10: 11.217671 | AG10: 11.389138 | AH10: 11.568284 | AI10: 11.751942 | AJ10: 11.939047 | AK10: 11.946789
A11: yg_toe_cfuh_0 | B11: 7.9231223 | C11: 8.0390968 | D11: 8.0198843 | E11: 7.8810981 | F11: 7.8535874 | G11: 8.0365217 | H11: 8.1104827 | I11: 8.2130945 | J11: 8.3283907 | K11: 8.4510011 | L11: 8.5814808 | M11: 8.7156655 | N11: 8.8548486 | O11: 8.9999898 | P11: 9.1517569 | Q11: 9.3106536 | R11: 9.4702555 | S11: 9.6353177 | T11: 9.8070341 | U11: 9.9858743 | V11: 10.170724 | W11: 10.357024 | X11: 10.549163 | Y11: 10.748161 | Z11: 10.954416 | AA11: 11.164151 | AB11: 11.343569 | AC11: 11.515462 | AD11: 11.685664 | AE11: 11.856099 | AF11: 12.02751 | AG11: 12.221825 | AH11: 12.424803 | AI11: 12.63326 | AJ11: 12.846227 | AK11: 13.063209
A12: yg_toe_cgas_2 | B12: 6.5977296 | C12: 6.5225731 | D12: 6.5225731 | E12: 6.5225731 | F12: 6.5225731 | G12: 6.5225731 | H12: 6.5225731 | I12: 6.5225731 | J12: 6.5225731 | K12: 6.5225731 | L12: 6.4952143 | M12: 6.4667413 | N12: 6.4373235 | O12: 6.4070879 | P12: 6.3762009 | Q12: 6.3448731 | R12: 6.2541215 | S12: 6.1555841 | T12: 6.0504965 | U12: 5.9408334 | V12: 5.8293604 | W12: 5.7195806 | X12: 5.6155466 | Y12: 5.5215288 | Z12: 5.4415777 | AA12: 5.3790552 | AB12: 5.3362386 | AC12: 5.3140892 | AD12: 5.3122307 | AE12: 5.3291266 | AF12: 5.3623918 | AG12: 5.4091553 | AH12: 5.4663988 | AI12: 5.5312229 | AJ12: 5.6010234 | AK12: 5.6735834
... A73: yg_toe_cote_spub_0 | B73: 1.2264258 | C73: 1.2460605 | D73: 1.2652906 | E73: 1.2804091 | F73: 1.2970729 | G73: 1.3230078 | H73: 1.3637104 | I73: 1.4070979 | J73: 1.4523302 | K73: 1.49933 | L73: 1.5484474 | M73: 1.5976625 | N73: 1.6486147 | O73: 1.7019967 | P73: 1.758146 | Q73: 1.8173099 | R73: 1.8779052 | S73: 1.9418735 | T73: 2.009314 | U73: 2.0803328 | V73: 2.1549717 | W73: 2.2298041 | X73: 2.3081507 | Y73: 2.3906039 | Z73: 2.4776374 | AA73: 2.5694499 | AB73: 2.6205526 | AC73: 2.6620273 | AD73: 2.7016079 | AE73: 2.7415033 | AF73: 2.7821949 | AG73: 2.8351638 | AH73: 2.8907819 | AI73: 2.9479996 | AJ73: 3.006514 | AK73: 3.0662087

Sheet Energy_Mix
A1: _date_ | B1: 42005 | C1: 42370 | D1: 42736 | E1: 43101 | F1: 43466 | G1: 43831 | H1: 44197 | I1: 44562 | J1: 44927 | K1: 45292 | L1: 45658 | M1: 46023 | N1: 46388 | O1: 46753 | P1: 47119 | Q1: 47484 | R1: 47849 | S1: 48214 | T1: 48580 | U1: 48945 | V1: 49310 | W1: 49675 | X1: 50041 | Y1: 50406 | Z1: 50771 | AA1: 51136 | AB1: 51502 | AC1: 51867 | AD1: 52232 | AE1: 52597 | AF1: 52963 | AG1: 53328 | AH1: 53693 | AI1: 54058 | AJ1: 54424 | AK1: 54789
A2: phiy_ccoa_smin_2 | B2: 0.20069089 | C2: 0.20069089 | D2: 0.20069089 | E2: 0.20069089 | F2: 0.20069089 | G2: 0.20069089 | H2: 0.20069089 | I2: 0.20069089 | J2: 0.20069089 | K2: 0.20069089 | L2: 0.20069089 | M2: 0.20069089 | N2: 0.20069089 | O2: 0.20069089 | P2: 0.20069089 | Q2: 0.20069089 | R2: 0.20069089 | S2: 0.20069089 | T2: 0.20069089 | U2: 0.20069089 | V2: 0.20069089 | W2: 0.20069089 | X2: 0.20069089 | Y2: 0.20069089 | Z2: 0.20069089 | AA2: 0.20069089 | AB2: 0.20069089 | AC2: 0.20069089 | AD2: 0.20069089 | AE2: 0.20069089 | AF2: 0.20069089 | AG2: 0.20069089 | AH2: 0.20069089 | AI2: 0.20069089 | AJ2: 0.20069089 | AK2: 0.20069089
A3: phiy_ccoa_soil_2 | B3: 0.79930911 | C3: 0.79930911 | D3: 0.79930911 | E3: 0.79930911 | F3: 0.79930911 | G3: 0.79930911 | H3: 0.79930911 | I3: 0.79930911 | J3: 0.79930911 | K3: 0.79930911 | L3: 0.79930911 | M3: 0.79930911 | N3: 0.79930911 | O3: 0.79930911 | P3: 0.79930911 | Q3: 0.79930911 | R3: 0.79930911 | S3: 0.79930911 | T3: 0.79930911 | U3: 0.79930911 | V3: 0.79930911 | W3: 0.79930911 | X3: 0.79930911 | Y3: 0.79930911 | Z3: 0.79930911 | AA3: 0.79930911 | AB3: 0.79930911 | AC3: 0.79930911 | AD3: 0.79930911 | AE3: 0.79930911 | AF3: 0.79930911 | AG3: 0.79930911 | AH3: 0.79930911 | AI3: 0.79930911 | AJ3: 0.79930911 | AK3: 0.79930911
A4: phiy_ccoi_smin_2 | B4: 0.7836667 | C4: 0.7836667 | D4: 0.7836667 | E4: 0.7836667 | F4: 0.7836667 | G4: 0.7836667 | H4: 0.7836667 | I4: 0.7836667 | J4: 0.7836667 | K4: 0.7836667 | L4: 0.7836667 | M4: 0.7836667 | N4: 0.7836667 | O4: 0.7836667 | P4: 0.7836667 | Q4: 0.7836667 | R4: 0.7836667 | S4: 0.7836667 | T4: 0.7836667 | U4: 0.7836667 | V4: 0.7836667 | W4: 0.7836667 | X4: 0.7836667 | Y4: 0.7836667 | Z4: 0.7836667 | AA4: 0.7836667 | AB4: 0.7836667 | AC4: 0.7836667 | AD4: 0.7836667 | AE4: 0.7836667 | AF4: 0.7836667 | AG4: 0.7836667 | AH4: 0.7836667 | AI4: 0.7836667 | AJ4: 0.7836667 | AK4: 0.7836667
A5: phiy_ccoi_soil_2 | B5: 0.2163333 | C5: 0.2163333 | D5: 0.2163333 | E5: 0.2163333 | F5: 0.2163333 | G5: 0.2163333 | H5: 0.2163333 | I5: 0.2163333 | J5: 0.2163333 | K5: 0.2163333 | L5: 0.2163333 | M5: 0.2163333 | N5: 0.2163333 | O5: 0.2163333 | P5: 0.2163333 | Q5: 0.2163333 | R5: 0.2163333 | S5: 0.2163333 | T5: 0.2163333 | U5: 0.2163333 | V5: 0.2163333 | W5: 0.2163333 | X5: 0.2163333 | Y5: 0.2163333 | Z5: 0.2163333 | AA5: 0.2163333 | AB5: 0.2163333 | AC5: 0.2163333 | AD5: 0.2163333 | AE5: 0.2163333 | AF5: 0.2163333 | AG5: 0.2163333 | AH5: 0.2163333 | AI5: 0.2163333 | AJ5: 0.2163333 | AK5: 0.2163333
A6: phiy_cfut_soil_2 | B6: 0.83809636 | C6: 0.83809636 | D6: 0.83809636 | E6: 0.83809636 | F6: 0.83809636 | G6: 0.83809636 | H6: 0.83809636 | I6: 0.83809636 | J6: 0.83809636 | K6: 0.83809636 | L6: 0.83809636 | M6: 0.83809636 | N6: 0.83809636 | O6: 0.83809636 | P6: 0.83809636 | Q6: 0.83809636 | R6: 0.83809636 | S6: 0.83809636 | T6: 0.83809636 | U6: 0.80375697 | V6: 0.77343167 | W6: 0.73993648 | X6: 0.70338849 | Y6: 0.66403632 | Z6: 0.62226696 | AA6: 0.57860006 | AB6: 0.53366818 | AC6: 0.48818333 | AD6: 0.44289332 | AE6: 0.39853329 | AF6: 0.35577891 | AG6: 0.31520749 | AH6: 0.27727137 | AI6: 0.24228558 | AJ6: 0.21042895 | AK6: 0.1817562
A7: phiy_cfut_sbfu_2 | B7: 0.16190364 | C7: 0.16190364 | D7: 0.16190364 | E7: 0.16190364 | F7: 0.16190364 | G7: 0.16190364 | H7: 0.16190364 | I7: 0.16190364 | J7: 0.16190364 | K7: 0.16190364 | L7: 0.16190364 | M7: 0.16190364 | N7: 0.16190364 | O7: 0.16190364 | P7: 0.16190364 | Q7: 0.16190364 | R7: 0.16190364 | S7: 0.16190364 | T7: 0.16190364 | U7: 0.19624303 | V7: 0.22656833 | W7: 0.26006352 | X7: 0.29661151 | Y7: 0.33596368 | Z7: 0.37773304 | AA7: 0.42139994 | AB7: 0.46633182 | AC7: 0.51181667 | AD7: 0.55710668 | AE7: 0.60146671 | AF7: 0.64422109 | AG7: 0.68479251 | AH7: 0.72272863 | AI7: 0.75771442 | AJ7: 0.78957105 | AK7: 0.8182438
A8: phiy_cfuh_soil_2 | B8: 1 | C8: 1 | D8: 1 | E8: 1 | F8: 1 | G8: 1 | H8: 1 | I8: 1 | J8: 1 | K8: 1 | L8: 1 | M8: 1 | N8: 1 | O8: 1 | P8: 1 | Q8: 1 | R8: 1 | S8: 1 | T8: 1 | U8: 1 | V8: 1 | W8: 1 | X8: 1 | Y8: 1 | Z8: 1 | AA8: 1 | AB8: 1 | AC8: 1 | AD8: 1 | AE8: 1 | AF8: 1 | AG8: 1 | AH8: 1 | AI8: 1 | AJ8: 1 | AK8: 1
A9: phiy_cgas_smet_2 | B9: 8.2704787e-05 | C9: 8.2704787e-05 | D9: 8.2704787e-05 | E9: 8.2704787e-05 | F9: 8.2704787e-05 | G9: 8.2704787e-05 | H9: 8.2704787e-05 | I9: 8.2704787e-05 | J9: 8.2704787e-05 | K9: 8.2704787e-05 | L9: 8.1496031e-05 | M9: 8.0244872e-05 | N9: 7.8959457e-05 | O9: 7.764593e-05 | P9: 7.6312009e-05 | Q9: 7.4967143e-05 | R9: 7.11166e-05 | S9: 6.7010422e-05 | T9: 6.2714631e-05 | U9: 5.832088e-05 | V9: 5.394506e-05 | W9: 4.9722156e-05 | X9: 4.5797128e-05 | Y9: 4.2312572e-05 | Z9: 3.9394956e-05 | AA9: 3.7141942e-05 | AB9: 3.5613278e-05 | AC9: 3.4826977e-05 | AD9: 3.476114e-05 | AE9: 3.536047e-05 | AF9: 3.6545649e-05 | AG9: 3.8223506e-05 | AH9: 4.0296315e-05 | AI9: 4.2669162e-05 | AJ9: 4.5255021e-05 | AK9: 4.7977666e-05
A10: phiy_cgas_soil_2 | B10: 0.64531662 | C10: 0.64531662 | D10: 0.64531662 | E10: 0.64531662 | F10: 0.64531662 | G10: 0.64531662 | H10: 0.64531662 | I10: 0.64531662 | J10: 0.64531662 | K10: 0.64531662 | L10: 0.63588512 | M10: 0.62612276 | N10: 0.61609312 | O10: 0.60584412 | P10: 0.595436 | Q10: 0.58494249 | R10: 0.55489804 | S10: 0.52285896 | T10: 0.48934041 | U10: 0.4550575 | V10: 0.4209145 | W10: 0.38796465 | X10: 0.35733903 | Y10: 0.33015025 | Z10: 0.30738511 | AA10: 0.28980562 | AB10: 0.27787799 | AC10: 0.27174276 | AD10: 0.27122906 | AE10: 0.27590542 | AF10: 0.28515296 | AG10: 0.29824469 | AH10: 0.3144181 | AI10: 0.3329326 | AJ10: 0.35310915 | AK10: 0.37435301
A11: phiy_cgas_sgas_2 | B11: 0.14751433 | C11: 0.14751433 | D11: 0.14751433 | E11: 0.14751433 | F11: 0.14751433 | G11: 0.14751433 | H11: 0.14751433 | I11: 0.14751433 | J11: 0.14751433 | K11: 0.14751433 | L11: 0.14535836 | M11: 0.14312676 | N11: 0.14083407 | O11: 0.13849123 | P11: 0.13611201 | Q11: 0.13371328 | R11: 0.12684535 | S11: 0.11952147 | T11: 0.11185939 | U11: 0.10402258 | V11: 0.096217761 | W11: 0.088685684 | X11: 0.081684906 | Y11: 0.075469765 | Z11: 0.070265832 | AA11: 0.066247298 | AB11: 0.063520735 | AC11: 0.06211827 | AD11: 0.062000841 | AE11: 0.063069821 | AF11: 0.065183735 | AG11: 0.068176402 | AH11: 0.071873517 | AI11: 0.076105787 | AJ11: 0.08071799 | AK11: 0.085574168
A12: phiy_cgas_sbga_2 | B12: 0.20708634 | C12: 0.20708634 | D12: 0.20708634 | E12: 0.20708634 | F12: 0.20708634 | G12: 0.20708634 | H12: 0.20708634 | I12: 0.20708634 | J12: 0.20708634 | K12: 0.20708634 | L12: 0.21867502 | M12: 0.23067023 | N12: 0.24299386 | O12: 0.255587 | P12: 0.26837567 | Q12: 0.28126927 | R12: 0.31818549 | S12: 0.35755256 | T12: 0.39873749 | U12: 0.4408616 | V12: 0.4828138 | W12: 0.52329994 | X12: 0.56093027 | Y12: 0.59433767 | Z12: 0.62230966 | AA12: 0.64390994 | AB12: 0.65856566 | AC12: 0.66610414 | AD12: 0.66673534 | AE12: 0.66098939 | AF12: 0.64962676 | AG12: 0.63354068 | AH12: 0.61366809 | AI12: 0.59091895 | AJ12: 0.5661276 | AK12: 0.54002485
... A51: phiy_cote_spub_0 | B51: 0.00010273909 | C51: 0.00010273909 | D51: 0.00010273909 | E51: 0.00010273909 | F51: 0.00010273909 | G51: 0.00010273909 | H51: 0.00010273909 | I51: 0.00010273909 | J51: 0.00010273909 | K51: 0.00010273909 | L51: 0.00010273909 | M51: 0.00010273909 | N51: 0.00010273909 | O51: 0.00010273909 | P51: 0.00010273909 | Q51: 0.00010273909 | R51: 0.00010273909 | S51: 0.00010273909 | T51: 0.00010273909 | U51: 0.00010273909 | V51: 0.00010273909 | W51: 0.00010273909 | X51: 0.00010273909 | Y51: 0.00010273909 | Z51: 0.00010273909 | AA51: 0.00010273909 | AB51: 0.00010273909 | AC51: 0.00010273909 | AD51: 0.00010273909 | AE51: 0.00010273909 | AF51: 0.00010273909 | AG51: 0.00010273909 | AH51: 0.00010273909 | AI51: 0.00010273909 | AJ51: 0.00010273909 | AK51: 0.00010273909

Sheet Transports
A1: _date_ | B1: 42005 | C1: 42370 | D1: 42736 | E1: 43101 | F1: 43466 | G1: 43831 | H1: 44197 | I1: 44562 | J1: 44927 | K1: 45292 | L1: 45658 | M1: 46023 | N1: 46388 | O1: 46753 | P1: 47119 | Q1: 47484 | R1: 47849 | S1: 48214 | T1: 48580 | U1: 48945 | V1: 49310 | W1: 49675 | X1: 50041 | Y1: 50406 | Z1: 50771 | AA1: 51136 | AB1: 51502 | AC1: 51867 | AD1: 52232 | AE1: 52597 | AF1: 52963 | AG1: 53328 | AH1: 53693 | AI1: 54058 | AJ1: 54424 | AK1: 54789
A2: km_traveler_cair_2 | B2: 291099.78 | C2: 298959.77 | D2: 301692.19 | E2: 301298.14 | F2: 307478.48 | G2: 324949.61 | H2: 334184.41 | I2: 343483.53 | J2: 351441.92 | K2: 358412.49 | L2: 364846.21 | M2: 372665.96 | N2: 384155 | O2: 397675.09 | P2: 412370.72 | Q2: 427831.18 | R2: 443433.31 | S2: 459073.71 | T2: 474950.67 | U2: 491226.77 | V2: 507688.9 | W2: 524849.75 | X2: 542718.14 | Y2: 561163.67 | Z2: 580126.64 | AA2: 598700.05 | AB2: 616359.09 | AC2: 633226.44 | AD2: 649517.28 | AE2: 665412.1 | AF2: 681072.01 | AG2: 697713.49 | AH2: 715268.13 | AI2: 733603.3 | AJ2: 752624.55 | AK2: 752624.55
A3: km_trav_auto_ld_2+km_trav_auto_sd_2 | B3: 724102.94 | C3: 716753.66 | D3: 711781.53 | E3: 707081.35 | F3: 707106.64 | G3: 715656.76 | H3: 722543.95 | I3: 729440.89 | J3: 736210.1 | K3: 742771.66 | L3: 749073.99 | M3: 756688.1 | N3: 765640.97 | O3: 775524.1 | P3: 785996.26 | Q3: 796826.82 | R3: 807698.02 | S3: 818559.35 | T3: 829433.5 | U3: 840214.02 | V3: 850911.9 | W3: 861717.22 | X3: 872587.98 | Y3: 883476.25 | Z3: 894345 | AA3: 904997.76 | AB3: 915299.12 | AC3: 925167.83 | AD3: 934614.37 | AE3: 943679.62 | AF3: 952413.3 | AG3: 961071.89 | AH3: 969726.46 | AI3: 978406.62 | AJ3: 987133.33 | AK3: 987133.47
A4: km_traveler_sd_2 | B4: 624600.34 | C4: 620133.52 | D4: 616964.95 | E4: 613724.99 | F4: 614028.38 | G4: 620960.77 | H4: 626322.1 | I4: 631731.86 | J4: 637043.74 | K4: 642220.71 | L4: 647251.52 | M4: 653076.33 | N4: 659906.83 | O4: 667413.9 | P4: 675337.2 | Q4: 683505.55 | R4: 691689.28 | S4: 699842.73 | T4: 707986.54 | U4: 716046.16 | V4: 724021.61 | W4: 732045.84 | X4: 740098.48 | Y4: 748144.86 | Z4: 756159.19 | AA4: 763978.56 | AB4: 771485.13 | AC4: 778636.49 | AD4: 785452.13 | AE4: 791970.1 | AF4: 798233.01 | AG4: 804451.67 | AH4: 810675.85 | AI4: 816922.8 | AJ4: 823204.03 | AK4: 823204.06
A5: km_trav_auto_sd_2 | B5: 554271.64 | C5: 548860.49 | D5: 545216.75 | E5: 541781.99 | F5: 541646.74 | G5: 547473.65 | H5: 552220.03 | I5: 556931.09 | J5: 561538.11 | K5: 565976.96 | L5: 570200.44 | M5: 575386.42 | N5: 581493.1 | O5: 588239.56 | P5: 595387.31 | Q5: 602773.72 | R5: 610175.74 | S5: 617559.8 | T5: 624939.85 | U5: 632240.74 | V5: 639474.11 | W5: 646773.02 | X5: 654105.58 | Y5: 661438.38 | Z5: 668745.63 | AA5: 675903.23 | AB5: 682827.99 | AC5: 689460 | AD5: 695802.68 | AE5: 701881.87 | AF5: 707730.19 | AG5: 713511.7 | AH5: 719275.93 | AI5: 725044.62 | AJ5: 730833.12 | AK5: 730833.19
A6: km_traveler_croa_2 | B6: 70328.7 | C6: 70559.959 | D6: 70652.89 | E6: 70602.839 | F6: 70870.351 | G6: 71840.133 | H6: 72448.748 | I6: 73109.463 | J6: 73769.56 | K6: 74443.76 | L6: 75153.778 | M6: 75796.852 | N6: 76535.688 | O6: 77326.857 | P6: 78146.049 | Q6: 78980.87 | R6: 79817.171 | S6: 80645.75 | T6: 81471.542 | U6: 82291.379 | V6: 83098.496 | W6: 83899.361 | X6: 84699.706 | Y6: 85497.196 | Z6: 86290.555 | AA6: 87050.263 | AB6: 87751.766 | AC6: 88402.898 | AD6: 89013.528 | AE6: 89592.135 | AF6: 90146.14 | AG6: 90710.906 | AH6: 91288.846 | AI6: 91878.312 | AJ6: 92477.816 | AK6: 92477.804
A7: km_traveler_ld_2 | B7: 275159.81 | C7: 271463.37 | D7: 268991.24 | E7: 266726.23 | F7: 266828.47 | G7: 271107.02 | H7: 274565.66 | I7: 278066.1 | J7: 281521.11 | K7: 284892.55 | L7: 288158.13 | M7: 292091.8 | N7: 296713.25 | O7: 301820.89 | P7: 307245.75 | Q7: 312873.66 | R7: 318543.55 | S7: 324230.92 | T7: 329948.12 | U7: 335640.73 | V7: 341312.59 | W7: 347062.36 | X7: 352867.95 | Y7: 358704.77 | Z7: 364553.39 | AA7: 370305.48 | AB7: 375885.76 | AC7: 381250.19 | AD7: 386404.18 | AE7: 391368.6 | AF7: 396168.82 | AG7: 400944.41 | AH7: 405732.51 | AI7: 410548.63 | AJ7: 415404.06 | AK7: 415404.12
A8: km_trav_auto_ld_2 | B8: 169831.3 | C8: 167893.17 | D8: 166564.78 | E8: 165299.36 | F8: 165459.91 | G8: 168183.11 | H8: 170323.92 | I8: 172509.8 | J8: 174671.99 | K8: 176794.7 | L8: 178873.55 | M8: 181301.68 | N8: 184147.87 | O8: 187284.54 | P8: 190608.94 | Q8: 194053.1 | R8: 197522.27 | S8: 200999.55 | T8: 204493.65 | U8: 207973.28 | V8: 211437.78 | W8: 214944.2 | X8: 218482.4 | Y8: 222037.88 | Z8: 225599.37 | AA8: 229094.53 | AB8: 232471.13 | AC8: 235707.83 | AD8: 238811.69 | AE8: 241797.75 | AF8: 244683.11 | AG8: 247560.2 | AH8: 250450.54 | AI8: 253362 | AJ8: 256300.21 | AK8: 256300.28
A9: km_traveler_crai_2 | B9: 105328.51 | C9: 107151.72 | D9: 108184.19 | E9: 108698.4 | F9: 109777.06 | G9: 112299.49 | H9: 113679.58 | I9: 115287.32 | J9: 116926.37 | K9: 118668.58 | L9: 120612.62 | M9: 122105.37 | N9: 123786.91 | O9: 125546.9 | P9: 127340.38 | Q9: 129153.29 | R9: 130976.71 | S9: 132781.94 | T9: 134586 | U9: 136392.53 | V9: 138170.92 | W9: 139918.57 | X9: 141664.91 | Y9: 143407.76 | Z9: 145147.45 | AA9: 146787.38 | AB9: 148242.72 | AC9: 149557.78 | AD9: 150772.51 | AE9: 151916.05 | AF9: 153011.63 | AG9: 154171.07 | AH9: 155393.37 | AI9: 156667.09 | AJ9: 157982.96 | AK9: 157983.29
A10: km_traveler_cair_0 | B10: 291099.78 | C10: 298959.77 | D10: 301692.19 | E10: 301298.14 | F10: 307478.48 | G10: 324949.61 | H10: 334184.41 | I10: 344639.85 | J10: 355571.99 | K10: 367046.39 | L10: 379476.91 | M10: 392108.54 | N10: 405290.71 | O10: 419010.74 | P10: 433272.98 | Q10: 448092.77 | R10: 463204.02 | S10: 478675.07 | T10: 494548.18 | U10: 510861.82 | V10: 527343.22 | W10: 544312.61 | X10: 561587.82 | Y10: 579253.32 | Z10: 597369.2 | AA10: 615026.87 | AB10: 631825.2 | AC10: 647664.09 | AD10: 662853.78 | AE10: 677625.84 | AF10: 692164.32 | AG10: 707611.69 | AH10: 723862.82 | AI10: 740872.78 | AJ10: 758592.21 | AK10: 776952.49
A11: km_trav_auto_ld_0+km_trav_auto_sd_0 | B11: 724102.94 | C11: 716753.66 | D11: 711781.53 | E11: 707081.35 | F11: 707106.64 | G11: 715656.76 | H11: 722543.95 | I11: 729926.99 | J11: 737774.42 | K11: 746040.95 | L11: 754796.95 | M11: 763884.44 | N11: 773273.05 | O11: 782925.74 | P11: 792804.02 | Q11: 802874.33 | R11: 813050.7 | S11: 823300.82 | T11: 833611.29 | U11: 843976.89 | V11: 854336.11 | W11: 864716.49 | X11: 875104.63 | Y11: 885508 | Z11: 895937.13 | AA11: 906230.93 | AB11: 916240.32 | AC11: 925908.85 | AD11: 935260.67 | AE11: 944334.63 | AF11: 953167.19 | AG11: 961942.91 | AH11: 970717.62 | AI11: 979510.52 | AJ11: 988329.47 | AK11: 997175.28
A12: km_traveler_sd_0 | B12: 624600.34 | C12: 620133.52 | D12: 616964.95 | E12: 613724.99 | F12: 614028.38 | G12: 620960.77 | H12: 626322.1 | I12: 632027.16 | J12: 638053.09 | K12: 644371.84 | L12: 651050.85 | M12: 657946.33 | N12: 665050.63 | O12: 672336.28 | P12: 679775.3 | Q12: 687343.53 | R12: 694968.64 | S12: 702630.03 | T12: 710319.63 | U12: 718035.02 | V12: 725724.15 | W12: 733416.8 | X12: 741097.07 | Y12: 748773.18 | Z12: 756454.53 | AA12: 764001.86 | AB12: 771298.69 | AC12: 778305.51 | AD12: 785051.7 | AE12: 791573.97 | AF12: 797905.72 | AG12: 804212.33 | AH12: 810528.81 | AI12: 816866.28 | AJ12: 823227.43 | AK12: 829609.35
... A17: km_traveler_crai_0 | B17: 105328.51 | C17: 107151.72 | D17: 108184.19 | E17: 108698.4 | F17: 109777.06 | G17: 112299.49 | H17: 113679.58 | I17: 115115.14 | J17: 116553.71 | K17: 118014.58 | L17: 119561.18 | M17: 121085.55 | N17: 122640.7 | O17: 124224.99 | P17: 125838.4 | Q17: 127481.64 | R17: 129116.79 | S17: 130753.24 | T17: 132396.42 | U17: 134050.83 | V17: 135684.82 | W17: 137334.4 | X17: 138977.79 | Y17: 140624.95 | Z17: 142282.37 | AA17: 143854.89 | AB17: 145298.37 | AC17: 146610.35 | AD17: 147829.75 | AE17: 148985.21 | AF17: 150099.26 | AG17: 151291.56 | AH17: 152548.56 | AI17: 153862.5 | AJ17: 155224.93 | AK17: 156625.79

Sheet Hybrid
A1: _date_ | B1: 42005 | C1: 42370 | D1: 42736 | E1: 43101 | F1: 43466 | G1: 43831 | H1: 44197 | I1: 44562 | J1: 44927 | K1: 45292 | L1: 45658 | M1: 46023 | N1: 46388 | O1: 46753 | P1: 47119 | Q1: 47484 | R1: 47849 | S1: 48214 | T1: 48580 | U1: 48945 | V1: 49310 | W1: 49675 | X1: 50041 | Y1: 50406 | Z1: 50771 | AA1: 51136 | AB1: 51502 | AC1: 51867 | AD1: 52232 | AE1: 52597 | AF1: 52963 | AG1: 53328 | AH1: 53693 | AI1: 54058 | AJ1: 54424 | AK1: 54789
A2: auto_2 | B2: 32317.941 | C2: 31989.266 | D2: 31766.848 | E2: 31556.566 | F2: 31558.174 | G2: 31942.005 | H2: 32251.021 | I2: 32560.604 | J2: 32864.506 | K2: 33159.169 | L2: 33442.315 | M2: 33784.136 | N2: 34186.031 | O2: 34629.669 | P2: 35099.751 | Q2: 35585.939 | R2: 36073.989 | S2: 36561.63 | T2: 37049.887 | U2: 37533.988 | V2: 38014.414 | W2: 38499.686 | X2: 38987.931 | Y2: 39476.998 | Z2: 39965.226 | AA2: 40443.766 | AB2: 40906.51 | AC2: 41349.825 | AD2: 41774.194 | AE2: 42181.456 | AF2: 42573.85 | AG2: 42962.92 | AH2: 43351.855 | AI2: 43741.98 | AJ2: 44134.231 | AK2: 44134.237
A3: auto_cfut_2 | B3: 32271.24 | C3: 31924.248 | D3: 31683.81 | E3: 31454.989 | F3: 31432.993 | G3: 31788.805 | H3: 32071.448 | I3: 32354.504 | J3: 32630.905 | K3: 32895.457 | L3: 33142.47 | M3: 33437.604 | N3: 33782.977 | O3: 34161.007 | P3: 34556.909 | Q3: 34960.623 | R3: 35358.146 | S3: 35746.89 | T3: 36127.407 | U3: 36494.578 | V3: 36848.16 | W3: 37195.587 | X3: 37534.454 | Y3: 37861.989 | Z3: 38175.779 | AA3: 38466.66 | AB3: 38728.032 | AC3: 38955.493 | AD3: 39148.278 | AE3: 39306.719 | AF3: 39431.377 | AG3: 39530.992 | AH3: 39606.684 | AI3: 39657.826 | AJ3: 39683.405 | AK3: 39550.518
A4: auto_cele_2 | B4: 44.765 | C4: 63.021127 | D4: 80.977049 | E4: 99.457266 | F4: 122.9902 | G4: 150.91049 | H4: 177.19542 | I4: 203.63756 | J4: 231.05778 | K4: 261.09127 | L4: 297.15214 | M4: 343.76665 | N4: 400.21388 | O4: 465.74685 | P4: 539.85214 | Q4: 622.25305 | R4: 712.70903 | S4: 811.53918 | T4: 919.21308 | U4: 1036.0799 | V4: 1162.8637 | W4: 1300.6518 | X4: 1449.9727 | Y4: 1611.4507 | Z4: 1785.8374 | AA4: 1973.4479 | AB4: 2174.7754 | AC4: 2390.5892 | AD4: 2622.1351 | AE4: 2870.9241 | AF4: 3138.6297 | AG4: 3428.0595 | AH4: 3741.2801 | AI4: 4080.2422 | AJ4: 4446.8964 | AK4: 4798.8813
A5: auto_cgas_2 | B5: 1.936 | C5: 1.9968324 | D5: 2.060546 | E5: 2.1196814 | F5: 2.1910005 | G5: 2.2894584 | H5: 2.3779418 | I5: 2.4627777 | J5: 2.5436027 | K5: 2.6201879 | L5: 2.6922425 | M5: 2.7654514 | N5: 2.8402349 | O5: 2.9153459 | P5: 2.9897354 | Q5: 3.0627203 | R5: 3.1332629 | S5: 3.2012579 | T5: 3.2668537 | U5: 3.3297162 | V5: 3.3899087 | W5: 3.4481337 | X5: 3.5042721 | Y5: 3.5581651 | Z5: 3.6096765 | AA5: 3.6580953 | AB5: 3.7029106 | AC5: 3.7437848 | AD5: 3.7806784 | AE5: 3.8136412 | AF5: 3.8427416 | AG5: 3.8687342 | AH5: 3.8917438 | AI5: 3.9117477 | AJ5: 3.9286882 | AK5: 3.9314241
A6: newauto_2 | B6: 1886.229 | C6: 2184.6168 | D6: 2264.6053 | E6: 2258.7517 | F6: 2453.578 | G6: 2835.035 | H6: 2789.0324 | I6: 2812.6521 | J6: 2830.0618 | K6: 2843.434 | L6: 2853.7108 | M6: 2933.0565 | N6: 3017.967 | O6: 3088.8496 | P6: 3147.3375 | Q6: 3197.2227 | R6: 3233.8024 | S6: 3267.9525 | T6: 3302.7776 | U6: 3332.5448 | V6: 3362.1223 | W6: 3399.5602 | X6: 3435.0846 | Y6: 3468.2539 | Z6: 3499.367 | AA6: 3521.0768 | AB6: 3535.425 | AC6: 3544.3923 | AD6: 3551.7816 | AE6: 3558.9432 | AF6: 3566.3571 | AG6: 3583.4457 | AH6: 3602.6412 | AI6: 3622.2508 | AJ6: 3641.9172 | AK6: 3266.3302
A7: newauto_cfut_2 | B7: 1868.672 | C7: 2164.3883 | D7: 2243.94 | E7: 2236.8445 | F7: 2425.863 | G7: 2801.9597 | H7: 2756.4794 | I7: 2778.8887 | J7: 2794.2613 | K7: 2803.9226 | L7: 2806.9705 | M7: 2874.3144 | N7: 2947.5215 | O7: 3007.0555 | P7: 3054.3457 | Q7: 3092.9679 | R7: 3118.1943 | S7: 3140.3502 | T7: 3162.3765 | U7: 3178.6424 | V7: 3193.6271 | W7: 3214.9875 | X7: 3233.4659 | Y7: 3248.5041 | Z7: 3260.2484 | AA7: 3261.7588 | AB7: 3254.886 | AC7: 3241.3152 | AD7: 3224.3411 | AE7: 3204.9995 | AF7: 3183.5471 | AG7: 3168.2045 | AH7: 3152.0334 | AI7: 3133.3742 | AJ7: 3111.7917 | AK7: 2955.3149
A8: newauto_cele_2 | B8: 17.399981 | C8: 20.046727 | D8: 20.476767 | E8: 21.719299 | F8: 27.511221 | G8: 32.839898 | H8: 32.321355 | I8: 33.529959 | J8: 35.565718 | K8: 39.275801 | L8: 46.504522 | M8: 58.500598 | N8: 70.197895 | O8: 81.541524 | P8: 92.735165 | Q8: 103.99499 | R8: 115.34611 | S8: 127.3385 | T8: 140.13547 | U8: 153.63538 | V8: 168.22692 | W8: 184.30267 | X8: 201.34703 | Y8: 219.4769 | Z8: 238.84472 | AA8: 259.04395 | AB8: 280.26545 | AC8: 302.80476 | AD8: 327.16956 | AE8: 353.6744 | AF8: 382.54253 | AG8: 414.97495 | AH8: 450.34301 | AI8: 488.61331 | AJ8: 529.86384 | AK8: 529.8608
A9: newauto_cgas_2 | B9: 0.156989 | C9: 0.18183241 | D9: 0.18851563 | E9: 0.18791953 | F9: 0.20379916 | G9: 0.23539542 | H9: 0.23157458 | I9: 0.23345721 | J9: 0.23474867 | K9: 0.23556033 | L9: 0.23581638 | M9: 0.24147401 | N9: 0.24762421 | O9: 0.25262572 | P9: 0.25659862 | Q9: 0.25984331 | R9: 0.26196261 | S9: 0.26382394 | T9: 0.2656744 | U9: 0.26704091 | V9: 0.26829979 | W9: 0.2700943 | X9: 0.27164669 | Y9: 0.27291006 | Z9: 0.27389672 | AA9: 0.2740236 | AB9: 0.27344622 | AC9: 0.27230612 | AD9: 0.27088011 | AE9: 0.2692552 | AF9: 0.26745296 | AG9: 0.26616402 | AH9: 0.26480546 | AI9: 0.26323789 | AJ9: 0.26142472 | AK9: 0.24827895
A10: auto_0 | B10: 32317.941 | C10: 31989.266 | D10: 31766.848 | E10: 31556.566 | F10: 31558.174 | G10: 31942.005 | H10: 32251.021 | I10: 32582.334 | J10: 32934.484 | K10: 33305.453 | L10: 33698.417 | M10: 34106.26 | N10: 34527.642 | O10: 34960.902 | P10: 35404.317 | Q10: 35856.385 | R10: 36313.239 | S10: 36773.434 | T10: 37236.374 | U10: 37701.824 | V10: 38167.016 | W10: 38633.196 | X10: 39099.757 | Y10: 39567.037 | Z10: 40035.511 | AA10: 40497.914 | AB10: 40947.545 | AC10: 41381.865 | AD10: 41801.972 | AE10: 42209.615 | AF10: 42606.436 | AG10: 43000.758 | AH10: 43395.081 | AI10: 43790.262 | AJ10: 44186.651 | AK10: 44584.282
A11: auto_cfut_0 | B11: 32271.24 | C11: 31924.248 | D11: 31683.81 | E11: 31454.989 | F11: 31432.993 | G11: 31788.805 | H11: 32071.448 | I11: 32376.242 | J11: 32701.68 | K11: 33045.666 | L11: 33411.23 | M11: 33791.251 | N11: 34184.341 | O11: 34588.795 | P11: 35002.838 | Q11: 35424.92 | R11: 35851.156 | S11: 36280.056 | T11: 36710.956 | U11: 37143.539 | V11: 37574.981 | W11: 38006.4 | X11: 38437.074 | Y11: 38867.195 | Z11: 39297.075 | AA11: 39719.42 | AB11: 40127.484 | AC11: 40518.58 | AD11: 40893.547 | AE11: 41253.848 | AF11: 41600.824 | AG11: 41942.314 | AH11: 42280.437 | AI11: 42615.692 | AJ11: 42948.055 | AK11: 43277.168
A12: auto_cele_0 | B12: 44.765 | C12: 63.021127 | D12: 80.977049 | E12: 99.457266 | F12: 122.9902 | G12: 150.91049 | H12: 177.19542 | I12: 203.6274 | J12: 230.25424 | K12: 257.15368 | L12: 284.47246 | M12: 312.21403 | N12: 340.42558 | O12: 369.15476 | P12: 398.44959 | Q12: 428.36153 | R12: 458.90536 | S12: 490.12861 | T12: 522.09806 | U12: 554.89673 | V12: 588.57881 | W12: 623.27415 | X12: 659.09701 | Y12: 696.19248 | Z12: 734.72435 | AA12: 774.72238 | AB12: 816.22989 | AC12: 859.39953 | AD12: 904.48538 | AE12: 951.77617 | AF12: 1001.5718 | AG12: 1054.3562 | AH12: 1110.5079 | AI12: 1170.3882 | AJ12: 1234.3698 | AK12: 1302.844
... A121: buil_des_0 | B121: 1.1716777 | C121: 1.1716777 | D121: 1.1565402 | E121: 1.1416083 | F121: 1.1268791 | G121: 1.1123494 | H121: 1.0980163 | I121: 1.083877 | J121: 1.0699286 | K121: 1.0561683 | L121: 1.0425934 | M121: 1.0292012 | N121: 1.0159892 | O121: 1.0029547 | P121: 0.99009523 | Q121: 0.97740825 | R121: 0.96489133 | S121: 0.95254204 | T121: 0.940358 | U121: 0.92833689 | V121: 0.91647639 | W121: 0.90477425 | X121: 0.89322823 | Y121: 0.88183615 | Z121: 0.87059586 | AA121: 0.85950523 | AB121: 0.84856218 | AC121: 0.83776466 | AD121: 0.82711064 | AE121: 0.81659814 | AF121: 0.8062252 | AG121: 0.7959899 | AH121: 0.78589034 | AI121: 0.77592465 | AJ121: 0.766091 | AK121: 0.75638758

Sheet Tab-macro
B1: en écart au scénario de référence (%)
B2: ThreeME
B3: 2021 | C3: 2022 | D3: 2023 | E3: 2025 | F3: 2030 | G3: 2050
A4: PIB en volume | B4: =Macro!H2 -> 0 | C4: =Macro!I2 -> 0.046922219 | D4: =Macro!J2 -> 0.11764597 | E4: =Macro!L2 -> 0.37060634 | F4: =Macro!Q2 -> 0.57045052 | G4: =Macro!AK2 -> 0.64283357
A5: Consommation des ménages | B5: =Macro!H3 -> 0 | C5: =Macro!I3 -> 0.05199264 | D5: =Macro!J3 -> 0.13041325 | E5: =Macro!L3 -> 0.40747066 | F5: =Macro!Q3 -> 0.60269236 | G5: =Macro!AK3 -> -0.91566963
A6: Investissement | B6: =Macro!H4 -> 0 | C6: =Macro!I4 -> 0.062010005 | D6: =Macro!J4 -> 0.16596114 | E6: =Macro!L4 -> 0.56567578 | F6: =Macro!Q4 -> 1.141779 | G6: =Macro!AK4 -> 1.1791171
A7: Exportations | B7: =Macro!H5 -> -4.1233237e-10 | C7: =Macro!I5 -> -0.014928541 | D7: =Macro!J5 -> -0.039825652 | E7: =Macro!L5 -> -0.10639805 | F7: =Macro!Q5 -> -0.0006018598 | G7: =Macro!AK5 -> -0.23630217
A8: Importations | B8: =Macro!H6 -> 0 | C8: =Macro!I6 -> 0 | D8: =Macro!J6 -> 0 | E8: =Macro!L6 -> 0 | F8: =Macro!Q6 -> 0 | G8: =Macro!AK6 -> 0
A9: Revenu disponible (réel) des ménages | B9: =Macro!H7 -> 0 | C9: =Macro!I7 -> -0.021231657 | D9: =Macro!J7 -> -0.070579973 | E9: =Macro!L7 -> -0.26623598 | F9: =Macro!Q7 -> -0.62997407 | G9: =Macro!AK7 -> -1.3323577
A10: Taux d'épargne (en pts) | B10: =Macro!H8 -> 0 | C10: =Macro!I8 -> 0 | D10: =Macro!J8 -> 0 | E10: =Macro!L8 -> 0 | F10: =Macro!Q8 -> 0 | G10: =Macro!AK8 -> 0
A11: Prix de la consommation des ménages | B11: =Macro!H9 -> 4.1233309e-09 | C11: =Macro!I9 -> 0.0061438629 | D11: =Macro!J9 -> 0.022264803 | E11: =Macro!L9 -> 0.07116657 | F11: =Macro!Q9 -> 0.05864562 | G11: =Macro!AK9 -> 0.79607412
A12: Prix de la production | B12: =Macro!H10 -> 0 | C12: =Macro!I10 -> 0.061582701 | D12: =Macro!J10 -> 0.16533157 | E12: =Macro!L10 -> 0.56430725 | F12: =Macro!Q10 -> 1.1341047 | G12: =Macro!AK10 -> 1.1684181
A13: Prix de la valeur ajoutée | B13: =Macro!H11 -> 0 | C13: =Macro!I11 -> -0.020804353 | D13: =Macro!J11 -> -0.069950402 | E13: =Macro!L11 -> -0.26486746 | F13: =Macro!Q11 -> -0.6222998 | G13: =Macro!AK11 -> -1.3216587
A14: Prix des consommations intermédiaires | B14: =Macro!H12 -> 0 | C14: =Macro!I12 -> -0.018961553 | D14: =Macro!J12 -> -0.063492252 | E14: =Macro!L12 -> -0.24141023 | F14: =Macro!Q12 -> -0.58150558 | G14: =Macro!AK12 -> -1.2617175
A15: Prix des exportations | B15: =Macro!H13 -> 0 | C15: =Macro!I13 -> 0.00042730447 | D15: =Macro!J13 -> 0.00062957121 | E15: =Macro!L13 -> 0.0013685275 | F15: =Macro!Q13 -> 0.0076742706 | G15: =Macro!AK13 -> 0.010698981
... A24: Emissions de CO2 | B24: =Macro!H22 -> 0 | C24: =Macro!I22 -> 0.11406933 | D24: =Macro!J22 -> 0.30637625 | E24: =Macro!L22 -> 1.0464996 | F24: =Macro!Q22 -> 2.107682 | G24: =Macro!AK22 -> 2.1965104
B26: % deviation from baseline
B27: ThreeME
B28: 2021 | C28: 2022 | D28: 2023 | E28: 2025 | F28: 2030 | G28: 2050
A29: GDP in volume | B29: =B4 -> 0 | C29: =C4 -> 0.046922219 | D29: =D4 -> 0.11764597 | E29: =E4 -> 0.37060634 | F29: =F4 -> 0.57045052 | G29: =G4 -> 0.64283357
A30: Household consumption | B30: =B5 -> 0 | C30: =C5 -> 0.05199264 | D30: =D5 -> 0.13041325 | E30: =E5 -> 0.40747066 | F30: =F5 -> 0.60269236 | G30: =G5 -> -0.91566963
A31: Investment | B31: =B6 -> 0 | C31: =C6 -> 0.062010005 | D31: =D6 -> 0.16596114 | E31: =E6 -> 0.56567578 | F31: =F6 -> 1.141779 | G31: =G6 -> 1.1791171
A32: Exports | B32: =B7 -> -4.1233237e-10 | C32: =C7 -> -0.014928541 | D32: =D7 -> -0.039825652 | E32: =E7 -> -0.10639805 | F32: =F7 -> -0.0006018598 | G32: =G7 -> -0.23630217
A33: Imports | B33: =B8 -> 0 | C33: =C8 -> 0 | D33: =D8 -> 0 | E33: =E8 -> 0 | F33: =F8 -> 0 | G33: =G8 -> 0
A34: Household disposable income (real) | B34: =B9 -> 0 | C34: =C9 -> -0.021231657 | D34: =D9 -> -0.070579973 | E34: =E9 -> -0.26623598 | F34: =F9 -> -0.62997407 | G34: =G9 -> -1.3323577
A35: Saving rate (in points) | B35: =B10 -> 0 | C35: =C10 -> 0 | D35: =D10 -> 0 | E35: =E10 -> 0 | F35: =F10 -> 0 | G35: =G10 -> 0
A36: Household consumption price index | B36: =B11 -> 4.1233309e-09 | C36: =C11 -> 0.0061438629 | D36: =D11 -> 0.022264803 | E36: =E11 -> 0.07116657 | F36: =F11 -> 0.05864562 | G36: =G11 -> 0.79607412
A37: Production price index | B37: =B12 -> 0 | C37: =C12 -> 0.061582701 | D37: =D12 -> 0.16533157 | E37: =E12 -> 0.56430725 | F37: =F12 -> 1.1341047 | G37: =G12 -> 1.1684181
A38: Added value price index | B38: =B13 -> 0 | C38: =C13 -> -0.020804353 | D38: =D13 -> -0.069950402 | E38: =E13 -> -0.26486746 | F38: =F13 -> -0.6222998 | G38: =G13 -> -1.3216587
A39: Intermediate consumption price index | B39: =B14 -> 0 | C39: =C14 -> -0.018961553 | D39: =D14 -> -0.063492252 | E39: =E14 -> -0.24141023 | F39: =F14 -> -0.58150558 | G39: =G14 -> -1.2617175
A40: Export price index | B40: =B15 -> 0 | C40: =C15 -> 0.00042730447 | D40: =D15 -> 0.00062957121 | E40: =E15 -> 0.0013685275 | F40: =F15 -> 0.0076742706 | G40: =G15 -> 0.010698981
... A49: CO2 emissions | B49: =B24 -> 0 | C49: =C24 -> 0.11406933 | D49: =D24 -> 0.30637625 | E49: =E24 -> 1.0464996 | F49: =F24 -> 2.107682 | G49: =G24 -> 2.1965104

Sheet Tab-baseline
C1: 8 | D1: 9 | E1: 10 | F1: 12 | G1: 17 | H1: 37
C2: ThreeME
C3: 2021 | D3: 2022 | E3: 2023 | F3: 2025 | G3: 2030 | H3: 2050
A4: Taux de croissance du PIB | B4: @pch(gdp_0) | C4: =VLOOKUP($B4,Baseline!$A$1:$AT$50,C$1,FALSE) -> 0.020542608 | D4: =VLOOKUP($B4,Baseline!$A$1:$AT$50,D$1,FALSE) -> 0.0206284 | E4: =VLOOKUP($B4,Baseline!$A$1:$AT$50,E$1,FALSE) -> 0.020733799 | F4: =VLOOKUP($B4,Baseline!$A$1:$AT$50,F$1,FALSE) -> 0.021361855 | G4: =VLOOKUP($B4,Baseline!$A$1:$AT$50,G$1,FALSE) -> 0.021909607 | H4: =VLOOKUP($B4,Baseline!$A$1:$AT$50,H$1,FALSE) -> 0.01613416
