Workbook
Name formatResults: [1]ResultsEXR10!$A$50

Sheet Results
A1: NB : on crée ici une liste : - globale, qui fusionne les sorties des reportings 1, 2 et 3 - "rationalisée" : suppression des doublons, et regroupements par thématique On continue par la suite à avoir 2 Excels de reporting (un "energie", fusion des reportings 1 et 2), et un "économie" (reporting 3)), dans lesquels on copiera cet onglet "results" (généré automatiquement par EViews). --> puis voir à la fin si on peut pas importer les graphs et tableaux dans l'excel automatiquement généré (éviterait les copiés collés, mais à voir si ça prend trop de temps, et si c'est pas trop gros comme excel)
A2: Nom du bloc de variables utilisé dans le code | B2: Sous-bloc de variables pour plus de lisibilité dans le Excel | E2: Year | F2: =date!B3 -> 2015 | G2: =date!C3 -> 2016 | H2: =date!D3 -> 2017 | I2: =date!E3 -> 2018 | J2: =date!F3 -> 2019 | K2: =date!G3 -> 2020 | L2: =date!H3 -> 2021 | M2: =date!I3 -> 2022 | ... AO2: =date!AK3 -> 2050
A3: HYBRID | B3: AUTOMOBILES (thousands) | C3: TOTAL STOCK SHOCK | E3: AUTO_2 | F3: =VLOOKUP($E3,Hybrid!$1:$1048576,MATCH(DATE(F$2,1,1),Hybrid!$A$1:$LI$1),FALSE) -> 32317.941 | G3: =VLOOKUP($E3,Hybrid!$1:$1048576,MATCH(DATE(G$2,1,1),Hybrid!$A$1:$LI$1),FALSE) -> 31926.557 | H3: =VLOOKUP($E3,Hybrid!$1:$1048576,MATCH(DATE(H$2,1,1),Hybrid!$A$1:$LI$1),FALSE) -> 31730.857 | I3: =VLOOKUP($E3,Hybrid!$1:$1048576,MATCH(DATE(I$2,1,1),Hybrid!$A$1:$LI$1),FALSE) -> 31665.91 | J3: =VLOOKUP($E3,Hybrid!$1:$1048576,MATCH(DATE(J$2,1,1),Hybrid!$A$1:$LI$1),FALSE) -> 31687.577 | K3: =VLOOKUP($E3,Hybrid!$1:$1048576,MATCH(DATE(K$2,1,1),Hybrid!$A$1:$LI$1),FALSE) -> 31766.229 | L3: =VLOOKUP($E3,Hybrid!$1:$1048576,MATCH(DATE(L$2,1,1),Hybrid!$A$1:$LI$1),FALSE) -> 31884.17 | M3: =VLOOKUP($E3,Hybrid!$1:$1048576,MATCH(DATE(M$2,1,1),Hybrid!$A$1:$LI$1),FALSE) -> 32031.35 | ... AO3: =VLOOKUP($E3,Hybrid!$1:$1048576,MATCH(DATE(AO$2,1,1),Hybrid!$A$1:$LI$1),FALSE) -> 37602.841
C4: OIL | E4: AUTO_cfut_2 | F4: =VLOOKUP($E4,Hybrid!$1:$1048576,MATCH(DATE(F$2,1,1),Hybrid!$A$1:$LI$1),FALSE) -> 32271.24 | G4: =VLOOKUP($E4,Hybrid!$1:$1048576,MATCH(DATE(G$2,1,1),Hybrid!$A$1:$LI$1),FALSE) -> 31862.134 | H4: =VLOOKUP($E4,Hybrid!$1:$1048576,MATCH(DATE(H$2,1,1),Hybrid!$A$1:$LI$1),FALSE) -> 31647.786 | I4: =VLOOKUP($E4,Hybrid!$1:$1048576,MATCH(DATE(I$2,1,1),Hybrid!$A$1:$LI$1),FALSE) -> 31563.667 | J4: =VLOOKUP($E4,Hybrid!$1:$1048576,MATCH(DATE(J$2,1,1),Hybrid!$A$1:$LI$1),FALSE) -> 31565.852 | K4: =VLOOKUP($E4,Hybrid!$1:$1048576,MATCH(DATE(K$2,1,1),Hybrid!$A$1:$LI$1),FALSE) -> 31624.781 | L4: =VLOOKUP($E4,Hybrid!$1:$1048576,MATCH(DATE(L$2,1,1),Hybrid!$A$1:$LI$1),FALSE) -> 31722.707 | M4: =VLOOKUP($E4,Hybrid!$1:$1048576,MATCH(DATE(M$2,1,1),Hybrid!$A$1:$LI$1),FALSE) -> 31849.465 | ... AO4: =VLOOKUP($E4,Hybrid!$1:$1048576,MATCH(DATE(AO$2,1,1),Hybrid!$A$1:$LI$1),FALSE) -> 35103.736
D5: class A | E5: AUTO_ca_cfut_2 | F5: =VLOOKUP($E5,Hybrid!$1:$1048576,MATCH(DATE(F$2,1,1),Hybrid!$A$1:$LI$1),FALSE) -> 7095.7005 | G5: =VLOOKUP($E5,Hybrid!$1:$1048576,MATCH(DATE(G$2,1,1),Hybrid!$A$1:$LI$1),FALSE) -> 7141.7725 | H5: =VLOOKUP($E5,Hybrid!$1:$1048576,MATCH(DATE(H$2,1,1),Hybrid!$A$1:$LI$1),FALSE) -> 7236.3372 | I5: =VLOOKUP($E5,Hybrid!$1:$1048576,MATCH(DATE(I$2,1,1),Hybrid!$A$1:$LI$1),FALSE) -> 7363.0817 | J5: =VLOOKUP($E5,Hybrid!$1:$1048576,MATCH(DATE(J$2,1,1),Hybrid!$A$1:$LI$1),FALSE) -> 7510.7006 | K5: =VLOOKUP($E5,Hybrid!$1:$1048576,MATCH(DATE(K$2,1,1),Hybrid!$A$1:$LI$1),FALSE) -> 7671.4836 | L5: =VLOOKUP($E5,Hybrid!$1:$1048576,MATCH(DATE(L$2,1,1),Hybrid!$A$1:$LI$1),FALSE) -> 7840.8349 | M5: =VLOOKUP($E5,Hybrid!$1:$1048576,MATCH(DATE(M$2,1,1),Hybrid!$A$1:$LI$1),FALSE) -> 8016.1766 | ... AO5: =VLOOKUP($E5,Hybrid!$1:$1048576,MATCH(DATE(AO$2,1,1),Hybrid!$A$1:$LI$1),FALSE) -> 12307.577
D6: class B | E6: AUTO_cb_cfut_2 | F6: =VLOOKUP($E6,Hybrid!$1:$1048576,MATCH(DATE(F$2,1,1),Hybrid!$A$1:$LI$1),FALSE) -> 8251.2564 | G6: =VLOOKUP($E6,Hybrid!$1:$1048576,MATCH(DATE(G$2,1,1),Hybrid!$A$1:$LI$1),FALSE) -> 8182.8121 | H6: =VLOOKUP($E6,Hybrid!$1:$1048576,MATCH(DATE(H$2,1,1),Hybrid!$A$1:$LI$1),FALSE) -> 8168.4592 | I6: =VLOOKUP($E6,Hybrid!$1:$1048576,MATCH(DATE(I$2,1,1),Hybrid!$A$1:$LI$1),FALSE) -> 8191.5872 | J6: =VLOOKUP($E6,Hybrid!$1:$1048576,MATCH(DATE(J$2,1,1),Hybrid!$A$1:$LI$1),FALSE) -> 8240.58 | K6: =VLOOKUP($E6,Hybrid!$1:$1048576,MATCH(DATE(K$2,1,1),Hybrid!$A$1:$LI$1),FALSE) -> 8307.3911 | L6: =VLOOKUP($E6,Hybrid!$1:$1048576,MATCH(DATE(L$2,1,1),Hybrid!$A$1:$LI$1),FALSE) -> 8387.0405 | M6: =VLOOKUP($E6,Hybrid!$1:$1048576,MATCH(DATE(M$2,1,1),Hybrid!$A$1:$LI$1),FALSE) -> 8476.5554 | ... AO6: =VLOOKUP($E6,Hybrid!$1:$1048576,MATCH(DATE(AO$2,1,1),Hybrid!$A$1:$LI$1),FALSE) -> 10896.479
D7: class C | E7: AUTO_cc_cfut_2 | F7: =VLOOKUP($E7,Hybrid!$1:$1048576,MATCH(DATE(F$2,1,1),Hybrid!$A$1:$LI$1),FALSE) -> 6777.6025 | G7: =VLOOKUP($E7,Hybrid!$1:$1048576,MATCH(DATE(G$2,1,1),Hybrid!$A$1:$LI$1),FALSE) -> 6646.7823 | H7: =VLOOKUP($E7,Hybrid!$1:$1048576,MATCH(DATE(H$2,1,1),Hybrid!$A$1:$LI$1),FALSE) -> 6559.0536 | I7: =VLOOKUP($E7,Hybrid!$1:$1048576,MATCH(DATE(I$2,1,1),Hybrid!$A$1:$LI$1),FALSE) -> 6502.2362 | J7: =VLOOKUP($E7,Hybrid!$1:$1048576,MATCH(DATE(J$2,1,1),Hybrid!$A$1:$LI$1),FALSE) -> 6467.7395 | K7: =VLOOKUP($E7,Hybrid!$1:$1048576,MATCH(DATE(K$2,1,1),Hybrid!$A$1:$LI$1),FALSE) -> 6449.5285 | L7: =VLOOKUP($E7,Hybrid!$1:$1048576,MATCH(DATE(L$2,1,1),Hybrid!$A$1:$LI$1),FALSE) -> 6443.746 | M7: =VLOOKUP($E7,Hybrid!$1:$1048576,MATCH(DATE(M$2,1,1),Hybrid!$A$1:$LI$1),FALSE) -> 6447.9746 | ... AO7: =VLOOKUP($E7,Hybrid!$1:$1048576,MATCH(DATE(AO$2,1,1),Hybrid!$A$1:$LI$1),FALSE) -> 6988.4264
D8: class D | E8: AUTO_cd_cfut_2 | F8: =VLOOKUP($E8,Hybrid!$1:$1048576,MATCH(DATE(F$2,1,1),Hybrid!$A$1:$LI$1),FALSE) -> 4159.6639 | G8: =VLOOKUP($E8,Hybrid!$1:$1048576,MATCH(DATE(G$2,1,1),Hybrid!$A$1:$LI$1),FALSE) -> 4054.5905 | H8: =VLOOKUP($E8,Hybrid!$1:$1048576,MATCH(DATE(H$2,1,1),Hybrid!$A$1:$LI$1),FALSE) -> 3973.877 | I8: =VLOOKUP($E8,Hybrid!$1:$1048576,MATCH(DATE(I$2,1,1),Hybrid!$A$1:$LI$1),FALSE) -> 3910.1866 | J8: =VLOOKUP($E8,Hybrid!$1:$1048576,MATCH(DATE(J$2,1,1),Hybrid!$A$1:$LI$1),FALSE) -> 3858.4319 | K8: =VLOOKUP($E8,Hybrid!$1:$1048576,MATCH(DATE(K$2,1,1),Hybrid!$A$1:$LI$1),FALSE) -> 3815.0948 | L8: =VLOOKUP($E8,Hybrid!$1:$1048576,MATCH(DATE(L$2,1,1),Hybrid!$A$1:$LI$1),FALSE) -> 3777.9381 | M8: =VLOOKUP($E8,Hybrid!$1:$1048576,MATCH(DATE(M$2,1,1),Hybrid!$A$1:$LI$1),FALSE) -> 3745.5592 | ... AO8: =VLOOKUP($E8,Hybrid!$1:$1048576,MATCH(DATE(AO$2,1,1),Hybrid!$A$1:$LI$1),FALSE) -> 2889.4513
D9: class E | E9: AUTO_ce_cfut_2 | F9: =VLOOKUP($E9,Hybrid!$1:$1048576,MATCH(DATE(F$2,1,1),Hybrid!$A$1:$LI$1),FALSE) -> 2503.7292 | G9: =VLOOKUP($E9,Hybrid!$1:$1048576,MATCH(DATE(G$2,1,1),Hybrid!$A$1:$LI$1),FALSE) -> 2442.7236 | H9: =VLOOKUP($E9,Hybrid!$1:$1048576,MATCH(DATE(H$2,1,1),Hybrid!$A$1:$LI$1),FALSE) -> 2395.2956 | I9: =VLOOKUP($E9,Hybrid!$1:$1048576,MATCH(DATE(I$2,1,1),Hybrid!$A$1:$LI$1),FALSE) -> 2356.7622 | J9: =VLOOKUP($E9,Hybrid!$1:$1048576,MATCH(DATE(J$2,1,1),Hybrid!$A$1:$LI$1),FALSE) -> 2323.9614 | K9: =VLOOKUP($E9,Hybrid!$1:$1048576,MATCH(DATE(K$2,1,1),Hybrid!$A$1:$LI$1),FALSE) -> 2294.7723 | L9: =VLOOKUP($E9,Hybrid!$1:$1048576,MATCH(DATE(L$2,1,1),Hybrid!$A$1:$LI$1),FALSE) -> 2267.8937 | M9: =VLOOKUP($E9,Hybrid!$1:$1048576,MATCH(DATE(M$2,1,1),Hybrid!$A$1:$LI$1),FALSE) -> 2242.5503 | ... AO9: =VLOOKUP($E9,Hybrid!$1:$1048576,MATCH(DATE(AO$2,1,1),Hybrid!$A$1:$LI$1),FALSE) -> 1345.3309
D10: class F | E10: AUTO_cf_cfut_2 | F10: =VLOOKUP($E10,Hybrid!$1:$1048576,MATCH(DATE(F$2,1,1),Hybrid!$A$1:$LI$1),FALSE) -> 1243.6668 | G10: =VLOOKUP($E10,Hybrid!$1:$1048576,MATCH(DATE(G$2,1,1),Hybrid!$A$1:$LI$1),FALSE) -> 1210.4957 | H10: =VLOOKUP($E10,Hybrid!$1:$1048576,MATCH(DATE(H$2,1,1),Hybrid!$A$1:$LI$1),FALSE) -> 1182.3382 | I10: =VLOOKUP($E10,Hybrid!$1:$1048576,MATCH(DATE(I$2,1,1),Hybrid!$A$1:$LI$1),FALSE) -> 1156.6734 | J10: =VLOOKUP($E10,Hybrid!$1:$1048576,MATCH(DATE(J$2,1,1),Hybrid!$A$1:$LI$1),FALSE) -> 1131.9653 | K10: =VLOOKUP($E10,Hybrid!$1:$1048576,MATCH(DATE(K$2,1,1),Hybrid!$A$1:$LI$1),FALSE) -> 1107.3163 | L10: =VLOOKUP($E10,Hybrid!$1:$1048576,MATCH(DATE(L$2,1,1),Hybrid!$A$1:$LI$1),FALSE) -> 1082.2791 | M10: =VLOOKUP($E10,Hybrid!$1:$1048576,MATCH(DATE(M$2,1,1),Hybrid!$A$1:$LI$1),FALSE) -> 1056.6745 | ... AO10: =VLOOKUP($E10,Hybrid!$1:$1048576,MATCH(DATE(AO$2,1,1),Hybrid!$A$1:$LI$1),FALSE) -> 307.18098
D11: class G | E11: AUTO_cg_cfut_2 | F11: =VLOOKUP($E11,Hybrid!$1:$1048576,MATCH(DATE(F$2,1,1),Hybrid!$A$1:$LI$1),FALSE) -> 2239.6206 | G11: =VLOOKUP($E11,Hybrid!$1:$1048576,MATCH(DATE(G$2,1,1),Hybrid!$A$1:$LI$1),FALSE) -> 2182.9572 | H11: =VLOOKUP($E11,Hybrid!$1:$1048576,MATCH(DATE(H$2,1,1),Hybrid!$A$1:$LI$1),FALSE) -> 2132.4256 | I11: =VLOOKUP($E11,Hybrid!$1:$1048576,MATCH(DATE(I$2,1,1),Hybrid!$A$1:$LI$1),FALSE) -> 2083.1395 | J11: =VLOOKUP($E11,Hybrid!$1:$1048576,MATCH(DATE(J$2,1,1),Hybrid!$A$1:$LI$1),FALSE) -> 2032.4729 | K11: =VLOOKUP($E11,Hybrid!$1:$1048576,MATCH(DATE(K$2,1,1),Hybrid!$A$1:$LI$1),FALSE) -> 1979.1945 | L11: =VLOOKUP($E11,Hybrid!$1:$1048576,MATCH(DATE(L$2,1,1),Hybrid!$A$1:$LI$1),FALSE) -> 1922.9745 | M11: =VLOOKUP($E11,Hybrid!$1:$1048576,MATCH(DATE(M$2,1,1),Hybrid!$A$1:$LI$1),FALSE) -> 1863.9747 | ... AO11: =VLOOKUP($E11,Hybrid!$1:$1048576,MATCH(DATE(AO$2,1,1),Hybrid!$A$1:$LI$1),FALSE) -> 369.29013
C12: ELEC | E12: AUTO_cele_2 | F12: =VLOOKUP($E12,Hybrid!$1:$1048576,MATCH(DATE(F$2,1,1),Hybrid!$A$1:$LI$1),FALSE) -> 44.765 | G12: =VLOOKUP($E12,Hybrid!$1:$1048576,MATCH(DATE(G$2,1,1),Hybrid!$A$1:$LI$1),FALSE) -> 62.431907 | H12: =VLOOKUP($E12,Hybrid!$1:$1048576,MATCH(DATE(H$2,1,1),Hybrid!$A$1:$LI$1),FALSE) -> 81.013139 | I12: =VLOOKUP($E12,Hybrid!$1:$1048576,MATCH(DATE(I$2,1,1),Hybrid!$A$1:$LI$1),FALSE) -> 100.11448 | J12: =VLOOKUP($E12,Hybrid!$1:$1048576,MATCH(DATE(J$2,1,1),Hybrid!$A$1:$LI$1),FALSE) -> 119.52341 | K12: =VLOOKUP($E12,Hybrid!$1:$1048576,MATCH(DATE(K$2,1,1),Hybrid!$A$1:$LI$1),FALSE) -> 139.17166 | L12: =VLOOKUP($E12,Hybrid!$1:$1048576,MATCH(DATE(L$2,1,1),Hybrid!$A$1:$LI$1),FALSE) -> 159.11464 | M12: =VLOOKUP($E12,Hybrid!$1:$1048576,MATCH(DATE(M$2,1,1),Hybrid!$A$1:$LI$1),FALSE) -> 179.46535 | ... AO12: =VLOOKUP($E12,Hybrid!$1:$1048576,MATCH(DATE(AO$2,1,1),Hybrid!$A$1:$LI$1),FALSE) -> 2495.6066
D13: class A | E13: AUTO_ca_cele_2 | F13: =VLOOKUP($E13,Hybrid!$1:$1048576,MATCH(DATE(F$2,1,1),Hybrid!$A$1:$LI$1),FALSE) -> 9.8427899 | G13: =VLOOKUP($E13,Hybrid!$1:$1048576,MATCH(DATE(G$2,1,1),Hybrid!$A$1:$LI$1),FALSE) -> 14.986855 | H13: =VLOOKUP($E13,Hybrid!$1:$1048576,MATCH(DATE(H$2,1,1),Hybrid!$A$1:$LI$1),FALSE) -> 20.441598 | I13: =VLOOKUP($E13,Hybrid!$1:$1048576,MATCH(DATE(I$2,1,1),Hybrid!$A$1:$LI$1),FALSE) -> 26.109475 | J13: =VLOOKUP($E13,Hybrid!$1:$1048576,MATCH(DATE(J$2,1,1),Hybrid!$A$1:$LI$1),FALSE) -> 31.93889 | K13: =VLOOKUP($E13,Hybrid!$1:$1048576,MATCH(DATE(K$2,1,1),Hybrid!$A$1:$LI$1),FALSE) -> 37.917119 | L13: =VLOOKUP($E13,Hybrid!$1:$1048576,MATCH(DATE(L$2,1,1),Hybrid!$A$1:$LI$1),FALSE) -> 44.066743 | M13: =VLOOKUP($E13,Hybrid!$1:$1048576,MATCH(DATE(M$2,1,1),Hybrid!$A$1:$LI$1),FALSE) -> 50.426862 | ... AO13: =VLOOKUP($E13,Hybrid!$1:$1048576,MATCH(DATE(AO$2,1,1),Hybrid!$A$1:$LI$1),FALSE) -> 915.33384
D14: class B | E14: AUTO_cb_cele_2 | F14: =VLOOKUP($E14,Hybrid!$1:$1048576,MATCH(DATE(F$2,1,1),Hybrid!$A$1:$LI$1),FALSE) -> 11.445717 | G14: =VLOOKUP($E14,Hybrid!$1:$1048576,MATCH(DATE(G$2,1,1),Hybrid!$A$1:$LI$1),FALSE) -> 16.298791 | H14: =VLOOKUP($E14,Hybrid!$1:$1048576,MATCH(DATE(H$2,1,1),Hybrid!$A$1:$LI$1),FALSE) -> 21.444778 | I14: =VLOOKUP($E14,Hybrid!$1:$1048576,MATCH(DATE(I$2,1,1),Hybrid!$A$1:$LI$1),FALSE) -> 26.78893 | J14: =VLOOKUP($E14,Hybrid!$1:$1048576,MATCH(DATE(J$2,1,1),Hybrid!$A$1:$LI$1),FALSE) -> 32.28194 | K14: =VLOOKUP($E14,Hybrid!$1:$1048576,MATCH(DATE(K$2,1,1),Hybrid!$A$1:$LI$1),FALSE) -> 37.912731 | L14: =VLOOKUP($E14,Hybrid!$1:$1048576,MATCH(DATE(L$2,1,1),Hybrid!$A$1:$LI$1),FALSE) -> 43.704512 | M14: =VLOOKUP($E14,Hybrid!$1:$1048576,MATCH(DATE(M$2,1,1),Hybrid!$A$1:$LI$1),FALSE) -> 49.696035 | ... AO14: =VLOOKUP($E14,Hybrid!$1:$1048576,MATCH(DATE(AO$2,1,1),Hybrid!$A$1:$LI$1),FALSE) -> 837.25868
D15: class C | E15: AUTO_cc_cele_2 | F15: =VLOOKUP($E15,Hybrid!$1:$1048576,MATCH(DATE(F$2,1,1),Hybrid!$A$1:$LI$1),FALSE) -> 9.4015406 | G15: =VLOOKUP($E15,Hybrid!$1:$1048576,MATCH(DATE(G$2,1,1),Hybrid!$A$1:$LI$1),FALSE) -> 12.697721 | H15: =VLOOKUP($E15,Hybrid!$1:$1048576,MATCH(DATE(H$2,1,1),Hybrid!$A$1:$LI$1),FALSE) -> 16.193052 | I15: =VLOOKUP($E15,Hybrid!$1:$1048576,MATCH(DATE(I$2,1,1),Hybrid!$A$1:$LI$1),FALSE) -> 19.821122 | J15: =VLOOKUP($E15,Hybrid!$1:$1048576,MATCH(DATE(J$2,1,1),Hybrid!$A$1:$LI$1),FALSE) -> 23.547853 | K15: =VLOOKUP($E15,Hybrid!$1:$1048576,MATCH(DATE(K$2,1,1),Hybrid!$A$1:$LI$1),FALSE) -> 27.366208 | L15: =VLOOKUP($E15,Hybrid!$1:$1048576,MATCH(DATE(L$2,1,1),Hybrid!$A$1:$LI$1),FALSE) -> 31.29309 | M15: =VLOOKUP($E15,Hybrid!$1:$1048576,MATCH(DATE(M$2,1,1),Hybrid!$A$1:$LI$1),FALSE) -> 35.355919 | ... AO15: =VLOOKUP($E15,Hybrid!$1:$1048576,MATCH(DATE(AO$2,1,1),Hybrid!$A$1:$LI$1),FALSE) -> 549.70794
D16: class D | E16: AUTO_cd_cele_2 | F16: =VLOOKUP($E16,Hybrid!$1:$1048576,MATCH(DATE(F$2,1,1),Hybrid!$A$1:$LI$1),FALSE) -> 5.7700713 | G16: =VLOOKUP($E16,Hybrid!$1:$1048576,MATCH(DATE(G$2,1,1),Hybrid!$A$1:$LI$1),FALSE) -> 7.5615669 | H16: =VLOOKUP($E16,Hybrid!$1:$1048576,MATCH(DATE(H$2,1,1),Hybrid!$A$1:$LI$1),FALSE) -> 9.4381353 | I16: =VLOOKUP($E16,Hybrid!$1:$1048576,MATCH(DATE(I$2,1,1),Hybrid!$A$1:$LI$1),FALSE) -> 11.352056 | J16: =VLOOKUP($E16,Hybrid!$1:$1048576,MATCH(DATE(J$2,1,1),Hybrid!$A$1:$LI$1),FALSE) -> 13.274162 | K16: =VLOOKUP($E16,Hybrid!$1:$1048576,MATCH(DATE(K$2,1,1),Hybrid!$A$1:$LI$1),FALSE) -> 15.18912 | L16: =VLOOKUP($E16,Hybrid!$1:$1048576,MATCH(DATE(L$2,1,1),Hybrid!$A$1:$LI$1),FALSE) -> 17.093136 | M16: =VLOOKUP($E16,Hybrid!$1:$1048576,MATCH(DATE(M$2,1,1),Hybrid!$A$1:$LI$1),FALSE) -> 18.988411 | ... AO16: =VLOOKUP($E16,Hybrid!$1:$1048576,MATCH(DATE(AO$2,1,1),Hybrid!$A$1:$LI$1),FALSE) -> 120.31725
D17: class E | E17: AUTO_ce_cele_2 | F17: =VLOOKUP($E17,Hybrid!$1:$1048576,MATCH(DATE(F$2,1,1),Hybrid!$A$1:$LI$1),FALSE) -> 3.4730441 | G17: =VLOOKUP($E17,Hybrid!$1:$1048576,MATCH(DATE(G$2,1,1),Hybrid!$A$1:$LI$1),FALSE) -> 4.5722504 | H17: =VLOOKUP($E17,Hybrid!$1:$1048576,MATCH(DATE(H$2,1,1),Hybrid!$A$1:$LI$1),FALSE) -> 5.7141145 | I17: =VLOOKUP($E17,Hybrid!$1:$1048576,MATCH(DATE(I$2,1,1),Hybrid!$A$1:$LI$1),FALSE) -> 6.8674553 | J17: =VLOOKUP($E17,Hybrid!$1:$1048576,MATCH(DATE(J$2,1,1),Hybrid!$A$1:$LI$1),FALSE) -> 8.0136634 | K17: =VLOOKUP($E17,Hybrid!$1:$1048576,MATCH(DATE(K$2,1,1),Hybrid!$A$1:$LI$1),FALSE) -> 9.1432705 | L17: =VLOOKUP($E17,Hybrid!$1:$1048576,MATCH(DATE(L$2,1,1),Hybrid!$A$1:$LI$1),FALSE) -> 10.254089 | M17: =VLOOKUP($E17,Hybrid!$1:$1048576,MATCH(DATE(M$2,1,1),Hybrid!$A$1:$LI$1),FALSE) -> 11.347514 | ... AO17: =VLOOKUP($E17,Hybrid!$1:$1048576,MATCH(DATE(AO$2,1,1),Hybrid!$A$1:$LI$1),FALSE) -> 56.507023
D18: class F | E18: AUTO_cf_cele_2 | F18: =VLOOKUP($E18,Hybrid!$1:$1048576,MATCH(DATE(F$2,1,1),Hybrid!$A$1:$LI$1),FALSE) -> 1.7251505 | G18: =VLOOKUP($E18,Hybrid!$1:$1048576,MATCH(DATE(G$2,1,1),Hybrid!$A$1:$LI$1),FALSE) -> 2.2444156 | H18: =VLOOKUP($E18,Hybrid!$1:$1048576,MATCH(DATE(H$2,1,1),Hybrid!$A$1:$LI$1),FALSE) -> 2.766963 | I18: =VLOOKUP($E18,Hybrid!$1:$1048576,MATCH(DATE(I$2,1,1),Hybrid!$A$1:$LI$1),FALSE) -> 3.2740974 | J18: =VLOOKUP($E18,Hybrid!$1:$1048576,MATCH(DATE(J$2,1,1),Hybrid!$A$1:$LI$1),FALSE) -> 3.755207 | K18: =VLOOKUP($E18,Hybrid!$1:$1048576,MATCH(DATE(K$2,1,1),Hybrid!$A$1:$LI$1),FALSE) -> 4.205033 | L18: =VLOOKUP($E18,Hybrid!$1:$1048576,MATCH(DATE(L$2,1,1),Hybrid!$A$1:$LI$1),FALSE) -> 4.622085 | M18: =VLOOKUP($E18,Hybrid!$1:$1048576,MATCH(DATE(M$2,1,1),Hybrid!$A$1:$LI$1),FALSE) -> 5.0067778 | ... AO18: =VLOOKUP($E18,Hybrid!$1:$1048576,MATCH(DATE(AO$2,1,1),Hybrid!$A$1:$LI$1),FALSE) -> 8.0802696
D19: class G | E19: AUTO_cg_cele_2 | F19: =VLOOKUP($E19,Hybrid!$1:$1048576,MATCH(DATE(F$2,1,1),Hybrid!$A$1:$LI$1),FALSE) -> 3.1066862 | G19: =VLOOKUP($E19,Hybrid!$1:$1048576,MATCH(DATE(G$2,1,1),Hybrid!$A$1:$LI$1),FALSE) -> 4.0703072 | H19: =VLOOKUP($E19,Hybrid!$1:$1048576,MATCH(DATE(H$2,1,1),Hybrid!$A$1:$LI$1),FALSE) -> 5.0144974 | I19: =VLOOKUP($E19,Hybrid!$1:$1048576,MATCH(DATE(I$2,1,1),Hybrid!$A$1:$LI$1),FALSE) -> 5.9013474 | J19: =VLOOKUP($E19,Hybrid!$1:$1048576,MATCH(DATE(J$2,1,1),Hybrid!$A$1:$LI$1),FALSE) -> 6.7116982 | K19: =VLOOKUP($E19,Hybrid!$1:$1048576,MATCH(DATE(K$2,1,1),Hybrid!$A$1:$LI$1),FALSE) -> 7.4381797 | L19: =VLOOKUP($E19,Hybrid!$1:$1048576,MATCH(DATE(L$2,1,1),Hybrid!$A$1:$LI$1),FALSE) -> 8.0809851 | M19: =VLOOKUP($E19,Hybrid!$1:$1048576,MATCH(DATE(M$2,1,1),Hybrid!$A$1:$LI$1),FALSE) -> 8.6438338 | ... AO19: =VLOOKUP($E19,Hybrid!$1:$1048576,MATCH(DATE(AO$2,1,1),Hybrid!$A$1:$LI$1),FALSE) -> 8.4015579
C20: GAS | E20: AUTO_cgas_2 | F20: =VLOOKUP($E20,Hybrid!$1:$1048576,MATCH(DATE(F$2,1,1),Hybrid!$A$1:$LI$1),FALSE) -> 1.936 | G20: =VLOOKUP($E20,Hybrid!$1:$1048576,MATCH(DATE(G$2,1,1),Hybrid!$A$1:$LI$1),FALSE) -> 1.9916142 | H20: =VLOOKUP($E20,Hybrid!$1:$1048576,MATCH(DATE(H$2,1,1),Hybrid!$A$1:$LI$1),FALSE) -> 2.0574397 | I20: =VLOOKUP($E20,Hybrid!$1:$1048576,MATCH(DATE(I$2,1,1),Hybrid!$A$1:$LI$1),FALSE) -> 2.1286903 | J20: =VLOOKUP($E20,Hybrid!$1:$1048576,MATCH(DATE(J$2,1,1),Hybrid!$A$1:$LI$1),FALSE) -> 2.2021882 | K20: =VLOOKUP($E20,Hybrid!$1:$1048576,MATCH(DATE(K$2,1,1),Hybrid!$A$1:$LI$1),FALSE) -> 2.2758741 | L20: =VLOOKUP($E20,Hybrid!$1:$1048576,MATCH(DATE(L$2,1,1),Hybrid!$A$1:$LI$1),FALSE) -> 2.3486159 | M20: =VLOOKUP($E20,Hybrid!$1:$1048576,MATCH(DATE(M$2,1,1),Hybrid!$A$1:$LI$1),FALSE) -> 2.4198739 | ... AO20: =VLOOKUP($E20,Hybrid!$1:$1048576,MATCH(DATE(AO$2,1,1),Hybrid!$A$1:$LI$1),FALSE) -> 3.4989915
D21: class A | E21: AUTO_ca_cgas_2 | F21: =VLOOKUP($E21,Hybrid!$1:$1048576,MATCH(DATE(F$2,1,1),Hybrid!$A$1:$LI$1),FALSE) -> 0.4256817 | G21: =VLOOKUP($E21,Hybrid!$1:$1048576,MATCH(DATE(G$2,1,1),Hybrid!$A$1:$LI$1),FALSE) -> 0.44933756 | H21: =VLOOKUP($E21,Hybrid!$1:$1048576,MATCH(DATE(H$2,1,1),Hybrid!$A$1:$LI$1),FALSE) -> 0.47589006 | I21: =VLOOKUP($E21,Hybrid!$1:$1048576,MATCH(DATE(I$2,1,1),Hybrid!$A$1:$LI$1),FALSE) -> 0.50410475 | J21: =VLOOKUP($E21,Hybrid!$1:$1048576,MATCH(DATE(J$2,1,1),Hybrid!$A$1:$LI$1),FALSE) -> 0.53313831 | K21: =VLOOKUP($E21,Hybrid!$1:$1048576,MATCH(DATE(K$2,1,1),Hybrid!$A$1:$LI$1),FALSE) -> 0.56242832 | L21: =VLOOKUP($E21,Hybrid!$1:$1048576,MATCH(DATE(L$2,1,1),Hybrid!$A$1:$LI$1),FALSE) -> 0.59165871 | M21: =VLOOKUP($E21,Hybrid!$1:$1048576,MATCH(DATE(M$2,1,1),Hybrid!$A$1:$LI$1),FALSE) -> 0.62067264 | ... AO21: =VLOOKUP($E21,Hybrid!$1:$1048576,MATCH(DATE(AO$2,1,1),Hybrid!$A$1:$LI$1),FALSE) -> 1.213193
D22: class B | E22: AUTO_cb_cgas_2 | F22: =VLOOKUP($E22,Hybrid!$1:$1048576,MATCH(DATE(F$2,1,1),Hybrid!$A$1:$LI$1),FALSE) -> 0.49500523 | G22: =VLOOKUP($E22,Hybrid!$1:$1048576,MATCH(DATE(G$2,1,1),Hybrid!$A$1:$LI$1),FALSE) -> 0.51226256 | H22: =VLOOKUP($E22,Hybrid!$1:$1048576,MATCH(DATE(H$2,1,1),Hybrid!$A$1:$LI$1),FALSE) -> 0.53253811 | I22: =VLOOKUP($E22,Hybrid!$1:$1048576,MATCH(DATE(I$2,1,1),Hybrid!$A$1:$LI$1),FALSE) -> 0.5546014 | J22: =VLOOKUP($E22,Hybrid!$1:$1048576,MATCH(DATE(J$2,1,1),Hybrid!$A$1:$LI$1),FALSE) -> 0.57760987 | K22: =VLOOKUP($E22,Hybrid!$1:$1048576,MATCH(DATE(K$2,1,1),Hybrid!$A$1:$LI$1),FALSE) -> 0.60099756 | L22: =VLOOKUP($E22,Hybrid!$1:$1048576,MATCH(DATE(L$2,1,1),Hybrid!$A$1:$LI$1),FALSE) -> 0.62443887 | M22: =VLOOKUP($E22,Hybrid!$1:$1048576,MATCH(DATE(M$2,1,1),Hybrid!$A$1:$LI$1),FALSE) -> 0.64776464 | ... AO22: =VLOOKUP($E22,Hybrid!$1:$1048576,MATCH(DATE(AO$2,1,1),Hybrid!$A$1:$LI$1),FALSE) -> 1.0802066
D23: class C | E23: AUTO_cc_cgas_2 | F23: =VLOOKUP($E23,Hybrid!$1:$1048576,MATCH(DATE(F$2,1,1),Hybrid!$A$1:$LI$1),FALSE) -> 0.40659852 | G23: =VLOOKUP($E23,Hybrid!$1:$1048576,MATCH(DATE(G$2,1,1),Hybrid!$A$1:$LI$1),FALSE) -> 0.41450652 | H23: =VLOOKUP($E23,Hybrid!$1:$1048576,MATCH(DATE(H$2,1,1),Hybrid!$A$1:$LI$1),FALSE) -> 0.42468516 | I23: =VLOOKUP($E23,Hybrid!$1:$1048576,MATCH(DATE(I$2,1,1),Hybrid!$A$1:$LI$1),FALSE) -> 0.43625097 | J23: =VLOOKUP($E23,Hybrid!$1:$1048576,MATCH(DATE(J$2,1,1),Hybrid!$A$1:$LI$1),FALSE) -> 0.44859764 | K23: =VLOOKUP($E23,Hybrid!$1:$1048576,MATCH(DATE(K$2,1,1),Hybrid!$A$1:$LI$1),FALSE) -> 0.46131529 | L23: =VLOOKUP($E23,Hybrid!$1:$1048576,MATCH(DATE(L$2,1,1),Hybrid!$A$1:$LI$1),FALSE) -> 0.47416315 | M23: =VLOOKUP($E23,Hybrid!$1:$1048576,MATCH(DATE(M$2,1,1),Hybrid!$A$1:$LI$1),FALSE) -> 0.48701125 | ... AO23: =VLOOKUP($E23,Hybrid!$1:$1048576,MATCH(DATE(AO$2,1,1),Hybrid!$A$1:$LI$1),FALSE) -> 0.69676976
D24: class D | E24: AUTO_cd_cgas_2 | F24: =VLOOKUP($E24,Hybrid!$1:$1048576,MATCH(DATE(F$2,1,1),Hybrid!$A$1:$LI$1),FALSE) -> 0.24954447 | G24: =VLOOKUP($E24,Hybrid!$1:$1048576,MATCH(DATE(G$2,1,1),Hybrid!$A$1:$LI$1),FALSE) -> 0.25231575 | H24: =VLOOKUP($E24,Hybrid!$1:$1048576,MATCH(DATE(H$2,1,1),Hybrid!$A$1:$LI$1),FALSE) -> 0.25627338 | I24: =VLOOKUP($E24,Hybrid!$1:$1048576,MATCH(DATE(I$2,1,1),Hybrid!$A$1:$LI$1),FALSE) -> 0.26088609 | J24: =VLOOKUP($E24,Hybrid!$1:$1048576,MATCH(DATE(J$2,1,1),Hybrid!$A$1:$LI$1),FALSE) -> 0.26579685 | K24: =VLOOKUP($E24,Hybrid!$1:$1048576,MATCH(DATE(K$2,1,1),Hybrid!$A$1:$LI$1),FALSE) -> 0.27076949 | L24: =VLOOKUP($E24,Hybrid!$1:$1048576,MATCH(DATE(L$2,1,1),Hybrid!$A$1:$LI$1),FALSE) -> 0.27566723 | M24: =VLOOKUP($E24,Hybrid!$1:$1048576,MATCH(DATE(M$2,1,1),Hybrid!$A$1:$LI$1),FALSE) -> 0.28041732 | ... AO24: =VLOOKUP($E24,Hybrid!$1:$1048576,MATCH(DATE(AO$2,1,1),Hybrid!$A$1:$LI$1),FALSE) -> 0.29344625
D25: class E | E25: AUTO_ce_cgas_2 | F25: =VLOOKUP($E25,Hybrid!$1:$1048576,MATCH(DATE(F$2,1,1),Hybrid!$A$1:$LI$1),FALSE) -> 0.15020247 | G25: =VLOOKUP($E25,Hybrid!$1:$1048576,MATCH(DATE(G$2,1,1),Hybrid!$A$1:$LI$1),FALSE) -> 0.1520586 | H25: =VLOOKUP($E25,Hybrid!$1:$1048576,MATCH(DATE(H$2,1,1),Hybrid!$A$1:$LI$1),FALSE) -> 0.15454056 | I25: =VLOOKUP($E25,Hybrid!$1:$1048576,MATCH(DATE(I$2,1,1),Hybrid!$A$1:$LI$1),FALSE) -> 0.15730455 | J25: =VLOOKUP($E25,Hybrid!$1:$1048576,MATCH(DATE(J$2,1,1),Hybrid!$A$1:$LI$1),FALSE) -> 0.16012548 | K25: =VLOOKUP($E25,Hybrid!$1:$1048576,MATCH(DATE(K$2,1,1),Hybrid!$A$1:$LI$1),FALSE) -> 0.16285907 | L25: =VLOOKUP($E25,Hybrid!$1:$1048576,MATCH(DATE(L$2,1,1),Hybrid!$A$1:$LI$1),FALSE) -> 0.16542509 | M25: =VLOOKUP($E25,Hybrid!$1:$1048576,MATCH(DATE(M$2,1,1),Hybrid!$A$1:$LI$1),FALSE) -> 0.16778398 | ... AO25: =VLOOKUP($E25,Hybrid!$1:$1048576,MATCH(DATE(AO$2,1,1),Hybrid!$A$1:$LI$1),FALSE) -> 0.13934386
D26: class F | E26: AUTO_cf_cgas_2 | F26: =VLOOKUP($E26,Hybrid!$1:$1048576,MATCH(DATE(F$2,1,1),Hybrid!$A$1:$LI$1),FALSE) -> 0.074609436 | G26: =VLOOKUP($E26,Hybrid!$1:$1048576,MATCH(DATE(G$2,1,1),Hybrid!$A$1:$LI$1),FALSE) -> 0.075290478 | H26: =VLOOKUP($E26,Hybrid!$1:$1048576,MATCH(DATE(H$2,1,1),Hybrid!$A$1:$LI$1),FALSE) -> 0.076133289 | I26: =VLOOKUP($E26,Hybrid!$1:$1048576,MATCH(DATE(I$2,1,1),Hybrid!$A$1:$LI$1),FALSE) -> 0.076948744 | J26: =VLOOKUP($E26,Hybrid!$1:$1048576,MATCH(DATE(J$2,1,1),Hybrid!$A$1:$LI$1),FALSE) -> 0.077625818 | K26: =VLOOKUP($E26,Hybrid!$1:$1048576,MATCH(DATE(K$2,1,1),Hybrid!$A$1:$LI$1),FALSE) -> 0.078104003 | L26: =VLOOKUP($E26,Hybrid!$1:$1048576,MATCH(DATE(L$2,1,1),Hybrid!$A$1:$LI$1),FALSE) -> 0.078358543 | M26: =VLOOKUP($E26,Hybrid!$1:$1048576,MATCH(DATE(M$2,1,1),Hybrid!$A$1:$LI$1),FALSE) -> 0.078385812 | ... AO26: =VLOOKUP($E26,Hybrid!$1:$1048576,MATCH(DATE(AO$2,1,1),Hybrid!$A$1:$LI$1),FALSE) -> 0.033841539
D27: class G | E27: AUTO_cg_cgas_2 | F27: =VLOOKUP($E27,Hybrid!$1:$1048576,MATCH(DATE(F$2,1,1),Hybrid!$A$1:$LI$1),FALSE) -> 0.13435819 | G27: =VLOOKUP($E27,Hybrid!$1:$1048576,MATCH(DATE(G$2,1,1),Hybrid!$A$1:$LI$1),FALSE) -> 0.1358427 | H27: =VLOOKUP($E27,Hybrid!$1:$1048576,MATCH(DATE(H$2,1,1),Hybrid!$A$1:$LI$1),FALSE) -> 0.1373791 | I27: =VLOOKUP($E27,Hybrid!$1:$1048576,MATCH(DATE(I$2,1,1),Hybrid!$A$1:$LI$1),FALSE) -> 0.13859375 | J27: =VLOOKUP($E27,Hybrid!$1:$1048576,MATCH(DATE(J$2,1,1),Hybrid!$A$1:$LI$1),FALSE) -> 0.13929428 | K27: =VLOOKUP($E27,Hybrid!$1:$1048576,MATCH(DATE(K$2,1,1),Hybrid!$A$1:$LI$1),FALSE) -> 0.13940036 | L27: =VLOOKUP($E27,Hybrid!$1:$1048576,MATCH(DATE(L$2,1,1),Hybrid!$A$1:$LI$1),FALSE) -> 0.13890435 | M27: =VLOOKUP($E27,Hybrid!$1:$1048576,MATCH(DATE(M$2,1,1),Hybrid!$A$1:$LI$1),FALSE) -> 0.13783826 | ... AO27: =VLOOKUP($E27,Hybrid!$1:$1048576,MATCH(DATE(AO$2,1,1),Hybrid!$A$1:$LI$1),FALSE) -> 0.042190416
C28: TOTAL STOCK BASELINE | E28: AUTO_0 | F28: =VLOOKUP($E28,Hybrid!$1:$1048576,MATCH(DATE(F$2,1,1),Hybrid!$A$1:$LI$1),FALSE) -> 32317.941 | G28: =VLOOKUP($E28,Hybrid!$1:$1048576,MATCH(DATE(G$2,1,1),Hybrid!$A$1:$LI$1),FALSE) -> 31931.625 | H28: =VLOOKUP($E28,Hybrid!$1:$1048576,MATCH(DATE(H$2,1,1),Hybrid!$A$1:$LI$1),FALSE) -> 31743.508 | I28: =VLOOKUP($E28,Hybrid!$1:$1048576,MATCH(DATE(I$2,1,1),Hybrid!$A$1:$LI$1),FALSE) -> 31687.792 | J28: =VLOOKUP($E28,Hybrid!$1:$1048576,MATCH(DATE(J$2,1,1),Hybrid!$A$1:$LI$1),FALSE) -> 31720.643 | K28: =VLOOKUP($E28,Hybrid!$1:$1048576,MATCH(DATE(K$2,1,1),Hybrid!$A$1:$LI$1),FALSE) -> 31813.337 | L28: =VLOOKUP($E28,Hybrid!$1:$1048576,MATCH(DATE(L$2,1,1),Hybrid!$A$1:$LI$1),FALSE) -> 31947.162 | M28: =VLOOKUP($E28,Hybrid!$1:$1048576,MATCH(DATE(M$2,1,1),Hybrid!$A$1:$LI$1),FALSE) -> 32109.877 | ... AO28: =VLOOKUP($E28,Hybrid!$1:$1048576,MATCH(DATE(AO$2,1,1),Hybrid!$A$1:$LI$1),FALSE) -> 38673.292
C29: OIL | E29: AUTO_cfut_0 | F29: =VLOOKUP($E29,Hybrid!$1:$1048576,MATCH(DATE(F$2,1,1),Hybrid!$A$1:$LI$1),FALSE) -> 32271.24 | G29: =VLOOKUP($E29,Hybrid!$1:$1048576,MATCH(DATE(G$2,1,1),Hybrid!$A$1:$LI$1),FALSE) -> 31867.185 | H29: =VLOOKUP($E29,Hybrid!$1:$1048576,MATCH(DATE(H$2,1,1),Hybrid!$A$1:$LI$1),FALSE) -> 31660.486 | I29: =VLOOKUP($E29,Hybrid!$1:$1048576,MATCH(DATE(I$2,1,1),Hybrid!$A$1:$LI$1),FALSE) -> 31585.838 | J29: =VLOOKUP($E29,Hybrid!$1:$1048576,MATCH(DATE(J$2,1,1),Hybrid!$A$1:$LI$1),FALSE) -> 31599.721 | K29: =VLOOKUP($E29,Hybrid!$1:$1048576,MATCH(DATE(K$2,1,1),Hybrid!$A$1:$LI$1),FALSE) -> 31673.603 | L29: =VLOOKUP($E29,Hybrid!$1:$1048576,MATCH(DATE(L$2,1,1),Hybrid!$A$1:$LI$1),FALSE) -> 31788.887 | M29: =VLOOKUP($E29,Hybrid!$1:$1048576,MATCH(DATE(M$2,1,1),Hybrid!$A$1:$LI$1),FALSE) -> 31933.397 | ... AO29: =VLOOKUP($E29,Hybrid!$1:$1048576,MATCH(DATE(AO$2,1,1),Hybrid!$A$1:$LI$1),FALSE) -> 38101.905
D30: class A | E30: AUTO_ca_cfut_0 | F30: =VLOOKUP($E30,Hybrid!$1:$1048576,MATCH(DATE(F$2,1,1),Hybrid!$A$1:$LI$1),FALSE) -> 7095.7005 | G30: =VLOOKUP($E30,Hybrid!$1:$1048576,MATCH(DATE(G$2,1,1),Hybrid!$A$1:$LI$1),FALSE) -> 7143.1788 | H30: =VLOOKUP($E30,Hybrid!$1:$1048576,MATCH(DATE(H$2,1,1),Hybrid!$A$1:$LI$1),FALSE) -> 7239.81 | I30: =VLOOKUP($E30,Hybrid!$1:$1048576,MATCH(DATE(I$2,1,1),Hybrid!$A$1:$LI$1),FALSE) -> 7369.0432 | J30: =VLOOKUP($E30,Hybrid!$1:$1048576,MATCH(DATE(J$2,1,1),Hybrid!$A$1:$LI$1),FALSE) -> 7519.6803 | K30: =VLOOKUP($E30,Hybrid!$1:$1048576,MATCH(DATE(K$2,1,1),Hybrid!$A$1:$LI$1),FALSE) -> 7684.2986 | L30: =VLOOKUP($E30,Hybrid!$1:$1048576,MATCH(DATE(L$2,1,1),Hybrid!$A$1:$LI$1),FALSE) -> 7858.0379 | M30: =VLOOKUP($E30,Hybrid!$1:$1048576,MATCH(DATE(M$2,1,1),Hybrid!$A$1:$LI$1),FALSE) -> 8037.7298 | ... AO30: =VLOOKUP($E30,Hybrid!$1:$1048576,MATCH(DATE(AO$2,1,1),Hybrid!$A$1:$LI$1),FALSE) -> 13271.9
D31: class B | E31: AUTO_cb_cfut_0 | F31: =VLOOKUP($E31,Hybrid!$1:$1048576,MATCH(DATE(F$2,1,1),Hybrid!$A$1:$LI$1),FALSE) -> 8251.2564 | G31: =VLOOKUP($E31,Hybrid!$1:$1048576,MATCH(DATE(G$2,1,1),Hybrid!$A$1:$LI$1),FALSE) -> 8184.1785 | H31: =VLOOKUP($E31,Hybrid!$1:$1048576,MATCH(DATE(H$2,1,1),Hybrid!$A$1:$LI$1),FALSE) -> 8171.8779 | I31: =VLOOKUP($E31,Hybrid!$1:$1048576,MATCH(DATE(I$2,1,1),Hybrid!$A$1:$LI$1),FALSE) -> 8197.5342 | J31: =VLOOKUP($E31,Hybrid!$1:$1048576,MATCH(DATE(J$2,1,1),Hybrid!$A$1:$LI$1),FALSE) -> 8249.6491 | K31: =VLOOKUP($E31,Hybrid!$1:$1048576,MATCH(DATE(K$2,1,1),Hybrid!$A$1:$LI$1),FALSE) -> 8320.4704 | L31: =VLOOKUP($E31,Hybrid!$1:$1048576,MATCH(DATE(L$2,1,1),Hybrid!$A$1:$LI$1),FALSE) -> 8404.7877 | M31: =VLOOKUP($E31,Hybrid!$1:$1048576,MATCH(DATE(M$2,1,1),Hybrid!$A$1:$LI$1),FALSE) -> 8499.0715 | ... AO31: =VLOOKUP($E31,Hybrid!$1:$1048576,MATCH(DATE(AO$2,1,1),Hybrid!$A$1:$LI$1),FALSE) -> 11875.349
D32: class C | E32: AUTO_cc_cfut_0 | F32: =VLOOKUP($E32,Hybrid!$1:$1048576,MATCH(DATE(F$2,1,1),Hybrid!$A$1:$LI$1),FALSE) -> 6777.6025 | G32: =VLOOKUP($E32,Hybrid!$1:$1048576,MATCH(DATE(G$2,1,1),Hybrid!$A$1:$LI$1),FALSE) -> 6647.7392 | H32: =VLOOKUP($E32,Hybrid!$1:$1048576,MATCH(DATE(H$2,1,1),Hybrid!$A$1:$LI$1),FALSE) -> 6561.4778 | I32: =VLOOKUP($E32,Hybrid!$1:$1048576,MATCH(DATE(I$2,1,1),Hybrid!$A$1:$LI$1),FALSE) -> 6506.5051 | J32: =VLOOKUP($E32,Hybrid!$1:$1048576,MATCH(DATE(J$2,1,1),Hybrid!$A$1:$LI$1),FALSE) -> 6474.3214 | K32: =VLOOKUP($E32,Hybrid!$1:$1048576,MATCH(DATE(K$2,1,1),Hybrid!$A$1:$LI$1),FALSE) -> 6459.1067 | L32: =VLOOKUP($E32,Hybrid!$1:$1048576,MATCH(DATE(L$2,1,1),Hybrid!$A$1:$LI$1),FALSE) -> 6456.8591 | M32: =VLOOKUP($E32,Hybrid!$1:$1048576,MATCH(DATE(M$2,1,1),Hybrid!$A$1:$LI$1),FALSE) -> 6464.7815 | ... AO32: =VLOOKUP($E32,Hybrid!$1:$1048576,MATCH(DATE(AO$2,1,1),Hybrid!$A$1:$LI$1),FALSE) -> 7687.7208
D33: class D | E33: AUTO_cd_cfut_0 | F33: =VLOOKUP($E33,Hybrid!$1:$1048576,MATCH(DATE(F$2,1,1),Hybrid!$A$1:$LI$1),FALSE) -> 4159.6639 | G33: =VLOOKUP($E33,Hybrid!$1:$1048576,MATCH(DATE(G$2,1,1),Hybrid!$A$1:$LI$1),FALSE) -> 4055.1231 | H33: =VLOOKUP($E33,Hybrid!$1:$1048576,MATCH(DATE(H$2,1,1),Hybrid!$A$1:$LI$1),FALSE) -> 3975.2329 | I33: =VLOOKUP($E33,Hybrid!$1:$1048576,MATCH(DATE(I$2,1,1),Hybrid!$A$1:$LI$1),FALSE) -> 3912.5808 | J33: =VLOOKUP($E33,Hybrid!$1:$1048576,MATCH(DATE(J$2,1,1),Hybrid!$A$1:$LI$1),FALSE) -> 3862.1234 | K33: =VLOOKUP($E33,Hybrid!$1:$1048576,MATCH(DATE(K$2,1,1),Hybrid!$A$1:$LI$1),FALSE) -> 3820.4516 | L33: =VLOOKUP($E33,Hybrid!$1:$1048576,MATCH(DATE(L$2,1,1),Hybrid!$A$1:$LI$1),FALSE) -> 3785.2435 | M33: =VLOOKUP($E33,Hybrid!$1:$1048576,MATCH(DATE(M$2,1,1),Hybrid!$A$1:$LI$1),FALSE) -> 3754.8857 | ... AO33: =VLOOKUP($E33,Hybrid!$1:$1048576,MATCH(DATE(AO$2,1,1),Hybrid!$A$1:$LI$1),FALSE) -> 3102.3334
D34: class E | E34: AUTO_ce_cfut_0 | F34: =VLOOKUP($E34,Hybrid!$1:$1048576,MATCH(DATE(F$2,1,1),Hybrid!$A$1:$LI$1),FALSE) -> 2503.7292 | G34: =VLOOKUP($E34,Hybrid!$1:$1048576,MATCH(DATE(G$2,1,1),Hybrid!$A$1:$LI$1),FALSE) -> 2443.054 | H34: =VLOOKUP($E34,Hybrid!$1:$1048576,MATCH(DATE(H$2,1,1),Hybrid!$A$1:$LI$1),FALSE) -> 2396.145 | I34: =VLOOKUP($E34,Hybrid!$1:$1048576,MATCH(DATE(I$2,1,1),Hybrid!$A$1:$LI$1),FALSE) -> 2358.2745 | J34: =VLOOKUP($E34,Hybrid!$1:$1048576,MATCH(DATE(J$2,1,1),Hybrid!$A$1:$LI$1),FALSE) -> 2326.3079 | K34: =VLOOKUP($E34,Hybrid!$1:$1048576,MATCH(DATE(K$2,1,1),Hybrid!$A$1:$LI$1),FALSE) -> 2298.1904 | L34: =VLOOKUP($E34,Hybrid!$1:$1048576,MATCH(DATE(L$2,1,1),Hybrid!$A$1:$LI$1),FALSE) -> 2272.5718 | M34: =VLOOKUP($E34,Hybrid!$1:$1048576,MATCH(DATE(M$2,1,1),Hybrid!$A$1:$LI$1),FALSE) -> 2248.5516 | ... AO34: =VLOOKUP($E34,Hybrid!$1:$1048576,MATCH(DATE(AO$2,1,1),Hybrid!$A$1:$LI$1),FALSE) -> 1454.1661
D35: class F | E35: AUTO_cf_cfut_0 | F35: =VLOOKUP($E35,Hybrid!$1:$1048576,MATCH(DATE(F$2,1,1),Hybrid!$A$1:$LI$1),FALSE) -> 1243.6668 | G35: =VLOOKUP($E35,Hybrid!$1:$1048576,MATCH(DATE(G$2,1,1),Hybrid!$A$1:$LI$1),FALSE) -> 1210.6549 | H35: =VLOOKUP($E35,Hybrid!$1:$1048576,MATCH(DATE(H$2,1,1),Hybrid!$A$1:$LI$1),FALSE) -> 1182.7476 | I35: =VLOOKUP($E35,Hybrid!$1:$1048576,MATCH(DATE(I$2,1,1),Hybrid!$A$1:$LI$1),FALSE) -> 1157.3995 | J35: =VLOOKUP($E35,Hybrid!$1:$1048576,MATCH(DATE(J$2,1,1),Hybrid!$A$1:$LI$1),FALSE) -> 1133.0829 | K35: =VLOOKUP($E35,Hybrid!$1:$1048576,MATCH(DATE(K$2,1,1),Hybrid!$A$1:$LI$1),FALSE) -> 1108.9242 | L35: =VLOOKUP($E35,Hybrid!$1:$1048576,MATCH(DATE(L$2,1,1),Hybrid!$A$1:$LI$1),FALSE) -> 1084.4506 | M35: =VLOOKUP($E35,Hybrid!$1:$1048576,MATCH(DATE(M$2,1,1),Hybrid!$A$1:$LI$1),FALSE) -> 1059.4277 | ... AO35: =VLOOKUP($E35,Hybrid!$1:$1048576,MATCH(DATE(AO$2,1,1),Hybrid!$A$1:$LI$1),FALSE) -> 325.27338
D36: class G | E36: AUTO_cg_cfut_0 | F36: =VLOOKUP($E36,Hybrid!$1:$1048576,MATCH(DATE(F$2,1,1),Hybrid!$A$1:$LI$1),FALSE) -> 2239.6206 | G36: =VLOOKUP($E36,Hybrid!$1:$1048576,MATCH(DATE(G$2,1,1),Hybrid!$A$1:$LI$1),FALSE) -> 2183.2559 | H36: =VLOOKUP($E36,Hybrid!$1:$1048576,MATCH(DATE(H$2,1,1),Hybrid!$A$1:$LI$1),FALSE) -> 2133.1946 | I36: =VLOOKUP($E36,Hybrid!$1:$1048576,MATCH(DATE(I$2,1,1),Hybrid!$A$1:$LI$1),FALSE) -> 2084.5006 | J36: =VLOOKUP($E36,Hybrid!$1:$1048576,MATCH(DATE(J$2,1,1),Hybrid!$A$1:$LI$1),FALSE) -> 2034.5555 | K36: =VLOOKUP($E36,Hybrid!$1:$1048576,MATCH(DATE(K$2,1,1),Hybrid!$A$1:$LI$1),FALSE) -> 1982.161 | L36: =VLOOKUP($E36,Hybrid!$1:$1048576,MATCH(DATE(L$2,1,1),Hybrid!$A$1:$LI$1),FALSE) -> 1926.9369 | M36: =VLOOKUP($E36,Hybrid!$1:$1048576,MATCH(DATE(M$2,1,1),Hybrid!$A$1:$LI$1),FALSE) -> 1868.9489 | ... AO36: =VLOOKUP($E36,Hybrid!$1:$1048576,MATCH(DATE(AO$2,1,1),Hybrid!$A$1:$LI$1),FALSE) -> 385.16287
C37: ELEC | E37: AUTO_cele_0 | F37: =VLOOKUP($E37,Hybrid!$1:$1048576,MATCH(DATE(F$2,1,1),Hybrid!$A$1:$LI$1),FALSE) -> 44.765 | G37: =VLOOKUP($E37,Hybrid!$1:$1048576,MATCH(DATE(G$2,1,1),Hybrid!$A$1:$LI$1),FALSE) -> 62.448716 | H37: =VLOOKUP($E37,Hybrid!$1:$1048576,MATCH(DATE(H$2,1,1),Hybrid!$A$1:$LI$1),FALSE) -> 80.963971 | I37: =VLOOKUP($E37,Hybrid!$1:$1048576,MATCH(DATE(I$2,1,1),Hybrid!$A$1:$LI$1),FALSE) -> 99.823967 | J37: =VLOOKUP($E37,Hybrid!$1:$1048576,MATCH(DATE(J$2,1,1),Hybrid!$A$1:$LI$1),FALSE) -> 118.71772 | K37: =VLOOKUP($E37,Hybrid!$1:$1048576,MATCH(DATE(K$2,1,1),Hybrid!$A$1:$LI$1),FALSE) -> 137.4542 | L37: =VLOOKUP($E37,Hybrid!$1:$1048576,MATCH(DATE(L$2,1,1),Hybrid!$A$1:$LI$1),FALSE) -> 155.92054 | M37: =VLOOKUP($E37,Hybrid!$1:$1048576,MATCH(DATE(M$2,1,1),Hybrid!$A$1:$LI$1),FALSE) -> 174.05324 | ... AO37: =VLOOKUP($E37,Hybrid!$1:$1048576,MATCH(DATE(AO$2,1,1),Hybrid!$A$1:$LI$1),FALSE) -> 567.61281
D38: class A | E38: AUTO_ca_cele_0 | F38: =VLOOKUP($E38,Hybrid!$1:$1048576,MATCH(DATE(F$2,1,1),Hybrid!$A$1:$LI$1),FALSE) -> 9.8427899 | G38: =VLOOKUP($E38,Hybrid!$1:$1048576,MATCH(DATE(G$2,1,1),Hybrid!$A$1:$LI$1),FALSE) -> 14.990816 | H38: =VLOOKUP($E38,Hybrid!$1:$1048576,MATCH(DATE(H$2,1,1),Hybrid!$A$1:$LI$1),FALSE) -> 20.422984 | I38: =VLOOKUP($E38,Hybrid!$1:$1048576,MATCH(DATE(I$2,1,1),Hybrid!$A$1:$LI$1),FALSE) -> 26.012773 | J38: =VLOOKUP($E38,Hybrid!$1:$1048576,MATCH(DATE(J$2,1,1),Hybrid!$A$1:$LI$1),FALSE) -> 31.67695 | K38: =VLOOKUP($E38,Hybrid!$1:$1048576,MATCH(DATE(K$2,1,1),Hybrid!$A$1:$LI$1),FALSE) -> 37.362607 | L38: =VLOOKUP($E38,Hybrid!$1:$1048576,MATCH(DATE(L$2,1,1),Hybrid!$A$1:$LI$1),FALSE) -> 43.037132 | M38: =VLOOKUP($E38,Hybrid!$1:$1048576,MATCH(DATE(M$2,1,1),Hybrid!$A$1:$LI$1),FALSE) -> 48.681062 | ... AO38: =VLOOKUP($E38,Hybrid!$1:$1048576,MATCH(DATE(AO$2,1,1),Hybrid!$A$1:$LI$1),FALSE) -> 195.65638
D39: class B | E39: AUTO_cb_cele_0 | F39: =VLOOKUP($E39,Hybrid!$1:$1048576,MATCH(DATE(F$2,1,1),Hybrid!$A$1:$LI$1),FALSE) -> 11.445717 | G39: =VLOOKUP($E39,Hybrid!$1:$1048576,MATCH(DATE(G$2,1,1),Hybrid!$A$1:$LI$1),FALSE) -> 16.302056 | H39: =VLOOKUP($E39,Hybrid!$1:$1048576,MATCH(DATE(H$2,1,1),Hybrid!$A$1:$LI$1),FALSE) -> 21.423897 | I39: =VLOOKUP($E39,Hybrid!$1:$1048576,MATCH(DATE(I$2,1,1),Hybrid!$A$1:$LI$1),FALSE) -> 26.687145 | J39: =VLOOKUP($E39,Hybrid!$1:$1048576,MATCH(DATE(J$2,1,1),Hybrid!$A$1:$LI$1),FALSE) -> 32.010429 | K39: =VLOOKUP($E39,Hybrid!$1:$1048576,MATCH(DATE(K$2,1,1),Hybrid!$A$1:$LI$1),FALSE) -> 37.342129 | L39: =VLOOKUP($E39,Hybrid!$1:$1048576,MATCH(DATE(L$2,1,1),Hybrid!$A$1:$LI$1),FALSE) -> 42.650406 | M39: =VLOOKUP($E39,Hybrid!$1:$1048576,MATCH(DATE(M$2,1,1),Hybrid!$A$1:$LI$1),FALSE) -> 47.916153 | ... AO39: =VLOOKUP($E39,Hybrid!$1:$1048576,MATCH(DATE(AO$2,1,1),Hybrid!$A$1:$LI$1),FALSE) -> 177.032
D40: class C | E40: AUTO_cc_cele_0 | F40: =VLOOKUP($E40,Hybrid!$1:$1048576,MATCH(DATE(F$2,1,1),Hybrid!$A$1:$LI$1),FALSE) -> 9.4015406 | G40: =VLOOKUP($E40,Hybrid!$1:$1048576,MATCH(DATE(G$2,1,1),Hybrid!$A$1:$LI$1),FALSE) -> 12.69964 | H40: =VLOOKUP($E40,Hybrid!$1:$1048576,MATCH(DATE(H$2,1,1),Hybrid!$A$1:$LI$1),FALSE) -> 16.176695 | I40: =VLOOKUP($E40,Hybrid!$1:$1048576,MATCH(DATE(I$2,1,1),Hybrid!$A$1:$LI$1),FALSE) -> 19.745034 | J40: =VLOOKUP($E40,Hybrid!$1:$1048576,MATCH(DATE(J$2,1,1),Hybrid!$A$1:$LI$1),FALSE) -> 23.347366 | K40: =VLOOKUP($E40,Hybrid!$1:$1048576,MATCH(DATE(K$2,1,1),Hybrid!$A$1:$LI$1),FALSE) -> 26.947438 | L40: =VLOOKUP($E40,Hybrid!$1:$1048576,MATCH(DATE(L$2,1,1),Hybrid!$A$1:$LI$1),FALSE) -> 30.522894 | M40: =VLOOKUP($E40,Hybrid!$1:$1048576,MATCH(DATE(M$2,1,1),Hybrid!$A$1:$LI$1),FALSE) -> 34.060268 | ... AO40: =VLOOKUP($E40,Hybrid!$1:$1048576,MATCH(DATE(AO$2,1,1),Hybrid!$A$1:$LI$1),FALSE) -> 115.62675
D41: class D | E41: AUTO_cd_cele_0 | F41: =VLOOKUP($E41,Hybrid!$1:$1048576,MATCH(DATE(F$2,1,1),Hybrid!$A$1:$LI$1),FALSE) -> 5.7700713 | G41: =VLOOKUP($E41,Hybrid!$1:$1048576,MATCH(DATE(G$2,1,1),Hybrid!$A$1:$LI$1),FALSE) -> 7.5646068 | H41: =VLOOKUP($E41,Hybrid!$1:$1048576,MATCH(DATE(H$2,1,1),Hybrid!$A$1:$LI$1),FALSE) -> 9.4403133 | I41: =VLOOKUP($E41,Hybrid!$1:$1048576,MATCH(DATE(I$2,1,1),Hybrid!$A$1:$LI$1),FALSE) -> 11.343637 | J41: =VLOOKUP($E41,Hybrid!$1:$1048576,MATCH(DATE(J$2,1,1),Hybrid!$A$1:$LI$1),FALSE) -> 13.239824 | K41: =VLOOKUP($E41,Hybrid!$1:$1048576,MATCH(DATE(K$2,1,1),Hybrid!$A$1:$LI$1),FALSE) -> 15.106985 | L41: =VLOOKUP($E41,Hybrid!$1:$1048576,MATCH(DATE(L$2,1,1),Hybrid!$A$1:$LI$1),FALSE) -> 16.931634 | M41: =VLOOKUP($E41,Hybrid!$1:$1048576,MATCH(DATE(M$2,1,1),Hybrid!$A$1:$LI$1),FALSE) -> 18.705614 | ... AO41: =VLOOKUP($E41,Hybrid!$1:$1048576,MATCH(DATE(AO$2,1,1),Hybrid!$A$1:$LI$1),FALSE) -> 45.588511
D42: class E | E42: AUTO_ce_cele_0 | F42: =VLOOKUP($E42,Hybrid!$1:$1048576,MATCH(DATE(F$2,1,1),Hybrid!$A$1:$LI$1),FALSE) -> 3.4730441 | G42: =VLOOKUP($E42,Hybrid!$1:$1048576,MATCH(DATE(G$2,1,1),Hybrid!$A$1:$LI$1),FALSE) -> 4.5739757 | H42: =VLOOKUP($E42,Hybrid!$1:$1048576,MATCH(DATE(H$2,1,1),Hybrid!$A$1:$LI$1),FALSE) -> 5.7146977 | I42: =VLOOKUP($E42,Hybrid!$1:$1048576,MATCH(DATE(I$2,1,1),Hybrid!$A$1:$LI$1),FALSE) -> 6.8601644 | J42: =VLOOKUP($E42,Hybrid!$1:$1048576,MATCH(DATE(J$2,1,1),Hybrid!$A$1:$LI$1),FALSE) -> 7.9881131 | K42: =VLOOKUP($E42,Hybrid!$1:$1048576,MATCH(DATE(K$2,1,1),Hybrid!$A$1:$LI$1),FALSE) -> 9.0848797 | L42: =VLOOKUP($E42,Hybrid!$1:$1048576,MATCH(DATE(L$2,1,1),Hybrid!$A$1:$LI$1),FALSE) -> 10.142321 | M42: =VLOOKUP($E42,Hybrid!$1:$1048576,MATCH(DATE(M$2,1,1),Hybrid!$A$1:$LI$1),FALSE) -> 11.155733 | ... AO42: =VLOOKUP($E42,Hybrid!$1:$1048576,MATCH(DATE(AO$2,1,1),Hybrid!$A$1:$LI$1),FALSE) -> 22.141075
D43: class F | E43: AUTO_cf_cele_0 | F43: =VLOOKUP($E43,Hybrid!$1:$1048576,MATCH(DATE(F$2,1,1),Hybrid!$A$1:$LI$1),FALSE) -> 1.7251505 | G43: =VLOOKUP($E43,Hybrid!$1:$1048576,MATCH(DATE(G$2,1,1),Hybrid!$A$1:$LI$1),FALSE) -> 2.2454556 | H43: =VLOOKUP($E43,Hybrid!$1:$1048576,MATCH(DATE(H$2,1,1),Hybrid!$A$1:$LI$1),FALSE) -> 2.7684618 | I43: =VLOOKUP($E43,Hybrid!$1:$1048576,MATCH(DATE(I$2,1,1),Hybrid!$A$1:$LI$1),FALSE) -> 3.2743104 | J43: =VLOOKUP($E43,Hybrid!$1:$1048576,MATCH(DATE(J$2,1,1),Hybrid!$A$1:$LI$1),FALSE) -> 3.7515155 | K43: =VLOOKUP($E43,Hybrid!$1:$1048576,MATCH(DATE(K$2,1,1),Hybrid!$A$1:$LI$1),FALSE) -> 4.1939767 | L43: =VLOOKUP($E43,Hybrid!$1:$1048576,MATCH(DATE(L$2,1,1),Hybrid!$A$1:$LI$1),FALSE) -> 4.5988845 | M43: =VLOOKUP($E43,Hybrid!$1:$1048576,MATCH(DATE(M$2,1,1),Hybrid!$A$1:$LI$1),FALSE) -> 4.9653764 | ... AO43: =VLOOKUP($E43,Hybrid!$1:$1048576,MATCH(DATE(AO$2,1,1),Hybrid!$A$1:$LI$1),FALSE) -> 5.2345643
D44: class G | E44: AUTO_cg_cele_0 | F44: =VLOOKUP($E44,Hybrid!$1:$1048576,MATCH(DATE(F$2,1,1),Hybrid!$A$1:$LI$1),FALSE) -> 3.1066862 | G44: =VLOOKUP($E44,Hybrid!$1:$1048576,MATCH(DATE(G$2,1,1),Hybrid!$A$1:$LI$1),FALSE) -> 4.0721667 | H44: =VLOOKUP($E44,Hybrid!$1:$1048576,MATCH(DATE(H$2,1,1),Hybrid!$A$1:$LI$1),FALSE) -> 5.0169226 | I44: =VLOOKUP($E44,Hybrid!$1:$1048576,MATCH(DATE(I$2,1,1),Hybrid!$A$1:$LI$1),FALSE) -> 5.9009041 | J44: =VLOOKUP($E44,Hybrid!$1:$1048576,MATCH(DATE(J$2,1,1),Hybrid!$A$1:$LI$1),FALSE) -> 6.703518 | K44: =VLOOKUP($E44,Hybrid!$1:$1048576,MATCH(DATE(K$2,1,1),Hybrid!$A$1:$LI$1),FALSE) -> 7.4161806 | L44: =VLOOKUP($E44,Hybrid!$1:$1048576,MATCH(DATE(L$2,1,1),Hybrid!$A$1:$LI$1),FALSE) -> 8.0372735 | M44: =VLOOKUP($E44,Hybrid!$1:$1048576,MATCH(DATE(M$2,1,1),Hybrid!$A$1:$LI$1),FALSE) -> 8.5690304 | ... AO44: =VLOOKUP($E44,Hybrid!$1:$1048576,MATCH(DATE(AO$2,1,1),Hybrid!$A$1:$LI$1),FALSE) -> 6.3335345
C45: GAS | E45: AUTO_cgas_0 | F45: =VLOOKUP($E45,Hybrid!$1:$1048576,MATCH(DATE(F$2,1,1),Hybrid!$A$1:$LI$1),FALSE) -> 1.936 | G45: =VLOOKUP($E45,Hybrid!$1:$1048576,MATCH(DATE(G$2,1,1),Hybrid!$A$1:$LI$1),FALSE) -> 1.9920385 | H45: =VLOOKUP($E45,Hybrid!$1:$1048576,MATCH(DATE(H$2,1,1),Hybrid!$A$1:$LI$1),FALSE) -> 2.058513 | I45: =VLOOKUP($E45,Hybrid!$1:$1048576,MATCH(DATE(I$2,1,1),Hybrid!$A$1:$LI$1),FALSE) -> 2.1305753 | J45: =VLOOKUP($E45,Hybrid!$1:$1048576,MATCH(DATE(J$2,1,1),Hybrid!$A$1:$LI$1),FALSE) -> 2.2050832 | K45: =VLOOKUP($E45,Hybrid!$1:$1048576,MATCH(DATE(K$2,1,1),Hybrid!$A$1:$LI$1),FALSE) -> 2.2800657 | L45: =VLOOKUP($E45,Hybrid!$1:$1048576,MATCH(DATE(L$2,1,1),Hybrid!$A$1:$LI$1),FALSE) -> 2.3543231 | M45: =VLOOKUP($E45,Hybrid!$1:$1048576,MATCH(DATE(M$2,1,1),Hybrid!$A$1:$LI$1),FALSE) -> 2.4271483 | ... AO45: =VLOOKUP($E45,Hybrid!$1:$1048576,MATCH(DATE(AO$2,1,1),Hybrid!$A$1:$LI$1),FALSE) -> 3.7739113
D46: class A | E46: AUTO_ca_cgas_0 | F46: =VLOOKUP($E46,Hybrid!$1:$1048576,MATCH(DATE(F$2,1,1),Hybrid!$A$1:$LI$1),FALSE) -> 0.4256817 | G46: =VLOOKUP($E46,Hybrid!$1:$1048576,MATCH(DATE(G$2,1,1),Hybrid!$A$1:$LI$1),FALSE) -> 0.4494557 | H46: =VLOOKUP($E46,Hybrid!$1:$1048576,MATCH(DATE(H$2,1,1),Hybrid!$A$1:$LI$1),FALSE) -> 0.47618363 | I46: =VLOOKUP($E46,Hybrid!$1:$1048576,MATCH(DATE(I$2,1,1),Hybrid!$A$1:$LI$1),FALSE) -> 0.50461174 | J46: =VLOOKUP($E46,Hybrid!$1:$1048576,MATCH(DATE(J$2,1,1),Hybrid!$A$1:$LI$1),FALSE) -> 0.53390617 | K46: =VLOOKUP($E46,Hybrid!$1:$1048576,MATCH(DATE(K$2,1,1),Hybrid!$A$1:$LI$1),FALSE) -> 0.56352909 | L46: =VLOOKUP($E46,Hybrid!$1:$1048576,MATCH(DATE(L$2,1,1),Hybrid!$A$1:$LI$1),FALSE) -> 0.5931431 | M46: =VLOOKUP($E46,Hybrid!$1:$1048576,MATCH(DATE(M$2,1,1),Hybrid!$A$1:$LI$1),FALSE) -> 0.6225422 | ... AO46: =VLOOKUP($E46,Hybrid!$1:$1048576,MATCH(DATE(AO$2,1,1),Hybrid!$A$1:$LI$1),FALSE) -> 1.3010962
D47: class B | E47: AUTO_cb_cgas_0 | F47: =VLOOKUP($E47,Hybrid!$1:$1048576,MATCH(DATE(F$2,1,1),Hybrid!$A$1:$LI$1),FALSE) -> 0.49500523 | G47: =VLOOKUP($E47,Hybrid!$1:$1048576,MATCH(DATE(G$2,1,1),Hybrid!$A$1:$LI$1),FALSE) -> 0.51237735 | H47: =VLOOKUP($E47,Hybrid!$1:$1048576,MATCH(DATE(H$2,1,1),Hybrid!$A$1:$LI$1),FALSE) -> 0.53282707 | I47: =VLOOKUP($E47,Hybrid!$1:$1048576,MATCH(DATE(I$2,1,1),Hybrid!$A$1:$LI$1),FALSE) -> 0.55510706 | J47: =VLOOKUP($E47,Hybrid!$1:$1048576,MATCH(DATE(J$2,1,1),Hybrid!$A$1:$LI$1),FALSE) -> 0.57838511 | K47: =VLOOKUP($E47,Hybrid!$1:$1048576,MATCH(DATE(K$2,1,1),Hybrid!$A$1:$LI$1),FALSE) -> 0.60212053 | L47: =VLOOKUP($E47,Hybrid!$1:$1048576,MATCH(DATE(L$2,1,1),Hybrid!$A$1:$LI$1),FALSE) -> 0.62596932 | M47: =VLOOKUP($E47,Hybrid!$1:$1048576,MATCH(DATE(M$2,1,1),Hybrid!$A$1:$LI$1),FALSE) -> 0.64971611 | ... AO47: =VLOOKUP($E47,Hybrid!$1:$1048576,MATCH(DATE(AO$2,1,1),Hybrid!$A$1:$LI$1),FALSE) -> 1.1696796
D48: class C | E48: AUTO_cc_cgas_0 | F48: =VLOOKUP($E48,Hybrid!$1:$1048576,MATCH(DATE(F$2,1,1),Hybrid!$A$1:$LI$1),FALSE) -> 0.40659852 | G48: =VLOOKUP($E48,Hybrid!$1:$1048576,MATCH(DATE(G$2,1,1),Hybrid!$A$1:$LI$1),FALSE) -> 0.41458692 | H48: =VLOOKUP($E48,Hybrid!$1:$1048576,MATCH(DATE(H$2,1,1),Hybrid!$A$1:$LI$1),FALSE) -> 0.42489006 | I48: =VLOOKUP($E48,Hybrid!$1:$1048576,MATCH(DATE(I$2,1,1),Hybrid!$A$1:$LI$1),FALSE) -> 0.43661388 | J48: =VLOOKUP($E48,Hybrid!$1:$1048576,MATCH(DATE(J$2,1,1),Hybrid!$A$1:$LI$1),FALSE) -> 0.44916009 | K48: =VLOOKUP($E48,Hybrid!$1:$1048576,MATCH(DATE(K$2,1,1),Hybrid!$A$1:$LI$1),FALSE) -> 0.46213734 | L48: =VLOOKUP($E48,Hybrid!$1:$1048576,MATCH(DATE(L$2,1,1),Hybrid!$A$1:$LI$1),FALSE) -> 0.47529341 | M48: =VLOOKUP($E48,Hybrid!$1:$1048576,MATCH(DATE(M$2,1,1),Hybrid!$A$1:$LI$1),FALSE) -> 0.48846693 | ... AO48: =VLOOKUP($E48,Hybrid!$1:$1048576,MATCH(DATE(AO$2,1,1),Hybrid!$A$1:$LI$1),FALSE) -> 0.760856
D49: class D | E49: AUTO_cd_cgas_0 | F49: =VLOOKUP($E49,Hybrid!$1:$1048576,MATCH(DATE(F$2,1,1),Hybrid!$A$1:$LI$1),FALSE) -> 0.24954447 | G49: =VLOOKUP($E49,Hybrid!$1:$1048576,MATCH(DATE(G$2,1,1),Hybrid!$A$1:$LI$1),FALSE) -> 0.2523605 | H49: =VLOOKUP($E49,Hybrid!$1:$1048576,MATCH(DATE(H$2,1,1),Hybrid!$A$1:$LI$1),FALSE) -> 0.25638798 | I49: =VLOOKUP($E49,Hybrid!$1:$1048576,MATCH(DATE(I$2,1,1),Hybrid!$A$1:$LI$1),FALSE) -> 0.26108963 | J49: =VLOOKUP($E49,Hybrid!$1:$1048576,MATCH(DATE(J$2,1,1),Hybrid!$A$1:$LI$1),FALSE) -> 0.2661123 | K49: =VLOOKUP($E49,Hybrid!$1:$1048576,MATCH(DATE(K$2,1,1),Hybrid!$A$1:$LI$1),FALSE) -> 0.27122926 | L49: =VLOOKUP($E49,Hybrid!$1:$1048576,MATCH(DATE(L$2,1,1),Hybrid!$A$1:$LI$1),FALSE) -> 0.27629699 | M49: =VLOOKUP($E49,Hybrid!$1:$1048576,MATCH(DATE(M$2,1,1),Hybrid!$A$1:$LI$1),FALSE) -> 0.28122528 | ... AO49: =VLOOKUP($E49,Hybrid!$1:$1048576,MATCH(DATE(AO$2,1,1),Hybrid!$A$1:$LI$1),FALSE) -> 0.31327502
D50: class E | E50: AUTO_ce_cgas_0 | F50: =VLOOKUP($E50,Hybrid!$1:$1048576,MATCH(DATE(F$2,1,1),Hybrid!$A$1:$LI$1),FALSE) -> 0.15020247 | G50: =VLOOKUP($E50,Hybrid!$1:$1048576,MATCH(DATE(G$2,1,1),Hybrid!$A$1:$LI$1),FALSE) -> 0.15208636 | H50: =VLOOKUP($E50,Hybrid!$1:$1048576,MATCH(DATE(H$2,1,1),Hybrid!$A$1:$LI$1),FALSE) -> 0.15461234 | I50: =VLOOKUP($E50,Hybrid!$1:$1048576,MATCH(DATE(I$2,1,1),Hybrid!$A$1:$LI$1),FALSE) -> 0.15743309 | J50: =VLOOKUP($E50,Hybrid!$1:$1048576,MATCH(DATE(J$2,1,1),Hybrid!$A$1:$LI$1),FALSE) -> 0.16032595 | K50: =VLOOKUP($E50,Hybrid!$1:$1048576,MATCH(DATE(K$2,1,1),Hybrid!$A$1:$LI$1),FALSE) -> 0.16315238 | L50: =VLOOKUP($E50,Hybrid!$1:$1048576,MATCH(DATE(L$2,1,1),Hybrid!$A$1:$LI$1),FALSE) -> 0.16582827 | M50: =VLOOKUP($E50,Hybrid!$1:$1048576,MATCH(DATE(M$2,1,1),Hybrid!$A$1:$LI$1),FALSE) -> 0.16830371 | ... AO50: =VLOOKUP($E50,Hybrid!$1:$1048576,MATCH(DATE(AO$2,1,1),Hybrid!$A$1:$LI$1),FALSE) -> 0.14957306
D51: class F | E51: AUTO_cf_cgas_0 | F51: =VLOOKUP($E51,Hybrid!$1:$1048576,MATCH(DATE(F$2,1,1),Hybrid!$A$1:$LI$1),FALSE) -> 0.074609436 | G51: =VLOOKUP($E51,Hybrid!$1:$1048576,MATCH(DATE(G$2,1,1),Hybrid!$A$1:$LI$1),FALSE) -> 0.075303854 | H51: =VLOOKUP($E51,Hybrid!$1:$1048576,MATCH(DATE(H$2,1,1),Hybrid!$A$1:$LI$1),FALSE) -> 0.076167883 | I51: =VLOOKUP($E51,Hybrid!$1:$1048576,MATCH(DATE(I$2,1,1),Hybrid!$A$1:$LI$1),FALSE) -> 0.077010461 | J51: =VLOOKUP($E51,Hybrid!$1:$1048576,MATCH(DATE(J$2,1,1),Hybrid!$A$1:$LI$1),FALSE) -> 0.077721316 | K51: =VLOOKUP($E51,Hybrid!$1:$1048576,MATCH(DATE(K$2,1,1),Hybrid!$A$1:$LI$1),FALSE) -> 0.078242029 | L51: =VLOOKUP($E51,Hybrid!$1:$1048576,MATCH(DATE(L$2,1,1),Hybrid!$A$1:$LI$1),FALSE) -> 0.0785458 | M51: =VLOOKUP($E51,Hybrid!$1:$1048576,MATCH(DATE(M$2,1,1),Hybrid!$A$1:$LI$1),FALSE) -> 0.078624437 | ... AO51: =VLOOKUP($E51,Hybrid!$1:$1048576,MATCH(DATE(AO$2,1,1),Hybrid!$A$1:$LI$1),FALSE) -> 0.035616963
D52: class G | E52: AUTO_cg_cgas_0 | F52: =VLOOKUP($E52,Hybrid!$1:$1048576,MATCH(DATE(F$2,1,1),Hybrid!$A$1:$LI$1),FALSE) -> 0.13435819 | G52: =VLOOKUP($E52,Hybrid!$1:$1048576,MATCH(DATE(G$2,1,1),Hybrid!$A$1:$LI$1),FALSE) -> 0.13586779 | H52: =VLOOKUP($E52,Hybrid!$1:$1048576,MATCH(DATE(H$2,1,1),Hybrid!$A$1:$LI$1),FALSE) -> 0.13744409 | I52: =VLOOKUP($E52,Hybrid!$1:$1048576,MATCH(DATE(I$2,1,1),Hybrid!$A$1:$LI$1),FALSE) -> 0.13870945 | J52: =VLOOKUP($E52,Hybrid!$1:$1048576,MATCH(DATE(J$2,1,1),Hybrid!$A$1:$LI$1),FALSE) -> 0.13947226 | K52: =VLOOKUP($E52,Hybrid!$1:$1048576,MATCH(DATE(K$2,1,1),Hybrid!$A$1:$LI$1),FALSE) -> 0.13965509 | L52: =VLOOKUP($E52,Hybrid!$1:$1048576,MATCH(DATE(L$2,1,1),Hybrid!$A$1:$LI$1),FALSE) -> 0.13924622 | M52: =VLOOKUP($E52,Hybrid!$1:$1048576,MATCH(DATE(M$2,1,1),Hybrid!$A$1:$LI$1),FALSE) -> 0.13826967 | ... AO52: =VLOOKUP($E52,Hybrid!$1:$1048576,MATCH(DATE(AO$2,1,1),Hybrid!$A$1:$LI$1),FALSE) -> 0.043814475
C53: TOTAL SALES SHOCK | E53: NEWAUTO_2 | F53: =VLOOKUP($E53,Hybrid!$1:$1048576,MATCH(DATE(F$2,1,1),Hybrid!$A$1:$LI$1),FALSE) -> 1886.229 | G53: =VLOOKUP($E53,Hybrid!$1:$1048576,MATCH(DATE(G$2,1,1),Hybrid!$A$1:$LI$1),FALSE) -> 2121.9086 | H53: =VLOOKUP($E53,Hybrid!$1:$1048576,MATCH(DATE(H$2,1,1),Hybrid!$A$1:$LI$1),FALSE) -> 2286.4648 | I53: =VLOOKUP($E53,Hybrid!$1:$1048576,MATCH(DATE(I$2,1,1),Hybrid!$A$1:$LI$1),FALSE) -> 2401.2849 | J53: =VLOOKUP($E53,Hybrid!$1:$1048576,MATCH(DATE(J$2,1,1),Hybrid!$A$1:$LI$1),FALSE) -> 2482.1212 | K53: =VLOOKUP($E53,Hybrid!$1:$1048576,MATCH(DATE(K$2,1,1),Hybrid!$A$1:$LI$1),FALSE) -> 2540.0565 | L53: =VLOOKUP($E53,Hybrid!$1:$1048576,MATCH(DATE(L$2,1,1),Hybrid!$A$1:$LI$1),FALSE) -> 2584.7231 | M53: =VLOOKUP($E53,Hybrid!$1:$1048576,MATCH(DATE(M$2,1,1),Hybrid!$A$1:$LI$1),FALSE) -> 2622.3847 | ... AO53: =VLOOKUP($E53,Hybrid!$1:$1048576,MATCH(DATE(AO$2,1,1),Hybrid!$A$1:$LI$1),FALSE) -> 3025.9258
C54: OIL | E54: NEWAUTO_cfut_2 | F54: =VLOOKUP($E54,Hybrid!$1:$1048576,MATCH(DATE(F$2,1,1),Hybrid!$A$1:$LI$1),FALSE) -> 1868.803 | G54: =VLOOKUP($E54,Hybrid!$1:$1048576,MATCH(DATE(G$2,1,1),Hybrid!$A$1:$LI$1),FALSE) -> 2102.2745 | H54: =VLOOKUP($E54,Hybrid!$1:$1048576,MATCH(DATE(H$2,1,1),Hybrid!$A$1:$LI$1),FALSE) -> 2265.1959 | I54: =VLOOKUP($E54,Hybrid!$1:$1048576,MATCH(DATE(I$2,1,1),Hybrid!$A$1:$LI$1),FALSE) -> 2378.7432 | J54: =VLOOKUP($E54,Hybrid!$1:$1048576,MATCH(DATE(J$2,1,1),Hybrid!$A$1:$LI$1),FALSE) -> 2458.5011 | K54: =VLOOKUP($E54,Hybrid!$1:$1048576,MATCH(DATE(K$2,1,1),Hybrid!$A$1:$LI$1),FALSE) -> 2515.416 | L54: =VLOOKUP($E54,Hybrid!$1:$1048576,MATCH(DATE(L$2,1,1),Hybrid!$A$1:$LI$1),FALSE) -> 2558.9983 | M54: =VLOOKUP($E54,Hybrid!$1:$1048576,MATCH(DATE(M$2,1,1),Hybrid!$A$1:$LI$1),FALSE) -> 2595.4514 | ... AO54: =VLOOKUP($E54,Hybrid!$1:$1048576,MATCH(DATE(AO$2,1,1),Hybrid!$A$1:$LI$1),FALSE) -> 2705.8813
D55: class A | E55: NEWAUTO_ca_cfut_2 | F55: =VLOOKUP($E55,Hybrid!$1:$1048576,MATCH(DATE(F$2,1,1),Hybrid!$A$1:$LI$1),FALSE) -> 528.68437 | G55: =VLOOKUP($E55,Hybrid!$1:$1048576,MATCH(DATE(G$2,1,1),Hybrid!$A$1:$LI$1),FALSE) -> 598.26655 | H55: =VLOOKUP($E55,Hybrid!$1:$1048576,MATCH(DATE(H$2,1,1),Hybrid!$A$1:$LI$1),FALSE) -> 650.34466 | I55: =VLOOKUP($E55,Hybrid!$1:$1048576,MATCH(DATE(I$2,1,1),Hybrid!$A$1:$LI$1),FALSE) -> 689.88363 | J55: =VLOOKUP($E55,Hybrid!$1:$1048576,MATCH(DATE(J$2,1,1),Hybrid!$A$1:$LI$1),FALSE) -> 720.62129 | K55: =VLOOKUP($E55,Hybrid!$1:$1048576,MATCH(DATE(K$2,1,1),Hybrid!$A$1:$LI$1),FALSE) -> 745.27335 | L55: =VLOOKUP($E55,Hybrid!$1:$1048576,MATCH(DATE(L$2,1,1),Hybrid!$A$1:$LI$1),FALSE) -> 766.35396 | M55: =VLOOKUP($E55,Hybrid!$1:$1048576,MATCH(DATE(M$2,1,1),Hybrid!$A$1:$LI$1),FALSE) -> 785.52338 | ... AO55: =VLOOKUP($E55,Hybrid!$1:$1048576,MATCH(DATE(AO$2,1,1),Hybrid!$A$1:$LI$1),FALSE) -> 1044.9272
D56: class B | E56: NEWAUTO_cb_cfut_2 | F56: =VLOOKUP($E56,Hybrid!$1:$1048576,MATCH(DATE(F$2,1,1),Hybrid!$A$1:$LI$1),FALSE) -> 507.56689 | G56: =VLOOKUP($E56,Hybrid!$1:$1048576,MATCH(DATE(G$2,1,1),Hybrid!$A$1:$LI$1),FALSE) -> 573.67684 | H56: =VLOOKUP($E56,Hybrid!$1:$1048576,MATCH(DATE(H$2,1,1),Hybrid!$A$1:$LI$1),FALSE) -> 622.44179 | I56: =VLOOKUP($E56,Hybrid!$1:$1048576,MATCH(DATE(I$2,1,1),Hybrid!$A$1:$LI$1),FALSE) -> 658.80578 | J56: =VLOOKUP($E56,Hybrid!$1:$1048576,MATCH(DATE(J$2,1,1),Hybrid!$A$1:$LI$1),FALSE) -> 686.47032 | K56: =VLOOKUP($E56,Hybrid!$1:$1048576,MATCH(DATE(K$2,1,1),Hybrid!$A$1:$LI$1),FALSE) -> 708.1014 | L56: =VLOOKUP($E56,Hybrid!$1:$1048576,MATCH(DATE(L$2,1,1),Hybrid!$A$1:$LI$1),FALSE) -> 726.139 | M56: =VLOOKUP($E56,Hybrid!$1:$1048576,MATCH(DATE(M$2,1,1),Hybrid!$A$1:$LI$1),FALSE) -> 742.20284 | ... AO56: =VLOOKUP($E56,Hybrid!$1:$1048576,MATCH(DATE(AO$2,1,1),Hybrid!$A$1:$LI$1),FALSE) -> 873.91808
D57: class C | E57: NEWAUTO_cc_cfut_2 | F57: =VLOOKUP($E57,Hybrid!$1:$1048576,MATCH(DATE(F$2,1,1),Hybrid!$A$1:$LI$1),FALSE) -> 351.33496 | G57: =VLOOKUP($E57,Hybrid!$1:$1048576,MATCH(DATE(G$2,1,1),Hybrid!$A$1:$LI$1),FALSE) -> 396.61968 | H57: =VLOOKUP($E57,Hybrid!$1:$1048576,MATCH(DATE(H$2,1,1),Hybrid!$A$1:$LI$1),FALSE) -> 429.53065 | I57: =VLOOKUP($E57,Hybrid!$1:$1048576,MATCH(DATE(I$2,1,1),Hybrid!$A$1:$LI$1),FALSE) -> 453.61483 | J57: =VLOOKUP($E57,Hybrid!$1:$1048576,MATCH(DATE(J$2,1,1),Hybrid!$A$1:$LI$1),FALSE) -> 471.51392 | K57: =VLOOKUP($E57,Hybrid!$1:$1048576,MATCH(DATE(K$2,1,1),Hybrid!$A$1:$LI$1),FALSE) -> 485.11504 | L57: =VLOOKUP($E57,Hybrid!$1:$1048576,MATCH(DATE(L$2,1,1),Hybrid!$A$1:$LI$1),FALSE) -> 496.12632 | M57: =VLOOKUP($E57,Hybrid!$1:$1048576,MATCH(DATE(M$2,1,1),Hybrid!$A$1:$LI$1),FALSE) -> 505.68738 | ... AO57: =VLOOKUP($E57,Hybrid!$1:$1048576,MATCH(DATE(AO$2,1,1),Hybrid!$A$1:$LI$1),FALSE) -> 528.1655
D58: class D | E58: NEWAUTO_cd_cfut_2 | F58: =VLOOKUP($E58,Hybrid!$1:$1048576,MATCH(DATE(F$2,1,1),Hybrid!$A$1:$LI$1),FALSE) -> 194.72927 | G58: =VLOOKUP($E58,Hybrid!$1:$1048576,MATCH(DATE(G$2,1,1),Hybrid!$A$1:$LI$1),FALSE) -> 218.63588 | H58: =VLOOKUP($E58,Hybrid!$1:$1048576,MATCH(DATE(H$2,1,1),Hybrid!$A$1:$LI$1),FALSE) -> 234.81881 | I58: =VLOOKUP($E58,Hybrid!$1:$1048576,MATCH(DATE(I$2,1,1),Hybrid!$A$1:$LI$1),FALSE) -> 245.56071 | J58: =VLOOKUP($E58,Hybrid!$1:$1048576,MATCH(DATE(J$2,1,1),Hybrid!$A$1:$LI$1),FALSE) -> 252.53999 | K58: =VLOOKUP($E58,Hybrid!$1:$1048576,MATCH(DATE(K$2,1,1),Hybrid!$A$1:$LI$1),FALSE) -> 256.92996 | L58: =VLOOKUP($E58,Hybrid!$1:$1048576,MATCH(DATE(L$2,1,1),Hybrid!$A$1:$LI$1),FALSE) -> 259.7379 | M58: =VLOOKUP($E58,Hybrid!$1:$1048576,MATCH(DATE(M$2,1,1),Hybrid!$A$1:$LI$1),FALSE) -> 261.62398 | ... AO58: =VLOOKUP($E58,Hybrid!$1:$1048576,MATCH(DATE(AO$2,1,1),Hybrid!$A$1:$LI$1),FALSE) -> 182.3448
D59: class E | E59: NEWAUTO_ce_cfut_2 | F59: =VLOOKUP($E59,Hybrid!$1:$1048576,MATCH(DATE(F$2,1,1),Hybrid!$A$1:$LI$1),FALSE) -> 119.79027 | G59: =VLOOKUP($E59,Hybrid!$1:$1048576,MATCH(DATE(G$2,1,1),Hybrid!$A$1:$LI$1),FALSE) -> 133.83711 | H59: =VLOOKUP($E59,Hybrid!$1:$1048576,MATCH(DATE(H$2,1,1),Hybrid!$A$1:$LI$1),FALSE) -> 142.66726 | I59: =VLOOKUP($E59,Hybrid!$1:$1048576,MATCH(DATE(I$2,1,1),Hybrid!$A$1:$LI$1),FALSE) -> 147.87088 | J59: =VLOOKUP($E59,Hybrid!$1:$1048576,MATCH(DATE(J$2,1,1),Hybrid!$A$1:$LI$1),FALSE) -> 150.60482 | K59: =VLOOKUP($E59,Hybrid!$1:$1048576,MATCH(DATE(K$2,1,1),Hybrid!$A$1:$LI$1),FALSE) -> 151.66389 | L59: =VLOOKUP($E59,Hybrid!$1:$1048576,MATCH(DATE(L$2,1,1),Hybrid!$A$1:$LI$1),FALSE) -> 151.70292 | M59: =VLOOKUP($E59,Hybrid!$1:$1048576,MATCH(DATE(M$2,1,1),Hybrid!$A$1:$LI$1),FALSE) -> 151.14636 | ... AO59: =VLOOKUP($E59,Hybrid!$1:$1048576,MATCH(DATE(AO$2,1,1),Hybrid!$A$1:$LI$1),FALSE) -> 68.077173
D60: class F | E60: NEWAUTO_cf_cfut_2 | F60: =VLOOKUP($E60,Hybrid!$1:$1048576,MATCH(DATE(F$2,1,1),Hybrid!$A$1:$LI$1),FALSE) -> 57.932893 | G60: =VLOOKUP($E60,Hybrid!$1:$1048576,MATCH(DATE(G$2,1,1),Hybrid!$A$1:$LI$1),FALSE) -> 63.612286 | H60: =VLOOKUP($E60,Hybrid!$1:$1048576,MATCH(DATE(H$2,1,1),Hybrid!$A$1:$LI$1),FALSE) -> 66.044522 | I60: =VLOOKUP($E60,Hybrid!$1:$1048576,MATCH(DATE(I$2,1,1),Hybrid!$A$1:$LI$1),FALSE) -> 66.345904 | J60: =VLOOKUP($E60,Hybrid!$1:$1048576,MATCH(DATE(J$2,1,1),Hybrid!$A$1:$LI$1),FALSE) -> 65.305385 | K60: =VLOOKUP($E60,Hybrid!$1:$1048576,MATCH(DATE(K$2,1,1),Hybrid!$A$1:$LI$1),FALSE) -> 63.44168 | L60: =VLOOKUP($E60,Hybrid!$1:$1048576,MATCH(DATE(L$2,1,1),Hybrid!$A$1:$LI$1),FALSE) -> 61.135334 | M60: =VLOOKUP($E60,Hybrid!$1:$1048576,MATCH(DATE(M$2,1,1),Hybrid!$A$1:$LI$1),FALSE) -> 58.619451 | ... AO60: =VLOOKUP($E60,Hybrid!$1:$1048576,MATCH(DATE(AO$2,1,1),Hybrid!$A$1:$LI$1),FALSE) -> 6.0056156
D61: class G | E61: NEWAUTO_cg_cfut_2 | F61: =VLOOKUP($E61,Hybrid!$1:$1048576,MATCH(DATE(F$2,1,1),Hybrid!$A$1:$LI$1),FALSE) -> 108.76433 | G61: =VLOOKUP($E61,Hybrid!$1:$1048576,MATCH(DATE(G$2,1,1),Hybrid!$A$1:$LI$1),FALSE) -> 117.62618 | H61: =VLOOKUP($E61,Hybrid!$1:$1048576,MATCH(DATE(H$2,1,1),Hybrid!$A$1:$LI$1),FALSE) -> 119.34826 | I61: =VLOOKUP($E61,Hybrid!$1:$1048576,MATCH(DATE(I$2,1,1),Hybrid!$A$1:$LI$1),FALSE) -> 116.66148 | J61: =VLOOKUP($E61,Hybrid!$1:$1048576,MATCH(DATE(J$2,1,1),Hybrid!$A$1:$LI$1),FALSE) -> 111.44541 | K61: =VLOOKUP($E61,Hybrid!$1:$1048576,MATCH(DATE(K$2,1,1),Hybrid!$A$1:$LI$1),FALSE) -> 104.89069 | L61: =VLOOKUP($E61,Hybrid!$1:$1048576,MATCH(DATE(L$2,1,1),Hybrid!$A$1:$LI$1),FALSE) -> 97.802878 | M61: =VLOOKUP($E61,Hybrid!$1:$1048576,MATCH(DATE(M$2,1,1),Hybrid!$A$1:$LI$1),FALSE) -> 90.648018 | ... AO61: =VLOOKUP($E61,Hybrid!$1:$1048576,MATCH(DATE(AO$2,1,1),Hybrid!$A$1:$LI$1),FALSE) -> 2.4429278
C62: ELEC | E62: NEWAUTO_cele_2 | F62: =VLOOKUP($E62,Hybrid!$1:$1048576,MATCH(DATE(F$2,1,1),Hybrid!$A$1:$LI$1),FALSE) -> 17.269 | G62: =VLOOKUP($E62,Hybrid!$1:$1048576,MATCH(DATE(G$2,1,1),Hybrid!$A$1:$LI$1),FALSE) -> 19.457507 | H62: =VLOOKUP($E62,Hybrid!$1:$1048576,MATCH(DATE(H$2,1,1),Hybrid!$A$1:$LI$1),FALSE) -> 21.078508 | I62: =VLOOKUP($E62,Hybrid!$1:$1048576,MATCH(DATE(I$2,1,1),Hybrid!$A$1:$LI$1),FALSE) -> 22.341869 | J62: =VLOOKUP($E62,Hybrid!$1:$1048576,MATCH(DATE(J$2,1,1),Hybrid!$A$1:$LI$1),FALSE) -> 23.413511 | K62: =VLOOKUP($E62,Hybrid!$1:$1048576,MATCH(DATE(K$2,1,1),Hybrid!$A$1:$LI$1),FALSE) -> 24.429183 | L62: =VLOOKUP($E62,Hybrid!$1:$1048576,MATCH(DATE(L$2,1,1),Hybrid!$A$1:$LI$1),FALSE) -> 25.509845 | M62: =VLOOKUP($E62,Hybrid!$1:$1048576,MATCH(DATE(M$2,1,1),Hybrid!$A$1:$LI$1),FALSE) -> 26.715298 | ... AO62: =VLOOKUP($E62,Hybrid!$1:$1048576,MATCH(DATE(AO$2,1,1),Hybrid!$A$1:$LI$1),FALSE) -> 319.81722
D63: class A | E63: NEWAUTO_ca_cele_2 | F63: =VLOOKUP($E63,Hybrid!$1:$1048576,MATCH(DATE(F$2,1,1),Hybrid!$A$1:$LI$1),FALSE) -> 4.8854001 | G63: =VLOOKUP($E63,Hybrid!$1:$1048576,MATCH(DATE(G$2,1,1),Hybrid!$A$1:$LI$1),FALSE) -> 5.5377767 | H63: =VLOOKUP($E63,Hybrid!$1:$1048576,MATCH(DATE(H$2,1,1),Hybrid!$A$1:$LI$1),FALSE) -> 6.0542177 | I63: =VLOOKUP($E63,Hybrid!$1:$1048576,MATCH(DATE(I$2,1,1),Hybrid!$A$1:$LI$1),FALSE) -> 6.48554 | J63: =VLOOKUP($E63,Hybrid!$1:$1048576,MATCH(DATE(J$2,1,1),Hybrid!$A$1:$LI$1),FALSE) -> 6.8737946 | K63: =VLOOKUP($E63,Hybrid!$1:$1048576,MATCH(DATE(K$2,1,1),Hybrid!$A$1:$LI$1),FALSE) -> 7.2557844 | L63: =VLOOKUP($E63,Hybrid!$1:$1048576,MATCH(DATE(L$2,1,1),Hybrid!$A$1:$LI$1),FALSE) -> 7.6663083 | M63: =VLOOKUP($E63,Hybrid!$1:$1048576,MATCH(DATE(M$2,1,1),Hybrid!$A$1:$LI$1),FALSE) -> 8.1227891 | ... AO63: =VLOOKUP($E63,Hybrid!$1:$1048576,MATCH(DATE(AO$2,1,1),Hybrid!$A$1:$LI$1),FALSE) -> 123.03909
D64: class B | E64: NEWAUTO_cb_cele_2 | F64: =VLOOKUP($E64,Hybrid!$1:$1048576,MATCH(DATE(F$2,1,1),Hybrid!$A$1:$LI$1),FALSE) -> 4.6902604 | G64: =VLOOKUP($E64,Hybrid!$1:$1048576,MATCH(DATE(G$2,1,1),Hybrid!$A$1:$LI$1),FALSE) -> 5.3109022 | H64: =VLOOKUP($E64,Hybrid!$1:$1048576,MATCH(DATE(H$2,1,1),Hybrid!$A$1:$LI$1),FALSE) -> 5.7979386 | I64: =VLOOKUP($E64,Hybrid!$1:$1048576,MATCH(DATE(I$2,1,1),Hybrid!$A$1:$LI$1),FALSE) -> 6.2019433 | J64: =VLOOKUP($E64,Hybrid!$1:$1048576,MATCH(DATE(J$2,1,1),Hybrid!$A$1:$LI$1),FALSE) -> 6.5645674 | K64: =VLOOKUP($E64,Hybrid!$1:$1048576,MATCH(DATE(K$2,1,1),Hybrid!$A$1:$LI$1),FALSE) -> 6.9220681 | L64: =VLOOKUP($E64,Hybrid!$1:$1048576,MATCH(DATE(L$2,1,1),Hybrid!$A$1:$LI$1),FALSE) -> 7.3082899 | M64: =VLOOKUP($E64,Hybrid!$1:$1048576,MATCH(DATE(M$2,1,1),Hybrid!$A$1:$LI$1),FALSE) -> 7.7397043 | ... AO64: =VLOOKUP($E64,Hybrid!$1:$1048576,MATCH(DATE(AO$2,1,1),Hybrid!$A$1:$LI$1),FALSE) -> 109.5249
D65: class C | E65: NEWAUTO_cc_cele_2 | F65: =VLOOKUP($E65,Hybrid!$1:$1048576,MATCH(DATE(F$2,1,1),Hybrid!$A$1:$LI$1),FALSE) -> 3.246572 | G65: =VLOOKUP($E65,Hybrid!$1:$1048576,MATCH(DATE(G$2,1,1),Hybrid!$A$1:$LI$1),FALSE) -> 3.672242 | H65: =VLOOKUP($E65,Hybrid!$1:$1048576,MATCH(DATE(H$2,1,1),Hybrid!$A$1:$LI$1),FALSE) -> 4.0032399 | I65: =VLOOKUP($E65,Hybrid!$1:$1048576,MATCH(DATE(I$2,1,1),Hybrid!$A$1:$LI$1),FALSE) -> 4.2757918 | J65: =VLOOKUP($E65,Hybrid!$1:$1048576,MATCH(DATE(J$2,1,1),Hybrid!$A$1:$LI$1),FALSE) -> 4.5195764 | K65: =VLOOKUP($E65,Hybrid!$1:$1048576,MATCH(DATE(K$2,1,1),Hybrid!$A$1:$LI$1),FALSE) -> 4.760269 | L65: =VLOOKUP($E65,Hybrid!$1:$1048576,MATCH(DATE(L$2,1,1),Hybrid!$A$1:$LI$1),FALSE) -> 5.0215302 | M65: =VLOOKUP($E65,Hybrid!$1:$1048576,MATCH(DATE(M$2,1,1),Hybrid!$A$1:$LI$1),FALSE) -> 5.3145526 | ... AO65: =VLOOKUP($E65,Hybrid!$1:$1048576,MATCH(DATE(AO$2,1,1),Hybrid!$A$1:$LI$1),FALSE) -> 69.922136
D66: class D | E66: NEWAUTO_cd_cele_2 | F66: =VLOOKUP($E66,Hybrid!$1:$1048576,MATCH(DATE(F$2,1,1),Hybrid!$A$1:$LI$1),FALSE) -> 1.7994298 | G66: =VLOOKUP($E66,Hybrid!$1:$1048576,MATCH(DATE(G$2,1,1),Hybrid!$A$1:$LI$1),FALSE) -> 2.0222985 | H66: =VLOOKUP($E66,Hybrid!$1:$1048576,MATCH(DATE(H$2,1,1),Hybrid!$A$1:$LI$1),FALSE) -> 2.179031 | I66: =VLOOKUP($E66,Hybrid!$1:$1048576,MATCH(DATE(I$2,1,1),Hybrid!$A$1:$LI$1),FALSE) -> 2.2914459 | J66: =VLOOKUP($E66,Hybrid!$1:$1048576,MATCH(DATE(J$2,1,1),Hybrid!$A$1:$LI$1),FALSE) -> 2.3761885 | K66: =VLOOKUP($E66,Hybrid!$1:$1048576,MATCH(DATE(K$2,1,1),Hybrid!$A$1:$LI$1),FALSE) -> 2.4459242 | L66: =VLOOKUP($E66,Hybrid!$1:$1048576,MATCH(DATE(L$2,1,1),Hybrid!$A$1:$LI$1),FALSE) -> 2.5115811 | M66: =VLOOKUP($E66,Hybrid!$1:$1048576,MATCH(DATE(M$2,1,1),Hybrid!$A$1:$LI$1),FALSE) -> 2.5790002 | ... AO66: =VLOOKUP($E66,Hybrid!$1:$1048576,MATCH(DATE(AO$2,1,1),Hybrid!$A$1:$LI$1),FALSE) -> 12.020067
D67: class E | E67: NEWAUTO_ce_cele_2 | F67: =VLOOKUP($E67,Hybrid!$1:$1048576,MATCH(DATE(F$2,1,1),Hybrid!$A$1:$LI$1),FALSE) -> 1.1069429 | G67: =VLOOKUP($E67,Hybrid!$1:$1048576,MATCH(DATE(G$2,1,1),Hybrid!$A$1:$LI$1),FALSE) -> 1.238128 | H67: =VLOOKUP($E67,Hybrid!$1:$1048576,MATCH(DATE(H$2,1,1),Hybrid!$A$1:$LI$1),FALSE) -> 1.3247542 | I67: =VLOOKUP($E67,Hybrid!$1:$1048576,MATCH(DATE(I$2,1,1),Hybrid!$A$1:$LI$1),FALSE) -> 1.3819054 | J67: =VLOOKUP($E67,Hybrid!$1:$1048576,MATCH(DATE(J$2,1,1),Hybrid!$A$1:$LI$1),FALSE) -> 1.4209063 | K67: =VLOOKUP($E67,Hybrid!$1:$1048576,MATCH(DATE(K$2,1,1),Hybrid!$A$1:$LI$1),FALSE) -> 1.4501536 | L67: =VLOOKUP($E67,Hybrid!$1:$1048576,MATCH(DATE(L$2,1,1),Hybrid!$A$1:$LI$1),FALSE) -> 1.4765497 | M67: =VLOOKUP($E67,Hybrid!$1:$1048576,MATCH(DATE(M$2,1,1),Hybrid!$A$1:$LI$1),FALSE) -> 1.5035879 | ... AO67: =VLOOKUP($E67,Hybrid!$1:$1048576,MATCH(DATE(AO$2,1,1),Hybrid!$A$1:$LI$1),FALSE) -> 4.8950291
D68: class F | E68: NEWAUTO_cf_cele_2 | F68: =VLOOKUP($E68,Hybrid!$1:$1048576,MATCH(DATE(F$2,1,1),Hybrid!$A$1:$LI$1),FALSE) -> 0.535339 | G68: =VLOOKUP($E68,Hybrid!$1:$1048576,MATCH(DATE(G$2,1,1),Hybrid!$A$1:$LI$1),FALSE) -> 0.58827106 | H68: =VLOOKUP($E68,Hybrid!$1:$1048576,MATCH(DATE(H$2,1,1),Hybrid!$A$1:$LI$1),FALSE) -> 0.61232405 | I68: =VLOOKUP($E68,Hybrid!$1:$1048576,MATCH(DATE(I$2,1,1),Hybrid!$A$1:$LI$1),FALSE) -> 0.61781292 | J68: =VLOOKUP($E68,Hybrid!$1:$1048576,MATCH(DATE(J$2,1,1),Hybrid!$A$1:$LI$1),FALSE) -> 0.61207347 | K68: =VLOOKUP($E68,Hybrid!$1:$1048576,MATCH(DATE(K$2,1,1),Hybrid!$A$1:$LI$1),FALSE) -> 0.60003429 | L68: =VLOOKUP($E68,Hybrid!$1:$1048576,MATCH(DATE(L$2,1,1),Hybrid!$A$1:$LI$1),FALSE) -> 0.58525332 | M68: =VLOOKUP($E68,Hybrid!$1:$1048576,MATCH(DATE(M$2,1,1),Hybrid!$A$1:$LI$1),FALSE) -> 0.56957622 | ... AO68: =VLOOKUP($E68,Hybrid!$1:$1048576,MATCH(DATE(AO$2,1,1),Hybrid!$A$1:$LI$1),FALSE) -> 0.29009622
D69: class G | E69: NEWAUTO_cg_cele_2 | F69: =VLOOKUP($E69,Hybrid!$1:$1048576,MATCH(DATE(F$2,1,1),Hybrid!$A$1:$LI$1),FALSE) -> 1.0050558 | G69: =VLOOKUP($E69,Hybrid!$1:$1048576,MATCH(DATE(G$2,1,1),Hybrid!$A$1:$LI$1),FALSE) -> 1.0878884 | H69: =VLOOKUP($E69,Hybrid!$1:$1048576,MATCH(DATE(H$2,1,1),Hybrid!$A$1:$LI$1),FALSE) -> 1.1070025 | I69: =VLOOKUP($E69,Hybrid!$1:$1048576,MATCH(DATE(I$2,1,1),Hybrid!$A$1:$LI$1),FALSE) -> 1.0874299 | J69: =VLOOKUP($E69,Hybrid!$1:$1048576,MATCH(DATE(J$2,1,1),Hybrid!$A$1:$LI$1),FALSE) -> 1.0464047 | K69: =VLOOKUP($E69,Hybrid!$1:$1048576,MATCH(DATE(K$2,1,1),Hybrid!$A$1:$LI$1),FALSE) -> 0.99494941 | L69: =VLOOKUP($E69,Hybrid!$1:$1048576,MATCH(DATE(L$2,1,1),Hybrid!$A$1:$LI$1),FALSE) -> 0.94033263 | M69: =VLOOKUP($E69,Hybrid!$1:$1048576,MATCH(DATE(M$2,1,1),Hybrid!$A$1:$LI$1),FALSE) -> 0.88608805 | ... AO69: =VLOOKUP($E69,Hybrid!$1:$1048576,MATCH(DATE(AO$2,1,1),Hybrid!$A$1:$LI$1),FALSE) -> 0.12590016
C70: GAS | E70: NEWAUTO_cgas_2 | F70: =VLOOKUP($E70,Hybrid!$1:$1048576,MATCH(DATE(F$2,1,1),Hybrid!$A$1:$LI$1),FALSE) -> 0.157 | G70: =VLOOKUP($E70,Hybrid!$1:$1048576,MATCH(DATE(G$2,1,1),Hybrid!$A$1:$LI$1),FALSE) -> 0.17661418 | H70: =VLOOKUP($E70,Hybrid!$1:$1048576,MATCH(DATE(H$2,1,1),Hybrid!$A$1:$LI$1),FALSE) -> 0.19030137 | I70: =VLOOKUP($E70,Hybrid!$1:$1048576,MATCH(DATE(I$2,1,1),Hybrid!$A$1:$LI$1),FALSE) -> 0.19984059 | J70: =VLOOKUP($E70,Hybrid!$1:$1048576,MATCH(DATE(J$2,1,1),Hybrid!$A$1:$LI$1),FALSE) -> 0.20654113 | K70: =VLOOKUP($E70,Hybrid!$1:$1048576,MATCH(DATE(K$2,1,1),Hybrid!$A$1:$LI$1),FALSE) -> 0.2113226 | L70: =VLOOKUP($E70,Hybrid!$1:$1048576,MATCH(DATE(L$2,1,1),Hybrid!$A$1:$LI$1),FALSE) -> 0.214984 | M70: =VLOOKUP($E70,Hybrid!$1:$1048576,MATCH(DATE(M$2,1,1),Hybrid!$A$1:$LI$1),FALSE) -> 0.21804646 | ... AO70: =VLOOKUP($E70,Hybrid!$1:$1048576,MATCH(DATE(AO$2,1,1),Hybrid!$A$1:$LI$1),FALSE) -> 0.22732378
D71: class A | E71: NEWAUTO_ca_cgas_2 | F71: =VLOOKUP($E71,Hybrid!$1:$1048576,MATCH(DATE(F$2,1,1),Hybrid!$A$1:$LI$1),FALSE) -> 0.0444153 | G71: =VLOOKUP($E71,Hybrid!$1:$1048576,MATCH(DATE(G$2,1,1),Hybrid!$A$1:$LI$1),FALSE) -> 0.050260969 | H71: =VLOOKUP($E71,Hybrid!$1:$1048576,MATCH(DATE(H$2,1,1),Hybrid!$A$1:$LI$1),FALSE) -> 0.054636102 | I71: =VLOOKUP($E71,Hybrid!$1:$1048576,MATCH(DATE(I$2,1,1),Hybrid!$A$1:$LI$1),FALSE) -> 0.05795781 | J71: =VLOOKUP($E71,Hybrid!$1:$1048576,MATCH(DATE(J$2,1,1),Hybrid!$A$1:$LI$1),FALSE) -> 0.060540111 | K71: =VLOOKUP($E71,Hybrid!$1:$1048576,MATCH(DATE(K$2,1,1),Hybrid!$A$1:$LI$1),FALSE) -> 0.062611156 | L71: =VLOOKUP($E71,Hybrid!$1:$1048576,MATCH(DATE(L$2,1,1),Hybrid!$A$1:$LI$1),FALSE) -> 0.064382159 | M71: =VLOOKUP($E71,Hybrid!$1:$1048576,MATCH(DATE(M$2,1,1),Hybrid!$A$1:$LI$1),FALSE) -> 0.065992601 | ... AO71: =VLOOKUP($E71,Hybrid!$1:$1048576,MATCH(DATE(AO$2,1,1),Hybrid!$A$1:$LI$1),FALSE) -> 0.087785374
D72: class B | E72: NEWAUTO_cb_cgas_2 | F72: =VLOOKUP($E72,Hybrid!$1:$1048576,MATCH(DATE(F$2,1,1),Hybrid!$A$1:$LI$1),FALSE) -> 0.0426412 | G72: =VLOOKUP($E72,Hybrid!$1:$1048576,MATCH(DATE(G$2,1,1),Hybrid!$A$1:$LI$1),FALSE) -> 0.048195163 | H72: =VLOOKUP($E72,Hybrid!$1:$1048576,MATCH(DATE(H$2,1,1),Hybrid!$A$1:$LI$1),FALSE) -> 0.052291955 | I72: =VLOOKUP($E72,Hybrid!$1:$1048576,MATCH(DATE(I$2,1,1),Hybrid!$A$1:$LI$1),FALSE) -> 0.05534693 | J72: =VLOOKUP($E72,Hybrid!$1:$1048576,MATCH(DATE(J$2,1,1),Hybrid!$A$1:$LI$1),FALSE) -> 0.057671055 | K72: =VLOOKUP($E72,Hybrid!$1:$1048576,MATCH(DATE(K$2,1,1),Hybrid!$A$1:$LI$1),FALSE) -> 0.059488303 | L72: =VLOOKUP($E72,Hybrid!$1:$1048576,MATCH(DATE(L$2,1,1),Hybrid!$A$1:$LI$1),FALSE) -> 0.06100366 | M72: =VLOOKUP($E72,Hybrid!$1:$1048576,MATCH(DATE(M$2,1,1),Hybrid!$A$1:$LI$1),FALSE) -> 0.062353199 | ... AO72: =VLOOKUP($E72,Hybrid!$1:$1048576,MATCH(DATE(AO$2,1,1),Hybrid!$A$1:$LI$1),FALSE) -> 0.073418728
D73: class C | E73: NEWAUTO_cc_cgas_2 | F73: =VLOOKUP($E73,Hybrid!$1:$1048576,MATCH(DATE(F$2,1,1),Hybrid!$A$1:$LI$1),FALSE) -> 0.029516 | G73: =VLOOKUP($E73,Hybrid!$1:$1048576,MATCH(DATE(G$2,1,1),Hybrid!$A$1:$LI$1),FALSE) -> 0.033320414 | H73: =VLOOKUP($E73,Hybrid!$1:$1048576,MATCH(DATE(H$2,1,1),Hybrid!$A$1:$LI$1),FALSE) -> 0.036085297 | I73: =VLOOKUP($E73,Hybrid!$1:$1048576,MATCH(DATE(I$2,1,1),Hybrid!$A$1:$LI$1),FALSE) -> 0.038108634 | J73: =VLOOKUP($E73,Hybrid!$1:$1048576,MATCH(DATE(J$2,1,1),Hybrid!$A$1:$LI$1),FALSE) -> 0.039612353 | K73: =VLOOKUP($E73,Hybrid!$1:$1048576,MATCH(DATE(K$2,1,1),Hybrid!$A$1:$LI$1),FALSE) -> 0.040754997 | L73: =VLOOKUP($E73,Hybrid!$1:$1048576,MATCH(DATE(L$2,1,1),Hybrid!$A$1:$LI$1),FALSE) -> 0.041680066 | M73: =VLOOKUP($E73,Hybrid!$1:$1048576,MATCH(DATE(M$2,1,1),Hybrid!$A$1:$LI$1),FALSE) -> 0.0424833 | ... AO73: =VLOOKUP($E73,Hybrid!$1:$1048576,MATCH(DATE(AO$2,1,1),Hybrid!$A$1:$LI$1),FALSE) -> 0.04437171
D74: class D | E74: NEWAUTO_cd_cgas_2 | F74: =VLOOKUP($E74,Hybrid!$1:$1048576,MATCH(DATE(F$2,1,1),Hybrid!$A$1:$LI$1),FALSE) -> 0.0163594 | G74: =VLOOKUP($E74,Hybrid!$1:$1048576,MATCH(DATE(G$2,1,1),Hybrid!$A$1:$LI$1),FALSE) -> 0.018367818 | H74: =VLOOKUP($E74,Hybrid!$1:$1048576,MATCH(DATE(H$2,1,1),Hybrid!$A$1:$LI$1),FALSE) -> 0.019727362 | I74: =VLOOKUP($E74,Hybrid!$1:$1048576,MATCH(DATE(I$2,1,1),Hybrid!$A$1:$LI$1),FALSE) -> 0.0206298 | J74: =VLOOKUP($E74,Hybrid!$1:$1048576,MATCH(DATE(J$2,1,1),Hybrid!$A$1:$LI$1),FALSE) -> 0.021216136 | K74: =VLOOKUP($E74,Hybrid!$1:$1048576,MATCH(DATE(K$2,1,1),Hybrid!$A$1:$LI$1),FALSE) -> 0.021584941 | L74: =VLOOKUP($E74,Hybrid!$1:$1048576,MATCH(DATE(L$2,1,1),Hybrid!$A$1:$LI$1),FALSE) -> 0.02182084 | M74: =VLOOKUP($E74,Hybrid!$1:$1048576,MATCH(DATE(M$2,1,1),Hybrid!$A$1:$LI$1),FALSE) -> 0.021979291 | ... AO74: =VLOOKUP($E74,Hybrid!$1:$1048576,MATCH(DATE(AO$2,1,1),Hybrid!$A$1:$LI$1),FALSE) -> 0.015318968
D75: class E | E75: NEWAUTO_ce_cgas_2 | F75: =VLOOKUP($E75,Hybrid!$1:$1048576,MATCH(DATE(F$2,1,1),Hybrid!$A$1:$LI$1),FALSE) -> 0.0100637 | G75: =VLOOKUP($E75,Hybrid!$1:$1048576,MATCH(DATE(G$2,1,1),Hybrid!$A$1:$LI$1),FALSE) -> 0.011243789 | H75: =VLOOKUP($E75,Hybrid!$1:$1048576,MATCH(DATE(H$2,1,1),Hybrid!$A$1:$LI$1),FALSE) -> 0.011985618 | I75: =VLOOKUP($E75,Hybrid!$1:$1048576,MATCH(DATE(I$2,1,1),Hybrid!$A$1:$LI$1),FALSE) -> 0.01242278 | J75: =VLOOKUP($E75,Hybrid!$1:$1048576,MATCH(DATE(J$2,1,1),Hybrid!$A$1:$LI$1),FALSE) -> 0.012652461 | K75: =VLOOKUP($E75,Hybrid!$1:$1048576,MATCH(DATE(K$2,1,1),Hybrid!$A$1:$LI$1),FALSE) -> 0.012741435 | L75: =VLOOKUP($E75,Hybrid!$1:$1048576,MATCH(DATE(L$2,1,1),Hybrid!$A$1:$LI$1),FALSE) -> 0.012744713 | M75: =VLOOKUP($E75,Hybrid!$1:$1048576,MATCH(DATE(M$2,1,1),Hybrid!$A$1:$LI$1),FALSE) -> 0.012697956 | ... AO75: =VLOOKUP($E75,Hybrid!$1:$1048576,MATCH(DATE(AO$2,1,1),Hybrid!$A$1:$LI$1),FALSE) -> 0.005719231
D76: class F | E76: NEWAUTO_cf_cgas_2 | F76: =VLOOKUP($E76,Hybrid!$1:$1048576,MATCH(DATE(F$2,1,1),Hybrid!$A$1:$LI$1),FALSE) -> 0.004867 | G76: =VLOOKUP($E76,Hybrid!$1:$1048576,MATCH(DATE(G$2,1,1),Hybrid!$A$1:$LI$1),FALSE) -> 0.0053441315 | H76: =VLOOKUP($E76,Hybrid!$1:$1048576,MATCH(DATE(H$2,1,1),Hybrid!$A$1:$LI$1),FALSE) -> 0.005548466 | I76: =VLOOKUP($E76,Hybrid!$1:$1048576,MATCH(DATE(I$2,1,1),Hybrid!$A$1:$LI$1),FALSE) -> 0.0055737855 | J76: =VLOOKUP($E76,Hybrid!$1:$1048576,MATCH(DATE(J$2,1,1),Hybrid!$A$1:$LI$1),FALSE) -> 0.0054863704 | K76: =VLOOKUP($E76,Hybrid!$1:$1048576,MATCH(DATE(K$2,1,1),Hybrid!$A$1:$LI$1),FALSE) -> 0.0053297987 | L76: =VLOOKUP($E76,Hybrid!$1:$1048576,MATCH(DATE(L$2,1,1),Hybrid!$A$1:$LI$1),FALSE) -> 0.0051360402 | M76: =VLOOKUP($E76,Hybrid!$1:$1048576,MATCH(DATE(M$2,1,1),Hybrid!$A$1:$LI$1),FALSE) -> 0.0049246784 | ... AO76: =VLOOKUP($E76,Hybrid!$1:$1048576,MATCH(DATE(AO$2,1,1),Hybrid!$A$1:$LI$1),FALSE) -> 0.00050453775
D77: class G | E77: NEWAUTO_cg_cgas_2 | F77: =VLOOKUP($E77,Hybrid!$1:$1048576,MATCH(DATE(F$2,1,1),Hybrid!$A$1:$LI$1),FALSE) -> 0.0091374 | G77: =VLOOKUP($E77,Hybrid!$1:$1048576,MATCH(DATE(G$2,1,1),Hybrid!$A$1:$LI$1),FALSE) -> 0.0098818921 | H77: =VLOOKUP($E77,Hybrid!$1:$1048576,MATCH(DATE(H$2,1,1),Hybrid!$A$1:$LI$1),FALSE) -> 0.010026566 | I77: =VLOOKUP($E77,Hybrid!$1:$1048576,MATCH(DATE(I$2,1,1),Hybrid!$A$1:$LI$1),FALSE) -> 0.0098008468 | J77: =VLOOKUP($E77,Hybrid!$1:$1048576,MATCH(DATE(J$2,1,1),Hybrid!$A$1:$LI$1),FALSE) -> 0.0093626396 | K77: =VLOOKUP($E77,Hybrid!$1:$1048576,MATCH(DATE(K$2,1,1),Hybrid!$A$1:$LI$1),FALSE) -> 0.008811971 | L77: =VLOOKUP($E77,Hybrid!$1:$1048576,MATCH(DATE(L$2,1,1),Hybrid!$A$1:$LI$1),FALSE) -> 0.0082165171 | M77: =VLOOKUP($E77,Hybrid!$1:$1048576,MATCH(DATE(M$2,1,1),Hybrid!$A$1:$LI$1),FALSE) -> 0.0076154303 | ... AO77: =VLOOKUP($E77,Hybrid!$1:$1048576,MATCH(DATE(AO$2,1,1),Hybrid!$A$1:$LI$1),FALSE) -> 0.00020523279
C78: TOTAL SALES BASELINE | E78: NEWAUTO_0 | F78: =VLOOKUP($E78,Hybrid!$1:$1048576,MATCH(DATE(F$2,1,1),Hybrid!$A$1:$LI$1),FALSE) -> 1886.229 | G78: =VLOOKUP($E78,Hybrid!$1:$1048576,MATCH(DATE(G$2,1,1),Hybrid!$A$1:$LI$1),FALSE) -> 2126.9764 | H78: =VLOOKUP($E78,Hybrid!$1:$1048576,MATCH(DATE(H$2,1,1),Hybrid!$A$1:$LI$1),FALSE) -> 2294.442 | I78: =VLOOKUP($E78,Hybrid!$1:$1048576,MATCH(DATE(I$2,1,1),Hybrid!$A$1:$LI$1),FALSE) -> 2411.5025 | J78: =VLOOKUP($E78,Hybrid!$1:$1048576,MATCH(DATE(J$2,1,1),Hybrid!$A$1:$LI$1),FALSE) -> 2495.0188 | K78: =VLOOKUP($E78,Hybrid!$1:$1048576,MATCH(DATE(K$2,1,1),Hybrid!$A$1:$LI$1),FALSE) -> 2556.7025 | L78: =VLOOKUP($E78,Hybrid!$1:$1048576,MATCH(DATE(L$2,1,1),Hybrid!$A$1:$LI$1),FALSE) -> 2604.3377 | M78: =VLOOKUP($E78,Hybrid!$1:$1048576,MATCH(DATE(M$2,1,1),Hybrid!$A$1:$LI$1),FALSE) -> 2642.9422 | ... AO78: =VLOOKUP($E78,Hybrid!$1:$1048576,MATCH(DATE(AO$2,1,1),Hybrid!$A$1:$LI$1),FALSE) -> 3207.9058
C79: OIL | E79: NEWAUTO_cfut_0 | F79: =VLOOKUP($E79,Hybrid!$1:$1048576,MATCH(DATE(F$2,1,1),Hybrid!$A$1:$LI$1),FALSE) -> 1868.803 | G79: =VLOOKUP($E79,Hybrid!$1:$1048576,MATCH(DATE(G$2,1,1),Hybrid!$A$1:$LI$1),FALSE) -> 2107.3251 | H79: =VLOOKUP($E79,Hybrid!$1:$1048576,MATCH(DATE(H$2,1,1),Hybrid!$A$1:$LI$1),FALSE) -> 2273.2378 | I79: =VLOOKUP($E79,Hybrid!$1:$1048576,MATCH(DATE(I$2,1,1),Hybrid!$A$1:$LI$1),FALSE) -> 2389.2032 | J79: =VLOOKUP($E79,Hybrid!$1:$1048576,MATCH(DATE(J$2,1,1),Hybrid!$A$1:$LI$1),FALSE) -> 2471.9245 | K79: =VLOOKUP($E79,Hybrid!$1:$1048576,MATCH(DATE(K$2,1,1),Hybrid!$A$1:$LI$1),FALSE) -> 2533.0045 | L79: =VLOOKUP($E79,Hybrid!$1:$1048576,MATCH(DATE(L$2,1,1),Hybrid!$A$1:$LI$1),FALSE) -> 2580.1565 | M79: =VLOOKUP($E79,Hybrid!$1:$1048576,MATCH(DATE(M$2,1,1),Hybrid!$A$1:$LI$1),FALSE) -> 2618.3528 | ... AO79: =VLOOKUP($E79,Hybrid!$1:$1048576,MATCH(DATE(AO$2,1,1),Hybrid!$A$1:$LI$1),FALSE) -> 3173.0094
D80: class A | E80: NEWAUTO_ca_cfut_0 | F80: =VLOOKUP($E80,Hybrid!$1:$1048576,MATCH(DATE(F$2,1,1),Hybrid!$A$1:$LI$1),FALSE) -> 528.68437 | G80: =VLOOKUP($E80,Hybrid!$1:$1048576,MATCH(DATE(G$2,1,1),Hybrid!$A$1:$LI$1),FALSE) -> 599.67283 | H80: =VLOOKUP($E80,Hybrid!$1:$1048576,MATCH(DATE(H$2,1,1),Hybrid!$A$1:$LI$1),FALSE) -> 652.52067 | I80: =VLOOKUP($E80,Hybrid!$1:$1048576,MATCH(DATE(I$2,1,1),Hybrid!$A$1:$LI$1),FALSE) -> 692.64252 | J80: =VLOOKUP($E80,Hybrid!$1:$1048576,MATCH(DATE(J$2,1,1),Hybrid!$A$1:$LI$1),FALSE) -> 724.10353 | K80: =VLOOKUP($E80,Hybrid!$1:$1048576,MATCH(DATE(K$2,1,1),Hybrid!$A$1:$LI$1),FALSE) -> 749.80735 | L80: =VLOOKUP($E80,Hybrid!$1:$1048576,MATCH(DATE(L$2,1,1),Hybrid!$A$1:$LI$1),FALSE) -> 771.73922 | M80: =VLOOKUP($E80,Hybrid!$1:$1048576,MATCH(DATE(M$2,1,1),Hybrid!$A$1:$LI$1),FALSE) -> 791.21241 | ... AO80: =VLOOKUP($E80,Hybrid!$1:$1048576,MATCH(DATE(AO$2,1,1),Hybrid!$A$1:$LI$1),FALSE) -> 1205.5752
D81: class B | E81: NEWAUTO_cb_cfut_0 | F81: =VLOOKUP($E81,Hybrid!$1:$1048576,MATCH(DATE(F$2,1,1),Hybrid!$A$1:$LI$1),FALSE) -> 507.56689 | G81: =VLOOKUP($E81,Hybrid!$1:$1048576,MATCH(DATE(G$2,1,1),Hybrid!$A$1:$LI$1),FALSE) -> 575.04323 | H81: =VLOOKUP($E81,Hybrid!$1:$1048576,MATCH(DATE(H$2,1,1),Hybrid!$A$1:$LI$1),FALSE) -> 624.6004 | I81: =VLOOKUP($E81,Hybrid!$1:$1048576,MATCH(DATE(I$2,1,1),Hybrid!$A$1:$LI$1),FALSE) -> 661.60013 | J81: =VLOOKUP($E81,Hybrid!$1:$1048576,MATCH(DATE(J$2,1,1),Hybrid!$A$1:$LI$1),FALSE) -> 690.05534 | K81: =VLOOKUP($E81,Hybrid!$1:$1048576,MATCH(DATE(K$2,1,1),Hybrid!$A$1:$LI$1),FALSE) -> 712.81732 | L81: =VLOOKUP($E81,Hybrid!$1:$1048576,MATCH(DATE(L$2,1,1),Hybrid!$A$1:$LI$1),FALSE) -> 731.8247 | M81: =VLOOKUP($E81,Hybrid!$1:$1048576,MATCH(DATE(M$2,1,1),Hybrid!$A$1:$LI$1),FALSE) -> 748.3529 | ... AO81: =VLOOKUP($E81,Hybrid!$1:$1048576,MATCH(DATE(AO$2,1,1),Hybrid!$A$1:$LI$1),FALSE) -> 1030.812
D82: class C | E82: NEWAUTO_cc_cfut_0 | F82: =VLOOKUP($E82,Hybrid!$1:$1048576,MATCH(DATE(F$2,1,1),Hybrid!$A$1:$LI$1),FALSE) -> 351.33496 | G82: =VLOOKUP($E82,Hybrid!$1:$1048576,MATCH(DATE(G$2,1,1),Hybrid!$A$1:$LI$1),FALSE) -> 397.57666 | H82: =VLOOKUP($E82,Hybrid!$1:$1048576,MATCH(DATE(H$2,1,1),Hybrid!$A$1:$LI$1),FALSE) -> 431.07235 | I82: =VLOOKUP($E82,Hybrid!$1:$1048576,MATCH(DATE(I$2,1,1),Hybrid!$A$1:$LI$1),FALSE) -> 455.64815 | J82: =VLOOKUP($E82,Hybrid!$1:$1048576,MATCH(DATE(J$2,1,1),Hybrid!$A$1:$LI$1),FALSE) -> 474.1591 | K82: =VLOOKUP($E82,Hybrid!$1:$1048576,MATCH(DATE(K$2,1,1),Hybrid!$A$1:$LI$1),FALSE) -> 488.62358 | L82: =VLOOKUP($E82,Hybrid!$1:$1048576,MATCH(DATE(L$2,1,1),Hybrid!$A$1:$LI$1),FALSE) -> 500.40662 | M82: =VLOOKUP($E82,Hybrid!$1:$1048576,MATCH(DATE(M$2,1,1),Hybrid!$A$1:$LI$1),FALSE) -> 510.40171 | ... AO82: =VLOOKUP($E82,Hybrid!$1:$1048576,MATCH(DATE(AO$2,1,1),Hybrid!$A$1:$LI$1),FALSE) -> 636.27918
D83: class D | E83: NEWAUTO_cd_cfut_0 | F83: =VLOOKUP($E83,Hybrid!$1:$1048576,MATCH(DATE(F$2,1,1),Hybrid!$A$1:$LI$1),FALSE) -> 194.72927 | G83: =VLOOKUP($E83,Hybrid!$1:$1048576,MATCH(DATE(G$2,1,1),Hybrid!$A$1:$LI$1),FALSE) -> 219.16848 | H83: =VLOOKUP($E83,Hybrid!$1:$1048576,MATCH(DATE(H$2,1,1),Hybrid!$A$1:$LI$1),FALSE) -> 235.68359 | I83: =VLOOKUP($E83,Hybrid!$1:$1048576,MATCH(DATE(I$2,1,1),Hybrid!$A$1:$LI$1),FALSE) -> 246.70455 | J83: =VLOOKUP($E83,Hybrid!$1:$1048576,MATCH(DATE(J$2,1,1),Hybrid!$A$1:$LI$1),FALSE) -> 254.0236 | K83: =VLOOKUP($E83,Hybrid!$1:$1048576,MATCH(DATE(K$2,1,1),Hybrid!$A$1:$LI$1),FALSE) -> 258.8825 | L83: =VLOOKUP($E83,Hybrid!$1:$1048576,MATCH(DATE(L$2,1,1),Hybrid!$A$1:$LI$1),FALSE) -> 262.10336 | M83: =VLOOKUP($E83,Hybrid!$1:$1048576,MATCH(DATE(M$2,1,1),Hybrid!$A$1:$LI$1),FALSE) -> 264.21365 | ... AO83: =VLOOKUP($E83,Hybrid!$1:$1048576,MATCH(DATE(AO$2,1,1),Hybrid!$A$1:$LI$1),FALSE) -> 209.56755
D84: class E | E84: NEWAUTO_ce_cfut_0 | F84: =VLOOKUP($E84,Hybrid!$1:$1048576,MATCH(DATE(F$2,1,1),Hybrid!$A$1:$LI$1),FALSE) -> 119.79027 | G84: =VLOOKUP($E84,Hybrid!$1:$1048576,MATCH(DATE(G$2,1,1),Hybrid!$A$1:$LI$1),FALSE) -> 134.16754 | H84: =VLOOKUP($E84,Hybrid!$1:$1048576,MATCH(DATE(H$2,1,1),Hybrid!$A$1:$LI$1),FALSE) -> 143.21188 | I84: =VLOOKUP($E84,Hybrid!$1:$1048576,MATCH(DATE(I$2,1,1),Hybrid!$A$1:$LI$1),FALSE) -> 148.59992 | J84: =VLOOKUP($E84,Hybrid!$1:$1048576,MATCH(DATE(J$2,1,1),Hybrid!$A$1:$LI$1),FALSE) -> 151.5567 | K84: =VLOOKUP($E84,Hybrid!$1:$1048576,MATCH(DATE(K$2,1,1),Hybrid!$A$1:$LI$1),FALSE) -> 152.91812 | L84: =VLOOKUP($E84,Hybrid!$1:$1048576,MATCH(DATE(L$2,1,1),Hybrid!$A$1:$LI$1),FALSE) -> 153.22891 | M84: =VLOOKUP($E84,Hybrid!$1:$1048576,MATCH(DATE(M$2,1,1),Hybrid!$A$1:$LI$1),FALSE) -> 152.83366 | ... AO84: =VLOOKUP($E84,Hybrid!$1:$1048576,MATCH(DATE(AO$2,1,1),Hybrid!$A$1:$LI$1),FALSE) -> 80.483787
D85: class F | E85: NEWAUTO_cf_cfut_0 | F85: =VLOOKUP($E85,Hybrid!$1:$1048576,MATCH(DATE(F$2,1,1),Hybrid!$A$1:$LI$1),FALSE) -> 57.932893 | G85: =VLOOKUP($E85,Hybrid!$1:$1048576,MATCH(DATE(G$2,1,1),Hybrid!$A$1:$LI$1),FALSE) -> 63.771508 | H85: =VLOOKUP($E85,Hybrid!$1:$1048576,MATCH(DATE(H$2,1,1),Hybrid!$A$1:$LI$1),FALSE) -> 66.307033 | I85: =VLOOKUP($E85,Hybrid!$1:$1048576,MATCH(DATE(I$2,1,1),Hybrid!$A$1:$LI$1),FALSE) -> 66.694489 | J85: =VLOOKUP($E85,Hybrid!$1:$1048576,MATCH(DATE(J$2,1,1),Hybrid!$A$1:$LI$1),FALSE) -> 65.753401 | K85: =VLOOKUP($E85,Hybrid!$1:$1048576,MATCH(DATE(K$2,1,1),Hybrid!$A$1:$LI$1),FALSE) -> 64.018948 | L85: =VLOOKUP($E85,Hybrid!$1:$1048576,MATCH(DATE(L$2,1,1),Hybrid!$A$1:$LI$1),FALSE) -> 61.82402 | M85: =VLOOKUP($E85,Hybrid!$1:$1048576,MATCH(DATE(M$2,1,1),Hybrid!$A$1:$LI$1),FALSE) -> 59.370208 | ... AO85: =VLOOKUP($E85,Hybrid!$1:$1048576,MATCH(DATE(AO$2,1,1),Hybrid!$A$1:$LI$1),FALSE) -> 7.2222627
D86: class G | E86: NEWAUTO_cg_cfut_0 | F86: =VLOOKUP($E86,Hybrid!$1:$1048576,MATCH(DATE(F$2,1,1),Hybrid!$A$1:$LI$1),FALSE) -> 108.76433 | G86: =VLOOKUP($E86,Hybrid!$1:$1048576,MATCH(DATE(G$2,1,1),Hybrid!$A$1:$LI$1),FALSE) -> 117.92484 | H86: =VLOOKUP($E86,Hybrid!$1:$1048576,MATCH(DATE(H$2,1,1),Hybrid!$A$1:$LI$1),FALSE) -> 119.84185 | I86: =VLOOKUP($E86,Hybrid!$1:$1048576,MATCH(DATE(I$2,1,1),Hybrid!$A$1:$LI$1),FALSE) -> 117.31344 | J86: =VLOOKUP($E86,Hybrid!$1:$1048576,MATCH(DATE(J$2,1,1),Hybrid!$A$1:$LI$1),FALSE) -> 112.27278 | K86: =VLOOKUP($E86,Hybrid!$1:$1048576,MATCH(DATE(K$2,1,1),Hybrid!$A$1:$LI$1),FALSE) -> 105.93669 | L86: =VLOOKUP($E86,Hybrid!$1:$1048576,MATCH(DATE(L$2,1,1),Hybrid!$A$1:$LI$1),FALSE) -> 99.029629 | M86: =VLOOKUP($E86,Hybrid!$1:$1048576,MATCH(DATE(M$2,1,1),Hybrid!$A$1:$LI$1),FALSE) -> 91.968223 | ... AO86: =VLOOKUP($E86,Hybrid!$1:$1048576,MATCH(DATE(AO$2,1,1),Hybrid!$A$1:$LI$1),FALSE) -> 3.069401
C87: ELEC | E87: NEWAUTO_cele_0 | F87: =VLOOKUP($E87,Hybrid!$1:$1048576,MATCH(DATE(F$2,1,1),Hybrid!$A$1:$LI$1),FALSE) -> 17.269 | G87: =VLOOKUP($E87,Hybrid!$1:$1048576,MATCH(DATE(G$2,1,1),Hybrid!$A$1:$LI$1),FALSE) -> 19.474316 | H87: =VLOOKUP($E87,Hybrid!$1:$1048576,MATCH(DATE(H$2,1,1),Hybrid!$A$1:$LI$1),FALSE) -> 21.013204 | I87: =VLOOKUP($E87,Hybrid!$1:$1048576,MATCH(DATE(I$2,1,1),Hybrid!$A$1:$LI$1),FALSE) -> 22.098555 | J87: =VLOOKUP($E87,Hybrid!$1:$1048576,MATCH(DATE(J$2,1,1),Hybrid!$A$1:$LI$1),FALSE) -> 22.886708 | K87: =VLOOKUP($E87,Hybrid!$1:$1048576,MATCH(DATE(K$2,1,1),Hybrid!$A$1:$LI$1),FALSE) -> 23.485189 | L87: =VLOOKUP($E87,Hybrid!$1:$1048576,MATCH(DATE(L$2,1,1),Hybrid!$A$1:$LI$1),FALSE) -> 23.964516 | M87: =VLOOKUP($E87,Hybrid!$1:$1048576,MATCH(DATE(M$2,1,1),Hybrid!$A$1:$LI$1),FALSE) -> 24.369515 | ... AO87: =VLOOKUP($E87,Hybrid!$1:$1048576,MATCH(DATE(AO$2,1,1),Hybrid!$A$1:$LI$1),FALSE) -> 34.629865
D88: class A | E88: NEWAUTO_ca_cele_0 | F88: =VLOOKUP($E88,Hybrid!$1:$1048576,MATCH(DATE(F$2,1,1),Hybrid!$A$1:$LI$1),FALSE) -> 4.8854001 | G88: =VLOOKUP($E88,Hybrid!$1:$1048576,MATCH(DATE(G$2,1,1),Hybrid!$A$1:$LI$1),FALSE) -> 5.5417375 | H88: =VLOOKUP($E88,Hybrid!$1:$1048576,MATCH(DATE(H$2,1,1),Hybrid!$A$1:$LI$1),FALSE) -> 6.0318007 | I88: =VLOOKUP($E88,Hybrid!$1:$1048576,MATCH(DATE(I$2,1,1),Hybrid!$A$1:$LI$1),FALSE) -> 6.4067081 | J88: =VLOOKUP($E88,Hybrid!$1:$1048576,MATCH(DATE(J$2,1,1),Hybrid!$A$1:$LI$1),FALSE) -> 6.7046879 | K88: =VLOOKUP($E88,Hybrid!$1:$1048576,MATCH(DATE(K$2,1,1),Hybrid!$A$1:$LI$1),FALSE) -> 6.9527355 | L88: =VLOOKUP($E88,Hybrid!$1:$1048576,MATCH(DATE(L$2,1,1),Hybrid!$A$1:$LI$1),FALSE) -> 7.1690294 | M88: =VLOOKUP($E88,Hybrid!$1:$1048576,MATCH(DATE(M$2,1,1),Hybrid!$A$1:$LI$1),FALSE) -> 7.3654149 | ... AO88: =VLOOKUP($E88,Hybrid!$1:$1048576,MATCH(DATE(AO$2,1,1),Hybrid!$A$1:$LI$1),FALSE) -> 13.091208
D89: class B | E89: NEWAUTO_cb_cele_0 | F89: =VLOOKUP($E89,Hybrid!$1:$1048576,MATCH(DATE(F$2,1,1),Hybrid!$A$1:$LI$1),FALSE) -> 4.6902604 | G89: =VLOOKUP($E89,Hybrid!$1:$1048576,MATCH(DATE(G$2,1,1),Hybrid!$A$1:$LI$1),FALSE) -> 5.3141672 | H89: =VLOOKUP($E89,Hybrid!$1:$1048576,MATCH(DATE(H$2,1,1),Hybrid!$A$1:$LI$1),FALSE) -> 5.7739233 | I89: =VLOOKUP($E89,Hybrid!$1:$1048576,MATCH(DATE(I$2,1,1),Hybrid!$A$1:$LI$1),FALSE) -> 6.120204 | J89: =VLOOKUP($E89,Hybrid!$1:$1048576,MATCH(DATE(J$2,1,1),Hybrid!$A$1:$LI$1),FALSE) -> 6.3907699 | K89: =VLOOKUP($E89,Hybrid!$1:$1048576,MATCH(DATE(K$2,1,1),Hybrid!$A$1:$LI$1),FALSE) -> 6.6121172 | L89: =VLOOKUP($E89,Hybrid!$1:$1048576,MATCH(DATE(L$2,1,1),Hybrid!$A$1:$LI$1),FALSE) -> 6.8019618 | M89: =VLOOKUP($E89,Hybrid!$1:$1048576,MATCH(DATE(M$2,1,1),Hybrid!$A$1:$LI$1),FALSE) -> 6.9717637 | ... AO89: =VLOOKUP($E89,Hybrid!$1:$1048576,MATCH(DATE(AO$2,1,1),Hybrid!$A$1:$LI$1),FALSE) -> 11.373165
D90: class C | E90: NEWAUTO_cc_cele_0 | F90: =VLOOKUP($E90,Hybrid!$1:$1048576,MATCH(DATE(F$2,1,1),Hybrid!$A$1:$LI$1),FALSE) -> 3.246572 | G90: =VLOOKUP($E90,Hybrid!$1:$1048576,MATCH(DATE(G$2,1,1),Hybrid!$A$1:$LI$1),FALSE) -> 3.6741607 | H90: =VLOOKUP($E90,Hybrid!$1:$1048576,MATCH(DATE(H$2,1,1),Hybrid!$A$1:$LI$1),FALSE) -> 3.9850409 | I90: =VLOOKUP($E90,Hybrid!$1:$1048576,MATCH(DATE(I$2,1,1),Hybrid!$A$1:$LI$1),FALSE) -> 4.2154068 | J90: =VLOOKUP($E90,Hybrid!$1:$1048576,MATCH(DATE(J$2,1,1),Hybrid!$A$1:$LI$1),FALSE) -> 4.3921338 | K90: =VLOOKUP($E90,Hybrid!$1:$1048576,MATCH(DATE(K$2,1,1),Hybrid!$A$1:$LI$1),FALSE) -> 4.5339664 | L90: =VLOOKUP($E90,Hybrid!$1:$1048576,MATCH(DATE(L$2,1,1),Hybrid!$A$1:$LI$1),FALSE) -> 4.6533531 | M90: =VLOOKUP($E90,Hybrid!$1:$1048576,MATCH(DATE(M$2,1,1),Hybrid!$A$1:$LI$1),FALSE) -> 4.7582905 | ... AO90: =VLOOKUP($E90,Hybrid!$1:$1048576,MATCH(DATE(AO$2,1,1),Hybrid!$A$1:$LI$1),FALSE) -> 7.1191279
D91: class D | E91: NEWAUTO_cd_cele_0 | F91: =VLOOKUP($E91,Hybrid!$1:$1048576,MATCH(DATE(F$2,1,1),Hybrid!$A$1:$LI$1),FALSE) -> 1.7994298 | G91: =VLOOKUP($E91,Hybrid!$1:$1048576,MATCH(DATE(G$2,1,1),Hybrid!$A$1:$LI$1),FALSE) -> 2.0253384 | H91: =VLOOKUP($E91,Hybrid!$1:$1048576,MATCH(DATE(H$2,1,1),Hybrid!$A$1:$LI$1),FALSE) -> 2.1782908 | I91: =VLOOKUP($E91,Hybrid!$1:$1048576,MATCH(DATE(I$2,1,1),Hybrid!$A$1:$LI$1),FALSE) -> 2.2809357 | J91: =VLOOKUP($E91,Hybrid!$1:$1048576,MATCH(DATE(J$2,1,1),Hybrid!$A$1:$LI$1),FALSE) -> 2.3499331 | K91: =VLOOKUP($E91,Hybrid!$1:$1048576,MATCH(DATE(K$2,1,1),Hybrid!$A$1:$LI$1),FALSE) -> 2.3967536 | L91: =VLOOKUP($E91,Hybrid!$1:$1048576,MATCH(DATE(L$2,1,1),Hybrid!$A$1:$LI$1),FALSE) -> 2.4289281 | M91: =VLOOKUP($E91,Hybrid!$1:$1048576,MATCH(DATE(M$2,1,1),Hybrid!$A$1:$LI$1),FALSE) -> 2.4512461 | ... AO91: =VLOOKUP($E91,Hybrid!$1:$1048576,MATCH(DATE(AO$2,1,1),Hybrid!$A$1:$LI$1),FALSE) -> 2.1165445
D92: class E | E92: NEWAUTO_ce_cele_0 | F92: =VLOOKUP($E92,Hybrid!$1:$1048576,MATCH(DATE(F$2,1,1),Hybrid!$A$1:$LI$1),FALSE) -> 1.1069429 | G92: =VLOOKUP($E92,Hybrid!$1:$1048576,MATCH(DATE(G$2,1,1),Hybrid!$A$1:$LI$1),FALSE) -> 1.2398534 | H92: =VLOOKUP($E92,Hybrid!$1:$1048576,MATCH(DATE(H$2,1,1),Hybrid!$A$1:$LI$1),FALSE) -> 1.3236809 | I92: =VLOOKUP($E92,Hybrid!$1:$1048576,MATCH(DATE(I$2,1,1),Hybrid!$A$1:$LI$1),FALSE) -> 1.3740547 | J92: =VLOOKUP($E92,Hybrid!$1:$1048576,MATCH(DATE(J$2,1,1),Hybrid!$A$1:$LI$1),FALSE) -> 1.4023553 | K92: =VLOOKUP($E92,Hybrid!$1:$1048576,MATCH(DATE(K$2,1,1),Hybrid!$A$1:$LI$1),FALSE) -> 1.4162911 | L92: =VLOOKUP($E92,Hybrid!$1:$1048576,MATCH(DATE(L$2,1,1),Hybrid!$A$1:$LI$1),FALSE) -> 1.4208363 | M92: =VLOOKUP($E92,Hybrid!$1:$1048576,MATCH(DATE(M$2,1,1),Hybrid!$A$1:$LI$1),FALSE) -> 1.4191046 | ... AO92: =VLOOKUP($E92,Hybrid!$1:$1048576,MATCH(DATE(AO$2,1,1),Hybrid!$A$1:$LI$1),FALSE) -> 0.82719028
D93: class F | E93: NEWAUTO_cf_cele_0 | F93: =VLOOKUP($E93,Hybrid!$1:$1048576,MATCH(DATE(F$2,1,1),Hybrid!$A$1:$LI$1),FALSE) -> 0.535339 | G93: =VLOOKUP($E93,Hybrid!$1:$1048576,MATCH(DATE(G$2,1,1),Hybrid!$A$1:$LI$1),FALSE) -> 0.58931108 | H93: =VLOOKUP($E93,Hybrid!$1:$1048576,MATCH(DATE(H$2,1,1),Hybrid!$A$1:$LI$1),FALSE) -> 0.61282441 | I93: =VLOOKUP($E93,Hybrid!$1:$1048576,MATCH(DATE(I$2,1,1),Hybrid!$A$1:$LI$1),FALSE) -> 0.61658713 | J93: =VLOOKUP($E93,Hybrid!$1:$1048576,MATCH(DATE(J$2,1,1),Hybrid!$A$1:$LI$1),FALSE) -> 0.60817748 | K93: =VLOOKUP($E93,Hybrid!$1:$1048576,MATCH(DATE(K$2,1,1),Hybrid!$A$1:$LI$1),FALSE) -> 0.59252181 | L93: =VLOOKUP($E93,Hybrid!$1:$1048576,MATCH(DATE(L$2,1,1),Hybrid!$A$1:$LI$1),FALSE) -> 0.57266692 | M93: =VLOOKUP($E93,Hybrid!$1:$1048576,MATCH(DATE(M$2,1,1),Hybrid!$A$1:$LI$1),FALSE) -> 0.55044725 | ... AO93: =VLOOKUP($E93,Hybrid!$1:$1048576,MATCH(DATE(AO$2,1,1),Hybrid!$A$1:$LI$1),FALSE) -> 0.071730931
D94: class G | E94: NEWAUTO_cg_cele_0 | F94: =VLOOKUP($E94,Hybrid!$1:$1048576,MATCH(DATE(F$2,1,1),Hybrid!$A$1:$LI$1),FALSE) -> 1.0050558 | G94: =VLOOKUP($E94,Hybrid!$1:$1048576,MATCH(DATE(G$2,1,1),Hybrid!$A$1:$LI$1),FALSE) -> 1.0897479 | H94: =VLOOKUP($E94,Hybrid!$1:$1048576,MATCH(DATE(H$2,1,1),Hybrid!$A$1:$LI$1),FALSE) -> 1.1076426 | I94: =VLOOKUP($E94,Hybrid!$1:$1048576,MATCH(DATE(I$2,1,1),Hybrid!$A$1:$LI$1),FALSE) -> 1.0846584 | J94: =VLOOKUP($E94,Hybrid!$1:$1048576,MATCH(DATE(J$2,1,1),Hybrid!$A$1:$LI$1),FALSE) -> 1.0386501 | K94: =VLOOKUP($E94,Hybrid!$1:$1048576,MATCH(DATE(K$2,1,1),Hybrid!$A$1:$LI$1),FALSE) -> 0.98080334 | L94: =VLOOKUP($E94,Hybrid!$1:$1048576,MATCH(DATE(L$2,1,1),Hybrid!$A$1:$LI$1),FALSE) -> 0.91774013 | M94: =VLOOKUP($E94,Hybrid!$1:$1048576,MATCH(DATE(M$2,1,1),Hybrid!$A$1:$LI$1),FALSE) -> 0.85324779 | ... AO94: =VLOOKUP($E94,Hybrid!$1:$1048576,MATCH(DATE(AO$2,1,1),Hybrid!$A$1:$LI$1),FALSE) -> 0.030897972
C95: GAS | E95: NEWAUTO_cgas_0 | F95: =VLOOKUP($E95,Hybrid!$1:$1048576,MATCH(DATE(F$2,1,1),Hybrid!$A$1:$LI$1),FALSE) -> 0.157 | G95: =VLOOKUP($E95,Hybrid!$1:$1048576,MATCH(DATE(G$2,1,1),Hybrid!$A$1:$LI$1),FALSE) -> 0.17703848 | H95: =VLOOKUP($E95,Hybrid!$1:$1048576,MATCH(DATE(H$2,1,1),Hybrid!$A$1:$LI$1),FALSE) -> 0.19097697 | I95: =VLOOKUP($E95,Hybrid!$1:$1048576,MATCH(DATE(I$2,1,1),Hybrid!$A$1:$LI$1),FALSE) -> 0.20071934 | J95: =VLOOKUP($E95,Hybrid!$1:$1048576,MATCH(DATE(J$2,1,1),Hybrid!$A$1:$LI$1),FALSE) -> 0.20766883 | K95: =VLOOKUP($E95,Hybrid!$1:$1048576,MATCH(DATE(K$2,1,1),Hybrid!$A$1:$LI$1),FALSE) -> 0.21280023 | L95: =VLOOKUP($E95,Hybrid!$1:$1048576,MATCH(DATE(L$2,1,1),Hybrid!$A$1:$LI$1),FALSE) -> 0.21676151 | M95: =VLOOKUP($E95,Hybrid!$1:$1048576,MATCH(DATE(M$2,1,1),Hybrid!$A$1:$LI$1),FALSE) -> 0.21997042 | ... AO95: =VLOOKUP($E95,Hybrid!$1:$1048576,MATCH(DATE(AO$2,1,1),Hybrid!$A$1:$LI$1),FALSE) -> 0.26656768
D96: class A | E96: NEWAUTO_ca_cgas_0 | F96: =VLOOKUP($E96,Hybrid!$1:$1048576,MATCH(DATE(F$2,1,1),Hybrid!$A$1:$LI$1),FALSE) -> 0.0444153 | G96: =VLOOKUP($E96,Hybrid!$1:$1048576,MATCH(DATE(G$2,1,1),Hybrid!$A$1:$LI$1),FALSE) -> 0.050379111 | H96: =VLOOKUP($E96,Hybrid!$1:$1048576,MATCH(DATE(H$2,1,1),Hybrid!$A$1:$LI$1),FALSE) -> 0.054818911 | I96: =VLOOKUP($E96,Hybrid!$1:$1048576,MATCH(DATE(I$2,1,1),Hybrid!$A$1:$LI$1),FALSE) -> 0.058189587 | J96: =VLOOKUP($E96,Hybrid!$1:$1048576,MATCH(DATE(J$2,1,1),Hybrid!$A$1:$LI$1),FALSE) -> 0.060832658 | K96: =VLOOKUP($E96,Hybrid!$1:$1048576,MATCH(DATE(K$2,1,1),Hybrid!$A$1:$LI$1),FALSE) -> 0.062992062 | L96: =VLOOKUP($E96,Hybrid!$1:$1048576,MATCH(DATE(L$2,1,1),Hybrid!$A$1:$LI$1),FALSE) -> 0.06483458 | M96: =VLOOKUP($E96,Hybrid!$1:$1048576,MATCH(DATE(M$2,1,1),Hybrid!$A$1:$LI$1),FALSE) -> 0.066470542 | ... AO96: =VLOOKUP($E96,Hybrid!$1:$1048576,MATCH(DATE(AO$2,1,1),Hybrid!$A$1:$LI$1),FALSE) -> 0.10128157
D97: class B | E97: NEWAUTO_cb_cgas_0 | F97: =VLOOKUP($E97,Hybrid!$1:$1048576,MATCH(DATE(F$2,1,1),Hybrid!$A$1:$LI$1),FALSE) -> 0.0426412 | G97: =VLOOKUP($E97,Hybrid!$1:$1048576,MATCH(DATE(G$2,1,1),Hybrid!$A$1:$LI$1),FALSE) -> 0.048309954 | H97: =VLOOKUP($E97,Hybrid!$1:$1048576,MATCH(DATE(H$2,1,1),Hybrid!$A$1:$LI$1),FALSE) -> 0.052473302 | I97: =VLOOKUP($E97,Hybrid!$1:$1048576,MATCH(DATE(I$2,1,1),Hybrid!$A$1:$LI$1),FALSE) -> 0.055581686 | J97: =VLOOKUP($E97,Hybrid!$1:$1048576,MATCH(DATE(J$2,1,1),Hybrid!$A$1:$LI$1),FALSE) -> 0.057972236 | K97: =VLOOKUP($E97,Hybrid!$1:$1048576,MATCH(DATE(K$2,1,1),Hybrid!$A$1:$LI$1),FALSE) -> 0.059884493 | L97: =VLOOKUP($E97,Hybrid!$1:$1048576,MATCH(DATE(L$2,1,1),Hybrid!$A$1:$LI$1),FALSE) -> 0.061481321 | M97: =VLOOKUP($E97,Hybrid!$1:$1048576,MATCH(DATE(M$2,1,1),Hybrid!$A$1:$LI$1),FALSE) -> 0.062869872 | ... AO97: =VLOOKUP($E97,Hybrid!$1:$1048576,MATCH(DATE(AO$2,1,1),Hybrid!$A$1:$LI$1),FALSE) -> 0.086599541
D98: class C | E98: NEWAUTO_cc_cgas_0 | F98: =VLOOKUP($E98,Hybrid!$1:$1048576,MATCH(DATE(F$2,1,1),Hybrid!$A$1:$LI$1),FALSE) -> 0.029516 | G98: =VLOOKUP($E98,Hybrid!$1:$1048576,MATCH(DATE(G$2,1,1),Hybrid!$A$1:$LI$1),FALSE) -> 0.033400811 | H98: =VLOOKUP($E98,Hybrid!$1:$1048576,MATCH(DATE(H$2,1,1),Hybrid!$A$1:$LI$1),FALSE) -> 0.036214817 | I98: =VLOOKUP($E98,Hybrid!$1:$1048576,MATCH(DATE(I$2,1,1),Hybrid!$A$1:$LI$1),FALSE) -> 0.038279454 | J98: =VLOOKUP($E98,Hybrid!$1:$1048576,MATCH(DATE(J$2,1,1),Hybrid!$A$1:$LI$1),FALSE) -> 0.039834578 | K98: =VLOOKUP($E98,Hybrid!$1:$1048576,MATCH(DATE(K$2,1,1),Hybrid!$A$1:$LI$1),FALSE) -> 0.041049753 | L98: =VLOOKUP($E98,Hybrid!$1:$1048576,MATCH(DATE(L$2,1,1),Hybrid!$A$1:$LI$1),FALSE) -> 0.042039658 | M98: =VLOOKUP($E98,Hybrid!$1:$1048576,MATCH(DATE(M$2,1,1),Hybrid!$A$1:$LI$1),FALSE) -> 0.042879355 | ... AO98: =VLOOKUP($E98,Hybrid!$1:$1048576,MATCH(DATE(AO$2,1,1),Hybrid!$A$1:$LI$1),FALSE) -> 0.053454447
D99: class D | E99: NEWAUTO_cd_cgas_0 | F99: =VLOOKUP($E99,Hybrid!$1:$1048576,MATCH(DATE(F$2,1,1),Hybrid!$A$1:$LI$1),FALSE) -> 0.0163594 | G99: =VLOOKUP($E99,Hybrid!$1:$1048576,MATCH(DATE(G$2,1,1),Hybrid!$A$1:$LI$1),FALSE) -> 0.018412562 | H99: =VLOOKUP($E99,Hybrid!$1:$1048576,MATCH(DATE(H$2,1,1),Hybrid!$A$1:$LI$1),FALSE) -> 0.019800013 | I99: =VLOOKUP($E99,Hybrid!$1:$1048576,MATCH(DATE(I$2,1,1),Hybrid!$A$1:$LI$1),FALSE) -> 0.020725895 | J99: =VLOOKUP($E99,Hybrid!$1:$1048576,MATCH(DATE(J$2,1,1),Hybrid!$A$1:$LI$1),FALSE) -> 0.021340775 | K99: =VLOOKUP($E99,Hybrid!$1:$1048576,MATCH(DATE(K$2,1,1),Hybrid!$A$1:$LI$1),FALSE) -> 0.021748976 | L99: =VLOOKUP($E99,Hybrid!$1:$1048576,MATCH(DATE(L$2,1,1),Hybrid!$A$1:$LI$1),FALSE) -> 0.022019564 | M99: =VLOOKUP($E99,Hybrid!$1:$1048576,MATCH(DATE(M$2,1,1),Hybrid!$A$1:$LI$1),FALSE) -> 0.022196851 | ... AO99: =VLOOKUP($E99,Hybrid!$1:$1048576,MATCH(DATE(AO$2,1,1),Hybrid!$A$1:$LI$1),FALSE) -> 0.017605979
D100: class E | E100: NEWAUTO_ce_cgas_0 | F100: =VLOOKUP($E100,Hybrid!$1:$1048576,MATCH(DATE(F$2,1,1),Hybrid!$A$1:$LI$1),FALSE) -> 0.0100637 | G100: =VLOOKUP($E100,Hybrid!$1:$1048576,MATCH(DATE(G$2,1,1),Hybrid!$A$1:$LI$1),FALSE) -> 0.011271549 | H100: =VLOOKUP($E100,Hybrid!$1:$1048576,MATCH(DATE(H$2,1,1),Hybrid!$A$1:$LI$1),FALSE) -> 0.012031373 | I100: =VLOOKUP($E100,Hybrid!$1:$1048576,MATCH(DATE(I$2,1,1),Hybrid!$A$1:$LI$1),FALSE) -> 0.012484027 | J100: =VLOOKUP($E100,Hybrid!$1:$1048576,MATCH(DATE(J$2,1,1),Hybrid!$A$1:$LI$1),FALSE) -> 0.012732429 | K100: =VLOOKUP($E100,Hybrid!$1:$1048576,MATCH(DATE(K$2,1,1),Hybrid!$A$1:$LI$1),FALSE) -> 0.012846804 | L100: =VLOOKUP($E100,Hybrid!$1:$1048576,MATCH(DATE(L$2,1,1),Hybrid!$A$1:$LI$1),FALSE) -> 0.012872913 | M100: =VLOOKUP($E100,Hybrid!$1:$1048576,MATCH(DATE(M$2,1,1),Hybrid!$A$1:$LI$1),FALSE) -> 0.012839708 | ... AO100: =VLOOKUP($E100,Hybrid!$1:$1048576,MATCH(DATE(AO$2,1,1),Hybrid!$A$1:$LI$1),FALSE) -> 0.006761523
...

Sheet date
A1: =Hybrid!A1 -> _date_ | B1: =Hybrid!B1 -> 42005 | C1: =Hybrid!C1 -> 42370 | D1: =Hybrid!D1 -> 42736 | E1: =Hybrid!E1 -> 43101 | F1: =Hybrid!F1 -> 43466 | G1: =Hybrid!G1 -> 43831 | H1: =Hybrid!H1 -> 44197 | ... AK1: =Hybrid!AK1 -> 54789
B2: =TEXT(B1,"jj mm aaaa") -> 01 01 2015 | C2: =TEXT(C1,"jj mm aaaa") -> 01 01 2016 | D2: =TEXT(D1,"jj mm aaaa") -> 01 01 2017 | E2: =TEXT(E1,"jj mm aaaa") -> 01 01 2018 | F2: =TEXT(F1,"jj mm aaaa") -> 01 01 2019 | G2: =TEXT(G1,"jj mm aaaa") -> 01 01 2020 | H2: =TEXT(H1,"jj mm aaaa") -> 01 01 2021 | I2: =TEXT(I1,"jj mm aaaa") -> 01 01 2022 | ... AK2: =TEXT(AK1,"jj mm aaaa") -> 01 01 2050
B3: =RIGHT(B2,4) -> 2015 | C3: =RIGHT(C2,4) -> 2016 | D3: =RIGHT(D2,4) -> 2017 | E3: =RIGHT(E2,4) -> 2018 | F3: =RIGHT(F2,4) -> 2019 | G3: =RIGHT(G2,4) -> 2020 | H3: =RIGHT(H2,4) -> 2021 | I3: =RIGHT(I2,4) -> 2022 | ... AK3: =RIGHT(AK2,4) -> 2050

Sheet Emissions
A1: _date_ | B1: 42005 | C1: 42370 | D1: 42736 | E1: 43101 | F1: 43466 | G1: 43831 | H1: 44197 | I1: 44562 | J1: 44927 | K1: 45292 | L1: 45658 | M1: 46023 | N1: 46388 | O1: 46753 | P1: 47119 | Q1: 47484 | R1: 47849 | S1: 48214 | T1: 48580 | U1: 48945 | V1: 49310 | W1: 49675 | X1: 50041 | Y1: 50406 | Z1: 50771 | AA1: 51136 | AB1: 51502 | AC1: 51867 | AD1: 52232 | AE1: 52597 | AF1: 52963 | AG1: 53328 | AH1: 53693 | AI1: 54058 | AJ1: 54424 | AK1: 54789
A2: ems_2 | B2: 470.0039 | C2: 472.84455 | D2: 474.86665 | E2: 476.76345 | F2: 478.71635 | G2: 480.69338 | H2: 482.74318 | I2: 484.98073 | J2: 487.42448 | K2: 490.03946 | L2: 492.7645 | M2: 495.52795 | N2: 498.25701 | O2: 500.88369 | P2: 503.3488 | Q2: 505.60459 | R2: 507.69101 | S2: 509.71056 | T2: 511.73272 | U2: 513.80209 | V2: 515.94658 | W2: 518.18322 | X2: 520.52194 | Y2: 522.96796 | Z2: 525.5234 | AA2: 528.18829 | AB2: 530.96133 | AC2: 533.84036 | AD2: 536.82271 | AE2: 539.90547 | AF2: 543.08563 | AG2: 546.36026 | AH2: 549.72658 | AI2: 553.182 | AJ2: 556.72421 | AK2: 560.35114
A3: ems_ch_2 | B3: 129.15358 | C3: 128.77123 | D3: 127.86909 | E3: 126.94185 | F3: 126.12206 | G3: 125.40586 | H3: 124.80024 | I3: 124.3226 | J3: 123.94978 | K3: 123.64788 | L3: 123.38375 | M3: 123.12891 | N3: 122.86043 | O3: 122.56074 | P3: 122.21715 | Q3: 121.82125 | R3: 121.39369 | S3: 120.96838 | T3: 120.55918 | U3: 120.17038 | V3: 119.80185 | W3: 119.45162 | X3: 119.11705 | Y3: 118.79536 | Z3: 118.48386 | AA3: 118.17998 | AB3: 117.88131 | AC3: 117.58553 | AD3: 117.29044 | AE3: 116.99392 | AF3: 116.6939 | AG3: 116.38838 | AH3: 116.07539 | AI3: 115.75301 | AJ3: 115.41938 | AK3: 115.07267
A4: ems_ch_2+ems_ci_2 | B4: 349.86054 | C4: 351.44065 | D4: 352.21014 | E4: 352.81448 | F4: 353.42145 | G4: 354.00057 | H4: 354.60775 | I4: 355.36536 | J4: 356.29689 | K4: 357.37086 | L4: 358.52872 | M4: 359.70094 | N4: 360.81661 | O4: 361.80957 | P4: 362.62248 | Q4: 363.20948 | R4: 363.61303 | S4: 363.9376 | T4: 364.25294 | U4: 364.603 | V4: 365.01464 | W4: 365.5037 | X4: 366.07885 | Y4: 366.74417 | Z4: 367.50077 | AA4: 368.34782 | AB4: 369.28331 | AC4: 370.30447 | AD4: 371.40813 | AE4: 372.59096 | AF4: 373.84955 | AG4: 375.18058 | AH4: 376.58089 | AI4: 378.04747 | AJ4: 379.57754 | AK4: 381.16858
A5: ems_ci_2 | B5: 220.70697 | C5: 222.66941 | D5: 224.34104 | E5: 225.87263 | F5: 227.29938 | G5: 228.59471 | H5: 229.8075 | I5: 231.04277 | J5: 232.34711 | K5: 233.72298 | L5: 235.14497 | M5: 236.57203 | N5: 237.95619 | O5: 239.24883 | P5: 240.40533 | Q5: 241.38823 | R5: 242.21934 | S5: 242.96922 | T5: 243.69376 | U5: 244.43262 | V5: 245.21279 | W5: 246.05208 | X5: 246.9618 | Y5: 247.94881 | Z5: 249.01691 | AA5: 250.16784 | AB5: 251.402 | AC5: 252.71894 | AD5: 254.11769 | AE5: 255.59704 | AF5: 257.15564 | AG5: 258.7922 | AH5: 260.5055 | AI5: 262.29446 | AJ5: 264.15817 | AK5: 266.09591
A6: ems_mat_2 | B6: 27.950294 | C6: 28.262141 | D6: 28.572697 | E6: 28.886185 | F6: 29.20448 | G6: 29.527886 | H6: 29.856269 | I6: 30.189684 | J6: 30.528205 | K6: 30.87176 | L6: 31.220109 | M6: 31.572874 | N6: 31.929569 | O6: 32.289639 | P6: 32.652487 | Q6: 33.017498 | R6: 33.384339 | S6: 33.753157 | T6: 34.124371 | U6: 34.498465 | V6: 34.875907 | W6: 35.257118 | X6: 35.642459 | Y6: 36.032235 | Z6: 36.426699 | AA6: 36.826056 | AB6: 37.230474 | AC6: 37.64009 | AD6: 38.055018 | AE6: 38.475351 | AF6: 38.901175 | AG6: 39.332563 | AH6: 39.769589 | AI6: 40.212322 | AJ6: 40.660834 | AK6: 41.115199
A7: ems_y_2 | B7: 92.193058 | C7: 93.141768 | D7: 94.083816 | E7: 95.062789 | F7: 96.090427 | G7: 97.164925 | H7: 98.279169 | I7: 99.42568 | J7: 100.59938 | K7: 101.79684 | L7: 103.01567 | M7: 104.25414 | N7: 105.51083 | O7: 106.78448 | P7: 108.07383 | Q7: 109.37761 | R7: 110.69364 | S7: 112.0198 | T7: 113.35541 | U7: 114.70063 | V7: 116.05603 | W7: 117.42241 | X7: 118.80063 | Y7: 120.19155 | Z7: 121.59593 | AA7: 123.01441 | AB7: 124.44755 | AC7: 125.89581 | AD7: 127.35956 | AE7: 128.83916 | AF7: 130.33491 | AG7: 131.84712 | AH7: 133.3761 | AI7: 134.92221 | AJ7: 136.48583 | AK7: 138.06737
A8: ems_sec_2 | B8: 340.85032 | C8: 344.07332 | D8: 346.99756 | E8: 349.82161 | F8: 352.59429 | G8: 355.28752 | H8: 357.94294 | I8: 360.65813 | J8: 363.4747 | K8: 366.39158 | L8: 369.38075 | M8: 372.39904 | N8: 375.39658 | O8: 378.32295 | P8: 381.13165 | Q8: 383.78334 | R8: 386.29732 | S8: 388.74218 | T8: 391.17354 | U8: 393.63171 | V8: 396.14473 | W8: 398.7316 | X8: 401.40489 | Y8: 404.1726 | Z8: 407.03953 | AA8: 410.0083 | AB8: 413.08002 | AC8: 416.25483 | AD8: 419.53227 | AE8: 422.91155 | AF8: 426.39173 | AG8: 429.97188 | AH8: 433.65119 | AI8: 437.42899 | AJ8: 441.30483 | AK8: 445.27848
A9: ems_ets_2 | B9: 126.91621 | C9: 128.03846 | D9: 128.98332 | E9: 129.84441 | F9: 130.64798 | G9: 131.38233 | H9: 132.06974 | I9: 132.76334 | J9: 133.49 | K9: 134.25326 | L9: 135.04078 | M9: 135.83083 | N9: 136.59722 | O9: 137.31303 | P9: 137.95325 | Q9: 138.49677 | R9: 138.95324 | S9: 139.35951 | T9: 139.74708 | U9: 140.13913 | V9: 140.55168 | W9: 140.99532 | X9: 141.47684 | Y9: 142.00033 | Z9: 142.56814 | AA9: 143.18142 | AB9: 143.84058 | AC9: 144.54557 | AD9: 145.29605 | AE9: 146.09156 | AF9: 146.93157 | AG9: 147.81555 | AH9: 148.74302 | AI9: 149.71356 | AJ9: 150.72684 | AK9: 151.78258
A10: ems_nets_2 | B10: 213.93412 | C10: 216.03486 | D10: 218.01424 | E10: 219.9772 | F10: 221.94631 | G10: 223.90519 | H10: 225.8732 | I10: 227.89479 | J10: 229.98469 | K10: 232.13831 | L10: 234.33997 | M10: 236.56822 | N10: 238.79936 | O10: 241.00992 | P10: 243.1784 | Q10: 245.28657 | R10: 247.34408 | S10: 249.38267 | T10: 251.42646 | U10: 253.49258 | V10: 255.59305 | W10: 257.73627 | X10: 259.92805 | Y10: 262.17227 | Z10: 264.4714 | AA10: 266.82689 | AB10: 269.23944 | AC10: 271.70927 | AD10: 274.23622 | AE10: 276.81998 | AF10: 279.46016 | AG10: 282.15633 | AH10: 284.90817 | AI10: 287.71543 | AJ10: 290.57799 | AK10: 293.4959
A11: ems_netsi_2 | B11: 25.647636 | C11: 25.89121 | D11: 26.113028 | E11: 26.325392 | F11: 26.530869 | G11: 26.727193 | H11: 26.919789 | I11: 27.118545 | J11: 27.327026 | K11: 27.544727 | L11: 27.768832 | M11: 27.99533 | N11: 28.219731 | O11: 28.437561 | P11: 28.644697 | Q11: 28.837619 | R11: 29.018366 | S11: 29.193381 | T11: 29.367467 | U11: 29.543946 | V11: 29.725095 | W11: 29.91247 | X11: 30.107118 | Y11: 30.309723 | Z11: 30.520709 | AA11: 30.740309 | AB11: 30.968619 | AC11: 31.205641 | AD11: 31.451312 | AE11: 31.705531 | AF11: 31.968175 | AG11: 32.239114 | AH11: 32.518221 | AI11: 32.805381 | AJ11: 33.100493 | AK11: 33.403478
A12: ems_trsp_2-ems_sair_2 | B12: 24.99273 | C12: 25.238917 | D12: 25.466326 | E12: 25.68735 | F12: 25.905589 | G12: 26.119952 | H12: 26.33202 | I12: 26.546369 | J12: 26.765242 | K12: 26.988745 | L12: 27.215497 | M12: 27.44316 | N12: 27.668836 | O12: 27.88936 | P12: 28.101522 | Q12: 28.302243 | R12: 28.491883 | S12: 28.674181 | T12: 28.852426 | U12: 29.029165 | V12: 29.206324 | W12: 29.385348 | X12: 29.56732 | Y12: 29.753053 | Z12: 29.943151 | AA12: 30.138068 | AB12: 30.338143 | AC12: 30.543633 | AD12: 30.754736 | AE12: 30.971609 | AF12: 31.194381 | AG12: 31.42316 | AH12: 31.658047 | AI12: 31.899135 | AJ12: 32.146516 | AK12: 32.400284
... A819: ems_ch_cbio_0+ems_ci_cbio_0 | B819: 31.971027 | C819: 32.007879 | D819: 31.913715 | E819: 31.777071 | F819: 31.634471 | G819: 31.499044 | H819: 31.374108 | I819: 31.259284 | J819: 31.153102 | K819: 31.054017 | L819: 30.96074 | M819: 30.872295 | N819: 30.787979 | O819: 30.707301 | P819: 30.629922 | Q819: 30.555608 | R819: 30.484203 | S819: 30.415596 | T819: 30.349705 | U819: 30.286408 | V819: 30.225638 | W819: 30.167359 | X819: 30.111552 | Y819: 30.058202 | Z819: 30.007304 | AA819: 29.958849 | AB819: 29.912833 | AC819: 29.869249 | AD819: 29.828093 | AE819: 29.789358 | AF819: 29.75304 | AG819: 29.719132 | AH819: 29.68763 | AI819: 29.658527 | AJ819: 29.63182 | AK819: 29.607503

Sheet Consumption
A1: _date_ | B1: 42005 | C1: 42370 | D1: 42736 | E1: 43101 | F1: 43466 | G1: 43831 | H1: 44197 | I1: 44562 | J1: 44927 | K1: 45292 | L1: 45658 | M1: 46023 | N1: 46388 | O1: 46753 | P1: 47119 | Q1: 47484 | R1: 47849 | S1: 48214 | T1: 48580 | U1: 48945 | V1: 49310 | W1: 49675 | X1: 50041 | Y1: 50406 | Z1: 50771 | AA1: 51136 | AB1: 51502 | AC1: 51867 | AD1: 52232 | AE1: 52597 | AF1: 52963 | AG1: 53328 | AH1: 53693 | AI1: 54058 | AJ1: 54424 | AK1: 54789
A2: ch_2 | B2: 1202071.8 | C2: 1215689.3 | D2: 1229305.1 | E2: 1242997.6 | F2: 1256839.9 | G2: 1270927.5 | H2: 1285337.6 | I2: 1300100 | J2: 1315211 | K2: 1330655.9 | L2: 1346423.6 | M2: 1362510.2 | N2: 1378918.7 | O2: 1395656.2 | P2: 1412732.6 | Q2: 1430158.4 | R2: 1447931.2 | S2: 1466027.1 | T2: 1484413 | U2: 1503059 | V2: 1521943.6 | W2: 1541053.6 | X2: 1560381.5 | Y2: 1579922.5 | Z2: 1599673.1 | AA2: 1619629.3 | AB2: 1639786.4 | AC2: 1660138.8 | AD2: 1680680.3 | AE2: 1701404.5 | AF2: 1722305.2 | AG2: 1743376.7 | AH2: 1764614.2 | AI2: 1786014.2 | AJ2: 1807574.5 | AK2: 1829294.5
A3: ch_0 | B3: 1202071.8 | C3: 1215641.6 | D3: 1229141.5 | E3: 1242648.3 | F3: 1256238.1 | G3: 1270001.2 | H3: 1284016.1 | I3: 1298333 | J3: 1312973.1 | K3: 1327935.9 | L3: 1343208.5 | M3: 1358772.9 | N3: 1374610.8 | O3: 1390705.9 | P3: 1407045.5 | Q3: 1423620.3 | R3: 1440423.8 | S3: 1457451.5 | T3: 1474700.5 | U3: 1492169 | V3: 1509855.2 | W3: 1527757.7 | X3: 1545875.1 | Y3: 1564206 | Z3: 1582749 | AA3: 1601502.9 | AB3: 1620466.6 | AC3: 1639639.4 | AD3: 1659020.8 | AE3: 1678610.9 | AF3: 1698410.1 | AG3: 1718419.4 | AH3: 1738640.1 | AI3: 1759074.1 | AJ3: 1779723.6 | AK3: 1800591.2
A4: pch_2 | B4: 1 | C4: 1.0202551 | D4: 1.0408151 | E4: 1.0617736 | F4: 1.0832399 | G4: 1.1053213 | H4: 1.1279684 | I4: 1.1511122 | J4: 1.1748104 | K4: 1.1991128 | L4: 1.2240667 | M4: 1.2497206 | N4: 1.2761268 | O4: 1.3033421 | P4: 1.3314278 | Q4: 1.3604493 | R4: 1.3903664 | S4: 1.4211088 | T4: 1.4526864 | U4: 1.4851 | V4: 1.5183438 | W4: 1.5524079 | X4: 1.5872802 | Y4: 1.6229477 | Z4: 1.6593976 | AA4: 1.6966171 | AB4: 1.7345944 | AC4: 1.7733182 | AD4: 1.8127784 | AE4: 1.8529658 | AF4: 1.8938724 | AG4: 1.9354915 | AH4: 1.9778174 | AI4: 2.0208462 | AJ4: 2.0645753 | AK4: 2.1090035
A5: pch_0 | B5: 1 | C5: 1.0198987 | D5: 1.0400695 | E5: 1.0605437 | F5: 1.0813678 | G5: 1.1025858 | H5: 1.1242353 | I5: 1.146347 | J5: 1.1689465 | K5: 1.1920554 | L5: 1.2156926 | M5: 1.2398742 | N5: 1.2646147 | O5: 1.2899264 | P5: 1.3158205 | Q5: 1.3423069 | R5: 1.3693946 | S5: 1.397092 | T5: 1.4254069 | U5: 1.454347 | V5: 1.4839199 | W5: 1.5141329 | X5: 1.5449937 | Y5: 1.5765098 | Z5: 1.6086892 | AA5: 1.64154 | AB5: 1.6750706 | AC5: 1.7092899 | AD5: 1.744207 | AE5: 1.7798315 | AF5: 1.8161737 | AG5: 1.8532442 | AH5: 1.891054 | AI5: 1.9296152 | AJ5: 1.9689399 | AK5: 2.0090411
A6: ch_cagr_2 | B6: 31638 | C6: 31926.255 | D6: 32212.966 | E6: 32522.845 | F6: 32861.418 | G6: 33227.204 | H6: 33615.841 | I6: 34022.762 | J6: 34445.002 | K6: 34880.533 | L6: 35327.987 | M6: 35786.465 | N6: 36255.406 | O6: 36734.483 | P6: 37223.523 | Q6: 37722.457 | R6: 38230.465 | S6: 38746.447 | T6: 39270.053 | U6: 39801.143 | V6: 40339.637 | W6: 40885.459 | X6: 41438.52 | Y6: 41998.697 | Z6: 42565.832 | AA6: 43139.734 | AB6: 43720.18 | AC6: 44306.929 | AD6: 44899.731 | AE6: 45498.339 | AF6: 46102.521 | AG6: 46712.069 | AH6: 47326.813 | AI6: 47946.622 | AJ6: 48571.409 | AK6: 49201.14
A7: ch_cagr_0 | B7: 31638 | C7: 31923.619 | D7: 32206.85 | E7: 32512.452 | F7: 32845.535 | G7: 33204.073 | H7: 33584.186 | I7: 33982.118 | J7: 34394.806 | K7: 34819.912 | L7: 35255.709 | M7: 35700.938 | N7: 36154.696 | O7: 36616.348 | P7: 37085.459 | Q7: 37561.74 | R7: 38045 | S7: 38535.116 | T7: 39032.007 | U7: 39535.611 | V7: 40045.87 | W7: 40562.729 | X7: 41086.13 | Y7: 41616.009 | Z7: 42152.303 | AA7: 42694.952 | AB7: 43243.898 | AC7: 43799.093 | AD7: 44360.5 | AE7: 44928.092 | AF7: 45501.861 | AG7: 46081.809 | AH7: 46667.955 | AI7: 47260.332 | AJ7: 47858.988 | AK7: 48463.982
A8: pch_cagr_2 | B8: 1 | C8: 1.0200609 | D8: 1.0405244 | E8: 1.0614215 | F8: 1.0828179 | G8: 1.1047918 | H8: 1.1273577 | I8: 1.1504798 | J8: 1.1741521 | K8: 1.1983903 | L8: 1.2232263 | M8: 1.2487049 | N8: 1.2748798 | O8: 1.3018117 | P8: 1.3295662 | Q8: 1.3582127 | R8: 1.3877667 | S8: 1.4181919 | T8: 1.4494613 | U8: 1.481554 | V8: 1.5144543 | W8: 1.5481499 | X8: 1.5826312 | Y8: 1.6178902 | Z8: 1.6539203 | AA8: 1.6907155 | AB8: 1.7282702 | AC8: 1.7665796 | AD8: 1.805639 | AE8: 1.8454446 | AF8: 1.8859932 | AG8: 1.9272826 | AH8: 1.9693114 | AI8: 2.0120793 | AJ8: 2.0555874 | AK8: 2.0998377
A9: pch_cagr_0 | B9: 1 | C9: 1.0199097 | D9: 1.0401102 | E9: 1.0606346 | F9: 1.0815269 | G9: 1.1028261 | H9: 1.1245631 | I9: 1.1467626 | J9: 1.1694451 | K9: 1.1926287 | L9: 1.2163293 | M9: 1.2405618 | N9: 1.2653394 | O9: 1.2906742 | P9: 1.3165769 | Q9: 1.3430574 | R9: 1.3701249 | S9: 1.3977879 | T9: 1.4260546 | U9: 1.454933 | V9: 1.484431 | W9: 1.5145566 | X9: 1.545318 | Y9: 1.5767236 | Z9: 1.6087819 | AA9: 1.6415018 | AB9: 1.6748927 | AC9: 1.7089641 | AD9: 1.743726 | AE9: 1.7791888 | AF9: 1.8153635 | AG9: 1.8522615 | AH9: 1.8898946 | AI9: 1.9282753 | AJ9: 1.9674164 | AK9: 2.0073314
A10: ch_cfoo_2 | B10: 175065 | C10: 176665.76 | D10: 178263.1 | E10: 179992.14 | F10: 181882.67 | G10: 183926.86 | H10: 186099.48 | I10: 188372.56 | J10: 190727.99 | K10: 193154.33 | L10: 195644.8 | M10: 198195.81 | N10: 200805.87 | O10: 203474.71 | P10: 206202.79 | Q10: 208990.92 | R10: 211833.87 | S10: 214722.96 | T10: 217653.83 | U10: 220624.16 | V10: 223632.7 | W10: 226678.84 | X10: 229762.22 | Y10: 232882.49 | Z10: 236039.19 | AA10: 239231.64 | AB10: 242458.98 | AC10: 245720.21 | AD10: 249014.2 | AE10: 252339.81 | AF10: 255695.95 | AG10: 259081.63 | AH10: 262496.03 | AI10: 265938.53 | AJ10: 269408.74 | AK10: 272906.54
A11: ch_cfoo_0 | B11: 175065 | C11: 176646.38 | D11: 178215.6 | E11: 179909.34 | F11: 181755.53 | G11: 183742.79 | H11: 185849.61 | I11: 188055.15 | J11: 190342.38 | K11: 192698.21 | L11: 195112.91 | M11: 197579.31 | N11: 200092.24 | O11: 202648.04 | P11: 205244.23 | Q11: 207879.16 | R11: 210551.78 | S11: 213261.44 | T11: 216007.75 | U11: 218790.43 | V11: 221609.24 | W11: 224463.97 | X11: 227354.36 | Y11: 230280.16 | Z11: 233241.08 | AA11: 236236.84 | AB11: 239267.21 | AC11: 242331.96 | AD11: 245430.95 | AE11: 248564.07 | AF11: 251731.31 | AG11: 254932.73 | AH11: 258168.46 | AI11: 261438.72 | AJ11: 264743.79 | AK11: 268084.01
A12: pch_cfoo_2 | B12: 1 | C12: 1.0199635 | D12: 1.0402796 | E12: 1.0610001 | F12: 1.0821902 | G12: 1.1039157 | H12: 1.1262121 | I12: 1.1490838 | J12: 1.172536 | K12: 1.1965784 | L12: 1.2212286 | M12: 1.2465134 | N12: 1.2724678 | O12: 1.2991348 | P12: 1.3265636 | Q12: 1.3548092 | R12: 1.3839059 | S12: 1.4138598 | T12: 1.4446681 | U12: 1.4763228 | V12: 1.5088127 | W12: 1.542126 | X12: 1.5762509 | Y12: 1.6111762 | Z12: 1.6468915 | AA12: 1.6833871 | AB12: 1.7206539 | AC12: 1.7586839 | AD12: 1.7974697 | AE12: 1.8370048 | AF12: 1.8772839 | AG12: 1.9183026 | AH12: 1.9600579 | AI12: 2.0025481 | AJ12: 2.0457728 | AK12: 2.089733
... A105: pch_cbio_0 | B105: 1 | C105: 1.0194853 | D105: 1.0388851 | E105: 1.0584794 | F105: 1.0785234 | G105: 1.0991574 | H105: 1.1204202 | I105: 1.1422939 | J105: 1.1647423 | K105: 1.1877351 | L105: 1.2112565 | M105: 1.2353062 | N105: 1.2598952 | O105: 1.2850411 | P105: 1.3107638 | Q105: 1.337083 | R105: 1.3640167 | S105: 1.3915798 | T105: 1.4197853 | U105: 1.4486433 | V105: 1.4781629 | W105: 1.5083515 | X105: 1.5392164 | Y105: 1.5707642 | Z105: 1.6030015 | AA105: 1.635935 | AB105: 1.6695716 | AC105: 1.7039186 | AD105: 1.7389836 | AE105: 1.7747749 | AF105: 1.811301 | AG105: 1.8485712 | AH105: 1.8865955 | AI105: 1.9253844 | AJ105: 1.964949 | AK105: 2.0053012

Sheet Value_Added
A1: _date_ | B1: 42005 | C1: 42370 | D1: 42736 | E1: 43101 | F1: 43466 | G1: 43831 | H1: 44197 | I1: 44562 | J1: 44927 | K1: 45292 | L1: 45658 | M1: 46023 | N1: 46388 | O1: 46753 | P1: 47119 | Q1: 47484 | R1: 47849 | S1: 48214 | T1: 48580 | U1: 48945 | V1: 49310 | W1: 49675 | X1: 50041 | Y1: 50406 | Z1: 50771 | AA1: 51136 | AB1: 51502 | AC1: 51867 | AD1: 52232 | AE1: 52597 | AF1: 52963 | AG1: 53328 | AH1: 53693 | AI1: 54058 | AJ1: 54424 | AK1: 54789
A2: va_2 | B2: 1965592.2 | C2: 1986967.1 | D2: 2008406.1 | E2: 2030322.4 | F2: 2052845.9 | G2: 2076000.7 | H2: 2099741.3 | I2: 2123989.1 | J2: 2148684.2 | K2: 2173787.1 | L2: 2199276.1 | M2: 2225143.3 | N2: 2251388.9 | O2: 2278016.7 | P2: 2305030.9 | Q2: 2332434.1 | R2: 2360203.5 | S2: 2388297.5 | T2: 2416686.2 | U2: 2445351.5 | V2: 2474286 | W2: 2503490.7 | X2: 2532972.1 | Y2: 2562739.2 | Z2: 2592802 | AA2: 2623170.1 | AB2: 2653852.3 | AC2: 2684856.1 | AD2: 2716188.2 | AE2: 2747854.3 | AF2: 2779859.8 | AG2: 2812209.7 | AH2: 2844909.2 | AI2: 2877963.8 | AJ2: 2911379.5 | AK2: 2945162.6
A3: va_0 | B3: 1965592.2 | C3: 1986885.6 | D3: 2008191.4 | E3: 2029937.4 | F3: 2052257.8 | G3: 2075171.5 | H3: 2098653.7 | I3: 2122664 | J3: 2147158.9 | K3: 2172097.9 | L3: 2197445.8 | M3: 2223174.1 | N3: 2249260.8 | O3: 2275690.3 | P3: 2302452.2 | Q3: 2329540.4 | R3: 2356952 | S3: 2384686.5 | T3: 2412744.9 | U3: 2441129.2 | V3: 2469841.7 | W3: 2498885 | X3: 2528261.8 | Y3: 2557974.8 | Z3: 2588026.6 | AA3: 2618419.7 | AB3: 2649156.8 | AC3: 2680240.9 | AD3: 2711674.8 | AE3: 2743461.8 | AF3: 2775605.2 | AG3: 2808108.9 | AH3: 2840976.6 | AI3: 2874212.5 | AJ3: 2907821.1 | AK3: 2941806.7
A4: va_sagr_2 | B4: 30790.815 | C4: 31102.036 | D4: 31418.676 | E4: 31753.153 | F4: 32107.39 | G4: 32480.339 | H4: 32868.699 | I4: 33268.522 | J4: 33677.54 | K4: 34094.574 | L4: 34519.146 | M4: 34951.198 | N4: 35390.901 | O4: 35838.51 | P4: 36294.272 | Q4: 36758.36 | R4: 37229.697 | S4: 37706.468 | T4: 38187.665 | U4: 38672.753 | V4: 39161.5 | W4: 39653.871 | X4: 40149.946 | Y4: 40649.858 | Z4: 41153.766 | AA4: 41661.827 | AB4: 42174.188 | AC4: 42690.985 | AD4: 43212.343 | AE4: 43738.38 | AF4: 44269.21 | AG4: 44804.952 | AH4: 45345.729 | AI4: 45891.676 | AJ4: 46442.94 | AK4: 46999.679
A5: va_sagr_0 | B5: 30790.815 | C5: 31097.824 | D5: 31408.103 | E5: 31734.666 | F5: 32079.262 | G5: 32440.277 | H5: 32815.402 | I5: 33202.492 | J5: 33599.776 | K5: 34005.861 | L5: 34419.667 | M5: 34840.376 | N5: 35267.383 | O5: 35700.251 | P5: 36138.684 | Q5: 36582.491 | R5: 37031.564 | S5: 37485.852 | T5: 37945.343 | U5: 38410.05 | V5: 38880 | W5: 39355.225 | X5: 39835.764 | Y5: 40321.654 | Z5: 40812.934 | AA5: 41309.645 | AB5: 41811.83 | AC5: 42319.535 | AD5: 42832.812 | AE5: 43351.717 | AF5: 43876.312 | AG5: 44406.665 | AH5: 44942.85 | AI5: 45484.945 | AJ5: 46033.034 | AK5: 46587.204
A6: va_sfor_2 | B6: 5288.8126 | C6: 5297.7707 | D6: 5287.5755 | E6: 5270.8214 | F6: 5251.7328 | G6: 5231.1034 | H6: 5210.8971 | I6: 5193.3711 | J6: 5178.5243 | K6: 5165.5827 | L6: 5153.5858 | M6: 5141.6185 | N6: 5128.8967 | O6: 5114.7963 | P6: 5098.8603 | Q6: 5080.7971 | R6: 5061.6587 | S6: 5043.0698 | T6: 5025.6819 | U6: 5009.7296 | V6: 4995.2696 | W6: 4982.2874 | X6: 4970.7427 | Y6: 4960.5884 | Z6: 4951.7779 | AA6: 4944.2674 | AB6: 4938.017 | AC6: 4932.9902 | AD6: 4929.1537 | AE6: 4926.4778 | AF6: 4924.9353 | AG6: 4924.5021 | AH6: 4925.1562 | AI6: 4926.878 | AJ6: 4929.6501 | AK6: 4933.4567
A7: va_sfor_0 | B7: 5288.8126 | C7: 5304.0347 | D7: 5302.0192 | E7: 5294.5751 | F7: 5286.4854 | G7: 5279.4506 | H7: 5273.8914 | I7: 5269.7509 | J7: 5266.835 | K7: 5264.9431 | L7: 5263.9093 | M7: 5263.6084 | N7: 5263.9504 | O7: 5264.872 | P7: 5266.329 | Q7: 5268.2912 | R7: 5270.738 | S7: 5273.6553 | T7: 5277.0329 | U7: 5280.8561 | V7: 5285.1182 | W7: 5289.8172 | X7: 5294.9534 | Y7: 5300.5286 | Z7: 5306.5452 | AA7: 5313.0062 | AB7: 5319.9145 | AC7: 5327.2731 | AD7: 5335.0852 | AE7: 5343.3539 | AF7: 5352.0818 | AG7: 5361.2718 | AH7: 5370.9267 | AI7: 5381.049 | AJ7: 5391.6415 | AK7: 5402.7065
A8: va_sfoo_2 | B8: 43654.88 | C8: 44079.824 | D8: 44521.242 | E8: 44992.203 | F8: 45492.252 | G8: 46018.704 | H8: 46566.766 | I8: 47131.347 | J8: 47709.724 | K8: 48300.377 | L8: 48902.576 | M8: 49516.11 | N8: 50141.056 | O8: 50777.632 | P8: 51426.084 | Q8: 52086.614 | R8: 52757.754 | S8: 53437.193 | T8: 54123.817 | U8: 54816.998 | V8: 55516.44 | W8: 56222.071 | X8: 56933.954 | Y8: 57652.216 | Z8: 58377.007 | AA8: 59108.468 | AB8: 59846.722 | AC8: 60591.876 | AD8: 61344.015 | AE8: 62103.217 | AF8: 62869.561 | AG8: 63643.128 | AH8: 64424.017 | AI8: 65212.347 | AJ8: 66008.257 | AK8: 66811.914
A9: va_sfoo_0 | B9: 43654.88 | C9: 44074.319 | D9: 44508.113 | E9: 44969.764 | F9: 45458.475 | G9: 45970.837 | H9: 46503.401 | I9: 47053.24 | J9: 47617.99 | K9: 48195.765 | L9: 48785.077 | M9: 49384.768 | N9: 49993.956 | O9: 50611.993 | P9: 51238.424 | Q9: 51872.946 | R9: 52515.37 | S9: 53165.593 | T9: 53823.57 | U9: 54489.29 | V9: 55162.761 | W9: 55844.004 | X9: 56533.043 | Y9: 57229.907 | Z9: 57934.625 | AA9: 58647.231 | AB9: 59367.763 | AC9: 60096.266 | AD9: 60832.792 | AE9: 61577.404 | AF9: 62330.173 | AG9: 63091.181 | AH9: 63860.521 | AI9: 64638.292 | AJ9: 65424.606 | AK9: 66219.579
A10: va_sveh_2 | B10: 29847.895 | C10: 30404.705 | D10: 30932.64 | E10: 31408.754 | F10: 31841.632 | G10: 32244.379 | H10: 32630.584 | I10: 33010.088 | J10: 33386.587 | K10: 33761.671 | L10: 34136.059 | M10: 34510.043 | N10: 34883.691 | O10: 35256.944 | P10: 35629.658 | Q10: 36001.627 | R10: 36374.675 | S10: 36750.755 | T10: 37129.447 | U10: 37510.229 | V10: 37892.826 | W10: 38277.187 | X10: 38663.408 | Y10: 39051.677 | Z10: 39442.225 | AA10: 39835.305 | AB10: 40231.177 | AC10: 40630.099 | AD10: 41032.322 | AE10: 41438.093 | AF10: 41847.649 | AG10: 42261.223 | AH10: 42679.039 | AI10: 43101.312 | AJ10: 43528.248 | AK10: 43960.042
A11: va_sveh_0 | B11: 29847.895 | C11: 30410.564 | D11: 30943.516 | E11: 31424.184 | F11: 31862.492 | G11: 32272.71 | H11: 32666.675 | I11: 33052.509 | J11: 33435.21 | K11: 33817.628 | L11: 34201.287 | M11: 34586.961 | N11: 34975.033 | O11: 35365.692 | P11: 35759.05 | Q11: 36155.19 | R11: 36554.191 | S11: 36956.134 | T11: 37361.107 | U11: 37769.204 | V11: 38180.52 | W11: 38595.157 | X11: 39013.219 | Y11: 39434.812 | Z11: 39860.048 | AA11: 40289.04 | AB11: 40721.904 | AC11: 41158.757 | AD11: 41599.719 | AE11: 42044.908 | AF11: 42494.445 | AG11: 42948.446 | AH11: 43407.029 | AI11: 43870.308 | AJ11: 44338.393 | AK11: 44811.394
A12: va_sgla_2 | B12: 7902.1978 | C12: 7989.9612 | D12: 8077.8948 | E12: 8167.2693 | F12: 8258.725 | G12: 8352.5211 | H12: 8448.3884 | I12: 8545.8653 | J12: 8644.7552 | K12: 8745.006 | L12: 8846.6209 | M12: 8949.6088 | N12: 9053.9557 | O12: 9159.6058 | P12: 9266.4498 | Q12: 9374.3171 | R12: 9482.8874 | S12: 9591.8568 | T12: 9701.125 | U12: 9810.7156 | V12: 9920.7173 | W12: 10031.249 | X12: 10142.441 | Y12: 10254.419 | Z12: 10367.301 | AA12: 10481.197 | AB12: 10596.201 | AC12: 10712.396 | AD12: 10829.858 | AE12: 10948.651 | AF12: 11068.833 | AG12: 11190.456 | AH12: 11313.567 | AI12: 11438.211 | AJ12: 11564.43 | AK12: 11692.265
... A79: va_ser_0 | B79: 1510944.6 | C79: 1527318.9 | D79: 1543784 | E79: 1560667.8 | F79: 1578055.3 | G79: 1595942.4 | H79: 1614295.5 | I79: 1633073.9 | J79: 1652238.4 | K79: 1671754.4 | L79: 1691592.8 | M79: 1711730.4 | N79: 1732149.6 | O79: 1752837.7 | P79: 1773786.4 | Q79: 1794990.5 | R79: 1816447.6 | S79: 1838157 | T79: 1860119.3 | U79: 1882335.7 | V79: 1904807.8 | W79: 1927537.5 | X79: 1950526.5 | Y79: 1973776.7 | Z79: 1997289.9 | AA79: 2021067.8 | AB79: 2045112.5 | AC79: 2069426 | AD79: 2094010.5 | AE79: 2118868.4 | AF79: 2144002.3 | AG79: 2169415.2 | AH79: 2195110 | AI79: 2221090 | AJ79: 2247358.8 | AK79: 2273919.9

Sheet INV
A1: _date_ | B1: 42005 | C1: 42370 | D1: 42736 | E1: 43101 | F1: 43466 | G1: 43831 | H1: 44197 | I1: 44562 | J1: 44927 | K1: 45292 | L1: 45658 | M1: 46023 | N1: 46388 | O1: 46753 | P1: 47119 | Q1: 47484 | R1: 47849 | S1: 48214 | T1: 48580 | U1: 48945 | V1: 49310 | W1: 49675 | X1: 50041 | Y1: 50406 | Z1: 50771 | AA1: 51136 | AB1: 51502 | AC1: 51867 | AD1: 52232 | AE1: 52597 | AF1: 52963 | AG1: 53328 | AH1: 53693 | AI1: 54058 | AJ1: 54424 | AK1: 54789
A2: ia_2 | B2: 472647 | C2: 478019.84 | D2: 483384.95 | E2: 488770.16 | F2: 494200.87 | G2: 499693.83 | H2: 505266.91 | I2: 510935.93 | J2: 516704.85 | K2: 522571.3 | L2: 528530.6 | M2: 534577.78 | N2: 540708.26 | O2: 546917.91 | P2: 553202.83 | Q2: 559559.24 | R2: 565989.16 | S2: 572498.32 | T2: 579088.85 | U2: 585761.47 | V2: 592516.96 | W2: 599356.73 | X2: 606282.74 | Y2: 613297.16 | Z2: 620402.01 | AA2: 627598.93 | AB2: 634888.99 | AC2: 642272.74 | AD2: 649750.16 | AE2: 657320.81 | AF2: 664983.92 | AG2: 672738.51 | AH2: 680583.52 | AI2: 688517.85 | AJ2: 696540.51 | AK2: 704650.62
A3: ia_0 | B3: 472647 | C3: 478041.55 | D3: 483438.29 | E3: 488861.72 | F3: 494339.57 | G3: 499893.34 | H3: 505536.92 | I3: 511277.46 | J3: 517117.16 | K3: 523055.07 | L3: 529088.68 | M3: 535215.11 | N3: 541431.74 | O3: 547736.65 | P3: 554128.65 | Q3: 560607.27 | R3: 567172.56 | S3: 573824.98 | T3: 580565.17 | U3: 587393.88 | V3: 594311.81 | W3: 601319.58 | X3: 608417.66 | Y3: 615606.41 | Z3: 622886.05 | AA3: 630256.67 | AB3: 637718.3 | AC3: 645270.89 | AD3: 652914.38 | AE3: 660648.67 | AF3: 668473.69 | AG3: 676389.4 | AH3: 684395.78 | AI3: 692492.88 | AJ3: 700680.78 | AK3: 708959.66
A4: ia_sagr_2 | B4: 4271.7493 | C4: 4316.7136 | D4: 4359.9908 | E4: 4403.7754 | F4: 4449.1778 | G4: 4496.4743 | H4: 4545.6026 | I4: 4596.4085 | J4: 4648.695 | K4: 4702.285 | L4: 4757.0282 | M4: 4812.7919 | N4: 4869.4529 | O4: 4926.89 | P4: 4984.9822 | Q4: 5043.6077 | R4: 5102.6906 | S4: 5162.2033 | T4: 5222.1361 | U4: 5282.5049 | V4: 5343.3436 | W4: 5404.6952 | X4: 5466.605 | Y4: 5529.1158 | Z4: 5592.265 | AA4: 5656.0839 | AB4: 5720.5971 | AC4: 5785.8235 | AD4: 5851.7777 | AE4: 5918.471 | AF4: 5985.9128 | AG4: 6054.1122 | AH4: 6123.0785 | AI4: 6192.8225 | AJ4: 6263.3571 | AK4: 6334.6973
A5: ia_sagr_0 | B5: 4271.7493 | C5: 4316.9191 | D5: 4360.566 | E5: 4404.9143 | F5: 4451.1227 | G5: 4499.5274 | H5: 4550.0535 | I5: 4602.4822 | J5: 4656.5777 | K5: 4712.1351 | L5: 4768.9904 | M5: 4827.0178 | N5: 4886.1226 | O5: 4946.2347 | P5: 5007.3037 | Q5: 5069.2935 | R5: 5132.1794 | S5: 5195.9442 | T5: 5260.5762 | U5: 5326.0669 | V5: 5392.4095 | W5: 5459.5978 | X5: 5527.6258 | Y5: 5596.4876 | Z5: 5666.1769 | AA5: 5736.6876 | AB5: 5808.0139 | AC5: 5880.1505 | AD5: 5953.0927 | AE5: 6026.8372 | AF5: 6101.3814 | AG5: 6176.7244 | AH5: 6252.8665 | AI5: 6329.8095 | AJ5: 6407.5565 | AK5: 6486.112
A6: ia_sfor_2 | B6: 166.90527 | C6: 167.66628 | D6: 167.5541 | E6: 166.93956 | F6: 166.03783 | G6: 164.93531 | H6: 163.7149 | I6: 162.47153 | J6: 161.24632 | K6: 160.04201 | L6: 158.84202 | M6: 157.62256 | N6: 156.35899 | O6: 155.02907 | P6: 153.61466 | Q6: 152.10254 | R6: 150.51651 | S6: 148.90872 | T6: 147.31679 | U6: 145.76351 | V6: 144.2622 | W6: 142.82071 | X6: 141.4439 | Y6: 140.13488 | Z6: 138.89569 | AA6: 137.72759 | AB6: 136.63135 | AC6: 135.60732 | AD6: 134.65553 | AE6: 133.77576 | AF6: 132.96762 | AG6: 132.23053 | AH6: 131.56383 | AI6: 130.96673 | AJ6: 130.4384 | AK6: 129.97792
A7: ia_sfor_0 | B7: 166.90527 | C7: 167.83885 | D7: 168.02018 | E7: 167.78375 | F7: 167.34781 | G7: 166.825 | H7: 166.26615 | I7: 165.69193 | J7: 165.1102 | K7: 164.52429 | L7: 163.93643 | M7: 163.34897 | N7: 162.76463 | O7: 162.18645 | P7: 161.61757 | Q7: 161.06114 | R7: 160.52017 | S7: 159.99749 | T7: 159.49567 | U7: 159.01687 | V7: 158.56304 | W7: 158.13598 | X7: 157.7373 | Y7: 157.36842 | Z7: 157.03058 | AA7: 156.72481 | AB7: 156.452 | AC7: 156.21287 | AD7: 156.00797 | AE7: 155.83776 | AF7: 155.70255 | AG7: 155.60254 | AH7: 155.53783 | AI7: 155.50847 | AJ7: 155.51438 | AK7: 155.55545
A8: ia_sfoo_2 | B8: 6742.5992 | C8: 6812.5447 | D8: 6879.7772 | E8: 6948.1372 | F8: 7019.4096 | G8: 7093.9752 | H8: 7171.7102 | I8: 7252.3584 | J8: 7335.5658 | K8: 7421.0092 | L8: 7508.4187 | M8: 7597.5675 | N8: 7688.255 | O8: 7780.2923 | P8: 7873.4941 | Q8: 7967.6743 | R8: 8062.7394 | S8: 8158.6724 | T8: 8255.4502 | U8: 8353.075 | V8: 8451.5733 | W8: 8550.9881 | X8: 8651.3688 | Y8: 8752.7638 | Z8: 8855.2147 | AA8: 8958.754 | AB8: 9063.4043 | AC8: 9169.1793 | AD8: 9276.0855 | AE8: 9384.1244 | AF8: 9493.2949 | AG8: 9603.5956 | AH8: 9715.0266 | AI8: 9827.5913 | AJ8: 9941.2974 | AK8: 10056.158
A9: ia_sfoo_0 | B9: 6742.5992 | C9: 6812.918 | D9: 6880.7425 | E9: 6949.9349 | F9: 7022.3561 | G9: 7098.4844 | H9: 7178.1486 | I9: 7260.9658 | J9: 7346.5408 | K9: 7434.5354 | L9: 7524.6819 | M9: 7616.7752 | N9: 7710.662 | O9: 7806.229 | P9: 7903.3949 | Q9: 8002.1017 | R9: 8102.309 | S9: 8203.9889 | T9: 8307.1212 | U9: 8411.6904 | V9: 8517.6829 | W9: 8625.0857 | X9: 8733.8854 | Y9: 8844.0679 | Z9: 8955.6185 | AA9: 9068.5224 | AB9: 9182.7648 | AC9: 9298.3317 | AD9: 9415.2105 | AE9: 9533.3902 | AF9: 9652.8617 | AG9: 9773.6184 | AH9: 9895.6561 | AI9: 10018.973 | AJ9: 10143.57 | AK9: 10269.45
A10: ia_sveh_2 | B10: 36330.779 | C10: 36893.036 | D10: 37526.885 | E10: 38159.864 | F10: 38757.762 | G10: 39313.621 | H10: 39835.226 | I10: 40334.69 | J10: 40821.094 | K10: 41299.855 | L10: 41773.77 | M10: 42244.06 | N10: 42711.088 | O10: 43174.78 | P10: 43634.856 | Q10: 44090.942 | R10: 44544.226 | S10: 44996.985 | T10: 45450.298 | U10: 45904.383 | V10: 46359.176 | W10: 46814.65 | X10: 47270.917 | Y10: 47728.224 | Z10: 48186.911 | AA10: 48647.372 | AB10: 49110.022 | AC10: 49575.282 | AD10: 50043.568 | AE10: 50515.284 | AF10: 50990.826 | AG10: 51470.575 | AH10: 51954.904 | AI10: 52444.173 | AJ10: 52938.727 | AK10: 53438.901
A11: ia_sveh_0 | B11: 36330.779 | C11: 36897.67 | D11: 37538.383 | E11: 38179.071 | F11: 38785.78 | G11: 39352.655 | H11: 39886.731 | I11: 40398.196 | J11: 40895.934 | K11: 41386.273 | L11: 41873.185 | M11: 42358.932 | N11: 42844.703 | O11: 43331.081 | P11: 43818.353 | Q11: 44306.685 | R11: 44796.209 | S11: 45287.066 | T11: 45779.416 | U11: 46273.439 | V11: 46769.334 | W11: 47267.315 | X11: 47767.605 | Y11: 48270.436 | Z11: 48776.045 | AA11: 49284.675 | AB11: 49796.575 | AC11: 50311.993 | AD11: 50831.181 | AE11: 51354.391 | AF11: 51881.875 | AG11: 52413.881 | AH11: 52950.655 | AI11: 53492.438 | AJ11: 54039.466 | AK11: 54591.969
A12: ia_sgla_2 | B12: 1455.1731 | C12: 1471.158 | D12: 1486.6502 | E12: 1501.8623 | F12: 1516.9245 | G12: 1531.8495 | H12: 1546.6956 | I12: 1561.597 | J12: 1576.6401 | K12: 1591.8583 | L12: 1607.2351 | M12: 1622.7127 | N12: 1638.2023 | O12: 1653.5939 | P12: 1668.7651 | Q12: 1683.5887 | R12: 1698.0254 | S12: 1712.142 | T12: 1726.0278 | U12: 1739.7764 | V12: 1753.4752 | W12: 1767.2018 | X12: 1781.0226 | Y12: 1794.9941 | Z12: 1809.1633 | AA12: 1823.5697 | AB12: 1838.246 | AC12: 1853.2198 | AD12: 1868.5143 | AE12: 1884.1492 | AF12: 1900.1415 | AG12: 1916.5058 | AH12: 1933.2553 | AI12: 1950.4016 | AJ12: 1967.9556 | AK12: 1985.927
... A79: ia_ser_0 | B79: 219461.28 | C79: 221888.44 | D79: 224292.96 | E79: 226729.35 | F79: 229226.27 | G79: 231793.06 | H79: 234429.3 | I79: 237130.78 | J79: 239892.4 | K79: 242709.38 | L79: 245577.67 | M79: 248494.04 | N79: 251456.09 | O79: 254462.06 | P79: 257510.8 | Q79: 260601.59 | R79: 263734.05 | S79: 266908 | T79: 270123.41 | U79: 273380.28 | V79: 276678.63 | W79: 280018.46 | X79: 283399.71 | Y79: 286822.29 | Z79: 290286.1 | AA79: 293790.98 | AB79: 297336.8 | AC79: 300923.4 | AD79: 304550.68 | AE79: 308218.55 | AF79: 311926.95 | AG79: 315675.89 | AH79: 319465.43 | AI79: 323295.66 | AJ79: 327166.76 | AK79: 331078.93

Sheet Labor
A1: _date_ | B1: 42005 | C1: 42370 | D1: 42736 | E1: 43101 | F1: 43466 | G1: 43831 | H1: 44197 | I1: 44562 | J1: 44927 | K1: 45292 | L1: 45658 | M1: 46023 | N1: 46388 | O1: 46753 | P1: 47119 | Q1: 47484 | R1: 47849 | S1: 48214 | T1: 48580 | U1: 48945 | V1: 49310 | W1: 49675 | X1: 50041 | Y1: 50406 | Z1: 50771 | AA1: 51136 | AB1: 51502 | AC1: 51867 | AD1: 52232 | AE1: 52597 | AF1: 52963 | AG1: 53328 | AH1: 53693 | AI1: 54058 | AJ1: 54424 | AK1: 54789
A2: f_l_2 | B2: 27390.88 | C2: 27450.148 | D2: 27503.436 | E2: 27556.124 | F2: 27612.274 | G2: 27674.143 | H2: 27742.109 | I2: 27815.189 | J2: 27892.1 | K2: 27971.733 | L2: 28053.323 | M2: 28136.453 | N2: 28220.982 | O2: 28306.952 | P2: 28394.497 | Q2: 28483.776 | R2: 28574.584 | S2: 28666.254 | T2: 28758.077 | U2: 28849.473 | V2: 28940.056 | W2: 29029.621 | X2: 29118.115 | Y2: 29205.581 | Z2: 29292.124 | AA2: 29377.872 | AB2: 29462.953 | AC2: 29547.484 | AD2: 29631.561 | AE2: 29715.263 | AF2: 29798.651 | AG2: 29881.772 | AH2: 29964.665 | AI2: 30047.363 | AJ2: 30129.898 | AK2: 30212.3
A3: f_l_0 | B3: 27390.88 | C3: 27448.862 | D3: 27499.539 | E3: 27548.51 | F3: 27599.973 | G3: 27656.135 | H3: 27717.672 | I3: 27784.329 | J3: 27855.384 | K3: 27929.95 | L3: 28007.151 | M3: 28086.22 | N3: 28166.532 | O3: 28247.612 | P3: 28329.119 | Q3: 28410.825 | R3: 28492.59 | S3: 28574.336 | T3: 28656.032 | U3: 28737.669 | V3: 28819.257 | W3: 28900.808 | X3: 28982.338 | Y3: 29063.857 | Z3: 29145.376 | AA3: 29226.899 | AB3: 29308.431 | AC3: 29389.972 | AD3: 29471.523 | AE3: 29553.086 | AF3: 29634.662 | AG3: 29716.255 | AH3: 29797.868 | AI3: 29879.506 | AJ3: 29961.176 | AK3: 30042.885
A4: f_l_sagr_2 | B4: 732.13 | C4: 733.52923 | D4: 734.7263 | E4: 736.05307 | F4: 737.74607 | G4: 739.9311 | H4: 742.59118 | I4: 745.59821 | J4: 748.823 | K4: 752.17558 | L4: 755.61206 | M4: 759.12768 | N4: 762.7455 | O4: 766.50542 | P4: 770.45522 | Q4: 774.64389 | R4: 779.07102 | S4: 783.67293 | T4: 788.37501 | U4: 793.11269 | V4: 797.83757 | W4: 802.51679 | X4: 807.13015 | Y4: 811.6666 | Z4: 816.12121 | AA4: 820.4928 | AB4: 824.78227 | AC4: 828.99154 | AD4: 833.12293 | AE4: 837.1788 | AF4: 841.16145 | AG4: 845.07311 | AH4: 848.91597 | AI4: 852.69225 | AJ4: 856.40424 | AK4: 860.05432
A5: f_l_sagr_0 | B5: 732.13 | C5: 733.35856 | D5: 734.20074 | E5: 735.0077 | F5: 736.0202 | G5: 737.34214 | H5: 738.98236 | I5: 740.90022 | J5: 743.03725 | K5: 745.33488 | L5: 747.74248 | M5: 750.21993 | N5: 752.73732 | O5: 755.27354 | P5: 757.81456 | Q5: 760.35165 | R5: 762.87995 | S5: 765.39723 | T5: 767.90295 | U5: 770.39754 | V5: 772.8819 | W5: 775.35709 | X5: 777.82412 | Y5: 780.28388 | Z5: 782.73708 | AA5: 785.18431 | AB5: 787.62605 | AC5: 790.06269 | AD5: 792.49463 | AE5: 794.92225 | AF5: 797.34598 | AG5: 799.76628 | AH5: 802.18366 | AI5: 804.59868 | AJ5: 807.01191 | AK5: 809.42397
A6: f_l_sfor_2 | B6: 29.08 | C6: 28.987949 | D6: 28.750779 | E6: 28.426383 | F6: 28.061582 | G6: 27.683425 | H6: 27.31006 | I6: 26.954971 | J6: 26.622834 | K6: 26.311961 | L6: 26.017487 | M6: 25.73367 | N6: 25.455204 | O6: 25.177831 | P6: 24.89853 | Q6: 24.615489 | R6: 24.33078 | S6: 24.049528 | T6: 23.775688 | U6: 23.511367 | V6: 23.257258 | W6: 23.013207 | X6: 22.778655 | Y6: 22.552915 | Z6: 22.335308 | AA6: 22.125233 | AB6: 21.922175 | AC6: 21.725709 | AD6: 21.535477 | AE6: 21.351182 | AF6: 21.172569 | AG6: 20.999416 | AH6: 20.831527 | AI6: 20.668726 | AJ6: 20.510849 | AK6: 20.357746
A7: f_l_sfor_0 | B7: 29.08 | C7: 29.005618 | D7: 28.799733 | E7: 28.51501 | F7: 28.196878 | G7: 27.874071 | H7: 27.561229 | I7: 27.263898 | J7: 26.982674 | K7: 26.715933 | L7: 26.461367 | M7: 26.216745 | N7: 25.980209 | O7: 25.750339 | P7: 25.526105 | Q7: 25.306793 | R7: 25.091918 | S7: 24.881155 | T7: 24.674289 | U7: 24.471151 | V7: 24.271621 | W7: 24.075618 | X7: 23.883085 | Y7: 23.69398 | Z7: 23.508268 | AA7: 23.325914 | AB7: 23.146886 | AC7: 22.97115 | AD7: 22.798668 | AE7: 22.629401 | AF7: 22.463308 | AG7: 22.300347 | AH7: 22.140474 | AI7: 21.983643 | AJ7: 21.829809 | AK7: 21.678924
A8: f_l_sfoo_2 | B8: 618.62 | C8: 619.64847 | D8: 620.40132 | E8: 621.19869 | F8: 622.24979 | G8: 623.64753 | H8: 625.38258 | I8: 627.38126 | J8: 629.56485 | K8: 631.87213 | L8: 634.26434 | M8: 636.72254 | N8: 639.24249 | O8: 641.82923 | P8: 644.49274 | Q8: 647.24464 | R8: 650.07782 | S8: 652.96212 | T8: 655.86623 | U8: 658.76524 | V8: 661.64225 | W8: 664.4874 | X8: 667.29618 | Y8: 670.06757 | Z8: 672.80256 | AA8: 675.50303 | AB8: 678.17107 | AC8: 680.80858 | AD8: 683.41712 | AE8: 685.99789 | AF8: 688.55183 | AG8: 691.07971 | AH8: 693.58227 | AI8: 696.06032 | AJ8: 698.51478 | AK8: 700.94678
A9: f_l_sfoo_0 | B9: 618.62 | C9: 619.58096 | D9: 620.19799 | E9: 620.80189 | F9: 621.60558 | G9: 622.69515 | H9: 624.07325 | I9: 625.70096 | J9: 627.52547 | K9: 629.49501 | L9: 631.56538 | M9: 633.70176 | N9: 635.87829 | O9: 638.07672 | P9: 640.28484 | Q9: 642.49501 | R9: 644.7028 | S9: 646.90604 | T9: 649.10393 | U9: 651.29649 | V9: 653.48407 | W9: 655.66713 | X9: 657.84606 | Y9: 660.02113 | Z9: 662.19247 | AA9: 664.3601 | AB9: 666.52395 | AC9: 668.68392 | AD9: 670.83993 | AE9: 672.99195 | AF9: 675.13999 | AG9: 677.28416 | AH9: 679.42464 | AI9: 681.5617 | AJ9: 683.69566 | AK9: 685.82691
A10: f_l_sveh_2 | B10: 185.81 | C10: 186.9055 | D10: 188.36388 | E10: 189.83565 | F10: 191.10824 | G10: 192.11245 | H10: 192.87326 | I10: 193.45495 | J10: 193.92011 | K10: 194.31526 | L10: 194.66977 | M10: 194.99961 | N10: 195.31181 | O10: 195.60807 | P10: 195.88719 | Q10: 196.14664 | R10: 196.38703 | S10: 196.6117 | T10: 196.82133 | U10: 197.01443 | V10: 197.18903 | W10: 197.34384 | X10: 197.47879 | Y10: 197.59497 | Z10: 197.69435 | AA10: 197.7795 | AB10: 197.8533 | AC10: 197.91867 | AD10: 197.97846 | AE10: 198.03536 | AF10: 198.09182 | AG10: 198.15004 | AH10: 198.21201 | AI10: 198.27944 | AJ10: 198.35385 | AK10: 198.43653
A11: f_l_sveh_0 | B11: 185.81 | C11: 186.91608 | D11: 188.39081 | E11: 189.88115 | F11: 191.17536 | G11: 192.20807 | H11: 193.00441 | I11: 193.62576 | J11: 194.13548 | K11: 194.58348 | L11: 195.00281 | M11: 195.41213 | N11: 195.81987 | O11: 196.22828 | P11: 196.63639 | Q11: 197.04198 | R11: 197.44272 | S11: 197.83673 | T11: 198.22269 | U11: 198.59992 | V11: 198.96823 | W11: 199.32783 | X11: 199.67917 | Y11: 200.02293 | Z11: 200.35986 | AA11: 200.69079 | AB11: 201.01656 | AC11: 201.33802 | AD11: 201.65597 | AE11: 201.97119 | AF11: 202.28442 | AG11: 202.59635 | AH11: 202.90759 | AI11: 203.21872 | AJ11: 203.53027 | AK11: 203.84269
A12: f_l_sgla_2 | B12: 98.04 | C12: 98.276004 | D12: 98.504103 | E12: 98.73424 | F12: 98.979021 | G12: 99.249637 | H12: 99.547179 | I12: 99.863255 | J12: 100.1902 | K12: 100.52372 | L12: 100.86283 | M12: 101.20894 | N12: 101.56491 | O12: 101.93426 | P12: 102.32057 | Q12: 102.72707 | R12: 103.15189 | S12: 103.58765 | T12: 104.02723 | U12: 104.46541 | V12: 104.89891 | W12: 105.32595 | X12: 105.74586 | Y12: 106.15856 | Z12: 106.56438 | AA12: 106.9638 | AB12: 107.35733 | AC12: 107.74548 | AD12: 108.1287 | AE12: 108.50737 | AF12: 108.88183 | AG12: 109.25234 | AH12: 109.61913 | AI12: 109.98242 | AJ12: 110.34236 | AK12: 110.69913
... A79: f_l_ser_0 | B79: 21284.868 | C79: 21330.075 | D79: 21370.068 | E79: 21409.305 | F79: 21450.968 | G79: 21496.614 | H79: 21546.611 | I79: 21600.64 | J79: 21658.063 | K79: 21718.152 | L79: 21780.218 | M79: 21843.669 | N79: 21908.031 | O79: 21972.949 | P79: 22038.17 | Q79: 22103.528 | R79: 22168.918 | S79: 22234.285 | T79: 22299.605 | U79: 22364.871 | V79: 22430.088 | W79: 22495.264 | X79: 22560.407 | Y79: 22625.523 | Z79: 22690.617 | AA79: 22755.689 | AB79: 22820.741 | AC79: 22885.773 | AD79: 22950.783 | AE79: 23015.774 | AF79: 23080.745 | AG79: 23145.699 | AH79: 23210.642 | AI79: 23275.578 | AJ79: 23340.514 | AK79: 23405.458

Sheet Final_nrj
A1: _date_ | B1: 42005 | C1: 42370 | D1: 42736 | E1: 43101 | F1: 43466 | G1: 43831 | H1: 44197 | I1: 44562 | J1: 44927 | K1: 45292 | L1: 45658 | M1: 46023 | N1: 46388 | O1: 46753 | P1: 47119 | Q1: 47484 | R1: 47849 | S1: 48214 | T1: 48580 | U1: 48945 | V1: 49310 | W1: 49675 | X1: 50041 | Y1: 50406 | Z1: 50771 | AA1: 51136 | AB1: 51502 | AC1: 51867 | AD1: 52232 | AE1: 52597 | AF1: 52963 | AG1: 53328 | AH1: 53693 | AI1: 54058 | AJ1: 54424 | AK1: 54789
A2: cf_toe_2 | B2: 162.18538 | C2: 163.06253 | D2: 163.6245 | E2: 164.13445 | F2: 164.66559 | G2: 165.21267 | H2: 165.78854 | I2: 166.42521 | J2: 167.12658 | K2: 167.88073 | L2: 168.66806 | M2: 169.46593 | N2: 170.25132 | O2: 171.00256 | P2: 171.70041 | Q2: 172.32882 | R2: 172.89899 | S2: 173.44259 | T2: 173.98177 | U2: 174.53104 | V2: 175.09968 | W2: 175.69355 | X2: 176.3163 | Y2: 176.97008 | Z2: 177.65608 | AA2: 178.37482 | AB2: 179.12638 | AC2: 179.91058 | AD2: 180.72704 | AE2: 181.5753 | AF2: 182.45488 | AG2: 183.36525 | AH2: 184.30596 | AI2: 185.27659 | AJ2: 186.27677 | AK2: 187.30621
A3: ch_toe_2 | B3: 64.30144 | C3: 64.18586 | D3: 63.817556 | E3: 63.424331 | F3: 63.072737 | G3: 62.766779 | H3: 62.508377 | I3: 62.301972 | J3: 62.138558 | K3: 62.005321 | L3: 61.889604 | M3: 61.780392 | N3: 61.668747 | O3: 61.54782 | P3: 61.4127 | Q3: 61.260208 | R3: 61.09704 | S3: 60.934906 | T3: 60.779439 | U3: 60.632898 | V3: 60.495756 | W3: 60.367614 | X3: 60.247708 | Y3: 60.135168 | Z3: 60.029141 | AA3: 59.92884 | AB3: 59.833557 | AC3: 59.742657 | AD3: 59.655564 | AE3: 59.571755 | AF3: 59.49075 | AG3: 59.412103 | AH3: 59.3354 | AI3: 59.260252 | AJ3: 59.186296 | AK3: 59.113194
A4: ch_hous_toe_2 | B4: 42520877 | C4: 42691819 | D4: 42480076 | E4: 42156997 | F4: 41818633 | G4: 41488722 | H4: 41180934 | I4: 40906363 | J4: 40660945 | K4: 40435695 | L4: 40221008 | M4: 40008370 | N4: 39790945 | O4: 39563701 | P4: 39323325 | Q4: 39068063 | R4: 38804744 | S4: 38544194 | T4: 38291644 | U4: 38049244 | V4: 37817512 | W4: 37596162 | X4: 37384581 | Y4: 37182065 | Z4: 36987938 | AA4: 36801593 | AB4: 36622510 | AC4: 36450240 | AD4: 36284403 | AE4: 36124668 | AF4: 35970749 | AG4: 35822394 | AH4: 35679378 | AI4: 35541501 | AJ4: 35408582 | AK4: 35280457
A5: ch_auto_toe_2 | B5: 21780563 | C5: 21494040 | D5: 21337481 | E5: 21267334 | F5: 21254103 | G5: 21278057 | H5: 21327443 | I5: 21395609 | J5: 21477613 | K5: 21569626 | L5: 21668595 | M5: 21772022 | N5: 21877801 | O5: 21984118 | P5: 22089375 | Q5: 22192145 | R5: 22292296 | S5: 22390712 | T5: 22487795 | U5: 22583654 | V5: 22678244 | W5: 22771452 | X5: 22863127 | Y5: 22953102 | Z5: 23041203 | AA5: 23127247 | AB5: 23211048 | AC5: 23292416 | AD5: 23371161 | AE5: 23447087 | AF5: 23520001 | AG5: 23589709 | AH5: 23656021 | AI5: 23718751 | AJ5: 23777715 | AK5: 23832737
A6: cf_toe_0 | B6: 162.18538 | C6: 163.18361 | D6: 163.93894 | E6: 164.69725 | F6: 165.53686 | G6: 166.4692 | H6: 167.48335 | I6: 168.56385 | J6: 169.69685 | K6: 170.87166 | L6: 172.08057 | M6: 173.31826 | N6: 174.58111 | O6: 175.8667 | P6: 177.17338 | Q6: 178.50013 | R6: 179.8463 | S6: 181.21149 | T6: 182.59545 | U6: 183.99804 | V6: 185.4192 | W6: 186.8589 | X6: 188.31714 | Y6: 189.79394 | Z6: 191.28931 | AA6: 192.80331 | AB6: 194.33597 | AC6: 195.88737 | AD6: 197.45759 | AE6: 199.04673 | AF6: 200.6549 | AG6: 202.28226 | AH6: 203.92897 | AI6: 205.59519 | AJ6: 207.28114 | AK6: 208.98701
A7: ch_toe_0 | B7: 64.30144 | C7: 64.233784 | D7: 63.931558 | E7: 63.614626 | F7: 63.352024 | G7: 63.15395 | H7: 63.01119 | I7: 62.910661 | J7: 62.840776 | K7: 62.792713 | L7: 62.760233 | M7: 62.739095 | N7: 62.72647 | O7: 62.720453 | P7: 62.719697 | Q7: 62.723315 | R7: 62.730704 | S7: 62.741401 | T7: 62.755059 | U7: 62.771409 | V7: 62.790253 | W7: 62.811437 | X7: 62.834839 | Y7: 62.860359 | Z7: 62.887917 | AA7: 62.917448 | AB7: 62.948899 | AC7: 62.982229 | AD7: 63.017408 | AE7: 63.054413 | AF7: 63.093228 | AG7: 63.133845 | AH7: 63.176261 | AI7: 63.220481 | AJ7: 63.266511 | AK7: 63.314362
A8: ch_hous_toe_0 | B8: 42520877 | C8: 42736368 | D8: 42585617 | E8: 42332591 | F8: 42075594 | G8: 41843924 | H8: 41640750 | I8: 41461049 | J8: 41298547 | K8: 41148003 | L8: 41005653 | M8: 40869017 | N8: 40736558 | O8: 40607342 | P8: 40480762 | Q8: 40356513 | R8: 40234444 | S8: 40114457 | T8: 39996492 | U8: 39880514 | V8: 39766511 | W8: 39654478 | X8: 39544414 | Y8: 39436315 | Z8: 39330174 | AA8: 39225984 | AB8: 39123732 | AC8: 39023407 | AD8: 38924996 | AE8: 38828483 | AF8: 38733853 | AG8: 38641087 | AH8: 38550170 | AI8: 38461088 | AJ8: 38373824 | AK8: 38288364
A9: ch_auto_toe_0 | B9: 21780563 | C9: 21497416 | D9: 21345941 | E9: 21282035 | F9: 21276430 | G9: 21310026 | H9: 21370440 | I9: 21449612 | J9: 21542228 | K9: 21644710 | L9: 21754580 | M9: 21870078 | N9: 21989911 | O9: 22113111 | P9: 22238934 | Q9: 22366802 | R9: 22496260 | S9: 22626944 | T9: 22758567 | U9: 22890895 | V9: 23023742 | W9: 23156959 | X9: 23290425 | Y9: 23424044 | Z9: 23557743 | AA9: 23691464 | AB9: 23825167 | AC9: 23958822 | AD9: 24092412 | AE9: 24225929 | AF9: 24359375 | AG9: 24492758 | AH9: 24626091 | AI9: 24759393 | AJ9: 24892687 | AK9: 25025998
A10: cf_toe_ccoa_2 | B10: 5.4734959 | C10: 5.5279399 | D10: 5.5770586 | E10: 5.6219863 | F10: 5.6625223 | G10: 5.6976117 | H10: 5.7287704 | I10: 5.759323 | J10: 5.7908446 | K10: 5.8235659 | L10: 5.8568497 | M10: 5.889549 | N10: 5.9202658 | O10: 5.9475439 | P10: 5.9700135 | Q10: 5.9864999 | R10: 5.9977121 | S10: 6.0058985 | T10: 6.0128058 | U10: 6.0196825 | V10: 6.0273976 | W10: 6.036545 | X10: 6.0475222 | Y10: 6.0605868 | Z10: 6.075898 | AA10: 6.0935471 | AB10: 6.1135785 | AC10: 6.1360053 | AD10: 6.1608209 | AE10: 6.188006 | AF10: 6.2175346 | AG10: 6.2493778 | AH10: 6.283506 | AI10: 6.3198908 | AJ10: 6.3585064 | AK10: 6.39933
A11: cf_toe_ccoa_0 | B11: 5.4734959 | C11: 5.5356888 | D11: 5.5982633 | E11: 5.6614783 | F11: 5.7254982 | G11: 5.7904348 | H11: 5.8563511 | I11: 5.9232659 | J11: 5.9911655 | K11: 6.0600186 | L11: 6.1297887 | M11: 6.2004423 | N11: 6.2719542 | O11: 6.3443082 | P11: 6.4174968 | Q11: 6.4915201 | R11: 6.566384 | S11: 6.6420978 | T11: 6.7186734 | U11: 6.7961236 | V11: 6.8744616 | W11: 6.9537 | X11: 7.0338512 | Y11: 7.1149265 | Z11: 7.1969371 | AA11: 7.2798932 | AB11: 7.363805 | AC11: 7.4486825 | AD11: 7.5345355 | AE11: 7.621374 | AF11: 7.7092081 | AG11: 7.7980482 | AH11: 7.8879046 | AI11: 7.9787883 | AJ11: 8.0707102 | AK11: 8.1636815
A12: cf_toe_ccoi_2 | B12: 0.084809986 | C12: 0.085668828 | D12: 0.086469358 | E12: 0.087239316 | F12: 0.087981866 | G12: 0.088685993 | H12: 0.089365122 | I12: 0.090051036 | J12: 0.090757927 | K12: 0.091486547 | L12: 0.092229136 | M12: 0.092973002 | N12: 0.093703038 | O12: 0.094403532 | P12: 0.095059531 | Q12: 0.09565784 | R12: 0.096204965 | S12: 0.096723909 | T12: 0.097232558 | U12: 0.097743669 | V12: 0.098266158 | W12: 0.098806201 | X12: 0.099368019 | Y12: 0.099954431 | Z12: 0.10056726 | AA12: 0.10120761 | AB12: 0.10187608 | AC12: 0.10257294 | AD12: 0.10329823 | AE12: 0.10405185 | AF12: 0.10483361 | AG12: 0.10564332 | AH12: 0.10648076 | AI12: 0.10734576 | AJ12: 0.10823819 | AK12: 0.10915796
... A737: ci_toe_cfuel_ser_0 | B737: 2.8654882 | C737: 2.8967075 | D737: 2.9278608 | E737: 2.9597623 | F737: 2.9926616 | G737: 3.0265472 | H737: 3.0613249 | I737: 3.0968928 | J737: 3.1331649 | K737: 3.170076 | L737: 3.2075792 | M737: 3.2456425 | N737: 3.2842451 | O737: 3.3233755 | P737: 3.363028 | Q737: 3.4032016 | R737: 3.443898 | S737: 3.4851202 | T737: 3.5268716 | U737: 3.5691552 | V737: 3.6119734 | W737: 3.6553275 | X737: 3.6992182 | Y737: 3.7436452 | Z737: 3.7886078 | AA737: 3.8341054 | AB737: 3.8801368 | AC737: 3.9267016 | AD737: 3.9737996 | AE737: 4.021431 | AF737: 4.0695968 | AG737: 4.1182989 | AH737: 4.1675396 | AI737: 4.2173221 | AJ737: 4.2676504 | AK737: 4.3185291

Sheet Primary_nrj
A1: _date_ | B1: 42005 | C1: 42370 | D1: 42736 | E1: 43101 | F1: 43466 | G1: 43831 | H1: 44197 | I1: 44562 | J1: 44927 | K1: 45292 | L1: 45658 | M1: 46023 | N1: 46388 | O1: 46753 | P1: 47119 | Q1: 47484 | R1: 47849 | S1: 48214 | T1: 48580 | U1: 48945 | V1: 49310 | W1: 49675 | X1: 50041 | Y1: 50406 | Z1: 50771 | AA1: 51136 | AB1: 51502 | AC1: 51867 | AD1: 52232 | AE1: 52597 | AF1: 52963 | AG1: 53328 | AH1: 53693 | AI1: 54058 | AJ1: 54424 | AK1: 54789
A2: yg_toe_2 | B2: 148.5762 | C2: 149.51936 | D2: 150.2081 | E2: 150.85926 | F2: 151.54151 | G2: 152.25991 | H2: 153.0152 | I2: 153.81547 | J2: 154.66012 | K2: 155.54246 | L2: 156.45229 | M2: 157.37772 | N2: 158.3064 | O2: 159.22632 | P2: 160.12635 | Q2: 160.99668 | R2: 161.83904 | S2: 162.66616 | T2: 163.48954 | U2: 164.31793 | V2: 165.15759 | W2: 166.01291 | X2: 166.88692 | Y2: 167.78176 | Z2: 168.69891 | AA2: 169.63946 | AB2: 170.60419 | AC2: 171.59373 | AD2: 172.60856 | AE2: 173.64913 | AF2: 174.71585 | AG2: 175.80912 | AH2: 176.92934 | AI2: 178.07695 | AJ2: 179.25241 | AK2: 180.45618
A3: yg_toe_0 | B3: 148.5762 | C3: 149.57013 | D3: 150.34484 | E3: 151.10989 | F3: 151.93569 | G3: 152.8347 | H3: 153.7993 | I3: 154.81742 | J3: 155.87806 | K3: 156.9727 | L3: 158.09525 | M3: 159.24155 | N3: 160.40878 | O3: 161.59512 | P3: 162.79935 | Q3: 164.0207 | R3: 165.25873 | S3: 166.51315 | T3: 167.78381 | U3: 169.07065 | V3: 170.37371 | W3: 171.69305 | X3: 173.02878 | Y3: 174.38103 | Z3: 175.74991 | AA3: 177.13559 | AB3: 178.53821 | AC3: 179.95794 | AD3: 181.39497 | AE3: 182.84948 | AF3: 184.32167 | AG3: 185.81175 | AH3: 187.31995 | AI3: 188.8465 | AJ3: 190.39163 | AK3: 191.95559
A4: yg_toe_ccoa_2 | B4: 2.391149 | C4: 2.4113891 | D4: 2.4288717 | E4: 2.4456982 | F4: 2.4621685 | G4: 2.4777432 | H4: 2.4926192 | I4: 2.5076797 | J4: 2.5232859 | K4: 2.5393893 | L4: 2.5556739 | M4: 2.5716626 | N4: 2.5867922 | O4: 2.600471 | P4: 2.6121236 | Q4: 2.6212282 | R4: 2.6279962 | S4: 2.6332725 | T4: 2.637724 | U4: 2.6418349 | V4: 2.6459506 | W4: 2.6503147 | X4: 2.6550968 | Y4: 2.6604129 | Z4: 2.66634 | AA4: 2.6729266 | AB4: 2.6802013 | AC4: 2.6881778 | AD4: 2.6968599 | AE4: 2.7062441 | AF4: 2.7163219 | AG4: 2.7270816 | AH4: 2.7385093 | AI4: 2.7505902 | AJ4: 2.7633083 | AK4: 2.7766479
A5: yg_toe_ccoa_0 | B5: 2.391149 | C5: 2.4138098 | D5: 2.4355281 | E5: 2.4581598 | F5: 2.4821766 | G5: 2.5075019 | H5: 2.5339147 | I5: 2.5611973 | J5: 2.5891753 | K5: 2.6177206 | L5: 2.6467433 | M5: 2.6761821 | N5: 2.7059965 | O5: 2.7361603 | P5: 2.7666574 | Q5: 2.7974788 | R5: 2.8286204 | S5: 2.8600819 | T5: 2.8918649 | U5: 2.9239721 | V5: 2.9564069 | W5: 2.989173 | X5: 3.0222742 | Y5: 3.0557146 | Z5: 3.0894982 | AA5: 3.1236291 | AB5: 3.1581116 | AC5: 3.1929498 | AD5: 3.2281483 | AE5: 3.2637113 | AF5: 3.2996436 | AG5: 3.3359498 | AH5: 3.3726347 | AI5: 3.4097029 | AJ5: 3.4471595 | AK5: 3.4850092
A6: yg_toe_ccoi_2 | B6: 1.095999 | C6: 1.1024468 | D6: 1.1067507 | E6: 1.1111346 | F6: 1.1162551 | G6: 1.1220649 | H6: 1.1284291 | I6: 1.1353064 | J6: 1.1426334 | K6: 1.1503167 | L6: 1.1582443 | M6: 1.1662947 | N6: 1.1743444 | O6: 1.1822724 | P6: 1.1899643 | Q6: 1.1973152 | R6: 1.2043218 | S6: 1.2110894 | T6: 1.2177223 | U6: 1.2243003 | V6: 1.2308797 | W6: 1.2374984 | X6: 1.2441811 | Y6: 1.2509432 | Z6: 1.2577932 | AA6: 1.2647354 | AB6: 1.2717706 | AC6: 1.2788974 | AD6: 1.2861129 | AE6: 1.2934133 | AF6: 1.3007937 | AG6: 1.3082491 | AH6: 1.3157741 | AI6: 1.3233633 | AJ6: 1.331011 | AK6: 1.3387119
A7: yg_toe_ccoi_0 | B7: 1.095999 | C7: 1.1028001 | D7: 1.1077768 | E7: 1.1130992 | F7: 1.1194315 | G7: 1.1267863 | H7: 1.1349781 | I7: 1.1438038 | J7: 1.1530986 | K7: 1.1627433 | L7: 1.1726568 | M7: 1.1827858 | N7: 1.1930955 | O7: 1.2035636 | P7: 1.2141752 | Q7: 1.2249212 | R7: 1.2357956 | S7: 1.2467947 | T7: 1.2579163 | U7: 1.2691592 | V7: 1.2805225 | W7: 1.2920062 | X7: 1.3036102 | Y7: 1.3153347 | Z7: 1.3271803 | AA7: 1.3391474 | AB7: 1.3512369 | AC7: 1.3634497 | AD7: 1.3757866 | AE7: 1.3882489 | AF7: 1.4008378 | AG7: 1.4135548 | AH7: 1.4264013 | AI7: 1.439379 | AJ7: 1.4524894 | AK7: 1.4657345
A8: yg_toe_cfut_2 | B8: 42.352189 | C8: 42.550606 | D8: 42.687581 | E8: 42.846741 | F8: 43.046125 | G8: 43.279187 | H8: 43.53806 | I8: 43.819273 | J8: 44.118994 | K8: 44.432916 | L8: 44.756428 | M8: 45.084783 | N8: 45.413218 | O8: 45.73707 | P8: 46.051887 | Q8: 46.353526 | R8: 46.641782 | S8: 46.92045 | T8: 47.193082 | U8: 47.462418 | V8: 47.730429 | W8: 47.998475 | X8: 48.267454 | Y8: 48.537921 | Z8: 48.810184 | AA8: 49.084366 | AB8: 49.360462 | AC8: 49.638367 | AD8: 49.917913 | AE8: 50.19888 | AF8: 50.481016 | AG8: 50.764047 | AH8: 51.047686 | AI8: 51.331639 | AJ8: 51.615609 | AK8: 51.899301
A9: yg_toe_cfut_0 | B9: 42.352189 | C9: 42.563839 | D9: 42.725107 | E9: 42.918049 | F9: 43.161282 | G9: 43.450606 | H9: 43.776175 | I9: 44.128632 | J9: 44.500733 | K9: 44.887349 | L9: 45.285004 | M9: 45.691392 | N9: 46.104998 | O9: 46.524822 | P9: 46.950201 | Q9: 47.380695 | R9: 47.816006 | S9: 48.255934 | T9: 48.700343 | U9: 49.149141 | V9: 49.602269 | W9: 50.059687 | X9: 50.521371 | Y9: 50.987312 | Z9: 51.457506 | AA9: 51.931962 | AB9: 52.410695 | AC9: 52.893729 | AD9: 53.381093 | AE9: 53.872825 | AF9: 54.368969 | AG9: 54.869575 | AH9: 55.3747 | AI9: 55.884403 | AJ9: 56.398749 | AK9: 56.917805
A10: yg_toe_cfuh_2 | B10: 7.935536 | C10: 7.9840674 | D10: 8.0149749 | E10: 8.0398035 | F10: 8.0628488 | G10: 8.0849657 | H10: 8.1072755 | I10: 8.1314428 | J10: 8.1579137 | K10: 8.1863899 | L10: 8.216174 | M10: 8.2463782 | N10: 8.2760467 | O10: 8.3042305 | P10: 8.3300366 | Q10: 8.3526614 | R10: 8.3725162 | S10: 8.3909934 | T10: 8.4090798 | U10: 8.4274389 | V10: 8.446516 | W10: 8.4666134 | X10: 8.4879377 | Y10: 8.5106309 | Z10: 8.5347901 | AA10: 8.560481 | AB10: 8.5877472 | AC10: 8.6166166 | AD10: 8.6471061 | AE10: 8.6792257 | AF10: 8.7129808 | AG10: 8.7483741 | AH10: 8.7854078 | AI10: 8.8240841 | AJ10: 8.8644062 | AK10: 8.9063789
A11: yg_toe_cfuh_0 | B11: 7.935536 | C11: 7.9882333 | D11: 8.0259842 | E11: 8.0597632 | F11: 8.0940822 | G11: 8.1304841 | H11: 8.1692775 | I11: 8.2103169 | J11: 8.2533318 | K11: 8.2980554 | L11: 8.3442671 | M11: 8.3917989 | N11: 8.4405296 | O11: 8.4903729 | P11: 8.5412592 | Q11: 8.593147 | R11: 8.6460126 | S11: 8.6998426 | T11: 8.7546299 | U11: 8.8103707 | V11: 8.8670632 | W11: 8.9247063 | X11: 8.9832992 | Y11: 9.0428414 | Z11: 9.1033324 | AA11: 9.1647719 | AB11: 9.2271599 | AC11: 9.2904971 | AD11: 9.3547846 | AE11: 9.4200245 | AF11: 9.4862195 | AG11: 9.5533735 | AH11: 9.621491 | AI11: 9.6905774 | AJ11: 9.7606392 | AK11: 9.8316833
A12: yg_toe_cgas_2 | B12: 6.597728 | C12: 6.6026416 | D12: 6.5812125 | E12: 6.5499481 | F12: 6.5140529 | G12: 6.4743936 | H12: 6.4361754 | I12: 6.4048289 | J12: 6.3796585 | K12: 6.3582527 | L12: 6.3381549 | M12: 6.317429 | N12: 6.2947933 | O12: 6.2695961 | P12: 6.2417373 | Q12: 6.2115704 | R12: 6.182132 | S12: 6.1568638 | T12: 6.1364728 | U12: 6.1206487 | V12: 6.1087812 | W12: 6.1002458 | X12: 6.0945035 | Y12: 6.0911219 | Z12: 6.089766 | AA12: 6.0901809 | AB12: 6.0921736 | AC12: 6.0955977 | AD12: 6.1003409 | AE12: 6.1063165 | AF12: 6.113456 | AG12: 6.1217043 | AH12: 6.1310163 | AI12: 6.1413535 | AJ12: 6.1526827 | AK12: 6.1649744
... A73: yg_toe_cote_spub_0 | B73: 1.228594 | C73: 1.2411461 | D73: 1.2532706 | E73: 1.2655764 | F73: 1.2782706 | G73: 1.2913746 | H73: 1.3048474 | I73: 1.3186369 | J73: 1.3326976 | K73: 1.3469951 | L73: 1.3615048 | M73: 1.3762097 | N73: 1.3910986 | O73: 1.4061646 | P73: 1.4214036 | Q73: 1.4368139 | R73: 1.4523952 | S73: 1.4681482 | T73: 1.4840745 | U73: 1.5001759 | V73: 1.5164548 | W73: 1.5329136 | X73: 1.5495547 | Y73: 1.5663806 | Z73: 1.5833938 | AA73: 1.6005968 | AB73: 1.6179919 | AC73: 1.6355818 | AD73: 1.6533688 | AE73: 1.6713555 | AF73: 1.6895445 | AG73: 1.7079383 | AH73: 1.7265396 | AI73: 1.745351 | AJ73: 1.7643753 | AK73: 1.7836152

Sheet Energy_Mix
A1: _date_ | B1: 42005 | C1: 42370 | D1: 42736 | E1: 43101 | F1: 43466 | G1: 43831 | H1: 44197 | I1: 44562 | J1: 44927 | K1: 45292 | L1: 45658 | M1: 46023 | N1: 46388 | O1: 46753 | P1: 47119 | Q1: 47484 | R1: 47849 | S1: 48214 | T1: 48580 | U1: 48945 | V1: 49310 | W1: 49675 | X1: 50041 | Y1: 50406 | Z1: 50771 | AA1: 51136 | AB1: 51502 | AC1: 51867 | AD1: 52232 | AE1: 52597 | AF1: 52963 | AG1: 53328 | AH1: 53693 | AI1: 54058 | AJ1: 54424 | AK1: 54789
A2: phiy_ccoa_smin_2 | B2: 0.20069089 | C2: 0.20069089 | D2: 0.20069089 | E2: 0.20069089 | F2: 0.20069089 | G2: 0.20069089 | H2: 0.20069089 | I2: 0.20069089 | J2: 0.20069089 | K2: 0.20069089 | L2: 0.20069089 | M2: 0.20069089 | N2: 0.20069089 | O2: 0.20069089 | P2: 0.20069089 | Q2: 0.20069089 | R2: 0.20069089 | S2: 0.20069089 | T2: 0.20069089 | U2: 0.20069089 | V2: 0.20069089 | W2: 0.20069089 | X2: 0.20069089 | Y2: 0.20069089 | Z2: 0.20069089 | AA2: 0.20069089 | AB2: 0.20069089 | AC2: 0.20069089 | AD2: 0.20069089 | AE2: 0.20069089 | AF2: 0.20069089 | AG2: 0.20069089 | AH2: 0.20069089 | AI2: 0.20069089 | AJ2: 0.20069089 | AK2: 0.20069089
A3: phiy_ccoa_soil_2 | B3: 0.79930911 | C3: 0.79930911 | D3: 0.79930911 | E3: 0.79930911 | F3: 0.79930911 | G3: 0.79930911 | H3: 0.79930911 | I3: 0.79930911 | J3: 0.79930911 | K3: 0.79930911 | L3: 0.79930911 | M3: 0.79930911 | N3: 0.79930911 | O3: 0.79930911 | P3: 0.79930911 | Q3: 0.79930911 | R3: 0.79930911 | S3: 0.79930911 | T3: 0.79930911 | U3: 0.79930911 | V3: 0.79930911 | W3: 0.79930911 | X3: 0.79930911 | Y3: 0.79930911 | Z3: 0.79930911 | AA3: 0.79930911 | AB3: 0.79930911 | AC3: 0.79930911 | AD3: 0.79930911 | AE3: 0.79930911 | AF3: 0.79930911 | AG3: 0.79930911 | AH3: 0.79930911 | AI3: 0.79930911 | AJ3: 0.79930911 | AK3: 0.79930911
A4: phiy_ccoi_smin_2 | B4: 0.7836667 | C4: 0.7836667 | D4: 0.7836667 | E4: 0.7836667 | F4: 0.7836667 | G4: 0.7836667 | H4: 0.7836667 | I4: 0.7836667 | J4: 0.7836667 | K4: 0.7836667 | L4: 0.7836667 | M4: 0.7836667 | N4: 0.7836667 | O4: 0.7836667 | P4: 0.7836667 | Q4: 0.7836667 | R4: 0.7836667 | S4: 0.7836667 | T4: 0.7836667 | U4: 0.7836667 | V4: 0.7836667 | W4: 0.7836667 | X4: 0.7836667 | Y4: 0.7836667 | Z4: 0.7836667 | AA4: 0.7836667 | AB4: 0.7836667 | AC4: 0.7836667 | AD4: 0.7836667 | AE4: 0.7836667 | AF4: 0.7836667 | AG4: 0.7836667 | AH4: 0.7836667 | AI4: 0.7836667 | AJ4: 0.7836667 | AK4: 0.7836667
A5: phiy_ccoi_soil_2 | B5: 0.2163333 | C5: 0.2163333 | D5: 0.2163333 | E5: 0.2163333 | F5: 0.2163333 | G5: 0.2163333 | H5: 0.2163333 | I5: 0.2163333 | J5: 0.2163333 | K5: 0.2163333 | L5: 0.2163333 | M5: 0.2163333 | N5: 0.2163333 | O5: 0.2163333 | P5: 0.2163333 | Q5: 0.2163333 | R5: 0.2163333 | S5: 0.2163333 | T5: 0.2163333 | U5: 0.2163333 | V5: 0.2163333 | W5: 0.2163333 | X5: 0.2163333 | Y5: 0.2163333 | Z5: 0.2163333 | AA5: 0.2163333 | AB5: 0.2163333 | AC5: 0.2163333 | AD5: 0.2163333 | AE5: 0.2163333 | AF5: 0.2163333 | AG5: 0.2163333 | AH5: 0.2163333 | AI5: 0.2163333 | AJ5: 0.2163333 | AK5: 0.2163333
A6: phiy_cfut_soil_2 | B6: 0.83809636 | C6: 0.83809636 | D6: 0.83809636 | E6: 0.83809636 | F6: 0.83809636 | G6: 0.83809636 | H6: 0.83809636 | I6: 0.83809636 | J6: 0.83809636 | K6: 0.83809636 | L6: 0.83809636 | M6: 0.83809636 | N6: 0.83809636 | O6: 0.83809636 | P6: 0.83809636 | Q6: 0.83809636 | R6: 0.83809636 | S6: 0.83809636 | T6: 0.83809636 | U6: 0.83809636 | V6: 0.83809636 | W6: 0.83809636 | X6: 0.83809636 | Y6: 0.83809636 | Z6: 0.83809636 | AA6: 0.83809636 | AB6: 0.83809636 | AC6: 0.83809636 | AD6: 0.83809636 | AE6: 0.83809636 | AF6: 0.83809636 | AG6: 0.83809636 | AH6: 0.83809636 | AI6: 0.83809636 | AJ6: 0.83809636 | AK6: 0.83809636
A7: phiy_cfut_sbfu_2 | B7: 0.16190364 | C7: 0.16190364 | D7: 0.16190364 | E7: 0.16190364 | F7: 0.16190364 | G7: 0.16190364 | H7: 0.16190364 | I7: 0.16190364 | J7: 0.16190364 | K7: 0.16190364 | L7: 0.16190364 | M7: 0.16190364 | N7: 0.16190364 | O7: 0.16190364 | P7: 0.16190364 | Q7: 0.16190364 | R7: 0.16190364 | S7: 0.16190364 | T7: 0.16190364 | U7: 0.16190364 | V7: 0.16190364 | W7: 0.16190364 | X7: 0.16190364 | Y7: 0.16190364 | Z7: 0.16190364 | AA7: 0.16190364 | AB7: 0.16190364 | AC7: 0.16190364 | AD7: 0.16190364 | AE7: 0.16190364 | AF7: 0.16190364 | AG7: 0.16190364 | AH7: 0.16190364 | AI7: 0.16190364 | AJ7: 0.16190364 | AK7: 0.16190364
A8: phiy_cfuh_soil_2 | B8: 1 | C8: 1 | D8: 1 | E8: 1 | F8: 1 | G8: 1 | H8: 1 | I8: 1 | J8: 1 | K8: 1 | L8: 1 | M8: 1 | N8: 1 | O8: 1 | P8: 1 | Q8: 1 | R8: 1 | S8: 1 | T8: 1 | U8: 1 | V8: 1 | W8: 1 | X8: 1 | Y8: 1 | Z8: 1 | AA8: 1 | AB8: 1 | AC8: 1 | AD8: 1 | AE8: 1 | AF8: 1 | AG8: 1 | AH8: 1 | AI8: 1 | AJ8: 1 | AK8: 1
A9: phiy_cgas_smet_2 | B9: 8.2704782e-05 | C9: 8.2704782e-05 | D9: 8.2704782e-05 | E9: 8.2704782e-05 | F9: 8.2704782e-05 | G9: 8.2704782e-05 | H9: 8.2704782e-05 | I9: 8.2704782e-05 | J9: 8.2704782e-05 | K9: 8.2704782e-05 | L9: 8.2704782e-05 | M9: 8.2704782e-05 | N9: 8.2704782e-05 | O9: 8.2704782e-05 | P9: 8.2704782e-05 | Q9: 8.2704782e-05 | R9: 8.2704782e-05 | S9: 8.2704782e-05 | T9: 8.2704782e-05 | U9: 8.2704782e-05 | V9: 8.2704782e-05 | W9: 8.2704782e-05 | X9: 8.2704782e-05 | Y9: 8.2704782e-05 | Z9: 8.2704782e-05 | AA9: 8.2704782e-05 | AB9: 8.2704782e-05 | AC9: 8.2704782e-05 | AD9: 8.2704782e-05 | AE9: 8.2704782e-05 | AF9: 8.2704782e-05 | AG9: 8.2704782e-05 | AH9: 8.2704782e-05 | AI9: 8.2704782e-05 | AJ9: 8.2704782e-05 | AK9: 8.2704782e-05
A10: phiy_cgas_soil_2 | B10: 0.64531659 | C10: 0.64531659 | D10: 0.64531659 | E10: 0.64531659 | F10: 0.64531659 | G10: 0.64531659 | H10: 0.64531659 | I10: 0.64531659 | J10: 0.64531659 | K10: 0.64531659 | L10: 0.64531659 | M10: 0.64531659 | N10: 0.64531659 | O10: 0.64531659 | P10: 0.64531659 | Q10: 0.64531659 | R10: 0.64531659 | S10: 0.64531659 | T10: 0.64531659 | U10: 0.64531659 | V10: 0.64531659 | W10: 0.64531659 | X10: 0.64531659 | Y10: 0.64531659 | Z10: 0.64531659 | AA10: 0.64531659 | AB10: 0.64531659 | AC10: 0.64531659 | AD10: 0.64531659 | AE10: 0.64531659 | AF10: 0.64531659 | AG10: 0.64531659 | AH10: 0.64531659 | AI10: 0.64531659 | AJ10: 0.64531659 | AK10: 0.64531659
A11: phiy_cgas_sgas_2 | B11: 0.14751432 | C11: 0.14751432 | D11: 0.14751432 | E11: 0.14751432 | F11: 0.14751432 | G11: 0.14751432 | H11: 0.14751432 | I11: 0.14751432 | J11: 0.14751432 | K11: 0.14751432 | L11: 0.14751432 | M11: 0.14751432 | N11: 0.14751432 | O11: 0.14751432 | P11: 0.14751432 | Q11: 0.14751432 | R11: 0.14751432 | S11: 0.14751432 | T11: 0.14751432 | U11: 0.14751432 | V11: 0.14751432 | W11: 0.14751432 | X11: 0.14751432 | Y11: 0.14751432 | Z11: 0.14751432 | AA11: 0.14751432 | AB11: 0.14751432 | AC11: 0.14751432 | AD11: 0.14751432 | AE11: 0.14751432 | AF11: 0.14751432 | AG11: 0.14751432 | AH11: 0.14751432 | AI11: 0.14751432 | AJ11: 0.14751432 | AK11: 0.14751432
A12: phiy_cgas_sbga_2 | B12: 0.20708639 | C12: 0.20708639 | D12: 0.20708639 | E12: 0.20708639 | F12: 0.20708639 | G12: 0.20708639 | H12: 0.20708639 | I12: 0.20708639 | J12: 0.20708639 | K12: 0.20708639 | L12: 0.20708639 | M12: 0.20708639 | N12: 0.20708639 | O12: 0.20708639 | P12: 0.20708639 | Q12: 0.20708639 | R12: 0.20708639 | S12: 0.20708639 | T12: 0.20708639 | U12: 0.20708639 | V12: 0.20708639 | W12: 0.20708639 | X12: 0.20708639 | Y12: 0.20708639 | Z12: 0.20708639 | AA12: 0.20708639 | AB12: 0.20708639 | AC12: 0.20708639 | AD12: 0.20708639 | AE12: 0.20708639 | AF12: 0.20708639 | AG12: 0.20708639 | AH12: 0.20708639 | AI12: 0.20708639 | AJ12: 0.20708639 | AK12: 0.20708639
... A51: phiy_cote_spub_0 | B51: 0.00010273909 | C51: 0.00010273909 | D51: 0.00010273909 | E51: 0.00010273909 | F51: 0.00010273909 | G51: 0.00010273909 | H51: 0.00010273909 | I51: 0.00010273909 | J51: 0.00010273909 | K51: 0.00010273909 | L51: 0.00010273909 | M51: 0.00010273909 | N51: 0.00010273909 | O51: 0.00010273909 | P51: 0.00010273909 | Q51: 0.00010273909 | R51: 0.00010273909 | S51: 0.00010273909 | T51: 0.00010273909 | U51: 0.00010273909 | V51: 0.00010273909 | W51: 0.00010273909 | X51: 0.00010273909 | Y51: 0.00010273909 | Z51: 0.00010273909 | AA51: 0.00010273909 | AB51: 0.00010273909 | AC51: 0.00010273909 | AD51: 0.00010273909 | AE51: 0.00010273909 | AF51: 0.00010273909 | AG51: 0.00010273909 | AH51: 0.00010273909 | AI51: 0.00010273909 | AJ51: 0.00010273909 | AK51: 0.00010273909

Sheet Transports
A1: _date_ | B1: 42005 | C1: 42370 | D1: 42736 | E1: 43101 | F1: 43466 | G1: 43831 | H1: 44197 | I1: 44562 | J1: 44927 | K1: 45292 | L1: 45658 | M1: 46023 | N1: 46388 | O1: 46753 | P1: 47119 | Q1: 47484 | R1: 47849 | S1: 48214 | T1: 48580 | U1: 48945 | V1: 49310 | W1: 49675 | X1: 50041 | Y1: 50406 | Z1: 50771 | AA1: 51136 | AB1: 51502 | AC1: 51867 | AD1: 52232 | AE1: 52597 | AF1: 52963 | AG1: 53328 | AH1: 53693 | AI1: 54058 | AJ1: 54424 | AK1: 54789
A2: km_traveler_cair_2 | B2: 291099.78 | C2: 295824.47 | D2: 300414.27 | E2: 304980.92 | F2: 309572.49 | G2: 314195.58 | H2: 318910.55 | I2: 323810.43 | J2: 328920.55 | K2: 334221.25 | L2: 339674.7 | M2: 345238.11 | N2: 350870.05 | O2: 356533.43 | P2: 362196.81 | Q2: 367834.87 | R2: 373482.28 | S2: 379217.63 | T2: 385087.37 | U2: 391111.98 | V2: 397299.02 | W2: 403649.7 | X2: 410162.24 | Y2: 416833.59 | Z2: 423660.22 | AA2: 430638.55 | AB2: 437765.03 | AC2: 445036.25 | AD2: 452449.08 | AE2: 460000.67 | AF2: 467688.59 | AG2: 475510.9 | AH2: 483466.26 | AI2: 491553.94 | AJ2: 499773.93 | AK2: 508126.88
A3: km_trav_auto_ld_2+km_trav_auto_sd_2 | B3: 724102.94 | C3: 715357.78 | D3: 710981.61 | E3: 709524.77 | F3: 710001.66 | G3: 711750.67 | H3: 714376.66 | I3: 717655.19 | J3: 721418.59 | K3: 725536.38 | L3: 729904.39 | M3: 734437.34 | N3: 739063.74 | O3: 743722.45 | P3: 748360.39 | Q3: 752931.09 | R3: 757433.37 | S3: 761901.38 | T3: 766353.11 | U3: 770796.71 | V3: 775235.5 | W3: 779670.68 | X3: 784102.62 | Y3: 788531.46 | Z3: 792957.42 | AA3: 797380.85 | AB3: 801802.34 | AC3: 806222.68 | AD3: 810642.95 | AE3: 815064.46 | AF3: 819488.83 | AG3: 823918.03 | AH3: 828354.32 | AI3: 832800.36 | AJ3: 837259.14 | AK3: 841734.02
A4: km_traveler_sd_2 | B4: 624600.34 | C4: 618863.5 | D4: 616093.94 | E4: 615338.85 | F4: 615931.37 | G4: 617415.86 | H4: 619516.89 | I4: 622077.74 | J4: 624981.65 | K4: 628136.6 | L4: 631468.49 | M4: 634916.36 | N4: 638428.97 | O4: 641962.52 | P4: 645479.09 | Q4: 648945.59 | R4: 652360.59 | S4: 655748.29 | T4: 659122.31 | U4: 662488.95 | V4: 665850.85 | W4: 669209.02 | X4: 672563.77 | Y4: 675915.2 | Z4: 679263.4 | AA4: 682608.58 | AB4: 685951.06 | AC4: 689291.33 | AD4: 692630.04 | AE4: 695968.06 | AF4: 699306.45 | AG4: 702646.5 | AH4: 705989.76 | AI4: 709338.02 | AJ4: 712693.34 | AK4: 716058.04
A5: km_trav_auto_sd_2 | B5: 554271.64 | C5: 547923.45 | D5: 544697.79 | E5: 543558.63 | F5: 543800.31 | G5: 544948.61 | H5: 546720.24 | I5: 548954.26 | J5: 551530.51 | K5: 554355.56 | L5: 557354.86 | M5: 560467.46 | N5: 563642.33 | O5: 566835.94 | P5: 570010.62 | Q5: 573133.48 | R5: 576203.9 | S5: 579246.35 | T5: 582273.81 | U5: 585292.2 | V5: 588304.01 | W5: 591310.15 | X5: 594310.94 | Y5: 597306.54 | Z5: 600297.14 | AA5: 603283.06 | AB5: 606264.76 | AC5: 609242.87 | AD5: 612218.2 | AE5: 615191.73 | AF5: 618164.65 | AG5: 621138.36 | AH5: 624114.5 | AI5: 627094.93 | AJ5: 630081.77 | AK5: 633077.35
A6: km_traveler_croa_2 | B6: 70328.7 | C6: 70321.744 | D6: 70422.436 | E6: 70598.454 | F6: 70826.65 | G6: 71090.912 | H6: 71380.915 | I6: 71691.093 | J6: 72017.763 | K6: 72357.465 | L6: 72707.078 | M6: 73063.802 | N6: 73425.148 | O6: 73788.904 | P6: 74153.118 | Q6: 74516.062 | R6: 74877.171 | S6: 75237.411 | T6: 75597.805 | U6: 75958.843 | V6: 76320.752 | W6: 76683.615 | X6: 77047.438 | Y6: 77412.183 | Z6: 77777.794 | AA6: 78144.207 | AB6: 78511.359 | AC6: 78879.19 | AD6: 79247.651 | AE6: 79616.708 | AF6: 79986.342 | AG6: 80356.555 | AH6: 80727.372 | AI6: 81098.844 | AJ6: 81471.044 | AK6: 81844.074
A7: km_traveler_ld_2 | B7: 275159.81 | C7: 270793.5 | D7: 268634.41 | E7: 267938.57 | F7: 268208.84 | G7: 269114.96 | H7: 270461.01 | I7: 272135.84 | J7: 274056.24 | K7: 276157.73 | L7: 278389 | M7: 280708.05 | N7: 283079.56 | O7: 285473.21 | P7: 287862.48 | Q7: 290223.97 | R7: 292557.01 | S7: 294878.43 | T7: 297196.71 | U7: 299515.54 | V7: 301836.38 | W7: 304159.66 | X7: 306485.48 | Y7: 308813.84 | Z7: 311144.79 | AA7: 313478.48 | AB7: 315815.14 | AC7: 318155.13 | AD7: 320498.97 | AE7: 322847.28 | AF7: 325200.87 | AG7: 327560.71 | AH7: 329927.98 | AI7: 332304.03 | AJ7: 334690.43 | AK7: 337088.96
A8: km_trav_auto_ld_2 | B8: 169831.3 | C8: 167434.33 | D8: 166283.82 | E8: 165966.14 | F8: 166201.36 | G8: 166802.06 | H8: 167656.42 | I8: 168700.93 | J8: 169888.08 | K8: 171180.82 | L8: 172549.53 | M8: 173969.88 | N8: 175421.41 | O8: 176886.51 | P8: 178349.76 | Q8: 179797.61 | R8: 181229.47 | S8: 182655.03 | T8: 184079.31 | U8: 185504.5 | V8: 186931.48 | W8: 188360.53 | X8: 189791.68 | Y8: 191224.93 | Z8: 192660.28 | AA8: 194097.79 | AB8: 195537.58 | AC8: 196979.81 | AD8: 198424.75 | AE8: 199872.73 | AF8: 201324.19 | AG8: 202779.67 | AH8: 204239.82 | AI8: 205705.43 | AJ8: 207177.37 | AK8: 208656.68
A9: km_traveler_crai_2 | B9: 105328.51 | C9: 106469.49 | D9: 107456.01 | E9: 108340.75 | F9: 109162.53 | G9: 109948.54 | H9: 110713.45 | I9: 111466.78 | J9: 112217.49 | K9: 112970.62 | L9: 113729.07 | M9: 114494.38 | N9: 115267.36 | O9: 116048.38 | P9: 116837.6 | Q9: 117635.07 | R9: 118438.84 | S9: 119247.58 | T9: 120062.32 | U9: 120883.54 | V9: 121711.51 | W9: 122546.33 | X9: 123387.94 | Y9: 124236.16 | Z9: 125090.73 | AA9: 125951.37 | AB9: 126817.72 | AC9: 127689.44 | AD9: 128566.18 | AE9: 129447.58 | AF9: 130333.33 | AG9: 131223.16 | AH9: 132116.82 | AI9: 133014.14 | AJ9: 133914.96 | AK9: 134819.23
A10: km_traveler_cair_0 | B10: 291099.78 | C10: 295997.44 | D10: 300860.61 | E10: 305754.88 | F10: 310735.66 | G10: 315838.96 | H10: 321084.31 | I10: 326479.86 | J10: 332026.96 | K10: 337723.35 | L10: 343565.4 | M10: 349549.32 | N10: 355671.93 | O10: 361930.82 | P10: 368324.44 | Q10: 374851.94 | R10: 381513.03 | S10: 388307.75 | T10: 395236.36 | U10: 402299.23 | V10: 409496.72 | W10: 416829.19 | X10: 424297 | Y10: 431900.48 | Z10: 439640.02 | AA10: 447516.04 | AB10: 455529.1 | AC10: 463679.89 | AD10: 471969.28 | AE10: 480398.31 | AF10: 488968.27 | AG10: 497680.64 | AH10: 506537.12 | AI10: 515539.66 | AJ10: 524690.39 | AK10: 533991.65
A11: km_trav_auto_ld_0+km_trav_auto_sd_0 | B11: 724102.94 | C11: 715470.96 | D11: 711264.17 | E11: 710013.52 | F11: 710740.21 | G11: 712802.83 | H11: 715783.55 | I11: 719409 | J11: 723497.85 | K11: 727927.14 | L11: 732611.21 | M11: 737488.53 | N11: 742513.6 | O11: 747651.94 | P11: 752876.85 | Q11: 758167.33 | R11: 763506.69 | S11: 768881.53 | T11: 774281.05 | U11: 779696.54 | V11: 785120.94 | W11: 790548.57 | X11: 795974.88 | Y11: 801396.29 | Z11: 806810.03 | AA11: 812214.02 | AB11: 817606.82 | AC11: 822987.5 | AD11: 828355.6 | AE11: 833711.09 | AF11: 839054.26 | AG11: 844385.75 | AH11: 849706.42 | AI11: 855017.36 | AJ11: 860319.87 | AK11: 865615.33
A12: km_traveler_sd_0 | B12: 624600.34 | C12: 618939.61 | D12: 616289.44 | E12: 615681.22 | F12: 616451.95 | G12: 618159.91 | H12: 620514.29 | I12: 623323.46 | J12: 626459.53 | K12: 629835.38 | L12: 633389.98 | M12: 637079.36 | N12: 640870.93 | O12: 644739.98 | P12: 648667.38 | Q12: 652638.14 | R12: 656640.39 | S12: 660664.65 | T12: 664703.32 | U12: 668750.31 | V12: 672800.7 | W12: 676850.59 | X12: 680896.84 | Y12: 684937.01 | Z12: 688969.24 | AA12: 692992.15 | AB12: 697004.79 | AC12: 701006.58 | AD12: 704997.26 | AE12: 708976.87 | AF12: 712945.68 | AG12: 716904.19 | AH12: 720853.04 | AI12: 724793.07 | AJ12: 728725.2 | AK12: 732650.46
... A17: km_traveler_crai_0 | B17: 105328.51 | C17: 106459.91 | D17: 107439.19 | E17: 108316.26 | F17: 109128.73 | G17: 109902.85 | H17: 110656.13 | I17: 111399.76 | J17: 112140.59 | K17: 112882.66 | L17: 113628.2 | M17: 114378.44 | N17: 115134.04 | O17: 115895.36 | P17: 116662.67 | Q17: 117436.16 | R17: 118216.02 | S17: 119002.41 | T17: 119795.47 | U17: 120595.32 | V17: 121402.02 | W17: 122215.62 | X17: 123036.12 | Y17: 123863.49 | Z17: 124697.68 | AA17: 125538.64 | AB17: 126386.3 | AC17: 127240.59 | AD17: 128101.43 | AE17: 128968.78 | AF17: 129842.6 | AG17: 130722.83 | AH17: 131609.47 | AI17: 132502.5 | AJ17: 133401.93 | AK17: 134307.77

Sheet Hybrid
A1: _date_ | B1: 42005 | C1: 42370 | D1: 42736 | E1: 43101 | F1: 43466 | G1: 43831 | H1: 44197 | I1: 44562 | J1: 44927 | K1: 45292 | L1: 45658 | M1: 46023 | N1: 46388 | O1: 46753 | P1: 47119 | Q1: 47484 | R1: 47849 | S1: 48214 | T1: 48580 | U1: 48945 | V1: 49310 | W1: 49675 | X1: 50041 | Y1: 50406 | Z1: 50771 | AA1: 51136 | AB1: 51502 | AC1: 51867 | AD1: 52232 | AE1: 52597 | AF1: 52963 | AG1: 53328 | AH1: 53693 | AI1: 54058 | AJ1: 54424 | AK1: 54789
A2: auto_2 | B2: 32317.941 | C2: 31926.557 | D2: 31730.857 | E2: 31665.91 | F2: 31687.577 | G2: 31766.229 | H2: 31884.17 | I2: 32031.35 | J2: 32200.261 | K2: 32385.058 | L2: 32581.077 | M2: 32784.497 | N2: 32992.117 | O2: 33201.198 | P2: 33409.361 | Q2: 33614.524 | R2: 33816.633 | S2: 34017.219 | T2: 34217.085 | U2: 34416.597 | V2: 34615.904 | W2: 34815.059 | X2: 35014.078 | Y2: 35212.967 | Z2: 35411.737 | AA2: 35610.402 | AB2: 35808.989 | AC2: 36007.533 | AD2: 36206.082 | AE2: 36404.695 | AF2: 36603.445 | AG2: 36802.419 | AH2: 37001.719 | AI2: 37201.464 | AJ2: 37401.788 | AK2: 37602.841
A3: auto_cfut_2 | B3: 32271.24 | C3: 31862.134 | D3: 31647.786 | E3: 31563.667 | F3: 31565.852 | G3: 31624.781 | H3: 31722.707 | I3: 31849.465 | J3: 31997.438 | K3: 32160.665 | L3: 32334.348 | M3: 32514.508 | N3: 32697.737 | O3: 32881.038 | P3: 33061.706 | Q3: 33237.241 | R3: 33407.054 | S3: 33572.057 | T3: 33732.416 | U3: 33887.84 | V3: 34037.795 | W3: 34181.626 | X3: 34318.615 | Y3: 34448.005 | Z3: 34569.015 | AA3: 34680.838 | AB3: 34782.648 | AC3: 34873.601 | AD3: 34952.833 | AE3: 35019.462 | AF3: 35072.592 | AG3: 35111.316 | AH3: 35134.716 | AI3: 35141.87 | AJ3: 35131.851 | AK3: 35103.736
A4: auto_cele_2 | B4: 44.765 | C4: 62.431907 | D4: 81.013139 | E4: 100.11448 | F4: 119.52341 | G4: 139.17166 | H4: 159.11464 | I4: 179.46535 | J4: 200.33426 | K4: 221.83724 | L4: 244.10709 | M4: 267.30561 | N4: 291.63617 | O4: 317.35712 | P4: 344.79711 | Q4: 374.37303 | R4: 406.61981 | S4: 442.15555 | T4: 481.61718 | U4: 525.66278 | V4: 574.97426 | W4: 630.25925 | X4: 692.25252 | Y4: 761.71694 | Z4: 839.44438 | AA4: 926.25625 | AB4: 1023.0039 | AC4: 1130.5688 | AD4: 1249.8619 | AE4: 1381.8239 | AF4: 1527.423 | AG4: 1687.6546 | AH4: 1863.5384 | AI4: 2056.1159 | AJ4: 2266.4472 | AK4: 2495.6066
A5: auto_cgas_2 | B5: 1.936 | C5: 1.9916142 | D5: 2.0574397 | E5: 2.1286903 | F5: 2.2021882 | G5: 2.2758741 | H5: 2.3486159 | I5: 2.4198739 | J5: 2.4892892 | K5: 2.556615 | L5: 2.6216785 | M5: 2.6843552 | N5: 2.7445503 | O5: 2.8021872 | P5: 2.8571989 | Q5: 2.9095223 | R5: 2.9592424 | S5: 3.0065611 | T5: 3.0516111 | U5: 3.0944792 | V5: 3.1352247 | W5: 3.1738896 | X5: 3.2105034 | Y5: 3.2450861 | Z5: 3.2776492 | AA5: 3.3081965 | AB5: 3.3367245 | AC5: 3.363223 | AD5: 3.3876753 | AE5: 3.4100585 | AF5: 3.4303443 | AG5: 3.4484993 | AH5: 3.4644855 | AI5: 3.4782606 | AJ5: 3.4897789 | AK5: 3.4989915
A6: newauto_2 | B6: 1886.229 | C6: 2121.9086 | D6: 2286.4648 | E6: 2401.2849 | F6: 2482.1212 | G6: 2540.0565 | H6: 2584.7231 | I6: 2622.3847 | J6: 2654.7983 | K6: 2683.0392 | L6: 2707.8273 | M6: 2729.6403 | N6: 2748.7918 | O6: 2765.4882 | P6: 2779.868 | Q6: 2792.0289 | R6: 2803.822 | S6: 2816.8059 | T6: 2830.3521 | U6: 2844.0583 | V6: 2857.7128 | W6: 2871.2053 | X6: 2884.4763 | Y6: 2897.4897 | Z6: 2910.2194 | AA6: 2922.6436 | AB6: 2934.7417 | AC6: 2946.4939 | AD6: 2957.881 | AE6: 2968.8842 | AF6: 2979.4859 | AG6: 2989.6697 | AH6: 2999.4199 | AI6: 3008.7219 | AJ6: 3017.5618 | AK6: 3025.9258
A7: newauto_cfut_2 | B7: 1868.803 | C7: 2102.2745 | D7: 2265.1959 | E7: 2378.7432 | F7: 2458.5011 | G7: 2515.416 | H7: 2558.9983 | I7: 2595.4514 | J7: 2626.5301 | K7: 2653.2999 | L7: 2676.4591 | M7: 2696.4509 | N7: 2713.5411 | O7: 2727.8726 | P7: 2739.5036 | Q7: 2748.4302 | R7: 2756.3688 | S7: 2764.7731 | T7: 2772.9713 | U7: 2780.5145 | V7: 2787.1406 | W7: 2792.6867 | X7: 2797.0377 | Y7: 2800.0999 | Z7: 2801.7879 | AA7: 2802.0185 | AB7: 2800.7085 | AC7: 2797.7739 | AD7: 2793.1304 | AE7: 2786.6937 | AF7: 2778.3804 | AG7: 2768.1086 | AH7: 2755.7984 | AI7: 2741.3725 | AJ7: 2724.7569 | AK7: 2705.8813
A8: newauto_cele_2 | B8: 17.269 | C8: 19.457507 | D8: 21.078508 | E8: 22.341869 | F8: 23.413511 | G8: 24.429183 | H8: 25.509845 | I8: 26.715298 | J8: 28.047521 | K8: 29.51635 | L8: 31.143338 | M8: 32.962809 | N8: 35.022778 | O8: 37.3864 | P8: 40.134271 | Q8: 43.36781 | R8: 47.2217 | S8: 51.800529 | T8: 57.147857 | U8: 63.310287 | V8: 70.337986 | W8: 78.283966 | X8: 87.203633 | Y8: 97.154524 | Z8: 108.19612 | AA8: 120.38965 | AB8: 133.79791 | AC8: 148.48499 | AD8: 164.51594 | AE8: 181.95639 | AF8: 200.87213 | AG8: 221.32853 | AH8: 243.38996 | AI8: 267.11906 | AJ8: 292.57593 | AK8: 319.81722
A9: newauto_cgas_2 | B9: 0.157 | C9: 0.17661418 | D9: 0.19030137 | E9: 0.19984059 | F9: 0.20654113 | G9: 0.2113226 | H9: 0.214984 | I9: 0.21804646 | J9: 0.22065741 | K9: 0.22290637 | L9: 0.22485199 | M9: 0.22653153 | N9: 0.22796729 | O9: 0.2291713 | P9: 0.23014842 | Q9: 0.23089836 | R9: 0.23156528 | S9: 0.23227134 | T9: 0.23296008 | U9: 0.23359379 | V9: 0.23415046 | W9: 0.23461639 | X9: 0.23498192 | Y9: 0.23523918 | Z9: 0.23538099 | AA9: 0.23540036 | AB9: 0.23529031 | AC9: 0.23504377 | AD9: 0.23465366 | AE9: 0.23411291 | AF9: 0.2334145 | AG9: 0.23255156 | AH9: 0.23151737 | AI9: 0.23030544 | AJ9: 0.22890954 | AK9: 0.22732378
A10: auto_0 | B10: 32317.941 | C10: 31931.625 | D10: 31743.508 | E10: 31687.792 | F10: 31720.643 | G10: 31813.337 | H10: 31947.162 | I10: 32109.877 | J10: 32293.361 | K10: 32492.109 | L10: 32702.282 | M10: 32921.126 | N10: 33146.603 | O10: 33377.168 | P10: 33611.625 | Q10: 33849.033 | R10: 34088.645 | S10: 34329.861 | T10: 34572.195 | U10: 34815.259 | V10: 35058.734 | W10: 35302.368 | X10: 35545.956 | Y10: 35789.336 | Z10: 36032.386 | AA10: 36275.011 | AB10: 36517.147 | AC10: 36758.751 | AD10: 36999.804 | AE10: 37240.303 | AF10: 37480.262 | AG10: 37719.709 | AH10: 37958.683 | AI10: 38197.232 | AJ10: 38435.414 | AK10: 38673.292
A11: auto_cfut_0 | B11: 32271.24 | C11: 31867.185 | D11: 31660.486 | E11: 31585.838 | F11: 31599.721 | G11: 31673.603 | H11: 31788.887 | I11: 31933.397 | J11: 32099.044 | K11: 32280.337 | L11: 32473.442 | M11: 32675.598 | N11: 32884.76 | O11: 33099.37 | P11: 33318.22 | Q11: 33540.352 | R11: 33765.004 | S11: 33991.56 | T11: 34219.518 | U11: 34448.472 | V11: 34678.087 | W11: 34908.092 | X11: 35138.266 | Y11: 35368.429 | Z11: 35598.44 | AA11: 35828.186 | AB11: 36057.582 | AC11: 36286.569 | AD11: 36515.105 | AE11: 36743.166 | AF11: 36970.745 | AG11: 37197.847 | AH11: 37424.486 | AI11: 37650.688 | AJ11: 37876.482 | AK11: 38101.905
A12: auto_cele_0 | B12: 44.765 | C12: 62.448716 | D12: 80.963971 | E12: 99.823967 | F12: 118.71772 | G12: 137.4542 | H12: 155.92054 | I12: 174.05324 | J12: 191.81931 | K12: 209.20456 | L12: 226.20631 | M12: 242.829 | N12: 259.08157 | O12: 274.97577 | P12: 290.52522 | Q12: 305.74472 | R12: 320.64986 | S12: 335.2568 | T12: 349.58202 | U12: 363.64234 | V12: 377.45479 | W12: 391.03665 | X12: 404.40544 | Y12: 417.57898 | Z12: 430.57544 | AA12: 443.4134 | AB12: 456.1119 | AC12: 468.69057 | AD12: 481.16965 | AE12: 493.57013 | AF12: 505.91381 | AG12: 518.22339 | AH12: 530.52261 | AI12: 542.83631 | AJ12: 555.19057 | AK12: 567.61281
... A121: buil_des_0 | B121: 1.1716777 | C121: 1.1716777 | D121: 1.1565402 | E121: 1.1416083 | F121: 1.1268791 | G121: 1.1123494 | H121: 1.0980163 | I121: 1.083877 | J121: 1.0699286 | K121: 1.0561683 | L121: 1.0425934 | M121: 1.0292012 | N121: 1.0159892 | O121: 1.0029547 | P121: 0.99009523 | Q121: 0.97740825 | R121: 0.96489133 | S121: 0.95254204 | T121: 0.940358 | U121: 0.92833689 | V121: 0.91647639 | W121: 0.90477425 | X121: 0.89322823 | Y121: 0.88183615 | Z121: 0.87059586 | AA121: 0.85950523 | AB121: 0.84856218 | AC121: 0.83776466 | AD121: 0.82711064 | AE121: 0.81659814 | AF121: 0.8062252 | AG121: 0.7959899 | AH121: 0.78589034 | AI121: 0.77592465 | AJ121: 0.766091 | AK121: 0.75638758

Sheet Tab-macro
B1: en écart au scénario de référence (%)
B2: ThreeME
B3: 2021 | C3: 2022 | D3: 2023 | E3: 2025 | F3: 2030 | G3: 2050
A4: PIB en volume | B4: =Macro!H2 -> 0.043977897 | C4: =Macro!I2 -> 0.053197441 | D4: =Macro!J2 -> 0.06077257 | E4: =Macro!L2 -> 0.071590899 | F4: =Macro!Q2 -> 0.10779222 | G4: =Macro!AK2 -> 0.092527927
A5: Consommation des ménages | B5: =Macro!H3 -> 0.057312129 | C5: =Macro!I3 -> 0.068895137 | D5: =Macro!J3 -> 0.078189304 | E5: =Macro!L3 -> 0.090983963 | F5: =Macro!Q3 -> 0.1333572 | G5: =Macro!AK3 -> 0.092610725
A6: Investissement | B6: =Macro!H4 -> 0.056354808 | C6: =Macro!I4 -> 0.074505579 | D6: =Macro!J4 -> 0.093292264 | E6: =Macro!L4 -> 0.13097622 | F6: =Macro!Q4 -> 0.251302 | G6: =Macro!AK4 -> 0.87413578
A7: Exportations | B7: =Macro!H5 -> -0.021358905 | C7: =Macro!I5 -> -0.023215848 | D7: =Macro!J5 -> -0.023920076 | E7: =Macro!L5 -> -0.025318646 | F7: =Macro!Q5 -> -0.048749124 | G7: =Macro!AK5 -> -0.14832736
A8: Importations | B8: =Macro!H6 -> 0 | C8: =Macro!I6 -> 0 | D8: =Macro!J6 -> 0 | E8: =Macro!L6 -> 0 | F8: =Macro!Q6 -> 0 | G8: =Macro!AK6 -> 0
A9: Revenu disponible (réel) des ménages | B9: =Macro!H7 -> -0.011514503 | C9: =Macro!I7 -> -0.01440095 | D9: =Macro!J7 -> -0.017188316 | E9: =Macro!L7 -> -0.02273525 | F9: =Macro!Q7 -> -0.040282986 | G9: =Macro!AK7 -> -0.13122817
A10: Taux d'épargne (en pts) | B10: =Macro!H8 -> 0 | C10: =Macro!I8 -> 0 | D10: =Macro!J8 -> 0 | E10: =Macro!L8 -> 0 | F10: =Macro!Q8 -> 0 | G10: =Macro!AK8 -> 0
A11: Prix de la consommation des ménages | B11: =Macro!H9 -> -0.00086242969 | C11: =Macro!I9 -> -0.0069071843 | D11: =Macro!J9 -> -0.015331408 | E11: =Macro!L9 -> -0.036650067 | F11: =Macro!Q9 -> -0.10322679 | G11: =Macro!AK9 -> -0.65037971
A12: Prix de la production | B12: =Macro!H10 -> 0.055394955 | C12: =Macro!I10 -> 0.073280475 | D12: =Macro!J10 -> 0.091798039 | E12: =Macro!L10 -> 0.12891602 | F12: =Macro!Q10 -> 0.24718579 | G12: =Macro!AK10 -> 0.86008434
A13: Prix de la valeur ajoutée | B13: =Macro!H11 -> -0.01055465 | C13: =Macro!I11 -> -0.013175845 | D13: =Macro!J11 -> -0.015694091 | E13: =Macro!L11 -> -0.020675046 | F13: =Macro!Q11 -> -0.036166778 | G13: =Macro!AK11 -> -0.11717673
A14: Prix des consommations intermédiaires | B14: =Macro!H12 -> -0.010016326 | C14: =Macro!I12 -> -0.012530075 | D14: =Macro!J12 -> -0.014964201 | E14: =Macro!L12 -> -0.019843385 | F14: =Macro!Q12 -> -0.035300329 | G14: =Macro!AK12 -> -0.11548069
A15: Prix des exportations | B15: =Macro!H13 -> 0.00095985353 | C15: =Macro!I13 -> 0.0012251047 | D15: =Macro!J13 -> 0.0014942249 | E15: =Macro!L13 -> 0.0020602039 | F15: =Macro!Q13 -> 0.0041162074 | G15: =Macro!AK13 -> 0.01405144
... A24: Emissions de CO2 | B24: =Macro!H22 -> 0.10268485 | C24: =Macro!I22 -> 0.13587103 | D24: =Macro!J22 -> 0.1702411 | E24: =Macro!L22 -> 0.23914873 | F24: =Macro!Q22 -> 0.45858707 | G24: =Macro!AK22 -> 1.5926979
B26: % deviation from baseline
B27: ThreeME
B28: 2021 | C28: 2022 | D28: 2023 | E28: 2025 | F28: 2030 | G28: 2050
A29: GDP in volume | B29: =B4 -> 0.043977897 | C29: =C4 -> 0.053197441 | D29: =D4 -> 0.06077257 | E29: =E4 -> 0.071590899 | F29: =F4 -> 0.10779222 | G29: =G4 -> 0.092527927
A30: Household consumption | B30: =B5 -> 0.057312129 | C30: =C5 -> 0.068895137 | D30: =D5 -> 0.078189304 | E30: =E5 -> 0.090983963 | F30: =F5 -> 0.1333572 | G30: =G5 -> 0.092610725
A31: Investment | B31: =B6 -> 0.056354808 | C31: =C6 -> 0.074505579 | D31: =D6 -> 0.093292264 | E31: =E6 -> 0.13097622 | F31: =F6 -> 0.251302 | G31: =G6 -> 0.87413578
A32: Exports | B32: =B7 -> -0.021358905 | C32: =C7 -> -0.023215848 | D32: =D7 -> -0.023920076 | E32: =E7 -> -0.025318646 | F32: =F7 -> -0.048749124 | G32: =G7 -> -0.14832736
A33: Imports | B33: =B8 -> 0 | C33: =C8 -> 0 | D33: =D8 -> 0 | E33: =E8 -> 0 | F33: =F8 -> 0 | G33: =G8 -> 0
A34: Household disposable income (real) | B34: =B9 -> -0.011514503 | C34: =C9 -> -0.01440095 | D34: =D9 -> -0.017188316 | E34: =E9 -> -0.02273525 | F34: =F9 -> -0.040282986 | G34: =G9 -> -0.13122817
A35: Saving rate (in points) | B35: =B10 -> 0 | C35: =C10 -> 0 | D35: =D10 -> 0 | E35: =E10 -> 0 | F35: =F10 -> 0 | G35: =G10 -> 0
A36: Household consumption price index | B36: =B11 -> -0.00086242969 | C36: =C11 -> -0.0069071843 | D36: =D11 -> -0.015331408 | E36: =E11 -> -0.036650067 | F36: =F11 -> -0.10322679 | G36: =G11 -> -0.65037971
A37: Production price index | B37: =B12 -> 0.055394955 | C37: =C12 -> 0.073280475 | D37: =D12 -> 0.091798039 | E37: =E12 -> 0.12891602 | F37: =F12 -> 0.24718579 | G37: =G12 -> 0.86008434
A38: Added value price index | B38: =B13 -> -0.01055465 | C38: =C13 -> -0.013175845 | D38: =D13 -> -0.015694091 | E38: =E13 -> -0.020675046 | F38: =F13 -> -0.036166778 | G38: =G13 -> -0.11717673
A39: Intermediate consumption price index | B39: =B14 -> -0.010016326 | C39: =C14 -> -0.012530075 | D39: =D14 -> -0.014964201 | E39: =E14 -> -0.019843385 | F39: =F14 -> -0.035300329 | G39: =G14 -> -0.11548069
A40: Export price index | B40: =B15 -> 0.00095985353 | C40: =C15 -> 0.0012251047 | D40: =D15 -> 0.0014942249 | E40: =E15 -> 0.0020602039 | F40: =F15 -> 0.0041162074 | G40: =G15 -> 0.01405144
... A49: CO2 emissions | B49: =B24 -> 0.10268485 | C49: =C24 -> 0.13587103 | D49: =D24 -> 0.1702411 | E49: =E24 -> 0.23914873 | F49: =F24 -> 0.45858707 | G49: =G24 -> 1.5926979

Sheet Tab-baseline
C1: 8 | D1: 9 | E1: 10 | F1: 12 | G1: 17 | H1: 37
C2: ThreeME
C3: 2021 | D3: 2022 | E3: 2023 | F3: 2025 | G3: 2030 | H3: 2050
A4: Taux de croissance du PIB | B4: @pch(gdp_0) | C4: =VLOOKUP($B4,Baseline!$A$1:$AT$50,C$1,FALSE) -> 0.011252093 | D4: =VLOOKUP($B4,Baseline!$A$1:$AT$50,D$1,FALSE) -> 0.011375473 | E4: =VLOOKUP($B4,Baseline!$A$1:$AT$50,E$1,FALSE) -> 0.011476236 | F4: =VLOOKUP($B4,Baseline!$A$1:$AT$50,F$1,FALSE) -> 0.011614092 | G4: =VLOOKUP($B4,Baseline!$A$1:$AT$50,G$1,FALSE) -> 0.011726136 | H4: =VLOOKUP($B4,Baseline!$A$1:$AT$50,H$1,FALSE) -> 0.011660368
A5: Prix de la consommation des ménages | B5: @pch(pch_0) | C5: =VLOOKUP($B5,Baseline!$A$1:$AT$50,C$1,FALSE) -> 0.019635206 | D5: =VLOOKUP($B5,Baseline!$A$1:$AT$50,D$1,FALSE) -> 0.019668198 | E5: =VLOOKUP($B5,Baseline!$A$1:$AT$50,E$1,FALSE) -> 0.019714317 | F5: =VLOOKUP($B5,Baseline!$A$1:$AT$50,F$1,FALSE) -> 0.019828898 | G5: =VLOOKUP($B5,Baseline!$A$1:$AT$50,G$1,FALSE) -> 0.020129185 | H5: =VLOOKUP($B5,Baseline!$A$1:$AT$50,H$1,FALSE) -> 0.020366929
A6: Taux de chômage | B6: unr_0 | C6: =VLOOKUP($B6,Baseline!$A$1:$AT$50,C$1,FALSE) -> 0.14415906 | D6: =VLOOKUP($B6,Baseline!$A$1:$AT$50,D$1,FALSE) -> 0.14419204 | E6: =VLOOKUP($B6,Baseline!$A$1:$AT$50,E$1,FALSE) -> 0.14412979 | F6: =VLOOKUP($B6,Baseline!$A$1:$AT$50,F$1,FALSE) -> 0.14381068 | G6: =VLOOKUP($B6,Baseline!$A$1:$AT$50,G$1,FALSE) -> 0.14261895 | H6: =VLOOKUP($B6,Baseline!$A$1:$AT$50,H$1,FALSE) -> 0.13887513
A7: Dette publique (en pts de PIB) | B7: rdebt_g_val_0 | C7: =VLOOKUP($B7,Baseline!$A$1:$AT$50,C$1,FALSE) -> 0.97004802 | D7: =VLOOKUP($B7,Baseline!$A$1:$AT$50,D$1,FALSE) -> 0.97258712 | E7: =VLOOKUP($B7,Baseline!$A$1:$AT$50,E$1,FALSE) -> 0.97503146 | F7: =VLOOKUP($B7,Baseline!$A$1:$AT$50,F$1,FALSE) -> 0.97946806 | G7: =VLOOKUP($B7,Baseline!$A$1:$AT$50,G$1,FALSE) -> 0.98723106 | H7: =VLOOKUP($B7,Baseline!$A$1:$AT$50,H$1,FALSE) -> 0.97986829
A8: Solde primaire public (en pts de PIB) | B8: rbal_g_prim_val_0 | C8: =VLOOKUP($B8,Baseline!$A$1:$AT$50,C$1,FALSE) -> -0.011460251 | D8: =VLOOKUP($B8,Baseline!$A$1:$AT$50,D$1,FALSE) -> -0.011637088 | E8: =VLOOKUP($B8,Baseline!$A$1:$AT$50,E$1,FALSE) -> -0.011732353 | F8: =VLOOKUP($B8,Baseline!$A$1:$AT$50,F$1,FALSE) -> -0.011733134 | G8: =VLOOKUP($B8,Baseline!$A$1:$AT$50,G$1,FALSE) -> -0.011177481 | H8: =VLOOKUP($B8,Baseline!$A$1:$AT$50,H$1,FALSE) -> -0.00849113
A9: Balance commerciale (en pts de PIB) | B9: rbal_trade_val_0 | C9: =VLOOKUP($B9,Baseline!$A$1:$AT$50,C$1,FALSE) -> -0.01277292 | D9: =VLOOKUP($B9,Baseline!$A$1:$AT$50,D$1,FALSE) -> -0.012784957 | E9: =VLOOKUP($B9,Baseline!$A$1:$AT$50,E$1,FALSE) -> -0.012769054 | F9: =VLOOKUP($B9,Baseline!$A$1:$AT$50,F$1,FALSE) -> -0.012698368 | G9: =VLOOKUP($B9,Baseline!$A$1:$AT$50,G$1,FALSE) -> -0.012442025 | H9: =VLOOKUP($B9,Baseline!$A$1:$AT$50,H$1,FALSE) -> -0.011138905
A10: Emissions de CO2 (en Kt CO2) | B10: ems_co2_0 | C10: =VLOOKUP($B10,Baseline!$A$1:$AT$50,C$1,FALSE) -> 362.04263 | D10: =VLOOKUP($B10,Baseline!$A$1:$AT$50,D$1,FALSE) -> 364.51423 | E10: =VLOOKUP($B10,Baseline!$A$1:$AT$50,E$1,FALSE) -> 367.1103 | F10: =VLOOKUP($B10,Baseline!$A$1:$AT$50,F$1,FALSE) -> 372.57878 | G10: =VLOOKUP($B10,Baseline!$A$1:$AT$50,G$1,FALSE) -> 387.32088 | H10: =VLOOKUP($B10,Baseline!$A$1:$AT$50,H$1,FALSE) -> 457.40889
C33: ThreeME
C34: 2021 | D34: 2022 | E34: 2023 | F34: 2025 | G34: 2030 | H34: 2050
A35: GDP growth rate | C35: =C4 -> 0.011252093 | D35: =D4 -> 0.011375473 | E35: =E4 -> 0.011476236 | F35: =F4 -> 0.011614092 | G35: =G4 -> 0.011726136 | H35: =H4 -> 0.011660368
A36: Household consumption price | C36: =C5 -> 0.019635206 | D36: =D5 -> 0.019668198 | E36: =E5 -> 0.019714317 | F36: =F5 -> 0.019828898 | G36: =G5 -> 0.020129185 | H36: =H5 -> 0.020366929
A37: unemployment rate | C37: =C6 -> 0.14415906 | D37: =D6 -> 0.14419204 | E37: =E6 -> 0.14412979 | F37: =F6 -> 0.14381068 | G37: =G6 -> 0.14261895 | H37: =H6 -> 0.13887513
A38: Public debt (in points of GDP) | C38: =C7 -> 0.97004802 | D38: =D7 -> 0.97258712 | E38: =E7 -> 0.97503146 | F38: =F7 -> 0.97946806 | G38: =G7 -> 0.98723106 | H38: =H7 -> 0.97986829
A39: Public budget balance (in points of GDP) | C39: =C8 -> -0.011460251 | D39: =D8 -> -0.011637088 | E39: =E8 -> -0.011732353 | F39: =F8 -> -0.011733134 | G39: =G8 -> -0.011177481 | H39: =H8 -> -0.00849113
A40: Trade balance (in points of GDP) | C40: =C9 -> -0.01277292 | D40: =D9 -> -0.012784957 | E40: =E9 -> -0.012769054 | F40: =F9 -> -0.012698368 | G40: =G9 -> -0.012442025 | H40: =H9 -> -0.011138905
A41: CO2 emissions (In Kt og CO2) | C41: =C10 -> 362.04263 | D41: =D10 -> 364.51423 | E41: =E10 -> 367.1103 | F41: =F10 -> 372.57878 | G41: =G10 -> 387.32088 | H41: =H10 -> 457.40889

Sheet Macro
A1: _date_ | B1: 42005 | C1: 42370 | D1: 42736 | E1: 43101 | F1: 43466 | G1: 43831 | H1: 44197 | I1: 44562 | J1: 44927 | K1: 45292 | L1: 45658 | M1: 46023 | N1: 46388 | O1: 46753 | P1: 47119 | Q1: 47484 | R1: 47849 | S1: 48214 | T1: 48580 | U1: 48945 | V1: 49310 | W1: 49675 | X1: 50041 | Y1: 50406 | Z1: 50771 | AA1: 51136 | AB1: 51502 | AC1: 51867 | AD1: 52232 | AE1: 52597 | AF1: 52963 | AG1: 53328 | AH1: 53693 | AI1: 54058 | AJ1: 54424 | AK1: 54789
A2: 100*(gdp_2/gdp_0-1) | B2: 0 | C2: 0.0032975093 | D2: 0.0087780434 | E2: 0.015823707 | F2: 0.024135068 | G2: 0.033797251 | H2: 0.043977897 | I2: 0.053197441 | J2: 0.06077257 | K2: 0.066716836 | L2: 0.071590899 | M2: 0.076243824 | N2: 0.081562508 | O2: 0.088294571 | P2: 0.096953857 | Q2: 0.10779222 | R2: 0.12003898 | S2: 0.13216063 | T2: 0.14297871 | U2: 0.15173712 | V2: 0.15810795 | W2: 0.16209732 | X2: 0.16391831 | Y2: 0.16387912 | Z2: 0.16230328 | AA2: 0.159482 | AB2: 0.15565164 | AC2: 0.15098856 | AD2: 0.14561488 | AE2: 0.13960972 | AF2: 0.13302273 | AG2: 0.12588741 | AH2: 0.11823222 | AI2: 0.11008984 | AJ2: 0.10150301 | AK2: 0.092527927
A3: 100*((va_2-va_spub_2)/(va_0-va_spub_0)-1) | B3: 0 | C3: 0.0045393429 | D3: 0.011844247 | E3: 0.021031285 | F3: 0.031777644 | G3: 0.044263684 | H3: 0.057312129 | I3: 0.068895137 | J3: 0.078189304 | K3: 0.085298255 | L3: 0.090983963 | M3: 0.096333798 | N3: 0.10246186 | O3: 0.110302 | P3: 0.12049535 | Q3: 0.1333572 | R3: 0.14783657 | S3: 0.16192759 | T3: 0.17418953 | U3: 0.18374294 | V3: 0.19022817 | W3: 0.19367962 | X3: 0.19437649 | Y3: 0.19271297 | Z3: 0.18910697 | AA3: 0.18394438 | AB3: 0.17755167 | AC3: 0.17018815 | AD3: 0.16205083 | AE3: 0.15328562 | AF3: 0.14400143 | AG3: 0.13428411 | AH3: 0.124209 | AI3: 0.1138501 | AJ3: 0.1032875 | AK3: 0.092610725
A4: 100*((ch_2-ch_0)/gdp_0) | B4: 0 | C4: 0.0021493844 | D4: 0.0072870161 | E4: 0.015397123 | F4: 0.026242919 | G4: 0.039947267 | H4: 0.056354808 | I4: 0.074505579 | J4: 0.093292264 | K4: 0.1120963 | L4: 0.13097622 | M4: 0.15049627 | N4: 0.17147151 | O4: 0.19476352 | P4: 0.22115675 | Q4: 0.251302 | R4: 0.28521622 | S4: 0.32201926 | T4: 0.36047947 | U4: 0.39949748 | V4: 0.43831876 | W4: 0.47651255 | X4: 0.5138669 | Y4: 0.55028289 | Z4: 0.58569797 | AA4: 0.62004066 | AB4: 0.6532103 | AC4: 0.68507342 | AD4: 0.71547094 | AE4: 0.74423009 | AF4: 0.77117806 | AG4: 0.79615529 | AH4: 0.81902583 | AI4: 0.83968527 | AJ4: 0.85806538 | AK4: 0.87413578
A5: 100*((ch_cveh_2-ch_cveh_0)/gdp_0) | B5: 0 | C5: -0.0037452388 | D5: -0.0075289513 | E5: -0.010751446 | F5: -0.013947599 | G5: -0.01783065 | H5: -0.021358905 | I5: -0.023215848 | J5: -0.023920076 | K5: -0.024374351 | L5: -0.025318646 | M5: -0.02724086 | N5: -0.030427581 | O5: -0.035033018 | P5: -0.041131338 | Q5: -0.048749124 | R5: -0.056747009 | S5: -0.063721283 | T5: -0.069572863 | U5: -0.07459295 | V5: -0.079090163 | W5: -0.083294609 | X5: -0.087357493 | Y5: -0.091373844 | Z5: -0.095404202 | AA5: -0.099489716 | AB5: -0.10366117 | AC5: -0.10794377 | AD5: -0.11235936 | AE5: -0.11692729 | AF5: -0.12166457 | AG5: -0.12658592 | AH5: -0.13170373 | AI5: -0.13702815 | AJ5: -0.14256726 | AK5: -0.14832736
A6: 100*((g_2-g_0)/gdp_0) | B6: 0 | C6: 0 | D6: 0 | E6: 0 | F6: 0 | G6: 0 | H6: 0 | I6: 0 | J6: 0 | K6: 0 | L6: 0 | M6: 0 | N6: 0 | O6: 0 | P6: 0 | Q6: 0 | R6: 0 | S6: 0 | T6: 0 | U6: 0 | V6: 0 | W6: 0 | X6: 0 | Y6: 0 | Z6: 0 | AA6: 0 | AB6: 0 | AC6: 0 | AD6: 0 | AE6: 0 | AF6: 0 | AG6: 0 | AH6: 0 | AI6: 0 | AJ6: 0 | AK6: 0
A7: 100*((i_2-i_0)/gdp_0) | B7: 0 | C7: -0.00097798005 | D7: -0.0023767186 | E7: -0.0040360862 | F7: -0.0060478317 | G7: -0.0086041142 | H7: -0.011514503 | I7: -0.01440095 | J7: -0.017188316 | K7: -0.019936667 | L7: -0.02273525 | M7: -0.025664498 | N7: -0.028797263 | O7: -0.032211959 | P7: -0.036002943 | Q7: -0.040282986 | R7: -0.044958675 | S7: -0.049816791 | T7: -0.054794013 | U7: -0.059884787 | V7: -0.065080303 | W7: -0.070346376 | X7: -0.075626333 | Y7: -0.080853788 | Z7: -0.085965765 | AA7: -0.090912057 | AB7: -0.095660082 | AC7: -0.10019589 | AD7: -0.10452261 | AE7: -0.10865728 | AF7: -0.11262718 | AG7: -0.11646595 | AH7: -0.12021017 | AI7: -0.12389641 | AJ7: -0.12755895 | AK7: -0.13122817
A8: 100*((ds_2-ds_0)/gdp_0) | B8: 0 | C8: 0 | D8: 0 | E8: 0 | F8: 0 | G8: 0 | H8: 0 | I8: 0 | J8: 0 | K8: 0 | L8: 0 | M8: 0 | N8: 0 | O8: 0 | P8: 0 | Q8: 0 | R8: 0 | S8: 0 | T8: 0 | U8: 0 | V8: 0 | W8: 0 | X8: 0 | Y8: 0 | Z8: 0 | AA8: 0 | AB8: 0 | AC8: 0 | AD8: 0 | AE8: 0 | AF8: 0 | AG8: 0 | AH8: 0 | AI8: 0 | AJ8: 0 | AK8: 0
A9: 100*((x_2-x_0)/gdp_0)-100*((m_2-m_0)/gdp_0) | B9: 0 | C9: 0.0021261184 | D9: 0.0038677325 | E9: 0.0044626709 | F9: 0.0039400025 | G9: 0.0024540896 | H9: -0.00086242969 | I9: -0.0069071843 | J9: -0.015331408 | K9: -0.025442811 | L9: -0.036650067 | M9: -0.048587953 | N9: -0.061111753 | O9: -0.074256966 | P9: -0.088199969 | Q9: -0.10322679 | R9: -0.12021855 | S9: -0.14004182 | T9: -0.16270674 | U9: -0.18787556 | V9: -0.21513048 | W9: -0.24406887 | X9: -0.27432227 | Y9: -0.30554998 | Z9: -0.33742891 | AA9: -0.3696466 | AB9: -0.40189857 | AC9: -0.43388896 | AD9: -0.46533346 | AE9: -0.49596307 | AF9: -0.52552815 | AG9: -0.55380196 | AH9: -0.58058343 | AI9: -0.60569898 | AJ9: -0.6290034 | AK9: -0.65037971
A10: 100*((ch_2-ch_ccon_2-(ch_0-ch_ccon_0))/gdp_0) | B10: 0 | C10: 0.0020785653 | D10: 0.0071128009 | E10: 0.015088113 | F10: 0.02576104 | G10: 0.039243669 | H10: 0.055394955 | I10: 0.073280475 | J10: 0.091798039 | K10: 0.11032637 | L10: 0.12891602 | M10: 0.14812008 | N10: 0.16874168 | O10: 0.19163142 | P10: 0.21756481 | Q10: 0.24718579 | R10: 0.28052662 | S10: 0.31673485 | T10: 0.35459317 | U10: 0.39301094 | V10: 0.43123835 | W10: 0.46884659 | X10: 0.50562429 | Y10: 0.54147295 | Z10: 0.576331 | AA10: 0.61012883 | AB10: 0.64276841 | AC10: 0.67411949 | AD10: 0.70402645 | AE10: 0.73231989 | AF10: 0.7588301 | AG10: 0.78340005 | AH10: 0.80589573 | AI10: 0.82621394 | AJ10: 0.84428699 | AK10: 0.86008434
A11: 100*((i_2+ch_ccon_2-(i_0+ch_ccon_0))/gdp_0) | B11: 0 | C11: -0.00090716093 | D11: -0.0022025034 | E11: -0.0037270765 | F11: -0.0055659523 | G11: -0.0079005166 | H11: -0.01055465 | I11: -0.013175845 | J11: -0.015694091 | K11: -0.018166736 | L11: -0.020675046 | M11: -0.023288312 | N11: -0.026067431 | O11: -0.029079865 | P11: -0.032411001 | Q11: -0.036166778 | R11: -0.040269072 | S11: -0.044532377 | T11: -0.048907714 | U11: -0.053398247 | V11: -0.057999897 | W11: -0.06268042 | X11: -0.067383723 | Y11: -0.07204384 | Z11: -0.076598792 | AA11: -0.081000221 | AB11: -0.085218193 | AC11: -0.08924197 | AD11: -0.093078117 | AE11: -0.096747087 | AF11: -0.10027922 | AG11: -0.10371071 | AH11: -0.10708007 | AI11: -0.11042509 | AJ11: -0.11378057 | AK11: -0.11717673
A12: 100*((i_2-ia_spub_2-(i_0-ia_spub_0))/gdp_0) | B12: 0 | C12: -0.00085743618 | D12: -0.0020804924 | E12: -0.0035228011 | F12: -0.0052664434 | G12: -0.0074852923 | H12: -0.010016326 | I12: -0.012530075 | J12: -0.014964201 | K12: -0.017375608 | L12: -0.019843385 | M12: -0.022434394 | N12: -0.025205904 | O12: -0.02821952 | P12: -0.03155235 | Q12: -0.035300329 | R12: -0.039381739 | S12: -0.043613571 | T12: -0.047948335 | U12: -0.052390726 | V12: -0.056940147 | W12: -0.061569531 | X12: -0.066228161 | Y12: -0.070854142 | Z12: -0.075387369 | AA12: -0.079778907 | AB12: -0.083996026 | AC12: -0.088023483 | AD12: -0.091862238 | AE12: -0.09552664 | AF12: -0.099040931 | AG12: -0.10243566 | AH12: -0.10574438 | AI12: -0.10900085 | AJ12: -0.11223689 | AK12: -0.11548069
... A55: pop | B55: 66422.5 | C55: 66588.556 | D55: 66755.028 | E55: 66921.915 | F55: 67089.22 | G55: 67256.943 | H55: 67425.085 | I55: 67593.648 | J55: 67762.632 | K55: 67932.039 | L55: 68101.869 | M55: 68272.124 | N55: 68442.804 | O55: 68613.911 | P55: 68785.446 | Q55: 68957.409 | R55: 69129.803 | S55: 69302.627 | T55: 69475.884 | U55: 69649.574 | V55: 69823.698 | W55: 69998.257 | X55: 70173.252 | Y55: 70348.686 | Z55: 70524.557 | AA55: 70700.869 | AB55: 70877.621 | AC55: 71054.815 | AD55: 71232.452 | AE55: 71410.533 | AF55: 71589.059 | AG55: 71768.032 | AH55: 71947.452 | AI55: 72127.321 | AJ55: 72307.639 | AK55: 72488.408

Sheet Baseline
A1: @date | B1: 42005 | C1: 42370 | D1: 42736 | E1: 43101 | F1: 43466 | G1: 43831 | H1: 44197 | I1: 44562 | J1: 44927 | K1: 45292 | L1: 45658 | M1: 46023 | N1: 46388 | O1: 46753 | P1: 47119 | Q1: 47484 | R1: 47849 | S1: 48214 | T1: 48580 | U1: 48945 | V1: 49310 | W1: 49675 | X1: 50041 | Y1: 50406 | Z1: 50771 | AA1: 51136 | AB1: 51502 | AC1: 51867 | AD1: 52232 | AE1: 52597 | AF1: 52963 | AG1: 53328 | AH1: 53693 | AI1: 54058 | AJ1: 54424 | AK1: 54789
A2: @pch(gdp_0) | B2: 0.0115225 | C2: 0.010855574 | D2: 0.010728383 | E2: 0.010808992 | F2: 0.010953895 | G2: 0.011108712 | H2: 0.011252093 | I2: 0.011375473 | J2: 0.011476236 | K2: 0.011554988 | L2: 0.011614092 | M2: 0.011656738 | N2: 0.011686315 | O2: 0.011706004 | P2: 0.011718548 | Q2: 0.011726136 | R2: 0.011730408 | S2: 0.011732513 | T2: 0.011733198 | U2: 0.011732909 | V2: 0.011731877 | W2: 0.011730202 | X2: 0.011727914 | Y2: 0.011725016 | Z2: 0.011721512 | AA2: 0.011717423 | AB2: 0.011712793 | AC2: 0.011707688 | AD2: 0.011702187 | AE2: 0.011696385 | AF2: 0.01169038 | AG2: 0.011684266 | AH2: 0.011678133 | AI2: 0.011672062 | AJ2: 0.011666121 | AK2: 0.011660368
A3: @pch(pch_0) | B3: 0.02 | C3: 0.019898733 | D3: 0.019777198 | E3: 0.019685451 | F3: 0.019635261 | G3: 0.019621524 | H3: 0.019635206 | I3: 0.019668198 | J3: 0.019714317 | K3: 0.019769024 | L3: 0.019828898 | M3: 0.019891268 | N3: 0.019953996 | O3: 0.020015378 | P3: 0.020074101 | Q3: 0.020129185 | R3: 0.020179956 | S3: 0.020225984 | T3: 0.020267046 | U3: 0.020303072 | V3: 0.020334107 | W3: 0.020360285 | X3: 0.020381797 | Y3: 0.020398878 | Z3: 0.020411799 | AA3: 0.020420845 | AB3: 0.020426324 | AC3: 0.020428547 | AD3: 0.020427835 | AE3: 0.020424509 | AF3: 0.020418888 | AG3: 0.020411284 | AH3: 0.020402003 | AI3: 0.020391336 | AJ3: 0.020379557 | AK3: 0.020366929
A4: unr_0 | B4: 0.14211338 | C4: 0.14239253 | D4: 0.14284801 | E4: 0.14332745 | F4: 0.14372958 | G4: 0.14400924 | H4: 0.14415906 | I4: 0.14419204 | J4: 0.14412979 | K4: 0.14399556 | L4: 0.14381068 | M4: 0.14359297 | N4: 0.14335631 | O4: 0.14311086 | P4: 0.1428636 | Q4: 0.14261895 | R4: 0.14237946 | S4: 0.14214634 | T4: 0.14191994 | U4: 0.14170015 | V4: 0.1414866 | W4: 0.14127888 | X4: 0.1410766 | Y4: 0.14087947 | Z4: 0.14068727 | AA4: 0.14049986 | AB4: 0.14031716 | AC4: 0.14013913 | AD4: 0.13996573 | AE4: 0.13979691 | AF4: 0.13963262 | AG4: 0.13947277 | AH4: 0.13931725 | AI4: 0.13916591 | AJ4: 0.13901859 | AK4: 0.13887513
A5: rdebt_g_val_0 | B5: 0.958 | C5: 0.95897527 | D5: 0.96058315 | E5: 0.96263011 | F5: 0.96497124 | G5: 0.96748013 | H5: 0.97004802 | I5: 0.97258712 | J5: 0.97503146 | K5: 0.97733498 | L5: 0.97946806 | M5: 0.98141366 | N5: 0.98316355 | O5: 0.98471535 | P5: 0.98607015 | Q5: 0.98723106 | R5: 0.98820224 | S5: 0.98898846 | T5: 0.98959494 | U5: 0.99002734 | V5: 0.99029187 | W5: 0.99039536 | X5: 0.99034531 | Y5: 0.99014987 | Z5: 0.98981782 | AA5: 0.98935842 | AB5: 0.9887813 | AC5: 0.98809631 | AD5: 0.98731335 | AE5: 0.98644222 | AF5: 0.98549246 | AG5: 0.98447327 | AH5: 0.98339337 | AI5: 0.98226095 | AJ5: 0.9810836 | AK5: 0.97986829
A6: rbal_g_prim_val_0 | B6: -0.0092851685 | C6: -0.0095358179 | D6: -0.0099463987 | E6: -0.010405279 | F6: -0.01083516 | G6: -0.011192718 | H6: -0.011460251 | I6: -0.011637088 | J6: -0.011732353 | K6: -0.011759578 | L6: -0.011733134 | M6: -0.011666163 | N6: -0.011569624 | O6: -0.011452069 | P6: -0.011319843 | Q6: -0.011177481 | R6: -0.011028163 | S6: -0.010874133 | T6: -0.010717037 | U6: -0.010558181 | V6: -0.01039869 | W6: -0.010239614 | X6: -0.010081963 | Y6: -0.0099267198 | Z6: -0.0097748208 | AA6: -0.0096271357 | AB6: -0.0094844412 | AC6: -0.0093473998 | AD6: -0.0092165451 | AE6: -0.0090922747 | AF6: -0.0089748501 | AG6: -0.0088644027 | AH6: -0.0087609442 | AI6: -0.0086643811 | AJ6: -0.0085745292 | AK6: -0.00849113
A7: rbal_trade_val_0 | B7: -0.01081433 | C7: -0.011339149 | D7: -0.011886849 | E7: -0.012303141 | F7: -0.012567896 | G7: -0.012711325 | H7: -0.01277292 | I7: -0.012784957 | J7: -0.012769054 | K7: -0.012737939 | L7: -0.012698368 | M7: -0.012653596 | N7: -0.012605063 | O7: -0.0125534 | P7: -0.012498953 | Q7: -0.012442025 | R7: -0.012382953 | S7: -0.012322107 | T7: -0.012259858 | U7: -0.012196549 | V7: -0.012132469 | W7: -0.012067848 | X7: -0.012002849 | Y7: -0.011937583 | Z7: -0.011872113 | AA7: -0.011806466 | AB7: -0.01174065 | AC7: -0.011674654 | AD7: -0.011608464 | AE7: -0.011542065 | AF7: -0.011475444 | AG7: -0.011408593 | AH7: -0.011341509 | AI7: -0.011274195 | AJ7: -0.011206656 | AK7: -0.011138905
A8: ems_co2_0 | B8: 350.29271 | C8: 352.43131 | D8: 354.06052 | E8: 355.7321 | F8: 357.61599 | G8: 359.72996 | H8: 362.04263 | I8: 364.51423 | J8: 367.1103 | K8: 369.80468 | L8: 372.57878 | M8: 375.41988 | N8: 378.31942 | O8: 381.27176 | P8: 384.27304 | Q8: 387.32088 | R8: 390.41383 | S8: 393.55096 | T8: 396.73175 | U8: 399.95582 | V8: 403.22297 | W8: 406.53308 | X8: 409.88608 | Y8: 413.28196 | Z8: 416.72071 | AA8: 420.20234 | AB8: 423.72691 | AC8: 427.29449 | AD8: 430.90523 | AE8: 434.55929 | AF8: 438.25689 | AG8: 441.9983 | AH8: 445.78382 | AI8: 449.61382 | AJ8: 453.48869 | AK8: 457.40889
A9: pop | B9: 66422.5 | C9: 66588.556 | D9: 66755.028 | E9: 66921.915 | F9: 67089.22 | G9: 67256.943 | H9: 67425.085 | I9: 67593.648 | J9: 67762.632 | K9: 67932.039 | L9: 68101.869 | M9: 68272.124 | N9: 68442.804 | O9: 68613.911 | P9: 68785.446 | Q9: 68957.409 | R9: 69129.803 | S9: 69302.627 | T9: 69475.884 | U9: 69649.574 | V9: 69823.698 | W9: 69998.257 | X9: 70173.252 | Y9: 70348.686 | Z9: 70524.557 | AA9: 70700.869 | AB9: 70877.621 | AC9: 71054.815 | AD9: 71232.452 | AE9: 71410.533 | AF9: 71589.059 | AG9: 71768.032 | AH9: 71947.452 | AI9: 72127.321 | AJ9: 72307.639 | AK9: 72488.408
A10: gdp_0 | B10: 2196558.3 | C10: 2220403.2 | D10: 2244224.5 | E10: 2268482.3 | F10: 2293331 | G10: 2318807 | H10: 2344898.4 | I10: 2371572.7 | J10: 2398789.5 | K10: 2426507.4 | L10: 2454689.1 | M10: 2483302.8 | N10: 2512323.4 | O10: 2541732.7 | P10: 2571518.1 | Q10: 2601672.1 | R10: 2632190.8 | S10: 2663073 | T10: 2694319.4 | U10: 2725931.6 | V10: 2757911.9 | W10: 2790262.7 | X10: 2822986.7 | Y10: 2856086.2 | Z10: 2889563.9 | AA10: 2923422.1 | AB10: 2957663.6 | AC10: 2992291 | AD10: 3027307.3 | AE10: 3062715.9 | AF10: 3098520.2 | AG10: 3134724.1 | AH10: 3171331.8 | AI10: 3208347.8 | AJ10: 3245776.8 | AK10: 3283623.8
A11: pch_0 | B11: 1 | C11: 1.0198987 | D11: 1.0400695 | E11: 1.0605437 | F11: 1.0813678 | G11: 1.1025858 | H11: 1.1242353 | I11: 1.146347 | J11: 1.1689465 | K11: 1.1920554 | L11: 1.2156926 | M11: 1.2398742 | N11: 1.2646147 | O11: 1.2899264 | P11: 1.3158205 | Q11: 1.3423069 | R11: 1.3693946 | S11: 1.397092 | T11: 1.4254069 | U11: 1.454347 | V11: 1.4839199 | W11: 1.5141329 | X11: 1.5449937 | Y11: 1.5765098 | Z11: 1.6086892 | AA11: 1.64154 | AB11: 1.6750706 | AC11: 1.7092899 | AD11: 1.744207 | AE11: 1.7798315 | AF11: 1.8161737 | AG11: 1.8532442 | AH11: 1.891054 | AI11: 1.9296152 | AJ11: 1.9689399 | AK11: 2.0090411
A12: ems_ch_co2_0 | B12: 119.49049 | C12: 119.25476 | D12: 118.5914 | E12: 117.94146 | F12: 117.43342 | G12: 117.07744 | H12: 116.84707 | I12: 116.7106 | J12: 116.64129 | K12: 116.61924 | L12: 116.63059 | M12: 116.66599 | N12: 116.71922 | O12: 116.78609 | P12: 116.86366 | Q12: 116.94993 | R12: 117.04357 | S12: 117.1436 | T12: 117.24929 | U12: 117.36001 | V12: 117.4753 | W12: 117.59478 | X12: 117.71816 | Y12: 117.84518 | Z12: 117.97565 | AA12: 118.10939 | AB12: 118.24629 | AC12: 118.38623 | AD12: 118.52913 | AE12: 118.67492 | AF12: 118.82357 | AG12: 118.97505 | AH12: 119.12935 | AI12: 119.28646 | AJ12: 119.44639 | AK12: 119.60915
... A28: ems_co2_cote_0 | B28: 17.86536 | C28: 18.049747 | D28: 18.22732 | E28: 18.406258 | F28: 18.589806 | G28: 18.778708 | H28: 18.972724 | I28: 19.17133 | J28: 19.373997 | K28: 19.580285 | L28: 19.789857 | M28: 20.002471 | N28: 20.217959 | O28: 20.436215 | P28: 20.657178 | Q28: 20.880819 | R28: 21.107135 | S28: 21.336135 | T28: 21.567842 | U28: 21.802281 | V28: 22.039486 | W28: 22.279487 | X28: 22.522317 | Y28: 22.768007 | Z28: 23.016586 | AA28: 23.268084 | AB28: 23.52253 | AC28: 23.779952 | AD28: 24.040379 | AE28: 24.303843 | AF28: 24.570373 | AG28: 24.840001 | AH28: 25.112761 | AI28: 25.388689 | AJ28: 25.667821 | AK28: 25.950193

Sheet produits-secteurs V2-V3
B1: ThreeME V3 | M1: ThreeME V2
B2: Produits | C2: V3 | E2: V2 | G2: Secteurs | H2: V3 | I2: V2 | K2: commentaires | M2: Produits | P2: secteurs
B3: Products of agriculture, Hunting, and Fishing | C3: cagr | E3: 1 | G3: Agriculture and fishing | H3: sagr | I3: 1 | M3: Agriculture, sylviculture et pêche | N3: 1 | P3: Agriculture, sylviculture et pêche | Q3: 1
B4: Products of Forestry | C4: cfor | G4: Forestry | H4: sfor | M4: Industrie agro-alimentaire | N4: 2 | P4: Industrie agro-alimentaire | Q4: 2
B5: Food products and beverages | C5: cfoo | E5: 2 | G5: Manufacture of food products and beverages | H5: sfoo | I5: 2 | M5: Automobile | N5: 3 | P5: Automobile | Q5: 3
B6: Motor vehicles, trailers and semi-trailers | C6: cveh | E6: 3 | G6: Manufacture of motor vehicles, trailers and semi-trailers | H6: sveh | I6: 3 | M6: FABRICATION DE VERRE ET D ARTICLES EN VE | N6: 4 | P6: FABRICATION DE VERRE ET D ARTICLES EN VE | Q6: 4
B7: Glass and ceramic products | C7: cgla | E7: 4 e t 5 | G7: Manufacture of glass, ceramic and ciment products | H7: sgla | I7: 4 et 5 | K7: ETS | M7: FABRICATION DE PRODUITS CERAMIQUES ET DE | N7: 5 | P7: FABRICATION DE PRODUITS CERAMIQUES ET DE | Q7: 5
B8: Paper and paperboard | C8: cpap | E8: 6 | G8: Manufacture of paper and paperboard | H8: spap | I8: 6 | K8: ETS | M8: Papier ert carton | N8: 6 | P8: Papier ert carton | Q8: 6
B9: Chemicals | C9: cche | E9: 7 et 8 | G9: Manufacture of chemicals | H9: sche | I9: 7 et 8 | K9: ETS | M9: INDUSTRIE CHIMIQUE MINERALE | N9: 7 | P9: INDUSTRIE CHIMIQUE MINERALE | Q9: 7
