Workbook
Name formatResults: [1]ResultsEXR10!$A$50

Sheet Results
A1: NB : on crée ici une liste : - globale, qui fusionne les sorties des reportings 1, 2 et 3 - "rationalisée" : suppression des doublons, et regroupements par thématique On continue par la suite à avoir 2 Excels de reporting (un "energie", fusion des reportings 1 et 2), et un "économie" (reporting 3)), dans lesquels on copiera cet onglet "results" (généré automatiquement par EViews). --> puis voir à la fin si on peut pas importer les graphs et tableaux dans l'excel automatiquement généré (éviterait les copiés collés, mais à voir si ça prend trop de temps, et si c'est pas trop gros comme excel)
E2: ThreeME V3 | F2: 2 | G2: 3 | H2: 4 | I2: 5 | J2: 6 | K2: 7 | L2: 8 | M2: 9 | N2: 10 | O2: 11 | P2: 12 | Q2: 13 | R2: 14 | S2: 15 | T2: 16 | U2: 17 | V2: 18 | W2: 19 | X2: 20 | Y2: 21 | Z2: 22 | AA2: 23 | AB2: 24 | AC2: 25 | AD2: 26 | AE2: 27 | AF2: 28 | AG2: 29 | AH2: 30 | AI2: 31 | AJ2: 32 | AK2: 33 | AL2: 34 | AM2: 35 | AN2: 36 | AO2: 37
A3: Nom du bloc de variables utilisé dans le code | B3: Sous-bloc de variables pour plus de lisibilité dans le Excel | E3: Year | F3: =date!B3 -> 2015 | G3: =date!C3 -> 2016 | H3: =date!D3 -> 2017 | I3: =date!E3 -> 2018 | J3: =date!F3 -> 2019 | K3: =date!G3 -> 2020 | L3: =date!H3 -> 2021 | M3: =date!I3 -> 2022 | ... AO3: =date!AK3 -> 2050
A4: HYBRID | B4: AUTOMOBILES (thousands) | C4: TOTAL STOCK SHOCK | E4: AUTO_2 | F4: =+VLOOKUP($E4,Hybrid!$1:$1048576,F$2,FALSE) -> 32317.941 | G4: =+VLOOKUP($E4,Hybrid!$1:$1048576,G$2,FALSE) -> 31926.455 | H4: =+VLOOKUP($E4,Hybrid!$1:$1048576,H$2,FALSE) -> 31730.401 | I4: =+VLOOKUP($E4,Hybrid!$1:$1048576,I$2,FALSE) -> 31664.733 | J4: =+VLOOKUP($E4,Hybrid!$1:$1048576,J$2,FALSE) -> 31685.152 | K4: =+VLOOKUP($E4,Hybrid!$1:$1048576,K$2,FALSE) -> 31761.774 | L4: =+VLOOKUP($E4,Hybrid!$1:$1048576,L$2,FALSE) -> 31876.82 | M4: =+VLOOKUP($E4,Hybrid!$1:$1048576,M$2,FALSE) -> 32020.398 | ... AO4: =+VLOOKUP($E4,Hybrid!$1:$1048576,AO$2,FALSE) -> 36554.972
C5: OIL | E5: AUTO_cfut_2 | F5: =+VLOOKUP($E5,Hybrid!$1:$1048576,F$2,FALSE) -> 32271.24 | G5: =+VLOOKUP($E5,Hybrid!$1:$1048576,G$2,FALSE) -> 31862.032 | H5: =+VLOOKUP($E5,Hybrid!$1:$1048576,H$2,FALSE) -> 31647.329 | I5: =+VLOOKUP($E5,Hybrid!$1:$1048576,I$2,FALSE) -> 31562.481 | J5: =+VLOOKUP($E5,Hybrid!$1:$1048576,J$2,FALSE) -> 31563.392 | K5: =+VLOOKUP($E5,Hybrid!$1:$1048576,K$2,FALSE) -> 31620.229 | L5: =+VLOOKUP($E5,Hybrid!$1:$1048576,L$2,FALSE) -> 31715.127 | M5: =+VLOOKUP($E5,Hybrid!$1:$1048576,M$2,FALSE) -> 31838.038 | ... AO5: =+VLOOKUP($E5,Hybrid!$1:$1048576,AO$2,FALSE) -> 32020.075
D6: class A | E6: AUTO_ca_cfut_2 | F6: =+VLOOKUP($E6,Hybrid!$1:$1048576,F$2,FALSE) -> 7095.7005 | G6: =+VLOOKUP($E6,Hybrid!$1:$1048576,G$2,FALSE) -> 7141.744 | H6: =+VLOOKUP($E6,Hybrid!$1:$1048576,H$2,FALSE) -> 7236.2108 | I6: =+VLOOKUP($E6,Hybrid!$1:$1048576,I$2,FALSE) -> 7362.7565 | J6: =+VLOOKUP($E6,Hybrid!$1:$1048576,J$2,FALSE) -> 7510.0299 | K6: =+VLOOKUP($E6,Hybrid!$1:$1048576,K$2,FALSE) -> 7670.2472 | L6: =+VLOOKUP($E6,Hybrid!$1:$1048576,L$2,FALSE) -> 7838.785 | M6: =+VLOOKUP($E6,Hybrid!$1:$1048576,M$2,FALSE) -> 8013.1055 | ... AO6: =+VLOOKUP($E6,Hybrid!$1:$1048576,AO$2,FALSE) -> 11240.43
D7: class B | E7: AUTO_cb_cfut_2 | F7: =+VLOOKUP($E7,Hybrid!$1:$1048576,F$2,FALSE) -> 8251.2564 | G7: =+VLOOKUP($E7,Hybrid!$1:$1048576,G$2,FALSE) -> 8182.7845 | H7: =+VLOOKUP($E7,Hybrid!$1:$1048576,H$2,FALSE) -> 8168.3356 | I7: =+VLOOKUP($E7,Hybrid!$1:$1048576,I$2,FALSE) -> 8191.2663 | J7: =+VLOOKUP($E7,Hybrid!$1:$1048576,J$2,FALSE) -> 8239.913 | K7: =+VLOOKUP($E7,Hybrid!$1:$1048576,K$2,FALSE) -> 8306.1531 | L7: =+VLOOKUP($E7,Hybrid!$1:$1048576,L$2,FALSE) -> 8384.9727 | M7: =+VLOOKUP($E7,Hybrid!$1:$1048576,M$2,FALSE) -> 8473.4298 | ... AO7: =+VLOOKUP($E7,Hybrid!$1:$1048576,AO$2,FALSE) -> 9881.9911
D8: class C | E8: AUTO_cc_cfut_2 | F8: =+VLOOKUP($E8,Hybrid!$1:$1048576,F$2,FALSE) -> 6777.6025 | G8: =+VLOOKUP($E8,Hybrid!$1:$1048576,G$2,FALSE) -> 6646.7629 | H8: =+VLOOKUP($E8,Hybrid!$1:$1048576,H$2,FALSE) -> 6558.9664 | I8: =+VLOOKUP($E8,Hybrid!$1:$1048576,I$2,FALSE) -> 6502.0082 | J8: =+VLOOKUP($E8,Hybrid!$1:$1048576,J$2,FALSE) -> 6467.2622 | K8: =+VLOOKUP($E8,Hybrid!$1:$1048576,K$2,FALSE) -> 6448.6373 | L8: =+VLOOKUP($E8,Hybrid!$1:$1048576,L$2,FALSE) -> 6442.2478 | M8: =+VLOOKUP($E8,Hybrid!$1:$1048576,M$2,FALSE) -> 6445.693 | ... AO8: =+VLOOKUP($E8,Hybrid!$1:$1048576,AO$2,FALSE) -> 6300.9328
D9: class D | E9: AUTO_cd_cfut_2 | F9: =+VLOOKUP($E9,Hybrid!$1:$1048576,F$2,FALSE) -> 4159.6639 | G9: =+VLOOKUP($E9,Hybrid!$1:$1048576,G$2,FALSE) -> 4054.5797 | H9: =+VLOOKUP($E9,Hybrid!$1:$1048576,H$2,FALSE) -> 3973.8285 | I9: =+VLOOKUP($E9,Hybrid!$1:$1048576,I$2,FALSE) -> 3910.0599 | J9: =+VLOOKUP($E9,Hybrid!$1:$1048576,J$2,FALSE) -> 3858.1675 | K9: =+VLOOKUP($E9,Hybrid!$1:$1048576,K$2,FALSE) -> 3814.6035 | L9: =+VLOOKUP($E9,Hybrid!$1:$1048576,L$2,FALSE) -> 3777.117 | M9: =+VLOOKUP($E9,Hybrid!$1:$1048576,M$2,FALSE) -> 3744.3156 | ... AO9: =+VLOOKUP($E9,Hybrid!$1:$1048576,AO$2,FALSE) -> 2689.2394
D10: class E | E10: AUTO_ce_cfut_2 | F10: =+VLOOKUP($E10,Hybrid!$1:$1048576,F$2,FALSE) -> 2503.7292 | G10: =+VLOOKUP($E10,Hybrid!$1:$1048576,G$2,FALSE) -> 2442.7169 | H10: =+VLOOKUP($E10,Hybrid!$1:$1048576,H$2,FALSE) -> 2395.2655 | I10: =+VLOOKUP($E10,Hybrid!$1:$1048576,I$2,FALSE) -> 2356.6831 | J10: =+VLOOKUP($E10,Hybrid!$1:$1048576,J$2,FALSE) -> 2323.7962 | K10: =+VLOOKUP($E10,Hybrid!$1:$1048576,K$2,FALSE) -> 2294.4653 | L10: =+VLOOKUP($E10,Hybrid!$1:$1048576,L$2,FALSE) -> 2267.3805 | M10: =+VLOOKUP($E10,Hybrid!$1:$1048576,M$2,FALSE) -> 2241.7723 | ... AO10: =+VLOOKUP($E10,Hybrid!$1:$1048576,AO$2,FALSE) -> 1253.0278
D11: class F | E11: AUTO_cf_cfut_2 | F11: =+VLOOKUP($E11,Hybrid!$1:$1048576,F$2,FALSE) -> 1243.6668 | G11: =+VLOOKUP($E11,Hybrid!$1:$1048576,G$2,FALSE) -> 1210.4925 | H11: =+VLOOKUP($E11,Hybrid!$1:$1048576,H$2,FALSE) -> 1182.3239 | I11: =+VLOOKUP($E11,Hybrid!$1:$1048576,I$2,FALSE) -> 1156.6362 | J11: =+VLOOKUP($E11,Hybrid!$1:$1048576,J$2,FALSE) -> 1131.8888 | K11: =+VLOOKUP($E11,Hybrid!$1:$1048576,K$2,FALSE) -> 1107.177 | L11: =+VLOOKUP($E11,Hybrid!$1:$1048576,L$2,FALSE) -> 1082.0509 | M11: =+VLOOKUP($E11,Hybrid!$1:$1048576,M$2,FALSE) -> 1056.3349 | ... AO11: =+VLOOKUP($E11,Hybrid!$1:$1048576,AO$2,FALSE) -> 294.49603
D12: class G | E12: AUTO_cg_cfut_2 | F12: =+VLOOKUP($E12,Hybrid!$1:$1048576,F$2,FALSE) -> 2239.6206 | G12: =+VLOOKUP($E12,Hybrid!$1:$1048576,G$2,FALSE) -> 2182.9512 | H12: =+VLOOKUP($E12,Hybrid!$1:$1048576,H$2,FALSE) -> 2132.3988 | I12: =+VLOOKUP($E12,Hybrid!$1:$1048576,I$2,FALSE) -> 2083.0711 | J12: =+VLOOKUP($E12,Hybrid!$1:$1048576,J$2,FALSE) -> 2032.334 | K12: =+VLOOKUP($E12,Hybrid!$1:$1048576,K$2,FALSE) -> 1978.9456 | L12: =+VLOOKUP($E12,Hybrid!$1:$1048576,L$2,FALSE) -> 1922.5734 | M12: =+VLOOKUP($E12,Hybrid!$1:$1048576,M$2,FALSE) -> 1863.3872 | ... AO12: =+VLOOKUP($E12,Hybrid!$1:$1048576,AO$2,FALSE) -> 359.95743
C13: ELEC | E13: AUTO_cele_2 | F13: =+VLOOKUP($E13,Hybrid!$1:$1048576,F$2,FALSE) -> 44.765 | G13: =+VLOOKUP($E13,Hybrid!$1:$1048576,G$2,FALSE) -> 62.431569 | H13: =+VLOOKUP($E13,Hybrid!$1:$1048576,H$2,FALSE) -> 81.013696 | I13: =+VLOOKUP($E13,Hybrid!$1:$1048576,I$2,FALSE) -> 100.12298 | J13: =+VLOOKUP($E13,Hybrid!$1:$1048576,J$2,FALSE) -> 119.55791 | K13: =+VLOOKUP($E13,Hybrid!$1:$1048576,K$2,FALSE) -> 139.26917 | L13: =+VLOOKUP($E13,Hybrid!$1:$1048576,L$2,FALSE) -> 159.3444 | M13: =+VLOOKUP($E13,Hybrid!$1:$1048576,M$2,FALSE) -> 179.94081 | ... AO13: =+VLOOKUP($E13,Hybrid!$1:$1048576,AO$2,FALSE) -> 4531.6755
D14: class A | E14: AUTO_ca_cele_2 | F14: =+VLOOKUP($E14,Hybrid!$1:$1048576,F$2,FALSE) -> 9.8427899 | G14: =+VLOOKUP($E14,Hybrid!$1:$1048576,G$2,FALSE) -> 14.986776 | H14: =+VLOOKUP($E14,Hybrid!$1:$1048576,H$2,FALSE) -> 20.441889 | I14: =+VLOOKUP($E14,Hybrid!$1:$1048576,I$2,FALSE) -> 26.112449 | J14: =+VLOOKUP($E14,Hybrid!$1:$1048576,J$2,FALSE) -> 31.950416 | K14: =+VLOOKUP($E14,Hybrid!$1:$1048576,K$2,FALSE) -> 37.949262 | L14: =+VLOOKUP($E14,Hybrid!$1:$1048576,L$2,FALSE) -> 44.142141 | M14: =+VLOOKUP($E14,Hybrid!$1:$1048576,M$2,FALSE) -> 50.58278 | ... AO14: =+VLOOKUP($E14,Hybrid!$1:$1048576,AO$2,FALSE) -> 1721.1452
D15: class B | E15: AUTO_cb_cele_2 | F15: =+VLOOKUP($E15,Hybrid!$1:$1048576,F$2,FALSE) -> 11.445717 | G15: =+VLOOKUP($E15,Hybrid!$1:$1048576,G$2,FALSE) -> 16.298726 | H15: =+VLOOKUP($E15,Hybrid!$1:$1048576,H$2,FALSE) -> 21.445143 | I15: =+VLOOKUP($E15,Hybrid!$1:$1048576,I$2,FALSE) -> 26.792131 | J15: =+VLOOKUP($E15,Hybrid!$1:$1048576,J$2,FALSE) -> 32.294 | K15: =+VLOOKUP($E15,Hybrid!$1:$1048576,K$2,FALSE) -> 37.945945 | L15: =+VLOOKUP($E15,Hybrid!$1:$1048576,L$2,FALSE) -> 43.781768 | M15: =+VLOOKUP($E15,Hybrid!$1:$1048576,M$2,FALSE) -> 49.854747 | ... AO15: =+VLOOKUP($E15,Hybrid!$1:$1048576,AO$2,FALSE) -> 1535.9361
D16: class C | E16: AUTO_cc_cele_2 | F16: =+VLOOKUP($E16,Hybrid!$1:$1048576,F$2,FALSE) -> 9.4015406 | G16: =+VLOOKUP($E16,Hybrid!$1:$1048576,G$2,FALSE) -> 12.697683 | H16: =+VLOOKUP($E16,Hybrid!$1:$1048576,H$2,FALSE) -> 16.193359 | I16: =+VLOOKUP($E16,Hybrid!$1:$1048576,I$2,FALSE) -> 19.823555 | J16: =+VLOOKUP($E16,Hybrid!$1:$1048576,J$2,FALSE) -> 23.556822 | K16: =+VLOOKUP($E16,Hybrid!$1:$1048576,K$2,FALSE) -> 27.390656 | L16: =+VLOOKUP($E16,Hybrid!$1:$1048576,L$2,FALSE) -> 31.349549 | M16: =+VLOOKUP($E16,Hybrid!$1:$1048576,M$2,FALSE) -> 35.471241 | ... AO16: =+VLOOKUP($E16,Hybrid!$1:$1048576,AO$2,FALSE) -> 985.3507
D17: class D | E17: AUTO_cd_cele_2 | F17: =+VLOOKUP($E17,Hybrid!$1:$1048576,F$2,FALSE) -> 5.7700713 | G17: =+VLOOKUP($E17,Hybrid!$1:$1048576,G$2,FALSE) -> 7.5615055 | H17: =+VLOOKUP($E17,Hybrid!$1:$1048576,H$2,FALSE) -> 9.4379839 | I17: =+VLOOKUP($E17,Hybrid!$1:$1048576,I$2,FALSE) -> 11.352079 | J17: =+VLOOKUP($E17,Hybrid!$1:$1048576,J$2,FALSE) -> 13.275194 | K17: =+VLOOKUP($E17,Hybrid!$1:$1048576,K$2,FALSE) -> 15.192959 | L17: =+VLOOKUP($E17,Hybrid!$1:$1048576,L$2,FALSE) -> 17.103324 | M17: =+VLOOKUP($E17,Hybrid!$1:$1048576,M$2,FALSE) -> 19.010938 | ... AO17: =+VLOOKUP($E17,Hybrid!$1:$1048576,AO$2,FALSE) -> 187.38943
D18: class E | E18: AUTO_ce_cele_2 | F18: =+VLOOKUP($E18,Hybrid!$1:$1048576,F$2,FALSE) -> 3.4730441 | G18: =+VLOOKUP($E18,Hybrid!$1:$1048576,G$2,FALSE) -> 4.5722155 | H18: =+VLOOKUP($E18,Hybrid!$1:$1048576,H$2,FALSE) -> 5.7140433 | I18: =+VLOOKUP($E18,Hybrid!$1:$1048576,I$2,FALSE) -> 6.8675525 | J18: =+VLOOKUP($E18,Hybrid!$1:$1048576,J$2,FALSE) -> 8.014519 | K18: =+VLOOKUP($E18,Hybrid!$1:$1048576,K$2,FALSE) -> 9.146111 | L18: =+VLOOKUP($E18,Hybrid!$1:$1048576,L$2,FALSE) -> 10.261244 | M18: =+VLOOKUP($E18,Hybrid!$1:$1048576,M$2,FALSE) -> 11.362807 | ... AO18: =+VLOOKUP($E18,Hybrid!$1:$1048576,AO$2,FALSE) -> 82.980357
D19: class F | E19: AUTO_cf_cele_2 | F19: =+VLOOKUP($E19,Hybrid!$1:$1048576,F$2,FALSE) -> 1.7251505 | G19: =+VLOOKUP($E19,Hybrid!$1:$1048576,G$2,FALSE) -> 2.2443945 | H19: =+VLOOKUP($E19,Hybrid!$1:$1048576,H$2,FALSE) -> 2.7668951 | I19: =+VLOOKUP($E19,Hybrid!$1:$1048576,I$2,FALSE) -> 3.2740042 | J19: =+VLOOKUP($E19,Hybrid!$1:$1048576,J$2,FALSE) -> 3.7551966 | K19: =+VLOOKUP($E19,Hybrid!$1:$1048576,K$2,FALSE) -> 4.2053456 | L19: =+VLOOKUP($E19,Hybrid!$1:$1048576,L$2,FALSE) -> 4.6232035 | M19: =+VLOOKUP($E19,Hybrid!$1:$1048576,M$2,FALSE) -> 5.0095094 | ... AO19: =+VLOOKUP($E19,Hybrid!$1:$1048576,AO$2,FALSE) -> 9.6175148
D20: class G | E20: AUTO_cg_cele_2 | F20: =+VLOOKUP($E20,Hybrid!$1:$1048576,F$2,FALSE) -> 3.1066862 | G20: =+VLOOKUP($E20,Hybrid!$1:$1048576,G$2,FALSE) -> 4.0702695 | H20: =+VLOOKUP($E20,Hybrid!$1:$1048576,H$2,FALSE) -> 5.014383 | I20: =+VLOOKUP($E20,Hybrid!$1:$1048576,I$2,FALSE) -> 5.9012135 | J20: =+VLOOKUP($E20,Hybrid!$1:$1048576,J$2,FALSE) -> 6.7117634 | K20: =+VLOOKUP($E20,Hybrid!$1:$1048576,K$2,FALSE) -> 7.4388891 | L20: =+VLOOKUP($E20,Hybrid!$1:$1048576,L$2,FALSE) -> 8.0831672 | M20: =+VLOOKUP($E20,Hybrid!$1:$1048576,M$2,FALSE) -> 8.6487843 | ... AO20: =+VLOOKUP($E20,Hybrid!$1:$1048576,AO$2,FALSE) -> 9.2561619
C21: GAS | E21: AUTO_cgas_2 | F21: =+VLOOKUP($E21,Hybrid!$1:$1048576,F$2,FALSE) -> 1.936 | G21: =+VLOOKUP($E21,Hybrid!$1:$1048576,G$2,FALSE) -> 1.9916056 | H21: =+VLOOKUP($E21,Hybrid!$1:$1048576,H$2,FALSE) -> 2.0574011 | I21: =+VLOOKUP($E21,Hybrid!$1:$1048576,I$2,FALSE) -> 2.1285899 | J21: =+VLOOKUP($E21,Hybrid!$1:$1048576,J$2,FALSE) -> 2.2019794 | K21: =+VLOOKUP($E21,Hybrid!$1:$1048576,K$2,FALSE) -> 2.2754864 | L21: =+VLOOKUP($E21,Hybrid!$1:$1048576,L$2,FALSE) -> 2.3479684 | M21: =+VLOOKUP($E21,Hybrid!$1:$1048576,M$2,FALSE) -> 2.4188941 | ... AO21: =+VLOOKUP($E21,Hybrid!$1:$1048576,AO$2,FALSE) -> 3.2214115
D22: class A | E22: AUTO_ca_cgas_2 | F22: =+VLOOKUP($E22,Hybrid!$1:$1048576,F$2,FALSE) -> 0.4256817 | G22: =+VLOOKUP($E22,Hybrid!$1:$1048576,G$2,FALSE) -> 0.44933517 | H22: =+VLOOKUP($E22,Hybrid!$1:$1048576,H$2,FALSE) -> 0.47587941 | I22: =+VLOOKUP($E22,Hybrid!$1:$1048576,I$2,FALSE) -> 0.50407723 | J22: =+VLOOKUP($E22,Hybrid!$1:$1048576,J$2,FALSE) -> 0.53308137 | K22: =+VLOOKUP($E22,Hybrid!$1:$1048576,K$2,FALSE) -> 0.56232302 | L22: =+VLOOKUP($E22,Hybrid!$1:$1048576,L$2,FALSE) -> 0.59148357 | M22: =+VLOOKUP($E22,Hybrid!$1:$1048576,M$2,FALSE) -> 0.62040925 | ... AO22: =+VLOOKUP($E22,Hybrid!$1:$1048576,AO$2,FALSE) -> 1.1175435
D23: class B | E23: AUTO_cb_cgas_2 | F23: =+VLOOKUP($E23,Hybrid!$1:$1048576,F$2,FALSE) -> 0.49500523 | G23: =+VLOOKUP($E23,Hybrid!$1:$1048576,G$2,FALSE) -> 0.51226024 | H23: =+VLOOKUP($E23,Hybrid!$1:$1048576,H$2,FALSE) -> 0.53252768 | I23: =+VLOOKUP($E23,Hybrid!$1:$1048576,I$2,FALSE) -> 0.55457425 | J23: =+VLOOKUP($E23,Hybrid!$1:$1048576,J$2,FALSE) -> 0.57755325 | K23: =+VLOOKUP($E23,Hybrid!$1:$1048576,K$2,FALSE) -> 0.60089214 | L23: =+VLOOKUP($E23,Hybrid!$1:$1048576,L$2,FALSE) -> 0.62426223 | M23: =+VLOOKUP($E23,Hybrid!$1:$1048576,M$2,FALSE) -> 0.64749666 | ... AO23: =+VLOOKUP($E23,Hybrid!$1:$1048576,AO$2,FALSE) -> 0.98903502
D24: class C | E24: AUTO_cc_cgas_2 | F24: =+VLOOKUP($E24,Hybrid!$1:$1048576,F$2,FALSE) -> 0.40659852 | G24: =+VLOOKUP($E24,Hybrid!$1:$1048576,G$2,FALSE) -> 0.4145049 | H24: =+VLOOKUP($E24,Hybrid!$1:$1048576,H$2,FALSE) -> 0.42467781 | I24: =+VLOOKUP($E24,Hybrid!$1:$1048576,I$2,FALSE) -> 0.43623168 | J24: =+VLOOKUP($E24,Hybrid!$1:$1048576,J$2,FALSE) -> 0.44855712 | K24: =+VLOOKUP($E24,Hybrid!$1:$1048576,K$2,FALSE) -> 0.4612394 | L24: =+VLOOKUP($E24,Hybrid!$1:$1048576,L$2,FALSE) -> 0.47403519 | M24: =+VLOOKUP($E24,Hybrid!$1:$1048576,M$2,FALSE) -> 0.48681568 | ... AO24: =+VLOOKUP($E24,Hybrid!$1:$1048576,AO$2,FALSE) -> 0.63482943
D25: class D | E25: AUTO_cd_cgas_2 | F25: =+VLOOKUP($E25,Hybrid!$1:$1048576,F$2,FALSE) -> 0.24954447 | G25: =+VLOOKUP($E25,Hybrid!$1:$1048576,G$2,FALSE) -> 0.25231485 | H25: =+VLOOKUP($E25,Hybrid!$1:$1048576,H$2,FALSE) -> 0.25626929 | I25: =+VLOOKUP($E25,Hybrid!$1:$1048576,I$2,FALSE) -> 0.26087537 | J25: =+VLOOKUP($E25,Hybrid!$1:$1048576,J$2,FALSE) -> 0.2657744 | K25: =+VLOOKUP($E25,Hybrid!$1:$1048576,K$2,FALSE) -> 0.27072766 | L25: =+VLOOKUP($E25,Hybrid!$1:$1048576,L$2,FALSE) -> 0.27559709 | M25: =+VLOOKUP($E25,Hybrid!$1:$1048576,M$2,FALSE) -> 0.28031071 | ... AO25: =+VLOOKUP($E25,Hybrid!$1:$1048576,AO$2,FALSE) -> 0.27521423
D26: class E | E26: AUTO_ce_cgas_2 | F26: =+VLOOKUP($E26,Hybrid!$1:$1048576,F$2,FALSE) -> 0.15020247 | G26: =+VLOOKUP($E26,Hybrid!$1:$1048576,G$2,FALSE) -> 0.15205804 | H26: =+VLOOKUP($E26,Hybrid!$1:$1048576,H$2,FALSE) -> 0.15453801 | I26: =+VLOOKUP($E26,Hybrid!$1:$1048576,I$2,FALSE) -> 0.15729786 | J26: =+VLOOKUP($E26,Hybrid!$1:$1048576,J$2,FALSE) -> 0.16011145 | K26: =+VLOOKUP($E26,Hybrid!$1:$1048576,K$2,FALSE) -> 0.16283293 | L26: =+VLOOKUP($E26,Hybrid!$1:$1048576,L$2,FALSE) -> 0.16538126 | M26: =+VLOOKUP($E26,Hybrid!$1:$1048576,M$2,FALSE) -> 0.16771728 | ... AO26: =+VLOOKUP($E26,Hybrid!$1:$1048576,AO$2,FALSE) -> 0.13087224
D27: class F | E27: AUTO_cf_cgas_2 | F27: =+VLOOKUP($E27,Hybrid!$1:$1048576,F$2,FALSE) -> 0.074609436 | G27: =+VLOOKUP($E27,Hybrid!$1:$1048576,G$2,FALSE) -> 0.075290207 | H27: =+VLOOKUP($E27,Hybrid!$1:$1048576,H$2,FALSE) -> 0.076132076 | I27: =+VLOOKUP($E27,Hybrid!$1:$1048576,I$2,FALSE) -> 0.076945597 | J27: =+VLOOKUP($E27,Hybrid!$1:$1048576,J$2,FALSE) -> 0.077619324 | K27: =+VLOOKUP($E27,Hybrid!$1:$1048576,K$2,FALSE) -> 0.078092136 | L27: =+VLOOKUP($E27,Hybrid!$1:$1048576,L$2,FALSE) -> 0.078339035 | M27: =+VLOOKUP($E27,Hybrid!$1:$1048576,M$2,FALSE) -> 0.078356678 | ... AO27: =+VLOOKUP($E27,Hybrid!$1:$1048576,AO$2,FALSE) -> 0.032639717
D28: class G | E28: AUTO_cg_cgas_2 | F28: =+VLOOKUP($E28,Hybrid!$1:$1048576,F$2,FALSE) -> 0.13435819 | G28: =+VLOOKUP($E28,Hybrid!$1:$1048576,G$2,FALSE) -> 0.13584219 | H28: =+VLOOKUP($E28,Hybrid!$1:$1048576,H$2,FALSE) -> 0.13737684 | I28: =+VLOOKUP($E28,Hybrid!$1:$1048576,I$2,FALSE) -> 0.13858796 | J28: =+VLOOKUP($E28,Hybrid!$1:$1048576,J$2,FALSE) -> 0.13928248 | K28: =+VLOOKUP($E28,Hybrid!$1:$1048576,K$2,FALSE) -> 0.13937915 | L28: =+VLOOKUP($E28,Hybrid!$1:$1048576,L$2,FALSE) -> 0.13887006 | M28: =+VLOOKUP($E28,Hybrid!$1:$1048576,M$2,FALSE) -> 0.13778783 | ... AO28: =+VLOOKUP($E28,Hybrid!$1:$1048576,AO$2,FALSE) -> 0.041277351
C29: TOTAL STOCK BASELINE | E29: AUTO_0 | F29: =+VLOOKUP($E29,Hybrid!$1:$1048576,F$2,FALSE) -> 32317.941 | G29: =+VLOOKUP($E29,Hybrid!$1:$1048576,G$2,FALSE) -> 31931.625 | H29: =+VLOOKUP($E29,Hybrid!$1:$1048576,H$2,FALSE) -> 31743.508 | I29: =+VLOOKUP($E29,Hybrid!$1:$1048576,I$2,FALSE) -> 31687.792 | J29: =+VLOOKUP($E29,Hybrid!$1:$1048576,J$2,FALSE) -> 31720.643 | K29: =+VLOOKUP($E29,Hybrid!$1:$1048576,K$2,FALSE) -> 31813.337 | L29: =+VLOOKUP($E29,Hybrid!$1:$1048576,L$2,FALSE) -> 31947.162 | M29: =+VLOOKUP($E29,Hybrid!$1:$1048576,M$2,FALSE) -> 32109.877 | ... AO29: =+VLOOKUP($E29,Hybrid!$1:$1048576,AO$2,FALSE) -> 38673.292
C30: OIL | E30: AUTO_cfut_0 | F30: =+VLOOKUP($E30,Hybrid!$1:$1048576,F$2,FALSE) -> 32271.24 | G30: =+VLOOKUP($E30,Hybrid!$1:$1048576,G$2,FALSE) -> 31867.185 | H30: =+VLOOKUP($E30,Hybrid!$1:$1048576,H$2,FALSE) -> 31660.486 | I30: =+VLOOKUP($E30,Hybrid!$1:$1048576,I$2,FALSE) -> 31585.838 | J30: =+VLOOKUP($E30,Hybrid!$1:$1048576,J$2,FALSE) -> 31599.721 | K30: =+VLOOKUP($E30,Hybrid!$1:$1048576,K$2,FALSE) -> 31673.603 | L30: =+VLOOKUP($E30,Hybrid!$1:$1048576,L$2,FALSE) -> 31788.887 | M30: =+VLOOKUP($E30,Hybrid!$1:$1048576,M$2,FALSE) -> 31933.397 | ... AO30: =+VLOOKUP($E30,Hybrid!$1:$1048576,AO$2,FALSE) -> 38101.906
D31: class A | E31: AUTO_ca_cfut_0 | F31: =+VLOOKUP($E31,Hybrid!$1:$1048576,F$2,FALSE) -> 7095.7005 | G31: =+VLOOKUP($E31,Hybrid!$1:$1048576,G$2,FALSE) -> 7143.1788 | H31: =+VLOOKUP($E31,Hybrid!$1:$1048576,H$2,FALSE) -> 7239.81 | I31: =+VLOOKUP($E31,Hybrid!$1:$1048576,I$2,FALSE) -> 7369.0432 | J31: =+VLOOKUP($E31,Hybrid!$1:$1048576,J$2,FALSE) -> 7519.6804 | K31: =+VLOOKUP($E31,Hybrid!$1:$1048576,K$2,FALSE) -> 7684.2986 | L31: =+VLOOKUP($E31,Hybrid!$1:$1048576,L$2,FALSE) -> 7858.0379 | M31: =+VLOOKUP($E31,Hybrid!$1:$1048576,M$2,FALSE) -> 8037.7299 | ... AO31: =+VLOOKUP($E31,Hybrid!$1:$1048576,AO$2,FALSE) -> 13271.9
D32: class B | E32: AUTO_cb_cfut_0 | F32: =+VLOOKUP($E32,Hybrid!$1:$1048576,F$2,FALSE) -> 8251.2564 | G32: =+VLOOKUP($E32,Hybrid!$1:$1048576,G$2,FALSE) -> 8184.1785 | H32: =+VLOOKUP($E32,Hybrid!$1:$1048576,H$2,FALSE) -> 8171.8779 | I32: =+VLOOKUP($E32,Hybrid!$1:$1048576,I$2,FALSE) -> 8197.5342 | J32: =+VLOOKUP($E32,Hybrid!$1:$1048576,J$2,FALSE) -> 8249.6491 | K32: =+VLOOKUP($E32,Hybrid!$1:$1048576,K$2,FALSE) -> 8320.4704 | L32: =+VLOOKUP($E32,Hybrid!$1:$1048576,L$2,FALSE) -> 8404.7877 | M32: =+VLOOKUP($E32,Hybrid!$1:$1048576,M$2,FALSE) -> 8499.0715 | ... AO32: =+VLOOKUP($E32,Hybrid!$1:$1048576,AO$2,FALSE) -> 11875.349
D33: class C | E33: AUTO_cc_cfut_0 | F33: =+VLOOKUP($E33,Hybrid!$1:$1048576,F$2,FALSE) -> 6777.6025 | G33: =+VLOOKUP($E33,Hybrid!$1:$1048576,G$2,FALSE) -> 6647.7392 | H33: =+VLOOKUP($E33,Hybrid!$1:$1048576,H$2,FALSE) -> 6561.4778 | I33: =+VLOOKUP($E33,Hybrid!$1:$1048576,I$2,FALSE) -> 6506.5051 | J33: =+VLOOKUP($E33,Hybrid!$1:$1048576,J$2,FALSE) -> 6474.3214 | K33: =+VLOOKUP($E33,Hybrid!$1:$1048576,K$2,FALSE) -> 6459.1067 | L33: =+VLOOKUP($E33,Hybrid!$1:$1048576,L$2,FALSE) -> 6456.8591 | M33: =+VLOOKUP($E33,Hybrid!$1:$1048576,M$2,FALSE) -> 6464.7815 | ... AO33: =+VLOOKUP($E33,Hybrid!$1:$1048576,AO$2,FALSE) -> 7687.7208
D34: class D | E34: AUTO_cd_cfut_0 | F34: =+VLOOKUP($E34,Hybrid!$1:$1048576,F$2,FALSE) -> 4159.6639 | G34: =+VLOOKUP($E34,Hybrid!$1:$1048576,G$2,FALSE) -> 4055.1231 | H34: =+VLOOKUP($E34,Hybrid!$1:$1048576,H$2,FALSE) -> 3975.2329 | I34: =+VLOOKUP($E34,Hybrid!$1:$1048576,I$2,FALSE) -> 3912.5808 | J34: =+VLOOKUP($E34,Hybrid!$1:$1048576,J$2,FALSE) -> 3862.1234 | K34: =+VLOOKUP($E34,Hybrid!$1:$1048576,K$2,FALSE) -> 3820.4516 | L34: =+VLOOKUP($E34,Hybrid!$1:$1048576,L$2,FALSE) -> 3785.2435 | M34: =+VLOOKUP($E34,Hybrid!$1:$1048576,M$2,FALSE) -> 3754.8857 | ... AO34: =+VLOOKUP($E34,Hybrid!$1:$1048576,AO$2,FALSE) -> 3102.3334
D35: class E | E35: AUTO_ce_cfut_0 | F35: =+VLOOKUP($E35,Hybrid!$1:$1048576,F$2,FALSE) -> 2503.7292 | G35: =+VLOOKUP($E35,Hybrid!$1:$1048576,G$2,FALSE) -> 2443.054 | H35: =+VLOOKUP($E35,Hybrid!$1:$1048576,H$2,FALSE) -> 2396.145 | I35: =+VLOOKUP($E35,Hybrid!$1:$1048576,I$2,FALSE) -> 2358.2745 | J35: =+VLOOKUP($E35,Hybrid!$1:$1048576,J$2,FALSE) -> 2326.3079 | K35: =+VLOOKUP($E35,Hybrid!$1:$1048576,K$2,FALSE) -> 2298.1904 | L35: =+VLOOKUP($E35,Hybrid!$1:$1048576,L$2,FALSE) -> 2272.5718 | M35: =+VLOOKUP($E35,Hybrid!$1:$1048576,M$2,FALSE) -> 2248.5516 | ... AO35: =+VLOOKUP($E35,Hybrid!$1:$1048576,AO$2,FALSE) -> 1454.1661
D36: class F | E36: AUTO_cf_cfut_0 | F36: =+VLOOKUP($E36,Hybrid!$1:$1048576,F$2,FALSE) -> 1243.6668 | G36: =+VLOOKUP($E36,Hybrid!$1:$1048576,G$2,FALSE) -> 1210.6549 | H36: =+VLOOKUP($E36,Hybrid!$1:$1048576,H$2,FALSE) -> 1182.7476 | I36: =+VLOOKUP($E36,Hybrid!$1:$1048576,I$2,FALSE) -> 1157.3995 | J36: =+VLOOKUP($E36,Hybrid!$1:$1048576,J$2,FALSE) -> 1133.0829 | K36: =+VLOOKUP($E36,Hybrid!$1:$1048576,K$2,FALSE) -> 1108.9242 | L36: =+VLOOKUP($E36,Hybrid!$1:$1048576,L$2,FALSE) -> 1084.4506 | M36: =+VLOOKUP($E36,Hybrid!$1:$1048576,M$2,FALSE) -> 1059.4277 | ... AO36: =+VLOOKUP($E36,Hybrid!$1:$1048576,AO$2,FALSE) -> 325.27338
D37: class G | E37: AUTO_cg_cfut_0 | F37: =+VLOOKUP($E37,Hybrid!$1:$1048576,F$2,FALSE) -> 2239.6206 | G37: =+VLOOKUP($E37,Hybrid!$1:$1048576,G$2,FALSE) -> 2183.2559 | H37: =+VLOOKUP($E37,Hybrid!$1:$1048576,H$2,FALSE) -> 2133.1946 | I37: =+VLOOKUP($E37,Hybrid!$1:$1048576,I$2,FALSE) -> 2084.5006 | J37: =+VLOOKUP($E37,Hybrid!$1:$1048576,J$2,FALSE) -> 2034.5555 | K37: =+VLOOKUP($E37,Hybrid!$1:$1048576,K$2,FALSE) -> 1982.161 | L37: =+VLOOKUP($E37,Hybrid!$1:$1048576,L$2,FALSE) -> 1926.9369 | M37: =+VLOOKUP($E37,Hybrid!$1:$1048576,M$2,FALSE) -> 1868.9489 | ... AO37: =+VLOOKUP($E37,Hybrid!$1:$1048576,AO$2,FALSE) -> 385.16287
C38: ELEC | E38: AUTO_cele_0 | F38: =+VLOOKUP($E38,Hybrid!$1:$1048576,F$2,FALSE) -> 44.765 | G38: =+VLOOKUP($E38,Hybrid!$1:$1048576,G$2,FALSE) -> 62.448716 | H38: =+VLOOKUP($E38,Hybrid!$1:$1048576,H$2,FALSE) -> 80.963971 | I38: =+VLOOKUP($E38,Hybrid!$1:$1048576,I$2,FALSE) -> 99.823967 | J38: =+VLOOKUP($E38,Hybrid!$1:$1048576,J$2,FALSE) -> 118.71772 | K38: =+VLOOKUP($E38,Hybrid!$1:$1048576,K$2,FALSE) -> 137.4542 | L38: =+VLOOKUP($E38,Hybrid!$1:$1048576,L$2,FALSE) -> 155.92054 | M38: =+VLOOKUP($E38,Hybrid!$1:$1048576,M$2,FALSE) -> 174.05324 | ... AO38: =+VLOOKUP($E38,Hybrid!$1:$1048576,AO$2,FALSE) -> 567.61281
D39: class A | E39: AUTO_ca_cele_0 | F39: =+VLOOKUP($E39,Hybrid!$1:$1048576,F$2,FALSE) -> 9.8427899 | G39: =+VLOOKUP($E39,Hybrid!$1:$1048576,G$2,FALSE) -> 14.990816 | H39: =+VLOOKUP($E39,Hybrid!$1:$1048576,H$2,FALSE) -> 20.422984 | I39: =+VLOOKUP($E39,Hybrid!$1:$1048576,I$2,FALSE) -> 26.012773 | J39: =+VLOOKUP($E39,Hybrid!$1:$1048576,J$2,FALSE) -> 31.67695 | K39: =+VLOOKUP($E39,Hybrid!$1:$1048576,K$2,FALSE) -> 37.362607 | L39: =+VLOOKUP($E39,Hybrid!$1:$1048576,L$2,FALSE) -> 43.037132 | M39: =+VLOOKUP($E39,Hybrid!$1:$1048576,M$2,FALSE) -> 48.681062 | ... AO39: =+VLOOKUP($E39,Hybrid!$1:$1048576,AO$2,FALSE) -> 195.65638
D40: class B | E40: AUTO_cb_cele_0 | F40: =+VLOOKUP($E40,Hybrid!$1:$1048576,F$2,FALSE) -> 11.445717 | G40: =+VLOOKUP($E40,Hybrid!$1:$1048576,G$2,FALSE) -> 16.302056 | H40: =+VLOOKUP($E40,Hybrid!$1:$1048576,H$2,FALSE) -> 21.423897 | I40: =+VLOOKUP($E40,Hybrid!$1:$1048576,I$2,FALSE) -> 26.687145 | J40: =+VLOOKUP($E40,Hybrid!$1:$1048576,J$2,FALSE) -> 32.010429 | K40: =+VLOOKUP($E40,Hybrid!$1:$1048576,K$2,FALSE) -> 37.342129 | L40: =+VLOOKUP($E40,Hybrid!$1:$1048576,L$2,FALSE) -> 42.650406 | M40: =+VLOOKUP($E40,Hybrid!$1:$1048576,M$2,FALSE) -> 47.916154 | ... AO40: =+VLOOKUP($E40,Hybrid!$1:$1048576,AO$2,FALSE) -> 177.032
D41: class C | E41: AUTO_cc_cele_0 | F41: =+VLOOKUP($E41,Hybrid!$1:$1048576,F$2,FALSE) -> 9.4015406 | G41: =+VLOOKUP($E41,Hybrid!$1:$1048576,G$2,FALSE) -> 12.69964 | H41: =+VLOOKUP($E41,Hybrid!$1:$1048576,H$2,FALSE) -> 16.176695 | I41: =+VLOOKUP($E41,Hybrid!$1:$1048576,I$2,FALSE) -> 19.745034 | J41: =+VLOOKUP($E41,Hybrid!$1:$1048576,J$2,FALSE) -> 23.347366 | K41: =+VLOOKUP($E41,Hybrid!$1:$1048576,K$2,FALSE) -> 26.947438 | L41: =+VLOOKUP($E41,Hybrid!$1:$1048576,L$2,FALSE) -> 30.522894 | M41: =+VLOOKUP($E41,Hybrid!$1:$1048576,M$2,FALSE) -> 34.060269 | ... AO41: =+VLOOKUP($E41,Hybrid!$1:$1048576,AO$2,FALSE) -> 115.62675
D42: class D | E42: AUTO_cd_cele_0 | F42: =+VLOOKUP($E42,Hybrid!$1:$1048576,F$2,FALSE) -> 5.7700713 | G42: =+VLOOKUP($E42,Hybrid!$1:$1048576,G$2,FALSE) -> 7.5646068 | H42: =+VLOOKUP($E42,Hybrid!$1:$1048576,H$2,FALSE) -> 9.4403133 | I42: =+VLOOKUP($E42,Hybrid!$1:$1048576,I$2,FALSE) -> 11.343637 | J42: =+VLOOKUP($E42,Hybrid!$1:$1048576,J$2,FALSE) -> 13.239824 | K42: =+VLOOKUP($E42,Hybrid!$1:$1048576,K$2,FALSE) -> 15.106985 | L42: =+VLOOKUP($E42,Hybrid!$1:$1048576,L$2,FALSE) -> 16.931634 | M42: =+VLOOKUP($E42,Hybrid!$1:$1048576,M$2,FALSE) -> 18.705614 | ... AO42: =+VLOOKUP($E42,Hybrid!$1:$1048576,AO$2,FALSE) -> 45.588511
D43: class E | E43: AUTO_ce_cele_0 | F43: =+VLOOKUP($E43,Hybrid!$1:$1048576,F$2,FALSE) -> 3.4730441 | G43: =+VLOOKUP($E43,Hybrid!$1:$1048576,G$2,FALSE) -> 4.5739757 | H43: =+VLOOKUP($E43,Hybrid!$1:$1048576,H$2,FALSE) -> 5.7146977 | I43: =+VLOOKUP($E43,Hybrid!$1:$1048576,I$2,FALSE) -> 6.8601644 | J43: =+VLOOKUP($E43,Hybrid!$1:$1048576,J$2,FALSE) -> 7.9881131 | K43: =+VLOOKUP($E43,Hybrid!$1:$1048576,K$2,FALSE) -> 9.0848797 | L43: =+VLOOKUP($E43,Hybrid!$1:$1048576,L$2,FALSE) -> 10.142321 | M43: =+VLOOKUP($E43,Hybrid!$1:$1048576,M$2,FALSE) -> 11.155733 | ... AO43: =+VLOOKUP($E43,Hybrid!$1:$1048576,AO$2,FALSE) -> 22.141075
D44: class F | E44: AUTO_cf_cele_0 | F44: =+VLOOKUP($E44,Hybrid!$1:$1048576,F$2,FALSE) -> 1.7251505 | G44: =+VLOOKUP($E44,Hybrid!$1:$1048576,G$2,FALSE) -> 2.2454556 | H44: =+VLOOKUP($E44,Hybrid!$1:$1048576,H$2,FALSE) -> 2.7684618 | I44: =+VLOOKUP($E44,Hybrid!$1:$1048576,I$2,FALSE) -> 3.2743104 | J44: =+VLOOKUP($E44,Hybrid!$1:$1048576,J$2,FALSE) -> 3.7515155 | K44: =+VLOOKUP($E44,Hybrid!$1:$1048576,K$2,FALSE) -> 4.1939767 | L44: =+VLOOKUP($E44,Hybrid!$1:$1048576,L$2,FALSE) -> 4.5988845 | M44: =+VLOOKUP($E44,Hybrid!$1:$1048576,M$2,FALSE) -> 4.9653764 | ... AO44: =+VLOOKUP($E44,Hybrid!$1:$1048576,AO$2,FALSE) -> 5.2345643
D45: class G | E45: AUTO_cg_cele_0 | F45: =+VLOOKUP($E45,Hybrid!$1:$1048576,F$2,FALSE) -> 3.1066862 | G45: =+VLOOKUP($E45,Hybrid!$1:$1048576,G$2,FALSE) -> 4.0721666 | H45: =+VLOOKUP($E45,Hybrid!$1:$1048576,H$2,FALSE) -> 5.0169226 | I45: =+VLOOKUP($E45,Hybrid!$1:$1048576,I$2,FALSE) -> 5.9009041 | J45: =+VLOOKUP($E45,Hybrid!$1:$1048576,J$2,FALSE) -> 6.703518 | K45: =+VLOOKUP($E45,Hybrid!$1:$1048576,K$2,FALSE) -> 7.4161806 | L45: =+VLOOKUP($E45,Hybrid!$1:$1048576,L$2,FALSE) -> 8.0372735 | M45: =+VLOOKUP($E45,Hybrid!$1:$1048576,M$2,FALSE) -> 8.5690304 | ... AO45: =+VLOOKUP($E45,Hybrid!$1:$1048576,AO$2,FALSE) -> 6.3335345
C46: GAS | E46: AUTO_cgas_0 | F46: =+VLOOKUP($E46,Hybrid!$1:$1048576,F$2,FALSE) -> 1.936 | G46: =+VLOOKUP($E46,Hybrid!$1:$1048576,G$2,FALSE) -> 1.9920385 | H46: =+VLOOKUP($E46,Hybrid!$1:$1048576,H$2,FALSE) -> 2.058513 | I46: =+VLOOKUP($E46,Hybrid!$1:$1048576,I$2,FALSE) -> 2.1305753 | J46: =+VLOOKUP($E46,Hybrid!$1:$1048576,J$2,FALSE) -> 2.2050832 | K46: =+VLOOKUP($E46,Hybrid!$1:$1048576,K$2,FALSE) -> 2.2800657 | L46: =+VLOOKUP($E46,Hybrid!$1:$1048576,L$2,FALSE) -> 2.3543231 | M46: =+VLOOKUP($E46,Hybrid!$1:$1048576,M$2,FALSE) -> 2.4271484 | ... AO46: =+VLOOKUP($E46,Hybrid!$1:$1048576,AO$2,FALSE) -> 3.7739113
D47: class A | E47: AUTO_ca_cgas_0 | F47: =+VLOOKUP($E47,Hybrid!$1:$1048576,F$2,FALSE) -> 0.4256817 | G47: =+VLOOKUP($E47,Hybrid!$1:$1048576,G$2,FALSE) -> 0.4494557 | H47: =+VLOOKUP($E47,Hybrid!$1:$1048576,H$2,FALSE) -> 0.47618363 | I47: =+VLOOKUP($E47,Hybrid!$1:$1048576,I$2,FALSE) -> 0.50461174 | J47: =+VLOOKUP($E47,Hybrid!$1:$1048576,J$2,FALSE) -> 0.53390617 | K47: =+VLOOKUP($E47,Hybrid!$1:$1048576,K$2,FALSE) -> 0.56352909 | L47: =+VLOOKUP($E47,Hybrid!$1:$1048576,L$2,FALSE) -> 0.59314311 | M47: =+VLOOKUP($E47,Hybrid!$1:$1048576,M$2,FALSE) -> 0.6225422 | ... AO47: =+VLOOKUP($E47,Hybrid!$1:$1048576,AO$2,FALSE) -> 1.3010962
D48: class B | E48: AUTO_cb_cgas_0 | F48: =+VLOOKUP($E48,Hybrid!$1:$1048576,F$2,FALSE) -> 0.49500523 | G48: =+VLOOKUP($E48,Hybrid!$1:$1048576,G$2,FALSE) -> 0.51237735 | H48: =+VLOOKUP($E48,Hybrid!$1:$1048576,H$2,FALSE) -> 0.53282707 | I48: =+VLOOKUP($E48,Hybrid!$1:$1048576,I$2,FALSE) -> 0.55510706 | J48: =+VLOOKUP($E48,Hybrid!$1:$1048576,J$2,FALSE) -> 0.57838511 | K48: =+VLOOKUP($E48,Hybrid!$1:$1048576,K$2,FALSE) -> 0.60212053 | L48: =+VLOOKUP($E48,Hybrid!$1:$1048576,L$2,FALSE) -> 0.62596932 | M48: =+VLOOKUP($E48,Hybrid!$1:$1048576,M$2,FALSE) -> 0.64971611 | ... AO48: =+VLOOKUP($E48,Hybrid!$1:$1048576,AO$2,FALSE) -> 1.1696796
D49: class C | E49: AUTO_cc_cgas_0 | F49: =+VLOOKUP($E49,Hybrid!$1:$1048576,F$2,FALSE) -> 0.40659852 | G49: =+VLOOKUP($E49,Hybrid!$1:$1048576,G$2,FALSE) -> 0.41458692 | H49: =+VLOOKUP($E49,Hybrid!$1:$1048576,H$2,FALSE) -> 0.42489006 | I49: =+VLOOKUP($E49,Hybrid!$1:$1048576,I$2,FALSE) -> 0.43661388 | J49: =+VLOOKUP($E49,Hybrid!$1:$1048576,J$2,FALSE) -> 0.44916009 | K49: =+VLOOKUP($E49,Hybrid!$1:$1048576,K$2,FALSE) -> 0.46213734 | L49: =+VLOOKUP($E49,Hybrid!$1:$1048576,L$2,FALSE) -> 0.47529342 | M49: =+VLOOKUP($E49,Hybrid!$1:$1048576,M$2,FALSE) -> 0.48846693 | ... AO49: =+VLOOKUP($E49,Hybrid!$1:$1048576,AO$2,FALSE) -> 0.760856
D50: class D | E50: AUTO_cd_cgas_0 | F50: =+VLOOKUP($E50,Hybrid!$1:$1048576,F$2,FALSE) -> 0.24954447 | G50: =+VLOOKUP($E50,Hybrid!$1:$1048576,G$2,FALSE) -> 0.2523605 | H50: =+VLOOKUP($E50,Hybrid!$1:$1048576,H$2,FALSE) -> 0.25638798 | I50: =+VLOOKUP($E50,Hybrid!$1:$1048576,I$2,FALSE) -> 0.26108963 | J50: =+VLOOKUP($E50,Hybrid!$1:$1048576,J$2,FALSE) -> 0.2661123 | K50: =+VLOOKUP($E50,Hybrid!$1:$1048576,K$2,FALSE) -> 0.27122926 | L50: =+VLOOKUP($E50,Hybrid!$1:$1048576,L$2,FALSE) -> 0.27629699 | M50: =+VLOOKUP($E50,Hybrid!$1:$1048576,M$2,FALSE) -> 0.28122528 | ... AO50: =+VLOOKUP($E50,Hybrid!$1:$1048576,AO$2,FALSE) -> 0.31327503
D51: class E | E51: AUTO_ce_cgas_0 | F51: =+VLOOKUP($E51,Hybrid!$1:$1048576,F$2,FALSE) -> 0.15020247 | G51: =+VLOOKUP($E51,Hybrid!$1:$1048576,G$2,FALSE) -> 0.15208636 | H51: =+VLOOKUP($E51,Hybrid!$1:$1048576,H$2,FALSE) -> 0.15461234 | I51: =+VLOOKUP($E51,Hybrid!$1:$1048576,I$2,FALSE) -> 0.15743309 | J51: =+VLOOKUP($E51,Hybrid!$1:$1048576,J$2,FALSE) -> 0.16032595 | K51: =+VLOOKUP($E51,Hybrid!$1:$1048576,K$2,FALSE) -> 0.16315238 | L51: =+VLOOKUP($E51,Hybrid!$1:$1048576,L$2,FALSE) -> 0.16582827 | M51: =+VLOOKUP($E51,Hybrid!$1:$1048576,M$2,FALSE) -> 0.16830371 | ... AO51: =+VLOOKUP($E51,Hybrid!$1:$1048576,AO$2,FALSE) -> 0.14957306
D52: class F | E52: AUTO_cf_cgas_0 | F52: =+VLOOKUP($E52,Hybrid!$1:$1048576,F$2,FALSE) -> 0.074609436 | G52: =+VLOOKUP($E52,Hybrid!$1:$1048576,G$2,FALSE) -> 0.075303854 | H52: =+VLOOKUP($E52,Hybrid!$1:$1048576,H$2,FALSE) -> 0.076167883 | I52: =+VLOOKUP($E52,Hybrid!$1:$1048576,I$2,FALSE) -> 0.077010461 | J52: =+VLOOKUP($E52,Hybrid!$1:$1048576,J$2,FALSE) -> 0.077721316 | K52: =+VLOOKUP($E52,Hybrid!$1:$1048576,K$2,FALSE) -> 0.078242029 | L52: =+VLOOKUP($E52,Hybrid!$1:$1048576,L$2,FALSE) -> 0.0785458 | M52: =+VLOOKUP($E52,Hybrid!$1:$1048576,M$2,FALSE) -> 0.078624438 | ... AO52: =+VLOOKUP($E52,Hybrid!$1:$1048576,AO$2,FALSE) -> 0.035616963
D53: class G | E53: AUTO_cg_cgas_0 | F53: =+VLOOKUP($E53,Hybrid!$1:$1048576,F$2,FALSE) -> 0.13435819 | G53: =+VLOOKUP($E53,Hybrid!$1:$1048576,G$2,FALSE) -> 0.13586779 | H53: =+VLOOKUP($E53,Hybrid!$1:$1048576,H$2,FALSE) -> 0.13744409 | I53: =+VLOOKUP($E53,Hybrid!$1:$1048576,I$2,FALSE) -> 0.13870945 | J53: =+VLOOKUP($E53,Hybrid!$1:$1048576,J$2,FALSE) -> 0.13947226 | K53: =+VLOOKUP($E53,Hybrid!$1:$1048576,K$2,FALSE) -> 0.13965509 | L53: =+VLOOKUP($E53,Hybrid!$1:$1048576,L$2,FALSE) -> 0.13924622 | M53: =+VLOOKUP($E53,Hybrid!$1:$1048576,M$2,FALSE) -> 0.13826967 | ... AO53: =+VLOOKUP($E53,Hybrid!$1:$1048576,AO$2,FALSE) -> 0.043814475
C54: TOTAL SALES SHOCK | E54: NEWAUTO_2 | F54: =+VLOOKUP($E54,Hybrid!$1:$1048576,F$2,FALSE) -> 1886.229 | G54: =+VLOOKUP($E54,Hybrid!$1:$1048576,G$2,FALSE) -> 2121.806 | H54: =+VLOOKUP($E54,Hybrid!$1:$1048576,H$2,FALSE) -> 2286.103 | I54: =+VLOOKUP($E54,Hybrid!$1:$1048576,I$2,FALSE) -> 2400.5287 | J54: =+VLOOKUP($E54,Hybrid!$1:$1048576,J$2,FALSE) -> 2480.7808 | K54: =+VLOOKUP($E54,Hybrid!$1:$1048576,K$2,FALSE) -> 2537.837 | L54: =+VLOOKUP($E54,Hybrid!$1:$1048576,L$2,FALSE) -> 2581.4773 | M54: =+VLOOKUP($E54,Hybrid!$1:$1048576,M$2,FALSE) -> 2618.2022 | ... AO54: =+VLOOKUP($E54,Hybrid!$1:$1048576,AO$2,FALSE) -> 2825.2831
C55: OIL | E55: NEWAUTO_cfut_2 | F55: =+VLOOKUP($E55,Hybrid!$1:$1048576,F$2,FALSE) -> 1868.803 | G55: =+VLOOKUP($E55,Hybrid!$1:$1048576,G$2,FALSE) -> 2102.1722 | H55: =+VLOOKUP($E55,Hybrid!$1:$1048576,H$2,FALSE) -> 2264.8333 | I55: =+VLOOKUP($E55,Hybrid!$1:$1048576,I$2,FALSE) -> 2377.9791 | J55: =+VLOOKUP($E55,Hybrid!$1:$1048576,J$2,FALSE) -> 2457.1346 | K55: =+VLOOKUP($E55,Hybrid!$1:$1048576,K$2,FALSE) -> 2513.1323 | L55: =+VLOOKUP($E55,Hybrid!$1:$1048576,L$2,FALSE) -> 2555.6166 | M55: =+VLOOKUP($E55,Hybrid!$1:$1048576,M$2,FALSE) -> 2591.0143 | ... AO55: =+VLOOKUP($E55,Hybrid!$1:$1048576,AO$2,FALSE) -> 2134.8214
D56: class A | E56: NEWAUTO_ca_cfut_2 | F56: =+VLOOKUP($E56,Hybrid!$1:$1048576,F$2,FALSE) -> 528.68437 | G56: =+VLOOKUP($E56,Hybrid!$1:$1048576,G$2,FALSE) -> 598.23806 | H56: =+VLOOKUP($E56,Hybrid!$1:$1048576,H$2,FALSE) -> 650.2446 | I56: =+VLOOKUP($E56,Hybrid!$1:$1048576,I$2,FALSE) -> 689.67493 | J56: =+VLOOKUP($E56,Hybrid!$1:$1048576,J$2,FALSE) -> 720.25057 | K56: =+VLOOKUP($E56,Hybrid!$1:$1048576,K$2,FALSE) -> 744.6554 | L56: =+VLOOKUP($E56,Hybrid!$1:$1048576,L$2,FALSE) -> 765.44423 | M56: =+VLOOKUP($E56,Hybrid!$1:$1048576,M$2,FALSE) -> 784.34266 | ... AO56: =+VLOOKUP($E56,Hybrid!$1:$1048576,AO$2,FALSE) -> 835.48108
D57: class B | E57: NEWAUTO_cb_cfut_2 | F57: =+VLOOKUP($E57,Hybrid!$1:$1048576,F$2,FALSE) -> 507.56689 | G57: =+VLOOKUP($E57,Hybrid!$1:$1048576,G$2,FALSE) -> 573.64916 | H57: =+VLOOKUP($E57,Hybrid!$1:$1048576,H$2,FALSE) -> 622.34368 | I57: =+VLOOKUP($E57,Hybrid!$1:$1048576,I$2,FALSE) -> 658.59889 | J57: =+VLOOKUP($E57,Hybrid!$1:$1048576,J$2,FALSE) -> 686.09931 | K57: =+VLOOKUP($E57,Hybrid!$1:$1048576,K$2,FALSE) -> 707.47846 | L57: =+VLOOKUP($E57,Hybrid!$1:$1048576,L$2,FALSE) -> 725.21286 | M57: =+VLOOKUP($E57,Hybrid!$1:$1048576,M$2,FALSE) -> 740.98417 | ... AO57: =+VLOOKUP($E57,Hybrid!$1:$1048576,AO$2,FALSE) -> 683.10047
D58: class C | E58: NEWAUTO_cc_cfut_2 | F58: =+VLOOKUP($E58,Hybrid!$1:$1048576,F$2,FALSE) -> 351.33496 | G58: =+VLOOKUP($E58,Hybrid!$1:$1048576,G$2,FALSE) -> 396.60029 | H58: =+VLOOKUP($E58,Hybrid!$1:$1048576,H$2,FALSE) -> 429.46134 | I58: =+VLOOKUP($E58,Hybrid!$1:$1048576,I$2,FALSE) -> 453.4672 | J58: =+VLOOKUP($E58,Hybrid!$1:$1048576,J$2,FALSE) -> 471.24691 | K58: =+VLOOKUP($E58,Hybrid!$1:$1048576,K$2,FALSE) -> 484.66391 | L58: =+VLOOKUP($E58,Hybrid!$1:$1048576,L$2,FALSE) -> 495.45006 | M58: =+VLOOKUP($E58,Hybrid!$1:$1048576,M$2,FALSE) -> 504.78742 | ... AO58: =+VLOOKUP($E58,Hybrid!$1:$1048576,AO$2,FALSE) -> 403.88776
D59: class D | E59: NEWAUTO_cd_cfut_2 | F59: =+VLOOKUP($E59,Hybrid!$1:$1048576,F$2,FALSE) -> 194.72927 | G59: =+VLOOKUP($E59,Hybrid!$1:$1048576,G$2,FALSE) -> 218.62509 | H59: =+VLOOKUP($E59,Hybrid!$1:$1048576,H$2,FALSE) -> 234.78025 | I59: =+VLOOKUP($E59,Hybrid!$1:$1048576,I$2,FALSE) -> 245.47874 | J59: =+VLOOKUP($E59,Hybrid!$1:$1048576,J$2,FALSE) -> 252.39244 | K59: =+VLOOKUP($E59,Hybrid!$1:$1048576,K$2,FALSE) -> 256.68252 | L59: =+VLOOKUP($E59,Hybrid!$1:$1048576,L$2,FALSE) -> 259.36974 | M59: =+VLOOKUP($E59,Hybrid!$1:$1048576,M$2,FALSE) -> 261.13769 | ... AO59: =+VLOOKUP($E59,Hybrid!$1:$1048576,AO$2,FALSE) -> 150.58953
D60: class E | E60: NEWAUTO_ce_cfut_2 | F60: =+VLOOKUP($E60,Hybrid!$1:$1048576,F$2,FALSE) -> 119.79027 | G60: =+VLOOKUP($E60,Hybrid!$1:$1048576,G$2,FALSE) -> 133.83042 | H60: =+VLOOKUP($E60,Hybrid!$1:$1048576,H$2,FALSE) -> 142.64325 | I60: =+VLOOKUP($E60,Hybrid!$1:$1048576,I$2,FALSE) -> 147.81966 | J60: =+VLOOKUP($E60,Hybrid!$1:$1048576,J$2,FALSE) -> 150.51251 | K60: =+VLOOKUP($E60,Hybrid!$1:$1048576,K$2,FALSE) -> 151.5093 | L60: =+VLOOKUP($E60,Hybrid!$1:$1048576,L$2,FALSE) -> 151.47284 | M60: =+VLOOKUP($E60,Hybrid!$1:$1048576,M$2,FALSE) -> 150.84157 | ... AO60: =+VLOOKUP($E60,Hybrid!$1:$1048576,AO$2,FALSE) -> 55.029359
D61: class F | E61: NEWAUTO_cf_cfut_2 | F61: =+VLOOKUP($E61,Hybrid!$1:$1048576,F$2,FALSE) -> 57.932893 | G61: =+VLOOKUP($E61,Hybrid!$1:$1048576,G$2,FALSE) -> 63.609061 | H61: =+VLOOKUP($E61,Hybrid!$1:$1048576,H$2,FALSE) -> 66.033114 | I61: =+VLOOKUP($E61,Hybrid!$1:$1048576,I$2,FALSE) -> 66.321974 | J61: =+VLOOKUP($E61,Hybrid!$1:$1048576,J$2,FALSE) -> 65.263207 | K61: =+VLOOKUP($E61,Hybrid!$1:$1048576,K$2,FALSE) -> 63.372895 | L61: =+VLOOKUP($E61,Hybrid!$1:$1048576,L$2,FALSE) -> 61.035555 | M61: =+VLOOKUP($E61,Hybrid!$1:$1048576,M$2,FALSE) -> 58.490348 | ... AO61: =+VLOOKUP($E61,Hybrid!$1:$1048576,AO$2,FALSE) -> 4.8403462
D62: class G | E62: NEWAUTO_cg_cfut_2 | F62: =+VLOOKUP($E62,Hybrid!$1:$1048576,F$2,FALSE) -> 108.76433 | G62: =+VLOOKUP($E62,Hybrid!$1:$1048576,G$2,FALSE) -> 117.62012 | H62: =+VLOOKUP($E62,Hybrid!$1:$1048576,H$2,FALSE) -> 119.32708 | I62: =+VLOOKUP($E62,Hybrid!$1:$1048576,I$2,FALSE) -> 116.61768 | J62: =+VLOOKUP($E62,Hybrid!$1:$1048576,J$2,FALSE) -> 111.36964 | K62: =+VLOOKUP($E62,Hybrid!$1:$1048576,K$2,FALSE) -> 104.76986 | L62: =+VLOOKUP($E62,Hybrid!$1:$1048576,L$2,FALSE) -> 97.631367 | M62: =+VLOOKUP($E62,Hybrid!$1:$1048576,M$2,FALSE) -> 90.430451 | ... AO62: =+VLOOKUP($E62,Hybrid!$1:$1048576,AO$2,FALSE) -> 1.8928765
C63: ELEC | E63: NEWAUTO_cele_2 | F63: =+VLOOKUP($E63,Hybrid!$1:$1048576,F$2,FALSE) -> 17.269 | G63: =+VLOOKUP($E63,Hybrid!$1:$1048576,G$2,FALSE) -> 19.457169 | H63: =+VLOOKUP($E63,Hybrid!$1:$1048576,H$2,FALSE) -> 21.079389 | I63: =+VLOOKUP($E63,Hybrid!$1:$1048576,I$2,FALSE) -> 22.349837 | J63: =+VLOOKUP($E63,Hybrid!$1:$1048576,J$2,FALSE) -> 23.439846 | K63: =+VLOOKUP($E63,Hybrid!$1:$1048576,K$2,FALSE) -> 24.493574 | L63: =+VLOOKUP($E63,Hybrid!$1:$1048576,L$2,FALSE) -> 25.645995 | M63: =+VLOOKUP($E63,Hybrid!$1:$1048576,M$2,FALSE) -> 26.970187 | ... AO63: =+VLOOKUP($E63,Hybrid!$1:$1048576,AO$2,FALSE) -> 690.28232
D64: class A | E64: NEWAUTO_ca_cele_2 | F64: =+VLOOKUP($E64,Hybrid!$1:$1048576,F$2,FALSE) -> 4.8854001 | G64: =+VLOOKUP($E64,Hybrid!$1:$1048576,G$2,FALSE) -> 5.5376974 | H64: =+VLOOKUP($E64,Hybrid!$1:$1048576,H$2,FALSE) -> 6.0545843 | I64: =+VLOOKUP($E64,Hybrid!$1:$1048576,I$2,FALSE) -> 6.4882358 | J64: =+VLOOKUP($E64,Hybrid!$1:$1048576,J$2,FALSE) -> 6.8824648 | K64: =+VLOOKUP($E64,Hybrid!$1:$1048576,K$2,FALSE) -> 7.2768624 | L64: =+VLOOKUP($E64,Hybrid!$1:$1048576,L$2,FALSE) -> 7.7108498 | M64: =+VLOOKUP($E64,Hybrid!$1:$1048576,M$2,FALSE) -> 8.2063244 | ... AO64: =+VLOOKUP($E64,Hybrid!$1:$1048576,AO$2,FALSE) -> 274.39294
D65: class B | E65: NEWAUTO_cb_cele_2 | F65: =+VLOOKUP($E65,Hybrid!$1:$1048576,F$2,FALSE) -> 4.6902604 | G65: =+VLOOKUP($E65,Hybrid!$1:$1048576,G$2,FALSE) -> 5.310837 | H65: =+VLOOKUP($E65,Hybrid!$1:$1048576,H$2,FALSE) -> 5.7983659 | I65: =+VLOOKUP($E65,Hybrid!$1:$1048576,I$2,FALSE) -> 6.2047942 | J65: =+VLOOKUP($E65,Hybrid!$1:$1048576,J$2,FALSE) -> 6.5735543 | K65: =+VLOOKUP($E65,Hybrid!$1:$1048576,K$2,FALSE) -> 6.9437051 | L65: =+VLOOKUP($E65,Hybrid!$1:$1048576,L$2,FALSE) -> 7.3536604 | M65: =+VLOOKUP($E65,Hybrid!$1:$1048576,M$2,FALSE) -> 7.8242502 | ... AO65: =+VLOOKUP($E65,Hybrid!$1:$1048576,AO$2,FALSE) -> 236.63077
D66: class C | E66: NEWAUTO_cc_cele_2 | F66: =+VLOOKUP($E66,Hybrid!$1:$1048576,F$2,FALSE) -> 3.246572 | G66: =+VLOOKUP($E66,Hybrid!$1:$1048576,G$2,FALSE) -> 3.6722039 | H66: =+VLOOKUP($E66,Hybrid!$1:$1048576,H$2,FALSE) -> 4.0035834 | I66: =+VLOOKUP($E66,Hybrid!$1:$1048576,I$2,FALSE) -> 4.27793 | J66: =+VLOOKUP($E66,Hybrid!$1:$1048576,J$2,FALSE) -> 4.5262093 | K66: =+VLOOKUP($E66,Hybrid!$1:$1048576,K$2,FALSE) -> 4.7761076 | L66: =+VLOOKUP($E66,Hybrid!$1:$1048576,L$2,FALSE) -> 5.0545188 | M66: =+VLOOKUP($E66,Hybrid!$1:$1048576,M$2,FALSE) -> 5.3756744 | ... AO66: =+VLOOKUP($E66,Hybrid!$1:$1048576,AO$2,FALSE) -> 146.69188
D67: class D | E67: NEWAUTO_cd_cele_2 | F67: =+VLOOKUP($E67,Hybrid!$1:$1048576,F$2,FALSE) -> 1.7994298 | G67: =+VLOOKUP($E67,Hybrid!$1:$1048576,G$2,FALSE) -> 2.0222371 | H67: =+VLOOKUP($E67,Hybrid!$1:$1048576,H$2,FALSE) -> 2.1789386 | I67: =+VLOOKUP($E67,Hybrid!$1:$1048576,I$2,FALSE) -> 2.2916149 | J67: =+VLOOKUP($E67,Hybrid!$1:$1048576,J$2,FALSE) -> 2.3771979 | K67: =+VLOOKUP($E67,Hybrid!$1:$1048576,K$2,FALSE) -> 2.4487728 | L67: =+VLOOKUP($E67,Hybrid!$1:$1048576,L$2,FALSE) -> 2.5180832 | M67: =+VLOOKUP($E67,Hybrid!$1:$1048576,M$2,FALSE) -> 2.591747 | ... AO67: =+VLOOKUP($E67,Hybrid!$1:$1048576,AO$2,FALSE) -> 23.141079
D68: class E | E68: NEWAUTO_ce_cele_2 | F68: =+VLOOKUP($E68,Hybrid!$1:$1048576,F$2,FALSE) -> 1.1069429 | G68: =+VLOOKUP($E68,Hybrid!$1:$1048576,G$2,FALSE) -> 1.2380931 | H68: =+VLOOKUP($E68,Hybrid!$1:$1048576,H$2,FALSE) -> 1.3247165 | I68: =+VLOOKUP($E68,Hybrid!$1:$1048576,I$2,FALSE) -> 1.3820709 | J68: =+VLOOKUP($E68,Hybrid!$1:$1048576,J$2,FALSE) -> 1.4216685 | K68: =+VLOOKUP($E68,Hybrid!$1:$1048576,K$2,FALSE) -> 1.4521728 | L68: =+VLOOKUP($E68,Hybrid!$1:$1048576,L$2,FALSE) -> 1.4809772 | M68: =+VLOOKUP($E68,Hybrid!$1:$1048576,M$2,FALSE) -> 1.5120132 | ... AO68: =+VLOOKUP($E68,Hybrid!$1:$1048576,AO$2,FALSE) -> 8.8067577
D69: class F | E69: NEWAUTO_cf_cele_2 | F69: =+VLOOKUP($E69,Hybrid!$1:$1048576,F$2,FALSE) -> 0.535339 | G69: =+VLOOKUP($E69,Hybrid!$1:$1048576,G$2,FALSE) -> 0.58825 | H69: =+VLOOKUP($E69,Hybrid!$1:$1048576,H$2,FALSE) -> 0.61227637 | I69: =+VLOOKUP($E69,Hybrid!$1:$1048576,I$2,FALSE) -> 0.61778488 | J69: =+VLOOKUP($E69,Hybrid!$1:$1048576,J$2,FALSE) -> 0.61215256 | K69: =+VLOOKUP($E69,Hybrid!$1:$1048576,K$2,FALSE) -> 0.60035693 | L69: =+VLOOKUP($E69,Hybrid!$1:$1048576,L$2,FALSE) -> 0.58607167 | M69: =+VLOOKUP($E69,Hybrid!$1:$1048576,M$2,FALSE) -> 0.57123405 | ... AO69: =+VLOOKUP($E69,Hybrid!$1:$1048576,AO$2,FALSE) -> 0.44199909
D70: class G | E70: NEWAUTO_cg_cele_2 | F70: =+VLOOKUP($E70,Hybrid!$1:$1048576,F$2,FALSE) -> 1.0050558 | G70: =+VLOOKUP($E70,Hybrid!$1:$1048576,G$2,FALSE) -> 1.0878508 | H70: =+VLOOKUP($E70,Hybrid!$1:$1048576,H$2,FALSE) -> 1.1069242 | I70: =+VLOOKUP($E70,Hybrid!$1:$1048576,I$2,FALSE) -> 1.0874058 | J70: =+VLOOKUP($E70,Hybrid!$1:$1048576,J$2,FALSE) -> 1.0465984 | K70: =+VLOOKUP($E70,Hybrid!$1:$1048576,K$2,FALSE) -> 0.99559627 | L70: =+VLOOKUP($E70,Hybrid!$1:$1048576,L$2,FALSE) -> 0.94183363 | M70: =+VLOOKUP($E70,Hybrid!$1:$1048576,M$2,FALSE) -> 0.88894387 | ... AO70: =+VLOOKUP($E70,Hybrid!$1:$1048576,AO$2,FALSE) -> 0.17688497
C71: GAS | E71: NEWAUTO_cgas_2 | F71: =+VLOOKUP($E71,Hybrid!$1:$1048576,F$2,FALSE) -> 0.157 | G71: =+VLOOKUP($E71,Hybrid!$1:$1048576,G$2,FALSE) -> 0.17660558 | H71: =+VLOOKUP($E71,Hybrid!$1:$1048576,H$2,FALSE) -> 0.1902709 | I71: =+VLOOKUP($E71,Hybrid!$1:$1048576,I$2,FALSE) -> 0.19977639 | J71: =+VLOOKUP($E71,Hybrid!$1:$1048576,J$2,FALSE) -> 0.20642632 | K71: =+VLOOKUP($E71,Hybrid!$1:$1048576,K$2,FALSE) -> 0.21113075 | L71: =+VLOOKUP($E71,Hybrid!$1:$1048576,L$2,FALSE) -> 0.2146999 | M71: =+VLOOKUP($E71,Hybrid!$1:$1048576,M$2,FALSE) -> 0.21767369 | ... AO71: =+VLOOKUP($E71,Hybrid!$1:$1048576,AO$2,FALSE) -> 0.17934847
D72: class A | E72: NEWAUTO_ca_cgas_2 | F72: =+VLOOKUP($E72,Hybrid!$1:$1048576,F$2,FALSE) -> 0.0444153 | G72: =+VLOOKUP($E72,Hybrid!$1:$1048576,G$2,FALSE) -> 0.050258575 | H72: =+VLOOKUP($E72,Hybrid!$1:$1048576,H$2,FALSE) -> 0.054627696 | I72: =+VLOOKUP($E72,Hybrid!$1:$1048576,I$2,FALSE) -> 0.057940277 | J72: =+VLOOKUP($E72,Hybrid!$1:$1048576,J$2,FALSE) -> 0.060508967 | K72: =+VLOOKUP($E72,Hybrid!$1:$1048576,K$2,FALSE) -> 0.062559241 | L72: =+VLOOKUP($E72,Hybrid!$1:$1048576,L$2,FALSE) -> 0.064305732 | M72: =+VLOOKUP($E72,Hybrid!$1:$1048576,M$2,FALSE) -> 0.065893408 | ... AO72: =+VLOOKUP($E72,Hybrid!$1:$1048576,AO$2,FALSE) -> 0.070189597
D73: class B | E73: NEWAUTO_cb_cgas_2 | F73: =+VLOOKUP($E73,Hybrid!$1:$1048576,F$2,FALSE) -> 0.0426412 | G73: =+VLOOKUP($E73,Hybrid!$1:$1048576,G$2,FALSE) -> 0.048192837 | H73: =+VLOOKUP($E73,Hybrid!$1:$1048576,H$2,FALSE) -> 0.052283712 | I73: =+VLOOKUP($E73,Hybrid!$1:$1048576,I$2,FALSE) -> 0.055329549 | J73: =+VLOOKUP($E73,Hybrid!$1:$1048576,J$2,FALSE) -> 0.057639886 | K73: =+VLOOKUP($E73,Hybrid!$1:$1048576,K$2,FALSE) -> 0.059435969 | L73: =+VLOOKUP($E73,Hybrid!$1:$1048576,L$2,FALSE) -> 0.060925854 | M73: =+VLOOKUP($E73,Hybrid!$1:$1048576,M$2,FALSE) -> 0.062250818 | ... AO73: =+VLOOKUP($E73,Hybrid!$1:$1048576,AO$2,FALSE) -> 0.05738795
D74: class C | E74: NEWAUTO_cc_cgas_2 | F74: =+VLOOKUP($E74,Hybrid!$1:$1048576,F$2,FALSE) -> 0.029516 | G74: =+VLOOKUP($E74,Hybrid!$1:$1048576,G$2,FALSE) -> 0.033318785 | H74: =+VLOOKUP($E74,Hybrid!$1:$1048576,H$2,FALSE) -> 0.036079474 | I74: =+VLOOKUP($E74,Hybrid!$1:$1048576,I$2,FALSE) -> 0.038096231 | J74: =+VLOOKUP($E74,Hybrid!$1:$1048576,J$2,FALSE) -> 0.039589922 | K74: =+VLOOKUP($E74,Hybrid!$1:$1048576,K$2,FALSE) -> 0.040717098 | L74: =+VLOOKUP($E74,Hybrid!$1:$1048576,L$2,FALSE) -> 0.041623252 | M74: =+VLOOKUP($E74,Hybrid!$1:$1048576,M$2,FALSE) -> 0.042407693 | ... AO74: =+VLOOKUP($E74,Hybrid!$1:$1048576,AO$2,FALSE) -> 0.033931013
D75: class D | E75: NEWAUTO_cd_cgas_2 | F75: =+VLOOKUP($E75,Hybrid!$1:$1048576,F$2,FALSE) -> 0.0163594 | G75: =+VLOOKUP($E75,Hybrid!$1:$1048576,G$2,FALSE) -> 0.018366911 | H75: =+VLOOKUP($E75,Hybrid!$1:$1048576,H$2,FALSE) -> 0.019724123 | I75: =+VLOOKUP($E75,Hybrid!$1:$1048576,I$2,FALSE) -> 0.020622913 | J75: =+VLOOKUP($E75,Hybrid!$1:$1048576,J$2,FALSE) -> 0.02120374 | K75: =+VLOOKUP($E75,Hybrid!$1:$1048576,K$2,FALSE) -> 0.021564154 | L75: =+VLOOKUP($E75,Hybrid!$1:$1048576,L$2,FALSE) -> 0.02178991 | M75: =+VLOOKUP($E75,Hybrid!$1:$1048576,M$2,FALSE) -> 0.021938437 | ... AO75: =+VLOOKUP($E75,Hybrid!$1:$1048576,AO$2,FALSE) -> 0.012651176
D76: class E | E76: NEWAUTO_ce_cgas_2 | F76: =+VLOOKUP($E76,Hybrid!$1:$1048576,F$2,FALSE) -> 0.0100637 | G76: =+VLOOKUP($E76,Hybrid!$1:$1048576,G$2,FALSE) -> 0.011243226 | H76: =+VLOOKUP($E76,Hybrid!$1:$1048576,H$2,FALSE) -> 0.011983602 | I76: =+VLOOKUP($E76,Hybrid!$1:$1048576,I$2,FALSE) -> 0.012418477 | J76: =+VLOOKUP($E76,Hybrid!$1:$1048576,J$2,FALSE) -> 0.012644705 | K76: =+VLOOKUP($E76,Hybrid!$1:$1048576,K$2,FALSE) -> 0.012728447 | L76: =+VLOOKUP($E76,Hybrid!$1:$1048576,L$2,FALSE) -> 0.012725384 | M76: =+VLOOKUP($E76,Hybrid!$1:$1048576,M$2,FALSE) -> 0.01267235 | ... AO76: =+VLOOKUP($E76,Hybrid!$1:$1048576,AO$2,FALSE) -> 0.0046230712
D77: class F | E77: NEWAUTO_cf_cgas_2 | F77: =+VLOOKUP($E77,Hybrid!$1:$1048576,F$2,FALSE) -> 0.004867 | G77: =+VLOOKUP($E77,Hybrid!$1:$1048576,G$2,FALSE) -> 0.0053438605 | H77: =+VLOOKUP($E77,Hybrid!$1:$1048576,H$2,FALSE) -> 0.0055475076 | I77: =+VLOOKUP($E77,Hybrid!$1:$1048576,I$2,FALSE) -> 0.005571775 | J77: =+VLOOKUP($E77,Hybrid!$1:$1048576,J$2,FALSE) -> 0.005482827 | K77: =+VLOOKUP($E77,Hybrid!$1:$1048576,K$2,FALSE) -> 0.00532402 | L77: =+VLOOKUP($E77,Hybrid!$1:$1048576,L$2,FALSE) -> 0.0051276577 | M77: =+VLOOKUP($E77,Hybrid!$1:$1048576,M$2,FALSE) -> 0.0049138323 | ... AO77: =+VLOOKUP($E77,Hybrid!$1:$1048576,AO$2,FALSE) -> 0.0004066423
D78: class G | E78: NEWAUTO_cg_cgas_2 | F78: =+VLOOKUP($E78,Hybrid!$1:$1048576,F$2,FALSE) -> 0.0091374 | G78: =+VLOOKUP($E78,Hybrid!$1:$1048576,G$2,FALSE) -> 0.0098813837 | H78: =+VLOOKUP($E78,Hybrid!$1:$1048576,H$2,FALSE) -> 0.010024787 | I78: =+VLOOKUP($E78,Hybrid!$1:$1048576,I$2,FALSE) -> 0.0097971677 | J78: =+VLOOKUP($E78,Hybrid!$1:$1048576,J$2,FALSE) -> 0.0093562739 | K78: =+VLOOKUP($E78,Hybrid!$1:$1048576,K$2,FALSE) -> 0.00880182 | L78: =+VLOOKUP($E78,Hybrid!$1:$1048576,L$2,FALSE) -> 0.0082021083 | M78: =+VLOOKUP($E78,Hybrid!$1:$1048576,M$2,FALSE) -> 0.0075971522 | ... AO78: =+VLOOKUP($E78,Hybrid!$1:$1048576,AO$2,FALSE) -> 0.00015902244
C79: TOTAL SALES BASELINE | E79: NEWAUTO_0 | F79: =+VLOOKUP($E79,Hybrid!$1:$1048576,F$2,FALSE) -> 1886.229 | G79: =+VLOOKUP($E79,Hybrid!$1:$1048576,G$2,FALSE) -> 2126.9764 | H79: =+VLOOKUP($E79,Hybrid!$1:$1048576,H$2,FALSE) -> 2294.4419 | I79: =+VLOOKUP($E79,Hybrid!$1:$1048576,I$2,FALSE) -> 2411.5025 | J79: =+VLOOKUP($E79,Hybrid!$1:$1048576,J$2,FALSE) -> 2495.0188 | K79: =+VLOOKUP($E79,Hybrid!$1:$1048576,K$2,FALSE) -> 2556.7025 | L79: =+VLOOKUP($E79,Hybrid!$1:$1048576,L$2,FALSE) -> 2604.3377 | M79: =+VLOOKUP($E79,Hybrid!$1:$1048576,M$2,FALSE) -> 2642.9423 | ... AO79: =+VLOOKUP($E79,Hybrid!$1:$1048576,AO$2,FALSE) -> 3207.9058
C80: OIL | E80: NEWAUTO_cfut_0 | F80: =+VLOOKUP($E80,Hybrid!$1:$1048576,F$2,FALSE) -> 1868.803 | G80: =+VLOOKUP($E80,Hybrid!$1:$1048576,G$2,FALSE) -> 2107.3251 | H80: =+VLOOKUP($E80,Hybrid!$1:$1048576,H$2,FALSE) -> 2273.2378 | I80: =+VLOOKUP($E80,Hybrid!$1:$1048576,I$2,FALSE) -> 2389.2032 | J80: =+VLOOKUP($E80,Hybrid!$1:$1048576,J$2,FALSE) -> 2471.9245 | K80: =+VLOOKUP($E80,Hybrid!$1:$1048576,K$2,FALSE) -> 2533.0045 | L80: =+VLOOKUP($E80,Hybrid!$1:$1048576,L$2,FALSE) -> 2580.1565 | M80: =+VLOOKUP($E80,Hybrid!$1:$1048576,M$2,FALSE) -> 2618.3528 | ... AO80: =+VLOOKUP($E80,Hybrid!$1:$1048576,AO$2,FALSE) -> 3173.0094
D81: class A | E81: NEWAUTO_ca_cfut_0 | F81: =+VLOOKUP($E81,Hybrid!$1:$1048576,F$2,FALSE) -> 528.68437 | G81: =+VLOOKUP($E81,Hybrid!$1:$1048576,G$2,FALSE) -> 599.67283 | H81: =+VLOOKUP($E81,Hybrid!$1:$1048576,H$2,FALSE) -> 652.52066 | I81: =+VLOOKUP($E81,Hybrid!$1:$1048576,I$2,FALSE) -> 692.64252 | J81: =+VLOOKUP($E81,Hybrid!$1:$1048576,J$2,FALSE) -> 724.10354 | K81: =+VLOOKUP($E81,Hybrid!$1:$1048576,K$2,FALSE) -> 749.80735 | L81: =+VLOOKUP($E81,Hybrid!$1:$1048576,L$2,FALSE) -> 771.73922 | M81: =+VLOOKUP($E81,Hybrid!$1:$1048576,M$2,FALSE) -> 791.21242 | ... AO81: =+VLOOKUP($E81,Hybrid!$1:$1048576,AO$2,FALSE) -> 1205.5752
D82: class B | E82: NEWAUTO_cb_cfut_0 | F82: =+VLOOKUP($E82,Hybrid!$1:$1048576,F$2,FALSE) -> 507.56689 | G82: =+VLOOKUP($E82,Hybrid!$1:$1048576,G$2,FALSE) -> 575.04323 | H82: =+VLOOKUP($E82,Hybrid!$1:$1048576,H$2,FALSE) -> 624.6004 | I82: =+VLOOKUP($E82,Hybrid!$1:$1048576,I$2,FALSE) -> 661.60014 | J82: =+VLOOKUP($E82,Hybrid!$1:$1048576,J$2,FALSE) -> 690.05535 | K82: =+VLOOKUP($E82,Hybrid!$1:$1048576,K$2,FALSE) -> 712.81733 | L82: =+VLOOKUP($E82,Hybrid!$1:$1048576,L$2,FALSE) -> 731.8247 | M82: =+VLOOKUP($E82,Hybrid!$1:$1048576,M$2,FALSE) -> 748.3529 | ... AO82: =+VLOOKUP($E82,Hybrid!$1:$1048576,AO$2,FALSE) -> 1030.812
D83: class C | E83: NEWAUTO_cc_cfut_0 | F83: =+VLOOKUP($E83,Hybrid!$1:$1048576,F$2,FALSE) -> 351.33496 | G83: =+VLOOKUP($E83,Hybrid!$1:$1048576,G$2,FALSE) -> 397.57666 | H83: =+VLOOKUP($E83,Hybrid!$1:$1048576,H$2,FALSE) -> 431.07235 | I83: =+VLOOKUP($E83,Hybrid!$1:$1048576,I$2,FALSE) -> 455.64815 | J83: =+VLOOKUP($E83,Hybrid!$1:$1048576,J$2,FALSE) -> 474.15911 | K83: =+VLOOKUP($E83,Hybrid!$1:$1048576,K$2,FALSE) -> 488.62358 | L83: =+VLOOKUP($E83,Hybrid!$1:$1048576,L$2,FALSE) -> 500.40662 | M83: =+VLOOKUP($E83,Hybrid!$1:$1048576,M$2,FALSE) -> 510.40171 | ... AO83: =+VLOOKUP($E83,Hybrid!$1:$1048576,AO$2,FALSE) -> 636.27918
D84: class D | E84: NEWAUTO_cd_cfut_0 | F84: =+VLOOKUP($E84,Hybrid!$1:$1048576,F$2,FALSE) -> 194.72927 | G84: =+VLOOKUP($E84,Hybrid!$1:$1048576,G$2,FALSE) -> 219.16848 | H84: =+VLOOKUP($E84,Hybrid!$1:$1048576,H$2,FALSE) -> 235.68358 | I84: =+VLOOKUP($E84,Hybrid!$1:$1048576,I$2,FALSE) -> 246.70455 | J84: =+VLOOKUP($E84,Hybrid!$1:$1048576,J$2,FALSE) -> 254.0236 | K84: =+VLOOKUP($E84,Hybrid!$1:$1048576,K$2,FALSE) -> 258.8825 | L84: =+VLOOKUP($E84,Hybrid!$1:$1048576,L$2,FALSE) -> 262.10336 | M84: =+VLOOKUP($E84,Hybrid!$1:$1048576,M$2,FALSE) -> 264.21365 | ... AO84: =+VLOOKUP($E84,Hybrid!$1:$1048576,AO$2,FALSE) -> 209.56755
D85: class E | E85: NEWAUTO_ce_cfut_0 | F85: =+VLOOKUP($E85,Hybrid!$1:$1048576,F$2,FALSE) -> 119.79027 | G85: =+VLOOKUP($E85,Hybrid!$1:$1048576,G$2,FALSE) -> 134.16754 | H85: =+VLOOKUP($E85,Hybrid!$1:$1048576,H$2,FALSE) -> 143.21188 | I85: =+VLOOKUP($E85,Hybrid!$1:$1048576,I$2,FALSE) -> 148.59992 | J85: =+VLOOKUP($E85,Hybrid!$1:$1048576,J$2,FALSE) -> 151.5567 | K85: =+VLOOKUP($E85,Hybrid!$1:$1048576,K$2,FALSE) -> 152.91812 | L85: =+VLOOKUP($E85,Hybrid!$1:$1048576,L$2,FALSE) -> 153.22891 | M85: =+VLOOKUP($E85,Hybrid!$1:$1048576,M$2,FALSE) -> 152.83366 | ... AO85: =+VLOOKUP($E85,Hybrid!$1:$1048576,AO$2,FALSE) -> 80.483787
D86: class F | E86: NEWAUTO_cf_cfut_0 | F86: =+VLOOKUP($E86,Hybrid!$1:$1048576,F$2,FALSE) -> 57.932893 | G86: =+VLOOKUP($E86,Hybrid!$1:$1048576,G$2,FALSE) -> 63.771508 | H86: =+VLOOKUP($E86,Hybrid!$1:$1048576,H$2,FALSE) -> 66.307034 | I86: =+VLOOKUP($E86,Hybrid!$1:$1048576,I$2,FALSE) -> 66.694489 | J86: =+VLOOKUP($E86,Hybrid!$1:$1048576,J$2,FALSE) -> 65.753401 | K86: =+VLOOKUP($E86,Hybrid!$1:$1048576,K$2,FALSE) -> 64.018949 | L86: =+VLOOKUP($E86,Hybrid!$1:$1048576,L$2,FALSE) -> 61.82402 | M86: =+VLOOKUP($E86,Hybrid!$1:$1048576,M$2,FALSE) -> 59.370209 | ... AO86: =+VLOOKUP($E86,Hybrid!$1:$1048576,AO$2,FALSE) -> 7.2222627
D87: class G | E87: NEWAUTO_cg_cfut_0 | F87: =+VLOOKUP($E87,Hybrid!$1:$1048576,F$2,FALSE) -> 108.76433 | G87: =+VLOOKUP($E87,Hybrid!$1:$1048576,G$2,FALSE) -> 117.92484 | H87: =+VLOOKUP($E87,Hybrid!$1:$1048576,H$2,FALSE) -> 119.84185 | I87: =+VLOOKUP($E87,Hybrid!$1:$1048576,I$2,FALSE) -> 117.31344 | J87: =+VLOOKUP($E87,Hybrid!$1:$1048576,J$2,FALSE) -> 112.27278 | K87: =+VLOOKUP($E87,Hybrid!$1:$1048576,K$2,FALSE) -> 105.93669 | L87: =+VLOOKUP($E87,Hybrid!$1:$1048576,L$2,FALSE) -> 99.029629 | M87: =+VLOOKUP($E87,Hybrid!$1:$1048576,M$2,FALSE) -> 91.968224 | ... AO87: =+VLOOKUP($E87,Hybrid!$1:$1048576,AO$2,FALSE) -> 3.069401
C88: ELEC | E88: NEWAUTO_cele_0 | F88: =+VLOOKUP($E88,Hybrid!$1:$1048576,F$2,FALSE) -> 17.269 | G88: =+VLOOKUP($E88,Hybrid!$1:$1048576,G$2,FALSE) -> 19.474316 | H88: =+VLOOKUP($E88,Hybrid!$1:$1048576,H$2,FALSE) -> 21.013204 | I88: =+VLOOKUP($E88,Hybrid!$1:$1048576,I$2,FALSE) -> 22.098555 | J88: =+VLOOKUP($E88,Hybrid!$1:$1048576,J$2,FALSE) -> 22.886708 | K88: =+VLOOKUP($E88,Hybrid!$1:$1048576,K$2,FALSE) -> 23.485189 | L88: =+VLOOKUP($E88,Hybrid!$1:$1048576,L$2,FALSE) -> 23.964516 | M88: =+VLOOKUP($E88,Hybrid!$1:$1048576,M$2,FALSE) -> 24.369515 | ... AO88: =+VLOOKUP($E88,Hybrid!$1:$1048576,AO$2,FALSE) -> 34.629865
D89: class A | E89: NEWAUTO_ca_cele_0 | F89: =+VLOOKUP($E89,Hybrid!$1:$1048576,F$2,FALSE) -> 4.8854001 | G89: =+VLOOKUP($E89,Hybrid!$1:$1048576,G$2,FALSE) -> 5.5417375 | H89: =+VLOOKUP($E89,Hybrid!$1:$1048576,H$2,FALSE) -> 6.0318007 | I89: =+VLOOKUP($E89,Hybrid!$1:$1048576,I$2,FALSE) -> 6.4067081 | J89: =+VLOOKUP($E89,Hybrid!$1:$1048576,J$2,FALSE) -> 6.7046879 | K89: =+VLOOKUP($E89,Hybrid!$1:$1048576,K$2,FALSE) -> 6.9527355 | L89: =+VLOOKUP($E89,Hybrid!$1:$1048576,L$2,FALSE) -> 7.1690295 | M89: =+VLOOKUP($E89,Hybrid!$1:$1048576,M$2,FALSE) -> 7.365415 | ... AO89: =+VLOOKUP($E89,Hybrid!$1:$1048576,AO$2,FALSE) -> 13.091208
D90: class B | E90: NEWAUTO_cb_cele_0 | F90: =+VLOOKUP($E90,Hybrid!$1:$1048576,F$2,FALSE) -> 4.6902604 | G90: =+VLOOKUP($E90,Hybrid!$1:$1048576,G$2,FALSE) -> 5.3141673 | H90: =+VLOOKUP($E90,Hybrid!$1:$1048576,H$2,FALSE) -> 5.7739232 | I90: =+VLOOKUP($E90,Hybrid!$1:$1048576,I$2,FALSE) -> 6.120204 | J90: =+VLOOKUP($E90,Hybrid!$1:$1048576,J$2,FALSE) -> 6.39077 | K90: =+VLOOKUP($E90,Hybrid!$1:$1048576,K$2,FALSE) -> 6.6121172 | L90: =+VLOOKUP($E90,Hybrid!$1:$1048576,L$2,FALSE) -> 6.8019619 | M90: =+VLOOKUP($E90,Hybrid!$1:$1048576,M$2,FALSE) -> 6.9717638 | ... AO90: =+VLOOKUP($E90,Hybrid!$1:$1048576,AO$2,FALSE) -> 11.373165
D91: class C | E91: NEWAUTO_cc_cele_0 | F91: =+VLOOKUP($E91,Hybrid!$1:$1048576,F$2,FALSE) -> 3.246572 | G91: =+VLOOKUP($E91,Hybrid!$1:$1048576,G$2,FALSE) -> 3.6741607 | H91: =+VLOOKUP($E91,Hybrid!$1:$1048576,H$2,FALSE) -> 3.9850408 | I91: =+VLOOKUP($E91,Hybrid!$1:$1048576,I$2,FALSE) -> 4.2154068 | J91: =+VLOOKUP($E91,Hybrid!$1:$1048576,J$2,FALSE) -> 4.3921339 | K91: =+VLOOKUP($E91,Hybrid!$1:$1048576,K$2,FALSE) -> 4.5339665 | L91: =+VLOOKUP($E91,Hybrid!$1:$1048576,L$2,FALSE) -> 4.6533531 | M91: =+VLOOKUP($E91,Hybrid!$1:$1048576,M$2,FALSE) -> 4.7582905 | ... AO91: =+VLOOKUP($E91,Hybrid!$1:$1048576,AO$2,FALSE) -> 7.1191279
D92: class D | E92: NEWAUTO_cd_cele_0 | F92: =+VLOOKUP($E92,Hybrid!$1:$1048576,F$2,FALSE) -> 1.7994298 | G92: =+VLOOKUP($E92,Hybrid!$1:$1048576,G$2,FALSE) -> 2.0253384 | H92: =+VLOOKUP($E92,Hybrid!$1:$1048576,H$2,FALSE) -> 2.1782908 | I92: =+VLOOKUP($E92,Hybrid!$1:$1048576,I$2,FALSE) -> 2.2809357 | J92: =+VLOOKUP($E92,Hybrid!$1:$1048576,J$2,FALSE) -> 2.3499331 | K92: =+VLOOKUP($E92,Hybrid!$1:$1048576,K$2,FALSE) -> 2.3967536 | L92: =+VLOOKUP($E92,Hybrid!$1:$1048576,L$2,FALSE) -> 2.4289281 | M92: =+VLOOKUP($E92,Hybrid!$1:$1048576,M$2,FALSE) -> 2.4512462 | ... AO92: =+VLOOKUP($E92,Hybrid!$1:$1048576,AO$2,FALSE) -> 2.1165445
D93: class E | E93: NEWAUTO_ce_cele_0 | F93: =+VLOOKUP($E93,Hybrid!$1:$1048576,F$2,FALSE) -> 1.1069429 | G93: =+VLOOKUP($E93,Hybrid!$1:$1048576,G$2,FALSE) -> 1.2398534 | H93: =+VLOOKUP($E93,Hybrid!$1:$1048576,H$2,FALSE) -> 1.3236809 | I93: =+VLOOKUP($E93,Hybrid!$1:$1048576,I$2,FALSE) -> 1.3740547 | J93: =+VLOOKUP($E93,Hybrid!$1:$1048576,J$2,FALSE) -> 1.4023553 | K93: =+VLOOKUP($E93,Hybrid!$1:$1048576,K$2,FALSE) -> 1.4162911 | L93: =+VLOOKUP($E93,Hybrid!$1:$1048576,L$2,FALSE) -> 1.4208363 | M93: =+VLOOKUP($E93,Hybrid!$1:$1048576,M$2,FALSE) -> 1.4191046 | ... AO93: =+VLOOKUP($E93,Hybrid!$1:$1048576,AO$2,FALSE) -> 0.82719028
D94: class F | E94: NEWAUTO_cf_cele_0 | F94: =+VLOOKUP($E94,Hybrid!$1:$1048576,F$2,FALSE) -> 0.535339 | G94: =+VLOOKUP($E94,Hybrid!$1:$1048576,G$2,FALSE) -> 0.58931108 | H94: =+VLOOKUP($E94,Hybrid!$1:$1048576,H$2,FALSE) -> 0.61282442 | I94: =+VLOOKUP($E94,Hybrid!$1:$1048576,I$2,FALSE) -> 0.61658713 | J94: =+VLOOKUP($E94,Hybrid!$1:$1048576,J$2,FALSE) -> 0.60817749 | K94: =+VLOOKUP($E94,Hybrid!$1:$1048576,K$2,FALSE) -> 0.59252181 | L94: =+VLOOKUP($E94,Hybrid!$1:$1048576,L$2,FALSE) -> 0.57266692 | M94: =+VLOOKUP($E94,Hybrid!$1:$1048576,M$2,FALSE) -> 0.55044725 | ... AO94: =+VLOOKUP($E94,Hybrid!$1:$1048576,AO$2,FALSE) -> 0.071730931
D95: class G | E95: NEWAUTO_cg_cele_0 | F95: =+VLOOKUP($E95,Hybrid!$1:$1048576,F$2,FALSE) -> 1.0050558 | G95: =+VLOOKUP($E95,Hybrid!$1:$1048576,G$2,FALSE) -> 1.0897479 | H95: =+VLOOKUP($E95,Hybrid!$1:$1048576,H$2,FALSE) -> 1.1076427 | I95: =+VLOOKUP($E95,Hybrid!$1:$1048576,I$2,FALSE) -> 1.0846584 | J95: =+VLOOKUP($E95,Hybrid!$1:$1048576,J$2,FALSE) -> 1.0386501 | K95: =+VLOOKUP($E95,Hybrid!$1:$1048576,K$2,FALSE) -> 0.98080334 | L95: =+VLOOKUP($E95,Hybrid!$1:$1048576,L$2,FALSE) -> 0.91774014 | M95: =+VLOOKUP($E95,Hybrid!$1:$1048576,M$2,FALSE) -> 0.85324779 | ... AO95: =+VLOOKUP($E95,Hybrid!$1:$1048576,AO$2,FALSE) -> 0.030897972
C96: GAS | E96: NEWAUTO_cgas_0 | F96: =+VLOOKUP($E96,Hybrid!$1:$1048576,F$2,FALSE) -> 0.157 | G96: =+VLOOKUP($E96,Hybrid!$1:$1048576,G$2,FALSE) -> 0.17703848 | H96: =+VLOOKUP($E96,Hybrid!$1:$1048576,H$2,FALSE) -> 0.19097697 | I96: =+VLOOKUP($E96,Hybrid!$1:$1048576,I$2,FALSE) -> 0.20071934 | J96: =+VLOOKUP($E96,Hybrid!$1:$1048576,J$2,FALSE) -> 0.20766883 | K96: =+VLOOKUP($E96,Hybrid!$1:$1048576,K$2,FALSE) -> 0.21280023 | L96: =+VLOOKUP($E96,Hybrid!$1:$1048576,L$2,FALSE) -> 0.21676151 | M96: =+VLOOKUP($E96,Hybrid!$1:$1048576,M$2,FALSE) -> 0.21997042 | ... AO96: =+VLOOKUP($E96,Hybrid!$1:$1048576,AO$2,FALSE) -> 0.26656768
D97: class A | E97: NEWAUTO_ca_cgas_0 | F97: =+VLOOKUP($E97,Hybrid!$1:$1048576,F$2,FALSE) -> 0.0444153 | G97: =+VLOOKUP($E97,Hybrid!$1:$1048576,G$2,FALSE) -> 0.050379111 | H97: =+VLOOKUP($E97,Hybrid!$1:$1048576,H$2,FALSE) -> 0.05481891 | I97: =+VLOOKUP($E97,Hybrid!$1:$1048576,I$2,FALSE) -> 0.058189588 | J97: =+VLOOKUP($E97,Hybrid!$1:$1048576,J$2,FALSE) -> 0.060832659 | K97: =+VLOOKUP($E97,Hybrid!$1:$1048576,K$2,FALSE) -> 0.062992062 | L97: =+VLOOKUP($E97,Hybrid!$1:$1048576,L$2,FALSE) -> 0.06483458 | M97: =+VLOOKUP($E97,Hybrid!$1:$1048576,M$2,FALSE) -> 0.066470542 | ... AO97: =+VLOOKUP($E97,Hybrid!$1:$1048576,AO$2,FALSE) -> 0.10128157
D98: class B | E98: NEWAUTO_cb_cgas_0 | F98: =+VLOOKUP($E98,Hybrid!$1:$1048576,F$2,FALSE) -> 0.0426412 | G98: =+VLOOKUP($E98,Hybrid!$1:$1048576,G$2,FALSE) -> 0.048309954 | H98: =+VLOOKUP($E98,Hybrid!$1:$1048576,H$2,FALSE) -> 0.052473301 | I98: =+VLOOKUP($E98,Hybrid!$1:$1048576,I$2,FALSE) -> 0.055581686 | J98: =+VLOOKUP($E98,Hybrid!$1:$1048576,J$2,FALSE) -> 0.057972236 | K98: =+VLOOKUP($E98,Hybrid!$1:$1048576,K$2,FALSE) -> 0.059884493 | L98: =+VLOOKUP($E98,Hybrid!$1:$1048576,L$2,FALSE) -> 0.061481322 | M98: =+VLOOKUP($E98,Hybrid!$1:$1048576,M$2,FALSE) -> 0.062869872 | ... AO98: =+VLOOKUP($E98,Hybrid!$1:$1048576,AO$2,FALSE) -> 0.086599542
D99: class C | E99: NEWAUTO_cc_cgas_0 | F99: =+VLOOKUP($E99,Hybrid!$1:$1048576,F$2,FALSE) -> 0.029516 | G99: =+VLOOKUP($E99,Hybrid!$1:$1048576,G$2,FALSE) -> 0.033400811 | H99: =+VLOOKUP($E99,Hybrid!$1:$1048576,H$2,FALSE) -> 0.036214817 | I99: =+VLOOKUP($E99,Hybrid!$1:$1048576,I$2,FALSE) -> 0.038279455 | J99: =+VLOOKUP($E99,Hybrid!$1:$1048576,J$2,FALSE) -> 0.039834578 | K99: =+VLOOKUP($E99,Hybrid!$1:$1048576,K$2,FALSE) -> 0.041049753 | L99: =+VLOOKUP($E99,Hybrid!$1:$1048576,L$2,FALSE) -> 0.042039659 | M99: =+VLOOKUP($E99,Hybrid!$1:$1048576,M$2,FALSE) -> 0.042879356 | ... AO99: =+VLOOKUP($E99,Hybrid!$1:$1048576,AO$2,FALSE) -> 0.053454448
D100: class D | E100: NEWAUTO_cd_cgas_0 | F100: =+VLOOKUP($E100,Hybrid!$1:$1048576,F$2,FALSE) -> 0.0163594 | G100: =+VLOOKUP($E100,Hybrid!$1:$1048576,G$2,FALSE) -> 0.018412562 | H100: =+VLOOKUP($E100,Hybrid!$1:$1048576,H$2,FALSE) -> 0.019800012 | I100: =+VLOOKUP($E100,Hybrid!$1:$1048576,I$2,FALSE) -> 0.020725895 | J100: =+VLOOKUP($E100,Hybrid!$1:$1048576,J$2,FALSE) -> 0.021340775 | K100: =+VLOOKUP($E100,Hybrid!$1:$1048576,K$2,FALSE) -> 0.021748976 | L100: =+VLOOKUP($E100,Hybrid!$1:$1048576,L$2,FALSE) -> 0.022019564 | M100: =+VLOOKUP($E100,Hybrid!$1:$1048576,M$2,FALSE) -> 0.022196851 | ... AO100: =+VLOOKUP($E100,Hybrid!$1:$1048576,AO$2,FALSE) -> 0.017605979
...

Sheet date
A1: =Hybrid!A1 -> _date_ | B1: =Hybrid!B1 -> 42005 | C1: =Hybrid!C1 -> 42370 | D1: =Hybrid!D1 -> 42736 | E1: =Hybrid!E1 -> 43101 | F1: =Hybrid!F1 -> 43466 | G1: =Hybrid!G1 -> 43831 | H1: =Hybrid!H1 -> 44197 | ... AK1: =Hybrid!AK1 -> 54789
B2: =TEXT(B1,"jj mm aaaa") -> 01 01 2015 | C2: =TEXT(C1,"jj mm aaaa") -> 01 01 2016 | D2: =TEXT(D1,"jj mm aaaa") -> 01 01 2017 | E2: =TEXT(E1,"jj mm aaaa") -> 01 01 2018 | F2: =TEXT(F1,"jj mm aaaa") -> 01 01 2019 | G2: =TEXT(G1,"jj mm aaaa") -> 01 01 2020 | H2: =TEXT(H1,"jj mm aaaa") -> 01 01 2021 | I2: =TEXT(I1,"jj mm aaaa") -> 01 01 2022 | ... AK2: =TEXT(AK1,"jj mm aaaa") -> 01 01 2050
B3: =RIGHT(B2,4) -> 2015 | C3: =RIGHT(C2,4) -> 2016 | D3: =RIGHT(D2,4) -> 2017 | E3: =RIGHT(E2,4) -> 2018 | F3: =RIGHT(F2,4) -> 2019 | G3: =RIGHT(G2,4) -> 2020 | H3: =RIGHT(H2,4) -> 2021 | I3: =RIGHT(I2,4) -> 2022 | ... AK3: =RIGHT(AK2,4) -> 2050

Sheet Emissions
A1: _date_ | B1: 42005 | C1: 42370 | D1: 42736 | E1: 43101 | F1: 43466 | G1: 43831 | H1: 44197 | I1: 44562 | J1: 44927 | K1: 45292 | L1: 45658 | M1: 46023 | N1: 46388 | O1: 46753 | P1: 47119 | Q1: 47484 | R1: 47849 | S1: 48214 | T1: 48580 | U1: 48945 | V1: 49310 | W1: 49675 | X1: 50041 | Y1: 50406 | Z1: 50771 | AA1: 51136 | AB1: 51502 | AC1: 51867 | AD1: 52232 | AE1: 52597 | AF1: 52963 | AG1: 53328 | AH1: 53693 | AI1: 54058 | AJ1: 54424 | AK1: 54789
A2: ems_2 | B2: 470.0039 | C2: 472.83603 | D2: 474.82849 | E2: 476.66484 | F2: 478.51486 | G2: 480.33131 | H2: 482.16006 | I2: 484.12721 | J2: 486.25674 | K2: 488.51337 | L2: 490.83035 | M2: 493.12615 | N2: 495.31487 | O2: 497.3136 | P2: 499.04795 | Q2: 500.45607 | R2: 501.58207 | S2: 502.54725 | T2: 503.43464 | U2: 504.29792 | V2: 505.17101 | W2: 506.07484 | X2: 507.02175 | Y2: 508.01828 | Z2: 509.06703 | AA2: 510.16788 | AB2: 511.31884 | AC2: 512.51662 | AD2: 513.75711 | AE2: 515.03572 | AF2: 516.34759 | AG2: 517.68791 | AH2: 519.05204 | AI2: 520.43573 | AJ2: 521.83525 | AK2: 523.24755
A3: ems_ch_2 | B3: 129.15358 | C3: 128.76844 | D3: 127.85718 | E3: 126.91251 | F3: 126.06444 | G3: 125.30537 | H3: 124.64342 | I3: 124.10122 | J3: 123.65738 | K3: 123.2774 | L3: 122.92597 | M3: 122.57142 | N3: 122.18707 | O3: 121.75145 | P3: 121.24819 | Q3: 120.66572 | R3: 120.02815 | S3: 119.37662 | T3: 118.72805 | U3: 118.08762 | V3: 117.45493 | W3: 116.82711 | X3: 116.2002 | Y3: 115.56979 | Z3: 114.93135 | AA3: 114.28022 | AB3: 113.61173 | AC3: 112.92114 | AD3: 112.20369 | AE3: 111.45462 | AF3: 110.66921 | AG3: 109.84283 | AH3: 108.97107 | AI3: 108.04978 | AJ3: 107.07523 | AK3: 106.04417
A4: ems_ch_2+ems_ci_2 | B4: 349.86054 | C4: 351.43208 | D4: 352.17187 | E4: 352.71574 | F4: 353.21997 | G4: 353.63894 | H4: 354.02606 | I4: 354.51518 | J4: 355.13547 | K4: 355.85521 | L4: 356.61034 | M4: 357.32151 | N4: 357.90489 | O4: 358.27969 | P4: 358.37381 | Q4: 358.12797 | R4: 357.58984 | S4: 356.88392 | T4: 356.09414 | U4: 355.27393 | V4: 354.45639 | W4: 353.66131 | X4: 352.89986 | Y4: 352.17746 | Z4: 351.49574 | AA4: 350.85375 | AB4: 350.24886 | AC4: 349.67728 | AD4: 349.13452 | AE4: 348.61565 | AF4: 348.1156 | AG4: 347.6293 | AH4: 347.15189 | AI4: 346.67884 | AJ4: 346.20613 | AK4: 345.73036
A5: ems_ci_2 | B5: 220.70697 | C5: 222.66364 | D5: 224.3147 | E5: 225.80323 | F5: 227.15553 | G5: 228.33357 | H5: 229.38264 | I5: 230.41397 | J5: 231.47809 | K5: 232.5778 | L5: 233.68436 | M5: 234.75009 | N5: 235.71782 | O5: 236.52825 | P5: 237.12563 | Q5: 237.46225 | R5: 237.56169 | S5: 237.5073 | T5: 237.36609 | U5: 237.18632 | V5: 237.00145 | W5: 236.8342 | X5: 236.69967 | Y5: 236.60767 | Z5: 236.56439 | AA5: 236.57353 | AB5: 236.63713 | AC5: 236.75614 | AD5: 236.93083 | AE5: 237.16103 | AF5: 237.4464 | AG5: 237.78647 | AH5: 238.18082 | AI5: 238.62905 | AJ5: 239.1309 | AK5: 239.68619
A6: ems_mat_2 | B6: 27.950294 | C6: 28.262122 | D6: 28.572597 | E6: 28.885878 | F6: 29.203763 | G6: 29.526446 | H6: 29.853693 | I6: 30.185514 | J6: 30.521966 | K6: 30.862957 | L6: 31.208203 | M6: 31.557239 | N6: 31.909441 | O6: 32.264058 | P6: 32.620235 | Q6: 32.977041 | R6: 33.333859 | S6: 33.690692 | T6: 34.04791 | U6: 34.405998 | V6: 34.765443 | W6: 35.126696 | X6: 35.490154 | Y6: 35.856157 | Z6: 36.224992 | AA6: 36.596898 | AB6: 36.972074 | AC6: 37.350687 | AD6: 37.73288 | AE6: 38.118775 | AF6: 38.508484 | AG6: 38.90211 | AH6: 39.299752 | AI6: 39.701508 | AJ6: 40.107477 | AK6: 40.51776
A7: ems_y_2 | B7: 92.193058 | C7: 93.141822 | D7: 94.084019 | E7: 95.06322 | F7: 96.091134 | G7: 97.165928 | H7: 98.28031 | I7: 99.426511 | J7: 100.59931 | K7: 101.7952 | L7: 103.01181 | M7: 104.2474 | N7: 105.50053 | O7: 106.76985 | P7: 108.0539 | Q7: 109.35106 | R7: 110.65837 | S7: 111.97263 | T7: 113.29259 | U7: 114.61799 | V7: 115.94918 | W7: 117.28684 | X7: 118.63174 | Y7: 119.98466 | Z7: 121.3463 | AA7: 122.71723 | AB7: 124.0979 | AC7: 125.48865 | AD7: 126.88972 | AE7: 128.30129 | AF7: 129.72351 | AG7: 131.1565 | AH7: 132.6004 | AI7: 134.05538 | AJ7: 135.52164 | AK7: 136.99943
A8: ems_sec_2 | B8: 340.85032 | C8: 344.06758 | D8: 346.97131 | E8: 349.75233 | F8: 352.45042 | G8: 355.02594 | H8: 357.51665 | I8: 360.02599 | J8: 362.59936 | K8: 365.23596 | L8: 367.90438 | M8: 370.55473 | N8: 373.1278 | O8: 375.56215 | P8: 377.79976 | Q8: 379.79036 | R8: 381.55391 | S8: 383.17063 | T8: 384.70658 | U8: 386.2103 | V8: 387.71607 | W8: 389.24773 | X8: 390.82156 | Y8: 392.44849 | Z8: 394.13568 | AA8: 395.88766 | AB8: 397.70711 | AC8: 399.59548 | AD8: 401.55342 | AE8: 403.5811 | AF8: 405.67839 | AG8: 407.84508 | AH8: 410.08097 | AI8: 412.38594 | AJ8: 414.76002 | AK8: 417.20338
A9: ems_ets_2 | B9: 126.91621 | C9: 128.03575 | D9: 128.97055 | E9: 129.80991 | F9: 130.57505 | G9: 131.24779 | H9: 131.8479 | I9: 132.4314 | J9: 133.02733 | K9: 133.63954 | L9: 134.25401 | M9: 134.84546 | N9: 135.38274 | O9: 135.83304 | P9: 136.16528 | Q9: 136.35275 | R9: 136.4057 | S9: 136.36751 | T9: 136.27583 | U9: 136.15873 | V9: 136.03587 | W9: 135.92057 | X9: 135.8216 | Y9: 135.74462 | Z9: 135.69319 | AA9: 135.66944 | AB9: 135.67462 | AC9: 135.70941 | AD9: 135.77413 | AE9: 135.86892 | AF9: 135.99383 | AG9: 136.14887 | AH9: 136.3341 | AI9: 136.54958 | AJ9: 136.79547 | AK9: 137.07197
A10: ems_nets_2 | B10: 213.93412 | C10: 216.03183 | D10: 218.00076 | E10: 219.94241 | F10: 221.87537 | G10: 223.77815 | H10: 225.66875 | I10: 227.59459 | J10: 229.57203 | K10: 231.59643 | L10: 233.65037 | M10: 235.70926 | N10: 237.74505 | O10: 239.72912 | P10: 241.63448 | Q10: 243.4376 | R10: 245.14821 | S10: 246.80312 | T10: 248.43075 | U10: 250.05157 | V10: 251.6802 | W10: 253.32717 | X10: 254.99996 | Y10: 256.70386 | Z10: 258.44249 | AA10: 260.21822 | AB10: 262.03248 | AC10: 263.88607 | AD10: 265.77929 | AE10: 267.71217 | AF10: 269.68455 | AG10: 271.6962 | AH10: 273.74687 | AI10: 275.83636 | AJ10: 277.96455 | AK10: 280.13141
A11: ems_netsi_2 | B11: 25.647636 | C11: 25.890505 | D11: 26.110082 | E11: 26.318111 | F11: 26.516486 | G11: 26.702008 | H11: 26.87982 | I11: 27.060347 | J11: 27.24744 | K11: 27.440549 | L11: 27.636482 | M11: 27.830557 | N11: 28.017372 | O11: 28.191366 | P11: 28.347265 | Q11: 28.480431 | R11: 28.592984 | S11: 28.692565 | T11: 28.784965 | U11: 28.874271 | V11: 28.963357 | W11: 29.054257 | X11: 29.148414 | Y11: 29.246839 | Z11: 29.350231 | AA11: 29.459052 | AB11: 29.57359 | AC11: 29.694006 | AD11: 29.820369 | AE11: 29.952686 | AF11: 30.090923 | AG11: 30.235019 | AH11: 30.3849 | AI11: 30.54049 | AJ11: 30.701713 | AK11: 30.8685
A12: ems_trsp_2-ems_sair_2 | B12: 24.99273 | C12: 25.238692 | D12: 25.465247 | E12: 25.684389 | F12: 25.899206 | G12: 26.107879 | H12: 26.311582 | I12: 26.515047 | J12: 26.720616 | K12: 26.928295 | L12: 27.136346 | M12: 27.341801 | N12: 27.54085 | O12: 27.729159 | P12: 27.902126 | Q12: 28.05512 | R12: 28.187882 | S12: 28.304685 | T12: 28.409396 | U12: 28.505062 | V12: 28.594034 | W12: 28.678132 | X12: 28.758775 | Y12: 28.837082 | Z12: 28.913944 | AA12: 28.990087 | AB12: 29.066107 | AC12: 29.14251 | AD12: 29.219734 | AE12: 29.298167 | AF12: 29.378163 | AG12: 29.46005 | AH12: 29.544141 | AI12: 29.630734 | AJ12: 29.720123 | AK12: 29.812594
... A819: ems_ch_cbio_0+ems_ci_cbio_0 | B819: 31.971027 | C819: 32.007879 | D819: 31.913715 | E819: 31.777071 | F819: 31.634471 | G819: 31.499044 | H819: 31.374108 | I819: 31.259284 | J819: 31.153102 | K819: 31.054017 | L819: 30.96074 | M819: 30.872295 | N819: 30.787979 | O819: 30.707301 | P819: 30.629922 | Q819: 30.555608 | R819: 30.484203 | S819: 30.415596 | T819: 30.349705 | U819: 30.286408 | V819: 30.225638 | W819: 30.167359 | X819: 30.111552 | Y819: 30.058202 | Z819: 30.007304 | AA819: 29.958849 | AB819: 29.912833 | AC819: 29.869249 | AD819: 29.828093 | AE819: 29.789358 | AF819: 29.75304 | AG819: 29.719132 | AH819: 29.68763 | AI819: 29.658527 | AJ819: 29.63182 | AK819: 29.607503

Sheet Consumption
A1: _date_ | B1: 42005 | C1: 42370 | D1: 42736 | E1: 43101 | F1: 43466 | G1: 43831 | H1: 44197 | I1: 44562 | J1: 44927 | K1: 45292 | L1: 45658 | M1: 46023 | N1: 46388 | O1: 46753 | P1: 47119 | Q1: 47484 | R1: 47849 | S1: 48214 | T1: 48580 | U1: 48945 | V1: 49310 | W1: 49675 | X1: 50041 | Y1: 50406 | Z1: 50771 | AA1: 51136 | AB1: 51502 | AC1: 51867 | AD1: 52232 | AE1: 52597 | AF1: 52963 | AG1: 53328 | AH1: 53693 | AI1: 54058 | AJ1: 54424 | AK1: 54789
A2: ch_2 | B2: 1202071.8 | C2: 1215690.3 | D2: 1229310.3 | E2: 1243013.1 | F2: 1256875.5 | G2: 1270997.6 | H2: 1285460.8 | I2: 1300296.3 | J2: 1315499.9 | K2: 1331056.7 | L2: 1346957.4 | M2: 1363202.4 | N2: 1379801.2 | O2: 1396770.3 | P2: 1414130.4 | Q2: 1431905 | R2: 1450101.3 | S2: 1468696.7 | T2: 1487656 | U2: 1506945.7 | V2: 1526542.6 | W2: 1546433.3 | X2: 1566610.7 | Y2: 1587071 | Z2: 1607810.9 | AA2: 1628826.1 | AB2: 1650110.2 | AC2: 1671655.2 | AD2: 1693451 | AE2: 1715486.1 | AF2: 1737748.4 | AG2: 1760225.1 | AH2: 1782903.7 | AI2: 1805772 | AJ2: 1828818.9 | AK2: 1852033.8
A3: ch_0 | B3: 1202071.8 | C3: 1215641.6 | D3: 1229141.5 | E3: 1242648.3 | F3: 1256238.1 | G3: 1270001.2 | H3: 1284016.1 | I3: 1298333 | J3: 1312973.1 | K3: 1327935.9 | L3: 1343208.5 | M3: 1358772.9 | N3: 1374610.8 | O3: 1390705.9 | P3: 1407045.5 | Q3: 1423620.3 | R3: 1440423.8 | S3: 1457451.5 | T3: 1474700.5 | U3: 1492169 | V3: 1509855.2 | W3: 1527757.7 | X3: 1545875.1 | Y3: 1564206 | Z3: 1582749 | AA3: 1601502.9 | AB3: 1620466.6 | AC3: 1639639.4 | AD3: 1659020.8 | AE3: 1678610.9 | AF3: 1698410.1 | AG3: 1718419.4 | AH3: 1738640.1 | AI3: 1759074.1 | AJ3: 1779723.6 | AK3: 1800591.2
A4: pch_2 | B4: 1 | C4: 1.0202623 | D4: 1.0408444 | E4: 1.0618446 | F4: 1.083382 | G4: 1.1055795 | H4: 1.1283896 | I4: 1.151736 | J4: 1.1756836 | K4: 1.2002924 | L4: 1.2256236 | M4: 1.2517441 | N4: 1.2787299 | O4: 1.306668 | P4: 1.3356569 | Q4: 1.3658072 | R4: 1.3970906 | S4: 1.4294313 | T4: 1.4628618 | U4: 1.4974028 | V4: 1.5330655 | W4: 1.5698545 | X4: 1.6077702 | Y4: 1.6468101 | Z4: 1.6869697 | AA4: 1.7282423 | AB4: 1.7706198 | AC4: 1.8140921 | AD4: 1.8586473 | AE4: 1.9042716 | AF4: 1.9509492 | AG4: 1.9986623 | AH4: 2.0473909 | AI4: 2.0971133 | AJ4: 2.1478055 | AK4: 2.1994422
A5: pch_0 | B5: 1 | C5: 1.0198987 | D5: 1.0400695 | E5: 1.0605437 | F5: 1.0813678 | G5: 1.1025858 | H5: 1.1242353 | I5: 1.146347 | J5: 1.1689465 | K5: 1.1920554 | L5: 1.2156926 | M5: 1.2398742 | N5: 1.2646147 | O5: 1.2899264 | P5: 1.3158205 | Q5: 1.3423069 | R5: 1.3693946 | S5: 1.397092 | T5: 1.4254069 | U5: 1.454347 | V5: 1.4839199 | W5: 1.5141329 | X5: 1.5449937 | Y5: 1.5765098 | Z5: 1.6086892 | AA5: 1.64154 | AB5: 1.6750706 | AC5: 1.7092899 | AD5: 1.744207 | AE5: 1.7798315 | AF5: 1.8161737 | AG5: 1.8532442 | AH5: 1.891054 | AI5: 1.9296152 | AJ5: 1.9689399 | AK5: 2.0090411
A6: ch_cagr_2 | B6: 31638 | C6: 31926.31 | D6: 32213.197 | E6: 32523.423 | F6: 32862.586 | G6: 33229.322 | H6: 33619.294 | I6: 34027.869 | J6: 34452.106 | K6: 34890.056 | L6: 35340.462 | M6: 35802.578 | N6: 36276.021 | O6: 36760.672 | P6: 37256.589 | Q6: 37763.954 | R6: 38281.902 | S6: 38809.112 | T6: 39345.253 | U6: 39890.278 | V6: 40444.218 | W6: 41007.104 | X6: 41578.934 | Y6: 42159.649 | Z6: 42749.123 | AA6: 43347.155 | AB6: 43953.48 | AC6: 44567.773 | AD6: 45189.661 | AE6: 45818.735 | AF6: 46454.567 | AG6: 47096.717 | AH6: 47744.75 | AI6: 48398.241 | AJ6: 49056.784 | AK6: 49720
A7: ch_cagr_0 | B7: 31638 | C7: 31923.619 | D7: 32206.85 | E7: 32512.452 | F7: 32845.535 | G7: 33204.073 | H7: 33584.186 | I7: 33982.118 | J7: 34394.806 | K7: 34819.912 | L7: 35255.709 | M7: 35700.938 | N7: 36154.696 | O7: 36616.348 | P7: 37085.459 | Q7: 37561.74 | R7: 38045 | S7: 38535.116 | T7: 39032.007 | U7: 39535.611 | V7: 40045.87 | W7: 40562.729 | X7: 41086.129 | Y7: 41616.009 | Z7: 42152.303 | AA7: 42694.952 | AB7: 43243.898 | AC7: 43799.093 | AD7: 44360.5 | AE7: 44928.092 | AF7: 45501.861 | AG7: 46081.809 | AH7: 46667.955 | AI7: 47260.332 | AJ7: 47858.988 | AK7: 48463.982
A8: pch_cagr_2 | B8: 1 | C8: 1.0200639 | D8: 1.0405389 | E8: 1.0614615 | F8: 1.0829052 | G8: 1.1049599 | H8: 1.1276481 | I8: 1.1509345 | J8: 1.1748158 | K8: 1.199313 | L8: 1.2244675 | M8: 1.2503383 | N8: 1.2769998 | O8: 1.3045398 | P8: 1.3330584 | Q8: 1.3626678 | R8: 1.3934134 | S8: 1.4252695 | T8: 1.4582214 | U8: 1.4922613 | V8: 1.5273867 | W8: 1.5635984 | X8: 1.6008996 | Y8: 1.6392947 | Z8: 1.6787882 | AA8: 1.7193843 | AB8: 1.761086 | AC8: 1.8038952 | AD8: 1.8478127 | AE8: 1.8928376 | AF8: 1.9389678 | AG8: 1.9861998 | AH8: 2.0345289 | AI8: 2.0839489 | AJ8: 2.1344525 | AK8: 2.1860311
A9: pch_cagr_0 | B9: 1 | C9: 1.0199097 | D9: 1.0401102 | E9: 1.0606346 | F9: 1.0815269 | G9: 1.1028261 | H9: 1.1245631 | I9: 1.1467626 | J9: 1.1694451 | K9: 1.1926287 | L9: 1.2163293 | M9: 1.2405618 | N9: 1.2653394 | O9: 1.2906742 | P9: 1.3165769 | Q9: 1.3430574 | R9: 1.3701249 | S9: 1.3977879 | T9: 1.4260546 | U9: 1.454933 | V9: 1.484431 | W9: 1.5145566 | X9: 1.545318 | Y9: 1.5767236 | Z9: 1.6087819 | AA9: 1.6415018 | AB9: 1.6748927 | AC9: 1.7089641 | AD9: 1.743726 | AE9: 1.7791888 | AF9: 1.8153636 | AG9: 1.8522615 | AH9: 1.8898946 | AI9: 1.9282753 | AJ9: 1.9674164 | AK9: 2.0073314
A10: ch_cfoo_2 | B10: 175065 | C10: 176666.16 | D10: 178264.86 | E10: 179996.63 | F10: 181891.89 | G10: 183943.73 | H10: 186127.19 | I10: 188413.71 | J10: 190785.17 | K10: 193230.44 | L10: 195743.51 | M10: 198321.9 | N10: 200965.57 | O10: 203676.02 | P10: 206455.7 | Q10: 209307.62 | R10: 212226.59 | S10: 215202.14 | T10: 218229.36 | U10: 221305.91 | V10: 224430.76 | W10: 227603.65 | X10: 230824.58 | Y10: 234093.49 | Z10: 237410.01 | AA10: 240773.44 | AB10: 244182.66 | AC10: 247636.18 | AD10: 251132.22 | AE10: 254668.74 | AF10: 258243.57 | AG10: 261854.44 | AH10: 265499.09 | AI10: 269175.31 | AJ10: 272880.98 | AK10: 276614.12
A11: ch_cfoo_0 | B11: 175065 | C11: 176646.38 | D11: 178215.6 | E11: 179909.34 | F11: 181755.53 | G11: 183742.79 | H11: 185849.61 | I11: 188055.15 | J11: 190342.38 | K11: 192698.21 | L11: 195112.91 | M11: 197579.31 | N11: 200092.24 | O11: 202648.04 | P11: 205244.23 | Q11: 207879.16 | R11: 210551.78 | S11: 213261.44 | T11: 216007.75 | U11: 218790.43 | V11: 221609.24 | W11: 224463.97 | X11: 227354.36 | Y11: 230280.16 | Z11: 233241.08 | AA11: 236236.84 | AB11: 239267.21 | AC11: 242331.96 | AD11: 245430.95 | AE11: 248564.07 | AF11: 251731.31 | AG11: 254932.73 | AH11: 258168.46 | AI11: 261438.72 | AJ11: 264743.79 | AK11: 268084.01
A12: pch_cfoo_2 | B12: 1 | C12: 1.0199649 | D12: 1.0402867 | E12: 1.061021 | F12: 1.0822382 | G12: 1.104012 | H12: 1.1263853 | I12: 1.1493667 | J12: 1.1729656 | K12: 1.1971968 | L12: 1.2220847 | M12: 1.2476654 | N12: 1.2739879 | O12: 1.3011135 | P12: 1.329116 | Q12: 1.3580812 | R12: 1.3880724 | S12: 1.4191165 | T12: 1.4512298 | U12: 1.484421 | V12: 1.5186944 | W12: 1.5540522 | X12: 1.590496 | Y12: 1.6280268 | Z12: 1.666645 | AA12: 1.7063505 | AB12: 1.7471425 | AC12: 1.7890191 | AD12: 1.8319773 | AE12: 1.8760131 | AF12: 1.9211212 | AG12: 1.9672951 | AH12: 2.014527 | AI12: 2.062808 | AJ12: 2.1121278 | AK12: 2.1624752
... A105: pch_cbio_0 | B105: 1 | C105: 1.0194853 | D105: 1.0388851 | E105: 1.0584794 | F105: 1.0785234 | G105: 1.0991574 | H105: 1.1204202 | I105: 1.1422939 | J105: 1.1647423 | K105: 1.1877351 | L105: 1.2112565 | M105: 1.2353062 | N105: 1.2598952 | O105: 1.2850411 | P105: 1.3107638 | Q105: 1.337083 | R105: 1.3640167 | S105: 1.3915798 | T105: 1.4197853 | U105: 1.4486433 | V105: 1.4781629 | W105: 1.5083515 | X105: 1.5392164 | Y105: 1.5707642 | Z105: 1.6030015 | AA105: 1.635935 | AB105: 1.6695716 | AC105: 1.7039186 | AD105: 1.7389836 | AE105: 1.7747749 | AF105: 1.811301 | AG105: 1.8485712 | AH105: 1.8865955 | AI105: 1.9253844 | AJ105: 1.964949 | AK105: 2.0053012

Sheet Value_Added
A1: _date_ | B1: 42005 | C1: 42370 | D1: 42736 | E1: 43101 | F1: 43466 | G1: 43831 | H1: 44197 | I1: 44562 | J1: 44927 | K1: 45292 | L1: 45658 | M1: 46023 | N1: 46388 | O1: 46753 | P1: 47119 | Q1: 47484 | R1: 47849 | S1: 48214 | T1: 48580 | U1: 48945 | V1: 49310 | W1: 49675 | X1: 50041 | Y1: 50406 | Z1: 50771 | AA1: 51136 | AB1: 51502 | AC1: 51867 | AD1: 52232 | AE1: 52597 | AF1: 52963 | AG1: 53328 | AH1: 53693 | AI1: 54058 | AJ1: 54424 | AK1: 54789
A2: va_2 | B2: 1965592.2 | C2: 1986968.8 | D2: 2008413.6 | E2: 2030342 | F2: 2052886.4 | G2: 2076074.3 | H2: 2099860.4 | I2: 2124162.5 | J2: 2148918.1 | K2: 2174086.1 | L2: 2199645.8 | M2: 2225591.9 | N2: 2251928.9 | O2: 2278665.6 | P2: 2305811.5 | Q2: 2333373.8 | R2: 2361326.1 | S2: 2389613.7 | T2: 2418196.2 | U2: 2447047.2 | V2: 2476153.4 | W2: 2505512.1 | X2: 2535127.5 | Y2: 2565007.8 | Z2: 2595162 | AA2: 2625599.3 | AB2: 2656327.6 | AC2: 2687353.6 | AD2: 2718682.7 | AE2: 2750319.1 | AF2: 2782266.5 | AG2: 2814528 | AH2: 2847106.6 | AI2: 2880005.5 | AJ2: 2913228.1 | AK2: 2946778.5
A3: va_0 | B3: 1965592.2 | C3: 1986885.6 | D3: 2008191.4 | E3: 2029937.4 | F3: 2052257.8 | G3: 2075171.5 | H3: 2098653.7 | I3: 2122664 | J3: 2147158.9 | K3: 2172097.9 | L3: 2197445.8 | M3: 2223174.1 | N3: 2249260.8 | O3: 2275690.3 | P3: 2302452.2 | Q3: 2329540.4 | R3: 2356952 | S3: 2384686.5 | T3: 2412744.9 | U3: 2441129.2 | V3: 2469841.7 | W3: 2498885 | X3: 2528261.8 | Y3: 2557974.8 | Z3: 2588026.6 | AA3: 2618419.7 | AB3: 2649156.8 | AC3: 2680240.9 | AD3: 2711674.8 | AE3: 2743461.8 | AF3: 2775605.2 | AG3: 2808108.9 | AH3: 2840976.6 | AI3: 2874212.5 | AJ3: 2907821.1 | AK3: 2941806.7
A4: va_sagr_2 | B4: 30790.815 | C4: 31102.121 | D4: 31419.057 | E4: 31754.134 | F4: 32109.395 | G4: 32483.963 | H4: 32874.552 | I4: 33277.044 | J4: 33689.089 | K4: 34109.509 | L4: 34537.901 | M4: 34974.344 | N4: 35419.185 | O4: 35872.871 | P4: 36335.826 | Q4: 36808.35 | R4: 37289.07 | S4: 37775.573 | T4: 38266.453 | U4: 38760.893 | V4: 39258.455 | W4: 39758.947 | X4: 40262.325 | Y4: 40768.62 | Z4: 41277.892 | AA4: 41790.209 | AB4: 42305.626 | AC4: 42824.186 | AD4: 43345.921 | AE4: 43870.853 | AF4: 44399 | AG4: 44930.385 | AH4: 45465.039 | AI4: 46003.005 | AJ4: 46544.343 | AK4: 47089.131
A5: va_sagr_0 | B5: 30790.815 | C5: 31097.824 | D5: 31408.103 | E5: 31734.666 | F5: 32079.262 | G5: 32440.277 | H5: 32815.402 | I5: 33202.492 | J5: 33599.776 | K5: 34005.861 | L5: 34419.667 | M5: 34840.376 | N5: 35267.383 | O5: 35700.251 | P5: 36138.684 | Q5: 36582.491 | R5: 37031.564 | S5: 37485.852 | T5: 37945.343 | U5: 38410.05 | V5: 38880 | W5: 39355.225 | X5: 39835.764 | Y5: 40321.654 | Z5: 40812.934 | AA5: 41309.645 | AB5: 41811.83 | AC5: 42319.535 | AD5: 42832.812 | AE5: 43351.717 | AF5: 43876.312 | AG5: 44406.665 | AH5: 44942.85 | AI5: 45484.945 | AJ5: 46033.034 | AK5: 46587.204
A6: va_sfor_2 | B6: 5288.8126 | C6: 5297.6409 | D6: 5287.0242 | E6: 5269.4674 | F6: 5249.0738 | G6: 5226.4599 | H6: 5203.6412 | I6: 5183.1236 | J6: 5164.983 | K6: 5148.4161 | L6: 5132.3637 | M6: 5115.7675 | N6: 5097.6778 | O6: 5077.3026 | P6: 5054.0352 | Q6: 5027.4696 | R6: 4998.888 | S6: 4970.3273 | T6: 4942.6378 | U6: 4916.1591 | V6: 4891.0102 | W6: 4867.2183 | X6: 4844.7753 | Y6: 4823.6611 | Z6: 4803.8527 | AA6: 4785.3279 | AB6: 4768.0665 | AC6: 4752.0504 | AD6: 4737.2637 | AE6: 4723.6927 | AF6: 4711.3259 | AG6: 4700.1536 | AH6: 4690.1678 | AI6: 4681.3618 | AJ6: 4673.7304 | AK6: 4667.2688
A7: va_sfor_0 | B7: 5288.8126 | C7: 5304.0347 | D7: 5302.0192 | E7: 5294.5751 | F7: 5286.4854 | G7: 5279.4506 | H7: 5273.8914 | I7: 5269.7509 | J7: 5266.835 | K7: 5264.9431 | L7: 5263.9093 | M7: 5263.6084 | N7: 5263.9504 | O7: 5264.872 | P7: 5266.329 | Q7: 5268.2912 | R7: 5270.738 | S7: 5273.6553 | T7: 5277.0329 | U7: 5280.8561 | V7: 5285.1182 | W7: 5289.8172 | X7: 5294.9534 | Y7: 5300.5286 | Z7: 5306.5452 | AA7: 5313.0062 | AB7: 5319.9145 | AC7: 5327.2731 | AD7: 5335.0852 | AE7: 5343.3539 | AF7: 5352.0818 | AG7: 5361.2718 | AH7: 5370.9267 | AI7: 5381.049 | AJ7: 5391.6415 | AK7: 5402.7065
A8: va_sfoo_2 | B8: 43654.88 | C8: 44079.936 | D8: 44521.727 | E8: 44993.424 | F8: 45494.719 | G8: 46023.142 | H8: 46573.909 | I8: 47141.713 | J8: 47723.764 | K8: 48318.566 | L8: 48925.513 | M8: 49544.597 | N8: 50176.168 | O8: 50820.758 | P8: 51478.946 | Q8: 52151.259 | R8: 52835.967 | S8: 53530.077 | T8: 54232.126 | U8: 54941.241 | V8: 55656.953 | W8: 56379.069 | X8: 57107.556 | Y8: 57842.463 | Z8: 58583.858 | AA8: 59331.792 | AB8: 60086.291 | AC8: 60847.343 | AD8: 61614.904 | AE8: 62388.908 | AF8: 63169.273 | AG8: 63955.913 | AH8: 64748.748 | AI8: 65547.712 | AJ8: 66352.755 | AK8: 67163.854
A9: va_sfoo_0 | B9: 43654.88 | C9: 44074.319 | D9: 44508.113 | E9: 44969.764 | F9: 45458.475 | G9: 45970.837 | H9: 46503.401 | I9: 47053.24 | J9: 47617.99 | K9: 48195.765 | L9: 48785.077 | M9: 49384.768 | N9: 49993.956 | O9: 50611.993 | P9: 51238.424 | Q9: 51872.946 | R9: 52515.37 | S9: 53165.593 | T9: 53823.57 | U9: 54489.29 | V9: 55162.761 | W9: 55844.004 | X9: 56533.043 | Y9: 57229.907 | Z9: 57934.625 | AA9: 58647.231 | AB9: 59367.763 | AC9: 60096.266 | AD9: 60832.792 | AE9: 61577.404 | AF9: 62330.173 | AG9: 63091.181 | AH9: 63860.521 | AI9: 64638.292 | AJ9: 65424.606 | AK9: 66219.579
A10: va_sveh_2 | B10: 29847.895 | C10: 30404.587 | D10: 30932.187 | E10: 31407.735 | F10: 31839.728 | G10: 32241.105 | H10: 32625.553 | I10: 33003.168 | J10: 33377.546 | K10: 33750.08 | L10: 34121.255 | M10: 34491.104 | N10: 34859.407 | O10: 35225.772 | P10: 35589.677 | Q10: 35950.485 | R10: 36310.352 | S10: 36671.833 | T10: 37034.291 | U10: 37396.91 | V10: 37759.181 | W10: 38120.88 | X10: 38481.977 | Y10: 38842.569 | Z10: 39202.823 | AA10: 39562.948 | AB10: 39923.177 | AC10: 40283.761 | AD10: 40644.964 | AE10: 41007.063 | AF10: 41370.349 | AG10: 41735.131 | AH10: 42101.732 | AI10: 42470.491 | AJ10: 42841.762 | AK10: 43215.914
A11: va_sveh_0 | B11: 29847.895 | C11: 30410.564 | D11: 30943.516 | E11: 31424.184 | F11: 31862.492 | G11: 32272.71 | H11: 32666.675 | I11: 33052.509 | J11: 33435.21 | K11: 33817.628 | L11: 34201.287 | M11: 34586.961 | N11: 34975.033 | O11: 35365.692 | P11: 35759.05 | Q11: 36155.19 | R11: 36554.191 | S11: 36956.134 | T11: 37361.107 | U11: 37769.204 | V11: 38180.52 | W11: 38595.157 | X11: 39013.219 | Y11: 39434.812 | Z11: 39860.048 | AA11: 40289.04 | AB11: 40721.904 | AC11: 41158.757 | AD11: 41599.719 | AE11: 42044.908 | AF11: 42494.445 | AG11: 42948.446 | AH11: 43407.029 | AI11: 43870.308 | AJ11: 44338.393 | AK11: 44811.394
A12: va_sgla_2 | B12: 7902.1978 | C12: 7989.9781 | D12: 8077.9673 | E12: 8167.4463 | F12: 8259.0631 | G12: 8353.0815 | H12: 8449.1995 | I12: 8546.8972 | J12: 8645.9433 | K12: 8746.2661 | L12: 8847.8532 | M12: 8950.6893 | N12: 9054.7153 | O12: 9159.7968 | P12: 9265.6991 | Q12: 9372.0664 | R12: 9478.3521 | S12: 9584.0627 | T12: 9688.973 | U12: 9793.024 | V12: 9896.2505 | W12: 9998.7375 | X12: 10100.594 | Y12: 10201.936 | Z12: 10302.88 | AA12: 10403.535 | AB12: 10504.006 | AC12: 10604.387 | AD12: 10704.768 | AE12: 10805.231 | AF12: 10905.857 | AG12: 11006.72 | AH12: 11107.896 | AI12: 11209.455 | AJ12: 11311.471 | AK12: 11414.014
... A79: va_ser_0 | B79: 1510944.6 | C79: 1527318.9 | D79: 1543784 | E79: 1560667.8 | F79: 1578055.3 | G79: 1595942.4 | H79: 1614295.5 | I79: 1633073.9 | J79: 1652238.4 | K79: 1671754.4 | L79: 1691592.8 | M79: 1711730.4 | N79: 1732149.6 | O79: 1752837.7 | P79: 1773786.4 | Q79: 1794990.5 | R79: 1816447.6 | S79: 1838157 | T79: 1860119.3 | U79: 1882335.7 | V79: 1904807.8 | W79: 1927537.5 | X79: 1950526.5 | Y79: 1973776.7 | Z79: 1997289.9 | AA79: 2021067.8 | AB79: 2045112.5 | AC79: 2069426 | AD79: 2094010.5 | AE79: 2118868.4 | AF79: 2144002.3 | AG79: 2169415.2 | AH79: 2195110 | AI79: 2221090 | AJ79: 2247358.8 | AK79: 2273919.9

Sheet INV
A1: _date_ | B1: 42005 | C1: 42370 | D1: 42736 | E1: 43101 | F1: 43466 | G1: 43831 | H1: 44197 | I1: 44562 | J1: 44927 | K1: 45292 | L1: 45658 | M1: 46023 | N1: 46388 | O1: 46753 | P1: 47119 | Q1: 47484 | R1: 47849 | S1: 48214 | T1: 48580 | U1: 48945 | V1: 49310 | W1: 49675 | X1: 50041 | Y1: 50406 | Z1: 50771 | AA1: 51136 | AB1: 51502 | AC1: 51867 | AD1: 52232 | AE1: 52597 | AF1: 52963 | AG1: 53328 | AH1: 53693 | AI1: 54058 | AJ1: 54424 | AK1: 54789
A2: ia_2 | B2: 472647 | C2: 478019.4 | D2: 483383.02 | E2: 488765.23 | F2: 494190.78 | G2: 499675.43 | H2: 505236.8 | I2: 510891.29 | J2: 516642.91 | K2: 522488.85 | L2: 528423.65 | M2: 534441.35 | N2: 540536.13 | O2: 546702.37 | P2: 552934.37 | Q2: 559226.23 | R2: 565579.52 | S2: 572000.88 | T2: 578492.4 | U2: 585054.38 | V2: 591687.29 | W2: 598392.57 | X2: 605172.52 | Y2: 612029.89 | Z2: 618967.37 | AA2: 625987.28 | AB2: 633091.27 | AC2: 640280.33 | AD2: 647554.73 | AE2: 654914.12 | AF2: 662357.64 | AG2: 669884.02 | AH2: 677491.71 | AI2: 685178.97 | AJ2: 692943.93 | AK2: 700784.7
A3: ia_0 | B3: 472647 | C3: 478041.55 | D3: 483438.29 | E3: 488861.72 | F3: 494339.57 | G3: 499893.34 | H3: 505536.92 | I3: 511277.46 | J3: 517117.16 | K3: 523055.07 | L3: 529088.68 | M3: 535215.11 | N3: 541431.74 | O3: 547736.65 | P3: 554128.65 | Q3: 560607.27 | R3: 567172.56 | S3: 573824.98 | T3: 580565.17 | U3: 587393.88 | V3: 594311.81 | W3: 601319.58 | X3: 608417.66 | Y3: 615606.41 | Z3: 622886.05 | AA3: 630256.67 | AB3: 637718.3 | AC3: 645270.89 | AD3: 652914.38 | AE3: 660648.67 | AF3: 668473.69 | AG3: 676389.4 | AH3: 684395.78 | AI3: 692492.88 | AJ3: 700680.78 | AK3: 708959.66
A4: ia_sagr_2 | B4: 4271.7493 | C4: 4316.7096 | D4: 4359.9715 | E4: 4403.7215 | F4: 4449.0584 | G4: 4496.2419 | H4: 4545.1965 | I4: 4595.7611 | J4: 4647.7303 | K4: 4700.9187 | L4: 4755.1656 | M4: 4810.3252 | N4: 4866.256 | O4: 4922.8133 | P4: 4979.846 | Q4: 5037.1969 | R4: 5094.7575 | S4: 5152.4716 | T4: 5210.3059 | U4: 5268.2618 | V4: 5326.3668 | W4: 5384.6627 | X4: 5443.1973 | Y4: 5502.0171 | Z4: 5561.1639 | AA4: 5620.6724 | AB4: 5680.5697 | AC4: 5740.876 | AD4: 5801.6056 | AE4: 5862.7681 | AF4: 5924.3701 | AG4: 5986.4163 | AH4: 6048.9107 | AI4: 6111.8578 | AJ4: 6175.2633 | AK4: 6239.1344
A5: ia_sagr_0 | B5: 4271.7493 | C5: 4316.9191 | D5: 4360.566 | E5: 4404.9143 | F5: 4451.1227 | G5: 4499.5274 | H5: 4550.0535 | I5: 4602.4822 | J5: 4656.5777 | K5: 4712.1351 | L5: 4768.9904 | M5: 4827.0178 | N5: 4886.1226 | O5: 4946.2347 | P5: 5007.3037 | Q5: 5069.2935 | R5: 5132.1794 | S5: 5195.9442 | T5: 5260.5762 | U5: 5326.0669 | V5: 5392.4095 | W5: 5459.5978 | X5: 5527.6258 | Y5: 5596.4876 | Z5: 5666.1769 | AA5: 5736.6876 | AB5: 5808.0139 | AC5: 5880.1505 | AD5: 5953.0927 | AE5: 6026.8372 | AF5: 6101.3814 | AG5: 6176.7244 | AH5: 6252.8665 | AI5: 6329.8095 | AJ5: 6407.5565 | AK5: 6486.112
A6: ia_sfor_2 | B6: 166.90527 | C6: 167.66273 | D6: 167.53761 | E6: 166.89591 | F6: 165.94733 | G6: 164.77096 | H6: 163.44791 | I6: 162.07868 | J6: 160.70813 | K6: 159.33944 | L6: 157.95352 | M6: 156.52185 | N6: 155.01357 | O6: 153.3995 | P6: 151.6547 | Q6: 149.76011 | R6: 147.74315 | S6: 145.66777 | T6: 143.58093 | U6: 141.51185 | V6: 139.47832 | W6: 137.49155 | X6: 135.55908 | Y6: 133.68627 | Z6: 131.87707 | AA6: 130.13447 | AB6: 128.46073 | AC6: 126.85751 | AD6: 125.32602 | AE6: 123.86707 | AF6: 122.48118 | AG6: 121.16856 | AH6: 119.92923 | AI6: 118.76301 | AJ6: 117.66956 | AK6: 116.64838
A7: ia_sfor_0 | B7: 166.90527 | C7: 167.83885 | D7: 168.02018 | E7: 167.78375 | F7: 167.34781 | G7: 166.825 | H7: 166.26615 | I7: 165.69193 | J7: 165.1102 | K7: 164.52429 | L7: 163.93643 | M7: 163.34897 | N7: 162.76463 | O7: 162.18645 | P7: 161.61757 | Q7: 161.06114 | R7: 160.52017 | S7: 159.99749 | T7: 159.49567 | U7: 159.01687 | V7: 158.56304 | W7: 158.13598 | X7: 157.7373 | Y7: 157.36842 | Z7: 157.03058 | AA7: 156.72481 | AB7: 156.452 | AC7: 156.21287 | AD7: 156.00797 | AE7: 155.83776 | AF7: 155.70255 | AG7: 155.60254 | AH7: 155.53783 | AI7: 155.50847 | AJ7: 155.51438 | AK7: 155.55545
A8: ia_sfoo_2 | B8: 6742.5992 | C8: 6812.5373 | D8: 6879.7436 | E8: 6948.0473 | F8: 7019.2166 | G8: 7093.6077 | H8: 7171.0809 | I8: 7251.3764 | J8: 7334.1298 | K8: 7419.0043 | L8: 7505.7123 | M8: 7594.0036 | N8: 7683.6462 | O8: 7774.4099 | P8: 7866.056 | Q8: 7958.3332 | R8: 8051.0963 | S8: 8144.2918 | T8: 8237.8571 | U8: 8331.7653 | V8: 8426.0239 | W8: 8520.6654 | X8: 8615.7342 | Y8: 8711.2762 | Z8: 8807.331 | AA8: 8903.9278 | AB8: 9001.0839 | AC8: 9098.805 | AD8: 9197.0869 | AE8: 9295.9174 | AF8: 9395.2792 | AG8: 9495.1519 | AH8: 9595.5143 | AI8: 9696.3466 | AJ8: 9797.6313 | AK8: 9899.3546
A9: ia_sfoo_0 | B9: 6742.5992 | C9: 6812.918 | D9: 6880.7425 | E9: 6949.9349 | F9: 7022.3561 | G9: 7098.4844 | H9: 7178.1486 | I9: 7260.9658 | J9: 7346.5408 | K9: 7434.5354 | L9: 7524.6818 | M9: 7616.7752 | N9: 7710.662 | O9: 7806.229 | P9: 7903.3949 | Q9: 8002.1017 | R9: 8102.309 | S9: 8203.9889 | T9: 8307.1212 | U9: 8411.6904 | V9: 8517.6829 | W9: 8625.0857 | X9: 8733.8854 | Y9: 8844.0679 | Z9: 8955.6185 | AA9: 9068.5224 | AB9: 9182.7648 | AC9: 9298.3317 | AD9: 9415.2105 | AE9: 9533.3901 | AF9: 9652.8617 | AG9: 9773.6184 | AH9: 9895.6561 | AI9: 10018.973 | AJ9: 10143.57 | AK9: 10269.45
A10: ia_sveh_2 | B10: 36330.779 | C10: 36892.942 | D10: 37526.468 | E10: 38158.801 | F10: 38755.612 | G10: 39309.742 | H10: 39828.945 | I10: 40325.527 | J10: 40808.622 | K10: 41283.532 | L10: 41752.811 | M10: 42217.352 | N10: 42677.119 | O10: 43131.574 | P10: 43579.903 | Q10: 44021.124 | R10: 44456.363 | S10: 44888.381 | T10: 45318.431 | U10: 45746.632 | V10: 46172.716 | W10: 46596.448 | X10: 47017.775 | Y10: 47436.821 | Z10: 47853.844 | AA10: 48269.188 | AB10: 48683.248 | AC10: 49096.444 | AD10: 49509.218 | AE10: 49922.024 | AF10: 50335.33 | AG10: 50749.622 | AH10: 51165.401 | AI10: 51583.189 | AJ10: 52003.525 | AK10: 52426.966
A11: ia_sveh_0 | B11: 36330.779 | C11: 36897.67 | D11: 37538.383 | E11: 38179.071 | F11: 38785.78 | G11: 39352.655 | H11: 39886.731 | I11: 40398.196 | J11: 40895.934 | K11: 41386.273 | L11: 41873.185 | M11: 42358.932 | N11: 42844.703 | O11: 43331.081 | P11: 43818.353 | Q11: 44306.685 | R11: 44796.209 | S11: 45287.066 | T11: 45779.416 | U11: 46273.439 | V11: 46769.334 | W11: 47267.315 | X11: 47767.605 | Y11: 48270.436 | Z11: 48776.045 | AA11: 49284.675 | AB11: 49796.575 | AC11: 50311.993 | AD11: 50831.181 | AE11: 51354.391 | AF11: 51881.875 | AG11: 52413.881 | AH11: 52950.655 | AI11: 53492.438 | AJ11: 54039.466 | AK11: 54591.969
A12: ia_sgla_2 | B12: 1455.1731 | C12: 1471.1513 | D12: 1486.6169 | E12: 1501.7673 | F12: 1516.7126 | G12: 1531.4382 | H12: 1545.9808 | I12: 1560.4684 | J12: 1574.9832 | K12: 1589.5514 | L12: 1604.1432 | M12: 1618.6789 | N12: 1633.0376 | O12: 1647.0672 | P12: 1660.5935 | Q12: 1673.4295 | R12: 1685.4934 | S12: 1696.8387 | T12: 1707.5528 | U12: 1717.7333 | V12: 1727.4753 | W12: 1736.8655 | X12: 1745.9804 | Y12: 1754.8868 | Z12: 1763.6424 | AA12: 1772.2975 | AB12: 1780.8958 | AC12: 1789.4757 | AD12: 1798.0715 | AE12: 1806.714 | AF12: 1815.4312 | AG12: 1824.2489 | AH12: 1833.191 | AI12: 1842.2802 | AJ12: 1851.5377 | AK12: 1860.9836
... A79: ia_ser_0 | B79: 219461.28 | C79: 221888.44 | D79: 224292.96 | E79: 226729.35 | F79: 229226.27 | G79: 231793.06 | H79: 234429.3 | I79: 237130.78 | J79: 239892.4 | K79: 242709.38 | L79: 245577.67 | M79: 248494.04 | N79: 251456.09 | O79: 254462.06 | P79: 257510.8 | Q79: 260601.59 | R79: 263734.05 | S79: 266908 | T79: 270123.41 | U79: 273380.28 | V79: 276678.63 | W79: 280018.46 | X79: 283399.71 | Y79: 286822.29 | Z79: 290286.1 | AA79: 293790.98 | AB79: 297336.8 | AC79: 300923.4 | AD79: 304550.68 | AE79: 308218.55 | AF79: 311926.95 | AG79: 315675.89 | AH79: 319465.43 | AI79: 323295.66 | AJ79: 327166.76 | AK79: 331078.93

Sheet Labor
A1: _date_ | B1: 42005 | C1: 42370 | D1: 42736 | E1: 43101 | F1: 43466 | G1: 43831 | H1: 44197 | I1: 44562 | J1: 44927 | K1: 45292 | L1: 45658 | M1: 46023 | N1: 46388 | O1: 46753 | P1: 47119 | Q1: 47484 | R1: 47849 | S1: 48214 | T1: 48580 | U1: 48945 | V1: 49310 | W1: 49675 | X1: 50041 | Y1: 50406 | Z1: 50771 | AA1: 51136 | AB1: 51502 | AC1: 51867 | AD1: 52232 | AE1: 52597 | AF1: 52963 | AG1: 53328 | AH1: 53693 | AI1: 54058 | AJ1: 54424 | AK1: 54789
A2: f_l_2 | B2: 27390.88 | C2: 27450.174 | D2: 27503.566 | E2: 27556.49 | F2: 27613.073 | G2: 27675.654 | H2: 27744.658 | I2: 27819.069 | J2: 27897.548 | K2: 27978.951 | L2: 28062.513 | M2: 28147.868 | N2: 28234.974 | O2: 28324.012 | P2: 28415.29 | Q2: 28509.16 | R2: 28605.493 | S2: 28703.505 | T2: 28802.308 | U2: 28901.143 | V2: 28999.468 | W2: 29096.964 | X2: 29193.491 | Y2: 29289.039 | Z2: 29383.677 | AA2: 29477.506 | AB2: 29570.634 | AC2: 29663.158 | AD2: 29755.155 | AE2: 29846.68 | AF2: 29937.768 | AG2: 30028.438 | AH2: 30118.701 | AI2: 30208.56 | AJ2: 30298.018 | AK2: 30387.076
A3: f_l_0 | B3: 27390.88 | C3: 27448.862 | D3: 27499.539 | E3: 27548.51 | F3: 27599.973 | G3: 27656.135 | H3: 27717.672 | I3: 27784.329 | J3: 27855.384 | K3: 27929.95 | L3: 28007.151 | M3: 28086.22 | N3: 28166.532 | O3: 28247.612 | P3: 28329.119 | Q3: 28410.825 | R3: 28492.59 | S3: 28574.336 | T3: 28656.032 | U3: 28737.669 | V3: 28819.257 | W3: 28900.808 | X3: 28982.338 | Y3: 29063.857 | Z3: 29145.376 | AA3: 29226.899 | AB3: 29308.431 | AC3: 29389.972 | AD3: 29471.523 | AE3: 29553.086 | AF3: 29634.662 | AG3: 29716.255 | AH3: 29797.868 | AI3: 29879.506 | AJ3: 29961.176 | AK3: 30042.885
A4: f_l_sagr_2 | B4: 732.13 | C4: 733.53268 | D4: 734.74367 | E4: 736.10273 | F4: 737.85588 | G4: 740.14183 | H4: 742.95251 | I4: 746.15883 | J4: 749.62815 | K4: 753.26911 | L4: 757.0411 | M4: 760.94854 | N4: 765.02987 | O4: 769.34625 | P4: 773.97192 | Q4: 778.98656 | R4: 784.40725 | S4: 790.16517 | T4: 796.17248 | U4: 802.35009 | V4: 808.63628 | W4: 814.98691 | X4: 821.37235 | Y4: 827.7736 | Z4: 834.17879 | AA4: 840.58038 | AB4: 846.97323 | AC4: 853.35333 | AD4: 859.71706 | AE4: 866.06082 | AF4: 872.38092 | AG4: 878.67356 | AH4: 884.93497 | AI4: 891.16149 | AJ4: 897.34967 | AK4: 903.49638
A5: f_l_sagr_0 | B5: 732.13 | C5: 733.35856 | D5: 734.20074 | E5: 735.0077 | F5: 736.0202 | G5: 737.34214 | H5: 738.98236 | I5: 740.90022 | J5: 743.03725 | K5: 745.33488 | L5: 747.74248 | M5: 750.21993 | N5: 752.73732 | O5: 755.27355 | P5: 757.81456 | Q5: 760.35165 | R5: 762.87995 | S5: 765.39723 | T5: 767.90295 | U5: 770.39754 | V5: 772.8819 | W5: 775.35709 | X5: 777.82412 | Y5: 780.28388 | Z5: 782.73708 | AA5: 785.18432 | AB5: 787.62605 | AC5: 790.06269 | AD5: 792.49463 | AE5: 794.92225 | AF5: 797.34598 | AG5: 799.76628 | AH5: 802.18366 | AI5: 804.59868 | AJ5: 807.01191 | AK5: 809.42397
A6: f_l_sfor_2 | B6: 29.08 | C6: 28.987581 | D6: 28.749051 | E6: 28.421798 | F6: 28.052146 | G6: 27.66653 | H6: 27.283069 | I6: 26.916018 | J6: 26.570698 | K6: 26.245682 | L6: 25.935992 | M6: 25.6355 | N6: 25.338373 | O6: 25.039805 | P6: 24.736325 | Q6: 24.425862 | R6: 24.111142 | S6: 23.798728 | T6: 23.49378 | U6: 23.199184 | V6: 22.916059 | W6: 22.644446 | X6: 22.383852 | Y6: 22.133587 | Z6: 21.892942 | AA6: 21.661277 | AB6: 21.438039 | AC6: 21.222769 | AD6: 21.015082 | AE6: 20.814656 | AF6: 20.621216 | AG6: 20.434524 | AH6: 20.254368 | AI6: 20.080557 | AJ6: 19.912915 | AK6: 19.751277
A7: f_l_sfor_0 | B7: 29.08 | C7: 29.005618 | D7: 28.799733 | E7: 28.51501 | F7: 28.196878 | G7: 27.874071 | H7: 27.561229 | I7: 27.263898 | J7: 26.982674 | K7: 26.715933 | L7: 26.461367 | M7: 26.216745 | N7: 25.980209 | O7: 25.750339 | P7: 25.526105 | Q7: 25.306793 | R7: 25.091918 | S7: 24.881155 | T7: 24.674289 | U7: 24.471151 | V7: 24.271621 | W7: 24.075618 | X7: 23.883085 | Y7: 23.69398 | Z7: 23.508268 | AA7: 23.325914 | AB7: 23.146886 | AC7: 22.97115 | AD7: 22.798668 | AE7: 22.629401 | AF7: 22.463308 | AG7: 22.300347 | AH7: 22.140474 | AI7: 21.983643 | AJ7: 21.829809 | AK7: 21.678924
A8: f_l_sfoo_2 | B8: 618.62 | C8: 619.64984 | D8: 620.40811 | E8: 621.21783 | F8: 622.29155 | G8: 623.72675 | H8: 625.51685 | I8: 627.58699 | J8: 629.85654 | K8: 632.26336 | L8: 634.76973 | M8: 637.36009 | N8: 640.03584 | O8: 642.8098 | P8: 645.7014 | Q8: 648.73307 | R8: 651.90265 | S8: 655.1757 | T8: 658.51415 | U8: 661.88657 | V8: 665.27066 | W8: 668.65245 | X8: 672.02438 | Y8: 675.38311 | Z8: 678.72771 | AA8: 682.05832 | AB8: 685.3753 | AC8: 688.67867 | AD8: 691.96795 | AE8: 695.24214 | AF8: 698.4998 | AG8: 701.73917 | AH8: 704.95838 | AI8: 708.15556 | AJ8: 711.32897 | AK8: 714.47708
A9: f_l_sfoo_0 | B9: 618.62 | C9: 619.58096 | D9: 620.19799 | E9: 620.80189 | F9: 621.60558 | G9: 622.69515 | H9: 624.07325 | I9: 625.70096 | J9: 627.52547 | K9: 629.49501 | L9: 631.56538 | M9: 633.70176 | N9: 635.87829 | O9: 638.07672 | P9: 640.28485 | Q9: 642.49501 | R9: 644.7028 | S9: 646.90604 | T9: 649.10393 | U9: 651.29649 | V9: 653.48407 | W9: 655.66713 | X9: 657.84606 | Y9: 660.02113 | Z9: 662.19247 | AA9: 664.3601 | AB9: 666.52395 | AC9: 668.68392 | AD9: 670.83993 | AE9: 672.99195 | AF9: 675.13999 | AG9: 677.28416 | AH9: 679.42464 | AI9: 681.5617 | AJ9: 683.69566 | AK9: 685.82691
A10: f_l_sveh_2 | B10: 185.81 | C10: 186.90529 | D10: 188.36292 | E10: 189.83317 | F10: 191.10318 | G10: 192.10321 | H10: 192.85802 | I10: 193.43216 | J10: 193.88812 | K10: 194.2718 | L10: 194.61157 | M10: 194.9222 | N10: 195.20939 | O10: 195.47338 | P10: 195.71139 | Q10: 195.91906 | R10: 196.09646 | S10: 196.24766 | T10: 196.37331 | U10: 196.47099 | V10: 196.53734 | W10: 196.56976 | X10: 196.56709 | Y10: 196.52967 | Z10: 196.45909 | AA10: 196.35786 | AB10: 196.229 | AC10: 196.07584 | AD10: 195.90181 | AE10: 195.71034 | AF10: 195.50474 | AG10: 195.28827 | AH10: 195.06403 | AI10: 194.83502 | AJ10: 194.60416 | AK10: 194.37422
A11: f_l_sveh_0 | B11: 185.81 | C11: 186.91608 | D11: 188.39081 | E11: 189.88115 | F11: 191.17536 | G11: 192.20807 | H11: 193.00441 | I11: 193.62576 | J11: 194.13548 | K11: 194.58348 | L11: 195.00281 | M11: 195.41213 | N11: 195.81987 | O11: 196.22828 | P11: 196.63639 | Q11: 197.04198 | R11: 197.44272 | S11: 197.83673 | T11: 198.22269 | U11: 198.59992 | V11: 198.96823 | W11: 199.32783 | X11: 199.67917 | Y11: 200.02293 | Z11: 200.35986 | AA11: 200.69079 | AB11: 201.01656 | AC11: 201.33802 | AD11: 201.65597 | AE11: 201.97119 | AF11: 202.28442 | AG11: 202.59635 | AH11: 202.90759 | AI11: 203.21872 | AJ11: 203.53027 | AK11: 203.84269
A12: f_l_sgla_2 | B12: 98.04 | C12: 98.276365 | D12: 98.505875 | E12: 98.739175 | F12: 98.98968 | G12: 99.269662 | H12: 99.580784 | I12: 99.914226 | J12: 100.26179 | K12: 100.61896 | L12: 100.985 | M12: 101.36207 | N12: 101.75423 | O12: 102.16652 | P12: 102.60431 | Q12: 103.07266 | R12: 103.57006 | S12: 104.08751 | T12: 104.61594 | U12: 105.14836 | V12: 105.68007 | W12: 106.2082 | X12: 106.73121 | Y12: 107.24838 | Z12: 107.75949 | AA12: 108.26457 | AB12: 108.76375 | AC12: 109.25722 | AD12: 109.74512 | AE12: 110.22759 | AF12: 110.70471 | AG12: 111.17658 | AH12: 111.64324 | AI12: 112.10477 | AJ12: 112.56122 | AK12: 113.01267
... A79: f_l_ser_0 | B79: 21284.868 | C79: 21330.075 | D79: 21370.068 | E79: 21409.305 | F79: 21450.968 | G79: 21496.614 | H79: 21546.611 | I79: 21600.64 | J79: 21658.063 | K79: 21718.152 | L79: 21780.218 | M79: 21843.669 | N79: 21908.031 | O79: 21972.949 | P79: 22038.17 | Q79: 22103.528 | R79: 22168.918 | S79: 22234.285 | T79: 22299.605 | U79: 22364.871 | V79: 22430.088 | W79: 22495.264 | X79: 22560.407 | Y79: 22625.523 | Z79: 22690.617 | AA79: 22755.689 | AB79: 22820.741 | AC79: 22885.773 | AD79: 22950.783 | AE79: 23015.774 | AF79: 23080.745 | AG79: 23145.699 | AH79: 23210.642 | AI79: 23275.578 | AJ79: 23340.514 | AK79: 23405.458

Sheet Final_nrj
A1: _date_ | B1: 42005 | C1: 42370 | D1: 42736 | E1: 43101 | F1: 43466 | G1: 43831 | H1: 44197 | I1: 44562 | J1: 44927 | K1: 45292 | L1: 45658 | M1: 46023 | N1: 46388 | O1: 46753 | P1: 47119 | Q1: 47484 | R1: 47849 | S1: 48214 | T1: 48580 | U1: 48945 | V1: 49310 | W1: 49675 | X1: 50041 | Y1: 50406 | Z1: 50771 | AA1: 51136 | AB1: 51502 | AC1: 51867 | AD1: 52232 | AE1: 52597 | AF1: 52963 | AG1: 53328 | AH1: 53693 | AI1: 54058 | AJ1: 54424 | AK1: 54789
A2: cf_toe_2 | B2: 162.18538 | C2: 163.06009 | D2: 163.61356 | E2: 164.10601 | F2: 164.60712 | G2: 165.1068 | H2: 165.6167 | I2: 166.17199 | J2: 166.77811 | K2: 167.42291 | L2: 168.08481 | M2: 168.73766 | N2: 169.35377 | O2: 169.90593 | P2: 170.369 | Q2: 170.72108 | R2: 170.97353 | S2: 171.16366 | T2: 171.31805 | U2: 171.45431 | V2: 171.58393 | W2: 171.71439 | X2: 171.85049 | Y2: 171.99529 | Z2: 172.15062 | AA2: 172.3175 | AB2: 172.49641 | AC2: 172.68746 | AD2: 172.89052 | AE2: 173.10532 | AF2: 173.33156 | AG2: 173.5689 | AH2: 173.8171 | AI2: 174.07596 | AJ2: 174.34544 | AK2: 174.62564
A3: ch_toe_2 | B3: 64.30144 | C3: 64.184879 | D3: 63.813337 | E3: 63.413869 | F3: 63.052106 | G3: 62.730765 | H3: 62.452108 | I3: 62.222359 | J3: 62.033207 | K3: 61.871749 | L3: 61.724679 | M3: 61.579957 | N3: 61.427415 | O3: 61.258923 | P3: 61.068389 | Q3: 60.851644 | R3: 60.6164 | S3: 60.376608 | T3: 60.139128 | U3: 59.906799 | V3: 59.680288 | W3: 59.459162 | X3: 59.242489 | Y3: 59.029157 | Z3: 58.818029 | AA3: 58.608005 | AB3: 58.39805 | AC3: 58.187196 | AD3: 57.974536 | AE3: 57.759231 | AF3: 57.540503 | AG3: 57.317651 | AH3: 57.090051 | AI3: 56.85718 | AJ3: 56.61862 | AK3: 56.374084
A4: ch_hous_toe_2 | B4: 42520877 | C4: 42690907 | D4: 42476161 | E4: 42147323 | F4: 41799630 | G4: 41455705 | H4: 41129627 | I4: 40834178 | J4: 40565966 | K4: 40315976 | L4: 40074099 | M4: 39831027 | N4: 39579016 | O4: 39312174 | P4: 39026524 | Q4: 38719952 | R4: 38400587 | S4: 38081393 | T4: 37768866 | U4: 37465878 | V4: 37173338 | W4: 36891169 | X4: 36618856 | Y4: 36355745 | Z4: 36101182 | AA4: 35854577 | AB4: 35615414 | AC4: 35383256 | AD4: 35157727 | AE4: 34938507 | AF4: 34725318 | AG4: 34517915 | AH4: 34316085 | AI4: 34119636 | AJ4: 33928399 | AK4: 33742222
A5: ch_auto_toe_2 | B5: 21780563 | C5: 21493972 | D5: 21337176 | E5: 21266546 | F5: 21252476 | G5: 21275060 | H5: 21322481 | I5: 21388180 | J5: 21467241 | K5: 21555773 | L5: 21650580 | M5: 21748931 | N5: 21848398 | O5: 21946749 | P5: 22041866 | Q5: 22131692 | R5: 22215813 | S5: 22295215 | T5: 22370262 | U5: 22440921 | V5: 22506950 | W5: 22567993 | X5: 22623633 | Y5: 22673413 | Z5: 22716846 | AA5: 22753428 | AB5: 22782636 | AC5: 22803940 | AD5: 22816809 | AE5: 22820724 | AF5: 22815186 | AG5: 22799735 | AH5: 22773966 | AI5: 22737543 | AJ5: 22690221 | AK5: 22631862
A6: cf_toe_0 | B6: 162.18538 | C6: 163.18361 | D6: 163.93894 | E6: 164.69725 | F6: 165.53686 | G6: 166.4692 | H6: 167.48335 | I6: 168.56385 | J6: 169.69685 | K6: 170.87166 | L6: 172.08057 | M6: 173.31826 | N6: 174.58111 | O6: 175.8667 | P6: 177.17338 | Q6: 178.50013 | R6: 179.8463 | S6: 181.21149 | T6: 182.59545 | U6: 183.99804 | V6: 185.4192 | W6: 186.8589 | X6: 188.31714 | Y6: 189.79394 | Z6: 191.28931 | AA6: 192.80331 | AB6: 194.33597 | AC6: 195.88737 | AD6: 197.45759 | AE6: 199.04673 | AF6: 200.6549 | AG6: 202.28226 | AH6: 203.92897 | AI6: 205.59519 | AJ6: 207.28114 | AK6: 208.98701
A7: ch_toe_0 | B7: 64.30144 | C7: 64.233784 | D7: 63.931558 | E7: 63.614626 | F7: 63.352024 | G7: 63.15395 | H7: 63.01119 | I7: 62.910661 | J7: 62.840776 | K7: 62.792713 | L7: 62.760233 | M7: 62.739095 | N7: 62.72647 | O7: 62.720453 | P7: 62.719697 | Q7: 62.723315 | R7: 62.730704 | S7: 62.741401 | T7: 62.755059 | U7: 62.771409 | V7: 62.790253 | W7: 62.811437 | X7: 62.834839 | Y7: 62.860359 | Z7: 62.887918 | AA7: 62.917448 | AB7: 62.948899 | AC7: 62.982229 | AD7: 63.017408 | AE7: 63.054413 | AF7: 63.093228 | AG7: 63.133845 | AH7: 63.176261 | AI7: 63.220481 | AJ7: 63.266511 | AK7: 63.314363
A8: ch_hous_toe_0 | B8: 42520877 | C8: 42736368 | D8: 42585617 | E8: 42332591 | F8: 42075594 | G8: 41843924 | H8: 41640750 | I8: 41461049 | J8: 41298547 | K8: 41148003 | L8: 41005653 | M8: 40869017 | N8: 40736558 | O8: 40607342 | P8: 40480762 | Q8: 40356513 | R8: 40234444 | S8: 40114457 | T8: 39996492 | U8: 39880514 | V8: 39766511 | W8: 39654478 | X8: 39544414 | Y8: 39436315 | Z8: 39330174 | AA8: 39225984 | AB8: 39123732 | AC8: 39023407 | AD8: 38924996 | AE8: 38828483 | AF8: 38733853 | AG8: 38641087 | AH8: 38550170 | AI8: 38461088 | AJ8: 38373824 | AK8: 38288364
A9: ch_auto_toe_0 | B9: 21780563 | C9: 21497416 | D9: 21345941 | E9: 21282035 | F9: 21276430 | G9: 21310026 | H9: 21370440 | I9: 21449612 | J9: 21542228 | K9: 21644710 | L9: 21754580 | M9: 21870078 | N9: 21989911 | O9: 22113111 | P9: 22238934 | Q9: 22366802 | R9: 22496260 | S9: 22626944 | T9: 22758567 | U9: 22890895 | V9: 23023742 | W9: 23156959 | X9: 23290425 | Y9: 23424044 | Z9: 23557743 | AA9: 23691465 | AB9: 23825167 | AC9: 23958822 | AD9: 24092412 | AE9: 24225929 | AF9: 24359375 | AG9: 24492758 | AH9: 24626091 | AI9: 24759393 | AJ9: 24892687 | AK9: 25025998
A10: cf_toe_ccoa_2 | B10: 5.4734959 | C10: 5.5277842 | D10: 5.5763322 | E10: 5.6200374 | F10: 5.6584105 | G10: 5.6900146 | H10: 5.7162224 | I10: 5.740534 | J10: 5.7646313 | K10: 5.788739 | L10: 5.8120972 | M10: 5.8333307 | N10: 5.850731 | O10: 5.8624817 | P10: 5.8668453 | Q10: 5.8623155 | R10: 5.8496952 | S10: 5.831699 | T10: 5.8104646 | U10: 5.7875406 | V10: 5.764025 | W10: 5.7406879 | X10: 5.7180639 | Y10: 5.6965189 | Z10: 5.676299 | AA10: 5.657566 | AB10: 5.6404226 | AC10: 5.624931 | AD10: 5.6111258 | AE10: 5.5990239 | AF10: 5.5886301 | AG10: 5.5799426 | AH10: 5.5729558 | AI10: 5.5676626 | AJ10: 5.5640557 | AK10: 5.5621288
A11: cf_toe_ccoa_0 | B11: 5.4734959 | C11: 5.5356888 | D11: 5.5982633 | E11: 5.6614783 | F11: 5.7254982 | G11: 5.7904348 | H11: 5.8563511 | I11: 5.9232659 | J11: 5.9911655 | K11: 6.0600186 | L11: 6.1297887 | M11: 6.2004423 | N11: 6.2719542 | O11: 6.3443082 | P11: 6.4174968 | Q11: 6.4915201 | R11: 6.566384 | S11: 6.6420978 | T11: 6.7186734 | U11: 6.7961236 | V11: 6.8744616 | W11: 6.9537 | X11: 7.0338512 | Y11: 7.1149265 | Z11: 7.1969371 | AA11: 7.2798932 | AB11: 7.363805 | AC11: 7.4486825 | AD11: 7.5345355 | AE11: 7.621374 | AF11: 7.7092081 | AG11: 7.7980482 | AH11: 7.8879046 | AI11: 7.9787883 | AJ11: 8.0707102 | AK11: 8.1636815
A12: cf_toe_ccoi_2 | B12: 0.084809986 | C12: 0.085667248 | D12: 0.086461996 | E12: 0.087219593 | F12: 0.087940294 | G12: 0.088609186 | H12: 0.089238191 | I12: 0.08986086 | J12: 0.090492412 | K12: 0.091133422 | L12: 0.091774684 | M12: 0.092400876 | N12: 0.092993253 | O12: 0.093531746 | P12: 0.093996669 | Q12: 0.094370137 | R12: 0.094658563 | S12: 0.094889281 | T12: 0.095083832 | U12: 0.095257792 | V12: 0.095422264 | W12: 0.095585158 | X12: 0.095752106 | Y12: 0.0959271 | Z12: 0.096112946 | AA12: 0.096311596 | AB12: 0.096524386 | AC12: 0.09675222 | AD12: 0.096995699 | AE12: 0.097255223 | AF12: 0.097531061 | AG12: 0.097823406 | AH12: 0.098132412 | AI12: 0.098458225 | AJ12: 0.098800993 | AK12: 0.099160884
... A737: ci_toe_cfuel_ser_0 | B737: 2.8654882 | C737: 2.8967075 | D737: 2.9278608 | E737: 2.9597623 | F737: 2.9926616 | G737: 3.0265472 | H737: 3.0613249 | I737: 3.0968928 | J737: 3.1331649 | K737: 3.170076 | L737: 3.2075792 | M737: 3.2456425 | N737: 3.2842451 | O737: 3.3233755 | P737: 3.363028 | Q737: 3.4032016 | R737: 3.443898 | S737: 3.4851202 | T737: 3.5268716 | U737: 3.5691552 | V737: 3.6119734 | W737: 3.6553275 | X737: 3.6992182 | Y737: 3.7436452 | Z737: 3.7886078 | AA737: 3.8341054 | AB737: 3.8801368 | AC737: 3.9267016 | AD737: 3.9737996 | AE737: 4.021431 | AF737: 4.0695968 | AG737: 4.1182989 | AH737: 4.1675396 | AI737: 4.2173221 | AJ737: 4.2676504 | AK737: 4.3185291

Sheet Primary_nrj
A1: _date_ | B1: 42005 | C1: 42370 | D1: 42736 | E1: 43101 | F1: 43466 | G1: 43831 | H1: 44197 | I1: 44562 | J1: 44927 | K1: 45292 | L1: 45658 | M1: 46023 | N1: 46388 | O1: 46753 | P1: 47119 | Q1: 47484 | R1: 47849 | S1: 48214 | T1: 48580 | U1: 48945 | V1: 49310 | W1: 49675 | X1: 50041 | Y1: 50406 | Z1: 50771 | AA1: 51136 | AB1: 51502 | AC1: 51867 | AD1: 52232 | AE1: 52597 | AF1: 52963 | AG1: 53328 | AH1: 53693 | AI1: 54058 | AJ1: 54424 | AK1: 54789
A2: yg_toe_2 | B2: 148.5762 | C2: 149.51833 | D2: 150.20339 | E2: 150.8468 | F2: 151.51552 | G2: 152.21225 | H2: 152.93671 | I2: 153.69789 | J2: 154.49581 | K2: 155.32369 | L2: 156.17039 | M2: 157.02223 | N2: 157.86422 | O2: 158.68104 | P2: 159.4577 | Q2: 160.18012 | R2: 160.84817 | S2: 161.47584 | T2: 162.07635 | U2: 162.65996 | V2: 163.23417 | W2: 163.80436 | X2: 164.37441 | Y2: 164.94717 | Z2: 165.5248 | AA2: 166.10902 | AB2: 166.7013 | AC2: 167.30293 | AD2: 167.91513 | AE2: 168.53913 | AF2: 169.17615 | AG2: 169.82746 | AH2: 170.4944 | AI2: 171.17836 | AJ2: 171.88078 | AK2: 172.60315
A3: yg_toe_0 | B3: 148.5762 | C3: 149.57013 | D3: 150.34484 | E3: 151.10989 | F3: 151.93569 | G3: 152.8347 | H3: 153.7993 | I3: 154.81742 | J3: 155.87806 | K3: 156.9727 | L3: 158.09525 | M3: 159.24155 | N3: 160.40878 | O3: 161.59512 | P3: 162.79935 | Q3: 164.0207 | R3: 165.25873 | S3: 166.51315 | T3: 167.78381 | U3: 169.07065 | V3: 170.37371 | W3: 171.69305 | X3: 173.02879 | Y3: 174.38103 | Z3: 175.74991 | AA3: 177.13559 | AB3: 178.53821 | AC3: 179.95794 | AD3: 181.39497 | AE3: 182.84948 | AF3: 184.32167 | AG3: 185.81175 | AH3: 187.31995 | AI3: 188.8465 | AJ3: 190.39163 | AK3: 191.95559
A4: yg_toe_ccoa_2 | B4: 2.391149 | C4: 2.4113403 | D4: 2.4286402 | E4: 2.4450674 | F4: 2.4608148 | G4: 2.4751913 | H4: 2.4883198 | I4: 2.5011328 | J4: 2.5140191 | K4: 2.5269145 | L4: 2.5394385 | M4: 2.5510018 | N4: 2.5608869 | O4: 2.5683162 | P4: 2.5725126 | Q4: 2.5727552 | R4: 2.5692525 | S4: 2.5630357 | T4: 2.5549306 | U4: 2.5455444 | V4: 2.5353159 | W4: 2.5245599 | X4: 2.5135003 | Y4: 2.5022939 | Z4: 2.4910476 | AA4: 2.4798318 | AB4: 2.468689 | AC4: 2.4576417 | AD4: 2.4466974 | AE4: 2.4358527 | AF4: 2.4250967 | AG4: 2.4144135 | AH4: 2.4037847 | AI4: 2.393191 | AJ4: 2.3826142 | AK4: 2.3720391
A5: yg_toe_ccoa_0 | B5: 2.391149 | C5: 2.4138098 | D5: 2.4355281 | E5: 2.4581598 | F5: 2.4821766 | G5: 2.5075019 | H5: 2.5339147 | I5: 2.5611973 | J5: 2.5891753 | K5: 2.6177206 | L5: 2.6467433 | M5: 2.6761821 | N5: 2.7059965 | O5: 2.7361603 | P5: 2.7666574 | Q5: 2.7974788 | R5: 2.8286204 | S5: 2.8600819 | T5: 2.8918649 | U5: 2.9239721 | V5: 2.9564069 | W5: 2.989173 | X5: 3.0222742 | Y5: 3.0557146 | Z5: 3.0894982 | AA5: 3.1236291 | AB5: 3.1581116 | AC5: 3.1929498 | AD5: 3.2281483 | AE5: 3.2637113 | AF5: 3.2996437 | AG5: 3.3359498 | AH5: 3.3726347 | AI5: 3.4097029 | AJ5: 3.4471595 | AK5: 3.4850092
A6: yg_toe_ccoi_2 | B6: 1.095999 | C6: 1.1024396 | D6: 1.1067161 | E6: 1.1110389 | F6: 1.1160485 | G6: 1.1216751 | H6: 1.127771 | I6: 1.1342991 | J6: 1.1412008 | K6: 1.1483812 | L6: 1.1557181 | M6: 1.1630714 | N6: 1.1702899 | O6: 1.177217 | P6: 1.1836957 | Q6: 1.1895728 | R6: 1.1948205 | S6: 1.1995524 | T6: 1.203885 | U6: 1.2079064 | V6: 1.2116771 | W6: 1.215235 | X6: 1.2186023 | Y6: 1.2217888 | Z6: 1.2247962 | AA6: 1.2276197 | AB6: 1.2302501 | AC6: 1.2326749 | AD6: 1.2348793 | AE6: 1.2368471 | AF6: 1.2385613 | AG6: 1.2400049 | AH6: 1.2411616 | AI6: 1.2420163 | AJ6: 1.2425564 | AK6: 1.2427718
A7: yg_toe_ccoi_0 | B7: 1.095999 | C7: 1.1028001 | D7: 1.1077768 | E7: 1.1130992 | F7: 1.1194315 | G7: 1.1267863 | H7: 1.1349781 | I7: 1.1438038 | J7: 1.1530986 | K7: 1.1627433 | L7: 1.1726568 | M7: 1.1827858 | N7: 1.1930955 | O7: 1.2035636 | P7: 1.2141752 | Q7: 1.2249212 | R7: 1.2357956 | S7: 1.2467947 | T7: 1.2579163 | U7: 1.2691592 | V7: 1.2805226 | W7: 1.2920062 | X7: 1.3036102 | Y7: 1.3153347 | Z7: 1.3271803 | AA7: 1.3391474 | AB7: 1.3512369 | AC7: 1.3634497 | AD7: 1.3757866 | AE7: 1.3882489 | AF7: 1.4008378 | AG7: 1.4135548 | AH7: 1.4264013 | AI7: 1.439379 | AJ7: 1.4524895 | AK7: 1.4657345
A8: yg_toe_cfut_2 | B8: 42.352189 | C8: 42.550339 | D8: 42.686302 | E8: 42.84323 | F8: 43.038564 | G8: 43.264921 | H8: 43.513952 | I8: 43.78234 | J8: 44.066371 | K8: 44.361627 | L8: 44.663093 | M8: 44.965278 | N8: 45.26234 | O8: 45.548213 | P8: 45.816747 | Q8: 46.061855 | R8: 46.282313 | S8: 46.48215 | T8: 46.665228 | U8: 46.834475 | V8: 46.991904 | W8: 47.138777 | X8: 47.275784 | Y8: 47.403172 | Z8: 47.520858 | AA8: 47.628503 | AB8: 47.725575 | AC8: 47.811398 | AD8: 47.885191 | AE8: 47.946101 | AF8: 47.993243 | AG8: 48.025727 | AH8: 48.042696 | AI8: 48.043357 | AJ8: 48.027023 | AK8: 47.993144
A9: yg_toe_cfut_0 | B9: 42.352189 | C9: 42.563839 | D9: 42.725107 | E9: 42.918049 | F9: 43.161282 | G9: 43.450606 | H9: 43.776175 | I9: 44.128632 | J9: 44.500733 | K9: 44.887349 | L9: 45.285004 | M9: 45.691393 | N9: 46.104998 | O9: 46.524822 | P9: 46.950201 | Q9: 47.380695 | R9: 47.816006 | S9: 48.255934 | T9: 48.700343 | U9: 49.149141 | V9: 49.602269 | W9: 50.059687 | X9: 50.521372 | Y9: 50.987312 | Z9: 51.457506 | AA9: 51.931962 | AB9: 52.410696 | AC9: 52.893729 | AD9: 53.381093 | AE9: 53.872825 | AF9: 54.368969 | AG9: 54.869575 | AH9: 55.3747 | AI9: 55.884403 | AJ9: 56.398749 | AK9: 56.917806
A10: yg_toe_cfuh_2 | B10: 7.935536 | C10: 7.9839831 | D10: 8.0145869 | E10: 8.0387744 | F10: 8.0606898 | G10: 8.0809697 | H10: 8.100653 | I10: 8.1215149 | J10: 8.1440541 | K10: 8.167944 | L10: 8.1923757 | M10: 8.2162685 | N10: 8.2383993 | O10: 8.2574887 | P10: 8.2722654 | Q10: 8.281521 | R10: 8.285611 | S10: 8.2862247 | T10: 8.284576 | U10: 8.2814961 | V10: 8.2775611 | W10: 8.2731806 | X10: 8.2686547 | Y10: 8.2642093 | Z10: 8.2600185 | AA10: 8.2562197 | AB10: 8.2529234 | AC10: 8.2502205 | AD10: 8.2481875 | AE10: 8.2468902 | AF10: 8.2463867 | AG10: 8.2467297 | AH10: 8.247968 | AI10: 8.2501482 | AJ10: 8.2533149 | AK10: 8.2575121
A11: yg_toe_cfuh_0 | B11: 7.935536 | C11: 7.9882333 | D11: 8.0259842 | E11: 8.0597632 | F11: 8.0940822 | G11: 8.1304841 | H11: 8.1692775 | I11: 8.2103169 | J11: 8.2533318 | K11: 8.2980554 | L11: 8.3442671 | M11: 8.3917989 | N11: 8.4405297 | O11: 8.4903729 | P11: 8.5412592 | Q11: 8.593147 | R11: 8.6460126 | S11: 8.6998426 | T11: 8.7546299 | U11: 8.8103707 | V11: 8.8670632 | W11: 8.9247063 | X11: 8.9832992 | Y11: 9.0428414 | Z11: 9.1033324 | AA11: 9.1647719 | AB11: 9.2271599 | AC11: 9.2904971 | AD11: 9.3547846 | AE11: 9.4200245 | AF11: 9.4862195 | AG11: 9.5533735 | AH11: 9.621491 | AI11: 9.6905774 | AJ11: 9.7606392 | AK11: 9.8316833
A12: yg_toe_cgas_2 | B12: 6.597728 | C12: 6.6023133 | D12: 6.5798666 | E12: 6.5467764 | F12: 6.5080886 | G12: 6.4644391 | H12: 6.4213775 | I12: 6.385027 | J12: 6.3548815 | K12: 6.3284719 | L12: 6.3031778 | M12: 6.2768809 | N12: 6.2481626 | O12: 6.2163283 | P12: 6.181363 | Q12: 6.1438464 | R12: 6.1075439 | S12: 6.076632 | T12: 6.0520068 | U12: 6.0333399 | V12: 6.0199343 | W12: 6.0110661 | X12: 6.0061042 | Y12: 6.0045364 | Z12: 6.005961 | AA12: 6.0100672 | AB12: 6.0166154 | AC12: 6.0254201 | AD12: 6.0363371 | AE12: 6.0492531 | AF12: 6.0640784 | AG12: 6.0807412 | AH12: 6.0991835 | AI12: 6.1193575 | AJ12: 6.1412231 | AK12: 6.1647457
... A73: yg_toe_cote_spub_0 | B73: 1.228594 | C73: 1.2411461 | D73: 1.2532706 | E73: 1.2655764 | F73: 1.2782706 | G73: 1.2913746 | H73: 1.3048474 | I73: 1.3186369 | J73: 1.3326976 | K73: 1.3469951 | L73: 1.3615048 | M73: 1.3762097 | N73: 1.3910986 | O73: 1.4061646 | P73: 1.4214036 | Q73: 1.4368139 | R73: 1.4523952 | S73: 1.4681482 | T73: 1.4840745 | U73: 1.5001759 | V73: 1.5164548 | W73: 1.5329136 | X73: 1.5495547 | Y73: 1.5663806 | Z73: 1.5833938 | AA73: 1.6005968 | AB73: 1.6179919 | AC73: 1.6355818 | AD73: 1.6533688 | AE73: 1.6713555 | AF73: 1.6895445 | AG73: 1.7079383 | AH73: 1.7265396 | AI73: 1.745351 | AJ73: 1.7643753 | AK73: 1.7836152

Sheet Energy_Mix
A1: _date_ | B1: 42005 | C1: 42370 | D1: 42736 | E1: 43101 | F1: 43466 | G1: 43831 | H1: 44197 | I1: 44562 | J1: 44927 | K1: 45292 | L1: 45658 | M1: 46023 | N1: 46388 | O1: 46753 | P1: 47119 | Q1: 47484 | R1: 47849 | S1: 48214 | T1: 48580 | U1: 48945 | V1: 49310 | W1: 49675 | X1: 50041 | Y1: 50406 | Z1: 50771 | AA1: 51136 | AB1: 51502 | AC1: 51867 | AD1: 52232 | AE1: 52597 | AF1: 52963 | AG1: 53328 | AH1: 53693 | AI1: 54058 | AJ1: 54424 | AK1: 54789
A2: phiy_ccoa_smin_2 | B2: 0.20069089 | C2: 0.20069089 | D2: 0.20069089 | E2: 0.20069089 | F2: 0.20069089 | G2: 0.20069089 | H2: 0.20069089 | I2: 0.20069089 | J2: 0.20069089 | K2: 0.20069089 | L2: 0.20069089 | M2: 0.20069089 | N2: 0.20069089 | O2: 0.20069089 | P2: 0.20069089 | Q2: 0.20069089 | R2: 0.20069089 | S2: 0.20069089 | T2: 0.20069089 | U2: 0.20069089 | V2: 0.20069089 | W2: 0.20069089 | X2: 0.20069089 | Y2: 0.20069089 | Z2: 0.20069089 | AA2: 0.20069089 | AB2: 0.20069089 | AC2: 0.20069089 | AD2: 0.20069089 | AE2: 0.20069089 | AF2: 0.20069089 | AG2: 0.20069089 | AH2: 0.20069089 | AI2: 0.20069089 | AJ2: 0.20069089 | AK2: 0.20069089
A3: phiy_ccoa_soil_2 | B3: 0.79930911 | C3: 0.79930911 | D3: 0.79930911 | E3: 0.79930911 | F3: 0.79930911 | G3: 0.79930911 | H3: 0.79930911 | I3: 0.79930911 | J3: 0.79930911 | K3: 0.79930911 | L3: 0.79930911 | M3: 0.79930911 | N3: 0.79930911 | O3: 0.79930911 | P3: 0.79930911 | Q3: 0.79930911 | R3: 0.79930911 | S3: 0.79930911 | T3: 0.79930911 | U3: 0.79930911 | V3: 0.79930911 | W3: 0.79930911 | X3: 0.79930911 | Y3: 0.79930911 | Z3: 0.79930911 | AA3: 0.79930911 | AB3: 0.79930911 | AC3: 0.79930911 | AD3: 0.79930911 | AE3: 0.79930911 | AF3: 0.79930911 | AG3: 0.79930911 | AH3: 0.79930911 | AI3: 0.79930911 | AJ3: 0.79930911 | AK3: 0.79930911
A4: phiy_ccoi_smin_2 | B4: 0.7836667 | C4: 0.7836667 | D4: 0.7836667 | E4: 0.7836667 | F4: 0.7836667 | G4: 0.7836667 | H4: 0.7836667 | I4: 0.7836667 | J4: 0.7836667 | K4: 0.7836667 | L4: 0.7836667 | M4: 0.7836667 | N4: 0.7836667 | O4: 0.7836667 | P4: 0.7836667 | Q4: 0.7836667 | R4: 0.7836667 | S4: 0.7836667 | T4: 0.7836667 | U4: 0.7836667 | V4: 0.7836667 | W4: 0.7836667 | X4: 0.7836667 | Y4: 0.7836667 | Z4: 0.7836667 | AA4: 0.7836667 | AB4: 0.7836667 | AC4: 0.7836667 | AD4: 0.7836667 | AE4: 0.7836667 | AF4: 0.7836667 | AG4: 0.7836667 | AH4: 0.7836667 | AI4: 0.7836667 | AJ4: 0.7836667 | AK4: 0.7836667
A5: phiy_ccoi_soil_2 | B5: 0.2163333 | C5: 0.2163333 | D5: 0.2163333 | E5: 0.2163333 | F5: 0.2163333 | G5: 0.2163333 | H5: 0.2163333 | I5: 0.2163333 | J5: 0.2163333 | K5: 0.2163333 | L5: 0.2163333 | M5: 0.2163333 | N5: 0.2163333 | O5: 0.2163333 | P5: 0.2163333 | Q5: 0.2163333 | R5: 0.2163333 | S5: 0.2163333 | T5: 0.2163333 | U5: 0.2163333 | V5: 0.2163333 | W5: 0.2163333 | X5: 0.2163333 | Y5: 0.2163333 | Z5: 0.2163333 | AA5: 0.2163333 | AB5: 0.2163333 | AC5: 0.2163333 | AD5: 0.2163333 | AE5: 0.2163333 | AF5: 0.2163333 | AG5: 0.2163333 | AH5: 0.2163333 | AI5: 0.2163333 | AJ5: 0.2163333 | AK5: 0.2163333
A6: phiy_cfut_soil_2 | B6: 0.83809636 | C6: 0.83809636 | D6: 0.83809636 | E6: 0.83809636 | F6: 0.83809636 | G6: 0.83809636 | H6: 0.83809636 | I6: 0.83809636 | J6: 0.83809636 | K6: 0.83809636 | L6: 0.83809636 | M6: 0.83809636 | N6: 0.83809636 | O6: 0.83809636 | P6: 0.83809636 | Q6: 0.83809636 | R6: 0.83809636 | S6: 0.83809636 | T6: 0.83809636 | U6: 0.83809636 | V6: 0.83809636 | W6: 0.83809636 | X6: 0.83809636 | Y6: 0.83809636 | Z6: 0.83809636 | AA6: 0.83809636 | AB6: 0.83809636 | AC6: 0.83809636 | AD6: 0.83809636 | AE6: 0.83809636 | AF6: 0.83809636 | AG6: 0.83809636 | AH6: 0.83809636 | AI6: 0.83809636 | AJ6: 0.83809636 | AK6: 0.83809636
A7: phiy_cfut_sbfu_2 | B7: 0.16190364 | C7: 0.16190364 | D7: 0.16190364 | E7: 0.16190364 | F7: 0.16190364 | G7: 0.16190364 | H7: 0.16190364 | I7: 0.16190364 | J7: 0.16190364 | K7: 0.16190364 | L7: 0.16190364 | M7: 0.16190364 | N7: 0.16190364 | O7: 0.16190364 | P7: 0.16190364 | Q7: 0.16190364 | R7: 0.16190364 | S7: 0.16190364 | T7: 0.16190364 | U7: 0.16190364 | V7: 0.16190364 | W7: 0.16190364 | X7: 0.16190364 | Y7: 0.16190364 | Z7: 0.16190364 | AA7: 0.16190364 | AB7: 0.16190364 | AC7: 0.16190364 | AD7: 0.16190364 | AE7: 0.16190364 | AF7: 0.16190364 | AG7: 0.16190364 | AH7: 0.16190364 | AI7: 0.16190364 | AJ7: 0.16190364 | AK7: 0.16190364
A8: phiy_cfuh_soil_2 | B8: 1 | C8: 1 | D8: 1 | E8: 1 | F8: 1 | G8: 1 | H8: 1 | I8: 1 | J8: 1 | K8: 1 | L8: 1 | M8: 1 | N8: 1 | O8: 1 | P8: 1 | Q8: 1 | R8: 1 | S8: 1 | T8: 1 | U8: 1 | V8: 1 | W8: 1 | X8: 1 | Y8: 1 | Z8: 1 | AA8: 1 | AB8: 1 | AC8: 1 | AD8: 1 | AE8: 1 | AF8: 1 | AG8: 1 | AH8: 1 | AI8: 1 | AJ8: 1 | AK8: 1
A9: phiy_cgas_smet_2 | B9: 8.2704782e-05 | C9: 8.2704782e-05 | D9: 8.2704782e-05 | E9: 8.2704782e-05 | F9: 8.2704782e-05 | G9: 8.2704782e-05 | H9: 8.2704782e-05 | I9: 8.2704782e-05 | J9: 8.2704782e-05 | K9: 8.2704782e-05 | L9: 8.2704782e-05 | M9: 8.2704782e-05 | N9: 8.2704782e-05 | O9: 8.2704782e-05 | P9: 8.2704782e-05 | Q9: 8.2704782e-05 | R9: 8.2704782e-05 | S9: 8.2704782e-05 | T9: 8.2704782e-05 | U9: 8.2704782e-05 | V9: 8.2704782e-05 | W9: 8.2704782e-05 | X9: 8.2704782e-05 | Y9: 8.2704782e-05 | Z9: 8.2704782e-05 | AA9: 8.2704782e-05 | AB9: 8.2704782e-05 | AC9: 8.2704782e-05 | AD9: 8.2704782e-05 | AE9: 8.2704782e-05 | AF9: 8.2704782e-05 | AG9: 8.2704782e-05 | AH9: 8.2704782e-05 | AI9: 8.2704782e-05 | AJ9: 8.2704782e-05 | AK9: 8.2704782e-05
A10: phiy_cgas_soil_2 | B10: 0.64531659 | C10: 0.64531659 | D10: 0.64531659 | E10: 0.64531659 | F10: 0.64531659 | G10: 0.64531659 | H10: 0.64531659 | I10: 0.64531659 | J10: 0.64531659 | K10: 0.64531659 | L10: 0.64531659 | M10: 0.64531659 | N10: 0.64531659 | O10: 0.64531659 | P10: 0.64531659 | Q10: 0.64531659 | R10: 0.64531659 | S10: 0.64531659 | T10: 0.64531659 | U10: 0.64531659 | V10: 0.64531659 | W10: 0.64531659 | X10: 0.64531659 | Y10: 0.64531659 | Z10: 0.64531659 | AA10: 0.64531659 | AB10: 0.64531659 | AC10: 0.64531659 | AD10: 0.64531659 | AE10: 0.64531659 | AF10: 0.64531659 | AG10: 0.64531659 | AH10: 0.64531659 | AI10: 0.64531659 | AJ10: 0.64531659 | AK10: 0.64531659
A11: phiy_cgas_sgas_2 | B11: 0.14751432 | C11: 0.14751432 | D11: 0.14751432 | E11: 0.14751432 | F11: 0.14751432 | G11: 0.14751432 | H11: 0.14751432 | I11: 0.14751432 | J11: 0.14751432 | K11: 0.14751432 | L11: 0.14751432 | M11: 0.14751432 | N11: 0.14751432 | O11: 0.14751432 | P11: 0.14751432 | Q11: 0.14751432 | R11: 0.14751432 | S11: 0.14751432 | T11: 0.14751432 | U11: 0.14751432 | V11: 0.14751432 | W11: 0.14751432 | X11: 0.14751432 | Y11: 0.14751432 | Z11: 0.14751432 | AA11: 0.14751432 | AB11: 0.14751432 | AC11: 0.14751432 | AD11: 0.14751432 | AE11: 0.14751432 | AF11: 0.14751432 | AG11: 0.14751432 | AH11: 0.14751432 | AI11: 0.14751432 | AJ11: 0.14751432 | AK11: 0.14751432
A12: phiy_cgas_sbga_2 | B12: 0.20708639 | C12: 0.20708639 | D12: 0.20708639 | E12: 0.20708639 | F12: 0.20708639 | G12: 0.20708639 | H12: 0.20708639 | I12: 0.20708639 | J12: 0.20708639 | K12: 0.20708639 | L12: 0.20708639 | M12: 0.20708639 | N12: 0.20708639 | O12: 0.20708639 | P12: 0.20708639 | Q12: 0.20708639 | R12: 0.20708639 | S12: 0.20708639 | T12: 0.20708639 | U12: 0.20708639 | V12: 0.20708639 | W12: 0.20708639 | X12: 0.20708639 | Y12: 0.20708639 | Z12: 0.20708639 | AA12: 0.20708639 | AB12: 0.20708639 | AC12: 0.20708639 | AD12: 0.20708639 | AE12: 0.20708639 | AF12: 0.20708639 | AG12: 0.20708639 | AH12: 0.20708639 | AI12: 0.20708639 | AJ12: 0.20708639 | AK12: 0.20708639
... A51: phiy_cote_spub_0 | B51: 0.00010273909 | C51: 0.00010273909 | D51: 0.00010273909 | E51: 0.00010273909 | F51: 0.00010273909 | G51: 0.00010273909 | H51: 0.00010273909 | I51: 0.00010273909 | J51: 0.00010273909 | K51: 0.00010273909 | L51: 0.00010273909 | M51: 0.00010273909 | N51: 0.00010273909 | O51: 0.00010273909 | P51: 0.00010273909 | Q51: 0.00010273909 | R51: 0.00010273909 | S51: 0.00010273909 | T51: 0.00010273909 | U51: 0.00010273909 | V51: 0.00010273909 | W51: 0.00010273909 | X51: 0.00010273909 | Y51: 0.00010273909 | Z51: 0.00010273909 | AA51: 0.00010273909 | AB51: 0.00010273909 | AC51: 0.00010273909 | AD51: 0.00010273909 | AE51: 0.00010273909 | AF51: 0.00010273909 | AG51: 0.00010273909 | AH51: 0.00010273909 | AI51: 0.00010273909 | AJ51: 0.00010273909 | AK51: 0.00010273909

Sheet Transports
A1: _date_ | B1: 42005 | C1: 42370 | D1: 42736 | E1: 43101 | F1: 43466 | G1: 43831 | H1: 44197 | I1: 44562 | J1: 44927 | K1: 45292 | L1: 45658 | M1: 46023 | N1: 46388 | O1: 46753 | P1: 47119 | Q1: 47484 | R1: 47849 | S1: 48214 | T1: 48580 | U1: 48945 | V1: 49310 | W1: 49675 | X1: 50041 | Y1: 50406 | Z1: 50771 | AA1: 51136 | AB1: 51502 | AC1: 51867 | AD1: 52232 | AE1: 52597 | AF1: 52963 | AG1: 53328 | AH1: 53693 | AI1: 54058 | AJ1: 54424 | AK1: 54789
A2: km_traveler_cair_2 | B2: 291099.78 | C2: 295820.99 | D2: 300398.31 | E2: 304939.29 | F2: 309486.94 | G2: 314040.24 | H2: 318658.45 | I2: 323442.27 | J2: 328421.13 | K2: 333574.55 | L2: 338859.98 | M2: 344226.69 | N2: 349622.81 | O2: 354999.02 | P2: 360310.57 | Q2: 365518.72 | R2: 370661.38 | S2: 375836.59 | T2: 381104.41 | U2: 386493 | V2: 392014.59 | W2: 397673.38 | X2: 403469.62 | Y2: 409401.64 | Z2: 415466.73 | AA2: 421661.63 | AB2: 427982.62 | AC2: 434425.61 | AD2: 440986.26 | AE2: 447659.98 | AF2: 454442.11 | AG2: 461327.96 | AH2: 468312.95 | AI2: 475392.66 | AJ2: 482562.96 | AK2: 489820.02
A3: km_trav_auto_ld_2+km_trav_auto_sd_2 | B3: 724102.94 | C3: 715355.49 | D3: 710971.42 | E3: 709498.48 | F3: 709947.49 | G3: 711651.17 | H3: 714212.51 | I3: 717410.6 | J3: 721079.02 | K3: 725085.74 | L3: 729322.26 | M3: 733696.15 | N3: 738125.9 | O3: 742537.43 | P3: 746861.78 | Q3: 751033.63 | R3: 755045.86 | S3: 758941.13 | T3: 762741.97 | U3: 766458.72 | V3: 770096.05 | W3: 773656.44 | X3: 777141.92 | Y3: 780554.97 | Z3: 783898.91 | AA3: 787178.12 | AB3: 790398.23 | AC3: 793566.13 | AD3: 796690.14 | AE3: 799780.09 | AF3: 802847.37 | AG3: 805904.99 | AH3: 808967.65 | AI3: 812051.66 | AJ3: 815174.9 | AK3: 818356.68
A4: km_traveler_sd_2 | B4: 624600.34 | C4: 618861.96 | D4: 616086.94 | E4: 615320.55 | F4: 615893.37 | G4: 617345.72 | H4: 619400.72 | I4: 621904.14 | J4: 624740.22 | K4: 627815.98 | L4: 631054.33 | M4: 634389.27 | N4: 637762.46 | O4: 641120.92 | P4: 644415.42 | Q4: 647599.45 | R4: 650667.15 | S4: 653648.66 | T4: 656561.13 | U4: 659412.6 | V4: 662206.81 | W4: 664945.74 | X4: 667630.94 | Y4: 670264.14 | Z4: 672847.6 | AA4: 675384.29 | AB4: 677878.01 | AC4: 680333.43 | AD4: 682756.21 | AE4: 685153.03 | AF4: 687531.66 | AG4: 689901.02 | AH4: 692271.18 | AI4: 694653.37 | AJ4: 697059.91 | AK4: 699504.1
A5: km_trav_auto_sd_2 | B5: 554271.64 | C5: 547921.8 | D5: 544690.45 | E5: 543539.71 | F5: 543761.34 | G5: 544877.08 | H5: 546602.29 | I5: 548778.6 | J5: 551286.78 | K5: 554032.31 | L5: 556937.57 | M5: 559936.54 | N5: 562971.09 | O5: 565988.51 | P5: 568939.9 | Q5: 571779.03 | R5: 574501.2 | S5: 577137.05 | T5: 579702.89 | U5: 582206.36 | V5: 584650.97 | W5: 587038.66 | X5: 589371.02 | Y5: 591649.94 | Z5: 593877.92 | AA5: 596058.19 | AB5: 598194.86 | AC5: 600292.93 | AD5: 602358.41 | AE5: 604398.34 | AF5: 606420.83 | AG5: 608435.13 | AH5: 610451.63 | AI5: 612481.83 | AJ5: 614538.29 | AK5: 616634.52
A6: km_traveler_croa_2 | B6: 70328.7 | C6: 70321.714 | D6: 70422.251 | E6: 70597.879 | F6: 70825.341 | G6: 71088.354 | H6: 71376.45 | I6: 71684.112 | J6: 72007.76 | K6: 72343.932 | L6: 72689.393 | M6: 73041.122 | N6: 73396.292 | O6: 73752.239 | P6: 74106.43 | Q6: 74456.445 | R6: 74801.305 | S6: 75142.139 | T6: 75480.232 | U6: 75816.213 | V6: 76150.391 | W6: 76482.908 | X6: 76813.819 | Y6: 77143.137 | Z6: 77470.868 | AA6: 77797.019 | AB6: 78121.617 | AC6: 78444.712 | AD6: 78766.388 | AE6: 79086.767 | AF6: 79406.016 | AG6: 79724.354 | AH6: 80042.056 | AI6: 80359.451 | AJ6: 80676.929 | AK6: 80994.935
A7: km_traveler_ld_2 | B7: 275159.81 | C7: 270792.35 | D7: 268629.34 | E7: 267925.6 | F7: 268182.2 | G7: 269066.09 | H7: 270380.45 | I7: 272015.85 | J7: 273889.6 | K7: 275936.38 | L7: 278102.65 | M7: 280342.82 | N7: 282616.53 | O7: 284886.94 | P7: 287119.53 | Q7: 289281.38 | R7: 291368.75 | S7: 293402.59 | T7: 295393.37 | U7: 297345.68 | V7: 299261.42 | W7: 301141.52 | X7: 302986.77 | Y7: 304798.24 | Z7: 306577.45 | AA7: 308326.49 | AB7: 310048.08 | AC7: 311745.62 | AD7: 313423.28 | AE7: 315085.99 | AF7: 316739.55 | AG7: 318390.62 | AH7: 320046.74 | AI7: 321716.35 | AJ7: 323408.76 | AK7: 325134.05
A8: km_trav_auto_ld_2 | B8: 169831.3 | C8: 167433.69 | D8: 166280.96 | E8: 165958.76 | F8: 166186.15 | G8: 166774.09 | H8: 167610.22 | I8: 168632 | J8: 169792.24 | K8: 171053.44 | L8: 172384.69 | M8: 173759.61 | N8: 175154.81 | O8: 176548.92 | P8: 177921.88 | Q8: 179254.59 | R8: 180544.66 | S8: 181804.09 | T8: 183039.08 | U8: 184252.36 | V8: 185445.08 | W8: 186617.78 | X8: 187770.9 | Y8: 188905.03 | Z8: 190020.99 | AA8: 191119.93 | AB8: 192203.37 | AC8: 193273.19 | AD8: 194331.73 | AE8: 195381.76 | AF8: 196426.54 | AG8: 197469.86 | AH8: 198516.02 | AI8: 199569.83 | AJ8: 200636.61 | AK8: 201722.15
A9: km_traveler_crai_2 | B9: 105328.51 | C9: 106469.68 | D9: 107456.72 | E9: 108342.29 | F9: 109165.34 | G9: 109953.23 | H9: 110720.41 | I9: 111476.07 | J9: 112229.34 | K9: 112985.45 | L9: 113747.47 | M9: 114517.13 | N9: 115295.4 | O9: 116082.8 | P9: 116879.61 | Q9: 117685.97 | R9: 118499.29 | S9: 119317.63 | T9: 120142.3 | U9: 120973.97 | V9: 121813.01 | W9: 122659.55 | X9: 123513.49 | Y9: 124374.54 | Z9: 125242.25 | AA9: 126116.04 | AB9: 126995.22 | AC9: 127878.97 | AD9: 128766.41 | AE9: 129656.57 | AF9: 130548.42 | AG9: 131440.88 | AH9: 132332.84 | AI9: 133223.15 | AJ9: 134110.68 | AK9: 134994.27
A10: km_traveler_cair_0 | B10: 291099.78 | C10: 295997.44 | D10: 300860.61 | E10: 305754.88 | F10: 310735.66 | G10: 315838.96 | H10: 321084.31 | I10: 326479.86 | J10: 332026.96 | K10: 337723.35 | L10: 343565.4 | M10: 349549.32 | N10: 355671.93 | O10: 361930.82 | P10: 368324.44 | Q10: 374851.94 | R10: 381513.03 | S10: 388307.75 | T10: 395236.36 | U10: 402299.23 | V10: 409496.72 | W10: 416829.19 | X10: 424297 | Y10: 431900.48 | Z10: 439640.02 | AA10: 447516.04 | AB10: 455529.1 | AC10: 463679.89 | AD10: 471969.28 | AE10: 480398.31 | AF10: 488968.27 | AG10: 497680.64 | AH10: 506537.12 | AI10: 515539.66 | AJ10: 524690.39 | AK10: 533991.65
A11: km_trav_auto_ld_0+km_trav_auto_sd_0 | B11: 724102.94 | C11: 715470.96 | D11: 711264.17 | E11: 710013.52 | F11: 710740.21 | G11: 712802.83 | H11: 715783.55 | I11: 719409 | J11: 723497.85 | K11: 727927.15 | L11: 732611.22 | M11: 737488.53 | N11: 742513.6 | O11: 747651.94 | P11: 752876.85 | Q11: 758167.34 | R11: 763506.69 | S11: 768881.53 | T11: 774281.06 | U11: 779696.54 | V11: 785120.94 | W11: 790548.57 | X11: 795974.88 | Y11: 801396.29 | Z11: 806810.03 | AA11: 812214.03 | AB11: 817606.82 | AC11: 822987.5 | AD11: 828355.61 | AE11: 833711.09 | AF11: 839054.27 | AG11: 844385.75 | AH11: 849706.42 | AI11: 855017.37 | AJ11: 860319.87 | AK11: 865615.34
A12: km_traveler_sd_0 | B12: 624600.34 | C12: 618939.61 | D12: 616289.43 | E12: 615681.22 | F12: 616451.95 | G12: 618159.91 | H12: 620514.29 | I12: 623323.46 | J12: 626459.54 | K12: 629835.38 | L12: 633389.98 | M12: 637079.36 | N12: 640870.93 | O12: 644739.98 | P12: 648667.38 | Q12: 652638.14 | R12: 656640.39 | S12: 660664.65 | T12: 664703.32 | U12: 668750.31 | V12: 672800.7 | W12: 676850.59 | X12: 680896.84 | Y12: 684937.02 | Z12: 688969.25 | AA12: 692992.16 | AB12: 697004.79 | AC12: 701006.58 | AD12: 704997.26 | AE12: 708976.87 | AF12: 712945.68 | AG12: 716904.19 | AH12: 720853.05 | AI12: 724793.07 | AJ12: 728725.2 | AK12: 732650.46
... A17: km_traveler_crai_0 | B17: 105328.51 | C17: 106459.91 | D17: 107439.19 | E17: 108316.26 | F17: 109128.73 | G17: 109902.85 | H17: 110656.13 | I17: 111399.76 | J17: 112140.59 | K17: 112882.66 | L17: 113628.2 | M17: 114378.45 | N17: 115134.04 | O17: 115895.36 | P17: 116662.67 | Q17: 117436.16 | R17: 118216.02 | S17: 119002.41 | T17: 119795.47 | U17: 120595.32 | V17: 121402.02 | W17: 122215.62 | X17: 123036.12 | Y17: 123863.49 | Z17: 124697.68 | AA17: 125538.64 | AB17: 126386.3 | AC17: 127240.59 | AD17: 128101.43 | AE17: 128968.79 | AF17: 129842.6 | AG17: 130722.83 | AH17: 131609.47 | AI17: 132502.5 | AJ17: 133401.93 | AK17: 134307.77

Sheet Hybrid
A1: _date_ | B1: 42005 | C1: 42370 | D1: 42736 | E1: 43101 | F1: 43466 | G1: 43831 | H1: 44197 | I1: 44562 | J1: 44927 | K1: 45292 | L1: 45658 | M1: 46023 | N1: 46388 | O1: 46753 | P1: 47119 | Q1: 47484 | R1: 47849 | S1: 48214 | T1: 48580 | U1: 48945 | V1: 49310 | W1: 49675 | X1: 50041 | Y1: 50406 | Z1: 50771 | AA1: 51136 | AB1: 51502 | AC1: 51867 | AD1: 52232 | AE1: 52597 | AF1: 52963 | AG1: 53328 | AH1: 53693 | AI1: 54058 | AJ1: 54424 | AK1: 54789
A2: auto_2 | B2: 32317.941 | C2: 31926.455 | D2: 31730.401 | E2: 31664.733 | F2: 31685.152 | G2: 31761.774 | H2: 31876.82 | I2: 32020.398 | J2: 32185.055 | K2: 32364.879 | L2: 32555.008 | M2: 32751.304 | N2: 32950.116 | O2: 33148.123 | P2: 33342.238 | Q2: 33529.533 | R2: 33709.688 | S2: 33884.612 | T2: 34055.315 | U2: 34222.258 | V2: 34385.651 | W2: 34545.604 | X2: 34702.207 | Y2: 34855.571 | Z2: 35005.845 | AA2: 35153.224 | AB2: 35297.96 | AC2: 35440.362 | AD2: 35580.802 | AE2: 35719.72 | AF2: 35857.626 | AG2: 35995.104 | AH2: 36132.812 | AI2: 36271.48 | AJ2: 36411.912 | AK2: 36554.972
A3: auto_cfut_2 | B3: 32271.24 | C3: 31862.032 | D3: 31647.329 | E3: 31562.481 | F3: 31563.392 | G3: 31620.229 | H3: 31715.127 | I3: 31838.038 | J3: 31981.349 | K3: 32138.974 | L3: 32305.854 | M3: 32477.604 | N3: 32650.259 | O3: 32820.093 | P3: 32983.48 | Q3: 33136.779 | R3: 33278.705 | S3: 33409.974 | T3: 33530.266 | U3: 33638.562 | V3: 33733.424 | W3: 33813.135 | X3: 33875.774 | Y3: 33919.241 | Z3: 33941.277 | AA3: 33939.472 | AB3: 33911.279 | AC3: 33854.036 | AD3: 33764.983 | AE3: 33641.306 | AF3: 33480.173 | AG3: 33278.793 | AH3: 33034.477 | AI3: 32744.706 | AJ3: 32407.216 | AK3: 32020.075
A4: auto_cele_2 | B4: 44.765 | C4: 62.431569 | D4: 81.013696 | E4: 100.12298 | F4: 119.55791 | G4: 139.26917 | H4: 159.3444 | I4: 179.94081 | J4: 201.21851 | K4: 223.34991 | L4: 246.53496 | M4: 271.01944 | N4: 297.11658 | O4: 325.23391 | P4: 355.90822 | Q4: 389.85321 | R4: 428.03471 | S4: 471.64531 | T4: 522.01458 | U4: 580.62349 | V4: 649.11914 | W4: 729.32712 | X4: 823.26146 | Y4: 933.13161 | Z4: 1061.3459 | AA4: 1210.5101 | AB4: 1383.4212 | AC4: 1583.0534 | AD4: 1812.5367 | AE4: 2075.1269 | AF4: 2374.165 | AG4: 2713.0263 | AH4: 3095.0588 | AI4: 3523.5113 | AJ4: 4001.4512 | AK4: 4531.6755
A5: auto_cgas_2 | B5: 1.936 | C5: 1.9916056 | D5: 2.0574011 | E5: 2.1285899 | F5: 2.2019794 | G5: 2.2754864 | H5: 2.3479684 | I5: 2.4188941 | J5: 2.4879043 | K5: 2.5547408 | L5: 2.6192081 | M5: 2.6811463 | N5: 2.7404124 | O5: 2.796866 | P5: 2.8503601 | Q5: 2.9007315 | R5: 2.9480014 | S5: 2.9923496 | T5: 3.033862 | U5: 3.0725586 | V5: 3.1084159 | W5: 3.1413797 | X5: 3.17137 | Y5: 3.1982849 | Z5: 3.2220012 | AA5: 3.2423764 | AB5: 3.2592496 | AC5: 3.2724433 | AD5: 3.2817658 | AE5: 3.2870146 | AF5: 3.2879801 | AG5: 3.2844506 | AH5: 3.2762179 | AI5: 3.2630839 | AJ5: 3.2448672 | AK5: 3.2214115
A6: newauto_2 | B6: 1886.229 | C6: 2121.806 | D6: 2286.103 | E6: 2400.5287 | F6: 2480.7808 | G6: 2537.837 | H6: 2581.4773 | I6: 2618.2022 | J6: 2649.6746 | K6: 2676.8483 | L6: 2700.3106 | M6: 2720.3954 | N6: 2737.2597 | O6: 2750.94 | P6: 2761.3918 | Q6: 2768.517 | R6: 2774.6678 | S6: 2782.0126 | T6: 2789.7533 | U6: 2797.3729 | V6: 2804.5969 | W6: 2811.2808 | X6: 2817.3451 | Y6: 2822.7399 | Z6: 2827.4284 | AA6: 2831.3791 | AB6: 2834.5629 | AC6: 2836.9523 | AD6: 2838.522 | AE6: 2839.2497 | AF6: 2839.1172 | AG6: 2838.111 | AH6: 2836.2234 | AI6: 2833.4523 | AJ6: 2829.8021 | AK6: 2825.2831
A7: newauto_cfut_2 | B7: 1868.803 | C7: 2102.1722 | D7: 2264.8333 | E7: 2377.9791 | F7: 2457.1346 | G7: 2513.1323 | H7: 2555.6166 | I7: 2591.0143 | J7: 2620.9791 | K7: 2646.4458 | L7: 2667.9674 | M7: 2685.8239 | N7: 2700.095 | O7: 2710.7103 | P7: 2717.4798 | Q7: 2720.1072 | R7: 2720.6636 | S7: 2721.052 | T7: 2720.2897 | U7: 2717.6551 | V7: 2712.6484 | W7: 2704.8808 | X7: 2694.0114 | Y7: 2679.7142 | Z7: 2661.6653 | AA7: 2639.5392 | AB7: 2613.0119 | AC7: 2581.7664 | AD7: 2545.5027 | AE7: 2503.9477 | AF7: 2456.8677 | AG7: 2404.0812 | AH7: 2345.4727 | AI7: 2281.0058 | AJ7: 2210.7359 | AK7: 2134.8214
A8: newauto_cele_2 | B8: 17.269 | C8: 19.457169 | D8: 21.079389 | E8: 22.349837 | F8: 23.439846 | G8: 24.493574 | H8: 25.645995 | I8: 26.970187 | J8: 28.475336 | K8: 30.180137 | L8: 32.119048 | M8: 34.345876 | N8: 36.937918 | O8: 40.001998 | P8: 43.683666 | Q8: 48.181314 | R8: 53.775634 | S8: 60.731991 | T8: 69.235074 | U8: 79.489496 | V8: 91.720592 | W8: 106.17275 | X8: 123.10742 | Y8: 142.80061 | Z8: 165.53951 | AA8: 191.6181 | AB8: 221.33152 | AC8: 254.96899 | AD8: 292.80546 | AE8: 335.09168 | AF8: 382.04314 | AG8: 433.82787 | AH8: 490.55361 | AI8: 552.25485 | AJ8: 618.88039 | AK8: 690.28232
A9: newauto_cgas_2 | B9: 0.157 | C9: 0.17660558 | D9: 0.1902709 | E9: 0.19977639 | F9: 0.20642632 | G9: 0.21113075 | H9: 0.2146999 | I9: 0.21767369 | J9: 0.22019106 | K9: 0.22233054 | L9: 0.2241386 | M9: 0.22563874 | N9: 0.22683766 | O9: 0.22772947 | P9: 0.22829818 | Q9: 0.22851891 | R9: 0.22856566 | S9: 0.22859828 | T9: 0.22853425 | U9: 0.22831291 | V9: 0.22789229 | W9: 0.22723973 | X9: 0.22632658 | Y9: 0.22512545 | Z9: 0.22360915 | AA9: 0.22175032 | AB9: 0.21952173 | AC9: 0.21689677 | AD9: 0.21385022 | AE9: 0.21035914 | AF9: 0.2064039 | AG9: 0.20196925 | AH9: 0.1970455 | AI9: 0.19162957 | AJ9: 0.18572613 | AK9: 0.17934847
A10: auto_0 | B10: 32317.941 | C10: 31931.625 | D10: 31743.508 | E10: 31687.792 | F10: 31720.643 | G10: 31813.337 | H10: 31947.162 | I10: 32109.877 | J10: 32293.361 | K10: 32492.109 | L10: 32702.282 | M10: 32921.126 | N10: 33146.603 | O10: 33377.168 | P10: 33611.625 | Q10: 33849.034 | R10: 34088.645 | S10: 34329.861 | T10: 34572.195 | U10: 34815.259 | V10: 35058.734 | W10: 35302.368 | X10: 35545.956 | Y10: 35789.336 | Z10: 36032.386 | AA10: 36275.011 | AB10: 36517.147 | AC10: 36758.751 | AD10: 36999.804 | AE10: 37240.303 | AF10: 37480.262 | AG10: 37719.709 | AH10: 37958.683 | AI10: 38197.232 | AJ10: 38435.414 | AK10: 38673.292
A11: auto_cfut_0 | B11: 32271.24 | C11: 31867.185 | D11: 31660.486 | E11: 31585.838 | F11: 31599.721 | G11: 31673.603 | H11: 31788.887 | I11: 31933.397 | J11: 32099.044 | K11: 32280.337 | L11: 32473.442 | M11: 32675.599 | N11: 32884.76 | O11: 33099.371 | P11: 33318.22 | Q11: 33540.352 | R11: 33765.004 | S11: 33991.56 | T11: 34219.518 | U11: 34448.472 | V11: 34678.087 | W11: 34908.092 | X11: 35138.266 | Y11: 35368.429 | Z11: 35598.44 | AA11: 35828.186 | AB11: 36057.582 | AC11: 36286.569 | AD11: 36515.105 | AE11: 36743.166 | AF11: 36970.745 | AG11: 37197.847 | AH11: 37424.486 | AI11: 37650.688 | AJ11: 37876.482 | AK11: 38101.906
A12: auto_cele_0 | B12: 44.765 | C12: 62.448716 | D12: 80.963971 | E12: 99.823967 | F12: 118.71772 | G12: 137.4542 | H12: 155.92054 | I12: 174.05324 | J12: 191.81931 | K12: 209.20456 | L12: 226.20631 | M12: 242.82901 | N12: 259.08157 | O12: 274.97577 | P12: 290.52522 | Q12: 305.74472 | R12: 320.64987 | S12: 335.2568 | T12: 349.58202 | U12: 363.64234 | V12: 377.45479 | W12: 391.03665 | X12: 404.40544 | Y12: 417.57898 | Z12: 430.57544 | AA12: 443.4134 | AB12: 456.11191 | AC12: 468.69057 | AD12: 481.16966 | AE12: 493.57013 | AF12: 505.91381 | AG12: 518.22339 | AH12: 530.52261 | AI12: 542.83631 | AJ12: 555.19057 | AK12: 567.61281
... A121: buil_des_0 | B121: 1.1716777 | C121: 1.1716777 | D121: 1.1565402 | E121: 1.1416083 | F121: 1.1268791 | G121: 1.1123494 | H121: 1.0980163 | I121: 1.083877 | J121: 1.0699286 | K121: 1.0561683 | L121: 1.0425934 | M121: 1.0292012 | N121: 1.0159892 | O121: 1.0029547 | P121: 0.99009523 | Q121: 0.97740825 | R121: 0.96489133 | S121: 0.95254204 | T121: 0.940358 | U121: 0.92833689 | V121: 0.91647639 | W121: 0.90477425 | X121: 0.89322823 | Y121: 0.88183615 | Z121: 0.87059586 | AA121: 0.85950523 | AB121: 0.84856218 | AC121: 0.83776466 | AD121: 0.82711064 | AE121: 0.81659814 | AF121: 0.8062252 | AG121: 0.7959899 | AH121: 0.78589034 | AI121: 0.77592465 | AJ121: 0.766091 | AK121: 0.75638758

Sheet Tab-macro
B1: en écart au scénario de référence (%)
B2: ThreeME
B3: 2021 | C3: 2022 | D3: 2023 | E3: 2025 | F3: 2030 | G3: 2050
A4: PIB en volume | B4: =Macro!H2 -> 0.048738572 | C4: =Macro!I2 -> 0.060095859 | D4: =Macro!J2 -> 0.070015107 | E4: =Macro!L2 -> 0.085962983 | F4: =Macro!Q2 -> 0.14265241 | G4: =Macro!AK2 -> 0.14504591
A5: Consommation des ménages | B5: =Macro!H3 -> 0.063591595 | C5: =Macro!I3 -> 0.077928064 | D5: =Macro!J3 -> 0.090208724 | E5: =Macro!L3 -> 0.1094652 | F5: =Macro!Q3 -> 0.17703503 | G5: =Macro!AK3 -> 0.12232402
A6: Investissement | B6: =Macro!H4 -> 0.061611156 | C6: =Macro!I4 -> 0.08278401 | D6: =Macro!J4 -> 0.10533605 | E6: =Macro!L4 -> 0.15272541 | F6: =Macro!Q4 -> 0.31843771 | G6: =Macro!AK4 -> 1.5666395
A7: Exportations | B7: =Macro!H5 -> -0.024587398 | C7: =Macro!I5 -> -0.027517752 | D7: =Macro!J5 -> -0.029270488 | E7: =Macro!L5 -> -0.033062862 | F7: =Macro!Q5 -> -0.071051222 | G7: =Macro!AK5 -> -0.31031219
A8: Importations | B8: =Macro!H6 -> 0 | C8: =Macro!I6 -> 0 | D8: =Macro!J6 -> 0 | E8: =Macro!L6 -> 0 | F8: =Macro!Q6 -> 0 | G8: =Macro!AK6 -> 0
A9: Revenu disponible (réel) des ménages | B9: =Macro!H7 -> -0.012798614 | C9: =Macro!I7 -> -0.016283169 | D9: =Macro!J7 -> -0.019770476 | E9: =Macro!L7 -> -0.027092237 | F9: =Macro!Q7 -> -0.053082546 | G9: =Macro!AK7 -> -0.24896132
A10: Taux d'épargne (en pts) | B10: =Macro!H8 -> 0 | C10: =Macro!I8 -> 0 | D10: =Macro!J8 -> 0 | E10: =Macro!L8 -> 0 | F10: =Macro!Q8 -> 0 | G10: =Macro!AK8 -> 0
A11: Prix de la consommation des ménages | B11: =Macro!H9 -> -7.3934973e-05 | C11: =Macro!I9 -> -0.0064049649 | D11: =Macro!J9 -> -0.015550473 | E11: =Macro!L9 -> -0.039670205 | F11: =Macro!Q9 -> -0.12270277 | G11: =Macro!AK9 -> -1.1726323
A12: Prix de la production | B12: =Macro!H10 -> 0.060548092 | C12: =Macro!I10 -> 0.081405037 | D12: =Macro!J10 -> 0.1036274 | E12: =Macro!L10 -> 0.1502951 | F12: =Macro!Q10 -> 0.31317578 | G12: =Macro!AK10 -> 1.5416795
A13: Prix de la valeur ajoutée | B13: =Macro!H11 -> -0.011735551 | C13: =Macro!I11 -> -0.014904197 | D13: =Macro!J11 -> -0.018061834 | E13: =Macro!L11 -> -0.024661926 | F13: =Macro!Q11 -> -0.047820621 | G13: =Macro!AK11 -> -0.2240013
A14: Prix des consommations intermédiaires | B14: =Macro!H12 -> -0.011136824 | C14: =Macro!I12 -> -0.014171638 | D14: =Macro!J12 -> -0.017215766 | E14: =Macro!L12 -> -0.023646689 | F14: =Macro!Q12 -> -0.046521399 | G14: =Macro!AK12 -> -0.21942615
A15: Prix des exportations | B15: =Macro!H13 -> 0.0010630635 | C15: =Macro!I13 -> 0.0013789727 | D15: =Macro!J13 -> 0.0017086427 | E15: =Macro!L13 -> 0.0024303114 | F15: =Macro!Q13 -> 0.0052619252 | G15: =Macro!AK13 -> 0.024960015
... A24: Emissions de CO2 | B24: =Macro!H22 -> 0.11223714 | C24: =Macro!I22 -> 0.15093497 | D24: =Macro!J22 -> 0.19217887 | E24: =Macro!L22 -> 0.2788085 | F24: =Macro!Q22 -> 0.58101383 | G24: =Macro!AK22 -> 2.8548709
B26: % deviation from baseline
B27: ThreeME
B28: 2021 | C28: 2022 | D28: 2023 | E28: 2025 | F28: 2030 | G28: 2050
A29: GDP in volume | B29: =B4 -> 0.048738572 | C29: =C4 -> 0.060095859 | D29: =D4 -> 0.070015107 | E29: =E4 -> 0.085962983 | F29: =F4 -> 0.14265241 | G29: =G4 -> 0.14504591
A30: Household consumption | B30: =B5 -> 0.063591595 | C30: =C5 -> 0.077928064 | D30: =D5 -> 0.090208724 | E30: =E5 -> 0.1094652 | F30: =F5 -> 0.17703503 | G30: =G5 -> 0.12232402
A31: Investment | B31: =B6 -> 0.061611156 | C31: =C6 -> 0.08278401 | D31: =D6 -> 0.10533605 | E31: =E6 -> 0.15272541 | F31: =F6 -> 0.31843771 | G31: =G6 -> 1.5666395
A32: Exports | B32: =B7 -> -0.024587398 | C32: =C7 -> -0.027517752 | D32: =D7 -> -0.029270488 | E32: =E7 -> -0.033062862 | F32: =F7 -> -0.071051222 | G32: =G7 -> -0.31031219
A33: Imports | B33: =B8 -> 0 | C33: =C8 -> 0 | D33: =D8 -> 0 | E33: =E8 -> 0 | F33: =F8 -> 0 | G33: =G8 -> 0
A34: Household disposable income (real) | B34: =B9 -> -0.012798614 | C34: =C9 -> -0.016283169 | D34: =D9 -> -0.019770476 | E34: =E9 -> -0.027092237 | F34: =F9 -> -0.053082546 | G34: =G9 -> -0.24896132
A35: Saving rate (in points) | B35: =B10 -> 0 | C35: =C10 -> 0 | D35: =D10 -> 0 | E35: =E10 -> 0 | F35: =F10 -> 0 | G35: =G10 -> 0
A36: Household consumption price index | B36: =B11 -> -7.3934973e-05 | C36: =C11 -> -0.0064049649 | D36: =D11 -> -0.015550473 | E36: =E11 -> -0.039670205 | F36: =F11 -> -0.12270277 | G36: =G11 -> -1.1726323
A37: Production price index | B37: =B12 -> 0.060548092 | C37: =C12 -> 0.081405037 | D37: =D12 -> 0.1036274 | E37: =E12 -> 0.1502951 | F37: =F12 -> 0.31317578 | G37: =G12 -> 1.5416795
A38: Added value price index | B38: =B13 -> -0.011735551 | C38: =C13 -> -0.014904197 | D38: =D13 -> -0.018061834 | E38: =E13 -> -0.024661926 | F38: =F13 -> -0.047820621 | G38: =G13 -> -0.2240013
A39: Intermediate consumption price index | B39: =B14 -> -0.011136824 | C39: =C14 -> -0.014171638 | D39: =D14 -> -0.017215766 | E39: =E14 -> -0.023646689 | F39: =F14 -> -0.046521399 | G39: =G14 -> -0.21942615
A40: Export price index | B40: =B15 -> 0.0010630635 | C40: =C15 -> 0.0013789727 | D40: =D15 -> 0.0017086427 | E40: =E15 -> 0.0024303114 | F40: =F15 -> 0.0052619252 | G40: =G15 -> 0.024960015
... A49: CO2 emissions | B49: =B24 -> 0.11223714 | C49: =C24 -> 0.15093497 | D49: =D24 -> 0.19217887 | E49: =E24 -> 0.2788085 | F49: =F24 -> 0.58101383 | G49: =G24 -> 2.8548709

Sheet Tab-baseline
C1: 8 | D1: 9 | E1: 10 | F1: 12 | G1: 17 | H1: 37
C2: ThreeME
C3: 2021 | D3: 2022 | E3: 2023 | F3: 2025 | G3: 2030 | H3: 2050
A4: Taux de croissance du PIB | B4: @pch(gdp_0) | C4: =VLOOKUP($B4,Baseline!$A$1:$AT$50,C$1,FALSE) -> 0.011252093 | D4: =VLOOKUP($B4,Baseline!$A$1:$AT$50,D$1,FALSE) -> 0.011375472 | E4: =VLOOKUP($B4,Baseline!$A$1:$AT$50,E$1,FALSE) -> 0.011476237 | F4: =VLOOKUP($B4,Baseline!$A$1:$AT$50,F$1,FALSE) -> 0.011614092 | G4: =VLOOKUP($B4,Baseline!$A$1:$AT$50,G$1,FALSE) -> 0.011726136 | H4: =VLOOKUP($B4,Baseline!$A$1:$AT$50,H$1,FALSE) -> 0.011660368
A5: Prix de la consommation des ménages | B5: @pch(pch_0) | C5: =VLOOKUP($B5,Baseline!$A$1:$AT$50,C$1,FALSE) -> 0.019635207 | D5: =VLOOKUP($B5,Baseline!$A$1:$AT$50,D$1,FALSE) -> 0.019668197 | E5: =VLOOKUP($B5,Baseline!$A$1:$AT$50,E$1,FALSE) -> 0.019714318 | F5: =VLOOKUP($B5,Baseline!$A$1:$AT$50,F$1,FALSE) -> 0.019828898 | G5: =VLOOKUP($B5,Baseline!$A$1:$AT$50,G$1,FALSE) -> 0.020129185 | H5: =VLOOKUP($B5,Baseline!$A$1:$AT$50,H$1,FALSE) -> 0.020366929
A6: Taux de chômage | B6: unr_0 | C6: =VLOOKUP($B6,Baseline!$A$1:$AT$50,C$1,FALSE) -> 0.14415906 | D6: =VLOOKUP($B6,Baseline!$A$1:$AT$50,D$1,FALSE) -> 0.14419204 | E6: =VLOOKUP($B6,Baseline!$A$1:$AT$50,E$1,FALSE) -> 0.14412979 | F6: =VLOOKUP($B6,Baseline!$A$1:$AT$50,F$1,FALSE) -> 0.14381068 | G6: =VLOOKUP($B6,Baseline!$A$1:$AT$50,G$1,FALSE) -> 0.14261895 | H6: =VLOOKUP($B6,Baseline!$A$1:$AT$50,H$1,FALSE) -> 0.13887513
A7: Dette publique (en pts de PIB) | B7: rdebt_g_val_0 | C7: =VLOOKUP($B7,Baseline!$A$1:$AT$50,C$1,FALSE) -> 0.97004802 | D7: =VLOOKUP($B7,Baseline!$A$1:$AT$50,D$1,FALSE) -> 0.97258712 | E7: =VLOOKUP($B7,Baseline!$A$1:$AT$50,E$1,FALSE) -> 0.97503146 | F7: =VLOOKUP($B7,Baseline!$A$1:$AT$50,F$1,FALSE) -> 0.97946806 | G7: =VLOOKUP($B7,Baseline!$A$1:$AT$50,G$1,FALSE) -> 0.98723106 | H7: =VLOOKUP($B7,Baseline!$A$1:$AT$50,H$1,FALSE) -> 0.97986829
A8: Solde primaire public (en pts de PIB) | B8: rbal_g_prim_val_0 | C8: =VLOOKUP($B8,Baseline!$A$1:$AT$50,C$1,FALSE) -> -0.011460252 | D8: =VLOOKUP($B8,Baseline!$A$1:$AT$50,D$1,FALSE) -> -0.011637089 | E8: =VLOOKUP($B8,Baseline!$A$1:$AT$50,E$1,FALSE) -> -0.011732353 | F8: =VLOOKUP($B8,Baseline!$A$1:$AT$50,F$1,FALSE) -> -0.011733134 | G8: =VLOOKUP($B8,Baseline!$A$1:$AT$50,G$1,FALSE) -> -0.011177481 | H8: =VLOOKUP($B8,Baseline!$A$1:$AT$50,H$1,FALSE) -> -0.00849113
A9: Balance commerciale (en pts de PIB) | B9: rbal_trade_val_0 | C9: =VLOOKUP($B9,Baseline!$A$1:$AT$50,C$1,FALSE) -> -0.01277292 | D9: =VLOOKUP($B9,Baseline!$A$1:$AT$50,D$1,FALSE) -> -0.012784957 | E9: =VLOOKUP($B9,Baseline!$A$1:$AT$50,E$1,FALSE) -> -0.012769054 | F9: =VLOOKUP($B9,Baseline!$A$1:$AT$50,F$1,FALSE) -> -0.012698368 | G9: =VLOOKUP($B9,Baseline!$A$1:$AT$50,G$1,FALSE) -> -0.012442025 | H9: =VLOOKUP($B9,Baseline!$A$1:$AT$50,H$1,FALSE) -> -0.011138905
A10: Emissions de CO2 (en Kt CO2) | B10: ems_co2_0 | C10: =VLOOKUP($B10,Baseline!$A$1:$AT$50,C$1,FALSE) -> 362.04263 | D10: =VLOOKUP($B10,Baseline!$A$1:$AT$50,D$1,FALSE) -> 364.51423 | E10: =VLOOKUP($B10,Baseline!$A$1:$AT$50,E$1,FALSE) -> 367.1103 | F10: =VLOOKUP($B10,Baseline!$A$1:$AT$50,F$1,FALSE) -> 372.57878 | G10: =VLOOKUP($B10,Baseline!$A$1:$AT$50,G$1,FALSE) -> 387.32088 | H10: =VLOOKUP($B10,Baseline!$A$1:$AT$50,H$1,FALSE) -> 457.40889
C33: ThreeME
C34: 2021 | D34: 2022 | E34: 2023 | F34: 2025 | G34: 2030 | H34: 2050
A35: GDP growth rate | C35: =C4 -> 0.011252093 | D35: =D4 -> 0.011375472 | E35: =E4 -> 0.011476237 | F35: =F4 -> 0.011614092 | G35: =G4 -> 0.011726136 | H35: =H4 -> 0.011660368
A36: Household consumption price | C36: =C5 -> 0.019635207 | D36: =D5 -> 0.019668197 | E36: =E5 -> 0.019714318 | F36: =F5 -> 0.019828898 | G36: =G5 -> 0.020129185 | H36: =H5 -> 0.020366929
A37: unemployment rate | C37: =C6 -> 0.14415906 | D37: =D6 -> 0.14419204 | E37: =E6 -> 0.14412979 | F37: =F6 -> 0.14381068 | G37: =G6 -> 0.14261895 | H37: =H6 -> 0.13887513
A38: Public debt (in points of GDP) | C38: =C7 -> 0.97004802 | D38: =D7 -> 0.97258712 | E38: =E7 -> 0.97503146 | F38: =F7 -> 0.97946806 | G38: =G7 -> 0.98723106 | H38: =H7 -> 0.97986829
A39: Public budget balance (in points of GDP) | C39: =C8 -> -0.011460252 | D39: =D8 -> -0.011637089 | E39: =E8 -> -0.011732353 | F39: =F8 -> -0.011733134 | G39: =G8 -> -0.011177481 | H39: =H8 -> -0.00849113
A40: Trade balance (in points of GDP) | C40: =C9 -> -0.01277292 | D40: =D9 -> -0.012784957 | E40: =E9 -> -0.012769054 | F40: =F9 -> -0.012698368 | G40: =G9 -> -0.012442025 | H40: =H9 -> -0.011138905
A41: CO2 emissions (In Kt og CO2) | C41: =C10 -> 362.04263 | D41: =D10 -> 364.51423 | E41: =E10 -> 367.1103 | F41: =F10 -> 372.57878 | G41: =G10 -> 387.32088 | H41: =H10 -> 457.40889

Sheet Macro
A1: _date_ | B1: 42005 | C1: 42370 | D1: 42736 | E1: 43101 | F1: 43466 | G1: 43831 | H1: 44197 | I1: 44562 | J1: 44927 | K1: 45292 | L1: 45658 | M1: 46023 | N1: 46388 | O1: 46753 | P1: 47119 | Q1: 47484 | R1: 47849 | S1: 48214 | T1: 48580 | U1: 48945 | V1: 49310 | W1: 49675 | X1: 50041 | Y1: 50406 | Z1: 50771 | AA1: 51136 | AB1: 51502 | AC1: 51867 | AD1: 52232 | AE1: 52597 | AF1: 52963 | AG1: 53328 | AH1: 53693 | AI1: 54058 | AJ1: 54424 | AK1: 54789
A2: 100*(gdp_2/gdp_0-1) | B2: 0 | C2: 0.0033641188 | D2: 0.009082291 | E2: 0.016620143 | F2: 0.02577382 | G2: 0.036754288 | H2: 0.048738572 | I2: 0.060095859 | J2: 0.070015107 | K2: 0.078444433 | L2: 0.085962983 | M2: 0.093517875 | N2: 0.10215197 | O2: 0.11279884 | P2: 0.12615999 | Q2: 0.14265241 | R2: 0.16135001 | S2: 0.18024887 | T2: 0.19776238 | U2: 0.21281822 | V2: 0.22488159 | W2: 0.2338464 | X2: 0.23987807 | Y2: 0.24327291 | Z2: 0.24435604 | AA2: 0.24341917 | AB2: 0.24069009 | AC2: 0.23632354 | AD2: 0.2304066 | AE2: 0.22297109 | AF2: 0.214009 | AG2: 0.20348859 | AH2: 0.1913679 | AI2: 0.17760612 | AJ2: 0.16217138 | AK2: 0.14504591
A3: 100*((va_2-va_spub_2)/(va_0-va_spub_0)-1) | B3: 0 | C3: 0.0046308167 | D3: 0.012257928 | E3: 0.022103622 | F3: 0.033966861 | G3: 0.048189737 | H3: 0.063591595 | I3: 0.077928064 | J3: 0.090208724 | K3: 0.10045819 | L3: 0.1094652 | M3: 0.1184394 | N3: 0.1286842 | O3: 0.14135391 | P3: 0.15730604 | Q3: 0.17703503 | R3: 0.19924261 | S3: 0.22128363 | T3: 0.24119395 | U3: 0.25769971 | V3: 0.27018273 | W3: 0.27853429 | X3: 0.28297033 | Y3: 0.28387016 | Z3: 0.28165927 | AA3: 0.27673714 | AB3: 0.26944028 | AC3: 0.26002941 | AD3: 0.24869328 | AE3: 0.23555983 | AF3: 0.2207121 | AG3: 0.20420388 | AH3: 0.18607388 | AI3: 0.16635677 | AJ3: 0.14509112 | AK3: 0.12232402
A4: 100*((ch_2-ch_0)/gdp_0) | B4: 0 | C4: 0.0021929801 | D4: 0.0075184546 | E4: 0.016082427 | F4: 0.027795421 | G4: 0.042970977 | H4: 0.061611156 | I4: 0.08278401 | J4: 0.10533605 | K4: 0.12861584 | L4: 0.15272541 | M4: 0.17837011 | N4: 0.20660031 | O4: 0.23859334 | P4: 0.27551309 | Q4: 0.31843771 | R4: 0.36765925 | S4: 0.42226695 | T4: 0.48084151 | U4: 0.54207887 | V4: 0.60507623 | W4: 0.6693145 | X4: 0.7345283 | Y4: 0.80057285 | Z4: 0.867326 | AA4: 0.9346302 | AB4: 1.0022654 | AC4: 1.0699443 | AD4: 1.1373208 | AE4: 1.2040053 | AF4: 1.2695832 | AG4: 1.3336324 | AH4: 1.3957396 | AI4: 1.4555121 | AJ4: 1.5125876 | AK4: 1.5666395
A5: 100*((ch_cveh_2-ch_cveh_0)/gdp_0) | B5: 0 | C5: -0.0038211489 | D5: -0.0078287774 | E5: -0.011437917 | F5: -0.01522218 | G5: -0.019979752 | H5: -0.024587398 | I5: -0.027517752 | J5: -0.029270488 | K5: -0.030830207 | L5: -0.033062862 | M5: -0.036601617 | N5: -0.041888144 | O5: -0.049238324 | P5: -0.05889336 | Q5: -0.071051222 | R5: -0.084293783 | S5: -0.096698207 | T5: -0.10805854 | U5: -0.11869867 | V5: -0.12898095 | W5: -0.13917584 | X5: -0.14945748 | Y5: -0.15993074 | Z5: -0.17065773 | AA5: -0.18167635 | AB5: -0.1930112 | AC5: -0.20467918 | AD5: -0.21669179 | AE5: -0.22905573 | AF5: -0.24177268 | AG5: -0.25483882 | AH5: -0.26824449 | AI5: -0.28197399 | AJ5: -0.29600566 | AK5: -0.31031219
A6: 100*((g_2-g_0)/gdp_0) | B6: 0 | C6: 0 | D6: 0 | E6: 0 | F6: 0 | G6: 0 | H6: 0 | I6: 0 | J6: 0 | K6: 0 | L6: 0 | M6: 0 | N6: 0 | O6: 0 | P6: 0 | Q6: 0 | R6: 0 | S6: 0 | T6: 0 | U6: 0 | V6: 0 | W6: 0 | X6: 0 | Y6: 0 | Z6: 0 | AA6: 0 | AB6: 0 | AC6: 0 | AD6: 0 | AE6: 0 | AF6: 0 | AG6: 0 | AH6: 0 | AI6: 0 | AJ6: 0 | AK6: 0
A7: 100*((i_2-i_0)/gdp_0) | B7: 0 | C7: -0.00099763414 | D7: -0.0024626904 | E7: -0.0042537118 | F7: -0.006488056 | G7: -0.0093974964 | H7: -0.012798614 | I7: -0.016283169 | J7: -0.019770476 | K7: -0.023334814 | L7: -0.027092237 | M7: -0.031158351 | N7: -0.035648547 | O7: -0.040691922 | P7: -0.046442581 | Q7: -0.053082546 | R7: -0.060521407 | S7: -0.068495847 | T7: -0.076931207 | U7: -0.085824172 | V7: -0.09516352 | W7: -0.10490086 | X7: -0.11495415 | Y7: -0.12522463 | Z7: -0.13561465 | AA7: -0.1460409 | AB7: -0.15644188 | AC7: -0.16678054 | AD7: -0.17704333 | AE7: -0.18723733 | AF7: -0.19738627 | AG7: -0.20752639 | AH7: -0.2177026 | AI7: -0.2279651 | AJ7: -0.2383668 | AK7: -0.24896132
A8: 100*((ds_2-ds_0)/gdp_0) | B8: 0 | C8: 0 | D8: 0 | E8: 0 | F8: 0 | G8: 0 | H8: 0 | I8: 0 | J8: 0 | K8: 0 | L8: 0 | M8: 0 | N8: 0 | O8: 0 | P8: 0 | Q8: 0 | R8: 0 | S8: 0 | T8: 0 | U8: 0 | V8: 0 | W8: 0 | X8: 0 | Y8: 0 | Z8: 0 | AA8: 0 | AB8: 0 | AC8: 0 | AD8: 0 | AE8: 0 | AF8: 0 | AG8: 0 | AH8: 0 | AI8: 0 | AJ8: 0 | AK8: 0
A9: 100*((x_2-x_0)/gdp_0)-100*((m_2-m_0)/gdp_0) | B9: 0 | C9: 0.0021687728 | D9: 0.0040265624 | E9: 0.0047914326 | F9: 0.0044664595 | G9: 0.0031807909 | H9: -7.3934973e-05 | I9: -0.0064049649 | J9: -0.015550473 | K9: -0.026836629 | L9: -0.039670205 | M9: -0.053693879 | N9: -0.068799796 | O9: -0.085102591 | P9: -0.10291054 | Q9: -0.12270277 | R9: -0.14578786 | S9: -0.17352223 | T9: -0.20614789 | U9: -0.24343649 | V9: -0.28503111 | W9: -0.33056725 | X9: -0.37969609 | Y9: -0.4320753 | Z9: -0.48735534 | AA9: -0.54517011 | AB9: -0.60513344 | AC9: -0.66684025 | AD9: -0.72987085 | AE9: -0.7937969 | AF9: -0.85818789 | AG9: -0.92261745 | AH9: -0.98666908 | AI9: -1.0499409 | AJ9: -1.1120494 | AK9: -1.1726323
A10: 100*((ch_2-ch_ccon_2-(ch_0-ch_ccon_0))/gdp_0) | B10: 0 | C10: 0.0021207018 | D10: 0.007337823 | E10: 0.015756902 | F10: 0.027279421 | G10: 0.0422047 | H10: 0.060548092 | I10: 0.081405037 | J10: 0.1036274 | K10: 0.12656015 | L10: 0.1502951 | M10: 0.17552297 | N10: 0.20327748 | O10: 0.2347194 | P10: 0.27099731 | Q10: 0.31317578 | R10: 0.36156279 | S10: 0.41528178 | T10: 0.47293042 | U10: 0.53321458 | V10: 0.59523666 | W10: 0.65847952 | X10: 0.72267832 | Y10: 0.78768907 | Z10: 0.85339154 | AA10: 0.91963167 | AB10: 0.98619446 | AC10: 1.0527988 | AD10: 1.1191057 | AE10: 1.1847329 | AF10: 1.2492735 | AG10: 1.3123126 | AH10: 1.3734436 | AI10: 1.4322804 | AJ10: 1.4884661 | AK10: 1.5416795
A11: 100*((i_2+ch_ccon_2-(i_0+ch_ccon_0))/gdp_0) | B11: 0 | C11: -0.00092535583 | D11: -0.0022820587 | E11: -0.0039281872 | F11: -0.0059720563 | G11: -0.00863122 | H11: -0.011735551 | I11: -0.014904197 | J11: -0.018061834 | K11: -0.021279116 | L11: -0.024661926 | M11: -0.02831121 | N11: -0.032325719 | O11: -0.036817978 | P11: -0.041926806 | Q11: -0.047820621 | R11: -0.054424942 | S11: -0.061510685 | T11: -0.069020114 | U11: -0.076959883 | V11: -0.08532395 | W11: -0.094065871 | X11: -0.10310417 | Y11: -0.11234085 | Z11: -0.12168019 | AA11: -0.13104237 | AB11: -0.14037094 | AC11: -0.14963504 | AD11: -0.1588282 | AE11: -0.16796496 | AF11: -0.17707654 | AG11: -0.18620651 | AH11: -0.19540661 | AI11: -0.20473337 | AJ11: -0.21424538 | AK11: -0.2240013
A12: 100*((i_2-ia_spub_2-(i_0-ia_spub_0))/gdp_0) | B12: 0 | C12: -0.00087466774 | D12: -0.0021557973 | E12: -0.0037131923 | F12: -0.0056511184 | G12: -0.0081779994 | H12: -0.011136824 | I12: -0.014171638 | J12: -0.017215766 | K12: -0.020339604 | L12: -0.023646689 | M12: -0.027235156 | N12: -0.031199408 | O12: -0.035644881 | P12: -0.040700252 | Q12: -0.046521399 | R12: -0.05302878 | S12: -0.059995985 | T12: -0.067367641 | U12: -0.075153307 | V12: -0.083352677 | W12: -0.091927434 | X12: -0.10080455 | Y12: -0.10989271 | Z12: -0.11909977 | AA12: -0.12834595 | AB12: -0.13757141 | AC12: -0.14673913 | AD12: -0.15583433 | AE12: -0.16486182 | AF12: -0.17384244 | AG12: -0.18280907 | AH12: -0.19180304 | AI12: -0.20087087 | AJ12: -0.21006188 | AK12: -0.21942615
... A55: pop | B55: 66422.5 | C55: 66588.556 | D55: 66755.028 | E55: 66921.915 | F55: 67089.22 | G55: 67256.943 | H55: 67425.085 | I55: 67593.648 | J55: 67762.632 | K55: 67932.039 | L55: 68101.869 | M55: 68272.124 | N55: 68442.804 | O55: 68613.911 | P55: 68785.446 | Q55: 68957.409 | R55: 69129.803 | S55: 69302.627 | T55: 69475.884 | U55: 69649.574 | V55: 69823.698 | W55: 69998.257 | X55: 70173.252 | Y55: 70348.686 | Z55: 70524.557 | AA55: 70700.869 | AB55: 70877.621 | AC55: 71054.815 | AD55: 71232.452 | AE55: 71410.533 | AF55: 71589.059 | AG55: 71768.032 | AH55: 71947.452 | AI55: 72127.321 | AJ55: 72307.639 | AK55: 72488.408

Sheet Baseline
A1: @date | B1: 42005 | C1: 42370 | D1: 42736 | E1: 43101 | F1: 43466 | G1: 43831 | H1: 44197 | I1: 44562 | J1: 44927 | K1: 45292 | L1: 45658 | M1: 46023 | N1: 46388 | O1: 46753 | P1: 47119 | Q1: 47484 | R1: 47849 | S1: 48214 | T1: 48580 | U1: 48945 | V1: 49310 | W1: 49675 | X1: 50041 | Y1: 50406 | Z1: 50771 | AA1: 51136 | AB1: 51502 | AC1: 51867 | AD1: 52232 | AE1: 52597 | AF1: 52963 | AG1: 53328 | AH1: 53693 | AI1: 54058 | AJ1: 54424 | AK1: 54789
A2: @pch(gdp_0) | B2: 0.0115225 | C2: 0.010855574 | D2: 0.010728383 | E2: 0.010808991 | F2: 0.010953896 | G2: 0.011108712 | H2: 0.011252093 | I2: 0.011375472 | J2: 0.011476237 | K2: 0.011554988 | L2: 0.011614092 | M2: 0.011656738 | N2: 0.011686315 | O2: 0.011706004 | P2: 0.011718548 | Q2: 0.011726136 | R2: 0.011730408 | S2: 0.011732513 | T2: 0.011733198 | U2: 0.011732909 | V2: 0.011731877 | W2: 0.011730202 | X2: 0.011727914 | Y2: 0.011725016 | Z2: 0.011721512 | AA2: 0.011717423 | AB2: 0.011712793 | AC2: 0.011707687 | AD2: 0.011702187 | AE2: 0.011696385 | AF2: 0.01169038 | AG2: 0.011684266 | AH2: 0.011678133 | AI2: 0.011672062 | AJ2: 0.011666122 | AK2: 0.011660368
A3: @pch(pch_0) | B3: 0.02 | C3: 0.019898733 | D3: 0.019777199 | E3: 0.01968545 | F3: 0.019635261 | G3: 0.019621524 | H3: 0.019635207 | I3: 0.019668197 | J3: 0.019714318 | K3: 0.019769024 | L3: 0.019828898 | M3: 0.019891268 | N3: 0.019953995 | O3: 0.020015379 | P3: 0.0200741 | Q3: 0.020129185 | R3: 0.020179956 | S3: 0.020225984 | T3: 0.020267047 | U3: 0.020303072 | V3: 0.020334107 | W3: 0.020360285 | X3: 0.020381796 | Y3: 0.020398879 | Z3: 0.020411799 | AA3: 0.020420845 | AB3: 0.020426324 | AC3: 0.020428547 | AD3: 0.020427835 | AE3: 0.020424509 | AF3: 0.020418888 | AG3: 0.020411284 | AH3: 0.020402003 | AI3: 0.020391335 | AJ3: 0.020379558 | AK3: 0.020366929
A4: unr_0 | B4: 0.14211338 | C4: 0.14239253 | D4: 0.14284801 | E4: 0.14332745 | F4: 0.14372958 | G4: 0.14400924 | H4: 0.14415906 | I4: 0.14419204 | J4: 0.14412979 | K4: 0.14399556 | L4: 0.14381068 | M4: 0.14359297 | N4: 0.14335631 | O4: 0.14311086 | P4: 0.1428636 | Q4: 0.14261895 | R4: 0.14237946 | S4: 0.14214634 | T4: 0.14191994 | U4: 0.14170015 | V4: 0.1414866 | W4: 0.14127888 | X4: 0.1410766 | Y4: 0.14087947 | Z4: 0.14068727 | AA4: 0.14049986 | AB4: 0.14031716 | AC4: 0.14013913 | AD4: 0.13996573 | AE4: 0.13979691 | AF4: 0.13963262 | AG4: 0.13947277 | AH4: 0.13931725 | AI4: 0.13916591 | AJ4: 0.13901859 | AK4: 0.13887513
A5: rdebt_g_val_0 | B5: 0.958 | C5: 0.95897527 | D5: 0.96058315 | E5: 0.96263011 | F5: 0.96497124 | G5: 0.96748013 | H5: 0.97004802 | I5: 0.97258712 | J5: 0.97503146 | K5: 0.97733498 | L5: 0.97946806 | M5: 0.98141366 | N5: 0.98316355 | O5: 0.98471535 | P5: 0.98607015 | Q5: 0.98723106 | R5: 0.98820224 | S5: 0.98898846 | T5: 0.98959494 | U5: 0.99002734 | V5: 0.99029187 | W5: 0.99039536 | X5: 0.99034531 | Y5: 0.99014987 | Z5: 0.98981782 | AA5: 0.98935842 | AB5: 0.9887813 | AC5: 0.98809631 | AD5: 0.98731335 | AE5: 0.98644222 | AF5: 0.98549246 | AG5: 0.98447327 | AH5: 0.98339337 | AI5: 0.98226095 | AJ5: 0.9810836 | AK5: 0.97986829
A6: rbal_g_prim_val_0 | B6: -0.0092851685 | C6: -0.0095358179 | D6: -0.0099463988 | E6: -0.010405279 | F6: -0.01083516 | G6: -0.011192718 | H6: -0.011460252 | I6: -0.011637089 | J6: -0.011732353 | K6: -0.011759578 | L6: -0.011733134 | M6: -0.011666163 | N6: -0.011569624 | O6: -0.011452069 | P6: -0.011319842 | Q6: -0.011177481 | R6: -0.011028163 | S6: -0.010874133 | T6: -0.010717037 | U6: -0.01055818 | V6: -0.01039869 | W6: -0.010239614 | X6: -0.010081963 | Y6: -0.0099267197 | Z6: -0.0097748207 | AA6: -0.0096271357 | AB6: -0.0094844412 | AC6: -0.0093473998 | AD6: -0.0092165451 | AE6: -0.0090922747 | AF6: -0.0089748501 | AG6: -0.0088644026 | AH6: -0.0087609442 | AI6: -0.0086643811 | AJ6: -0.0085745291 | AK6: -0.00849113
A7: rbal_trade_val_0 | B7: -0.01081433 | C7: -0.011339149 | D7: -0.011886849 | E7: -0.012303141 | F7: -0.012567896 | G7: -0.012711325 | H7: -0.01277292 | I7: -0.012784957 | J7: -0.012769054 | K7: -0.012737939 | L7: -0.012698368 | M7: -0.012653596 | N7: -0.012605063 | O7: -0.0125534 | P7: -0.012498953 | Q7: -0.012442025 | R7: -0.012382953 | S7: -0.012322107 | T7: -0.012259858 | U7: -0.012196549 | V7: -0.012132469 | W7: -0.012067848 | X7: -0.012002849 | Y7: -0.011937583 | Z7: -0.011872113 | AA7: -0.011806466 | AB7: -0.01174065 | AC7: -0.011674654 | AD7: -0.011608464 | AE7: -0.011542065 | AF7: -0.011475444 | AG7: -0.011408593 | AH7: -0.011341509 | AI7: -0.011274195 | AJ7: -0.011206656 | AK7: -0.011138905
A8: ems_co2_0 | B8: 350.29271 | C8: 352.43131 | D8: 354.06052 | E8: 355.7321 | F8: 357.61599 | G8: 359.72996 | H8: 362.04263 | I8: 364.51423 | J8: 367.1103 | K8: 369.80468 | L8: 372.57878 | M8: 375.41988 | N8: 378.31942 | O8: 381.27176 | P8: 384.27304 | Q8: 387.32088 | R8: 390.41383 | S8: 393.55096 | T8: 396.73175 | U8: 399.95582 | V8: 403.22297 | W8: 406.53308 | X8: 409.88608 | Y8: 413.28196 | Z8: 416.72071 | AA8: 420.20234 | AB8: 423.72691 | AC8: 427.29449 | AD8: 430.90523 | AE8: 434.55929 | AF8: 438.25689 | AG8: 441.9983 | AH8: 445.78382 | AI8: 449.61382 | AJ8: 453.4887 | AK8: 457.40889
A9: pop | B9: 66422.5 | C9: 66588.556 | D9: 66755.028 | E9: 66921.915 | F9: 67089.22 | G9: 67256.943 | H9: 67425.085 | I9: 67593.648 | J9: 67762.632 | K9: 67932.039 | L9: 68101.869 | M9: 68272.124 | N9: 68442.804 | O9: 68613.911 | P9: 68785.446 | Q9: 68957.409 | R9: 69129.803 | S9: 69302.627 | T9: 69475.884 | U9: 69649.574 | V9: 69823.698 | W9: 69998.257 | X9: 70173.252 | Y9: 70348.686 | Z9: 70524.557 | AA9: 70700.869 | AB9: 70877.621 | AC9: 71054.815 | AD9: 71232.452 | AE9: 71410.533 | AF9: 71589.059 | AG9: 71768.032 | AH9: 71947.452 | AI9: 72127.321 | AJ9: 72307.639 | AK9: 72488.408
A10: gdp_0 | B10: 2196558.3 | C10: 2220403.2 | D10: 2244224.5 | E10: 2268482.3 | F10: 2293331 | G10: 2318807 | H10: 2344898.4 | I10: 2371572.7 | J10: 2398789.5 | K10: 2426507.4 | L10: 2454689.1 | M10: 2483302.8 | N10: 2512323.4 | O10: 2541732.7 | P10: 2571518.1 | Q10: 2601672.1 | R10: 2632190.8 | S10: 2663073 | T10: 2694319.4 | U10: 2725931.6 | V10: 2757911.9 | W10: 2790262.7 | X10: 2822986.7 | Y10: 2856086.2 | Z10: 2889563.9 | AA10: 2923422.1 | AB10: 2957663.6 | AC10: 2992291 | AD10: 3027307.3 | AE10: 3062715.9 | AF10: 3098520.2 | AG10: 3134724.1 | AH10: 3171331.8 | AI10: 3208347.8 | AJ10: 3245776.8 | AK10: 3283623.8
A11: pch_0 | B11: 1 | C11: 1.0198987 | D11: 1.0400695 | E11: 1.0605437 | F11: 1.0813678 | G11: 1.1025858 | H11: 1.1242353 | I11: 1.146347 | J11: 1.1689465 | K11: 1.1920554 | L11: 1.2156926 | M11: 1.2398742 | N11: 1.2646147 | O11: 1.2899264 | P11: 1.3158205 | Q11: 1.3423069 | R11: 1.3693946 | S11: 1.397092 | T11: 1.4254069 | U11: 1.454347 | V11: 1.4839199 | W11: 1.5141329 | X11: 1.5449937 | Y11: 1.5765098 | Z11: 1.6086892 | AA11: 1.64154 | AB11: 1.6750706 | AC11: 1.7092899 | AD11: 1.744207 | AE11: 1.7798315 | AF11: 1.8161737 | AG11: 1.8532442 | AH11: 1.891054 | AI11: 1.9296152 | AJ11: 1.9689399 | AK11: 2.0090411
A12: ems_ch_co2_0 | B12: 119.49049 | C12: 119.25476 | D12: 118.5914 | E12: 117.94146 | F12: 117.43342 | G12: 117.07744 | H12: 116.84707 | I12: 116.7106 | J12: 116.64129 | K12: 116.61924 | L12: 116.63059 | M12: 116.66599 | N12: 116.71922 | O12: 116.78609 | P12: 116.86366 | Q12: 116.94993 | R12: 117.04357 | S12: 117.1436 | T12: 117.24929 | U12: 117.36001 | V12: 117.4753 | W12: 117.59479 | X12: 117.71816 | Y12: 117.84518 | Z12: 117.97565 | AA12: 118.10939 | AB12: 118.24629 | AC12: 118.38623 | AD12: 118.52913 | AE12: 118.67492 | AF12: 118.82357 | AG12: 118.97505 | AH12: 119.12935 | AI12: 119.28646 | AJ12: 119.44639 | AK12: 119.60915
... A28: ems_co2_cote_0 | B28: 17.86536 | C28: 18.049747 | D28: 18.22732 | E28: 18.406258 | F28: 18.589806 | G28: 18.778708 | H28: 18.972724 | I28: 19.17133 | J28: 19.373997 | K28: 19.580285 | L28: 19.789857 | M28: 20.002471 | N28: 20.217959 | O28: 20.436215 | P28: 20.657178 | Q28: 20.880819 | R28: 21.107135 | S28: 21.336135 | T28: 21.567842 | U28: 21.802281 | V28: 22.039486 | W28: 22.279487 | X28: 22.522317 | Y28: 22.768007 | Z28: 23.016586 | AA28: 23.268084 | AB28: 23.52253 | AC28: 23.779952 | AD28: 24.040379 | AE28: 24.303843 | AF28: 24.570373 | AG28: 24.840001 | AH28: 25.112761 | AI28: 25.388689 | AJ28: 25.667821 | AK28: 25.950193

Sheet produits-secteurs V2-V3
B1: ThreeME V3 | M1: ThreeME V2
B2: Produits | C2: V3 | E2: V2 | G2: Secteurs | H2: V3 | I2: V2 | K2: commentaires | M2: Produits | P2: secteurs
B3: Products of agriculture, Hunting, and Fishing | C3: cagr | E3: 1 | G3: Agriculture and fishing | H3: sagr | I3: 1 | M3: Agriculture, sylviculture et pêche | N3: 1 | P3: Agriculture, sylviculture et pêche | Q3: 1
B4: Products of Forestry | C4: cfor | G4: Forestry | H4: sfor | M4: Industrie agro-alimentaire | N4: 2 | P4: Industrie agro-alimentaire | Q4: 2
B5: Food products and beverages | C5: cfoo | E5: 2 | G5: Manufacture of food products and beverages | H5: sfoo | I5: 2 | M5: Automobile | N5: 3 | P5: Automobile | Q5: 3
B6: Motor vehicles, trailers and semi-trailers | C6: cveh | E6: 3 | G6: Manufacture of motor vehicles, trailers and semi-trailers | H6: sveh | I6: 3 | M6: FABRICATION DE VERRE ET D ARTICLES EN VE | N6: 4 | P6: FABRICATION DE VERRE ET D ARTICLES EN VE | Q6: 4
B7: Glass and ceramic products | C7: cgla | E7: 4 e t 5 | G7: Manufacture of glass, ceramic and ciment products | H7: sgla | I7: 4 et 5 | K7: ETS | M7: FABRICATION DE PRODUITS CERAMIQUES ET DE | N7: 5 | P7: FABRICATION DE PRODUITS CERAMIQUES ET DE | Q7: 5
B8: Paper and paperboard | C8: cpap | E8: 6 | G8: Manufacture of paper and paperboard | H8: spap | I8: 6 | K8: ETS | M8: Papier ert carton | N8: 6 | P8: Papier ert carton | Q8: 6
B9: Chemicals | C9: cche | E9: 7 et 8 | G9: Manufacture of chemicals | H9: sche | I9: 7 et 8 | K9: ETS | M9: INDUSTRIE CHIMIQUE MINERALE | N9: 7 | P9: INDUSTRIE CHIMIQUE MINERALE | Q9: 7
B10: Plastics products | C10: cpla | E10: 9 | G10: Manufacture of plastics products | H10: spla | I10: 9 | K10: ETS | M10: INDUSTRIE CHIMIQUE ORGANIQUE | N10: 8 | P10: INDUSTRIE CHIMIQUE ORGANIQUE | Q10: 8
B11: Metals | C11: cmet | E11: 10 et 11 | G11: Metallurgy | H11: smet | I11: 10 et 11 | K11: ETS | M11: TRANSFORMATION DES MATIERES PLASTIQUES | N11: 9 | P11: TRANSFORMATION DES MATIERES PLASTIQUES | Q11: 9
B12: Other goods for industry | C12: cigo | E12: 12 | G12: Manufacture of other goods for industry | H12: sigo | I12: 12 | M12: SIDERURGIE ET PREMIERE TRANSFORMATION DE | N12: 10 | P12: SIDERURGIE ET PREMIERE TRANSFORMATION DE | Q12: 10
B13: Other goods for consumers | C13: ccgo | E13: 12 | G13: Manufacture of other goods for consumers | H13: scgo | I13: 12 | M13: PRODUCTION DE METAUX NON FERREUX | N13: 11 | P13: PRODUCTION DE METAUX NON FERREUX | Q13: 11
B14: Buildings and Civil engineering | C14: ccon | E14: 13 | G14: Construction of buildings and Civil engineering | H14: scon | I14: 13 | M14: Autres | N14: 12 | P14: Autres | Q14: 12
B15: Rail transport | C15: crai | E15: 14 | G15: Rail transport | H15: srai | I15: 14 | M15: BTP | N15: 13 | P15: BTP | Q15: 13
B16: Road transport | C16: croa | E16: 15 et 16 | G16: Road transport | H16: sroa | I16: 15 et 16 | M16: TRANSPORTS FERROVIAIRES | N16: 14 | P16: TRANSPORTS FERROVIAIRES | Q16: 14
B17: Water transport | C17: cwat | E17: 17 | G17: Water transport | H17: swat | I17: 17 | M17: TRANSPORT ROUTIER DE VOYAGEURS | N17: 15 | P17: TRANSPORT ROUTIER DE VOYAGEURS | Q17: 15
B18: Air transport | C18: cair | E18: 18 | G18: Air transport | H18: sair | I18: 18 | K18: ETS | M18: TRANSPORT ROUTIER (OU PAR CONDUITES) DE | N18: 16 | P18: TRANSPORT ROUTIER (OU PAR CONDUITES) DE | Q18: 16
B19: Business services | C19: cpri | E19: 19 | G19: Business services | H19: spri | I19: 19 | M19: TRANSPORTS PAR EAU | N19: 17 | P19: TRANSPORTS PAR EAU | Q19: 17
B20: Public services | C20: cpub | E20: 20 | G20: Public services | H20: spub | I20: 20 | M20: TRANSPORTS AERIENS | N20: 18 | P20: TRANSPORTS AERIENS | Q20: 18
B21: Non-energy mining | C21: cmin | G21: Mining | H21: smin | I21: 21 | K21: ETS | M21: Services marchands | N21: 19 | P21: Services marchands | Q21: 19
B22: Coal | C22: ccoa | E22: 21 | G22: Production of refined oil | H22: soil | I22: 22_1 | J22: TRSF | K22: ETS | M22: Services non marchands | N22: 20 | P22: Services non marchands | Q22: 20
B23: Crude oil | C23: ccoi | D23: pétrole | E23: 22 | G23: Production of biofuel | H23: sbfu | I23: 22_2 | J23: TRSF | K23: ETS | M23: EXTRACTION ET AGGLOMERATION DE LA HOUILL | N23: 21 | P23: EXTRACTION ET AGGLOMERATION DE LA HOUILLE | Q23: 21
B24: Transport fuels | C24: cfut | D24: pétrole | E24: 22 | G24: Distribution of natural gas | H24: sgas | I24: 24_1 | J24: TRSF | K24: ETS | M24: RAFFINAGE DE PETROLE | N24: 22 | P24: pétrole | Q24: 22_1
B25: Heating fuel | C25: cfuh | D25: pétrole | E25: 22 | G25: Production and distribution of biogas | H25: sbga | I25: 24_3 | J25: TRSF | K25: ETS | M25: PRODUCTION ET DISTRIBUTION D ELECTRICITE | N25: 23 | P25: biocarburants | Q25: 22_2
B26: Natural gas | C26: cgas | D26: gaz | E26: 24 | G26: Nuclear electricity generation | H26: senu | I26: 23_1 | J26: ELE | K26: ETS | M26: PRODUCTION ET DISTRIBUTION DE COMBUSTIBL | N26: 24 | P26: Nucléaire | Q26: 23_1
B27: Electricity | C27: cele | D27: elec | E27: 23 | G27: Oil-fired electricity generation | H27: seoi | I27: 23_2 | J27: ELE | K27: ETS | P27: centrale fioul | Q27: 23_2
B28: Heat | C28: chea | G28: Gas-fired electricity generation | H28: sega | I28: 23_3 | J28: ELE | K28: ETS | P28: centrale combinée gaz | Q28: 23_3
B29: Biomass | C29: cbio | G29: Coal-fired electricity generation | H29: seco | I29: 23_4 | J29: ELE | K29: ETS | P29: centrale charbon | Q29: 23_4
B30: Other energy | C30: cote | G30: Wind electricity generation | H30: sewi | I30: 23_5 | J30: ELE | K30: ETS | P30: Eolien | Q30: 23_5
G31: Solar electricity generation | H31: seso | I31: 23_6 | J31: ELE | K31: ETS | P31: PV | Q31: 23_6
G32: Hydroelectric electricity generation | H32: sehy | I32: 23_7 | J32: ELE | K32: ETS | P32: Hydraulique | Q32: 23_7
G33: Cogeneration (CHP) electricity generation and other heat supply | H33: sech | I33: 23_8, 24_4, 24_5, 24,6 | J33: ELE | K33: ETS | P33: cogénération | Q33: 23_8
G34: Electricity - Others | H34: seot | J34: ELE | K34: ETS | P34: gaz naturel | Q34: 24_1
P35: bois énergie | Q35: 24_2
P36: Biogaz | Q36: 24_3
P37: UIOM | Q37: 24_4
P38: Géothermie | Q38: 24_5
P39: cogénération | Q39: 24_6

Sheet Sect&Com_V3
B1: Sectors/activities | C1: Acronym | D1: Commodities | E1: =C1 -> Acronym
B2: Agriculture and fishing | C2: sagr | D2: Products of agriculture, Hunting, and Fishing | E2: cagr
D3: Biomass and other energy | E3: cbio
B4: Forestry | C4: sfor | D4: Products of Forestry | E4: cfor
B5: Manufacture of food products and beverages | C5: sfoo | D5: Food products and beverages | E5: cfoo
B6: Manufacture of motor vehicles, trailers and semi-trailers | C6: sveh | D6: Motor vehicles, trailers and semi-trailers | E6: cveh
B7: Manufacture of glass, ceramic and ciment products | C7: sgla | D7: Glass and ceramic products | E7: cgla
B8: Manufacture of paper and paperboard | C8: spap | D8: Paper and paperboard | E8: cpap
B9: Manufacture of chemicals | C9: sche | D9: Chemicals | E9: cche
B10: Manufacture of plastics products | C10: spla | D10: Plastics products | E10: cpla
B11: Metallurgy | C11: smet | D11: Metals | E11: cmet
B12: Manufacture of other goods for industry | C12: sigo | D12: Other goods for industry | E12: cigo
B13: Manufacture of other goods for consumers | C13: scgo | D13: Other goods for consumers | E13: ccgo
B14: Construction of buildings and Civil engineering | C14: scon | D14: Buildings and Civil engineering | E14: ccon
B15: Rail transport | C15: srai | D15: Rail transport | E15: crai
... B21: Mining | C21: smin | D21: Non-energy mining | E21: cmin
D22: Coal | E22: ccoa
D23: Coal for non-energy use | E23: coan
D24: Crude oil | E24: ccoi
D25: Natural gas mining | E25: cgam
A26: secteurs TRSF | B26: Production of refined oil | C26: soil | D26: Transport fuels | E26: cfut
B27: Production of biofuel | C27: sbfu | D27: Heating fuel | E27: cfuh
D28: Fuel for non-energy use | E28: cfun
B29: Distribution of natural gas | C29: sgas | D29: Natural gas | E29: cgas
B30: Production and distribution of biogas | C30: sbga | D30: Natural gas for non-energy use | E30: cgan
A31: Secteurs SELE + setd | B31: Transmission and distribution of electricity | C31: setd
B32: Nuclear electricity generation | C32: senu
B33: Oil-fired electricity generation | C33: seoi
B34: Gas-fired electricity generation | C34: sega | D34: Electricity | E34: cele
B35: Coal-fired electricity generation | C35: seco
B36: Wind electricity generation | C36: sewi
B37: Solar electricity generation | C37: seso
B38: Hydroelectric electricity generation | C38: sehy | D38: Heat | E38: chea
B39: Cogeneration (CHP) electricity generation and other heat supply | C39: sech
B40: Electricity - Others | C40: seot
