Workbook
Name formatResults: [1]ResultsEXR10!$A$50

Sheet Results
A1: NB : on crée ici une liste : - globale, qui fusionne les reportings 1, 2 et 3 (même si seules les valeurs du scénario de choc présentées ici) - "rationalisée" : suppression des doublons, et regroupements par thématique On pourra continuer par la suite à avoir 3 Excels de reporting (pour éviter un Excel trop gros), mais dans lesquels on copiera toujours les mêmes sorties (et faire des RECHERCHEV)
E2: ThreeME V3 | F2: 2 | G2: 3 | H2: 4 | I2: 5 | J2: 6 | K2: 7 | L2: 8 | M2: 9 | N2: 10 | O2: 11 | P2: 12 | Q2: 13 | R2: 14 | S2: 15 | T2: 16 | U2: 17 | V2: 18 | W2: 19 | X2: 20 | Y2: 21 | Z2: 22 | AA2: 23 | AB2: 24 | AC2: 25 | AD2: 26 | AE2: 27 | AF2: 28 | AG2: 29 | AH2: 30 | AI2: 31 | AJ2: 32 | AK2: 33 | AL2: 34 | AM2: 35 | AN2: 36 | AO2: 37
A3: Nom du bloc de variables utilisé dans le code | B3: Sous-bloc de variables pour plus de lisibilité dans le Excel | E3: Year | F3: =Hybrid!B1 -> 42005 | G3: =Hybrid!C1 -> 42370 | H3: =Hybrid!D1 -> 42736 | I3: =Hybrid!E1 -> 43101 | J3: =Hybrid!F1 -> 43466 | K3: =Hybrid!G1 -> 43831 | L3: =Hybrid!H1 -> 44197 | M3: =Hybrid!I1 -> 44562 | ... AO3: =Hybrid!AK1 -> 54789
A4: HYBRID | B4: AUTOMOBILES (unit) | C4: TOTAL STOCK SHOCK | E4: AUTO_2 | F4: =+VLOOKUP($E4,Hybrid!$1:$1048576,F$2,FALSE) -> 32317.941 | G4: =+VLOOKUP($E4,Hybrid!$1:$1048576,G$2,FALSE) -> 31926.455 | H4: =+VLOOKUP($E4,Hybrid!$1:$1048576,H$2,FALSE) -> 31730.401 | I4: =+VLOOKUP($E4,Hybrid!$1:$1048576,I$2,FALSE) -> 31664.733 | J4: =+VLOOKUP($E4,Hybrid!$1:$1048576,J$2,FALSE) -> 31685.152 | K4: =+VLOOKUP($E4,Hybrid!$1:$1048576,K$2,FALSE) -> 31761.774 | L4: =+VLOOKUP($E4,Hybrid!$1:$1048576,L$2,FALSE) -> 31876.82 | M4: =+VLOOKUP($E4,Hybrid!$1:$1048576,M$2,FALSE) -> 32020.398 | ... AO4: =+VLOOKUP($E4,Hybrid!$1:$1048576,AO$2,FALSE) -> 36554.972
C5: OIL | E5: AUTO_cfut_2 | F5: =+VLOOKUP($E5,Hybrid!$1:$1048576,F$2,FALSE) -> 32271.24 | G5: =+VLOOKUP($E5,Hybrid!$1:$1048576,G$2,FALSE) -> 31862.032 | H5: =+VLOOKUP($E5,Hybrid!$1:$1048576,H$2,FALSE) -> 31647.329 | I5: =+VLOOKUP($E5,Hybrid!$1:$1048576,I$2,FALSE) -> 31562.481 | J5: =+VLOOKUP($E5,Hybrid!$1:$1048576,J$2,FALSE) -> 31563.392 | K5: =+VLOOKUP($E5,Hybrid!$1:$1048576,K$2,FALSE) -> 31620.229 | L5: =+VLOOKUP($E5,Hybrid!$1:$1048576,L$2,FALSE) -> 31715.127 | M5: =+VLOOKUP($E5,Hybrid!$1:$1048576,M$2,FALSE) -> 31838.038 | ... AO5: =+VLOOKUP($E5,Hybrid!$1:$1048576,AO$2,FALSE) -> 32020.075
D6: class A | E6: AUTO_ca_cfut_2 | F6: =+VLOOKUP($E6,Hybrid!$1:$1048576,F$2,FALSE) -> 7095.7005 | G6: =+VLOOKUP($E6,Hybrid!$1:$1048576,G$2,FALSE) -> 7141.744 | H6: =+VLOOKUP($E6,Hybrid!$1:$1048576,H$2,FALSE) -> 7236.2109 | I6: =+VLOOKUP($E6,Hybrid!$1:$1048576,I$2,FALSE) -> 7362.7565 | J6: =+VLOOKUP($E6,Hybrid!$1:$1048576,J$2,FALSE) -> 7510.0299 | K6: =+VLOOKUP($E6,Hybrid!$1:$1048576,K$2,FALSE) -> 7670.2472 | L6: =+VLOOKUP($E6,Hybrid!$1:$1048576,L$2,FALSE) -> 7838.785 | M6: =+VLOOKUP($E6,Hybrid!$1:$1048576,M$2,FALSE) -> 8013.1055 | ... AO6: =+VLOOKUP($E6,Hybrid!$1:$1048576,AO$2,FALSE) -> 11240.43
D7: class B | E7: AUTO_cb_cfut_2 | F7: =+VLOOKUP($E7,Hybrid!$1:$1048576,F$2,FALSE) -> 8251.2564 | G7: =+VLOOKUP($E7,Hybrid!$1:$1048576,G$2,FALSE) -> 8182.7845 | H7: =+VLOOKUP($E7,Hybrid!$1:$1048576,H$2,FALSE) -> 8168.3356 | I7: =+VLOOKUP($E7,Hybrid!$1:$1048576,I$2,FALSE) -> 8191.2663 | J7: =+VLOOKUP($E7,Hybrid!$1:$1048576,J$2,FALSE) -> 8239.913 | K7: =+VLOOKUP($E7,Hybrid!$1:$1048576,K$2,FALSE) -> 8306.1531 | L7: =+VLOOKUP($E7,Hybrid!$1:$1048576,L$2,FALSE) -> 8384.9727 | M7: =+VLOOKUP($E7,Hybrid!$1:$1048576,M$2,FALSE) -> 8473.4298 | ... AO7: =+VLOOKUP($E7,Hybrid!$1:$1048576,AO$2,FALSE) -> 9881.9911
D8: class C | E8: AUTO_cc_cfut_2 | F8: =+VLOOKUP($E8,Hybrid!$1:$1048576,F$2,FALSE) -> 6777.6025 | G8: =+VLOOKUP($E8,Hybrid!$1:$1048576,G$2,FALSE) -> 6646.7629 | H8: =+VLOOKUP($E8,Hybrid!$1:$1048576,H$2,FALSE) -> 6558.9664 | I8: =+VLOOKUP($E8,Hybrid!$1:$1048576,I$2,FALSE) -> 6502.0082 | J8: =+VLOOKUP($E8,Hybrid!$1:$1048576,J$2,FALSE) -> 6467.2622 | K8: =+VLOOKUP($E8,Hybrid!$1:$1048576,K$2,FALSE) -> 6448.6373 | L8: =+VLOOKUP($E8,Hybrid!$1:$1048576,L$2,FALSE) -> 6442.2478 | M8: =+VLOOKUP($E8,Hybrid!$1:$1048576,M$2,FALSE) -> 6445.693 | ... AO8: =+VLOOKUP($E8,Hybrid!$1:$1048576,AO$2,FALSE) -> 6300.9328
D9: class D | E9: AUTO_cd_cfut_2 | F9: =+VLOOKUP($E9,Hybrid!$1:$1048576,F$2,FALSE) -> 4159.6639 | G9: =+VLOOKUP($E9,Hybrid!$1:$1048576,G$2,FALSE) -> 4054.5797 | H9: =+VLOOKUP($E9,Hybrid!$1:$1048576,H$2,FALSE) -> 3973.8285 | I9: =+VLOOKUP($E9,Hybrid!$1:$1048576,I$2,FALSE) -> 3910.0599 | J9: =+VLOOKUP($E9,Hybrid!$1:$1048576,J$2,FALSE) -> 3858.1675 | K9: =+VLOOKUP($E9,Hybrid!$1:$1048576,K$2,FALSE) -> 3814.6035 | L9: =+VLOOKUP($E9,Hybrid!$1:$1048576,L$2,FALSE) -> 3777.117 | M9: =+VLOOKUP($E9,Hybrid!$1:$1048576,M$2,FALSE) -> 3744.3156 | ... AO9: =+VLOOKUP($E9,Hybrid!$1:$1048576,AO$2,FALSE) -> 2689.2394
D10: class E | E10: AUTO_ce_cfut_2 | F10: =+VLOOKUP($E10,Hybrid!$1:$1048576,F$2,FALSE) -> 2503.7292 | G10: =+VLOOKUP($E10,Hybrid!$1:$1048576,G$2,FALSE) -> 2442.7169 | H10: =+VLOOKUP($E10,Hybrid!$1:$1048576,H$2,FALSE) -> 2395.2655 | I10: =+VLOOKUP($E10,Hybrid!$1:$1048576,I$2,FALSE) -> 2356.6831 | J10: =+VLOOKUP($E10,Hybrid!$1:$1048576,J$2,FALSE) -> 2323.7962 | K10: =+VLOOKUP($E10,Hybrid!$1:$1048576,K$2,FALSE) -> 2294.4653 | L10: =+VLOOKUP($E10,Hybrid!$1:$1048576,L$2,FALSE) -> 2267.3805 | M10: =+VLOOKUP($E10,Hybrid!$1:$1048576,M$2,FALSE) -> 2241.7723 | ... AO10: =+VLOOKUP($E10,Hybrid!$1:$1048576,AO$2,FALSE) -> 1253.0278
D11: class F | E11: AUTO_cf_cfut_2 | F11: =+VLOOKUP($E11,Hybrid!$1:$1048576,F$2,FALSE) -> 1243.6668 | G11: =+VLOOKUP($E11,Hybrid!$1:$1048576,G$2,FALSE) -> 1210.4925 | H11: =+VLOOKUP($E11,Hybrid!$1:$1048576,H$2,FALSE) -> 1182.3239 | I11: =+VLOOKUP($E11,Hybrid!$1:$1048576,I$2,FALSE) -> 1156.6362 | J11: =+VLOOKUP($E11,Hybrid!$1:$1048576,J$2,FALSE) -> 1131.8888 | K11: =+VLOOKUP($E11,Hybrid!$1:$1048576,K$2,FALSE) -> 1107.177 | L11: =+VLOOKUP($E11,Hybrid!$1:$1048576,L$2,FALSE) -> 1082.0509 | M11: =+VLOOKUP($E11,Hybrid!$1:$1048576,M$2,FALSE) -> 1056.3349 | ... AO11: =+VLOOKUP($E11,Hybrid!$1:$1048576,AO$2,FALSE) -> 294.49603
D12: class G | E12: AUTO_cg_cfut_2 | F12: =+VLOOKUP($E12,Hybrid!$1:$1048576,F$2,FALSE) -> 2239.6206 | G12: =+VLOOKUP($E12,Hybrid!$1:$1048576,G$2,FALSE) -> 2182.9512 | H12: =+VLOOKUP($E12,Hybrid!$1:$1048576,H$2,FALSE) -> 2132.3988 | I12: =+VLOOKUP($E12,Hybrid!$1:$1048576,I$2,FALSE) -> 2083.0711 | J12: =+VLOOKUP($E12,Hybrid!$1:$1048576,J$2,FALSE) -> 2032.334 | K12: =+VLOOKUP($E12,Hybrid!$1:$1048576,K$2,FALSE) -> 1978.9456 | L12: =+VLOOKUP($E12,Hybrid!$1:$1048576,L$2,FALSE) -> 1922.5734 | M12: =+VLOOKUP($E12,Hybrid!$1:$1048576,M$2,FALSE) -> 1863.3872 | ... AO12: =+VLOOKUP($E12,Hybrid!$1:$1048576,AO$2,FALSE) -> 359.95743
C13: ELEC | E13: AUTO_cele_2 | F13: =+VLOOKUP($E13,Hybrid!$1:$1048576,F$2,FALSE) -> 44.765 | G13: =+VLOOKUP($E13,Hybrid!$1:$1048576,G$2,FALSE) -> 62.431569 | H13: =+VLOOKUP($E13,Hybrid!$1:$1048576,H$2,FALSE) -> 81.013696 | I13: =+VLOOKUP($E13,Hybrid!$1:$1048576,I$2,FALSE) -> 100.12298 | J13: =+VLOOKUP($E13,Hybrid!$1:$1048576,J$2,FALSE) -> 119.55791 | K13: =+VLOOKUP($E13,Hybrid!$1:$1048576,K$2,FALSE) -> 139.26917 | L13: =+VLOOKUP($E13,Hybrid!$1:$1048576,L$2,FALSE) -> 159.3444 | M13: =+VLOOKUP($E13,Hybrid!$1:$1048576,M$2,FALSE) -> 179.94081 | ... AO13: =+VLOOKUP($E13,Hybrid!$1:$1048576,AO$2,FALSE) -> 4531.6755
D14: class A | E14: AUTO_ca_cele_2 | F14: =+VLOOKUP($E14,Hybrid!$1:$1048576,F$2,FALSE) -> 9.8427899 | G14: =+VLOOKUP($E14,Hybrid!$1:$1048576,G$2,FALSE) -> 14.986776 | H14: =+VLOOKUP($E14,Hybrid!$1:$1048576,H$2,FALSE) -> 20.441889 | I14: =+VLOOKUP($E14,Hybrid!$1:$1048576,I$2,FALSE) -> 26.112449 | J14: =+VLOOKUP($E14,Hybrid!$1:$1048576,J$2,FALSE) -> 31.950416 | K14: =+VLOOKUP($E14,Hybrid!$1:$1048576,K$2,FALSE) -> 37.949262 | L14: =+VLOOKUP($E14,Hybrid!$1:$1048576,L$2,FALSE) -> 44.142141 | M14: =+VLOOKUP($E14,Hybrid!$1:$1048576,M$2,FALSE) -> 50.58278 | ... AO14: =+VLOOKUP($E14,Hybrid!$1:$1048576,AO$2,FALSE) -> 1721.1452
D15: class B | E15: AUTO_cb_cele_2 | F15: =+VLOOKUP($E15,Hybrid!$1:$1048576,F$2,FALSE) -> 11.445717 | G15: =+VLOOKUP($E15,Hybrid!$1:$1048576,G$2,FALSE) -> 16.298726 | H15: =+VLOOKUP($E15,Hybrid!$1:$1048576,H$2,FALSE) -> 21.445143 | I15: =+VLOOKUP($E15,Hybrid!$1:$1048576,I$2,FALSE) -> 26.792131 | J15: =+VLOOKUP($E15,Hybrid!$1:$1048576,J$2,FALSE) -> 32.294 | K15: =+VLOOKUP($E15,Hybrid!$1:$1048576,K$2,FALSE) -> 37.945945 | L15: =+VLOOKUP($E15,Hybrid!$1:$1048576,L$2,FALSE) -> 43.781768 | M15: =+VLOOKUP($E15,Hybrid!$1:$1048576,M$2,FALSE) -> 49.854747 | ... AO15: =+VLOOKUP($E15,Hybrid!$1:$1048576,AO$2,FALSE) -> 1535.9361
D16: class C | E16: AUTO_cc_cele_2 | F16: =+VLOOKUP($E16,Hybrid!$1:$1048576,F$2,FALSE) -> 9.4015406 | G16: =+VLOOKUP($E16,Hybrid!$1:$1048576,G$2,FALSE) -> 12.697683 | H16: =+VLOOKUP($E16,Hybrid!$1:$1048576,H$2,FALSE) -> 16.193359 | I16: =+VLOOKUP($E16,Hybrid!$1:$1048576,I$2,FALSE) -> 19.823555 | J16: =+VLOOKUP($E16,Hybrid!$1:$1048576,J$2,FALSE) -> 23.556822 | K16: =+VLOOKUP($E16,Hybrid!$1:$1048576,K$2,FALSE) -> 27.390656 | L16: =+VLOOKUP($E16,Hybrid!$1:$1048576,L$2,FALSE) -> 31.349549 | M16: =+VLOOKUP($E16,Hybrid!$1:$1048576,M$2,FALSE) -> 35.471242 | ... AO16: =+VLOOKUP($E16,Hybrid!$1:$1048576,AO$2,FALSE) -> 985.35071
D17: class D | E17: AUTO_cd_cele_2 | F17: =+VLOOKUP($E17,Hybrid!$1:$1048576,F$2,FALSE) -> 5.7700713 | G17: =+VLOOKUP($E17,Hybrid!$1:$1048576,G$2,FALSE) -> 7.5615055 | H17: =+VLOOKUP($E17,Hybrid!$1:$1048576,H$2,FALSE) -> 9.4379839 | I17: =+VLOOKUP($E17,Hybrid!$1:$1048576,I$2,FALSE) -> 11.352079 | J17: =+VLOOKUP($E17,Hybrid!$1:$1048576,J$2,FALSE) -> 13.275194 | K17: =+VLOOKUP($E17,Hybrid!$1:$1048576,K$2,FALSE) -> 15.192959 | L17: =+VLOOKUP($E17,Hybrid!$1:$1048576,L$2,FALSE) -> 17.103324 | M17: =+VLOOKUP($E17,Hybrid!$1:$1048576,M$2,FALSE) -> 19.010938 | ... AO17: =+VLOOKUP($E17,Hybrid!$1:$1048576,AO$2,FALSE) -> 187.38943
D18: class E | E18: AUTO_ce_cele_2 | F18: =+VLOOKUP($E18,Hybrid!$1:$1048576,F$2,FALSE) -> 3.4730441 | G18: =+VLOOKUP($E18,Hybrid!$1:$1048576,G$2,FALSE) -> 4.5722155 | H18: =+VLOOKUP($E18,Hybrid!$1:$1048576,H$2,FALSE) -> 5.7140433 | I18: =+VLOOKUP($E18,Hybrid!$1:$1048576,I$2,FALSE) -> 6.8675525 | J18: =+VLOOKUP($E18,Hybrid!$1:$1048576,J$2,FALSE) -> 8.014519 | K18: =+VLOOKUP($E18,Hybrid!$1:$1048576,K$2,FALSE) -> 9.146111 | L18: =+VLOOKUP($E18,Hybrid!$1:$1048576,L$2,FALSE) -> 10.261244 | M18: =+VLOOKUP($E18,Hybrid!$1:$1048576,M$2,FALSE) -> 11.362807 | ... AO18: =+VLOOKUP($E18,Hybrid!$1:$1048576,AO$2,FALSE) -> 82.980357
D19: class F | E19: AUTO_cf_cele_2 | F19: =+VLOOKUP($E19,Hybrid!$1:$1048576,F$2,FALSE) -> 1.7251505 | G19: =+VLOOKUP($E19,Hybrid!$1:$1048576,G$2,FALSE) -> 2.2443945 | H19: =+VLOOKUP($E19,Hybrid!$1:$1048576,H$2,FALSE) -> 2.7668951 | I19: =+VLOOKUP($E19,Hybrid!$1:$1048576,I$2,FALSE) -> 3.2740042 | J19: =+VLOOKUP($E19,Hybrid!$1:$1048576,J$2,FALSE) -> 3.7551966 | K19: =+VLOOKUP($E19,Hybrid!$1:$1048576,K$2,FALSE) -> 4.2053456 | L19: =+VLOOKUP($E19,Hybrid!$1:$1048576,L$2,FALSE) -> 4.6232035 | M19: =+VLOOKUP($E19,Hybrid!$1:$1048576,M$2,FALSE) -> 5.0095094 | ... AO19: =+VLOOKUP($E19,Hybrid!$1:$1048576,AO$2,FALSE) -> 9.6175149
D20: class G | E20: AUTO_cg_cele_2 | F20: =+VLOOKUP($E20,Hybrid!$1:$1048576,F$2,FALSE) -> 3.1066862 | G20: =+VLOOKUP($E20,Hybrid!$1:$1048576,G$2,FALSE) -> 4.0702695 | H20: =+VLOOKUP($E20,Hybrid!$1:$1048576,H$2,FALSE) -> 5.014383 | I20: =+VLOOKUP($E20,Hybrid!$1:$1048576,I$2,FALSE) -> 5.9012135 | J20: =+VLOOKUP($E20,Hybrid!$1:$1048576,J$2,FALSE) -> 6.7117634 | K20: =+VLOOKUP($E20,Hybrid!$1:$1048576,K$2,FALSE) -> 7.4388891 | L20: =+VLOOKUP($E20,Hybrid!$1:$1048576,L$2,FALSE) -> 8.0831672 | M20: =+VLOOKUP($E20,Hybrid!$1:$1048576,M$2,FALSE) -> 8.6487844 | ... AO20: =+VLOOKUP($E20,Hybrid!$1:$1048576,AO$2,FALSE) -> 9.2561619
C21: GAS | E21: AUTO_cgas_2 | F21: =+VLOOKUP($E21,Hybrid!$1:$1048576,F$2,FALSE) -> 1.936 | G21: =+VLOOKUP($E21,Hybrid!$1:$1048576,G$2,FALSE) -> 1.9916056 | H21: =+VLOOKUP($E21,Hybrid!$1:$1048576,H$2,FALSE) -> 2.0574011 | I21: =+VLOOKUP($E21,Hybrid!$1:$1048576,I$2,FALSE) -> 2.1285899 | J21: =+VLOOKUP($E21,Hybrid!$1:$1048576,J$2,FALSE) -> 2.2019794 | K21: =+VLOOKUP($E21,Hybrid!$1:$1048576,K$2,FALSE) -> 2.2754864 | L21: =+VLOOKUP($E21,Hybrid!$1:$1048576,L$2,FALSE) -> 2.3479684 | M21: =+VLOOKUP($E21,Hybrid!$1:$1048576,M$2,FALSE) -> 2.4188941 | ... AO21: =+VLOOKUP($E21,Hybrid!$1:$1048576,AO$2,FALSE) -> 3.2214115
D22: class A | E22: AUTO_ca_cgas_2 | F22: =+VLOOKUP($E22,Hybrid!$1:$1048576,F$2,FALSE) -> 0.4256817 | G22: =+VLOOKUP($E22,Hybrid!$1:$1048576,G$2,FALSE) -> 0.44933517 | H22: =+VLOOKUP($E22,Hybrid!$1:$1048576,H$2,FALSE) -> 0.47587941 | I22: =+VLOOKUP($E22,Hybrid!$1:$1048576,I$2,FALSE) -> 0.50407723 | J22: =+VLOOKUP($E22,Hybrid!$1:$1048576,J$2,FALSE) -> 0.53308137 | K22: =+VLOOKUP($E22,Hybrid!$1:$1048576,K$2,FALSE) -> 0.56232302 | L22: =+VLOOKUP($E22,Hybrid!$1:$1048576,L$2,FALSE) -> 0.59148357 | M22: =+VLOOKUP($E22,Hybrid!$1:$1048576,M$2,FALSE) -> 0.62040925 | ... AO22: =+VLOOKUP($E22,Hybrid!$1:$1048576,AO$2,FALSE) -> 1.1175435
D23: class B | E23: AUTO_cb_cgas_2 | F23: =+VLOOKUP($E23,Hybrid!$1:$1048576,F$2,FALSE) -> 0.49500523 | G23: =+VLOOKUP($E23,Hybrid!$1:$1048576,G$2,FALSE) -> 0.51226024 | H23: =+VLOOKUP($E23,Hybrid!$1:$1048576,H$2,FALSE) -> 0.53252768 | I23: =+VLOOKUP($E23,Hybrid!$1:$1048576,I$2,FALSE) -> 0.55457425 | J23: =+VLOOKUP($E23,Hybrid!$1:$1048576,J$2,FALSE) -> 0.57755325 | K23: =+VLOOKUP($E23,Hybrid!$1:$1048576,K$2,FALSE) -> 0.60089214 | L23: =+VLOOKUP($E23,Hybrid!$1:$1048576,L$2,FALSE) -> 0.62426223 | M23: =+VLOOKUP($E23,Hybrid!$1:$1048576,M$2,FALSE) -> 0.64749666 | ... AO23: =+VLOOKUP($E23,Hybrid!$1:$1048576,AO$2,FALSE) -> 0.98903502
D24: class C | E24: AUTO_cc_cgas_2 | F24: =+VLOOKUP($E24,Hybrid!$1:$1048576,F$2,FALSE) -> 0.40659852 | G24: =+VLOOKUP($E24,Hybrid!$1:$1048576,G$2,FALSE) -> 0.4145049 | H24: =+VLOOKUP($E24,Hybrid!$1:$1048576,H$2,FALSE) -> 0.42467781 | I24: =+VLOOKUP($E24,Hybrid!$1:$1048576,I$2,FALSE) -> 0.43623168 | J24: =+VLOOKUP($E24,Hybrid!$1:$1048576,J$2,FALSE) -> 0.44855712 | K24: =+VLOOKUP($E24,Hybrid!$1:$1048576,K$2,FALSE) -> 0.4612394 | L24: =+VLOOKUP($E24,Hybrid!$1:$1048576,L$2,FALSE) -> 0.47403519 | M24: =+VLOOKUP($E24,Hybrid!$1:$1048576,M$2,FALSE) -> 0.48681568 | ... AO24: =+VLOOKUP($E24,Hybrid!$1:$1048576,AO$2,FALSE) -> 0.63482943
D25: class D | E25: AUTO_cd_cgas_2 | F25: =+VLOOKUP($E25,Hybrid!$1:$1048576,F$2,FALSE) -> 0.24954447 | G25: =+VLOOKUP($E25,Hybrid!$1:$1048576,G$2,FALSE) -> 0.25231485 | H25: =+VLOOKUP($E25,Hybrid!$1:$1048576,H$2,FALSE) -> 0.25626929 | I25: =+VLOOKUP($E25,Hybrid!$1:$1048576,I$2,FALSE) -> 0.26087537 | J25: =+VLOOKUP($E25,Hybrid!$1:$1048576,J$2,FALSE) -> 0.2657744 | K25: =+VLOOKUP($E25,Hybrid!$1:$1048576,K$2,FALSE) -> 0.27072766 | L25: =+VLOOKUP($E25,Hybrid!$1:$1048576,L$2,FALSE) -> 0.27559709 | M25: =+VLOOKUP($E25,Hybrid!$1:$1048576,M$2,FALSE) -> 0.28031071 | ... AO25: =+VLOOKUP($E25,Hybrid!$1:$1048576,AO$2,FALSE) -> 0.27521423
D26: class E | E26: AUTO_ce_cgas_2 | F26: =+VLOOKUP($E26,Hybrid!$1:$1048576,F$2,FALSE) -> 0.15020247 | G26: =+VLOOKUP($E26,Hybrid!$1:$1048576,G$2,FALSE) -> 0.15205804 | H26: =+VLOOKUP($E26,Hybrid!$1:$1048576,H$2,FALSE) -> 0.15453801 | I26: =+VLOOKUP($E26,Hybrid!$1:$1048576,I$2,FALSE) -> 0.15729786 | J26: =+VLOOKUP($E26,Hybrid!$1:$1048576,J$2,FALSE) -> 0.16011145 | K26: =+VLOOKUP($E26,Hybrid!$1:$1048576,K$2,FALSE) -> 0.16283293 | L26: =+VLOOKUP($E26,Hybrid!$1:$1048576,L$2,FALSE) -> 0.16538126 | M26: =+VLOOKUP($E26,Hybrid!$1:$1048576,M$2,FALSE) -> 0.16771728 | ... AO26: =+VLOOKUP($E26,Hybrid!$1:$1048576,AO$2,FALSE) -> 0.13087224
D27: class F | E27: AUTO_cf_cgas_2 | F27: =+VLOOKUP($E27,Hybrid!$1:$1048576,F$2,FALSE) -> 0.074609436 | G27: =+VLOOKUP($E27,Hybrid!$1:$1048576,G$2,FALSE) -> 0.075290207 | H27: =+VLOOKUP($E27,Hybrid!$1:$1048576,H$2,FALSE) -> 0.076132076 | I27: =+VLOOKUP($E27,Hybrid!$1:$1048576,I$2,FALSE) -> 0.076945597 | J27: =+VLOOKUP($E27,Hybrid!$1:$1048576,J$2,FALSE) -> 0.077619324 | K27: =+VLOOKUP($E27,Hybrid!$1:$1048576,K$2,FALSE) -> 0.078092136 | L27: =+VLOOKUP($E27,Hybrid!$1:$1048576,L$2,FALSE) -> 0.078339035 | M27: =+VLOOKUP($E27,Hybrid!$1:$1048576,M$2,FALSE) -> 0.078356678 | ... AO27: =+VLOOKUP($E27,Hybrid!$1:$1048576,AO$2,FALSE) -> 0.032639717
D28: class G | E28: AUTO_cg_cgas_2 | F28: =+VLOOKUP($E28,Hybrid!$1:$1048576,F$2,FALSE) -> 0.13435819 | G28: =+VLOOKUP($E28,Hybrid!$1:$1048576,G$2,FALSE) -> 0.13584219 | H28: =+VLOOKUP($E28,Hybrid!$1:$1048576,H$2,FALSE) -> 0.13737684 | I28: =+VLOOKUP($E28,Hybrid!$1:$1048576,I$2,FALSE) -> 0.13858796 | J28: =+VLOOKUP($E28,Hybrid!$1:$1048576,J$2,FALSE) -> 0.13928248 | K28: =+VLOOKUP($E28,Hybrid!$1:$1048576,K$2,FALSE) -> 0.13937915 | L28: =+VLOOKUP($E28,Hybrid!$1:$1048576,L$2,FALSE) -> 0.13887006 | M28: =+VLOOKUP($E28,Hybrid!$1:$1048576,M$2,FALSE) -> 0.13778783 | ... AO28: =+VLOOKUP($E28,Hybrid!$1:$1048576,AO$2,FALSE) -> 0.041277351
C29: TOTAL STOCK BASELINE | E29: AUTO_0 | F29: =+VLOOKUP($E29,Hybrid!$1:$1048576,F$2,FALSE) -> 32317.941 | G29: =+VLOOKUP($E29,Hybrid!$1:$1048576,G$2,FALSE) -> 31931.625 | H29: =+VLOOKUP($E29,Hybrid!$1:$1048576,H$2,FALSE) -> 31743.508 | I29: =+VLOOKUP($E29,Hybrid!$1:$1048576,I$2,FALSE) -> 31687.792 | J29: =+VLOOKUP($E29,Hybrid!$1:$1048576,J$2,FALSE) -> 31720.643 | K29: =+VLOOKUP($E29,Hybrid!$1:$1048576,K$2,FALSE) -> 31813.337 | L29: =+VLOOKUP($E29,Hybrid!$1:$1048576,L$2,FALSE) -> 31947.162 | M29: =+VLOOKUP($E29,Hybrid!$1:$1048576,M$2,FALSE) -> 32109.877 | ... AO29: =+VLOOKUP($E29,Hybrid!$1:$1048576,AO$2,FALSE) -> 38673.292
C30: OIL | E30: AUTO_cfut_0 | F30: =+VLOOKUP($E30,Hybrid!$1:$1048576,F$2,FALSE) -> 32271.24 | G30: =+VLOOKUP($E30,Hybrid!$1:$1048576,G$2,FALSE) -> 31867.185 | H30: =+VLOOKUP($E30,Hybrid!$1:$1048576,H$2,FALSE) -> 31660.486 | I30: =+VLOOKUP($E30,Hybrid!$1:$1048576,I$2,FALSE) -> 31585.838 | J30: =+VLOOKUP($E30,Hybrid!$1:$1048576,J$2,FALSE) -> 31599.721 | K30: =+VLOOKUP($E30,Hybrid!$1:$1048576,K$2,FALSE) -> 31673.603 | L30: =+VLOOKUP($E30,Hybrid!$1:$1048576,L$2,FALSE) -> 31788.887 | M30: =+VLOOKUP($E30,Hybrid!$1:$1048576,M$2,FALSE) -> 31933.397 | ... AO30: =+VLOOKUP($E30,Hybrid!$1:$1048576,AO$2,FALSE) -> 38101.905
D31: class A | E31: AUTO_ca_cfut_0 | F31: =+VLOOKUP($E31,Hybrid!$1:$1048576,F$2,FALSE) -> 7095.7005 | G31: =+VLOOKUP($E31,Hybrid!$1:$1048576,G$2,FALSE) -> 7143.1788 | H31: =+VLOOKUP($E31,Hybrid!$1:$1048576,H$2,FALSE) -> 7239.81 | I31: =+VLOOKUP($E31,Hybrid!$1:$1048576,I$2,FALSE) -> 7369.0432 | J31: =+VLOOKUP($E31,Hybrid!$1:$1048576,J$2,FALSE) -> 7519.6804 | K31: =+VLOOKUP($E31,Hybrid!$1:$1048576,K$2,FALSE) -> 7684.2986 | L31: =+VLOOKUP($E31,Hybrid!$1:$1048576,L$2,FALSE) -> 7858.0379 | M31: =+VLOOKUP($E31,Hybrid!$1:$1048576,M$2,FALSE) -> 8037.7299 | ... AO31: =+VLOOKUP($E31,Hybrid!$1:$1048576,AO$2,FALSE) -> 13271.9
D32: class B | E32: AUTO_cb_cfut_0 | F32: =+VLOOKUP($E32,Hybrid!$1:$1048576,F$2,FALSE) -> 8251.2564 | G32: =+VLOOKUP($E32,Hybrid!$1:$1048576,G$2,FALSE) -> 8184.1785 | H32: =+VLOOKUP($E32,Hybrid!$1:$1048576,H$2,FALSE) -> 8171.8779 | I32: =+VLOOKUP($E32,Hybrid!$1:$1048576,I$2,FALSE) -> 8197.5342 | J32: =+VLOOKUP($E32,Hybrid!$1:$1048576,J$2,FALSE) -> 8249.6491 | K32: =+VLOOKUP($E32,Hybrid!$1:$1048576,K$2,FALSE) -> 8320.4704 | L32: =+VLOOKUP($E32,Hybrid!$1:$1048576,L$2,FALSE) -> 8404.7877 | M32: =+VLOOKUP($E32,Hybrid!$1:$1048576,M$2,FALSE) -> 8499.0715 | ... AO32: =+VLOOKUP($E32,Hybrid!$1:$1048576,AO$2,FALSE) -> 11875.349
D33: class C | E33: AUTO_cc_cfut_0 | F33: =+VLOOKUP($E33,Hybrid!$1:$1048576,F$2,FALSE) -> 6777.6025 | G33: =+VLOOKUP($E33,Hybrid!$1:$1048576,G$2,FALSE) -> 6647.7392 | H33: =+VLOOKUP($E33,Hybrid!$1:$1048576,H$2,FALSE) -> 6561.4778 | I33: =+VLOOKUP($E33,Hybrid!$1:$1048576,I$2,FALSE) -> 6506.5051 | J33: =+VLOOKUP($E33,Hybrid!$1:$1048576,J$2,FALSE) -> 6474.3214 | K33: =+VLOOKUP($E33,Hybrid!$1:$1048576,K$2,FALSE) -> 6459.1067 | L33: =+VLOOKUP($E33,Hybrid!$1:$1048576,L$2,FALSE) -> 6456.8591 | M33: =+VLOOKUP($E33,Hybrid!$1:$1048576,M$2,FALSE) -> 6464.7815 | ... AO33: =+VLOOKUP($E33,Hybrid!$1:$1048576,AO$2,FALSE) -> 7687.7208
D34: class D | E34: AUTO_cd_cfut_0 | F34: =+VLOOKUP($E34,Hybrid!$1:$1048576,F$2,FALSE) -> 4159.6639 | G34: =+VLOOKUP($E34,Hybrid!$1:$1048576,G$2,FALSE) -> 4055.1231 | H34: =+VLOOKUP($E34,Hybrid!$1:$1048576,H$2,FALSE) -> 3975.2329 | I34: =+VLOOKUP($E34,Hybrid!$1:$1048576,I$2,FALSE) -> 3912.5808 | J34: =+VLOOKUP($E34,Hybrid!$1:$1048576,J$2,FALSE) -> 3862.1234 | K34: =+VLOOKUP($E34,Hybrid!$1:$1048576,K$2,FALSE) -> 3820.4516 | L34: =+VLOOKUP($E34,Hybrid!$1:$1048576,L$2,FALSE) -> 3785.2435 | M34: =+VLOOKUP($E34,Hybrid!$1:$1048576,M$2,FALSE) -> 3754.8857 | ... AO34: =+VLOOKUP($E34,Hybrid!$1:$1048576,AO$2,FALSE) -> 3102.3334
D35: class E | E35: AUTO_ce_cfut_0 | F35: =+VLOOKUP($E35,Hybrid!$1:$1048576,F$2,FALSE) -> 2503.7292 | G35: =+VLOOKUP($E35,Hybrid!$1:$1048576,G$2,FALSE) -> 2443.054 | H35: =+VLOOKUP($E35,Hybrid!$1:$1048576,H$2,FALSE) -> 2396.145 | I35: =+VLOOKUP($E35,Hybrid!$1:$1048576,I$2,FALSE) -> 2358.2745 | J35: =+VLOOKUP($E35,Hybrid!$1:$1048576,J$2,FALSE) -> 2326.3079 | K35: =+VLOOKUP($E35,Hybrid!$1:$1048576,K$2,FALSE) -> 2298.1904 | L35: =+VLOOKUP($E35,Hybrid!$1:$1048576,L$2,FALSE) -> 2272.5718 | M35: =+VLOOKUP($E35,Hybrid!$1:$1048576,M$2,FALSE) -> 2248.5516 | ... AO35: =+VLOOKUP($E35,Hybrid!$1:$1048576,AO$2,FALSE) -> 1454.1661
D36: class F | E36: AUTO_cf_cfut_0 | F36: =+VLOOKUP($E36,Hybrid!$1:$1048576,F$2,FALSE) -> 1243.6668 | G36: =+VLOOKUP($E36,Hybrid!$1:$1048576,G$2,FALSE) -> 1210.6549 | H36: =+VLOOKUP($E36,Hybrid!$1:$1048576,H$2,FALSE) -> 1182.7476 | I36: =+VLOOKUP($E36,Hybrid!$1:$1048576,I$2,FALSE) -> 1157.3995 | J36: =+VLOOKUP($E36,Hybrid!$1:$1048576,J$2,FALSE) -> 1133.0829 | K36: =+VLOOKUP($E36,Hybrid!$1:$1048576,K$2,FALSE) -> 1108.9242 | L36: =+VLOOKUP($E36,Hybrid!$1:$1048576,L$2,FALSE) -> 1084.4506 | M36: =+VLOOKUP($E36,Hybrid!$1:$1048576,M$2,FALSE) -> 1059.4277 | ... AO36: =+VLOOKUP($E36,Hybrid!$1:$1048576,AO$2,FALSE) -> 325.27338
D37: class G | E37: AUTO_cg_cfut_0 | F37: =+VLOOKUP($E37,Hybrid!$1:$1048576,F$2,FALSE) -> 2239.6206 | G37: =+VLOOKUP($E37,Hybrid!$1:$1048576,G$2,FALSE) -> 2183.2559 | H37: =+VLOOKUP($E37,Hybrid!$1:$1048576,H$2,FALSE) -> 2133.1946 | I37: =+VLOOKUP($E37,Hybrid!$1:$1048576,I$2,FALSE) -> 2084.5006 | J37: =+VLOOKUP($E37,Hybrid!$1:$1048576,J$2,FALSE) -> 2034.5555 | K37: =+VLOOKUP($E37,Hybrid!$1:$1048576,K$2,FALSE) -> 1982.161 | L37: =+VLOOKUP($E37,Hybrid!$1:$1048576,L$2,FALSE) -> 1926.9369 | M37: =+VLOOKUP($E37,Hybrid!$1:$1048576,M$2,FALSE) -> 1868.9489 | ... AO37: =+VLOOKUP($E37,Hybrid!$1:$1048576,AO$2,FALSE) -> 385.16287
C38: ELEC | E38: AUTO_cele_0 | F38: =+VLOOKUP($E38,Hybrid!$1:$1048576,F$2,FALSE) -> 44.765 | G38: =+VLOOKUP($E38,Hybrid!$1:$1048576,G$2,FALSE) -> 62.448716 | H38: =+VLOOKUP($E38,Hybrid!$1:$1048576,H$2,FALSE) -> 80.963971 | I38: =+VLOOKUP($E38,Hybrid!$1:$1048576,I$2,FALSE) -> 99.823967 | J38: =+VLOOKUP($E38,Hybrid!$1:$1048576,J$2,FALSE) -> 118.71772 | K38: =+VLOOKUP($E38,Hybrid!$1:$1048576,K$2,FALSE) -> 137.4542 | L38: =+VLOOKUP($E38,Hybrid!$1:$1048576,L$2,FALSE) -> 155.92054 | M38: =+VLOOKUP($E38,Hybrid!$1:$1048576,M$2,FALSE) -> 174.05324 | ... AO38: =+VLOOKUP($E38,Hybrid!$1:$1048576,AO$2,FALSE) -> 567.61282
D39: class A | E39: AUTO_ca_cele_0 | F39: =+VLOOKUP($E39,Hybrid!$1:$1048576,F$2,FALSE) -> 9.8427899 | G39: =+VLOOKUP($E39,Hybrid!$1:$1048576,G$2,FALSE) -> 14.990816 | H39: =+VLOOKUP($E39,Hybrid!$1:$1048576,H$2,FALSE) -> 20.422984 | I39: =+VLOOKUP($E39,Hybrid!$1:$1048576,I$2,FALSE) -> 26.012773 | J39: =+VLOOKUP($E39,Hybrid!$1:$1048576,J$2,FALSE) -> 31.67695 | K39: =+VLOOKUP($E39,Hybrid!$1:$1048576,K$2,FALSE) -> 37.362607 | L39: =+VLOOKUP($E39,Hybrid!$1:$1048576,L$2,FALSE) -> 43.037132 | M39: =+VLOOKUP($E39,Hybrid!$1:$1048576,M$2,FALSE) -> 48.681062 | ... AO39: =+VLOOKUP($E39,Hybrid!$1:$1048576,AO$2,FALSE) -> 195.65639
D40: class B | E40: AUTO_cb_cele_0 | F40: =+VLOOKUP($E40,Hybrid!$1:$1048576,F$2,FALSE) -> 11.445717 | G40: =+VLOOKUP($E40,Hybrid!$1:$1048576,G$2,FALSE) -> 16.302056 | H40: =+VLOOKUP($E40,Hybrid!$1:$1048576,H$2,FALSE) -> 21.423897 | I40: =+VLOOKUP($E40,Hybrid!$1:$1048576,I$2,FALSE) -> 26.687145 | J40: =+VLOOKUP($E40,Hybrid!$1:$1048576,J$2,FALSE) -> 32.010429 | K40: =+VLOOKUP($E40,Hybrid!$1:$1048576,K$2,FALSE) -> 37.342129 | L40: =+VLOOKUP($E40,Hybrid!$1:$1048576,L$2,FALSE) -> 42.650406 | M40: =+VLOOKUP($E40,Hybrid!$1:$1048576,M$2,FALSE) -> 47.916154 | ... AO40: =+VLOOKUP($E40,Hybrid!$1:$1048576,AO$2,FALSE) -> 177.032
D41: class C | E41: AUTO_cc_cele_0 | F41: =+VLOOKUP($E41,Hybrid!$1:$1048576,F$2,FALSE) -> 9.4015406 | G41: =+VLOOKUP($E41,Hybrid!$1:$1048576,G$2,FALSE) -> 12.69964 | H41: =+VLOOKUP($E41,Hybrid!$1:$1048576,H$2,FALSE) -> 16.176695 | I41: =+VLOOKUP($E41,Hybrid!$1:$1048576,I$2,FALSE) -> 19.745034 | J41: =+VLOOKUP($E41,Hybrid!$1:$1048576,J$2,FALSE) -> 23.347366 | K41: =+VLOOKUP($E41,Hybrid!$1:$1048576,K$2,FALSE) -> 26.947438 | L41: =+VLOOKUP($E41,Hybrid!$1:$1048576,L$2,FALSE) -> 30.522894 | M41: =+VLOOKUP($E41,Hybrid!$1:$1048576,M$2,FALSE) -> 34.060269 | ... AO41: =+VLOOKUP($E41,Hybrid!$1:$1048576,AO$2,FALSE) -> 115.62675
D42: class D | E42: AUTO_cd_cele_0 | F42: =+VLOOKUP($E42,Hybrid!$1:$1048576,F$2,FALSE) -> 5.7700713 | G42: =+VLOOKUP($E42,Hybrid!$1:$1048576,G$2,FALSE) -> 7.5646068 | H42: =+VLOOKUP($E42,Hybrid!$1:$1048576,H$2,FALSE) -> 9.4403133 | I42: =+VLOOKUP($E42,Hybrid!$1:$1048576,I$2,FALSE) -> 11.343637 | J42: =+VLOOKUP($E42,Hybrid!$1:$1048576,J$2,FALSE) -> 13.239824 | K42: =+VLOOKUP($E42,Hybrid!$1:$1048576,K$2,FALSE) -> 15.106985 | L42: =+VLOOKUP($E42,Hybrid!$1:$1048576,L$2,FALSE) -> 16.931634 | M42: =+VLOOKUP($E42,Hybrid!$1:$1048576,M$2,FALSE) -> 18.705614 | ... AO42: =+VLOOKUP($E42,Hybrid!$1:$1048576,AO$2,FALSE) -> 45.588511
D43: class E | E43: AUTO_ce_cele_0 | F43: =+VLOOKUP($E43,Hybrid!$1:$1048576,F$2,FALSE) -> 3.4730441 | G43: =+VLOOKUP($E43,Hybrid!$1:$1048576,G$2,FALSE) -> 4.5739757 | H43: =+VLOOKUP($E43,Hybrid!$1:$1048576,H$2,FALSE) -> 5.7146977 | I43: =+VLOOKUP($E43,Hybrid!$1:$1048576,I$2,FALSE) -> 6.8601644 | J43: =+VLOOKUP($E43,Hybrid!$1:$1048576,J$2,FALSE) -> 7.9881131 | K43: =+VLOOKUP($E43,Hybrid!$1:$1048576,K$2,FALSE) -> 9.0848797 | L43: =+VLOOKUP($E43,Hybrid!$1:$1048576,L$2,FALSE) -> 10.142321 | M43: =+VLOOKUP($E43,Hybrid!$1:$1048576,M$2,FALSE) -> 11.155733 | ... AO43: =+VLOOKUP($E43,Hybrid!$1:$1048576,AO$2,FALSE) -> 22.141075
D44: class F | E44: AUTO_cf_cele_0 | F44: =+VLOOKUP($E44,Hybrid!$1:$1048576,F$2,FALSE) -> 1.7251505 | G44: =+VLOOKUP($E44,Hybrid!$1:$1048576,G$2,FALSE) -> 2.2454556 | H44: =+VLOOKUP($E44,Hybrid!$1:$1048576,H$2,FALSE) -> 2.7684618 | I44: =+VLOOKUP($E44,Hybrid!$1:$1048576,I$2,FALSE) -> 3.2743104 | J44: =+VLOOKUP($E44,Hybrid!$1:$1048576,J$2,FALSE) -> 3.7515155 | K44: =+VLOOKUP($E44,Hybrid!$1:$1048576,K$2,FALSE) -> 4.1939767 | L44: =+VLOOKUP($E44,Hybrid!$1:$1048576,L$2,FALSE) -> 4.5988846 | M44: =+VLOOKUP($E44,Hybrid!$1:$1048576,M$2,FALSE) -> 4.9653764 | ... AO44: =+VLOOKUP($E44,Hybrid!$1:$1048576,AO$2,FALSE) -> 5.2345644
D45: class G | E45: AUTO_cg_cele_0 | F45: =+VLOOKUP($E45,Hybrid!$1:$1048576,F$2,FALSE) -> 3.1066862 | G45: =+VLOOKUP($E45,Hybrid!$1:$1048576,G$2,FALSE) -> 4.0721667 | H45: =+VLOOKUP($E45,Hybrid!$1:$1048576,H$2,FALSE) -> 5.0169226 | I45: =+VLOOKUP($E45,Hybrid!$1:$1048576,I$2,FALSE) -> 5.9009041 | J45: =+VLOOKUP($E45,Hybrid!$1:$1048576,J$2,FALSE) -> 6.703518 | K45: =+VLOOKUP($E45,Hybrid!$1:$1048576,K$2,FALSE) -> 7.4161806 | L45: =+VLOOKUP($E45,Hybrid!$1:$1048576,L$2,FALSE) -> 8.0372736 | M45: =+VLOOKUP($E45,Hybrid!$1:$1048576,M$2,FALSE) -> 8.5690304 | ... AO45: =+VLOOKUP($E45,Hybrid!$1:$1048576,AO$2,FALSE) -> 6.3335345
C46: GAS | E46: AUTO_cgas_0 | F46: =+VLOOKUP($E46,Hybrid!$1:$1048576,F$2,FALSE) -> 1.936 | G46: =+VLOOKUP($E46,Hybrid!$1:$1048576,G$2,FALSE) -> 1.9920385 | H46: =+VLOOKUP($E46,Hybrid!$1:$1048576,H$2,FALSE) -> 2.058513 | I46: =+VLOOKUP($E46,Hybrid!$1:$1048576,I$2,FALSE) -> 2.1305753 | J46: =+VLOOKUP($E46,Hybrid!$1:$1048576,J$2,FALSE) -> 2.2050832 | K46: =+VLOOKUP($E46,Hybrid!$1:$1048576,K$2,FALSE) -> 2.2800657 | L46: =+VLOOKUP($E46,Hybrid!$1:$1048576,L$2,FALSE) -> 2.3543231 | M46: =+VLOOKUP($E46,Hybrid!$1:$1048576,M$2,FALSE) -> 2.4271484 | ... AO46: =+VLOOKUP($E46,Hybrid!$1:$1048576,AO$2,FALSE) -> 3.7739113
D47: class A | E47: AUTO_ca_cgas_0 | F47: =+VLOOKUP($E47,Hybrid!$1:$1048576,F$2,FALSE) -> 0.4256817 | G47: =+VLOOKUP($E47,Hybrid!$1:$1048576,G$2,FALSE) -> 0.4494557 | H47: =+VLOOKUP($E47,Hybrid!$1:$1048576,H$2,FALSE) -> 0.47618363 | I47: =+VLOOKUP($E47,Hybrid!$1:$1048576,I$2,FALSE) -> 0.50461174 | J47: =+VLOOKUP($E47,Hybrid!$1:$1048576,J$2,FALSE) -> 0.53390617 | K47: =+VLOOKUP($E47,Hybrid!$1:$1048576,K$2,FALSE) -> 0.56352909 | L47: =+VLOOKUP($E47,Hybrid!$1:$1048576,L$2,FALSE) -> 0.59314311 | M47: =+VLOOKUP($E47,Hybrid!$1:$1048576,M$2,FALSE) -> 0.6225422 | ... AO47: =+VLOOKUP($E47,Hybrid!$1:$1048576,AO$2,FALSE) -> 1.3010962
D48: class B | E48: AUTO_cb_cgas_0 | F48: =+VLOOKUP($E48,Hybrid!$1:$1048576,F$2,FALSE) -> 0.49500523 | G48: =+VLOOKUP($E48,Hybrid!$1:$1048576,G$2,FALSE) -> 0.51237735 | H48: =+VLOOKUP($E48,Hybrid!$1:$1048576,H$2,FALSE) -> 0.53282707 | I48: =+VLOOKUP($E48,Hybrid!$1:$1048576,I$2,FALSE) -> 0.55510706 | J48: =+VLOOKUP($E48,Hybrid!$1:$1048576,J$2,FALSE) -> 0.57838511 | K48: =+VLOOKUP($E48,Hybrid!$1:$1048576,K$2,FALSE) -> 0.60212053 | L48: =+VLOOKUP($E48,Hybrid!$1:$1048576,L$2,FALSE) -> 0.62596932 | M48: =+VLOOKUP($E48,Hybrid!$1:$1048576,M$2,FALSE) -> 0.64971611 | ... AO48: =+VLOOKUP($E48,Hybrid!$1:$1048576,AO$2,FALSE) -> 1.1696796
D49: class C | E49: AUTO_cc_cgas_0 | F49: =+VLOOKUP($E49,Hybrid!$1:$1048576,F$2,FALSE) -> 0.40659852 | G49: =+VLOOKUP($E49,Hybrid!$1:$1048576,G$2,FALSE) -> 0.41458692 | H49: =+VLOOKUP($E49,Hybrid!$1:$1048576,H$2,FALSE) -> 0.42489006 | I49: =+VLOOKUP($E49,Hybrid!$1:$1048576,I$2,FALSE) -> 0.43661388 | J49: =+VLOOKUP($E49,Hybrid!$1:$1048576,J$2,FALSE) -> 0.44916009 | K49: =+VLOOKUP($E49,Hybrid!$1:$1048576,K$2,FALSE) -> 0.46213734 | L49: =+VLOOKUP($E49,Hybrid!$1:$1048576,L$2,FALSE) -> 0.47529341 | M49: =+VLOOKUP($E49,Hybrid!$1:$1048576,M$2,FALSE) -> 0.48846693 | ... AO49: =+VLOOKUP($E49,Hybrid!$1:$1048576,AO$2,FALSE) -> 0.760856
D50: class D | E50: AUTO_cd_cgas_0 | F50: =+VLOOKUP($E50,Hybrid!$1:$1048576,F$2,FALSE) -> 0.24954447 | G50: =+VLOOKUP($E50,Hybrid!$1:$1048576,G$2,FALSE) -> 0.2523605 | H50: =+VLOOKUP($E50,Hybrid!$1:$1048576,H$2,FALSE) -> 0.25638798 | I50: =+VLOOKUP($E50,Hybrid!$1:$1048576,I$2,FALSE) -> 0.26108963 | J50: =+VLOOKUP($E50,Hybrid!$1:$1048576,J$2,FALSE) -> 0.2661123 | K50: =+VLOOKUP($E50,Hybrid!$1:$1048576,K$2,FALSE) -> 0.27122926 | L50: =+VLOOKUP($E50,Hybrid!$1:$1048576,L$2,FALSE) -> 0.27629699 | M50: =+VLOOKUP($E50,Hybrid!$1:$1048576,M$2,FALSE) -> 0.28122528 | ... AO50: =+VLOOKUP($E50,Hybrid!$1:$1048576,AO$2,FALSE) -> 0.31327503
D51: class E | E51: AUTO_ce_cgas_0 | F51: =+VLOOKUP($E51,Hybrid!$1:$1048576,F$2,FALSE) -> 0.15020247 | G51: =+VLOOKUP($E51,Hybrid!$1:$1048576,G$2,FALSE) -> 0.15208636 | H51: =+VLOOKUP($E51,Hybrid!$1:$1048576,H$2,FALSE) -> 0.15461234 | I51: =+VLOOKUP($E51,Hybrid!$1:$1048576,I$2,FALSE) -> 0.15743309 | J51: =+VLOOKUP($E51,Hybrid!$1:$1048576,J$2,FALSE) -> 0.16032595 | K51: =+VLOOKUP($E51,Hybrid!$1:$1048576,K$2,FALSE) -> 0.16315238 | L51: =+VLOOKUP($E51,Hybrid!$1:$1048576,L$2,FALSE) -> 0.16582827 | M51: =+VLOOKUP($E51,Hybrid!$1:$1048576,M$2,FALSE) -> 0.16830371 | ... AO51: =+VLOOKUP($E51,Hybrid!$1:$1048576,AO$2,FALSE) -> 0.14957306
D52: class F | E52: AUTO_cf_cgas_0 | F52: =+VLOOKUP($E52,Hybrid!$1:$1048576,F$2,FALSE) -> 0.074609436 | G52: =+VLOOKUP($E52,Hybrid!$1:$1048576,G$2,FALSE) -> 0.075303854 | H52: =+VLOOKUP($E52,Hybrid!$1:$1048576,H$2,FALSE) -> 0.076167883 | I52: =+VLOOKUP($E52,Hybrid!$1:$1048576,I$2,FALSE) -> 0.077010461 | J52: =+VLOOKUP($E52,Hybrid!$1:$1048576,J$2,FALSE) -> 0.077721316 | K52: =+VLOOKUP($E52,Hybrid!$1:$1048576,K$2,FALSE) -> 0.078242029 | L52: =+VLOOKUP($E52,Hybrid!$1:$1048576,L$2,FALSE) -> 0.0785458 | M52: =+VLOOKUP($E52,Hybrid!$1:$1048576,M$2,FALSE) -> 0.078624438 | ... AO52: =+VLOOKUP($E52,Hybrid!$1:$1048576,AO$2,FALSE) -> 0.035616963
D53: class G | E53: AUTO_cg_cgas_0 | F53: =+VLOOKUP($E53,Hybrid!$1:$1048576,F$2,FALSE) -> 0.13435819 | G53: =+VLOOKUP($E53,Hybrid!$1:$1048576,G$2,FALSE) -> 0.13586779 | H53: =+VLOOKUP($E53,Hybrid!$1:$1048576,H$2,FALSE) -> 0.13744409 | I53: =+VLOOKUP($E53,Hybrid!$1:$1048576,I$2,FALSE) -> 0.13870945 | J53: =+VLOOKUP($E53,Hybrid!$1:$1048576,J$2,FALSE) -> 0.13947226 | K53: =+VLOOKUP($E53,Hybrid!$1:$1048576,K$2,FALSE) -> 0.13965509 | L53: =+VLOOKUP($E53,Hybrid!$1:$1048576,L$2,FALSE) -> 0.13924622 | M53: =+VLOOKUP($E53,Hybrid!$1:$1048576,M$2,FALSE) -> 0.13826967 | ... AO53: =+VLOOKUP($E53,Hybrid!$1:$1048576,AO$2,FALSE) -> 0.043814475
C54: TOTAL SALES SHOCK | E54: NEWAUTO_2 | F54: =+VLOOKUP($E54,Hybrid!$1:$1048576,F$2,FALSE) -> 1886.229 | G54: =+VLOOKUP($E54,Hybrid!$1:$1048576,G$2,FALSE) -> 2121.806 | H54: =+VLOOKUP($E54,Hybrid!$1:$1048576,H$2,FALSE) -> 2286.103 | I54: =+VLOOKUP($E54,Hybrid!$1:$1048576,I$2,FALSE) -> 2400.5287 | J54: =+VLOOKUP($E54,Hybrid!$1:$1048576,J$2,FALSE) -> 2480.7808 | K54: =+VLOOKUP($E54,Hybrid!$1:$1048576,K$2,FALSE) -> 2537.837 | L54: =+VLOOKUP($E54,Hybrid!$1:$1048576,L$2,FALSE) -> 2581.4774 | M54: =+VLOOKUP($E54,Hybrid!$1:$1048576,M$2,FALSE) -> 2618.2022 | ... AO54: =+VLOOKUP($E54,Hybrid!$1:$1048576,AO$2,FALSE) -> 2825.2831
C55: OIL | E55: NEWAUTO_cfut_2 | F55: =+VLOOKUP($E55,Hybrid!$1:$1048576,F$2,FALSE) -> 1868.803 | G55: =+VLOOKUP($E55,Hybrid!$1:$1048576,G$2,FALSE) -> 2102.1722 | H55: =+VLOOKUP($E55,Hybrid!$1:$1048576,H$2,FALSE) -> 2264.8333 | I55: =+VLOOKUP($E55,Hybrid!$1:$1048576,I$2,FALSE) -> 2377.9791 | J55: =+VLOOKUP($E55,Hybrid!$1:$1048576,J$2,FALSE) -> 2457.1346 | K55: =+VLOOKUP($E55,Hybrid!$1:$1048576,K$2,FALSE) -> 2513.1323 | L55: =+VLOOKUP($E55,Hybrid!$1:$1048576,L$2,FALSE) -> 2555.6166 | M55: =+VLOOKUP($E55,Hybrid!$1:$1048576,M$2,FALSE) -> 2591.0143 | ... AO55: =+VLOOKUP($E55,Hybrid!$1:$1048576,AO$2,FALSE) -> 2134.8214
D56: class A | E56: NEWAUTO_ca_cfut_2 | F56: =+VLOOKUP($E56,Hybrid!$1:$1048576,F$2,FALSE) -> 528.68437 | G56: =+VLOOKUP($E56,Hybrid!$1:$1048576,G$2,FALSE) -> 598.23806 | H56: =+VLOOKUP($E56,Hybrid!$1:$1048576,H$2,FALSE) -> 650.2446 | I56: =+VLOOKUP($E56,Hybrid!$1:$1048576,I$2,FALSE) -> 689.67493 | J56: =+VLOOKUP($E56,Hybrid!$1:$1048576,J$2,FALSE) -> 720.25057 | K56: =+VLOOKUP($E56,Hybrid!$1:$1048576,K$2,FALSE) -> 744.6554 | L56: =+VLOOKUP($E56,Hybrid!$1:$1048576,L$2,FALSE) -> 765.44423 | M56: =+VLOOKUP($E56,Hybrid!$1:$1048576,M$2,FALSE) -> 784.34266 | ... AO56: =+VLOOKUP($E56,Hybrid!$1:$1048576,AO$2,FALSE) -> 835.48108
D57: class B | E57: NEWAUTO_cb_cfut_2 | F57: =+VLOOKUP($E57,Hybrid!$1:$1048576,F$2,FALSE) -> 507.56689 | G57: =+VLOOKUP($E57,Hybrid!$1:$1048576,G$2,FALSE) -> 573.64916 | H57: =+VLOOKUP($E57,Hybrid!$1:$1048576,H$2,FALSE) -> 622.34368 | I57: =+VLOOKUP($E57,Hybrid!$1:$1048576,I$2,FALSE) -> 658.5989 | J57: =+VLOOKUP($E57,Hybrid!$1:$1048576,J$2,FALSE) -> 686.09931 | K57: =+VLOOKUP($E57,Hybrid!$1:$1048576,K$2,FALSE) -> 707.47845 | L57: =+VLOOKUP($E57,Hybrid!$1:$1048576,L$2,FALSE) -> 725.21286 | M57: =+VLOOKUP($E57,Hybrid!$1:$1048576,M$2,FALSE) -> 740.98417 | ... AO57: =+VLOOKUP($E57,Hybrid!$1:$1048576,AO$2,FALSE) -> 683.10047
D58: class C | E58: NEWAUTO_cc_cfut_2 | F58: =+VLOOKUP($E58,Hybrid!$1:$1048576,F$2,FALSE) -> 351.33496 | G58: =+VLOOKUP($E58,Hybrid!$1:$1048576,G$2,FALSE) -> 396.60029 | H58: =+VLOOKUP($E58,Hybrid!$1:$1048576,H$2,FALSE) -> 429.46134 | I58: =+VLOOKUP($E58,Hybrid!$1:$1048576,I$2,FALSE) -> 453.4672 | J58: =+VLOOKUP($E58,Hybrid!$1:$1048576,J$2,FALSE) -> 471.24691 | K58: =+VLOOKUP($E58,Hybrid!$1:$1048576,K$2,FALSE) -> 484.66391 | L58: =+VLOOKUP($E58,Hybrid!$1:$1048576,L$2,FALSE) -> 495.45006 | M58: =+VLOOKUP($E58,Hybrid!$1:$1048576,M$2,FALSE) -> 504.78742 | ... AO58: =+VLOOKUP($E58,Hybrid!$1:$1048576,AO$2,FALSE) -> 403.88777
D59: class D | E59: NEWAUTO_cd_cfut_2 | F59: =+VLOOKUP($E59,Hybrid!$1:$1048576,F$2,FALSE) -> 194.72927 | G59: =+VLOOKUP($E59,Hybrid!$1:$1048576,G$2,FALSE) -> 218.62509 | H59: =+VLOOKUP($E59,Hybrid!$1:$1048576,H$2,FALSE) -> 234.78025 | I59: =+VLOOKUP($E59,Hybrid!$1:$1048576,I$2,FALSE) -> 245.47874 | J59: =+VLOOKUP($E59,Hybrid!$1:$1048576,J$2,FALSE) -> 252.39244 | K59: =+VLOOKUP($E59,Hybrid!$1:$1048576,K$2,FALSE) -> 256.68252 | L59: =+VLOOKUP($E59,Hybrid!$1:$1048576,L$2,FALSE) -> 259.36974 | M59: =+VLOOKUP($E59,Hybrid!$1:$1048576,M$2,FALSE) -> 261.13769 | ... AO59: =+VLOOKUP($E59,Hybrid!$1:$1048576,AO$2,FALSE) -> 150.58953
D60: class E | E60: NEWAUTO_ce_cfut_2 | F60: =+VLOOKUP($E60,Hybrid!$1:$1048576,F$2,FALSE) -> 119.79027 | G60: =+VLOOKUP($E60,Hybrid!$1:$1048576,G$2,FALSE) -> 133.83042 | H60: =+VLOOKUP($E60,Hybrid!$1:$1048576,H$2,FALSE) -> 142.64325 | I60: =+VLOOKUP($E60,Hybrid!$1:$1048576,I$2,FALSE) -> 147.81966 | J60: =+VLOOKUP($E60,Hybrid!$1:$1048576,J$2,FALSE) -> 150.51251 | K60: =+VLOOKUP($E60,Hybrid!$1:$1048576,K$2,FALSE) -> 151.5093 | L60: =+VLOOKUP($E60,Hybrid!$1:$1048576,L$2,FALSE) -> 151.47284 | M60: =+VLOOKUP($E60,Hybrid!$1:$1048576,M$2,FALSE) -> 150.84157 | ... AO60: =+VLOOKUP($E60,Hybrid!$1:$1048576,AO$2,FALSE) -> 55.029359
D61: class F | E61: NEWAUTO_cf_cfut_2 | F61: =+VLOOKUP($E61,Hybrid!$1:$1048576,F$2,FALSE) -> 57.932893 | G61: =+VLOOKUP($E61,Hybrid!$1:$1048576,G$2,FALSE) -> 63.60906 | H61: =+VLOOKUP($E61,Hybrid!$1:$1048576,H$2,FALSE) -> 66.033114 | I61: =+VLOOKUP($E61,Hybrid!$1:$1048576,I$2,FALSE) -> 66.321974 | J61: =+VLOOKUP($E61,Hybrid!$1:$1048576,J$2,FALSE) -> 65.263207 | K61: =+VLOOKUP($E61,Hybrid!$1:$1048576,K$2,FALSE) -> 63.372895 | L61: =+VLOOKUP($E61,Hybrid!$1:$1048576,L$2,FALSE) -> 61.035555 | M61: =+VLOOKUP($E61,Hybrid!$1:$1048576,M$2,FALSE) -> 58.490348 | ... AO61: =+VLOOKUP($E61,Hybrid!$1:$1048576,AO$2,FALSE) -> 4.8403462
D62: class G | E62: NEWAUTO_cg_cfut_2 | F62: =+VLOOKUP($E62,Hybrid!$1:$1048576,F$2,FALSE) -> 108.76433 | G62: =+VLOOKUP($E62,Hybrid!$1:$1048576,G$2,FALSE) -> 117.62013 | H62: =+VLOOKUP($E62,Hybrid!$1:$1048576,H$2,FALSE) -> 119.32708 | I62: =+VLOOKUP($E62,Hybrid!$1:$1048576,I$2,FALSE) -> 116.61768 | J62: =+VLOOKUP($E62,Hybrid!$1:$1048576,J$2,FALSE) -> 111.36964 | K62: =+VLOOKUP($E62,Hybrid!$1:$1048576,K$2,FALSE) -> 104.76986 | L62: =+VLOOKUP($E62,Hybrid!$1:$1048576,L$2,FALSE) -> 97.631367 | M62: =+VLOOKUP($E62,Hybrid!$1:$1048576,M$2,FALSE) -> 90.430451 | ... AO62: =+VLOOKUP($E62,Hybrid!$1:$1048576,AO$2,FALSE) -> 1.8928765
C63: ELEC | E63: NEWAUTO_cele_2 | F63: =+VLOOKUP($E63,Hybrid!$1:$1048576,F$2,FALSE) -> 17.269 | G63: =+VLOOKUP($E63,Hybrid!$1:$1048576,G$2,FALSE) -> 19.457169 | H63: =+VLOOKUP($E63,Hybrid!$1:$1048576,H$2,FALSE) -> 21.079389 | I63: =+VLOOKUP($E63,Hybrid!$1:$1048576,I$2,FALSE) -> 22.349837 | J63: =+VLOOKUP($E63,Hybrid!$1:$1048576,J$2,FALSE) -> 23.439846 | K63: =+VLOOKUP($E63,Hybrid!$1:$1048576,K$2,FALSE) -> 24.493574 | L63: =+VLOOKUP($E63,Hybrid!$1:$1048576,L$2,FALSE) -> 25.645995 | M63: =+VLOOKUP($E63,Hybrid!$1:$1048576,M$2,FALSE) -> 26.970187 | ... AO63: =+VLOOKUP($E63,Hybrid!$1:$1048576,AO$2,FALSE) -> 690.28232
D64: class A | E64: NEWAUTO_ca_cele_2 | F64: =+VLOOKUP($E64,Hybrid!$1:$1048576,F$2,FALSE) -> 4.8854001 | G64: =+VLOOKUP($E64,Hybrid!$1:$1048576,G$2,FALSE) -> 5.5376973 | H64: =+VLOOKUP($E64,Hybrid!$1:$1048576,H$2,FALSE) -> 6.0545843 | I64: =+VLOOKUP($E64,Hybrid!$1:$1048576,I$2,FALSE) -> 6.4882358 | J64: =+VLOOKUP($E64,Hybrid!$1:$1048576,J$2,FALSE) -> 6.8824648 | K64: =+VLOOKUP($E64,Hybrid!$1:$1048576,K$2,FALSE) -> 7.2768624 | L64: =+VLOOKUP($E64,Hybrid!$1:$1048576,L$2,FALSE) -> 7.7108498 | M64: =+VLOOKUP($E64,Hybrid!$1:$1048576,M$2,FALSE) -> 8.2063243 | ... AO64: =+VLOOKUP($E64,Hybrid!$1:$1048576,AO$2,FALSE) -> 274.39294
D65: class B | E65: NEWAUTO_cb_cele_2 | F65: =+VLOOKUP($E65,Hybrid!$1:$1048576,F$2,FALSE) -> 4.6902604 | G65: =+VLOOKUP($E65,Hybrid!$1:$1048576,G$2,FALSE) -> 5.310837 | H65: =+VLOOKUP($E65,Hybrid!$1:$1048576,H$2,FALSE) -> 5.7983659 | I65: =+VLOOKUP($E65,Hybrid!$1:$1048576,I$2,FALSE) -> 6.2047942 | J65: =+VLOOKUP($E65,Hybrid!$1:$1048576,J$2,FALSE) -> 6.5735544 | K65: =+VLOOKUP($E65,Hybrid!$1:$1048576,K$2,FALSE) -> 6.943705 | L65: =+VLOOKUP($E65,Hybrid!$1:$1048576,L$2,FALSE) -> 7.3536603 | M65: =+VLOOKUP($E65,Hybrid!$1:$1048576,M$2,FALSE) -> 7.8242502 | ... AO65: =+VLOOKUP($E65,Hybrid!$1:$1048576,AO$2,FALSE) -> 236.63077
D66: class C | E66: NEWAUTO_cc_cele_2 | F66: =+VLOOKUP($E66,Hybrid!$1:$1048576,F$2,FALSE) -> 3.246572 | G66: =+VLOOKUP($E66,Hybrid!$1:$1048576,G$2,FALSE) -> 3.6722039 | H66: =+VLOOKUP($E66,Hybrid!$1:$1048576,H$2,FALSE) -> 4.0035834 | I66: =+VLOOKUP($E66,Hybrid!$1:$1048576,I$2,FALSE) -> 4.27793 | J66: =+VLOOKUP($E66,Hybrid!$1:$1048576,J$2,FALSE) -> 4.5262093 | K66: =+VLOOKUP($E66,Hybrid!$1:$1048576,K$2,FALSE) -> 4.7761076 | L66: =+VLOOKUP($E66,Hybrid!$1:$1048576,L$2,FALSE) -> 5.0545188 | M66: =+VLOOKUP($E66,Hybrid!$1:$1048576,M$2,FALSE) -> 5.3756744 | ... AO66: =+VLOOKUP($E66,Hybrid!$1:$1048576,AO$2,FALSE) -> 146.69189
D67: class D | E67: NEWAUTO_cd_cele_2 | F67: =+VLOOKUP($E67,Hybrid!$1:$1048576,F$2,FALSE) -> 1.7994298 | G67: =+VLOOKUP($E67,Hybrid!$1:$1048576,G$2,FALSE) -> 2.0222371 | H67: =+VLOOKUP($E67,Hybrid!$1:$1048576,H$2,FALSE) -> 2.1789386 | I67: =+VLOOKUP($E67,Hybrid!$1:$1048576,I$2,FALSE) -> 2.2916149 | J67: =+VLOOKUP($E67,Hybrid!$1:$1048576,J$2,FALSE) -> 2.3771979 | K67: =+VLOOKUP($E67,Hybrid!$1:$1048576,K$2,FALSE) -> 2.4487728 | L67: =+VLOOKUP($E67,Hybrid!$1:$1048576,L$2,FALSE) -> 2.5180832 | M67: =+VLOOKUP($E67,Hybrid!$1:$1048576,M$2,FALSE) -> 2.591747 | ... AO67: =+VLOOKUP($E67,Hybrid!$1:$1048576,AO$2,FALSE) -> 23.141079
D68: class E | E68: NEWAUTO_ce_cele_2 | F68: =+VLOOKUP($E68,Hybrid!$1:$1048576,F$2,FALSE) -> 1.1069429 | G68: =+VLOOKUP($E68,Hybrid!$1:$1048576,G$2,FALSE) -> 1.2380931 | H68: =+VLOOKUP($E68,Hybrid!$1:$1048576,H$2,FALSE) -> 1.3247165 | I68: =+VLOOKUP($E68,Hybrid!$1:$1048576,I$2,FALSE) -> 1.382071 | J68: =+VLOOKUP($E68,Hybrid!$1:$1048576,J$2,FALSE) -> 1.4216685 | K68: =+VLOOKUP($E68,Hybrid!$1:$1048576,K$2,FALSE) -> 1.4521728 | L68: =+VLOOKUP($E68,Hybrid!$1:$1048576,L$2,FALSE) -> 1.4809772 | M68: =+VLOOKUP($E68,Hybrid!$1:$1048576,M$2,FALSE) -> 1.5120132 | ... AO68: =+VLOOKUP($E68,Hybrid!$1:$1048576,AO$2,FALSE) -> 8.8067577
D69: class F | E69: NEWAUTO_cf_cele_2 | F69: =+VLOOKUP($E69,Hybrid!$1:$1048576,F$2,FALSE) -> 0.535339 | G69: =+VLOOKUP($E69,Hybrid!$1:$1048576,G$2,FALSE) -> 0.58825 | H69: =+VLOOKUP($E69,Hybrid!$1:$1048576,H$2,FALSE) -> 0.61227637 | I69: =+VLOOKUP($E69,Hybrid!$1:$1048576,I$2,FALSE) -> 0.61778488 | J69: =+VLOOKUP($E69,Hybrid!$1:$1048576,J$2,FALSE) -> 0.61215256 | K69: =+VLOOKUP($E69,Hybrid!$1:$1048576,K$2,FALSE) -> 0.60035694 | L69: =+VLOOKUP($E69,Hybrid!$1:$1048576,L$2,FALSE) -> 0.58607168 | M69: =+VLOOKUP($E69,Hybrid!$1:$1048576,M$2,FALSE) -> 0.57123405 | ... AO69: =+VLOOKUP($E69,Hybrid!$1:$1048576,AO$2,FALSE) -> 0.44199909
D70: class G | E70: NEWAUTO_cg_cele_2 | F70: =+VLOOKUP($E70,Hybrid!$1:$1048576,F$2,FALSE) -> 1.0050558 | G70: =+VLOOKUP($E70,Hybrid!$1:$1048576,G$2,FALSE) -> 1.0878508 | H70: =+VLOOKUP($E70,Hybrid!$1:$1048576,H$2,FALSE) -> 1.1069242 | I70: =+VLOOKUP($E70,Hybrid!$1:$1048576,I$2,FALSE) -> 1.0874058 | J70: =+VLOOKUP($E70,Hybrid!$1:$1048576,J$2,FALSE) -> 1.0465984 | K70: =+VLOOKUP($E70,Hybrid!$1:$1048576,K$2,FALSE) -> 0.99559627 | L70: =+VLOOKUP($E70,Hybrid!$1:$1048576,L$2,FALSE) -> 0.94183363 | M70: =+VLOOKUP($E70,Hybrid!$1:$1048576,M$2,FALSE) -> 0.88894387 | ... AO70: =+VLOOKUP($E70,Hybrid!$1:$1048576,AO$2,FALSE) -> 0.17688497
C71: GAS | E71: NEWAUTO_cgas_2 | F71: =+VLOOKUP($E71,Hybrid!$1:$1048576,F$2,FALSE) -> 0.157 | G71: =+VLOOKUP($E71,Hybrid!$1:$1048576,G$2,FALSE) -> 0.17660558 | H71: =+VLOOKUP($E71,Hybrid!$1:$1048576,H$2,FALSE) -> 0.1902709 | I71: =+VLOOKUP($E71,Hybrid!$1:$1048576,I$2,FALSE) -> 0.19977639 | J71: =+VLOOKUP($E71,Hybrid!$1:$1048576,J$2,FALSE) -> 0.20642632 | K71: =+VLOOKUP($E71,Hybrid!$1:$1048576,K$2,FALSE) -> 0.21113075 | L71: =+VLOOKUP($E71,Hybrid!$1:$1048576,L$2,FALSE) -> 0.2146999 | M71: =+VLOOKUP($E71,Hybrid!$1:$1048576,M$2,FALSE) -> 0.21767369 | ... AO71: =+VLOOKUP($E71,Hybrid!$1:$1048576,AO$2,FALSE) -> 0.17934847
D72: class A | E72: NEWAUTO_ca_cgas_2 | F72: =+VLOOKUP($E72,Hybrid!$1:$1048576,F$2,FALSE) -> 0.0444153 | G72: =+VLOOKUP($E72,Hybrid!$1:$1048576,G$2,FALSE) -> 0.050258575 | H72: =+VLOOKUP($E72,Hybrid!$1:$1048576,H$2,FALSE) -> 0.054627696 | I72: =+VLOOKUP($E72,Hybrid!$1:$1048576,I$2,FALSE) -> 0.057940277 | J72: =+VLOOKUP($E72,Hybrid!$1:$1048576,J$2,FALSE) -> 0.060508967 | K72: =+VLOOKUP($E72,Hybrid!$1:$1048576,K$2,FALSE) -> 0.062559241 | L72: =+VLOOKUP($E72,Hybrid!$1:$1048576,L$2,FALSE) -> 0.064305732 | M72: =+VLOOKUP($E72,Hybrid!$1:$1048576,M$2,FALSE) -> 0.065893407 | ... AO72: =+VLOOKUP($E72,Hybrid!$1:$1048576,AO$2,FALSE) -> 0.070189597
D73: class B | E73: NEWAUTO_cb_cgas_2 | F73: =+VLOOKUP($E73,Hybrid!$1:$1048576,F$2,FALSE) -> 0.0426412 | G73: =+VLOOKUP($E73,Hybrid!$1:$1048576,G$2,FALSE) -> 0.048192837 | H73: =+VLOOKUP($E73,Hybrid!$1:$1048576,H$2,FALSE) -> 0.052283712 | I73: =+VLOOKUP($E73,Hybrid!$1:$1048576,I$2,FALSE) -> 0.055329549 | J73: =+VLOOKUP($E73,Hybrid!$1:$1048576,J$2,FALSE) -> 0.057639886 | K73: =+VLOOKUP($E73,Hybrid!$1:$1048576,K$2,FALSE) -> 0.059435969 | L73: =+VLOOKUP($E73,Hybrid!$1:$1048576,L$2,FALSE) -> 0.060925854 | M73: =+VLOOKUP($E73,Hybrid!$1:$1048576,M$2,FALSE) -> 0.062250818 | ... AO73: =+VLOOKUP($E73,Hybrid!$1:$1048576,AO$2,FALSE) -> 0.05738795
D74: class C | E74: NEWAUTO_cc_cgas_2 | F74: =+VLOOKUP($E74,Hybrid!$1:$1048576,F$2,FALSE) -> 0.029516 | G74: =+VLOOKUP($E74,Hybrid!$1:$1048576,G$2,FALSE) -> 0.033318785 | H74: =+VLOOKUP($E74,Hybrid!$1:$1048576,H$2,FALSE) -> 0.036079474 | I74: =+VLOOKUP($E74,Hybrid!$1:$1048576,I$2,FALSE) -> 0.038096231 | J74: =+VLOOKUP($E74,Hybrid!$1:$1048576,J$2,FALSE) -> 0.039589922 | K74: =+VLOOKUP($E74,Hybrid!$1:$1048576,K$2,FALSE) -> 0.040717098 | L74: =+VLOOKUP($E74,Hybrid!$1:$1048576,L$2,FALSE) -> 0.041623252 | M74: =+VLOOKUP($E74,Hybrid!$1:$1048576,M$2,FALSE) -> 0.042407693 | ... AO74: =+VLOOKUP($E74,Hybrid!$1:$1048576,AO$2,FALSE) -> 0.033931013
D75: class D | E75: NEWAUTO_cd_cgas_2 | F75: =+VLOOKUP($E75,Hybrid!$1:$1048576,F$2,FALSE) -> 0.0163594 | G75: =+VLOOKUP($E75,Hybrid!$1:$1048576,G$2,FALSE) -> 0.018366911 | H75: =+VLOOKUP($E75,Hybrid!$1:$1048576,H$2,FALSE) -> 0.019724123 | I75: =+VLOOKUP($E75,Hybrid!$1:$1048576,I$2,FALSE) -> 0.020622913 | J75: =+VLOOKUP($E75,Hybrid!$1:$1048576,J$2,FALSE) -> 0.02120374 | K75: =+VLOOKUP($E75,Hybrid!$1:$1048576,K$2,FALSE) -> 0.021564154 | L75: =+VLOOKUP($E75,Hybrid!$1:$1048576,L$2,FALSE) -> 0.02178991 | M75: =+VLOOKUP($E75,Hybrid!$1:$1048576,M$2,FALSE) -> 0.021938437 | ... AO75: =+VLOOKUP($E75,Hybrid!$1:$1048576,AO$2,FALSE) -> 0.012651176
D76: class E | E76: NEWAUTO_ce_cgas_2 | F76: =+VLOOKUP($E76,Hybrid!$1:$1048576,F$2,FALSE) -> 0.0100637 | G76: =+VLOOKUP($E76,Hybrid!$1:$1048576,G$2,FALSE) -> 0.011243226 | H76: =+VLOOKUP($E76,Hybrid!$1:$1048576,H$2,FALSE) -> 0.011983602 | I76: =+VLOOKUP($E76,Hybrid!$1:$1048576,I$2,FALSE) -> 0.012418477 | J76: =+VLOOKUP($E76,Hybrid!$1:$1048576,J$2,FALSE) -> 0.012644705 | K76: =+VLOOKUP($E76,Hybrid!$1:$1048576,K$2,FALSE) -> 0.012728447 | L76: =+VLOOKUP($E76,Hybrid!$1:$1048576,L$2,FALSE) -> 0.012725384 | M76: =+VLOOKUP($E76,Hybrid!$1:$1048576,M$2,FALSE) -> 0.01267235 | ... AO76: =+VLOOKUP($E76,Hybrid!$1:$1048576,AO$2,FALSE) -> 0.0046230712
D77: class F | E77: NEWAUTO_cf_cgas_2 | F77: =+VLOOKUP($E77,Hybrid!$1:$1048576,F$2,FALSE) -> 0.004867 | G77: =+VLOOKUP($E77,Hybrid!$1:$1048576,G$2,FALSE) -> 0.0053438605 | H77: =+VLOOKUP($E77,Hybrid!$1:$1048576,H$2,FALSE) -> 0.0055475076 | I77: =+VLOOKUP($E77,Hybrid!$1:$1048576,I$2,FALSE) -> 0.005571775 | J77: =+VLOOKUP($E77,Hybrid!$1:$1048576,J$2,FALSE) -> 0.005482827 | K77: =+VLOOKUP($E77,Hybrid!$1:$1048576,K$2,FALSE) -> 0.00532402 | L77: =+VLOOKUP($E77,Hybrid!$1:$1048576,L$2,FALSE) -> 0.0051276577 | M77: =+VLOOKUP($E77,Hybrid!$1:$1048576,M$2,FALSE) -> 0.0049138324 | ... AO77: =+VLOOKUP($E77,Hybrid!$1:$1048576,AO$2,FALSE) -> 0.0004066423
D78: class G | E78: NEWAUTO_cg_cgas_2 | F78: =+VLOOKUP($E78,Hybrid!$1:$1048576,F$2,FALSE) -> 0.0091374 | G78: =+VLOOKUP($E78,Hybrid!$1:$1048576,G$2,FALSE) -> 0.0098813838 | H78: =+VLOOKUP($E78,Hybrid!$1:$1048576,H$2,FALSE) -> 0.010024787 | I78: =+VLOOKUP($E78,Hybrid!$1:$1048576,I$2,FALSE) -> 0.0097971677 | J78: =+VLOOKUP($E78,Hybrid!$1:$1048576,J$2,FALSE) -> 0.0093562739 | K78: =+VLOOKUP($E78,Hybrid!$1:$1048576,K$2,FALSE) -> 0.00880182 | L78: =+VLOOKUP($E78,Hybrid!$1:$1048576,L$2,FALSE) -> 0.0082021083 | M78: =+VLOOKUP($E78,Hybrid!$1:$1048576,M$2,FALSE) -> 0.0075971522 | ... AO78: =+VLOOKUP($E78,Hybrid!$1:$1048576,AO$2,FALSE) -> 0.00015902244
C79: TOTAL SALES BASELINE | E79: NEWAUTO_0 | F79: =+VLOOKUP($E79,Hybrid!$1:$1048576,F$2,FALSE) -> 1886.229 | G79: =+VLOOKUP($E79,Hybrid!$1:$1048576,G$2,FALSE) -> 2126.9764 | H79: =+VLOOKUP($E79,Hybrid!$1:$1048576,H$2,FALSE) -> 2294.4419 | I79: =+VLOOKUP($E79,Hybrid!$1:$1048576,I$2,FALSE) -> 2411.5025 | J79: =+VLOOKUP($E79,Hybrid!$1:$1048576,J$2,FALSE) -> 2495.0188 | K79: =+VLOOKUP($E79,Hybrid!$1:$1048576,K$2,FALSE) -> 2556.7025 | L79: =+VLOOKUP($E79,Hybrid!$1:$1048576,L$2,FALSE) -> 2604.3378 | M79: =+VLOOKUP($E79,Hybrid!$1:$1048576,M$2,FALSE) -> 2642.9423 | ... AO79: =+VLOOKUP($E79,Hybrid!$1:$1048576,AO$2,FALSE) -> 3207.9058
C80: OIL | E80: NEWAUTO_cfut_0 | F80: =+VLOOKUP($E80,Hybrid!$1:$1048576,F$2,FALSE) -> 1868.803 | G80: =+VLOOKUP($E80,Hybrid!$1:$1048576,G$2,FALSE) -> 2107.3251 | H80: =+VLOOKUP($E80,Hybrid!$1:$1048576,H$2,FALSE) -> 2273.2378 | I80: =+VLOOKUP($E80,Hybrid!$1:$1048576,I$2,FALSE) -> 2389.2032 | J80: =+VLOOKUP($E80,Hybrid!$1:$1048576,J$2,FALSE) -> 2471.9245 | K80: =+VLOOKUP($E80,Hybrid!$1:$1048576,K$2,FALSE) -> 2533.0045 | L80: =+VLOOKUP($E80,Hybrid!$1:$1048576,L$2,FALSE) -> 2580.1565 | M80: =+VLOOKUP($E80,Hybrid!$1:$1048576,M$2,FALSE) -> 2618.3528 | ... AO80: =+VLOOKUP($E80,Hybrid!$1:$1048576,AO$2,FALSE) -> 3173.0094
D81: class A | E81: NEWAUTO_ca_cfut_0 | F81: =+VLOOKUP($E81,Hybrid!$1:$1048576,F$2,FALSE) -> 528.68437 | G81: =+VLOOKUP($E81,Hybrid!$1:$1048576,G$2,FALSE) -> 599.67283 | H81: =+VLOOKUP($E81,Hybrid!$1:$1048576,H$2,FALSE) -> 652.52067 | I81: =+VLOOKUP($E81,Hybrid!$1:$1048576,I$2,FALSE) -> 692.64252 | J81: =+VLOOKUP($E81,Hybrid!$1:$1048576,J$2,FALSE) -> 724.10354 | K81: =+VLOOKUP($E81,Hybrid!$1:$1048576,K$2,FALSE) -> 749.80735 | L81: =+VLOOKUP($E81,Hybrid!$1:$1048576,L$2,FALSE) -> 771.73922 | M81: =+VLOOKUP($E81,Hybrid!$1:$1048576,M$2,FALSE) -> 791.21241 | ... AO81: =+VLOOKUP($E81,Hybrid!$1:$1048576,AO$2,FALSE) -> 1205.5752
D82: class B | E82: NEWAUTO_cb_cfut_0 | F82: =+VLOOKUP($E82,Hybrid!$1:$1048576,F$2,FALSE) -> 507.56689 | G82: =+VLOOKUP($E82,Hybrid!$1:$1048576,G$2,FALSE) -> 575.04323 | H82: =+VLOOKUP($E82,Hybrid!$1:$1048576,H$2,FALSE) -> 624.6004 | I82: =+VLOOKUP($E82,Hybrid!$1:$1048576,I$2,FALSE) -> 661.60014 | J82: =+VLOOKUP($E82,Hybrid!$1:$1048576,J$2,FALSE) -> 690.05535 | K82: =+VLOOKUP($E82,Hybrid!$1:$1048576,K$2,FALSE) -> 712.81732 | L82: =+VLOOKUP($E82,Hybrid!$1:$1048576,L$2,FALSE) -> 731.8247 | M82: =+VLOOKUP($E82,Hybrid!$1:$1048576,M$2,FALSE) -> 748.3529 | ... AO82: =+VLOOKUP($E82,Hybrid!$1:$1048576,AO$2,FALSE) -> 1030.812
D83: class C | E83: NEWAUTO_cc_cfut_0 | F83: =+VLOOKUP($E83,Hybrid!$1:$1048576,F$2,FALSE) -> 351.33496 | G83: =+VLOOKUP($E83,Hybrid!$1:$1048576,G$2,FALSE) -> 397.57666 | H83: =+VLOOKUP($E83,Hybrid!$1:$1048576,H$2,FALSE) -> 431.07235 | I83: =+VLOOKUP($E83,Hybrid!$1:$1048576,I$2,FALSE) -> 455.64815 | J83: =+VLOOKUP($E83,Hybrid!$1:$1048576,J$2,FALSE) -> 474.15911 | K83: =+VLOOKUP($E83,Hybrid!$1:$1048576,K$2,FALSE) -> 488.62358 | L83: =+VLOOKUP($E83,Hybrid!$1:$1048576,L$2,FALSE) -> 500.40662 | M83: =+VLOOKUP($E83,Hybrid!$1:$1048576,M$2,FALSE) -> 510.40171 | ... AO83: =+VLOOKUP($E83,Hybrid!$1:$1048576,AO$2,FALSE) -> 636.27918
D84: class D | E84: NEWAUTO_cd_cfut_0 | F84: =+VLOOKUP($E84,Hybrid!$1:$1048576,F$2,FALSE) -> 194.72927 | G84: =+VLOOKUP($E84,Hybrid!$1:$1048576,G$2,FALSE) -> 219.16848 | H84: =+VLOOKUP($E84,Hybrid!$1:$1048576,H$2,FALSE) -> 235.68359 | I84: =+VLOOKUP($E84,Hybrid!$1:$1048576,I$2,FALSE) -> 246.70455 | J84: =+VLOOKUP($E84,Hybrid!$1:$1048576,J$2,FALSE) -> 254.0236 | K84: =+VLOOKUP($E84,Hybrid!$1:$1048576,K$2,FALSE) -> 258.8825 | L84: =+VLOOKUP($E84,Hybrid!$1:$1048576,L$2,FALSE) -> 262.10336 | M84: =+VLOOKUP($E84,Hybrid!$1:$1048576,M$2,FALSE) -> 264.21365 | ... AO84: =+VLOOKUP($E84,Hybrid!$1:$1048576,AO$2,FALSE) -> 209.56755
D85: class E | E85: NEWAUTO_ce_cfut_0 | F85: =+VLOOKUP($E85,Hybrid!$1:$1048576,F$2,FALSE) -> 119.79027 | G85: =+VLOOKUP($E85,Hybrid!$1:$1048576,G$2,FALSE) -> 134.16754 | H85: =+VLOOKUP($E85,Hybrid!$1:$1048576,H$2,FALSE) -> 143.21188 | I85: =+VLOOKUP($E85,Hybrid!$1:$1048576,I$2,FALSE) -> 148.59992 | J85: =+VLOOKUP($E85,Hybrid!$1:$1048576,J$2,FALSE) -> 151.5567 | K85: =+VLOOKUP($E85,Hybrid!$1:$1048576,K$2,FALSE) -> 152.91812 | L85: =+VLOOKUP($E85,Hybrid!$1:$1048576,L$2,FALSE) -> 153.22891 | M85: =+VLOOKUP($E85,Hybrid!$1:$1048576,M$2,FALSE) -> 152.83366 | ... AO85: =+VLOOKUP($E85,Hybrid!$1:$1048576,AO$2,FALSE) -> 80.483787
D86: class F | E86: NEWAUTO_cf_cfut_0 | F86: =+VLOOKUP($E86,Hybrid!$1:$1048576,F$2,FALSE) -> 57.932893 | G86: =+VLOOKUP($E86,Hybrid!$1:$1048576,G$2,FALSE) -> 63.771507 | H86: =+VLOOKUP($E86,Hybrid!$1:$1048576,H$2,FALSE) -> 66.307034 | I86: =+VLOOKUP($E86,Hybrid!$1:$1048576,I$2,FALSE) -> 66.694489 | J86: =+VLOOKUP($E86,Hybrid!$1:$1048576,J$2,FALSE) -> 65.753401 | K86: =+VLOOKUP($E86,Hybrid!$1:$1048576,K$2,FALSE) -> 64.018949 | L86: =+VLOOKUP($E86,Hybrid!$1:$1048576,L$2,FALSE) -> 61.824021 | M86: =+VLOOKUP($E86,Hybrid!$1:$1048576,M$2,FALSE) -> 59.370209 | ... AO86: =+VLOOKUP($E86,Hybrid!$1:$1048576,AO$2,FALSE) -> 7.2222626
D87: class G | E87: NEWAUTO_cg_cfut_0 | F87: =+VLOOKUP($E87,Hybrid!$1:$1048576,F$2,FALSE) -> 108.76433 | G87: =+VLOOKUP($E87,Hybrid!$1:$1048576,G$2,FALSE) -> 117.92484 | H87: =+VLOOKUP($E87,Hybrid!$1:$1048576,H$2,FALSE) -> 119.84185 | I87: =+VLOOKUP($E87,Hybrid!$1:$1048576,I$2,FALSE) -> 117.31344 | J87: =+VLOOKUP($E87,Hybrid!$1:$1048576,J$2,FALSE) -> 112.27278 | K87: =+VLOOKUP($E87,Hybrid!$1:$1048576,K$2,FALSE) -> 105.93669 | L87: =+VLOOKUP($E87,Hybrid!$1:$1048576,L$2,FALSE) -> 99.029629 | M87: =+VLOOKUP($E87,Hybrid!$1:$1048576,M$2,FALSE) -> 91.968223 | ... AO87: =+VLOOKUP($E87,Hybrid!$1:$1048576,AO$2,FALSE) -> 3.069401
C88: ELEC | E88: NEWAUTO_cele_0 | F88: =+VLOOKUP($E88,Hybrid!$1:$1048576,F$2,FALSE) -> 17.269 | G88: =+VLOOKUP($E88,Hybrid!$1:$1048576,G$2,FALSE) -> 19.474316 | H88: =+VLOOKUP($E88,Hybrid!$1:$1048576,H$2,FALSE) -> 21.013204 | I88: =+VLOOKUP($E88,Hybrid!$1:$1048576,I$2,FALSE) -> 22.098555 | J88: =+VLOOKUP($E88,Hybrid!$1:$1048576,J$2,FALSE) -> 22.886708 | K88: =+VLOOKUP($E88,Hybrid!$1:$1048576,K$2,FALSE) -> 23.485189 | L88: =+VLOOKUP($E88,Hybrid!$1:$1048576,L$2,FALSE) -> 23.964516 | M88: =+VLOOKUP($E88,Hybrid!$1:$1048576,M$2,FALSE) -> 24.369515 | ... AO88: =+VLOOKUP($E88,Hybrid!$1:$1048576,AO$2,FALSE) -> 34.629865
D89: class A | E89: NEWAUTO_ca_cele_0 | F89: =+VLOOKUP($E89,Hybrid!$1:$1048576,F$2,FALSE) -> 4.8854001 | G89: =+VLOOKUP($E89,Hybrid!$1:$1048576,G$2,FALSE) -> 5.5417375 | H89: =+VLOOKUP($E89,Hybrid!$1:$1048576,H$2,FALSE) -> 6.0318007 | I89: =+VLOOKUP($E89,Hybrid!$1:$1048576,I$2,FALSE) -> 6.4067081 | J89: =+VLOOKUP($E89,Hybrid!$1:$1048576,J$2,FALSE) -> 6.7046879 | K89: =+VLOOKUP($E89,Hybrid!$1:$1048576,K$2,FALSE) -> 6.9527355 | L89: =+VLOOKUP($E89,Hybrid!$1:$1048576,L$2,FALSE) -> 7.1690295 | M89: =+VLOOKUP($E89,Hybrid!$1:$1048576,M$2,FALSE) -> 7.365415 | ... AO89: =+VLOOKUP($E89,Hybrid!$1:$1048576,AO$2,FALSE) -> 13.091208
D90: class B | E90: NEWAUTO_cb_cele_0 | F90: =+VLOOKUP($E90,Hybrid!$1:$1048576,F$2,FALSE) -> 4.6902604 | G90: =+VLOOKUP($E90,Hybrid!$1:$1048576,G$2,FALSE) -> 5.3141672 | H90: =+VLOOKUP($E90,Hybrid!$1:$1048576,H$2,FALSE) -> 5.7739232 | I90: =+VLOOKUP($E90,Hybrid!$1:$1048576,I$2,FALSE) -> 6.120204 | J90: =+VLOOKUP($E90,Hybrid!$1:$1048576,J$2,FALSE) -> 6.39077 | K90: =+VLOOKUP($E90,Hybrid!$1:$1048576,K$2,FALSE) -> 6.6121172 | L90: =+VLOOKUP($E90,Hybrid!$1:$1048576,L$2,FALSE) -> 6.8019619 | M90: =+VLOOKUP($E90,Hybrid!$1:$1048576,M$2,FALSE) -> 6.9717638 | ... AO90: =+VLOOKUP($E90,Hybrid!$1:$1048576,AO$2,FALSE) -> 11.373165
D91: class C | E91: NEWAUTO_cc_cele_0 | F91: =+VLOOKUP($E91,Hybrid!$1:$1048576,F$2,FALSE) -> 3.246572 | G91: =+VLOOKUP($E91,Hybrid!$1:$1048576,G$2,FALSE) -> 3.6741607 | H91: =+VLOOKUP($E91,Hybrid!$1:$1048576,H$2,FALSE) -> 3.9850409 | I91: =+VLOOKUP($E91,Hybrid!$1:$1048576,I$2,FALSE) -> 4.2154068 | J91: =+VLOOKUP($E91,Hybrid!$1:$1048576,J$2,FALSE) -> 4.3921339 | K91: =+VLOOKUP($E91,Hybrid!$1:$1048576,K$2,FALSE) -> 4.5339665 | L91: =+VLOOKUP($E91,Hybrid!$1:$1048576,L$2,FALSE) -> 4.6533531 | M91: =+VLOOKUP($E91,Hybrid!$1:$1048576,M$2,FALSE) -> 4.7582905 | ... AO91: =+VLOOKUP($E91,Hybrid!$1:$1048576,AO$2,FALSE) -> 7.119128
D92: class D | E92: NEWAUTO_cd_cele_0 | F92: =+VLOOKUP($E92,Hybrid!$1:$1048576,F$2,FALSE) -> 1.7994298 | G92: =+VLOOKUP($E92,Hybrid!$1:$1048576,G$2,FALSE) -> 2.0253384 | H92: =+VLOOKUP($E92,Hybrid!$1:$1048576,H$2,FALSE) -> 2.1782908 | I92: =+VLOOKUP($E92,Hybrid!$1:$1048576,I$2,FALSE) -> 2.2809357 | J92: =+VLOOKUP($E92,Hybrid!$1:$1048576,J$2,FALSE) -> 2.3499331 | K92: =+VLOOKUP($E92,Hybrid!$1:$1048576,K$2,FALSE) -> 2.3967536 | L92: =+VLOOKUP($E92,Hybrid!$1:$1048576,L$2,FALSE) -> 2.4289281 | M92: =+VLOOKUP($E92,Hybrid!$1:$1048576,M$2,FALSE) -> 2.4512462 | ... AO92: =+VLOOKUP($E92,Hybrid!$1:$1048576,AO$2,FALSE) -> 2.1165445
D93: class E | E93: NEWAUTO_ce_cele_0 | F93: =+VLOOKUP($E93,Hybrid!$1:$1048576,F$2,FALSE) -> 1.1069429 | G93: =+VLOOKUP($E93,Hybrid!$1:$1048576,G$2,FALSE) -> 1.2398534 | H93: =+VLOOKUP($E93,Hybrid!$1:$1048576,H$2,FALSE) -> 1.3236809 | I93: =+VLOOKUP($E93,Hybrid!$1:$1048576,I$2,FALSE) -> 1.3740547 | J93: =+VLOOKUP($E93,Hybrid!$1:$1048576,J$2,FALSE) -> 1.4023553 | K93: =+VLOOKUP($E93,Hybrid!$1:$1048576,K$2,FALSE) -> 1.4162911 | L93: =+VLOOKUP($E93,Hybrid!$1:$1048576,L$2,FALSE) -> 1.4208363 | M93: =+VLOOKUP($E93,Hybrid!$1:$1048576,M$2,FALSE) -> 1.4191046 | ... AO93: =+VLOOKUP($E93,Hybrid!$1:$1048576,AO$2,FALSE) -> 0.82719029
D94: class F | E94: NEWAUTO_cf_cele_0 | F94: =+VLOOKUP($E94,Hybrid!$1:$1048576,F$2,FALSE) -> 0.535339 | G94: =+VLOOKUP($E94,Hybrid!$1:$1048576,G$2,FALSE) -> 0.58931108 | H94: =+VLOOKUP($E94,Hybrid!$1:$1048576,H$2,FALSE) -> 0.61282442 | I94: =+VLOOKUP($E94,Hybrid!$1:$1048576,I$2,FALSE) -> 0.61658713 | J94: =+VLOOKUP($E94,Hybrid!$1:$1048576,J$2,FALSE) -> 0.60817749 | K94: =+VLOOKUP($E94,Hybrid!$1:$1048576,K$2,FALSE) -> 0.59252181 | L94: =+VLOOKUP($E94,Hybrid!$1:$1048576,L$2,FALSE) -> 0.57266692 | M94: =+VLOOKUP($E94,Hybrid!$1:$1048576,M$2,FALSE) -> 0.55044725 | ... AO94: =+VLOOKUP($E94,Hybrid!$1:$1048576,AO$2,FALSE) -> 0.071730932
D95: class G | E95: NEWAUTO_cg_cele_0 | F95: =+VLOOKUP($E95,Hybrid!$1:$1048576,F$2,FALSE) -> 1.0050558 | G95: =+VLOOKUP($E95,Hybrid!$1:$1048576,G$2,FALSE) -> 1.0897479 | H95: =+VLOOKUP($E95,Hybrid!$1:$1048576,H$2,FALSE) -> 1.1076427 | I95: =+VLOOKUP($E95,Hybrid!$1:$1048576,I$2,FALSE) -> 1.0846584 | J95: =+VLOOKUP($E95,Hybrid!$1:$1048576,J$2,FALSE) -> 1.0386501 | K95: =+VLOOKUP($E95,Hybrid!$1:$1048576,K$2,FALSE) -> 0.98080334 | L95: =+VLOOKUP($E95,Hybrid!$1:$1048576,L$2,FALSE) -> 0.91774014 | M95: =+VLOOKUP($E95,Hybrid!$1:$1048576,M$2,FALSE) -> 0.85324779 | ... AO95: =+VLOOKUP($E95,Hybrid!$1:$1048576,AO$2,FALSE) -> 0.030897972
C96: GAS | E96: NEWAUTO_cgas_0 | F96: =+VLOOKUP($E96,Hybrid!$1:$1048576,F$2,FALSE) -> 0.157 | G96: =+VLOOKUP($E96,Hybrid!$1:$1048576,G$2,FALSE) -> 0.17703848 | H96: =+VLOOKUP($E96,Hybrid!$1:$1048576,H$2,FALSE) -> 0.19097697 | I96: =+VLOOKUP($E96,Hybrid!$1:$1048576,I$2,FALSE) -> 0.20071934 | J96: =+VLOOKUP($E96,Hybrid!$1:$1048576,J$2,FALSE) -> 0.20766883 | K96: =+VLOOKUP($E96,Hybrid!$1:$1048576,K$2,FALSE) -> 0.21280023 | L96: =+VLOOKUP($E96,Hybrid!$1:$1048576,L$2,FALSE) -> 0.21676151 | M96: =+VLOOKUP($E96,Hybrid!$1:$1048576,M$2,FALSE) -> 0.21997042 | ... AO96: =+VLOOKUP($E96,Hybrid!$1:$1048576,AO$2,FALSE) -> 0.26656768
D97: class A | E97: NEWAUTO_ca_cgas_0 | F97: =+VLOOKUP($E97,Hybrid!$1:$1048576,F$2,FALSE) -> 0.0444153 | G97: =+VLOOKUP($E97,Hybrid!$1:$1048576,G$2,FALSE) -> 0.050379111 | H97: =+VLOOKUP($E97,Hybrid!$1:$1048576,H$2,FALSE) -> 0.054818911 | I97: =+VLOOKUP($E97,Hybrid!$1:$1048576,I$2,FALSE) -> 0.058189588 | J97: =+VLOOKUP($E97,Hybrid!$1:$1048576,J$2,FALSE) -> 0.060832659 | K97: =+VLOOKUP($E97,Hybrid!$1:$1048576,K$2,FALSE) -> 0.062992062 | L97: =+VLOOKUP($E97,Hybrid!$1:$1048576,L$2,FALSE) -> 0.06483458 | M97: =+VLOOKUP($E97,Hybrid!$1:$1048576,M$2,FALSE) -> 0.066470542 | ... AO97: =+VLOOKUP($E97,Hybrid!$1:$1048576,AO$2,FALSE) -> 0.10128157
D98: class B | E98: NEWAUTO_cb_cgas_0 | F98: =+VLOOKUP($E98,Hybrid!$1:$1048576,F$2,FALSE) -> 0.0426412 | G98: =+VLOOKUP($E98,Hybrid!$1:$1048576,G$2,FALSE) -> 0.048309954 | H98: =+VLOOKUP($E98,Hybrid!$1:$1048576,H$2,FALSE) -> 0.052473301 | I98: =+VLOOKUP($E98,Hybrid!$1:$1048576,I$2,FALSE) -> 0.055581686 | J98: =+VLOOKUP($E98,Hybrid!$1:$1048576,J$2,FALSE) -> 0.057972236 | K98: =+VLOOKUP($E98,Hybrid!$1:$1048576,K$2,FALSE) -> 0.059884493 | L98: =+VLOOKUP($E98,Hybrid!$1:$1048576,L$2,FALSE) -> 0.061481322 | M98: =+VLOOKUP($E98,Hybrid!$1:$1048576,M$2,FALSE) -> 0.062869872 | ... AO98: =+VLOOKUP($E98,Hybrid!$1:$1048576,AO$2,FALSE) -> 0.086599541
D99: class C | E99: NEWAUTO_cc_cgas_0 | F99: =+VLOOKUP($E99,Hybrid!$1:$1048576,F$2,FALSE) -> 0.029516 | G99: =+VLOOKUP($E99,Hybrid!$1:$1048576,G$2,FALSE) -> 0.033400811 | H99: =+VLOOKUP($E99,Hybrid!$1:$1048576,H$2,FALSE) -> 0.036214817 | I99: =+VLOOKUP($E99,Hybrid!$1:$1048576,I$2,FALSE) -> 0.038279455 | J99: =+VLOOKUP($E99,Hybrid!$1:$1048576,J$2,FALSE) -> 0.039834578 | K99: =+VLOOKUP($E99,Hybrid!$1:$1048576,K$2,FALSE) -> 0.041049753 | L99: =+VLOOKUP($E99,Hybrid!$1:$1048576,L$2,FALSE) -> 0.042039659 | M99: =+VLOOKUP($E99,Hybrid!$1:$1048576,M$2,FALSE) -> 0.042879356 | ... AO99: =+VLOOKUP($E99,Hybrid!$1:$1048576,AO$2,FALSE) -> 0.053454448
D100: class D | E100: NEWAUTO_cd_cgas_0 | F100: =+VLOOKUP($E100,Hybrid!$1:$1048576,F$2,FALSE) -> 0.0163594 | G100: =+VLOOKUP($E100,Hybrid!$1:$1048576,G$2,FALSE) -> 0.018412562 | H100: =+VLOOKUP($E100,Hybrid!$1:$1048576,H$2,FALSE) -> 0.019800013 | I100: =+VLOOKUP($E100,Hybrid!$1:$1048576,I$2,FALSE) -> 0.020725895 | J100: =+VLOOKUP($E100,Hybrid!$1:$1048576,J$2,FALSE) -> 0.021340775 | K100: =+VLOOKUP($E100,Hybrid!$1:$1048576,K$2,FALSE) -> 0.021748976 | L100: =+VLOOKUP($E100,Hybrid!$1:$1048576,L$2,FALSE) -> 0.022019564 | M100: =+VLOOKUP($E100,Hybrid!$1:$1048576,M$2,FALSE) -> 0.022196851 | ... AO100: =+VLOOKUP($E100,Hybrid!$1:$1048576,AO$2,FALSE) -> 0.017605979
...

Sheet Final_nrj
A1: _date_ | B1: 42005 | C1: 42370 | D1: 42736 | E1: 43101 | F1: 43466 | G1: 43831 | H1: 44197 | I1: 44562 | J1: 44927 | K1: 45292 | L1: 45658 | M1: 46023 | N1: 46388 | O1: 46753 | P1: 47119 | Q1: 47484 | R1: 47849 | S1: 48214 | T1: 48580 | U1: 48945 | V1: 49310 | W1: 49675 | X1: 50041 | Y1: 50406 | Z1: 50771 | AA1: 51136 | AB1: 51502 | AC1: 51867 | AD1: 52232 | AE1: 52597 | AF1: 52963 | AG1: 53328 | AH1: 53693 | AI1: 54058 | AJ1: 54424 | AK1: 54789
A2: cf_toe_2 | B2: 162.18538 | C2: 163.06009 | D2: 163.61356 | E2: 164.10601 | F2: 164.60712 | G2: 165.1068 | H2: 165.6167 | I2: 166.17199 | J2: 166.77811 | K2: 167.42291 | L2: 168.08481 | M2: 168.73766 | N2: 169.35377 | O2: 169.90593 | P2: 170.369 | Q2: 170.72108 | R2: 170.97353 | S2: 171.16366 | T2: 171.31805 | U2: 171.45431 | V2: 171.58393 | W2: 171.71439 | X2: 171.85049 | Y2: 171.99529 | Z2: 172.15062 | AA2: 172.3175 | AB2: 172.49641 | AC2: 172.68746 | AD2: 172.89052 | AE2: 173.10532 | AF2: 173.33156 | AG2: 173.5689 | AH2: 173.8171 | AI2: 174.07596 | AJ2: 174.34544 | AK2: 174.62564
A3: ch_toe_2 | B3: 64.30144 | C3: 64.184879 | D3: 63.813337 | E3: 63.413869 | F3: 63.052106 | G3: 62.730765 | H3: 62.452108 | I3: 62.222359 | J3: 62.033207 | K3: 61.871749 | L3: 61.724679 | M3: 61.579957 | N3: 61.427415 | O3: 61.258923 | P3: 61.068389 | Q3: 60.851644 | R3: 60.6164 | S3: 60.376608 | T3: 60.139128 | U3: 59.906799 | V3: 59.680288 | W3: 59.459162 | X3: 59.242489 | Y3: 59.029157 | Z3: 58.818029 | AA3: 58.608005 | AB3: 58.39805 | AC3: 58.187196 | AD3: 57.974536 | AE3: 57.759231 | AF3: 57.540503 | AG3: 57.317651 | AH3: 57.090051 | AI3: 56.85718 | AJ3: 56.61862 | AK3: 56.374084
A4: ci_toe_trsp_2 | B4: 26.341533 | C4: 26.597143 | D4: 26.828835 | E4: 27.04972 | F4: 27.262912 | G4: 27.465846 | H4: 27.660598 | I4: 27.854189 | J4: 28.050196 | K4: 28.248848 | L4: 28.447944 | M4: 28.643645 | N4: 28.831091 | O4: 29.004885 | P4: 29.159487 | Q4: 29.289549 | R4: 29.395419 | S4: 29.48308 | T4: 29.55781 | U4: 29.62363 | V4: 29.683515 | W4: 29.739662 | X4: 29.793692 | Y4: 29.846817 | Z4: 29.899946 | AA4: 29.953776 | AB4: 30.008851 | AC4: 30.065604 | AD4: 30.124394 | AE4: 30.185529 | AF4: 30.24928 | AG4: 30.315897 | AH4: 30.385615 | AI4: 30.458666 | AJ4: 30.535274 | AK4: 30.615667
A5: ci_toe_agrf_2 | B5: 4.8910688 | C5: 4.9373031 | D5: 4.9795592 | E5: 5.0212137 | F5: 5.0629707 | G5: 5.1040926 | H5: 5.1446563 | I5: 5.185699 | J5: 5.2276588 | K5: 5.2704297 | L5: 5.3135181 | M5: 5.3561695 | N5: 5.3974667 | O5: 5.4364126 | P5: 5.4720042 | Q5: 5.5033 | R5: 5.5304192 | S5: 5.5544897 | T5: 5.5765024 | U5: 5.5972283 | V5: 5.6172525 | W5: 5.6370161 | X5: 5.6568497 | Y5: 5.676999 | Z5: 5.6976449 | AA5: 5.7189188 | AB5: 5.7409153 | AC5: 5.7637013 | AD5: 5.7873234 | AE5: 5.8118144 | AF5: 5.8371967 | AG5: 5.8634867 | AH5: 5.8906967 | AI5: 5.9188374 | AJ5: 5.9479186 | AK5: 5.9779507
A6: ci_toe_ind_2 | B6: 44.175485 | C6: 44.63811 | D6: 45.076045 | E6: 45.497834 | F6: 45.903039 | G6: 46.285392 | H6: 46.649559 | I6: 47.009452 | J6: 47.371984 | K6: 47.737903 | L6: 48.103606 | M6: 48.462619 | N6: 48.806731 | O6: 49.126906 | P6: 49.414045 | Q6: 49.659616 | R6: 49.86509 | S6: 50.041292 | T6: 50.197527 | U6: 50.340891 | V6: 50.476661 | W6: 50.608737 | X6: 50.73999 | Y6: 50.872526 | Z6: 51.007889 | AA6: 51.147211 | AB6: 51.291331 | AC6: 51.440876 | AD6: 51.596331 | AE6: 51.758081 | AF6: 51.926451 | AG6: 52.101725 | AH6: 52.284168 | AI6: 52.474036 | AJ6: 52.671583 | AK6: 52.877069
A7: ci_toe_ser_2 | B7: 22.475857 | C7: 22.702658 | D7: 22.915783 | E7: 23.123375 | F7: 23.326096 | G7: 23.520701 | H7: 23.709782 | I7: 23.900289 | J7: 24.095069 | K7: 24.293985 | L7: 24.495063 | M7: 24.69527 | N7: 24.891063 | O7: 25.0788 | P7: 25.255073 | Q7: 25.416969 | R7: 25.566201 | S7: 25.708192 | T7: 25.847082 | U7: 25.985758 | V7: 26.126211 | W7: 26.26981 | X7: 26.417474 | Y7: 26.569792 | Z7: 26.727108 | AA7: 26.889587 | AB7: 27.057263 | AC7: 27.230082 | AD7: 27.407932 | AE7: 27.590668 | AF7: 27.778127 | AG7: 27.970145 | AH7: 28.166565 | AI7: 28.367241 | AJ7: 28.572046 | AK7: 28.780874
A8: cf_toe_0 | B8: 162.18538 | C8: 163.18361 | D8: 163.93894 | E8: 164.69725 | F8: 165.53686 | G8: 166.4692 | H8: 167.48335 | I8: 168.56385 | J8: 169.69685 | K8: 170.87166 | L8: 172.08057 | M8: 173.31826 | N8: 174.58111 | O8: 175.8667 | P8: 177.17338 | Q8: 178.50013 | R8: 179.8463 | S8: 181.21149 | T8: 182.59545 | U8: 183.99804 | V8: 185.4192 | W8: 186.8589 | X8: 188.31714 | Y8: 189.79394 | Z8: 191.28931 | AA8: 192.80331 | AB8: 194.33597 | AC8: 195.88737 | AD8: 197.45759 | AE8: 199.04673 | AF8: 200.6549 | AG8: 202.28226 | AH8: 203.92897 | AI8: 205.59519 | AJ8: 207.28114 | AK8: 208.98701
A9: ch_toe_0 | B9: 64.30144 | C9: 64.233784 | D9: 63.931558 | E9: 63.614626 | F9: 63.352024 | G9: 63.15395 | H9: 63.01119 | I9: 62.910661 | J9: 62.840776 | K9: 62.792713 | L9: 62.760233 | M9: 62.739095 | N9: 62.72647 | O9: 62.720453 | P9: 62.719697 | Q9: 62.723315 | R9: 62.730704 | S9: 62.741401 | T9: 62.755059 | U9: 62.771409 | V9: 62.790253 | W9: 62.811437 | X9: 62.834839 | Y9: 62.860359 | Z9: 62.887918 | AA9: 62.917448 | AB9: 62.948899 | AC9: 62.982229 | AD9: 63.017408 | AE9: 63.054413 | AF9: 63.093228 | AG9: 63.133845 | AH9: 63.176261 | AI9: 63.220481 | AJ9: 63.266511 | AK9: 63.314363
A10: ci_toe_trsp_0 | B10: 26.341533 | C10: 26.613548 | D10: 26.875563 | E10: 27.139256 | F10: 27.409132 | G10: 27.686287 | H10: 27.970553 | I10: 28.26139 | J10: 28.558213 | K10: 28.860495 | L10: 29.167793 | M10: 29.479751 | N10: 29.796095 | O10: 30.116621 | P10: 30.441188 | Q10: 30.769705 | R10: 31.102118 | S10: 31.438403 | T10: 31.778557 | U10: 32.122587 | V10: 32.470509 | W10: 32.82234 | X10: 33.1781 | Y10: 33.537809 | Z10: 33.901485 | AA10: 34.269149 | AB10: 34.640823 | AC10: 35.01653 | AD10: 35.396297 | AE10: 35.780152 | AF10: 36.168129 | AG10: 36.560266 | AH10: 36.956603 | AI10: 37.357186 | AJ10: 37.762063 | AK10: 38.171287
A11: ci_toe_agrf_0 | B11: 4.8910688 | C11: 4.9404679 | D11: 4.9884928 | E11: 5.0382642 | F11: 5.090783 | G11: 5.1460256 | H11: 5.2036325 | I11: 5.2632099 | J11: 5.32443 | K11: 5.3870461 | L11: 5.4508809 | M11: 5.5158091 | N11: 5.5817442 | O11: 5.6486276 | P11: 5.7164215 | Q11: 5.7851033 | R11: 5.8546609 | S11: 5.9250897 | T11: 5.9963897 | U11: 6.0685632 | V11: 6.1416134 | W11: 6.2155439 | X11: 6.2903577 | Y11: 6.3660576 | Z11: 6.4426459 | AA11: 6.5201245 | AB11: 6.5984958 | AC11: 6.6777622 | AD11: 6.7579271 | AE11: 6.8389946 | AF11: 6.9209698 | AG11: 7.0038592 | AH11: 7.08767 | AI11: 7.172411 | AJ11: 7.2580918 | AK11: 7.3447231
A12: ci_toe_ind_0 | B12: 44.175485 | C12: 44.674068 | D12: 45.175573 | E12: 45.685126 | F12: 46.204778 | G12: 46.734934 | H12: 47.275285 | I12: 47.825257 | J12: 48.384226 | K12: 48.951609 | L12: 49.526916 | M12: 50.109759 | N12: 50.69986 | O12: 51.297035 | P12: 51.901185 | Q12: 52.512277 | R12: 53.130328 | S12: 53.755391 | T12: 54.387542 | U12: 55.026869 | V12: 55.673463 | W12: 56.327417 | X12: 56.988819 | Y12: 57.657753 | Z12: 58.3343 | AA12: 59.018538 | AB12: 59.710543 | AC12: 60.410391 | AD12: 61.118157 | AE12: 61.83392 | AF12: 62.557761 | AG12: 63.289762 | AH12: 64.03001 | AI12: 64.778595 | AJ12: 65.535608 | AK12: 66.301146
... A67: ci_toe_cote_ind_0 | B67: 8.3925557 | C67: 8.4864021 | D67: 8.5806127 | E67: 8.6765404 | F67: 8.7746649 | G67: 8.8750173 | H67: 8.9774572 | I67: 9.0818047 | J67: 9.1878918 | K67: 9.2955792 | L67: 9.4047579 | M67: 9.5153467 | N67: 9.6272886 | O67: 9.7405465 | P67: 9.8551003 | Q67: 9.9709426 | R67: 10.088076 | S67: 10.206512 | T67: 10.326263 | U67: 10.447349 | V67: 10.569789 | W67: 10.693602 | X67: 10.818809 | Y67: 10.945429 | Z67: 11.07348 | AA67: 11.202982 | AB67: 11.333952 | AC67: 11.466408 | AD67: 11.600368 | AE67: 11.735849 | AF67: 11.872871 | AG67: 12.011451 | AH67: 12.151608 | AI67: 12.293361 | AJ67: 12.436729 | AK67: 12.581733

Sheet Primary_nrj
A1: _date_ | B1: 42005 | C1: 42370 | D1: 42736 | E1: 43101 | F1: 43466 | G1: 43831 | H1: 44197 | I1: 44562 | J1: 44927 | K1: 45292 | L1: 45658 | M1: 46023 | N1: 46388 | O1: 46753 | P1: 47119 | Q1: 47484 | R1: 47849 | S1: 48214 | T1: 48580 | U1: 48945 | V1: 49310 | W1: 49675 | X1: 50041 | Y1: 50406 | Z1: 50771 | AA1: 51136 | AB1: 51502 | AC1: 51867 | AD1: 52232 | AE1: 52597 | AF1: 52963 | AG1: 53328 | AH1: 53693 | AI1: 54058 | AJ1: 54424 | AK1: 54789
A2: yg_toe_2 | B2: 148.5762 | C2: 149.51833 | D2: 150.20339 | E2: 150.8468 | F2: 151.51552 | G2: 152.21225 | H2: 152.93671 | I2: 153.69789 | J2: 154.49581 | K2: 155.32369 | L2: 156.17039 | M2: 157.02223 | N2: 157.86422 | O2: 158.68104 | P2: 159.4577 | Q2: 160.18012 | R2: 160.84817 | S2: 161.47584 | T2: 162.07635 | U2: 162.65996 | V2: 163.23417 | W2: 163.80436 | X2: 164.37441 | Y2: 164.94717 | Z2: 165.5248 | AA2: 166.10902 | AB2: 166.7013 | AC2: 167.30293 | AD2: 167.91513 | AE2: 168.53913 | AF2: 169.17615 | AG2: 169.82746 | AH2: 170.4944 | AI2: 171.17836 | AJ2: 171.88078 | AK2: 172.60315
A3: yg_toe_0 | B3: 148.5762 | C3: 149.57013 | D3: 150.34484 | E3: 151.10989 | F3: 151.93569 | G3: 152.8347 | H3: 153.7993 | I3: 154.81743 | J3: 155.87806 | K3: 156.9727 | L3: 158.09525 | M3: 159.24155 | N3: 160.40878 | O3: 161.59512 | P3: 162.79935 | Q3: 164.0207 | R3: 165.25873 | S3: 166.51315 | T3: 167.78381 | U3: 169.07065 | V3: 170.37371 | W3: 171.69305 | X3: 173.02878 | Y3: 174.38103 | Z3: 175.74991 | AA3: 177.13559 | AB3: 178.53821 | AC3: 179.95794 | AD3: 181.39497 | AE3: 182.84948 | AF3: 184.32167 | AG3: 185.81175 | AH3: 187.31995 | AI3: 188.8465 | AJ3: 190.39163 | AK3: 191.95559
A4: yg_toe_ccoa_2 | B4: 2.391149 | C4: 2.4113403 | D4: 2.4286402 | E4: 2.4450674 | F4: 2.4608148 | G4: 2.4751913 | H4: 2.4883198 | I4: 2.5011328 | J4: 2.5140191 | K4: 2.5269145 | L4: 2.5394385 | M4: 2.5510018 | N4: 2.5608869 | O4: 2.5683162 | P4: 2.5725126 | Q4: 2.5727552 | R4: 2.5692525 | S4: 2.5630357 | T4: 2.5549306 | U4: 2.5455444 | V4: 2.5353159 | W4: 2.5245599 | X4: 2.5135003 | Y4: 2.5022939 | Z4: 2.4910476 | AA4: 2.4798318 | AB4: 2.468689 | AC4: 2.4576417 | AD4: 2.4466974 | AE4: 2.4358527 | AF4: 2.4250967 | AG4: 2.4144135 | AH4: 2.4037847 | AI4: 2.393191 | AJ4: 2.3826142 | AK4: 2.3720391
A5: yg_toe_ccoa_0 | B5: 2.391149 | C5: 2.4138098 | D5: 2.4355281 | E5: 2.4581598 | F5: 2.4821766 | G5: 2.5075019 | H5: 2.5339147 | I5: 2.5611973 | J5: 2.5891753 | K5: 2.6177206 | L5: 2.6467433 | M5: 2.6761821 | N5: 2.7059965 | O5: 2.7361603 | P5: 2.7666574 | Q5: 2.7974788 | R5: 2.8286204 | S5: 2.8600819 | T5: 2.8918649 | U5: 2.9239721 | V5: 2.9564069 | W5: 2.989173 | X5: 3.0222742 | Y5: 3.0557146 | Z5: 3.0894982 | AA5: 3.1236291 | AB5: 3.1581116 | AC5: 3.1929498 | AD5: 3.2281483 | AE5: 3.2637113 | AF5: 3.2996436 | AG5: 3.3359498 | AH5: 3.3726347 | AI5: 3.4097029 | AJ5: 3.4471595 | AK5: 3.4850092
A6: yg_toe_ccoi_2 | B6: 1.095999 | C6: 1.1024396 | D6: 1.1067161 | E6: 1.1110389 | F6: 1.1160485 | G6: 1.1216751 | H6: 1.127771 | I6: 1.1342991 | J6: 1.1412008 | K6: 1.1483812 | L6: 1.1557181 | M6: 1.1630714 | N6: 1.17029 | O6: 1.1772171 | P6: 1.1836957 | Q6: 1.1895728 | R6: 1.1948205 | S6: 1.1995524 | T6: 1.2038849 | U6: 1.2079064 | V6: 1.2116771 | W6: 1.215235 | X6: 1.2186023 | Y6: 1.2217888 | Z6: 1.2247962 | AA6: 1.2276197 | AB6: 1.2302501 | AC6: 1.2326749 | AD6: 1.2348793 | AE6: 1.2368471 | AF6: 1.2385613 | AG6: 1.2400049 | AH6: 1.2411616 | AI6: 1.2420163 | AJ6: 1.2425564 | AK6: 1.2427718
A7: yg_toe_ccoi_0 | B7: 1.095999 | C7: 1.1028001 | D7: 1.1077768 | E7: 1.1130992 | F7: 1.1194315 | G7: 1.1267863 | H7: 1.1349781 | I7: 1.1438038 | J7: 1.1530986 | K7: 1.1627433 | L7: 1.1726568 | M7: 1.1827858 | N7: 1.1930955 | O7: 1.2035636 | P7: 1.2141752 | Q7: 1.2249212 | R7: 1.2357956 | S7: 1.2467947 | T7: 1.2579163 | U7: 1.2691592 | V7: 1.2805225 | W7: 1.2920062 | X7: 1.3036102 | Y7: 1.3153347 | Z7: 1.3271803 | AA7: 1.3391474 | AB7: 1.3512369 | AC7: 1.3634497 | AD7: 1.3757866 | AE7: 1.3882489 | AF7: 1.4008378 | AG7: 1.4135548 | AH7: 1.4264013 | AI7: 1.439379 | AJ7: 1.4524895 | AK7: 1.4657345
A8: yg_toe_cfut_2 | B8: 42.352189 | C8: 42.550339 | D8: 42.686302 | E8: 42.84323 | F8: 43.038564 | G8: 43.264921 | H8: 43.513952 | I8: 43.78234 | J8: 44.066371 | K8: 44.361627 | L8: 44.663093 | M8: 44.965278 | N8: 45.26234 | O8: 45.548213 | P8: 45.816747 | Q8: 46.061855 | R8: 46.282313 | S8: 46.48215 | T8: 46.665228 | U8: 46.834475 | V8: 46.991904 | W8: 47.138777 | X8: 47.275784 | Y8: 47.403172 | Z8: 47.520858 | AA8: 47.628503 | AB8: 47.725575 | AC8: 47.811398 | AD8: 47.885191 | AE8: 47.946101 | AF8: 47.993243 | AG8: 48.025727 | AH8: 48.042696 | AI8: 48.043357 | AJ8: 48.027023 | AK8: 47.993144
A9: yg_toe_cfut_0 | B9: 42.352189 | C9: 42.563839 | D9: 42.725107 | E9: 42.918049 | F9: 43.161282 | G9: 43.450606 | H9: 43.776175 | I9: 44.128632 | J9: 44.500733 | K9: 44.887349 | L9: 45.285004 | M9: 45.691393 | N9: 46.104998 | O9: 46.524822 | P9: 46.950201 | Q9: 47.380695 | R9: 47.816006 | S9: 48.255934 | T9: 48.700343 | U9: 49.149141 | V9: 49.602269 | W9: 50.059687 | X9: 50.521372 | Y9: 50.987312 | Z9: 51.457506 | AA9: 51.931962 | AB9: 52.410696 | AC9: 52.893729 | AD9: 53.381093 | AE9: 53.872825 | AF9: 54.368969 | AG9: 54.869575 | AH9: 55.3747 | AI9: 55.884403 | AJ9: 56.398749 | AK9: 56.917805
A10: yg_toe_cfuh_2 | B10: 7.935536 | C10: 7.9839831 | D10: 8.0145869 | E10: 8.0387744 | F10: 8.0606898 | G10: 8.0809697 | H10: 8.100653 | I10: 8.1215149 | J10: 8.1440541 | K10: 8.1679441 | L10: 8.1923757 | M10: 8.2162685 | N10: 8.2383993 | O10: 8.2574887 | P10: 8.2722654 | Q10: 8.281521 | R10: 8.285611 | S10: 8.2862247 | T10: 8.284576 | U10: 8.2814961 | V10: 8.2775611 | W10: 8.2731806 | X10: 8.2686547 | Y10: 8.2642093 | Z10: 8.2600185 | AA10: 8.2562197 | AB10: 8.2529234 | AC10: 8.2502205 | AD10: 8.2481875 | AE10: 8.2468902 | AF10: 8.2463867 | AG10: 8.2467297 | AH10: 8.247968 | AI10: 8.2501482 | AJ10: 8.2533149 | AK10: 8.2575121
A11: yg_toe_cfuh_0 | B11: 7.935536 | C11: 7.9882333 | D11: 8.0259842 | E11: 8.0597632 | F11: 8.0940822 | G11: 8.1304841 | H11: 8.1692775 | I11: 8.2103169 | J11: 8.2533318 | K11: 8.2980554 | L11: 8.3442671 | M11: 8.3917989 | N11: 8.4405297 | O11: 8.4903729 | P11: 8.5412592 | Q11: 8.593147 | R11: 8.6460126 | S11: 8.6998426 | T11: 8.7546299 | U11: 8.8103707 | V11: 8.8670632 | W11: 8.9247063 | X11: 8.9832992 | Y11: 9.0428414 | Z11: 9.1033324 | AA11: 9.1647719 | AB11: 9.2271599 | AC11: 9.2904971 | AD11: 9.3547846 | AE11: 9.4200245 | AF11: 9.4862195 | AG11: 9.5533735 | AH11: 9.621491 | AI11: 9.6905774 | AJ11: 9.7606392 | AK11: 9.8316833
A12: yg_toe_cgas_2 | B12: 6.597728 | C12: 6.6023133 | D12: 6.5798666 | E12: 6.5467764 | F12: 6.5080886 | G12: 6.4644391 | H12: 6.4213775 | I12: 6.385027 | J12: 6.3548815 | K12: 6.3284719 | L12: 6.3031778 | M12: 6.2768809 | N12: 6.2481626 | O12: 6.2163283 | P12: 6.181363 | Q12: 6.1438464 | R12: 6.1075439 | S12: 6.076632 | T12: 6.0520068 | U12: 6.0333399 | V12: 6.0199343 | W12: 6.0110661 | X12: 6.0061042 | Y12: 6.0045364 | Z12: 6.005961 | AA12: 6.0100672 | AB12: 6.0166154 | AC12: 6.0254201 | AD12: 6.0363371 | AE12: 6.0492531 | AF12: 6.0640784 | AG12: 6.0807412 | AH12: 6.0991835 | AI12: 6.1193575 | AJ12: 6.1412232 | AK12: 6.1647457
... A71: yg_toe_cote_spub_0 | B71: 1.228594 | C71: 1.2411461 | D71: 1.2532706 | E71: 1.2655764 | F71: 1.2782706 | G71: 1.2913746 | H71: 1.3048474 | I71: 1.3186369 | J71: 1.3326976 | K71: 1.3469951 | L71: 1.3615048 | M71: 1.3762097 | N71: 1.3910986 | O71: 1.4061646 | P71: 1.4214036 | Q71: 1.4368139 | R71: 1.4523952 | S71: 1.4681482 | T71: 1.4840745 | U71: 1.5001759 | V71: 1.5164548 | W71: 1.5329136 | X71: 1.5495547 | Y71: 1.5663806 | Z71: 1.5833938 | AA71: 1.6005968 | AB71: 1.6179919 | AC71: 1.6355818 | AD71: 1.6533688 | AE71: 1.6713555 | AF71: 1.6895445 | AG71: 1.7079383 | AH71: 1.7265396 | AI71: 1.745351 | AJ71: 1.7643753 | AK71: 1.7836152

Sheet Energy_Mix
A1: _date_ | B1: 42005 | C1: 42370 | D1: 42736 | E1: 43101 | F1: 43466 | G1: 43831 | H1: 44197 | I1: 44562 | J1: 44927 | K1: 45292 | L1: 45658 | M1: 46023 | N1: 46388 | O1: 46753 | P1: 47119 | Q1: 47484 | R1: 47849 | S1: 48214 | T1: 48580 | U1: 48945 | V1: 49310 | W1: 49675 | X1: 50041 | Y1: 50406 | Z1: 50771 | AA1: 51136 | AB1: 51502 | AC1: 51867 | AD1: 52232 | AE1: 52597 | AF1: 52963 | AG1: 53328 | AH1: 53693 | AI1: 54058 | AJ1: 54424 | AK1: 54789
A2: phiy_ccoa_smin_2 | B2: 0.20069089 | C2: 0.20069089 | D2: 0.20069089 | E2: 0.20069089 | F2: 0.20069089 | G2: 0.20069089 | H2: 0.20069089 | I2: 0.20069089 | J2: 0.20069089 | K2: 0.20069089 | L2: 0.20069089 | M2: 0.20069089 | N2: 0.20069089 | O2: 0.20069089 | P2: 0.20069089 | Q2: 0.20069089 | R2: 0.20069089 | S2: 0.20069089 | T2: 0.20069089 | U2: 0.20069089 | V2: 0.20069089 | W2: 0.20069089 | X2: 0.20069089 | Y2: 0.20069089 | Z2: 0.20069089 | AA2: 0.20069089 | AB2: 0.20069089 | AC2: 0.20069089 | AD2: 0.20069089 | AE2: 0.20069089 | AF2: 0.20069089 | AG2: 0.20069089 | AH2: 0.20069089 | AI2: 0.20069089 | AJ2: 0.20069089 | AK2: 0.20069089
A3: phiy_ccoa_soil_2 | B3: 0.79930911 | C3: 0.79930911 | D3: 0.79930911 | E3: 0.79930911 | F3: 0.79930911 | G3: 0.79930911 | H3: 0.79930911 | I3: 0.79930911 | J3: 0.79930911 | K3: 0.79930911 | L3: 0.79930911 | M3: 0.79930911 | N3: 0.79930911 | O3: 0.79930911 | P3: 0.79930911 | Q3: 0.79930911 | R3: 0.79930911 | S3: 0.79930911 | T3: 0.79930911 | U3: 0.79930911 | V3: 0.79930911 | W3: 0.79930911 | X3: 0.79930911 | Y3: 0.79930911 | Z3: 0.79930911 | AA3: 0.79930911 | AB3: 0.79930911 | AC3: 0.79930911 | AD3: 0.79930911 | AE3: 0.79930911 | AF3: 0.79930911 | AG3: 0.79930911 | AH3: 0.79930911 | AI3: 0.79930911 | AJ3: 0.79930911 | AK3: 0.79930911
A4: phiy_ccoi_smin_2 | B4: 0.7836667 | C4: 0.7836667 | D4: 0.7836667 | E4: 0.7836667 | F4: 0.7836667 | G4: 0.7836667 | H4: 0.7836667 | I4: 0.7836667 | J4: 0.7836667 | K4: 0.7836667 | L4: 0.7836667 | M4: 0.7836667 | N4: 0.7836667 | O4: 0.7836667 | P4: 0.7836667 | Q4: 0.7836667 | R4: 0.7836667 | S4: 0.7836667 | T4: 0.7836667 | U4: 0.7836667 | V4: 0.7836667 | W4: 0.7836667 | X4: 0.7836667 | Y4: 0.7836667 | Z4: 0.7836667 | AA4: 0.7836667 | AB4: 0.7836667 | AC4: 0.7836667 | AD4: 0.7836667 | AE4: 0.7836667 | AF4: 0.7836667 | AG4: 0.7836667 | AH4: 0.7836667 | AI4: 0.7836667 | AJ4: 0.7836667 | AK4: 0.7836667
A5: phiy_ccoi_soil_2 | B5: 0.2163333 | C5: 0.2163333 | D5: 0.2163333 | E5: 0.2163333 | F5: 0.2163333 | G5: 0.2163333 | H5: 0.2163333 | I5: 0.2163333 | J5: 0.2163333 | K5: 0.2163333 | L5: 0.2163333 | M5: 0.2163333 | N5: 0.2163333 | O5: 0.2163333 | P5: 0.2163333 | Q5: 0.2163333 | R5: 0.2163333 | S5: 0.2163333 | T5: 0.2163333 | U5: 0.2163333 | V5: 0.2163333 | W5: 0.2163333 | X5: 0.2163333 | Y5: 0.2163333 | Z5: 0.2163333 | AA5: 0.2163333 | AB5: 0.2163333 | AC5: 0.2163333 | AD5: 0.2163333 | AE5: 0.2163333 | AF5: 0.2163333 | AG5: 0.2163333 | AH5: 0.2163333 | AI5: 0.2163333 | AJ5: 0.2163333 | AK5: 0.2163333
A6: phiy_cfut_soil_2 | B6: 0.83809636 | C6: 0.83809636 | D6: 0.83809636 | E6: 0.83809636 | F6: 0.83809636 | G6: 0.83809636 | H6: 0.83809636 | I6: 0.83809636 | J6: 0.83809636 | K6: 0.83809636 | L6: 0.83809636 | M6: 0.83809636 | N6: 0.83809636 | O6: 0.83809636 | P6: 0.83809636 | Q6: 0.83809636 | R6: 0.83809636 | S6: 0.83809636 | T6: 0.83809636 | U6: 0.83809636 | V6: 0.83809636 | W6: 0.83809636 | X6: 0.83809636 | Y6: 0.83809636 | Z6: 0.83809636 | AA6: 0.83809636 | AB6: 0.83809636 | AC6: 0.83809636 | AD6: 0.83809636 | AE6: 0.83809636 | AF6: 0.83809636 | AG6: 0.83809636 | AH6: 0.83809636 | AI6: 0.83809636 | AJ6: 0.83809636 | AK6: 0.83809636
A7: phiy_cfut_sbfu_2 | B7: 0.16190364 | C7: 0.16190364 | D7: 0.16190364 | E7: 0.16190364 | F7: 0.16190364 | G7: 0.16190364 | H7: 0.16190364 | I7: 0.16190364 | J7: 0.16190364 | K7: 0.16190364 | L7: 0.16190364 | M7: 0.16190364 | N7: 0.16190364 | O7: 0.16190364 | P7: 0.16190364 | Q7: 0.16190364 | R7: 0.16190364 | S7: 0.16190364 | T7: 0.16190364 | U7: 0.16190364 | V7: 0.16190364 | W7: 0.16190364 | X7: 0.16190364 | Y7: 0.16190364 | Z7: 0.16190364 | AA7: 0.16190364 | AB7: 0.16190364 | AC7: 0.16190364 | AD7: 0.16190364 | AE7: 0.16190364 | AF7: 0.16190364 | AG7: 0.16190364 | AH7: 0.16190364 | AI7: 0.16190364 | AJ7: 0.16190364 | AK7: 0.16190364
A8: phiy_cfuh_soil_2 | B8: 1 | C8: 1 | D8: 1 | E8: 1 | F8: 1 | G8: 1 | H8: 1 | I8: 1 | J8: 1 | K8: 1 | L8: 1 | M8: 1 | N8: 1 | O8: 1 | P8: 1 | Q8: 1 | R8: 1 | S8: 1 | T8: 1 | U8: 1 | V8: 1 | W8: 1 | X8: 1 | Y8: 1 | Z8: 1 | AA8: 1 | AB8: 1 | AC8: 1 | AD8: 1 | AE8: 1 | AF8: 1 | AG8: 1 | AH8: 1 | AI8: 1 | AJ8: 1 | AK8: 1
A9: phiy_cgas_smet_2 | B9: 8.2704782e-05 | C9: 8.2704782e-05 | D9: 8.2704782e-05 | E9: 8.2704782e-05 | F9: 8.2704782e-05 | G9: 8.2704782e-05 | H9: 8.2704782e-05 | I9: 8.2704782e-05 | J9: 8.2704782e-05 | K9: 8.2704782e-05 | L9: 8.2704782e-05 | M9: 8.2704782e-05 | N9: 8.2704782e-05 | O9: 8.2704782e-05 | P9: 8.2704782e-05 | Q9: 8.2704782e-05 | R9: 8.2704782e-05 | S9: 8.2704782e-05 | T9: 8.2704782e-05 | U9: 8.2704782e-05 | V9: 8.2704782e-05 | W9: 8.2704782e-05 | X9: 8.2704782e-05 | Y9: 8.2704782e-05 | Z9: 8.2704782e-05 | AA9: 8.2704782e-05 | AB9: 8.2704782e-05 | AC9: 8.2704782e-05 | AD9: 8.2704782e-05 | AE9: 8.2704782e-05 | AF9: 8.2704782e-05 | AG9: 8.2704782e-05 | AH9: 8.2704782e-05 | AI9: 8.2704782e-05 | AJ9: 8.2704782e-05 | AK9: 8.2704782e-05
A10: phiy_cgas_soil_2 | B10: 0.64531659 | C10: 0.64531659 | D10: 0.64531659 | E10: 0.64531659 | F10: 0.64531659 | G10: 0.64531659 | H10: 0.64531659 | I10: 0.64531659 | J10: 0.64531659 | K10: 0.64531659 | L10: 0.64531659 | M10: 0.64531659 | N10: 0.64531659 | O10: 0.64531659 | P10: 0.64531659 | Q10: 0.64531659 | R10: 0.64531659 | S10: 0.64531659 | T10: 0.64531659 | U10: 0.64531659 | V10: 0.64531659 | W10: 0.64531659 | X10: 0.64531659 | Y10: 0.64531659 | Z10: 0.64531659 | AA10: 0.64531659 | AB10: 0.64531659 | AC10: 0.64531659 | AD10: 0.64531659 | AE10: 0.64531659 | AF10: 0.64531659 | AG10: 0.64531659 | AH10: 0.64531659 | AI10: 0.64531659 | AJ10: 0.64531659 | AK10: 0.64531659
A11: phiy_cgas_sgas_2 | B11: 0.14751432 | C11: 0.14751432 | D11: 0.14751432 | E11: 0.14751432 | F11: 0.14751432 | G11: 0.14751432 | H11: 0.14751432 | I11: 0.14751432 | J11: 0.14751432 | K11: 0.14751432 | L11: 0.14751432 | M11: 0.14751432 | N11: 0.14751432 | O11: 0.14751432 | P11: 0.14751432 | Q11: 0.14751432 | R11: 0.14751432 | S11: 0.14751432 | T11: 0.14751432 | U11: 0.14751432 | V11: 0.14751432 | W11: 0.14751432 | X11: 0.14751432 | Y11: 0.14751432 | Z11: 0.14751432 | AA11: 0.14751432 | AB11: 0.14751432 | AC11: 0.14751432 | AD11: 0.14751432 | AE11: 0.14751432 | AF11: 0.14751432 | AG11: 0.14751432 | AH11: 0.14751432 | AI11: 0.14751432 | AJ11: 0.14751432 | AK11: 0.14751432
A12: phiy_cgas_sbga_2 | B12: 0.20708639 | C12: 0.20708639 | D12: 0.20708639 | E12: 0.20708639 | F12: 0.20708639 | G12: 0.20708639 | H12: 0.20708639 | I12: 0.20708639 | J12: 0.20708639 | K12: 0.20708639 | L12: 0.20708639 | M12: 0.20708639 | N12: 0.20708639 | O12: 0.20708639 | P12: 0.20708639 | Q12: 0.20708639 | R12: 0.20708639 | S12: 0.20708639 | T12: 0.20708639 | U12: 0.20708639 | V12: 0.20708639 | W12: 0.20708639 | X12: 0.20708639 | Y12: 0.20708639 | Z12: 0.20708639 | AA12: 0.20708639 | AB12: 0.20708639 | AC12: 0.20708639 | AD12: 0.20708639 | AE12: 0.20708639 | AF12: 0.20708639 | AG12: 0.20708639 | AH12: 0.20708639 | AI12: 0.20708639 | AJ12: 0.20708639 | AK12: 0.20708639
... A51: phiy_cote_spub_0 | B51: 0.00010273909 | C51: 0.00010273909 | D51: 0.00010273909 | E51: 0.00010273909 | F51: 0.00010273909 | G51: 0.00010273909 | H51: 0.00010273909 | I51: 0.00010273909 | J51: 0.00010273909 | K51: 0.00010273909 | L51: 0.00010273909 | M51: 0.00010273909 | N51: 0.00010273909 | O51: 0.00010273909 | P51: 0.00010273909 | Q51: 0.00010273909 | R51: 0.00010273909 | S51: 0.00010273909 | T51: 0.00010273909 | U51: 0.00010273909 | V51: 0.00010273909 | W51: 0.00010273909 | X51: 0.00010273909 | Y51: 0.00010273909 | Z51: 0.00010273909 | AA51: 0.00010273909 | AB51: 0.00010273909 | AC51: 0.00010273909 | AD51: 0.00010273909 | AE51: 0.00010273909 | AF51: 0.00010273909 | AG51: 0.00010273909 | AH51: 0.00010273909 | AI51: 0.00010273909 | AJ51: 0.00010273909 | AK51: 0.00010273909

Sheet Transports
A1: _date_ | B1: 42005 | C1: 42370 | D1: 42736 | E1: 43101 | F1: 43466 | G1: 43831 | H1: 44197 | I1: 44562 | J1: 44927 | K1: 45292 | L1: 45658 | M1: 46023 | N1: 46388 | O1: 46753 | P1: 47119 | Q1: 47484 | R1: 47849 | S1: 48214 | T1: 48580 | U1: 48945 | V1: 49310 | W1: 49675 | X1: 50041 | Y1: 50406 | Z1: 50771 | AA1: 51136 | AB1: 51502 | AC1: 51867 | AD1: 52232 | AE1: 52597 | AF1: 52963 | AG1: 53328 | AH1: 53693 | AI1: 54058 | AJ1: 54424 | AK1: 54789
A2: km_traveler_cair_2 | B2: 291099.78 | C2: 295820.99 | D2: 300398.31 | E2: 304939.29 | F2: 309486.94 | G2: 314040.24 | H2: 318658.45 | I2: 323442.27 | J2: 328421.13 | K2: 333574.55 | L2: 338859.98 | M2: 344226.69 | N2: 349622.81 | O2: 354999.02 | P2: 360310.58 | Q2: 365518.72 | R2: 370661.38 | S2: 375836.59 | T2: 381104.41 | U2: 386493 | V2: 392014.59 | W2: 397673.38 | X2: 403469.62 | Y2: 409401.64 | Z2: 415466.73 | AA2: 421661.63 | AB2: 427982.62 | AC2: 434425.61 | AD2: 440986.26 | AE2: 447659.98 | AF2: 454442.11 | AG2: 461327.96 | AH2: 468312.95 | AI2: 475392.66 | AJ2: 482562.95 | AK2: 489820.02
A3: km_trav_auto_ld_2+km_trav_auto_sd_2 | B3: 724102.94 | C3: 715355.49 | D3: 710971.42 | E3: 709498.48 | F3: 709947.49 | G3: 711651.17 | H3: 714212.51 | I3: 717410.6 | J3: 721079.02 | K3: 725085.74 | L3: 729322.26 | M3: 733696.16 | N3: 738125.9 | O3: 742537.43 | P3: 746861.78 | Q3: 751033.63 | R3: 755045.86 | S3: 758941.14 | T3: 762741.97 | U3: 766458.72 | V3: 770096.05 | W3: 773656.44 | X3: 777141.92 | Y3: 780554.97 | Z3: 783898.91 | AA3: 787178.13 | AB3: 790398.23 | AC3: 793566.13 | AD3: 796690.14 | AE3: 799780.09 | AF3: 802847.37 | AG3: 805904.99 | AH3: 808967.65 | AI3: 812051.66 | AJ3: 815174.9 | AK3: 818356.68
A4: km_traveler_sd_2 | B4: 624600.34 | C4: 618861.96 | D4: 616086.94 | E4: 615320.55 | F4: 615893.37 | G4: 617345.72 | H4: 619400.72 | I4: 621904.14 | J4: 624740.22 | K4: 627815.98 | L4: 631054.33 | M4: 634389.27 | N4: 637762.46 | O4: 641120.92 | P4: 644415.42 | Q4: 647599.46 | R4: 650667.15 | S4: 653648.66 | T4: 656561.13 | U4: 659412.6 | V4: 662206.81 | W4: 664945.75 | X4: 667630.94 | Y4: 670264.14 | Z4: 672847.6 | AA4: 675384.29 | AB4: 677878.01 | AC4: 680333.43 | AD4: 682756.21 | AE4: 685153.03 | AF4: 687531.66 | AG4: 689901.02 | AH4: 692271.18 | AI4: 694653.38 | AJ4: 697059.91 | AK4: 699504.11
A5: km_trav_auto_sd_2 | B5: 554271.64 | C5: 547921.8 | D5: 544690.45 | E5: 543539.71 | F5: 543761.34 | G5: 544877.08 | H5: 546602.29 | I5: 548778.6 | J5: 551286.78 | K5: 554032.31 | L5: 556937.57 | M5: 559936.54 | N5: 562971.09 | O5: 565988.51 | P5: 568939.9 | Q5: 571779.04 | R5: 574501.2 | S5: 577137.05 | T5: 579702.89 | U5: 582206.36 | V5: 584650.97 | W5: 587038.66 | X5: 589371.02 | Y5: 591649.95 | Z5: 593877.92 | AA5: 596058.19 | AB5: 598194.86 | AC5: 600292.93 | AD5: 602358.42 | AE5: 604398.34 | AF5: 606420.83 | AG5: 608435.13 | AH5: 610451.63 | AI5: 612481.83 | AJ5: 614538.29 | AK5: 616634.53
A6: km_traveler_croa_2 | B6: 70328.7 | C6: 70321.714 | D6: 70422.251 | E6: 70597.879 | F6: 70825.341 | G6: 71088.354 | H6: 71376.45 | I6: 71684.112 | J6: 72007.76 | K6: 72343.932 | L6: 72689.393 | M6: 73041.122 | N6: 73396.293 | O6: 73752.239 | P6: 74106.43 | Q6: 74456.445 | R6: 74801.305 | S6: 75142.139 | T6: 75480.232 | U6: 75816.213 | V6: 76150.391 | W6: 76482.908 | X6: 76813.819 | Y6: 77143.137 | Z6: 77470.868 | AA6: 77797.019 | AB6: 78121.617 | AC6: 78444.712 | AD6: 78766.388 | AE6: 79086.767 | AF6: 79406.016 | AG6: 79724.355 | AH6: 80042.056 | AI6: 80359.451 | AJ6: 80676.929 | AK6: 80994.935
A7: km_traveler_ld_2 | B7: 275159.81 | C7: 270792.35 | D7: 268629.34 | E7: 267925.6 | F7: 268182.2 | G7: 269066.09 | H7: 270380.45 | I7: 272015.85 | J7: 273889.6 | K7: 275936.38 | L7: 278102.66 | M7: 280342.82 | N7: 282616.53 | O7: 284886.94 | P7: 287119.53 | Q7: 289281.38 | R7: 291368.75 | S7: 293402.59 | T7: 295393.37 | U7: 297345.68 | V7: 299261.42 | W7: 301141.52 | X7: 302986.77 | Y7: 304798.25 | Z7: 306577.46 | AA7: 308326.49 | AB7: 310048.08 | AC7: 311745.62 | AD7: 313423.28 | AE7: 315086 | AF7: 316739.56 | AG7: 318390.62 | AH7: 320046.74 | AI7: 321716.35 | AJ7: 323408.76 | AK7: 325134.06
A8: km_trav_auto_ld_2 | B8: 169831.3 | C8: 167433.69 | D8: 166280.96 | E8: 165958.76 | F8: 166186.15 | G8: 166774.09 | H8: 167610.22 | I8: 168632 | J8: 169792.24 | K8: 171053.44 | L8: 172384.69 | M8: 173759.61 | N8: 175154.82 | O8: 176548.92 | P8: 177921.88 | Q8: 179254.59 | R8: 180544.66 | S8: 181804.09 | T8: 183039.08 | U8: 184252.36 | V8: 185445.08 | W8: 186617.78 | X8: 187770.9 | Y8: 188905.03 | Z8: 190020.99 | AA8: 191119.93 | AB8: 192203.37 | AC8: 193273.19 | AD8: 194331.73 | AE8: 195381.76 | AF8: 196426.54 | AG8: 197469.86 | AH8: 198516.02 | AI8: 199569.83 | AJ8: 200636.61 | AK8: 201722.15
A9: km_traveler_crai_2 | B9: 105328.51 | C9: 106469.68 | D9: 107456.72 | E9: 108342.29 | F9: 109165.34 | G9: 109953.23 | H9: 110720.41 | I9: 111476.07 | J9: 112229.34 | K9: 112985.45 | L9: 113747.47 | M9: 114517.13 | N9: 115295.4 | O9: 116082.8 | P9: 116879.61 | Q9: 117685.97 | R9: 118499.29 | S9: 119317.63 | T9: 120142.3 | U9: 120973.97 | V9: 121813.01 | W9: 122659.55 | X9: 123513.49 | Y9: 124374.54 | Z9: 125242.25 | AA9: 126116.04 | AB9: 126995.22 | AC9: 127878.97 | AD9: 128766.41 | AE9: 129656.57 | AF9: 130548.42 | AG9: 131440.88 | AH9: 132332.84 | AI9: 133223.15 | AJ9: 134110.68 | AK9: 134994.27
A10: km_traveler_cair_0 | B10: 291099.78 | C10: 295997.44 | D10: 300860.61 | E10: 305754.88 | F10: 310735.66 | G10: 315838.96 | H10: 321084.31 | I10: 326479.86 | J10: 332026.96 | K10: 337723.36 | L10: 343565.4 | M10: 349549.33 | N10: 355671.93 | O10: 361930.82 | P10: 368324.44 | Q10: 374851.94 | R10: 381513.03 | S10: 388307.75 | T10: 395236.36 | U10: 402299.23 | V10: 409496.72 | W10: 416829.19 | X10: 424297 | Y10: 431900.48 | Z10: 439640.02 | AA10: 447516.04 | AB10: 455529.1 | AC10: 463679.89 | AD10: 471969.28 | AE10: 480398.31 | AF10: 488968.27 | AG10: 497680.64 | AH10: 506537.12 | AI10: 515539.66 | AJ10: 524690.39 | AK10: 533991.65
A11: km_trav_auto_ld_0+km_trav_auto_sd_0 | B11: 724102.94 | C11: 715470.96 | D11: 711264.17 | E11: 710013.52 | F11: 710740.21 | G11: 712802.83 | H11: 715783.55 | I11: 719409 | J11: 723497.85 | K11: 727927.15 | L11: 732611.22 | M11: 737488.53 | N11: 742513.6 | O11: 747651.94 | P11: 752876.85 | Q11: 758167.34 | R11: 763506.69 | S11: 768881.53 | T11: 774281.06 | U11: 779696.54 | V11: 785120.94 | W11: 790548.57 | X11: 795974.88 | Y11: 801396.29 | Z11: 806810.03 | AA11: 812214.03 | AB11: 817606.83 | AC11: 822987.5 | AD11: 828355.61 | AE11: 833711.09 | AF11: 839054.27 | AG11: 844385.75 | AH11: 849706.42 | AI11: 855017.37 | AJ11: 860319.87 | AK11: 865615.34
A12: km_traveler_sd_0 | B12: 624600.34 | C12: 618939.61 | D12: 616289.44 | E12: 615681.22 | F12: 616451.95 | G12: 618159.91 | H12: 620514.3 | I12: 623323.46 | J12: 626459.54 | K12: 629835.38 | L12: 633389.98 | M12: 637079.36 | N12: 640870.94 | O12: 644739.98 | P12: 648667.38 | Q12: 652638.14 | R12: 656640.39 | S12: 660664.65 | T12: 664703.32 | U12: 668750.31 | V12: 672800.7 | W12: 676850.59 | X12: 680896.84 | Y12: 684937.02 | Z12: 688969.25 | AA12: 692992.16 | AB12: 697004.79 | AC12: 701006.58 | AD12: 704997.26 | AE12: 708976.87 | AF12: 712945.68 | AG12: 716904.19 | AH12: 720853.05 | AI12: 724793.07 | AJ12: 728725.2 | AK12: 732650.46
... A17: km_traveler_crai_0 | B17: 105328.51 | C17: 106459.91 | D17: 107439.19 | E17: 108316.26 | F17: 109128.73 | G17: 109902.85 | H17: 110656.13 | I17: 111399.76 | J17: 112140.59 | K17: 112882.66 | L17: 113628.2 | M17: 114378.45 | N17: 115134.04 | O17: 115895.36 | P17: 116662.67 | Q17: 117436.16 | R17: 118216.02 | S17: 119002.41 | T17: 119795.47 | U17: 120595.32 | V17: 121402.02 | W17: 122215.62 | X17: 123036.12 | Y17: 123863.49 | Z17: 124697.68 | AA17: 125538.64 | AB17: 126386.3 | AC17: 127240.59 | AD17: 128101.43 | AE17: 128968.79 | AF17: 129842.6 | AG17: 130722.83 | AH17: 131609.47 | AI17: 132502.5 | AJ17: 133401.93 | AK17: 134307.77

Sheet Hybrid
A1: _date_ | B1: 42005 | C1: 42370 | D1: 42736 | E1: 43101 | F1: 43466 | G1: 43831 | H1: 44197 | I1: 44562 | J1: 44927 | K1: 45292 | L1: 45658 | M1: 46023 | N1: 46388 | O1: 46753 | P1: 47119 | Q1: 47484 | R1: 47849 | S1: 48214 | T1: 48580 | U1: 48945 | V1: 49310 | W1: 49675 | X1: 50041 | Y1: 50406 | Z1: 50771 | AA1: 51136 | AB1: 51502 | AC1: 51867 | AD1: 52232 | AE1: 52597 | AF1: 52963 | AG1: 53328 | AH1: 53693 | AI1: 54058 | AJ1: 54424 | AK1: 54789
A2: auto_2 | B2: 32317.941 | C2: 31926.455 | D2: 31730.401 | E2: 31664.733 | F2: 31685.152 | G2: 31761.774 | H2: 31876.82 | I2: 32020.398 | J2: 32185.056 | K2: 32364.879 | L2: 32555.008 | M2: 32751.304 | N2: 32950.116 | O2: 33148.124 | P2: 33342.238 | Q2: 33529.533 | R2: 33709.688 | S2: 33884.612 | T2: 34055.315 | U2: 34222.258 | V2: 34385.651 | W2: 34545.604 | X2: 34702.207 | Y2: 34855.571 | Z2: 35005.845 | AA2: 35153.224 | AB2: 35297.96 | AC2: 35440.362 | AD2: 35580.802 | AE2: 35719.72 | AF2: 35857.626 | AG2: 35995.104 | AH2: 36132.812 | AI2: 36271.48 | AJ2: 36411.912 | AK2: 36554.972
A3: auto_cfut_2 | B3: 32271.24 | C3: 31862.032 | D3: 31647.329 | E3: 31562.481 | F3: 31563.392 | G3: 31620.229 | H3: 31715.127 | I3: 31838.038 | J3: 31981.349 | K3: 32138.974 | L3: 32305.854 | M3: 32477.604 | N3: 32650.259 | O3: 32820.093 | P3: 32983.48 | Q3: 33136.779 | R3: 33278.705 | S3: 33409.974 | T3: 33530.266 | U3: 33638.562 | V3: 33733.424 | W3: 33813.135 | X3: 33875.774 | Y3: 33919.241 | Z3: 33941.277 | AA3: 33939.472 | AB3: 33911.279 | AC3: 33854.036 | AD3: 33764.983 | AE3: 33641.306 | AF3: 33480.173 | AG3: 33278.793 | AH3: 33034.477 | AI3: 32744.706 | AJ3: 32407.216 | AK3: 32020.075
A4: auto_cele_2 | B4: 44.765 | C4: 62.431569 | D4: 81.013696 | E4: 100.12298 | F4: 119.55791 | G4: 139.26917 | H4: 159.3444 | I4: 179.94081 | J4: 201.21851 | K4: 223.34991 | L4: 246.53496 | M4: 271.01944 | N4: 297.11658 | O4: 325.23391 | P4: 355.90822 | Q4: 389.85321 | R4: 428.03471 | S4: 471.64532 | T4: 522.01458 | U4: 580.62349 | V4: 649.11914 | W4: 729.32712 | X4: 823.26146 | Y4: 933.13161 | Z4: 1061.3459 | AA4: 1210.5101 | AB4: 1383.4212 | AC4: 1583.0534 | AD4: 1812.5367 | AE4: 2075.1269 | AF4: 2374.165 | AG4: 2713.0263 | AH4: 3095.0588 | AI4: 3523.5113 | AJ4: 4001.4513 | AK4: 4531.6755
A5: auto_cgas_2 | B5: 1.936 | C5: 1.9916056 | D5: 2.0574011 | E5: 2.1285899 | F5: 2.2019794 | G5: 2.2754864 | H5: 2.3479684 | I5: 2.4188941 | J5: 2.4879043 | K5: 2.5547408 | L5: 2.6192081 | M5: 2.6811463 | N5: 2.7404123 | O5: 2.796866 | P5: 2.8503601 | Q5: 2.9007315 | R5: 2.9480014 | S5: 2.9923496 | T5: 3.033862 | U5: 3.0725586 | V5: 3.1084159 | W5: 3.1413797 | X5: 3.17137 | Y5: 3.1982849 | Z5: 3.2220012 | AA5: 3.2423764 | AB5: 3.2592496 | AC5: 3.2724433 | AD5: 3.2817658 | AE5: 3.2870146 | AF5: 3.2879801 | AG5: 3.2844506 | AH5: 3.2762179 | AI5: 3.2630839 | AJ5: 3.2448672 | AK5: 3.2214115
A6: newauto_2 | B6: 1886.229 | C6: 2121.806 | D6: 2286.103 | E6: 2400.5287 | F6: 2480.7808 | G6: 2537.837 | H6: 2581.4774 | I6: 2618.2022 | J6: 2649.6746 | K6: 2676.8483 | L6: 2700.3106 | M6: 2720.3954 | N6: 2737.2597 | O6: 2750.94 | P6: 2761.3918 | Q6: 2768.517 | R6: 2774.6678 | S6: 2782.0126 | T6: 2789.7533 | U6: 2797.3729 | V6: 2804.5969 | W6: 2811.2808 | X6: 2817.3451 | Y6: 2822.7399 | Z6: 2827.4284 | AA6: 2831.3791 | AB6: 2834.5629 | AC6: 2836.9523 | AD6: 2838.522 | AE6: 2839.2497 | AF6: 2839.1172 | AG6: 2838.111 | AH6: 2836.2233 | AI6: 2833.4523 | AJ6: 2829.8021 | AK6: 2825.2831
A7: newauto_cfut_2 | B7: 1868.803 | C7: 2102.1722 | D7: 2264.8333 | E7: 2377.9791 | F7: 2457.1346 | G7: 2513.1323 | H7: 2555.6166 | I7: 2591.0143 | J7: 2620.9791 | K7: 2646.4458 | L7: 2667.9674 | M7: 2685.8239 | N7: 2700.095 | O7: 2710.7103 | P7: 2717.4798 | Q7: 2720.1072 | R7: 2720.6636 | S7: 2721.052 | T7: 2720.2897 | U7: 2717.6551 | V7: 2712.6484 | W7: 2704.8808 | X7: 2694.0114 | Y7: 2679.7142 | Z7: 2661.6653 | AA7: 2639.5392 | AB7: 2613.0118 | AC7: 2581.7664 | AD7: 2545.5027 | AE7: 2503.9477 | AF7: 2456.8677 | AG7: 2404.0812 | AH7: 2345.4727 | AI7: 2281.0058 | AJ7: 2210.7359 | AK7: 2134.8214
A8: newauto_cele_2 | B8: 17.269 | C8: 19.457169 | D8: 21.079389 | E8: 22.349837 | F8: 23.439846 | G8: 24.493574 | H8: 25.645995 | I8: 26.970187 | J8: 28.475336 | K8: 30.180137 | L8: 32.119048 | M8: 34.345876 | N8: 36.937918 | O8: 40.001998 | P8: 43.683666 | Q8: 48.181314 | R8: 53.775634 | S8: 60.731991 | T8: 69.235074 | U8: 79.489497 | V8: 91.720592 | W8: 106.17275 | X8: 123.10742 | Y8: 142.80061 | Z8: 165.53951 | AA8: 191.6181 | AB8: 221.33152 | AC8: 254.96899 | AD8: 292.80546 | AE8: 335.09168 | AF8: 382.04314 | AG8: 433.82787 | AH8: 490.55361 | AI8: 552.25485 | AJ8: 618.8804 | AK8: 690.28232
A9: newauto_cgas_2 | B9: 0.157 | C9: 0.17660558 | D9: 0.1902709 | E9: 0.19977639 | F9: 0.20642632 | G9: 0.21113075 | H9: 0.2146999 | I9: 0.21767369 | J9: 0.22019106 | K9: 0.22233054 | L9: 0.2241386 | M9: 0.22563874 | N9: 0.22683767 | O9: 0.22772947 | P9: 0.22829818 | Q9: 0.22851891 | R9: 0.22856566 | S9: 0.22859828 | T9: 0.22853425 | U9: 0.22831291 | V9: 0.22789229 | W9: 0.22723973 | X9: 0.22632658 | Y9: 0.22512545 | Z9: 0.22360915 | AA9: 0.22175032 | AB9: 0.21952173 | AC9: 0.21689677 | AD9: 0.21385022 | AE9: 0.21035914 | AF9: 0.2064039 | AG9: 0.20196925 | AH9: 0.1970455 | AI9: 0.19162957 | AJ9: 0.18572613 | AK9: 0.17934847
A10: auto_ca_cfut_2 | B10: 7095.7005 | C10: 7141.744 | D10: 7236.2109 | E10: 7362.7565 | F10: 7510.0299 | G10: 7670.2472 | H10: 7838.785 | I10: 8013.1055 | J10: 8191.247 | K10: 8371.6256 | L10: 8552.9219 | M10: 8733.9921 | N10: 8913.8008 | O10: 9091.3684 | P10: 9265.7305 | Q10: 9435.9023 | R10: 9601.6399 | S10: 9763.3044 | T10: 9920.8512 | U10: 10073.962 | V10: 10222.146 | W10: 10364.788 | X10: 10501.176 | Y10: 10630.509 | Z10: 10751.903 | AA10: 10864.388 | AB10: 10966.919 | AC10: 11058.37 | AD10: 11137.548 | AE10: 11203.202 | AF10: 11254.038 | AG10: 11288.736 | AH10: 11305.979 | AI10: 11304.477 | AJ10: 11283.004 | AK10: 11240.43
A11: auto_cb_cfut_2 | B11: 8251.2564 | C11: 8182.7845 | D11: 8168.3356 | E11: 8191.2663 | F11: 8239.913 | G11: 8306.1531 | H11: 8384.9727 | I11: 8473.4298 | J11: 8569.2032 | K11: 8670.3749 | L11: 8775.306 | M11: 8882.5442 | N11: 8990.7536 | O11: 9098.6627 | P11: 9205.023 | Q11: 9308.5738 | R11: 9408.7536 | S11: 9505.5998 | T11: 9598.8301 | U11: 9687.9491 | V11: 9772.3323 | W11: 9851.2702 | X11: 9923.9898 | Y11: 9989.6639 | Z11: 10047.417 | AA11: 10096.329 | AB11: 10135.439 | AC11: 10163.754 | AD11: 10180.258 | AE11: 10183.922 | AF11: 10173.723 | AG11: 10148.662 | AH11: 10107.786 | AI11: 10050.216 | AJ11: 9975.1683 | AK11: 9881.9911
A12: auto_cc_cfut_2 | B12: 6777.6025 | C12: 6646.7629 | D12: 6558.9664 | E12: 6502.0082 | F12: 6467.2622 | G12: 6448.6373 | H12: 6442.2478 | I12: 6445.693 | J12: 6457.0498 | K12: 6474.7042 | L12: 6497.2553 | M12: 6523.4452 | N12: 6552.1089 | O12: 6582.1356 | P12: 6612.4399 | Q12: 6641.9367 | R12: 6670.0211 | S12: 6696.5179 | T12: 6721.0788 | U12: 6743.2423 | V12: 6762.4848 | W12: 6778.2466 | X12: 6789.946 | Y12: 6796.985 | Z12: 6798.7539 | AA12: 6794.6346 | AB12: 6784.0053 | AC12: 6766.2455 | AD12: 6740.7441 | AE12: 6706.9077 | AF12: 6664.1718 | AG12: 6612.0131 | AH12: 6549.9638 | AI12: 6477.6256 | AJ12: 6394.686 | AK12: 6300.9328
... A119: buil_des_0 | B119: 1.1716777 | C119: 1.1716777 | D119: 1.1565402 | E119: 1.1416083 | F119: 1.1268791 | G119: 1.1123494 | H119: 1.0980163 | I119: 1.083877 | J119: 1.0699286 | K119: 1.0561683 | L119: 1.0425934 | M119: 1.0292012 | N119: 1.0159892 | O119: 1.0029547 | P119: 0.99009523 | Q119: 0.97740825 | R119: 0.96489133 | S119: 0.95254204 | T119: 0.940358 | U119: 0.92833689 | V119: 0.91647639 | W119: 0.90477425 | X119: 0.89322823 | Y119: 0.88183615 | Z119: 0.87059586 | AA119: 0.85950523 | AB119: 0.84856218 | AC119: 0.83776466 | AD119: 0.82711064 | AE119: 0.81659814 | AF119: 0.8062252 | AG119: 0.7959899 | AH119: 0.78589034 | AI119: 0.77592465 | AJ119: 0.766091 | AK119: 0.75638758

Sheet Tab-macro
B1: en écart au scénario de référence (%)
B2: ThreeME
B3: 2021 | C3: 2022 | D3: 2023 | E3: 2025 | F3: 2030 | G3: 2050
A4: PIB en volume | B4: =Macro!H2 -> 0.048738572 | C4: =Macro!I2 -> 0.060095859 | D4: =Macro!J2 -> 0.070015107 | E4: =Macro!L2 -> 0.085962983 | F4: =Macro!Q2 -> 0.14265241 | G4: =Macro!AK2 -> 0.14504591
A5: Consommation des ménages | B5: =Macro!H3 -> 0.11251557 | C5: =Macro!I3 -> 0.15121567 | D5: =Macro!J3 -> 0.19244796 | E5: =Macro!L3 -> 0.27910298 | F5: =Macro!Q3 -> 0.58194624 | G5: =Macro!AK3 -> 2.856981
A6: Investissement | B6: =Macro!H4 -> -0.059365516 | C6: =Macro!I4 -> -0.075529889 | D6: =Macro!J4 -> -0.091710764 | E6: =Macro!L4 -> -0.1256935 | F6: =Macro!Q4 -> -0.24634602 | G6: =Macro!AK4 -> -1.1530914
A7: Exportations | B7: =Macro!H5 -> -0.084743657 | C7: =Macro!I5 -> -0.12011476 | D7: =Macro!J5 -> -0.16133863 | E7: =Macro!L5 -> -0.25968197 | F7: =Macro!Q5 -> -0.62273486 | G7: =Macro!AK5 -> -4.3575533
A8: Importations | B8: =Macro!H6 -> -0.081006385 | C8: =Macro!I6 -> -0.093915887 | D8: =Macro!J6 -> -0.10310887 | E8: =Macro!L6 -> -0.11740134 | F8: =Macro!Q6 -> -0.18982161 | G8: =Macro!AK6 -> -0.25427953
A9: Revenu disponible (réel) des ménages | B9: =Macro!H7 -> 0.12157521 | C9: =Macro!I7 -> 0.16017255 | D9: =Macro!J7 -> 0.20029739 | E9: =Macro!L7 -> 0.28453424 | F9: =Macro!Q7 -> 0.59324441 | G9: =Macro!AK7 -> 2.8463131
A10: Taux d'épargne (en pts) | B10: =Macro!H8 -> 0.00802139 | C10: =Macro!I8 -> 0.00792673 | D10: =Macro!J8 -> 0.00694347 | E10: =Macro!L8 -> 0.00480004 | F10: =Macro!Q8 -> 0.0099548 | G10: =Macro!AK8 -> -0.00919449
A11: Prix de la consommation des ménages | B11: =Macro!H9 -> 0.36952058 | C11: =Macro!I9 -> 0.47010293 | D11: =Macro!J9 -> 0.57633973 | E11: =Macro!L9 -> 0.81690358 | F11: =Macro!Q9 -> 1.7507387 | G11: =Macro!AK9 -> 9.4772123
A12: Prix de la production | B12: =Macro!H10 -> 0.16101628 | C12: =Macro!I10 -> 0.22699331 | D12: =Macro!J10 -> 0.30376119 | E12: =Macro!L10 -> 0.48622175 | F12: =Macro!Q10 -> 1.1478252 | G12: =Macro!AK10 -> 7.9308716
A13: Prix de la valeur ajoutée | B13: =Macro!H11 -> -0.11409151 | C13: =Macro!I11 -> -0.099489263 | D13: =Macro!J11 -> -0.068390502 | E13: =Macro!L11 -> 0.021294043 | F13: =Macro!Q11 -> 0.24697079 | G13: =Macro!AK11 -> 4.4747757
A14: Prix des consommations intermédiaires | B14: =Macro!H12 -> 0.44768827 | C14: =Macro!I12 -> 0.56728174 | D14: =Macro!J12 -> 0.69175235 | E14: =Macro!L12 -> 0.97122732 | F14: =Macro!Q12 -> 2.0898956 | G14: =Macro!AK12 -> 11.613078
A15: Prix des exportations | B15: =Macro!H13 -> 0.25431324 | C15: =Macro!I13 -> 0.33938229 | D15: =Macro!J13 -> 0.43168577 | E15: =Macro!L13 -> 0.63899439 | F15: =Macro!Q13 -> 1.4145331 | G15: =Macro!AK13 -> 8.7682091
... A24: Emissions de CO2 | B24: =Macro!H22 -> -1.761206 | C24: =Macro!I22 -> -2.2324391 | D24: =Macro!J22 -> -2.6954212 | E24: =Macro!L22 -> -3.6119939 | F24: =Macro!Q22 -> -6.6014016 | G24: =Macro!AK22 -> -22.746641
B26: % deviation from baseline
B27: ThreeME
B28: 2021 | C28: 2022 | D28: 2023 | E28: 2025 | F28: 2030 | G28: 2050
A29: GDP in volume | B29: =B4 -> 0.048738572 | C29: =C4 -> 0.060095859 | D29: =D4 -> 0.070015107 | E29: =E4 -> 0.085962983 | F29: =F4 -> 0.14265241 | G29: =G4 -> 0.14504591
A30: Household consumption | B30: =B5 -> 0.11251557 | C30: =C5 -> 0.15121567 | D30: =D5 -> 0.19244796 | E30: =E5 -> 0.27910298 | F30: =F5 -> 0.58194624 | G30: =G5 -> 2.856981
A31: Investment | B31: =B6 -> -0.059365516 | C31: =C6 -> -0.075529889 | D31: =D6 -> -0.091710764 | E31: =E6 -> -0.1256935 | F31: =F6 -> -0.24634602 | G31: =G6 -> -1.1530914
A32: Exports | B32: =B7 -> -0.084743657 | C32: =C7 -> -0.12011476 | D32: =D7 -> -0.16133863 | E32: =E7 -> -0.25968197 | F32: =F7 -> -0.62273486 | G32: =G7 -> -4.3575533
A33: Imports | B33: =B8 -> -0.081006385 | C33: =C8 -> -0.093915887 | D33: =D8 -> -0.10310887 | E33: =E8 -> -0.11740134 | F33: =F8 -> -0.18982161 | G33: =G8 -> -0.25427953
A34: Household disposable income (real) | B34: =B9 -> 0.12157521 | C34: =C9 -> 0.16017255 | D34: =D9 -> 0.20029739 | E34: =E9 -> 0.28453424 | F34: =F9 -> 0.59324441 | G34: =G9 -> 2.8463131
A35: Saving rate (in points) | B35: =B10 -> 0.00802139 | C35: =C10 -> 0.00792673 | D35: =D10 -> 0.00694347 | E35: =E10 -> 0.00480004 | F35: =F10 -> 0.0099548 | G35: =G10 -> -0.00919449
A36: Household consumption price index | B36: =B11 -> 0.36952058 | C36: =C11 -> 0.47010293 | D36: =D11 -> 0.57633973 | E36: =E11 -> 0.81690358 | F36: =F11 -> 1.7507387 | G36: =G11 -> 9.4772123
A37: Production price index | B37: =B12 -> 0.16101628 | C37: =C12 -> 0.22699331 | D37: =D12 -> 0.30376119 | E37: =E12 -> 0.48622175 | F37: =F12 -> 1.1478252 | G37: =G12 -> 7.9308716
A38: Added value price index | B38: =B13 -> -0.11409151 | C38: =C13 -> -0.099489263 | D38: =D13 -> -0.068390502 | E38: =E13 -> 0.021294043 | F38: =F13 -> 0.24697079 | G38: =G13 -> 4.4747757
A39: Intermediate consumption price index | B39: =B14 -> 0.44768827 | C39: =C14 -> 0.56728174 | D39: =D14 -> 0.69175235 | E39: =E14 -> 0.97122732 | F39: =F14 -> 2.0898956 | G39: =G14 -> 11.613078
A40: Export price index | B40: =B15 -> 0.25431324 | C40: =C15 -> 0.33938229 | D40: =D15 -> 0.43168577 | E40: =E15 -> 0.63899439 | F40: =F15 -> 1.4145331 | G40: =G15 -> 8.7682091
... A49: CO2 emissions | B49: =B24 -> -1.761206 | C49: =C24 -> -2.2324391 | D49: =D24 -> -2.6954212 | E49: =E24 -> -3.6119939 | F49: =F24 -> -6.6014016 | G49: =G24 -> -22.746641

Sheet Tab-baseline
C1: 8 | D1: 9 | E1: 10 | F1: 12 | G1: 17 | H1: 37
C2: ThreeME
C3: 2021 | D3: 2022 | E3: 2023 | F3: 2025 | G3: 2030 | H3: 2050
A4: Taux de croissance du PIB | B4: @pch(gdp_0) | C4: =VLOOKUP($B4,Baseline!$A$1:$AT$50,C$1,FALSE) -> 0.011252093 | D4: =VLOOKUP($B4,Baseline!$A$1:$AT$50,D$1,FALSE) -> 0.011375473 | E4: =VLOOKUP($B4,Baseline!$A$1:$AT$50,E$1,FALSE) -> 0.011476237 | F4: =VLOOKUP($B4,Baseline!$A$1:$AT$50,F$1,FALSE) -> 0.011614092 | G4: =VLOOKUP($B4,Baseline!$A$1:$AT$50,G$1,FALSE) -> 0.011726136 | H4: =VLOOKUP($B4,Baseline!$A$1:$AT$50,H$1,FALSE) -> 0.011660368
A5: Prix de la consommation des ménages | B5: @pch(pch_0) | C5: =VLOOKUP($B5,Baseline!$A$1:$AT$50,C$1,FALSE) -> 0.019635207 | D5: =VLOOKUP($B5,Baseline!$A$1:$AT$50,D$1,FALSE) -> 0.019668198 | E5: =VLOOKUP($B5,Baseline!$A$1:$AT$50,E$1,FALSE) -> 0.019714317 | F5: =VLOOKUP($B5,Baseline!$A$1:$AT$50,F$1,FALSE) -> 0.019828898 | G5: =VLOOKUP($B5,Baseline!$A$1:$AT$50,G$1,FALSE) -> 0.020129185 | H5: =VLOOKUP($B5,Baseline!$A$1:$AT$50,H$1,FALSE) -> 0.020366929
A6: Taux de chômage | B6: unr_0 | C6: =VLOOKUP($B6,Baseline!$A$1:$AT$50,C$1,FALSE) -> 0.14415905 | D6: =VLOOKUP($B6,Baseline!$A$1:$AT$50,D$1,FALSE) -> 0.14419204 | E6: =VLOOKUP($B6,Baseline!$A$1:$AT$50,E$1,FALSE) -> 0.14412979 | F6: =VLOOKUP($B6,Baseline!$A$1:$AT$50,F$1,FALSE) -> 0.14381068 | G6: =VLOOKUP($B6,Baseline!$A$1:$AT$50,G$1,FALSE) -> 0.14261895 | H6: =VLOOKUP($B6,Baseline!$A$1:$AT$50,H$1,FALSE) -> 0.13887513
A7: Dette publique (en pts de PIB) | B7: rdebt_g_val_0 | C7: =VLOOKUP($B7,Baseline!$A$1:$AT$50,C$1,FALSE) -> 0.97004802 | D7: =VLOOKUP($B7,Baseline!$A$1:$AT$50,D$1,FALSE) -> 0.97258712 | E7: =VLOOKUP($B7,Baseline!$A$1:$AT$50,E$1,FALSE) -> 0.97503146 | F7: =VLOOKUP($B7,Baseline!$A$1:$AT$50,F$1,FALSE) -> 0.97946806 | G7: =VLOOKUP($B7,Baseline!$A$1:$AT$50,G$1,FALSE) -> 0.98723105 | H7: =VLOOKUP($B7,Baseline!$A$1:$AT$50,H$1,FALSE) -> 0.97986829
A8: Solde primaire public (en pts de PIB) | B8: rbal_g_prim_val_0 | C8: =VLOOKUP($B8,Baseline!$A$1:$AT$50,C$1,FALSE) -> -0.011460251 | D8: =VLOOKUP($B8,Baseline!$A$1:$AT$50,D$1,FALSE) -> -0.011637088 | E8: =VLOOKUP($B8,Baseline!$A$1:$AT$50,E$1,FALSE) -> -0.011732352 | F8: =VLOOKUP($B8,Baseline!$A$1:$AT$50,F$1,FALSE) -> -0.011733133 | G8: =VLOOKUP($B8,Baseline!$A$1:$AT$50,G$1,FALSE) -> -0.01117748 | H8: =VLOOKUP($B8,Baseline!$A$1:$AT$50,H$1,FALSE) -> -0.0084911301
A9: Balance commerciale (en pts de PIB) | B9: rbal_trade_val_0 | C9: =VLOOKUP($B9,Baseline!$A$1:$AT$50,C$1,FALSE) -> -0.01277292 | D9: =VLOOKUP($B9,Baseline!$A$1:$AT$50,D$1,FALSE) -> -0.012784958 | E9: =VLOOKUP($B9,Baseline!$A$1:$AT$50,E$1,FALSE) -> -0.012769054 | F9: =VLOOKUP($B9,Baseline!$A$1:$AT$50,F$1,FALSE) -> -0.012698369 | G9: =VLOOKUP($B9,Baseline!$A$1:$AT$50,G$1,FALSE) -> -0.012442025 | H9: =VLOOKUP($B9,Baseline!$A$1:$AT$50,H$1,FALSE) -> -0.011138905
A10: Emissions de CO2 (en Kt CO2) | B10: ems_co2_0 | C10: =VLOOKUP($B10,Baseline!$A$1:$AT$50,C$1,FALSE) -> 362.04263 | D10: =VLOOKUP($B10,Baseline!$A$1:$AT$50,D$1,FALSE) -> 364.51423 | E10: =VLOOKUP($B10,Baseline!$A$1:$AT$50,E$1,FALSE) -> 367.1103 | F10: =VLOOKUP($B10,Baseline!$A$1:$AT$50,F$1,FALSE) -> 372.57878 | G10: =VLOOKUP($B10,Baseline!$A$1:$AT$50,G$1,FALSE) -> 387.32088 | H10: =VLOOKUP($B10,Baseline!$A$1:$AT$50,H$1,FALSE) -> 457.40889
C33: ThreeME
C34: 2021 | D34: 2022 | E34: 2023 | F34: 2025 | G34: 2030 | H34: 2050
A35: GDP growth rate | C35: =C4 -> 0.011252093 | D35: =D4 -> 0.011375473 | E35: =E4 -> 0.011476237 | F35: =F4 -> 0.011614092 | G35: =G4 -> 0.011726136 | H35: =H4 -> 0.011660368
A36: Household consumption price | C36: =C5 -> 0.019635207 | D36: =D5 -> 0.019668198 | E36: =E5 -> 0.019714317 | F36: =F5 -> 0.019828898 | G36: =G5 -> 0.020129185 | H36: =H5 -> 0.020366929
A37: unemployment rate | C37: =C6 -> 0.14415905 | D37: =D6 -> 0.14419204 | E37: =E6 -> 0.14412979 | F37: =F6 -> 0.14381068 | G37: =G6 -> 0.14261895 | H37: =H6 -> 0.13887513
A38: Public debt (in points of GDP) | C38: =C7 -> 0.97004802 | D38: =D7 -> 0.97258712 | E38: =E7 -> 0.97503146 | F38: =F7 -> 0.97946806 | G38: =G7 -> 0.98723105 | H38: =H7 -> 0.97986829
A39: Public budget balance (in points of GDP) | C39: =C8 -> -0.011460251 | D39: =D8 -> -0.011637088 | E39: =E8 -> -0.011732352 | F39: =F8 -> -0.011733133 | G39: =G8 -> -0.01117748 | H39: =H8 -> -0.0084911301
A40: Trade balance (in points of GDP) | C40: =C9 -> -0.01277292 | D40: =D9 -> -0.012784958 | E40: =E9 -> -0.012769054 | F40: =F9 -> -0.012698369 | G40: =G9 -> -0.012442025 | H40: =H9 -> -0.011138905
A41: CO2 emissions (In Kt og CO2) | C41: =C10 -> 362.04263 | D41: =D10 -> 364.51423 | E41: =E10 -> 367.1103 | F41: =F10 -> 372.57878 | G41: =G10 -> 387.32088 | H41: =H10 -> 457.40889

Sheet Macro
A1: _date_ | B1: 42005 | C1: 42370 | D1: 42736 | E1: 43101 | F1: 43466 | G1: 43831 | H1: 44197 | I1: 44562 | J1: 44927 | K1: 45292 | L1: 45658 | M1: 46023 | N1: 46388 | O1: 46753 | P1: 47119 | Q1: 47484 | R1: 47849 | S1: 48214 | T1: 48580 | U1: 48945 | V1: 49310 | W1: 49675 | X1: 50041 | Y1: 50406 | Z1: 50771 | AA1: 51136 | AB1: 51502 | AC1: 51867 | AD1: 52232 | AE1: 52597 | AF1: 52963 | AG1: 53328 | AH1: 53693 | AI1: 54058 | AJ1: 54424 | AK1: 54789
A2: 100*(gdp_2/gdp_0-1) | B2: 0 | C2: 0.0033641188 | D2: 0.009082291 | E2: 0.016620143 | F2: 0.02577382 | G2: 0.036754288 | H2: 0.048738572 | I2: 0.060095859 | J2: 0.070015107 | K2: 0.078444433 | L2: 0.085962983 | M2: 0.093517875 | N2: 0.10215197 | O2: 0.11279884 | P2: 0.12615999 | Q2: 0.14265241 | R2: 0.16135001 | S2: 0.18024891 | T2: 0.19776241 | U2: 0.21281822 | V2: 0.22488163 | W2: 0.2338464 | X2: 0.23987807 | Y2: 0.24327291 | Z2: 0.24435604 | AA2: 0.24341917 | AB2: 0.24069009 | AC2: 0.23632354 | AD2: 0.23040664 | AE2: 0.22297109 | AF2: 0.21400903 | AG2: 0.20348859 | AH2: 0.1913679 | AI2: 0.17760609 | AJ2: 0.16217138 | AK2: 0.14504591
A3: 100*(ch_2/ch_0-1) | B3: 0 | C3: 0.0040055393 | D3: 0.013727548 | E3: 0.02935883 | F3: 0.050742053 | G3: 0.078457722 | H3: 0.11251557 | I3: 0.15121567 | J3: 0.19244796 | K3: 0.23501692 | L3: 0.27910298 | M3: 0.32599045 | N3: 0.37759555 | O3: 0.43606676 | P3: 0.50352806 | Q3: 0.58194624 | R3: 0.67185042 | S3: 0.77157129 | T3: 0.87851096 | U3: 0.99028322 | V3: 1.1052365 | W3: 1.2224212 | X3: 1.3413526 | Y3: 1.4617673 | Z3: 1.5834438 | AA3: 1.7060966 | AB3: 1.8293274 | AC3: 1.9526152 | AD3: 2.0753324 | AE3: 2.1967726 | AF3: 2.3161833 | AG3: 2.4327994 | AH3: 2.5458709 | AI3: 2.6546858 | AJ3: 2.7585865 | AK3: 2.856981
A4: 100*(i_2/i_0-1) | B4: 0 | C4: -0.0046338231 | D4: -0.011432338 | E4: -0.019738649 | F4: -0.03009929 | G4: -0.043591279 | H4: -0.059365516 | I4: -0.075529889 | J4: -0.091710764 | K4: -0.10825266 | L4: -0.1256935 | M4: -0.14456916 | N4: -0.16541452 | O4: -0.18882793 | P4: -0.21552383 | Q4: -0.24634602 | R4: -0.28087374 | S4: -0.31788339 | T4: -0.35702665 | U4: -0.3982861 | V4: -0.44160759 | W4: -0.48676438 | X4: -0.53337375 | Y4: -0.58097564 | Z4: -0.62911538 | AA4: -0.67740527 | AB4: -0.72555933 | AC4: -0.77340526 | AD4: -0.82088033 | AE4: -0.8680177 | AF4: -0.91492806 | AG4: -0.96178028 | AH4: -1.0087835 | AI4: -1.0561717 | AJ4: -1.104191 | AK4: -1.1530914
A5: 100*(x_2/x_0-1) | B5: 0 | C5: -0.0025491856 | D5: -0.0085910817 | E5: -0.018818883 | F5: -0.034155167 | G5: -0.055920622 | H5: -0.084743657 | I5: -0.12011476 | J5: -0.16133863 | K5: -0.20791035 | L5: -0.25968197 | M5: -0.31694184 | N5: -0.38044515 | O5: -0.45141089 | P5: -0.53149317 | Q5: -0.62273486 | R5: -0.72664833 | S5: -0.84365631 | T5: -0.9736266 | U5: -1.1160905 | V5: -1.2703569 | W5: -1.4355883 | X5: -1.6108574 | Y5: -1.7951871 | Z5: -1.9875784 | AA5: -2.1870277 | AB5: -2.3925368 | AC5: -2.6031189 | AD5: -2.8178017 | AE5: -3.0356292 | AF5: -3.2556635 | AG5: -3.476986 | AH5: -3.6986992 | AI5: -3.9199277 | AJ5: -4.1398207 | AK5: -4.3575533
A6: 100*(m_2/m_0-1) | B6: 0 | C6: -0.009707453 | D6: -0.02168718 | E6: -0.034010922 | F6: -0.047603819 | G6: -0.064181485 | H6: -0.081006385 | I6: -0.093915887 | J6: -0.10310887 | K6: -0.1103307 | L6: -0.11740134 | M6: -0.12577707 | N6: -0.13653471 | O6: -0.15045687 | P6: -0.16809946 | Q6: -0.18982161 | R6: -0.21270705 | S6: -0.23262719 | T6: -0.24862889 | U6: -0.2610023 | V6: -0.27025332 | W6: -0.27677431 | X6: -0.28082105 | Y6: -0.28258266 | Z6: -0.28225408 | AA6: -0.2800842 | AB6: -0.27639747 | AC6: -0.27159551 | AD6: -0.26614581 | AE6: -0.26056376 | AF6: -0.255392 | AG6: -0.25118047 | AH6: -0.24846851 | AI6: -0.24777016 | AJ6: -0.2495629 | AK6: -0.25427953
A7: 100*((dispinc_at_val_2/pch_2)/(dispinc_at_val_0/pch_0)-1) | B7: 0 | C7: 0.0053999497 | D7: 0.017255271 | E7: 0.034772077 | F7: 0.057523276 | G7: 0.086540382 | H7: 0.12157521 | I7: 0.16017255 | J7: 0.20029739 | K7: 0.24145168 | L7: 0.28453424 | M7: 0.33122178 | N7: 0.38349257 | O7: 0.4433508 | P7: 0.51269019 | Q7: 0.59324441 | R7: 0.68488719 | S7: 0.78515264 | T7: 0.89132881 | U7: 1.0014622 | V7: 1.1144572 | W7: 1.2297586 | X7: 1.3470636 | Y7: 1.4661316 | Z7: 1.5866781 | AA7: 1.7083231 | AB7: 1.8305774 | AC7: 1.9528498 | AD7: 2.0744675 | AE7: 2.1947049 | AF7: 2.3128106 | AG7: 2.4280347 | AH7: 2.5396519 | AI7: 2.646979 | AJ7: 2.7493879 | AK7: 2.8463131
A8: 100*(rsav_h_val_2-rsav_h_val_0) | B8: 0 | C8: 0.00123598 | D8: 0.00312679 | E8: 0.00479765 | F8: 0.00600868 | G8: 0.00715944 | H8: 0.00802139 | I8: 0.00792673 | J8: 0.00694347 | K8: 0.00568948 | L8: 0.00480004 | M8: 0.00462108 | N8: 0.00520655 | O8: 0.0064273 | P8: 0.00807906 | Q8: 0.0099548 | R8: 0.01147633 | S8: 0.01194392 | T8: 0.01126075 | U8: 0.00981038 | V8: 0.00808293 | W8: 0.00642473 | X8: 0.00499472 | Y8: 0.00381257 | Z8: 0.00282212 | AA8: 0.00194051 | AB8: 0.00108822 | AC8: 0.00020387 | AD8: -0.00075109 | AE8: -0.00179339 | AF8: -0.00292208 | AG8: -0.00412348 | AH8: -0.00537616 | AI8: -0.00665524 | AJ8: -0.00793568 | AK8: -0.00919449
A9: 100*(pch_2/pch_0-1) | B9: 0 | C9: 0.035644813 | D9: 0.074511753 | E9: 0.12266123 | F9: 0.18626679 | G9: 0.27150893 | H9: 0.36952058 | I9: 0.47010293 | J9: 0.57633973 | K9: 0.69099154 | L9: 0.81690358 | M9: 0.95734259 | N9: 1.1161685 | O9: 1.2978717 | P9: 1.5075322 | Q9: 1.7507387 | R9: 2.0224971 | S9: 2.314761 | T9: 2.6276678 | U9: 2.9604916 | V9: 3.3118777 | W9: 3.680096 | X9: 4.0632206 | Y9: 4.4592381 | Z9: 4.8661039 | AA9: 5.2817691 | AB9: 5.7041902 | AC9: 6.1313319 | AD9: 6.5611674 | AE9: 6.9916765 | AF9: 7.4208474 | AG9: 7.846678 | AH9: 8.2671806 | AI9: 8.6803884 | AJ9: 9.0843642 | AK9: 9.4772123
A10: 100*(py_2/py_0-1) | B10: 0 | C10: 0.0058105778 | D10: 0.0174092 | E10: 0.036601329 | F10: 0.065554013 | G10: 0.10680856 | H10: 0.16101628 | I10: 0.22699331 | J10: 0.30376119 | K10: 0.39035097 | L10: 0.48622175 | M10: 0.59162577 | N10: 0.70778923 | O10: 0.83694583 | P10: 0.98227978 | Q10: 1.1478252 | R10: 1.336419 | S10: 1.5490139 | T10: 1.7858319 | U10: 2.0461512 | V10: 2.3285825 | W10: 2.6313652 | X10: 2.9525728 | Y10: 3.2902296 | Z10: 3.6423653 | AA10: 4.0070351 | AB10: 4.3823223 | AC10: 4.7663351 | AD10: 5.1572009 | AE10: 5.5530621 | AF10: 5.9520746 | AG10: 6.3524065 | AH10: 6.7522404 | AI10: 7.1497764 | AJ10: 7.5432368 | AK10: 7.9308716
A11: 100*(pva_2/pva_0-1) | B11: 0 | C11: -0.029375201 | D11: -0.052075455 | E11: -0.070848407 | F11: -0.088333193 | G11: -0.10681034 | H11: -0.11409151 | I11: -0.099489263 | J11: -0.068390502 | K11: -0.026412005 | L11: 0.021294043 | M11: 0.070585526 | N11: 0.11861257 | O11: 0.1639013 | P11: 0.2063175 | Q11: 0.24697079 | R11: 0.29877485 | S11: 0.37525907 | T11: 0.47735263 | U11: 0.60458246 | V11: 0.75553243 | W11: 0.92828093 | X11: 1.1206934 | Y11: 1.3305874 | Z11: 1.5558079 | AA11: 1.7942545 | AB11: 2.0438829 | AC11: 2.3026966 | AD11: 2.5687382 | AE11: 2.8400808 | AF11: 3.1148234 | AG11: 3.3910889 | AH11: 3.6670247 | AI11: 3.9408062 | AJ11: 4.210641 | AK11: 4.4747757
A12: 100*(pci_2/pci_0-1) | B12: 0 | C12: 0.042458743 | D12: 0.08977868 | E12: 0.14851579 | F12: 0.22585094 | G12: 0.32935999 | H12: 0.44768827 | I12: 0.56728174 | J12: 0.69175235 | K12: 0.82497564 | L12: 0.97122732 | M12: 1.1353593 | N12: 1.3228774 | O12: 1.5399254 | P12: 1.7932093 | Q12: 2.0898956 | R12: 2.4223556 | S12: 2.7784097 | T12: 3.1575395 | U12: 3.5587584 | V12: 3.9806984 | W12: 4.4217609 | X12: 4.8802303 | Y12: 5.3543406 | Z12: 5.8423079 | AA12: 6.342344 | AB12: 6.8526602 | AC12: 7.3714682 | AD12: 7.8969785 | AE12: 8.4274013 | AF12: 8.9609465 | AG12: 9.4958245 | AH12: 10.03025 | AI12: 10.562443 | AJ12: 11.090636 | AK12: 11.613078
... A26: 100*ds_0/gdp_0*(ds_2/ds_0-1) | B26: 0 | C26: 0 | D26: 0 | E26: 0 | F26: 0 | G26: 0 | H26: 0 | I26: 0 | J26: 0 | K26: 0 | L26: 0 | M26: 0 | N26: 0 | O26: 0 | P26: 0 | Q26: 0 | R26: 0 | S26: 0 | T26: 0 | U26: 0 | V26: 0 | W26: 0 | X26: 0 | Y26: 0 | Z26: 0 | AA26: 0 | AB26: 0 | AC26: 0 | AD26: 0 | AE26: 0 | AF26: 0 | AG26: 0 | AH26: 0 | AI26: 0 | AJ26: 0 | AK26: 0

Sheet Baseline
A1: @date | B1: 42005 | C1: 42370 | D1: 42736 | E1: 43101 | F1: 43466 | G1: 43831 | H1: 44197 | I1: 44562 | J1: 44927 | K1: 45292 | L1: 45658 | M1: 46023 | N1: 46388 | O1: 46753 | P1: 47119 | Q1: 47484 | R1: 47849 | S1: 48214 | T1: 48580 | U1: 48945 | V1: 49310 | W1: 49675 | X1: 50041 | Y1: 50406 | Z1: 50771 | AA1: 51136 | AB1: 51502 | AC1: 51867 | AD1: 52232 | AE1: 52597 | AF1: 52963 | AG1: 53328 | AH1: 53693 | AI1: 54058 | AJ1: 54424 | AK1: 54789
A2: @pch(gdp_0) | B2: 0.0115225 | C2: 0.010855574 | D2: 0.010728383 | E2: 0.010808991 | F2: 0.010953896 | G2: 0.011108712 | H2: 0.011252093 | I2: 0.011375473 | J2: 0.011476237 | K2: 0.011554988 | L2: 0.011614092 | M2: 0.011656738 | N2: 0.011686314 | O2: 0.011706003 | P2: 0.011718548 | Q2: 0.011726136 | R2: 0.011730408 | S2: 0.011732513 | T2: 0.011733198 | U2: 0.011732909 | V2: 0.011731877 | W2: 0.011730202 | X2: 0.011727914 | Y2: 0.011725016 | Z2: 0.011721512 | AA2: 0.011717423 | AB2: 0.011712793 | AC2: 0.011707688 | AD2: 0.011702187 | AE2: 0.011696385 | AF2: 0.01169038 | AG2: 0.011684266 | AH2: 0.011678133 | AI2: 0.011672062 | AJ2: 0.011666121 | AK2: 0.011660368
A3: @pch(pch_0) | B3: 0.02 | C3: 0.019898733 | D3: 0.019777199 | E3: 0.01968545 | F3: 0.019635261 | G3: 0.019621524 | H3: 0.019635207 | I3: 0.019668198 | J3: 0.019714317 | K3: 0.019769025 | L3: 0.019828898 | M3: 0.019891268 | N3: 0.019953995 | O3: 0.020015379 | P3: 0.0200741 | Q3: 0.020129185 | R3: 0.020179956 | S3: 0.020225984 | T3: 0.020267047 | U3: 0.020303071 | V3: 0.020334108 | W3: 0.020360285 | X3: 0.020381796 | Y3: 0.020398879 | Z3: 0.020411798 | AA3: 0.020420845 | AB3: 0.020426324 | AC3: 0.020428547 | AD3: 0.020427834 | AE3: 0.020424509 | AF3: 0.020418888 | AG3: 0.020411284 | AH3: 0.020402003 | AI3: 0.020391336 | AJ3: 0.020379557 | AK3: 0.020366929
A4: unr_0 | B4: 0.14211338 | C4: 0.14239253 | D4: 0.14284801 | E4: 0.14332745 | F4: 0.14372958 | G4: 0.14400924 | H4: 0.14415905 | I4: 0.14419204 | J4: 0.14412979 | K4: 0.14399556 | L4: 0.14381068 | M4: 0.14359297 | N4: 0.14335631 | O4: 0.14311086 | P4: 0.1428636 | Q4: 0.14261895 | R4: 0.14237946 | S4: 0.14214634 | T4: 0.14191994 | U4: 0.14170015 | V4: 0.1414866 | W4: 0.14127888 | X4: 0.1410766 | Y4: 0.14087947 | Z4: 0.14068727 | AA4: 0.14049986 | AB4: 0.14031716 | AC4: 0.14013913 | AD4: 0.13996573 | AE4: 0.13979691 | AF4: 0.13963262 | AG4: 0.13947277 | AH4: 0.13931725 | AI4: 0.13916591 | AJ4: 0.13901859 | AK4: 0.13887513
A5: rdebt_g_val_0 | B5: 0.958 | C5: 0.95897527 | D5: 0.96058315 | E5: 0.96263011 | F5: 0.96497124 | G5: 0.96748013 | H5: 0.97004802 | I5: 0.97258712 | J5: 0.97503146 | K5: 0.97733497 | L5: 0.97946806 | M5: 0.98141365 | N5: 0.98316355 | O5: 0.98471534 | P5: 0.98607014 | Q5: 0.98723105 | R5: 0.98820223 | S5: 0.98898846 | T5: 0.98959493 | U5: 0.99002733 | V5: 0.99029187 | W5: 0.99039536 | X5: 0.9903453 | Y5: 0.99014987 | Z5: 0.98981781 | AA5: 0.98935841 | AB5: 0.98878129 | AC5: 0.98809631 | AD5: 0.98731335 | AE5: 0.98644221 | AF5: 0.98549246 | AG5: 0.98447326 | AH5: 0.98339337 | AI5: 0.98226095 | AJ5: 0.9810836 | AK5: 0.97986829
A6: rbal_g_prim_val_0 | B6: -0.0092851685 | C6: -0.0095358179 | D6: -0.0099463987 | E6: -0.010405279 | F6: -0.01083516 | G6: -0.011192718 | H6: -0.011460251 | I6: -0.011637088 | J6: -0.011732352 | K6: -0.011759577 | L6: -0.011733133 | M6: -0.011666162 | N6: -0.011569623 | O6: -0.011452068 | P6: -0.011319842 | Q6: -0.01117748 | R6: -0.011028163 | S6: -0.010874133 | T6: -0.010717037 | U6: -0.010558181 | V6: -0.01039869 | W6: -0.010239614 | X6: -0.010081963 | Y6: -0.0099267198 | Z6: -0.0097748208 | AA6: -0.0096271357 | AB6: -0.0094844413 | AC6: -0.0093473998 | AD6: -0.0092165451 | AE6: -0.0090922748 | AF6: -0.0089748502 | AG6: -0.0088644027 | AH6: -0.0087609443 | AI6: -0.0086643811 | AJ6: -0.0085745292 | AK6: -0.0084911301
A7: rbal_trade_val_0 | B7: -0.01081433 | C7: -0.011339149 | D7: -0.011886849 | E7: -0.012303141 | F7: -0.012567896 | G7: -0.012711325 | H7: -0.01277292 | I7: -0.012784958 | J7: -0.012769054 | K7: -0.012737939 | L7: -0.012698369 | M7: -0.012653596 | N7: -0.012605063 | O7: -0.0125534 | P7: -0.012498953 | Q7: -0.012442025 | R7: -0.012382953 | S7: -0.012322107 | T7: -0.012259858 | U7: -0.012196549 | V7: -0.012132469 | W7: -0.012067848 | X7: -0.012002849 | Y7: -0.011937583 | Z7: -0.011872113 | AA7: -0.011806466 | AB7: -0.01174065 | AC7: -0.011674654 | AD7: -0.011608464 | AE7: -0.011542065 | AF7: -0.011475444 | AG7: -0.011408593 | AH7: -0.011341509 | AI7: -0.011274195 | AJ7: -0.011206656 | AK7: -0.011138905
A8: ems_co2_0 | B8: 350.29271 | C8: 352.43131 | D8: 354.06052 | E8: 355.7321 | F8: 357.61599 | G8: 359.72996 | H8: 362.04263 | I8: 364.51423 | J8: 367.1103 | K8: 369.80468 | L8: 372.57878 | M8: 375.41988 | N8: 378.31942 | O8: 381.27176 | P8: 384.27304 | Q8: 387.32088 | R8: 390.41383 | S8: 393.55096 | T8: 396.73175 | U8: 399.95582 | V8: 403.22297 | W8: 406.53308 | X8: 409.88608 | Y8: 413.28196 | Z8: 416.72071 | AA8: 420.20234 | AB8: 423.72691 | AC8: 427.29449 | AD8: 430.90523 | AE8: 434.55929 | AF8: 438.25689 | AG8: 441.9983 | AH8: 445.78382 | AI8: 449.61382 | AJ8: 453.48869 | AK8: 457.40889
A9: pop | B9: 66422.5 | C9: 66588.556 | D9: 66755.028 | E9: 66921.915 | F9: 67089.22 | G9: 67256.943 | H9: 67425.085 | I9: 67593.648 | J9: 67762.632 | K9: 67932.039 | L9: 68101.869 | M9: 68272.124 | N9: 68442.804 | O9: 68613.911 | P9: 68785.446 | Q9: 68957.409 | R9: 69129.803 | S9: 69302.627 | T9: 69475.884 | U9: 69649.574 | V9: 69823.698 | W9: 69998.257 | X9: 70173.252 | Y9: 70348.686 | Z9: 70524.557 | AA9: 70700.869 | AB9: 70877.621 | AC9: 71054.815 | AD9: 71232.452 | AE9: 71410.533 | AF9: 71589.059 | AG9: 71768.032 | AH9: 71947.452 | AI9: 72127.321 | AJ9: 72307.639 | AK9: 72488.408
A10: gdp_0 | B10: 2196558.3 | C10: 2220403.2 | D10: 2244224.5 | E10: 2268482.3 | F10: 2293331 | G10: 2318807 | H10: 2344898.4 | I10: 2371572.7 | J10: 2398789.5 | K10: 2426507.4 | L10: 2454689.1 | M10: 2483302.8 | N10: 2512323.4 | O10: 2541732.7 | P10: 2571518.1 | Q10: 2601672.1 | R10: 2632190.8 | S10: 2663073 | T10: 2694319.4 | U10: 2725931.6 | V10: 2757911.9 | W10: 2790262.7 | X10: 2822986.7 | Y10: 2856086.2 | Z10: 2889563.9 | AA10: 2923422.1 | AB10: 2957663.6 | AC10: 2992291 | AD10: 3027307.3 | AE10: 3062715.9 | AF10: 3098520.2 | AG10: 3134724.1 | AH10: 3171331.8 | AI10: 3208347.8 | AJ10: 3245776.8 | AK10: 3283623.8
A11: pch_0 | B11: 1 | C11: 1.0198987 | D11: 1.0400695 | E11: 1.0605437 | F11: 1.0813678 | G11: 1.1025858 | H11: 1.1242353 | I11: 1.146347 | J11: 1.1689465 | K11: 1.1920554 | L11: 1.2156926 | M11: 1.2398742 | N11: 1.2646147 | O11: 1.2899264 | P11: 1.3158205 | Q11: 1.3423069 | R11: 1.3693946 | S11: 1.397092 | T11: 1.4254069 | U11: 1.454347 | V11: 1.4839199 | W11: 1.5141329 | X11: 1.5449937 | Y11: 1.5765098 | Z11: 1.6086892 | AA11: 1.64154 | AB11: 1.6750706 | AC11: 1.7092899 | AD11: 1.744207 | AE11: 1.7798315 | AF11: 1.8161737 | AG11: 1.8532442 | AH11: 1.891054 | AI11: 1.9296152 | AJ11: 1.9689399 | AK11: 2.0090411
A12: ems_ch_co2_0 | B12: 119.49049 | C12: 119.25476 | D12: 118.5914 | E12: 117.94146 | F12: 117.43342 | G12: 117.07744 | H12: 116.84707 | I12: 116.7106 | J12: 116.64129 | K12: 116.61924 | L12: 116.63059 | M12: 116.66599 | N12: 116.71922 | O12: 116.78609 | P12: 116.86366 | Q12: 116.94993 | R12: 117.04357 | S12: 117.1436 | T12: 117.24929 | U12: 117.36001 | V12: 117.4753 | W12: 117.59478 | X12: 117.71816 | Y12: 117.84518 | Z12: 117.97565 | AA12: 118.10939 | AB12: 118.24629 | AC12: 118.38623 | AD12: 118.52913 | AE12: 118.67492 | AF12: 118.82357 | AG12: 118.97505 | AH12: 119.12935 | AI12: 119.28646 | AJ12: 119.44639 | AK12: 119.60915
... A28: ems_co2_cote_0 | B28: 17.86536 | C28: 18.049747 | D28: 18.22732 | E28: 18.406258 | F28: 18.589806 | G28: 18.778708 | H28: 18.972724 | I28: 19.17133 | J28: 19.373997 | K28: 19.580285 | L28: 19.789857 | M28: 20.002471 | N28: 20.217959 | O28: 20.436215 | P28: 20.657178 | Q28: 20.880819 | R28: 21.107135 | S28: 21.336135 | T28: 21.567842 | U28: 21.802281 | V28: 22.039486 | W28: 22.279487 | X28: 22.522317 | Y28: 22.768007 | Z28: 23.016586 | AA28: 23.268084 | AB28: 23.52253 | AC28: 23.779952 | AD28: 24.040379 | AE28: 24.303843 | AF28: 24.570373 | AG28: 24.840001 | AH28: 25.112761 | AI28: 25.388689 | AJ28: 25.667821 | AK28: 25.950193

Sheet produits-secteurs V2-V3
B1: ThreeME V3 | M1: ThreeME V2
B2: Produits | C2: V3 | E2: V2 | G2: Secteurs | H2: V3 | I2: V2 | K2: commentaires | M2: Produits | P2: secteurs
B3: Products of agriculture, Hunting, and Fishing | C3: cagr | E3: 1 | G3: Agriculture and fishing | H3: sagr | I3: 1 | M3: Agriculture, sylviculture et pêche | N3: 1 | P3: Agriculture, sylviculture et pêche | Q3: 1
B4: Products of Forestry | C4: cfor | G4: Forestry | H4: sfor | M4: Industrie agro-alimentaire | N4: 2 | P4: Industrie agro-alimentaire | Q4: 2
B5: Food products and beverages | C5: cfoo | E5: 2 | G5: Manufacture of food products and beverages | H5: sfoo | I5: 2 | M5: Automobile | N5: 3 | P5: Automobile | Q5: 3
B6: Motor vehicles, trailers and semi-trailers | C6: cveh | E6: 3 | G6: Manufacture of motor vehicles, trailers and semi-trailers | H6: sveh | I6: 3 | M6: FABRICATION DE VERRE ET D ARTICLES EN VE | N6: 4 | P6: FABRICATION DE VERRE ET D ARTICLES EN VE | Q6: 4
B7: Glass and ceramic products | C7: cgla | E7: 4 e t 5 | G7: Manufacture of glass, ceramic and ciment products | H7: sgla | I7: 4 et 5 | K7: ETS | M7: FABRICATION DE PRODUITS CERAMIQUES ET DE | N7: 5 | P7: FABRICATION DE PRODUITS CERAMIQUES ET DE | Q7: 5
B8: Paper and paperboard | C8: cpap | E8: 6 | G8: Manufacture of paper and paperboard | H8: spap | I8: 6 | K8: ETS | M8: Papier ert carton | N8: 6 | P8: Papier ert carton | Q8: 6
B9: Chemicals | C9: cche | E9: 7 et 8 | G9: Manufacture of chemicals | H9: sche | I9: 7 et 8 | K9: ETS | M9: INDUSTRIE CHIMIQUE MINERALE | N9: 7 | P9: INDUSTRIE CHIMIQUE MINERALE | Q9: 7
B10: Plastics products | C10: cpla | E10: 9 | G10: Manufacture of plastics products | H10: spla | I10: 9 | K10: ETS | M10: INDUSTRIE CHIMIQUE ORGANIQUE | N10: 8 | P10: INDUSTRIE CHIMIQUE ORGANIQUE | Q10: 8
B11: Metals | C11: cmet | E11: 10 et 11 | G11: Metallurgy | H11: smet | I11: 10 et 11 | K11: ETS | M11: TRANSFORMATION DES MATIERES PLASTIQUES | N11: 9 | P11: TRANSFORMATION DES MATIERES PLASTIQUES | Q11: 9
B12: Other goods for industry | C12: cigo | E12: 12 | G12: Manufacture of other goods for industry | H12: sigo | I12: 12 | M12: SIDERURGIE ET PREMIERE TRANSFORMATION DE | N12: 10 | P12: SIDERURGIE ET PREMIERE TRANSFORMATION DE | Q12: 10
B13: Other goods for consumers | C13: ccgo | E13: 12 | G13: Manufacture of other goods for consumers | H13: scgo | I13: 12 | M13: PRODUCTION DE METAUX NON FERREUX | N13: 11 | P13: PRODUCTION DE METAUX NON FERREUX | Q13: 11
B14: Buildings and Civil engineering | C14: ccon | E14: 13 | G14: Construction of buildings and Civil engineering | H14: scon | I14: 13 | M14: Autres | N14: 12 | P14: Autres | Q14: 12
B15: Rail transport | C15: crai | E15: 14 | G15: Rail transport | H15: srai | I15: 14 | M15: BTP | N15: 13 | P15: BTP | Q15: 13
B16: Road transport | C16: croa | E16: 15 et 16 | G16: Road transport | H16: sroa | I16: 15 et 16 | M16: TRANSPORTS FERROVIAIRES | N16: 14 | P16: TRANSPORTS FERROVIAIRES | Q16: 14
B17: Water transport | C17: cwat | E17: 17 | G17: Water transport | H17: swat | I17: 17 | M17: TRANSPORT ROUTIER DE VOYAGEURS | N17: 15 | P17: TRANSPORT ROUTIER DE VOYAGEURS | Q17: 15
B18: Air transport | C18: cair | E18: 18 | G18: Air transport | H18: sair | I18: 18 | K18: ETS | M18: TRANSPORT ROUTIER (OU PAR CONDUITES) DE | N18: 16 | P18: TRANSPORT ROUTIER (OU PAR CONDUITES) DE | Q18: 16
B19: Business services | C19: cpri | E19: 19 | G19: Business services | H19: spri | I19: 19 | M19: TRANSPORTS PAR EAU | N19: 17 | P19: TRANSPORTS PAR EAU | Q19: 17
B20: Public services | C20: cpub | E20: 20 | G20: Public services | H20: spub | I20: 20 | M20: TRANSPORTS AERIENS | N20: 18 | P20: TRANSPORTS AERIENS | Q20: 18
B21: Non-energy mining | C21: cmin | G21: Mining | H21: smin | I21: 21 | K21: ETS | M21: Services marchands | N21: 19 | P21: Services marchands | Q21: 19
B22: Coal | C22: ccoa | E22: 21 | G22: Production of refined oil | H22: soil | I22: 22_1 | J22: TRSF | K22: ETS | M22: Services non marchands | N22: 20 | P22: Services non marchands | Q22: 20
B23: Crude oil | C23: ccoi | D23: pétrole | E23: 22 | G23: Production of biofuel | H23: sbfu | I23: 22_2 | J23: TRSF | K23: ETS | M23: EXTRACTION ET AGGLOMERATION DE LA HOUILL | N23: 21 | P23: EXTRACTION ET AGGLOMERATION DE LA HOUILLE | Q23: 21
B24: Transport fuels | C24: cfut | D24: pétrole | E24: 22 | G24: Distribution of natural gas | H24: sgas | I24: 24_1 | J24: TRSF | K24: ETS | M24: RAFFINAGE DE PETROLE | N24: 22 | P24: pétrole | Q24: 22_1
B25: Heating fuel | C25: cfuh | D25: pétrole | E25: 22 | G25: Production and distribution of biogas | H25: sbga | I25: 24_3 | J25: TRSF | K25: ETS | M25: PRODUCTION ET DISTRIBUTION D ELECTRICITE | N25: 23 | P25: biocarburants | Q25: 22_2
B26: Natural gas | C26: cgas | D26: gaz | E26: 24 | G26: Nuclear electricity generation | H26: senu | I26: 23_1 | J26: ELE | K26: ETS | M26: PRODUCTION ET DISTRIBUTION DE COMBUSTIBL | N26: 24 | P26: Nucléaire | Q26: 23_1
B27: Electricity | C27: cele | D27: elec | E27: 23 | G27: Oil-fired electricity generation | H27: seoi | I27: 23_2 | J27: ELE | K27: ETS | P27: centrale fioul | Q27: 23_2
B28: Heat | C28: chea | G28: Gas-fired electricity generation | H28: sega | I28: 23_3 | J28: ELE | K28: ETS | P28: centrale combinée gaz | Q28: 23_3
B29: Biomass | C29: cbio | G29: Coal-fired electricity generation | H29: seco | I29: 23_4 | J29: ELE | K29: ETS | P29: centrale charbon | Q29: 23_4
B30: Other energy | C30: cote | G30: Wind electricity generation | H30: sewi | I30: 23_5 | J30: ELE | K30: ETS | P30: Eolien | Q30: 23_5
G31: Solar electricity generation | H31: seso | I31: 23_6 | J31: ELE | K31: ETS | P31: PV | Q31: 23_6
G32: Hydroelectric electricity generation | H32: sehy | I32: 23_7 | J32: ELE | K32: ETS | P32: Hydraulique | Q32: 23_7
G33: Cogeneration (CHP) electricity generation and other heat supply | H33: sech | I33: 23_8, 24_4, 24_5, 24,6 | J33: ELE | K33: ETS | P33: cogénération | Q33: 23_8
G34: Electricity - Others | H34: seot | J34: ELE | K34: ETS | P34: gaz naturel | Q34: 24_1
P35: bois énergie | Q35: 24_2
P36: Biogaz | Q36: 24_3
P37: UIOM | Q37: 24_4
P38: Géothermie | Q38: 24_5
P39: cogénération | Q39: 24_6

Sheet Sect&Com_V3
B1: Sectors/activities | C1: Acronym | D1: Commodities | E1: =C1 -> Acronym
B2: Agriculture and fishing | C2: sagr | D2: Products of agriculture, Hunting, and Fishing | E2: cagr
D3: Biomass and other energy | E3: cbio
B4: Forestry | C4: sfor | D4: Products of Forestry | E4: cfor
B5: Manufacture of food products and beverages | C5: sfoo | D5: Food products and beverages | E5: cfoo
B6: Manufacture of motor vehicles, trailers and semi-trailers | C6: sveh | D6: Motor vehicles, trailers and semi-trailers | E6: cveh
B7: Manufacture of glass, ceramic and ciment products | C7: sgla | D7: Glass and ceramic products | E7: cgla
B8: Manufacture of paper and paperboard | C8: spap | D8: Paper and paperboard | E8: cpap
B9: Manufacture of chemicals | C9: sche | D9: Chemicals | E9: cche
B10: Manufacture of plastics products | C10: spla | D10: Plastics products | E10: cpla
B11: Metallurgy | C11: smet | D11: Metals | E11: cmet
B12: Manufacture of other goods for industry | C12: sigo | D12: Other goods for industry | E12: cigo
B13: Manufacture of other goods for consumers | C13: scgo | D13: Other goods for consumers | E13: ccgo
B14: Construction of buildings and Civil engineering | C14: scon | D14: Buildings and Civil engineering | E14: ccon
B15: Rail transport | C15: srai | D15: Rail transport | E15: crai
... B21: Mining | C21: smin | D21: Non-energy mining | E21: cmin
D22: Coal | E22: ccoa
D23: Coal for non-energy use | E23: coan
D24: Crude oil | E24: ccoi
D25: Natural gas mining | E25: cgam
A26: secteurs TRSF | B26: Production of refined oil | C26: soil | D26: Transport fuels | E26: cfut
B27: Production of biofuel | C27: sbfu | D27: Heating fuel | E27: cfuh
D28: Fuel for non-energy use | E28: cfun
B29: Distribution of natural gas | C29: sgas | D29: Natural gas | E29: cgas
B30: Production and distribution of biogas | C30: sbga | D30: Natural gas for non-energy use | E30: cgan
A31: Secteurs SELE + setd | B31: Transmission and distribution of electricity | C31: setd
B32: Nuclear electricity generation | C32: senu
B33: Oil-fired electricity generation | C33: seoi
B34: Gas-fired electricity generation | C34: sega | D34: Electricity | E34: cele
B35: Coal-fired electricity generation | C35: seco
B36: Wind electricity generation | C36: sewi
B37: Solar electricity generation | C37: seso
B38: Hydroelectric electricity generation | C38: sehy | D38: Heat | E38: chea
B39: Cogeneration (CHP) electricity generation and other heat supply | C39: sech
B40: Electricity - Others | C40: seot
