Workbook
Name formatResults: [1]ResultsEXR10!$A$50

Sheet Hybrid
A1: _date_ | B1: 42005 | C1: 42370 | D1: 42736 | E1: 43101 | F1: 43466 | G1: 43831 | H1: 44197 | I1: 44562 | J1: 44927 | K1: 45292 | L1: 45658 | M1: 46023 | N1: 46388 | O1: 46753 | P1: 47119 | Q1: 47484 | R1: 47849 | S1: 48214 | T1: 48580 | U1: 48945 | V1: 49310 | W1: 49675 | X1: 50041 | Y1: 50406 | Z1: 50771 | AA1: 51136 | AB1: 51502 | AC1: 51867 | AD1: 52232 | AE1: 52597 | AF1: 52963 | AG1: 53328 | AH1: 53693 | AI1: 54058 | AJ1: 54424 | AK1: 54789
A2: auto_2 | B2: 32317.941 | C2: 31926.455 | D2: 31730.401 | E2: 31664.733 | F2: 31685.152 | G2: 31761.774 | H2: 31876.82 | I2: 32020.398 | J2: 32185.056 | K2: 32364.879 | L2: 32555.008 | M2: 32751.304 | N2: 32950.116 | O2: 33148.124 | P2: 33342.238 | Q2: 33529.533 | R2: 33709.688 | S2: 33884.612 | T2: 34055.315 | U2: 34222.258 | V2: 34385.651 | W2: 34545.604 | X2: 34702.207 | Y2: 34855.571 | Z2: 35005.845 | AA2: 35153.224 | AB2: 35297.96 | AC2: 35440.362 | AD2: 35580.802 | AE2: 35719.72 | AF2: 35857.626 | AG2: 35995.104 | AH2: 36132.812 | AI2: 36271.48 | AJ2: 36411.912 | AK2: 36554.972
A3: auto_cfut_2 | B3: 32271.24 | C3: 31862.032 | D3: 31647.329 | E3: 31562.481 | F3: 31563.392 | G3: 31620.229 | H3: 31715.127 | I3: 31838.038 | J3: 31981.349 | K3: 32138.974 | L3: 32305.854 | M3: 32477.604 | N3: 32650.259 | O3: 32820.093 | P3: 32983.48 | Q3: 33136.779 | R3: 33278.705 | S3: 33409.974 | T3: 33530.266 | U3: 33638.562 | V3: 33733.424 | W3: 33813.135 | X3: 33875.774 | Y3: 33919.241 | Z3: 33941.277 | AA3: 33939.472 | AB3: 33911.279 | AC3: 33854.036 | AD3: 33764.983 | AE3: 33641.306 | AF3: 33480.173 | AG3: 33278.793 | AH3: 33034.477 | AI3: 32744.706 | AJ3: 32407.216 | AK3: 32020.075
A4: auto_cele_2 | B4: 44.765 | C4: 62.431569 | D4: 81.013696 | E4: 100.12298 | F4: 119.55791 | G4: 139.26917 | H4: 159.3444 | I4: 179.94081 | J4: 201.21851 | K4: 223.34991 | L4: 246.53496 | M4: 271.01944 | N4: 297.11658 | O4: 325.23391 | P4: 355.90822 | Q4: 389.85321 | R4: 428.03471 | S4: 471.64532 | T4: 522.01458 | U4: 580.62349 | V4: 649.11914 | W4: 729.32713 | X4: 823.26146 | Y4: 933.13161 | Z4: 1061.3459 | AA4: 1210.5101 | AB4: 1383.4212 | AC4: 1583.0534 | AD4: 1812.5367 | AE4: 2075.1269 | AF4: 2374.165 | AG4: 2713.0263 | AH4: 3095.0588 | AI4: 3523.5113 | AJ4: 4001.4513 | AK4: 4531.6755
A5: auto_cgas_2 | B5: 1.936 | C5: 1.9916056 | D5: 2.0574011 | E5: 2.1285899 | F5: 2.2019794 | G5: 2.2754864 | H5: 2.3479684 | I5: 2.4188941 | J5: 2.4879043 | K5: 2.5547408 | L5: 2.6192081 | M5: 2.6811463 | N5: 2.7404123 | O5: 2.796866 | P5: 2.8503601 | Q5: 2.9007315 | R5: 2.9480014 | S5: 2.9923496 | T5: 3.033862 | U5: 3.0725586 | V5: 3.1084159 | W5: 3.1413797 | X5: 3.17137 | Y5: 3.1982849 | Z5: 3.2220012 | AA5: 3.2423764 | AB5: 3.2592496 | AC5: 3.2724433 | AD5: 3.2817658 | AE5: 3.2870146 | AF5: 3.2879801 | AG5: 3.2844506 | AH5: 3.2762179 | AI5: 3.2630839 | AJ5: 3.2448672 | AK5: 3.2214115
A6: auto_ca_cfut_2 | B6: 7095.7005 | C6: 7141.744 | D6: 7236.2109 | E6: 7362.7565 | F6: 7510.0299 | G6: 7670.2472 | H6: 7838.785 | I6: 8013.1055 | J6: 8191.247 | K6: 8371.6256 | L6: 8552.9219 | M6: 8733.9921 | N6: 8913.8008 | O6: 9091.3684 | P6: 9265.7305 | Q6: 9435.9023 | R6: 9601.6399 | S6: 9763.3044 | T6: 9920.8512 | U6: 10073.962 | V6: 10222.146 | W6: 10364.788 | X6: 10501.176 | Y6: 10630.509 | Z6: 10751.903 | AA6: 10864.388 | AB6: 10966.919 | AC6: 11058.37 | AD6: 11137.548 | AE6: 11203.202 | AF6: 11254.038 | AG6: 11288.736 | AH6: 11305.979 | AI6: 11304.477 | AJ6: 11283.004 | AK6: 11240.43
A7: auto_cb_cfut_2 | B7: 8251.2564 | C7: 8182.7845 | D7: 8168.3356 | E7: 8191.2663 | F7: 8239.913 | G7: 8306.1531 | H7: 8384.9727 | I7: 8473.4298 | J7: 8569.2032 | K7: 8670.3749 | L7: 8775.306 | M7: 8882.5442 | N7: 8990.7536 | O7: 9098.6627 | P7: 9205.023 | Q7: 9308.5738 | R7: 9408.7536 | S7: 9505.5998 | T7: 9598.8301 | U7: 9687.9491 | V7: 9772.3323 | W7: 9851.2702 | X7: 9923.9898 | Y7: 9989.6639 | Z7: 10047.417 | AA7: 10096.329 | AB7: 10135.439 | AC7: 10163.754 | AD7: 10180.258 | AE7: 10183.922 | AF7: 10173.723 | AG7: 10148.662 | AH7: 10107.786 | AI7: 10050.216 | AJ7: 9975.1683 | AK7: 9881.9911
A8: auto_cc_cfut_2 | B8: 6777.6025 | C8: 6646.7629 | D8: 6558.9664 | E8: 6502.0082 | F8: 6467.2622 | G8: 6448.6373 | H8: 6442.2478 | I8: 6445.693 | J8: 6457.0498 | K8: 6474.7042 | L8: 6497.2553 | M8: 6523.4452 | N8: 6552.1089 | O8: 6582.1356 | P8: 6612.4399 | Q8: 6641.9367 | R8: 6670.0211 | S8: 6696.5179 | T8: 6721.0788 | U8: 6743.2423 | V8: 6762.4848 | W8: 6778.2466 | X8: 6789.946 | Y8: 6796.985 | Z8: 6798.7539 | AA8: 6794.6346 | AB8: 6784.0053 | AC8: 6766.2455 | AD8: 6740.7441 | AE8: 6706.9077 | AF8: 6664.1718 | AG8: 6612.0131 | AH8: 6549.9638 | AI8: 6477.6256 | AJ8: 6394.686 | AK8: 6300.9328
A9: auto_cd_cfut_2 | B9: 4159.6639 | C9: 4054.5797 | D9: 3973.8285 | E9: 3910.0599 | F9: 3858.1675 | G9: 3814.6035 | H9: 3777.117 | I9: 3744.3156 | J9: 3715.1047 | K9: 3688.5795 | L9: 3663.9665 | M9: 3640.5846 | N9: 3617.818 | O9: 3595.0978 | P9: 3571.8901 | Q9: 3547.6856 | R9: 3522.2279 | S9: 3495.4859 | T9: 3467.374 | U9: 3437.7764 | V9: 3406.5692 | W9: 3373.6323 | X9: 3338.8542 | Y9: 3302.1347 | Z9: 3263.3849 | AA9: 3222.5277 | AB9: 3179.4973 | AC9: 3134.2391 | AD9: 3086.7097 | AE9: 3036.8772 | AF9: 2984.7211 | AG9: 2930.233 | AH9: 2873.4168 | AI9: 2814.2895 | AJ9: 2752.882 | AK9: 2689.2394
A10: auto_ce_cfut_2 | B10: 2503.7292 | C10: 2442.7169 | D10: 2395.2655 | E10: 2356.6831 | F10: 2323.7962 | G10: 2294.4653 | H10: 2267.3805 | I10: 2241.7723 | J10: 2217.0647 | K10: 2192.8017 | L10: 2168.6075 | M10: 2144.162 | N10: 2119.1847 | O10: 2093.4237 | P10: 2066.6498 | Q10: 2038.6508 | R10: 2009.3526 | S10: 1978.8038 | T10: 1947.0309 | U10: 1914.0487 | V10: 1879.8711 | W10: 1844.5168 | X10: 1808.0111 | Y10: 1770.3874 | Z10: 1731.6863 | AA10: 1691.9562 | AB10: 1651.2522 | AC10: 1609.6356 | AD10: 1567.174 | AE10: 1523.9407 | AF10: 1480.0137 | AG10: 1435.4764 | AH10: 1390.416 | AI10: 1344.9241 | AJ10: 1299.0954 | AK10: 1253.0278
A11: auto_cf_cfut_2 | B11: 1243.6668 | C11: 1210.4925 | D11: 1182.3239 | E11: 1156.6362 | F11: 1131.8888 | G11: 1107.177 | H11: 1082.0509 | I11: 1056.3349 | J11: 1029.9552 | K11: 1002.8948 | L11: 975.17131 | M11: 946.82415 | N11: 917.9064 | O11: 888.4802 | P11: 858.61373 | Q11: 828.37916 | R11: 797.88431 | S11: 767.26368 | T11: 736.63803 | U11: 706.11731 | V11: 675.8034 | W11: 645.79139 | X11: 616.16995 | Y11: 587.02123 | Z11: 558.42062 | AA11: 530.43659 | AB11: 503.13048 | AC11: 476.55639 | AD11: 450.76125 | AE11: 425.78482 | AF11: 401.6599 | AG11: 378.41249 | AH11: 356.06205 | AI11: 334.62184 | AJ11: 314.0992 | AK11: 294.49603
A12: auto_cg_cfut_2 | B12: 2239.6206 | C12: 2182.9512 | D12: 2132.3988 | E12: 2083.0711 | F12: 2032.334 | G12: 1978.9456 | H12: 1922.5734 | I12: 1863.3872 | J12: 1801.7246 | K12: 1737.9934 | L12: 1672.6254 | M12: 1606.0511 | N12: 1538.6862 | O12: 1470.9243 | P12: 1403.1326 | Q12: 1335.6507 | R12: 1268.8256 | S12: 1202.999 | T12: 1138.4631 | U12: 1075.4659 | V12: 1014.2168 | W12: 954.88992 | X12: 897.62714 | Y12: 842.53991 | Z12: 789.71152 | AA12: 739.19926 | AB12: 691.03659 | AC12: 645.23547 | AD12: 601.78864 | AE12: 560.6719 | AF12: 521.84637 | AG12: 485.26059 | AH12: 450.8526 | AI12: 418.55185 | AJ12: 388.28097 | AK12: 359.95743
... A51: auto_cg_cgas_0 | B51: 0.13435819 | C51: 0.13586779 | D51: 0.13744409 | E51: 0.13870945 | F51: 0.13947226 | G51: 0.13965509 | H51: 0.13924622 | I51: 0.13826967 | J51: 0.13676768 | K51: 0.13479082 | L51: 0.1323926 | M51: 0.12962652 | N51: 0.12654447 | O51: 0.12319587 | P51: 0.11962718 | Q51: 0.11588171 | R51: 0.11199946 | S51: 0.10801707 | T51: 0.10396794 | U51: 0.099882204 | V51: 0.09578691 | W51: 0.091706106 | X51: 0.087661003 | Y51: 0.083670125 | Z51: 0.079749476 | AA51: 0.075912709 | AB51: 0.072171292 | AC51: 0.068534683 | AD51: 0.065010496 | AE51: 0.06160466 | AF51: 0.058321589 | AG51: 0.055164327 | AH51: 0.052134699 | AI51: 0.049233452 | AJ51: 0.046460385 | AK51: 0.043814475

Sheet Tab-macro
B1: en écart au scénario de référence (%)
B2: ThreeME
B3: 2021 | C3: 2022 | D3: 2023 | E3: 2025 | F3: 2030 | G3: 2050
A4: PIB en volume | B4: =Macro!H2 -> 0.048738572 | C4: =Macro!I2 -> 0.060095859 | D4: =Macro!J2 -> 0.070015107 | E4: =Macro!L2 -> 0.085962983 | F4: =Macro!Q2 -> 0.14265241 | G4: =Macro!AK2 -> 0.14504591
A5: Consommation des ménages | B5: =Macro!H3 -> 0.11251557 | C5: =Macro!I3 -> 0.15121567 | D5: =Macro!J3 -> 0.19244796 | E5: =Macro!L3 -> 0.27910298 | F5: =Macro!Q3 -> 0.58194624 | G5: =Macro!AK3 -> 2.856981
A6: Investissement | B6: =Macro!H4 -> -0.059365516 | C6: =Macro!I4 -> -0.075529889 | D6: =Macro!J4 -> -0.091710764 | E6: =Macro!L4 -> -0.1256935 | F6: =Macro!Q4 -> -0.24634604 | G6: =Macro!AK4 -> -1.1530914
A7: Exportations | B7: =Macro!H5 -> -0.084743657 | C7: =Macro!I5 -> -0.12011476 | D7: =Macro!J5 -> -0.16133864 | E7: =Macro!L5 -> -0.25968198 | F7: =Macro!Q5 -> -0.62273486 | G7: =Macro!AK5 -> -4.3575533
A8: Importations | B8: =Macro!H6 -> -0.081006385 | C8: =Macro!I6 -> -0.093915873 | D8: =Macro!J6 -> -0.10310887 | E8: =Macro!L6 -> -0.11740134 | F8: =Macro!Q6 -> -0.18982161 | G8: =Macro!AK6 -> -0.25427952
A9: Revenu disponible (réel) des ménages | B9: =Macro!H7 -> 0.12157521 | C9: =Macro!I7 -> 0.16017255 | D9: =Macro!J7 -> 0.20029739 | E9: =Macro!L7 -> 0.28453424 | F9: =Macro!Q7 -> 0.59324441 | G9: =Macro!AK7 -> 2.8463131
A10: Taux d'épargne (en pts) | B10: =Macro!H8 -> 0.00802139 | C10: =Macro!I8 -> 0.00792673 | D10: =Macro!J8 -> 0.00694347 | E10: =Macro!L8 -> 0.00480004 | F10: =Macro!Q8 -> 0.0099548 | G10: =Macro!AK8 -> -0.00919449
A11: Prix de la consommation des ménages | B11: =Macro!H9 -> 0.36952058 | C11: =Macro!I9 -> 0.47010293 | D11: =Macro!J9 -> 0.57633973 | E11: =Macro!L9 -> 0.81690358 | F11: =Macro!Q9 -> 1.7507387 | G11: =Macro!AK9 -> 9.4772123
A12: Prix de la production | B12: =Macro!H10 -> 0.16101628 | C12: =Macro!I10 -> 0.22699322 | D12: =Macro!J10 -> 0.30376127 | E12: =Macro!L10 -> 0.48622175 | F12: =Macro!Q10 -> 1.1478252 | G12: =Macro!AK10 -> 7.9308716
A13: Prix de la valeur ajoutée | B13: =Macro!H11 -> -0.1140916 | C13: =Macro!I11 -> -0.099489263 | D13: =Macro!J11 -> -0.068390416 | E13: =Macro!L11 -> 0.021294126 | F13: =Macro!Q11 -> 0.24697079 | G13: =Macro!AK11 -> 4.4747757
A14: Prix des consommations intermédiaires | B14: =Macro!H12 -> 0.44768827 | C14: =Macro!I12 -> 0.56728174 | D14: =Macro!J12 -> 0.69175235 | E14: =Macro!L12 -> 0.97122732 | F14: =Macro!Q12 -> 2.0898956 | G14: =Macro!AK12 -> 11.613078
A15: Prix des exportations | B15: =Macro!H13 -> 0.25431316 | C15: =Macro!I13 -> 0.33938229 | D15: =Macro!J13 -> 0.43168577 | E15: =Macro!L13 -> 0.63899439 | F15: =Macro!Q13 -> 1.4145331 | G15: =Macro!AK13 -> 8.768209
... A24: Emissions de CO2 | B24: =Macro!H22 -> -1.761206 | C24: =Macro!I22 -> -2.2324391 | D24: =Macro!J22 -> -2.6954212 | E24: =Macro!L22 -> -3.6119939 | F24: =Macro!Q22 -> -6.6014016 | G24: =Macro!AK22 -> -22.746641
B26: % deviation from baseline
B27: ThreeME
B28: 2021 | C28: 2022 | D28: 2023 | E28: 2025 | F28: 2030 | G28: 2050
A29: GDP in volume | B29: =B4 -> 0.048738572 | C29: =C4 -> 0.060095859 | D29: =D4 -> 0.070015107 | E29: =E4 -> 0.085962983 | F29: =F4 -> 0.14265241 | G29: =G4 -> 0.14504591
A30: Household consumption | B30: =B5 -> 0.11251557 | C30: =C5 -> 0.15121567 | D30: =D5 -> 0.19244796 | E30: =E5 -> 0.27910298 | F30: =F5 -> 0.58194624 | G30: =G5 -> 2.856981
A31: Investment | B31: =B6 -> -0.059365516 | C31: =C6 -> -0.075529889 | D31: =D6 -> -0.091710764 | E31: =E6 -> -0.1256935 | F31: =F6 -> -0.24634604 | G31: =G6 -> -1.1530914
A32: Exports | B32: =B7 -> -0.084743657 | C32: =C7 -> -0.12011476 | D32: =D7 -> -0.16133864 | E32: =E7 -> -0.25968198 | F32: =F7 -> -0.62273486 | G32: =G7 -> -4.3575533
A33: Imports | B33: =B8 -> -0.081006385 | C33: =C8 -> -0.093915873 | D33: =D8 -> -0.10310887 | E33: =E8 -> -0.11740134 | F33: =F8 -> -0.18982161 | G33: =G8 -> -0.25427952
A34: Household disposable income (real) | B34: =B9 -> 0.12157521 | C34: =C9 -> 0.16017255 | D34: =D9 -> 0.20029739 | E34: =E9 -> 0.28453424 | F34: =F9 -> 0.59324441 | G34: =G9 -> 2.8463131
A35: Saving rate (in points) | B35: =B10 -> 0.00802139 | C35: =C10 -> 0.00792673 | D35: =D10 -> 0.00694347 | E35: =E10 -> 0.00480004 | F35: =F10 -> 0.0099548 | G35: =G10 -> -0.00919449
A36: Household consumption price index | B36: =B11 -> 0.36952058 | C36: =C11 -> 0.47010293 | D36: =D11 -> 0.57633973 | E36: =E11 -> 0.81690358 | F36: =F11 -> 1.7507387 | G36: =G11 -> 9.4772123
A37: Production price index | B37: =B12 -> 0.16101628 | C37: =C12 -> 0.22699322 | D37: =D12 -> 0.30376127 | E37: =E12 -> 0.48622175 | F37: =F12 -> 1.1478252 | G37: =G12 -> 7.9308716
A38: Added value price index | B38: =B13 -> -0.1140916 | C38: =C13 -> -0.099489263 | D38: =D13 -> -0.068390416 | E38: =E13 -> 0.021294126 | F38: =F13 -> 0.24697079 | G38: =G13 -> 4.4747757
A39: Intermediate consumption price index | B39: =B14 -> 0.44768827 | C39: =C14 -> 0.56728174 | D39: =D14 -> 0.69175235 | E39: =E14 -> 0.97122732 | F39: =F14 -> 2.0898956 | G39: =G14 -> 11.613078
A40: Export price index | B40: =B15 -> 0.25431316 | C40: =C15 -> 0.33938229 | D40: =D15 -> 0.43168577 | E40: =E15 -> 0.63899439 | F40: =F15 -> 1.4145331 | G40: =G15 -> 8.768209
... A49: CO2 emissions | B49: =B24 -> -1.761206 | C49: =C24 -> -2.2324391 | D49: =D24 -> -2.6954212 | E49: =E24 -> -3.6119939 | F49: =F24 -> -6.6014016 | G49: =G24 -> -22.746641

Sheet Tab-baseline
C1: 8 | D1: 9 | E1: 10 | F1: 12 | G1: 17 | H1: 37
C2: ThreeME
C3: 2021 | D3: 2022 | E3: 2023 | F3: 2025 | G3: 2030 | H3: 2050
A4: Taux de croissance du PIB | B4: @pch(gdp_0) | C4: =VLOOKUP($B4,Baseline!$A$1:$AT$50,C$1,FALSE) -> 0.011252093 | D4: =VLOOKUP($B4,Baseline!$A$1:$AT$50,D$1,FALSE) -> 0.011375473 | E4: =VLOOKUP($B4,Baseline!$A$1:$AT$50,E$1,FALSE) -> 0.011476237 | F4: =VLOOKUP($B4,Baseline!$A$1:$AT$50,F$1,FALSE) -> 0.011614092 | G4: =VLOOKUP($B4,Baseline!$A$1:$AT$50,G$1,FALSE) -> 0.011726136 | H4: =VLOOKUP($B4,Baseline!$A$1:$AT$50,H$1,FALSE) -> 0.011660368
A5: Prix de la consommation des ménages | B5: @pch(pch_0) | C5: =VLOOKUP($B5,Baseline!$A$1:$AT$50,C$1,FALSE) -> 0.019635207 | D5: =VLOOKUP($B5,Baseline!$A$1:$AT$50,D$1,FALSE) -> 0.019668198 | E5: =VLOOKUP($B5,Baseline!$A$1:$AT$50,E$1,FALSE) -> 0.019714317 | F5: =VLOOKUP($B5,Baseline!$A$1:$AT$50,F$1,FALSE) -> 0.019828899 | G5: =VLOOKUP($B5,Baseline!$A$1:$AT$50,G$1,FALSE) -> 0.020129185 | H5: =VLOOKUP($B5,Baseline!$A$1:$AT$50,H$1,FALSE) -> 0.020366929
A6: Taux de chômage | B6: unr_0 | C6: =VLOOKUP($B6,Baseline!$A$1:$AT$50,C$1,FALSE) -> 0.14415905 | D6: =VLOOKUP($B6,Baseline!$A$1:$AT$50,D$1,FALSE) -> 0.14419204 | E6: =VLOOKUP($B6,Baseline!$A$1:$AT$50,E$1,FALSE) -> 0.14412979 | F6: =VLOOKUP($B6,Baseline!$A$1:$AT$50,F$1,FALSE) -> 0.14381068 | G6: =VLOOKUP($B6,Baseline!$A$1:$AT$50,G$1,FALSE) -> 0.14261895 | H6: =VLOOKUP($B6,Baseline!$A$1:$AT$50,H$1,FALSE) -> 0.13887513
A7: Dette publique (en pts de PIB) | B7: rdebt_g_val_0 | C7: =VLOOKUP($B7,Baseline!$A$1:$AT$50,C$1,FALSE) -> 0.97004802 | D7: =VLOOKUP($B7,Baseline!$A$1:$AT$50,D$1,FALSE) -> 0.97258712 | E7: =VLOOKUP($B7,Baseline!$A$1:$AT$50,E$1,FALSE) -> 0.97503146 | F7: =VLOOKUP($B7,Baseline!$A$1:$AT$50,F$1,FALSE) -> 0.97946806 | G7: =VLOOKUP($B7,Baseline!$A$1:$AT$50,G$1,FALSE) -> 0.98723105 | H7: =VLOOKUP($B7,Baseline!$A$1:$AT$50,H$1,FALSE) -> 0.97986829
A8: Solde primaire public (en pts de PIB) | B8: rbal_g_prim_val_0 | C8: =VLOOKUP($B8,Baseline!$A$1:$AT$50,C$1,FALSE) -> -0.011460251 | D8: =VLOOKUP($B8,Baseline!$A$1:$AT$50,D$1,FALSE) -> -0.011637088 | E8: =VLOOKUP($B8,Baseline!$A$1:$AT$50,E$1,FALSE) -> -0.011732352 | F8: =VLOOKUP($B8,Baseline!$A$1:$AT$50,F$1,FALSE) -> -0.011733133 | G8: =VLOOKUP($B8,Baseline!$A$1:$AT$50,G$1,FALSE) -> -0.01117748 | H8: =VLOOKUP($B8,Baseline!$A$1:$AT$50,H$1,FALSE) -> -0.00849113
A9: Balance commerciale (en pts de PIB) | B9: rbal_trade_val_0 | C9: =VLOOKUP($B9,Baseline!$A$1:$AT$50,C$1,FALSE) -> -0.01277292 | D9: =VLOOKUP($B9,Baseline!$A$1:$AT$50,D$1,FALSE) -> -0.012784958 | E9: =VLOOKUP($B9,Baseline!$A$1:$AT$50,E$1,FALSE) -> -0.012769054 | F9: =VLOOKUP($B9,Baseline!$A$1:$AT$50,F$1,FALSE) -> -0.012698369 | G9: =VLOOKUP($B9,Baseline!$A$1:$AT$50,G$1,FALSE) -> -0.012442025 | H9: =VLOOKUP($B9,Baseline!$A$1:$AT$50,H$1,FALSE) -> -0.011138905
A10: Emissions de CO2 (en Kt CO2) | B10: ems_co2_0 | C10: =VLOOKUP($B10,Baseline!$A$1:$AT$50,C$1,FALSE) -> 362.04263 | D10: =VLOOKUP($B10,Baseline!$A$1:$AT$50,D$1,FALSE) -> 364.51423 | E10: =VLOOKUP($B10,Baseline!$A$1:$AT$50,E$1,FALSE) -> 367.1103 | F10: =VLOOKUP($B10,Baseline!$A$1:$AT$50,F$1,FALSE) -> 372.57878 | G10: =VLOOKUP($B10,Baseline!$A$1:$AT$50,G$1,FALSE) -> 387.32088 | H10: =VLOOKUP($B10,Baseline!$A$1:$AT$50,H$1,FALSE) -> 457.40889
C33: ThreeME
C34: 2021 | D34: 2022 | E34: 2023 | F34: 2025 | G34: 2030 | H34: 2050
A35: GDP growth rate | C35: =C4 -> 0.011252093 | D35: =D4 -> 0.011375473 | E35: =E4 -> 0.011476237 | F35: =F4 -> 0.011614092 | G35: =G4 -> 0.011726136 | H35: =H4 -> 0.011660368
A36: Household consumption price | C36: =C5 -> 0.019635207 | D36: =D5 -> 0.019668198 | E36: =E5 -> 0.019714317 | F36: =F5 -> 0.019828899 | G36: =G5 -> 0.020129185 | H36: =H5 -> 0.020366929
A37: unemployment rate | C37: =C6 -> 0.14415905 | D37: =D6 -> 0.14419204 | E37: =E6 -> 0.14412979 | F37: =F6 -> 0.14381068 | G37: =G6 -> 0.14261895 | H37: =H6 -> 0.13887513
A38: Public debt (in points of GDP) | C38: =C7 -> 0.97004802 | D38: =D7 -> 0.97258712 | E38: =E7 -> 0.97503146 | F38: =F7 -> 0.97946806 | G38: =G7 -> 0.98723105 | H38: =H7 -> 0.97986829
A39: Public budget balance (in points of GDP) | C39: =C8 -> -0.011460251 | D39: =D8 -> -0.011637088 | E39: =E8 -> -0.011732352 | F39: =F8 -> -0.011733133 | G39: =G8 -> -0.01117748 | H39: =H8 -> -0.00849113
A40: Trade balance (in points of GDP) | C40: =C9 -> -0.01277292 | D40: =D9 -> -0.012784958 | E40: =E9 -> -0.012769054 | F40: =F9 -> -0.012698369 | G40: =G9 -> -0.012442025 | H40: =H9 -> -0.011138905
A41: CO2 emissions (In Kt og CO2) | C41: =C10 -> 362.04263 | D41: =D10 -> 364.51423 | E41: =E10 -> 367.1103 | F41: =F10 -> 372.57878 | G41: =G10 -> 387.32088 | H41: =H10 -> 457.40889

Sheet Macro
A1: _date_ | B1: 42005 | C1: 42370 | D1: 42736 | E1: 43101 | F1: 43466 | G1: 43831 | H1: 44197 | I1: 44562 | J1: 44927 | K1: 45292 | L1: 45658 | M1: 46023 | N1: 46388 | O1: 46753 | P1: 47119 | Q1: 47484 | R1: 47849 | S1: 48214 | T1: 48580 | U1: 48945 | V1: 49310 | W1: 49675 | X1: 50041 | Y1: 50406 | Z1: 50771 | AA1: 51136 | AB1: 51502 | AC1: 51867 | AD1: 52232 | AE1: 52597 | AF1: 52963 | AG1: 53328 | AH1: 53693 | AI1: 54058 | AJ1: 54424 | AK1: 54789
A2: 100*(gdp_2/gdp_0-1) | B2: 0 | C2: 0.0033641188 | D2: 0.009082291 | E2: 0.016620143 | F2: 0.02577382 | G2: 0.036754288 | H2: 0.048738572 | I2: 0.060095859 | J2: 0.070015107 | K2: 0.078444474 | L2: 0.085962983 | M2: 0.093517875 | N2: 0.10215197 | O2: 0.11279884 | P2: 0.12615999 | Q2: 0.14265241 | R2: 0.16135001 | S2: 0.18024891 | T2: 0.19776241 | U2: 0.21281822 | V2: 0.22488163 | W2: 0.2338464 | X2: 0.23987807 | Y2: 0.24327291 | Z2: 0.24435604 | AA2: 0.24341921 | AB2: 0.24069009 | AC2: 0.23632354 | AD2: 0.23040664 | AE2: 0.22297109 | AF2: 0.21400903 | AG2: 0.20348859 | AH2: 0.1913679 | AI2: 0.17760609 | AJ2: 0.16217138 | AK2: 0.14504591
A3: 100*(ch_2/ch_0-1) | B3: 0 | C3: 0.0040055393 | D3: 0.013727548 | E3: 0.02935883 | F3: 0.050742053 | G3: 0.078457722 | H3: 0.11251557 | I3: 0.15121567 | J3: 0.19244796 | K3: 0.23501692 | L3: 0.27910298 | M3: 0.32599045 | N3: 0.37759555 | O3: 0.43606676 | P3: 0.50352806 | Q3: 0.58194624 | R3: 0.67185042 | S3: 0.77157129 | T3: 0.87851096 | U3: 0.99028322 | V3: 1.1052365 | W3: 1.2224212 | X3: 1.3413526 | Y3: 1.4617673 | Z3: 1.5834438 | AA3: 1.7060966 | AB3: 1.8293274 | AC3: 1.9526152 | AD3: 2.0753324 | AE3: 2.1967726 | AF3: 2.3161833 | AG3: 2.4327995 | AH3: 2.5458709 | AI3: 2.6546858 | AJ3: 2.7585865 | AK3: 2.856981
A4: 100*(i_2/i_0-1) | B4: 0 | C4: -0.0046338231 | D4: -0.011432338 | E4: -0.019738649 | F4: -0.03009929 | G4: -0.043591259 | H4: -0.059365516 | I4: -0.075529889 | J4: -0.091710764 | K4: -0.10825266 | L4: -0.1256935 | M4: -0.14456918 | N4: -0.16541452 | O4: -0.18882793 | P4: -0.21552385 | Q4: -0.24634604 | R4: -0.28087376 | S4: -0.31788339 | T4: -0.35702665 | U4: -0.3982861 | V4: -0.44160759 | W4: -0.48676438 | X4: -0.53337377 | Y4: -0.58097564 | Z4: -0.62911538 | AA4: -0.67740527 | AB4: -0.72555933 | AC4: -0.77340524 | AD4: -0.82088034 | AE4: -0.86801772 | AF4: -0.91492806 | AG4: -0.9617803 | AH4: -1.0087835 | AI4: -1.0561717 | AJ4: -1.104191 | AK4: -1.1530914
A5: 100*(x_2/x_0-1) | B5: 0 | C5: -0.0025491856 | D5: -0.0085910817 | E5: -0.018818883 | F5: -0.034155152 | G5: -0.055920637 | H5: -0.084743657 | I5: -0.12011476 | J5: -0.16133864 | K5: -0.20791034 | L5: -0.25968198 | M5: -0.31694184 | N5: -0.38044515 | O5: -0.4514109 | P5: -0.53149316 | Q5: -0.62273486 | R5: -0.72664833 | S5: -0.84365631 | T5: -0.9736266 | U5: -1.1160905 | V5: -1.2703569 | W5: -1.4355883 | X5: -1.6108574 | Y5: -1.7951871 | Z5: -1.9875784 | AA5: -2.1870277 | AB5: -2.3925368 | AC5: -2.6031189 | AD5: -2.8178017 | AE5: -3.0356292 | AF5: -3.2556635 | AG5: -3.476986 | AH5: -3.6986992 | AI5: -3.9199277 | AJ5: -4.1398207 | AK5: -4.3575533
A6: 100*(m_2/m_0-1) | B6: 0 | C6: -0.009707468 | D6: -0.02168718 | E6: -0.034010908 | F6: -0.047603819 | G6: -0.064181485 | H6: -0.081006385 | I6: -0.093915873 | J6: -0.10310887 | K6: -0.1103307 | L6: -0.11740134 | M6: -0.12577707 | N6: -0.13653471 | O6: -0.15045687 | P6: -0.16809946 | Q6: -0.18982161 | R6: -0.21270705 | S6: -0.23262719 | T6: -0.24862889 | U6: -0.2610023 | V6: -0.27025334 | W6: -0.27677431 | X6: -0.28082105 | Y6: -0.28258266 | Z6: -0.28225408 | AA6: -0.2800842 | AB6: -0.27639748 | AC6: -0.27159551 | AD6: -0.26614581 | AE6: -0.26056375 | AF6: -0.25539201 | AG6: -0.25118049 | AH6: -0.24846851 | AI6: -0.24777016 | AJ6: -0.2495629 | AK6: -0.25427952
A7: 100*((dispinc_at_val_2/pch_2)/(dispinc_at_val_0/pch_0)-1) | B7: 0 | C7: 0.0053998782 | D7: 0.017255175 | E7: 0.034772145 | F7: 0.057523276 | G7: 0.086540382 | H7: 0.12157521 | I7: 0.16017255 | J7: 0.20029739 | K7: 0.24145159 | L7: 0.28453424 | M7: 0.3312217 | N7: 0.38349257 | O7: 0.4433508 | P7: 0.51269023 | Q7: 0.59324441 | R7: 0.68488719 | S7: 0.78515257 | T7: 0.89132881 | U7: 1.0014622 | V7: 1.1144572 | W7: 1.2297586 | X7: 1.3470636 | Y7: 1.4661316 | Z7: 1.5866781 | AA7: 1.7083232 | AB7: 1.8305774 | AC7: 1.9528498 | AD7: 2.0744676 | AE7: 2.1947049 | AF7: 2.3128106 | AG7: 2.4280347 | AH7: 2.5396519 | AI7: 2.646979 | AJ7: 2.7493879 | AK7: 2.8463131
A8: 100*(rsav_h_val_2-rsav_h_val_0) | B8: 0 | C8: 0.00123597 | D8: 0.0031268 | E8: 0.00479765 | F8: 0.00600868 | G8: 0.00715944 | H8: 0.00802139 | I8: 0.00792673 | J8: 0.00694347 | K8: 0.00568948 | L8: 0.00480004 | M8: 0.00462108 | N8: 0.00520655 | O8: 0.0064273 | P8: 0.00807906 | Q8: 0.0099548 | R8: 0.01147633 | S8: 0.01194392 | T8: 0.01126075 | U8: 0.00981038 | V8: 0.00808293 | W8: 0.00642473 | X8: 0.00499472 | Y8: 0.00381257 | Z8: 0.00282212 | AA8: 0.00194051 | AB8: 0.00108822 | AC8: 0.00020387 | AD8: -0.00075109 | AE8: -0.00179339 | AF8: -0.00292208 | AG8: -0.00412348 | AH8: -0.00537616 | AI8: -0.00665524 | AJ8: -0.00793568 | AK8: -0.00919449
A9: 100*(pch_2/pch_0-1) | B9: 0 | C9: 0.035644813 | D9: 0.07451185 | E9: 0.12266123 | F9: 0.18626679 | G9: 0.27150893 | H9: 0.36952058 | I9: 0.47010293 | J9: 0.57633973 | K9: 0.69099162 | L9: 0.81690358 | M9: 0.95734267 | N9: 1.1161685 | O9: 1.2978717 | P9: 1.5075322 | Q9: 1.7507387 | R9: 2.0224971 | S9: 2.3147611 | T9: 2.6276678 | U9: 2.9604916 | V9: 3.3118777 | W9: 3.680096 | X9: 4.0632206 | Y9: 4.4592381 | Z9: 4.8661039 | AA9: 5.281769 | AB9: 5.7041902 | AC9: 6.1313319 | AD9: 6.5611674 | AE9: 6.9916765 | AF9: 7.4208474 | AG9: 7.846678 | AH9: 8.2671806 | AI9: 8.6803884 | AJ9: 9.0843642 | AK9: 9.4772123
A10: 100*(py_2/py_0-1) | B10: 0 | C10: 0.0058105778 | D10: 0.0174092 | E10: 0.036601329 | F10: 0.065554013 | G10: 0.10680847 | H10: 0.16101628 | I10: 0.22699322 | J10: 0.30376127 | K10: 0.39035097 | L10: 0.48622175 | M10: 0.59162577 | N10: 0.70778923 | O10: 0.83694583 | P10: 0.98227978 | Q10: 1.1478252 | R10: 1.336419 | S10: 1.5490139 | T10: 1.7858319 | U10: 2.0461513 | V10: 2.3285825 | W10: 2.6313652 | X10: 2.9525728 | Y10: 3.2902296 | Z10: 3.6423653 | AA10: 4.0070351 | AB10: 4.3823223 | AC10: 4.7663351 | AD10: 5.1572009 | AE10: 5.5530621 | AF10: 5.9520745 | AG10: 6.3524065 | AH10: 6.7522404 | AI10: 7.1497764 | AJ10: 7.5432368 | AK10: 7.9308716
A11: 100*(pva_2/pva_0-1) | B11: 0 | C11: -0.029375201 | D11: -0.052075359 | E11: -0.070848407 | F11: -0.088333193 | G11: -0.10681034 | H11: -0.1140916 | I11: -0.099489263 | J11: -0.068390416 | K11: -0.026412005 | L11: 0.021294126 | M11: 0.070585526 | N11: 0.11861257 | O11: 0.1639013 | P11: 0.2063175 | Q11: 0.24697079 | R11: 0.29877485 | S11: 0.37525907 | T11: 0.47735263 | U11: 0.60458246 | V11: 0.75553243 | W11: 0.92828093 | X11: 1.1206934 | Y11: 1.3305874 | Z11: 1.5558079 | AA11: 1.7942545 | AB11: 2.0438829 | AC11: 2.3026966 | AD11: 2.5687382 | AE11: 2.8400809 | AF11: 3.1148235 | AG11: 3.3910889 | AH11: 3.6670247 | AI11: 3.9408062 | AJ11: 4.210641 | AK11: 4.4747757
A12: 100*(pci_2/pci_0-1) | B12: 0 | C12: 0.042458743 | D12: 0.08977868 | E12: 0.14851579 | F12: 0.22585094 | G12: 0.32935999 | H12: 0.44768827 | I12: 0.56728174 | J12: 0.69175235 | K12: 0.82497564 | L12: 0.97122732 | M12: 1.1353593 | N12: 1.3228774 | O12: 1.5399254 | P12: 1.7932093 | Q12: 2.0898956 | R12: 2.4223556 | S12: 2.7784097 | T12: 3.1575395 | U12: 3.5587584 | V12: 3.9806984 | W12: 4.4217609 | X12: 4.8802303 | Y12: 5.3543406 | Z12: 5.8423079 | AA12: 6.342344 | AB12: 6.8526602 | AC12: 7.3714682 | AD12: 7.8969785 | AE12: 8.4274013 | AF12: 8.9609465 | AG12: 9.4958245 | AH12: 10.03025 | AI12: 10.562443 | AJ12: 11.090636 | AK12: 11.613078
... A26: 100*ds_0/gdp_0*(ds_2/ds_0-1) | B26: 0 | C26: 0 | D26: 0 | E26: 0 | F26: 0 | G26: 0 | H26: 0 | I26: 0 | J26: 0 | K26: 0 | L26: 0 | M26: 0 | N26: 0 | O26: 0 | P26: 0 | Q26: 0 | R26: 0 | S26: 0 | T26: 0 | U26: 0 | V26: 0 | W26: 0 | X26: 0 | Y26: 0 | Z26: 0 | AA26: 0 | AB26: 0 | AC26: 0 | AD26: 0 | AE26: 0 | AF26: 0 | AG26: 0 | AH26: 0 | AI26: 0 | AJ26: 0 | AK26: 0

Sheet Baseline
A1: @date | B1: 42005 | C1: 42370 | D1: 42736 | E1: 43101 | F1: 43466 | G1: 43831 | H1: 44197 | I1: 44562 | J1: 44927 | K1: 45292 | L1: 45658 | M1: 46023 | N1: 46388 | O1: 46753 | P1: 47119 | Q1: 47484 | R1: 47849 | S1: 48214 | T1: 48580 | U1: 48945 | V1: 49310 | W1: 49675 | X1: 50041 | Y1: 50406 | Z1: 50771 | AA1: 51136 | AB1: 51502 | AC1: 51867 | AD1: 52232 | AE1: 52597 | AF1: 52963 | AG1: 53328 | AH1: 53693 | AI1: 54058 | AJ1: 54424 | AK1: 54789
A2: @pch(gdp_0) | B2: 0.0115225 | C2: 0.010855574 | D2: 0.010728383 | E2: 0.010808991 | F2: 0.010953896 | G2: 0.011108712 | H2: 0.011252093 | I2: 0.011375473 | J2: 0.011476237 | K2: 0.011554988 | L2: 0.011614092 | M2: 0.011656738 | N2: 0.011686314 | O2: 0.011706003 | P2: 0.011718548 | Q2: 0.011726136 | R2: 0.011730408 | S2: 0.011732513 | T2: 0.011733198 | U2: 0.011732909 | V2: 0.011731877 | W2: 0.011730202 | X2: 0.011727914 | Y2: 0.011725016 | Z2: 0.011721512 | AA2: 0.011717423 | AB2: 0.011712793 | AC2: 0.011707688 | AD2: 0.011702187 | AE2: 0.011696385 | AF2: 0.01169038 | AG2: 0.011684266 | AH2: 0.011678133 | AI2: 0.011672062 | AJ2: 0.011666121 | AK2: 0.011660368
A3: @pch(pch_0) | B3: 0.02 | C3: 0.019898733 | D3: 0.019777198 | E3: 0.019685451 | F3: 0.019635261 | G3: 0.019621524 | H3: 0.019635207 | I3: 0.019668198 | J3: 0.019714317 | K3: 0.019769024 | L3: 0.019828899 | M3: 0.019891268 | N3: 0.019953996 | O3: 0.020015379 | P3: 0.0200741 | Q3: 0.020129185 | R3: 0.020179956 | S3: 0.020225984 | T3: 0.020267047 | U3: 0.020303071 | V3: 0.020334108 | W3: 0.020360285 | X3: 0.020381796 | Y3: 0.020398879 | Z3: 0.020411798 | AA3: 0.020420846 | AB3: 0.020426323 | AC3: 0.020428547 | AD3: 0.020427835 | AE3: 0.020424509 | AF3: 0.020418888 | AG3: 0.020411284 | AH3: 0.020402003 | AI3: 0.020391336 | AJ3: 0.020379557 | AK3: 0.020366929
A4: unr_0 | B4: 0.14211338 | C4: 0.14239253 | D4: 0.14284801 | E4: 0.14332745 | F4: 0.14372958 | G4: 0.14400924 | H4: 0.14415905 | I4: 0.14419204 | J4: 0.14412979 | K4: 0.14399556 | L4: 0.14381068 | M4: 0.14359297 | N4: 0.14335631 | O4: 0.14311086 | P4: 0.1428636 | Q4: 0.14261895 | R4: 0.14237946 | S4: 0.14214634 | T4: 0.14191994 | U4: 0.14170015 | V4: 0.1414866 | W4: 0.14127888 | X4: 0.1410766 | Y4: 0.14087947 | Z4: 0.14068727 | AA4: 0.14049986 | AB4: 0.14031716 | AC4: 0.14013913 | AD4: 0.13996573 | AE4: 0.13979691 | AF4: 0.13963262 | AG4: 0.13947277 | AH4: 0.13931725 | AI4: 0.13916591 | AJ4: 0.13901859 | AK4: 0.13887513
A5: rdebt_g_val_0 | B5: 0.958 | C5: 0.95897527 | D5: 0.96058315 | E5: 0.96263011 | F5: 0.96497124 | G5: 0.96748013 | H5: 0.97004802 | I5: 0.97258712 | J5: 0.97503146 | K5: 0.97733497 | L5: 0.97946806 | M5: 0.98141365 | N5: 0.98316355 | O5: 0.98471534 | P5: 0.98607014 | Q5: 0.98723105 | R5: 0.98820223 | S5: 0.98898846 | T5: 0.98959493 | U5: 0.99002733 | V5: 0.99029187 | W5: 0.99039536 | X5: 0.9903453 | Y5: 0.99014987 | Z5: 0.98981781 | AA5: 0.98935841 | AB5: 0.98878129 | AC5: 0.98809631 | AD5: 0.98731335 | AE5: 0.98644221 | AF5: 0.98549246 | AG5: 0.98447326 | AH5: 0.98339337 | AI5: 0.98226095 | AJ5: 0.9810836 | AK5: 0.97986829
A6: rbal_g_prim_val_0 | B6: -0.0092851687 | C6: -0.009535818 | D6: -0.0099463988 | E6: -0.010405279 | F6: -0.01083516 | G6: -0.011192718 | H6: -0.011460251 | I6: -0.011637088 | J6: -0.011732352 | K6: -0.011759577 | L6: -0.011733133 | M6: -0.011666162 | N6: -0.011569623 | O6: -0.011452068 | P6: -0.011319842 | Q6: -0.01117748 | R6: -0.011028163 | S6: -0.010874132 | T6: -0.010717037 | U6: -0.010558181 | V6: -0.01039869 | W6: -0.010239614 | X6: -0.010081963 | Y6: -0.0099267198 | Z6: -0.0097748208 | AA6: -0.0096271357 | AB6: -0.0094844412 | AC6: -0.0093473998 | AD6: -0.0092165451 | AE6: -0.0090922748 | AF6: -0.0089748501 | AG6: -0.0088644027 | AH6: -0.0087609443 | AI6: -0.0086643811 | AJ6: -0.0085745292 | AK6: -0.00849113
A7: rbal_trade_val_0 | B7: -0.01081433 | C7: -0.011339149 | D7: -0.011886849 | E7: -0.012303141 | F7: -0.012567896 | G7: -0.012711325 | H7: -0.01277292 | I7: -0.012784958 | J7: -0.012769054 | K7: -0.012737939 | L7: -0.012698369 | M7: -0.012653596 | N7: -0.012605063 | O7: -0.0125534 | P7: -0.012498953 | Q7: -0.012442025 | R7: -0.012382953 | S7: -0.012322107 | T7: -0.012259858 | U7: -0.012196549 | V7: -0.012132469 | W7: -0.012067848 | X7: -0.012002849 | Y7: -0.011937583 | Z7: -0.011872113 | AA7: -0.011806466 | AB7: -0.01174065 | AC7: -0.011674654 | AD7: -0.011608464 | AE7: -0.011542065 | AF7: -0.011475444 | AG7: -0.011408593 | AH7: -0.011341509 | AI7: -0.011274195 | AJ7: -0.011206656 | AK7: -0.011138905
A8: ems_co2_0 | B8: 350.29271 | C8: 352.43131 | D8: 354.06052 | E8: 355.7321 | F8: 357.61599 | G8: 359.72996 | H8: 362.04263 | I8: 364.51423 | J8: 367.1103 | K8: 369.80468 | L8: 372.57878 | M8: 375.41988 | N8: 378.31942 | O8: 381.27176 | P8: 384.27304 | Q8: 387.32088 | R8: 390.41383 | S8: 393.55096 | T8: 396.73175 | U8: 399.95582 | V8: 403.22297 | W8: 406.53308 | X8: 409.88608 | Y8: 413.28196 | Z8: 416.72071 | AA8: 420.20234 | AB8: 423.72691 | AC8: 427.29449 | AD8: 430.90523 | AE8: 434.55929 | AF8: 438.25689 | AG8: 441.9983 | AH8: 445.78382 | AI8: 449.61382 | AJ8: 453.48869 | AK8: 457.40889
A9: pop | B9: 66422.5 | C9: 66588.556 | D9: 66755.028 | E9: 66921.915 | F9: 67089.22 | G9: 67256.943 | H9: 67425.085 | I9: 67593.648 | J9: 67762.632 | K9: 67932.039 | L9: 68101.869 | M9: 68272.124 | N9: 68442.804 | O9: 68613.911 | P9: 68785.446 | Q9: 68957.409 | R9: 69129.803 | S9: 69302.627 | T9: 69475.884 | U9: 69649.574 | V9: 69823.698 | W9: 69998.257 | X9: 70173.252 | Y9: 70348.686 | Z9: 70524.557 | AA9: 70700.869 | AB9: 70877.621 | AC9: 71054.815 | AD9: 71232.452 | AE9: 71410.533 | AF9: 71589.059 | AG9: 71768.032 | AH9: 71947.452 | AI9: 72127.321 | AJ9: 72307.639 | AK9: 72488.408
A10: gdp_0 | B10: 2196558.3 | C10: 2220403.2 | D10: 2244224.5 | E10: 2268482.3 | F10: 2293331 | G10: 2318807 | H10: 2344898.4 | I10: 2371572.7 | J10: 2398789.5 | K10: 2426507.4 | L10: 2454689.1 | M10: 2483302.8 | N10: 2512323.4 | O10: 2541732.7 | P10: 2571518.1 | Q10: 2601672.1 | R10: 2632190.8 | S10: 2663073 | T10: 2694319.4 | U10: 2725931.6 | V10: 2757911.9 | W10: 2790262.7 | X10: 2822986.7 | Y10: 2856086.2 | Z10: 2889563.9 | AA10: 2923422.1 | AB10: 2957663.6 | AC10: 2992291 | AD10: 3027307.3 | AE10: 3062715.9 | AF10: 3098520.2 | AG10: 3134724.1 | AH10: 3171331.8 | AI10: 3208347.8 | AJ10: 3245776.8 | AK10: 3283623.8
A11: pch_0 | B11: 1 | C11: 1.0198987 | D11: 1.0400695 | E11: 1.0605437 | F11: 1.0813678 | G11: 1.1025858 | H11: 1.1242353 | I11: 1.146347 | J11: 1.1689465 | K11: 1.1920554 | L11: 1.2156926 | M11: 1.2398742 | N11: 1.2646147 | O11: 1.2899264 | P11: 1.3158205 | Q11: 1.3423069 | R11: 1.3693946 | S11: 1.397092 | T11: 1.4254069 | U11: 1.454347 | V11: 1.4839199 | W11: 1.5141329 | X11: 1.5449937 | Y11: 1.5765098 | Z11: 1.6086892 | AA11: 1.64154 | AB11: 1.6750706 | AC11: 1.7092899 | AD11: 1.744207 | AE11: 1.7798315 | AF11: 1.8161737 | AG11: 1.8532442 | AH11: 1.891054 | AI11: 1.9296152 | AJ11: 1.9689399 | AK11: 2.0090411
A12: ems_ch_co2_0 | B12: 119.49049 | C12: 119.25476 | D12: 118.5914 | E12: 117.94146 | F12: 117.43342 | G12: 117.07744 | H12: 116.84707 | I12: 116.7106 | J12: 116.64129 | K12: 116.61924 | L12: 116.63059 | M12: 116.66599 | N12: 116.71922 | O12: 116.78609 | P12: 116.86366 | Q12: 116.94993 | R12: 117.04357 | S12: 117.1436 | T12: 117.24929 | U12: 117.36001 | V12: 117.4753 | W12: 117.59478 | X12: 117.71816 | Y12: 117.84518 | Z12: 117.97565 | AA12: 118.10939 | AB12: 118.24629 | AC12: 118.38623 | AD12: 118.52913 | AE12: 118.67492 | AF12: 118.82357 | AG12: 118.97505 | AH12: 119.12935 | AI12: 119.28646 | AJ12: 119.44639 | AK12: 119.60915
... A28: ems_co2_cote_0 | B28: 17.86536 | C28: 18.049747 | D28: 18.22732 | E28: 18.406258 | F28: 18.589806 | G28: 18.778708 | H28: 18.972724 | I28: 19.17133 | J28: 19.373997 | K28: 19.580285 | L28: 19.789857 | M28: 20.002471 | N28: 20.217959 | O28: 20.436215 | P28: 20.657178 | Q28: 20.880819 | R28: 21.107135 | S28: 21.336135 | T28: 21.567842 | U28: 21.802281 | V28: 22.039486 | W28: 22.279487 | X28: 22.522317 | Y28: 22.768007 | Z28: 23.016586 | AA28: 23.268084 | AB28: 23.52253 | AC28: 23.779952 | AD28: 24.040379 | AE28: 24.303843 | AF28: 24.570373 | AG28: 24.840001 | AH28: 25.112761 | AI28: 25.388689 | AJ28: 25.667821 | AK28: 25.950193
