Workbook
Name formatResults: [1]ResultsEXR10!$A$50

Sheet Feuil1
B1: 42005 | C1: 42370 | D1: 42736 | E1: 43101 | F1: 43466 | G1: 43831 | H1: 44197 | I1: 44562 | J1: 44927 | K1: 45292 | L1: 45658 | M1: 46023 | N1: 46388 | O1: 46753 | P1: 47119 | Q1: 47484 | R1: 47849 | S1: 48214 | T1: 48580 | U1: 48945 | V1: 49310 | W1: 49675 | X1: 50041 | Y1: 50406 | Z1: 50771 | AA1: 51136 | AB1: 51502 | AC1: 51867 | AD1: 52232 | AE1: 52597 | AF1: 52963 | AG1: 53328 | AH1: 53693 | AI1: 54058 | AJ1: 54424 | AK1: 54789
A2: y_2 | B2: =Capital!B2/Production!B2 -> 1.3555282 | C2: =Capital!C2/Production!C2 -> 1.3505388 | D2: =Capital!D2/Production!D2 -> 1.3470192 | E2: =Capital!E2/Production!E2 -> 1.3447498 | F2: =Capital!F2/Production!F2 -> 1.3404508 | G2: =Capital!G2/Production!G2 -> 1.33118 | H2: =Capital!H2/Production!H2 -> 1.3232296 | I2: =Capital!I2/Production!I2 -> 1.3160229 | ... AK2: =Capital!AK2/Production!AK2 -> 1.369046
A3: y_0 | B3: =Capital!B3/Production!B3 -> 1.3555282 | C3: =Capital!C3/Production!C3 -> 1.3505388 | D3: =Capital!D3/Production!D3 -> 1.3470192 | E3: =Capital!E3/Production!E3 -> 1.3447498 | F3: =Capital!F3/Production!F3 -> 1.3404508 | G3: =Capital!G3/Production!G3 -> 1.33118 | H3: =Capital!H3/Production!H3 -> 1.322512 | I3: =Capital!I3/Production!I3 -> 1.3151374 | ... AK3: =Capital!AK3/Production!AK3 -> 1.4162897
A4: y_sagr_2 | B4: =Capital!B4/Production!B4 -> 0.57725408 | C4: =Capital!C4/Production!C4 -> 0.5762539 | D4: =Capital!D4/Production!D4 -> 0.57544883 | E4: =Capital!E4/Production!E4 -> 0.57472252 | F4: =Capital!F4/Production!F4 -> 0.57297005 | G4: =Capital!G4/Production!G4 -> 0.56859041 | H4: =Capital!H4/Production!H4 -> 0.56418904 | I4: =Capital!I4/Production!I4 -> 0.5598063 | ... AK4: =Capital!AK4/Production!AK4 -> 0.57446702
A5: y_sagr_0 | B5: =Capital!B5/Production!B5 -> 0.57725408 | C5: =Capital!C5/Production!C5 -> 0.5762539 | D5: =Capital!D5/Production!D5 -> 0.57544883 | E5: =Capital!E5/Production!E5 -> 0.57472252 | F5: =Capital!F5/Production!F5 -> 0.57297005 | G5: =Capital!G5/Production!G5 -> 0.56859041 | H5: =Capital!H5/Production!H5 -> 0.56381042 | I5: =Capital!I5/Production!I5 -> 0.55950462 | ... AK5: =Capital!AK5/Production!AK5 -> 0.58377488
A6: y_sfor_2 | B6: =Capital!B6/Production!B6 -> 0.28237955 | C6: =Capital!C6/Production!C6 -> 0.28802041 | D6: =Capital!D6/Production!D6 -> 0.2931403 | E6: =Capital!E6/Production!E6 -> 0.29800872 | F6: =Capital!F6/Production!F6 -> 0.30097404 | G6: =Capital!G6/Production!G6 -> 0.30275836 | H6: =Capital!H6/Production!H6 -> 0.30377946 | I6: =Capital!I6/Production!I6 -> 0.30598273 | ... AK6: =Capital!AK6/Production!AK6 -> 0.27797914
A7: y_sfor_0 | B7: =Capital!B7/Production!B7 -> 0.28237955 | C7: =Capital!C7/Production!C7 -> 0.28802041 | D7: =Capital!D7/Production!D7 -> 0.2931403 | E7: =Capital!E7/Production!E7 -> 0.29800872 | F7: =Capital!F7/Production!F7 -> 0.30097404 | G7: =Capital!G7/Production!G7 -> 0.30275836 | H7: =Capital!H7/Production!H7 -> 0.30370325 | I7: =Capital!I7/Production!I7 -> 0.30423268 | ... AK7: =Capital!AK7/Production!AK7 -> 0.28951048
A8: y_sfoo_2 | B8: =Capital!B8/Production!B8 -> 0.47229749 | C8: =Capital!C8/Production!C8 -> 0.47080096 | D8: =Capital!D8/Production!D8 -> 0.46966523 | E8: =Capital!E8/Production!E8 -> 0.46846533 | F8: =Capital!F8/Production!F8 -> 0.46652099 | G8: =Capital!G8/Production!G8 -> 0.46270907 | H8: =Capital!H8/Production!H8 -> 0.45918745 | I8: =Capital!I8/Production!I8 -> 0.45570148 | ... AK8: =Capital!AK8/Production!AK8 -> 0.46389281
A9: y_sfoo_0 | B9: =Capital!B9/Production!B9 -> 0.47229749 | C9: =Capital!C9/Production!C9 -> 0.47080096 | D9: =Capital!D9/Production!D9 -> 0.46966523 | E9: =Capital!E9/Production!E9 -> 0.46846533 | F9: =Capital!F9/Production!F9 -> 0.46652099 | G9: =Capital!G9/Production!G9 -> 0.46270907 | H9: =Capital!H9/Production!H9 -> 0.45891989 | I9: =Capital!I9/Production!I9 -> 0.45562924 | ... AK9: =Capital!AK9/Production!AK9 -> 0.47916195
A10: y_sveh_2 | B10: =Capital!B10/Production!B10 -> 3.1979996 | C10: =Capital!C10/Production!C10 -> 3.1499425 | D10: =Capital!D10/Production!D10 -> 3.1157701 | E10: =Capital!E10/Production!E10 -> 3.0995511 | F10: =Capital!F10/Production!F10 -> 3.0736169 | G10: =Capital!G10/Production!G10 -> 3.0290922 | H10: =Capital!H10/Production!H10 -> 3.0091748 | I10: =Capital!I10/Production!I10 -> 2.9956021 | ... AK10: =Capital!AK10/Production!AK10 -> 3.2077483
A11: y_sveh_0 | B11: =Capital!B11/Production!B11 -> 3.1979996 | C11: =Capital!C11/Production!C11 -> 3.1499425 | D11: =Capital!D11/Production!D11 -> 3.1157701 | E11: =Capital!E11/Production!E11 -> 3.0995511 | F11: =Capital!F11/Production!F11 -> 3.0736169 | G11: =Capital!G11/Production!G11 -> 3.0290922 | H11: =Capital!H11/Production!H11 -> 3.005323 | I11: =Capital!I11/Production!I11 -> 2.988729 | ... AK11: =Capital!AK11/Production!AK11 -> 3.2110958
A12: y_sgla_2 | B12: =Capital!B12/Production!B12 -> 0.72812366 | C12: =Capital!C12/Production!C12 -> 0.72608803 | D12: =Capital!D12/Production!D12 -> 0.72477592 | E12: =Capital!E12/Production!E12 -> 0.72454027 | F12: =Capital!F12/Production!F12 -> 0.72288322 | G12: =Capital!G12/Production!G12 -> 0.71752021 | H12: =Capital!H12/Production!H12 -> 0.7117047 | I12: =Capital!I12/Production!I12 -> 0.70653151 | ... AK12: =Capital!AK12/Production!AK12 -> 0.68495569
A13: y_sgla_0 | B13: =Capital!B13/Production!B13 -> 0.72812366 | C13: =Capital!C13/Production!C13 -> 0.72608803 | D13: =Capital!D13/Production!D13 -> 0.72477592 | E13: =Capital!E13/Production!E13 -> 0.72454027 | F13: =Capital!F13/Production!F13 -> 0.72288322 | G13: =Capital!G13/Production!G13 -> 0.71752021 | H13: =Capital!H13/Production!H13 -> 0.7112918 | I13: =Capital!I13/Production!I13 -> 0.70527576 | ... AK13: =Capital!AK13/Production!AK13 -> 0.71328007
... A67: y_seot_0 | B67: =Capital!B67/Production!B67 -> 0.59456653 | C67: =Capital!C67/Production!C67 -> 0.5961179 | D67: =Capital!D67/Production!D67 -> 0.60027416 | E67: =Capital!E67/Production!E67 -> 0.60467611 | F67: =Capital!F67/Production!F67 -> 0.60765956 | G67: =Capital!G67/Production!G67 -> 0.60701893 | H67: =Capital!H67/Production!H67 -> 0.60566075 | I67: =Capital!I67/Production!I67 -> 0.60431762 | ... AK67: =Capital!AK67/Production!AK67 -> 0.5992089

Sheet Carbontax
A1: _date_ | B1: 42005 | C1: 42370 | D1: 42736 | E1: 43101 | F1: 43466 | G1: 43831 | H1: 44197 | I1: 44562 | J1: 44927 | K1: 45292 | L1: 45658 | M1: 46023 | N1: 46388 | O1: 46753 | P1: 47119 | Q1: 47484 | R1: 47849 | S1: 48214 | T1: 48580 | U1: 48945 | V1: 49310 | W1: 49675 | X1: 50041 | Y1: 50406 | Z1: 50771 | AA1: 51136 | AB1: 51502 | AC1: 51867 | AD1: 52232 | AE1: 52597 | AF1: 52963 | AG1: 53328 | AH1: 53693 | AI1: 54058 | AJ1: 54424 | AK1: 54789
A2: t2val_ch_0 | B2: 1732.612 | C2: 2615.9669 | D2: 3567.0639 | E2: 5114.2089 | F2: 5077.8121 | G2: 5101.9503 | H2: 5083.4882 | I2: 5084.4352 | J2: 5092.8628 | K2: 5104.3817 | L2: 5118.9897 | M2: 5133.5219 | N2: 5148.6038 | O2: 5164.7041 | P2: 5182.0087 | Q2: 5200.4646 | R2: 5219.72 | S2: 5239.4286 | T2: 5259.3202 | U2: 5279.1958 | V2: 5297.7286 | W2: 5316.4681 | X2: 5334.9093 | Y2: 5352.7993 | Z2: 5370.0333 | AA2: 5383.3415 | AB2: 5395.4154 | AC2: 5405.6475 | AD2: 5413.7299 | AE2: 5419.65 | AF2: 5423.5061 | AG2: 5426.0594 | AH2: 5428.0281 | AI2: 5429.951 | AJ2: 5432.2002 | AK2: 5435.0165
A3: t2val_ch_2 | B3: 1732.612 | C3: 2615.9669 | D3: 3567.0639 | E3: 5114.2089 | F3: 5077.8121 | G3: 5101.9503 | H3: 5083.4016 | I3: 7558.3488 | J3: 11221.039 | K3: 16630.939 | L3: 24606.033 | M3: 26058.076 | N3: 27718.371 | O3: 29544.396 | P3: 31516.83 | Q3: 33629.412 | R3: 36644.989 | S3: 39887.424 | T3: 43360.432 | U3: 47081.188 | V3: 51065.513 | W3: 54170.42 | X3: 57463.325 | Y3: 60941.538 | Z3: 64608.768 | AA3: 68433.606 | AB3: 71596.391 | AC3: 74895.65 | AD3: 78322.977 | AE3: 81876.745 | AF3: 85559.292 | AG3: 88697.126 | AH3: 91934.184 | AI3: 95264.662 | AJ3: 98687.011 | AK3: 102202
A4: t2val_sec_0 | B4: 3328.0856 | C4: 5086.3384 | D4: 7054.5326 | E4: 10260.969 | F4: 10303.774 | G4: 10552.493 | H4: 10774.329 | I4: 11006.176 | J4: 11242.655 | K4: 11482.985 | L4: 11730.237 | M4: 11983.012 | N4: 12244.607 | O4: 12516.7 | P4: 12799.604 | Q4: 13092.843 | R4: 13380.416 | S4: 13672.192 | T4: 13969.931 | U4: 14273.986 | V4: 14583.123 | W4: 14884.395 | X4: 15188.173 | Y4: 15496.727 | Z4: 15810.826 | AA4: 16126.819 | AB4: 16377.537 | AC4: 16612.474 | AD4: 16842.039 | AE4: 17069.266 | AF4: 17295.577 | AG4: 17565.465 | AH4: 17849.277 | AI4: 18141.272 | AJ4: 18440.2 | AK4: 18745.712
A5: t2val_sec_2 | B5: 3328.0856 | C5: 5086.3384 | D5: 7054.5326 | E5: 10260.969 | F5: 10303.774 | G5: 10552.493 | H5: 10767.177 | I5: 16338.152 | J5: 24677.712 | K5: 37100.433 | L5: 55507.258 | M5: 59200.597 | N5: 63498.026 | O5: 68409.956 | P5: 73921.148 | Q5: 80017.517 | R5: 88467.001 | S5: 97687.653 | T5: 107699.94 | U5: 118554.67 | V5: 130316.85 | W5: 139867.47 | X5: 150085.07 | Y5: 161036.79 | Z5: 172771.17 | AA5: 185288.51 | AB5: 196108.92 | AC5: 207566.76 | AD5: 219710.03 | AE5: 232571.34 | AF5: 246183.1 | AG5: 258528.8 | AH5: 271544.16 | AI5: 285250.17 | AJ5: 299659.38 | AK5: 314785.11
A6: t2val_ci_0 | B6: 3106.9939 | C6: 4746.3343 | D6: 6576.9956 | E6: 9554.4215 | F6: 9587.9691 | G6: 9824.1278 | H6: 10031.748 | I6: 10248.588 | J6: 10469.565 | K6: 10693.971 | L6: 10924.799 | M6: 11160.762 | N6: 11405.067 | O6: 11659.334 | P6: 11923.849 | Q6: 12198.133 | R6: 12466.939 | S6: 12739.693 | T6: 13018.039 | U6: 13302.273 | V6: 13591.177 | W6: 13872.419 | X6: 14155.886 | Y6: 14443.695 | Z6: 14736.54 | AA6: 15030.905 | AB6: 15262.893 | AC6: 15479.882 | AD6: 15691.731 | AE6: 15901.26 | AF6: 16109.78 | AG6: 16359.638 | AH6: 16622.443 | AI6: 16892.785 | AJ6: 17169.558 | AK6: 17452.513
A7: t2val_ci_2 | B7: 3106.9939 | C7: 4746.3343 | D7: 6576.9956 | E7: 9554.4215 | F7: 9587.9691 | G7: 9824.1278 | H7: 10024.929 | I7: 15208.379 | J7: 22959.276 | K7: 34489.258 | L7: 51544.176 | M7: 54936.516 | N7: 58906.306 | O7: 63459.737 | P7: 68579.227 | Q7: 74249.053 | R7: 82101.584 | S7: 90665.222 | T7: 99955.614 | U7: 110017.65 | V7: 120909.79 | W7: 129743.28 | X7: 139191.33 | Y7: 149314.99 | Z7: 160157.46 | AA7: 171715.97 | AB7: 181694.94 | AC7: 192259.79 | AD7: 203453.27 | AE7: 215303.65 | AF7: 227839.05 | AG7: 239196.29 | AH7: 251166.74 | AI7: 263767.71 | AJ7: 277008.8 | AK7: 290900.55
A8: t2val_y_0 | B8: 0.39942416 | C8: 0.61419804 | D8: 0.86273467 | E8: 1.2778673 | F8: 1.2968857 | G8: 1.3235325 | H8: 1.3530777 | I8: 1.3835707 | J8: 1.4147564 | K8: 1.4466901 | L8: 1.4799139 | M8: 1.5139633 | N8: 1.5491788 | O8: 1.5856032 | P8: 1.6231345 | Q8: 1.6616173 | R8: 1.6987733 | S8: 1.7360457 | T8: 1.7735126 | U8: 1.8112386 | V8: 1.8490362 | W8: 1.8853194 | X8: 1.9216464 | Y8: 1.9582347 | Z8: 1.9952588 | AA8: 2.0320802 | AB8: 2.0598471 | AC8: 2.0857687 | AD8: 2.1105976 | AE8: 2.1348494 | AF8: 2.1589778 | AG8: 2.1893307 | AH8: 2.2218603 | AI8: 2.2563992 | AJ8: 2.292854 | AK8: 2.3310978
A9: t2val_y_2 | B9: 0.39942416 | C9: 0.61419804 | D9: 0.86273467 | E9: 1.2778673 | F9: 1.2968857 | G9: 1.3235325 | H9: 1.3520955 | I9: 2.0647454 | J9: 3.1554134 | K9: 4.8272263 | L9: 7.3965186 | M9: 8.0245402 | N9: 8.7074214 | O9: 9.453067 | P9: 10.264827 | Q9: 11.145054 | R9: 12.356291 | S9: 13.688299 | T9: 15.149943 | U9: 16.752915 | V9: 18.508816 | W9: 19.952216 | X9: 21.492627 | Y9: 23.140782 | Z9: 24.906588 | AA9: 26.789793 | AB9: 28.417279 | AC9: 30.131989 | AD9: 31.944696 | AE9: 33.865426 | AF9: 35.904052 | AG9: 37.753373 | AH9: 39.70187 | AI9: 41.757933 | AJ9: 43.928669 | AK9: 46.220744
A10: t2val_mat_0 | B10: 220.69222 | C10: 339.3899 | D10: 476.6742 | E10: 705.26956 | F10: 714.50787 | G10: 727.04198 | H10: 741.22729 | I10: 756.20448 | J10: 771.67569 | K10: 787.56729 | L10: 803.95721 | M10: 820.73648 | N10: 837.99103 | O10: 855.77978 | P10: 874.13184 | Q10: 893.0489 | R10: 911.7783 | S10: 930.76269 | T10: 950.1181 | U10: 969.90166 | V10: 990.09706 | W10: 1010.0901 | X10: 1030.3655 | Y10: 1051.0738 | Z10: 1072.2912 | AA10: 1093.8821 | AB10: 1112.5837 | AC10: 1130.506 | AD10: 1148.1969 | AE10: 1165.8708 | AF10: 1183.6386 | AG10: 1203.6377 | AH10: 1224.6123 | AI10: 1246.2315 | AJ10: 1268.3487 | AK10: 1290.8674
A11: t2val_mat_2 | B11: 220.69222 | C11: 339.3899 | D11: 476.6742 | E11: 705.26956 | F11: 714.50787 | G11: 727.04198 | H11: 740.89542 | I11: 1127.7085 | J11: 1715.2802 | K11: 2606.3481 | L11: 3955.6855 | M11: 4256.0567 | N11: 4583.013 | O11: 4940.7651 | P11: 5331.6562 | Q11: 5757.3185 | R11: 6353.0605 | S11: 7008.7419 | T11: 7729.1742 | U11: 8520.2648 | V11: 9388.5524 | W11: 10104.235 | X11: 10872.244 | Y11: 11698.656 | Z11: 12588.805 | AA11: 13545.744 | AB11: 14385.559 | AC11: 15276.846 | AD11: 16224.81 | AE11: 17233.821 | AF11: 18308.147 | AG11: 19294.761 | AH11: 20337.727 | AI11: 21440.701 | AJ11: 22606.654 | AK11: 23838.341

Sheet Production
A1: _date_ | B1: 42005 | C1: 42370 | D1: 42736 | E1: 43101 | F1: 43466 | G1: 43831 | H1: 44197 | I1: 44562 | J1: 44927 | K1: 45292 | L1: 45658 | M1: 46023 | N1: 46388 | O1: 46753 | P1: 47119 | Q1: 47484 | R1: 47849 | S1: 48214 | T1: 48580 | U1: 48945 | V1: 49310 | W1: 49675 | X1: 50041 | Y1: 50406 | Z1: 50771 | AA1: 51136 | AB1: 51502 | AC1: 51867 | AD1: 52232 | AE1: 52597 | AF1: 52963 | AG1: 53328 | AH1: 53693 | AI1: 54058 | AJ1: 54424 | AK1: 54789
A2: y_2 | B2: 3853438.3 | C2: 3913578.5 | D2: 3971218.3 | E2: 4025747.4 | F2: 4088090.5 | G2: 4171089.1 | H2: 4255554.7 | I2: 4342547 | J2: 4432219.4 | K2: 4525782.4 | L2: 4625280.2 | M2: 4723147.2 | N2: 4824685 | O2: 4930394 | P2: 5039255 | Q2: 5150165.3 | R2: 5259436.7 | S2: 5368036.8 | T2: 5475761.8 | U2: 5582901.7 | V2: 5689329.6 | W2: 5790395.1 | X2: 5890999 | Y2: 5992035.9 | Z2: 6093973.3 | AA2: 6195304.4 | AB2: 6292128.3 | AC2: 6388991.9 | AD2: 6486842.5 | AE2: 6586329.2 | AF2: 6687927.9 | AG2: 6790083.8 | AH2: 6894507 | AI2: 7001529.6 | AJ2: 7111264.5 | AK2: 7223728.3
A3: y_0 | B3: 3853438.3 | C3: 3913578.5 | D3: 3971218.3 | E3: 4025747.4 | F3: 4088090.5 | G3: 4171089.1 | H3: 4258072.3 | I3: 4346779.9 | J3: 4436969.4 | K3: 4528941.7 | L3: 4624036.2 | M3: 4721262.2 | N3: 4821551.4 | O3: 4925135.3 | P3: 5031896.1 | Q3: 5141558.2 | R3: 5248419.3 | S3: 5356236.8 | T3: 5465355.6 | U3: 5576004 | V3: 5687780.2 | W3: 5796504.1 | X3: 5906146.2 | Y3: 6017327 | Z3: 6130467.9 | AA3: 6244053 | AB3: 6335103 | AC3: 6421936.4 | AD3: 6506752.5 | AE3: 6590795.6 | AF3: 6674969.9 | AG3: 6775207.6 | AH3: 6880841.9 | AI3: 6990965.2 | AJ3: 7105125.9 | AK3: 7222951.4
A4: y_sagr_2 | B4: 81785.168 | C4: 82888.439 | D4: 83981.887 | E4: 85066.606 | F4: 86332.648 | G4: 88106.507 | H4: 90007.923 | I4: 92031.014 | J4: 94171.242 | K4: 96461.507 | L4: 98964.19 | M4: 101362.91 | N4: 103838.09 | O4: 106426.08 | P4: 109102.62 | Q4: 111834.02 | R4: 114526.35 | S4: 117190.46 | T4: 119806.2 | U4: 122372.6 | V4: 124881.46 | W4: 127203.03 | X4: 129474.07 | Y4: 131722.01 | Z4: 133961.98 | AA4: 136151.89 | AB4: 138191.28 | AC4: 140207.03 | AD4: 142227.83 | AE4: 144273.37 | AF4: 146358.16 | AG4: 148437.51 | AH4: 150561.28 | AI4: 152741.05 | AJ4: 154981.28 | AK4: 157283.28
A5: y_sagr_0 | B5: 81785.168 | C5: 82888.439 | D5: 83981.887 | E5: 85066.606 | F5: 86332.648 | G5: 88106.507 | H5: 90073.308 | I5: 92103.2 | J5: 94179.208 | K5: 96305.009 | L5: 98516.69 | M5: 100783.33 | N5: 103127.6 | O5: 105552.34 | P5: 108050.77 | Q5: 110612.54 | R5: 113085.98 | S5: 115567.18 | T5: 118061.32 | U5: 120572.71 | V5: 123088.87 | W5: 125504.21 | X5: 127922.47 | Y5: 130358.13 | Z5: 132822.79 | AA5: 135273.96 | AB5: 137122.38 | AC5: 138847.96 | AD5: 140500.8 | AE5: 142115.22 | AF5: 143721.43 | AG5: 145742 | AH5: 147907.47 | AI5: 150206.7 | AJ5: 152633.46 | AK5: 155179.32
A6: y_sfor_2 | B6: 6531.5683 | C6: 6468.742 | D6: 6408.5421 | E6: 6342.2118 | F6: 6308.1592 | G6: 6296.1724 | H6: 6296.7195 | I6: 6267.1529 | J6: 6214.7353 | K6: 6142.0059 | L6: 6051.8174 | M6: 6021.671 | N6: 6020.0963 | O6: 6031.7783 | P6: 6049.3757 | Q6: 6069.4396 | R6: 6083.1864 | S6: 6094.6671 | T6: 6104.7858 | U6: 6113.9856 | V6: 6120.9226 | W6: 6129.9608 | X6: 6141.5491 | Y6: 6154.4644 | Z6: 6168.1328 | AA6: 6177.8469 | AB6: 6187.9339 | AC6: 6200.3986 | AD6: 6214.6582 | AE6: 6230.3696 | AF6: 6247.3611 | AG6: 6266.4559 | AH6: 6287.7335 | AI6: 6310.7141 | AJ6: 6335.0963 | AK6: 6360.6719
A7: y_sfor_0 | B7: 6531.5683 | C7: 6468.742 | D7: 6408.5421 | E7: 6342.2118 | F7: 6308.1592 | G7: 6296.1724 | H7: 6298.4617 | I7: 6306.9025 | J7: 6319.7577 | K7: 6336.3597 | L7: 6359.0959 | M7: 6382.9666 | N7: 6408.7078 | O7: 6436.4219 | P7: 6466.0577 | Q7: 6497.5155 | R7: 6526.4599 | S7: 6556.4533 | T7: 6587.7495 | U7: 6620.4674 | V7: 6652.8847 | W7: 6683.8891 | X7: 6716.5874 | Y7: 6751.1066 | Z7: 6787.5339 | AA7: 6820.9432 | AB7: 6837.7323 | AC7: 6854.5058 | AD7: 6872.4813 | AE7: 6892.0273 | AF7: 6913.2884 | AG7: 6948.0476 | AH7: 6986.0718 | AI7: 7026.5394 | AJ7: 7069.145 | AK7: 7113.708
A8: y_sfoo_2 | B8: 157777.39 | C8: 160141.37 | D8: 162421.55 | E8: 164735.16 | F8: 167388.58 | G8: 170955.55 | H8: 174665.94 | I8: 178598.52 | J8: 182768.8 | K8: 187269.48 | L8: 192279.29 | M8: 196998.68 | N8: 201837.65 | O8: 206872.52 | P8: 212059.05 | Q8: 217337.24 | R8: 222574.11 | S8: 227766.58 | T8: 232884.33 | U8: 237932.5 | V8: 242890.92 | W8: 247538.62 | X8: 252093.09 | Y8: 256598.88 | Z8: 261083.42 | AA8: 265447.39 | AB8: 269540.96 | AC8: 273560.61 | AD8: 277559.8 | AE8: 281581.84 | AF8: 285660.94 | AG8: 289715.86 | AH8: 293835.97 | AI8: 298046.71 | AJ8: 302361.32 | AK8: 306787.27
A9: y_sfoo_0 | B9: 157777.39 | C9: 160141.37 | D9: 162421.55 | E9: 164735.16 | F9: 167388.58 | G9: 170955.55 | H9: 174776.8 | I9: 178674.69 | J9: 182632.66 | K9: 186655 | L9: 190821.51 | M9: 195073.93 | N9: 199468.89 | O9: 204019.4 | P9: 208713.72 | Q9: 213530.24 | R9: 218224.04 | S9: 222931.35 | T9: 227654.96 | U9: 232401.05 | V9: 237138.05 | W9: 241718.54 | X9: 246292.1 | Y9: 250879.64 | Z9: 255502.01 | AA9: 260058.82 | AB9: 263656.13 | AC9: 266996.58 | AD9: 270151.9 | AE9: 273189.37 | AF9: 276172.54 | AG9: 279786.37 | AH9: 283650.31 | AI9: 287762.87 | AJ9: 292116.35 | AK9: 296695.74
A10: y_sveh_2 | B10: 125550.78 | C10: 129068.3 | D10: 132266.42 | E10: 134863.11 | F10: 138072.48 | G10: 142471.63 | H10: 146017.79 | I10: 149474.06 | J10: 152984.99 | K10: 156592.38 | L10: 160229.73 | M10: 164105.04 | N10: 168186.25 | O10: 172313.61 | P10: 176425.62 | Q10: 180517.29 | R10: 184279 | S10: 187942.38 | T10: 191546.59 | U10: 195152.52 | V10: 198792.08 | W10: 202088.71 | X10: 205478.77 | Y10: 208964.77 | Z10: 212549.98 | AA10: 216201.46 | AB10: 219549.56 | AC10: 223038.57 | AD10: 226677.22 | AE10: 230468.38 | AF10: 234410.43 | AG10: 238387.08 | AH10: 242524.91 | AI10: 246813.42 | AJ10: 251242.97 | AK10: 255803.53
A11: y_sveh_0 | B11: 125550.78 | C11: 129068.3 | D11: 132266.42 | E11: 134863.11 | F11: 138072.48 | G11: 142471.63 | H11: 146219.5 | I11: 149876.64 | J11: 153568.41 | K11: 157385.65 | L11: 161387.5 | M11: 165499.06 | N11: 169747.8 | O11: 174112.91 | P11: 178580.37 | Q11: 183144.42 | R11: 187315.58 | S11: 191555.2 | T11: 195887.59 | U11: 200329.69 | V11: 204882.58 | W11: 209108.88 | X11: 213455.42 | Y11: 217948.28 | Z11: 222603.77 | AA11: 227395.81 | AB11: 230148.69 | AC11: 232972.55 | AD11: 235947.06 | AE11: 239101.37 | AF11: 242441.34 | AG11: 247334.61 | AH11: 252461.93 | AI11: 257759.36 | AJ11: 263193.46 | AK11: 268745.32
A12: y_sgla_2 | B12: 22084.892 | C12: 22401.864 | D12: 22699.258 | E12: 22959.581 | F12: 23268.984 | G12: 23724.178 | H12: 24225.888 | I12: 24735.017 | J12: 25227.255 | K12: 25690.641 | L12: 26116.194 | M12: 26540.177 | N12: 27005.878 | O12: 27522.509 | P12: 28084.763 | Q12: 28683.278 | R12: 29285.547 | S12: 29892.43 | T12: 30497.753 | U12: 31100.234 | V12: 31699.218 | W12: 32273.639 | X12: 32854.403 | Y12: 33447.425 | Z12: 34055.141 | AA12: 34671.59 | AB12: 35274.3 | AC12: 35889.652 | AD12: 36521.062 | AE12: 37169.901 | AF12: 37836.749 | AG12: 38515.485 | AH12: 39214.871 | AI12: 39935.103 | AJ12: 40674.943 | AK12: 41432.614
... A26: y_scon_2 | B26: 270916.74 | C26: 275024.44 | D26: 278703.89 | E26: 281671.37 | F26: 285340.34 | G26: 291433.84 | H26: 297854.99 | I26: 304158.65 | J26: 310127.36 | K26: 315671.24 | L26: 320868.95 | M26: 326291.63 | N26: 332325.14 | O26: 339109.9 | P26: 346622.52 | Q26: 354779.02 | R26: 363332.55 | S26: 372119.18 | T26: 381061.26 | U26: 390156.7 | V26: 399413.02 | W26: 408794.51 | X26: 418405.88 | Y26: 428316.47 | Z26: 438565.22 | AA26: 449077.95 | AB26: 459732.74 | AC26: 470538.45 | AD26: 481517.55 | AE26: 492694.92 | AF26: 504092.55 | AG26: 515695.3 | AH26: 527521.66 | AI26: 539579.23 | AJ26: 551865.52 | AK26: 564374.54
A27: y_scon_0 | B27: 270916.74 | C27: 275024.44 | D27: 278703.89 | E27: 281671.37 | F27: 285340.34 | G27: 291433.84 | H27: 297976.12 | I27: 304885.83 | J27: 311979.49 | K27: 319126.64 | L27: 326341.91 | M27: 333660.65 | N27: 341218.27 | O27: 349136.14 | P27: 357482.16 | Q27: 366278.42 | R27: 375373.86 | S27: 384796.61 | T27: 394569.92 | U27: 404708.2 | V27: 415185.93 | W27: 425882.56 | X27: 436836.2 | Y27: 448073.69 | Z27: 459606.84 | AA27: 471332.6 | AB27: 482539.73 | AC27: 493357.96 | AD27: 503888.31 | AE27: 514186.95 | AF27: 524275.97 | AG27: 534610.86 | AH27: 545085.88 | AI27: 555604.82 | AJ27: 566099.64 | AK27: 576524.4 | AL27: =AK26/AK27 -> 0.97892569
A28: y_srai_2 | B28: 6786.595 | C28: 6886.0416 | D28: 6975.4613 | E28: 7050.7087 | F28: 7140.3838 | G28: 7276.5254 | H28: 7409.8002 | I28: 7547.9648 | J28: 7693.0316 | K28: 7847.5528 | L28: 8013.4174 | M28: 8180.7172 | N28: 8355.1971 | O28: 8535.5009 | P28: 8718.8645 | Q28: 8903.1257 | R28: 9081.1149 | S28: 9254.1336 | T28: 9421.327 | U28: 9583.2408 | V28: 9740.1661 | W28: 9884.6068 | X28: 10025.986 | Y28: 10166.116 | Z28: 10306.02 | AA28: 10443.796 | AB28: 10572.903 | AC28: 10702.29 | AD28: 10833.702 | AE28: 10968.147 | AF28: 11106.278 | AG28: 11245.625 | AH28: 11389.171 | AI28: 11537.333 | AJ28: 11690.138 | AK28: 11847.444
A29: y_srai_0 | B29: 6786.595 | C29: 6886.0416 | D29: 6975.4613 | E29: 7050.7087 | F29: 7140.3838 | G29: 7276.5254 | H29: 7413.9829 | I29: 7552.9893 | J29: 7693.8265 | K29: 7838.0142 | L29: 7988.1439 | M29: 8142.368 | N29: 8301.5208 | O29: 8465.2737 | P29: 8633.0154 | Q29: 8804.134 | R29: 8968.244 | S29: 9132.5193 | T29: 9297.648 | U29: 9464.0918 | V29: 9631.4237 | W29: 9791.8675 | X29: 9953.0699 | Y29: 10116.278 | Z29: 10282.351 | AA29: 10449.356 | AB29: 10575.386 | AC29: 10695.253 | AD29: 10813.084 | AE29: 10931.06 | AF29: 11050.763 | AG29: 11200.868 | AH29: 11361.207 | AI29: 11530.103 | AJ29: 11706.78 | AK29: 11890.555
A30: y_sroa_2 | B30: 78075.665 | C30: 79219.737 | D30: 80248.458 | E30: 81114.133 | F30: 82145.791 | G30: 83712.018 | H30: 85245.263 | I30: 86834.763 | J30: 88503.669 | K30: 90281.341 | L30: 92189.513 | M30: 94114.196 | N30: 96121.482 | O30: 98195.768 | P30: 100305.25 | Q30: 102425.07 | R30: 104472.73 | S30: 106463.2 | T30: 108386.66 | U30: 110249.38 | V30: 112054.71 | W30: 113716.41 | X30: 115342.9 | Y30: 116955.01 | Z30: 118564.51 | AA30: 120149.55 | AB30: 121634.84 | AC30: 123123.37 | AD30: 124635.18 | AE30: 126181.89 | AF30: 127771.01 | AG30: 129374.1 | AH30: 131025.51 | AI30: 132730.02 | AJ30: 134487.95 | AK30: 136297.67
A31: y_sroa_0 | B31: 78075.665 | C31: 79219.737 | D31: 80248.458 | E31: 81114.133 | F31: 82145.791 | G31: 83712.018 | H31: 85293.382 | I31: 86892.567 | J31: 88512.813 | K31: 90171.606 | L31: 91898.757 | M31: 93673.012 | N31: 95503.968 | O31: 97387.847 | P31: 99317.614 | Q31: 101286.23 | R31: 103174.22 | S31: 105064.1 | T31: 106963.81 | U31: 108878.64 | V31: 110803.7 | W31: 112649.5 | X31: 114504.04 | Y31: 116381.65 | Z31: 118292.22 | AA31: 120213.51 | AB31: 121663.41 | AC31: 123042.41 | AD31: 124397.98 | AE31: 125755.23 | AF31: 127132.34 | AG31: 128859.21 | AH31: 130703.8 | AI31: 132646.85 | AJ31: 134679.41 | AK31: 136793.64
A32: y_swat_2 | B32: 15431.435 | C32: 15813.187 | D32: 16192.649 | E32: 16537.964 | F32: 16885.228 | G32: 17286.586 | H32: 17740.761 | I32: 18220.407 | J32: 18713.673 | K32: 19216.217 | L32: 19712.465 | M32: 20205.726 | N32: 20719.87 | O32: 21251.644 | P32: 21796.274 | Q32: 22349.811 | R32: 22866.063 | S32: 23381.254 | T32: 23889.744 | U32: 24388.925 | V32: 24878.84 | W32: 25295.624 | X32: 25714.906 | Y32: 26140.123 | Z32: 26573.462 | AA32: 27015.876 | AB32: 27406.904 | AC32: 27820.809 | AD32: 28258.396 | AE32: 28718.779 | AF32: 29200.562 | AG32: 29684.478 | AH32: 30192.469 | AI32: 30723.168 | AJ32: 31274.568 | AK32: 31844.349
A33: y_swat_0 | B33: 15431.435 | C33: 15813.187 | D33: 16192.649 | E33: 16537.964 | F33: 16885.228 | G33: 17286.586 | H33: 17769.065 | I33: 18268.84 | J33: 18783.923 | K33: 19321.096 | L33: 19882.62 | M33: 20457.558 | N33: 21046.506 | O33: 21645.576 | P33: 22254.011 | Q33: 22872.704 | R33: 23430.015 | S33: 23997.826 | T33: 24577.834 | U33: 25171.884 | V33: 25781.703 | W33: 26339.687 | X33: 26915.85 | Y33: 27512.565 | Z33: 28131.925 | AA33: 28775.056 | AB33: 29114.989 | AC33: 29477.767 | AD33: 29866.216 | AE33: 30281.445 | AF33: 30723.443 | AG33: 31393.925 | AH33: 32091.26 | AI33: 32812.559 | AJ33: 33555.566 | AK33: 34318.531
A34: y_sair_2 | B34: 20630.344 | C34: 21087.717 | D34: 21481.476 | E34: 21761.426 | F34: 22113.477 | G34: 22733.766 | H34: 23340.91 | I34: 23930.499 | J34: 24493.261 | K34: 25024.592 | L34: 25515.761 | M34: 26017.499 | N34: 26611.535 | O34: 27290.921 | P34: 28030.247 | Q34: 28806.417 | R34: 29561.637 | S34: 30293.858 | T34: 30992.699 | U34: 31659.903 | V34: 32296.656 | W34: 32873.354 | X34: 33447.07 | Y34: 34021.203 | Z34: 34595.982 | AA34: 35155.791 | AB34: 35670.705 | AC34: 36190.676 | AD34: 36719.544 | AE34: 37259.328 | AF34: 37811.271 | AG34: 38364.967 | AH34: 38938.131 | AI34: 39530.856 | AJ34: 40141.726 | AK34: 40769.052
A35: y_sair_0 | B35: 20630.344 | C35: 21087.717 | D35: 21481.476 | E35: 21761.426 | F35: 22113.477 | G35: 22733.766 | H35: 23365.646 | I35: 24002.699 | J35: 24651.982 | K35: 25320.625 | L35: 26021.768 | M35: 26745.123 | N35: 27497.751 | O35: 28278.265 | P35: 29083.295 | Q35: 29909.421 | R35: 30696.806 | S35: 31491.444 | T35: 32294.148 | U35: 33106.261 | V35: 33924.3 | W35: 34702.983 | X35: 35489.317 | Y35: 36286.799 | Z35: 37098.896 | AA35: 37912.622 | AB35: 38484.673 | AC35: 39034.748 | AD35: 39572.298 | AE35: 40105.872 | AF35: 40643.528 | AG35: 41353.943 | AH35: 42108.719 | AI35: 42907.608 | AJ35: 43749.619 | AK35: 44632.676
A36: y_spri_2 | B36: 2017751.5 | C36: 2049826.6 | D36: 2080796.5 | E36: 2110679.6 | F36: 2144986 | G36: 2190809.1 | H36: 2237065.9 | I36: 2284889.5 | J36: 2334699 | K36: 2387552.7 | L36: 2445206.2 | M36: 2501430.2 | N36: 2559423.6 | O36: 2619575.7 | P36: 2681287 | Q36: 2743913.3 | R36: 2805738.3 | S36: 2866980.2 | T36: 2927552.7 | U36: 2987673.4 | V36: 3047246.7 | W36: 3103832.5 | X36: 3159778.8 | Y36: 3215629.9 | Z36: 3271675.1 | AA36: 3326903.3 | AB36: 3379428 | AC36: 3431429.8 | AD36: 3483559.9 | AE36: 3536289.6 | AF36: 3589975.6 | AG36: 3643773.1 | AH36: 3698587.5 | AI36: 3754679.9 | AJ36: 3812170.9 | AK36: 3871118.5
A37: y_spri_0 | B37: 2017751.5 | C37: 2049826.6 | D37: 2080796.5 | E37: 2110679.6 | F37: 2144986 | G37: 2190809.1 | H37: 2238370.5 | I37: 2286621.2 | J37: 2335478.7 | K37: 2385131.1 | L37: 2436479.3 | M37: 2488990.4 | N37: 2543247.7 | O37: 2599409.5 | P37: 2657368.5 | Q37: 2716903.7 | R37: 2775101.9 | S37: 2833580.5 | T37: 2892523.9 | U37: 2952051 | V37: 3011869.3 | W37: 3070055.1 | X37: 3128401.1 | Y37: 3187278.1 | Z37: 3246941.8 | AA37: 3306378.1 | AB37: 3354452.2 | AC37: 3399424.5 | AD37: 3442676.9 | AE37: 3485032.1 | AF37: 3527122.2 | AG37: 3577047.3 | AH37: 3630196.1 | AI37: 3686086 | AJ37: 3744490.8 | AK37: 3805210.4
A38: y_spub_2 | B38: 539665.66 | C38: 546356.22 | D38: 553045.27 | E38: 559788.36 | F38: 566831.14 | G38: 574571.86 | H38: 582417.29 | I38: 590465.74 | J38: 598745.88 | K38: 607334.14 | L38: 616364.23 | M38: 625286.73 | N38: 634337.03 | O38: 643555.28 | P38: 652912.11 | Q38: 662373.9 | R38: 671869.8 | S38: 681396.84 | T38: 690949.63 | U38: 700539.91 | V38: 710154.81 | W38: 719659.84 | X38: 729174.14 | Y38: 738733.21 | Z38: 748357.91 | AA38: 757975.11 | AB38: 767500.68 | AC38: 777045.97 | AD38: 786656.2 | AE38: 796365.57 | AF38: 806200.54 | AG38: 816112.02 | AH38: 826152.91 | AI38: 836343.02 | AJ38: 846692.91 | AK38: 857208.94
A39: y_spub_0 | B39: 539665.66 | C39: 546356.22 | D39: 553045.27 | E39: 559788.36 | F39: 566831.14 | G39: 574571.86 | H39: 582485.09 | I39: 590502.19 | J39: 598619.48 | K39: 606846.79 | L39: 615244.45 | M39: 623771.79 | N39: 632462.63 | O39: 641325.69 | P39: 650353.4 | Q39: 659531.82 | R39: 668711.05 | S39: 677959.31 | T39: 687287 | U39: 696702.43 | V39: 706184.45 | W39: 715651.55 | X39: 725183.6 | Y39: 734802.93 | Z39: 744526.77 | AA39: 754280.95 | AB39: 763528.48 | AC39: 772632.99 | AD39: 781675.81 | AE39: 790713.41 | AF39: 799793.36 | AG39: 809341.17 | AH39: 819169.96 | AI39: 829259.1 | AJ39: 839596.43 | AK39: 850168.37
... A67: y_seot_0 | B67: 109.60596 | C67: 110.57357 | D67: 111.01736 | E67: 111.35141 | F67: 111.89965 | G67: 113.13275 | H67: 114.53458 | I67: 115.9758 | J67: 117.43804 | K67: 118.91491 | L67: 120.44029 | M67: 121.98248 | N67: 123.57133 | O67: 125.22195 | P67: 126.93886 | Q67: 128.71995 | R67: 130.43776 | S67: 132.18195 | T67: 133.96736 | U67: 135.79866 | V67: 137.66004 | W67: 139.46093 | X67: 141.29093 | Y67: 143.16676 | Z67: 145.09451 | AA67: 147.02478 | AB67: 148.44533 | AC67: 149.78626 | AD67: 151.12248 | AE67: 152.47586 | AF67: 153.85489 | AG67: 155.6097 | AH67: 157.47868 | AI67: 159.41681 | AJ67: 161.41199 | AK67: 163.46017

Sheet Capital
A1: _date_ | B1: 42005 | C1: 42370 | D1: 42736 | E1: 43101 | F1: 43466 | G1: 43831 | H1: 44197 | I1: 44562 | J1: 44927 | K1: 45292 | L1: 45658 | M1: 46023 | N1: 46388 | O1: 46753 | P1: 47119 | Q1: 47484 | R1: 47849 | S1: 48214 | T1: 48580 | U1: 48945 | V1: 49310 | W1: 49675 | X1: 50041 | Y1: 50406 | Z1: 50771 | AA1: 51136 | AB1: 51502 | AC1: 51867 | AD1: 52232 | AE1: 52597 | AF1: 52963 | AG1: 53328 | AH1: 53693 | AI1: 54058 | AJ1: 54424 | AK1: 54789
A2: f_k_2 | B2: 5223444.3 | C2: 5285439.8 | D2: 5349307.5 | E2: 5413622.9 | F2: 5479884 | G2: 5552470.6 | H2: 5631075.8 | I2: 5714891.4 | J2: 5802948.4 | K2: 5894251.9 | L2: 5987994.7 | M2: 6084708.2 | N2: 6185297.3 | O2: 6290708.4 | P2: 6401715.2 | Q2: 6518868.1 | R2: 6642121.7 | S2: 6771223.4 | T2: 6905851 | U2: 7045730.9 | V2: 7190638.6 | W2: 7340174.3 | X2: 7494230.7 | Y2: 7652857.8 | Z2: 7816174.9 | AA2: 7984173.4 | AB2: 8156491.9 | AC2: 8332928.8 | AD2: 8513392.9 | AE2: 8697863.6 | AF2: 8886365.8 | AG2: 9078866.9 | AH2: 9275394 | AI2: 9475998 | AJ2: 9680726.9 | AK2: 9889616.6
A3: f_k_0 | B3: 5223444.3 | C3: 5285439.8 | D3: 5349307.5 | E3: 5413622.9 | F3: 5479884 | G3: 5552470.6 | H3: 5631351.7 | I3: 5716612.8 | J3: 5808051 | K3: 5905304.3 | L3: 6008099.2 | M3: 6116243.3 | N3: 6229773.2 | O3: 6348896.9 | P3: 6473890.1 | Q3: 6605023.3 | R3: 6742099.2 | S3: 6885085.7 | T3: 7034035.5 | U3: 7189036.3 | V3: 7350132.5 | W3: 7516985.3 | X3: 7689461.9 | Y3: 7867535.9 | Z3: 8051223.4 | AA3: 8240382.5 | AB3: 8432834.1 | AC3: 8627344.9 | AD3: 8823192.7 | AE3: 9019898.1 | AF3: 9217097.4 | AG3: 9415780.2 | AH3: 9616361.9 | AI3: 9818939.6 | AJ3: 10023459 | AK3: 10229792
A4: f_k_sagr_2 | B4: 47210.822 | C4: 47764.786 | D4: 48327.278 | E4: 48889.694 | F4: 49466.022 | G4: 50096.515 | H4: 50781.483 | I4: 51519.541 | J4: 52308.192 | K4: 53145.407 | L4: 54031.722 | M4: 54969.325 | N4: 55963.313 | O4: 57020.111 | P4: 58144.815 | Q4: 59340.255 | R4: 60603.411 | S4: 61929.187 | T4: 63311.272 | U4: 64743.341 | V4: 66219.105 | W4: 67729.03 | X4: 69267.282 | Y4: 70830.262 | Z4: 72415.56 | AA4: 74019.389 | AB4: 75634.2 | AC4: 77255.539 | AD4: 78881.081 | AE4: 80509.896 | AF4: 82141.999 | AG4: 83776.501 | AH4: 85413.741 | AI4: 87054.802 | AJ4: 88701.079 | AK4: 90354.056
A5: f_k_sagr_0 | B5: 47210.822 | C5: 47764.786 | D5: 48327.278 | E5: 48889.694 | F5: 49466.022 | G5: 50096.515 | H5: 50784.27 | I5: 51532.167 | J5: 52339.526 | K5: 53204.345 | L5: 54125.857 | M5: 55103.315 | N5: 56137.494 | O5: 57230.089 | P5: 58382.817 | Q5: 59596.889 | R5: 60867.723 | S5: 62192.55 | T5: 63569.421 | U5: 64996.732 | V5: 66472.389 | W5: 67990.145 | X5: 69546.436 | Y5: 71139.089 | Z5: 72766.683 | AA5: 74426.157 | AB5: 76091.519 | AC5: 77748.716 | AD5: 79389.848 | AE5: 81010.233 | AF5: 82607.285 | AG5: 84195.183 | AH5: 85782.23 | AI5: 87374.076 | AJ5: 88975.286 | AK5: 90589.79
A6: f_k_sfor_2 | B6: 1844.3813 | C6: 1863.1297 | D6: 1878.6019 | E6: 1890.0344 | F6: 1898.5921 | G6: 1906.2188 | H6: 1912.8141 | I6: 1917.6406 | J6: 1919.8937 | K6: 1918.8259 | L6: 1913.8086 | M6: 1906.326 | N6: 1897.6112 | O6: 1888.4564 | P6: 1879.3337 | Q6: 1870.5212 | R6: 1862.0097 | S6: 1853.7444 | T6: 1845.6761 | U6: 1837.7761 | V6: 1830.0096 | W6: 1822.4703 | X6: 1815.2672 | Y6: 1808.4826 | Z6: 1802.1712 | AA6: 1796.2969 | AB6: 1790.8835 | AC6: 1785.978 | AD6: 1781.618 | AE6: 1777.826 | AF6: 1774.6127 | AG6: 1772.0149 | AH6: 1770.0616 | AI6: 1768.7658 | AJ6: 1768.1268 | AK6: 1768.1341
A7: f_k_sfor_0 | B7: 1844.3813 | C7: 1863.1297 | D7: 1878.6019 | E7: 1890.0344 | F7: 1898.5921 | G7: 1906.2188 | H7: 1912.8633 | I7: 1918.7659 | J7: 1924.0447 | K7: 1928.7585 | L7: 1933.0064 | M7: 1936.8458 | N7: 1940.3622 | O7: 1943.664 | P7: 1946.8638 | Q7: 1950.0674 | R7: 1953.3031 | S7: 1956.6346 | T7: 1960.1377 | U7: 1963.8865 | V7: 1967.9185 | W7: 1972.2381 | X7: 1976.8896 | Y7: 1981.9258 | Z7: 1987.3962 | AA7: 1993.2562 | AB7: 1999.2145 | AC7: 2005.1922 | AD7: 2011.1956 | AE7: 2017.2545 | AF7: 2023.3989 | AG7: 2029.8397 | AH7: 2036.6574 | AI7: 2043.8733 | AJ7: 2051.487 | AK7: 2059.493
A8: f_k_sfoo_2 | B8: 74517.868 | C8: 75394.71 | D8: 76283.754 | E8: 77172.709 | F8: 78090.286 | G8: 79102.686 | H8: 80204.408 | I8: 81387.608 | J8: 82643.639 | K8: 83965.517 | L8: 85352.119 | M8: 86808.726 | N8: 88345.424 | O8: 89974.103 | P8: 91704.063 | Q8: 93540.69 | R8: 95480.764 | S8: 97517.345 | T8: 99641.767 | U8: 101845.68 | V8: 104120.8 | W8: 106455.47 | X8: 108842.52 | Y8: 111277.41 | Z8: 113756.93 | AA8: 116274.88 | AB8: 118820.47 | AC8: 121386.19 | AD8: 123967.1 | AE8: 126560.31 | AF8: 129164.49 | AG8: 131777.43 | AH8: 134398.44 | AI8: 137027.92 | AJ8: 139666.83 | AK8: 142316.41
A9: f_k_sfoo_0 | B9: 74517.868 | C9: 75394.71 | D9: 76283.754 | E9: 77172.709 | F9: 78090.286 | G9: 79102.686 | H9: 80208.551 | I9: 81409.412 | J9: 82701.775 | K9: 84080.019 | L9: 85540.957 | M9: 87082.103 | N9: 88704.384 | O9: 90410.937 | P9: 92205.242 | Q9: 94089.984 | R9: 96060.228 | S9: 98112.857 | T9: 100245.44 | U9: 102455.78 | V9: 104740.54 | W9: 107091.43 | X9: 109503.33 | Y9: 111972.62 | Z9: 114496.54 | AA9: 117068.91 | AB9: 119655.18 | AC9: 122234.85 | AD9: 124794.56 | AE9: 127325.13 | AF9: 129820.46 | AG9: 132296.26 | AH9: 134762.06 | AI9: 137224.88 | AJ9: 139690.81 | AK9: 142165.31
A10: f_k_sveh_2 | B10: 401511.35 | C10: 406557.73 | D10: 412111.74 | E10: 418015.09 | F10: 424381.92 | G10: 431559.71 | H10: 439393.07 | I10: 447764.82 | J10: 456605.49 | K10: 465868.61 | L10: 475504.41 | M10: 485568.94 | N10: 496124.9 | O10: 507197.95 | P10: 518784.53 | Q10: 530868.12 | R10: 543356.19 | S10: 556178.8 | T10: 569284.69 | U10: 582644.33 | V10: 596243.94 | W10: 610002.18 | X10: 623908.19 | Y10: 637974.49 | Z10: 652220.3 | AA10: 666658.11 | AB10: 681219.25 | AC10: 695902.52 | AD10: 710730.37 | AE10: 725731.87 | AF10: 740936.48 | AG10: 756349.81 | AH10: 771994.77 | AI10: 787896.3 | AJ10: 804076.48 | AK10: 820553.34
A11: f_k_sveh_0 | B11: 401511.35 | C11: 406557.73 | D11: 412111.74 | E11: 418015.09 | F11: 424381.92 | G11: 431559.71 | H11: 439436.83 | I11: 447940.66 | J11: 457027.71 | K11: 466679.79 | L11: 476900.7 | M11: 487690.31 | N11: 499057.13 | O11: 511010.13 | P11: 523555.32 | Q11: 536695.69 | R11: 550330.19 | S11: 564423.35 | T11: 578967.29 | U11: 593965.64 | V11: 609424.69 | W11: 625256.89 | X11: 641442.21 | Y11: 657988.29 | Z11: 674913.43 | AA11: 692230.98 | AB11: 709475.78 | AC11: 726504.59 | AD11: 743301.82 | AE11: 759896.25 | AF11: 776329.37 | AG11: 792946.09 | AH11: 809883.3 | AI11: 827191.29 | AJ11: 844885.58 | AK11: 862966.95
A12: f_k_sgla_2 | B12: 16080.533 | C12: 16265.725 | D12: 16451.876 | E12: 16635.141 | F12: 16820.758 | G12: 17022.577 | H12: 17241.678 | I12: 17476.069 | J12: 17721.745 | K12: 17973.52 | L12: 18225.703 | M12: 18479.569 | N12: 18738.649 | O12: 19007.136 | P12: 19288.781 | Q12: 19586.482 | R12: 19900.727 | S12: 20231.15 | T12: 20576.881 | U12: 20936.934 | V12: 21310.339 | W12: 21695.749 | X12: 22092.892 | Y12: 22502.046 | Z12: 22923.697 | AA12: 23358.023 | AB12: 23804.252 | AC12: 24262.245 | AD12: 24732.18 | AE12: 25214.338 | AF12: 25709 | AG12: 26216.356 | AH12: 26736.774 | AI12: 27270.626 | AJ12: 27818.169 | AK12: 28379.504
... A26: f_k_scon_2 | B26: 1693874.9 | C26: 1713763.9 | D26: 1734105.1 | E26: 1754404.3 | F26: 1775008.3 | G26: 1797328.8 | H26: 1821578.8 | I26: 1847598.4 | J26: 1875031.6 | K26: 1903426.6 | L26: 1932353.9 | M26: 1961896.5 | N26: 1992367.7 | O26: 2024180.9 | P26: 2057745.5 | Q26: 2093415.2 | R26: 2131390 | S26: 2171738.8 | T26: 2214459.9 | U26: 2259535.3 | V26: 2306948.8 | W26: 2356699.4 | X26: 2408822.6 | Y26: 2463389.9 | Z26: 2520494 | AA26: 2580196.5 | AB26: 2642501.7 | AC26: 2707381.7 | AD26: 2774804.1 | AE26: 2844742.5 | AF26: 2917177.8 | AG26: 2992095.7 | AH26: 3069479 | AI26: 3149308.5 | AJ26: 3231559.3 | AK26: 3316199.8
A27: f_k_scon_0 | B27: 1693874.9 | C27: 1713763.9 | D27: 1734105.1 | E27: 1754404.3 | F27: 1775008.3 | G27: 1797328.8 | H27: 1821638.5 | I27: 1848121.2 | J27: 1876803.8 | K27: 1907597.2 | L27: 1940390.1 | M27: 1975100.6 | N27: 2011730.4 | O27: 2050364.9 | P27: 2091141.9 | Q27: 2134218.5 | R27: 2179696 | S27: 2227666.2 | T27: 2278225.2 | U27: 2331470.6 | V27: 2387484.1 | W27: 2446290.1 | X27: 2507908 | Y27: 2572361.5 | Z27: 2639674.3 | AA27: 2709816.7 | AB27: 2782455.8 | AC27: 2857222.6 | AD27: 2933782.6 | AE27: 3011834.7 | AF27: 3091094.8 | AG27: 3171463.6 | AH27: 3252846.5 | AI27: 3335106.5 | AJ27: 3418067.5 | AK27: 3501528.5 | AL27: =AK26/AK27 -> 0.94707204
A28: f_k_srai_2 | B28: 4359.527 | C28: 4411.0816 | D28: 4463.46 | E28: 4514.9853 | F28: 4566.8536 | G28: 4623.6454 | H28: 4684.5312 | I28: 4749.0491 | J28: 4816.8211 | K28: 4887.5664 | L28: 4961.0909 | M28: 5038.1338 | N28: 5119.4996 | O28: 5205.8424 | P28: 5297.568 | Q28: 5394.8594 | R28: 5497.3428 | S28: 5604.3901 | T28: 5715.2611 | U28: 5829.2532 | V28: 5945.7349 | W28: 6063.9676 | X28: 6183.5293 | Y28: 6304.1766 | Z28: 6425.7594 | AA28: 6548.0655 | AB28: 6670.6449 | AC28: 6793.2941 | AD28: 6915.961 | AE28: 7038.6758 | AF28: 7161.5148 | AG28: 7284.5174 | AH28: 7407.7937 | AI28: 7531.4812 | AJ28: 7655.7153 | AK28: 7780.6172
A29: f_k_srai_0 | B29: 4359.527 | C29: 4411.0816 | D29: 4463.46 | E29: 4514.9853 | F29: 4566.8536 | G29: 4623.6454 | H29: 4684.7386 | I29: 4750.0705 | J29: 4819.4073 | K29: 4892.5095 | L29: 4969.2805 | M29: 5049.6684 | N29: 5133.7351 | O29: 5221.5972 | P29: 5313.3642 | Q29: 5409.1093 | R29: 5508.4672 | S29: 5611.2377 | T29: 5717.3051 | U29: 5826.5919 | V29: 5939.0035 | W29: 6054.1119 | X29: 6171.7084 | Y29: 6291.7025 | Z29: 6414.0645 | AA29: 6538.6804 | AB29: 6663.6501 | AC29: 6788.0413 | AD29: 6911.4304 | AE29: 7033.635 | AF29: 7154.5998 | AG29: 7275.5023 | AH29: 7396.9873 | AI29: 7519.4305 | AJ29: 7643.0914 | AK29: 7768.1698
A30: f_k_sroa_2 | B30: 43522.728 | C30: 44038.801 | D30: 44561.784 | E30: 45071.167 | F30: 45581.287 | G30: 46146.232 | H30: 46753.738 | I30: 47398.31 | J30: 48075.411 | K30: 48781.387 | L30: 49513.064 | M30: 50279.893 | N30: 51091.568 | O30: 51955.849 | P30: 52877.703 | Q30: 53859.664 | R30: 54898.115 | S30: 55986.177 | T30: 57115.517 | U30: 58278.15 | V30: 59466.901 | W30: 60674.067 | X30: 61895.13 | Y30: 63127.369 | Z30: 64369.005 | AA30: 65617.65 | AB30: 66868.778 | AC30: 68120.27 | AD30: 69371.473 | AE30: 70622.525 | AF30: 71873.992 | AG30: 73126.251 | AH30: 74380.328 | AI30: 75637.47 | AJ30: 76898.867 | AK30: 78165.537
A31: f_k_sroa_0 | B31: 43522.728 | C31: 44038.801 | D31: 44561.784 | E31: 45071.167 | F31: 45581.287 | G31: 46146.232 | H31: 46755.837 | I31: 47409.271 | J31: 48103.844 | K31: 48836.835 | L31: 49607.005 | M31: 50413.675 | N31: 51257.412 | O31: 52139.407 | P31: 53060.827 | Q31: 54022.483 | R31: 55020.814 | S31: 56053.909 | T31: 57120.691 | U31: 58220.449 | V31: 59352.287 | W31: 60511.95 | X31: 61697.359 | Y31: 62907.6 | Z31: 64142.34 | AA31: 65400.393 | AB31: 66662.671 | AC31: 67919.769 | AD31: 69167.353 | AE31: 70403.466 | AF31: 71627.398 | AG31: 72850.76 | AH31: 74079.797 | AI31: 75318.061 | AJ31: 76567.956 | AK31: 77831.317
A32: f_k_swat_2 | B32: 25745.773 | C32: 26063.336 | D32: 26411.253 | E32: 26786.683 | F32: 27189.686 | G32: 27626.453 | H32: 28101.74 | I32: 28617.3 | J32: 29172.792 | K32: 29766.769 | L32: 30396.208 | M32: 31059.158 | N32: 31756.482 | O32: 32489.471 | P32: 33258.863 | Q32: 34064.665 | R32: 34901.473 | S32: 35766.206 | T32: 36656.165 | U32: 37568.618 | V32: 38500.927 | W32: 39443.497 | X32: 40393.094 | Y32: 41349.017 | Z32: 42311.562 | AA32: 43281.37 | AB32: 44252.232 | AC32: 45224.185 | AD32: 46199.431 | AE32: 47180.683 | AF32: 48170.596 | AG32: 49169.539 | AH32: 50179.616 | AI32: 51203.29 | AJ32: 52242.834 | AK32: 53300.147
A33: f_k_swat_0 | B33: 25745.773 | C33: 26063.336 | D33: 26411.253 | E33: 26786.683 | F33: 27189.686 | G33: 27626.453 | H33: 28104.885 | I33: 28628.004 | J33: 29196.628 | K33: 29811.396 | L33: 30473.196 | M33: 31182.027 | N33: 31937.866 | O33: 32740.357 | P33: 33588.929 | Q33: 34482.985 | R33: 35414.041 | S33: 36379.102 | T33: 37377.232 | U33: 38408.304 | V33: 39472.568 | W33: 40562.763 | X33: 41677.217 | Y33: 42816.383 | Z33: 43981.533 | AA33: 45174.172 | AB33: 46358.404 | AC33: 47524.667 | AD33: 48672.731 | AE33: 49805.283 | AF33: 50925.786 | AG33: 52061.089 | AH33: 53221.29 | AI33: 54410.372 | AJ33: 55630.121 | AK33: 56881.427
A34: f_k_sair_2 | B34: 14913.04 | C34: 15093.019 | D34: 15281.667 | E34: 15469.419 | F34: 15661.654 | G34: 15882.274 | H34: 16128.47 | I34: 16395.883 | J34: 16678.897 | K34: 16971.363 | L34: 17266.996 | M34: 17567.724 | N34: 17879.478 | O34: 18208.584 | P34: 18559.891 | Q34: 18936.426 | R34: 19337.178 | S34: 19759.565 | T34: 20200.137 | U34: 20655.442 | V34: 21122.248 | W34: 21596.785 | X34: 22077.52 | Y34: 22563.769 | Z34: 23055.075 | AA34: 23550.266 | AB34: 24046.821 | AC34: 24543.886 | AD34: 25041.304 | AE34: 25539.191 | AF34: 26037.774 | AG34: 26537.061 | AH34: 27037.632 | AI34: 27540.201 | AJ34: 28045.407 | AK34: 28553.753
A35: f_k_sair_0 | B35: 14913.04 | C35: 15093.019 | D35: 15281.667 | E35: 15469.419 | F35: 15661.654 | G35: 15882.274 | H35: 16129.734 | I35: 16404.243 | J35: 16705.097 | K35: 17031.579 | L35: 17383.686 | M35: 17761.433 | N35: 18165.401 | O35: 18596.403 | P35: 19055.161 | Q35: 19542.162 | R35: 20054.995 | S35: 20592.517 | T35: 21154.052 | U35: 21739.094 | V35: 22346.969 | W35: 22974.736 | X35: 23621.028 | Y35: 24285.144 | Z35: 24966.699 | AA35: 25664.672 | AB35: 26365.822 | AC35: 27064.231 | AD35: 27756.994 | AE35: 28442.54 | AF35: 29120.076 | AG35: 29797.442 | AH35: 30478.412 | AI35: 31165.298 | AJ35: 31859.898 | AK35: 32563.762
A36: f_k_spri_2 | B36: 1988889 | C36: 2012555.3 | D36: 2036863.5 | E36: 2061298.4 | F36: 2086566 | G36: 2114469.6 | H36: 2144747.4 | I36: 2177036 | J36: 2210982.4 | K36: 2246287.2 | L36: 2282799.8 | M36: 2320776.4 | N36: 2360561.4 | O36: 2402490.7 | P36: 2446807.6 | Q36: 2493650 | R36: 2542927.1 | S36: 2594461.4 | T36: 2648058.2 | U36: 2703554.8 | V36: 2760810.3 | W36: 2819619.7 | X36: 2879881.5 | Y36: 2941556.4 | Z36: 3004633.4 | AA36: 3069031.6 | AB36: 3134544.1 | AC36: 3201025.1 | AD36: 3268388.5 | AE36: 3336593.3 | AF36: 3405631.3 | AG36: 3475474.9 | AH36: 3546124.1 | AI36: 3617597.8 | AJ36: 3689922.7 | AK36: 3763129.3
A37: f_k_spri_0 | B37: 1988889 | C37: 2012555.3 | D37: 2036863.5 | E37: 2061298.4 | F37: 2086566 | G37: 2114469.6 | H37: 2144857.2 | I37: 2177687.1 | J37: 2212814.5 | K37: 2250047.9 | L37: 2289262.3 | M37: 2330376 | N37: 2373407.4 | O37: 2418441.2 | P37: 2465576.4 | Q37: 2514895 | R37: 2566292.2 | S37: 2619710.2 | T37: 2675118.7 | U37: 2732498.3 | V37: 2791805.4 | W37: 2852866.2 | X37: 2915582.2 | Y37: 2979898.5 | Z37: 3045780.8 | AA37: 3113117.1 | AB37: 3181068.4 | AC37: 3249133.7 | AD37: 3317019.1 | AE37: 3384540.9 | AF37: 3451579.8 | AG37: 3518538.8 | AH37: 3585647.7 | AI37: 3653035.1 | AJ37: 3720785.2 | AK37: 3788962
A38: f_k_spub_2 | B38: 436500.74 | C38: 441579.28 | D38: 446674.06 | E38: 451679.2 | F38: 456729.32 | G38: 462113.01 | H38: 467728.02 | I38: 473470.44 | J38: 479241.8 | K38: 484946.84 | L38: 490505.05 | M38: 495996.71 | N38: 501503.74 | O38: 507095.73 | P38: 512824.71 | Q38: 518727.26 | R38: 524811.35 | S38: 531070.15 | T38: 537494.55 | U38: 544079.66 | V38: 550824.21 | W38: 557738.45 | X38: 564835.5 | Y38: 572128.81 | Z38: 579630.34 | AA38: 587344.7 | AB38: 595273.58 | AC38: 603414.39 | AD38: 611764.06 | AE38: 620319.71 | AF38: 629078.55 | AG38: 638040.67 | AH38: 647204.21 | AI38: 656566.14 | AJ38: 666122.35 | AK38: 675868.21
A39: f_k_spub_0 | B39: 436500.74 | C39: 441579.28 | D39: 446674.06 | E39: 451679.2 | F39: 456729.32 | G39: 462113.01 | H39: 467738.14 | I39: 473583.66 | J39: 479618.58 | K39: 485803.7 | L39: 492106.48 | M39: 498507.62 | N39: 505005.39 | O39: 511609.77 | P39: 518334.5 | Q39: 525192.55 | R39: 532190.02 | S39: 539334.82 | T39: 546635.52 | U39: 554100.04 | V39: 561733.06 | W39: 569534.29 | X39: 577505.58 | Y39: 585649.06 | Z39: 593965.73 | AA39: 602448.79 | AB39: 611067.43 | AC39: 619804.4 | AD39: 628649.6 | AE39: 637595.08 | AF39: 646632.79 | AG39: 655768.22 | AH39: 664996.98 | AI39: 674309.3 | AJ39: 683694.16 | AK39: 693141.34
... A67: f_k_seot_0 | B67: 65.168033 | C67: 65.914886 | D67: 66.640855 | E67: 67.331537 | F67: 67.996892 | G67: 68.673719 | H67: 69.369097 | I67: 70.08622 | J67: 70.824643 | K67: 71.58232 | L67: 72.358448 | M67: 73.15212 | N67: 73.964127 | O67: 74.796615 | P67: 75.652252 | Q67: 76.53364 | R67: 77.438568 | S67: 78.36677 | T67: 79.319185 | U67: 80.297221 | V67: 81.301667 | W67: 82.329739 | X67: 83.380966 | Y67: 84.456191 | Z67: 85.556759 | AA67: 86.681966 | AB67: 87.811465 | AC67: 88.935625 | AD67: 90.051387 | AE67: 91.158483 | AF67: 92.257677 | AG67: 93.362918 | AH67: 94.481759 | AI67: 95.617669 | AJ67: 96.772341 | AK67: 97.946788

Sheet Results
A1: NB : on crée ici une liste : - globale, qui fusionne les sorties des reportings 1, 2 et 3 - "rationalisée" : suppression des doublons, et regroupements par thématique On continue par la suite à avoir 2 Excels de reporting (un "energie", fusion des reportings 1 et 2), et un "économie" (reporting 3)), dans lesquels on copiera cet onglet "results" (généré automatiquement par EViews). --> puis voir à la fin si on peut pas importer les graphs et tableaux dans l'excel automatiquement généré (éviterait les copiés collés, mais à voir si ça prend trop de temps, et si c'est pas trop gros comme excel)
A2: Nom du bloc de variables utilisé dans le code | B2: Sous-bloc de variables pour plus de lisibilité dans le Excel | E2: Year | F2: =date!B3 -> 2015 | G2: =date!C3 -> 2016 | H2: =date!D3 -> 2017 | I2: =date!E3 -> 2018 | J2: =date!F3 -> 2019 | K2: =date!G3 -> 2020 | L2: =date!H3 -> 2021 | M2: =date!I3 -> 2022 | ... AO2: =date!AK3 -> 2050
A3: HYBRID | B3: AUTOMOBILES (thousands) | C3: TOTAL STOCK SHOCK | E3: AUTO_2 | F3: =VLOOKUP($E3,Hybrid!$1:$1048576,MATCH(DATE(F$2,1,1),Hybrid!$A$1:$LI$1),FALSE) -> 32317.941 | G3: =VLOOKUP($E3,Hybrid!$1:$1048576,MATCH(DATE(G$2,1,1),Hybrid!$A$1:$LI$1),FALSE) -> 32010.864 | H3: =VLOOKUP($E3,Hybrid!$1:$1048576,MATCH(DATE(H$2,1,1),Hybrid!$A$1:$LI$1),FALSE) -> 31809.838 | I3: =VLOOKUP($E3,Hybrid!$1:$1048576,MATCH(DATE(I$2,1,1),Hybrid!$A$1:$LI$1),FALSE) -> 31619.962 | J3: =VLOOKUP($E3,Hybrid!$1:$1048576,MATCH(DATE(J$2,1,1),Hybrid!$A$1:$LI$1),FALSE) -> 31633.548 | K3: =VLOOKUP($E3,Hybrid!$1:$1048576,MATCH(DATE(K$2,1,1),Hybrid!$A$1:$LI$1),FALSE) -> 32018.121 | L3: =VLOOKUP($E3,Hybrid!$1:$1048576,MATCH(DATE(L$2,1,1),Hybrid!$A$1:$LI$1),FALSE) -> 32309.847 | M3: =VLOOKUP($E3,Hybrid!$1:$1048576,MATCH(DATE(M$2,1,1),Hybrid!$A$1:$LI$1),FALSE) -> 32597.019 | ... AO3: =VLOOKUP($E3,Hybrid!$1:$1048576,MATCH(DATE(AO$2,1,1),Hybrid!$A$1:$LI$1),FALSE) -> 44079.584
C4: OIL | E4: AUTO_cfut_2 | F4: =VLOOKUP($E4,Hybrid!$1:$1048576,MATCH(DATE(F$2,1,1),Hybrid!$A$1:$LI$1),FALSE) -> 32271.24 | G4: =VLOOKUP($E4,Hybrid!$1:$1048576,MATCH(DATE(G$2,1,1),Hybrid!$A$1:$LI$1),FALSE) -> 31945.681 | H4: =VLOOKUP($E4,Hybrid!$1:$1048576,MATCH(DATE(H$2,1,1),Hybrid!$A$1:$LI$1),FALSE) -> 31726.506 | I4: =VLOOKUP($E4,Hybrid!$1:$1048576,MATCH(DATE(I$2,1,1),Hybrid!$A$1:$LI$1),FALSE) -> 31518.017 | J4: =VLOOKUP($E4,Hybrid!$1:$1048576,MATCH(DATE(J$2,1,1),Hybrid!$A$1:$LI$1),FALSE) -> 31508.065 | K4: =VLOOKUP($E4,Hybrid!$1:$1048576,MATCH(DATE(K$2,1,1),Hybrid!$A$1:$LI$1),FALSE) -> 31864.988 | L4: =VLOOKUP($E4,Hybrid!$1:$1048576,MATCH(DATE(L$2,1,1),Hybrid!$A$1:$LI$1),FALSE) -> 32131.068 | M4: =VLOOKUP($E4,Hybrid!$1:$1048576,MATCH(DATE(M$2,1,1),Hybrid!$A$1:$LI$1),FALSE) -> 32392.83 | ... AO4: =VLOOKUP($E4,Hybrid!$1:$1048576,MATCH(DATE(AO$2,1,1),Hybrid!$A$1:$LI$1),FALSE) -> 42511.874
D5: class A | E5: AUTO_ca_cfut_2 | F5: =VLOOKUP($E5,Hybrid!$1:$1048576,MATCH(DATE(F$2,1,1),Hybrid!$A$1:$LI$1),FALSE) -> 7095.7005 | G5: =VLOOKUP($E5,Hybrid!$1:$1048576,MATCH(DATE(G$2,1,1),Hybrid!$A$1:$LI$1),FALSE) -> 7163.595 | H5: =VLOOKUP($E5,Hybrid!$1:$1048576,MATCH(DATE(H$2,1,1),Hybrid!$A$1:$LI$1),FALSE) -> 7253.3446 | I5: =VLOOKUP($E5,Hybrid!$1:$1048576,MATCH(DATE(I$2,1,1),Hybrid!$A$1:$LI$1),FALSE) -> 7342.6292 | J5: =VLOOKUP($E5,Hybrid!$1:$1048576,MATCH(DATE(J$2,1,1),Hybrid!$A$1:$LI$1),FALSE) -> 7487.9362 | K5: =VLOOKUP($E5,Hybrid!$1:$1048576,MATCH(DATE(K$2,1,1),Hybrid!$A$1:$LI$1),FALSE) -> 7734.59 | L5: =VLOOKUP($E5,Hybrid!$1:$1048576,MATCH(DATE(L$2,1,1),Hybrid!$A$1:$LI$1),FALSE) -> 7946.437 | M5: =VLOOKUP($E5,Hybrid!$1:$1048576,MATCH(DATE(M$2,1,1),Hybrid!$A$1:$LI$1),FALSE) -> 8154.1169 | ... AO5: =VLOOKUP($E5,Hybrid!$1:$1048576,MATCH(DATE(AO$2,1,1),Hybrid!$A$1:$LI$1),FALSE) -> 15676.456
D6: class B | E6: AUTO_cb_cfut_2 | F6: =VLOOKUP($E6,Hybrid!$1:$1048576,MATCH(DATE(F$2,1,1),Hybrid!$A$1:$LI$1),FALSE) -> 8251.2564 | G6: =VLOOKUP($E6,Hybrid!$1:$1048576,MATCH(DATE(G$2,1,1),Hybrid!$A$1:$LI$1),FALSE) -> 8204.1818 | H6: =VLOOKUP($E6,Hybrid!$1:$1048576,MATCH(DATE(H$2,1,1),Hybrid!$A$1:$LI$1),FALSE) -> 8186.0524 | I6: =VLOOKUP($E6,Hybrid!$1:$1048576,MATCH(DATE(I$2,1,1),Hybrid!$A$1:$LI$1),FALSE) -> 8173.2987 | J6: =VLOOKUP($E6,Hybrid!$1:$1048576,MATCH(DATE(J$2,1,1),Hybrid!$A$1:$LI$1),FALSE) -> 8218.6024 | K6: =VLOOKUP($E6,Hybrid!$1:$1048576,MATCH(DATE(K$2,1,1),Hybrid!$A$1:$LI$1),FALSE) -> 8366.7584 | L6: =VLOOKUP($E6,Hybrid!$1:$1048576,MATCH(DATE(L$2,1,1),Hybrid!$A$1:$LI$1),FALSE) -> 8488.5781 | M6: =VLOOKUP($E6,Hybrid!$1:$1048576,MATCH(DATE(M$2,1,1),Hybrid!$A$1:$LI$1),FALSE) -> 8610.9099 | ... AO6: =VLOOKUP($E6,Hybrid!$1:$1048576,MATCH(DATE(AO$2,1,1),Hybrid!$A$1:$LI$1),FALSE) -> 13505.803
D7: class C | E7: AUTO_cc_cfut_2 | F7: =VLOOKUP($E7,Hybrid!$1:$1048576,MATCH(DATE(F$2,1,1),Hybrid!$A$1:$LI$1),FALSE) -> 6777.6025 | G7: =VLOOKUP($E7,Hybrid!$1:$1048576,MATCH(DATE(G$2,1,1),Hybrid!$A$1:$LI$1),FALSE) -> 6661.8607 | H7: =VLOOKUP($E7,Hybrid!$1:$1048576,MATCH(DATE(H$2,1,1),Hybrid!$A$1:$LI$1),FALSE) -> 6572.095 | I7: =VLOOKUP($E7,Hybrid!$1:$1048576,MATCH(DATE(I$2,1,1),Hybrid!$A$1:$LI$1),FALSE) -> 6490.4961 | J7: =VLOOKUP($E7,Hybrid!$1:$1048576,MATCH(DATE(J$2,1,1),Hybrid!$A$1:$LI$1),FALSE) -> 6452.4548 | K7: =VLOOKUP($E7,Hybrid!$1:$1048576,MATCH(DATE(K$2,1,1),Hybrid!$A$1:$LI$1),FALSE) -> 6489.804 | L7: =VLOOKUP($E7,Hybrid!$1:$1048576,MATCH(DATE(L$2,1,1),Hybrid!$A$1:$LI$1),FALSE) -> 6514.1247 | M7: =VLOOKUP($E7,Hybrid!$1:$1048576,MATCH(DATE(M$2,1,1),Hybrid!$A$1:$LI$1),FALSE) -> 6542.2438 | ... AO7: =VLOOKUP($E7,Hybrid!$1:$1048576,MATCH(DATE(AO$2,1,1),Hybrid!$A$1:$LI$1),FALSE) -> 8434.9071
D8: class D | E8: AUTO_cd_cfut_2 | F8: =VLOOKUP($E8,Hybrid!$1:$1048576,MATCH(DATE(F$2,1,1),Hybrid!$A$1:$LI$1),FALSE) -> 4159.6639 | G8: =VLOOKUP($E8,Hybrid!$1:$1048576,MATCH(DATE(G$2,1,1),Hybrid!$A$1:$LI$1),FALSE) -> 4063.5393 | H8: =VLOOKUP($E8,Hybrid!$1:$1048576,MATCH(DATE(H$2,1,1),Hybrid!$A$1:$LI$1),FALSE) -> 3982.8175 | I8: =VLOOKUP($E8,Hybrid!$1:$1048576,MATCH(DATE(I$2,1,1),Hybrid!$A$1:$LI$1),FALSE) -> 3906.3668 | J8: =VLOOKUP($E8,Hybrid!$1:$1048576,MATCH(DATE(J$2,1,1),Hybrid!$A$1:$LI$1),FALSE) -> 3852.9234 | K8: =VLOOKUP($E8,Hybrid!$1:$1048576,MATCH(DATE(K$2,1,1),Hybrid!$A$1:$LI$1),FALSE) -> 3840.4882 | L8: =VLOOKUP($E8,Hybrid!$1:$1048576,MATCH(DATE(L$2,1,1),Hybrid!$A$1:$LI$1),FALSE) -> 3822.2448 | M8: =VLOOKUP($E8,Hybrid!$1:$1048576,MATCH(DATE(M$2,1,1),Hybrid!$A$1:$LI$1),FALSE) -> 3805.6208 | ... AO8: =VLOOKUP($E8,Hybrid!$1:$1048576,MATCH(DATE(AO$2,1,1),Hybrid!$A$1:$LI$1),FALSE) -> 3028.637
D9: class E | E9: AUTO_ce_cfut_2 | F9: =VLOOKUP($E9,Hybrid!$1:$1048576,MATCH(DATE(F$2,1,1),Hybrid!$A$1:$LI$1),FALSE) -> 2503.7292 | G9: =VLOOKUP($E9,Hybrid!$1:$1048576,MATCH(DATE(G$2,1,1),Hybrid!$A$1:$LI$1),FALSE) -> 2448.5604 | H9: =VLOOKUP($E9,Hybrid!$1:$1048576,MATCH(DATE(H$2,1,1),Hybrid!$A$1:$LI$1),FALSE) -> 2401.7659 | I9: =VLOOKUP($E9,Hybrid!$1:$1048576,MATCH(DATE(I$2,1,1),Hybrid!$A$1:$LI$1),FALSE) -> 2355.8796 | J9: =VLOOKUP($E9,Hybrid!$1:$1048576,MATCH(DATE(J$2,1,1),Hybrid!$A$1:$LI$1),FALSE) -> 2321.9985 | K9: =VLOOKUP($E9,Hybrid!$1:$1048576,MATCH(DATE(K$2,1,1),Hybrid!$A$1:$LI$1),FALSE) -> 2311.6313 | L9: =VLOOKUP($E9,Hybrid!$1:$1048576,MATCH(DATE(L$2,1,1),Hybrid!$A$1:$LI$1),FALSE) -> 2297.3429 | M9: =VLOOKUP($E9,Hybrid!$1:$1048576,MATCH(DATE(M$2,1,1),Hybrid!$A$1:$LI$1),FALSE) -> 2282.7834 | ... AO9: =VLOOKUP($E9,Hybrid!$1:$1048576,MATCH(DATE(AO$2,1,1),Hybrid!$A$1:$LI$1),FALSE) -> 1293.8522
D10: class F | E10: AUTO_cf_cfut_2 | F10: =VLOOKUP($E10,Hybrid!$1:$1048576,MATCH(DATE(F$2,1,1),Hybrid!$A$1:$LI$1),FALSE) -> 1243.6668 | G10: =VLOOKUP($E10,Hybrid!$1:$1048576,MATCH(DATE(G$2,1,1),Hybrid!$A$1:$LI$1),FALSE) -> 1213.8476 | H10: =VLOOKUP($E10,Hybrid!$1:$1048576,MATCH(DATE(H$2,1,1),Hybrid!$A$1:$LI$1),FALSE) -> 1186.9708 | I10: =VLOOKUP($E10,Hybrid!$1:$1048576,MATCH(DATE(I$2,1,1),Hybrid!$A$1:$LI$1),FALSE) -> 1158.6962 | J10: =VLOOKUP($E10,Hybrid!$1:$1048576,MATCH(DATE(J$2,1,1),Hybrid!$A$1:$LI$1),FALSE) -> 1133.8751 | K10: =VLOOKUP($E10,Hybrid!$1:$1048576,MATCH(DATE(K$2,1,1),Hybrid!$A$1:$LI$1),FALSE) -> 1118.247 | L10: =VLOOKUP($E10,Hybrid!$1:$1048576,MATCH(DATE(L$2,1,1),Hybrid!$A$1:$LI$1),FALSE) -> 1100.4708 | M10: =VLOOKUP($E10,Hybrid!$1:$1048576,MATCH(DATE(M$2,1,1),Hybrid!$A$1:$LI$1),FALSE) -> 1081.3056 | ... AO10: =VLOOKUP($E10,Hybrid!$1:$1048576,MATCH(DATE(AO$2,1,1),Hybrid!$A$1:$LI$1),FALSE) -> 255.40576
D11: class G | E11: AUTO_cg_cfut_2 | F11: =VLOOKUP($E11,Hybrid!$1:$1048576,MATCH(DATE(F$2,1,1),Hybrid!$A$1:$LI$1),FALSE) -> 2239.6206 | G11: =VLOOKUP($E11,Hybrid!$1:$1048576,MATCH(DATE(G$2,1,1),Hybrid!$A$1:$LI$1),FALSE) -> 2190.0963 | H11: =VLOOKUP($E11,Hybrid!$1:$1048576,MATCH(DATE(H$2,1,1),Hybrid!$A$1:$LI$1),FALSE) -> 2143.4602 | I11: =VLOOKUP($E11,Hybrid!$1:$1048576,MATCH(DATE(I$2,1,1),Hybrid!$A$1:$LI$1),FALSE) -> 2090.6508 | J11: =VLOOKUP($E11,Hybrid!$1:$1048576,MATCH(DATE(J$2,1,1),Hybrid!$A$1:$LI$1),FALSE) -> 2040.2746 | K11: =VLOOKUP($E11,Hybrid!$1:$1048576,MATCH(DATE(K$2,1,1),Hybrid!$A$1:$LI$1),FALSE) -> 2003.4687 | L11: =VLOOKUP($E11,Hybrid!$1:$1048576,MATCH(DATE(L$2,1,1),Hybrid!$A$1:$LI$1),FALSE) -> 1961.8698 | M11: =VLOOKUP($E11,Hybrid!$1:$1048576,MATCH(DATE(M$2,1,1),Hybrid!$A$1:$LI$1),FALSE) -> 1915.8497 | ... AO11: =VLOOKUP($E11,Hybrid!$1:$1048576,MATCH(DATE(AO$2,1,1),Hybrid!$A$1:$LI$1),FALSE) -> 316.81297
C12: ELEC | E12: AUTO_cele_2 | F12: =VLOOKUP($E12,Hybrid!$1:$1048576,MATCH(DATE(F$2,1,1),Hybrid!$A$1:$LI$1),FALSE) -> 44.765 | G12: =VLOOKUP($E12,Hybrid!$1:$1048576,MATCH(DATE(G$2,1,1),Hybrid!$A$1:$LI$1),FALSE) -> 63.184204 | H12: =VLOOKUP($E12,Hybrid!$1:$1048576,MATCH(DATE(H$2,1,1),Hybrid!$A$1:$LI$1),FALSE) -> 81.267092 | I12: =VLOOKUP($E12,Hybrid!$1:$1048576,MATCH(DATE(I$2,1,1),Hybrid!$A$1:$LI$1),FALSE) -> 99.820025 | J12: =VLOOKUP($E12,Hybrid!$1:$1048576,MATCH(DATE(J$2,1,1),Hybrid!$A$1:$LI$1),FALSE) -> 123.28585 | K12: =VLOOKUP($E12,Hybrid!$1:$1048576,MATCH(DATE(K$2,1,1),Hybrid!$A$1:$LI$1),FALSE) -> 150.83685 | L12: =VLOOKUP($E12,Hybrid!$1:$1048576,MATCH(DATE(L$2,1,1),Hybrid!$A$1:$LI$1),FALSE) -> 176.39535 | M12: =VLOOKUP($E12,Hybrid!$1:$1048576,MATCH(DATE(M$2,1,1),Hybrid!$A$1:$LI$1),FALSE) -> 201.72272 | ... AO12: =VLOOKUP($E12,Hybrid!$1:$1048576,MATCH(DATE(AO$2,1,1),Hybrid!$A$1:$LI$1),FALSE) -> 1563.4995
D13: class A | E13: AUTO_ca_cele_2 | F13: =VLOOKUP($E13,Hybrid!$1:$1048576,MATCH(DATE(F$2,1,1),Hybrid!$A$1:$LI$1),FALSE) -> 9.8427899 | G13: =VLOOKUP($E13,Hybrid!$1:$1048576,MATCH(DATE(G$2,1,1),Hybrid!$A$1:$LI$1),FALSE) -> 15.183587 | H13: =VLOOKUP($E13,Hybrid!$1:$1048576,MATCH(DATE(H$2,1,1),Hybrid!$A$1:$LI$1),FALSE) -> 20.45814 | I13: =VLOOKUP($E13,Hybrid!$1:$1048576,MATCH(DATE(I$2,1,1),Hybrid!$A$1:$LI$1),FALSE) -> 25.97122 | J13: =VLOOKUP($E13,Hybrid!$1:$1048576,MATCH(DATE(J$2,1,1),Hybrid!$A$1:$LI$1),FALSE) -> 33.113699 | K13: =VLOOKUP($E13,Hybrid!$1:$1048576,MATCH(DATE(K$2,1,1),Hybrid!$A$1:$LI$1),FALSE) -> 41.540103 | L13: =VLOOKUP($E13,Hybrid!$1:$1048576,MATCH(DATE(L$2,1,1),Hybrid!$A$1:$LI$1),FALSE) -> 49.400939 | M13: =VLOOKUP($E13,Hybrid!$1:$1048576,MATCH(DATE(M$2,1,1),Hybrid!$A$1:$LI$1),FALSE) -> 57.279668 | ... AO13: =VLOOKUP($E13,Hybrid!$1:$1048576,MATCH(DATE(AO$2,1,1),Hybrid!$A$1:$LI$1),FALSE) -> 593.04452
D14: class B | E14: AUTO_cb_cele_2 | F14: =VLOOKUP($E14,Hybrid!$1:$1048576,MATCH(DATE(F$2,1,1),Hybrid!$A$1:$LI$1),FALSE) -> 11.445717 | G14: =VLOOKUP($E14,Hybrid!$1:$1048576,MATCH(DATE(G$2,1,1),Hybrid!$A$1:$LI$1),FALSE) -> 16.490827 | H14: =VLOOKUP($E14,Hybrid!$1:$1048576,MATCH(DATE(H$2,1,1),Hybrid!$A$1:$LI$1),FALSE) -> 21.459313 | I14: =VLOOKUP($E14,Hybrid!$1:$1048576,MATCH(DATE(I$2,1,1),Hybrid!$A$1:$LI$1),FALSE) -> 26.663425 | J14: =VLOOKUP($E14,Hybrid!$1:$1048576,MATCH(DATE(J$2,1,1),Hybrid!$A$1:$LI$1),FALSE) -> 33.46949 | K14: =VLOOKUP($E14,Hybrid!$1:$1048576,MATCH(DATE(K$2,1,1),Hybrid!$A$1:$LI$1),FALSE) -> 41.519739 | L14: =VLOOKUP($E14,Hybrid!$1:$1048576,MATCH(DATE(L$2,1,1),Hybrid!$A$1:$LI$1),FALSE) -> 49.021052 | M14: =VLOOKUP($E14,Hybrid!$1:$1048576,MATCH(DATE(M$2,1,1),Hybrid!$A$1:$LI$1),FALSE) -> 56.529979 | ... AO14: =VLOOKUP($E14,Hybrid!$1:$1048576,MATCH(DATE(AO$2,1,1),Hybrid!$A$1:$LI$1),FALSE) -> 517.18033
D15: class C | E15: AUTO_cc_cele_2 | F15: =VLOOKUP($E15,Hybrid!$1:$1048576,MATCH(DATE(F$2,1,1),Hybrid!$A$1:$LI$1),FALSE) -> 9.4015406 | G15: =VLOOKUP($E15,Hybrid!$1:$1048576,MATCH(DATE(G$2,1,1),Hybrid!$A$1:$LI$1),FALSE) -> 12.832838 | H15: =VLOOKUP($E15,Hybrid!$1:$1048576,MATCH(DATE(H$2,1,1),Hybrid!$A$1:$LI$1),FALSE) -> 16.202642 | I15: =VLOOKUP($E15,Hybrid!$1:$1048576,MATCH(DATE(I$2,1,1),Hybrid!$A$1:$LI$1),FALSE) -> 19.739118 | J15: =VLOOKUP($E15,Hybrid!$1:$1048576,MATCH(DATE(J$2,1,1),Hybrid!$A$1:$LI$1),FALSE) -> 24.40642 | K15: =VLOOKUP($E15,Hybrid!$1:$1048576,MATCH(DATE(K$2,1,1),Hybrid!$A$1:$LI$1),FALSE) -> 29.941402 | L15: =VLOOKUP($E15,Hybrid!$1:$1048576,MATCH(DATE(L$2,1,1),Hybrid!$A$1:$LI$1),FALSE) -> 35.093184 | M15: =VLOOKUP($E15,Hybrid!$1:$1048576,MATCH(DATE(M$2,1,1),Hybrid!$A$1:$LI$1),FALSE) -> 40.243356 | ... AO15: =VLOOKUP($E15,Hybrid!$1:$1048576,MATCH(DATE(AO$2,1,1),Hybrid!$A$1:$LI$1),FALSE) -> 324.95954
D16: class D | E16: AUTO_cd_cele_2 | F16: =VLOOKUP($E16,Hybrid!$1:$1048576,MATCH(DATE(F$2,1,1),Hybrid!$A$1:$LI$1),FALSE) -> 5.7700713 | G16: =VLOOKUP($E16,Hybrid!$1:$1048576,MATCH(DATE(G$2,1,1),Hybrid!$A$1:$LI$1),FALSE) -> 7.6428377 | H16: =VLOOKUP($E16,Hybrid!$1:$1048576,MATCH(DATE(H$2,1,1),Hybrid!$A$1:$LI$1),FALSE) -> 9.4920994 | I16: =VLOOKUP($E16,Hybrid!$1:$1048576,MATCH(DATE(I$2,1,1),Hybrid!$A$1:$LI$1),FALSE) -> 11.326103 | J16: =VLOOKUP($E16,Hybrid!$1:$1048576,MATCH(DATE(J$2,1,1),Hybrid!$A$1:$LI$1),FALSE) -> 13.474679 | K16: =VLOOKUP($E16,Hybrid!$1:$1048576,MATCH(DATE(K$2,1,1),Hybrid!$A$1:$LI$1),FALSE) -> 15.973369 | L16: =VLOOKUP($E16,Hybrid!$1:$1048576,MATCH(DATE(L$2,1,1),Hybrid!$A$1:$LI$1),FALSE) -> 18.287422 | M16: =VLOOKUP($E16,Hybrid!$1:$1048576,MATCH(DATE(M$2,1,1),Hybrid!$A$1:$LI$1),FALSE) -> 20.543924 | ... AO16: =VLOOKUP($E16,Hybrid!$1:$1048576,MATCH(DATE(AO$2,1,1),Hybrid!$A$1:$LI$1),FALSE) -> 81.879316
D17: class E | E17: AUTO_ce_cele_2 | F17: =VLOOKUP($E17,Hybrid!$1:$1048576,MATCH(DATE(F$2,1,1),Hybrid!$A$1:$LI$1),FALSE) -> 3.4730441 | G17: =VLOOKUP($E17,Hybrid!$1:$1048576,MATCH(DATE(G$2,1,1),Hybrid!$A$1:$LI$1),FALSE) -> 4.6249148 | H17: =VLOOKUP($E17,Hybrid!$1:$1048576,MATCH(DATE(H$2,1,1),Hybrid!$A$1:$LI$1),FALSE) -> 5.7523786 | I17: =VLOOKUP($E17,Hybrid!$1:$1048576,MATCH(DATE(I$2,1,1),Hybrid!$A$1:$LI$1),FALSE) -> 6.8615175 | J17: =VLOOKUP($E17,Hybrid!$1:$1048576,MATCH(DATE(J$2,1,1),Hybrid!$A$1:$LI$1),FALSE) -> 8.1537725 | K17: =VLOOKUP($E17,Hybrid!$1:$1048576,MATCH(DATE(K$2,1,1),Hybrid!$A$1:$LI$1),FALSE) -> 9.6477859 | L17: =VLOOKUP($E17,Hybrid!$1:$1048576,MATCH(DATE(L$2,1,1),Hybrid!$A$1:$LI$1),FALSE) -> 11.020385 | M17: =VLOOKUP($E17,Hybrid!$1:$1048576,MATCH(DATE(M$2,1,1),Hybrid!$A$1:$LI$1),FALSE) -> 12.343742 | ... AO17: =VLOOKUP($E17,Hybrid!$1:$1048576,MATCH(DATE(AO$2,1,1),Hybrid!$A$1:$LI$1),FALSE) -> 34.813935
D18: class F | E18: AUTO_cf_cele_2 | F18: =VLOOKUP($E18,Hybrid!$1:$1048576,MATCH(DATE(F$2,1,1),Hybrid!$A$1:$LI$1),FALSE) -> 1.7251505 | G18: =VLOOKUP($E18,Hybrid!$1:$1048576,MATCH(DATE(G$2,1,1),Hybrid!$A$1:$LI$1),FALSE) -> 2.2746845 | H18: =VLOOKUP($E18,Hybrid!$1:$1048576,MATCH(DATE(H$2,1,1),Hybrid!$A$1:$LI$1),FALSE) -> 2.8024089 | I18: =VLOOKUP($E18,Hybrid!$1:$1048576,MATCH(DATE(I$2,1,1),Hybrid!$A$1:$LI$1),FALSE) -> 3.2921455 | J18: =VLOOKUP($E18,Hybrid!$1:$1048576,MATCH(DATE(J$2,1,1),Hybrid!$A$1:$LI$1),FALSE) -> 3.813303 | K18: =VLOOKUP($E18,Hybrid!$1:$1048576,MATCH(DATE(K$2,1,1),Hybrid!$A$1:$LI$1),FALSE) -> 4.3950533 | L18: =VLOOKUP($E18,Hybrid!$1:$1048576,MATCH(DATE(L$2,1,1),Hybrid!$A$1:$LI$1),FALSE) -> 4.9147746 | M18: =VLOOKUP($E18,Hybrid!$1:$1048576,MATCH(DATE(M$2,1,1),Hybrid!$A$1:$LI$1),FALSE) -> 5.3901822 | ... AO18: =VLOOKUP($E18,Hybrid!$1:$1048576,MATCH(DATE(AO$2,1,1),Hybrid!$A$1:$LI$1),FALSE) -> 5.4257884
D19: class G | E19: AUTO_cg_cele_2 | F19: =VLOOKUP($E19,Hybrid!$1:$1048576,MATCH(DATE(F$2,1,1),Hybrid!$A$1:$LI$1),FALSE) -> 3.1066862 | G19: =VLOOKUP($E19,Hybrid!$1:$1048576,MATCH(DATE(G$2,1,1),Hybrid!$A$1:$LI$1),FALSE) -> 4.1345154 | H19: =VLOOKUP($E19,Hybrid!$1:$1048576,MATCH(DATE(H$2,1,1),Hybrid!$A$1:$LI$1),FALSE) -> 5.1001109 | I19: =VLOOKUP($E19,Hybrid!$1:$1048576,MATCH(DATE(I$2,1,1),Hybrid!$A$1:$LI$1),FALSE) -> 5.9664963 | J19: =VLOOKUP($E19,Hybrid!$1:$1048576,MATCH(DATE(J$2,1,1),Hybrid!$A$1:$LI$1),FALSE) -> 6.8544854 | K19: =VLOOKUP($E19,Hybrid!$1:$1048576,MATCH(DATE(K$2,1,1),Hybrid!$A$1:$LI$1),FALSE) -> 7.8193969 | L19: =VLOOKUP($E19,Hybrid!$1:$1048576,MATCH(DATE(L$2,1,1),Hybrid!$A$1:$LI$1),FALSE) -> 8.6575944 | M19: =VLOOKUP($E19,Hybrid!$1:$1048576,MATCH(DATE(M$2,1,1),Hybrid!$A$1:$LI$1),FALSE) -> 9.3918738 | ... AO19: =VLOOKUP($E19,Hybrid!$1:$1048576,MATCH(DATE(AO$2,1,1),Hybrid!$A$1:$LI$1),FALSE) -> 6.1960426
C20: GAS | E20: AUTO_cgas_2 | F20: =VLOOKUP($E20,Hybrid!$1:$1048576,MATCH(DATE(F$2,1,1),Hybrid!$A$1:$LI$1),FALSE) -> 1.936 | G20: =VLOOKUP($E20,Hybrid!$1:$1048576,MATCH(DATE(G$2,1,1),Hybrid!$A$1:$LI$1),FALSE) -> 1.998633 | H20: =VLOOKUP($E20,Hybrid!$1:$1048576,MATCH(DATE(H$2,1,1),Hybrid!$A$1:$LI$1),FALSE) -> 2.0641605 | I20: =VLOOKUP($E20,Hybrid!$1:$1048576,MATCH(DATE(I$2,1,1),Hybrid!$A$1:$LI$1),FALSE) -> 2.1250573 | J20: =VLOOKUP($E20,Hybrid!$1:$1048576,MATCH(DATE(J$2,1,1),Hybrid!$A$1:$LI$1),FALSE) -> 2.1974643 | K20: =VLOOKUP($E20,Hybrid!$1:$1048576,MATCH(DATE(K$2,1,1),Hybrid!$A$1:$LI$1),FALSE) -> 2.2961023 | L20: =VLOOKUP($E20,Hybrid!$1:$1048576,MATCH(DATE(L$2,1,1),Hybrid!$A$1:$LI$1),FALSE) -> 2.3832771 | M20: =VLOOKUP($E20,Hybrid!$1:$1048576,MATCH(DATE(M$2,1,1),Hybrid!$A$1:$LI$1),FALSE) -> 2.4663804 | ... AO20: =VLOOKUP($E20,Hybrid!$1:$1048576,MATCH(DATE(AO$2,1,1),Hybrid!$A$1:$LI$1),FALSE) -> 4.2104219
D21: class A | E21: AUTO_ca_cgas_2 | F21: =VLOOKUP($E21,Hybrid!$1:$1048576,MATCH(DATE(F$2,1,1),Hybrid!$A$1:$LI$1),FALSE) -> 0.4256817 | G21: =VLOOKUP($E21,Hybrid!$1:$1048576,MATCH(DATE(G$2,1,1),Hybrid!$A$1:$LI$1),FALSE) -> 0.45117089 | H21: =VLOOKUP($E21,Hybrid!$1:$1048576,MATCH(DATE(H$2,1,1),Hybrid!$A$1:$LI$1),FALSE) -> 0.47734696 | I21: =VLOOKUP($E21,Hybrid!$1:$1048576,MATCH(DATE(I$2,1,1),Hybrid!$A$1:$LI$1),FALSE) -> 0.50243473 | J21: =VLOOKUP($E21,Hybrid!$1:$1048576,MATCH(DATE(J$2,1,1),Hybrid!$A$1:$LI$1),FALSE) -> 0.53124474 | K21: =VLOOKUP($E21,Hybrid!$1:$1048576,MATCH(DATE(K$2,1,1),Hybrid!$A$1:$LI$1),FALSE) -> 0.56771835 | L21: =VLOOKUP($E21,Hybrid!$1:$1048576,MATCH(DATE(L$2,1,1),Hybrid!$A$1:$LI$1),FALSE) -> 0.6006008 | M21: =VLOOKUP($E21,Hybrid!$1:$1048576,MATCH(DATE(M$2,1,1),Hybrid!$A$1:$LI$1),FALSE) -> 0.63246302 | ... AO21: =VLOOKUP($E21,Hybrid!$1:$1048576,MATCH(DATE(AO$2,1,1),Hybrid!$A$1:$LI$1),FALSE) -> 1.5340259
D22: class B | E22: AUTO_cb_cgas_2 | F22: =VLOOKUP($E22,Hybrid!$1:$1048576,MATCH(DATE(F$2,1,1),Hybrid!$A$1:$LI$1),FALSE) -> 0.49500523 | G22: =VLOOKUP($E22,Hybrid!$1:$1048576,MATCH(DATE(G$2,1,1),Hybrid!$A$1:$LI$1),FALSE) -> 0.51405784 | H22: =VLOOKUP($E22,Hybrid!$1:$1048576,MATCH(DATE(H$2,1,1),Hybrid!$A$1:$LI$1),FALSE) -> 0.53404363 | I22: =VLOOKUP($E22,Hybrid!$1:$1048576,MATCH(DATE(I$2,1,1),Hybrid!$A$1:$LI$1),FALSE) -> 0.55311339 | J22: =VLOOKUP($E22,Hybrid!$1:$1048576,MATCH(DATE(J$2,1,1),Hybrid!$A$1:$LI$1),FALSE) -> 0.57578538 | K22: =VLOOKUP($E22,Hybrid!$1:$1048576,MATCH(DATE(K$2,1,1),Hybrid!$A$1:$LI$1),FALSE) -> 0.60597728 | L22: =VLOOKUP($E22,Hybrid!$1:$1048576,MATCH(DATE(L$2,1,1),Hybrid!$A$1:$LI$1),FALSE) -> 0.63303825 | M22: =VLOOKUP($E22,Hybrid!$1:$1048576,MATCH(DATE(M$2,1,1),Hybrid!$A$1:$LI$1),FALSE) -> 0.65924738 | ... AO22: =VLOOKUP($E22,Hybrid!$1:$1048576,MATCH(DATE(AO$2,1,1),Hybrid!$A$1:$LI$1),FALSE) -> 1.3300807
D23: class C | E23: AUTO_cc_cgas_2 | F23: =VLOOKUP($E23,Hybrid!$1:$1048576,MATCH(DATE(F$2,1,1),Hybrid!$A$1:$LI$1),FALSE) -> 0.40659852 | G23: =VLOOKUP($E23,Hybrid!$1:$1048576,MATCH(DATE(G$2,1,1),Hybrid!$A$1:$LI$1),FALSE) -> 0.41577328 | H23: =VLOOKUP($E23,Hybrid!$1:$1048576,MATCH(DATE(H$2,1,1),Hybrid!$A$1:$LI$1),FALSE) -> 0.42580019 | I23: =VLOOKUP($E23,Hybrid!$1:$1048576,MATCH(DATE(I$2,1,1),Hybrid!$A$1:$LI$1),FALSE) -> 0.43529965 | J23: =VLOOKUP($E23,Hybrid!$1:$1048576,MATCH(DATE(J$2,1,1),Hybrid!$A$1:$LI$1),FALSE) -> 0.44733124 | K23: =VLOOKUP($E23,Hybrid!$1:$1048576,MATCH(DATE(K$2,1,1),Hybrid!$A$1:$LI$1),FALSE) -> 0.46469577 | L23: =VLOOKUP($E23,Hybrid!$1:$1048576,MATCH(DATE(L$2,1,1),Hybrid!$A$1:$LI$1),FALSE) -> 0.48012467 | M23: =VLOOKUP($E23,Hybrid!$1:$1048576,MATCH(DATE(M$2,1,1),Hybrid!$A$1:$LI$1),FALSE) -> 0.49506737 | ... AO23: =VLOOKUP($E23,Hybrid!$1:$1048576,MATCH(DATE(AO$2,1,1),Hybrid!$A$1:$LI$1),FALSE) -> 0.83616867
D24: class D | E24: AUTO_cd_cgas_2 | F24: =VLOOKUP($E24,Hybrid!$1:$1048576,MATCH(DATE(F$2,1,1),Hybrid!$A$1:$LI$1),FALSE) -> 0.24954447 | G24: =VLOOKUP($E24,Hybrid!$1:$1048576,MATCH(DATE(G$2,1,1),Hybrid!$A$1:$LI$1),FALSE) -> 0.25306755 | H24: =VLOOKUP($E24,Hybrid!$1:$1048576,MATCH(DATE(H$2,1,1),Hybrid!$A$1:$LI$1),FALSE) -> 0.257036 | I24: =VLOOKUP($E24,Hybrid!$1:$1048576,MATCH(DATE(I$2,1,1),Hybrid!$A$1:$LI$1),FALSE) -> 0.2605875 | J24: =VLOOKUP($E24,Hybrid!$1:$1048576,MATCH(DATE(J$2,1,1),Hybrid!$A$1:$LI$1),FALSE) -> 0.26535007 | K24: =VLOOKUP($E24,Hybrid!$1:$1048576,MATCH(DATE(K$2,1,1),Hybrid!$A$1:$LI$1),FALSE) -> 0.27291072 | L24: =VLOOKUP($E24,Hybrid!$1:$1048576,MATCH(DATE(L$2,1,1),Hybrid!$A$1:$LI$1),FALSE) -> 0.27942957 | M24: =VLOOKUP($E24,Hybrid!$1:$1048576,MATCH(DATE(M$2,1,1),Hybrid!$A$1:$LI$1),FALSE) -> 0.28555778 | ... AO24: =VLOOKUP($E24,Hybrid!$1:$1048576,MATCH(DATE(AO$2,1,1),Hybrid!$A$1:$LI$1),FALSE) -> 0.30860857
D25: class E | E25: AUTO_ce_cgas_2 | F25: =VLOOKUP($E25,Hybrid!$1:$1048576,MATCH(DATE(F$2,1,1),Hybrid!$A$1:$LI$1),FALSE) -> 0.15020247 | G25: =VLOOKUP($E25,Hybrid!$1:$1048576,MATCH(DATE(G$2,1,1),Hybrid!$A$1:$LI$1),FALSE) -> 0.15254896 | H25: =VLOOKUP($E25,Hybrid!$1:$1048576,MATCH(DATE(H$2,1,1),Hybrid!$A$1:$LI$1),FALSE) -> 0.15509164 | I25: =VLOOKUP($E25,Hybrid!$1:$1048576,MATCH(DATE(I$2,1,1),Hybrid!$A$1:$LI$1),FALSE) -> 0.15724578 | J25: =VLOOKUP($E25,Hybrid!$1:$1048576,MATCH(DATE(J$2,1,1),Hybrid!$A$1:$LI$1),FALSE) -> 0.15997385 | K25: =VLOOKUP($E25,Hybrid!$1:$1048576,MATCH(DATE(K$2,1,1),Hybrid!$A$1:$LI$1),FALSE) -> 0.16428533 | L25: =VLOOKUP($E25,Hybrid!$1:$1048576,MATCH(DATE(L$2,1,1),Hybrid!$A$1:$LI$1),FALSE) -> 0.16793015 | M25: =VLOOKUP($E25,Hybrid!$1:$1048576,MATCH(DATE(M$2,1,1),Hybrid!$A$1:$LI$1),FALSE) -> 0.17123097 | ... AO25: =VLOOKUP($E25,Hybrid!$1:$1048576,MATCH(DATE(AO$2,1,1),Hybrid!$A$1:$LI$1),FALSE) -> 0.13541507
D26: class F | E26: AUTO_cf_cgas_2 | F26: =VLOOKUP($E26,Hybrid!$1:$1048576,MATCH(DATE(F$2,1,1),Hybrid!$A$1:$LI$1),FALSE) -> 0.074609436 | G26: =VLOOKUP($E26,Hybrid!$1:$1048576,MATCH(DATE(G$2,1,1),Hybrid!$A$1:$LI$1),FALSE) -> 0.075572076 | H26: =VLOOKUP($E26,Hybrid!$1:$1048576,MATCH(DATE(H$2,1,1),Hybrid!$A$1:$LI$1),FALSE) -> 0.076526792 | I26: =VLOOKUP($E26,Hybrid!$1:$1048576,MATCH(DATE(I$2,1,1),Hybrid!$A$1:$LI$1),FALSE) -> 0.077128688 | J26: =VLOOKUP($E26,Hybrid!$1:$1048576,MATCH(DATE(J$2,1,1),Hybrid!$A$1:$LI$1),FALSE) -> 0.077798251 | K26: =VLOOKUP($E26,Hybrid!$1:$1048576,MATCH(DATE(K$2,1,1),Hybrid!$A$1:$LI$1),FALSE) -> 0.079036001 | L26: =VLOOKUP($E26,Hybrid!$1:$1048576,MATCH(DATE(L$2,1,1),Hybrid!$A$1:$LI$1),FALSE) -> 0.079913747 | M26: =VLOOKUP($E26,Hybrid!$1:$1048576,MATCH(DATE(M$2,1,1),Hybrid!$A$1:$LI$1),FALSE) -> 0.080503731 | ... AO26: =VLOOKUP($E26,Hybrid!$1:$1048576,MATCH(DATE(AO$2,1,1),Hybrid!$A$1:$LI$1),FALSE) -> 0.028975295
D27: class G | E27: AUTO_cg_cgas_2 | F27: =VLOOKUP($E27,Hybrid!$1:$1048576,MATCH(DATE(F$2,1,1),Hybrid!$A$1:$LI$1),FALSE) -> 0.13435819 | G27: =VLOOKUP($E27,Hybrid!$1:$1048576,MATCH(DATE(G$2,1,1),Hybrid!$A$1:$LI$1),FALSE) -> 0.13644246 | H27: =VLOOKUP($E27,Hybrid!$1:$1048576,MATCH(DATE(H$2,1,1),Hybrid!$A$1:$LI$1),FALSE) -> 0.13831532 | I27: =VLOOKUP($E27,Hybrid!$1:$1048576,MATCH(DATE(I$2,1,1),Hybrid!$A$1:$LI$1),FALSE) -> 0.1392476 | J27: =VLOOKUP($E27,Hybrid!$1:$1048576,MATCH(DATE(J$2,1,1),Hybrid!$A$1:$LI$1),FALSE) -> 0.13998077 | K27: =VLOOKUP($E27,Hybrid!$1:$1048576,MATCH(DATE(K$2,1,1),Hybrid!$A$1:$LI$1),FALSE) -> 0.14147882 | L27: =VLOOKUP($E27,Hybrid!$1:$1048576,MATCH(DATE(L$2,1,1),Hybrid!$A$1:$LI$1),FALSE) -> 0.14223995 | M27: =VLOOKUP($E27,Hybrid!$1:$1048576,MATCH(DATE(M$2,1,1),Hybrid!$A$1:$LI$1),FALSE) -> 0.14231011 | ... AO27: =VLOOKUP($E27,Hybrid!$1:$1048576,MATCH(DATE(AO$2,1,1),Hybrid!$A$1:$LI$1),FALSE) -> 0.037147693
C28: TOTAL STOCK BASELINE | E28: AUTO_0 | F28: =VLOOKUP($E28,Hybrid!$1:$1048576,MATCH(DATE(F$2,1,1),Hybrid!$A$1:$LI$1),FALSE) -> 32317.941 | G28: =VLOOKUP($E28,Hybrid!$1:$1048576,MATCH(DATE(G$2,1,1),Hybrid!$A$1:$LI$1),FALSE) -> 32010.864 | H28: =VLOOKUP($E28,Hybrid!$1:$1048576,MATCH(DATE(H$2,1,1),Hybrid!$A$1:$LI$1),FALSE) -> 31809.838 | I28: =VLOOKUP($E28,Hybrid!$1:$1048576,MATCH(DATE(I$2,1,1),Hybrid!$A$1:$LI$1),FALSE) -> 31619.962 | J28: =VLOOKUP($E28,Hybrid!$1:$1048576,MATCH(DATE(J$2,1,1),Hybrid!$A$1:$LI$1),FALSE) -> 31633.548 | K28: =VLOOKUP($E28,Hybrid!$1:$1048576,MATCH(DATE(K$2,1,1),Hybrid!$A$1:$LI$1),FALSE) -> 32018.121 | L28: =VLOOKUP($E28,Hybrid!$1:$1048576,MATCH(DATE(L$2,1,1),Hybrid!$A$1:$LI$1),FALSE) -> 32313.722 | M28: =VLOOKUP($E28,Hybrid!$1:$1048576,MATCH(DATE(M$2,1,1),Hybrid!$A$1:$LI$1),FALSE) -> 32619.741 | ... AO28: =VLOOKUP($E28,Hybrid!$1:$1048576,MATCH(DATE(AO$2,1,1),Hybrid!$A$1:$LI$1),FALSE) -> 41935.996
C29: OIL | E29: AUTO_cfut_0 | F29: =VLOOKUP($E29,Hybrid!$1:$1048576,MATCH(DATE(F$2,1,1),Hybrid!$A$1:$LI$1),FALSE) -> 32271.24 | G29: =VLOOKUP($E29,Hybrid!$1:$1048576,MATCH(DATE(G$2,1,1),Hybrid!$A$1:$LI$1),FALSE) -> 31945.681 | H29: =VLOOKUP($E29,Hybrid!$1:$1048576,MATCH(DATE(H$2,1,1),Hybrid!$A$1:$LI$1),FALSE) -> 31726.506 | I29: =VLOOKUP($E29,Hybrid!$1:$1048576,MATCH(DATE(I$2,1,1),Hybrid!$A$1:$LI$1),FALSE) -> 31518.017 | J29: =VLOOKUP($E29,Hybrid!$1:$1048576,MATCH(DATE(J$2,1,1),Hybrid!$A$1:$LI$1),FALSE) -> 31508.065 | K29: =VLOOKUP($E29,Hybrid!$1:$1048576,MATCH(DATE(K$2,1,1),Hybrid!$A$1:$LI$1),FALSE) -> 31864.988 | L29: =VLOOKUP($E29,Hybrid!$1:$1048576,MATCH(DATE(L$2,1,1),Hybrid!$A$1:$LI$1),FALSE) -> 32134.903 | M29: =VLOOKUP($E29,Hybrid!$1:$1048576,MATCH(DATE(M$2,1,1),Hybrid!$A$1:$LI$1),FALSE) -> 32415.48 | ... AO29: =VLOOKUP($E29,Hybrid!$1:$1048576,MATCH(DATE(AO$2,1,1),Hybrid!$A$1:$LI$1),FALSE) -> 41055.538
D30: class A | E30: AUTO_ca_cfut_0 | F30: =VLOOKUP($E30,Hybrid!$1:$1048576,MATCH(DATE(F$2,1,1),Hybrid!$A$1:$LI$1),FALSE) -> 7095.7005 | G30: =VLOOKUP($E30,Hybrid!$1:$1048576,MATCH(DATE(G$2,1,1),Hybrid!$A$1:$LI$1),FALSE) -> 7163.595 | H30: =VLOOKUP($E30,Hybrid!$1:$1048576,MATCH(DATE(H$2,1,1),Hybrid!$A$1:$LI$1),FALSE) -> 7253.3446 | I30: =VLOOKUP($E30,Hybrid!$1:$1048576,MATCH(DATE(I$2,1,1),Hybrid!$A$1:$LI$1),FALSE) -> 7342.6292 | J30: =VLOOKUP($E30,Hybrid!$1:$1048576,MATCH(DATE(J$2,1,1),Hybrid!$A$1:$LI$1),FALSE) -> 7487.9362 | K30: =VLOOKUP($E30,Hybrid!$1:$1048576,MATCH(DATE(K$2,1,1),Hybrid!$A$1:$LI$1),FALSE) -> 7734.59 | L30: =VLOOKUP($E30,Hybrid!$1:$1048576,MATCH(DATE(L$2,1,1),Hybrid!$A$1:$LI$1),FALSE) -> 7947.3144 | M30: =VLOOKUP($E30,Hybrid!$1:$1048576,MATCH(DATE(M$2,1,1),Hybrid!$A$1:$LI$1),FALSE) -> 8158.3698 | ... AO30: =VLOOKUP($E30,Hybrid!$1:$1048576,MATCH(DATE(AO$2,1,1),Hybrid!$A$1:$LI$1),FALSE) -> 13990.99
D31: class B | E31: AUTO_cb_cfut_0 | F31: =VLOOKUP($E31,Hybrid!$1:$1048576,MATCH(DATE(F$2,1,1),Hybrid!$A$1:$LI$1),FALSE) -> 8251.2564 | G31: =VLOOKUP($E31,Hybrid!$1:$1048576,MATCH(DATE(G$2,1,1),Hybrid!$A$1:$LI$1),FALSE) -> 8204.1818 | H31: =VLOOKUP($E31,Hybrid!$1:$1048576,MATCH(DATE(H$2,1,1),Hybrid!$A$1:$LI$1),FALSE) -> 8186.0524 | I31: =VLOOKUP($E31,Hybrid!$1:$1048576,MATCH(DATE(I$2,1,1),Hybrid!$A$1:$LI$1),FALSE) -> 8173.2987 | J31: =VLOOKUP($E31,Hybrid!$1:$1048576,MATCH(DATE(J$2,1,1),Hybrid!$A$1:$LI$1),FALSE) -> 8218.6024 | K31: =VLOOKUP($E31,Hybrid!$1:$1048576,MATCH(DATE(K$2,1,1),Hybrid!$A$1:$LI$1),FALSE) -> 8366.7584 | L31: =VLOOKUP($E31,Hybrid!$1:$1048576,MATCH(DATE(L$2,1,1),Hybrid!$A$1:$LI$1),FALSE) -> 8489.4693 | M31: =VLOOKUP($E31,Hybrid!$1:$1048576,MATCH(DATE(M$2,1,1),Hybrid!$A$1:$LI$1),FALSE) -> 8615.599 | ... AO31: =VLOOKUP($E31,Hybrid!$1:$1048576,MATCH(DATE(AO$2,1,1),Hybrid!$A$1:$LI$1),FALSE) -> 12664.977
D32: class C | E32: AUTO_cc_cfut_0 | F32: =VLOOKUP($E32,Hybrid!$1:$1048576,MATCH(DATE(F$2,1,1),Hybrid!$A$1:$LI$1),FALSE) -> 6777.6025 | G32: =VLOOKUP($E32,Hybrid!$1:$1048576,MATCH(DATE(G$2,1,1),Hybrid!$A$1:$LI$1),FALSE) -> 6661.8607 | H32: =VLOOKUP($E32,Hybrid!$1:$1048576,MATCH(DATE(H$2,1,1),Hybrid!$A$1:$LI$1),FALSE) -> 6572.095 | I32: =VLOOKUP($E32,Hybrid!$1:$1048576,MATCH(DATE(I$2,1,1),Hybrid!$A$1:$LI$1),FALSE) -> 6490.4961 | J32: =VLOOKUP($E32,Hybrid!$1:$1048576,MATCH(DATE(J$2,1,1),Hybrid!$A$1:$LI$1),FALSE) -> 6452.4548 | K32: =VLOOKUP($E32,Hybrid!$1:$1048576,MATCH(DATE(K$2,1,1),Hybrid!$A$1:$LI$1),FALSE) -> 6489.804 | L32: =VLOOKUP($E32,Hybrid!$1:$1048576,MATCH(DATE(L$2,1,1),Hybrid!$A$1:$LI$1),FALSE) -> 6514.7743 | M32: =VLOOKUP($E32,Hybrid!$1:$1048576,MATCH(DATE(M$2,1,1),Hybrid!$A$1:$LI$1),FALSE) -> 6545.8934 | ... AO32: =VLOOKUP($E32,Hybrid!$1:$1048576,MATCH(DATE(AO$2,1,1),Hybrid!$A$1:$LI$1),FALSE) -> 8288.5114
D33: class D | E33: AUTO_cd_cfut_0 | F33: =VLOOKUP($E33,Hybrid!$1:$1048576,MATCH(DATE(F$2,1,1),Hybrid!$A$1:$LI$1),FALSE) -> 4159.6639 | G33: =VLOOKUP($E33,Hybrid!$1:$1048576,MATCH(DATE(G$2,1,1),Hybrid!$A$1:$LI$1),FALSE) -> 4063.5393 | H33: =VLOOKUP($E33,Hybrid!$1:$1048576,MATCH(DATE(H$2,1,1),Hybrid!$A$1:$LI$1),FALSE) -> 3982.8175 | I33: =VLOOKUP($E33,Hybrid!$1:$1048576,MATCH(DATE(I$2,1,1),Hybrid!$A$1:$LI$1),FALSE) -> 3906.3668 | J33: =VLOOKUP($E33,Hybrid!$1:$1048576,MATCH(DATE(J$2,1,1),Hybrid!$A$1:$LI$1),FALSE) -> 3852.9234 | K33: =VLOOKUP($E33,Hybrid!$1:$1048576,MATCH(DATE(K$2,1,1),Hybrid!$A$1:$LI$1),FALSE) -> 3840.4882 | L33: =VLOOKUP($E33,Hybrid!$1:$1048576,MATCH(DATE(L$2,1,1),Hybrid!$A$1:$LI$1),FALSE) -> 3822.6867 | M33: =VLOOKUP($E33,Hybrid!$1:$1048576,MATCH(DATE(M$2,1,1),Hybrid!$A$1:$LI$1),FALSE) -> 3808.469 | ... AO33: =VLOOKUP($E33,Hybrid!$1:$1048576,MATCH(DATE(AO$2,1,1),Hybrid!$A$1:$LI$1),FALSE) -> 3519.3956
D34: class E | E34: AUTO_ce_cfut_0 | F34: =VLOOKUP($E34,Hybrid!$1:$1048576,MATCH(DATE(F$2,1,1),Hybrid!$A$1:$LI$1),FALSE) -> 2503.7292 | G34: =VLOOKUP($E34,Hybrid!$1:$1048576,MATCH(DATE(G$2,1,1),Hybrid!$A$1:$LI$1),FALSE) -> 2448.5604 | H34: =VLOOKUP($E34,Hybrid!$1:$1048576,MATCH(DATE(H$2,1,1),Hybrid!$A$1:$LI$1),FALSE) -> 2401.7659 | I34: =VLOOKUP($E34,Hybrid!$1:$1048576,MATCH(DATE(I$2,1,1),Hybrid!$A$1:$LI$1),FALSE) -> 2355.8796 | J34: =VLOOKUP($E34,Hybrid!$1:$1048576,MATCH(DATE(J$2,1,1),Hybrid!$A$1:$LI$1),FALSE) -> 2321.9985 | K34: =VLOOKUP($E34,Hybrid!$1:$1048576,MATCH(DATE(K$2,1,1),Hybrid!$A$1:$LI$1),FALSE) -> 2311.6313 | L34: =VLOOKUP($E34,Hybrid!$1:$1048576,MATCH(DATE(L$2,1,1),Hybrid!$A$1:$LI$1),FALSE) -> 2297.6561 | M34: =VLOOKUP($E34,Hybrid!$1:$1048576,MATCH(DATE(M$2,1,1),Hybrid!$A$1:$LI$1),FALSE) -> 2284.9522 | ... AO34: =VLOOKUP($E34,Hybrid!$1:$1048576,MATCH(DATE(AO$2,1,1),Hybrid!$A$1:$LI$1),FALSE) -> 1708.8877
D35: class F | E35: AUTO_cf_cfut_0 | F35: =VLOOKUP($E35,Hybrid!$1:$1048576,MATCH(DATE(F$2,1,1),Hybrid!$A$1:$LI$1),FALSE) -> 1243.6668 | G35: =VLOOKUP($E35,Hybrid!$1:$1048576,MATCH(DATE(G$2,1,1),Hybrid!$A$1:$LI$1),FALSE) -> 1213.8476 | H35: =VLOOKUP($E35,Hybrid!$1:$1048576,MATCH(DATE(H$2,1,1),Hybrid!$A$1:$LI$1),FALSE) -> 1186.9708 | I35: =VLOOKUP($E35,Hybrid!$1:$1048576,MATCH(DATE(I$2,1,1),Hybrid!$A$1:$LI$1),FALSE) -> 1158.6962 | J35: =VLOOKUP($E35,Hybrid!$1:$1048576,MATCH(DATE(J$2,1,1),Hybrid!$A$1:$LI$1),FALSE) -> 1133.8751 | K35: =VLOOKUP($E35,Hybrid!$1:$1048576,MATCH(DATE(K$2,1,1),Hybrid!$A$1:$LI$1),FALSE) -> 1118.247 | L35: =VLOOKUP($E35,Hybrid!$1:$1048576,MATCH(DATE(L$2,1,1),Hybrid!$A$1:$LI$1),FALSE) -> 1100.6789 | M35: =VLOOKUP($E35,Hybrid!$1:$1048576,MATCH(DATE(M$2,1,1),Hybrid!$A$1:$LI$1),FALSE) -> 1082.8744 | ... AO35: =VLOOKUP($E35,Hybrid!$1:$1048576,MATCH(DATE(AO$2,1,1),Hybrid!$A$1:$LI$1),FALSE) -> 405.9994
D36: class G | E36: AUTO_cg_cfut_0 | F36: =VLOOKUP($E36,Hybrid!$1:$1048576,MATCH(DATE(F$2,1,1),Hybrid!$A$1:$LI$1),FALSE) -> 2239.6206 | G36: =VLOOKUP($E36,Hybrid!$1:$1048576,MATCH(DATE(G$2,1,1),Hybrid!$A$1:$LI$1),FALSE) -> 2190.0963 | H36: =VLOOKUP($E36,Hybrid!$1:$1048576,MATCH(DATE(H$2,1,1),Hybrid!$A$1:$LI$1),FALSE) -> 2143.4602 | I36: =VLOOKUP($E36,Hybrid!$1:$1048576,MATCH(DATE(I$2,1,1),Hybrid!$A$1:$LI$1),FALSE) -> 2090.6508 | J36: =VLOOKUP($E36,Hybrid!$1:$1048576,MATCH(DATE(J$2,1,1),Hybrid!$A$1:$LI$1),FALSE) -> 2040.2746 | K36: =VLOOKUP($E36,Hybrid!$1:$1048576,MATCH(DATE(K$2,1,1),Hybrid!$A$1:$LI$1),FALSE) -> 2003.4687 | L36: =VLOOKUP($E36,Hybrid!$1:$1048576,MATCH(DATE(L$2,1,1),Hybrid!$A$1:$LI$1),FALSE) -> 1962.3231 | M36: =VLOOKUP($E36,Hybrid!$1:$1048576,MATCH(DATE(M$2,1,1),Hybrid!$A$1:$LI$1),FALSE) -> 1919.3218 | ... AO36: =VLOOKUP($E36,Hybrid!$1:$1048576,MATCH(DATE(AO$2,1,1),Hybrid!$A$1:$LI$1),FALSE) -> 476.77743
C37: ELEC | E37: AUTO_cele_0 | F37: =VLOOKUP($E37,Hybrid!$1:$1048576,MATCH(DATE(F$2,1,1),Hybrid!$A$1:$LI$1),FALSE) -> 44.765 | G37: =VLOOKUP($E37,Hybrid!$1:$1048576,MATCH(DATE(G$2,1,1),Hybrid!$A$1:$LI$1),FALSE) -> 63.184204 | H37: =VLOOKUP($E37,Hybrid!$1:$1048576,MATCH(DATE(H$2,1,1),Hybrid!$A$1:$LI$1),FALSE) -> 81.267092 | I37: =VLOOKUP($E37,Hybrid!$1:$1048576,MATCH(DATE(I$2,1,1),Hybrid!$A$1:$LI$1),FALSE) -> 99.820025 | J37: =VLOOKUP($E37,Hybrid!$1:$1048576,MATCH(DATE(J$2,1,1),Hybrid!$A$1:$LI$1),FALSE) -> 123.28585 | K37: =VLOOKUP($E37,Hybrid!$1:$1048576,MATCH(DATE(K$2,1,1),Hybrid!$A$1:$LI$1),FALSE) -> 150.83685 | L37: =VLOOKUP($E37,Hybrid!$1:$1048576,MATCH(DATE(L$2,1,1),Hybrid!$A$1:$LI$1),FALSE) -> 176.43533 | M37: =VLOOKUP($E37,Hybrid!$1:$1048576,MATCH(DATE(M$2,1,1),Hybrid!$A$1:$LI$1),FALSE) -> 201.79347 | ... AO37: =VLOOKUP($E37,Hybrid!$1:$1048576,MATCH(DATE(AO$2,1,1),Hybrid!$A$1:$LI$1),FALSE) -> 876.39107
D38: class A | E38: AUTO_ca_cele_0 | F38: =VLOOKUP($E38,Hybrid!$1:$1048576,MATCH(DATE(F$2,1,1),Hybrid!$A$1:$LI$1),FALSE) -> 9.8427899 | G38: =VLOOKUP($E38,Hybrid!$1:$1048576,MATCH(DATE(G$2,1,1),Hybrid!$A$1:$LI$1),FALSE) -> 15.183587 | H38: =VLOOKUP($E38,Hybrid!$1:$1048576,MATCH(DATE(H$2,1,1),Hybrid!$A$1:$LI$1),FALSE) -> 20.45814 | I38: =VLOOKUP($E38,Hybrid!$1:$1048576,MATCH(DATE(I$2,1,1),Hybrid!$A$1:$LI$1),FALSE) -> 25.97122 | J38: =VLOOKUP($E38,Hybrid!$1:$1048576,MATCH(DATE(J$2,1,1),Hybrid!$A$1:$LI$1),FALSE) -> 33.113699 | K38: =VLOOKUP($E38,Hybrid!$1:$1048576,MATCH(DATE(K$2,1,1),Hybrid!$A$1:$LI$1),FALSE) -> 41.540103 | L38: =VLOOKUP($E38,Hybrid!$1:$1048576,MATCH(DATE(L$2,1,1),Hybrid!$A$1:$LI$1),FALSE) -> 49.410277 | M38: =VLOOKUP($E38,Hybrid!$1:$1048576,MATCH(DATE(M$2,1,1),Hybrid!$A$1:$LI$1),FALSE) -> 57.272909 | ... AO38: =VLOOKUP($E38,Hybrid!$1:$1048576,MATCH(DATE(AO$2,1,1),Hybrid!$A$1:$LI$1),FALSE) -> 305.40002
D39: class B | E39: AUTO_cb_cele_0 | F39: =VLOOKUP($E39,Hybrid!$1:$1048576,MATCH(DATE(F$2,1,1),Hybrid!$A$1:$LI$1),FALSE) -> 11.445717 | G39: =VLOOKUP($E39,Hybrid!$1:$1048576,MATCH(DATE(G$2,1,1),Hybrid!$A$1:$LI$1),FALSE) -> 16.490827 | H39: =VLOOKUP($E39,Hybrid!$1:$1048576,MATCH(DATE(H$2,1,1),Hybrid!$A$1:$LI$1),FALSE) -> 21.459313 | I39: =VLOOKUP($E39,Hybrid!$1:$1048576,MATCH(DATE(I$2,1,1),Hybrid!$A$1:$LI$1),FALSE) -> 26.663425 | J39: =VLOOKUP($E39,Hybrid!$1:$1048576,MATCH(DATE(J$2,1,1),Hybrid!$A$1:$LI$1),FALSE) -> 33.46949 | K39: =VLOOKUP($E39,Hybrid!$1:$1048576,MATCH(DATE(K$2,1,1),Hybrid!$A$1:$LI$1),FALSE) -> 41.519739 | L39: =VLOOKUP($E39,Hybrid!$1:$1048576,MATCH(DATE(L$2,1,1),Hybrid!$A$1:$LI$1),FALSE) -> 49.030683 | M39: =VLOOKUP($E39,Hybrid!$1:$1048576,MATCH(DATE(M$2,1,1),Hybrid!$A$1:$LI$1),FALSE) -> 56.528158 | ... AO39: =VLOOKUP($E39,Hybrid!$1:$1048576,MATCH(DATE(AO$2,1,1),Hybrid!$A$1:$LI$1),FALSE) -> 280.21415
D40: class C | E40: AUTO_cc_cele_0 | F40: =VLOOKUP($E40,Hybrid!$1:$1048576,MATCH(DATE(F$2,1,1),Hybrid!$A$1:$LI$1),FALSE) -> 9.4015406 | G40: =VLOOKUP($E40,Hybrid!$1:$1048576,MATCH(DATE(G$2,1,1),Hybrid!$A$1:$LI$1),FALSE) -> 12.832838 | H40: =VLOOKUP($E40,Hybrid!$1:$1048576,MATCH(DATE(H$2,1,1),Hybrid!$A$1:$LI$1),FALSE) -> 16.202642 | I40: =VLOOKUP($E40,Hybrid!$1:$1048576,MATCH(DATE(I$2,1,1),Hybrid!$A$1:$LI$1),FALSE) -> 19.739118 | J40: =VLOOKUP($E40,Hybrid!$1:$1048576,MATCH(DATE(J$2,1,1),Hybrid!$A$1:$LI$1),FALSE) -> 24.40642 | K40: =VLOOKUP($E40,Hybrid!$1:$1048576,MATCH(DATE(K$2,1,1),Hybrid!$A$1:$LI$1),FALSE) -> 29.941402 | L40: =VLOOKUP($E40,Hybrid!$1:$1048576,MATCH(DATE(L$2,1,1),Hybrid!$A$1:$LI$1),FALSE) -> 35.100306 | M40: =VLOOKUP($E40,Hybrid!$1:$1048576,MATCH(DATE(M$2,1,1),Hybrid!$A$1:$LI$1),FALSE) -> 40.245505 | ... AO40: =VLOOKUP($E40,Hybrid!$1:$1048576,MATCH(DATE(AO$2,1,1),Hybrid!$A$1:$LI$1),FALSE) -> 185.39915
D41: class D | E41: AUTO_cd_cele_0 | F41: =VLOOKUP($E41,Hybrid!$1:$1048576,MATCH(DATE(F$2,1,1),Hybrid!$A$1:$LI$1),FALSE) -> 5.7700713 | G41: =VLOOKUP($E41,Hybrid!$1:$1048576,MATCH(DATE(G$2,1,1),Hybrid!$A$1:$LI$1),FALSE) -> 7.6428377 | H41: =VLOOKUP($E41,Hybrid!$1:$1048576,MATCH(DATE(H$2,1,1),Hybrid!$A$1:$LI$1),FALSE) -> 9.4920994 | I41: =VLOOKUP($E41,Hybrid!$1:$1048576,MATCH(DATE(I$2,1,1),Hybrid!$A$1:$LI$1),FALSE) -> 11.326103 | J41: =VLOOKUP($E41,Hybrid!$1:$1048576,MATCH(DATE(J$2,1,1),Hybrid!$A$1:$LI$1),FALSE) -> 13.474679 | K41: =VLOOKUP($E41,Hybrid!$1:$1048576,MATCH(DATE(K$2,1,1),Hybrid!$A$1:$LI$1),FALSE) -> 15.973369 | L41: =VLOOKUP($E41,Hybrid!$1:$1048576,MATCH(DATE(L$2,1,1),Hybrid!$A$1:$LI$1),FALSE) -> 18.291801 | M41: =VLOOKUP($E41,Hybrid!$1:$1048576,MATCH(DATE(M$2,1,1),Hybrid!$A$1:$LI$1),FALSE) -> 20.562195 | ... AO41: =VLOOKUP($E41,Hybrid!$1:$1048576,MATCH(DATE(AO$2,1,1),Hybrid!$A$1:$LI$1),FALSE) -> 61.02655
D42: class E | E42: AUTO_ce_cele_0 | F42: =VLOOKUP($E42,Hybrid!$1:$1048576,MATCH(DATE(F$2,1,1),Hybrid!$A$1:$LI$1),FALSE) -> 3.4730441 | G42: =VLOOKUP($E42,Hybrid!$1:$1048576,MATCH(DATE(G$2,1,1),Hybrid!$A$1:$LI$1),FALSE) -> 4.6249148 | H42: =VLOOKUP($E42,Hybrid!$1:$1048576,MATCH(DATE(H$2,1,1),Hybrid!$A$1:$LI$1),FALSE) -> 5.7523786 | I42: =VLOOKUP($E42,Hybrid!$1:$1048576,MATCH(DATE(I$2,1,1),Hybrid!$A$1:$LI$1),FALSE) -> 6.8615175 | J42: =VLOOKUP($E42,Hybrid!$1:$1048576,MATCH(DATE(J$2,1,1),Hybrid!$A$1:$LI$1),FALSE) -> 8.1537725 | K42: =VLOOKUP($E42,Hybrid!$1:$1048576,MATCH(DATE(K$2,1,1),Hybrid!$A$1:$LI$1),FALSE) -> 9.6477859 | L42: =VLOOKUP($E42,Hybrid!$1:$1048576,MATCH(DATE(L$2,1,1),Hybrid!$A$1:$LI$1),FALSE) -> 11.023515 | M42: =VLOOKUP($E42,Hybrid!$1:$1048576,MATCH(DATE(M$2,1,1),Hybrid!$A$1:$LI$1),FALSE) -> 12.358868 | ... AO42: =VLOOKUP($E42,Hybrid!$1:$1048576,MATCH(DATE(AO$2,1,1),Hybrid!$A$1:$LI$1),FALSE) -> 29.699479
D43: class F | E43: AUTO_cf_cele_0 | F43: =VLOOKUP($E43,Hybrid!$1:$1048576,MATCH(DATE(F$2,1,1),Hybrid!$A$1:$LI$1),FALSE) -> 1.7251505 | G43: =VLOOKUP($E43,Hybrid!$1:$1048576,MATCH(DATE(G$2,1,1),Hybrid!$A$1:$LI$1),FALSE) -> 2.2746845 | H43: =VLOOKUP($E43,Hybrid!$1:$1048576,MATCH(DATE(H$2,1,1),Hybrid!$A$1:$LI$1),FALSE) -> 2.8024089 | I43: =VLOOKUP($E43,Hybrid!$1:$1048576,MATCH(DATE(I$2,1,1),Hybrid!$A$1:$LI$1),FALSE) -> 3.2921455 | J43: =VLOOKUP($E43,Hybrid!$1:$1048576,MATCH(DATE(J$2,1,1),Hybrid!$A$1:$LI$1),FALSE) -> 3.813303 | K43: =VLOOKUP($E43,Hybrid!$1:$1048576,MATCH(DATE(K$2,1,1),Hybrid!$A$1:$LI$1),FALSE) -> 4.3950533 | L43: =VLOOKUP($E43,Hybrid!$1:$1048576,MATCH(DATE(L$2,1,1),Hybrid!$A$1:$LI$1),FALSE) -> 4.9167755 | M43: =VLOOKUP($E43,Hybrid!$1:$1048576,MATCH(DATE(M$2,1,1),Hybrid!$A$1:$LI$1),FALSE) -> 5.4034925 | ... AO43: =VLOOKUP($E43,Hybrid!$1:$1048576,MATCH(DATE(AO$2,1,1),Hybrid!$A$1:$LI$1),FALSE) -> 6.6177069
D44: class G | E44: AUTO_cg_cele_0 | F44: =VLOOKUP($E44,Hybrid!$1:$1048576,MATCH(DATE(F$2,1,1),Hybrid!$A$1:$LI$1),FALSE) -> 3.1066862 | G44: =VLOOKUP($E44,Hybrid!$1:$1048576,MATCH(DATE(G$2,1,1),Hybrid!$A$1:$LI$1),FALSE) -> 4.1345154 | H44: =VLOOKUP($E44,Hybrid!$1:$1048576,MATCH(DATE(H$2,1,1),Hybrid!$A$1:$LI$1),FALSE) -> 5.1001109 | I44: =VLOOKUP($E44,Hybrid!$1:$1048576,MATCH(DATE(I$2,1,1),Hybrid!$A$1:$LI$1),FALSE) -> 5.9664963 | J44: =VLOOKUP($E44,Hybrid!$1:$1048576,MATCH(DATE(J$2,1,1),Hybrid!$A$1:$LI$1),FALSE) -> 6.8544854 | K44: =VLOOKUP($E44,Hybrid!$1:$1048576,MATCH(DATE(K$2,1,1),Hybrid!$A$1:$LI$1),FALSE) -> 7.8193969 | L44: =VLOOKUP($E44,Hybrid!$1:$1048576,MATCH(DATE(L$2,1,1),Hybrid!$A$1:$LI$1),FALSE) -> 8.6619765 | M44: =VLOOKUP($E44,Hybrid!$1:$1048576,MATCH(DATE(M$2,1,1),Hybrid!$A$1:$LI$1),FALSE) -> 9.422338 | ... AO44: =VLOOKUP($E44,Hybrid!$1:$1048576,MATCH(DATE(AO$2,1,1),Hybrid!$A$1:$LI$1),FALSE) -> 8.0340157
C45: GAS | E45: AUTO_cgas_0 | F45: =VLOOKUP($E45,Hybrid!$1:$1048576,MATCH(DATE(F$2,1,1),Hybrid!$A$1:$LI$1),FALSE) -> 1.936 | G45: =VLOOKUP($E45,Hybrid!$1:$1048576,MATCH(DATE(G$2,1,1),Hybrid!$A$1:$LI$1),FALSE) -> 1.998633 | H45: =VLOOKUP($E45,Hybrid!$1:$1048576,MATCH(DATE(H$2,1,1),Hybrid!$A$1:$LI$1),FALSE) -> 2.0641605 | I45: =VLOOKUP($E45,Hybrid!$1:$1048576,MATCH(DATE(I$2,1,1),Hybrid!$A$1:$LI$1),FALSE) -> 2.1250573 | J45: =VLOOKUP($E45,Hybrid!$1:$1048576,MATCH(DATE(J$2,1,1),Hybrid!$A$1:$LI$1),FALSE) -> 2.1974643 | K45: =VLOOKUP($E45,Hybrid!$1:$1048576,MATCH(DATE(K$2,1,1),Hybrid!$A$1:$LI$1),FALSE) -> 2.2961023 | L45: =VLOOKUP($E45,Hybrid!$1:$1048576,MATCH(DATE(L$2,1,1),Hybrid!$A$1:$LI$1),FALSE) -> 2.3835993 | M45: =VLOOKUP($E45,Hybrid!$1:$1048576,MATCH(DATE(M$2,1,1),Hybrid!$A$1:$LI$1),FALSE) -> 2.4682881 | ... AO45: =VLOOKUP($E45,Hybrid!$1:$1048576,MATCH(DATE(AO$2,1,1),Hybrid!$A$1:$LI$1),FALSE) -> 4.066811
D46: class A | E46: AUTO_ca_cgas_0 | F46: =VLOOKUP($E46,Hybrid!$1:$1048576,MATCH(DATE(F$2,1,1),Hybrid!$A$1:$LI$1),FALSE) -> 0.4256817 | G46: =VLOOKUP($E46,Hybrid!$1:$1048576,MATCH(DATE(G$2,1,1),Hybrid!$A$1:$LI$1),FALSE) -> 0.45117089 | H46: =VLOOKUP($E46,Hybrid!$1:$1048576,MATCH(DATE(H$2,1,1),Hybrid!$A$1:$LI$1),FALSE) -> 0.47734696 | I46: =VLOOKUP($E46,Hybrid!$1:$1048576,MATCH(DATE(I$2,1,1),Hybrid!$A$1:$LI$1),FALSE) -> 0.50243473 | J46: =VLOOKUP($E46,Hybrid!$1:$1048576,MATCH(DATE(J$2,1,1),Hybrid!$A$1:$LI$1),FALSE) -> 0.53124474 | K46: =VLOOKUP($E46,Hybrid!$1:$1048576,MATCH(DATE(K$2,1,1),Hybrid!$A$1:$LI$1),FALSE) -> 0.56771835 | L46: =VLOOKUP($E46,Hybrid!$1:$1048576,MATCH(DATE(L$2,1,1),Hybrid!$A$1:$LI$1),FALSE) -> 0.60067452 | M46: =VLOOKUP($E46,Hybrid!$1:$1048576,MATCH(DATE(M$2,1,1),Hybrid!$A$1:$LI$1),FALSE) -> 0.63282145 | ... AO46: =VLOOKUP($E46,Hybrid!$1:$1048576,MATCH(DATE(AO$2,1,1),Hybrid!$A$1:$LI$1),FALSE) -> 1.3735346
D47: class B | E47: AUTO_cb_cgas_0 | F47: =VLOOKUP($E47,Hybrid!$1:$1048576,MATCH(DATE(F$2,1,1),Hybrid!$A$1:$LI$1),FALSE) -> 0.49500523 | G47: =VLOOKUP($E47,Hybrid!$1:$1048576,MATCH(DATE(G$2,1,1),Hybrid!$A$1:$LI$1),FALSE) -> 0.51405784 | H47: =VLOOKUP($E47,Hybrid!$1:$1048576,MATCH(DATE(H$2,1,1),Hybrid!$A$1:$LI$1),FALSE) -> 0.53404363 | I47: =VLOOKUP($E47,Hybrid!$1:$1048576,MATCH(DATE(I$2,1,1),Hybrid!$A$1:$LI$1),FALSE) -> 0.55311339 | J47: =VLOOKUP($E47,Hybrid!$1:$1048576,MATCH(DATE(J$2,1,1),Hybrid!$A$1:$LI$1),FALSE) -> 0.57578538 | K47: =VLOOKUP($E47,Hybrid!$1:$1048576,MATCH(DATE(K$2,1,1),Hybrid!$A$1:$LI$1),FALSE) -> 0.60597728 | L47: =VLOOKUP($E47,Hybrid!$1:$1048576,MATCH(DATE(L$2,1,1),Hybrid!$A$1:$LI$1),FALSE) -> 0.63311312 | M47: =VLOOKUP($E47,Hybrid!$1:$1048576,MATCH(DATE(M$2,1,1),Hybrid!$A$1:$LI$1),FALSE) -> 0.65964246 | ... AO47: =VLOOKUP($E47,Hybrid!$1:$1048576,MATCH(DATE(AO$2,1,1),Hybrid!$A$1:$LI$1),FALSE) -> 1.2481048
D48: class C | E48: AUTO_cc_cgas_0 | F48: =VLOOKUP($E48,Hybrid!$1:$1048576,MATCH(DATE(F$2,1,1),Hybrid!$A$1:$LI$1),FALSE) -> 0.40659852 | G48: =VLOOKUP($E48,Hybrid!$1:$1048576,MATCH(DATE(G$2,1,1),Hybrid!$A$1:$LI$1),FALSE) -> 0.41577328 | H48: =VLOOKUP($E48,Hybrid!$1:$1048576,MATCH(DATE(H$2,1,1),Hybrid!$A$1:$LI$1),FALSE) -> 0.42580019 | I48: =VLOOKUP($E48,Hybrid!$1:$1048576,MATCH(DATE(I$2,1,1),Hybrid!$A$1:$LI$1),FALSE) -> 0.43529965 | J48: =VLOOKUP($E48,Hybrid!$1:$1048576,MATCH(DATE(J$2,1,1),Hybrid!$A$1:$LI$1),FALSE) -> 0.44733124 | K48: =VLOOKUP($E48,Hybrid!$1:$1048576,MATCH(DATE(K$2,1,1),Hybrid!$A$1:$LI$1),FALSE) -> 0.46469577 | L48: =VLOOKUP($E48,Hybrid!$1:$1048576,MATCH(DATE(L$2,1,1),Hybrid!$A$1:$LI$1),FALSE) -> 0.48017924 | M48: =VLOOKUP($E48,Hybrid!$1:$1048576,MATCH(DATE(M$2,1,1),Hybrid!$A$1:$LI$1),FALSE) -> 0.49537481 | ... AO48: =VLOOKUP($E48,Hybrid!$1:$1048576,MATCH(DATE(AO$2,1,1),Hybrid!$A$1:$LI$1),FALSE) -> 0.81999641
D49: class D | E49: AUTO_cd_cgas_0 | F49: =VLOOKUP($E49,Hybrid!$1:$1048576,MATCH(DATE(F$2,1,1),Hybrid!$A$1:$LI$1),FALSE) -> 0.24954447 | G49: =VLOOKUP($E49,Hybrid!$1:$1048576,MATCH(DATE(G$2,1,1),Hybrid!$A$1:$LI$1),FALSE) -> 0.25306755 | H49: =VLOOKUP($E49,Hybrid!$1:$1048576,MATCH(DATE(H$2,1,1),Hybrid!$A$1:$LI$1),FALSE) -> 0.257036 | I49: =VLOOKUP($E49,Hybrid!$1:$1048576,MATCH(DATE(I$2,1,1),Hybrid!$A$1:$LI$1),FALSE) -> 0.2605875 | J49: =VLOOKUP($E49,Hybrid!$1:$1048576,MATCH(DATE(J$2,1,1),Hybrid!$A$1:$LI$1),FALSE) -> 0.26535007 | K49: =VLOOKUP($E49,Hybrid!$1:$1048576,MATCH(DATE(K$2,1,1),Hybrid!$A$1:$LI$1),FALSE) -> 0.27291072 | L49: =VLOOKUP($E49,Hybrid!$1:$1048576,MATCH(DATE(L$2,1,1),Hybrid!$A$1:$LI$1),FALSE) -> 0.2794667 | M49: =VLOOKUP($E49,Hybrid!$1:$1048576,MATCH(DATE(M$2,1,1),Hybrid!$A$1:$LI$1),FALSE) -> 0.28579763 | ... AO49: =VLOOKUP($E49,Hybrid!$1:$1048576,MATCH(DATE(AO$2,1,1),Hybrid!$A$1:$LI$1),FALSE) -> 0.35372682
D50: class E | E50: AUTO_ce_cgas_0 | F50: =VLOOKUP($E50,Hybrid!$1:$1048576,MATCH(DATE(F$2,1,1),Hybrid!$A$1:$LI$1),FALSE) -> 0.15020247 | G50: =VLOOKUP($E50,Hybrid!$1:$1048576,MATCH(DATE(G$2,1,1),Hybrid!$A$1:$LI$1),FALSE) -> 0.15254896 | H50: =VLOOKUP($E50,Hybrid!$1:$1048576,MATCH(DATE(H$2,1,1),Hybrid!$A$1:$LI$1),FALSE) -> 0.15509164 | I50: =VLOOKUP($E50,Hybrid!$1:$1048576,MATCH(DATE(I$2,1,1),Hybrid!$A$1:$LI$1),FALSE) -> 0.15724578 | J50: =VLOOKUP($E50,Hybrid!$1:$1048576,MATCH(DATE(J$2,1,1),Hybrid!$A$1:$LI$1),FALSE) -> 0.15997385 | K50: =VLOOKUP($E50,Hybrid!$1:$1048576,MATCH(DATE(K$2,1,1),Hybrid!$A$1:$LI$1),FALSE) -> 0.16428533 | L50: =VLOOKUP($E50,Hybrid!$1:$1048576,MATCH(DATE(L$2,1,1),Hybrid!$A$1:$LI$1),FALSE) -> 0.16795646 | M50: =VLOOKUP($E50,Hybrid!$1:$1048576,MATCH(DATE(M$2,1,1),Hybrid!$A$1:$LI$1),FALSE) -> 0.17141357 | ... AO50: =VLOOKUP($E50,Hybrid!$1:$1048576,MATCH(DATE(AO$2,1,1),Hybrid!$A$1:$LI$1),FALSE) -> 0.17430321
D51: class F | E51: AUTO_cf_cgas_0 | F51: =VLOOKUP($E51,Hybrid!$1:$1048576,MATCH(DATE(F$2,1,1),Hybrid!$A$1:$LI$1),FALSE) -> 0.074609436 | G51: =VLOOKUP($E51,Hybrid!$1:$1048576,MATCH(DATE(G$2,1,1),Hybrid!$A$1:$LI$1),FALSE) -> 0.075572076 | H51: =VLOOKUP($E51,Hybrid!$1:$1048576,MATCH(DATE(H$2,1,1),Hybrid!$A$1:$LI$1),FALSE) -> 0.076526792 | I51: =VLOOKUP($E51,Hybrid!$1:$1048576,MATCH(DATE(I$2,1,1),Hybrid!$A$1:$LI$1),FALSE) -> 0.077128688 | J51: =VLOOKUP($E51,Hybrid!$1:$1048576,MATCH(DATE(J$2,1,1),Hybrid!$A$1:$LI$1),FALSE) -> 0.077798251 | K51: =VLOOKUP($E51,Hybrid!$1:$1048576,MATCH(DATE(K$2,1,1),Hybrid!$A$1:$LI$1),FALSE) -> 0.079036001 | L51: =VLOOKUP($E51,Hybrid!$1:$1048576,MATCH(DATE(L$2,1,1),Hybrid!$A$1:$LI$1),FALSE) -> 0.079931234 | M51: =VLOOKUP($E51,Hybrid!$1:$1048576,MATCH(DATE(M$2,1,1),Hybrid!$A$1:$LI$1),FALSE) -> 0.080635799 | ... AO51: =VLOOKUP($E51,Hybrid!$1:$1048576,MATCH(DATE(AO$2,1,1),Hybrid!$A$1:$LI$1),FALSE) -> 0.043714391
D52: class G | E52: AUTO_cg_cgas_0 | F52: =VLOOKUP($E52,Hybrid!$1:$1048576,MATCH(DATE(F$2,1,1),Hybrid!$A$1:$LI$1),FALSE) -> 0.13435819 | G52: =VLOOKUP($E52,Hybrid!$1:$1048576,MATCH(DATE(G$2,1,1),Hybrid!$A$1:$LI$1),FALSE) -> 0.13644246 | H52: =VLOOKUP($E52,Hybrid!$1:$1048576,MATCH(DATE(H$2,1,1),Hybrid!$A$1:$LI$1),FALSE) -> 0.13831532 | I52: =VLOOKUP($E52,Hybrid!$1:$1048576,MATCH(DATE(I$2,1,1),Hybrid!$A$1:$LI$1),FALSE) -> 0.1392476 | J52: =VLOOKUP($E52,Hybrid!$1:$1048576,MATCH(DATE(J$2,1,1),Hybrid!$A$1:$LI$1),FALSE) -> 0.13998077 | K52: =VLOOKUP($E52,Hybrid!$1:$1048576,MATCH(DATE(K$2,1,1),Hybrid!$A$1:$LI$1),FALSE) -> 0.14147882 | L52: =VLOOKUP($E52,Hybrid!$1:$1048576,MATCH(DATE(L$2,1,1),Hybrid!$A$1:$LI$1),FALSE) -> 0.14227802 | M52: =VLOOKUP($E52,Hybrid!$1:$1048576,MATCH(DATE(M$2,1,1),Hybrid!$A$1:$LI$1),FALSE) -> 0.14260238 | ... AO52: =VLOOKUP($E52,Hybrid!$1:$1048576,MATCH(DATE(AO$2,1,1),Hybrid!$A$1:$LI$1),FALSE) -> 0.053430768
C53: TOTAL SALES SHOCK | E53: NEWAUTO_2 | F53: =VLOOKUP($E53,Hybrid!$1:$1048576,MATCH(DATE(F$2,1,1),Hybrid!$A$1:$LI$1),FALSE) -> 1886.229 | G53: =VLOOKUP($E53,Hybrid!$1:$1048576,MATCH(DATE(G$2,1,1),Hybrid!$A$1:$LI$1),FALSE) -> 2206.2151 | H53: =VLOOKUP($E53,Hybrid!$1:$1048576,MATCH(DATE(H$2,1,1),Hybrid!$A$1:$LI$1),FALSE) -> 2287.6712 | I53: =VLOOKUP($E53,Hybrid!$1:$1048576,MATCH(DATE(I$2,1,1),Hybrid!$A$1:$LI$1),FALSE) -> 2282.4934 | J53: =VLOOKUP($E53,Hybrid!$1:$1048576,MATCH(DATE(J$2,1,1),Hybrid!$A$1:$LI$1),FALSE) -> 2470.4755 | K53: =VLOOKUP($E53,Hybrid!$1:$1048576,MATCH(DATE(K$2,1,1),Hybrid!$A$1:$LI$1),FALSE) -> 2841.6304 | L53: =VLOOKUP($E53,Hybrid!$1:$1048576,MATCH(DATE(L$2,1,1),Hybrid!$A$1:$LI$1),FALSE) -> 2777.6687 | M53: =VLOOKUP($E53,Hybrid!$1:$1048576,MATCH(DATE(M$2,1,1),Hybrid!$A$1:$LI$1),FALSE) -> 2794.8495 | ... AO53: =VLOOKUP($E53,Hybrid!$1:$1048576,MATCH(DATE(AO$2,1,1),Hybrid!$A$1:$LI$1),FALSE) -> 3596.8623
C54: OIL | E54: NEWAUTO_cfut_2 | F54: =VLOOKUP($E54,Hybrid!$1:$1048576,MATCH(DATE(F$2,1,1),Hybrid!$A$1:$LI$1),FALSE) -> 1868.6763 | G54: =VLOOKUP($E54,Hybrid!$1:$1048576,MATCH(DATE(G$2,1,1),Hybrid!$A$1:$LI$1),FALSE) -> 2185.8216 | H54: =VLOOKUP($E54,Hybrid!$1:$1048576,MATCH(DATE(H$2,1,1),Hybrid!$A$1:$LI$1),FALSE) -> 2266.8705 | I54: =VLOOKUP($E54,Hybrid!$1:$1048576,MATCH(DATE(I$2,1,1),Hybrid!$A$1:$LI$1),FALSE) -> 2260.4998 | J54: =VLOOKUP($E54,Hybrid!$1:$1048576,MATCH(DATE(J$2,1,1),Hybrid!$A$1:$LI$1),FALSE) -> 2442.8117 | K54: =VLOOKUP($E54,Hybrid!$1:$1048576,MATCH(DATE(K$2,1,1),Hybrid!$A$1:$LI$1),FALSE) -> 2808.912 | L54: =VLOOKUP($E54,Hybrid!$1:$1048576,MATCH(DATE(L$2,1,1),Hybrid!$A$1:$LI$1),FALSE) -> 2745.8461 | M54: =VLOOKUP($E54,Hybrid!$1:$1048576,MATCH(DATE(M$2,1,1),Hybrid!$A$1:$LI$1),FALSE) -> 2762.2342 | ... AO54: =VLOOKUP($E54,Hybrid!$1:$1048576,MATCH(DATE(AO$2,1,1),Hybrid!$A$1:$LI$1),FALSE) -> 3434.299
D55: class A | E55: NEWAUTO_ca_cfut_2 | F55: =VLOOKUP($E55,Hybrid!$1:$1048576,MATCH(DATE(F$2,1,1),Hybrid!$A$1:$LI$1),FALSE) -> 528.64613 | G55: =VLOOKUP($E55,Hybrid!$1:$1048576,MATCH(DATE(G$2,1,1),Hybrid!$A$1:$LI$1),FALSE) -> 620.08903 | H55: =VLOOKUP($E55,Hybrid!$1:$1048576,MATCH(DATE(H$2,1,1),Hybrid!$A$1:$LI$1),FALSE) -> 647.22781 | I55: =VLOOKUP($E55,Hybrid!$1:$1048576,MATCH(DATE(I$2,1,1),Hybrid!$A$1:$LI$1),FALSE) -> 653.74726 | J55: =VLOOKUP($E55,Hybrid!$1:$1048576,MATCH(DATE(J$2,1,1),Hybrid!$A$1:$LI$1),FALSE) -> 716.71784 | K55: =VLOOKUP($E55,Hybrid!$1:$1048576,MATCH(DATE(K$2,1,1),Hybrid!$A$1:$LI$1),FALSE) -> 829.37251 | L55: =VLOOKUP($E55,Hybrid!$1:$1048576,MATCH(DATE(L$2,1,1),Hybrid!$A$1:$LI$1),FALSE) -> 813.76065 | M55: =VLOOKUP($E55,Hybrid!$1:$1048576,MATCH(DATE(M$2,1,1),Hybrid!$A$1:$LI$1),FALSE) -> 826.07963 | ... AO55: =VLOOKUP($E55,Hybrid!$1:$1048576,MATCH(DATE(AO$2,1,1),Hybrid!$A$1:$LI$1),FALSE) -> 1387.5535
D56: class B | E56: NEWAUTO_cb_cfut_2 | F56: =VLOOKUP($E56,Hybrid!$1:$1048576,MATCH(DATE(F$2,1,1),Hybrid!$A$1:$LI$1),FALSE) -> 507.52728 | G56: =VLOOKUP($E56,Hybrid!$1:$1048576,MATCH(DATE(G$2,1,1),Hybrid!$A$1:$LI$1),FALSE) -> 595.04646 | H56: =VLOOKUP($E56,Hybrid!$1:$1048576,MATCH(DATE(H$2,1,1),Hybrid!$A$1:$LI$1),FALSE) -> 620.32838 | I56: =VLOOKUP($E56,Hybrid!$1:$1048576,MATCH(DATE(I$2,1,1),Hybrid!$A$1:$LI$1),FALSE) -> 624.29313 | J56: =VLOOKUP($E56,Hybrid!$1:$1048576,MATCH(DATE(J$2,1,1),Hybrid!$A$1:$LI$1),FALSE) -> 681.35808 | K56: =VLOOKUP($E56,Hybrid!$1:$1048576,MATCH(DATE(K$2,1,1),Hybrid!$A$1:$LI$1),FALSE) -> 787.73599 | L56: =VLOOKUP($E56,Hybrid!$1:$1048576,MATCH(DATE(L$2,1,1),Hybrid!$A$1:$LI$1),FALSE) -> 772.92925 | M56: =VLOOKUP($E56,Hybrid!$1:$1048576,MATCH(DATE(M$2,1,1),Hybrid!$A$1:$LI$1),FALSE) -> 782.92153 | ... AO56: =VLOOKUP($E56,Hybrid!$1:$1048576,MATCH(DATE(AO$2,1,1),Hybrid!$A$1:$LI$1),FALSE) -> 1130.5667
D57: class C | E57: NEWAUTO_cc_cfut_2 | F57: =VLOOKUP($E57,Hybrid!$1:$1048576,MATCH(DATE(F$2,1,1),Hybrid!$A$1:$LI$1),FALSE) -> 351.30566 | G57: =VLOOKUP($E57,Hybrid!$1:$1048576,MATCH(DATE(G$2,1,1),Hybrid!$A$1:$LI$1),FALSE) -> 411.69811 | H57: =VLOOKUP($E57,Hybrid!$1:$1048576,MATCH(DATE(H$2,1,1),Hybrid!$A$1:$LI$1),FALSE) -> 428.66706 | I57: =VLOOKUP($E57,Hybrid!$1:$1048576,MATCH(DATE(I$2,1,1),Hybrid!$A$1:$LI$1),FALSE) -> 429.84813 | J57: =VLOOKUP($E57,Hybrid!$1:$1048576,MATCH(DATE(J$2,1,1),Hybrid!$A$1:$LI$1),FALSE) -> 467.05572 | K57: =VLOOKUP($E57,Hybrid!$1:$1048576,MATCH(DATE(K$2,1,1),Hybrid!$A$1:$LI$1),FALSE) -> 539.48574 | L57: =VLOOKUP($E57,Hybrid!$1:$1048576,MATCH(DATE(L$2,1,1),Hybrid!$A$1:$LI$1),FALSE) -> 529.36385 | M57: =VLOOKUP($E57,Hybrid!$1:$1048576,MATCH(DATE(M$2,1,1),Hybrid!$A$1:$LI$1),FALSE) -> 535.0549 | ... AO57: =VLOOKUP($E57,Hybrid!$1:$1048576,MATCH(DATE(AO$2,1,1),Hybrid!$A$1:$LI$1),FALSE) -> 665.50868
D58: class D | E58: NEWAUTO_cd_cfut_2 | F58: =VLOOKUP($E58,Hybrid!$1:$1048576,MATCH(DATE(F$2,1,1),Hybrid!$A$1:$LI$1),FALSE) -> 194.72124 | G58: =VLOOKUP($E58,Hybrid!$1:$1048576,MATCH(DATE(G$2,1,1),Hybrid!$A$1:$LI$1),FALSE) -> 227.58465 | H58: =VLOOKUP($E58,Hybrid!$1:$1048576,MATCH(DATE(H$2,1,1),Hybrid!$A$1:$LI$1),FALSE) -> 235.5069 | I58: =VLOOKUP($E58,Hybrid!$1:$1048576,MATCH(DATE(I$2,1,1),Hybrid!$A$1:$LI$1),FALSE) -> 233.49621 | J58: =VLOOKUP($E58,Hybrid!$1:$1048576,MATCH(DATE(J$2,1,1),Hybrid!$A$1:$LI$1),FALSE) -> 250.55402 | K58: =VLOOKUP($E58,Hybrid!$1:$1048576,MATCH(DATE(K$2,1,1),Hybrid!$A$1:$LI$1),FALSE) -> 287.4032 | L58: =VLOOKUP($E58,Hybrid!$1:$1048576,MATCH(DATE(L$2,1,1),Hybrid!$A$1:$LI$1),FALSE) -> 280.62726 | M58: =VLOOKUP($E58,Hybrid!$1:$1048576,MATCH(DATE(M$2,1,1),Hybrid!$A$1:$LI$1),FALSE) -> 280.82701 | ... AO58: =VLOOKUP($E58,Hybrid!$1:$1048576,MATCH(DATE(AO$2,1,1),Hybrid!$A$1:$LI$1),FALSE) -> 186.25933
D59: class E | E59: NEWAUTO_ce_cfut_2 | F59: =VLOOKUP($E59,Hybrid!$1:$1048576,MATCH(DATE(F$2,1,1),Hybrid!$A$1:$LI$1),FALSE) -> 119.78459 | G59: =VLOOKUP($E59,Hybrid!$1:$1048576,MATCH(DATE(G$2,1,1),Hybrid!$A$1:$LI$1),FALSE) -> 139.6739 | H59: =VLOOKUP($E59,Hybrid!$1:$1048576,MATCH(DATE(H$2,1,1),Hybrid!$A$1:$LI$1),FALSE) -> 143.7549 | I59: =VLOOKUP($E59,Hybrid!$1:$1048576,MATCH(DATE(I$2,1,1),Hybrid!$A$1:$LI$1),FALSE) -> 141.02162 | J59: =VLOOKUP($E59,Hybrid!$1:$1048576,MATCH(DATE(J$2,1,1),Hybrid!$A$1:$LI$1),FALSE) -> 149.45585 | K59: =VLOOKUP($E59,Hybrid!$1:$1048576,MATCH(DATE(K$2,1,1),Hybrid!$A$1:$LI$1),FALSE) -> 170.33302 | L59: =VLOOKUP($E59,Hybrid!$1:$1048576,MATCH(DATE(L$2,1,1),Hybrid!$A$1:$LI$1),FALSE) -> 165.60509 | M59: =VLOOKUP($E59,Hybrid!$1:$1048576,MATCH(DATE(M$2,1,1),Hybrid!$A$1:$LI$1),FALSE) -> 164.22209 | ... AO59: =VLOOKUP($E59,Hybrid!$1:$1048576,MATCH(DATE(AO$2,1,1),Hybrid!$A$1:$LI$1),FALSE) -> 60.53567
D60: class F | E60: NEWAUTO_cf_cfut_2 | F60: =VLOOKUP($E60,Hybrid!$1:$1048576,MATCH(DATE(F$2,1,1),Hybrid!$A$1:$LI$1),FALSE) -> 57.931012 | G60: =VLOOKUP($E60,Hybrid!$1:$1048576,MATCH(DATE(G$2,1,1),Hybrid!$A$1:$LI$1),FALSE) -> 66.96421 | H60: =VLOOKUP($E60,Hybrid!$1:$1048576,MATCH(DATE(H$2,1,1),Hybrid!$A$1:$LI$1),FALSE) -> 67.586045 | I60: =VLOOKUP($E60,Hybrid!$1:$1048576,MATCH(DATE(I$2,1,1),Hybrid!$A$1:$LI$1),FALSE) -> 64.096609 | J60: =VLOOKUP($E60,Hybrid!$1:$1048576,MATCH(DATE(J$2,1,1),Hybrid!$A$1:$LI$1),FALSE) -> 65.349851 | K60: =VLOOKUP($E60,Hybrid!$1:$1048576,MATCH(DATE(K$2,1,1),Hybrid!$A$1:$LI$1),FALSE) -> 72.611225 | L60: =VLOOKUP($E60,Hybrid!$1:$1048576,MATCH(DATE(L$2,1,1),Hybrid!$A$1:$LI$1),FALSE) -> 69.246838 | M60: =VLOOKUP($E60,Hybrid!$1:$1048576,MATCH(DATE(M$2,1,1),Hybrid!$A$1:$LI$1),FALSE) -> 66.474548 | ... AO60: =VLOOKUP($E60,Hybrid!$1:$1048576,MATCH(DATE(AO$2,1,1),Hybrid!$A$1:$LI$1),FALSE) -> 3.0891999
D61: class G | E61: NEWAUTO_cg_cfut_2 | F61: =VLOOKUP($E61,Hybrid!$1:$1048576,MATCH(DATE(F$2,1,1),Hybrid!$A$1:$LI$1),FALSE) -> 108.76036 | G61: =VLOOKUP($E61,Hybrid!$1:$1048576,MATCH(DATE(G$2,1,1),Hybrid!$A$1:$LI$1),FALSE) -> 124.76525 | H61: =VLOOKUP($E61,Hybrid!$1:$1048576,MATCH(DATE(H$2,1,1),Hybrid!$A$1:$LI$1),FALSE) -> 123.79942 | I61: =VLOOKUP($E61,Hybrid!$1:$1048576,MATCH(DATE(I$2,1,1),Hybrid!$A$1:$LI$1),FALSE) -> 113.99686 | J61: =VLOOKUP($E61,Hybrid!$1:$1048576,MATCH(DATE(J$2,1,1),Hybrid!$A$1:$LI$1),FALSE) -> 112.32032 | K61: =VLOOKUP($E61,Hybrid!$1:$1048576,MATCH(DATE(K$2,1,1),Hybrid!$A$1:$LI$1),FALSE) -> 121.97031 | L61: =VLOOKUP($E61,Hybrid!$1:$1048576,MATCH(DATE(L$2,1,1),Hybrid!$A$1:$LI$1),FALSE) -> 114.31312 | M61: =VLOOKUP($E61,Hybrid!$1:$1048576,MATCH(DATE(M$2,1,1),Hybrid!$A$1:$LI$1),FALSE) -> 106.65453 | ... AO61: =VLOOKUP($E61,Hybrid!$1:$1048576,MATCH(DATE(AO$2,1,1),Hybrid!$A$1:$LI$1),FALSE) -> 0.7859065
C62: ELEC | E62: NEWAUTO_cele_2 | F62: =VLOOKUP($E62,Hybrid!$1:$1048576,MATCH(DATE(F$2,1,1),Hybrid!$A$1:$LI$1),FALSE) -> 17.395732 | G62: =VLOOKUP($E62,Hybrid!$1:$1048576,MATCH(DATE(G$2,1,1),Hybrid!$A$1:$LI$1),FALSE) -> 20.209804 | H62: =VLOOKUP($E62,Hybrid!$1:$1048576,MATCH(DATE(H$2,1,1),Hybrid!$A$1:$LI$1),FALSE) -> 20.610256 | I62: =VLOOKUP($E62,Hybrid!$1:$1048576,MATCH(DATE(I$2,1,1),Hybrid!$A$1:$LI$1),FALSE) -> 21.803616 | J62: =VLOOKUP($E62,Hybrid!$1:$1048576,MATCH(DATE(J$2,1,1),Hybrid!$A$1:$LI$1),FALSE) -> 27.458625 | K62: =VLOOKUP($E62,Hybrid!$1:$1048576,MATCH(DATE(K$2,1,1),Hybrid!$A$1:$LI$1),FALSE) -> 32.482434 | L62: =VLOOKUP($E62,Hybrid!$1:$1048576,MATCH(DATE(L$2,1,1),Hybrid!$A$1:$LI$1),FALSE) -> 31.591975 | M62: =VLOOKUP($E62,Hybrid!$1:$1048576,MATCH(DATE(M$2,1,1),Hybrid!$A$1:$LI$1),FALSE) -> 32.383188 | ... AO62: =VLOOKUP($E62,Hybrid!$1:$1048576,MATCH(DATE(AO$2,1,1),Hybrid!$A$1:$LI$1),FALSE) -> 162.27482
D63: class A | E63: NEWAUTO_ca_cele_2 | F63: =VLOOKUP($E63,Hybrid!$1:$1048576,MATCH(DATE(F$2,1,1),Hybrid!$A$1:$LI$1),FALSE) -> 4.9236399 | G63: =VLOOKUP($E63,Hybrid!$1:$1048576,MATCH(DATE(G$2,1,1),Hybrid!$A$1:$LI$1),FALSE) -> 5.7345091 | H63: =VLOOKUP($E63,Hybrid!$1:$1048576,MATCH(DATE(H$2,1,1),Hybrid!$A$1:$LI$1),FALSE) -> 5.881896 | I63: =VLOOKUP($E63,Hybrid!$1:$1048576,MATCH(DATE(I$2,1,1),Hybrid!$A$1:$LI$1),FALSE) -> 6.3314054 | J63: =VLOOKUP($E63,Hybrid!$1:$1048576,MATCH(DATE(J$2,1,1),Hybrid!$A$1:$LI$1),FALSE) -> 8.1813279 | K63: =VLOOKUP($E63,Hybrid!$1:$1048576,MATCH(DATE(K$2,1,1),Hybrid!$A$1:$LI$1),FALSE) -> 9.7509516 | L63: =VLOOKUP($E63,Hybrid!$1:$1048576,MATCH(DATE(L$2,1,1),Hybrid!$A$1:$LI$1),FALSE) -> 9.5224404 | M63: =VLOOKUP($E63,Hybrid!$1:$1048576,MATCH(DATE(M$2,1,1),Hybrid!$A$1:$LI$1),FALSE) -> 9.8547663 | ... AO63: =VLOOKUP($E63,Hybrid!$1:$1048576,MATCH(DATE(AO$2,1,1),Hybrid!$A$1:$LI$1),FALSE) -> 65.713983
D64: class B | E64: NEWAUTO_cb_cele_2 | F64: =VLOOKUP($E64,Hybrid!$1:$1048576,MATCH(DATE(F$2,1,1),Hybrid!$A$1:$LI$1),FALSE) -> 4.7298801 | G64: =VLOOKUP($E64,Hybrid!$1:$1048576,MATCH(DATE(G$2,1,1),Hybrid!$A$1:$LI$1),FALSE) -> 5.5029379 | H64: =VLOOKUP($E64,Hybrid!$1:$1048576,MATCH(DATE(H$2,1,1),Hybrid!$A$1:$LI$1),FALSE) -> 5.6281191 | I64: =VLOOKUP($E64,Hybrid!$1:$1048576,MATCH(DATE(I$2,1,1),Hybrid!$A$1:$LI$1),FALSE) -> 6.0624848 | J64: =VLOOKUP($E64,Hybrid!$1:$1048576,MATCH(DATE(J$2,1,1),Hybrid!$A$1:$LI$1),FALSE) -> 7.8726023 | K64: =VLOOKUP($E64,Hybrid!$1:$1048576,MATCH(DATE(K$2,1,1),Hybrid!$A$1:$LI$1),FALSE) -> 9.3890285 | L64: =VLOOKUP($E64,Hybrid!$1:$1048576,MATCH(DATE(L$2,1,1),Hybrid!$A$1:$LI$1),FALSE) -> 9.162103 | M64: =VLOOKUP($E64,Hybrid!$1:$1048576,MATCH(DATE(M$2,1,1),Hybrid!$A$1:$LI$1),FALSE) -> 9.4697687 | ... AO64: =VLOOKUP($E64,Hybrid!$1:$1048576,MATCH(DATE(AO$2,1,1),Hybrid!$A$1:$LI$1),FALSE) -> 55.074936
D65: class C | E65: NEWAUTO_cc_cele_2 | F65: =VLOOKUP($E65,Hybrid!$1:$1048576,MATCH(DATE(F$2,1,1),Hybrid!$A$1:$LI$1),FALSE) -> 3.2758789 | G65: =VLOOKUP($E65,Hybrid!$1:$1048576,MATCH(DATE(G$2,1,1),Hybrid!$A$1:$LI$1),FALSE) -> 3.8073589 | H65: =VLOOKUP($E65,Hybrid!$1:$1048576,MATCH(DATE(H$2,1,1),Hybrid!$A$1:$LI$1),FALSE) -> 3.8831177 | I65: =VLOOKUP($E65,Hybrid!$1:$1048576,MATCH(DATE(I$2,1,1),Hybrid!$A$1:$LI$1),FALSE) -> 4.184582 | J65: =VLOOKUP($E65,Hybrid!$1:$1048576,MATCH(DATE(J$2,1,1),Hybrid!$A$1:$LI$1),FALSE) -> 5.4568664 | K65: =VLOOKUP($E65,Hybrid!$1:$1048576,MATCH(DATE(K$2,1,1),Hybrid!$A$1:$LI$1),FALSE) -> 6.511239 | L65: =VLOOKUP($E65,Hybrid!$1:$1048576,MATCH(DATE(L$2,1,1),Hybrid!$A$1:$LI$1),FALSE) -> 6.3494377 | M65: =VLOOKUP($E65,Hybrid!$1:$1048576,MATCH(DATE(M$2,1,1),Hybrid!$A$1:$LI$1),FALSE) -> 6.5538998 | ... AO65: =VLOOKUP($E65,Hybrid!$1:$1048576,MATCH(DATE(AO$2,1,1),Hybrid!$A$1:$LI$1),FALSE) -> 33.172989
D66: class D | E66: NEWAUTO_cd_cele_2 | F66: =VLOOKUP($E66,Hybrid!$1:$1048576,MATCH(DATE(F$2,1,1),Hybrid!$A$1:$LI$1),FALSE) -> 1.8074599 | G66: =VLOOKUP($E66,Hybrid!$1:$1048576,MATCH(DATE(G$2,1,1),Hybrid!$A$1:$LI$1),FALSE) -> 2.1035693 | H66: =VLOOKUP($E66,Hybrid!$1:$1048576,MATCH(DATE(H$2,1,1),Hybrid!$A$1:$LI$1),FALSE) -> 2.1549752 | I66: =VLOOKUP($E66,Hybrid!$1:$1048576,MATCH(DATE(I$2,1,1),Hybrid!$A$1:$LI$1),FALSE) -> 2.2136874 | J66: =VLOOKUP($E66,Hybrid!$1:$1048576,MATCH(DATE(J$2,1,1),Hybrid!$A$1:$LI$1),FALSE) -> 2.60162 | K66: =VLOOKUP($E66,Hybrid!$1:$1048576,MATCH(DATE(K$2,1,1),Hybrid!$A$1:$LI$1),FALSE) -> 3.0376777 | L66: =VLOOKUP($E66,Hybrid!$1:$1048576,MATCH(DATE(L$2,1,1),Hybrid!$A$1:$LI$1),FALSE) -> 2.952987 | M66: =VLOOKUP($E66,Hybrid!$1:$1048576,MATCH(DATE(M$2,1,1),Hybrid!$A$1:$LI$1),FALSE) -> 2.9879991 | ... AO66: =VLOOKUP($E66,Hybrid!$1:$1048576,MATCH(DATE(AO$2,1,1),Hybrid!$A$1:$LI$1),FALSE) -> 6.1396698
D67: class E | E67: NEWAUTO_ce_cele_2 | F67: =VLOOKUP($E67,Hybrid!$1:$1048576,MATCH(DATE(F$2,1,1),Hybrid!$A$1:$LI$1),FALSE) -> 1.1126215 | G67: =VLOOKUP($E67,Hybrid!$1:$1048576,MATCH(DATE(G$2,1,1),Hybrid!$A$1:$LI$1),FALSE) -> 1.2907925 | H67: =VLOOKUP($E67,Hybrid!$1:$1048576,MATCH(DATE(H$2,1,1),Hybrid!$A$1:$LI$1),FALSE) -> 1.3124604 | I67: =VLOOKUP($E67,Hybrid!$1:$1048576,MATCH(DATE(I$2,1,1),Hybrid!$A$1:$LI$1),FALSE) -> 1.339234 | J67: =VLOOKUP($E67,Hybrid!$1:$1048576,MATCH(DATE(J$2,1,1),Hybrid!$A$1:$LI$1),FALSE) -> 1.5667157 | K67: =VLOOKUP($E67,Hybrid!$1:$1048576,MATCH(DATE(K$2,1,1),Hybrid!$A$1:$LI$1),FALSE) -> 1.8201643 | L67: =VLOOKUP($E67,Hybrid!$1:$1048576,MATCH(DATE(L$2,1,1),Hybrid!$A$1:$LI$1),FALSE) -> 1.7585104 | M67: =VLOOKUP($E67,Hybrid!$1:$1048576,MATCH(DATE(M$2,1,1),Hybrid!$A$1:$LI$1),FALSE) -> 1.7641729 | ... AO67: =VLOOKUP($E67,Hybrid!$1:$1048576,MATCH(DATE(AO$2,1,1),Hybrid!$A$1:$LI$1),FALSE) -> 2.0662447
D68: class F | E68: NEWAUTO_cf_cele_2 | F68: =VLOOKUP($E68,Hybrid!$1:$1048576,MATCH(DATE(F$2,1,1),Hybrid!$A$1:$LI$1),FALSE) -> 0.53721981 | G68: =VLOOKUP($E68,Hybrid!$1:$1048576,MATCH(DATE(G$2,1,1),Hybrid!$A$1:$LI$1),FALSE) -> 0.61853998 | H68: =VLOOKUP($E68,Hybrid!$1:$1048576,MATCH(DATE(H$2,1,1),Hybrid!$A$1:$LI$1),FALSE) -> 0.61871178 | I68: =VLOOKUP($E68,Hybrid!$1:$1048576,MATCH(DATE(I$2,1,1),Hybrid!$A$1:$LI$1),FALSE) -> 0.60183294 | J68: =VLOOKUP($E68,Hybrid!$1:$1048576,MATCH(DATE(J$2,1,1),Hybrid!$A$1:$LI$1),FALSE) -> 0.65284332 | K68: =VLOOKUP($E68,Hybrid!$1:$1048576,MATCH(DATE(K$2,1,1),Hybrid!$A$1:$LI$1),FALSE) -> 0.73428243 | L68: =VLOOKUP($E68,Hybrid!$1:$1048576,MATCH(DATE(L$2,1,1),Hybrid!$A$1:$LI$1),FALSE) -> 0.69552349 | M68: =VLOOKUP($E68,Hybrid!$1:$1048576,MATCH(DATE(M$2,1,1),Hybrid!$A$1:$LI$1),FALSE) -> 0.67199857 | ... AO68: =VLOOKUP($E68,Hybrid!$1:$1048576,MATCH(DATE(AO$2,1,1),Hybrid!$A$1:$LI$1),FALSE) -> 0.085124651
D69: class G | E69: NEWAUTO_cg_cele_2 | F69: =VLOOKUP($E69,Hybrid!$1:$1048576,MATCH(DATE(F$2,1,1),Hybrid!$A$1:$LI$1),FALSE) -> 1.0090321 | G69: =VLOOKUP($E69,Hybrid!$1:$1048576,MATCH(DATE(G$2,1,1),Hybrid!$A$1:$LI$1),FALSE) -> 1.1520966 | H69: =VLOOKUP($E69,Hybrid!$1:$1048576,MATCH(DATE(H$2,1,1),Hybrid!$A$1:$LI$1),FALSE) -> 1.1309761 | I69: =VLOOKUP($E69,Hybrid!$1:$1048576,MATCH(DATE(I$2,1,1),Hybrid!$A$1:$LI$1),FALSE) -> 1.0703897 | J69: =VLOOKUP($E69,Hybrid!$1:$1048576,MATCH(DATE(J$2,1,1),Hybrid!$A$1:$LI$1),FALSE) -> 1.126649 | K69: =VLOOKUP($E69,Hybrid!$1:$1048576,MATCH(DATE(K$2,1,1),Hybrid!$A$1:$LI$1),FALSE) -> 1.2390909 | L69: =VLOOKUP($E69,Hybrid!$1:$1048576,MATCH(DATE(L$2,1,1),Hybrid!$A$1:$LI$1),FALSE) -> 1.1509734 | M69: =VLOOKUP($E69,Hybrid!$1:$1048576,MATCH(DATE(M$2,1,1),Hybrid!$A$1:$LI$1),FALSE) -> 1.0805832 | ... AO69: =VLOOKUP($E69,Hybrid!$1:$1048576,MATCH(DATE(AO$2,1,1),Hybrid!$A$1:$LI$1),FALSE) -> 0.021876832
C70: GAS | E70: NEWAUTO_cgas_2 | F70: =VLOOKUP($E70,Hybrid!$1:$1048576,MATCH(DATE(F$2,1,1),Hybrid!$A$1:$LI$1),FALSE) -> 0.15698935 | G70: =VLOOKUP($E70,Hybrid!$1:$1048576,MATCH(DATE(G$2,1,1),Hybrid!$A$1:$LI$1),FALSE) -> 0.18363305 | H70: =VLOOKUP($E70,Hybrid!$1:$1048576,MATCH(DATE(H$2,1,1),Hybrid!$A$1:$LI$1),FALSE) -> 0.19044205 | I70: =VLOOKUP($E70,Hybrid!$1:$1048576,MATCH(DATE(I$2,1,1),Hybrid!$A$1:$LI$1),FALSE) -> 0.18990684 | J70: =VLOOKUP($E70,Hybrid!$1:$1048576,MATCH(DATE(J$2,1,1),Hybrid!$A$1:$LI$1),FALSE) -> 0.20522304 | K70: =VLOOKUP($E70,Hybrid!$1:$1048576,MATCH(DATE(K$2,1,1),Hybrid!$A$1:$LI$1),FALSE) -> 0.23597949 | L70: =VLOOKUP($E70,Hybrid!$1:$1048576,MATCH(DATE(L$2,1,1),Hybrid!$A$1:$LI$1),FALSE) -> 0.23068126 | M70: =VLOOKUP($E70,Hybrid!$1:$1048576,MATCH(DATE(M$2,1,1),Hybrid!$A$1:$LI$1),FALSE) -> 0.23205805 | ... AO70: =VLOOKUP($E70,Hybrid!$1:$1048576,MATCH(DATE(AO$2,1,1),Hybrid!$A$1:$LI$1),FALSE) -> 0.28851888
D71: class A | E71: NEWAUTO_ca_cgas_2 | F71: =VLOOKUP($E71,Hybrid!$1:$1048576,MATCH(DATE(F$2,1,1),Hybrid!$A$1:$LI$1),FALSE) -> 0.044412088 | G71: =VLOOKUP($E71,Hybrid!$1:$1048576,MATCH(DATE(G$2,1,1),Hybrid!$A$1:$LI$1),FALSE) -> 0.052094296 | H71: =VLOOKUP($E71,Hybrid!$1:$1048576,MATCH(DATE(H$2,1,1),Hybrid!$A$1:$LI$1),FALSE) -> 0.054374253 | I71: =VLOOKUP($E71,Hybrid!$1:$1048576,MATCH(DATE(I$2,1,1),Hybrid!$A$1:$LI$1),FALSE) -> 0.054921958 | J71: =VLOOKUP($E71,Hybrid!$1:$1048576,MATCH(DATE(J$2,1,1),Hybrid!$A$1:$LI$1),FALSE) -> 0.060212179 | K71: =VLOOKUP($E71,Hybrid!$1:$1048576,MATCH(DATE(K$2,1,1),Hybrid!$A$1:$LI$1),FALSE) -> 0.06967641 | L71: =VLOOKUP($E71,Hybrid!$1:$1048576,MATCH(DATE(L$2,1,1),Hybrid!$A$1:$LI$1),FALSE) -> 0.068364842 | M71: =VLOOKUP($E71,Hybrid!$1:$1048576,MATCH(DATE(M$2,1,1),Hybrid!$A$1:$LI$1),FALSE) -> 0.069399772 | ... AO71: =VLOOKUP($E71,Hybrid!$1:$1048576,MATCH(DATE(AO$2,1,1),Hybrid!$A$1:$LI$1),FALSE) -> 0.11656975
D72: class B | E72: NEWAUTO_cb_cgas_2 | F72: =VLOOKUP($E72,Hybrid!$1:$1048576,MATCH(DATE(F$2,1,1),Hybrid!$A$1:$LI$1),FALSE) -> 0.042637872 | G72: =VLOOKUP($E72,Hybrid!$1:$1048576,MATCH(DATE(G$2,1,1),Hybrid!$A$1:$LI$1),FALSE) -> 0.049990446 | H72: =VLOOKUP($E72,Hybrid!$1:$1048576,MATCH(DATE(H$2,1,1),Hybrid!$A$1:$LI$1),FALSE) -> 0.052114405 | I72: =VLOOKUP($E72,Hybrid!$1:$1048576,MATCH(DATE(I$2,1,1),Hybrid!$A$1:$LI$1),FALSE) -> 0.052447487 | J72: =VLOOKUP($E72,Hybrid!$1:$1048576,MATCH(DATE(J$2,1,1),Hybrid!$A$1:$LI$1),FALSE) -> 0.057241571 | K72: =VLOOKUP($E72,Hybrid!$1:$1048576,MATCH(DATE(K$2,1,1),Hybrid!$A$1:$LI$1),FALSE) -> 0.066178484 | L72: =VLOOKUP($E72,Hybrid!$1:$1048576,MATCH(DATE(L$2,1,1),Hybrid!$A$1:$LI$1),FALSE) -> 0.064934556 | M72: =VLOOKUP($E72,Hybrid!$1:$1048576,MATCH(DATE(M$2,1,1),Hybrid!$A$1:$LI$1),FALSE) -> 0.065774017 | ... AO72: =VLOOKUP($E72,Hybrid!$1:$1048576,MATCH(DATE(AO$2,1,1),Hybrid!$A$1:$LI$1),FALSE) -> 0.094980035
D73: class C | E73: NEWAUTO_cc_cgas_2 | F73: =VLOOKUP($E73,Hybrid!$1:$1048576,MATCH(DATE(F$2,1,1),Hybrid!$A$1:$LI$1),FALSE) -> 0.029513538 | G73: =VLOOKUP($E73,Hybrid!$1:$1048576,MATCH(DATE(G$2,1,1),Hybrid!$A$1:$LI$1),FALSE) -> 0.034587168 | H73: =VLOOKUP($E73,Hybrid!$1:$1048576,MATCH(DATE(H$2,1,1),Hybrid!$A$1:$LI$1),FALSE) -> 0.036012746 | I73: =VLOOKUP($E73,Hybrid!$1:$1048576,MATCH(DATE(I$2,1,1),Hybrid!$A$1:$LI$1),FALSE) -> 0.036111969 | J73: =VLOOKUP($E73,Hybrid!$1:$1048576,MATCH(DATE(J$2,1,1),Hybrid!$A$1:$LI$1),FALSE) -> 0.039237816 | K73: =VLOOKUP($E73,Hybrid!$1:$1048576,MATCH(DATE(K$2,1,1),Hybrid!$A$1:$LI$1),FALSE) -> 0.045322734 | L73: =VLOOKUP($E73,Hybrid!$1:$1048576,MATCH(DATE(L$2,1,1),Hybrid!$A$1:$LI$1),FALSE) -> 0.044472384 | M73: =VLOOKUP($E73,Hybrid!$1:$1048576,MATCH(DATE(M$2,1,1),Hybrid!$A$1:$LI$1),FALSE) -> 0.044950495 | ... AO73: =VLOOKUP($E73,Hybrid!$1:$1048576,MATCH(DATE(AO$2,1,1),Hybrid!$A$1:$LI$1),FALSE) -> 0.055910046
D74: class D | E74: NEWAUTO_cd_cgas_2 | F74: =VLOOKUP($E74,Hybrid!$1:$1048576,MATCH(DATE(F$2,1,1),Hybrid!$A$1:$LI$1),FALSE) -> 0.016358725 | G74: =VLOOKUP($E74,Hybrid!$1:$1048576,MATCH(DATE(G$2,1,1),Hybrid!$A$1:$LI$1),FALSE) -> 0.019119613 | H74: =VLOOKUP($E74,Hybrid!$1:$1048576,MATCH(DATE(H$2,1,1),Hybrid!$A$1:$LI$1),FALSE) -> 0.019785169 | I74: =VLOOKUP($E74,Hybrid!$1:$1048576,MATCH(DATE(I$2,1,1),Hybrid!$A$1:$LI$1),FALSE) -> 0.019616249 | J74: =VLOOKUP($E74,Hybrid!$1:$1048576,MATCH(DATE(J$2,1,1),Hybrid!$A$1:$LI$1),FALSE) -> 0.021049293 | K74: =VLOOKUP($E74,Hybrid!$1:$1048576,MATCH(DATE(K$2,1,1),Hybrid!$A$1:$LI$1),FALSE) -> 0.024145029 | L74: =VLOOKUP($E74,Hybrid!$1:$1048576,MATCH(DATE(L$2,1,1),Hybrid!$A$1:$LI$1),FALSE) -> 0.023575775 | M74: =VLOOKUP($E74,Hybrid!$1:$1048576,MATCH(DATE(M$2,1,1),Hybrid!$A$1:$LI$1),FALSE) -> 0.023592557 | ... AO74: =VLOOKUP($E74,Hybrid!$1:$1048576,MATCH(DATE(AO$2,1,1),Hybrid!$A$1:$LI$1),FALSE) -> 0.015647832
D75: class E | E75: NEWAUTO_ce_cgas_2 | F75: =VLOOKUP($E75,Hybrid!$1:$1048576,MATCH(DATE(F$2,1,1),Hybrid!$A$1:$LI$1),FALSE) -> 0.010063223 | G75: =VLOOKUP($E75,Hybrid!$1:$1048576,MATCH(DATE(G$2,1,1),Hybrid!$A$1:$LI$1),FALSE) -> 0.011734144 | H75: =VLOOKUP($E75,Hybrid!$1:$1048576,MATCH(DATE(H$2,1,1),Hybrid!$A$1:$LI$1),FALSE) -> 0.012076993 | I75: =VLOOKUP($E75,Hybrid!$1:$1048576,MATCH(DATE(I$2,1,1),Hybrid!$A$1:$LI$1),FALSE) -> 0.011847367 | J75: =VLOOKUP($E75,Hybrid!$1:$1048576,MATCH(DATE(J$2,1,1),Hybrid!$A$1:$LI$1),FALSE) -> 0.012555934 | K75: =VLOOKUP($E75,Hybrid!$1:$1048576,MATCH(DATE(K$2,1,1),Hybrid!$A$1:$LI$1),FALSE) -> 0.014309847 | L75: =VLOOKUP($E75,Hybrid!$1:$1048576,MATCH(DATE(L$2,1,1),Hybrid!$A$1:$LI$1),FALSE) -> 0.013912648 | M75: =VLOOKUP($E75,Hybrid!$1:$1048576,MATCH(DATE(M$2,1,1),Hybrid!$A$1:$LI$1),FALSE) -> 0.013796461 | ... AO75: =VLOOKUP($E75,Hybrid!$1:$1048576,MATCH(DATE(AO$2,1,1),Hybrid!$A$1:$LI$1),FALSE) -> 0.0050856619
D76: class F | E76: NEWAUTO_cf_cgas_2 | F76: =VLOOKUP($E76,Hybrid!$1:$1048576,MATCH(DATE(F$2,1,1),Hybrid!$A$1:$LI$1),FALSE) -> 0.004866842 | G76: =VLOOKUP($E76,Hybrid!$1:$1048576,MATCH(DATE(G$2,1,1),Hybrid!$A$1:$LI$1),FALSE) -> 0.0056257299 | H76: =VLOOKUP($E76,Hybrid!$1:$1048576,MATCH(DATE(H$2,1,1),Hybrid!$A$1:$LI$1),FALSE) -> 0.0056779709 | I76: =VLOOKUP($E76,Hybrid!$1:$1048576,MATCH(DATE(I$2,1,1),Hybrid!$A$1:$LI$1),FALSE) -> 0.0053848199 | J76: =VLOOKUP($E76,Hybrid!$1:$1048576,MATCH(DATE(J$2,1,1),Hybrid!$A$1:$LI$1),FALSE) -> 0.005490106 | K76: =VLOOKUP($E76,Hybrid!$1:$1048576,MATCH(DATE(K$2,1,1),Hybrid!$A$1:$LI$1),FALSE) -> 0.0061001413 | L76: =VLOOKUP($E76,Hybrid!$1:$1048576,MATCH(DATE(L$2,1,1),Hybrid!$A$1:$LI$1),FALSE) -> 0.0058174958 | M76: =VLOOKUP($E76,Hybrid!$1:$1048576,MATCH(DATE(M$2,1,1),Hybrid!$A$1:$LI$1),FALSE) -> 0.0055845929 | ... AO76: =VLOOKUP($E76,Hybrid!$1:$1048576,MATCH(DATE(AO$2,1,1),Hybrid!$A$1:$LI$1),FALSE) -> 0.00025952676
D77: class G | E77: NEWAUTO_cg_cgas_2 | F77: =VLOOKUP($E77,Hybrid!$1:$1048576,MATCH(DATE(F$2,1,1),Hybrid!$A$1:$LI$1),FALSE) -> 0.009137066 | G77: =VLOOKUP($E77,Hybrid!$1:$1048576,MATCH(DATE(G$2,1,1),Hybrid!$A$1:$LI$1),FALSE) -> 0.010481653 | H77: =VLOOKUP($E77,Hybrid!$1:$1048576,MATCH(DATE(H$2,1,1),Hybrid!$A$1:$LI$1),FALSE) -> 0.010400513 | I77: =VLOOKUP($E77,Hybrid!$1:$1048576,MATCH(DATE(I$2,1,1),Hybrid!$A$1:$LI$1),FALSE) -> 0.0095769896 | J77: =VLOOKUP($E77,Hybrid!$1:$1048576,MATCH(DATE(J$2,1,1),Hybrid!$A$1:$LI$1),FALSE) -> 0.0094361423 | K77: =VLOOKUP($E77,Hybrid!$1:$1048576,MATCH(DATE(K$2,1,1),Hybrid!$A$1:$LI$1),FALSE) -> 0.010246847 | L77: =VLOOKUP($E77,Hybrid!$1:$1048576,MATCH(DATE(L$2,1,1),Hybrid!$A$1:$LI$1),FALSE) -> 0.0096035586 | M77: =VLOOKUP($E77,Hybrid!$1:$1048576,MATCH(DATE(M$2,1,1),Hybrid!$A$1:$LI$1),FALSE) -> 0.0089601533 | ... AO77: =VLOOKUP($E77,Hybrid!$1:$1048576,MATCH(DATE(AO$2,1,1),Hybrid!$A$1:$LI$1),FALSE) -> 6.6024788e-05
C78: TOTAL SALES BASELINE | E78: NEWAUTO_0 | F78: =VLOOKUP($E78,Hybrid!$1:$1048576,MATCH(DATE(F$2,1,1),Hybrid!$A$1:$LI$1),FALSE) -> 1886.229 | G78: =VLOOKUP($E78,Hybrid!$1:$1048576,MATCH(DATE(G$2,1,1),Hybrid!$A$1:$LI$1),FALSE) -> 2206.2151 | H78: =VLOOKUP($E78,Hybrid!$1:$1048576,MATCH(DATE(H$2,1,1),Hybrid!$A$1:$LI$1),FALSE) -> 2287.6712 | I78: =VLOOKUP($E78,Hybrid!$1:$1048576,MATCH(DATE(I$2,1,1),Hybrid!$A$1:$LI$1),FALSE) -> 2282.4934 | J78: =VLOOKUP($E78,Hybrid!$1:$1048576,MATCH(DATE(J$2,1,1),Hybrid!$A$1:$LI$1),FALSE) -> 2470.4755 | K78: =VLOOKUP($E78,Hybrid!$1:$1048576,MATCH(DATE(K$2,1,1),Hybrid!$A$1:$LI$1),FALSE) -> 2841.6304 | L78: =VLOOKUP($E78,Hybrid!$1:$1048576,MATCH(DATE(L$2,1,1),Hybrid!$A$1:$LI$1),FALSE) -> 2781.5438 | M78: =VLOOKUP($E78,Hybrid!$1:$1048576,MATCH(DATE(M$2,1,1),Hybrid!$A$1:$LI$1),FALSE) -> 2813.9967 | ... AO78: =VLOOKUP($E78,Hybrid!$1:$1048576,MATCH(DATE(AO$2,1,1),Hybrid!$A$1:$LI$1),FALSE) -> 3426.101
C79: OIL | E79: NEWAUTO_cfut_0 | F79: =VLOOKUP($E79,Hybrid!$1:$1048576,MATCH(DATE(F$2,1,1),Hybrid!$A$1:$LI$1),FALSE) -> 1868.6763 | G79: =VLOOKUP($E79,Hybrid!$1:$1048576,MATCH(DATE(G$2,1,1),Hybrid!$A$1:$LI$1),FALSE) -> 2185.8216 | H79: =VLOOKUP($E79,Hybrid!$1:$1048576,MATCH(DATE(H$2,1,1),Hybrid!$A$1:$LI$1),FALSE) -> 2266.8705 | I79: =VLOOKUP($E79,Hybrid!$1:$1048576,MATCH(DATE(I$2,1,1),Hybrid!$A$1:$LI$1),FALSE) -> 2260.4998 | J79: =VLOOKUP($E79,Hybrid!$1:$1048576,MATCH(DATE(J$2,1,1),Hybrid!$A$1:$LI$1),FALSE) -> 2442.8117 | K79: =VLOOKUP($E79,Hybrid!$1:$1048576,MATCH(DATE(K$2,1,1),Hybrid!$A$1:$LI$1),FALSE) -> 2808.912 | L79: =VLOOKUP($E79,Hybrid!$1:$1048576,MATCH(DATE(L$2,1,1),Hybrid!$A$1:$LI$1),FALSE) -> 2749.6808 | M79: =VLOOKUP($E79,Hybrid!$1:$1048576,MATCH(DATE(M$2,1,1),Hybrid!$A$1:$LI$1),FALSE) -> 2781.3475 | ... AO79: =VLOOKUP($E79,Hybrid!$1:$1048576,MATCH(DATE(AO$2,1,1),Hybrid!$A$1:$LI$1),FALSE) -> 3366.9945
D80: class A | E80: NEWAUTO_ca_cfut_0 | F80: =VLOOKUP($E80,Hybrid!$1:$1048576,MATCH(DATE(F$2,1,1),Hybrid!$A$1:$LI$1),FALSE) -> 528.64613 | G80: =VLOOKUP($E80,Hybrid!$1:$1048576,MATCH(DATE(G$2,1,1),Hybrid!$A$1:$LI$1),FALSE) -> 620.08903 | H80: =VLOOKUP($E80,Hybrid!$1:$1048576,MATCH(DATE(H$2,1,1),Hybrid!$A$1:$LI$1),FALSE) -> 647.22781 | I80: =VLOOKUP($E80,Hybrid!$1:$1048576,MATCH(DATE(I$2,1,1),Hybrid!$A$1:$LI$1),FALSE) -> 653.74726 | J80: =VLOOKUP($E80,Hybrid!$1:$1048576,MATCH(DATE(J$2,1,1),Hybrid!$A$1:$LI$1),FALSE) -> 716.71784 | K80: =VLOOKUP($E80,Hybrid!$1:$1048576,MATCH(DATE(K$2,1,1),Hybrid!$A$1:$LI$1),FALSE) -> 829.37251 | L80: =VLOOKUP($E80,Hybrid!$1:$1048576,MATCH(DATE(L$2,1,1),Hybrid!$A$1:$LI$1),FALSE) -> 814.6381 | M80: =VLOOKUP($E80,Hybrid!$1:$1048576,MATCH(DATE(M$2,1,1),Hybrid!$A$1:$LI$1),FALSE) -> 829.52345 | ... AO80: =VLOOKUP($E80,Hybrid!$1:$1048576,MATCH(DATE(AO$2,1,1),Hybrid!$A$1:$LI$1),FALSE) -> 1235.6501
D81: class B | E81: NEWAUTO_cb_cfut_0 | F81: =VLOOKUP($E81,Hybrid!$1:$1048576,MATCH(DATE(F$2,1,1),Hybrid!$A$1:$LI$1),FALSE) -> 507.52728 | G81: =VLOOKUP($E81,Hybrid!$1:$1048576,MATCH(DATE(G$2,1,1),Hybrid!$A$1:$LI$1),FALSE) -> 595.04646 | H81: =VLOOKUP($E81,Hybrid!$1:$1048576,MATCH(DATE(H$2,1,1),Hybrid!$A$1:$LI$1),FALSE) -> 620.32838 | I81: =VLOOKUP($E81,Hybrid!$1:$1048576,MATCH(DATE(I$2,1,1),Hybrid!$A$1:$LI$1),FALSE) -> 624.29313 | J81: =VLOOKUP($E81,Hybrid!$1:$1048576,MATCH(DATE(J$2,1,1),Hybrid!$A$1:$LI$1),FALSE) -> 681.35808 | K81: =VLOOKUP($E81,Hybrid!$1:$1048576,MATCH(DATE(K$2,1,1),Hybrid!$A$1:$LI$1),FALSE) -> 787.73599 | L81: =VLOOKUP($E81,Hybrid!$1:$1048576,MATCH(DATE(L$2,1,1),Hybrid!$A$1:$LI$1),FALSE) -> 773.82047 | M81: =VLOOKUP($E81,Hybrid!$1:$1048576,MATCH(DATE(M$2,1,1),Hybrid!$A$1:$LI$1),FALSE) -> 786.78878 | ... AO81: =VLOOKUP($E81,Hybrid!$1:$1048576,MATCH(DATE(AO$2,1,1),Hybrid!$A$1:$LI$1),FALSE) -> 1079.0348
D82: class C | E82: NEWAUTO_cc_cfut_0 | F82: =VLOOKUP($E82,Hybrid!$1:$1048576,MATCH(DATE(F$2,1,1),Hybrid!$A$1:$LI$1),FALSE) -> 351.30566 | G82: =VLOOKUP($E82,Hybrid!$1:$1048576,MATCH(DATE(G$2,1,1),Hybrid!$A$1:$LI$1),FALSE) -> 411.69811 | H82: =VLOOKUP($E82,Hybrid!$1:$1048576,MATCH(DATE(H$2,1,1),Hybrid!$A$1:$LI$1),FALSE) -> 428.66706 | I82: =VLOOKUP($E82,Hybrid!$1:$1048576,MATCH(DATE(I$2,1,1),Hybrid!$A$1:$LI$1),FALSE) -> 429.84813 | J82: =VLOOKUP($E82,Hybrid!$1:$1048576,MATCH(DATE(J$2,1,1),Hybrid!$A$1:$LI$1),FALSE) -> 467.05572 | K82: =VLOOKUP($E82,Hybrid!$1:$1048576,MATCH(DATE(K$2,1,1),Hybrid!$A$1:$LI$1),FALSE) -> 539.48574 | L82: =VLOOKUP($E82,Hybrid!$1:$1048576,MATCH(DATE(L$2,1,1),Hybrid!$A$1:$LI$1),FALSE) -> 530.0134 | M82: =VLOOKUP($E82,Hybrid!$1:$1048576,MATCH(DATE(M$2,1,1),Hybrid!$A$1:$LI$1),FALSE) -> 538.10548 | ... AO82: =VLOOKUP($E82,Hybrid!$1:$1048576,MATCH(DATE(AO$2,1,1),Hybrid!$A$1:$LI$1),FALSE) -> 680.09691
D83: class D | E83: NEWAUTO_cd_cfut_0 | F83: =VLOOKUP($E83,Hybrid!$1:$1048576,MATCH(DATE(F$2,1,1),Hybrid!$A$1:$LI$1),FALSE) -> 194.72124 | G83: =VLOOKUP($E83,Hybrid!$1:$1048576,MATCH(DATE(G$2,1,1),Hybrid!$A$1:$LI$1),FALSE) -> 227.58465 | H83: =VLOOKUP($E83,Hybrid!$1:$1048576,MATCH(DATE(H$2,1,1),Hybrid!$A$1:$LI$1),FALSE) -> 235.5069 | I83: =VLOOKUP($E83,Hybrid!$1:$1048576,MATCH(DATE(I$2,1,1),Hybrid!$A$1:$LI$1),FALSE) -> 233.49621 | J83: =VLOOKUP($E83,Hybrid!$1:$1048576,MATCH(DATE(J$2,1,1),Hybrid!$A$1:$LI$1),FALSE) -> 250.55402 | K83: =VLOOKUP($E83,Hybrid!$1:$1048576,MATCH(DATE(K$2,1,1),Hybrid!$A$1:$LI$1),FALSE) -> 287.4032 | L83: =VLOOKUP($E83,Hybrid!$1:$1048576,MATCH(DATE(L$2,1,1),Hybrid!$A$1:$LI$1),FALSE) -> 281.0692 | M83: =VLOOKUP($E83,Hybrid!$1:$1048576,MATCH(DATE(M$2,1,1),Hybrid!$A$1:$LI$1),FALSE) -> 283.26765 | ... AO83: =VLOOKUP($E83,Hybrid!$1:$1048576,MATCH(DATE(AO$2,1,1),Hybrid!$A$1:$LI$1),FALSE) -> 248.24316
D84: class E | E84: NEWAUTO_ce_cfut_0 | F84: =VLOOKUP($E84,Hybrid!$1:$1048576,MATCH(DATE(F$2,1,1),Hybrid!$A$1:$LI$1),FALSE) -> 119.78459 | G84: =VLOOKUP($E84,Hybrid!$1:$1048576,MATCH(DATE(G$2,1,1),Hybrid!$A$1:$LI$1),FALSE) -> 139.6739 | H84: =VLOOKUP($E84,Hybrid!$1:$1048576,MATCH(DATE(H$2,1,1),Hybrid!$A$1:$LI$1),FALSE) -> 143.7549 | I84: =VLOOKUP($E84,Hybrid!$1:$1048576,MATCH(DATE(I$2,1,1),Hybrid!$A$1:$LI$1),FALSE) -> 141.02162 | J84: =VLOOKUP($E84,Hybrid!$1:$1048576,MATCH(DATE(J$2,1,1),Hybrid!$A$1:$LI$1),FALSE) -> 149.45585 | K84: =VLOOKUP($E84,Hybrid!$1:$1048576,MATCH(DATE(K$2,1,1),Hybrid!$A$1:$LI$1),FALSE) -> 170.33302 | L84: =VLOOKUP($E84,Hybrid!$1:$1048576,MATCH(DATE(L$2,1,1),Hybrid!$A$1:$LI$1),FALSE) -> 165.91833 | M84: =VLOOKUP($E84,Hybrid!$1:$1048576,MATCH(DATE(M$2,1,1),Hybrid!$A$1:$LI$1),FALSE) -> 166.10196 | ... AO84: =VLOOKUP($E84,Hybrid!$1:$1048576,MATCH(DATE(AO$2,1,1),Hybrid!$A$1:$LI$1),FALSE) -> 104.12072
D85: class F | E85: NEWAUTO_cf_cfut_0 | F85: =VLOOKUP($E85,Hybrid!$1:$1048576,MATCH(DATE(F$2,1,1),Hybrid!$A$1:$LI$1),FALSE) -> 57.931012 | G85: =VLOOKUP($E85,Hybrid!$1:$1048576,MATCH(DATE(G$2,1,1),Hybrid!$A$1:$LI$1),FALSE) -> 66.96421 | H85: =VLOOKUP($E85,Hybrid!$1:$1048576,MATCH(DATE(H$2,1,1),Hybrid!$A$1:$LI$1),FALSE) -> 67.586045 | I85: =VLOOKUP($E85,Hybrid!$1:$1048576,MATCH(DATE(I$2,1,1),Hybrid!$A$1:$LI$1),FALSE) -> 64.096609 | J85: =VLOOKUP($E85,Hybrid!$1:$1048576,MATCH(DATE(J$2,1,1),Hybrid!$A$1:$LI$1),FALSE) -> 65.349851 | K85: =VLOOKUP($E85,Hybrid!$1:$1048576,MATCH(DATE(K$2,1,1),Hybrid!$A$1:$LI$1),FALSE) -> 72.611225 | L85: =VLOOKUP($E85,Hybrid!$1:$1048576,MATCH(DATE(L$2,1,1),Hybrid!$A$1:$LI$1),FALSE) -> 69.454984 | M85: =VLOOKUP($E85,Hybrid!$1:$1048576,MATCH(DATE(M$2,1,1),Hybrid!$A$1:$LI$1),FALSE) -> 67.851451 | ... AO85: =VLOOKUP($E85,Hybrid!$1:$1048576,MATCH(DATE(AO$2,1,1),Hybrid!$A$1:$LI$1),FALSE) -> 12.755543
D86: class G | E86: NEWAUTO_cg_cfut_0 | F86: =VLOOKUP($E86,Hybrid!$1:$1048576,MATCH(DATE(F$2,1,1),Hybrid!$A$1:$LI$1),FALSE) -> 108.76036 | G86: =VLOOKUP($E86,Hybrid!$1:$1048576,MATCH(DATE(G$2,1,1),Hybrid!$A$1:$LI$1),FALSE) -> 124.76525 | H86: =VLOOKUP($E86,Hybrid!$1:$1048576,MATCH(DATE(H$2,1,1),Hybrid!$A$1:$LI$1),FALSE) -> 123.79942 | I86: =VLOOKUP($E86,Hybrid!$1:$1048576,MATCH(DATE(I$2,1,1),Hybrid!$A$1:$LI$1),FALSE) -> 113.99686 | J86: =VLOOKUP($E86,Hybrid!$1:$1048576,MATCH(DATE(J$2,1,1),Hybrid!$A$1:$LI$1),FALSE) -> 112.32032 | K86: =VLOOKUP($E86,Hybrid!$1:$1048576,MATCH(DATE(K$2,1,1),Hybrid!$A$1:$LI$1),FALSE) -> 121.97031 | L86: =VLOOKUP($E86,Hybrid!$1:$1048576,MATCH(DATE(L$2,1,1),Hybrid!$A$1:$LI$1),FALSE) -> 114.76633 | M86: =VLOOKUP($E86,Hybrid!$1:$1048576,MATCH(DATE(M$2,1,1),Hybrid!$A$1:$LI$1),FALSE) -> 109.70868 | ... AO86: =VLOOKUP($E86,Hybrid!$1:$1048576,MATCH(DATE(AO$2,1,1),Hybrid!$A$1:$LI$1),FALSE) -> 7.0932765
C87: ELEC | E87: NEWAUTO_cele_0 | F87: =VLOOKUP($E87,Hybrid!$1:$1048576,MATCH(DATE(F$2,1,1),Hybrid!$A$1:$LI$1),FALSE) -> 17.395732 | G87: =VLOOKUP($E87,Hybrid!$1:$1048576,MATCH(DATE(G$2,1,1),Hybrid!$A$1:$LI$1),FALSE) -> 20.209804 | H87: =VLOOKUP($E87,Hybrid!$1:$1048576,MATCH(DATE(H$2,1,1),Hybrid!$A$1:$LI$1),FALSE) -> 20.610256 | I87: =VLOOKUP($E87,Hybrid!$1:$1048576,MATCH(DATE(I$2,1,1),Hybrid!$A$1:$LI$1),FALSE) -> 21.803616 | J87: =VLOOKUP($E87,Hybrid!$1:$1048576,MATCH(DATE(J$2,1,1),Hybrid!$A$1:$LI$1),FALSE) -> 27.458625 | K87: =VLOOKUP($E87,Hybrid!$1:$1048576,MATCH(DATE(K$2,1,1),Hybrid!$A$1:$LI$1),FALSE) -> 32.482434 | L87: =VLOOKUP($E87,Hybrid!$1:$1048576,MATCH(DATE(L$2,1,1),Hybrid!$A$1:$LI$1),FALSE) -> 31.631958 | M87: =VLOOKUP($E87,Hybrid!$1:$1048576,MATCH(DATE(M$2,1,1),Hybrid!$A$1:$LI$1),FALSE) -> 32.415545 | ... AO87: =VLOOKUP($E87,Hybrid!$1:$1048576,MATCH(DATE(AO$2,1,1),Hybrid!$A$1:$LI$1),FALSE) -> 58.823623
D88: class A | E88: NEWAUTO_ca_cele_0 | F88: =VLOOKUP($E88,Hybrid!$1:$1048576,MATCH(DATE(F$2,1,1),Hybrid!$A$1:$LI$1),FALSE) -> 4.9236399 | G88: =VLOOKUP($E88,Hybrid!$1:$1048576,MATCH(DATE(G$2,1,1),Hybrid!$A$1:$LI$1),FALSE) -> 5.7345091 | H88: =VLOOKUP($E88,Hybrid!$1:$1048576,MATCH(DATE(H$2,1,1),Hybrid!$A$1:$LI$1),FALSE) -> 5.881896 | I88: =VLOOKUP($E88,Hybrid!$1:$1048576,MATCH(DATE(I$2,1,1),Hybrid!$A$1:$LI$1),FALSE) -> 6.3314054 | J88: =VLOOKUP($E88,Hybrid!$1:$1048576,MATCH(DATE(J$2,1,1),Hybrid!$A$1:$LI$1),FALSE) -> 8.1813279 | K88: =VLOOKUP($E88,Hybrid!$1:$1048576,MATCH(DATE(K$2,1,1),Hybrid!$A$1:$LI$1),FALSE) -> 9.7509516 | L88: =VLOOKUP($E88,Hybrid!$1:$1048576,MATCH(DATE(L$2,1,1),Hybrid!$A$1:$LI$1),FALSE) -> 9.5317784 | M88: =VLOOKUP($E88,Hybrid!$1:$1048576,MATCH(DATE(M$2,1,1),Hybrid!$A$1:$LI$1),FALSE) -> 9.8390432 | ... AO88: =VLOOKUP($E88,Hybrid!$1:$1048576,MATCH(DATE(AO$2,1,1),Hybrid!$A$1:$LI$1),FALSE) -> 22.206087
D89: class B | E89: NEWAUTO_cb_cele_0 | F89: =VLOOKUP($E89,Hybrid!$1:$1048576,MATCH(DATE(F$2,1,1),Hybrid!$A$1:$LI$1),FALSE) -> 4.7298801 | G89: =VLOOKUP($E89,Hybrid!$1:$1048576,MATCH(DATE(G$2,1,1),Hybrid!$A$1:$LI$1),FALSE) -> 5.5029379 | H89: =VLOOKUP($E89,Hybrid!$1:$1048576,MATCH(DATE(H$2,1,1),Hybrid!$A$1:$LI$1),FALSE) -> 5.6281191 | I89: =VLOOKUP($E89,Hybrid!$1:$1048576,MATCH(DATE(I$2,1,1),Hybrid!$A$1:$LI$1),FALSE) -> 6.0624848 | J89: =VLOOKUP($E89,Hybrid!$1:$1048576,MATCH(DATE(J$2,1,1),Hybrid!$A$1:$LI$1),FALSE) -> 7.8726023 | K89: =VLOOKUP($E89,Hybrid!$1:$1048576,MATCH(DATE(K$2,1,1),Hybrid!$A$1:$LI$1),FALSE) -> 9.3890285 | L89: =VLOOKUP($E89,Hybrid!$1:$1048576,MATCH(DATE(L$2,1,1),Hybrid!$A$1:$LI$1),FALSE) -> 9.171733 | M89: =VLOOKUP($E89,Hybrid!$1:$1048576,MATCH(DATE(M$2,1,1),Hybrid!$A$1:$LI$1),FALSE) -> 9.4587024 | ... AO89: =VLOOKUP($E89,Hybrid!$1:$1048576,MATCH(DATE(AO$2,1,1),Hybrid!$A$1:$LI$1),FALSE) -> 19.672894
D90: class C | E90: NEWAUTO_cc_cele_0 | F90: =VLOOKUP($E90,Hybrid!$1:$1048576,MATCH(DATE(F$2,1,1),Hybrid!$A$1:$LI$1),FALSE) -> 3.2758789 | G90: =VLOOKUP($E90,Hybrid!$1:$1048576,MATCH(DATE(G$2,1,1),Hybrid!$A$1:$LI$1),FALSE) -> 3.8073589 | H90: =VLOOKUP($E90,Hybrid!$1:$1048576,MATCH(DATE(H$2,1,1),Hybrid!$A$1:$LI$1),FALSE) -> 3.8831177 | I90: =VLOOKUP($E90,Hybrid!$1:$1048576,MATCH(DATE(I$2,1,1),Hybrid!$A$1:$LI$1),FALSE) -> 4.184582 | J90: =VLOOKUP($E90,Hybrid!$1:$1048576,MATCH(DATE(J$2,1,1),Hybrid!$A$1:$LI$1),FALSE) -> 5.4568664 | K90: =VLOOKUP($E90,Hybrid!$1:$1048576,MATCH(DATE(K$2,1,1),Hybrid!$A$1:$LI$1),FALSE) -> 6.511239 | L90: =VLOOKUP($E90,Hybrid!$1:$1048576,MATCH(DATE(L$2,1,1),Hybrid!$A$1:$LI$1),FALSE) -> 6.3565597 | M90: =VLOOKUP($E90,Hybrid!$1:$1048576,MATCH(DATE(M$2,1,1),Hybrid!$A$1:$LI$1),FALSE) -> 6.5492116 | ... AO90: =VLOOKUP($E90,Hybrid!$1:$1048576,MATCH(DATE(AO$2,1,1),Hybrid!$A$1:$LI$1),FALSE) -> 12.560463
D91: class D | E91: NEWAUTO_cd_cele_0 | F91: =VLOOKUP($E91,Hybrid!$1:$1048576,MATCH(DATE(F$2,1,1),Hybrid!$A$1:$LI$1),FALSE) -> 1.8074599 | G91: =VLOOKUP($E91,Hybrid!$1:$1048576,MATCH(DATE(G$2,1,1),Hybrid!$A$1:$LI$1),FALSE) -> 2.1035693 | H91: =VLOOKUP($E91,Hybrid!$1:$1048576,MATCH(DATE(H$2,1,1),Hybrid!$A$1:$LI$1),FALSE) -> 2.1549752 | I91: =VLOOKUP($E91,Hybrid!$1:$1048576,MATCH(DATE(I$2,1,1),Hybrid!$A$1:$LI$1),FALSE) -> 2.2136874 | J91: =VLOOKUP($E91,Hybrid!$1:$1048576,MATCH(DATE(J$2,1,1),Hybrid!$A$1:$LI$1),FALSE) -> 2.60162 | K91: =VLOOKUP($E91,Hybrid!$1:$1048576,MATCH(DATE(K$2,1,1),Hybrid!$A$1:$LI$1),FALSE) -> 3.0376777 | L91: =VLOOKUP($E91,Hybrid!$1:$1048576,MATCH(DATE(L$2,1,1),Hybrid!$A$1:$LI$1),FALSE) -> 2.9573661 | M91: =VLOOKUP($E91,Hybrid!$1:$1048576,MATCH(DATE(M$2,1,1),Hybrid!$A$1:$LI$1),FALSE) -> 3.0020662 | ... AO91: =VLOOKUP($E91,Hybrid!$1:$1048576,MATCH(DATE(AO$2,1,1),Hybrid!$A$1:$LI$1),FALSE) -> 3.049046
D92: class E | E92: NEWAUTO_ce_cele_0 | F92: =VLOOKUP($E92,Hybrid!$1:$1048576,MATCH(DATE(F$2,1,1),Hybrid!$A$1:$LI$1),FALSE) -> 1.1126215 | G92: =VLOOKUP($E92,Hybrid!$1:$1048576,MATCH(DATE(G$2,1,1),Hybrid!$A$1:$LI$1),FALSE) -> 1.2907925 | H92: =VLOOKUP($E92,Hybrid!$1:$1048576,MATCH(DATE(H$2,1,1),Hybrid!$A$1:$LI$1),FALSE) -> 1.3124604 | I92: =VLOOKUP($E92,Hybrid!$1:$1048576,MATCH(DATE(I$2,1,1),Hybrid!$A$1:$LI$1),FALSE) -> 1.339234 | J92: =VLOOKUP($E92,Hybrid!$1:$1048576,MATCH(DATE(J$2,1,1),Hybrid!$A$1:$LI$1),FALSE) -> 1.5667157 | K92: =VLOOKUP($E92,Hybrid!$1:$1048576,MATCH(DATE(K$2,1,1),Hybrid!$A$1:$LI$1),FALSE) -> 1.8201643 | L92: =VLOOKUP($E92,Hybrid!$1:$1048576,MATCH(DATE(L$2,1,1),Hybrid!$A$1:$LI$1),FALSE) -> 1.7616409 | M92: =VLOOKUP($E92,Hybrid!$1:$1048576,MATCH(DATE(M$2,1,1),Hybrid!$A$1:$LI$1),FALSE) -> 1.7762935 | ... AO92: =VLOOKUP($E92,Hybrid!$1:$1048576,MATCH(DATE(AO$2,1,1),Hybrid!$A$1:$LI$1),FALSE) -> 1.1895475
D93: class F | E93: NEWAUTO_cf_cele_0 | F93: =VLOOKUP($E93,Hybrid!$1:$1048576,MATCH(DATE(F$2,1,1),Hybrid!$A$1:$LI$1),FALSE) -> 0.53721981 | G93: =VLOOKUP($E93,Hybrid!$1:$1048576,MATCH(DATE(G$2,1,1),Hybrid!$A$1:$LI$1),FALSE) -> 0.61853998 | H93: =VLOOKUP($E93,Hybrid!$1:$1048576,MATCH(DATE(H$2,1,1),Hybrid!$A$1:$LI$1),FALSE) -> 0.61871178 | I93: =VLOOKUP($E93,Hybrid!$1:$1048576,MATCH(DATE(I$2,1,1),Hybrid!$A$1:$LI$1),FALSE) -> 0.60183294 | J93: =VLOOKUP($E93,Hybrid!$1:$1048576,MATCH(DATE(J$2,1,1),Hybrid!$A$1:$LI$1),FALSE) -> 0.65284332 | K93: =VLOOKUP($E93,Hybrid!$1:$1048576,MATCH(DATE(K$2,1,1),Hybrid!$A$1:$LI$1),FALSE) -> 0.73428243 | L93: =VLOOKUP($E93,Hybrid!$1:$1048576,MATCH(DATE(L$2,1,1),Hybrid!$A$1:$LI$1),FALSE) -> 0.69752432 | M93: =VLOOKUP($E93,Hybrid!$1:$1048576,MATCH(DATE(M$2,1,1),Hybrid!$A$1:$LI$1),FALSE) -> 0.683388 | ... AO93: =VLOOKUP($E93,Hybrid!$1:$1048576,MATCH(DATE(AO$2,1,1),Hybrid!$A$1:$LI$1),FALSE) -> 0.10031617
D94: class G | E94: NEWAUTO_cg_cele_0 | F94: =VLOOKUP($E94,Hybrid!$1:$1048576,MATCH(DATE(F$2,1,1),Hybrid!$A$1:$LI$1),FALSE) -> 1.0090321 | G94: =VLOOKUP($E94,Hybrid!$1:$1048576,MATCH(DATE(G$2,1,1),Hybrid!$A$1:$LI$1),FALSE) -> 1.1520966 | H94: =VLOOKUP($E94,Hybrid!$1:$1048576,MATCH(DATE(H$2,1,1),Hybrid!$A$1:$LI$1),FALSE) -> 1.1309761 | I94: =VLOOKUP($E94,Hybrid!$1:$1048576,MATCH(DATE(I$2,1,1),Hybrid!$A$1:$LI$1),FALSE) -> 1.0703897 | J94: =VLOOKUP($E94,Hybrid!$1:$1048576,MATCH(DATE(J$2,1,1),Hybrid!$A$1:$LI$1),FALSE) -> 1.126649 | K94: =VLOOKUP($E94,Hybrid!$1:$1048576,MATCH(DATE(K$2,1,1),Hybrid!$A$1:$LI$1),FALSE) -> 1.2390909 | L94: =VLOOKUP($E94,Hybrid!$1:$1048576,MATCH(DATE(L$2,1,1),Hybrid!$A$1:$LI$1),FALSE) -> 1.1553556 | M94: =VLOOKUP($E94,Hybrid!$1:$1048576,MATCH(DATE(M$2,1,1),Hybrid!$A$1:$LI$1),FALSE) -> 1.1068405 | ... AO94: =VLOOKUP($E94,Hybrid!$1:$1048576,MATCH(DATE(AO$2,1,1),Hybrid!$A$1:$LI$1),FALSE) -> 0.045269234
C95: GAS | E95: NEWAUTO_cgas_0 | F95: =VLOOKUP($E95,Hybrid!$1:$1048576,MATCH(DATE(F$2,1,1),Hybrid!$A$1:$LI$1),FALSE) -> 0.15698935 | G95: =VLOOKUP($E95,Hybrid!$1:$1048576,MATCH(DATE(G$2,1,1),Hybrid!$A$1:$LI$1),FALSE) -> 0.18363305 | H95: =VLOOKUP($E95,Hybrid!$1:$1048576,MATCH(DATE(H$2,1,1),Hybrid!$A$1:$LI$1),FALSE) -> 0.19044205 | I95: =VLOOKUP($E95,Hybrid!$1:$1048576,MATCH(DATE(I$2,1,1),Hybrid!$A$1:$LI$1),FALSE) -> 0.18990684 | J95: =VLOOKUP($E95,Hybrid!$1:$1048576,MATCH(DATE(J$2,1,1),Hybrid!$A$1:$LI$1),FALSE) -> 0.20522304 | K95: =VLOOKUP($E95,Hybrid!$1:$1048576,MATCH(DATE(K$2,1,1),Hybrid!$A$1:$LI$1),FALSE) -> 0.23597949 | L95: =VLOOKUP($E95,Hybrid!$1:$1048576,MATCH(DATE(L$2,1,1),Hybrid!$A$1:$LI$1),FALSE) -> 0.23100342 | M95: =VLOOKUP($E95,Hybrid!$1:$1048576,MATCH(DATE(M$2,1,1),Hybrid!$A$1:$LI$1),FALSE) -> 0.23366377 | ... AO95: =VLOOKUP($E95,Hybrid!$1:$1048576,MATCH(DATE(AO$2,1,1),Hybrid!$A$1:$LI$1),FALSE) -> 0.28286456
D96: class A | E96: NEWAUTO_ca_cgas_0 | F96: =VLOOKUP($E96,Hybrid!$1:$1048576,MATCH(DATE(F$2,1,1),Hybrid!$A$1:$LI$1),FALSE) -> 0.044412088 | G96: =VLOOKUP($E96,Hybrid!$1:$1048576,MATCH(DATE(G$2,1,1),Hybrid!$A$1:$LI$1),FALSE) -> 0.052094296 | H96: =VLOOKUP($E96,Hybrid!$1:$1048576,MATCH(DATE(H$2,1,1),Hybrid!$A$1:$LI$1),FALSE) -> 0.054374253 | I96: =VLOOKUP($E96,Hybrid!$1:$1048576,MATCH(DATE(I$2,1,1),Hybrid!$A$1:$LI$1),FALSE) -> 0.054921958 | J96: =VLOOKUP($E96,Hybrid!$1:$1048576,MATCH(DATE(J$2,1,1),Hybrid!$A$1:$LI$1),FALSE) -> 0.060212179 | K96: =VLOOKUP($E96,Hybrid!$1:$1048576,MATCH(DATE(K$2,1,1),Hybrid!$A$1:$LI$1),FALSE) -> 0.06967641 | L96: =VLOOKUP($E96,Hybrid!$1:$1048576,MATCH(DATE(L$2,1,1),Hybrid!$A$1:$LI$1),FALSE) -> 0.068438558 | M96: =VLOOKUP($E96,Hybrid!$1:$1048576,MATCH(DATE(M$2,1,1),Hybrid!$A$1:$LI$1),FALSE) -> 0.06968909 | ... AO96: =VLOOKUP($E96,Hybrid!$1:$1048576,MATCH(DATE(AO$2,1,1),Hybrid!$A$1:$LI$1),FALSE) -> 0.1038082
D97: class B | E97: NEWAUTO_cb_cgas_0 | F97: =VLOOKUP($E97,Hybrid!$1:$1048576,MATCH(DATE(F$2,1,1),Hybrid!$A$1:$LI$1),FALSE) -> 0.042637872 | G97: =VLOOKUP($E97,Hybrid!$1:$1048576,MATCH(DATE(G$2,1,1),Hybrid!$A$1:$LI$1),FALSE) -> 0.049990446 | H97: =VLOOKUP($E97,Hybrid!$1:$1048576,MATCH(DATE(H$2,1,1),Hybrid!$A$1:$LI$1),FALSE) -> 0.052114405 | I97: =VLOOKUP($E97,Hybrid!$1:$1048576,MATCH(DATE(I$2,1,1),Hybrid!$A$1:$LI$1),FALSE) -> 0.052447487 | J97: =VLOOKUP($E97,Hybrid!$1:$1048576,MATCH(DATE(J$2,1,1),Hybrid!$A$1:$LI$1),FALSE) -> 0.057241571 | K97: =VLOOKUP($E97,Hybrid!$1:$1048576,MATCH(DATE(K$2,1,1),Hybrid!$A$1:$LI$1),FALSE) -> 0.066178484 | L97: =VLOOKUP($E97,Hybrid!$1:$1048576,MATCH(DATE(L$2,1,1),Hybrid!$A$1:$LI$1),FALSE) -> 0.065009428 | M97: =VLOOKUP($E97,Hybrid!$1:$1048576,MATCH(DATE(M$2,1,1),Hybrid!$A$1:$LI$1),FALSE) -> 0.066098909 | ... AO97: =VLOOKUP($E97,Hybrid!$1:$1048576,MATCH(DATE(AO$2,1,1),Hybrid!$A$1:$LI$1),FALSE) -> 0.09065079
D98: class C | E98: NEWAUTO_cc_cgas_0 | F98: =VLOOKUP($E98,Hybrid!$1:$1048576,MATCH(DATE(F$2,1,1),Hybrid!$A$1:$LI$1),FALSE) -> 0.029513538 | G98: =VLOOKUP($E98,Hybrid!$1:$1048576,MATCH(DATE(G$2,1,1),Hybrid!$A$1:$LI$1),FALSE) -> 0.034587168 | H98: =VLOOKUP($E98,Hybrid!$1:$1048576,MATCH(DATE(H$2,1,1),Hybrid!$A$1:$LI$1),FALSE) -> 0.036012746 | I98: =VLOOKUP($E98,Hybrid!$1:$1048576,MATCH(DATE(I$2,1,1),Hybrid!$A$1:$LI$1),FALSE) -> 0.036111969 | J98: =VLOOKUP($E98,Hybrid!$1:$1048576,MATCH(DATE(J$2,1,1),Hybrid!$A$1:$LI$1),FALSE) -> 0.039237816 | K98: =VLOOKUP($E98,Hybrid!$1:$1048576,MATCH(DATE(K$2,1,1),Hybrid!$A$1:$LI$1),FALSE) -> 0.045322734 | L98: =VLOOKUP($E98,Hybrid!$1:$1048576,MATCH(DATE(L$2,1,1),Hybrid!$A$1:$LI$1),FALSE) -> 0.044526953 | M98: =VLOOKUP($E98,Hybrid!$1:$1048576,MATCH(DATE(M$2,1,1),Hybrid!$A$1:$LI$1),FALSE) -> 0.045206777 | ... AO98: =VLOOKUP($E98,Hybrid!$1:$1048576,MATCH(DATE(AO$2,1,1),Hybrid!$A$1:$LI$1),FALSE) -> 0.057135618
D99: class D | E99: NEWAUTO_cd_cgas_0 | F99: =VLOOKUP($E99,Hybrid!$1:$1048576,MATCH(DATE(F$2,1,1),Hybrid!$A$1:$LI$1),FALSE) -> 0.016358725 | G99: =VLOOKUP($E99,Hybrid!$1:$1048576,MATCH(DATE(G$2,1,1),Hybrid!$A$1:$LI$1),FALSE) -> 0.019119613 | H99: =VLOOKUP($E99,Hybrid!$1:$1048576,MATCH(DATE(H$2,1,1),Hybrid!$A$1:$LI$1),FALSE) -> 0.019785169 | I99: =VLOOKUP($E99,Hybrid!$1:$1048576,MATCH(DATE(I$2,1,1),Hybrid!$A$1:$LI$1),FALSE) -> 0.019616249 | J99: =VLOOKUP($E99,Hybrid!$1:$1048576,MATCH(DATE(J$2,1,1),Hybrid!$A$1:$LI$1),FALSE) -> 0.021049293 | K99: =VLOOKUP($E99,Hybrid!$1:$1048576,MATCH(DATE(K$2,1,1),Hybrid!$A$1:$LI$1),FALSE) -> 0.024145029 | L99: =VLOOKUP($E99,Hybrid!$1:$1048576,MATCH(DATE(L$2,1,1),Hybrid!$A$1:$LI$1),FALSE) -> 0.023612903 | M99: =VLOOKUP($E99,Hybrid!$1:$1048576,MATCH(DATE(M$2,1,1),Hybrid!$A$1:$LI$1),FALSE) -> 0.023797597 | ... AO99: =VLOOKUP($E99,Hybrid!$1:$1048576,MATCH(DATE(AO$2,1,1),Hybrid!$A$1:$LI$1),FALSE) -> 0.020855155
D100: class E | E100: NEWAUTO_ce_cgas_0 | F100: =VLOOKUP($E100,Hybrid!$1:$1048576,MATCH(DATE(F$2,1,1),Hybrid!$A$1:$LI$1),FALSE) -> 0.010063223 | G100: =VLOOKUP($E100,Hybrid!$1:$1048576,MATCH(DATE(G$2,1,1),Hybrid!$A$1:$LI$1),FALSE) -> 0.011734144 | H100: =VLOOKUP($E100,Hybrid!$1:$1048576,MATCH(DATE(H$2,1,1),Hybrid!$A$1:$LI$1),FALSE) -> 0.012076993 | I100: =VLOOKUP($E100,Hybrid!$1:$1048576,MATCH(DATE(I$2,1,1),Hybrid!$A$1:$LI$1),FALSE) -> 0.011847367 | J100: =VLOOKUP($E100,Hybrid!$1:$1048576,MATCH(DATE(J$2,1,1),Hybrid!$A$1:$LI$1),FALSE) -> 0.012555934 | K100: =VLOOKUP($E100,Hybrid!$1:$1048576,MATCH(DATE(K$2,1,1),Hybrid!$A$1:$LI$1),FALSE) -> 0.014309847 | L100: =VLOOKUP($E100,Hybrid!$1:$1048576,MATCH(DATE(L$2,1,1),Hybrid!$A$1:$LI$1),FALSE) -> 0.013938964 | M100: =VLOOKUP($E100,Hybrid!$1:$1048576,MATCH(DATE(M$2,1,1),Hybrid!$A$1:$LI$1),FALSE) -> 0.013954391 | ... AO100: =VLOOKUP($E100,Hybrid!$1:$1048576,MATCH(DATE(AO$2,1,1),Hybrid!$A$1:$LI$1),FALSE) -> 0.0087472851
...

Sheet date
A1: =Hybrid!A1 -> _date_ | B1: =Hybrid!B1 -> 42005 | C1: =Hybrid!C1 -> 42370 | D1: =Hybrid!D1 -> 42736 | E1: =Hybrid!E1 -> 43101 | F1: =Hybrid!F1 -> 43466 | G1: =Hybrid!G1 -> 43831 | H1: =Hybrid!H1 -> 44197 | ... AK1: =Hybrid!AK1 -> 54789
B2: =TEXT(B1,"jj mm aaaa") -> 01 01 2015 | C2: =TEXT(C1,"jj mm aaaa") -> 01 01 2016 | D2: =TEXT(D1,"jj mm aaaa") -> 01 01 2017 | E2: =TEXT(E1,"jj mm aaaa") -> 01 01 2018 | F2: =TEXT(F1,"jj mm aaaa") -> 01 01 2019 | G2: =TEXT(G1,"jj mm aaaa") -> 01 01 2020 | H2: =TEXT(H1,"jj mm aaaa") -> 01 01 2021 | I2: =TEXT(I1,"jj mm aaaa") -> 01 01 2022 | ... AK2: =TEXT(AK1,"jj mm aaaa") -> 01 01 2050
B3: =RIGHT(B2,4) -> 2015 | C3: =RIGHT(C2,4) -> 2016 | D3: =RIGHT(D2,4) -> 2017 | E3: =RIGHT(E2,4) -> 2018 | F3: =RIGHT(F2,4) -> 2019 | G3: =RIGHT(G2,4) -> 2020 | H3: =RIGHT(H2,4) -> 2021 | I3: =RIGHT(I2,4) -> 2022 | ... AK3: =RIGHT(AK2,4) -> 2050

Sheet Emissions
A1: _date_ | B1: 42005 | C1: 42370 | D1: 42736 | E1: 43101 | F1: 43466 | G1: 43831 | H1: 44197 | I1: 44562 | J1: 44927 | K1: 45292 | L1: 45658 | M1: 46023 | N1: 46388 | O1: 46753 | P1: 47119 | Q1: 47484 | R1: 47849 | S1: 48214 | T1: 48580 | U1: 48945 | V1: 49310 | W1: 49675 | X1: 50041 | Y1: 50406 | Z1: 50771 | AA1: 51136 | AB1: 51502 | AC1: 51867 | AD1: 52232 | AE1: 52597 | AF1: 52963 | AG1: 53328 | AH1: 53693 | AI1: 54058 | AJ1: 54424 | AK1: 54789
A2: ems_2 | B2: 468.73647 | C2: 471.22784 | D2: 470.68197 | E2: 468.43159 | F2: 470.11734 | G2: 478.47781 | H2: 485.24382 | I2: 491.07808 | J2: 495.76141 | K2: 499.26709 | L2: 501.59731 | M2: 506.17146 | N2: 512.82161 | O2: 521.04819 | P2: 530.35351 | Q2: 540.35066 | R2: 550.14357 | S2: 559.55212 | T2: 568.41313 | U2: 576.7247 | V2: 584.49731 | W2: 591.83549 | X2: 599.11502 | Y2: 606.38249 | Z2: 613.63764 | AA2: 620.66174 | AB2: 627.39957 | AC2: 634.16391 | AD2: 640.98233 | AE2: 647.85693 | AF2: 654.78924 | AG2: 661.79459 | AH2: 668.95931 | AI2: 676.26692 | AJ2: 683.68978 | AK2: 691.20282
A3: ems_ch_2 | B3: 129.15358 | C3: 128.52486 | D3: 126.47311 | E3: 124.08764 | F3: 123.19834 | G3: 123.6922 | H3: 123.22422 | I3: 122.66258 | J3: 121.92415 | K3: 120.99812 | L3: 119.8841 | M3: 119.80768 | N3: 120.23544 | O3: 120.90099 | P3: 121.66957 | Q3: 122.47506 | R3: 123.1907 | S3: 123.78432 | T3: 124.22935 | U3: 124.54017 | V3: 124.72177 | W3: 124.96393 | X3: 125.20693 | Y3: 125.42331 | Z3: 125.60209 | AA3: 125.66707 | AB3: 125.76146 | AC3: 125.84251 | AD3: 125.88896 | AE3: 125.89276 | AF3: 125.85284 | AG3: 125.81601 | AH3: 125.76033 | AI3: 125.67546 | AJ3: 125.55763 | AK3: 125.40636
A4: ems_ch_2+ems_ci_2 | B4: 348.54687 | C4: 349.38541 | D4: 347.20821 | E4: 343.36185 | F4: 343.22134 | G4: 349.10564 | H4: 353.23132 | I4: 356.28414 | J4: 358.06109 | K4: 358.50337 | L4: 357.547 | M4: 358.94717 | N4: 362.31537 | O4: 367.10777 | P4: 372.8566 | Q4: 379.21703 | R4: 385.41674 | S4: 391.25986 | T4: 396.60642 | U4: 401.45494 | V4: 405.82498 | W4: 409.98124 | X4: 414.12867 | Y4: 418.27856 | Z4: 422.41198 | AA4: 426.36067 | AB4: 430.19754 | AC4: 434.07743 | AD4: 437.99228 | AE4: 441.92083 | AF4: 445.84782 | AG4: 449.84282 | AH4: 453.93126 | AI4: 458.08319 | AJ4: 462.26652 | AK4: 466.45566
A5: ems_ci_2 | B5: 219.3933 | C5: 220.86055 | D5: 220.73509 | E5: 219.27422 | F5: 220.023 | G5: 225.41344 | H5: 230.00709 | I5: 233.62156 | J5: 236.13694 | K5: 237.50526 | L5: 237.66289 | M5: 239.13948 | N5: 242.07994 | O5: 246.20678 | P5: 251.18704 | Q5: 256.74197 | R5: 262.22604 | S5: 267.47554 | T5: 272.37707 | U5: 276.91477 | V5: 281.10321 | W5: 285.01731 | X5: 288.92174 | Y5: 292.85525 | Z5: 296.80989 | AA5: 300.69361 | AB5: 304.43608 | AC5: 308.23492 | AD5: 312.10332 | AE5: 316.02807 | AF5: 319.99499 | AG5: 324.0268 | AH5: 328.17093 | AI5: 332.40773 | AJ5: 336.70889 | AK5: 341.0493
A6: ems_mat_2 | B6: 27.946324 | C6: 28.310096 | D6: 28.670015 | E6: 29.013804 | F6: 29.386711 | G6: 29.849273 | H6: 30.345243 | I6: 30.853197 | J6: 31.360608 | K6: 31.863058 | L6: 32.360053 | M6: 32.852325 | N6: 33.366642 | O6: 33.911264 | P6: 34.483664 | Q6: 35.078184 | R6: 35.677269 | S6: 36.279344 | T6: 36.881379 | U6: 37.482897 | V6: 38.083261 | W6: 38.668967 | X6: 39.256191 | Y6: 39.850494 | Z6: 40.454156 | AA6: 41.062527 | AB6: 41.662378 | AC6: 42.267565 | AD6: 42.882505 | AE6: 43.509243 | AF6: 44.148969 | AG6: 44.797539 | AH6: 45.459998 | AI6: 46.137535 | AJ6: 46.829977 | AK6: 47.536644
A7: ems_y_2 | B7: 92.243273 | C7: 93.532327 | D7: 94.803751 | E7: 96.055935 | F7: 97.509283 | G7: 99.522902 | H7: 101.66726 | I7: 103.94074 | J7: 106.33971 | K7: 108.90066 | L7: 111.69026 | M7: 114.37197 | N7: 117.13959 | O7: 120.02916 | P7: 123.01325 | Q7: 126.05544 | R7: 129.04957 | S7: 132.01291 | T7: 134.92533 | U7: 137.78686 | V7: 140.58906 | W7: 143.18528 | X7: 145.73016 | Y7: 148.25344 | Z7: 150.7715 | AA7: 153.23854 | AB7: 155.53965 | AC7: 157.81892 | AD7: 160.10755 | AE7: 162.42685 | AF7: 164.79245 | AG7: 167.15424 | AH7: 169.56805 | AI7: 172.04619 | AJ7: 174.59328 | AK7: 177.21052
A8: ems_sec_2 | B8: 339.58289 | C8: 342.70298 | D8: 344.20886 | E8: 344.34395 | F8: 346.919 | G8: 354.78561 | H8: 362.0196 | I8: 368.41549 | J8: 373.83726 | K8: 378.26897 | L8: 381.71321 | M8: 386.36377 | N8: 392.58617 | O8: 400.1472 | P8: 408.68395 | Q8: 417.8756 | R8: 426.95287 | S8: 435.7678 | T8: 444.18378 | U8: 452.18453 | V8: 459.77553 | W8: 466.87156 | X8: 473.9081 | Y8: 480.95918 | Z8: 488.03555 | AA8: 494.99468 | AB8: 501.63811 | AC8: 508.3214 | AD8: 515.09337 | AE8: 521.96416 | AF8: 528.93641 | AG8: 535.97858 | AH8: 543.19898 | AI8: 550.59146 | AJ8: 558.13215 | AK8: 565.79646
A9: ems_ets_2 | B9: 126.27982 | C9: 126.55264 | D9: 126.24845 | E9: 125.61435 | F9: 126.00563 | G9: 128.53239 | H9: 130.99371 | I9: 133.10159 | J9: 134.70683 | K9: 135.73809 | L9: 136.12586 | M9: 137.02415 | N9: 138.61327 | O9: 140.79145 | P9: 143.39633 | Q9: 146.27756 | R9: 149.08067 | S9: 151.78348 | T9: 154.35048 | U9: 156.76755 | V9: 159.02818 | W9: 161.11304 | X9: 163.20601 | Y9: 165.33576 | Z9: 167.49725 | AA9: 169.63656 | AB9: 171.67892 | AC9: 173.77178 | AD9: 175.92787 | AE9: 178.13854 | AF9: 180.39359 | AG9: 182.68822 | AH9: 185.06153 | AI9: 187.50475 | AJ9: 190.00168 | AK9: 192.5368
A10: ems_nets_2 | B10: 213.30307 | C10: 216.15034 | D10: 217.96041 | E10: 218.72961 | F10: 220.91336 | G10: 226.25322 | H10: 231.02588 | I10: 235.3139 | J10: 239.13043 | K10: 242.53088 | L10: 245.58735 | M10: 249.33962 | N10: 253.97291 | O10: 259.35576 | P10: 265.28762 | Q10: 271.59804 | R10: 277.8722 | S10: 283.98432 | T10: 289.8333 | U10: 295.41698 | V10: 300.74735 | W10: 305.75852 | X10: 310.70209 | Y10: 315.62342 | Z10: 320.53829 | AA10: 325.35812 | AB10: 329.95918 | AC10: 334.54962 | AD10: 339.16551 | AE10: 343.82562 | AF10: 348.54281 | AG10: 353.29036 | AH10: 358.13745 | AI10: 363.08671 | AJ10: 368.13047 | AK10: 373.25966
A11: ems_netsi_2 | B11: 25.501031 | C11: 25.796923 | D11: 25.911732 | E11: 25.885419 | F11: 26.129272 | G11: 26.86478 | H11: 27.489602 | I11: 28.005436 | J11: 28.399008 | K11: 28.667493 | L11: 28.812013 | M11: 29.091998 | N11: 29.524594 | O11: 30.084677 | P11: 30.740944 | Q11: 31.46711 | R11: 32.198964 | S11: 32.918396 | T11: 33.61311 | U11: 34.282879 | V11: 34.929489 | W11: 35.556979 | X11: 36.191113 | Y11: 36.834804 | Z11: 37.48762 | AA11: 38.138207 | AB11: 38.775881 | AC11: 39.419298 | AD11: 40.069357 | AE11: 40.725928 | AF11: 41.38891 | AG11: 42.060058 | AH11: 42.744656 | AI11: 43.441008 | AJ11: 44.146744 | AK11: 44.859752
A12: ems_trsp_2-ems_sair_2 | B12: 24.94055 | C12: 25.485912 | D12: 25.776421 | E12: 25.713928 | F12: 25.829645 | G12: 26.665358 | H12: 27.281626 | I12: 27.855881 | J12: 28.415996 | K12: 28.96321 | L12: 29.467358 | M12: 30.121625 | N12: 30.9359 | O12: 31.875442 | P12: 32.906015 | Q12: 34.003796 | R12: 35.088438 | S12: 36.104423 | T12: 37.012173 | U12: 37.806945 | V12: 38.499565 | W12: 39.101245 | X12: 39.662305 | Y12: 40.195551 | Z12: 40.707501 | AA12: 41.195907 | AB12: 41.648292 | AC12: 42.103952 | AD12: 42.567983 | AE12: 43.040175 | AF12: 43.519339 | AG12: 44.006905 | AH12: 44.512021 | AI12: 45.032161 | AJ12: 45.563353 | AK12: 46.101856
... A819: ems_ch_cbio_0+ems_ci_cbio_0 | B819: 31.868019 | C819: 31.508897 | D819: 31.130598 | E819: 30.68572 | F819: 30.430265 | G819: 30.2839 | H819: 30.188909 | I819: 30.119593 | J819: 30.065292 | K819: 30.020527 | L819: 29.997656 | M819: 29.972747 | N819: 29.95102 | O819: 29.934812 | P819: 29.924832 | Q819: 29.920999 | R819: 29.917421 | S819: 29.917639 | T819: 29.922223 | U819: 29.931243 | V819: 29.934975 | W819: 29.943335 | X819: 29.957067 | Y819: 29.97559 | Z819: 29.998544 | AA819: 29.999115 | AB819: 29.980905 | AC819: 29.960778 | AD819: 29.941834 | AE819: 29.924798 | AF819: 29.909968 | AG819: 29.913502 | AH819: 29.924301 | AI819: 29.940158 | AJ819: 29.960556 | AK819: 29.985336

Sheet Consumption
A1: _date_ | B1: 42005 | C1: 42370 | D1: 42736 | E1: 43101 | F1: 43466 | G1: 43831 | H1: 44197 | I1: 44562 | J1: 44927 | K1: 45292 | L1: 45658 | M1: 46023 | N1: 46388 | O1: 46753 | P1: 47119 | Q1: 47484 | R1: 47849 | S1: 48214 | T1: 48580 | U1: 48945 | V1: 49310 | W1: 49675 | X1: 50041 | Y1: 50406 | Z1: 50771 | AA1: 51136 | AB1: 51502 | AC1: 51867 | AD1: 52232 | AE1: 52597 | AF1: 52963 | AG1: 53328 | AH1: 53693 | AI1: 54058 | AJ1: 54424 | AK1: 54789
A2: ch_2 | B2: 1203751.7 | C2: 1225522.3 | D2: 1243141.7 | E2: 1258585.7 | F2: 1279600.4 | G2: 1313434.8 | H2: 1341060.6 | I2: 1368505.8 | J2: 1397301.7 | K2: 1428898 | L2: 1465808.1 | M2: 1501277 | N2: 1538663.1 | O2: 1577981.3 | P2: 1618530.5 | Q2: 1659738 | R2: 1701167.9 | S2: 1741664.6 | T2: 1781211.8 | U2: 1820231.4 | V2: 1858652.1 | W2: 1896167.4 | X2: 1933034.1 | Y2: 1969385.5 | Z2: 2005343.9 | AA2: 2039602.6 | AB2: 2072358.6 | AC2: 2103624.4 | AD2: 2133797.1 | AE2: 2163344 | AF2: 2192673.7 | AG2: 2221502.8 | AH2: 2250157.6 | AI2: 2278881.2 | AJ2: 2307869.5 | AK2: 2337293.3
A3: ch_0 | B3: 1203751.7 | C3: 1225522.3 | D3: 1243141.7 | E3: 1258585.7 | F3: 1279600.4 | G3: 1313434.8 | H3: 1341619.7 | I3: 1368820.9 | J3: 1395552.4 | K3: 1421817.5 | L3: 1448645.4 | M3: 1475789.7 | N3: 1504134.6 | O3: 1534022.5 | P3: 1565339.9 | Q3: 1597788.4 | R3: 1630574.5 | S3: 1663395.9 | T3: 1696156.8 | U3: 1728837.6 | V3: 1760967.6 | W3: 1792786.4 | X3: 1824108.2 | Y3: 1854979.5 | Z3: 1885507 | AA3: 1914395.4 | AB3: 1940703.1 | AC3: 1963969.5 | AD3: 1984528.7 | AE3: 2002967.4 | AF3: 2019903.9 | AG3: 2037438.6 | AH3: 2056331.3 | AI3: 2076829.2 | AJ3: 2098967.3 | AK3: 2122678.7
A4: pch_2 | B4: 1.0026242 | C4: 1.0164384 | D4: 1.0422139 | E4: 1.074108 | F4: 1.0964129 | G4: 1.1036427 | H4: 1.1248293 | I4: 1.150596 | J4: 1.1822647 | K4: 1.2220636 | L4: 1.2718451 | M4: 1.317943 | N4: 1.3649507 | O4: 1.4132114 | P4: 1.462888 | Q4: 1.5139433 | R4: 1.5676984 | S4: 1.624535 | T4: 1.684099 | U4: 1.7459134 | V4: 1.8096485 | W4: 1.8731596 | X4: 1.9366075 | Y4: 1.9996102 | Z4: 2.0618155 | AA4: 2.1232212 | AB4: 2.1828483 | AC4: 2.2411956 | AD4: 2.2979546 | AE4: 2.352933 | AF4: 2.4060038 | AG4: 2.45638 | AH4: 2.5044505 | AI4: 2.5501861 | AJ4: 2.5935852 | AK4: 2.634618
A5: pch_0 | B5: 1.0026242 | C5: 1.0164384 | D5: 1.0422139 | E5: 1.074108 | F5: 1.0964129 | G5: 1.1036427 | H5: 1.1243158 | I5: 1.1434323 | J5: 1.1638889 | K5: 1.1865031 | L5: 1.21123 | M5: 1.2375897 | N5: 1.2650224 | O5: 1.29324 | P5: 1.3222142 | Q5: 1.3519683 | R5: 1.3822574 | S5: 1.4128779 | T5: 1.4436767 | U5: 1.474553 | V5: 1.5055242 | W5: 1.5363034 | X5: 1.5667327 | Y5: 1.5967634 | Z5: 1.6264145 | AA5: 1.6560222 | AB5: 1.6847515 | AC5: 1.7122648 | AD5: 1.7385228 | AE5: 1.7636 | AF5: 1.7876427 | AG5: 1.8114001 | AH5: 1.8353228 | AI5: 1.859692 | AJ5: 1.8846995 | AK5: 1.9104928
A6: ch_cagr_2 | B6: 31680.775 | C6: 32199.68 | D6: 32644.107 | E6: 33062.254 | F6: 33575.595 | G6: 34401.857 | H6: 35213.593 | I6: 36026.514 | J6: 36859.141 | K6: 37744.115 | L6: 38754.905 | M6: 39698.351 | N6: 40711.912 | O6: 41816.48 | P6: 42992.126 | Q6: 44214.563 | R6: 45464.152 | S6: 46701.26 | T6: 47915.206 | U6: 49109.628 | V6: 50280.831 | W6: 51415.911 | X6: 52529.804 | Y6: 53629.477 | Z6: 54718.714 | AA6: 55763.703 | AB6: 56760.974 | AC6: 57712.115 | AD6: 58628.023 | AE6: 59520.921 | AF6: 60401.83 | AG6: 61260.809 | AH6: 62109.782 | AI6: 62956.769 | AJ6: 63807.548 | AK6: 64667.144
A7: ch_cagr_0 | B7: 31680.775 | C7: 32199.68 | D7: 32644.107 | E7: 33062.254 | F7: 33575.595 | G7: 34401.857 | H7: 35231.006 | I7: 36050.307 | J7: 36857.028 | K7: 37641.693 | L7: 38428.916 | M7: 39218.106 | N7: 40038.439 | O7: 40904.225 | P7: 41815.437 | Q7: 42765.135 | R7: 43731.723 | S7: 44705.434 | T7: 45681.977 | U7: 46659.282 | V7: 47624.073 | W7: 48580.121 | X7: 49521.218 | Y7: 50447.475 | Z7: 51361.031 | AA7: 52228.359 | AB7: 53019.743 | AC7: 53719.028 | AD7: 54332.824 | AE7: 54876.457 | AF7: 55367.311 | AG7: 55864.278 | AH7: 56391.875 | AI7: 56959.828 | AJ7: 57571.101 | AK7: 58225.206
A8: pch_cagr_2 | B8: 1.0017119 | C8: 1.014487 | D8: 1.0371554 | E8: 1.0668035 | F8: 1.0915725 | G8: 1.1013407 | H8: 1.1181515 | I8: 1.1424032 | J8: 1.1730701 | K8: 1.2124518 | L8: 1.2618699 | M8: 1.3105893 | N8: 1.3581624 | O8: 1.4053338 | P8: 1.4527117 | Q8: 1.5006246 | R8: 1.5505842 | S8: 1.6034854 | T8: 1.6591374 | U8: 1.7171518 | V8: 1.7771335 | W8: 1.8371926 | X8: 1.8969362 | Y8: 1.9560467 | Z8: 2.0142478 | AA8: 2.0715317 | AB8: 2.1274456 | AC8: 2.1823262 | AD8: 2.2358769 | AE8: 2.2879578 | AF8: 2.3384775 | AG8: 2.3868499 | AH8: 2.4332408 | AI8: 2.4776216 | AJ8: 2.5199994 | AK8: 2.5603294
A9: pch_cagr_0 | B9: 1.0017119 | C9: 1.014487 | D9: 1.0371554 | E9: 1.0668035 | F9: 1.0915725 | G9: 1.1013407 | H9: 1.1174167 | I9: 1.134855 | J9: 1.1537725 | K9: 1.1754478 | L9: 1.1996756 | M9: 1.2256085 | N9: 1.2524149 | O9: 1.2797074 | P9: 1.3074723 | Q9: 1.3357662 | R9: 1.3643981 | S9: 1.3932039 | T9: 1.4220713 | U9: 1.4509469 | V9: 1.4798696 | W9: 1.5086484 | X9: 1.5371804 | Y9: 1.5654573 | Z9: 1.593526 | AA9: 1.6216715 | AB9: 1.6492688 | AC9: 1.6760931 | AD9: 1.7021442 | AE9: 1.7274842 | AF9: 1.7522358 | AG9: 1.7770124 | AH9: 1.8021718 | AI9: 1.8279436 | AJ9: 1.8544839 | AK9: 1.8819082
A10: ch_cfoo_2 | B10: 175334.5 | C10: 178037.53 | D10: 180455.09 | E10: 182929.33 | F10: 185876.49 | G10: 190208.78 | H10: 194520.77 | I10: 198980.68 | J10: 203658.5 | K10: 208725.16 | L10: 214572.87 | M10: 219926 | N10: 225505.78 | O10: 231462.31 | P10: 237730.97 | Q10: 244213.42 | R10: 250849.51 | S10: 257457.1 | T10: 263984.9 | U10: 270444.47 | V10: 276801.3 | W10: 282952.24 | X10: 288973.95 | Y10: 294908.75 | Z10: 300783.68 | AA10: 306418.17 | AB10: 311794.53 | AC10: 316933.34 | AD10: 321897.7 | AE10: 326755.81 | AF10: 331568.19 | AG10: 336272.22 | AH10: 340935.27 | AI10: 345602.44 | AJ10: 350305.89 | AK10: 355072.25
A11: ch_cfoo_0 | B11: 175334.5 | C11: 178037.53 | D11: 180455.09 | E11: 182929.33 | F11: 185876.49 | G11: 190208.78 | H11: 194605.1 | I11: 199001.38 | J11: 203375.35 | K11: 207680.71 | L11: 212039.37 | M11: 216419.5 | N11: 220955.58 | O11: 225713.45 | P11: 230692.7 | Q11: 235860.42 | R11: 241103.31 | S11: 246372.44 | T11: 251648.69 | U11: 256925.11 | V11: 262132.4 | W11: 267294.96 | X11: 272381.64 | Y11: 277396.04 | Z11: 282352.55 | AA11: 287068.29 | AB11: 291382.56 | AC11: 295210.04 | AD11: 298590.8 | AE11: 301611.1 | AF11: 304366.97 | AG11: 307180.13 | AH11: 310181.46 | AI11: 313419.7 | AJ11: 316906.52 | AK11: 320635.23
A12: pch_cfoo_2 | B12: 1.0011606 | C12: 1.0169854 | D12: 1.0391976 | E12: 1.0658871 | F12: 1.0900035 | G12: 1.1046123 | H12: 1.1227035 | I12: 1.1463911 | J12: 1.1757149 | K12: 1.2128148 | L12: 1.2590991 | M12: 1.3072755 | N12: 1.3561632 | O12: 1.4057282 | P12: 1.4560972 | Q12: 1.5073335 | R12: 1.5603622 | S12: 1.6157761 | T12: 1.673496 | U12: 1.7333043 | V12: 1.7949666 | W12: 1.8570566 | X12: 1.9190279 | Y12: 1.9804478 | Z12: 2.0409533 | AA12: 2.1004839 | AB12: 2.1585958 | AC12: 2.2153944 | AD12: 2.2706007 | AE12: 2.3240617 | AF12: 2.3756793 | AG12: 2.4250155 | AH12: 2.4721219 | AI12: 2.5169597 | AJ12: 2.559534 | AK12: 2.5998222
... A105: pch_cbio_0 | B105: 1.0606665 | C105: 1.1063782 | D105: 1.1624385 | E105: 1.2486138 | F105: 1.2738137 | G105: 1.2869472 | H105: 1.306554 | I105: 1.326818 | J105: 1.3480375 | K105: 1.3707377 | L105: 1.3950873 | M105: 1.4210531 | N105: 1.4484204 | O105: 1.4770071 | P105: 1.5067269 | Q105: 1.5375251 | R105: 1.569127 | S105: 1.6013095 | T105: 1.6338765 | U105: 1.6666619 | V105: 1.699615 | W105: 1.7324002 | X105: 1.764822 | Y105: 1.7967743 | Z105: 1.8282157 | AA105: 1.8594276 | AB105: 1.8895598 | AC105: 1.9182898 | AD105: 1.9455271 | AE105: 1.9712777 | AF105: 1.9956182 | AG105: 2.0192616 | AH105: 2.042638 | AI105: 2.0660747 | AJ105: 2.0898553 | AK105: 2.114231

Sheet Value_Added
A1: _date_ | B1: 42005 | C1: 42370 | D1: 42736 | E1: 43101 | F1: 43466 | G1: 43831 | H1: 44197 | I1: 44562 | J1: 44927 | K1: 45292 | L1: 45658 | M1: 46023 | N1: 46388 | O1: 46753 | P1: 47119 | Q1: 47484 | R1: 47849 | S1: 48214 | T1: 48580 | U1: 48945 | V1: 49310 | W1: 49675 | X1: 50041 | Y1: 50406 | Z1: 50771 | AA1: 51136 | AB1: 51502 | AC1: 51867 | AD1: 52232 | AE1: 52597 | AF1: 52963 | AG1: 53328 | AH1: 53693 | AI1: 54058 | AJ1: 54424 | AK1: 54789
A2: va_2 | B2: 1966438.4 | C2: 1997094.1 | D2: 2026199.6 | E2: 2054509.9 | F2: 2086664 | G2: 2128034.7 | H2: 2169476 | I2: 2212478.5 | J2: 2257212.2 | K2: 2304391.6 | L2: 2355220.4 | M2: 2404466 | N2: 2455294.4 | O2: 2507861.3 | P2: 2561671.8 | Q2: 2616254.6 | R2: 2669995.4 | S2: 2723591 | T2: 2776934.2 | U2: 2830191.9 | V2: 2883255.6 | W2: 2933690.5 | X2: 2984129.4 | Y2: 3034796.5 | Z2: 3085879.4 | AA2: 3136527.6 | AB2: 3184863.8 | AC2: 3233338.6 | AD2: 3282252.2 | AE2: 3331914.4 | AF2: 3382574.7 | AG2: 3433395.6 | AH2: 3485334.7 | AI2: 3538516.2 | AJ2: 3593005 | AK2: 3648828
A3: va_0 | B3: 1966438.4 | C3: 1997094.1 | D3: 2026199.6 | E3: 2054509.9 | F3: 2086664 | G3: 2128034.7 | H3: 2170733.8 | I3: 2214104.7 | J3: 2258223.5 | K3: 2303260.7 | L3: 2349912.8 | M3: 2397580.4 | N3: 2446785.5 | O3: 2497603 | P3: 2549944.9 | Q3: 2603658.3 | R3: 2655918.7 | S3: 2708811.6 | T3: 2762317.4 | U3: 2816514 | V3: 2871161 | W3: 2924265.3 | X3: 2977964.5 | Y3: 3032378.8 | Z3: 3087683.3 | AA3: 3143023.5 | AB3: 3187216 | AC3: 3230270.3 | AD3: 3272402.8 | AE3: 3314084.5 | AF3: 3355752.1 | AG3: 3405297.3 | AH3: 3456842.8 | AI3: 3510493.6 | AJ3: 3566137.2 | AK3: 3623614.1
A4: va_sagr_2 | B4: 30826.643 | C4: 31238.433 | D4: 31677.22 | E4: 32156.691 | F4: 32686.687 | G4: 33338.582 | H4: 34045.687 | I4: 34815.262 | J4: 35647.768 | K4: 36560.697 | L4: 37584.49 | M4: 38527.847 | N4: 39487.56 | O4: 40475.327 | P4: 41482.398 | Q4: 42499.14 | R4: 43496.02 | S4: 44490.279 | T4: 45475.959 | U4: 46453.675 | V4: 47418.556 | W4: 48307.223 | X4: 49185.762 | Y4: 50058.406 | Z4: 50929.704 | AA4: 51780.799 | AB4: 52567.567 | AC4: 53351.777 | AD4: 54139.541 | AE4: 54937.899 | AF4: 55752.612 | AG4: 56561.427 | AH4: 57389.423 | AI4: 58239.809 | AJ4: 59114.414 | AK4: 60014.13
A5: va_sagr_0 | B5: 30826.643 | C5: 31238.433 | D5: 31677.22 | E5: 32156.691 | F5: 32686.687 | G5: 33338.582 | H5: 34073.492 | I5: 34825.072 | J5: 35595.475 | K5: 36388.127 | L5: 37217.802 | M5: 38067.95 | N5: 38948.901 | O5: 39859.817 | P5: 40797.074 | Q5: 41756.502 | R5: 42673.936 | S5: 43599.714 | T5: 44530.671 | U5: 45467.795 | V5: 46405.492 | W5: 47299.668 | X5: 48201.241 | Y5: 49110.541 | Z5: 50031.278 | AA5: 50944.622 | AB5: 51602.104 | AC5: 52244.291 | AD5: 52865.136 | AE5: 53473.65 | AF5: 54080.711 | AG5: 54865.204 | AH5: 55687.326 | AI5: 56557.85 | AJ5: 57476.725 | AK5: 58440.931
A6: va_sfor_2 | B6: 5287.5473 | C6: 5234.3659 | D6: 5187.2896 | E6: 5136.8657 | F6: 5111.8293 | G6: 5101.1954 | H6: 5101.5161 | I6: 5077.5087 | J6: 5035.9161 | K6: 4978.7593 | L6: 4908.3692 | M6: 4886.8289 | N6: 4886.9129 | O6: 4896.741 | P6: 4910.8084 | Q6: 4926.5741 | R6: 4937.1081 | S6: 4946.0814 | T6: 4954.2292 | U6: 4961.8738 | V6: 4967.8484 | W6: 4975.5758 | X6: 4985.3499 | Y6: 4996.1674 | Z6: 5007.5952 | AA6: 5015.7641 | AB6: 5024.2569 | AC6: 5034.686 | AD6: 5046.5556 | AE6: 5059.612 | AF6: 5073.7362 | AG6: 5089.5606 | AH6: 5107.1552 | AI6: 5126.1405 | AJ6: 5146.2904 | AK6: 5167.4476
A7: va_sfor_0 | B7: 5287.5473 | C7: 5234.3659 | D7: 5187.2896 | E7: 5136.8657 | F7: 5111.8293 | G7: 5101.1954 | H7: 5102.9425 | I7: 5109.5393 | J7: 5119.7164 | K7: 5132.9891 | L7: 5151.3366 | M7: 5170.5549 | N7: 5191.3011 | O7: 5213.6246 | P7: 5237.4669 | Q7: 5262.7444 | R7: 5285.8823 | S7: 5309.902 | T7: 5334.9567 | U7: 5361.1408 | V7: 5387.0381 | W7: 5411.7703 | X7: 5437.9289 | Y7: 5465.5686 | Z7: 5494.7624 | AA7: 5521.4503 | AB7: 5534.5052 | AC7: 5547.8742 | AD7: 5562.2714 | AE7: 5577.9611 | AF7: 5595.0666 | AG7: 5623.3198 | AH7: 5654.0786 | AI7: 5686.8455 | AJ7: 5721.3959 | AK7: 5757.5778
A8: va_sfoo_2 | B8: 43713.563 | C8: 44411.459 | D8: 45075.75 | E8: 45765.607 | F8: 46539.67 | G8: 47551.69 | H8: 48563.094 | I8: 49655.02 | J8: 50834.743 | K8: 52133.668 | L8: 53607.065 | M8: 54934.884 | N8: 56308.973 | O8: 57732.528 | P8: 59185.584 | Q8: 60653.207 | R8: 62100.584 | S8: 63539.343 | T8: 64960.971 | U8: 66368.783 | V8: 67754.725 | W8: 69040.946 | X8: 70315.688 | Y8: 71579.537 | Z8: 72837.664 | AA8: 74055.022 | AB8: 75186.573 | AC8: 76310.442 | AD8: 77432.134 | AE8: 78562.02 | AF8: 79709.099 | AG8: 80842.512 | AH8: 81998.947 | AI8: 83182.073 | AJ8: 84394.907 | AK8: 85639.612
A9: va_sfoo_0 | B9: 43713.563 | C9: 44411.459 | D9: 45075.75 | E9: 45765.607 | F9: 46539.67 | G9: 47551.69 | H9: 48599.965 | I9: 49656.428 | J9: 50733.647 | K9: 51835.518 | L9: 52987.546 | M9: 54162.647 | N9: 55381.809 | O9: 56644.445 | P9: 57944.83 | Q9: 59276.391 | R9: 60558.554 | S9: 61854.334 | T9: 63155.767 | U9: 64463.594 | V9: 65766.638 | W9: 67017.742 | X9: 68277.549 | Y9: 69543.019 | Z9: 70818.867 | AA9: 72070.112 | AB9: 73004.409 | AC9: 73919.941 | AD9: 74793.868 | AE9: 75638.851 | AF9: 76471.307 | AG9: 77517.057 | AH9: 78601.9 | AI9: 79750.804 | AJ9: 80965.066 | AK9: 82241.023
A10: va_sveh_2 | B10: 29834.843 | C10: 30802.958 | D10: 31520.472 | E10: 32077.12 | F10: 32867.939 | G10: 33972.599 | H10: 34734.599 | I10: 35534.437 | J10: 36368.681 | K10: 37232.625 | L10: 38101.634 | M10: 39039.104 | N10: 40019.91 | O10: 40998.121 | P10: 41968.286 | Q10: 42934.7 | R10: 43805.698 | S10: 44673.269 | T10: 45532.53 | U10: 46396.667 | V10: 47270.195 | W10: 48037.7 | X10: 48857.458 | Y10: 49699.461 | Z10: 50562.193 | AA10: 51436.189 | AB10: 52213.908 | AC10: 53056.046 | AD10: 53933.84 | AE10: 54845.116 | AF10: 55789.775 | AG10: 56733.731 | AH10: 57723.978 | AI10: 58748.807 | AJ10: 59805.641 | AK10: 60892.546
A11: va_sveh_0 | B11: 29834.843 | C11: 30802.958 | D11: 31520.472 | E11: 32077.12 | F11: 32867.939 | G11: 33972.599 | H11: 34794.891 | I11: 35638.373 | J11: 36508.135 | K11: 37416.645 | L11: 38372.756 | M11: 39348.93 | N11: 40358.863 | O11: 41394.875 | P11: 42454.255 | Q11: 43536.453 | R11: 44495.77 | S11: 45506.295 | T11: 46542.283 | U11: 47603.739 | V11: 48689.718 | W11: 49669.938 | X11: 50710.666 | Y11: 51788.105 | Z11: 52902.501 | AA11: 54045.139 | AB11: 54569.355 | AC11: 55265.88 | AD11: 56009.015 | AE11: 56787.866 | AF11: 57602.798 | AG11: 58864.16 | AH11: 60078.604 | AI11: 61321.82 | AJ11: 62598.441 | AK11: 63905.759
A12: va_sgla_2 | B12: 7905.0528 | C12: 8043.1167 | D12: 8177.3422 | E12: 8300.092 | F12: 8429.8203 | G12: 8595.4171 | H12: 8775.7334 | I12: 8965.6946 | J12: 9160.1139 | K12: 9356.3984 | L12: 9551.7992 | M12: 9739.2963 | N12: 9934.6546 | O12: 10141.336 | P12: 10358.638 | Q12: 10584.722 | R12: 10809.602 | S12: 11036.897 | T12: 11264.608 | U12: 11492.649 | V12: 11720.714 | W12: 11937.82 | X12: 12158.332 | Y12: 12383.258 | Z12: 12613.475 | AA12: 12846.579 | AB12: 13072.559 | AC12: 13304.374 | AD12: 13542.379 | AE12: 13787.166 | AF12: 14039.161 | AG12: 14295.054 | AH12: 14559.206 | AI12: 14831.512 | AJ12: 15111.647 | AK12: 15399.118
... A79: va_ser_0 | B79: 1511704 | C79: 1534651.4 | D79: 1556702 | E79: 1578284.8 | F79: 1602662.7 | G79: 1633961.6 | H79: 1665952 | I79: 1698353.8 | J79: 1731206.8 | K79: 1764637.9 | L79: 1799206.6 | M79: 1834513.3 | N79: 1870936.3 | O79: 1908542.4 | P79: 1947250.2 | Q79: 1986923.1 | R79: 2025740.8 | S79: 2064839.4 | T79: 2104268.3 | U79: 2144086.9 | V79: 2184100 | W79: 2223125 | X79: 2262365.5 | Y79: 2301980.8 | Z79: 2342111.7 | AA79: 2382094 | AB79: 2415004.7 | AC79: 2446483.3 | AD79: 2477057.2 | AE79: 2507154.1 | AF79: 2537142.2 | AG79: 2572095.7 | AH79: 2608804.2 | AI79: 2647164.4 | AJ79: 2687084.5 | AK79: 2728453.9

Sheet INV
A1: _date_ | B1: 42005 | C1: 42370 | D1: 42736 | E1: 43101 | F1: 43466 | G1: 43831 | H1: 44197 | I1: 44562 | J1: 44927 | K1: 45292 | L1: 45658 | M1: 46023 | N1: 46388 | O1: 46753 | P1: 47119 | Q1: 47484 | R1: 47849 | S1: 48214 | T1: 48580 | U1: 48945 | V1: 49310 | W1: 49675 | X1: 50041 | Y1: 50406 | Z1: 50771 | AA1: 51136 | AB1: 51502 | AC1: 51867 | AD1: 52232 | AE1: 52597 | AF1: 52963 | AG1: 53328 | AH1: 53693 | AI1: 54058 | AJ1: 54424 | AK1: 54789
A2: ia_2 | B2: 472314.87 | C2: 479871.09 | D2: 486702.88 | E2: 492260 | F2: 499350.91 | G2: 510977.27 | H2: 522802.91 | I2: 534301.66 | J2: 545248.3 | K2: 555539.4 | L2: 565282.88 | M2: 575753.12 | N2: 587365.75 | O2: 600234.91 | P2: 614263.44 | Q2: 629290.16 | R2: 644763.06 | S2: 660471.38 | T2: 676325.5 | U2: 692347.94 | V2: 708566.24 | W2: 724786.81 | X2: 741270.27 | Y2: 758165.54 | Z2: 775545.77 | AA2: 793292.47 | AB2: 811052.36 | AC2: 828956.26 | AD2: 847098.44 | AE2: 865542.12 | AF2: 884331.29 | AG2: 903410.34 | AH2: 922836.42 | AI2: 942635.55 | AJ2: 962808.73 | AK2: 983347.88
A3: ia_0 | B3: 472314.87 | C3: 479871.09 | D3: 486702.88 | E3: 492260 | F3: 499350.91 | G3: 510977.27 | H3: 523078.82 | I3: 535769.24 | J3: 548767.17 | K3: 561897.4 | L3: 575219.24 | M3: 588792.09 | N3: 602829.34 | O3: 617505.52 | P3: 632904.97 | Q3: 649044.39 | R3: 665477.81 | S3: 682354.39 | T3: 699756.72 | U3: 717723.56 | V3: 736219.16 | W3: 754863.42 | X3: 773835.42 | Y3: 793230.87 | Z3: 813090.38 | AA3: 833256.96 | AB3: 851682.27 | AC3: 869137.54 | AD3: 886035.33 | AE3: 902560.86 | AF3: 918791.08 | AG3: 936050.65 | AH3: 953844.09 | AI3: 971886.7 | AJ3: 990034.32 | AK3: 1008209.7
A4: ia_sagr_2 | B4: 4270.4593 | C4: 4330.8301 | D4: 4383.6749 | E4: 4428.5978 | F4: 4487.5035 | G4: 4587.7752 | H4: 4692.6891 | I4: 4800.5767 | J4: 4910.2136 | K4: 5021.8706 | L4: 5137.9481 | M4: 5260.1405 | N4: 5391.5337 | O4: 5533.8629 | P4: 5686.3128 | Q4: 5847.0255 | R4: 6010.3767 | S4: 6174.0487 | T4: 6336.4203 | U4: 6496.9702 | V4: 6655.2318 | W4: 6807.4526 | X4: 6956.5743 | Y4: 7104.3633 | Z4: 7251.7184 | AA4: 7397.0739 | AB4: 7536.3624 | AC4: 7672.0744 | AD4: 7805.9858 | AE4: 7939.3017 | AF4: 8072.8939 | AG4: 8205.8625 | AH4: 8339.36 | AI4: 8474.1607 | AJ4: 8610.6606 | AK4: 8749.0633
A5: ia_sagr_0 | B5: 4270.4593 | C5: 4330.8301 | D5: 4383.6749 | E5: 4428.5978 | F5: 4487.5035 | G5: 4587.7752 | H5: 4695.4756 | I5: 4810.6383 | J5: 4929.9329 | K5: 5051.9811 | L5: 5177.8594 | M5: 5307.5263 | N5: 5442.4442 | O5: 5583.5943 | P5: 5731.1355 | Q5: 5884.6974 | R5: 6038.5853 | S5: 6194.2449 | T5: 6352.2752 | U5: 6512.8646 | V5: 6675.3955 | W5: 6835.5473 | X5: 6995.5026 | Y5: 7156.3676 | Z5: 7318.7212 | AA5: 7480.8083 | AB5: 7619.4546 | AC5: 7744.5188 | AD5: 7861.0288 | AE5: 7971.5732 | AF5: 8077.8708 | AG5: 8196.481 | AH5: 8322.6611 | AI5: 8454.4251 | AJ5: 8591.1362 | AK5: 8732.5262
A6: ia_sfor_2 | B6: 166.62067 | C6: 166.2989 | D6: 164.52261 | E6: 161.72065 | F6: 159.76047 | G6: 159.51405 | H6: 159.09276 | I6: 157.8516 | J6: 155.66435 | K6: 152.5237 | L6: 148.48879 | M6: 145.62209 | N6: 143.79127 | O6: 142.6541 | P6: 141.9538 | Q6: 141.53416 | R6: 141.13019 | S6: 140.69552 | T6: 140.23123 | U6: 139.75409 | V6: 139.25556 | W6: 138.86153 | X6: 138.59453 | Y6: 138.43672 | Z6: 138.36725 | AA6: 138.29937 | AB6: 138.29037 | AC6: 138.36521 | AD6: 138.51817 | AE6: 138.7375 | AF6: 139.01276 | AG6: 139.37127 | AH6: 139.80787 | AI6: 140.30911 | AJ6: 140.86227 | AK6: 141.45746
A7: ia_sfor_0 | B7: 166.62067 | C7: 166.2989 | D7: 164.52261 | E7: 161.72065 | F7: 159.76047 | G7: 159.51405 | H7: 159.14194 | I7: 158.93166 | J7: 158.78007 | K7: 158.63743 | L7: 158.54859 | M7: 158.47989 | N7: 158.46403 | O7: 158.53076 | P7: 158.69299 | Q7: 158.9527 | R7: 159.24102 | S7: 159.59583 | T7: 160.03379 | U7: 160.55988 | V7: 161.14289 | W7: 161.75307 | X7: 162.43054 | Y7: 163.18741 | Z7: 164.02439 | AA7: 164.85172 | AB7: 165.41878 | AC7: 165.91487 | AD7: 166.41884 | AE7: 166.95454 | AF7: 167.52476 | AG7: 168.31268 | AH7: 169.20493 | AI7: 170.14843 | AJ7: 171.12361 | AK7: 172.12493
A8: ia_sfoo_2 | B8: 6740.0951 | C8: 6838.2707 | D8: 6920.6216 | E8: 6991.6549 | F8: 7091.3934 | G8: 7259.6231 | H8: 7429.9374 | I8: 7599.5527 | J8: 7767.0391 | K8: 7933.3694 | L8: 8103.8436 | M8: 8284.7765 | N8: 8481.3954 | O8: 8696.3129 | P8: 8927.8888 | Q8: 9172.9515 | R8: 9423.3292 | S8: 9675.042 | T8: 9925.8105 | U8: 10175.252 | V8: 10422.774 | W8: 10664.333 | X8: 10903.49 | Y8: 11142.291 | Z8: 11381.717 | AA8: 11618.498 | AB8: 11847.587 | AC8: 12071.35 | AD8: 12291.803 | AE8: 12510.58 | AF8: 12729.008 | AG8: 12946.093 | AH8: 13163.206 | AI8: 13381.361 | AJ8: 13601.141 | AK8: 13822.924
A9: ia_sfoo_0 | B9: 6740.0951 | C9: 6838.2707 | D9: 6920.6216 | E9: 6991.6549 | F9: 7091.3934 | G9: 7259.6231 | H9: 7434.0805 | I9: 7617.5444 | J9: 7805.1162 | K9: 7994.3856 | L9: 8187.3405 | M9: 8384.4225 | N9: 8588.8488 | O9: 8802.9033 | P9: 9027.1801 | Q9: 9261.1616 | R9: 9497.443 | S9: 9737.4467 | T9: 9981.6115 | U9: 10229.98 | V9: 10481.214 | W9: 10730.139 | X9: 10979.216 | Y9: 11229.558 | Z9: 11481.721 | AA9: 11732.098 | AB9: 11951.783 | AC9: 12152.081 | AD9: 12338.499 | AE9: 12514.141 | AF9: 12681.333 | AG9: 12861.443 | AH9: 13049.499 | AI9: 13243.787 | AJ9: 13443.916 | AK9: 13649.766
A10: ia_sveh_2 | B10: 36308.075 | C10: 37167.291 | D10: 38078.631 | E10: 38872.286 | F10: 39808.035 | G10: 41128.351 | H10: 42358.134 | I10: 43523.196 | J10: 44661.856 | K10: 45791.561 | L10: 46905.288 | M10: 48104.879 | N10: 49401.482 | O10: 50763.042 | P10: 52162.409 | Q10: 53586.359 | R10: 54957.511 | S10: 56291.107 | T10: 57600.2 | U10: 58902.412 | V10: 60211.159 | W10: 61457.754 | X10: 62706.18 | Y10: 63978.956 | Z10: 65283.77 | AA10: 66615.438 | AB10: 67893.782 | AC10: 69180.81 | AD10: 70500.053 | AE10: 71859.932 | AF10: 73263.164 | AG10: 74688.246 | AH10: 76152.938 | AI10: 77661.114 | AJ10: 79211.884 | AK10: 80802.979
A11: ia_sveh_0 | B11: 36308.075 | C11: 37167.291 | D11: 38078.631 | E11: 38872.286 | F11: 39808.035 | G11: 41128.351 | H11: 42401.89 | I11: 43658.78 | J11: 44922.306 | K11: 46214.291 | L11: 47555.291 | M11: 48941.673 | N11: 50382.043 | O11: 51877.568 | P11: 53425.997 | Q11: 55024.797 | R11: 56570.155 | S11: 58119.582 | T11: 59697.807 | U11: 61315.732 | V11: 62976.297 | W11: 64586.177 | X11: 66205.868 | Y11: 67861.462 | Z11: 69564.205 | AA11: 71310.622 | AB11: 72623.281 | AC11: 73786.866 | AD11: 74917.604 | AE11: 76058.569 | AF11: 77224.82 | AG11: 78723.067 | AH11: 80372.901 | AI11: 82098.658 | AJ11: 83869.588 | AK11: 85672.216
A12: ia_sgla_2 | B12: 1452.8806 | C12: 1471.6351 | D12: 1487.4087 | E12: 1499.415 | F12: 1516.429 | G12: 1547.4792 | H12: 1580.9075 | I12: 1613.7252 | J12: 1643.7617 | K12: 1669.5141 | L12: 1690.0644 | M12: 1711.9222 | N12: 1737.446 | O12: 1767.5787 | P12: 1802.2163 | Q12: 1840.8031 | R12: 1881.1636 | S12: 1922.4811 | T12: 1964.2233 | U12: 2006.2034 | V12: 2048.3594 | W12: 2090.2375 | X12: 2132.8022 | Y12: 2176.5863 | Z12: 2221.8141 | AA12: 2268.2224 | AB12: 2314.8703 | AC12: 2362.3332 | AD12: 2410.9149 | AE12: 2460.7318 | AF12: 2511.8099 | AG12: 2564.076 | AH12: 2617.7266 | AI12: 2672.7937 | AJ12: 2729.1928 | AK12: 2786.789
... A79: ia_ser_0 | B79: 219326.95 | C79: 222776.04 | D79: 225733.7 | E79: 228123.11 | F79: 231355.93 | G79: 236750.84 | H79: 242139.37 | I79: 247683.05 | J79: 253264.01 | K79: 258813.16 | L79: 264385.29 | M79: 270024.31 | N79: 275839.92 | O79: 281911.2 | P79: 288263.97 | Q79: 294889.5 | R79: 301601.67 | S79: 308441.41 | T79: 315432.76 | U79: 322584.45 | V79: 329868.03 | W79: 337145.1 | X79: 344479.32 | Y79: 351906.79 | Z79: 359442.83 | AA79: 366999.08 | AB79: 373815.22 | AC79: 380173.12 | AD79: 386245.58 | AE79: 392120.77 | AF79: 397847.52 | AG79: 403951.48 | AH79: 410282.19 | AI79: 416751.27 | AJ79: 423322.52 | AK79: 429982.3

Sheet Labor
A1: _date_ | B1: 42005 | C1: 42370 | D1: 42736 | E1: 43101 | F1: 43466 | G1: 43831 | H1: 44197 | I1: 44562 | J1: 44927 | K1: 45292 | L1: 45658 | M1: 46023 | N1: 46388 | O1: 46753 | P1: 47119 | Q1: 47484 | R1: 47849 | S1: 48214 | T1: 48580 | U1: 48945 | V1: 49310 | W1: 49675 | X1: 50041 | Y1: 50406 | Z1: 50771 | AA1: 51136 | AB1: 51502 | AC1: 51867 | AD1: 52232 | AE1: 52597 | AF1: 52963 | AG1: 53328 | AH1: 53693 | AI1: 54058 | AJ1: 54424 | AK1: 54789
A2: f_l_2 | B2: 27381.51 | C2: 27465.389 | D2: 27580.01 | E2: 27720.465 | F2: 27867.824 | G2: 28027.303 | H2: 28217.549 | I2: 28446.768 | J2: 28718.422 | K2: 29039.262 | L2: 29420.939 | M2: 29794.299 | N2: 30143.708 | O2: 30468.662 | P2: 30770.732 | Q2: 31050.989 | R2: 31305.559 | S2: 31538.006 | T2: 31750.355 | U2: 31944.143 | V2: 32118.932 | W2: 32257.232 | X2: 32364.64 | Y2: 32448.184 | Z2: 32513.95 | AA2: 32561.224 | AB2: 32579.008 | AC2: 32575.253 | AD2: 32557.93 | AE2: 32533.448 | AF2: 32506.475 | AG2: 32473.916 | AH2: 32438.765 | AI2: 32403.614 | AJ2: 32370.009 | AK2: 32338.557
A3: f_l_0 | B3: 27381.51 | C3: 27465.389 | D3: 27580.01 | E3: 27720.465 | F3: 27867.824 | G3: 28027.303 | H3: 28224.888 | I3: 28444.453 | J3: 28677.205 | K3: 28920.387 | L3: 29176.547 | M3: 29440.869 | N3: 29710.958 | O3: 29984.31 | P3: 30258.246 | Q3: 30530.159 | R3: 30781.493 | S3: 31013.27 | T3: 31227.711 | U3: 31427.292 | V3: 31612.496 | W3: 31772.776 | X3: 31913.694 | Y3: 32040.618 | Z3: 32158.017 | AA3: 32264.036 | AB3: 32298.817 | AC3: 32277.92 | AD3: 32217.857 | AE3: 32132.244 | AF3: 32031.596 | AG3: 31960.675 | AH3: 31917.623 | AI3: 31897.579 | AJ3: 31895.324 | AK3: 31905.871
A4: f_l_sagr_2 | B4: 732.62892 | C4: 734.00589 | D4: 737.2098 | E4: 743.67626 | F4: 750.35827 | G4: 753.92488 | H4: 758.8562 | I4: 766.1684 | J4: 776.29207 | K4: 789.71104 | L4: 807.24914 | M4: 824.12282 | N4: 839.04175 | O4: 851.98705 | P4: 863.23811 | Q4: 873.07253 | R4: 881.74976 | S4: 889.80339 | T4: 897.53265 | U4: 905.05307 | V4: 912.30697 | W4: 918.26991 | X4: 923.07507 | Y4: 926.97969 | Z4: 930.23224 | AA4: 932.81827 | AB4: 934.16133 | AC4: 934.60204 | AD4: 934.50505 | AE4: 934.17377 | AF4: 933.83417 | AG4: 933.28729 | AH4: 932.66503 | AI4: 932.10523 | AJ4: 931.70557 | AK4: 931.52029
A5: f_l_sagr_0 | B5: 732.62892 | C5: 734.00589 | D5: 737.2098 | E5: 743.67626 | F5: 750.35827 | G5: 753.92488 | H5: 759.15299 | I5: 765.50746 | J5: 772.69013 | K5: 780.55174 | L5: 789.1285 | M5: 798.16669 | N5: 807.51928 | O5: 817.03898 | P5: 826.57972 | Q5: 836.01088 | R5: 844.58053 | S5: 852.35922 | T5: 859.44043 | U5: 865.92321 | V5: 871.83113 | W5: 876.75392 | X5: 880.95028 | Y5: 884.6416 | Z5: 888.00736 | AA5: 890.98158 | AB5: 891.21773 | AC5: 889.48122 | AD5: 886.44394 | AE5: 882.63253 | AF5: 878.45356 | AG5: 875.66621 | AH5: 874.12328 | AI5: 873.63512 | AJ5: 874.01367 | AK5: 875.07457
A6: f_l_sfor_2 | B6: 29.064581 | C6: 28.723328 | D6: 28.235224 | E6: 27.712843 | F6: 27.234662 | G6: 26.762668 | H6: 26.36918 | I6: 25.964723 | J6: 25.521406 | K6: 25.034416 | L6: 24.512941 | M6: 24.095327 | N6: 23.778339 | O6: 23.526512 | P6: 23.307449 | Q6: 23.099508 | R6: 22.878601 | S6: 22.646226 | T6: 22.407161 | U6: 22.165 | V6: 21.918203 | W6: 21.670933 | X6: 21.426949 | Y6: 21.186104 | Z6: 20.947545 | AA6: 20.70171 | AB6: 20.451141 | AC6: 20.202333 | AD6: 19.957977 | AE6: 19.718981 | AF6: 19.485532 | AG6: 19.257823 | AH6: 19.036457 | AI6: 18.821044 | AJ6: 18.61092 | AK6: 18.405419
A7: f_l_sfor_0 | B7: 29.064581 | C7: 28.723328 | D7: 28.235224 | E7: 27.712843 | F7: 27.234662 | G7: 26.762668 | H7: 26.372982 | I7: 26.045604 | J7: 25.764529 | K7: 25.518383 | L7: 25.305309 | M7: 25.110022 | N7: 24.924628 | O7: 24.744388 | P7: 24.566568 | Q7: 24.389753 | R7: 24.203747 | S7: 24.01184 | T7: 23.81674 | U7: 23.620462 | V7: 23.420637 | W7: 23.21406 | X7: 23.005952 | Y7: 22.79943 | Z7: 22.596315 | AA7: 22.387842 | AB7: 22.14325 | AC7: 21.880599 | AD7: 21.612215 | AE7: 21.345272 | AF7: 21.083577 | AG7: 20.85029 | AH7: 20.637558 | AI7: 20.43905 | AJ7: 20.250378 | AK7: 20.068571
A8: f_l_sfoo_2 | B8: 618.70869 | C8: 621.19603 | D8: 624.60767 | E8: 628.80673 | F8: 633.06844 | G8: 637.76331 | H8: 643.44117 | I8: 650.43053 | J8: 658.93438 | K8: 669.27873 | L8: 682.04363 | M8: 694.48177 | N8: 706.08076 | O8: 716.89019 | P8: 726.99366 | Q8: 736.42702 | R8: 745.13183 | S8: 753.16915 | T8: 760.547 | U8: 767.28335 | V8: 773.34253 | W8: 778.17283 | X8: 781.94951 | Y8: 784.89427 | Z8: 787.2074 | AA8: 788.83933 | AB8: 789.47329 | AC8: 789.35674 | AD8: 788.74486 | AE8: 787.85667 | AF8: 786.86181 | AG8: 785.66193 | AH8: 784.36454 | AI8: 783.06824 | AJ8: 781.83934 | AK8: 780.71394
A9: f_l_sfoo_0 | B9: 618.70869 | C9: 621.19603 | D9: 624.60767 | E9: 628.80673 | F9: 633.06844 | G9: 637.76331 | H9: 643.66432 | I9: 650.18353 | J9: 657.01668 | K9: 664.03774 | L9: 671.33804 | M9: 678.78392 | N9: 686.35984 | O9: 694.03827 | P9: 701.75846 | Q9: 709.43901 | R9: 716.54875 | S9: 723.09762 | T9: 729.11693 | U9: 734.65523 | V9: 739.69603 | W9: 743.97217 | X9: 747.64573 | Y9: 750.85794 | Z9: 753.73199 | AA9: 756.16651 | AB9: 756.56351 | AC9: 755.38204 | AD9: 753.04365 | AE9: 749.91937 | AF9: 746.32624 | AG9: 743.54153 | AH9: 741.56061 | AI9: 740.32457 | AJ9: 739.73988 | AK9: 739.6916
A10: f_l_sveh_2 | B10: 185.75766 | C10: 187.53451 | D10: 190.19143 | E10: 193.12096 | F10: 196.10324 | G10: 198.92313 | H10: 201.34032 | I10: 203.85436 | J10: 206.81545 | K10: 210.429 | L10: 214.70576 | M10: 219.05691 | N10: 223.13918 | O10: 226.72011 | P10: 229.72162 | Q10: 232.17811 | R10: 233.98978 | S10: 235.35805 | T10: 236.42881 | U10: 237.30368 | V10: 238.03471 | W10: 238.30664 | X10: 238.28272 | Y10: 238.06688 | Z10: 237.73018 | AA10: 237.30322 | AB10: 236.55728 | AC10: 235.70466 | AD10: 234.87256 | AE10: 234.12881 | AF10: 233.50348 | AG10: 232.91946 | AH10: 232.41988 | AI10: 232.02264 | AJ10: 231.72989 | AK10: 231.53303
A11: f_l_sveh_0 | B11: 185.75766 | C11: 187.53451 | D11: 190.19143 | E11: 193.12096 | F11: 196.10324 | G11: 198.92313 | H11: 201.47925 | I11: 203.86623 | J11: 206.26316 | K11: 208.86286 | L11: 211.78545 | M11: 214.95971 | N11: 218.28981 | O11: 221.65619 | P11: 224.96588 | Q11: 228.16631 | R11: 230.86507 | S11: 233.21266 | T11: 235.3178 | U11: 237.25959 | V11: 239.08991 | W11: 240.53378 | X11: 241.77086 | Y11: 242.92213 | Z11: 244.06837 | AA11: 245.24541 | AB11: 245.0567 | AC11: 244.17646 | AD11: 243.03306 | AE11: 241.87788 | AF11: 240.84795 | AG11: 240.83379 | AH11: 241.48862 | AI11: 242.57763 | AJ11: 243.94342 | AK11: 245.47914
A12: f_l_sgla_2 | B12: 98.04239 | C12: 98.601283 | D12: 99.434171 | E12: 100.31974 | F12: 101.04859 | G12: 101.66138 | H12: 102.44468 | I12: 103.47862 | J12: 104.75871 | K12: 106.27557 | L12: 108.03635 | M12: 109.65695 | N12: 111.08435 | O12: 112.3646 | P12: 113.5511 | Q12: 114.67906 | R12: 115.7474 | S12: 116.77552 | T12: 117.76583 | U12: 118.71674 | V12: 119.6234 | W12: 120.3912 | X12: 121.05214 | Y12: 121.64605 | Z12: 122.20607 | AA12: 122.7405 | AB12: 123.18625 | AC12: 123.57982 | AD12: 123.95505 | AE12: 124.33608 | AF12: 124.73783 | AG12: 125.13813 | AH12: 125.54818 | AI12: 125.97724 | AJ12: 126.42894 | AK12: 126.90197
... A79: f_l_ser_0 | B79: 21276.459 | C79: 21340.259 | D79: 21421.835 | E79: 21517.255 | F79: 21620.401 | G79: 21745.056 | H79: 21895.502 | I79: 22058.767 | J79: 22228.169 | K79: 22401.873 | L79: 22582.48 | M79: 22767.22 | N79: 22955.155 | O79: 23145.077 | P79: 23335.269 | Q79: 23523.769 | R79: 23697.735 | S79: 23857.21 | T79: 24003.399 | U79: 24137.858 | V79: 24260.659 | W79: 24364.956 | X79: 24454.353 | Y79: 24532.541 | Z79: 24602.682 | AA79: 24663.035 | AB79: 24673.634 | AC79: 24643.988 | AD79: 24585.355 | AE79: 24507.421 | AF79: 24417.905 | AG79: 24347.694 | AH79: 24296.846 | AI79: 24262.627 | AJ79: 24241.741 | AK79: 24230.879

Sheet Final_nrj
A1: _date_ | B1: 42005 | C1: 42370 | D1: 42736 | E1: 43101 | F1: 43466 | G1: 43831 | H1: 44197 | I1: 44562 | J1: 44927 | K1: 45292 | L1: 45658 | M1: 46023 | N1: 46388 | O1: 46753 | P1: 47119 | Q1: 47484 | R1: 47849 | S1: 48214 | T1: 48580 | U1: 48945 | V1: 49310 | W1: 49675 | X1: 50041 | Y1: 50406 | Z1: 50771 | AA1: 51136 | AB1: 51502 | AC1: 51867 | AD1: 52232 | AE1: 52597 | AF1: 52963 | AG1: 53328 | AH1: 53693 | AI1: 54058 | AJ1: 54424 | AK1: 54789
A2: cf_toe_2 | B2: 161.84505 | C2: 162.95379 | D2: 162.62881 | E2: 161.54877 | F2: 161.96656 | G2: 164.97584 | H2: 167.12991 | I2: 169.00261 | J2: 170.50167 | K2: 171.60925 | L2: 172.30139 | M2: 173.77516 | N2: 175.99845 | O2: 178.79389 | P2: 181.98708 | Q2: 185.44732 | R2: 188.86079 | S2: 192.11103 | T2: 195.11136 | U2: 197.85913 | V2: 200.36675 | W2: 202.70582 | X2: 205.00867 | Y2: 207.29591 | Z2: 209.5695 | AA2: 211.7519 | AB2: 213.84712 | AC2: 215.95937 | AD2: 218.09612 | AE2: 220.25321 | AF2: 222.42675 | AG2: 224.62881 | AH2: 226.88521 | AI2: 229.18671 | AJ2: 231.52038 | AK2: 233.87507
A3: ch_toe_2 | B3: 64.30144 | C3: 64.083292 | D3: 63.135616 | E3: 62.111064 | F3: 61.746494 | G3: 61.977296 | H3: 61.751815 | I3: 61.556194 | J3: 61.316779 | K3: 61.025178 | L3: 60.694614 | M3: 60.673823 | N3: 60.834924 | O3: 61.097784 | P3: 61.411892 | Q3: 61.747284 | R3: 62.057694 | S3: 62.321034 | T3: 62.523447 | U3: 62.670166 | V3: 62.757531 | W3: 62.863178 | X3: 62.970457 | Y3: 63.070152 | Z3: 63.157717 | AA3: 63.185145 | AB3: 63.223378 | AC3: 63.259103 | AD3: 63.284297 | AE3: 63.29544 | AF3: 63.291794 | AG3: 63.288744 | AH3: 63.280654 | AI3: 63.26412 | AJ3: 63.237704 | AK3: 63.201233
A4: ch_hous_toe_2 | B4: 42520877 | C4: 42532730 | D4: 41744021 | E4: 40871896 | F4: 40526972 | G4: 40532332 | H4: 40141800 | I4: 39784556 | J4: 39376437 | K4: 38905495 | L4: 38384187 | M4: 38115483 | N4: 37977480 | O4: 37908649 | P4: 37872170 | Q4: 37846551 | R4: 37799876 | S4: 37726075 | T4: 37616042 | U4: 37472543 | V4: 37289527 | W4: 37133835 | X4: 36989657 | Y4: 36848899 | Z4: 36707355 | AA4: 36522061 | AB4: 36357934 | AC4: 36204780 | AD4: 36055193 | AE4: 35904744 | AF4: 35751350 | AG4: 35606336 | AH4: 35464594 | AI4: 35322840 | AJ4: 35179238 | AK4: 35032955
A5: ch_auto_toe_2 | B5: 21780563 | C5: 21550561 | D5: 21391595 | E5: 21239168 | F5: 21219522 | G5: 21444963 | H5: 21610014 | I5: 21771638 | J5: 21940341 | K5: 22119684 | L5: 22310427 | M5: 22558340 | N5: 22857444 | O5: 23189135 | P5: 23539723 | Q5: 23900733 | R5: 24257818 | S5: 24594959 | T5: 24907405 | U5: 25197623 | V5: 25468004 | W5: 25729343 | X5: 25980800 | Y5: 26221253 | Z5: 26450362 | AA5: 26663084 | AB5: 26865445 | AC5: 27054323 | AD5: 27229104 | AE5: 27390697 | AF5: 27540444 | AG5: 27682408 | AH5: 27816060 | AI5: 27941281 | AJ5: 28058466 | AK5: 28168278
A6: cf_toe_0 | B6: 161.84505 | C6: 162.95379 | D6: 162.62881 | E6: 161.54877 | F6: 161.96656 | G6: 164.97584 | H6: 167.20937 | I6: 169.681 | J6: 172.23948 | K6: 174.84469 | L6: 177.5408 | M6: 180.27588 | N6: 183.09499 | O6: 186.02123 | P6: 189.06049 | Q6: 192.20828 | R6: 195.28497 | S6: 198.40264 | T6: 201.57922 | U6: 204.81768 | V6: 208.08999 | W6: 211.27311 | X6: 214.48022 | Y6: 217.73385 | Z6: 221.04154 | AA6: 224.32536 | AB6: 226.87812 | AC6: 229.26013 | AD6: 231.58118 | AE6: 233.87258 | AF6: 236.14909 | AG6: 238.90794 | AH6: 241.81435 | AI6: 244.80983 | AJ6: 247.88396 | AK6: 251.03484
A7: ch_toe_0 | B7: 64.30144 | C7: 64.083292 | D7: 63.135616 | E7: 62.111064 | F7: 61.746494 | G7: 61.977296 | H7: 61.752503 | I7: 61.723966 | J7: 61.770071 | K7: 61.846903 | L7: 61.963605 | M7: 62.074303 | N7: 62.187984 | O7: 62.310539 | P7: 62.444561 | Q7: 62.589977 | R7: 62.743773 | S7: 62.902829 | T7: 63.064638 | U7: 63.227324 | V7: 63.371744 | W7: 63.523147 | X7: 63.67465 | Y7: 63.822868 | Z7: 63.966323 | AA7: 64.055883 | AB7: 64.137587 | AC7: 64.20494 | AD7: 64.254218 | AE7: 64.284775 | AF7: 64.296964 | AG7: 64.297564 | AH7: 64.293162 | AI7: 64.288822 | AJ7: 64.288135 | AK7: 64.293482
A8: ch_hous_toe_0 | B8: 42520877 | C8: 42532730 | D8: 41744021 | E8: 40871896 | F8: 40526972 | G8: 40532332 | H8: 40139858 | I8: 39936621 | J8: 39801571 | K8: 39693679 | L8: 39619325 | M8: 39533014 | N8: 39439679 | O8: 39343362 | P8: 39247298 | Q8: 39153398 | R8: 39063027 | S8: 38975733 | T8: 38890782 | U8: 38807608 | V8: 38709821 | W8: 38623054 | X8: 38541910 | Y8: 38463565 | Z8: 38386693 | AA8: 38267057 | AB8: 38155822 | AC8: 38049581 | AD8: 37944736 | AE8: 37839320 | AF8: 37731617 | AG8: 37620040 | AH8: 37506579 | AI8: 37393334 | AJ8: 37281859 | AK8: 37173191
A9: ch_auto_toe_0 | B9: 21780563 | C9: 21550561 | D9: 21391595 | E9: 21239168 | F9: 21219522 | G9: 21444963 | H9: 21612645 | I9: 21787345 | J9: 21968501 | K9: 22153224 | L9: 22344281 | M9: 22541289 | N9: 22748306 | O9: 22967177 | P9: 23197263 | Q9: 23436580 | R9: 23680746 | S9: 23927096 | T9: 24173855 | U9: 24419716 | V9: 24661923 | W9: 24900093 | X9: 25132740 | Y9: 25359303 | Z9: 25579630 | AA9: 25788825 | AB9: 25981765 | AC9: 26155359 | AD9: 26309482 | AE9: 26445455 | AF9: 26565347 | AG9: 26677524 | AH9: 26786582 | AI9: 26895488 | AJ9: 27006276 | AK9: 27120291
A10: cf_toe_ccoa_2 | B10: 5.4367312 | C10: 5.3017006 | D10: 5.1777124 | E10: 5.1244816 | F10: 5.122354 | G10: 5.2040608 | H10: 5.3045804 | I10: 5.3907029 | J10: 5.4537245 | K10: 5.4896601 | L10: 5.4934554 | M10: 5.5270412 | N10: 5.5934305 | O10: 5.6863248 | P10: 5.7986444 | Q10: 5.924607 | R10: 6.048363 | S10: 6.1698231 | T10: 6.2872175 | U10: 6.3999182 | V10: 6.5079111 | W10: 6.6090901 | X10: 6.7119836 | Y10: 6.8177709 | Z10: 6.9260951 | AA10: 7.0354633 | AB10: 7.1408756 | AC10: 7.2493553 | AD10: 7.3613509 | AE10: 7.4763034 | AF10: 7.5935915 | AG10: 7.7130834 | AH10: 7.8362333 | AI10: 7.962377 | AJ10: 8.0906733 | AK10: 8.2203603
A11: cf_toe_ccoa_0 | B11: 5.4367312 | C11: 5.3017006 | D11: 5.1777124 | E11: 5.1244816 | F11: 5.122354 | G11: 5.2040608 | H11: 5.3094371 | I11: 5.4287658 | J11: 5.5555689 | K11: 5.6889465 | L11: 5.8292938 | M11: 5.974949 | N11: 6.1264739 | O11: 6.2838342 | P11: 6.4469057 | Q11: 6.6155306 | R11: 6.7779193 | S11: 6.9425493 | T11: 7.1110914 | U11: 7.2839885 | V11: 7.461136 | W11: 7.6318982 | X11: 7.8049075 | Y11: 7.9820947 | Z11: 8.1640871 | AA11: 8.3501632 | AB11: 8.4878042 | AC11: 8.6174914 | AD11: 8.7473307 | AE11: 8.879104 | AF11: 9.0132107 | AG11: 9.1825696 | AH11: 9.3621197 | AI11: 9.5467559 | AJ11: 9.7352508 | AK11: 9.9272173
A12: cf_toe_ccoi_2 | B12: 0.084440286 | C12: 0.086426543 | D12: 0.086994394 | E12: 0.08621459 | F12: 0.086605563 | G12: 0.090276061 | H12: 0.092283988 | I12: 0.094084795 | J12: 0.095660768 | K12: 0.096968175 | L12: 0.097904391 | M12: 0.099555103 | N12: 0.10189105 | O12: 0.10476056 | P12: 0.10803234 | Q12: 0.11161783 | R12: 0.11519645 | S12: 0.11852192 | T12: 0.12148523 | U12: 0.12410832 | V12: 0.12644255 | W12: 0.12857386 | X12: 0.13063001 | Y12: 0.13263583 | Z12: 0.13460042 | AA12: 0.13649919 | AB12: 0.13831192 | AC12: 0.14013865 | AD12: 0.14198824 | AE12: 0.14385714 | AF12: 0.14574085 | AG12: 0.14766072 | AH12: 0.14963647 | AI12: 0.15165697 | AJ12: 0.15370805 | AK12: 0.15577744
... A737: ci_toe_cfuel_ser_0 | B737: 2.8654882 | C737: 2.8967075 | D737: 2.9278608 | E737: 2.9597623 | F737: 2.9926616 | G737: 3.0265472 | H737: 3.0613249 | I737: 3.0968928 | J737: 3.1331649 | K737: 3.170076 | L737: 3.2075792 | M737: 3.2456425 | N737: 3.2842451 | O737: 3.3233755 | P737: 3.363028 | Q737: 3.4032016 | R737: 3.443898 | S737: 3.4851202 | T737: 3.5268716 | U737: 3.5691552 | V737: 3.6119734 | W737: 3.6553275 | X737: 3.6992182 | Y737: 3.7436452 | Z737: 3.7886078 | AA737: 3.8341054 | AB737: 3.8801368 | AC737: 3.9267016 | AD737: 3.9737996 | AE737: 4.021431 | AF737: 4.0695968 | AG737: 4.1182989 | AH737: 4.1675396 | AI737: 4.2173221 | AJ737: 4.2676504 | AK737: 4.3185291

Sheet Primary_nrj
A1: _date_ | B1: 42005 | C1: 42370 | D1: 42736 | E1: 43101 | F1: 43466 | G1: 43831 | H1: 44197 | I1: 44562 | J1: 44927 | K1: 45292 | L1: 45658 | M1: 46023 | N1: 46388 | O1: 46753 | P1: 47119 | Q1: 47484 | R1: 47849 | S1: 48214 | T1: 48580 | U1: 48945 | V1: 49310 | W1: 49675 | X1: 50041 | Y1: 50406 | Z1: 50771 | AA1: 51136 | AB1: 51502 | AC1: 51867 | AD1: 52232 | AE1: 52597 | AF1: 52963 | AG1: 53328 | AH1: 53693 | AI1: 54058 | AJ1: 54424 | AK1: 54789
A2: yg_toe_2 | B2: 148.42298 | C2: 149.34263 | D2: 149.86338 | E2: 150.06133 | F2: 150.55254 | G2: 151.96832 | H2: 153.97508 | I2: 155.85072 | J2: 157.52883 | K2: 158.97701 | L2: 160.15957 | M2: 161.52781 | N2: 163.25159 | O2: 165.28143 | P2: 167.49278 | Q2: 169.74275 | R2: 171.75577 | S2: 173.6969 | T2: 175.62105 | U2: 177.50557 | V2: 179.30942 | W2: 180.9808 | X2: 182.6919 | Y2: 184.46622 | Z2: 186.2972 | AA2: 188.10929 | AB2: 189.8442 | AC2: 191.62958 | AD2: 193.47092 | AE2: 195.36336 | AF2: 197.30185 | AG2: 199.26711 | AH2: 201.29977 | AI2: 203.39562 | AJ2: 205.54524 | AK2: 207.73947
A3: yg_toe_0 | B3: 148.42298 | C3: 149.34263 | D3: 149.86338 | E3: 150.06133 | F3: 150.55254 | G3: 151.96832 | H3: 154.04776 | I3: 156.22183 | J3: 158.45369 | K3: 160.72287 | L3: 163.06728 | M3: 165.43685 | N3: 167.86516 | O3: 170.36808 | P3: 172.95096 | Q3: 175.61229 | R3: 178.18572 | S3: 180.79316 | T3: 183.4493 | U3: 186.15852 | V3: 188.89977 | W3: 191.55372 | X3: 194.24123 | Y3: 196.97978 | Z3: 199.77643 | AA3: 202.56852 | AB3: 204.68353 | AC3: 206.70656 | AD3: 208.71697 | AE3: 210.73856 | AF3: 212.78159 | AG3: 215.30744 | AH3: 217.96217 | AI3: 220.70104 | AJ3: 223.51303 | AK3: 226.39429
A4: yg_toe_ccoa_2 | B4: 2.3804957 | C4: 2.2594333 | D4: 2.1763031 | E4: 2.1530794 | F4: 2.1432342 | G4: 2.1380207 | H4: 2.1700143 | I4: 2.1963977 | J4: 2.2121383 | K4: 2.2149586 | L4: 2.2022589 | M4: 2.1983704 | N4: 2.2049677 | O4: 2.2197729 | P4: 2.2395095 | Q4: 2.2607947 | R4: 2.2772827 | S4: 2.2952284 | T4: 2.3168365 | U4: 2.3413084 | V4: 2.3674486 | W4: 2.3934799 | X4: 2.4223821 | Y4: 2.4543922 | Z4: 2.4889642 | AA4: 2.5253959 | AB4: 2.5613819 | AC4: 2.5990764 | AD4: 2.6384181 | AE4: 2.6790443 | AF4: 2.7206231 | AG4: 2.7630192 | AH4: 2.8066026 | AI4: 2.8510606 | AJ4: 2.8960758 | AK4: 2.9413793
A5: yg_toe_ccoa_0 | B5: 2.3804957 | C5: 2.2594333 | D5: 2.1763031 | E5: 2.1530794 | F5: 2.1432342 | G5: 2.1380207 | H5: 2.1717022 | I5: 2.2127599 | J5: 2.2580128 | K5: 2.3066156 | L5: 2.3582748 | M5: 2.4122837 | N5: 2.468603 | O5: 2.5270794 | P5: 2.5876119 | Q5: 2.6501315 | R5: 2.7103945 | S5: 2.7713998 | T5: 2.8337794 | U5: 2.8976878 | V5: 2.963158 | W5: 3.0262461 | X5: 3.0900326 | Y5: 3.1552668 | Z5: 3.2221893 | AA5: 3.290778 | AB5: 3.3419449 | AC5: 3.3900957 | AD5: 3.4383626 | AE5: 3.487412 | AF5: 3.5373738 | AG5: 3.6000645 | AH5: 3.6665705 | AI5: 3.7349337 | AJ5: 3.8047012 | AK5: 3.8757438
A6: yg_toe_ccoi_2 | B6: 1.0947953 | C6: 1.1044258 | D6: 1.108848 | E6: 1.1063466 | F6: 1.1075485 | G6: 1.1213105 | H6: 1.1364846 | I6: 1.1525927 | J6: 1.1685067 | K6: 1.1838478 | L6: 1.1977888 | M6: 1.2147391 | N6: 1.2359033 | O6: 1.2607362 | P6: 1.2882172 | Q6: 1.3172643 | R6: 1.345078 | S6: 1.3711586 | T6: 1.3952488 | U6: 1.4169757 | V6: 1.4360989 | W6: 1.4527345 | X6: 1.4683025 | Y6: 1.4832615 | Z6: 1.4977173 | AA6: 1.5114604 | AB6: 1.5241581 | AC6: 1.5368296 | AD6: 1.5496253 | AE6: 1.5625031 | AF6: 1.5754052 | AG6: 1.5884185 | AH6: 1.6018096 | AI6: 1.6155269 | AJ6: 1.6294518 | AK6: 1.6434688
A7: yg_toe_ccoi_0 | B7: 1.0947953 | C7: 1.1044258 | D7: 1.108848 | E7: 1.1063466 | F7: 1.1075485 | G7: 1.1213105 | H7: 1.136968 | I7: 1.1546934 | J7: 1.1732347 | K7: 1.1922979 | L7: 1.2119696 | M7: 1.2320604 | N7: 1.2526907 | O7: 1.2739324 | P7: 1.295812 | Q7: 1.3183196 | R7: 1.3402431 | S7: 1.3623005 | T7: 1.3846706 | U7: 1.4073855 | V7: 1.4303786 | W7: 1.4526189 | X7: 1.4748704 | Y7: 1.4973598 | Z7: 1.5201629 | AA7: 1.5431061 | AB7: 1.5609964 | AC7: 1.5774576 | AD7: 1.5935142 | AE7: 1.6094359 | AF7: 1.6253327 | AG7: 1.6445956 | AH7: 1.665098 | AI7: 1.6862884 | AJ7: 1.7080658 | AK7: 1.7304164
A8: yg_toe_cfut_2 | B8: 42.296057 | C8: 42.446148 | D8: 42.655776 | E8: 42.78489 | F8: 42.898685 | G8: 43.092582 | H8: 43.776075 | I8: 44.35125 | J8: 44.81189 | K8: 45.13929 | L8: 45.297192 | M8: 45.48307 | N8: 45.745551 | O8: 46.065083 | P8: 46.385552 | Q8: 46.628522 | R8: 46.679042 | S8: 46.706438 | T8: 46.801377 | U8: 46.950777 | V8: 47.122627 | W8: 47.307397 | X8: 47.540304 | Y8: 47.82312 | Z8: 48.143121 | AA8: 48.478989 | AB8: 48.817578 | AC8: 49.16903 | AD8: 49.52873 | AE8: 49.891809 | AF8: 50.254845 | AG8: 50.621208 | AH8: 50.995161 | AI8: 51.374301 | AJ8: 51.755286 | AK8: 52.135168
A9: yg_toe_cfut_0 | B9: 42.296057 | C9: 42.446148 | D9: 42.655776 | E9: 42.78489 | F9: 42.898685 | G9: 43.092582 | H9: 43.789553 | I9: 44.470399 | J9: 45.149457 | K9: 45.825752 | L9: 46.507299 | M9: 47.194637 | N9: 47.897004 | O9: 48.620332 | P9: 49.366718 | Q9: 50.135473 | R9: 50.896829 | S9: 51.666246 | T9: 52.445797 | U9: 53.235355 | V9: 54.031867 | W9: 54.811645 | X9: 55.592201 | Y9: 56.377576 | Z9: 57.169327 | AA9: 57.960354 | AB9: 58.629379 | AC9: 59.260036 | AD9: 59.871123 | AE9: 60.469098 | AF9: 61.058107 | AG9: 61.720247 | AH9: 62.408045 | AI9: 63.113415 | AJ9: 63.835522 | AK9: 64.574517
A10: yg_toe_cfuh_2 | B10: 7.9231252 | C10: 8.0403171 | D10: 8.019723 | E10: 7.8746114 | F10: 7.8401297 | G10: 8.0193575 | H10: 8.078351 | I10: 8.1568371 | J10: 8.2447049 | K10: 8.3309929 | L10: 8.3993497 | M10: 8.5053895 | N10: 8.6443587 | O10: 8.8059481 | P10: 8.9810647 | Q10: 9.1622782 | R10: 9.3305791 | S10: 9.4787101 | T10: 9.6018109 | U10: 9.7007887 | V10: 9.7786257 | W10: 9.8491789 | X10: 9.9170977 | Y10: 9.9832648 | Z10: 10.047842 | AA10: 10.106863 | AB10: 10.165953 | AC10: 10.227437 | AD10: 10.290692 | AE10: 10.355002 | AF10: 10.419853 | AG10: 10.4883 | AH10: 10.560037 | AI10: 10.633963 | AJ10: 10.709117 | AK10: 10.78477
A11: yg_toe_cfuh_0 | B11: 7.9231252 | C11: 8.0403171 | D11: 8.019723 | E11: 7.8746114 | F11: 7.8401297 | G11: 8.0193575 | H11: 8.0811912 | I11: 8.1700083 | J11: 8.2689225 | K11: 8.3721533 | L11: 8.4803302 | M11: 8.5902523 | N11: 8.7035893 | O11: 8.8212076 | P11: 8.9432984 | Q11: 9.0696644 | R11: 9.1934512 | S11: 9.3186152 | T11: 9.4458689 | U11: 9.5753499 | V11: 9.7057094 | W11: 9.8327843 | X11: 9.9605332 | Y11: 10.089835 | Z11: 10.221032 | AA11: 10.350391 | AB11: 10.452055 | AC11: 10.546113 | AD11: 10.63689 | AE11: 10.725789 | AF11: 10.813632 | AG11: 10.919599 | AH11: 11.031977 | AI11: 11.148545 | AJ11: 11.268882 | AK11: 11.392891
A12: yg_toe_cgas_2 | B12: 6.6168923 | C12: 6.5322191 | D12: 6.4182361 | E12: 6.3261578 | F12: 6.1796524 | G12: 5.9698233 | H12: 5.7869856 | I12: 5.5882221 | J12: 5.3857068 | K12: 5.1873567 | L12: 5.0007291 | M12: 4.9388203 | N12: 4.911587 | O12: 4.8857832 | P12: 4.851547 | Q12: 4.8085041 | R12: 4.7580788 | S12: 4.6965863 | T12: 4.6234489 | U12: 4.5403281 | V12: 4.4478528 | W12: 4.3696271 | X12: 4.2899674 | Y12: 4.2060442 | Z12: 4.1183628 | AA12: 4.0241963 | AB12: 3.9449744 | AC12: 3.8682098 | AD12: 3.7916286 | AE12: 3.7150825 | AF12: 3.6389361 | AG12: 3.5692265 | AH12: 3.5010335 | AI12: 3.4335786 | AJ12: 3.3671294 | AK12: 3.3022268
... A73: yg_toe_cote_spub_0 | B73: 1.2261715 | C73: 1.2467174 | D73: 1.2645003 | E73: 1.273284 | F73: 1.2837239 | G73: 1.311546 | H73: 1.346859 | I73: 1.3822799 | J73: 1.4178617 | K73: 1.4539718 | L73: 1.4910723 | M73: 1.5288106 | N73: 1.5674774 | O73: 1.6070938 | P73: 1.647685 | Q73: 1.6892803 | R73: 1.7283462 | S73: 1.7679108 | T73: 1.8082336 | U73: 1.8494053 | V73: 1.8914057 | W73: 1.931002 | X73: 1.9711959 | Y73: 2.0122946 | Z73: 2.0544277 | AA73: 2.0974253 | AB73: 2.1253728 | AC73: 2.1524105 | AD73: 2.1797153 | AE73: 2.2075672 | AF73: 2.2360691 | AG73: 2.2752297 | AH73: 2.3164168 | AI73: 2.3589453 | AJ73: 2.4026592 | AK73: 2.4474945

Sheet Energy_Mix
A1: _date_ | B1: 42005 | C1: 42370 | D1: 42736 | E1: 43101 | F1: 43466 | G1: 43831 | H1: 44197 | I1: 44562 | J1: 44927 | K1: 45292 | L1: 45658 | M1: 46023 | N1: 46388 | O1: 46753 | P1: 47119 | Q1: 47484 | R1: 47849 | S1: 48214 | T1: 48580 | U1: 48945 | V1: 49310 | W1: 49675 | X1: 50041 | Y1: 50406 | Z1: 50771 | AA1: 51136 | AB1: 51502 | AC1: 51867 | AD1: 52232 | AE1: 52597 | AF1: 52963 | AG1: 53328 | AH1: 53693 | AI1: 54058 | AJ1: 54424 | AK1: 54789
A2: phiy_ccoa_smin_2 | B2: 0.20069089 | C2: 0.20069089 | D2: 0.20069089 | E2: 0.20069089 | F2: 0.20069089 | G2: 0.20069089 | H2: 0.20069089 | I2: 0.20069089 | J2: 0.20069089 | K2: 0.20069089 | L2: 0.20069089 | M2: 0.20069089 | N2: 0.20069089 | O2: 0.20069089 | P2: 0.20069089 | Q2: 0.20069089 | R2: 0.20069089 | S2: 0.20069089 | T2: 0.20069089 | U2: 0.20069089 | V2: 0.20069089 | W2: 0.20069089 | X2: 0.20069089 | Y2: 0.20069089 | Z2: 0.20069089 | AA2: 0.20069089 | AB2: 0.20069089 | AC2: 0.20069089 | AD2: 0.20069089 | AE2: 0.20069089 | AF2: 0.20069089 | AG2: 0.20069089 | AH2: 0.20069089 | AI2: 0.20069089 | AJ2: 0.20069089 | AK2: 0.20069089
A3: phiy_ccoa_soil_2 | B3: 0.79930911 | C3: 0.79930911 | D3: 0.79930911 | E3: 0.79930911 | F3: 0.79930911 | G3: 0.79930911 | H3: 0.79930911 | I3: 0.79930911 | J3: 0.79930911 | K3: 0.79930911 | L3: 0.79930911 | M3: 0.79930911 | N3: 0.79930911 | O3: 0.79930911 | P3: 0.79930911 | Q3: 0.79930911 | R3: 0.79930911 | S3: 0.79930911 | T3: 0.79930911 | U3: 0.79930911 | V3: 0.79930911 | W3: 0.79930911 | X3: 0.79930911 | Y3: 0.79930911 | Z3: 0.79930911 | AA3: 0.79930911 | AB3: 0.79930911 | AC3: 0.79930911 | AD3: 0.79930911 | AE3: 0.79930911 | AF3: 0.79930911 | AG3: 0.79930911 | AH3: 0.79930911 | AI3: 0.79930911 | AJ3: 0.79930911 | AK3: 0.79930911
A4: phiy_ccoi_smin_2 | B4: 0.7836667 | C4: 0.7836667 | D4: 0.7836667 | E4: 0.7836667 | F4: 0.7836667 | G4: 0.7836667 | H4: 0.7836667 | I4: 0.7836667 | J4: 0.7836667 | K4: 0.7836667 | L4: 0.7836667 | M4: 0.7836667 | N4: 0.7836667 | O4: 0.7836667 | P4: 0.7836667 | Q4: 0.7836667 | R4: 0.7836667 | S4: 0.7836667 | T4: 0.7836667 | U4: 0.7836667 | V4: 0.7836667 | W4: 0.7836667 | X4: 0.7836667 | Y4: 0.7836667 | Z4: 0.7836667 | AA4: 0.7836667 | AB4: 0.7836667 | AC4: 0.7836667 | AD4: 0.7836667 | AE4: 0.7836667 | AF4: 0.7836667 | AG4: 0.7836667 | AH4: 0.7836667 | AI4: 0.7836667 | AJ4: 0.7836667 | AK4: 0.7836667
A5: phiy_ccoi_soil_2 | B5: 0.2163333 | C5: 0.2163333 | D5: 0.2163333 | E5: 0.2163333 | F5: 0.2163333 | G5: 0.2163333 | H5: 0.2163333 | I5: 0.2163333 | J5: 0.2163333 | K5: 0.2163333 | L5: 0.2163333 | M5: 0.2163333 | N5: 0.2163333 | O5: 0.2163333 | P5: 0.2163333 | Q5: 0.2163333 | R5: 0.2163333 | S5: 0.2163333 | T5: 0.2163333 | U5: 0.2163333 | V5: 0.2163333 | W5: 0.2163333 | X5: 0.2163333 | Y5: 0.2163333 | Z5: 0.2163333 | AA5: 0.2163333 | AB5: 0.2163333 | AC5: 0.2163333 | AD5: 0.2163333 | AE5: 0.2163333 | AF5: 0.2163333 | AG5: 0.2163333 | AH5: 0.2163333 | AI5: 0.2163333 | AJ5: 0.2163333 | AK5: 0.2163333
A6: phiy_cfut_soil_2 | B6: 0.83809636 | C6: 0.83809636 | D6: 0.83809636 | E6: 0.83809636 | F6: 0.83809636 | G6: 0.83809636 | H6: 0.83809636 | I6: 0.83809636 | J6: 0.83809636 | K6: 0.83809636 | L6: 0.83809636 | M6: 0.83809636 | N6: 0.83809636 | O6: 0.83809636 | P6: 0.83809636 | Q6: 0.83809636 | R6: 0.83809636 | S6: 0.83809636 | T6: 0.83809636 | U6: 0.83809636 | V6: 0.83809636 | W6: 0.83809636 | X6: 0.83809636 | Y6: 0.83809636 | Z6: 0.83809636 | AA6: 0.83809636 | AB6: 0.83809636 | AC6: 0.83809636 | AD6: 0.83809636 | AE6: 0.83809636 | AF6: 0.83809636 | AG6: 0.83809636 | AH6: 0.83809636 | AI6: 0.83809636 | AJ6: 0.83809636 | AK6: 0.83809636
A7: phiy_cfut_sbfu_2 | B7: 0.16190364 | C7: 0.16190364 | D7: 0.16190364 | E7: 0.16190364 | F7: 0.16190364 | G7: 0.16190364 | H7: 0.16190364 | I7: 0.16190364 | J7: 0.16190364 | K7: 0.16190364 | L7: 0.16190364 | M7: 0.16190364 | N7: 0.16190364 | O7: 0.16190364 | P7: 0.16190364 | Q7: 0.16190364 | R7: 0.16190364 | S7: 0.16190364 | T7: 0.16190364 | U7: 0.16190364 | V7: 0.16190364 | W7: 0.16190364 | X7: 0.16190364 | Y7: 0.16190364 | Z7: 0.16190364 | AA7: 0.16190364 | AB7: 0.16190364 | AC7: 0.16190364 | AD7: 0.16190364 | AE7: 0.16190364 | AF7: 0.16190364 | AG7: 0.16190364 | AH7: 0.16190364 | AI7: 0.16190364 | AJ7: 0.16190364 | AK7: 0.16190364
A8: phiy_cfuh_soil_2 | B8: 1 | C8: 1 | D8: 1 | E8: 1 | F8: 1 | G8: 1 | H8: 1 | I8: 1 | J8: 1 | K8: 1 | L8: 1 | M8: 1 | N8: 1 | O8: 1 | P8: 1 | Q8: 1 | R8: 1 | S8: 1 | T8: 1 | U8: 1 | V8: 1 | W8: 1 | X8: 1 | Y8: 1 | Z8: 1 | AA8: 1 | AB8: 1 | AC8: 1 | AD8: 1 | AE8: 1 | AF8: 1 | AG8: 1 | AH8: 1 | AI8: 1 | AJ8: 1 | AK8: 1
A9: phiy_cgas_smet_2 | B9: 8.2704782e-05 | C9: 8.2704782e-05 | D9: 8.2704782e-05 | E9: 8.2704782e-05 | F9: 8.2704782e-05 | G9: 8.2704782e-05 | H9: 8.2704782e-05 | I9: 8.2704782e-05 | J9: 8.2704782e-05 | K9: 8.2704782e-05 | L9: 8.2704782e-05 | M9: 8.2704782e-05 | N9: 8.2704782e-05 | O9: 8.2704782e-05 | P9: 8.2704782e-05 | Q9: 8.2704782e-05 | R9: 8.2704782e-05 | S9: 8.2704782e-05 | T9: 8.2704782e-05 | U9: 8.2704782e-05 | V9: 8.2704782e-05 | W9: 8.2704782e-05 | X9: 8.2704782e-05 | Y9: 8.2704782e-05 | Z9: 8.2704782e-05 | AA9: 8.2704782e-05 | AB9: 8.2704782e-05 | AC9: 8.2704782e-05 | AD9: 8.2704782e-05 | AE9: 8.2704782e-05 | AF9: 8.2704782e-05 | AG9: 8.2704782e-05 | AH9: 8.2704782e-05 | AI9: 8.2704782e-05 | AJ9: 8.2704782e-05 | AK9: 8.2704782e-05
