Workbook
Name formatResults: [1]ResultsEXR10!$A$50

Sheet Carbontax
A1: _date_ | B1: 42005 | C1: 42370 | D1: 42736 | E1: 43101 | F1: 43466 | G1: 43831 | H1: 44197 | I1: 44562 | J1: 44927 | K1: 45292 | L1: 45658 | M1: 46023 | N1: 46388 | O1: 46753 | P1: 47119 | Q1: 47484 | R1: 47849 | S1: 48214 | T1: 48580 | U1: 48945 | V1: 49310 | W1: 49675 | X1: 50041 | Y1: 50406 | Z1: 50771 | AA1: 51136 | AB1: 51502 | AC1: 51867 | AD1: 52232 | AE1: 52597 | AF1: 52963 | AG1: 53328 | AH1: 53693 | AI1: 54058 | AJ1: 54424 | AK1: 54789
A2: t2val_ch_0 | B2: 1732.612 | C2: 2604.4617 | D2: 3573.26 | E2: 5172.311 | F2: 5148.6408 | G2: 5142.9411 | H2: 5135.9657 | I2: 5247.0501 | J2: 5359.135 | K2: 5480.1012 | L2: 5611.1786 | M2: 5747.1604 | N2: 5883.9586 | O2: 6017.1489 | P2: 6143.0168 | Q2: 6259.2574 | R2: 6373.9467 | S2: 6478.3445 | T2: 6571.5626 | U2: 6654.1116 | V2: 6726.1578 | W2: 6792.5557 | X2: 6855.2553 | Y2: 6916.9117 | Z2: 6980.4679 | AA2: 7045.0359 | AB2: 7119.2742 | AC2: 7205.9333 | AD2: 7307.6273 | AE2: 7426.7797 | AF2: 7564.732 | AG2: 7722.2462 | AH2: 7899.2902 | AI2: 8095.5298 | AJ2: 8310.3496 | AK2: 8514.8567
A3: t2val_ch_2 | B3: 1732.6121 | C3: 2604.4619 | D3: 3573.2602 | E3: 5172.3113 | F3: 5148.641 | G3: 5142.9413 | H3: 5147.3724 | I3: 12549.587 | J3: 16944.264 | K3: 21290.993 | L3: 25663.111 | M3: 27428.15 | N3: 29180.109 | O3: 30887.284 | P3: 32501.508 | Q3: 33985.201 | R3: 36850.663 | S3: 39499.251 | T3: 41894.16 | U3: 44017.203 | V3: 45846.502 | W3: 47394.751 | X3: 48654.907 | Y3: 49627.163 | Z3: 50313.014 | AA3: 50685.712 | AB3: 50795.111 | AC3: 50654.853 | AD3: 50275.18 | AE3: 49650.032 | AF3: 48764.531 | AG3: 47596.998 | AH3: 46121.422 | AI3: 44303.893 | AJ3: 42097.29 | AK3: 39539.031
A4: t2val_sec_0 | B4: 3312.8737 | C4: 5053.9623 | D4: 7049.9112 | E4: 10359.555 | F4: 10469.624 | G4: 10629.623 | H4: 10805.266 | I4: 11237.466 | J4: 11683.418 | K4: 12155.894 | L4: 12644.074 | M4: 13107.215 | N4: 13540.085 | O4: 13940.243 | P4: 14309.572 | Q4: 14653.405 | R4: 14999.356 | S4: 15344.623 | T4: 15697.948 | U4: 16066.073 | V4: 16454.879 | W4: 16874.6 | X4: 17333.418 | Y4: 17839.852 | Z4: 18401.969 | AA4: 19025.451 | AB4: 19727.52 | AC4: 20521.048 | AD4: 21417.319 | AE4: 22422.572 | AF4: 23538.064 | AG4: 24764.984 | AH4: 26105.071 | AI4: 27560.115 | AJ4: 29131.616 | AK4: 29870.505
A5: t2val_sec_2 | B5: 3312.8739 | C5: 5053.9627 | D5: 7049.9117 | E5: 10359.556 | F5: 10469.624 | G5: 10629.624 | H5: 10828.996 | I5: 26830.044 | J5: 36677.137 | K5: 46805.797 | L5: 57282.489 | M5: 61988.05 | N5: 66672.93 | O5: 71332.874 | P5: 75940.167 | Q5: 80466.125 | R5: 88582.968 | S5: 96580.577 | T5: 104418.36 | U5: 112101.21 | V5: 119641.53 | W5: 127091.98 | X5: 134500.11 | Y5: 141902.89 | Z5: 149314.61 | AA5: 156720.4 | AB5: 164208.33 | AC5: 171864.59 | AD5: 179723.7 | AE5: 187710.54 | AF5: 195686.28 | AG5: 203490.21 | AH5: 210946.89 | AI5: 217817.47 | AJ5: 223755.07 | AK5: 221562.32
A6: t2val_ci_0 | B6: 3091.7816 | C6: 4713.1329 | D6: 6568.9457 | E6: 9642.9613 | F6: 9738.7494 | G6: 9883.428 | H6: 10043.006 | I6: 10440.519 | J6: 10850.488 | K6: 11284.579 | L6: 11732.441 | M6: 12155.314 | N6: 12548.444 | O6: 12909.699 | P6: 13241.025 | Q6: 13547.605 | R6: 13856.523 | S6: 14165.36 | T6: 14482.257 | U6: 14813.439 | V6: 15164.327 | W6: 15544.464 | X6: 15961.44 | Y6: 16423.147 | Z6: 16937.044 | AA6: 17508.344 | AB6: 18153.175 | AC6: 18883.485 | AD6: 19709.668 | AE6: 20637.28 | AF6: 21667.181 | AG6: 22800.146 | AH6: 24037.441 | AI6: 25380.328 | AJ6: 26829.709 | AK6: 27505.264
A7: t2val_ci_2 | B7: 3091.7818 | C7: 4713.1333 | D7: 6568.9462 | E7: 9642.962 | F7: 9738.75 | G7: 9883.4287 | H7: 10066.551 | I7: 24864.163 | J7: 33877.007 | K7: 43091.897 | L7: 52565.165 | M7: 56704.723 | N7: 60800.063 | O7: 64843.695 | P7: 68808.263 | Q7: 72665.594 | R7: 79705.975 | S7: 86568.838 | T7: 93217.63 | U7: 99655.858 | V7: 105892.78 | W7: 111973.53 | X7: 117936.61 | Y7: 123808.51 | Z7: 129593.13 | AA7: 135266 | AB7: 140897.78 | AC7: 146546.36 | AD7: 152218.49 | AE7: 157818.02 | AF7: 163187.21 | AG7: 168144.18 | AH7: 172486.64 | AI7: 175945.91 | AJ7: 178145.92 | AK7: 173277.94
A8: t2val_y_0 | B8: 0.39920408 | C8: 0.61575367 | D8: 0.87006208 | E8: 1.2997035 | F8: 1.3298811 | G8: 1.3625981 | H8: 1.3967815 | I8: 1.4650001 | J8: 1.5355483 | K8: 1.6104313 | L8: 1.6883979 | M8: 1.7637332 | N8: 1.8360975 | O8: 1.9049038 | P8: 1.970107 | Q8: 2.0321552 | R8: 2.0924774 | S8: 2.1507128 | T8: 2.2082704 | U8: 2.2663161 | V8: 2.3257382 | W8: 2.3883461 | X8: 2.4553975 | Y8: 2.5281311 | Z8: 2.6076268 | AA8: 2.694126 | AB8: 2.7903147 | AC8: 2.8978742 | AD8: 3.0182688 | AE8: 3.1522799 | AF8: 3.299989 | AG8: 3.4614278 | AH8: 3.6366093 | AI8: 3.8254297 | AJ8: 4.0276407 | AK8: 4.1278694
A9: t2val_y_2 | B9: 0.39920408 | C9: 0.61575367 | D9: 0.87006208 | E9: 1.2997035 | F9: 1.3298811 | G9: 1.3625981 | H9: 1.3972479 | I9: 3.6170006 | J9: 5.1766565 | K9: 6.9132345 | L9: 8.8375188 | M9: 9.9386935 | N9: 11.074579 | O9: 12.249664 | P9: 13.462653 | Q9: 14.711281 | R9: 16.717998 | S9: 18.824575 | T9: 21.02501 | U9: 23.323105 | V9: 25.724184 | W9: 28.247467 | X9: 30.912442 | Y9: 33.741564 | Z9: 36.756142 | AA9: 39.967317 | AB9: 43.416807 | AC9: 47.16179 | AD9: 51.256604 | AE9: 55.738132 | AF9: 60.634272 | AG9: 65.972812 | AH9: 71.78735 | AI9: 78.111948 | AJ9: 84.971398 | AK9: 89.727749
A10: t2val_mat_0 | B10: 220.6929 | C10: 340.21364 | D10: 480.09546 | E10: 715.2941 | F10: 729.54429 | G10: 744.83255 | H10: 760.86268 | I10: 795.48244 | J10: 831.395 | K10: 869.7054 | L10: 909.94422 | M10: 950.13736 | N10: 989.80468 | O10: 1028.6393 | P10: 1066.5761 | Q10: 1103.7679 | R10: 1140.7412 | S10: 1177.1119 | T10: 1213.4834 | U10: 1250.3679 | V10: 1288.2258 | W10: 1327.7467 | X10: 1369.5219 | Y10: 1414.1771 | Z10: 1462.3174 | AA10: 1514.4126 | AB10: 1571.5556 | AC10: 1634.665 | AD10: 1704.6325 | AE10: 1782.1397 | AF10: 1867.5831 | AG10: 1961.3765 | AH10: 2063.9932 | AI10: 2175.9614 | AJ10: 2297.8791 | AK10: 2361.1129
A11: t2val_mat_2 | B11: 220.6929 | C11: 340.21364 | D11: 480.09546 | E11: 715.2941 | F11: 729.54429 | G11: 744.83255 | H11: 761.04741 | I11: 1962.2633 | J11: 2794.9535 | K11: 3706.9862 | L11: 4708.4873 | M11: 5273.389 | N11: 5861.793 | O11: 6476.9287 | P11: 7118.4414 | Q11: 7785.8199 | R11: 8860.2745 | S11: 9992.9141 | T11: 11179.702 | U11: 12422.029 | V11: 13723.031 | W11: 15090.199 | X11: 16532.584 | Y11: 18060.643 | Z11: 19684.722 | AA11: 21414.43 | AB11: 23267.137 | AC11: 25271.07 | AD11: 27453.957 | AE11: 29836.788 | AF11: 32438.436 | AG11: 35280.059 | AH11: 38388.46 | AI11: 41793.449 | AJ11: 45524.181 | AK11: 48194.646

Sheet Production
A1: _date_ | B1: 42005 | C1: 42370 | D1: 42736 | E1: 43101 | F1: 43466 | G1: 43831 | H1: 44197 | I1: 44562 | J1: 44927 | K1: 45292 | L1: 45658 | M1: 46023 | N1: 46388 | O1: 46753 | P1: 47119 | Q1: 47484 | R1: 47849 | S1: 48214 | T1: 48580 | U1: 48945 | V1: 49310 | W1: 49675 | X1: 50041 | Y1: 50406 | Z1: 50771 | AA1: 51136 | AB1: 51502 | AC1: 51867 | AD1: 52232 | AE1: 52597 | AF1: 52963 | AG1: 53328 | AH1: 53693 | AI1: 54058 | AJ1: 54424 | AK1: 54789
A2: y_2 | B2: 3852771.8 | C2: 3923398 | D2: 4002771.3 | E2: 4089232.2 | F2: 4181337.9 | G2: 4278574.5 | H2: 4379701.2 | I2: 4473575.9 | J2: 4569000 | K2: 4685094.5 | L2: 4803497.2 | M2: 4908869.2 | N2: 5002799.7 | O2: 5088267.6 | P2: 5169373.6 | Q2: 5248870 | R2: 5327906.3 | S2: 5409262.4 | T2: 5495110.3 | U2: 5587034.1 | V2: 5685837.9 | W2: 5793537.7 | X2: 5911483 | Y2: 6040657.4 | Z2: 6181472.3 | AA2: 6332485.9 | AB2: 6496024.2 | AC2: 6673177.6 | AD2: 6864736.5 | AE2: 7070295.3 | AF2: 7288839.2 | AG2: 7519636.7 | AH2: 7762463.2 | AI2: 8017432 | AJ2: 8285067.4 | AK2: 8285060.7
A3: y_0 | B3: 3852771.8 | C3: 3923398 | D3: 4002771.3 | E3: 4089232.2 | F3: 4181337.9 | G3: 4278574.5 | H3: 4378592 | I3: 4482693.9 | J3: 4589335.3 | K3: 4698310.3 | L3: 4806961.4 | M3: 4903573 | N3: 4990776.7 | O3: 5070732.7 | P3: 5146094.8 | Q3: 5219434.1 | R3: 5294461.8 | S3: 5373946.4 | T3: 5459808.6 | U3: 5553160.8 | V3: 5654359.9 | W3: 5765037 | X3: 5886233.5 | Y3: 6018678.3 | Z3: 6162538 | AA3: 6316193 | AB3: 6481488.1 | AC3: 6659396 | AD3: 6850471.6 | AE3: 7054012.1 | AF3: 7268716.3 | AG3: 7493562.2 | AH3: 7728002.7 | AI3: 7971819.4 | AJ3: 8225147.9 | AK3: 8225136.2
A4: y_sagr_2 | B4: 81740.104 | C4: 83098.378 | D4: 84695.165 | E4: 86520.227 | F4: 88529.128 | G4: 90707.069 | H4: 93013.679 | I4: 95050.672 | J4: 97067.28 | K4: 99534.467 | L4: 102009.47 | M4: 104120.78 | N4: 105932.9 | O4: 107521.93 | P4: 108981.83 | Q4: 110373.88 | R4: 111757.52 | S4: 113164.16 | T4: 114645.01 | U4: 116241.41 | V4: 117974.12 | W4: 119898.54 | X4: 122048.42 | Y4: 124447.47 | Z4: 127104.24 | AA4: 129974.94 | AB4: 133088.91 | AC4: 136492.91 | AD4: 140200.22 | AE4: 144190.98 | AF4: 148426.34 | AG4: 152868.33 | AH4: 157484.5 | AI4: 162243.59 | AJ4: 167114.62 | AK4: 167114.4
A5: y_sagr_0 | B5: 81740.104 | C5: 83098.378 | D5: 84695.165 | E5: 86520.227 | F5: 88529.128 | G5: 90707.069 | H5: 92982.631 | I5: 95327.027 | J5: 97721.461 | K5: 100157.93 | L5: 102564.29 | M5: 104628.4 | N5: 106416.51 | O5: 107979.12 | P5: 109381.38 | Q5: 110689.23 | R5: 112002.13 | S5: 113396.93 | T5: 114928.09 | U5: 116627.18 | V5: 118502.69 | W5: 120598.82 | X5: 122939.57 | Y5: 125539.77 | Z5: 128399.51 | AA5: 131468.27 | AB5: 134794.42 | AC5: 138395.36 | AD5: 142274.68 | AE5: 146401.81 | AF5: 150728.05 | AG5: 155207.59 | AH5: 159801.15 | AI5: 164471 | AJ5: 169179.91 | AK5: 169179.55
A6: y_sfor_2 | B6: 6533.4139 | C6: 6484.9363 | D6: 6440.7805 | E6: 6396.1589 | F6: 6383.4013 | G6: 6389.0043 | H6: 6404.3497 | I6: 6326.8358 | J6: 6264.1712 | K6: 6237.5695 | L6: 6224.6 | M6: 6226.8742 | N6: 6231.8068 | O6: 6236.6067 | P6: 6243.1632 | Q6: 6252.8809 | R6: 6245.4174 | S6: 6238.6386 | T6: 6236.9732 | U6: 6242.4875 | V6: 6254.8592 | W6: 6277.4362 | X6: 6310.7371 | Y6: 6355.1026 | Z6: 6410.6506 | AA6: 6473.4913 | AB6: 6553.1535 | AC6: 6647.3932 | AD6: 6756.8914 | AE6: 6881.3696 | AF6: 7020.3878 | AG6: 7174.258 | AH6: 7344.1523 | AI6: 7531.8131 | AJ6: 7739.7499 | AK6: 7739.1433
A7: y_sfor_0 | B7: 6533.4139 | C7: 6484.9363 | D7: 6440.7805 | E7: 6396.1589 | F7: 6383.4013 | G7: 6389.0043 | H7: 6404.596 | I7: 6430.19 | J7: 6462.2581 | K7: 6498.7425 | L7: 6538.6238 | M7: 6568.535 | N7: 6592.0405 | O7: 6611.5467 | P7: 6629.5259 | Q7: 6648.0933 | R7: 6668.5161 | S7: 6692.9831 | T7: 6723.0678 | U7: 6759.6736 | V7: 6801.8275 | W7: 6853.0125 | X7: 6913.6319 | Y7: 6984.05 | Z7: 7064.2911 | AA7: 7149.7491 | AB7: 7246.4668 | AC7: 7355.4994 | AD7: 7477.5038 | AE7: 7612.119 | AF7: 7758.7187 | AG7: 7917.1826 | AH7: 8088.0622 | AI7: 8272.5711 | AJ7: 8472.6404 | AK7: 8471.6305
A8: y_sfoo_2 | B8: 157672.64 | C8: 160409.07 | D8: 163572.61 | E8: 167180.21 | F8: 171115.96 | G8: 175352.31 | H8: 179808 | I8: 183961.6 | J8: 188111.82 | K8: 192984.35 | L8: 197951.42 | M8: 202354.71 | N8: 206271.79 | O8: 209778.62 | P8: 212994.51 | Q8: 216010.53 | R8: 218942.97 | S8: 221851.69 | T8: 224831.75 | U8: 227964.44 | V8: 231283.82 | W8: 234908.07 | X8: 238896.37 | Y8: 243297.75 | Z8: 248136.03 | AA8: 253312.68 | AB8: 258898.19 | AC8: 264976.65 | AD8: 271577.32 | AE8: 278681.85 | AF8: 286236.16 | AG8: 294176.29 | AH8: 302440.22 | AI8: 310969.42 | AJ8: 319705.52 | AK8: 319705.46
A9: y_sfoo_0 | B9: 157672.64 | C9: 160409.07 | D9: 163572.61 | E9: 167180.21 | F9: 171115.96 | G9: 175352.31 | H9: 179745.74 | I9: 184258.43 | J9: 188862.94 | K9: 193548.6 | L9: 198217.98 | M9: 202344.14 | N9: 206004.69 | O9: 209254.14 | P9: 212182.01 | Q9: 214891.62 | R9: 217562.74 | S9: 220327.86 | T9: 223284.81 | U9: 226496.59 | V9: 229977.51 | W9: 233830.23 | X9: 238100.9 | Y9: 242824.03 | Z9: 248009.09 | AA9: 253547.86 | AB9: 259561.26 | AC9: 266079.14 | AD9: 273115.32 | AE9: 280631.05 | AF9: 288554.14 | AG9: 296810.45 | AH9: 305331.1 | AI9: 314046.82 | AJ9: 322887.99 | AK9: 322887.87
A10: y_sveh_2 | B10: 125569.22 | C10: 130054.02 | D10: 134888.1 | E10: 139652.33 | F10: 144377.28 | G10: 149034.58 | H10: 153617.79 | I10: 156481.46 | J10: 159383.1 | K10: 164123.69 | L10: 168480 | M10: 171508.88 | N10: 173637.14 | O10: 175308.04 | P10: 176985.93 | Q10: 178904.13 | R10: 180862.55 | S10: 183179.51 | T10: 185953.2 | U10: 189208.92 | V10: 192956.89 | W10: 197224.09 | X10: 202042.43 | Y10: 207419.57 | Z10: 213324.57 | AA10: 219707.78 | AB10: 226753.33 | AC10: 234335.99 | AD10: 242429.66 | AE10: 250902.13 | AF10: 259596.99 | AG10: 268404.14 | AH10: 277256.27 | AI10: 286104.99 | AJ10: 294910.08 | AK10: 294909.82
A11: y_sveh_0 | B11: 125569.22 | C11: 130054.02 | D11: 134888.1 | E11: 139652.33 | F11: 144377.28 | G11: 149034.58 | H11: 153552.3 | I11: 157977 | J11: 162389.16 | K11: 166854.74 | L11: 171112.68 | M11: 174262.4 | N11: 176794.17 | O11: 178995.56 | P11: 181130.5 | Q11: 183393.13 | R11: 186008.24 | S11: 189083.59 | T11: 192657.14 | U11: 196717.14 | V11: 201253.31 | W11: 206283.14 | X11: 211835.92 | Y11: 217912.26 | Z11: 224468.67 | AA11: 231442.65 | AB11: 238861.35 | AC11: 246755.39 | AD11: 255103.51 | AE11: 263767.09 | AF11: 272581.75 | AG11: 281436.9 | AH11: 290272.45 | AI11: 299045.8 | AJ11: 307719.07 | AK11: 307718.68
A12: y_sgla_2 | B12: 22086.068 | C12: 22481.821 | D12: 22925.057 | E12: 23401.224 | F12: 23918.547 | G12: 24478.929 | H12: 25077.581 | I12: 25542.894 | J12: 25976.308 | K12: 26495.325 | L12: 27010.798 | M12: 27470.695 | N12: 27888.785 | O12: 28284.036 | P12: 28679.157 | Q12: 29088.194 | R12: 29514.765 | S12: 29958.68 | T12: 30431.876 | U12: 30944.642 | V12: 31504.347 | W12: 32121.686 | X12: 32805.744 | Y12: 33562.133 | Z12: 34393.012 | AA12: 35293.198 | AB12: 36262.665 | AC12: 37316.495 | AD12: 38457.736 | AE12: 39683.297 | AF12: 40987.838 | AG12: 42369.084 | AH12: 43828.268 | AI12: 45367.896 | AJ12: 46993.133 | AK12: 46992.944
... A67: y_seot_0 | B67: 109.82449 | C67: 111.47273 | D67: 113.01877 | E67: 114.69243 | F67: 116.20998 | G67: 117.74585 | H67: 119.39082 | I67: 123.86909 | J67: 129.08415 | K67: 134.6601 | L67: 140.47648 | M67: 146.20079 | N67: 151.88913 | O67: 157.62308 | P67: 163.51585 | Q67: 169.69322 | R67: 176.2291 | S67: 183.29492 | T67: 191.05859 | U67: 199.67423 | V67: 209.27873 | W67: 220.07355 | X67: 232.25186 | Y67: 246.02083 | Z67: 261.60209 | AA67: 279.17341 | AB67: 299.11034 | AC67: 321.80284 | AD67: 347.68712 | AE67: 377.21248 | AF67: 410.88689 | AG67: 449.3538 | AH67: 493.46033 | AI67: 544.32518 | AJ67: 603.44 | AK67: 603.43889

Sheet Capital
A1: _date_ | B1: 42005 | C1: 42370 | D1: 42736 | E1: 43101 | F1: 43466 | G1: 43831 | H1: 44197 | I1: 44562 | J1: 44927 | K1: 45292 | L1: 45658 | M1: 46023 | N1: 46388 | O1: 46753 | P1: 47119 | Q1: 47484 | R1: 47849 | S1: 48214 | T1: 48580 | U1: 48945 | V1: 49310 | W1: 49675 | X1: 50041 | Y1: 50406 | Z1: 50771 | AA1: 51136 | AB1: 51502 | AC1: 51867 | AD1: 52232 | AE1: 52597 | AF1: 52963 | AG1: 53328 | AH1: 53693 | AI1: 54058 | AJ1: 54424 | AK1: 54789
A2: f_k_2 | B2: 5223771.6 | C2: 5286510.5 | D2: 5354071.6 | E2: 5427422.4 | F2: 5507273.2 | G2: 5594113.3 | H2: 5688233.9 | I2: 5788410.3 | J2: 5894390.5 | K2: 6007793.7 | L2: 6129318.9 | M2: 6258283.6 | N2: 6393644.4 | O2: 6534490.6 | P2: 6680291.4 | Q2: 6830849.2 | R2: 6986041.6 | S2: 7146040 | T2: 7311280 | U2: 7482379.1 | V2: 7660031.1 | W2: 7845064.2 | X2: 8038416.7 | Y2: 8241108.2 | Z2: 8454172.4 | AA2: 8678463.6 | AB2: 8914907.3 | AC2: 9164467 | AD2: 9428188.1 | AE2: 9707131.7 | AF2: 10002302 | AG2: 10314638 | AH2: 10645051 | AI2: 10994503 | AJ2: 11364071 | AK2: 11722087
A3: f_k_0 | B3: 5223771.6 | C3: 5286510.5 | D3: 5354071.6 | E3: 5427422.4 | F3: 5507273.2 | G3: 5594113.3 | H3: 5688109.7 | I3: 5789398.7 | J3: 5898078.4 | K3: 6014258.7 | L3: 6137864.2 | M3: 6267848.5 | N3: 6403108.1 | O3: 6542737.5 | P3: 6686121.6 | Q3: 6832936.4 | R3: 6983295.9 | S3: 7137649.9 | T3: 7296651.9 | U3: 7461039.3 | V3: 7631530.7 | W3: 7808910.2 | X3: 7994023.4 | Y3: 8187750.6 | Z3: 8390947 | AA3: 8604267.2 | AB3: 8828417.5 | AC3: 9064206.9 | AD3: 9312540.5 | AE3: 9574332.7 | AF3: 9850433.4 | AG3: 10141636 | AH3: 10448729 | AI3: 10772542 | AJ3: 11113998 | AK3: 11444421
A4: f_k_sagr_2 | B4: 47217.163 | C4: 47790.485 | D4: 48409.369 | E4: 49087.588 | F4: 49831.406 | G4: 50645.318 | H4: 51532 | I4: 52496.763 | J4: 53542.025 | K4: 54687.777 | L4: 55941.702 | M4: 57287.166 | N4: 58705.143 | O4: 60179.387 | P4: 61698.479 | Q4: 63254.989 | R4: 64847.858 | S4: 66477.569 | T4: 68146.567 | U4: 69858.767 | V4: 71618.278 | W4: 73430.625 | X4: 75302.213 | Y4: 77239.831 | Z4: 79249.676 | AA4: 81334.304 | AB4: 83495.062 | AC4: 85733.973 | AD4: 88053.584 | AE4: 90455.575 | AF4: 92939.395 | AG4: 95501.68 | AH4: 98136.346 | AI4: 100834.97 | AJ4: 103586.88 | AK4: 106182.16
A5: f_k_sagr_0 | B5: 47217.163 | C5: 47790.485 | D5: 48409.369 | E5: 49087.588 | F5: 49831.406 | G5: 50645.318 | H5: 51531.69 | I5: 52491.819 | J5: 53526.245 | K5: 54635.199 | L5: 55816.411 | M5: 57055.674 | N5: 58338.179 | O5: 59651.419 | P5: 60986.229 | Q5: 62336.917 | R5: 63701.541 | S5: 65081.964 | T5: 66482.742 | U5: 67909.873 | V5: 69369.408 | W5: 70868.751 | X5: 72416.206 | Y5: 74020.423 | Z5: 75689.533 | AA5: 77428.566 | AB5: 79243.296 | AC5: 81140.34 | AD5: 83126.665 | AE5: 85208.288 | AF5: 87389.181 | AG5: 89671.122 | AH5: 92053.967 | AI5: 94535.81 | AJ5: 97113.042 | AK5: 99584.041
A6: f_k_sfor_2 | B6: 1844.804 | C6: 1864.2896 | D6: 1881.613 | E6: 1896.7243 | F6: 1910.1528 | G6: 1922.3856 | H6: 1933.7374 | I6: 1943.0138 | J6: 1950.2762 | K6: 1956.3681 | L6: 1961.9148 | M6: 1967.3853 | N6: 1973.038 | O6: 1979.0142 | P6: 1985.4453 | Q6: 1992.4706 | R6: 1999.8914 | S6: 2007.6917 | T6: 2015.9799 | U6: 2024.9144 | V6: 2034.6314 | W6: 2045.2965 | X6: 2057.0698 | Y6: 2070.0967 | Z6: 2084.4989 | AA6: 2100.2878 | AB6: 2117.6031 | AC6: 2136.5612 | AD6: 2157.2855 | AE6: 2179.9025 | AF6: 2204.5368 | AG6: 2231.3167 | AH6: 2260.3916 | AI6: 2291.9528 | AJ6: 2326.2494 | AK6: 2359.3275
A7: f_k_sfor_0 | B7: 1844.804 | C7: 1864.2896 | D7: 1881.613 | E7: 1896.7243 | F7: 1910.1528 | G7: 1922.3856 | H7: 1933.7401 | I7: 1944.5075 | J7: 1954.9185 | K7: 1965.1572 | L7: 1975.3856 | M7: 1985.545 | N7: 1995.5926 | O7: 2005.543 | P7: 2015.4646 | Q7: 2025.4642 | R7: 2035.6649 | S7: 2046.2057 | T7: 2057.2286 | U7: 2068.8643 | V7: 2081.1951 | W7: 2094.3355 | X7: 2108.4023 | Y7: 2123.5054 | Z7: 2139.7387 | AA7: 2157.0899 | AB7: 2175.6235 | AC7: 2195.4515 | AD7: 2216.7171 | AE7: 2239.5788 | AF7: 2264.2011 | AG7: 2290.7608 | AH7: 2319.4597 | AI7: 2350.5386 | AJ7: 2384.2907 | AK7: 2416.898
A8: f_k_sfoo_2 | B8: 74526.379 | C8: 75429.933 | D8: 76405.392 | E8: 77473.102 | F8: 78643.982 | G8: 79925.634 | H8: 81321.538 | I8: 82833.476 | J8: 84463.754 | K8: 86237.022 | L8: 88164.629 | M8: 90228.69 | N8: 92406.886 | O8: 94678.333 | P8: 97026.399 | Q8: 99438.476 | R8: 101909.31 | S8: 104436.42 | T8: 107020.58 | U8: 109665.22 | V8: 112374.3 | W8: 115154.71 | X8: 118015.09 | Y8: 120965.31 | Z8: 124015.23 | AA8: 127169.5 | AB8: 130431.99 | AC8: 133808.2 | AD8: 137305.13 | AE8: 140929.8 | AF8: 144687.3 | AG8: 148579.51 | AH8: 152604.67 | AI8: 156757.83 | AJ8: 161030.75 | AK8: 165089.01
A9: f_k_sfoo_0 | B9: 74526.379 | C9: 75429.933 | D9: 76405.392 | E9: 77473.102 | F9: 78643.982 | G9: 79925.634 | H9: 81323.526 | I9: 82840.416 | J9: 84477.726 | K9: 86236.392 | L9: 88114.619 | M9: 90094.376 | N9: 92155.768 | O9: 94280.662 | P9: 96454.292 | Q9: 98665.877 | R9: 100908.11 | S9: 103180.11 | T9: 105485.25 | U9: 107829.37 | V9: 110218.41 | W9: 112661.11 | X9: 115167.95 | Y9: 117750.38 | Z9: 120419.63 | AA9: 123182.09 | AB9: 126046.45 | AC9: 129023.11 | AD9: 132123.58 | AE9: 135358.77 | AF9: 138737.53 | AG9: 142266.06 | AH9: 145948.05 | AI9: 149784.62 | AJ9: 153774.3 | AK9: 157604.7
A10: f_k_sveh_2 | B10: 401529.23 | C10: 406775.67 | D10: 412954.31 | E10: 420105.65 | F10: 428210.08 | G10: 437220.68 | H10: 447079.64 | I10: 457379.8 | J10: 467992.12 | K10: 479251.54 | L10: 491171.66 | M10: 503464.72 | N10: 515838.69 | O10: 528100.39 | P10: 540190.63 | Q10: 552143.14 | R10: 563974.09 | S10: 575762.99 | T10: 587629.01 | U10: 599705.46 | V10: 612127.78 | W10: 625033.46 | X10: 638563.31 | Y10: 652856.82 | Z10: 668041.87 | AA10: 684227.06 | AB10: 701551.02 | AC10: 720129.59 | AD10: 740062.41 | AE10: 761412.4 | AF10: 784193.78 | AG10: 808378.76 | AH10: 833909.84 | AI10: 860709.17 | AJ10: 888683.53 | AK10: 915697.54
A11: f_k_sveh_0 | B11: 401529.23 | C11: 406775.67 | D11: 412954.31 | E11: 420105.65 | F11: 428210.08 | G11: 437220.68 | H11: 447069.64 | I11: 457692.18 | J11: 469043.46 | K11: 481100.03 | L11: 493791.87 | M11: 506846.74 | N11: 520035.17 | O11: 533208.61 | P11: 546302.89 | Q11: 559322.42 | R11: 572340.05 | S11: 585471.83 | T11: 598851 | U11: 612608.61 | V11: 626867.69 | W11: 641748.54 | X11: 657373.13 | Y11: 673860.11 | Z11: 691313.3 | AA11: 709813.56 | AB11: 729437.75 | AC11: 750266.26 | AD11: 772373.95 | AE11: 795801.6 | AF11: 820541.4 | AG11: 846545.5 | AH11: 873741.03 | AI11: 902039.39 | AJ11: 931340.54 | AK11: 959544.64
A12: f_k_sgla_2 | B12: 16084.261 | C12: 16281 | D12: 16494.941 | E12: 16729.633 | F12: 16986.238 | G12: 17265.882 | H12: 17569.401 | I12: 17897.046 | J12: 18248.064 | K12: 18627.534 | L12: 19037.782 | M12: 19475.164 | N12: 19936.212 | O12: 20418.703 | P12: 20922.039 | Q12: 21446.852 | R12: 21995.854 | S12: 22571.518 | T12: 23176.625 | U12: 23814.302 | V12: 24487.798 | W12: 25200.647 | X12: 25956.652 | Y12: 26759.742 | Z12: 27613.67 | AA12: 28521.311 | AB12: 29484.721 | AC12: 30506.219 | AD12: 31588.373 | AE12: 32733.717 | AF12: 33944.497 | AG12: 35222.683 | AH12: 36570.199 | AI12: 37989.239 | AJ12: 39482.504 | AK12: 40940.948
... A67: f_k_seot_0 | B67: 65.175815 | C67: 65.949181 | D67: 66.745822 | E67: 67.569103 | F67: 68.413249 | G67: 69.276228 | H67: 70.160712 | I67: 71.173093 | J67: 72.37154 | K67: 73.783172 | L67: 75.420477 | M67: 77.2786 | N67: 79.349126 | O67: 81.625644 | P67: 84.106695 | Q67: 86.797154 | R67: 89.706612 | S67: 92.852631 | T67: 96.261682 | U67: 99.968849 | V67: 104.017 | W67: 108.45914 | X67: 113.35886 | Y67: 118.79106 | Z67: 124.8429 | AA67: 131.61226 | AB67: 139.21569 | AC67: 147.79196 | AD67: 157.50539 | AE67: 168.54778 | AF67: 181.14199 | AG67: 195.54951 | AH67: 212.08275 | AI67: 231.12255 | AJ67: 253.14272 | AK67: 275.38153

Sheet Results
A1: NB : on crée ici une liste : - globale, qui fusionne les sorties des reportings 1, 2 et 3 - "rationalisée" : suppression des doublons, et regroupements par thématique On continue par la suite à avoir 2 Excels de reporting (un "energie", fusion des reportings 1 et 2), et un "économie" (reporting 3)), dans lesquels on copiera cet onglet "results" (généré automatiquement par EViews). --> puis voir à la fin si on peut pas importer les graphs et tableaux dans l'excel automatiquement généré (éviterait les copiés collés, mais à voir si ça prend trop de temps, et si c'est pas trop gros comme excel)
A2: Nom du bloc de variables utilisé dans le code | B2: Sous-bloc de variables pour plus de lisibilité dans le Excel | E2: Year | F2: =date!B3 -> 2015 | G2: =date!C3 -> 2016 | H2: =date!D3 -> 2017 | I2: =date!E3 -> 2018 | J2: =date!F3 -> 2019 | K2: =date!G3 -> 2020 | L2: =date!H3 -> 2021 | M2: =date!I3 -> 2022 | ... AO2: =date!AK3 -> 2050
A3: HYBRID | B3: AUTOMOBILES (thousands) | C3: TOTAL STOCK SHOCK | E3: AUTO_2 | F3: =VLOOKUP($E3,Hybrid!$1:$1048576,MATCH(DATE(F$2,1,1),Hybrid!$A$1:$LI$1),FALSE) -> 32317.941 | G3: =VLOOKUP($E3,Hybrid!$1:$1048576,MATCH(DATE(G$2,1,1),Hybrid!$A$1:$LI$1),FALSE) -> 31918.631 | H3: =VLOOKUP($E3,Hybrid!$1:$1048576,MATCH(DATE(H$2,1,1),Hybrid!$A$1:$LI$1),FALSE) -> 31759.311 | I3: =VLOOKUP($E3,Hybrid!$1:$1048576,MATCH(DATE(I$2,1,1),Hybrid!$A$1:$LI$1),FALSE) -> 31761.553 | J3: =VLOOKUP($E3,Hybrid!$1:$1048576,MATCH(DATE(J$2,1,1),Hybrid!$A$1:$LI$1),FALSE) -> 31899.124 | K3: =VLOOKUP($E3,Hybrid!$1:$1048576,MATCH(DATE(K$2,1,1),Hybrid!$A$1:$LI$1),FALSE) -> 32133.592 | L3: =VLOOKUP($E3,Hybrid!$1:$1048576,MATCH(DATE(L$2,1,1),Hybrid!$A$1:$LI$1),FALSE) -> 32430.086 | M3: =VLOOKUP($E3,Hybrid!$1:$1048576,MATCH(DATE(M$2,1,1),Hybrid!$A$1:$LI$1),FALSE) -> 32666.633 | ... AO3: =VLOOKUP($E3,Hybrid!$1:$1048576,MATCH(DATE(AO$2,1,1),Hybrid!$A$1:$LI$1),FALSE) -> 42732.091
C4: OIL | E4: AUTO_cfut_2 | F4: =VLOOKUP($E4,Hybrid!$1:$1048576,MATCH(DATE(F$2,1,1),Hybrid!$A$1:$LI$1),FALSE) -> 32271.24 | G4: =VLOOKUP($E4,Hybrid!$1:$1048576,MATCH(DATE(G$2,1,1),Hybrid!$A$1:$LI$1),FALSE) -> 31853.75 | H4: =VLOOKUP($E4,Hybrid!$1:$1048576,MATCH(DATE(H$2,1,1),Hybrid!$A$1:$LI$1),FALSE) -> 31674.362 | I4: =VLOOKUP($E4,Hybrid!$1:$1048576,MATCH(DATE(I$2,1,1),Hybrid!$A$1:$LI$1),FALSE) -> 31654.909 | J4: =VLOOKUP($E4,Hybrid!$1:$1048576,MATCH(DATE(J$2,1,1),Hybrid!$A$1:$LI$1),FALSE) -> 31769.037 | K4: =VLOOKUP($E4,Hybrid!$1:$1048576,MATCH(DATE(K$2,1,1),Hybrid!$A$1:$LI$1),FALSE) -> 31978.673 | L4: =VLOOKUP($E4,Hybrid!$1:$1048576,MATCH(DATE(L$2,1,1),Hybrid!$A$1:$LI$1),FALSE) -> 32249.27 | M4: =VLOOKUP($E4,Hybrid!$1:$1048576,MATCH(DATE(M$2,1,1),Hybrid!$A$1:$LI$1),FALSE) -> 32459.098 | ... AO4: =VLOOKUP($E4,Hybrid!$1:$1048576,MATCH(DATE(AO$2,1,1),Hybrid!$A$1:$LI$1),FALSE) -> 35009.221
D5: class A | E5: AUTO_ca_cfut_2 | F5: =VLOOKUP($E5,Hybrid!$1:$1048576,MATCH(DATE(F$2,1,1),Hybrid!$A$1:$LI$1),FALSE) -> 7095.7005 | G5: =VLOOKUP($E5,Hybrid!$1:$1048576,MATCH(DATE(G$2,1,1),Hybrid!$A$1:$LI$1),FALSE) -> 7138.9134 | H5: =VLOOKUP($E5,Hybrid!$1:$1048576,MATCH(DATE(H$2,1,1),Hybrid!$A$1:$LI$1),FALSE) -> 7241.8937 | I5: =VLOOKUP($E5,Hybrid!$1:$1048576,MATCH(DATE(I$2,1,1),Hybrid!$A$1:$LI$1),FALSE) -> 7384.5407 | J5: =VLOOKUP($E5,Hybrid!$1:$1048576,MATCH(DATE(J$2,1,1),Hybrid!$A$1:$LI$1),FALSE) -> 7560.8902 | K5: =VLOOKUP($E5,Hybrid!$1:$1048576,MATCH(DATE(K$2,1,1),Hybrid!$A$1:$LI$1),FALSE) -> 7760.7036 | L5: =VLOOKUP($E5,Hybrid!$1:$1048576,MATCH(DATE(L$2,1,1),Hybrid!$A$1:$LI$1),FALSE) -> 7974.6489 | M5: =VLOOKUP($E5,Hybrid!$1:$1048576,MATCH(DATE(M$2,1,1),Hybrid!$A$1:$LI$1),FALSE) -> 8168.5328 | ... AO5: =VLOOKUP($E5,Hybrid!$1:$1048576,MATCH(DATE(AO$2,1,1),Hybrid!$A$1:$LI$1),FALSE) -> 11491.393
D6: class B | E6: AUTO_cb_cfut_2 | F6: =VLOOKUP($E6,Hybrid!$1:$1048576,MATCH(DATE(F$2,1,1),Hybrid!$A$1:$LI$1),FALSE) -> 8251.2564 | G6: =VLOOKUP($E6,Hybrid!$1:$1048576,MATCH(DATE(G$2,1,1),Hybrid!$A$1:$LI$1),FALSE) -> 8180.0639 | H6: =VLOOKUP($E6,Hybrid!$1:$1048576,MATCH(DATE(H$2,1,1),Hybrid!$A$1:$LI$1),FALSE) -> 8173.9007 | I6: =VLOOKUP($E6,Hybrid!$1:$1048576,MATCH(DATE(I$2,1,1),Hybrid!$A$1:$LI$1),FALSE) -> 8212.4993 | J6: =VLOOKUP($E6,Hybrid!$1:$1048576,MATCH(DATE(J$2,1,1),Hybrid!$A$1:$LI$1),FALSE) -> 8289.337 | K6: =VLOOKUP($E6,Hybrid!$1:$1048576,MATCH(DATE(K$2,1,1),Hybrid!$A$1:$LI$1),FALSE) -> 8394.1234 | L6: =VLOOKUP($E6,Hybrid!$1:$1048576,MATCH(DATE(L$2,1,1),Hybrid!$A$1:$LI$1),FALSE) -> 8517.4157 | M6: =VLOOKUP($E6,Hybrid!$1:$1048576,MATCH(DATE(M$2,1,1),Hybrid!$A$1:$LI$1),FALSE) -> 8625.5607 | ... AO6: =VLOOKUP($E6,Hybrid!$1:$1048576,MATCH(DATE(AO$2,1,1),Hybrid!$A$1:$LI$1),FALSE) -> 10545.568
D7: class C | E7: AUTO_cc_cfut_2 | F7: =VLOOKUP($E7,Hybrid!$1:$1048576,MATCH(DATE(F$2,1,1),Hybrid!$A$1:$LI$1),FALSE) -> 6777.6025 | G7: =VLOOKUP($E7,Hybrid!$1:$1048576,MATCH(DATE(G$2,1,1),Hybrid!$A$1:$LI$1),FALSE) -> 6644.8772 | H7: =VLOOKUP($E7,Hybrid!$1:$1048576,MATCH(DATE(H$2,1,1),Hybrid!$A$1:$LI$1),FALSE) -> 6562.8912 | I7: =VLOOKUP($E7,Hybrid!$1:$1048576,MATCH(DATE(I$2,1,1),Hybrid!$A$1:$LI$1),FALSE) -> 6516.918 | J7: =VLOOKUP($E7,Hybrid!$1:$1048576,MATCH(DATE(J$2,1,1),Hybrid!$A$1:$LI$1),FALSE) -> 6501.8685 | K7: =VLOOKUP($E7,Hybrid!$1:$1048576,MATCH(DATE(K$2,1,1),Hybrid!$A$1:$LI$1),FALSE) -> 6510.2772 | L7: =VLOOKUP($E7,Hybrid!$1:$1048576,MATCH(DATE(L$2,1,1),Hybrid!$A$1:$LI$1),FALSE) -> 6535.2531 | M7: =VLOOKUP($E7,Hybrid!$1:$1048576,MATCH(DATE(M$2,1,1),Hybrid!$A$1:$LI$1),FALSE) -> 6552.9237 | ... AO7: =VLOOKUP($E7,Hybrid!$1:$1048576,MATCH(DATE(AO$2,1,1),Hybrid!$A$1:$LI$1),FALSE) -> 6882.4965
D8: class D | E8: AUTO_cd_cfut_2 | F8: =VLOOKUP($E8,Hybrid!$1:$1048576,MATCH(DATE(F$2,1,1),Hybrid!$A$1:$LI$1),FALSE) -> 4159.6639 | G8: =VLOOKUP($E8,Hybrid!$1:$1048576,MATCH(DATE(G$2,1,1),Hybrid!$A$1:$LI$1),FALSE) -> 4053.7616 | H8: =VLOOKUP($E8,Hybrid!$1:$1048576,MATCH(DATE(H$2,1,1),Hybrid!$A$1:$LI$1),FALSE) -> 3976.8722 | I8: =VLOOKUP($E8,Hybrid!$1:$1048576,MATCH(DATE(I$2,1,1),Hybrid!$A$1:$LI$1),FALSE) -> 3920.2702 | J8: =VLOOKUP($E8,Hybrid!$1:$1048576,MATCH(DATE(J$2,1,1),Hybrid!$A$1:$LI$1),FALSE) -> 3880.7049 | K8: =VLOOKUP($E8,Hybrid!$1:$1048576,MATCH(DATE(K$2,1,1),Hybrid!$A$1:$LI$1),FALSE) -> 3853.8714 | L8: =VLOOKUP($E8,Hybrid!$1:$1048576,MATCH(DATE(L$2,1,1),Hybrid!$A$1:$LI$1),FALSE) -> 3835.8285 | M8: =VLOOKUP($E8,Hybrid!$1:$1048576,MATCH(DATE(M$2,1,1),Hybrid!$A$1:$LI$1),FALSE) -> 3813.4535 | ... AO8: =VLOOKUP($E8,Hybrid!$1:$1048576,MATCH(DATE(AO$2,1,1),Hybrid!$A$1:$LI$1),FALSE) -> 3412.0546
D9: class E | E9: AUTO_ce_cfut_2 | F9: =VLOOKUP($E9,Hybrid!$1:$1048576,MATCH(DATE(F$2,1,1),Hybrid!$A$1:$LI$1),FALSE) -> 2503.7292 | G9: =VLOOKUP($E9,Hybrid!$1:$1048576,MATCH(DATE(G$2,1,1),Hybrid!$A$1:$LI$1),FALSE) -> 2442.3141 | H9: =VLOOKUP($E9,Hybrid!$1:$1048576,MATCH(DATE(H$2,1,1),Hybrid!$A$1:$LI$1),FALSE) -> 2397.5371 | I9: =VLOOKUP($E9,Hybrid!$1:$1048576,MATCH(DATE(I$2,1,1),Hybrid!$A$1:$LI$1),FALSE) -> 2363.8546 | J9: =VLOOKUP($E9,Hybrid!$1:$1048576,MATCH(DATE(J$2,1,1),Hybrid!$A$1:$LI$1),FALSE) -> 2339.1637 | K9: =VLOOKUP($E9,Hybrid!$1:$1048576,MATCH(DATE(K$2,1,1),Hybrid!$A$1:$LI$1),FALSE) -> 2320.8652 | L9: =VLOOKUP($E9,Hybrid!$1:$1048576,MATCH(DATE(L$2,1,1),Hybrid!$A$1:$LI$1),FALSE) -> 2306.5983 | M9: =VLOOKUP($E9,Hybrid!$1:$1048576,MATCH(DATE(M$2,1,1),Hybrid!$A$1:$LI$1),FALSE) -> 2288.4363 | ... AO9: =VLOOKUP($E9,Hybrid!$1:$1048576,MATCH(DATE(AO$2,1,1),Hybrid!$A$1:$LI$1),FALSE) -> 1677.9123
D10: class F | E10: AUTO_cf_cfut_2 | F10: =VLOOKUP($E10,Hybrid!$1:$1048576,MATCH(DATE(F$2,1,1),Hybrid!$A$1:$LI$1),FALSE) -> 1243.6668 | G10: =VLOOKUP($E10,Hybrid!$1:$1048576,MATCH(DATE(G$2,1,1),Hybrid!$A$1:$LI$1),FALSE) -> 1210.5103 | H10: =VLOOKUP($E10,Hybrid!$1:$1048576,MATCH(DATE(H$2,1,1),Hybrid!$A$1:$LI$1),FALSE) -> 1184.1996 | I10: =VLOOKUP($E10,Hybrid!$1:$1048576,MATCH(DATE(I$2,1,1),Hybrid!$A$1:$LI$1),FALSE) -> 1161.7685 | J10: =VLOOKUP($E10,Hybrid!$1:$1048576,MATCH(DATE(J$2,1,1),Hybrid!$A$1:$LI$1),FALSE) -> 1142.0394 | K10: =VLOOKUP($E10,Hybrid!$1:$1048576,MATCH(DATE(K$2,1,1),Hybrid!$A$1:$LI$1),FALSE) -> 1123.8073 | L10: =VLOOKUP($E10,Hybrid!$1:$1048576,MATCH(DATE(L$2,1,1),Hybrid!$A$1:$LI$1),FALSE) -> 1106.0439 | M10: =VLOOKUP($E10,Hybrid!$1:$1048576,MATCH(DATE(M$2,1,1),Hybrid!$A$1:$LI$1),FALSE) -> 1085.3372 | ... AO10: =VLOOKUP($E10,Hybrid!$1:$1048576,MATCH(DATE(AO$2,1,1),Hybrid!$A$1:$LI$1),FALSE) -> 457.31925
D11: class G | E11: AUTO_cg_cfut_2 | F11: =VLOOKUP($E11,Hybrid!$1:$1048576,MATCH(DATE(F$2,1,1),Hybrid!$A$1:$LI$1),FALSE) -> 2239.6206 | G11: =VLOOKUP($E11,Hybrid!$1:$1048576,MATCH(DATE(G$2,1,1),Hybrid!$A$1:$LI$1),FALSE) -> 2183.3099 | H11: =VLOOKUP($E11,Hybrid!$1:$1048576,MATCH(DATE(H$2,1,1),Hybrid!$A$1:$LI$1),FALSE) -> 2137.0676 | I11: =VLOOKUP($E11,Hybrid!$1:$1048576,MATCH(DATE(I$2,1,1),Hybrid!$A$1:$LI$1),FALSE) -> 2095.0577 | J11: =VLOOKUP($E11,Hybrid!$1:$1048576,MATCH(DATE(J$2,1,1),Hybrid!$A$1:$LI$1),FALSE) -> 2055.0332 | K11: =VLOOKUP($E11,Hybrid!$1:$1048576,MATCH(DATE(K$2,1,1),Hybrid!$A$1:$LI$1),FALSE) -> 2015.0245 | L11: =VLOOKUP($E11,Hybrid!$1:$1048576,MATCH(DATE(L$2,1,1),Hybrid!$A$1:$LI$1),FALSE) -> 1973.4819 | M11: =VLOOKUP($E11,Hybrid!$1:$1048576,MATCH(DATE(M$2,1,1),Hybrid!$A$1:$LI$1),FALSE) -> 1924.8534 | ... AO11: =VLOOKUP($E11,Hybrid!$1:$1048576,MATCH(DATE(AO$2,1,1),Hybrid!$A$1:$LI$1),FALSE) -> 542.47741
C12: ELEC | E12: AUTO_cele_2 | F12: =VLOOKUP($E12,Hybrid!$1:$1048576,MATCH(DATE(F$2,1,1),Hybrid!$A$1:$LI$1),FALSE) -> 44.765 | G12: =VLOOKUP($E12,Hybrid!$1:$1048576,MATCH(DATE(G$2,1,1),Hybrid!$A$1:$LI$1),FALSE) -> 62.889352 | H12: =VLOOKUP($E12,Hybrid!$1:$1048576,MATCH(DATE(H$2,1,1),Hybrid!$A$1:$LI$1),FALSE) -> 82.889294 | I12: =VLOOKUP($E12,Hybrid!$1:$1048576,MATCH(DATE(I$2,1,1),Hybrid!$A$1:$LI$1),FALSE) -> 104.50723 | J12: =VLOOKUP($E12,Hybrid!$1:$1048576,MATCH(DATE(J$2,1,1),Hybrid!$A$1:$LI$1),FALSE) -> 127.86793 | K12: =VLOOKUP($E12,Hybrid!$1:$1048576,MATCH(DATE(K$2,1,1),Hybrid!$A$1:$LI$1),FALSE) -> 152.61341 | L12: =VLOOKUP($E12,Hybrid!$1:$1048576,MATCH(DATE(L$2,1,1),Hybrid!$A$1:$LI$1),FALSE) -> 178.42191 | M12: =VLOOKUP($E12,Hybrid!$1:$1048576,MATCH(DATE(M$2,1,1),Hybrid!$A$1:$LI$1),FALSE) -> 205.06274 | ... AO12: =VLOOKUP($E12,Hybrid!$1:$1048576,MATCH(DATE(AO$2,1,1),Hybrid!$A$1:$LI$1),FALSE) -> 8081.4317
D13: class A | E13: AUTO_ca_cele_2 | F13: =VLOOKUP($E13,Hybrid!$1:$1048576,MATCH(DATE(F$2,1,1),Hybrid!$A$1:$LI$1),FALSE) -> 9.8427899 | G13: =VLOOKUP($E13,Hybrid!$1:$1048576,MATCH(DATE(G$2,1,1),Hybrid!$A$1:$LI$1),FALSE) -> 15.123232 | H13: =VLOOKUP($E13,Hybrid!$1:$1048576,MATCH(DATE(H$2,1,1),Hybrid!$A$1:$LI$1),FALSE) -> 20.991591 | I13: =VLOOKUP($E13,Hybrid!$1:$1048576,MATCH(DATE(I$2,1,1),Hybrid!$A$1:$LI$1),FALSE) -> 27.398546 | J13: =VLOOKUP($E13,Hybrid!$1:$1048576,MATCH(DATE(J$2,1,1),Hybrid!$A$1:$LI$1),FALSE) -> 34.399336 | K13: =VLOOKUP($E13,Hybrid!$1:$1048576,MATCH(DATE(K$2,1,1),Hybrid!$A$1:$LI$1),FALSE) -> 41.894067 | L13: =VLOOKUP($E13,Hybrid!$1:$1048576,MATCH(DATE(L$2,1,1),Hybrid!$A$1:$LI$1),FALSE) -> 49.793243 | M13: =VLOOKUP($E13,Hybrid!$1:$1048576,MATCH(DATE(M$2,1,1),Hybrid!$A$1:$LI$1),FALSE) -> 58.068705 | ... AO13: =VLOOKUP($E13,Hybrid!$1:$1048576,MATCH(DATE(AO$2,1,1),Hybrid!$A$1:$LI$1),FALSE) -> 2886.1679
D14: class B | E14: AUTO_cb_cele_2 | F14: =VLOOKUP($E14,Hybrid!$1:$1048576,MATCH(DATE(F$2,1,1),Hybrid!$A$1:$LI$1),FALSE) -> 11.445717 | G14: =VLOOKUP($E14,Hybrid!$1:$1048576,MATCH(DATE(G$2,1,1),Hybrid!$A$1:$LI$1),FALSE) -> 16.441946 | H14: =VLOOKUP($E14,Hybrid!$1:$1048576,MATCH(DATE(H$2,1,1),Hybrid!$A$1:$LI$1),FALSE) -> 22.010704 | I14: =VLOOKUP($E14,Hybrid!$1:$1048576,MATCH(DATE(I$2,1,1),Hybrid!$A$1:$LI$1),FALSE) -> 28.107951 | J14: =VLOOKUP($E14,Hybrid!$1:$1048576,MATCH(DATE(J$2,1,1),Hybrid!$A$1:$LI$1),FALSE) -> 34.789079 | K14: =VLOOKUP($E14,Hybrid!$1:$1048576,MATCH(DATE(K$2,1,1),Hybrid!$A$1:$LI$1),FALSE) -> 41.955856 | L14: =VLOOKUP($E14,Hybrid!$1:$1048576,MATCH(DATE(L$2,1,1),Hybrid!$A$1:$LI$1),FALSE) -> 49.51981 | M14: =VLOOKUP($E14,Hybrid!$1:$1048576,MATCH(DATE(M$2,1,1),Hybrid!$A$1:$LI$1),FALSE) -> 57.461117 | ... AO14: =VLOOKUP($E14,Hybrid!$1:$1048576,MATCH(DATE(AO$2,1,1),Hybrid!$A$1:$LI$1),FALSE) -> 2706.1264
D15: class C | E15: AUTO_cc_cele_2 | F15: =VLOOKUP($E15,Hybrid!$1:$1048576,MATCH(DATE(F$2,1,1),Hybrid!$A$1:$LI$1),FALSE) -> 9.4015406 | G15: =VLOOKUP($E15,Hybrid!$1:$1048576,MATCH(DATE(G$2,1,1),Hybrid!$A$1:$LI$1),FALSE) -> 12.804718 | H15: =VLOOKUP($E15,Hybrid!$1:$1048576,MATCH(DATE(H$2,1,1),Hybrid!$A$1:$LI$1),FALSE) -> 16.609264 | I15: =VLOOKUP($E15,Hybrid!$1:$1048576,MATCH(DATE(I$2,1,1),Hybrid!$A$1:$LI$1),FALSE) -> 20.786573 | J15: =VLOOKUP($E15,Hybrid!$1:$1048576,MATCH(DATE(J$2,1,1),Hybrid!$A$1:$LI$1),FALSE) -> 25.376235 | K15: =VLOOKUP($E15,Hybrid!$1:$1048576,MATCH(DATE(K$2,1,1),Hybrid!$A$1:$LI$1),FALSE) -> 30.30866 | L15: =VLOOKUP($E15,Hybrid!$1:$1048576,MATCH(DATE(L$2,1,1),Hybrid!$A$1:$LI$1),FALSE) -> 35.520855 | M15: =VLOOKUP($E15,Hybrid!$1:$1048576,MATCH(DATE(M$2,1,1),Hybrid!$A$1:$LI$1),FALSE) -> 41.002841 | ... AO15: =VLOOKUP($E15,Hybrid!$1:$1048576,MATCH(DATE(AO$2,1,1),Hybrid!$A$1:$LI$1),FALSE) -> 1821.9223
D16: class D | E16: AUTO_cd_cele_2 | F16: =VLOOKUP($E16,Hybrid!$1:$1048576,MATCH(DATE(F$2,1,1),Hybrid!$A$1:$LI$1),FALSE) -> 5.7700713 | G16: =VLOOKUP($E16,Hybrid!$1:$1048576,MATCH(DATE(G$2,1,1),Hybrid!$A$1:$LI$1),FALSE) -> 7.5870606 | H16: =VLOOKUP($E16,Hybrid!$1:$1048576,MATCH(DATE(H$2,1,1),Hybrid!$A$1:$LI$1),FALSE) -> 9.5658742 | I16: =VLOOKUP($E16,Hybrid!$1:$1048576,MATCH(DATE(I$2,1,1),Hybrid!$A$1:$LI$1),FALSE) -> 11.661626 | J16: =VLOOKUP($E16,Hybrid!$1:$1048576,MATCH(DATE(J$2,1,1),Hybrid!$A$1:$LI$1),FALSE) -> 13.871889 | K16: =VLOOKUP($E16,Hybrid!$1:$1048576,MATCH(DATE(K$2,1,1),Hybrid!$A$1:$LI$1),FALSE) -> 16.161271 | L16: =VLOOKUP($E16,Hybrid!$1:$1048576,MATCH(DATE(L$2,1,1),Hybrid!$A$1:$LI$1),FALSE) -> 18.496851 | M16: =VLOOKUP($E16,Hybrid!$1:$1048576,MATCH(DATE(M$2,1,1),Hybrid!$A$1:$LI$1),FALSE) -> 20.810544 | ... AO16: =VLOOKUP($E16,Hybrid!$1:$1048576,MATCH(DATE(AO$2,1,1),Hybrid!$A$1:$LI$1),FALSE) -> 404.40471
D17: class E | E17: AUTO_ce_cele_2 | F17: =VLOOKUP($E17,Hybrid!$1:$1048576,MATCH(DATE(F$2,1,1),Hybrid!$A$1:$LI$1),FALSE) -> 3.4730441 | G17: =VLOOKUP($E17,Hybrid!$1:$1048576,MATCH(DATE(G$2,1,1),Hybrid!$A$1:$LI$1),FALSE) -> 4.5917108 | H17: =VLOOKUP($E17,Hybrid!$1:$1048576,MATCH(DATE(H$2,1,1),Hybrid!$A$1:$LI$1),FALSE) -> 5.8046001 | I17: =VLOOKUP($E17,Hybrid!$1:$1048576,MATCH(DATE(I$2,1,1),Hybrid!$A$1:$LI$1),FALSE) -> 7.0827696 | J17: =VLOOKUP($E17,Hybrid!$1:$1048576,MATCH(DATE(J$2,1,1),Hybrid!$A$1:$LI$1),FALSE) -> 8.4233535 | K17: =VLOOKUP($E17,Hybrid!$1:$1048576,MATCH(DATE(K$2,1,1),Hybrid!$A$1:$LI$1),FALSE) -> 9.8032197 | L17: =VLOOKUP($E17,Hybrid!$1:$1048576,MATCH(DATE(L$2,1,1),Hybrid!$A$1:$LI$1),FALSE) -> 11.201005 | M17: =VLOOKUP($E17,Hybrid!$1:$1048576,MATCH(DATE(M$2,1,1),Hybrid!$A$1:$LI$1),FALSE) -> 12.575823 | ... AO17: =VLOOKUP($E17,Hybrid!$1:$1048576,MATCH(DATE(AO$2,1,1),Hybrid!$A$1:$LI$1),FALSE) -> 204.85521
D18: class F | E18: AUTO_cf_cele_2 | F18: =VLOOKUP($E18,Hybrid!$1:$1048576,MATCH(DATE(F$2,1,1),Hybrid!$A$1:$LI$1),FALSE) -> 1.7251505 | G18: =VLOOKUP($E18,Hybrid!$1:$1048576,MATCH(DATE(G$2,1,1),Hybrid!$A$1:$LI$1),FALSE) -> 2.2518855 | H18: =VLOOKUP($E18,Hybrid!$1:$1048576,MATCH(DATE(H$2,1,1),Hybrid!$A$1:$LI$1),FALSE) -> 2.80569 | I18: =VLOOKUP($E18,Hybrid!$1:$1048576,MATCH(DATE(I$2,1,1),Hybrid!$A$1:$LI$1),FALSE) -> 3.3665411 | J18: =VLOOKUP($E18,Hybrid!$1:$1048576,MATCH(DATE(J$2,1,1),Hybrid!$A$1:$LI$1),FALSE) -> 3.9283843 | K18: =VLOOKUP($E18,Hybrid!$1:$1048576,MATCH(DATE(K$2,1,1),Hybrid!$A$1:$LI$1),FALSE) -> 4.4801406 | L18: =VLOOKUP($E18,Hybrid!$1:$1048576,MATCH(DATE(L$2,1,1),Hybrid!$A$1:$LI$1),FALSE) -> 5.0121241 | M18: =VLOOKUP($E18,Hybrid!$1:$1048576,MATCH(DATE(M$2,1,1),Hybrid!$A$1:$LI$1),FALSE) -> 5.5005073 | ... AO18: =VLOOKUP($E18,Hybrid!$1:$1048576,MATCH(DATE(AO$2,1,1),Hybrid!$A$1:$LI$1),FALSE) -> 28.730623
D19: class G | E19: AUTO_cg_cele_2 | F19: =VLOOKUP($E19,Hybrid!$1:$1048576,MATCH(DATE(F$2,1,1),Hybrid!$A$1:$LI$1),FALSE) -> 3.1066862 | G19: =VLOOKUP($E19,Hybrid!$1:$1048576,MATCH(DATE(G$2,1,1),Hybrid!$A$1:$LI$1),FALSE) -> 4.0887993 | H19: =VLOOKUP($E19,Hybrid!$1:$1048576,MATCH(DATE(H$2,1,1),Hybrid!$A$1:$LI$1),FALSE) -> 5.1015716 | I19: =VLOOKUP($E19,Hybrid!$1:$1048576,MATCH(DATE(I$2,1,1),Hybrid!$A$1:$LI$1),FALSE) -> 6.1032213 | J19: =VLOOKUP($E19,Hybrid!$1:$1048576,MATCH(DATE(J$2,1,1),Hybrid!$A$1:$LI$1),FALSE) -> 7.0796515 | K19: =VLOOKUP($E19,Hybrid!$1:$1048576,MATCH(DATE(K$2,1,1),Hybrid!$A$1:$LI$1),FALSE) -> 8.0101921 | L19: =VLOOKUP($E19,Hybrid!$1:$1048576,MATCH(DATE(L$2,1,1),Hybrid!$A$1:$LI$1),FALSE) -> 8.8780269 | M19: =VLOOKUP($E19,Hybrid!$1:$1048576,MATCH(DATE(M$2,1,1),Hybrid!$A$1:$LI$1),FALSE) -> 9.6431996 | ... AO19: =VLOOKUP($E19,Hybrid!$1:$1048576,MATCH(DATE(AO$2,1,1),Hybrid!$A$1:$LI$1),FALSE) -> 29.224625
C20: GAS | E20: AUTO_cgas_2 | F20: =VLOOKUP($E20,Hybrid!$1:$1048576,MATCH(DATE(F$2,1,1),Hybrid!$A$1:$LI$1),FALSE) -> 1.936 | G20: =VLOOKUP($E20,Hybrid!$1:$1048576,MATCH(DATE(G$2,1,1),Hybrid!$A$1:$LI$1),FALSE) -> 1.9909099 | H20: =VLOOKUP($E20,Hybrid!$1:$1048576,MATCH(DATE(H$2,1,1),Hybrid!$A$1:$LI$1),FALSE) -> 2.0596615 | I20: =VLOOKUP($E20,Hybrid!$1:$1048576,MATCH(DATE(I$2,1,1),Hybrid!$A$1:$LI$1),FALSE) -> 2.1363797 | J20: =VLOOKUP($E20,Hybrid!$1:$1048576,MATCH(DATE(J$2,1,1),Hybrid!$A$1:$LI$1),FALSE) -> 2.2193981 | K20: =VLOOKUP($E20,Hybrid!$1:$1048576,MATCH(DATE(K$2,1,1),Hybrid!$A$1:$LI$1),FALSE) -> 2.3059977 | L20: =VLOOKUP($E20,Hybrid!$1:$1048576,MATCH(DATE(L$2,1,1),Hybrid!$A$1:$LI$1),FALSE) -> 2.3936768 | M20: =VLOOKUP($E20,Hybrid!$1:$1048576,MATCH(DATE(M$2,1,1),Hybrid!$A$1:$LI$1),FALSE) -> 2.4725398 | ... AO20: =VLOOKUP($E20,Hybrid!$1:$1048576,MATCH(DATE(AO$2,1,1),Hybrid!$A$1:$LI$1),FALSE) -> 3.5012802
D21: class A | E21: AUTO_ca_cgas_2 | F21: =VLOOKUP($E21,Hybrid!$1:$1048576,MATCH(DATE(F$2,1,1),Hybrid!$A$1:$LI$1),FALSE) -> 0.4256817 | G21: =VLOOKUP($E21,Hybrid!$1:$1048576,MATCH(DATE(G$2,1,1),Hybrid!$A$1:$LI$1),FALSE) -> 0.44909736 | H21: =VLOOKUP($E21,Hybrid!$1:$1048576,MATCH(DATE(H$2,1,1),Hybrid!$A$1:$LI$1),FALSE) -> 0.47635319 | I21: =VLOOKUP($E21,Hybrid!$1:$1048576,MATCH(DATE(I$2,1,1),Hybrid!$A$1:$LI$1),FALSE) -> 0.50591124 | J21: =VLOOKUP($E21,Hybrid!$1:$1048576,MATCH(DATE(J$2,1,1),Hybrid!$A$1:$LI$1),FALSE) -> 0.53738588 | K21: =VLOOKUP($E21,Hybrid!$1:$1048576,MATCH(DATE(K$2,1,1),Hybrid!$A$1:$LI$1),FALSE) -> 0.57001754 | L21: =VLOOKUP($E21,Hybrid!$1:$1048576,MATCH(DATE(L$2,1,1),Hybrid!$A$1:$LI$1),FALSE) -> 0.60310328 | M21: =VLOOKUP($E21,Hybrid!$1:$1048576,MATCH(DATE(M$2,1,1),Hybrid!$A$1:$LI$1),FALSE) -> 0.63383453 | ... AO21: =VLOOKUP($E21,Hybrid!$1:$1048576,MATCH(DATE(AO$2,1,1),Hybrid!$A$1:$LI$1),FALSE) -> 1.1426523
D22: class B | E22: AUTO_cb_cgas_2 | F22: =VLOOKUP($E22,Hybrid!$1:$1048576,MATCH(DATE(F$2,1,1),Hybrid!$A$1:$LI$1),FALSE) -> 0.49500523 | G22: =VLOOKUP($E22,Hybrid!$1:$1048576,MATCH(DATE(G$2,1,1),Hybrid!$A$1:$LI$1),FALSE) -> 0.51203168 | H22: =VLOOKUP($E22,Hybrid!$1:$1048576,MATCH(DATE(H$2,1,1),Hybrid!$A$1:$LI$1),FALSE) -> 0.53299171 | I22: =VLOOKUP($E22,Hybrid!$1:$1048576,MATCH(DATE(I$2,1,1),Hybrid!$A$1:$LI$1),FALSE) -> 0.55636194 | J22: =VLOOKUP($E22,Hybrid!$1:$1048576,MATCH(DATE(J$2,1,1),Hybrid!$A$1:$LI$1),FALSE) -> 0.58173637 | K22: =VLOOKUP($E22,Hybrid!$1:$1048576,MATCH(DATE(K$2,1,1),Hybrid!$A$1:$LI$1),FALSE) -> 0.60837525 | L22: =VLOOKUP($E22,Hybrid!$1:$1048576,MATCH(DATE(L$2,1,1),Hybrid!$A$1:$LI$1),FALSE) -> 0.63558899 | M22: =VLOOKUP($E22,Hybrid!$1:$1048576,MATCH(DATE(M$2,1,1),Hybrid!$A$1:$LI$1),FALSE) -> 0.66063538 | ... AO22: =VLOOKUP($E22,Hybrid!$1:$1048576,MATCH(DATE(AO$2,1,1),Hybrid!$A$1:$LI$1),FALSE) -> 1.0500198
D23: class C | E23: AUTO_cc_cgas_2 | F23: =VLOOKUP($E23,Hybrid!$1:$1048576,MATCH(DATE(F$2,1,1),Hybrid!$A$1:$LI$1),FALSE) -> 0.40659852 | G23: =VLOOKUP($E23,Hybrid!$1:$1048576,MATCH(DATE(G$2,1,1),Hybrid!$A$1:$LI$1),FALSE) -> 0.41434648 | H23: =VLOOKUP($E23,Hybrid!$1:$1048576,MATCH(DATE(H$2,1,1),Hybrid!$A$1:$LI$1),FALSE) -> 0.42500511 | I23: =VLOOKUP($E23,Hybrid!$1:$1048576,MATCH(DATE(I$2,1,1),Hybrid!$A$1:$LI$1),FALSE) -> 0.43748705 | J23: =VLOOKUP($E23,Hybrid!$1:$1048576,MATCH(DATE(J$2,1,1),Hybrid!$A$1:$LI$1),FALSE) -> 0.45148622 | K23: =VLOOKUP($E23,Hybrid!$1:$1048576,MATCH(DATE(K$2,1,1),Hybrid!$A$1:$LI$1),FALSE) -> 0.46648281 | L23: =VLOOKUP($E23,Hybrid!$1:$1048576,MATCH(DATE(L$2,1,1),Hybrid!$A$1:$LI$1),FALSE) -> 0.4819889 | M23: =VLOOKUP($E23,Hybrid!$1:$1048576,MATCH(DATE(M$2,1,1),Hybrid!$A$1:$LI$1),FALSE) -> 0.49607544 | ... AO23: =VLOOKUP($E23,Hybrid!$1:$1048576,MATCH(DATE(AO$2,1,1),Hybrid!$A$1:$LI$1),FALSE) -> 0.68809577
D24: class D | E24: AUTO_cd_cgas_2 | F24: =VLOOKUP($E24,Hybrid!$1:$1048576,MATCH(DATE(F$2,1,1),Hybrid!$A$1:$LI$1),FALSE) -> 0.24954447 | G24: =VLOOKUP($E24,Hybrid!$1:$1048576,MATCH(DATE(G$2,1,1),Hybrid!$A$1:$LI$1),FALSE) -> 0.25224611 | H24: =VLOOKUP($E24,Hybrid!$1:$1048576,MATCH(DATE(H$2,1,1),Hybrid!$A$1:$LI$1),FALSE) -> 0.25652394 | I24: =VLOOKUP($E24,Hybrid!$1:$1048576,MATCH(DATE(I$2,1,1),Hybrid!$A$1:$LI$1),FALSE) -> 0.26173608 | J24: =VLOOKUP($E24,Hybrid!$1:$1048576,MATCH(DATE(J$2,1,1),Hybrid!$A$1:$LI$1),FALSE) -> 0.26768368 | K24: =VLOOKUP($E24,Hybrid!$1:$1048576,MATCH(DATE(K$2,1,1),Hybrid!$A$1:$LI$1),FALSE) -> 0.2740705 | L24: =VLOOKUP($E24,Hybrid!$1:$1048576,MATCH(DATE(L$2,1,1),Hybrid!$A$1:$LI$1),FALSE) -> 0.28062121 | M24: =VLOOKUP($E24,Hybrid!$1:$1048576,MATCH(DATE(M$2,1,1),Hybrid!$A$1:$LI$1),FALSE) -> 0.28628059 | ... AO24: =VLOOKUP($E24,Hybrid!$1:$1048576,MATCH(DATE(AO$2,1,1),Hybrid!$A$1:$LI$1),FALSE) -> 0.34227244
D25: class E | E25: AUTO_ce_cgas_2 | F25: =VLOOKUP($E25,Hybrid!$1:$1048576,MATCH(DATE(F$2,1,1),Hybrid!$A$1:$LI$1),FALSE) -> 0.15020247 | G25: =VLOOKUP($E25,Hybrid!$1:$1048576,MATCH(DATE(G$2,1,1),Hybrid!$A$1:$LI$1),FALSE) -> 0.15202419 | H25: =VLOOKUP($E25,Hybrid!$1:$1048576,MATCH(DATE(H$2,1,1),Hybrid!$A$1:$LI$1),FALSE) -> 0.15472833 | I25: =VLOOKUP($E25,Hybrid!$1:$1048576,MATCH(DATE(I$2,1,1),Hybrid!$A$1:$LI$1),FALSE) -> 0.15790278 | J25: =VLOOKUP($E25,Hybrid!$1:$1048576,MATCH(DATE(J$2,1,1),Hybrid!$A$1:$LI$1),FALSE) -> 0.16141401 | K25: =VLOOKUP($E25,Hybrid!$1:$1048576,MATCH(DATE(K$2,1,1),Hybrid!$A$1:$LI$1),FALSE) -> 0.16508139 | L25: =VLOOKUP($E25,Hybrid!$1:$1048576,MATCH(DATE(L$2,1,1),Hybrid!$A$1:$LI$1),FALSE) -> 0.16873863 | M25: =VLOOKUP($E25,Hybrid!$1:$1048576,MATCH(DATE(M$2,1,1),Hybrid!$A$1:$LI$1),FALSE) -> 0.17174678 | ... AO25: =VLOOKUP($E25,Hybrid!$1:$1048576,MATCH(DATE(AO$2,1,1),Hybrid!$A$1:$LI$1),FALSE) -> 0.17074118
D26: class F | E26: AUTO_cf_cgas_2 | F26: =VLOOKUP($E26,Hybrid!$1:$1048576,MATCH(DATE(F$2,1,1),Hybrid!$A$1:$LI$1),FALSE) -> 0.074609436 | G26: =VLOOKUP($E26,Hybrid!$1:$1048576,MATCH(DATE(G$2,1,1),Hybrid!$A$1:$LI$1),FALSE) -> 0.075291701 | H26: =VLOOKUP($E26,Hybrid!$1:$1048576,MATCH(DATE(H$2,1,1),Hybrid!$A$1:$LI$1),FALSE) -> 0.076289682 | I26: =VLOOKUP($E26,Hybrid!$1:$1048576,MATCH(DATE(I$2,1,1),Hybrid!$A$1:$LI$1),FALSE) -> 0.077379202 | J26: =VLOOKUP($E26,Hybrid!$1:$1048576,MATCH(DATE(J$2,1,1),Hybrid!$A$1:$LI$1),FALSE) -> 0.078480977 | K26: =VLOOKUP($E26,Hybrid!$1:$1048576,MATCH(DATE(K$2,1,1),Hybrid!$A$1:$LI$1),FALSE) -> 0.07951067 | L26: =VLOOKUP($E26,Hybrid!$1:$1048576,MATCH(DATE(L$2,1,1),Hybrid!$A$1:$LI$1),FALSE) -> 0.080396183 | M26: =VLOOKUP($E26,Hybrid!$1:$1048576,MATCH(DATE(M$2,1,1),Hybrid!$A$1:$LI$1),FALSE) -> 0.080862947 | ... AO26: =VLOOKUP($E26,Hybrid!$1:$1048576,MATCH(DATE(AO$2,1,1),Hybrid!$A$1:$LI$1),FALSE) -> 0.048233221
D27: class G | E27: AUTO_cg_cgas_2 | F27: =VLOOKUP($E27,Hybrid!$1:$1048576,MATCH(DATE(F$2,1,1),Hybrid!$A$1:$LI$1),FALSE) -> 0.13435819 | G27: =VLOOKUP($E27,Hybrid!$1:$1048576,MATCH(DATE(G$2,1,1),Hybrid!$A$1:$LI$1),FALSE) -> 0.13587233 | H27: =VLOOKUP($E27,Hybrid!$1:$1048576,MATCH(DATE(H$2,1,1),Hybrid!$A$1:$LI$1),FALSE) -> 0.13776953 | I27: =VLOOKUP($E27,Hybrid!$1:$1048576,MATCH(DATE(I$2,1,1),Hybrid!$A$1:$LI$1),FALSE) -> 0.1396014 | J27: =VLOOKUP($E27,Hybrid!$1:$1048576,MATCH(DATE(J$2,1,1),Hybrid!$A$1:$LI$1),FALSE) -> 0.14121093 | K27: =VLOOKUP($E27,Hybrid!$1:$1048576,MATCH(DATE(K$2,1,1),Hybrid!$A$1:$LI$1),FALSE) -> 0.14245951 | L27: =VLOOKUP($E27,Hybrid!$1:$1048576,MATCH(DATE(L$2,1,1),Hybrid!$A$1:$LI$1),FALSE) -> 0.14323963 | M27: =VLOOKUP($E27,Hybrid!$1:$1048576,MATCH(DATE(M$2,1,1),Hybrid!$A$1:$LI$1),FALSE) -> 0.14310409 | ... AO27: =VLOOKUP($E27,Hybrid!$1:$1048576,MATCH(DATE(AO$2,1,1),Hybrid!$A$1:$LI$1),FALSE) -> 0.059265473
C28: TOTAL STOCK BASELINE | E28: AUTO_0 | F28: =VLOOKUP($E28,Hybrid!$1:$1048576,MATCH(DATE(F$2,1,1),Hybrid!$A$1:$LI$1),FALSE) -> 32317.941 | G28: =VLOOKUP($E28,Hybrid!$1:$1048576,MATCH(DATE(G$2,1,1),Hybrid!$A$1:$LI$1),FALSE) -> 31918.631 | H28: =VLOOKUP($E28,Hybrid!$1:$1048576,MATCH(DATE(H$2,1,1),Hybrid!$A$1:$LI$1),FALSE) -> 31759.311 | I28: =VLOOKUP($E28,Hybrid!$1:$1048576,MATCH(DATE(I$2,1,1),Hybrid!$A$1:$LI$1),FALSE) -> 31761.553 | J28: =VLOOKUP($E28,Hybrid!$1:$1048576,MATCH(DATE(J$2,1,1),Hybrid!$A$1:$LI$1),FALSE) -> 31899.124 | K28: =VLOOKUP($E28,Hybrid!$1:$1048576,MATCH(DATE(K$2,1,1),Hybrid!$A$1:$LI$1),FALSE) -> 32133.592 | L28: =VLOOKUP($E28,Hybrid!$1:$1048576,MATCH(DATE(L$2,1,1),Hybrid!$A$1:$LI$1),FALSE) -> 32419.623 | M28: =VLOOKUP($E28,Hybrid!$1:$1048576,MATCH(DATE(M$2,1,1),Hybrid!$A$1:$LI$1),FALSE) -> 32735.512 | ... AO28: =VLOOKUP($E28,Hybrid!$1:$1048576,MATCH(DATE(AO$2,1,1),Hybrid!$A$1:$LI$1),FALSE) -> 42002.247
C29: OIL | E29: AUTO_cfut_0 | F29: =VLOOKUP($E29,Hybrid!$1:$1048576,MATCH(DATE(F$2,1,1),Hybrid!$A$1:$LI$1),FALSE) -> 32271.24 | G29: =VLOOKUP($E29,Hybrid!$1:$1048576,MATCH(DATE(G$2,1,1),Hybrid!$A$1:$LI$1),FALSE) -> 31853.75 | H29: =VLOOKUP($E29,Hybrid!$1:$1048576,MATCH(DATE(H$2,1,1),Hybrid!$A$1:$LI$1),FALSE) -> 31674.362 | I29: =VLOOKUP($E29,Hybrid!$1:$1048576,MATCH(DATE(I$2,1,1),Hybrid!$A$1:$LI$1),FALSE) -> 31654.909 | J29: =VLOOKUP($E29,Hybrid!$1:$1048576,MATCH(DATE(J$2,1,1),Hybrid!$A$1:$LI$1),FALSE) -> 31769.037 | K29: =VLOOKUP($E29,Hybrid!$1:$1048576,MATCH(DATE(K$2,1,1),Hybrid!$A$1:$LI$1),FALSE) -> 31978.673 | L29: =VLOOKUP($E29,Hybrid!$1:$1048576,MATCH(DATE(L$2,1,1),Hybrid!$A$1:$LI$1),FALSE) -> 32238.864 | M29: =VLOOKUP($E29,Hybrid!$1:$1048576,MATCH(DATE(M$2,1,1),Hybrid!$A$1:$LI$1),FALSE) -> 32527.868 | ... AO29: =VLOOKUP($E29,Hybrid!$1:$1048576,MATCH(DATE(AO$2,1,1),Hybrid!$A$1:$LI$1),FALSE) -> 39537.676
D30: class A | E30: AUTO_ca_cfut_0 | F30: =VLOOKUP($E30,Hybrid!$1:$1048576,MATCH(DATE(F$2,1,1),Hybrid!$A$1:$LI$1),FALSE) -> 7095.7005 | G30: =VLOOKUP($E30,Hybrid!$1:$1048576,MATCH(DATE(G$2,1,1),Hybrid!$A$1:$LI$1),FALSE) -> 7138.9134 | H30: =VLOOKUP($E30,Hybrid!$1:$1048576,MATCH(DATE(H$2,1,1),Hybrid!$A$1:$LI$1),FALSE) -> 7241.8937 | I30: =VLOOKUP($E30,Hybrid!$1:$1048576,MATCH(DATE(I$2,1,1),Hybrid!$A$1:$LI$1),FALSE) -> 7384.5407 | J30: =VLOOKUP($E30,Hybrid!$1:$1048576,MATCH(DATE(J$2,1,1),Hybrid!$A$1:$LI$1),FALSE) -> 7560.8902 | K30: =VLOOKUP($E30,Hybrid!$1:$1048576,MATCH(DATE(K$2,1,1),Hybrid!$A$1:$LI$1),FALSE) -> 7760.7036 | L30: =VLOOKUP($E30,Hybrid!$1:$1048576,MATCH(DATE(L$2,1,1),Hybrid!$A$1:$LI$1),FALSE) -> 7971.6733 | M30: =VLOOKUP($E30,Hybrid!$1:$1048576,MATCH(DATE(M$2,1,1),Hybrid!$A$1:$LI$1),FALSE) -> 8188.3294 | ... AO30: =VLOOKUP($E30,Hybrid!$1:$1048576,MATCH(DATE(AO$2,1,1),Hybrid!$A$1:$LI$1),FALSE) -> 12926.607
D31: class B | E31: AUTO_cb_cfut_0 | F31: =VLOOKUP($E31,Hybrid!$1:$1048576,MATCH(DATE(F$2,1,1),Hybrid!$A$1:$LI$1),FALSE) -> 8251.2564 | G31: =VLOOKUP($E31,Hybrid!$1:$1048576,MATCH(DATE(G$2,1,1),Hybrid!$A$1:$LI$1),FALSE) -> 8180.0639 | H31: =VLOOKUP($E31,Hybrid!$1:$1048576,MATCH(DATE(H$2,1,1),Hybrid!$A$1:$LI$1),FALSE) -> 8173.9007 | I31: =VLOOKUP($E31,Hybrid!$1:$1048576,MATCH(DATE(I$2,1,1),Hybrid!$A$1:$LI$1),FALSE) -> 8212.4993 | J31: =VLOOKUP($E31,Hybrid!$1:$1048576,MATCH(DATE(J$2,1,1),Hybrid!$A$1:$LI$1),FALSE) -> 8289.337 | K31: =VLOOKUP($E31,Hybrid!$1:$1048576,MATCH(DATE(K$2,1,1),Hybrid!$A$1:$LI$1),FALSE) -> 8394.1234 | L31: =VLOOKUP($E31,Hybrid!$1:$1048576,MATCH(DATE(L$2,1,1),Hybrid!$A$1:$LI$1),FALSE) -> 8514.5426 | M31: =VLOOKUP($E31,Hybrid!$1:$1048576,MATCH(DATE(M$2,1,1),Hybrid!$A$1:$LI$1),FALSE) -> 8644.7147 | ... AO31: =VLOOKUP($E31,Hybrid!$1:$1048576,MATCH(DATE(AO$2,1,1),Hybrid!$A$1:$LI$1),FALSE) -> 11971.279
D32: class C | E32: AUTO_cc_cfut_0 | F32: =VLOOKUP($E32,Hybrid!$1:$1048576,MATCH(DATE(F$2,1,1),Hybrid!$A$1:$LI$1),FALSE) -> 6777.6025 | G32: =VLOOKUP($E32,Hybrid!$1:$1048576,MATCH(DATE(G$2,1,1),Hybrid!$A$1:$LI$1),FALSE) -> 6644.8772 | H32: =VLOOKUP($E32,Hybrid!$1:$1048576,MATCH(DATE(H$2,1,1),Hybrid!$A$1:$LI$1),FALSE) -> 6562.8912 | I32: =VLOOKUP($E32,Hybrid!$1:$1048576,MATCH(DATE(I$2,1,1),Hybrid!$A$1:$LI$1),FALSE) -> 6516.918 | J32: =VLOOKUP($E32,Hybrid!$1:$1048576,MATCH(DATE(J$2,1,1),Hybrid!$A$1:$LI$1),FALSE) -> 6501.8685 | K32: =VLOOKUP($E32,Hybrid!$1:$1048576,MATCH(DATE(K$2,1,1),Hybrid!$A$1:$LI$1),FALSE) -> 6510.2772 | L32: =VLOOKUP($E32,Hybrid!$1:$1048576,MATCH(DATE(L$2,1,1),Hybrid!$A$1:$LI$1),FALSE) -> 6533.2536 | M32: =VLOOKUP($E32,Hybrid!$1:$1048576,MATCH(DATE(M$2,1,1),Hybrid!$A$1:$LI$1),FALSE) -> 6566.2781 | ... AO32: =VLOOKUP($E32,Hybrid!$1:$1048576,MATCH(DATE(AO$2,1,1),Hybrid!$A$1:$LI$1),FALSE) -> 7910.2714
D33: class D | E33: AUTO_cd_cfut_0 | F33: =VLOOKUP($E33,Hybrid!$1:$1048576,MATCH(DATE(F$2,1,1),Hybrid!$A$1:$LI$1),FALSE) -> 4159.6639 | G33: =VLOOKUP($E33,Hybrid!$1:$1048576,MATCH(DATE(G$2,1,1),Hybrid!$A$1:$LI$1),FALSE) -> 4053.7616 | H33: =VLOOKUP($E33,Hybrid!$1:$1048576,MATCH(DATE(H$2,1,1),Hybrid!$A$1:$LI$1),FALSE) -> 3976.8722 | I33: =VLOOKUP($E33,Hybrid!$1:$1048576,MATCH(DATE(I$2,1,1),Hybrid!$A$1:$LI$1),FALSE) -> 3920.2702 | J33: =VLOOKUP($E33,Hybrid!$1:$1048576,MATCH(DATE(J$2,1,1),Hybrid!$A$1:$LI$1),FALSE) -> 3880.7049 | K33: =VLOOKUP($E33,Hybrid!$1:$1048576,MATCH(DATE(K$2,1,1),Hybrid!$A$1:$LI$1),FALSE) -> 3853.8714 | L33: =VLOOKUP($E33,Hybrid!$1:$1048576,MATCH(DATE(L$2,1,1),Hybrid!$A$1:$LI$1),FALSE) -> 3834.7399 | M33: =VLOOKUP($E33,Hybrid!$1:$1048576,MATCH(DATE(M$2,1,1),Hybrid!$A$1:$LI$1),FALSE) -> 3820.6377 | ... AO33: =VLOOKUP($E33,Hybrid!$1:$1048576,MATCH(DATE(AO$2,1,1),Hybrid!$A$1:$LI$1),FALSE) -> 3702.557
D34: class E | E34: AUTO_ce_cfut_0 | F34: =VLOOKUP($E34,Hybrid!$1:$1048576,MATCH(DATE(F$2,1,1),Hybrid!$A$1:$LI$1),FALSE) -> 2503.7292 | G34: =VLOOKUP($E34,Hybrid!$1:$1048576,MATCH(DATE(G$2,1,1),Hybrid!$A$1:$LI$1),FALSE) -> 2442.3141 | H34: =VLOOKUP($E34,Hybrid!$1:$1048576,MATCH(DATE(H$2,1,1),Hybrid!$A$1:$LI$1),FALSE) -> 2397.5371 | I34: =VLOOKUP($E34,Hybrid!$1:$1048576,MATCH(DATE(I$2,1,1),Hybrid!$A$1:$LI$1),FALSE) -> 2363.8546 | J34: =VLOOKUP($E34,Hybrid!$1:$1048576,MATCH(DATE(J$2,1,1),Hybrid!$A$1:$LI$1),FALSE) -> 2339.1637 | K34: =VLOOKUP($E34,Hybrid!$1:$1048576,MATCH(DATE(K$2,1,1),Hybrid!$A$1:$LI$1),FALSE) -> 2320.8652 | L34: =VLOOKUP($E34,Hybrid!$1:$1048576,MATCH(DATE(L$2,1,1),Hybrid!$A$1:$LI$1),FALSE) -> 2305.9376 | M34: =VLOOKUP($E34,Hybrid!$1:$1048576,MATCH(DATE(M$2,1,1),Hybrid!$A$1:$LI$1),FALSE) -> 2292.7598 | ... AO34: =VLOOKUP($E34,Hybrid!$1:$1048576,MATCH(DATE(AO$2,1,1),Hybrid!$A$1:$LI$1),FALSE) -> 1870.4198
D35: class F | E35: AUTO_cf_cfut_0 | F35: =VLOOKUP($E35,Hybrid!$1:$1048576,MATCH(DATE(F$2,1,1),Hybrid!$A$1:$LI$1),FALSE) -> 1243.6668 | G35: =VLOOKUP($E35,Hybrid!$1:$1048576,MATCH(DATE(G$2,1,1),Hybrid!$A$1:$LI$1),FALSE) -> 1210.5103 | H35: =VLOOKUP($E35,Hybrid!$1:$1048576,MATCH(DATE(H$2,1,1),Hybrid!$A$1:$LI$1),FALSE) -> 1184.1996 | I35: =VLOOKUP($E35,Hybrid!$1:$1048576,MATCH(DATE(I$2,1,1),Hybrid!$A$1:$LI$1),FALSE) -> 1161.7685 | J35: =VLOOKUP($E35,Hybrid!$1:$1048576,MATCH(DATE(J$2,1,1),Hybrid!$A$1:$LI$1),FALSE) -> 1142.0394 | K35: =VLOOKUP($E35,Hybrid!$1:$1048576,MATCH(DATE(K$2,1,1),Hybrid!$A$1:$LI$1),FALSE) -> 1123.8073 | L35: =VLOOKUP($E35,Hybrid!$1:$1048576,MATCH(DATE(L$2,1,1),Hybrid!$A$1:$LI$1),FALSE) -> 1105.7491 | M35: =VLOOKUP($E35,Hybrid!$1:$1048576,MATCH(DATE(M$2,1,1),Hybrid!$A$1:$LI$1),FALSE) -> 1087.1871 | ... AO35: =VLOOKUP($E35,Hybrid!$1:$1048576,MATCH(DATE(AO$2,1,1),Hybrid!$A$1:$LI$1),FALSE) -> 521.33687
D36: class G | E36: AUTO_cg_cfut_0 | F36: =VLOOKUP($E36,Hybrid!$1:$1048576,MATCH(DATE(F$2,1,1),Hybrid!$A$1:$LI$1),FALSE) -> 2239.6206 | G36: =VLOOKUP($E36,Hybrid!$1:$1048576,MATCH(DATE(G$2,1,1),Hybrid!$A$1:$LI$1),FALSE) -> 2183.3099 | H36: =VLOOKUP($E36,Hybrid!$1:$1048576,MATCH(DATE(H$2,1,1),Hybrid!$A$1:$LI$1),FALSE) -> 2137.0676 | I36: =VLOOKUP($E36,Hybrid!$1:$1048576,MATCH(DATE(I$2,1,1),Hybrid!$A$1:$LI$1),FALSE) -> 2095.0577 | J36: =VLOOKUP($E36,Hybrid!$1:$1048576,MATCH(DATE(J$2,1,1),Hybrid!$A$1:$LI$1),FALSE) -> 2055.0332 | K36: =VLOOKUP($E36,Hybrid!$1:$1048576,MATCH(DATE(K$2,1,1),Hybrid!$A$1:$LI$1),FALSE) -> 2015.0245 | L36: =VLOOKUP($E36,Hybrid!$1:$1048576,MATCH(DATE(L$2,1,1),Hybrid!$A$1:$LI$1),FALSE) -> 1972.968 | M36: =VLOOKUP($E36,Hybrid!$1:$1048576,MATCH(DATE(M$2,1,1),Hybrid!$A$1:$LI$1),FALSE) -> 1927.9616 | ... AO36: =VLOOKUP($E36,Hybrid!$1:$1048576,MATCH(DATE(AO$2,1,1),Hybrid!$A$1:$LI$1),FALSE) -> 635.205
C37: ELEC | E37: AUTO_cele_0 | F37: =VLOOKUP($E37,Hybrid!$1:$1048576,MATCH(DATE(F$2,1,1),Hybrid!$A$1:$LI$1),FALSE) -> 44.765 | G37: =VLOOKUP($E37,Hybrid!$1:$1048576,MATCH(DATE(G$2,1,1),Hybrid!$A$1:$LI$1),FALSE) -> 62.889352 | H37: =VLOOKUP($E37,Hybrid!$1:$1048576,MATCH(DATE(H$2,1,1),Hybrid!$A$1:$LI$1),FALSE) -> 82.889294 | I37: =VLOOKUP($E37,Hybrid!$1:$1048576,MATCH(DATE(I$2,1,1),Hybrid!$A$1:$LI$1),FALSE) -> 104.50723 | J37: =VLOOKUP($E37,Hybrid!$1:$1048576,MATCH(DATE(J$2,1,1),Hybrid!$A$1:$LI$1),FALSE) -> 127.86793 | K37: =VLOOKUP($E37,Hybrid!$1:$1048576,MATCH(DATE(K$2,1,1),Hybrid!$A$1:$LI$1),FALSE) -> 152.61341 | L37: =VLOOKUP($E37,Hybrid!$1:$1048576,MATCH(DATE(L$2,1,1),Hybrid!$A$1:$LI$1),FALSE) -> 178.36635 | M37: =VLOOKUP($E37,Hybrid!$1:$1048576,MATCH(DATE(M$2,1,1),Hybrid!$A$1:$LI$1),FALSE) -> 205.16507 | ... AO37: =VLOOKUP($E37,Hybrid!$1:$1048576,MATCH(DATE(AO$2,1,1),Hybrid!$A$1:$LI$1),FALSE) -> 2766.3372
D38: class A | E38: AUTO_ca_cele_0 | F38: =VLOOKUP($E38,Hybrid!$1:$1048576,MATCH(DATE(F$2,1,1),Hybrid!$A$1:$LI$1),FALSE) -> 9.8427899 | G38: =VLOOKUP($E38,Hybrid!$1:$1048576,MATCH(DATE(G$2,1,1),Hybrid!$A$1:$LI$1),FALSE) -> 15.123232 | H38: =VLOOKUP($E38,Hybrid!$1:$1048576,MATCH(DATE(H$2,1,1),Hybrid!$A$1:$LI$1),FALSE) -> 20.991591 | I38: =VLOOKUP($E38,Hybrid!$1:$1048576,MATCH(DATE(I$2,1,1),Hybrid!$A$1:$LI$1),FALSE) -> 27.398546 | J38: =VLOOKUP($E38,Hybrid!$1:$1048576,MATCH(DATE(J$2,1,1),Hybrid!$A$1:$LI$1),FALSE) -> 34.399336 | K38: =VLOOKUP($E38,Hybrid!$1:$1048576,MATCH(DATE(K$2,1,1),Hybrid!$A$1:$LI$1),FALSE) -> 41.894067 | L38: =VLOOKUP($E38,Hybrid!$1:$1048576,MATCH(DATE(L$2,1,1),Hybrid!$A$1:$LI$1),FALSE) -> 49.778774 | M38: =VLOOKUP($E38,Hybrid!$1:$1048576,MATCH(DATE(M$2,1,1),Hybrid!$A$1:$LI$1),FALSE) -> 58.078159 | ... AO38: =VLOOKUP($E38,Hybrid!$1:$1048576,MATCH(DATE(AO$2,1,1),Hybrid!$A$1:$LI$1),FALSE) -> 949.97974
D39: class B | E39: AUTO_cb_cele_0 | F39: =VLOOKUP($E39,Hybrid!$1:$1048576,MATCH(DATE(F$2,1,1),Hybrid!$A$1:$LI$1),FALSE) -> 11.445717 | G39: =VLOOKUP($E39,Hybrid!$1:$1048576,MATCH(DATE(G$2,1,1),Hybrid!$A$1:$LI$1),FALSE) -> 16.441946 | H39: =VLOOKUP($E39,Hybrid!$1:$1048576,MATCH(DATE(H$2,1,1),Hybrid!$A$1:$LI$1),FALSE) -> 22.010704 | I39: =VLOOKUP($E39,Hybrid!$1:$1048576,MATCH(DATE(I$2,1,1),Hybrid!$A$1:$LI$1),FALSE) -> 28.107951 | J39: =VLOOKUP($E39,Hybrid!$1:$1048576,MATCH(DATE(J$2,1,1),Hybrid!$A$1:$LI$1),FALSE) -> 34.789079 | K39: =VLOOKUP($E39,Hybrid!$1:$1048576,MATCH(DATE(K$2,1,1),Hybrid!$A$1:$LI$1),FALSE) -> 41.955856 | L39: =VLOOKUP($E39,Hybrid!$1:$1048576,MATCH(DATE(L$2,1,1),Hybrid!$A$1:$LI$1),FALSE) -> 49.506371 | M39: =VLOOKUP($E39,Hybrid!$1:$1048576,MATCH(DATE(M$2,1,1),Hybrid!$A$1:$LI$1),FALSE) -> 57.464189 | ... AO39: =VLOOKUP($E39,Hybrid!$1:$1048576,MATCH(DATE(AO$2,1,1),Hybrid!$A$1:$LI$1),FALSE) -> 913.7881
D40: class C | E40: AUTO_cc_cele_0 | F40: =VLOOKUP($E40,Hybrid!$1:$1048576,MATCH(DATE(F$2,1,1),Hybrid!$A$1:$LI$1),FALSE) -> 9.4015406 | G40: =VLOOKUP($E40,Hybrid!$1:$1048576,MATCH(DATE(G$2,1,1),Hybrid!$A$1:$LI$1),FALSE) -> 12.804718 | H40: =VLOOKUP($E40,Hybrid!$1:$1048576,MATCH(DATE(H$2,1,1),Hybrid!$A$1:$LI$1),FALSE) -> 16.609264 | I40: =VLOOKUP($E40,Hybrid!$1:$1048576,MATCH(DATE(I$2,1,1),Hybrid!$A$1:$LI$1),FALSE) -> 20.786573 | J40: =VLOOKUP($E40,Hybrid!$1:$1048576,MATCH(DATE(J$2,1,1),Hybrid!$A$1:$LI$1),FALSE) -> 25.376235 | K40: =VLOOKUP($E40,Hybrid!$1:$1048576,MATCH(DATE(K$2,1,1),Hybrid!$A$1:$LI$1),FALSE) -> 30.30866 | L40: =VLOOKUP($E40,Hybrid!$1:$1048576,MATCH(DATE(L$2,1,1),Hybrid!$A$1:$LI$1),FALSE) -> 35.511808 | M40: =VLOOKUP($E40,Hybrid!$1:$1048576,MATCH(DATE(M$2,1,1),Hybrid!$A$1:$LI$1),FALSE) -> 41.001551 | ... AO40: =VLOOKUP($E40,Hybrid!$1:$1048576,MATCH(DATE(AO$2,1,1),Hybrid!$A$1:$LI$1),FALSE) -> 630.09316
D41: class D | E41: AUTO_cd_cele_0 | F41: =VLOOKUP($E41,Hybrid!$1:$1048576,MATCH(DATE(F$2,1,1),Hybrid!$A$1:$LI$1),FALSE) -> 5.7700713 | G41: =VLOOKUP($E41,Hybrid!$1:$1048576,MATCH(DATE(G$2,1,1),Hybrid!$A$1:$LI$1),FALSE) -> 7.5870606 | H41: =VLOOKUP($E41,Hybrid!$1:$1048576,MATCH(DATE(H$2,1,1),Hybrid!$A$1:$LI$1),FALSE) -> 9.5658742 | I41: =VLOOKUP($E41,Hybrid!$1:$1048576,MATCH(DATE(I$2,1,1),Hybrid!$A$1:$LI$1),FALSE) -> 11.661626 | J41: =VLOOKUP($E41,Hybrid!$1:$1048576,MATCH(DATE(J$2,1,1),Hybrid!$A$1:$LI$1),FALSE) -> 13.871889 | K41: =VLOOKUP($E41,Hybrid!$1:$1048576,MATCH(DATE(K$2,1,1),Hybrid!$A$1:$LI$1),FALSE) -> 16.161271 | L41: =VLOOKUP($E41,Hybrid!$1:$1048576,MATCH(DATE(L$2,1,1),Hybrid!$A$1:$LI$1),FALSE) -> 18.489162 | M41: =VLOOKUP($E41,Hybrid!$1:$1048576,MATCH(DATE(M$2,1,1),Hybrid!$A$1:$LI$1),FALSE) -> 20.847177 | ... AO41: =VLOOKUP($E41,Hybrid!$1:$1048576,MATCH(DATE(AO$2,1,1),Hybrid!$A$1:$LI$1),FALSE) -> 155.0975
D42: class E | E42: AUTO_ce_cele_0 | F42: =VLOOKUP($E42,Hybrid!$1:$1048576,MATCH(DATE(F$2,1,1),Hybrid!$A$1:$LI$1),FALSE) -> 3.4730441 | G42: =VLOOKUP($E42,Hybrid!$1:$1048576,MATCH(DATE(G$2,1,1),Hybrid!$A$1:$LI$1),FALSE) -> 4.5917108 | H42: =VLOOKUP($E42,Hybrid!$1:$1048576,MATCH(DATE(H$2,1,1),Hybrid!$A$1:$LI$1),FALSE) -> 5.8046001 | I42: =VLOOKUP($E42,Hybrid!$1:$1048576,MATCH(DATE(I$2,1,1),Hybrid!$A$1:$LI$1),FALSE) -> 7.0827696 | J42: =VLOOKUP($E42,Hybrid!$1:$1048576,MATCH(DATE(J$2,1,1),Hybrid!$A$1:$LI$1),FALSE) -> 8.4233535 | K42: =VLOOKUP($E42,Hybrid!$1:$1048576,MATCH(DATE(K$2,1,1),Hybrid!$A$1:$LI$1),FALSE) -> 9.8032197 | L42: =VLOOKUP($E42,Hybrid!$1:$1048576,MATCH(DATE(L$2,1,1),Hybrid!$A$1:$LI$1),FALSE) -> 11.196436 | M42: =VLOOKUP($E42,Hybrid!$1:$1048576,MATCH(DATE(M$2,1,1),Hybrid!$A$1:$LI$1),FALSE) -> 12.596927 | ... AO42: =VLOOKUP($E42,Hybrid!$1:$1048576,MATCH(DATE(AO$2,1,1),Hybrid!$A$1:$LI$1),FALSE) -> 83.8452
D43: class F | E43: AUTO_cf_cele_0 | F43: =VLOOKUP($E43,Hybrid!$1:$1048576,MATCH(DATE(F$2,1,1),Hybrid!$A$1:$LI$1),FALSE) -> 1.7251505 | G43: =VLOOKUP($E43,Hybrid!$1:$1048576,MATCH(DATE(G$2,1,1),Hybrid!$A$1:$LI$1),FALSE) -> 2.2518855 | H43: =VLOOKUP($E43,Hybrid!$1:$1048576,MATCH(DATE(H$2,1,1),Hybrid!$A$1:$LI$1),FALSE) -> 2.80569 | I43: =VLOOKUP($E43,Hybrid!$1:$1048576,MATCH(DATE(I$2,1,1),Hybrid!$A$1:$LI$1),FALSE) -> 3.3665411 | J43: =VLOOKUP($E43,Hybrid!$1:$1048576,MATCH(DATE(J$2,1,1),Hybrid!$A$1:$LI$1),FALSE) -> 3.9283843 | K43: =VLOOKUP($E43,Hybrid!$1:$1048576,MATCH(DATE(K$2,1,1),Hybrid!$A$1:$LI$1),FALSE) -> 4.4801406 | L43: =VLOOKUP($E43,Hybrid!$1:$1048576,MATCH(DATE(L$2,1,1),Hybrid!$A$1:$LI$1),FALSE) -> 5.0098079 | M43: =VLOOKUP($E43,Hybrid!$1:$1048576,MATCH(DATE(M$2,1,1),Hybrid!$A$1:$LI$1),FALSE) -> 5.5129669 | ... AO43: =VLOOKUP($E43,Hybrid!$1:$1048576,MATCH(DATE(AO$2,1,1),Hybrid!$A$1:$LI$1),FALSE) -> 15.386442
D44: class G | E44: AUTO_cg_cele_0 | F44: =VLOOKUP($E44,Hybrid!$1:$1048576,MATCH(DATE(F$2,1,1),Hybrid!$A$1:$LI$1),FALSE) -> 3.1066862 | G44: =VLOOKUP($E44,Hybrid!$1:$1048576,MATCH(DATE(G$2,1,1),Hybrid!$A$1:$LI$1),FALSE) -> 4.0887993 | H44: =VLOOKUP($E44,Hybrid!$1:$1048576,MATCH(DATE(H$2,1,1),Hybrid!$A$1:$LI$1),FALSE) -> 5.1015716 | I44: =VLOOKUP($E44,Hybrid!$1:$1048576,MATCH(DATE(I$2,1,1),Hybrid!$A$1:$LI$1),FALSE) -> 6.1032213 | J44: =VLOOKUP($E44,Hybrid!$1:$1048576,MATCH(DATE(J$2,1,1),Hybrid!$A$1:$LI$1),FALSE) -> 7.0796515 | K44: =VLOOKUP($E44,Hybrid!$1:$1048576,MATCH(DATE(K$2,1,1),Hybrid!$A$1:$LI$1),FALSE) -> 8.0101921 | L44: =VLOOKUP($E44,Hybrid!$1:$1048576,MATCH(DATE(L$2,1,1),Hybrid!$A$1:$LI$1),FALSE) -> 8.8739936 | M44: =VLOOKUP($E44,Hybrid!$1:$1048576,MATCH(DATE(M$2,1,1),Hybrid!$A$1:$LI$1),FALSE) -> 9.6640974 | ... AO44: =VLOOKUP($E44,Hybrid!$1:$1048576,MATCH(DATE(AO$2,1,1),Hybrid!$A$1:$LI$1),FALSE) -> 18.14705
C45: GAS | E45: AUTO_cgas_0 | F45: =VLOOKUP($E45,Hybrid!$1:$1048576,MATCH(DATE(F$2,1,1),Hybrid!$A$1:$LI$1),FALSE) -> 1.936 | G45: =VLOOKUP($E45,Hybrid!$1:$1048576,MATCH(DATE(G$2,1,1),Hybrid!$A$1:$LI$1),FALSE) -> 1.9909099 | H45: =VLOOKUP($E45,Hybrid!$1:$1048576,MATCH(DATE(H$2,1,1),Hybrid!$A$1:$LI$1),FALSE) -> 2.0596615 | I45: =VLOOKUP($E45,Hybrid!$1:$1048576,MATCH(DATE(I$2,1,1),Hybrid!$A$1:$LI$1),FALSE) -> 2.1363797 | J45: =VLOOKUP($E45,Hybrid!$1:$1048576,MATCH(DATE(J$2,1,1),Hybrid!$A$1:$LI$1),FALSE) -> 2.2193981 | K45: =VLOOKUP($E45,Hybrid!$1:$1048576,MATCH(DATE(K$2,1,1),Hybrid!$A$1:$LI$1),FALSE) -> 2.3059977 | L45: =VLOOKUP($E45,Hybrid!$1:$1048576,MATCH(DATE(L$2,1,1),Hybrid!$A$1:$LI$1),FALSE) -> 2.3928026 | M45: =VLOOKUP($E45,Hybrid!$1:$1048576,MATCH(DATE(M$2,1,1),Hybrid!$A$1:$LI$1),FALSE) -> 2.4783039 | ... AO45: =VLOOKUP($E45,Hybrid!$1:$1048576,MATCH(DATE(AO$2,1,1),Hybrid!$A$1:$LI$1),FALSE) -> 3.9171707
D46: class A | E46: AUTO_ca_cgas_0 | F46: =VLOOKUP($E46,Hybrid!$1:$1048576,MATCH(DATE(F$2,1,1),Hybrid!$A$1:$LI$1),FALSE) -> 0.4256817 | G46: =VLOOKUP($E46,Hybrid!$1:$1048576,MATCH(DATE(G$2,1,1),Hybrid!$A$1:$LI$1),FALSE) -> 0.44909736 | H46: =VLOOKUP($E46,Hybrid!$1:$1048576,MATCH(DATE(H$2,1,1),Hybrid!$A$1:$LI$1),FALSE) -> 0.47635319 | I46: =VLOOKUP($E46,Hybrid!$1:$1048576,MATCH(DATE(I$2,1,1),Hybrid!$A$1:$LI$1),FALSE) -> 0.50591124 | J46: =VLOOKUP($E46,Hybrid!$1:$1048576,MATCH(DATE(J$2,1,1),Hybrid!$A$1:$LI$1),FALSE) -> 0.53738588 | K46: =VLOOKUP($E46,Hybrid!$1:$1048576,MATCH(DATE(K$2,1,1),Hybrid!$A$1:$LI$1),FALSE) -> 0.57001754 | L46: =VLOOKUP($E46,Hybrid!$1:$1048576,MATCH(DATE(L$2,1,1),Hybrid!$A$1:$LI$1),FALSE) -> 0.6028533 | M46: =VLOOKUP($E46,Hybrid!$1:$1048576,MATCH(DATE(M$2,1,1),Hybrid!$A$1:$LI$1),FALSE) -> 0.63549383 | ... AO46: =VLOOKUP($E46,Hybrid!$1:$1048576,MATCH(DATE(AO$2,1,1),Hybrid!$A$1:$LI$1),FALSE) -> 1.2725809
D47: class B | E47: AUTO_cb_cgas_0 | F47: =VLOOKUP($E47,Hybrid!$1:$1048576,MATCH(DATE(F$2,1,1),Hybrid!$A$1:$LI$1),FALSE) -> 0.49500523 | G47: =VLOOKUP($E47,Hybrid!$1:$1048576,MATCH(DATE(G$2,1,1),Hybrid!$A$1:$LI$1),FALSE) -> 0.51203168 | H47: =VLOOKUP($E47,Hybrid!$1:$1048576,MATCH(DATE(H$2,1,1),Hybrid!$A$1:$LI$1),FALSE) -> 0.53299171 | I47: =VLOOKUP($E47,Hybrid!$1:$1048576,MATCH(DATE(I$2,1,1),Hybrid!$A$1:$LI$1),FALSE) -> 0.55636194 | J47: =VLOOKUP($E47,Hybrid!$1:$1048576,MATCH(DATE(J$2,1,1),Hybrid!$A$1:$LI$1),FALSE) -> 0.58173637 | K47: =VLOOKUP($E47,Hybrid!$1:$1048576,MATCH(DATE(K$2,1,1),Hybrid!$A$1:$LI$1),FALSE) -> 0.60837525 | L47: =VLOOKUP($E47,Hybrid!$1:$1048576,MATCH(DATE(L$2,1,1),Hybrid!$A$1:$LI$1),FALSE) -> 0.63534762 | M47: =VLOOKUP($E47,Hybrid!$1:$1048576,MATCH(DATE(M$2,1,1),Hybrid!$A$1:$LI$1),FALSE) -> 0.66224083 | ... AO47: =VLOOKUP($E47,Hybrid!$1:$1048576,MATCH(DATE(AO$2,1,1),Hybrid!$A$1:$LI$1),FALSE) -> 1.1802926
D48: class C | E48: AUTO_cc_cgas_0 | F48: =VLOOKUP($E48,Hybrid!$1:$1048576,MATCH(DATE(F$2,1,1),Hybrid!$A$1:$LI$1),FALSE) -> 0.40659852 | G48: =VLOOKUP($E48,Hybrid!$1:$1048576,MATCH(DATE(G$2,1,1),Hybrid!$A$1:$LI$1),FALSE) -> 0.41434648 | H48: =VLOOKUP($E48,Hybrid!$1:$1048576,MATCH(DATE(H$2,1,1),Hybrid!$A$1:$LI$1),FALSE) -> 0.42500511 | I48: =VLOOKUP($E48,Hybrid!$1:$1048576,MATCH(DATE(I$2,1,1),Hybrid!$A$1:$LI$1),FALSE) -> 0.43748705 | J48: =VLOOKUP($E48,Hybrid!$1:$1048576,MATCH(DATE(J$2,1,1),Hybrid!$A$1:$LI$1),FALSE) -> 0.45148622 | K48: =VLOOKUP($E48,Hybrid!$1:$1048576,MATCH(DATE(K$2,1,1),Hybrid!$A$1:$LI$1),FALSE) -> 0.46648281 | L48: =VLOOKUP($E48,Hybrid!$1:$1048576,MATCH(DATE(L$2,1,1),Hybrid!$A$1:$LI$1),FALSE) -> 0.48182092 | M48: =VLOOKUP($E48,Hybrid!$1:$1048576,MATCH(DATE(M$2,1,1),Hybrid!$A$1:$LI$1),FALSE) -> 0.49719478 | ... AO48: =VLOOKUP($E48,Hybrid!$1:$1048576,MATCH(DATE(AO$2,1,1),Hybrid!$A$1:$LI$1),FALSE) -> 0.78258553
D49: class D | E49: AUTO_cd_cgas_0 | F49: =VLOOKUP($E49,Hybrid!$1:$1048576,MATCH(DATE(F$2,1,1),Hybrid!$A$1:$LI$1),FALSE) -> 0.24954447 | G49: =VLOOKUP($E49,Hybrid!$1:$1048576,MATCH(DATE(G$2,1,1),Hybrid!$A$1:$LI$1),FALSE) -> 0.25224611 | H49: =VLOOKUP($E49,Hybrid!$1:$1048576,MATCH(DATE(H$2,1,1),Hybrid!$A$1:$LI$1),FALSE) -> 0.25652394 | I49: =VLOOKUP($E49,Hybrid!$1:$1048576,MATCH(DATE(I$2,1,1),Hybrid!$A$1:$LI$1),FALSE) -> 0.26173608 | J49: =VLOOKUP($E49,Hybrid!$1:$1048576,MATCH(DATE(J$2,1,1),Hybrid!$A$1:$LI$1),FALSE) -> 0.26768368 | K49: =VLOOKUP($E49,Hybrid!$1:$1048576,MATCH(DATE(K$2,1,1),Hybrid!$A$1:$LI$1),FALSE) -> 0.2740705 | L49: =VLOOKUP($E49,Hybrid!$1:$1048576,MATCH(DATE(L$2,1,1),Hybrid!$A$1:$LI$1),FALSE) -> 0.28052975 | M49: =VLOOKUP($E49,Hybrid!$1:$1048576,MATCH(DATE(M$2,1,1),Hybrid!$A$1:$LI$1),FALSE) -> 0.28688274 | ... AO49: =VLOOKUP($E49,Hybrid!$1:$1048576,MATCH(DATE(AO$2,1,1),Hybrid!$A$1:$LI$1),FALSE) -> 0.36956823
D50: class E | E50: AUTO_ce_cgas_0 | F50: =VLOOKUP($E50,Hybrid!$1:$1048576,MATCH(DATE(F$2,1,1),Hybrid!$A$1:$LI$1),FALSE) -> 0.15020247 | G50: =VLOOKUP($E50,Hybrid!$1:$1048576,MATCH(DATE(G$2,1,1),Hybrid!$A$1:$LI$1),FALSE) -> 0.15202419 | H50: =VLOOKUP($E50,Hybrid!$1:$1048576,MATCH(DATE(H$2,1,1),Hybrid!$A$1:$LI$1),FALSE) -> 0.15472833 | I50: =VLOOKUP($E50,Hybrid!$1:$1048576,MATCH(DATE(I$2,1,1),Hybrid!$A$1:$LI$1),FALSE) -> 0.15790278 | J50: =VLOOKUP($E50,Hybrid!$1:$1048576,MATCH(DATE(J$2,1,1),Hybrid!$A$1:$LI$1),FALSE) -> 0.16141401 | K50: =VLOOKUP($E50,Hybrid!$1:$1048576,MATCH(DATE(K$2,1,1),Hybrid!$A$1:$LI$1),FALSE) -> 0.16508139 | L50: =VLOOKUP($E50,Hybrid!$1:$1048576,MATCH(DATE(L$2,1,1),Hybrid!$A$1:$LI$1),FALSE) -> 0.16868312 | M50: =VLOOKUP($E50,Hybrid!$1:$1048576,MATCH(DATE(M$2,1,1),Hybrid!$A$1:$LI$1),FALSE) -> 0.17210915 | ... AO50: =VLOOKUP($E50,Hybrid!$1:$1048576,MATCH(DATE(AO$2,1,1),Hybrid!$A$1:$LI$1),FALSE) -> 0.18902078
D51: class F | E51: AUTO_cf_cgas_0 | F51: =VLOOKUP($E51,Hybrid!$1:$1048576,MATCH(DATE(F$2,1,1),Hybrid!$A$1:$LI$1),FALSE) -> 0.074609436 | G51: =VLOOKUP($E51,Hybrid!$1:$1048576,MATCH(DATE(G$2,1,1),Hybrid!$A$1:$LI$1),FALSE) -> 0.075291701 | H51: =VLOOKUP($E51,Hybrid!$1:$1048576,MATCH(DATE(H$2,1,1),Hybrid!$A$1:$LI$1),FALSE) -> 0.076289682 | I51: =VLOOKUP($E51,Hybrid!$1:$1048576,MATCH(DATE(I$2,1,1),Hybrid!$A$1:$LI$1),FALSE) -> 0.077379202 | J51: =VLOOKUP($E51,Hybrid!$1:$1048576,MATCH(DATE(J$2,1,1),Hybrid!$A$1:$LI$1),FALSE) -> 0.078480977 | K51: =VLOOKUP($E51,Hybrid!$1:$1048576,MATCH(DATE(K$2,1,1),Hybrid!$A$1:$LI$1),FALSE) -> 0.07951067 | L51: =VLOOKUP($E51,Hybrid!$1:$1048576,MATCH(DATE(L$2,1,1),Hybrid!$A$1:$LI$1),FALSE) -> 0.080371411 | M51: =VLOOKUP($E51,Hybrid!$1:$1048576,MATCH(DATE(M$2,1,1),Hybrid!$A$1:$LI$1),FALSE) -> 0.081017973 | ... AO51: =VLOOKUP($E51,Hybrid!$1:$1048576,MATCH(DATE(AO$2,1,1),Hybrid!$A$1:$LI$1),FALSE) -> 0.054540458
D52: class G | E52: AUTO_cg_cgas_0 | F52: =VLOOKUP($E52,Hybrid!$1:$1048576,MATCH(DATE(F$2,1,1),Hybrid!$A$1:$LI$1),FALSE) -> 0.13435819 | G52: =VLOOKUP($E52,Hybrid!$1:$1048576,MATCH(DATE(G$2,1,1),Hybrid!$A$1:$LI$1),FALSE) -> 0.13587233 | H52: =VLOOKUP($E52,Hybrid!$1:$1048576,MATCH(DATE(H$2,1,1),Hybrid!$A$1:$LI$1),FALSE) -> 0.13776953 | I52: =VLOOKUP($E52,Hybrid!$1:$1048576,MATCH(DATE(I$2,1,1),Hybrid!$A$1:$LI$1),FALSE) -> 0.1396014 | J52: =VLOOKUP($E52,Hybrid!$1:$1048576,MATCH(DATE(J$2,1,1),Hybrid!$A$1:$LI$1),FALSE) -> 0.14121093 | K52: =VLOOKUP($E52,Hybrid!$1:$1048576,MATCH(DATE(K$2,1,1),Hybrid!$A$1:$LI$1),FALSE) -> 0.14245951 | L52: =VLOOKUP($E52,Hybrid!$1:$1048576,MATCH(DATE(L$2,1,1),Hybrid!$A$1:$LI$1),FALSE) -> 0.14319646 | M52: =VLOOKUP($E52,Hybrid!$1:$1048576,MATCH(DATE(M$2,1,1),Hybrid!$A$1:$LI$1),FALSE) -> 0.14336456 | ... AO52: =VLOOKUP($E52,Hybrid!$1:$1048576,MATCH(DATE(AO$2,1,1),Hybrid!$A$1:$LI$1),FALSE) -> 0.068582169
C53: TOTAL SALES SHOCK | E53: NEWAUTO_2 | F53: =VLOOKUP($E53,Hybrid!$1:$1048576,MATCH(DATE(F$2,1,1),Hybrid!$A$1:$LI$1),FALSE) -> 1886.229 | G53: =VLOOKUP($E53,Hybrid!$1:$1048576,MATCH(DATE(G$2,1,1),Hybrid!$A$1:$LI$1),FALSE) -> 2113.9817 | H53: =VLOOKUP($E53,Hybrid!$1:$1048576,MATCH(DATE(H$2,1,1),Hybrid!$A$1:$LI$1),FALSE) -> 2322.2115 | I53: =VLOOKUP($E53,Hybrid!$1:$1048576,MATCH(DATE(I$2,1,1),Hybrid!$A$1:$LI$1),FALSE) -> 2470.6168 | J53: =VLOOKUP($E53,Hybrid!$1:$1048576,MATCH(DATE(J$2,1,1),Hybrid!$A$1:$LI$1),FALSE) -> 2605.3024 | K53: =VLOOKUP($E53,Hybrid!$1:$1048576,MATCH(DATE(K$2,1,1),Hybrid!$A$1:$LI$1),FALSE) -> 2712.0199 | L53: =VLOOKUP($E53,Hybrid!$1:$1048576,MATCH(DATE(L$2,1,1),Hybrid!$A$1:$LI$1),FALSE) -> 2791.3552 | M53: =VLOOKUP($E53,Hybrid!$1:$1048576,MATCH(DATE(M$2,1,1),Hybrid!$A$1:$LI$1),FALSE) -> 2753.5043 | ... AO53: =VLOOKUP($E53,Hybrid!$1:$1048576,MATCH(DATE(AO$2,1,1),Hybrid!$A$1:$LI$1),FALSE) -> 3042.4024
C54: OIL | E54: NEWAUTO_cfut_2 | F54: =VLOOKUP($E54,Hybrid!$1:$1048576,MATCH(DATE(F$2,1,1),Hybrid!$A$1:$LI$1),FALSE) -> 1868.6748 | G54: =VLOOKUP($E54,Hybrid!$1:$1048576,MATCH(DATE(G$2,1,1),Hybrid!$A$1:$LI$1),FALSE) -> 2093.8909 | H54: =VLOOKUP($E54,Hybrid!$1:$1048576,MATCH(DATE(H$2,1,1),Hybrid!$A$1:$LI$1),FALSE) -> 2299.5028 | I54: =VLOOKUP($E54,Hybrid!$1:$1048576,MATCH(DATE(I$2,1,1),Hybrid!$A$1:$LI$1),FALSE) -> 2445.4778 | J54: =VLOOKUP($E54,Hybrid!$1:$1048576,MATCH(DATE(J$2,1,1),Hybrid!$A$1:$LI$1),FALSE) -> 2577.5448 | K54: =VLOOKUP($E54,Hybrid!$1:$1048576,MATCH(DATE(K$2,1,1),Hybrid!$A$1:$LI$1),FALSE) -> 2681.9344 | L54: =VLOOKUP($E54,Hybrid!$1:$1048576,MATCH(DATE(L$2,1,1),Hybrid!$A$1:$LI$1),FALSE) -> 2759.2104 | M54: =VLOOKUP($E54,Hybrid!$1:$1048576,MATCH(DATE(M$2,1,1),Hybrid!$A$1:$LI$1),FALSE) -> 2719.4982 | ... AO54: =VLOOKUP($E54,Hybrid!$1:$1048576,MATCH(DATE(AO$2,1,1),Hybrid!$A$1:$LI$1),FALSE) -> 2510.1899
D55: class A | E55: NEWAUTO_ca_cfut_2 | F55: =VLOOKUP($E55,Hybrid!$1:$1048576,MATCH(DATE(F$2,1,1),Hybrid!$A$1:$LI$1),FALSE) -> 528.64567 | G55: =VLOOKUP($E55,Hybrid!$1:$1048576,MATCH(DATE(G$2,1,1),Hybrid!$A$1:$LI$1),FALSE) -> 595.40745 | H55: =VLOOKUP($E55,Hybrid!$1:$1048576,MATCH(DATE(H$2,1,1),Hybrid!$A$1:$LI$1),FALSE) -> 658.53776 | I55: =VLOOKUP($E55,Hybrid!$1:$1048576,MATCH(DATE(I$2,1,1),Hybrid!$A$1:$LI$1),FALSE) -> 706.21855 | J55: =VLOOKUP($E55,Hybrid!$1:$1048576,MATCH(DATE(J$2,1,1),Hybrid!$A$1:$LI$1),FALSE) -> 751.02186 | K55: =VLOOKUP($E55,Hybrid!$1:$1048576,MATCH(DATE(K$2,1,1),Hybrid!$A$1:$LI$1),FALSE) -> 788.20961 | L55: =VLOOKUP($E55,Hybrid!$1:$1048576,MATCH(DATE(L$2,1,1),Hybrid!$A$1:$LI$1),FALSE) -> 817.89103 | M55: =VLOOKUP($E55,Hybrid!$1:$1048576,MATCH(DATE(M$2,1,1),Hybrid!$A$1:$LI$1),FALSE) -> 814.4792 | ... AO55: =VLOOKUP($E55,Hybrid!$1:$1048576,MATCH(DATE(AO$2,1,1),Hybrid!$A$1:$LI$1),FALSE) -> 762.61309
D56: class B | E56: NEWAUTO_cb_cfut_2 | F56: =VLOOKUP($E56,Hybrid!$1:$1048576,MATCH(DATE(F$2,1,1),Hybrid!$A$1:$LI$1),FALSE) -> 507.52677 | G56: =VLOOKUP($E56,Hybrid!$1:$1048576,MATCH(DATE(G$2,1,1),Hybrid!$A$1:$LI$1),FALSE) -> 570.92859 | H56: =VLOOKUP($E56,Hybrid!$1:$1048576,MATCH(DATE(H$2,1,1),Hybrid!$A$1:$LI$1),FALSE) -> 630.41766 | I56: =VLOOKUP($E56,Hybrid!$1:$1048576,MATCH(DATE(I$2,1,1),Hybrid!$A$1:$LI$1),FALSE) -> 674.69986 | J56: =VLOOKUP($E56,Hybrid!$1:$1048576,MATCH(DATE(J$2,1,1),Hybrid!$A$1:$LI$1),FALSE) -> 715.94264 | K56: =VLOOKUP($E56,Hybrid!$1:$1048576,MATCH(DATE(K$2,1,1),Hybrid!$A$1:$LI$1),FALSE) -> 749.87097 | L56: =VLOOKUP($E56,Hybrid!$1:$1048576,MATCH(DATE(L$2,1,1),Hybrid!$A$1:$LI$1),FALSE) -> 776.53154 | M56: =VLOOKUP($E56,Hybrid!$1:$1048576,MATCH(DATE(M$2,1,1),Hybrid!$A$1:$LI$1),FALSE) -> 770.9789 | ... AO56: =VLOOKUP($E56,Hybrid!$1:$1048576,MATCH(DATE(AO$2,1,1),Hybrid!$A$1:$LI$1),FALSE) -> 841.31552
D57: class C | E57: NEWAUTO_cc_cfut_2 | F57: =VLOOKUP($E57,Hybrid!$1:$1048576,MATCH(DATE(F$2,1,1),Hybrid!$A$1:$LI$1),FALSE) -> 351.30527 | G57: =VLOOKUP($E57,Hybrid!$1:$1048576,MATCH(DATE(G$2,1,1),Hybrid!$A$1:$LI$1),FALSE) -> 394.71462 | H57: =VLOOKUP($E57,Hybrid!$1:$1048576,MATCH(DATE(H$2,1,1),Hybrid!$A$1:$LI$1),FALSE) -> 435.12508 | I57: =VLOOKUP($E57,Hybrid!$1:$1048576,MATCH(DATE(I$2,1,1),Hybrid!$A$1:$LI$1),FALSE) -> 464.75766 | J57: =VLOOKUP($E57,Hybrid!$1:$1048576,MATCH(DATE(J$2,1,1),Hybrid!$A$1:$LI$1),FALSE) -> 492.10362 | K57: =VLOOKUP($E57,Hybrid!$1:$1048576,MATCH(DATE(K$2,1,1),Hybrid!$A$1:$LI$1),FALSE) -> 514.39067 | L57: =VLOOKUP($E57,Hybrid!$1:$1048576,MATCH(DATE(L$2,1,1),Hybrid!$A$1:$LI$1),FALSE) -> 531.61224 | M57: =VLOOKUP($E57,Hybrid!$1:$1048576,MATCH(DATE(M$2,1,1),Hybrid!$A$1:$LI$1),FALSE) -> 526.25064 | ... AO57: =VLOOKUP($E57,Hybrid!$1:$1048576,MATCH(DATE(AO$2,1,1),Hybrid!$A$1:$LI$1),FALSE) -> 527.34994
D58: class D | E58: NEWAUTO_cd_cfut_2 | F58: =VLOOKUP($E58,Hybrid!$1:$1048576,MATCH(DATE(F$2,1,1),Hybrid!$A$1:$LI$1),FALSE) -> 194.72118 | G58: =VLOOKUP($E58,Hybrid!$1:$1048576,MATCH(DATE(G$2,1,1),Hybrid!$A$1:$LI$1),FALSE) -> 217.80693 | H58: =VLOOKUP($E58,Hybrid!$1:$1048576,MATCH(DATE(H$2,1,1),Hybrid!$A$1:$LI$1),FALSE) -> 238.57843 | I58: =VLOOKUP($E58,Hybrid!$1:$1048576,MATCH(DATE(I$2,1,1),Hybrid!$A$1:$LI$1),FALSE) -> 252.88222 | J58: =VLOOKUP($E58,Hybrid!$1:$1048576,MATCH(DATE(J$2,1,1),Hybrid!$A$1:$LI$1),FALSE) -> 265.51409 | K58: =VLOOKUP($E58,Hybrid!$1:$1048576,MATCH(DATE(K$2,1,1),Hybrid!$A$1:$LI$1),FALSE) -> 275.1669 | L58: =VLOOKUP($E58,Hybrid!$1:$1048576,MATCH(DATE(L$2,1,1),Hybrid!$A$1:$LI$1),FALSE) -> 281.86931 | M58: =VLOOKUP($E58,Hybrid!$1:$1048576,MATCH(DATE(M$2,1,1),Hybrid!$A$1:$LI$1),FALSE) -> 276.13302 | ... AO58: =VLOOKUP($E58,Hybrid!$1:$1048576,MATCH(DATE(AO$2,1,1),Hybrid!$A$1:$LI$1),FALSE) -> 254.91047
D59: class E | E59: NEWAUTO_ce_cfut_2 | F59: =VLOOKUP($E59,Hybrid!$1:$1048576,MATCH(DATE(F$2,1,1),Hybrid!$A$1:$LI$1),FALSE) -> 119.78455 | G59: =VLOOKUP($E59,Hybrid!$1:$1048576,MATCH(DATE(G$2,1,1),Hybrid!$A$1:$LI$1),FALSE) -> 133.42755 | H59: =VLOOKUP($E59,Hybrid!$1:$1048576,MATCH(DATE(H$2,1,1),Hybrid!$A$1:$LI$1),FALSE) -> 145.28636 | I59: =VLOOKUP($E59,Hybrid!$1:$1048576,MATCH(DATE(I$2,1,1),Hybrid!$A$1:$LI$1),FALSE) -> 152.89626 | J59: =VLOOKUP($E59,Hybrid!$1:$1048576,MATCH(DATE(J$2,1,1),Hybrid!$A$1:$LI$1),FALSE) -> 159.2667 | K59: =VLOOKUP($E59,Hybrid!$1:$1048576,MATCH(DATE(K$2,1,1),Hybrid!$A$1:$LI$1),FALSE) -> 163.73759 | L59: =VLOOKUP($E59,Hybrid!$1:$1048576,MATCH(DATE(L$2,1,1),Hybrid!$A$1:$LI$1),FALSE) -> 166.34517 | M59: =VLOOKUP($E59,Hybrid!$1:$1048576,MATCH(DATE(M$2,1,1),Hybrid!$A$1:$LI$1),FALSE) -> 161.33984 | ... AO59: =VLOOKUP($E59,Hybrid!$1:$1048576,MATCH(DATE(AO$2,1,1),Hybrid!$A$1:$LI$1),FALSE) -> 89.890079
D60: class F | E60: NEWAUTO_cf_cfut_2 | F60: =VLOOKUP($E60,Hybrid!$1:$1048576,MATCH(DATE(F$2,1,1),Hybrid!$A$1:$LI$1),FALSE) -> 57.931007 | G60: =VLOOKUP($E60,Hybrid!$1:$1048576,MATCH(DATE(G$2,1,1),Hybrid!$A$1:$LI$1),FALSE) -> 63.626841 | H60: =VLOOKUP($E60,Hybrid!$1:$1048576,MATCH(DATE(H$2,1,1),Hybrid!$A$1:$LI$1),FALSE) -> 67.89246 | I60: =VLOOKUP($E60,Hybrid!$1:$1048576,MATCH(DATE(I$2,1,1),Hybrid!$A$1:$LI$1),FALSE) -> 69.724502 | J60: =VLOOKUP($E60,Hybrid!$1:$1048576,MATCH(DATE(J$2,1,1),Hybrid!$A$1:$LI$1),FALSE) -> 70.680926 | K60: =VLOOKUP($E60,Hybrid!$1:$1048576,MATCH(DATE(K$2,1,1),Hybrid!$A$1:$LI$1),FALSE) -> 70.642585 | L60: =VLOOKUP($E60,Hybrid!$1:$1048576,MATCH(DATE(L$2,1,1),Hybrid!$A$1:$LI$1),FALSE) -> 69.692431 | M60: =VLOOKUP($E60,Hybrid!$1:$1048576,MATCH(DATE(M$2,1,1),Hybrid!$A$1:$LI$1),FALSE) -> 65.36674 | ... AO60: =VLOOKUP($E60,Hybrid!$1:$1048576,MATCH(DATE(AO$2,1,1),Hybrid!$A$1:$LI$1),FALSE) -> 19.946052
D61: class G | E61: NEWAUTO_cg_cfut_2 | F61: =VLOOKUP($E61,Hybrid!$1:$1048576,MATCH(DATE(F$2,1,1),Hybrid!$A$1:$LI$1),FALSE) -> 108.76034 | G61: =VLOOKUP($E61,Hybrid!$1:$1048576,MATCH(DATE(G$2,1,1),Hybrid!$A$1:$LI$1),FALSE) -> 117.97888 | H61: =VLOOKUP($E61,Hybrid!$1:$1048576,MATCH(DATE(H$2,1,1),Hybrid!$A$1:$LI$1),FALSE) -> 123.66507 | I61: =VLOOKUP($E61,Hybrid!$1:$1048576,MATCH(DATE(I$2,1,1),Hybrid!$A$1:$LI$1),FALSE) -> 124.2988 | J61: =VLOOKUP($E61,Hybrid!$1:$1048576,MATCH(DATE(J$2,1,1),Hybrid!$A$1:$LI$1),FALSE) -> 123.01499 | K61: =VLOOKUP($E61,Hybrid!$1:$1048576,MATCH(DATE(K$2,1,1),Hybrid!$A$1:$LI$1),FALSE) -> 119.91607 | L61: =VLOOKUP($E61,Hybrid!$1:$1048576,MATCH(DATE(L$2,1,1),Hybrid!$A$1:$LI$1),FALSE) -> 115.26868 | M61: =VLOOKUP($E61,Hybrid!$1:$1048576,MATCH(DATE(M$2,1,1),Hybrid!$A$1:$LI$1),FALSE) -> 104.94983 | ... AO61: =VLOOKUP($E61,Hybrid!$1:$1048576,MATCH(DATE(AO$2,1,1),Hybrid!$A$1:$LI$1),FALSE) -> 14.164705
C62: ELEC | E62: NEWAUTO_cele_2 | F62: =VLOOKUP($E62,Hybrid!$1:$1048576,MATCH(DATE(F$2,1,1),Hybrid!$A$1:$LI$1),FALSE) -> 17.397214 | G62: =VLOOKUP($E62,Hybrid!$1:$1048576,MATCH(DATE(G$2,1,1),Hybrid!$A$1:$LI$1),FALSE) -> 19.914952 | H62: =VLOOKUP($E62,Hybrid!$1:$1048576,MATCH(DATE(H$2,1,1),Hybrid!$A$1:$LI$1),FALSE) -> 22.515516 | I62: =VLOOKUP($E62,Hybrid!$1:$1048576,MATCH(DATE(I$2,1,1),Hybrid!$A$1:$LI$1),FALSE) -> 24.933506 | J62: =VLOOKUP($E62,Hybrid!$1:$1048576,MATCH(DATE(J$2,1,1),Hybrid!$A$1:$LI$1),FALSE) -> 27.54099 | K62: =VLOOKUP($E62,Hybrid!$1:$1048576,MATCH(DATE(K$2,1,1),Hybrid!$A$1:$LI$1),FALSE) -> 29.860195 | L62: =VLOOKUP($E62,Hybrid!$1:$1048576,MATCH(DATE(L$2,1,1),Hybrid!$A$1:$LI$1),FALSE) -> 31.913043 | M62: =VLOOKUP($E62,Hybrid!$1:$1048576,MATCH(DATE(M$2,1,1),Hybrid!$A$1:$LI$1),FALSE) -> 33.777701 | ... AO62: =VLOOKUP($E62,Hybrid!$1:$1048576,MATCH(DATE(AO$2,1,1),Hybrid!$A$1:$LI$1),FALSE) -> 894.06436
D63: class A | E63: NEWAUTO_ca_cele_2 | F63: =VLOOKUP($E63,Hybrid!$1:$1048576,MATCH(DATE(F$2,1,1),Hybrid!$A$1:$LI$1),FALSE) -> 4.924099 | G63: =VLOOKUP($E63,Hybrid!$1:$1048576,MATCH(DATE(G$2,1,1),Hybrid!$A$1:$LI$1),FALSE) -> 5.674154 | H63: =VLOOKUP($E63,Hybrid!$1:$1048576,MATCH(DATE(H$2,1,1),Hybrid!$A$1:$LI$1),FALSE) -> 6.4732876 | I63: =VLOOKUP($E63,Hybrid!$1:$1048576,MATCH(DATE(I$2,1,1),Hybrid!$A$1:$LI$1),FALSE) -> 7.2466191 | J63: =VLOOKUP($E63,Hybrid!$1:$1048576,MATCH(DATE(J$2,1,1),Hybrid!$A$1:$LI$1),FALSE) -> 8.0967317 | K63: =VLOOKUP($E63,Hybrid!$1:$1048576,MATCH(DATE(K$2,1,1),Hybrid!$A$1:$LI$1),FALSE) -> 8.8707049 | L63: =VLOOKUP($E63,Hybrid!$1:$1048576,MATCH(DATE(L$2,1,1),Hybrid!$A$1:$LI$1),FALSE) -> 9.5749381 | M63: =VLOOKUP($E63,Hybrid!$1:$1048576,MATCH(DATE(M$2,1,1),Hybrid!$A$1:$LI$1),FALSE) -> 10.267192 | ... AO63: =VLOOKUP($E63,Hybrid!$1:$1048576,MATCH(DATE(AO$2,1,1),Hybrid!$A$1:$LI$1),FALSE) -> 327.42177
D64: class B | E64: NEWAUTO_cb_cele_2 | F64: =VLOOKUP($E64,Hybrid!$1:$1048576,MATCH(DATE(F$2,1,1),Hybrid!$A$1:$LI$1),FALSE) -> 4.7303839 | G64: =VLOOKUP($E64,Hybrid!$1:$1048576,MATCH(DATE(G$2,1,1),Hybrid!$A$1:$LI$1),FALSE) -> 5.454057 | H64: =VLOOKUP($E64,Hybrid!$1:$1048576,MATCH(DATE(H$2,1,1),Hybrid!$A$1:$LI$1),FALSE) -> 6.2264357 | I64: =VLOOKUP($E64,Hybrid!$1:$1048576,MATCH(DATE(I$2,1,1),Hybrid!$A$1:$LI$1),FALSE) -> 6.9776756 | J64: =VLOOKUP($E64,Hybrid!$1:$1048576,MATCH(DATE(J$2,1,1),Hybrid!$A$1:$LI$1),FALSE) -> 7.8054462 | K64: =VLOOKUP($E64,Hybrid!$1:$1048576,MATCH(DATE(K$2,1,1),Hybrid!$A$1:$LI$1),FALSE) -> 8.5583403 | L64: =VLOOKUP($E64,Hybrid!$1:$1048576,MATCH(DATE(L$2,1,1),Hybrid!$A$1:$LI$1),FALSE) -> 9.2421875 | M64: =VLOOKUP($E64,Hybrid!$1:$1048576,MATCH(DATE(M$2,1,1),Hybrid!$A$1:$LI$1),FALSE) -> 9.9220999 | ... AO64: =VLOOKUP($E64,Hybrid!$1:$1048576,MATCH(DATE(AO$2,1,1),Hybrid!$A$1:$LI$1),FALSE) -> 301.62156
D65: class C | E65: NEWAUTO_cc_cele_2 | F65: =VLOOKUP($E65,Hybrid!$1:$1048576,MATCH(DATE(F$2,1,1),Hybrid!$A$1:$LI$1),FALSE) -> 3.2762707 | G65: =VLOOKUP($E65,Hybrid!$1:$1048576,MATCH(DATE(G$2,1,1),Hybrid!$A$1:$LI$1),FALSE) -> 3.7792389 | H65: =VLOOKUP($E65,Hybrid!$1:$1048576,MATCH(DATE(H$2,1,1),Hybrid!$A$1:$LI$1),FALSE) -> 4.3167347 | I65: =VLOOKUP($E65,Hybrid!$1:$1048576,MATCH(DATE(I$2,1,1),Hybrid!$A$1:$LI$1),FALSE) -> 4.8416799 | J65: =VLOOKUP($E65,Hybrid!$1:$1048576,MATCH(DATE(J$2,1,1),Hybrid!$A$1:$LI$1),FALSE) -> 5.4211249 | K65: =VLOOKUP($E65,Hybrid!$1:$1048576,MATCH(DATE(K$2,1,1),Hybrid!$A$1:$LI$1),FALSE) -> 5.9474742 | L65: =VLOOKUP($E65,Hybrid!$1:$1048576,MATCH(DATE(L$2,1,1),Hybrid!$A$1:$LI$1),FALSE) -> 6.424541 | M65: =VLOOKUP($E65,Hybrid!$1:$1048576,MATCH(DATE(M$2,1,1),Hybrid!$A$1:$LI$1),FALSE) -> 6.9028204 | ... AO65: =VLOOKUP($E65,Hybrid!$1:$1048576,MATCH(DATE(AO$2,1,1),Hybrid!$A$1:$LI$1),FALSE) -> 199.5835
D66: class D | E66: NEWAUTO_cd_cele_2 | F66: =VLOOKUP($E66,Hybrid!$1:$1048576,MATCH(DATE(F$2,1,1),Hybrid!$A$1:$LI$1),FALSE) -> 1.8075193 | G66: =VLOOKUP($E66,Hybrid!$1:$1048576,MATCH(DATE(G$2,1,1),Hybrid!$A$1:$LI$1),FALSE) -> 2.0477922 | H66: =VLOOKUP($E66,Hybrid!$1:$1048576,MATCH(DATE(H$2,1,1),Hybrid!$A$1:$LI$1),FALSE) -> 2.282296 | I66: =VLOOKUP($E66,Hybrid!$1:$1048576,MATCH(DATE(I$2,1,1),Hybrid!$A$1:$LI$1),FALSE) -> 2.4783865 | J66: =VLOOKUP($E66,Hybrid!$1:$1048576,MATCH(DATE(J$2,1,1),Hybrid!$A$1:$LI$1),FALSE) -> 2.6767285 | K66: =VLOOKUP($E66,Hybrid!$1:$1048576,MATCH(DATE(K$2,1,1),Hybrid!$A$1:$LI$1),FALSE) -> 2.8442571 | L66: =VLOOKUP($E66,Hybrid!$1:$1048576,MATCH(DATE(L$2,1,1),Hybrid!$A$1:$LI$1),FALSE) -> 2.9820308 | M66: =VLOOKUP($E66,Hybrid!$1:$1048576,MATCH(DATE(M$2,1,1),Hybrid!$A$1:$LI$1),FALSE) -> 3.0535675 | ... AO66: =VLOOKUP($E66,Hybrid!$1:$1048576,MATCH(DATE(AO$2,1,1),Hybrid!$A$1:$LI$1),FALSE) -> 42.095974
D67: class E | E67: NEWAUTO_ce_cele_2 | F67: =VLOOKUP($E67,Hybrid!$1:$1048576,MATCH(DATE(F$2,1,1),Hybrid!$A$1:$LI$1),FALSE) -> 1.1126687 | G67: =VLOOKUP($E67,Hybrid!$1:$1048576,MATCH(DATE(G$2,1,1),Hybrid!$A$1:$LI$1),FALSE) -> 1.2575884 | H67: =VLOOKUP($E67,Hybrid!$1:$1048576,MATCH(DATE(H$2,1,1),Hybrid!$A$1:$LI$1),FALSE) -> 1.3965578 | I67: =VLOOKUP($E67,Hybrid!$1:$1048576,MATCH(DATE(I$2,1,1),Hybrid!$A$1:$LI$1),FALSE) -> 1.5103535 | J67: =VLOOKUP($E67,Hybrid!$1:$1048576,MATCH(DATE(J$2,1,1),Hybrid!$A$1:$LI$1),FALSE) -> 1.6238947 | K67: =VLOOKUP($E67,Hybrid!$1:$1048576,MATCH(DATE(K$2,1,1),Hybrid!$A$1:$LI$1),FALSE) -> 1.7168004 | L67: =VLOOKUP($E67,Hybrid!$1:$1048576,MATCH(DATE(L$2,1,1),Hybrid!$A$1:$LI$1),FALSE) -> 1.7899141 | M67: =VLOOKUP($E67,Hybrid!$1:$1048576,MATCH(DATE(M$2,1,1),Hybrid!$A$1:$LI$1),FALSE) -> 1.8228585 | ... AO67: =VLOOKUP($E67,Hybrid!$1:$1048576,MATCH(DATE(AO$2,1,1),Hybrid!$A$1:$LI$1),FALSE) -> 19.880349
D68: class F | E68: NEWAUTO_cf_cele_2 | F68: =VLOOKUP($E68,Hybrid!$1:$1048576,MATCH(DATE(F$2,1,1),Hybrid!$A$1:$LI$1),FALSE) -> 0.53722532 | G68: =VLOOKUP($E68,Hybrid!$1:$1048576,MATCH(DATE(G$2,1,1),Hybrid!$A$1:$LI$1),FALSE) -> 0.59574104 | H68: =VLOOKUP($E68,Hybrid!$1:$1048576,MATCH(DATE(H$2,1,1),Hybrid!$A$1:$LI$1),FALSE) -> 0.64387985 | I68: =VLOOKUP($E68,Hybrid!$1:$1048576,MATCH(DATE(I$2,1,1),Hybrid!$A$1:$LI$1),FALSE) -> 0.67307876 | J68: =VLOOKUP($E68,Hybrid!$1:$1048576,MATCH(DATE(J$2,1,1),Hybrid!$A$1:$LI$1),FALSE) -> 0.69650479 | K68: =VLOOKUP($E68,Hybrid!$1:$1048576,MATCH(DATE(K$2,1,1),Hybrid!$A$1:$LI$1),FALSE) -> 0.70889167 | L68: =VLOOKUP($E68,Hybrid!$1:$1048576,MATCH(DATE(L$2,1,1),Hybrid!$A$1:$LI$1),FALSE) -> 0.71118917 | M68: =VLOOKUP($E68,Hybrid!$1:$1048576,MATCH(DATE(M$2,1,1),Hybrid!$A$1:$LI$1),FALSE) -> 0.68886818 | ... AO68: =VLOOKUP($E68,Hybrid!$1:$1048576,MATCH(DATE(AO$2,1,1),Hybrid!$A$1:$LI$1),FALSE) -> 1.9950111
D69: class G | E69: NEWAUTO_cg_cele_2 | F69: =VLOOKUP($E69,Hybrid!$1:$1048576,MATCH(DATE(F$2,1,1),Hybrid!$A$1:$LI$1),FALSE) -> 1.0090476 | G69: =VLOOKUP($E69,Hybrid!$1:$1048576,MATCH(DATE(G$2,1,1),Hybrid!$A$1:$LI$1),FALSE) -> 1.1063806 | H69: =VLOOKUP($E69,Hybrid!$1:$1048576,MATCH(DATE(H$2,1,1),Hybrid!$A$1:$LI$1),FALSE) -> 1.1763242 | I69: =VLOOKUP($E69,Hybrid!$1:$1048576,MATCH(DATE(I$2,1,1),Hybrid!$A$1:$LI$1),FALSE) -> 1.2057126 | J69: =VLOOKUP($E69,Hybrid!$1:$1048576,MATCH(DATE(J$2,1,1),Hybrid!$A$1:$LI$1),FALSE) -> 1.2205591 | K69: =VLOOKUP($E69,Hybrid!$1:$1048576,MATCH(DATE(K$2,1,1),Hybrid!$A$1:$LI$1),FALSE) -> 1.2137267 | L69: =VLOOKUP($E69,Hybrid!$1:$1048576,MATCH(DATE(L$2,1,1),Hybrid!$A$1:$LI$1),FALSE) -> 1.1882424 | M69: =VLOOKUP($E69,Hybrid!$1:$1048576,MATCH(DATE(M$2,1,1),Hybrid!$A$1:$LI$1),FALSE) -> 1.1202938 | ... AO69: =VLOOKUP($E69,Hybrid!$1:$1048576,MATCH(DATE(AO$2,1,1),Hybrid!$A$1:$LI$1),FALSE) -> 1.4661914
C70: GAS | E70: NEWAUTO_cgas_2 | F70: =VLOOKUP($E70,Hybrid!$1:$1048576,MATCH(DATE(F$2,1,1),Hybrid!$A$1:$LI$1),FALSE) -> 0.15698923 | G70: =VLOOKUP($E70,Hybrid!$1:$1048576,MATCH(DATE(G$2,1,1),Hybrid!$A$1:$LI$1),FALSE) -> 0.17590986 | H70: =VLOOKUP($E70,Hybrid!$1:$1048576,MATCH(DATE(H$2,1,1),Hybrid!$A$1:$LI$1),FALSE) -> 0.19318352 | I70: =VLOOKUP($E70,Hybrid!$1:$1048576,MATCH(DATE(I$2,1,1),Hybrid!$A$1:$LI$1),FALSE) -> 0.20544703 | J70: =VLOOKUP($E70,Hybrid!$1:$1048576,MATCH(DATE(J$2,1,1),Hybrid!$A$1:$LI$1),FALSE) -> 0.21654211 | K70: =VLOOKUP($E70,Hybrid!$1:$1048576,MATCH(DATE(K$2,1,1),Hybrid!$A$1:$LI$1),FALSE) -> 0.22531198 | L70: =VLOOKUP($E70,Hybrid!$1:$1048576,MATCH(DATE(L$2,1,1),Hybrid!$A$1:$LI$1),FALSE) -> 0.23180401 | M70: =VLOOKUP($E70,Hybrid!$1:$1048576,MATCH(DATE(M$2,1,1),Hybrid!$A$1:$LI$1),FALSE) -> 0.22846775 | ... AO70: =VLOOKUP($E70,Hybrid!$1:$1048576,MATCH(DATE(AO$2,1,1),Hybrid!$A$1:$LI$1),FALSE) -> 0.21088355
D71: class A | E71: NEWAUTO_ca_cgas_2 | F71: =VLOOKUP($E71,Hybrid!$1:$1048576,MATCH(DATE(F$2,1,1),Hybrid!$A$1:$LI$1),FALSE) -> 0.044412049 | G71: =VLOOKUP($E71,Hybrid!$1:$1048576,MATCH(DATE(G$2,1,1),Hybrid!$A$1:$LI$1),FALSE) -> 0.050020772 | H71: =VLOOKUP($E71,Hybrid!$1:$1048576,MATCH(DATE(H$2,1,1),Hybrid!$A$1:$LI$1),FALSE) -> 0.055324412 | I71: =VLOOKUP($E71,Hybrid!$1:$1048576,MATCH(DATE(I$2,1,1),Hybrid!$A$1:$LI$1),FALSE) -> 0.059330123 | J71: =VLOOKUP($E71,Hybrid!$1:$1048576,MATCH(DATE(J$2,1,1),Hybrid!$A$1:$LI$1),FALSE) -> 0.063094094 | K71: =VLOOKUP($E71,Hybrid!$1:$1048576,MATCH(DATE(K$2,1,1),Hybrid!$A$1:$LI$1),FALSE) -> 0.066218273 | L71: =VLOOKUP($E71,Hybrid!$1:$1048576,MATCH(DATE(L$2,1,1),Hybrid!$A$1:$LI$1),FALSE) -> 0.068711839 | M71: =VLOOKUP($E71,Hybrid!$1:$1048576,MATCH(DATE(M$2,1,1),Hybrid!$A$1:$LI$1),FALSE) -> 0.068425208 | ... AO71: =VLOOKUP($E71,Hybrid!$1:$1048576,MATCH(DATE(AO$2,1,1),Hybrid!$A$1:$LI$1),FALSE) -> 0.064067885
D72: class B | E72: NEWAUTO_cb_cgas_2 | F72: =VLOOKUP($E72,Hybrid!$1:$1048576,MATCH(DATE(F$2,1,1),Hybrid!$A$1:$LI$1),FALSE) -> 0.04263783 | G72: =VLOOKUP($E72,Hybrid!$1:$1048576,MATCH(DATE(G$2,1,1),Hybrid!$A$1:$LI$1),FALSE) -> 0.047964279 | H72: =VLOOKUP($E72,Hybrid!$1:$1048576,MATCH(DATE(H$2,1,1),Hybrid!$A$1:$LI$1),FALSE) -> 0.052962015 | I72: =VLOOKUP($E72,Hybrid!$1:$1048576,MATCH(DATE(I$2,1,1),Hybrid!$A$1:$LI$1),FALSE) -> 0.056682207 | J72: =VLOOKUP($E72,Hybrid!$1:$1048576,MATCH(DATE(J$2,1,1),Hybrid!$A$1:$LI$1),FALSE) -> 0.060147054 | K72: =VLOOKUP($E72,Hybrid!$1:$1048576,MATCH(DATE(K$2,1,1),Hybrid!$A$1:$LI$1),FALSE) -> 0.062997406 | L72: =VLOOKUP($E72,Hybrid!$1:$1048576,MATCH(DATE(L$2,1,1),Hybrid!$A$1:$LI$1),FALSE) -> 0.065237188 | M72: =VLOOKUP($E72,Hybrid!$1:$1048576,MATCH(DATE(M$2,1,1),Hybrid!$A$1:$LI$1),FALSE) -> 0.064770705 | ... AO72: =VLOOKUP($E72,Hybrid!$1:$1048576,MATCH(DATE(AO$2,1,1),Hybrid!$A$1:$LI$1),FALSE) -> 0.070679754
D73: class C | E73: NEWAUTO_cc_cgas_2 | F73: =VLOOKUP($E73,Hybrid!$1:$1048576,MATCH(DATE(F$2,1,1),Hybrid!$A$1:$LI$1),FALSE) -> 0.029513505 | G73: =VLOOKUP($E73,Hybrid!$1:$1048576,MATCH(DATE(G$2,1,1),Hybrid!$A$1:$LI$1),FALSE) -> 0.033160368 | H73: =VLOOKUP($E73,Hybrid!$1:$1048576,MATCH(DATE(H$2,1,1),Hybrid!$A$1:$LI$1),FALSE) -> 0.036555291 | I73: =VLOOKUP($E73,Hybrid!$1:$1048576,MATCH(DATE(I$2,1,1),Hybrid!$A$1:$LI$1),FALSE) -> 0.039044753 | J73: =VLOOKUP($E73,Hybrid!$1:$1048576,MATCH(DATE(J$2,1,1),Hybrid!$A$1:$LI$1),FALSE) -> 0.041342115 | K73: =VLOOKUP($E73,Hybrid!$1:$1048576,MATCH(DATE(K$2,1,1),Hybrid!$A$1:$LI$1),FALSE) -> 0.043214472 | L73: =VLOOKUP($E73,Hybrid!$1:$1048576,MATCH(DATE(L$2,1,1),Hybrid!$A$1:$LI$1),FALSE) -> 0.044661273 | M73: =VLOOKUP($E73,Hybrid!$1:$1048576,MATCH(DATE(M$2,1,1),Hybrid!$A$1:$LI$1),FALSE) -> 0.04421084 | ... AO73: =VLOOKUP($E73,Hybrid!$1:$1048576,MATCH(DATE(AO$2,1,1),Hybrid!$A$1:$LI$1),FALSE) -> 0.044303193
D74: class D | E74: NEWAUTO_cd_cgas_2 | F74: =VLOOKUP($E74,Hybrid!$1:$1048576,MATCH(DATE(F$2,1,1),Hybrid!$A$1:$LI$1),FALSE) -> 0.01635872 | G74: =VLOOKUP($E74,Hybrid!$1:$1048576,MATCH(DATE(G$2,1,1),Hybrid!$A$1:$LI$1),FALSE) -> 0.018298177 | H74: =VLOOKUP($E74,Hybrid!$1:$1048576,MATCH(DATE(H$2,1,1),Hybrid!$A$1:$LI$1),FALSE) -> 0.020043211 | I74: =VLOOKUP($E74,Hybrid!$1:$1048576,MATCH(DATE(I$2,1,1),Hybrid!$A$1:$LI$1),FALSE) -> 0.021244887 | J74: =VLOOKUP($E74,Hybrid!$1:$1048576,MATCH(DATE(J$2,1,1),Hybrid!$A$1:$LI$1),FALSE) -> 0.022306103 | K74: =VLOOKUP($E74,Hybrid!$1:$1048576,MATCH(DATE(K$2,1,1),Hybrid!$A$1:$LI$1),FALSE) -> 0.023117045 | L74: =VLOOKUP($E74,Hybrid!$1:$1048576,MATCH(DATE(L$2,1,1),Hybrid!$A$1:$LI$1),FALSE) -> 0.023680121 | M74: =VLOOKUP($E74,Hybrid!$1:$1048576,MATCH(DATE(M$2,1,1),Hybrid!$A$1:$LI$1),FALSE) -> 0.02319821 | ... AO74: =VLOOKUP($E74,Hybrid!$1:$1048576,MATCH(DATE(AO$2,1,1),Hybrid!$A$1:$LI$1),FALSE) -> 0.021415282
D75: class E | E75: NEWAUTO_ce_cgas_2 | F75: =VLOOKUP($E75,Hybrid!$1:$1048576,MATCH(DATE(F$2,1,1),Hybrid!$A$1:$LI$1),FALSE) -> 0.010063219 | G75: =VLOOKUP($E75,Hybrid!$1:$1048576,MATCH(DATE(G$2,1,1),Hybrid!$A$1:$LI$1),FALSE) -> 0.011209382 | H75: =VLOOKUP($E75,Hybrid!$1:$1048576,MATCH(DATE(H$2,1,1),Hybrid!$A$1:$LI$1),FALSE) -> 0.012205652 | I75: =VLOOKUP($E75,Hybrid!$1:$1048576,MATCH(DATE(I$2,1,1),Hybrid!$A$1:$LI$1),FALSE) -> 0.012844967 | J75: =VLOOKUP($E75,Hybrid!$1:$1048576,MATCH(DATE(J$2,1,1),Hybrid!$A$1:$LI$1),FALSE) -> 0.013380154 | K75: =VLOOKUP($E75,Hybrid!$1:$1048576,MATCH(DATE(K$2,1,1),Hybrid!$A$1:$LI$1),FALSE) -> 0.013755758 | L75: =VLOOKUP($E75,Hybrid!$1:$1048576,MATCH(DATE(L$2,1,1),Hybrid!$A$1:$LI$1),FALSE) -> 0.013974823 | M75: =VLOOKUP($E75,Hybrid!$1:$1048576,MATCH(DATE(M$2,1,1),Hybrid!$A$1:$LI$1),FALSE) -> 0.01355432 | ... AO75: =VLOOKUP($E75,Hybrid!$1:$1048576,MATCH(DATE(AO$2,1,1),Hybrid!$A$1:$LI$1),FALSE) -> 0.007551755
D76: class F | E76: NEWAUTO_cf_cgas_2 | F76: =VLOOKUP($E76,Hybrid!$1:$1048576,MATCH(DATE(F$2,1,1),Hybrid!$A$1:$LI$1),FALSE) -> 0.0048668415 | G76: =VLOOKUP($E76,Hybrid!$1:$1048576,MATCH(DATE(G$2,1,1),Hybrid!$A$1:$LI$1),FALSE) -> 0.0053453542 | H76: =VLOOKUP($E76,Hybrid!$1:$1048576,MATCH(DATE(H$2,1,1),Hybrid!$A$1:$LI$1),FALSE) -> 0.0057037131 | I76: =VLOOKUP($E76,Hybrid!$1:$1048576,MATCH(DATE(I$2,1,1),Hybrid!$A$1:$LI$1),FALSE) -> 0.0058576248 | J76: =VLOOKUP($E76,Hybrid!$1:$1048576,MATCH(DATE(J$2,1,1),Hybrid!$A$1:$LI$1),FALSE) -> 0.0059379749 | K76: =VLOOKUP($E76,Hybrid!$1:$1048576,MATCH(DATE(K$2,1,1),Hybrid!$A$1:$LI$1),FALSE) -> 0.0059347539 | L76: =VLOOKUP($E76,Hybrid!$1:$1048576,MATCH(DATE(L$2,1,1),Hybrid!$A$1:$LI$1),FALSE) -> 0.0058549305 | M76: =VLOOKUP($E76,Hybrid!$1:$1048576,MATCH(DATE(M$2,1,1),Hybrid!$A$1:$LI$1),FALSE) -> 0.0054915249 | ... AO76: =VLOOKUP($E76,Hybrid!$1:$1048576,MATCH(DATE(AO$2,1,1),Hybrid!$A$1:$LI$1),FALSE) -> 0.0016756877
D77: class G | E77: NEWAUTO_cg_cgas_2 | F77: =VLOOKUP($E77,Hybrid!$1:$1048576,MATCH(DATE(F$2,1,1),Hybrid!$A$1:$LI$1),FALSE) -> 0.0091370647 | G77: =VLOOKUP($E77,Hybrid!$1:$1048576,MATCH(DATE(G$2,1,1),Hybrid!$A$1:$LI$1),FALSE) -> 0.0099115229 | H77: =VLOOKUP($E77,Hybrid!$1:$1048576,MATCH(DATE(H$2,1,1),Hybrid!$A$1:$LI$1),FALSE) -> 0.010389226 | I77: =VLOOKUP($E77,Hybrid!$1:$1048576,MATCH(DATE(I$2,1,1),Hybrid!$A$1:$LI$1),FALSE) -> 0.010442466 | J77: =VLOOKUP($E77,Hybrid!$1:$1048576,MATCH(DATE(J$2,1,1),Hybrid!$A$1:$LI$1),FALSE) -> 0.010334612 | K77: =VLOOKUP($E77,Hybrid!$1:$1048576,MATCH(DATE(K$2,1,1),Hybrid!$A$1:$LI$1),FALSE) -> 0.010074269 | L77: =VLOOKUP($E77,Hybrid!$1:$1048576,MATCH(DATE(L$2,1,1),Hybrid!$A$1:$LI$1),FALSE) -> 0.0096838362 | M77: =VLOOKUP($E77,Hybrid!$1:$1048576,MATCH(DATE(M$2,1,1),Hybrid!$A$1:$LI$1),FALSE) -> 0.0088169394 | ... AO77: =VLOOKUP($E77,Hybrid!$1:$1048576,MATCH(DATE(AO$2,1,1),Hybrid!$A$1:$LI$1),FALSE) -> 0.001189991
C78: TOTAL SALES BASELINE | E78: NEWAUTO_0 | F78: =VLOOKUP($E78,Hybrid!$1:$1048576,MATCH(DATE(F$2,1,1),Hybrid!$A$1:$LI$1),FALSE) -> 1886.229 | G78: =VLOOKUP($E78,Hybrid!$1:$1048576,MATCH(DATE(G$2,1,1),Hybrid!$A$1:$LI$1),FALSE) -> 2113.9817 | H78: =VLOOKUP($E78,Hybrid!$1:$1048576,MATCH(DATE(H$2,1,1),Hybrid!$A$1:$LI$1),FALSE) -> 2322.2115 | I78: =VLOOKUP($E78,Hybrid!$1:$1048576,MATCH(DATE(I$2,1,1),Hybrid!$A$1:$LI$1),FALSE) -> 2470.6168 | J78: =VLOOKUP($E78,Hybrid!$1:$1048576,MATCH(DATE(J$2,1,1),Hybrid!$A$1:$LI$1),FALSE) -> 2605.3024 | K78: =VLOOKUP($E78,Hybrid!$1:$1048576,MATCH(DATE(K$2,1,1),Hybrid!$A$1:$LI$1),FALSE) -> 2712.0199 | L78: =VLOOKUP($E78,Hybrid!$1:$1048576,MATCH(DATE(L$2,1,1),Hybrid!$A$1:$LI$1),FALSE) -> 2780.8926 | M78: =VLOOKUP($E78,Hybrid!$1:$1048576,MATCH(DATE(M$2,1,1),Hybrid!$A$1:$LI$1),FALSE) -> 2832.0336 | ... AO78: =VLOOKUP($E78,Hybrid!$1:$1048576,MATCH(DATE(AO$2,1,1),Hybrid!$A$1:$LI$1),FALSE) -> 3171.5453
C79: OIL | E79: NEWAUTO_cfut_0 | F79: =VLOOKUP($E79,Hybrid!$1:$1048576,MATCH(DATE(F$2,1,1),Hybrid!$A$1:$LI$1),FALSE) -> 1868.6748 | G79: =VLOOKUP($E79,Hybrid!$1:$1048576,MATCH(DATE(G$2,1,1),Hybrid!$A$1:$LI$1),FALSE) -> 2093.8909 | H79: =VLOOKUP($E79,Hybrid!$1:$1048576,MATCH(DATE(H$2,1,1),Hybrid!$A$1:$LI$1),FALSE) -> 2299.5028 | I79: =VLOOKUP($E79,Hybrid!$1:$1048576,MATCH(DATE(I$2,1,1),Hybrid!$A$1:$LI$1),FALSE) -> 2445.4778 | J79: =VLOOKUP($E79,Hybrid!$1:$1048576,MATCH(DATE(J$2,1,1),Hybrid!$A$1:$LI$1),FALSE) -> 2577.5448 | K79: =VLOOKUP($E79,Hybrid!$1:$1048576,MATCH(DATE(K$2,1,1),Hybrid!$A$1:$LI$1),FALSE) -> 2681.9344 | L79: =VLOOKUP($E79,Hybrid!$1:$1048576,MATCH(DATE(L$2,1,1),Hybrid!$A$1:$LI$1),FALSE) -> 2748.8042 | M79: =VLOOKUP($E79,Hybrid!$1:$1048576,MATCH(DATE(M$2,1,1),Hybrid!$A$1:$LI$1),FALSE) -> 2797.8652 | ... AO79: =VLOOKUP($E79,Hybrid!$1:$1048576,MATCH(DATE(AO$2,1,1),Hybrid!$A$1:$LI$1),FALSE) -> 3178.9776
D80: class A | E80: NEWAUTO_ca_cfut_0 | F80: =VLOOKUP($E80,Hybrid!$1:$1048576,MATCH(DATE(F$2,1,1),Hybrid!$A$1:$LI$1),FALSE) -> 528.64567 | G80: =VLOOKUP($E80,Hybrid!$1:$1048576,MATCH(DATE(G$2,1,1),Hybrid!$A$1:$LI$1),FALSE) -> 595.40745 | H80: =VLOOKUP($E80,Hybrid!$1:$1048576,MATCH(DATE(H$2,1,1),Hybrid!$A$1:$LI$1),FALSE) -> 658.53775 | I80: =VLOOKUP($E80,Hybrid!$1:$1048576,MATCH(DATE(I$2,1,1),Hybrid!$A$1:$LI$1),FALSE) -> 706.21855 | J80: =VLOOKUP($E80,Hybrid!$1:$1048576,MATCH(DATE(J$2,1,1),Hybrid!$A$1:$LI$1),FALSE) -> 751.02186 | K80: =VLOOKUP($E80,Hybrid!$1:$1048576,MATCH(DATE(K$2,1,1),Hybrid!$A$1:$LI$1),FALSE) -> 788.2096 | L80: =VLOOKUP($E80,Hybrid!$1:$1048576,MATCH(DATE(L$2,1,1),Hybrid!$A$1:$LI$1),FALSE) -> 814.91551 | M80: =VLOOKUP($E80,Hybrid!$1:$1048576,MATCH(DATE(M$2,1,1),Hybrid!$A$1:$LI$1),FALSE) -> 837.01972 | ... AO80: =VLOOKUP($E80,Hybrid!$1:$1048576,MATCH(DATE(AO$2,1,1),Hybrid!$A$1:$LI$1),FALSE) -> 1018.3463
D81: class B | E81: NEWAUTO_cb_cfut_0 | F81: =VLOOKUP($E81,Hybrid!$1:$1048576,MATCH(DATE(F$2,1,1),Hybrid!$A$1:$LI$1),FALSE) -> 507.52677 | G81: =VLOOKUP($E81,Hybrid!$1:$1048576,MATCH(DATE(G$2,1,1),Hybrid!$A$1:$LI$1),FALSE) -> 570.92859 | H81: =VLOOKUP($E81,Hybrid!$1:$1048576,MATCH(DATE(H$2,1,1),Hybrid!$A$1:$LI$1),FALSE) -> 630.41766 | I81: =VLOOKUP($E81,Hybrid!$1:$1048576,MATCH(DATE(I$2,1,1),Hybrid!$A$1:$LI$1),FALSE) -> 674.69986 | J81: =VLOOKUP($E81,Hybrid!$1:$1048576,MATCH(DATE(J$2,1,1),Hybrid!$A$1:$LI$1),FALSE) -> 715.94264 | K81: =VLOOKUP($E81,Hybrid!$1:$1048576,MATCH(DATE(K$2,1,1),Hybrid!$A$1:$LI$1),FALSE) -> 749.87096 | L81: =VLOOKUP($E81,Hybrid!$1:$1048576,MATCH(DATE(L$2,1,1),Hybrid!$A$1:$LI$1),FALSE) -> 773.65847 | M81: =VLOOKUP($E81,Hybrid!$1:$1048576,MATCH(DATE(M$2,1,1),Hybrid!$A$1:$LI$1),FALSE) -> 792.78239 | ... AO81: =VLOOKUP($E81,Hybrid!$1:$1048576,MATCH(DATE(AO$2,1,1),Hybrid!$A$1:$LI$1),FALSE) -> 1050.4926
D82: class C | E82: NEWAUTO_cc_cfut_0 | F82: =VLOOKUP($E82,Hybrid!$1:$1048576,MATCH(DATE(F$2,1,1),Hybrid!$A$1:$LI$1),FALSE) -> 351.30527 | G82: =VLOOKUP($E82,Hybrid!$1:$1048576,MATCH(DATE(G$2,1,1),Hybrid!$A$1:$LI$1),FALSE) -> 394.71462 | H82: =VLOOKUP($E82,Hybrid!$1:$1048576,MATCH(DATE(H$2,1,1),Hybrid!$A$1:$LI$1),FALSE) -> 435.12508 | I82: =VLOOKUP($E82,Hybrid!$1:$1048576,MATCH(DATE(I$2,1,1),Hybrid!$A$1:$LI$1),FALSE) -> 464.75766 | J82: =VLOOKUP($E82,Hybrid!$1:$1048576,MATCH(DATE(J$2,1,1),Hybrid!$A$1:$LI$1),FALSE) -> 492.10362 | K82: =VLOOKUP($E82,Hybrid!$1:$1048576,MATCH(DATE(K$2,1,1),Hybrid!$A$1:$LI$1),FALSE) -> 514.39067 | L82: =VLOOKUP($E82,Hybrid!$1:$1048576,MATCH(DATE(L$2,1,1),Hybrid!$A$1:$LI$1),FALSE) -> 529.61273 | M82: =VLOOKUP($E82,Hybrid!$1:$1048576,MATCH(DATE(M$2,1,1),Hybrid!$A$1:$LI$1),FALSE) -> 541.44893 | ... AO82: =VLOOKUP($E82,Hybrid!$1:$1048576,MATCH(DATE(AO$2,1,1),Hybrid!$A$1:$LI$1),FALSE) -> 670.0889
D83: class D | E83: NEWAUTO_cd_cfut_0 | F83: =VLOOKUP($E83,Hybrid!$1:$1048576,MATCH(DATE(F$2,1,1),Hybrid!$A$1:$LI$1),FALSE) -> 194.72118 | G83: =VLOOKUP($E83,Hybrid!$1:$1048576,MATCH(DATE(G$2,1,1),Hybrid!$A$1:$LI$1),FALSE) -> 217.80693 | H83: =VLOOKUP($E83,Hybrid!$1:$1048576,MATCH(DATE(H$2,1,1),Hybrid!$A$1:$LI$1),FALSE) -> 238.57842 | I83: =VLOOKUP($E83,Hybrid!$1:$1048576,MATCH(DATE(I$2,1,1),Hybrid!$A$1:$LI$1),FALSE) -> 252.88222 | J83: =VLOOKUP($E83,Hybrid!$1:$1048576,MATCH(DATE(J$2,1,1),Hybrid!$A$1:$LI$1),FALSE) -> 265.51409 | K83: =VLOOKUP($E83,Hybrid!$1:$1048576,MATCH(DATE(K$2,1,1),Hybrid!$A$1:$LI$1),FALSE) -> 275.1669 | L83: =VLOOKUP($E83,Hybrid!$1:$1048576,MATCH(DATE(L$2,1,1),Hybrid!$A$1:$LI$1),FALSE) -> 280.78064 | M83: =VLOOKUP($E83,Hybrid!$1:$1048576,MATCH(DATE(M$2,1,1),Hybrid!$A$1:$LI$1),FALSE) -> 284.32117 | ... AO83: =VLOOKUP($E83,Hybrid!$1:$1048576,MATCH(DATE(AO$2,1,1),Hybrid!$A$1:$LI$1),FALSE) -> 287.32201
D84: class E | E84: NEWAUTO_ce_cfut_0 | F84: =VLOOKUP($E84,Hybrid!$1:$1048576,MATCH(DATE(F$2,1,1),Hybrid!$A$1:$LI$1),FALSE) -> 119.78455 | G84: =VLOOKUP($E84,Hybrid!$1:$1048576,MATCH(DATE(G$2,1,1),Hybrid!$A$1:$LI$1),FALSE) -> 133.42755 | H84: =VLOOKUP($E84,Hybrid!$1:$1048576,MATCH(DATE(H$2,1,1),Hybrid!$A$1:$LI$1),FALSE) -> 145.28636 | I84: =VLOOKUP($E84,Hybrid!$1:$1048576,MATCH(DATE(I$2,1,1),Hybrid!$A$1:$LI$1),FALSE) -> 152.89626 | J84: =VLOOKUP($E84,Hybrid!$1:$1048576,MATCH(DATE(J$2,1,1),Hybrid!$A$1:$LI$1),FALSE) -> 159.2667 | K84: =VLOOKUP($E84,Hybrid!$1:$1048576,MATCH(DATE(K$2,1,1),Hybrid!$A$1:$LI$1),FALSE) -> 163.73759 | L84: =VLOOKUP($E84,Hybrid!$1:$1048576,MATCH(DATE(L$2,1,1),Hybrid!$A$1:$LI$1),FALSE) -> 165.68448 | M84: =VLOOKUP($E84,Hybrid!$1:$1048576,MATCH(DATE(M$2,1,1),Hybrid!$A$1:$LI$1),FALSE) -> 166.27256 | ... AO84: =VLOOKUP($E84,Hybrid!$1:$1048576,MATCH(DATE(AO$2,1,1),Hybrid!$A$1:$LI$1),FALSE) -> 110.76943
D85: class F | E85: NEWAUTO_cf_cfut_0 | F85: =VLOOKUP($E85,Hybrid!$1:$1048576,MATCH(DATE(F$2,1,1),Hybrid!$A$1:$LI$1),FALSE) -> 57.931007 | G85: =VLOOKUP($E85,Hybrid!$1:$1048576,MATCH(DATE(G$2,1,1),Hybrid!$A$1:$LI$1),FALSE) -> 63.626841 | H85: =VLOOKUP($E85,Hybrid!$1:$1048576,MATCH(DATE(H$2,1,1),Hybrid!$A$1:$LI$1),FALSE) -> 67.89246 | I85: =VLOOKUP($E85,Hybrid!$1:$1048576,MATCH(DATE(I$2,1,1),Hybrid!$A$1:$LI$1),FALSE) -> 69.724502 | J85: =VLOOKUP($E85,Hybrid!$1:$1048576,MATCH(DATE(J$2,1,1),Hybrid!$A$1:$LI$1),FALSE) -> 70.680926 | K85: =VLOOKUP($E85,Hybrid!$1:$1048576,MATCH(DATE(K$2,1,1),Hybrid!$A$1:$LI$1),FALSE) -> 70.642585 | L85: =VLOOKUP($E85,Hybrid!$1:$1048576,MATCH(DATE(L$2,1,1),Hybrid!$A$1:$LI$1),FALSE) -> 69.397563 | M85: =VLOOKUP($E85,Hybrid!$1:$1048576,MATCH(DATE(M$2,1,1),Hybrid!$A$1:$LI$1),FALSE) -> 67.488484 | ... AO85: =VLOOKUP($E85,Hybrid!$1:$1048576,MATCH(DATE(AO$2,1,1),Hybrid!$A$1:$LI$1),FALSE) -> 23.733843
D86: class G | E86: NEWAUTO_cg_cfut_0 | F86: =VLOOKUP($E86,Hybrid!$1:$1048576,MATCH(DATE(F$2,1,1),Hybrid!$A$1:$LI$1),FALSE) -> 108.76034 | G86: =VLOOKUP($E86,Hybrid!$1:$1048576,MATCH(DATE(G$2,1,1),Hybrid!$A$1:$LI$1),FALSE) -> 117.97888 | H86: =VLOOKUP($E86,Hybrid!$1:$1048576,MATCH(DATE(H$2,1,1),Hybrid!$A$1:$LI$1),FALSE) -> 123.66507 | I86: =VLOOKUP($E86,Hybrid!$1:$1048576,MATCH(DATE(I$2,1,1),Hybrid!$A$1:$LI$1),FALSE) -> 124.2988 | J86: =VLOOKUP($E86,Hybrid!$1:$1048576,MATCH(DATE(J$2,1,1),Hybrid!$A$1:$LI$1),FALSE) -> 123.01499 | K86: =VLOOKUP($E86,Hybrid!$1:$1048576,MATCH(DATE(K$2,1,1),Hybrid!$A$1:$LI$1),FALSE) -> 119.91607 | L86: =VLOOKUP($E86,Hybrid!$1:$1048576,MATCH(DATE(L$2,1,1),Hybrid!$A$1:$LI$1),FALSE) -> 114.75483 | M86: =VLOOKUP($E86,Hybrid!$1:$1048576,MATCH(DATE(M$2,1,1),Hybrid!$A$1:$LI$1),FALSE) -> 108.53193 | ... AO86: =VLOOKUP($E86,Hybrid!$1:$1048576,MATCH(DATE(AO$2,1,1),Hybrid!$A$1:$LI$1),FALSE) -> 18.224564
C87: ELEC | E87: NEWAUTO_cele_0 | F87: =VLOOKUP($E87,Hybrid!$1:$1048576,MATCH(DATE(F$2,1,1),Hybrid!$A$1:$LI$1),FALSE) -> 17.397214 | G87: =VLOOKUP($E87,Hybrid!$1:$1048576,MATCH(DATE(G$2,1,1),Hybrid!$A$1:$LI$1),FALSE) -> 19.914952 | H87: =VLOOKUP($E87,Hybrid!$1:$1048576,MATCH(DATE(H$2,1,1),Hybrid!$A$1:$LI$1),FALSE) -> 22.515516 | I87: =VLOOKUP($E87,Hybrid!$1:$1048576,MATCH(DATE(I$2,1,1),Hybrid!$A$1:$LI$1),FALSE) -> 24.933506 | J87: =VLOOKUP($E87,Hybrid!$1:$1048576,MATCH(DATE(J$2,1,1),Hybrid!$A$1:$LI$1),FALSE) -> 27.54099 | K87: =VLOOKUP($E87,Hybrid!$1:$1048576,MATCH(DATE(K$2,1,1),Hybrid!$A$1:$LI$1),FALSE) -> 29.860195 | L87: =VLOOKUP($E87,Hybrid!$1:$1048576,MATCH(DATE(L$2,1,1),Hybrid!$A$1:$LI$1),FALSE) -> 31.857481 | M87: =VLOOKUP($E87,Hybrid!$1:$1048576,MATCH(DATE(M$2,1,1),Hybrid!$A$1:$LI$1),FALSE) -> 33.93337 | ... AO87: =VLOOKUP($E87,Hybrid!$1:$1048576,MATCH(DATE(AO$2,1,1),Hybrid!$A$1:$LI$1),FALSE) -> 297.98318
D88: class A | E88: NEWAUTO_ca_cele_0 | F88: =VLOOKUP($E88,Hybrid!$1:$1048576,MATCH(DATE(F$2,1,1),Hybrid!$A$1:$LI$1),FALSE) -> 4.924099 | G88: =VLOOKUP($E88,Hybrid!$1:$1048576,MATCH(DATE(G$2,1,1),Hybrid!$A$1:$LI$1),FALSE) -> 5.674154 | H88: =VLOOKUP($E88,Hybrid!$1:$1048576,MATCH(DATE(H$2,1,1),Hybrid!$A$1:$LI$1),FALSE) -> 6.4732876 | I88: =VLOOKUP($E88,Hybrid!$1:$1048576,MATCH(DATE(I$2,1,1),Hybrid!$A$1:$LI$1),FALSE) -> 7.2466191 | J88: =VLOOKUP($E88,Hybrid!$1:$1048576,MATCH(DATE(J$2,1,1),Hybrid!$A$1:$LI$1),FALSE) -> 8.0967317 | K88: =VLOOKUP($E88,Hybrid!$1:$1048576,MATCH(DATE(K$2,1,1),Hybrid!$A$1:$LI$1),FALSE) -> 8.8707049 | L88: =VLOOKUP($E88,Hybrid!$1:$1048576,MATCH(DATE(L$2,1,1),Hybrid!$A$1:$LI$1),FALSE) -> 9.5604693 | M88: =VLOOKUP($E88,Hybrid!$1:$1048576,MATCH(DATE(M$2,1,1),Hybrid!$A$1:$LI$1),FALSE) -> 10.290536 | ... AO88: =VLOOKUP($E88,Hybrid!$1:$1048576,MATCH(DATE(AO$2,1,1),Hybrid!$A$1:$LI$1),FALSE) -> 106.07567
D89: class B | E89: NEWAUTO_cb_cele_0 | F89: =VLOOKUP($E89,Hybrid!$1:$1048576,MATCH(DATE(F$2,1,1),Hybrid!$A$1:$LI$1),FALSE) -> 4.7303839 | G89: =VLOOKUP($E89,Hybrid!$1:$1048576,MATCH(DATE(G$2,1,1),Hybrid!$A$1:$LI$1),FALSE) -> 5.454057 | H89: =VLOOKUP($E89,Hybrid!$1:$1048576,MATCH(DATE(H$2,1,1),Hybrid!$A$1:$LI$1),FALSE) -> 6.2264358 | I89: =VLOOKUP($E89,Hybrid!$1:$1048576,MATCH(DATE(I$2,1,1),Hybrid!$A$1:$LI$1),FALSE) -> 6.9776756 | J89: =VLOOKUP($E89,Hybrid!$1:$1048576,MATCH(DATE(J$2,1,1),Hybrid!$A$1:$LI$1),FALSE) -> 7.8054462 | K89: =VLOOKUP($E89,Hybrid!$1:$1048576,MATCH(DATE(K$2,1,1),Hybrid!$A$1:$LI$1),FALSE) -> 8.5583403 | L89: =VLOOKUP($E89,Hybrid!$1:$1048576,MATCH(DATE(L$2,1,1),Hybrid!$A$1:$LI$1),FALSE) -> 9.2287484 | M89: =VLOOKUP($E89,Hybrid!$1:$1048576,MATCH(DATE(M$2,1,1),Hybrid!$A$1:$LI$1),FALSE) -> 9.9380733 | ... AO89: =VLOOKUP($E89,Hybrid!$1:$1048576,MATCH(DATE(AO$2,1,1),Hybrid!$A$1:$LI$1),FALSE) -> 100.64269
D90: class C | E90: NEWAUTO_cc_cele_0 | F90: =VLOOKUP($E90,Hybrid!$1:$1048576,MATCH(DATE(F$2,1,1),Hybrid!$A$1:$LI$1),FALSE) -> 3.2762707 | G90: =VLOOKUP($E90,Hybrid!$1:$1048576,MATCH(DATE(G$2,1,1),Hybrid!$A$1:$LI$1),FALSE) -> 3.7792389 | H90: =VLOOKUP($E90,Hybrid!$1:$1048576,MATCH(DATE(H$2,1,1),Hybrid!$A$1:$LI$1),FALSE) -> 4.3167347 | I90: =VLOOKUP($E90,Hybrid!$1:$1048576,MATCH(DATE(I$2,1,1),Hybrid!$A$1:$LI$1),FALSE) -> 4.8416799 | J90: =VLOOKUP($E90,Hybrid!$1:$1048576,MATCH(DATE(J$2,1,1),Hybrid!$A$1:$LI$1),FALSE) -> 5.4211249 | K90: =VLOOKUP($E90,Hybrid!$1:$1048576,MATCH(DATE(K$2,1,1),Hybrid!$A$1:$LI$1),FALSE) -> 5.9474742 | L90: =VLOOKUP($E90,Hybrid!$1:$1048576,MATCH(DATE(L$2,1,1),Hybrid!$A$1:$LI$1),FALSE) -> 6.4154938 | M90: =VLOOKUP($E90,Hybrid!$1:$1048576,MATCH(DATE(M$2,1,1),Hybrid!$A$1:$LI$1),FALSE) -> 6.9102156 | ... AO90: =VLOOKUP($E90,Hybrid!$1:$1048576,MATCH(DATE(AO$2,1,1),Hybrid!$A$1:$LI$1),FALSE) -> 68.400381
D91: class D | E91: NEWAUTO_cd_cele_0 | F91: =VLOOKUP($E91,Hybrid!$1:$1048576,MATCH(DATE(F$2,1,1),Hybrid!$A$1:$LI$1),FALSE) -> 1.8075193 | G91: =VLOOKUP($E91,Hybrid!$1:$1048576,MATCH(DATE(G$2,1,1),Hybrid!$A$1:$LI$1),FALSE) -> 2.0477922 | H91: =VLOOKUP($E91,Hybrid!$1:$1048576,MATCH(DATE(H$2,1,1),Hybrid!$A$1:$LI$1),FALSE) -> 2.282296 | I91: =VLOOKUP($E91,Hybrid!$1:$1048576,MATCH(DATE(I$2,1,1),Hybrid!$A$1:$LI$1),FALSE) -> 2.4783865 | J91: =VLOOKUP($E91,Hybrid!$1:$1048576,MATCH(DATE(J$2,1,1),Hybrid!$A$1:$LI$1),FALSE) -> 2.6767285 | K91: =VLOOKUP($E91,Hybrid!$1:$1048576,MATCH(DATE(K$2,1,1),Hybrid!$A$1:$LI$1),FALSE) -> 2.8442572 | L91: =VLOOKUP($E91,Hybrid!$1:$1048576,MATCH(DATE(L$2,1,1),Hybrid!$A$1:$LI$1),FALSE) -> 2.974342 | M91: =VLOOKUP($E91,Hybrid!$1:$1048576,MATCH(DATE(M$2,1,1),Hybrid!$A$1:$LI$1),FALSE) -> 3.0975815 | ... AO91: =VLOOKUP($E91,Hybrid!$1:$1048576,MATCH(DATE(AO$2,1,1),Hybrid!$A$1:$LI$1),FALSE) -> 14.232877
D92: class E | E92: NEWAUTO_ce_cele_0 | F92: =VLOOKUP($E92,Hybrid!$1:$1048576,MATCH(DATE(F$2,1,1),Hybrid!$A$1:$LI$1),FALSE) -> 1.1126687 | G92: =VLOOKUP($E92,Hybrid!$1:$1048576,MATCH(DATE(G$2,1,1),Hybrid!$A$1:$LI$1),FALSE) -> 1.2575884 | H92: =VLOOKUP($E92,Hybrid!$1:$1048576,MATCH(DATE(H$2,1,1),Hybrid!$A$1:$LI$1),FALSE) -> 1.3965578 | I92: =VLOOKUP($E92,Hybrid!$1:$1048576,MATCH(DATE(I$2,1,1),Hybrid!$A$1:$LI$1),FALSE) -> 1.5103535 | J92: =VLOOKUP($E92,Hybrid!$1:$1048576,MATCH(DATE(J$2,1,1),Hybrid!$A$1:$LI$1),FALSE) -> 1.6238947 | K92: =VLOOKUP($E92,Hybrid!$1:$1048576,MATCH(DATE(K$2,1,1),Hybrid!$A$1:$LI$1),FALSE) -> 1.7168004 | L92: =VLOOKUP($E92,Hybrid!$1:$1048576,MATCH(DATE(L$2,1,1),Hybrid!$A$1:$LI$1),FALSE) -> 1.7853454 | M92: =VLOOKUP($E92,Hybrid!$1:$1048576,MATCH(DATE(M$2,1,1),Hybrid!$A$1:$LI$1),FALSE) -> 1.8483485 | ... AO92: =VLOOKUP($E92,Hybrid!$1:$1048576,MATCH(DATE(AO$2,1,1),Hybrid!$A$1:$LI$1),FALSE) -> 7.1589953
D93: class F | E93: NEWAUTO_cf_cele_0 | F93: =VLOOKUP($E93,Hybrid!$1:$1048576,MATCH(DATE(F$2,1,1),Hybrid!$A$1:$LI$1),FALSE) -> 0.53722532 | G93: =VLOOKUP($E93,Hybrid!$1:$1048576,MATCH(DATE(G$2,1,1),Hybrid!$A$1:$LI$1),FALSE) -> 0.59574104 | H93: =VLOOKUP($E93,Hybrid!$1:$1048576,MATCH(DATE(H$2,1,1),Hybrid!$A$1:$LI$1),FALSE) -> 0.64387985 | I93: =VLOOKUP($E93,Hybrid!$1:$1048576,MATCH(DATE(I$2,1,1),Hybrid!$A$1:$LI$1),FALSE) -> 0.67307876 | J93: =VLOOKUP($E93,Hybrid!$1:$1048576,MATCH(DATE(J$2,1,1),Hybrid!$A$1:$LI$1),FALSE) -> 0.69650479 | K93: =VLOOKUP($E93,Hybrid!$1:$1048576,MATCH(DATE(K$2,1,1),Hybrid!$A$1:$LI$1),FALSE) -> 0.70889167 | L93: =VLOOKUP($E93,Hybrid!$1:$1048576,MATCH(DATE(L$2,1,1),Hybrid!$A$1:$LI$1),FALSE) -> 0.70887295 | M93: =VLOOKUP($E93,Hybrid!$1:$1048576,MATCH(DATE(M$2,1,1),Hybrid!$A$1:$LI$1),FALSE) -> 0.70355136 | ... AO93: =VLOOKUP($E93,Hybrid!$1:$1048576,MATCH(DATE(AO$2,1,1),Hybrid!$A$1:$LI$1),FALSE) -> 0.81221466
D94: class G | E94: NEWAUTO_cg_cele_0 | F94: =VLOOKUP($E94,Hybrid!$1:$1048576,MATCH(DATE(F$2,1,1),Hybrid!$A$1:$LI$1),FALSE) -> 1.0090476 | G94: =VLOOKUP($E94,Hybrid!$1:$1048576,MATCH(DATE(G$2,1,1),Hybrid!$A$1:$LI$1),FALSE) -> 1.1063806 | H94: =VLOOKUP($E94,Hybrid!$1:$1048576,MATCH(DATE(H$2,1,1),Hybrid!$A$1:$LI$1),FALSE) -> 1.1763242 | I94: =VLOOKUP($E94,Hybrid!$1:$1048576,MATCH(DATE(I$2,1,1),Hybrid!$A$1:$LI$1),FALSE) -> 1.2057126 | J94: =VLOOKUP($E94,Hybrid!$1:$1048576,MATCH(DATE(J$2,1,1),Hybrid!$A$1:$LI$1),FALSE) -> 1.2205591 | K94: =VLOOKUP($E94,Hybrid!$1:$1048576,MATCH(DATE(K$2,1,1),Hybrid!$A$1:$LI$1),FALSE) -> 1.2137267 | L94: =VLOOKUP($E94,Hybrid!$1:$1048576,MATCH(DATE(L$2,1,1),Hybrid!$A$1:$LI$1),FALSE) -> 1.1842091 | M94: =VLOOKUP($E94,Hybrid!$1:$1048576,MATCH(DATE(M$2,1,1),Hybrid!$A$1:$LI$1),FALSE) -> 1.1450636 | ... AO94: =VLOOKUP($E94,Hybrid!$1:$1048576,MATCH(DATE(AO$2,1,1),Hybrid!$A$1:$LI$1),FALSE) -> 0.66034456
C95: GAS | E95: NEWAUTO_cgas_0 | F95: =VLOOKUP($E95,Hybrid!$1:$1048576,MATCH(DATE(F$2,1,1),Hybrid!$A$1:$LI$1),FALSE) -> 0.15698923 | G95: =VLOOKUP($E95,Hybrid!$1:$1048576,MATCH(DATE(G$2,1,1),Hybrid!$A$1:$LI$1),FALSE) -> 0.17590986 | H95: =VLOOKUP($E95,Hybrid!$1:$1048576,MATCH(DATE(H$2,1,1),Hybrid!$A$1:$LI$1),FALSE) -> 0.19318352 | I95: =VLOOKUP($E95,Hybrid!$1:$1048576,MATCH(DATE(I$2,1,1),Hybrid!$A$1:$LI$1),FALSE) -> 0.20544703 | J95: =VLOOKUP($E95,Hybrid!$1:$1048576,MATCH(DATE(J$2,1,1),Hybrid!$A$1:$LI$1),FALSE) -> 0.21654211 | K95: =VLOOKUP($E95,Hybrid!$1:$1048576,MATCH(DATE(K$2,1,1),Hybrid!$A$1:$LI$1),FALSE) -> 0.22531198 | L95: =VLOOKUP($E95,Hybrid!$1:$1048576,MATCH(DATE(L$2,1,1),Hybrid!$A$1:$LI$1),FALSE) -> 0.23092978 | M95: =VLOOKUP($E95,Hybrid!$1:$1048576,MATCH(DATE(M$2,1,1),Hybrid!$A$1:$LI$1),FALSE) -> 0.23505144 | ... AO95: =VLOOKUP($E95,Hybrid!$1:$1048576,MATCH(DATE(AO$2,1,1),Hybrid!$A$1:$LI$1),FALSE) -> 0.26706907
D96: class A | E96: NEWAUTO_ca_cgas_0 | F96: =VLOOKUP($E96,Hybrid!$1:$1048576,MATCH(DATE(F$2,1,1),Hybrid!$A$1:$LI$1),FALSE) -> 0.044412049 | G96: =VLOOKUP($E96,Hybrid!$1:$1048576,MATCH(DATE(G$2,1,1),Hybrid!$A$1:$LI$1),FALSE) -> 0.050020772 | H96: =VLOOKUP($E96,Hybrid!$1:$1048576,MATCH(DATE(H$2,1,1),Hybrid!$A$1:$LI$1),FALSE) -> 0.055324412 | I96: =VLOOKUP($E96,Hybrid!$1:$1048576,MATCH(DATE(I$2,1,1),Hybrid!$A$1:$LI$1),FALSE) -> 0.059330123 | J96: =VLOOKUP($E96,Hybrid!$1:$1048576,MATCH(DATE(J$2,1,1),Hybrid!$A$1:$LI$1),FALSE) -> 0.063094094 | K96: =VLOOKUP($E96,Hybrid!$1:$1048576,MATCH(DATE(K$2,1,1),Hybrid!$A$1:$LI$1),FALSE) -> 0.066218273 | L96: =VLOOKUP($E96,Hybrid!$1:$1048576,MATCH(DATE(L$2,1,1),Hybrid!$A$1:$LI$1),FALSE) -> 0.068461863 | M96: =VLOOKUP($E96,Hybrid!$1:$1048576,MATCH(DATE(M$2,1,1),Hybrid!$A$1:$LI$1),FALSE) -> 0.07031886 | ... AO96: =VLOOKUP($E96,Hybrid!$1:$1048576,MATCH(DATE(AO$2,1,1),Hybrid!$A$1:$LI$1),FALSE) -> 0.085552288
D97: class B | E97: NEWAUTO_cb_cgas_0 | F97: =VLOOKUP($E97,Hybrid!$1:$1048576,MATCH(DATE(F$2,1,1),Hybrid!$A$1:$LI$1),FALSE) -> 0.04263783 | G97: =VLOOKUP($E97,Hybrid!$1:$1048576,MATCH(DATE(G$2,1,1),Hybrid!$A$1:$LI$1),FALSE) -> 0.047964279 | H97: =VLOOKUP($E97,Hybrid!$1:$1048576,MATCH(DATE(H$2,1,1),Hybrid!$A$1:$LI$1),FALSE) -> 0.052962015 | I97: =VLOOKUP($E97,Hybrid!$1:$1048576,MATCH(DATE(I$2,1,1),Hybrid!$A$1:$LI$1),FALSE) -> 0.056682207 | J97: =VLOOKUP($E97,Hybrid!$1:$1048576,MATCH(DATE(J$2,1,1),Hybrid!$A$1:$LI$1),FALSE) -> 0.060147054 | K97: =VLOOKUP($E97,Hybrid!$1:$1048576,MATCH(DATE(K$2,1,1),Hybrid!$A$1:$LI$1),FALSE) -> 0.062997406 | L97: =VLOOKUP($E97,Hybrid!$1:$1048576,MATCH(DATE(L$2,1,1),Hybrid!$A$1:$LI$1),FALSE) -> 0.064995818 | M97: =VLOOKUP($E97,Hybrid!$1:$1048576,MATCH(DATE(M$2,1,1),Hybrid!$A$1:$LI$1),FALSE) -> 0.066602438 | ... AO97: =VLOOKUP($E97,Hybrid!$1:$1048576,MATCH(DATE(AO$2,1,1),Hybrid!$A$1:$LI$1),FALSE) -> 0.088252925
D98: class C | E98: NEWAUTO_cc_cgas_0 | F98: =VLOOKUP($E98,Hybrid!$1:$1048576,MATCH(DATE(F$2,1,1),Hybrid!$A$1:$LI$1),FALSE) -> 0.029513505 | G98: =VLOOKUP($E98,Hybrid!$1:$1048576,MATCH(DATE(G$2,1,1),Hybrid!$A$1:$LI$1),FALSE) -> 0.033160368 | H98: =VLOOKUP($E98,Hybrid!$1:$1048576,MATCH(DATE(H$2,1,1),Hybrid!$A$1:$LI$1),FALSE) -> 0.036555291 | I98: =VLOOKUP($E98,Hybrid!$1:$1048576,MATCH(DATE(I$2,1,1),Hybrid!$A$1:$LI$1),FALSE) -> 0.039044753 | J98: =VLOOKUP($E98,Hybrid!$1:$1048576,MATCH(DATE(J$2,1,1),Hybrid!$A$1:$LI$1),FALSE) -> 0.041342115 | K98: =VLOOKUP($E98,Hybrid!$1:$1048576,MATCH(DATE(K$2,1,1),Hybrid!$A$1:$LI$1),FALSE) -> 0.043214472 | L98: =VLOOKUP($E98,Hybrid!$1:$1048576,MATCH(DATE(L$2,1,1),Hybrid!$A$1:$LI$1),FALSE) -> 0.044493292 | M98: =VLOOKUP($E98,Hybrid!$1:$1048576,MATCH(DATE(M$2,1,1),Hybrid!$A$1:$LI$1),FALSE) -> 0.045487664 | ... AO98: =VLOOKUP($E98,Hybrid!$1:$1048576,MATCH(DATE(AO$2,1,1),Hybrid!$A$1:$LI$1),FALSE) -> 0.056294835
D99: class D | E99: NEWAUTO_cd_cgas_0 | F99: =VLOOKUP($E99,Hybrid!$1:$1048576,MATCH(DATE(F$2,1,1),Hybrid!$A$1:$LI$1),FALSE) -> 0.01635872 | G99: =VLOOKUP($E99,Hybrid!$1:$1048576,MATCH(DATE(G$2,1,1),Hybrid!$A$1:$LI$1),FALSE) -> 0.018298177 | H99: =VLOOKUP($E99,Hybrid!$1:$1048576,MATCH(DATE(H$2,1,1),Hybrid!$A$1:$LI$1),FALSE) -> 0.020043211 | I99: =VLOOKUP($E99,Hybrid!$1:$1048576,MATCH(DATE(I$2,1,1),Hybrid!$A$1:$LI$1),FALSE) -> 0.021244887 | J99: =VLOOKUP($E99,Hybrid!$1:$1048576,MATCH(DATE(J$2,1,1),Hybrid!$A$1:$LI$1),FALSE) -> 0.022306103 | K99: =VLOOKUP($E99,Hybrid!$1:$1048576,MATCH(DATE(K$2,1,1),Hybrid!$A$1:$LI$1),FALSE) -> 0.023117045 | L99: =VLOOKUP($E99,Hybrid!$1:$1048576,MATCH(DATE(L$2,1,1),Hybrid!$A$1:$LI$1),FALSE) -> 0.023588661 | M99: =VLOOKUP($E99,Hybrid!$1:$1048576,MATCH(DATE(M$2,1,1),Hybrid!$A$1:$LI$1),FALSE) -> 0.023886104 | ... AO99: =VLOOKUP($E99,Hybrid!$1:$1048576,MATCH(DATE(AO$2,1,1),Hybrid!$A$1:$LI$1),FALSE) -> 0.024138208
D100: class E | E100: NEWAUTO_ce_cgas_0 | F100: =VLOOKUP($E100,Hybrid!$1:$1048576,MATCH(DATE(F$2,1,1),Hybrid!$A$1:$LI$1),FALSE) -> 0.010063219 | G100: =VLOOKUP($E100,Hybrid!$1:$1048576,MATCH(DATE(G$2,1,1),Hybrid!$A$1:$LI$1),FALSE) -> 0.011209382 | H100: =VLOOKUP($E100,Hybrid!$1:$1048576,MATCH(DATE(H$2,1,1),Hybrid!$A$1:$LI$1),FALSE) -> 0.012205652 | I100: =VLOOKUP($E100,Hybrid!$1:$1048576,MATCH(DATE(I$2,1,1),Hybrid!$A$1:$LI$1),FALSE) -> 0.012844967 | J100: =VLOOKUP($E100,Hybrid!$1:$1048576,MATCH(DATE(J$2,1,1),Hybrid!$A$1:$LI$1),FALSE) -> 0.013380154 | K100: =VLOOKUP($E100,Hybrid!$1:$1048576,MATCH(DATE(K$2,1,1),Hybrid!$A$1:$LI$1),FALSE) -> 0.013755758 | L100: =VLOOKUP($E100,Hybrid!$1:$1048576,MATCH(DATE(L$2,1,1),Hybrid!$A$1:$LI$1),FALSE) -> 0.013919318 | M100: =VLOOKUP($E100,Hybrid!$1:$1048576,MATCH(DATE(M$2,1,1),Hybrid!$A$1:$LI$1),FALSE) -> 0.013968723 | ... AO100: =VLOOKUP($E100,Hybrid!$1:$1048576,MATCH(DATE(AO$2,1,1),Hybrid!$A$1:$LI$1),FALSE) -> 0.0093058502
...

Sheet date
A1: =Hybrid!A1 -> _date_ | B1: =Hybrid!B1 -> 42005 | C1: =Hybrid!C1 -> 42370 | D1: =Hybrid!D1 -> 42736 | E1: =Hybrid!E1 -> 43101 | F1: =Hybrid!F1 -> 43466 | G1: =Hybrid!G1 -> 43831 | H1: =Hybrid!H1 -> 44197 | ... AK1: =Hybrid!AK1 -> 54789
B2: =TEXT(B1,"jj mm aaaa") -> 01 01 2015 | C2: =TEXT(C1,"jj mm aaaa") -> 01 01 2016 | D2: =TEXT(D1,"jj mm aaaa") -> 01 01 2017 | E2: =TEXT(E1,"jj mm aaaa") -> 01 01 2018 | F2: =TEXT(F1,"jj mm aaaa") -> 01 01 2019 | G2: =TEXT(G1,"jj mm aaaa") -> 01 01 2020 | H2: =TEXT(H1,"jj mm aaaa") -> 01 01 2021 | I2: =TEXT(I1,"jj mm aaaa") -> 01 01 2022 | ... AK2: =TEXT(AK1,"jj mm aaaa") -> 01 01 2050
B3: =RIGHT(B2,4) -> 2015 | C3: =RIGHT(C2,4) -> 2016 | D3: =RIGHT(D2,4) -> 2017 | E3: =RIGHT(E2,4) -> 2018 | F3: =RIGHT(F2,4) -> 2019 | G3: =RIGHT(G2,4) -> 2020 | H3: =RIGHT(H2,4) -> 2021 | I3: =RIGHT(I2,4) -> 2022 | ... AK3: =RIGHT(AK2,4) -> 2050

Sheet Emissions
A1: _date_ | B1: 42005 | C1: 42370 | D1: 42736 | E1: 43101 | F1: 43466 | G1: 43831 | H1: 44197 | I1: 44562 | J1: 44927 | K1: 45292 | L1: 45658 | M1: 46023 | N1: 46388 | O1: 46753 | P1: 47119 | Q1: 47484 | R1: 47849 | S1: 48214 | T1: 48580 | U1: 48945 | V1: 49310 | W1: 49675 | X1: 50041 | Y1: 50406 | Z1: 50771 | AA1: 51136 | AB1: 51502 | AC1: 51867 | AD1: 52232 | AE1: 52597 | AF1: 52963 | AG1: 53328 | AH1: 53693 | AI1: 54058 | AJ1: 54424 | AK1: 54789
A2: ems_2 | B2: 467.59248 | C2: 469.44342 | D2: 471.57749 | E2: 473.70422 | F2: 478.07334 | G2: 484.19172 | H2: 491.58896 | I2: 484.22877 | J2: 476.62255 | K2: 471.06805 | L2: 466.23038 | M2: 461.78142 | N2: 457.26125 | O2: 452.57082 | P2: 447.81904 | Q2: 443.07633 | R2: 437.9768 | S2: 432.81822 | T2: 427.83308 | U2: 423.16544 | V2: 418.86226 | W2: 415.06938 | X2: 411.832 | Y2: 409.15427 | Z2: 406.99713 | AA2: 405.17858 | AB2: 403.79279 | AC2: 402.87546 | AD2: 402.37532 | AE2: 402.15072 | AF2: 402.01821 | AG2: 401.81044 | AH2: 401.37762 | AI2: 400.55727 | AJ2: 399.16656 | AK2: 386.65438
A3: ems_ch_2 | B3: 129.15358 | C3: 128.0181 | D3: 126.72404 | E3: 125.46213 | F3: 124.86435 | G3: 124.67948 | H3: 124.72737 | I3: 120.27372 | J3: 116.09145 | K3: 112.21389 | L3: 108.63896 | M3: 105.56055 | N3: 102.71272 | O3: 99.94825 | P3: 97.188898 | Q3: 94.396552 | R3: 91.433762 | S3: 88.388092 | T3: 85.305253 | U3: 82.208879 | V3: 79.092914 | W3: 75.99463 | X3: 72.906563 | Y3: 69.826702 | Z3: 66.754529 | AA3: 63.647055 | AB3: 60.554632 | AC3: 57.474906 | AD3: 54.406398 | AE3: 51.347448 | AF3: 48.295217 | AG3: 45.245271 | AH3: 42.191909 | AI3: 39.128584 | AJ3: 36.047632 | AK3: 32.950877
A4: ems_ch_2+ems_ci_2 | B4: 347.45082 | C4: 347.30993 | D4: 347.15079 | E4: 346.71147 | F4: 348.28926 | G4: 351.40647 | H4: 355.63974 | I4: 345.4594 | J4: 335.06282 | K4: 326.13817 | L4: 317.90804 | M4: 310.51143 | N4: 303.4163 | O4: 296.4256 | P4: 289.52463 | Q4: 282.70257 | R4: 275.52474 | S4: 268.24509 | T4: 261.03011 | U4: 253.97095 | V4: 247.08677 | W4: 240.45476 | X4: 234.07624 | Y4: 227.92515 | Z4: 221.95174 | AA4: 216.02635 | AB4: 210.20432 | AC4: 204.46275 | AD4: 198.73271 | AE4: 192.89685 | AF4: 186.81922 | AG4: 180.37606 | AH4: 173.45172 | AI4: 165.91527 | AJ4: 157.61291 | AK4: 144.97245
A5: ems_ci_2 | B5: 218.29724 | C5: 219.29183 | D5: 220.42676 | E5: 221.24934 | F5: 223.42491 | G5: 226.72699 | H5: 230.91237 | I5: 225.18568 | J5: 218.97137 | K5: 213.92428 | L5: 209.26908 | M5: 204.95088 | N5: 200.70358 | O5: 196.47735 | P5: 192.33573 | Q5: 188.30602 | R5: 184.09098 | S5: 179.857 | T5: 175.72486 | U5: 171.76207 | V5: 167.99386 | W5: 164.46013 | X5: 161.16968 | Y5: 158.09845 | Z5: 155.19721 | AA5: 152.3793 | AB5: 149.64968 | AC5: 146.98785 | AD5: 144.32631 | AE5: 141.5494 | AF5: 138.52401 | AG5: 135.13079 | AH5: 131.25981 | AI5: 126.78669 | AJ5: 121.56528 | AK5: 112.02157
A6: ems_mat_2 | B6: 27.944917 | C6: 28.350366 | D6: 28.798369 | E6: 29.275814 | F6: 29.782485 | G6: 30.318556 | H6: 30.880195 | I6: 31.382988 | J6: 31.866622 | K6: 32.403874 | L6: 32.951405 | M6: 33.466282 | N6: 33.949965 | O6: 34.41252 | P6: 34.867931 | Q6: 35.326305 | R6: 35.792454 | S6: 36.268887 | T6: 36.763423 | U6: 37.283318 | V6: 37.833299 | W6: 38.421117 | X6: 39.052893 | Y6: 39.732771 | Z6: 40.462604 | AA6: 41.237964 | AB6: 42.061026 | AC6: 42.939634 | AD6: 43.876768 | AE6: 44.871119 | AF6: 45.919125 | AG6: 47.018207 | AH6: 48.167646 | AI6: 49.367694 | AJ6: 50.620062 | AK6: 50.72402
A7: ems_y_2 | B7: 92.196745 | C7: 93.783117 | D7: 95.628331 | E7: 97.716929 | F7: 100.0016 | G7: 102.4667 | H7: 105.06903 | I7: 107.38639 | J7: 109.69311 | K7: 112.52601 | L7: 115.37094 | M7: 117.8037 | N7: 119.89498 | O7: 121.7327 | P7: 123.42648 | Q7: 125.04746 | R7: 126.65961 | S7: 128.30425 | T7: 130.03955 | U7: 131.91117 | V7: 133.94219 | W7: 136.19349 | X7: 138.70287 | Y7: 141.49634 | Z7: 144.58279 | AA7: 147.91426 | AB7: 151.52745 | AC7: 155.47307 | AD7: 159.76585 | AE7: 164.38275 | AF7: 169.27987 | AG7: 174.41617 | AH7: 179.75826 | AI7: 185.2743 | AJ7: 190.93359 | AK7: 190.95791
A8: ems_sec_2 | B8: 338.4389 | C8: 341.42532 | D8: 344.85346 | E8: 348.24209 | F8: 353.20899 | G8: 359.51225 | H8: 366.86159 | I8: 363.95506 | J8: 360.53111 | K8: 358.85416 | L8: 357.59142 | M8: 356.22087 | N8: 354.54853 | O8: 352.62257 | P8: 350.63014 | Q8: 348.67978 | R8: 346.54304 | S8: 344.43013 | T8: 342.52783 | U8: 340.95656 | V8: 339.76935 | W8: 339.07475 | X8: 338.92543 | Y8: 339.32756 | Z8: 340.2426 | AA8: 341.53152 | AB8: 343.23816 | AC8: 345.40056 | AD8: 347.96893 | AE8: 350.80327 | AF8: 353.723 | AG8: 356.56517 | AH8: 359.18571 | AI8: 361.42868 | AJ8: 363.11893 | AK8: 353.70351
A9: ems_ets_2 | B9: 126.43137 | C9: 128.22158 | D9: 130.14417 | E9: 132.03236 | F9: 134.27274 | G9: 136.8698 | H9: 139.76466 | I9: 139.5975 | J9: 139.17644 | K9: 139.34732 | L9: 139.47496 | M9: 139.26073 | N9: 138.72803 | O9: 137.98073 | P9: 137.14836 | Q9: 136.29836 | R9: 135.3323 | S9: 134.33474 | T9: 133.37454 | U9: 132.4943 | V9: 131.71321 | W9: 131.06825 | X9: 130.57843 | Y9: 130.23932 | Z9: 130.02674 | AA9: 129.8853 | AB9: 129.83327 | AC9: 129.87799 | AD9: 129.9897 | AE9: 130.0989 | AF9: 130.1219 | AG9: 129.98945 | AH9: 129.64597 | AI9: 129.03199 | AJ9: 128.08263 | AK9: 123.34338
A10: ems_nets_2 | B10: 212.00753 | C10: 213.20374 | D10: 214.70928 | E10: 216.20972 | F10: 218.93625 | G10: 222.64244 | H10: 227.09692 | I10: 224.35756 | J10: 221.35467 | K10: 219.50684 | L10: 218.11646 | M10: 216.96014 | N10: 215.82049 | O10: 214.64184 | P10: 213.48178 | Q10: 212.38143 | R10: 211.21074 | S10: 210.09539 | T10: 209.15329 | U10: 208.46226 | V10: 208.05614 | W10: 208.0065 | X10: 208.347 | Y10: 209.08825 | Z10: 210.21586 | AA10: 211.64622 | AB10: 213.40489 | AC10: 215.52256 | AD10: 217.97922 | AE10: 220.70437 | AF10: 223.6011 | AG10: 226.57572 | AH10: 229.53974 | AI10: 232.39669 | AJ10: 235.0363 | AK10: 230.36013
A11: ems_netsi_2 | B11: 25.113302 | C11: 24.871433 | D11: 24.621897 | E11: 24.2982 | F11: 24.268305 | G11: 24.484248 | H11: 24.894776 | I11: 23.702579 | J11: 22.391543 | K11: 21.256801 | L11: 20.262475 | M11: 19.475286 | N11: 18.814935 | O11: 18.234427 | P11: 17.714724 | Q11: 17.244721 | R11: 16.768053 | S11: 16.306765 | T11: 15.877949 | U11: 15.491983 | V11: 15.153804 | W11: 14.868497 | X11: 14.636992 | Y11: 14.457349 | Z11: 14.325566 | AA11: 14.233881 | AB11: 14.182117 | AC11: 14.168663 | AD11: 14.186972 | AE11: 14.225807 | AF11: 14.271644 | AG11: 14.310944 | AH11: 14.329332 | AI11: 14.309029 | AJ11: 14.22709 | AK11: 13.466085
A12: ems_trsp_2-ems_sair_2 | B12: 24.968508 | C12: 25.428685 | D12: 25.93215 | E12: 26.454338 | F12: 27.016286 | G12: 27.616466 | H12: 28.24381 | I12: 27.880554 | J12: 27.481673 | K12: 27.206883 | L12: 26.909036 | M12: 26.493269 | N12: 25.96273 | O12: 25.346297 | P12: 24.680159 | Q12: 23.986563 | R12: 23.276421 | S12: 22.565989 | T12: 21.86586 | U12: 21.179408 | V12: 20.506273 | W12: 19.847998 | X12: 19.204304 | Y12: 18.570475 | Z12: 17.938668 | AA12: 17.298476 | AB12: 16.649415 | AC12: 15.990804 | AD12: 15.314456 | AE12: 14.606629 | AF12: 13.853044 | AG12: 13.04355 | AH12: 12.170976 | AI12: 11.227657 | AJ12: 10.206111 | AK12: 8.7969718
... A829: ems_ch_co2_2 | B829: 119.49049 | C829: 118.38463 | D829: 117.15607 | E829: 115.97111 | F829: 115.44038 | G829: 115.31259 | H829: 115.41194 | I829: 111.07794 | J829: 107.01336 | K829: 103.24759 | L829: 99.772583 | M829: 96.782401 | N829: 94.011791 | O829: 91.31547 | P829: 88.617352 | Q829: 85.881072 | R829: 82.97162 | S829: 79.976862 | T829: 76.942135 | U829: 73.890523 | V829: 70.817912 | W829: 67.757349 | X829: 64.701937 | Y829: 61.649861 | Z829: 58.600622 | AA829: 55.517761 | AB829: 52.444224 | AC829: 49.377906 | AD829: 46.317411 | AE829: 43.261045 | AF829: 40.205793 | AG829: 37.147012 | AH829: 34.078805 | AI829: 30.994437 | AJ829: 27.886089 | AK829: 24.803038

Sheet Consumption
A1: _date_ | B1: 42005 | C1: 42370 | D1: 42736 | E1: 43101 | F1: 43466 | G1: 43831 | H1: 44197 | I1: 44562 | J1: 44927 | K1: 45292 | L1: 45658 | M1: 46023 | N1: 46388 | O1: 46753 | P1: 47119 | Q1: 47484 | R1: 47849 | S1: 48214 | T1: 48580 | U1: 48945 | V1: 49310 | W1: 49675 | X1: 50041 | Y1: 50406 | Z1: 50771 | AA1: 51136 | AB1: 51502 | AC1: 51867 | AD1: 52232 | AE1: 52597 | AF1: 52963 | AG1: 53328 | AH1: 53693 | AI1: 54058 | AJ1: 54424 | AK1: 54789
A2: ch_2 | B2: 1202604.7 | C2: 1221238.1 | D2: 1244228.4 | E2: 1270774.7 | F2: 1299765.9 | G2: 1330732.6 | H2: 1362753.5 | I2: 1394994.1 | J2: 1427370.2 | K2: 1462475.5 | L2: 1501002.2 | M2: 1540053.5 | N2: 1578458 | O2: 1614813.2 | P2: 1648361.4 | Q2: 1678990.9 | R2: 1707332.2 | S2: 1733775.6 | T2: 1759071.6 | U2: 1783913.1 | V2: 1808395 | W2: 1833731.1 | X2: 1860264.6 | Y2: 1888460.8 | Z2: 1918662 | AA2: 1949709.2 | AB2: 1983119 | AC2: 2018983.5 | AD2: 2057790.5 | AE2: 2099972.4 | AF2: 2145641.7 | AG2: 2194550.3 | AH2: 2246278.9 | AI2: 2300457.5 | AJ2: 2356692.9 | AK2: 2374575.4
A3: ch_0 | B3: 1202604.7 | C3: 1221238.1 | D3: 1244228.4 | E3: 1270774.7 | F3: 1299765.9 | G3: 1330732.6 | H3: 1362041.3 | I3: 1393729.1 | J3: 1425973.7 | K3: 1458944.7 | L3: 1493025.6 | M3: 1525974.5 | N3: 1556955.4 | O3: 1585399.9 | P3: 1611101.1 | Q3: 1634226.1 | R3: 1656134.9 | S3: 1677444.4 | T3: 1698572.8 | U3: 1719899.2 | V3: 1741345.6 | W3: 1764093.4 | X3: 1788478.5 | Y3: 1814897.5 | Z3: 1843638.2 | AA3: 1873552.3 | AB3: 1906313.3 | AC3: 1942155.4 | AD3: 1981417.8 | AE3: 2024378 | AF3: 2071061.4 | AG3: 2121263.6 | AH3: 2174628.5 | AI3: 2230706.9 | AJ3: 2289000.4 | AK3: 2307155.4
A4: pch_2 | B4: 1.0018777 | C4: 1.0212839 | D4: 1.0413435 | E4: 1.0631468 | F4: 1.0841451 | G4: 1.1058914 | H4: 1.1286033 | I4: 1.1629873 | J4: 1.1975968 | K4: 1.235247 | L4: 1.2759159 | M4: 1.315204 | N4: 1.3536187 | O4: 1.3904683 | P4: 1.4252438 | Q4: 1.4575749 | R4: 1.4886597 | S4: 1.517448 | T4: 1.5437893 | U4: 1.5677882 | V4: 1.5897803 | W4: 1.6101145 | X4: 1.629216 | Y4: 1.6474697 | Z4: 1.6653783 | AA4: 1.6836928 | AB4: 1.7032089 | AC4: 1.7246736 | AD4: 1.7484023 | AE4: 1.7745731 | AF4: 1.8033273 | AG4: 1.8348803 | AH4: 1.8694023 | AI4: 1.9068231 | AJ4: 1.947026 | AK4: 1.947026
A5: pch_0 | B5: 1.0018777 | C5: 1.0212839 | D5: 1.0413435 | E5: 1.0631468 | F5: 1.0841451 | G5: 1.1058914 | H5: 1.1295249 | I5: 1.1549089 | J5: 1.1817648 | K5: 1.2099093 | L5: 1.2389606 | M5: 1.2681218 | N5: 1.2966043 | O5: 1.3237947 | P5: 1.3493534 | Q5: 1.3731207 | R5: 1.3939761 | S5: 1.4122133 | T5: 1.4282194 | U5: 1.4424702 | V5: 1.4555543 | W5: 1.4679266 | X5: 1.4801049 | Y5: 1.4926442 | Z5: 1.5061603 | AA5: 1.5214423 | AB5: 1.5389773 | AC5: 1.5592096 | AD5: 1.5825321 | AE5: 1.6091356 | AF5: 1.6391419 | AG5: 1.6725957 | AH5: 1.7094843 | AI5: 1.7497506 | AJ5: 1.7932974 | AK5: 1.7932974
A6: ch_cagr_2 | B6: 31645.106 | C6: 32089.821 | D6: 32644.059 | E6: 33321.254 | F6: 34090.664 | G6: 34944.976 | H6: 35858.468 | I6: 36815.174 | J6: 37754.909 | K6: 38748.641 | L6: 39827.831 | M6: 40923.19 | N6: 42024.43 | O6: 43096.983 | P6: 44113.823 | Q6: 45062.91 | R6: 45954.735 | S6: 46786.178 | T6: 47574.128 | U6: 48338.45 | V6: 49084.955 | W6: 49847.012 | X6: 50636.668 | Y6: 51469.276 | Z6: 52356.523 | AA6: 53271.666 | AB6: 54253.417 | AC6: 55305.623 | AD6: 56444.547 | AE6: 57685.674 | AF6: 59035.619 | AG6: 60489.857 | AH6: 62038.157 | AI6: 63671.769 | AJ6: 65380.866 | AK6: 66237.119
A7: ch_cagr_0 | B7: 31645.106 | C7: 32089.821 | D7: 32644.059 | E7: 33321.254 | F7: 34090.664 | G7: 34944.976 | H7: 35842.814 | I7: 36774.483 | J7: 37733.809 | K7: 38719.005 | L7: 39736.521 | M7: 40727.636 | N7: 41667.428 | O7: 42538.116 | P7: 43331.44 | Q7: 44049.522 | R7: 44722.917 | S7: 45371.871 | T7: 46011.774 | U7: 46654.811 | V7: 47299.965 | W7: 47977.598 | X7: 48697.416 | Y7: 49470.915 | Z7: 50306.905 | AA7: 51177.829 | AB7: 52127.817 | AC7: 53165.797 | AD7: 54303.433 | AE7: 55551.201 | AF7: 56912.454 | AG7: 58383.744 | AH7: 59956.788 | AI7: 61620.021 | AJ7: 63359.895 | AK7: 64163.33
A8: pch_cagr_2 | B8: 1.0010267 | C8: 1.0194115 | D8: 1.0382837 | E8: 1.0584341 | F8: 1.0785665 | G8: 1.0989944 | H8: 1.1199877 | I8: 1.1499566 | J8: 1.1829505 | K8: 1.2192886 | L8: 1.2586526 | M8: 1.2971499 | N8: 1.3334992 | O8: 1.3673775 | P8: 1.3986182 | Q8: 1.4271385 | R8: 1.454004 | S8: 1.4791573 | T8: 1.5023417 | U8: 1.5236176 | V8: 1.543256 | W8: 1.5616229 | X8: 1.5791069 | Y8: 1.595994 | Z8: 1.6127232 | AA8: 1.6298721 | AB8: 1.6483047 | AC8: 1.6687427 | AD8: 1.6912906 | AE8: 1.7159532 | AF8: 1.7427517 | AG8: 1.7718621 | AH8: 1.8034164 | AI8: 1.8372343 | AJ8: 1.8731237 | AK8: 1.873128
A9: pch_cagr_0 | B9: 1.0010267 | C9: 1.0194115 | D9: 1.0382837 | E9: 1.0584341 | F9: 1.0785665 | G9: 1.0989944 | H9: 1.120578 | I9: 1.1435752 | J9: 1.1679205 | K9: 1.1934707 | L9: 1.2198937 | M9: 1.2463732 | N9: 1.2721565 | O9: 1.2966906 | P9: 1.3197209 | Q9: 1.3411583 | R9: 1.36023 | S9: 1.3769126 | T9: 1.3915514 | U9: 1.4046358 | V9: 1.4167485 | W9: 1.4283713 | X9: 1.4400078 | Y9: 1.4521734 | Z9: 1.4654428 | AA9: 1.4804549 | AB9: 1.4976543 | AC9: 1.5174081 | AD9: 1.5400252 | AE9: 1.565585 | AF9: 1.5941376 | AG9: 1.6256763 | AH9: 1.6601526 | AI9: 1.6974849 | AJ9: 1.7375604 | AK9: 1.7375656
A10: ch_cfoo_2 | B10: 175140.21 | C10: 177599.31 | D10: 180647.71 | E10: 184379.3 | F10: 188591.36 | G10: 193241.78 | H10: 198198.09 | I10: 203616.45 | J10: 209042.13 | K10: 214802.06 | L10: 221031.29 | M10: 227240.65 | N10: 233342.73 | O10: 239173.27 | P10: 244623.16 | Q10: 249662.04 | R10: 254408.53 | S10: 258867.19 | T10: 263124.85 | U10: 267281.73 | V10: 271361.77 | W10: 275546.39 | X10: 279898.88 | Y10: 284495.77 | Z10: 289394.81 | AA10: 294440.59 | AB10: 299854.24 | AC10: 305663.04 | AD10: 311943.42 | AE10: 318764.38 | AF10: 326149.48 | AG10: 334070.59 | AH10: 342472.05 | AI10: 351299.29 | AJ10: 360491.6 | AK10: 365125.67
A11: ch_cfoo_0 | B11: 175140.21 | C11: 177599.31 | D11: 180647.71 | E11: 184379.3 | F11: 188591.36 | G11: 193241.78 | H11: 198114.27 | I11: 203168.11 | J11: 208372.58 | K11: 213715.99 | L11: 219231.29 | M11: 224589.5 | N11: 229651.68 | O11: 234323.42 | P11: 238567.71 | Q11: 242405.8 | R11: 246004.79 | S11: 249475.95 | T11: 252908.97 | U11: 256377.56 | V11: 259880.89 | W11: 263587.56 | X11: 267550.03 | Y11: 271828.73 | Z11: 276469.16 | AA11: 281314.12 | AB11: 286599.79 | AC11: 292368.16 | AD11: 298676.09 | AE11: 305571.96 | AF11: 313066.65 | AG11: 321135.75 | AH11: 329730.26 | AI11: 338784.85 | AJ11: 348224.63 | AK11: 352591.25
A12: pch_cfoo_2 | B12: 1.0004235 | C12: 1.0190826 | D12: 1.0382406 | E12: 1.0585166 | F12: 1.0793036 | G12: 1.1007039 | H12: 1.1228143 | I12: 1.1500777 | J12: 1.1802526 | K12: 1.2137993 | L12: 1.2505753 | M12: 1.288194 | N12: 1.3251896 | O12: 1.360633 | P12: 1.3939273 | Q12: 1.4246977 | R12: 1.4532521 | S12: 1.4795741 | T12: 1.5036357 | U12: 1.5255785 | V12: 1.5457224 | W12: 1.5644157 | X12: 1.5820773 | Y12: 1.5991084 | Z12: 1.6160037 | AA12: 1.6334229 | AB12: 1.6520671 | AC12: 1.6726172 | AD12: 1.6954371 | AE12: 1.7207023 | AF12: 1.748528 | AG12: 1.7790546 | AH12: 1.8123851 | AI12: 1.8484441 | AJ12: 1.8870994 | AK12: 1.8871008
... A105: pch_cbio_0 | B105: 1.0595323 | C105: 1.1089304 | D105: 1.1625785 | E105: 1.2405202 | F105: 1.2622591 | G105: 1.2852955 | H105: 1.31025 | I105: 1.3413348 | J105: 1.3741612 | K105: 1.4087619 | L105: 1.4447038 | M105: 1.4812118 | N105: 1.5173929 | O105: 1.5524472 | P105: 1.5857864 | Q105: 1.6170363 | R105: 1.6452672 | S105: 1.6701288 | T105: 1.6918517 | U105: 1.7108863 | V105: 1.727901 | W105: 1.7435134 | X105: 1.7583969 | Y105: 1.7732753 | Z105: 1.7889138 | AA105: 1.8063071 | AB105: 1.8261924 | AC105: 1.8492237 | AD105: 1.8759869 | AE105: 1.906892 | AF105: 1.9421958 | AG105: 1.9820445 | AH105: 2.0264995 | AI105: 2.0755573 | AJ105: 2.1291601 | AK105: 2.1517986

Sheet Value_Added
A1: _date_ | B1: 42005 | C1: 42370 | D1: 42736 | E1: 43101 | F1: 43466 | G1: 43831 | H1: 44197 | I1: 44562 | J1: 44927 | K1: 45292 | L1: 45658 | M1: 46023 | N1: 46388 | O1: 46753 | P1: 47119 | Q1: 47484 | R1: 47849 | S1: 48214 | T1: 48580 | U1: 48945 | V1: 49310 | W1: 49675 | X1: 50041 | Y1: 50406 | Z1: 50771 | AA1: 51136 | AB1: 51502 | AC1: 51867 | AD1: 52232 | AE1: 52597 | AF1: 52963 | AG1: 53328 | AH1: 53693 | AI1: 54058 | AJ1: 54424 | AK1: 54789
A2: va_2 | B2: 1966068.3 | C2: 2002067.4 | D2: 2041412.3 | E2: 2084231.4 | F2: 2129676.7 | G2: 2177537.1 | H2: 2227180.2 | I2: 2272887.7 | J2: 2319746.5 | K2: 2376782.9 | L2: 2434060 | M2: 2484607.5 | N2: 2529976.9 | O2: 2571483.9 | P2: 2610881.3 | Q2: 2649263.7 | R2: 2687119.9 | S2: 2725764.1 | T2: 2766152.8 | U2: 2808981.3 | V2: 2854544.4 | W2: 2903832.5 | X2: 2957387.9 | Y2: 3015596.9 | Z2: 3078565 | AA2: 3145390.9 | AB2: 3217223.7 | AC2: 3294331 | AD2: 3376881.8 | AE2: 3464455.7 | AF2: 3556331.6 | AG2: 3651852.3 | AH2: 3750470.4 | AI2: 3851652.6 | AJ2: 3954867.9 | AK2: 3945293.6
A3: va_0 | B3: 1966068.3 | C3: 2002067.4 | D3: 2041412.3 | E3: 2084231.4 | F3: 2129676.7 | G3: 2177537.1 | H3: 2226667.3 | I3: 2276807.8 | J3: 2327958 | K3: 2380180.2 | L3: 2432222.2 | M3: 2478342.2 | N3: 2520315.6 | O3: 2559004.7 | P3: 2595517.9 | Q3: 2630943.7 | R3: 2666977 | S3: 2704806.3 | T3: 2745254.5 | U3: 2788792.9 | V3: 2835522.2 | W3: 2886280.5 | X3: 2941492.4 | Y3: 3001437.2 | Z3: 3066114.1 | AA3: 3134553.2 | AB3: 3207730.2 | AC3: 3285927.6 | AD3: 3369230.5 | AE3: 3457113 | AF3: 3548775.1 | AG3: 3643518.6 | AH3: 3740777.2 | AI3: 3840011.6 | AJ3: 3940697.1 | AK3: 3931575.4
A4: va_sagr_2 | B4: 30804.437 | C4: 31356.076 | D4: 31987.884 | E4: 32706.613 | F4: 33485.052 | G4: 34319.46 | H4: 35195.053 | I4: 35982.522 | J4: 36791.727 | K4: 37803.06 | L4: 38792.791 | M4: 39619.64 | N4: 40336.614 | O4: 40974.536 | P4: 41568.507 | Q4: 42138.513 | R4: 42708.529 | S4: 43288.305 | T4: 43897.394 | U4: 44549.936 | V4: 45251.558 | W4: 46024.339 | X4: 46879.084 | Y4: 47823.564 | Z4: 48859.609 | AA4: 49966.862 | AB4: 51159.757 | AC4: 52456.038 | AD4: 53858.019 | AE4: 55355.92 | AF4: 56933.804 | AG4: 58576.948 | AH4: 60272.486 | AI4: 62007.353 | AJ4: 63767.791 | AK4: 63541.427
A5: va_sagr_0 | B5: 30804.437 | C5: 31356.076 | D5: 31987.884 | E5: 32706.613 | F5: 33485.052 | G5: 34319.46 | H5: 35183.887 | I5: 36073.107 | J5: 36982.231 | K5: 37909.408 | L5: 38824.457 | M5: 39598.652 | N5: 40279.904 | O5: 40886.399 | P5: 41441.235 | Q5: 41967.138 | R5: 42500.12 | S5: 43065.444 | T5: 43680.92 | U5: 44356.539 | V5: 45093.998 | W5: 45912.149 | X5: 46819.036 | Y5: 47819.721 | Z5: 48913.385 | AA5: 50077.94 | AB5: 51337.371 | AC5: 52696.663 | AD5: 54156.42 | AE5: 55703.892 | AF5: 57320.866 | AG5: 58991.669 | AH5: 60703.212 | AI5: 62442.482 | AJ5: 64196.39 | AK5: 63977.059
A6: va_sfor_2 | B6: 5289.0339 | C6: 5248.8866 | D6: 5214.6354 | E6: 5180.2061 | F6: 5171.5898 | G6: 5177.1287 | H6: 5190.0555 | I6: 5127.8371 | J6: 5079.9682 | K6: 5061.7524 | L6: 5053.9841 | M6: 5058.03 | N6: 5063.6053 | O6: 5068.7473 | P6: 5075.164 | Q6: 5084.0337 | R6: 5078.6485 | S6: 5074.1419 | T6: 5073.8468 | U6: 5079.3422 | V6: 5090.2999 | W6: 5109.4903 | X6: 5137.2802 | Y6: 5173.937 | Z6: 5219.5491 | AA6: 5270.8783 | AB6: 5335.8839 | AC6: 5412.5278 | AD6: 5501.399 | AE6: 5602.2564 | AF6: 5714.7335 | AG6: 5839.0832 | AH6: 5976.2489 | AI6: 6127.6225 | AJ6: 6295.2074 | AK6: 6290.1253
A7: va_sfor_0 | B7: 5289.0339 | C7: 5248.8866 | D7: 5214.6354 | E7: 5180.2061 | F7: 5171.5898 | G7: 5177.1287 | H7: 5190.3348 | I7: 5211.5547 | J7: 5237.9498 | K7: 5267.9089 | L7: 5300.6425 | M7: 5325.1428 | N7: 5344.6025 | O7: 5360.9533 | P7: 5376.1714 | Q7: 5391.9393 | R7: 5409.1895 | S7: 5429.673 | T7: 5454.6426 | U7: 5484.8186 | V7: 5519.3857 | W7: 5561.2508 | X7: 5610.6946 | Y7: 5668.0124 | Z7: 5733.2203 | AA7: 5802.5034 | AB7: 5880.9426 | AC7: 5969.3081 | AD7: 6068.1204 | AE7: 6177.0781 | AF7: 6295.682 | AG7: 6423.8578 | AH7: 6562.0754 | AI7: 6711.3377 | AJ7: 6873.2256 | AK7: 6866.4849
A8: va_sfoo_2 | B8: 43681.378 | C8: 44515.042 | D8: 45433.94 | E8: 46475.203 | F8: 47591.206 | G8: 48780.868 | H8: 50019.912 | I8: 51180.809 | J8: 52381.649 | K8: 53839.391 | L8: 55285.19 | M8: 56530.516 | N8: 57651.595 | O8: 58670.901 | P8: 59620.603 | Q8: 60520.733 | R8: 61405.931 | S8: 62287.508 | T8: 63192.214 | U8: 64140.056 | V8: 65135.839 | W8: 66216.635 | X8: 67394.115 | Y8: 68680.511 | Z8: 70080.522 | AA8: 71558.53 | AB8: 73144.847 | AC8: 74862.963 | AD8: 76716.454 | AE8: 78696.956 | AF8: 80787.48 | AG8: 82969.722 | AH8: 85225.994 | AI8: 87538.862 | AJ8: 89889.271 | AK8: 89384.898
A9: va_sfoo_0 | B9: 43681.378 | C9: 44515.042 | D9: 45433.939 | E9: 46475.203 | F9: 47591.206 | G9: 48780.868 | H9: 50006.558 | I9: 51267.554 | J9: 52558.042 | K9: 53875.967 | L9: 55188.973 | M9: 56327.002 | N9: 57353.614 | O9: 58282.366 | P9: 59136.133 | Q9: 59940.358 | R9: 60742.249 | S9: 61572.257 | T9: 62453.378 | U9: 63400.067 | V9: 64413.098 | W9: 65527.021 | X9: 66751.259 | Y9: 68094.686 | Z9: 69558.638 | AA9: 71105.934 | AB9: 72785.694 | AC9: 74600.718 | AD9: 76553.773 | AE9: 78631.997 | AF9: 80815.28 | AG9: 83085.456 | AH9: 85426.153 | AI9: 87820.135 | AJ9: 90249.707 | AK9: 89739.688
A10: va_sveh_2 | B10: 29847.656 | C10: 31126.908 | D10: 32289.835 | E10: 33400.087 | F10: 34511.288 | G10: 35611.015 | H10: 36694.527 | I10: 37287.385 | J10: 38041.173 | K10: 39365.263 | L10: 40442.39 | M10: 41143.563 | N10: 41678.836 | O10: 42148.644 | P10: 42651.376 | Q10: 43218.001 | R10: 43769.932 | S10: 44418.821 | T10: 45173.716 | U10: 46034.729 | V10: 47003.976 | W10: 48090.308 | X10: 49302.747 | Y10: 50642.342 | Z10: 52099.855 | AA10: 53662.734 | AB10: 55390.803 | AC10: 57231.906 | AD10: 59186.447 | AE10: 61216.911 | AF10: 63285.435 | AG10: 65369.846 | AH10: 67456.736 | AI10: 69534.546 | AJ10: 71592.104 | AK10: 71057.831
A11: va_sveh_0 | B11: 29847.656 | C11: 31126.908 | D11: 32289.835 | E11: 33400.087 | F11: 34511.288 | G11: 35611.015 | H11: 36683.151 | I11: 37746.212 | J11: 38820.825 | K11: 39920 | L11: 40960.096 | M11: 41691.209 | N11: 42328.388 | O11: 42922.075 | P11: 43522.476 | Q11: 44163.498 | R11: 44892.514 | S11: 45725.59 | T11: 46666.758 | U11: 47710.933 | V11: 48857.302 | W11: 50113.66 | X11: 51488.913 | Y11: 52981.833 | Z11: 54579.494 | AA11: 56265.982 | AB11: 58054.513 | AC11: 59952.733 | AD11: 61951.869 | AE11: 64012.057 | AF11: 66095.177 | AG11: 68182.052 | AH11: 70264.624 | AI11: 72335.756 | AJ11: 74388.116 | AK11: 73862.808
A12: va_sgla_2 | B12: 7902.5651 | C12: 8061.0777 | D12: 8230.8485 | E12: 8412.9754 | F12: 8607.6547 | G12: 8815.2285 | H12: 9033.9859 | I12: 9211.3372 | J12: 9389.315 | K12: 9607.2837 | L12: 9819.1015 | M12: 10005.028 | N12: 10174.806 | O12: 10336.321 | P12: 10498.152 | Q12: 10664.934 | R12: 10838.889 | S12: 11019.703 | T12: 11212.136 | U12: 11419.529 | V12: 11644.049 | W12: 11889.545 | X12: 12159.062 | Y12: 12454.339 | Z12: 12775.886 | AA12: 13121.227 | AB12: 13490.512 | AC12: 13889.986 | AD12: 14320.011 | AE12: 14779.122 | AF12: 15265.328 | AG12: 15777.967 | AH12: 16317.542 | AI12: 16884.77 | AJ12: 17481.204 | AK12: 17403.702
... A79: va_ser_0 | B79: 1511266 | C79: 1537176 | D79: 1566105.5 | E79: 1597788.9 | F79: 1631507.6 | G79: 1667039.7 | H79: 1703472.9 | I79: 1740794.9 | J79: 1778874.3 | K79: 1817704.5 | L79: 1856545 | M79: 1891563.8 | N79: 1923545.6 | O79: 1953009.6 | P79: 1980673.7 | Q79: 2007291.7 | R79: 2034097 | S79: 2061949.8 | T79: 2091462.6 | U79: 2123014.3 | V79: 2156684.2 | W79: 2193143.1 | X79: 2232714.1 | Y79: 2275638 | Z79: 2321967 | AA79: 2370975.3 | AB79: 2423454.9 | AC79: 2479629 | AD79: 2539615.6 | AE79: 2603139.4 | AF79: 2669705.6 | AG79: 2738849.5 | AH79: 2810186.2 | AI79: 2883360.2 | AJ79: 2958043.8 | AK79: 2953682.5

Sheet INV
A1: _date_ | B1: 42005 | C1: 42370 | D1: 42736 | E1: 43101 | F1: 43466 | G1: 43831 | H1: 44197 | I1: 44562 | J1: 44927 | K1: 45292 | L1: 45658 | M1: 46023 | N1: 46388 | O1: 46753 | P1: 47119 | Q1: 47484 | R1: 47849 | S1: 48214 | T1: 48580 | U1: 48945 | V1: 49310 | W1: 49675 | X1: 50041 | Y1: 50406 | Z1: 50771 | AA1: 51136 | AB1: 51502 | AC1: 51867 | AD1: 52232 | AE1: 52597 | AF1: 52963 | AG1: 53328 | AH1: 53693 | AI1: 54058 | AJ1: 54424 | AK1: 54789
A2: ia_2 | B2: 472642.18 | C2: 480640.64 | D2: 490481.94 | E2: 501676.53 | F2: 514044.59 | G2: 527421.99 | H2: 541649.67 | I2: 555235.08 | J2: 569053.05 | K2: 584954.46 | L2: 602148.63 | M2: 619310.23 | N2: 636023.44 | O2: 652337.8 | P2: 668560.07 | Q2: 684981.1 | R2: 701660.31 | S2: 718881.72 | T2: 736923.17 | U2: 756001.53 | V2: 776242.39 | W2: 797835.55 | X2: 820957.61 | Y2: 845764.88 | Z2: 872352.84 | AA2: 900625.03 | AB2: 930720.76 | AC2: 962752.24 | AD2: 996878.47 | AE2: 1033198.6 | AF2: 1071741.2 | AG2: 1112519.4 | AH2: 1155584 | AI2: 1201056.2 | AJ2: 1249128.5 | AK2: 1267141.3
A3: ia_0 | B3: 472642.18 | C3: 480640.64 | D3: 490481.94 | E3: 501676.53 | F3: 514044.59 | G3: 527421.99 | H3: 541525.44 | I3: 556337.77 | J3: 571831.6 | K3: 588026.59 | L3: 604746.13 | M3: 621013.48 | N3: 636687.45 | O3: 651878.07 | P3: 666803.07 | Q3: 681704.55 | R3: 696994.37 | S3: 713017.72 | T3: 730014 | U3: 748119.57 | V3: 767374.54 | W3: 787901.97 | X3: 809825.95 | Y3: 833249.12 | Z3: 858216.45 | AA3: 884595.92 | AB3: 912491.66 | AC3: 942062.86 | AD3: 973470.18 | AE3: 1006795.4 | AF3: 1042047.3 | AG3: 1079237.6 | AH3: 1118423.7 | AI3: 1159711 | AJ3: 1203259.7 | AK3: 1219542.8
A4: ia_sagr_2 | B4: 4276.7998 | C4: 4350.6957 | D4: 4442.1228 | E4: 4550.9686 | F4: 4670.825 | G4: 4800.4246 | H4: 4938.3069 | I4: 5087.3229 | J4: 5245.0032 | K4: 5429.1143 | L4: 5628.9472 | M4: 5820.8003 | N4: 6000.9501 | O4: 6170.6549 | P4: 6333.4436 | Q4: 6492.3876 | R4: 6653.2682 | S4: 6817.5401 | T4: 6987.2035 | U4: 7163.9257 | V4: 7348.2124 | W4: 7541.8092 | X4: 7746.0374 | Y4: 7961.7951 | Z4: 8189.0321 | AA4: 8424.6018 | AB4: 8667.5018 | AC4: 8918.5165 | AD4: 9178.3289 | AE4: 9446.2771 | AF4: 9720.2662 | AG4: 9997.4366 | AH4: 10274.801 | AI4: 10549.536 | AJ4: 10818.699 | AK4: 10882.231
A5: ia_sagr_0 | B5: 4276.7998 | C5: 4350.6957 | D5: 4442.1228 | E5: 4550.9686 | F5: 4670.825 | G5: 4800.4246 | H5: 4937.9967 | I5: 5082.6645 | J5: 5233.7716 | K5: 5391.0531 | L5: 5552.0287 | M5: 5704.5752 | N5: 5846.9589 | O5: 5980.2946 | P5: 6106.9237 | Q5: 6229.5861 | R5: 6351.5771 | S5: 6476.5466 | T5: 6607.3356 | U5: 6745.7497 | V5: 6892.3256 | W5: 7048.8948 | X5: 7216.9556 | Y5: 7397.5131 | Z5: 7590.7439 | AA5: 7794.1956 | AB5: 8009.0157 | AC5: 8236.5077 | AD5: 8477.5516 | AE5: 8731.7569 | AF5: 8997.556 | AG5: 9273.075 | AH5: 9556.5352 | AI5: 9846.1603 | AJ5: 10140.096 | AK5: 10240.043
A6: ia_sfor_2 | B6: 167.04337 | C6: 167.06994 | D6: 166.46656 | E6: 165.64032 | F6: 165.16648 | G6: 165.04502 | H6: 165.14267 | I6: 163.97535 | J6: 162.70356 | K6: 162.11395 | L6: 162.05619 | M6: 162.42364 | N6: 163.04349 | O6: 163.81933 | P6: 164.75214 | Q6: 165.86099 | R6: 166.8184 | S6: 167.79168 | T6: 168.90354 | U6: 170.21288 | V6: 171.7101 | W6: 173.43562 | X6: 175.39708 | Y6: 177.59245 | Z6: 180.00988 | AA6: 182.54887 | AB6: 185.3383 | AC6: 188.3664 | AD6: 191.64913 | AE6: 195.19989 | AF6: 199.02647 | AG6: 203.14286 | AH6: 207.58028 | AI6: 212.39247 | AJ6: 217.65279 | AK6: 219.17813
A7: ia_sfor_0 | B7: 167.04337 | C7: 167.06994 | D7: 166.46656 | E7: 165.64032 | F7: 165.16648 | G7: 165.04502 | H7: 165.14535 | I7: 165.46654 | J7: 165.97166 | K7: 166.63216 | L7: 167.44096 | M7: 168.19023 | N7: 168.89124 | O7: 169.59777 | P7: 170.36505 | Q7: 171.23679 | R7: 172.23779 | S7: 173.39404 | T7: 174.71938 | U7: 176.21391 | V7: 177.83999 | W7: 179.63603 | X7: 181.61363 | Y7: 183.77523 | Z7: 186.11373 | AA7: 188.53031 | AB7: 191.10085 | AC7: 193.87786 | AD7: 196.90169 | AE7: 200.19908 | AF7: 203.7886 | AG7: 207.69576 | AH7: 211.95984 | AI7: 216.63561 | AJ7: 221.79521 | AK7: 223.35055
A8: ia_sfoo_2 | B8: 6748.6064 | C8: 6865.6638 | D8: 7009.8534 | E8: 7180.1421 | F8: 7368.728 | G8: 7573.1701 | H8: 7789.9544 | I8: 8017.6619 | J8: 8256.9558 | K8: 8530.3678 | L8: 8826.569 | M8: 9117.2318 | N8: 9396.4904 | O8: 9663.9978 | P8: 9922.333 | Q8: 10174.189 | R8: 10425.916 | S8: 10679.854 | T8: 10939.074 | U8: 11206.285 | V8: 11482.293 | W8: 11770.354 | X8: 12072.761 | Y8: 12391.427 | Z8: 12727.144 | AA8: 13075.483 | AB8: 13436.05 | AC8: 13810.769 | AD8: 14201.592 | AE8: 14609.076 | AF8: 15031.884 | AG8: 15467.193 | AH8: 15911.529 | AI8: 16361.531 | AJ8: 16813.542 | AK8: 16940.719
A9: ia_sfoo_0 | B9: 6748.6064 | C9: 6865.6638 | D9: 7009.8534 | E9: 7180.1421 | F9: 7368.728 | G9: 7573.1701 | H9: 7791.9427 | I9: 8022.7721 | J9: 8264.543 | K9: 8516.8846 | L9: 8777.1382 | M9: 9028.9266 | N9: 9268.9421 | O9: 9497.3557 | P9: 9716.0827 | Q9: 9927.9285 | R9: 10135.507 | S9: 10344.642 | T9: 10559.555 | U9: 10782.94 | V9: 11015.391 | W9: 11260.173 | X9: 11519.728 | Y9: 11795.862 | Z9: 12089.285 | AA9: 12396.03 | AB9: 12718.921 | AC9: 13060.383 | AD9: 13422.312 | AE9: 13805.084 | AF9: 14207.456 | AG9: 14627.535 | AH9: 15063.276 | AI9: 15512.418 | AJ9: 15972.444 | AK9: 16132.348
A10: ia_sveh_2 | B10: 36325.961 | C10: 37368.777 | D10: 38720.69 | E10: 40187.683 | F10: 41712.884 | G10: 43267.408 | H10: 44836.614 | I10: 46066.527 | J10: 47202.708 | K10: 48698.788 | L10: 50260.241 | M10: 51586.801 | N10: 52651.141 | O10: 53528.793 | P10: 54338.277 | Q10: 55167.759 | R10: 56002.403 | S10: 56906.823 | T10: 57927.057 | U10: 59086.777 | V10: 60398.755 | W10: 61875.902 | X10: 63532.53 | Y10: 65378.572 | Z10: 67413.595 | AA10: 69628.538 | AB10: 72062.129 | AC10: 74702.651 | AD10: 77543.19 | AE10: 80554.978 | AF10: 83694.374 | AG10: 86920.486 | AH10: 90201.381 | AI10: 93512.114 | AJ10: 96831.097 | AK10: 98108.689
A11: ia_sveh_0 | B11: 36325.961 | C11: 37368.777 | D11: 38720.69 | E11: 40187.683 | F11: 41712.884 | G11: 43267.408 | H11: 44826.617 | I11: 46388.111 | J11: 47966.648 | K11: 49580.049 | L11: 51179.847 | M11: 52558.213 | N11: 53736.171 | O11: 54776.251 | P11: 55750.97 | Q11: 56723.765 | R11: 57763.422 | S11: 58918.981 | T11: 60216.921 | U11: 61665.684 | V11: 63267.774 | W11: 65030.268 | X11: 66964.468 | Y11: 69076.832 | Z11: 71361.997 | AA11: 73805.329 | AB11: 76409.273 | AC11: 79183.53 | AD11: 82128.993 | AE11: 85217.563 | AF11: 88403.929 | AG11: 91647.408 | AH11: 94919.169 | AI11: 98197.644 | AJ11: 101464.31 | AK11: 102711.34
A12: ia_sgla_2 | B12: 1456.6088 | C12: 1483.4797 | D12: 1516.4216 | E12: 1554.2873 | F12: 1594.9757 | G12: 1638.5423 | H12: 1684.7898 | I12: 1733.197 | J12: 1782.7819 | K12: 1839.315 | L12: 1900.451 | M12: 1960.4039 | N12: 2019.0619 | O12: 2077.3878 | P12: 2136.8319 | Q12: 2198.5758 | R12: 2264.7505 | S12: 2335.3325 | T12: 2410.8287 | U12: 2491.8067 | V12: 2578.6397 | W12: 2671.8732 | X12: 2772.0567 | Y12: 2879.6224 | Z12: 2994.7071 | AA12: 3116.7343 | AB12: 3245.1154 | AC12: 3380.2751 | AD12: 3522.652 | AE12: 3672.4138 | AF12: 3829.4776 | AG12: 3993.7461 | AH12: 4165.3307 | AI12: 4344.6553 | AJ12: 4532.404 | AK12: 4617.0446
... A79: ia_ser_0 | B79: 219444.02 | C79: 222914.78 | D79: 227125.52 | E79: 231903.78 | F79: 237192.97 | G79: 242903.74 | H79: 248877.73 | I79: 255062.51 | J79: 261445.2 | K79: 268033.34 | L79: 274767.14 | M79: 281246.99 | N79: 287393.56 | O79: 293232.31 | P79: 298834.08 | Q79: 304285.63 | R79: 309767.93 | S79: 315419.09 | T79: 321329.68 | U79: 327548.93 | V79: 334080.16 | W79: 340981.08 | X79: 348300.39 | Y79: 356075.07 | Z79: 364316.74 | AA79: 372940.15 | AB79: 381996.15 | AC79: 391542.21 | AD79: 401628.45 | AE79: 412269.43 | AF79: 423440.94 | AG79: 435105.97 | AH79: 447229.25 | AI79: 459776.24 | AJ79: 472712.1 | AK79: 477142.16

Sheet Labor
A1: _date_ | B1: 42005 | C1: 42370 | D1: 42736 | E1: 43101 | F1: 43466 | G1: 43831 | H1: 44197 | I1: 44562 | J1: 44927 | K1: 45292 | L1: 45658 | M1: 46023 | N1: 46388 | O1: 46753 | P1: 47119 | Q1: 47484 | R1: 47849 | S1: 48214 | T1: 48580 | U1: 48945 | V1: 49310 | W1: 49675 | X1: 50041 | Y1: 50406 | Z1: 50771 | AA1: 51136 | AB1: 51502 | AC1: 51867 | AD1: 52232 | AE1: 52597 | AF1: 52963 | AG1: 53328 | AH1: 53693 | AI1: 54058 | AJ1: 54424 | AK1: 54789
A2: f_l_2 | B2: 27371.429 | C2: 27495.952 | D2: 27689.216 | E2: 27940.872 | F2: 28233.086 | G2: 28554.595 | H2: 28893.531 | I2: 29219.503 | J2: 29533.602 | K2: 29897.796 | L2: 30286.806 | M2: 30630.395 | N2: 30896.974 | O2: 31081.962 | P2: 31198.99 | Q2: 31266.73 | R2: 31302.98 | S2: 31325.247 | T2: 31348.801 | U2: 31385.645 | V2: 31443.155 | W2: 31530.122 | X2: 31653.414 | Y2: 31817.67 | Z2: 32024.686 | AA2: 32269.197 | AB2: 32553.449 | AC2: 32879.848 | AD2: 33249.568 | AE2: 33659.796 | AF2: 34103.92 | AG2: 34573.993 | AH2: 35062.621 | AI2: 35563.379 | AJ2: 36071.073 | AK2: 36040.827
A3: f_l_0 | B3: 27371.429 | C3: 27495.952 | D3: 27689.216 | E3: 27940.872 | F3: 28233.086 | G3: 28554.595 | H3: 28890.897 | I3: 29234.716 | J3: 29579.992 | K3: 29923.216 | L3: 30254.403 | M3: 30530.382 | N3: 30736.562 | O3: 30873.764 | P3: 30952.815 | Q3: 30989.286 | R3: 31002.892 | S3: 31012.735 | T3: 31034.536 | U3: 31079.342 | V3: 31152.827 | W3: 31261.791 | X3: 31411.184 | Y3: 31603.974 | Z3: 31840.484 | AA3: 32114.277 | AB3: 32425.87 | AC3: 32776.18 | AD3: 33165.089 | AE3: 33588.549 | AF3: 34038.855 | AG3: 34507.1 | AH3: 34985.03 | AI3: 35465.597 | AJ3: 35943.158 | AK3: 35900.936
A4: f_l_sagr_2 | B4: 731.66323 | C4: 734.94233 | D4: 740.33925 | E4: 747.87343 | F4: 757.05155 | G4: 767.53586 | H4: 778.91167 | I4: 789.67887 | J4: 799.84686 | K4: 811.69413 | L4: 824.14592 | M4: 834.55802 | N4: 841.95746 | O4: 846.35926 | P4: 848.36792 | Q4: 848.69345 | R4: 848.13138 | S4: 847.21712 | T4: 846.41869 | U4: 846.11315 | V4: 846.53173 | W4: 847.97882 | X4: 850.6934 | Y4: 854.82993 | Z4: 860.43469 | AA4: 867.29145 | AB4: 875.3633 | AC4: 884.77098 | AD4: 895.56713 | AE4: 907.63311 | AF4: 920.69481 | AG4: 934.4184 | AH4: 948.47748 | AI4: 962.56467 | AJ4: 976.39501 | AK4: 972.89492
A5: f_l_sagr_0 | B5: 731.66323 | C5: 734.94233 | D5: 740.33925 | E5: 747.87343 | F5: 757.05155 | G5: 767.53586 | H5: 778.80653 | I5: 790.46224 | J5: 802.20545 | K5: 813.84792 | L5: 824.94897 | M5: 833.7953 | N5: 839.89201 | O5: 843.32967 | P5: 844.56211 | Q5: 844.20458 | R5: 843.0136 | S5: 841.72056 | T5: 840.92173 | U5: 841.02371 | V5: 842.22205 | W5: 844.75162 | X5: 848.77277 | Y5: 854.36577 | Z5: 861.50971 | AA5: 869.93481 | AB5: 879.64781 | AC5: 890.66944 | AD5: 902.96987 | AE5: 916.36006 | AF5: 930.50875 | AG5: 945.03821 | AH5: 959.58963 | AI5: 973.8367 | AJ5: 987.48704 | AK5: 984.09147
A6: f_l_sfor_2 | B6: 29.058664 | C6: 28.770835 | D6: 28.33003 | E6: 27.82763 | F6: 27.386631 | G6: 27.03056 | H6: 26.7439 | I6: 26.28172 | J6: 25.776573 | K6: 25.346523 | L6: 24.990893 | M6: 24.702046 | N6: 24.444442 | O6: 24.193711 | P6: 23.943194 | Q6: 23.694233 | R6: 23.405316 | S6: 23.097127 | T6: 22.79077 | U6: 22.501243 | V6: 22.234611 | W6: 22.000085 | X6: 21.80213 | Y6: 21.642292 | Z6: 21.520212 | AA6: 21.426722 | AB6: 21.375246 | AC6: 21.366888 | AD6: 21.401874 | AE6: 21.478025 | AF6: 21.591711 | AG6: 21.740156 | AH6: 21.922689 | AI6: 22.140578 | AJ6: 22.397206 | AK6: 22.643812
A7: f_l_sfor_0 | B7: 29.058664 | C7: 28.770835 | D7: 28.33003 | E7: 27.82763 | F7: 27.386631 | G7: 27.03056 | H7: 26.745836 | I7: 26.522378 | J7: 26.343627 | K7: 26.194352 | L7: 26.063311 | M7: 25.912318 | N7: 25.731181 | O7: 25.521819 | P7: 25.292367 | Q7: 25.052847 | R7: 24.810551 | S7: 24.574129 | T7: 24.351472 | U7: 24.14836 | V7: 23.965217 | W7: 23.809062 | X7: 23.683418 | Y7: 23.589784 | Z7: 23.527899 | AA7: 23.487521 | AB7: 23.474651 | AC7: 23.493353 | AD7: 23.545649 | AE7: 23.630403 | AF7: 23.744408 | AG7: 23.884485 | AH7: 24.048849 | AI7: 24.237648 | AJ7: 24.453208 | AK7: 25.119321
A8: f_l_sfoo_2 | B8: 618.23086 | C8: 621.21856 | D8: 626.01615 | E8: 632.60016 | F8: 640.5321 | G8: 649.50837 | H8: 659.14994 | I8: 668.45087 | J8: 677.33381 | K8: 687.30934 | L8: 697.77159 | M8: 706.87925 | N8: 713.89962 | O8: 718.71542 | P8: 721.61715 | Q8: 723.02325 | R8: 723.4797 | S8: 723.39089 | T8: 723.13628 | U8: 723.04171 | V8: 723.30456 | W8: 724.21033 | X8: 725.96977 | Y8: 728.72955 | Z8: 732.5555 | AA8: 737.25985 | AB8: 742.83556 | AC8: 749.38907 | AD8: 756.98022 | AE8: 765.55918 | AF8: 774.96317 | AG8: 784.96598 | AH8: 795.3247 | AI8: 805.80255 | AJ8: 816.17575 | AK8: 812.86983
A9: f_l_sfoo_0 | B9: 618.23086 | C9: 621.21856 | D9: 626.01615 | E9: 632.60016 | F9: 640.5321 | G9: 649.50837 | H9: 659.05819 | I9: 668.85211 | J9: 678.66443 | K9: 688.36337 | L9: 697.68299 | M9: 705.3918 | N9: 711.07173 | O9: 714.69977 | P9: 716.52588 | Q9: 716.95002 | R9: 716.53446 | S9: 715.84009 | T9: 715.33455 | U9: 715.35121 | V9: 716.04968 | W9: 717.66097 | X9: 720.33955 | Y9: 724.17567 | Z9: 729.18128 | AA9: 735.12635 | AB9: 742.0656 | AC9: 750.03726 | AD9: 759.04052 | AE9: 768.96478 | AF9: 779.5932 | AG9: 790.66232 | AH9: 801.90687 | AI9: 813.07283 | AJ9: 823.92343 | AK9: 820.85203
A10: f_l_sveh_2 | B10: 185.66199 | C10: 188.5372 | D10: 192.92092 | E10: 197.89854 | F10: 202.95454 | G10: 207.82439 | H10: 212.3856 | I10: 215.4633 | J10: 217.75263 | K10: 221.08897 | L10: 224.57332 | M10: 226.88515 | N10: 227.71627 | O10: 227.32926 | P10: 226.28333 | Q10: 225.07438 | R10: 223.83531 | S10: 222.85543 | T10: 222.32961 | U10: 222.34987 | V10: 222.94744 | W10: 224.13748 | X10: 225.93109 | Y10: 228.31998 | Z10: 231.2625 | AA10: 234.69214 | AB10: 238.68475 | AC10: 243.1891 | AD10: 248.1439 | AE10: 253.41542 | AF10: 258.82221 | AG10: 264.19558 | AH10: 269.40672 | AI10: 274.36053 | AJ10: 278.98654 | AK10: 278.39171
A11: f_l_sveh_0 | B11: 185.66199 | C11: 188.5372 | D11: 192.92092 | E11: 197.89854 | F11: 202.95454 | G11: 207.82439 | H11: 212.35209 | I11: 216.52014 | J11: 220.39751 | K11: 224.07742 | L11: 227.39592 | M11: 229.54942 | N11: 230.53647 | O11: 230.6212 | P11: 230.17516 | Q11: 229.55252 | R11: 229.08122 | S11: 228.99455 | T11: 229.4251 | U11: 230.41794 | V11: 231.9751 | W11: 234.0953 | X11: 236.7827 | Y11: 240.02475 | Z11: 243.77255 | AA11: 247.94955 | AB11: 252.52263 | AC11: 257.47982 | AD11: 262.78489 | AE11: 268.31348 | AF11: 273.8833 | AG11: 279.32153 | AH11: 284.49801 | AI11: 289.32082 | AJ11: 293.72501 | AK11: 292.90536
A12: f_l_sgla_2 | B12: 97.944579 | C12: 98.450594 | D12: 99.246877 | E12: 100.25966 | F12: 101.43154 | G12: 102.74031 | H12: 104.15858 | I12: 105.36477 | J12: 106.37157 | K12: 107.46996 | L12: 108.58432 | M12: 109.5043 | N12: 110.16405 | O12: 110.58925 | P12: 110.85933 | Q12: 111.05587 | R12: 111.24991 | S12: 111.47135 | T12: 111.75576 | U12: 112.13782 | V12: 112.64473 | W12: 113.30695 | X12: 114.1521 | Y12: 115.19794 | Z12: 116.44971 | AA12: 117.8916 | AB12: 119.50963 | AC12: 121.32061 | AD12: 123.33126 | AE12: 125.52981 | AF12: 127.89078 | AG12: 130.38877 | AH12: 133.00607 | AI12: 135.73118 | AJ12: 138.56036 | AK12: 139.93994
... A79: f_l_ser_0 | B79: 21269.634 | C79: 21358.657 | D79: 21496.635 | E79: 21677.239 | F79: 21887.555 | G79: 22119.063 | H79: 22360.427 | I79: 22605.197 | J79: 22849.032 | K79: 23089.604 | L79: 23320.646 | M79: 23512.478 | N79: 23654.138 | O79: 23745.37 | P79: 23793.071 | Q79: 23807.793 | R79: 23803.612 | S79: 23794.158 | T79: 23790.659 | U79: 23801.088 | V79: 23829.456 | W79: 23880.966 | X79: 23959.337 | Y79: 24066.824 | Z79: 24203.767 | AA79: 24365.185 | AB79: 24551.696 | AC79: 24763.98 | AD79: 25001.913 | AE79: 25262.636 | AF79: 25540.64 | AG79: 25829.364 | AH79: 26122.467 | AI79: 26414.223 | AJ79: 26699.671 | AK79: 26641.471

Sheet Final_nrj
A1: _date_ | B1: 42005 | C1: 42370 | D1: 42736 | E1: 43101 | F1: 43466 | G1: 43831 | H1: 44197 | I1: 44562 | J1: 44927 | K1: 45292 | L1: 45658 | M1: 46023 | N1: 46388 | O1: 46753 | P1: 47119 | Q1: 47484 | R1: 47849 | S1: 48214 | T1: 48580 | U1: 48945 | V1: 49310 | W1: 49675 | X1: 50041 | Y1: 50406 | Z1: 50771 | AA1: 51136 | AB1: 51502 | AC1: 51867 | AD1: 52232 | AE1: 52597 | AF1: 52963 | AG1: 53328 | AH1: 53693 | AI1: 54058 | AJ1: 54424 | AK1: 54789
A2: cf_toe_2 | B2: 161.67129 | C2: 162.48434 | D2: 163.32959 | E2: 164.18437 | F2: 165.63541 | G2: 167.58128 | H2: 169.90437 | I2: 170.24791 | J2: 170.38265 | K2: 171.11676 | L2: 172.02608 | M2: 172.91425 | N2: 173.70297 | O2: 174.41031 | P2: 175.11111 | Q2: 175.85507 | R2: 176.55092 | S2: 177.28216 | T2: 178.13712 | U2: 179.18323 | V2: 180.45375 | W2: 182.03669 | X2: 183.97161 | Y2: 186.28602 | Z2: 188.9942 | AA2: 192.04183 | AB2: 195.52978 | AC2: 199.51756 | AD2: 204.03135 | AE2: 209.05843 | AF2: 214.57343 | AG2: 220.57221 | AH2: 227.07934 | AI2: 234.13964 | AJ2: 241.83372 | AK2: 241.97482
A3: ch_toe_2 | B3: 64.30144 | C3: 63.918967 | D3: 63.418855 | E3: 62.924205 | F3: 62.662553 | G3: 62.563054 | H3: 62.558742 | I3: 62.047815 | J3: 61.601261 | K3: 61.251916 | L3: 61.02938 | M3: 60.983609 | N3: 61.054353 | O3: 61.193235 | P3: 61.365462 | Q3: 61.548653 | R3: 61.691707 | S3: 61.81107 | T3: 61.92083 | U3: 62.031787 | V3: 62.13493 | W3: 62.263411 | X3: 62.411154 | Y3: 62.57726 | Z3: 62.762793 | AA3: 62.922369 | AB3: 63.110337 | AC3: 63.327878 | AD3: 63.578849 | AE3: 63.868479 | AF3: 64.202375 | AG3: 64.585206 | AH3: 65.021873 | AI3: 65.519885 | AJ3: 66.090163 | AK3: 66.185457
A4: ch_hous_toe_2 | B4: 42520877 | C4: 42430148 | D4: 42062218 | E4: 41592799 | F4: 41267212 | G4: 41040155 | H4: 40867797 | I4: 40229353 | J4: 39656795 | K4: 39164475 | L4: 38777964 | M4: 38535729 | N4: 38391977 | O4: 38313795 | P4: 38277095 | Q4: 38265691 | R4: 38239835 | S4: 38211726 | T4: 38190416 | U4: 38182604 | V4: 38177532 | W4: 38202625 | X4: 38248904 | Y4: 38312144 | Z4: 38390542 | AA4: 38441090 | AB4: 38511918 | AC4: 38602567 | AD4: 38714141 | AE4: 38849132 | AF4: 39011667 | AG4: 39206492 | AH4: 39439614 | AI4: 39719861 | AJ4: 40059659 | AK4: 40312017
A5: ch_auto_toe_2 | B5: 21780563 | C5: 21488819 | D5: 21356636 | E5: 21331406 | F5: 21395341 | G5: 21522899 | H5: 21690945 | I5: 21818463 | J5: 21944466 | K5: 22087441 | L5: 22251416 | M5: 22447880 | N5: 22662376 | O5: 22879440 | P5: 23088368 | Q5: 23282962 | R5: 23451871 | S5: 23599344 | T5: 23730415 | U5: 23849183 | V5: 23957398 | W5: 24060786 | X5: 24162250 | Y5: 24265116 | Z5: 24372251 | AA5: 24481279 | AB5: 24598419 | AC5: 24725310 | AD5: 24864708 | AE5: 25019347 | AF5: 25190708 | AG5: 25378714 | AH5: 25582259 | AI5: 25800024 | AJ5: 26030504 | AK5: 25873440
A6: cf_toe_0 | B6: 161.67129 | C6: 162.48434 | D6: 163.32959 | E6: 164.18437 | F6: 165.63541 | G6: 167.58128 | H6: 169.56723 | I6: 171.5623 | J6: 173.56859 | K6: 175.59334 | L6: 177.57237 | M6: 179.10563 | N6: 180.26138 | O6: 181.12219 | P6: 181.78549 | Q6: 182.34512 | R6: 183.10218 | S6: 184.10214 | T6: 185.37519 | U6: 186.935 | V6: 188.77153 | W6: 190.93663 | X6: 193.44915 | Y6: 196.32359 | Z6: 199.56238 | AA6: 203.0991 | AB6: 207.01424 | AC6: 211.32757 | AD6: 216.04077 | AE6: 221.11001 | AF6: 226.46738 | AG6: 232.0484 | AH6: 237.79782 | AI6: 243.66713 | AJ6: 249.61215 | AK6: 249.69174
A7: ch_toe_0 | B7: 64.30144 | C7: 63.918967 | D7: 63.418855 | E7: 62.924205 | F7: 62.662553 | G7: 62.563054 | H7: 62.419993 | I7: 62.262799 | J7: 62.114567 | K7: 61.987402 | L7: 61.912153 | M7: 61.844158 | N7: 61.7842 | O7: 61.727475 | P7: 61.667367 | Q7: 61.598101 | R7: 61.605481 | S7: 61.651598 | T7: 61.712691 | U7: 61.77448 | V7: 61.81372 | W7: 61.855549 | X7: 61.896441 | Y7: 61.937172 | Z7: 61.979932 | AA7: 61.981319 | AB7: 61.996067 | AC7: 62.026596 | AD7: 62.075989 | AE7: 62.14763 | AF7: 62.243795 | AG7: 62.364829 | AH7: 62.508047 | AI7: 62.670614 | AJ7: 62.849326 | AK7: 62.847629
A8: ch_hous_toe_0 | B8: 42520877 | C8: 42430148 | D8: 42062218 | E8: 41592799 | F8: 41267212 | G8: 41040156 | H8: 40735988 | I8: 40398640 | J8: 40056738 | K8: 39724820 | L8: 39434216 | M8: 39150841 | N8: 38881658 | O8: 38627262 | P8: 38385092 | Q8: 38151616 | R8: 38002211 | S8: 37895505 | T8: 37807749 | U8: 37725117 | V8: 37625847 | W8: 37531195 | X8: 37435700 | Y8: 37337550 | Z8: 37236556 | AA8: 37091897 | AB8: 36951358 | AC8: 36814796 | AD8: 36682562 | AE8: 36555655 | AF8: 36435197 | AG8: 36321733 | AH8: 36213874 | AI8: 36110907 | AJ8: 36012298 | AK8: 35948823
A9: ch_auto_toe_0 | B9: 21780563 | C9: 21488819 | D9: 21356636 | E9: 21331406 | F9: 21395341 | G9: 21522899 | H9: 21684005 | I9: 21864159 | J9: 22057829 | K9: 22262582 | L9: 22477938 | M9: 22693317 | N9: 22902541 | O9: 23100213 | P9: 23282275 | Q9: 23446485 | R9: 23603270 | S9: 23756093 | T9: 23904942 | U9: 24049362 | V9: 24187872 | W9: 24324354 | X9: 24460741 | Y9: 24599622 | Z9: 24743376 | AA9: 24889423 | AB9: 25044709 | AC9: 25211800 | AD9: 25393427 | AE9: 25591975 | AF9: 25808598 | AG9: 26043097 | AH9: 26294172 | AI9: 26559707 | AJ9: 26837029 | AK9: 26898806
A10: cf_toe_ccoa_2 | B10: 5.4022394 | C10: 5.4396922 | D10: 5.4824606 | E10: 5.5083347 | F10: 5.5728862 | G10: 5.6678206 | H10: 5.7829181 | I10: 5.6848474 | J10: 5.5553986 | K10: 5.4576232 | L10: 5.363122 | M10: 5.2816908 | N10: 5.2067183 | O10: 5.1385792 | P10: 5.080781 | Q10: 5.0346541 | R10: 4.9861466 | S10: 4.9410645 | T10: 4.9039075 | U10: 4.8771286 | V10: 4.8621694 | W10: 4.8603347 | X10: 4.8727397 | Y10: 4.8995991 | Z10: 4.9403501 | AA10: 4.9939533 | AB10: 5.0604542 | AC10: 5.1412895 | AD10: 5.2359515 | AE10: 5.3420895 | AF10: 5.4568268 | AG10: 5.5781788 | AH10: 5.7050194 | AI10: 5.836289 | AJ10: 5.9711287 | AK10: 5.9653748
A11: cf_toe_ccoa_0 | B11: 5.4022394 | C11: 5.4396922 | D11: 5.4824606 | E11: 5.5083347 | F11: 5.5728862 | G11: 5.6678206 | H11: 5.7752911 | I11: 5.8849698 | J11: 5.9949026 | K11: 6.1048828 | L11: 6.2081132 | M11: 6.2816362 | N11: 6.3327262 | O11: 6.3690864 | P11: 6.3982756 | Q11: 6.426452 | R11: 6.4688174 | S11: 6.5310955 | T11: 6.6152281 | U11: 6.7208846 | V11: 6.8472024 | W11: 6.9938203 | X11: 7.1610386 | Y11: 7.3488386 | Z11: 7.5564203 | AA11: 7.7824986 | AB11: 8.0275554 | AC11: 8.2927171 | AD11: 8.578086 | AE11: 8.8809252 | AF11: 9.1973285 | AG11: 9.5241858 | AH11: 9.8595176 | AI11: 10.201933 | AJ11: 10.550393 | AK11: 10.56326
A12: cf_toe_ccoi_2 | B12: 0.083932566 | C12: 0.084420682 | D12: 0.08495321 | E12: 0.085330164 | F12: 0.086253537 | G12: 0.087633551 | H12: 0.089184497 | I12: 0.088177003 | J12: 0.08670092 | K12: 0.085602653 | L12: 0.084592892 | M12: 0.083767434 | N12: 0.083005315 | O12: 0.082278454 | P12: 0.08161728 | Q12: 0.081039832 | R12: 0.080504239 | S12: 0.080037466 | T12: 0.07968324 | U12: 0.079474266 | V12: 0.079433924 | W12: 0.079593759 | X12: 0.079978354 | Y12: 0.080599223 | Z12: 0.081456248 | AA12: 0.08253577 | AB12: 0.08386099 | AC12: 0.085463578 | AD12: 0.087347535 | AE12: 0.089487406 | AF12: 0.091847321 | AG12: 0.094404726 | AH12: 0.097152407 | AI12: 0.10008723 | AJ12: 0.10321582 | AK12: 0.10012521
... A737: ci_toe_cfuel_ser_0 | B737: 2.8654882 | C737: 2.8967075 | D737: 2.9278608 | E737: 2.9597623 | F737: 2.9926616 | G737: 3.0265472 | H737: 3.0613249 | I737: 3.0968928 | J737: 3.1331649 | K737: 3.170076 | L737: 3.2075792 | M737: 3.2456425 | N737: 3.2842451 | O737: 3.3233755 | P737: 3.363028 | Q737: 3.4032016 | R737: 3.443898 | S737: 3.4851202 | T737: 3.5268716 | U737: 3.5691552 | V737: 3.6119734 | W737: 3.6553275 | X737: 3.6992182 | Y737: 3.7436452 | Z737: 3.7886078 | AA737: 3.8341054 | AB737: 3.8801368 | AC737: 3.9267016 | AD737: 3.9737996 | AE737: 4.021431 | AF737: 4.0695968 | AG737: 4.1182989 | AH737: 4.1675396 | AI737: 4.2173221 | AJ737: 4.2676504 | AK737: 4.3185291

Sheet Primary_nrj
A1: _date_ | B1: 42005 | C1: 42370 | D1: 42736 | E1: 43101 | F1: 43466 | G1: 43831 | H1: 44197 | I1: 44562 | J1: 44927 | K1: 45292 | L1: 45658 | M1: 46023 | N1: 46388 | O1: 46753 | P1: 47119 | Q1: 47484 | R1: 47849 | S1: 48214 | T1: 48580 | U1: 48945 | V1: 49310 | W1: 49675 | X1: 50041 | Y1: 50406 | Z1: 50771 | AA1: 51136 | AB1: 51502 | AC1: 51867 | AD1: 52232 | AE1: 52597 | AF1: 52963 | AG1: 53328 | AH1: 53693 | AI1: 54058 | AJ1: 54424 | AK1: 54789
A2: yg_toe_2 | B2: 148.54628 | C2: 150.14777 | D2: 151.75253 | E2: 153.4754 | F2: 155.40224 | G2: 157.55935 | H2: 159.89363 | I2: 163.18216 | J2: 166.81232 | K2: 171.32574 | L2: 176.02344 | M2: 180.29 | N2: 184.22153 | O2: 187.97407 | P2: 191.73341 | Q2: 195.61811 | R2: 199.51276 | S2: 203.69665 | T2: 208.25457 | U2: 213.26595 | V2: 218.79473 | W2: 224.97418 | X2: 231.91244 | Y2: 239.70668 | Z2: 248.44783 | AA2: 258.17025 | AB2: 269.1999 | AC2: 281.68852 | AD2: 295.83679 | AE2: 311.81769 | AF2: 329.82236 | AG2: 350.1323 | AH2: 373.14825 | AI2: 399.38505 | AJ2: 429.5259 | AK2: 429.2512
A3: yg_toe_0 | B3: 148.54628 | C3: 150.14777 | D3: 151.75253 | E3: 153.4754 | F3: 155.40224 | G3: 157.55935 | H3: 159.87419 | I3: 163.2944 | J3: 167.03981 | K3: 170.95188 | L3: 174.92633 | M3: 178.56651 | N3: 181.96261 | O3: 185.20357 | P3: 188.39616 | Q3: 191.64529 | R3: 195.06589 | S3: 198.78534 | T3: 202.90417 | U3: 207.49684 | V3: 212.61265 | W3: 218.36005 | X3: 224.82439 | Y3: 232.0908 | Z3: 240.24015 | AA3: 249.29568 | AB3: 259.44432 | AC3: 270.84413 | AD3: 283.65602 | AE3: 298.01362 | AF3: 314.05835 | AG3: 331.9875 | AH3: 352.08189 | AI3: 374.72712 | AJ3: 400.44855 | AK3: 400.54305
A4: yg_toe_ccoa_2 | B4: 2.368776 | C4: 2.385094 | D4: 2.4027634 | E4: 2.4149347 | F4: 2.4421573 | G4: 2.4815533 | H4: 2.5292711 | I4: 2.4801546 | J4: 2.4169915 | K4: 2.3669987 | L4: 2.3190959 | M4: 2.2771572 | N4: 2.2381086 | O4: 2.2016287 | P4: 2.1688263 | Q4: 2.1400415 | R4: 2.1083694 | S4: 2.0771717 | T4: 2.0483854 | U4: 2.0229242 | V4: 2.001319 | W4: 1.9838528 | X4: 1.9709075 | Y4: 1.9625919 | Z4: 1.9587373 | AA4: 1.9592583 | AB4: 1.9646132 | AC4: 1.9750711 | AD4: 1.9907779 | AE4: 2.0113464 | AF4: 2.036326 | AG4: 2.0657639 | AH4: 2.1002654 | AI4: 2.1408291 | AJ4: 2.1890789 | AK4: 2.1806688
A5: yg_toe_ccoa_0 | B5: 2.368776 | C5: 2.385094 | D5: 2.4027634 | E5: 2.4149347 | F5: 2.4421573 | G5: 2.4815533 | H5: 2.5256667 | I5: 2.5747357 | J5: 2.6229553 | K5: 2.6712552 | L5: 2.7174332 | M5: 2.7531927 | N5: 2.7812179 | O5: 2.8044216 | P5: 2.825557 | Q5: 2.8467882 | R5: 2.873896 | S5: 2.9089466 | T5: 2.9525421 | U5: 3.0044326 | V5: 3.0642776 | W5: 3.1318395 | X5: 3.2073383 | Y5: 3.2909372 | Z5: 3.3825362 | AA5: 3.4820695 | AB5: 3.5898961 | AC5: 3.7069108 | AD5: 3.8337148 | AE5: 3.969923 | AF5: 4.1148006 | AG5: 4.2680603 | AH5: 4.4300307 | AI5: 4.6015262 | AJ5: 4.7839329 | AK5: 4.8096422
A6: yg_toe_ccoi_2 | B6: 1.094611 | C6: 1.1047482 | D6: 1.1148985 | E6: 1.1259428 | F6: 1.1397053 | G6: 1.1562111 | H6: 1.1748026 | I6: 1.1705271 | J6: 1.163796 | K6: 1.1611479 | L6: 1.1586646 | M6: 1.1535752 | N6: 1.1458677 | O6: 1.1361593 | P6: 1.1253213 | Q6: 1.1138496 | R6: 1.1006727 | S6: 1.0870056 | T6: 1.0732936 | U6: 1.059743 | V6: 1.0464374 | W6: 1.0335444 | X6: 1.021182 | Y6: 1.0093598 | Z6: 0.997962 | AA6: 0.98673228 | AB6: 0.97616161 | AC6: 0.96599521 | AD6: 0.95610705 | AE6: 0.94614124 | AF6: 0.93563502 | AG6: 0.92420288 | AH6: 0.91155769 | AI6: 0.89743324 | AJ6: 0.88156973 | AK6: 0.87943366
A7: yg_toe_ccoi_0 | B7: 1.094611 | C7: 1.1047482 | D7: 1.1148985 | E7: 1.1259428 | F7: 1.1397053 | G7: 1.1562111 | H7: 1.1742719 | I7: 1.1931259 | J7: 1.2124433 | K7: 1.23206 | L7: 1.2512802 | M7: 1.2675692 | N7: 1.281305 | O7: 1.2931323 | P7: 1.3037405 | Q7: 1.3137349 | R7: 1.324187 | S7: 1.3358692 | T7: 1.3491733 | U7: 1.3642202 | V7: 1.3810027 | W7: 1.3996531 | X7: 1.4203093 | Y7: 1.4430627 | Z7: 1.4679074 | AA7: 1.4946539 | AB7: 1.5235227 | AC7: 1.5547271 | AD7: 1.5883453 | AE7: 1.6241405 | AF7: 1.6617072 | AG7: 1.7006834 | AH7: 1.7407953 | AI7: 1.7818192 | AJ7: 1.8235566 | AK7: 1.8321047
A8: yg_toe_cfut_2 | B8: 42.284658 | C8: 42.535731 | D8: 42.78126 | E8: 43.07496 | F8: 43.488757 | G8: 44.011258 | H8: 44.613824 | I8: 45.479486 | J8: 46.384982 | K8: 47.404292 | L8: 48.464478 | M8: 49.533757 | N8: 50.60035 | O8: 51.665295 | P8: 52.73876 | Q8: 53.827776 | R8: 54.914934 | S8: 56.017062 | T8: 57.152129 | U8: 58.335018 | V8: 59.576664 | W8: 60.89317 | X8: 62.298729 | Y8: 63.804613 | Z8: 65.419011 | AA8: 67.141983 | AB8: 68.991536 | AC8: 70.985314 | AD8: 73.1357 | AE8: 75.446896 | AF8: 77.918746 | AG8: 80.553645 | AH8: 83.358247 | AI8: 86.340891 | AJ8: 89.513246 | AK8: 89.519777
A9: yg_toe_cfut_0 | B9: 42.284658 | C9: 42.535731 | D9: 42.78126 | E9: 43.07496 | F9: 43.488757 | G9: 44.011258 | H9: 44.605255 | I9: 45.223909 | J9: 45.862792 | K9: 46.511954 | L9: 47.152998 | M9: 47.722831 | N9: 48.225714 | O9: 48.67121 | P9: 49.072406 | Q9: 49.442814 | R9: 49.810087 | S9: 50.199352 | T9: 50.623933 | U9: 51.089066 | V9: 51.595141 | W9: 52.147276 | X9: 52.749583 | Y9: 53.405017 | Z9: 54.114273 | AA9: 54.871031 | AB9: 55.681746 | AC9: 56.550798 | AD9: 57.479194 | AE9: 58.460349 | AF9: 59.483023 | AG9: 60.535477 | AH9: 61.606503 | AI9: 62.684481 | AJ9: 63.756729 | AK9: 63.777617
A10: yg_toe_cfuh_2 | B10: 7.9202674 | C10: 7.9744452 | D10: 8.0266828 | E10: 8.0763485 | F10: 8.1454076 | G10: 8.2304048 | H10: 8.324565 | I10: 8.0740696 | J10: 7.8135183 | K10: 7.5734992 | L10: 7.3396934 | M10: 7.1083552 | N10: 6.8746936 | O10: 6.6381212 | P10: 6.4002689 | Q10: 6.1621698 | R10: 5.9220172 | S10: 5.6823731 | T10: 5.4448028 | U10: 5.2098485 | V10: 4.9768599 | W10: 4.7468058 | X10: 4.5191695 | Y10: 4.2930622 | Z10: 4.0670941 | AA10: 3.8384003 | AB10: 3.6075975 | AC10: 3.3736618 | AD10: 3.1351931 | AE10: 2.8902574 | AF10: 2.6367728 | AG10: 2.372844 | AH10: 2.0967836 | AI10: 1.8069942 | AJ10: 1.5018784 | AK10: 1.1472168
A11: yg_toe_cfuh_0 | B11: 7.9202674 | C11: 7.9744452 | D11: 8.0266828 | E11: 8.0763485 | F11: 8.1454076 | G11: 8.2304048 | H11: 8.3180078 | I11: 8.4033936 | J11: 8.4871077 | K11: 8.5705196 | L11: 8.652601 | M11: 8.7176307 | N11: 8.7681075 | O11: 8.8071516 | P11: 8.8383494 | Q11: 8.8651582 | R11: 8.8987418 | S11: 8.9434991 | T11: 9.0002405 | U11: 9.068743 | V11: 9.1476879 | W11: 9.2391145 | X11: 9.3434392 | Y11: 9.4611517 | Z11: 9.5923642 | AA11: 9.7335333 | AB11: 9.8890152 | AC11: 10.0598 | AD11: 10.246214 | AE11: 10.446903 | AF11: 10.659533 | AG11: 10.881856 | AH11: 11.111771 | AI11: 11.34751 | AJ11: 11.587534 | AK11: 11.606002
A12: yg_toe_cgas_2 | B12: 6.6402813 | C12: 6.5233019 | D12: 6.4188993 | E12: 6.3133354 | F12: 6.2472884 | G12: 6.187402 | H12: 6.1156496 | I12: 5.8882664 | J12: 5.7255146 | K12: 5.5700455 | L12: 5.4481956 | M12: 5.3877509 | N12: 5.3575764 | O12: 5.3392895 | P12: 5.3206826 | Q12: 5.2961316 | R12: 5.2570335 | S12: 5.2101796 | T12: 5.1557892 | U12: 5.0924636 | V12: 5.0165802 | W12: 4.9285357 | X12: 4.822677 | Y12: 4.6960539 | Z12: 4.5475308 | AA12: 4.3722168 | AB12: 4.1733798 | AC12: 3.9470873 | AD12: 3.6915054 | AE12: 3.4068321 | AF12: 3.093579 | AG12: 2.7506087 | AH12: 2.374823 | AI12: 1.9617561 | AJ12: 1.5047849 | AK12: 1.5020041
... A73: yg_toe_cote_spub_0 | B73: 1.2270759 | C73: 1.256376 | D73: 1.2875134 | E73: 1.3197248 | F73: 1.3542471 | G73: 1.3912389 | H73: 1.4303698 | I73: 1.4721549 | J73: 1.5152312 | K73: 1.5591775 | L73: 1.6017386 | M73: 1.6359412 | N73: 1.6645415 | O73: 1.6895063 | P73: 1.7127625 | Q73: 1.7358651 | R73: 1.7603209 | S73: 1.7878672 | T73: 1.8194791 | U73: 1.8555115 | V73: 1.8961696 | W73: 1.941768 | X73: 1.9927563 | Y73: 2.0493824 | Z73: 2.111598 | AA73: 2.1792551 | AB73: 2.2528346 | AC73: 2.3330191 | AD73: 2.4201139 | AE73: 2.5135631 | AF73: 2.6125489 | AG73: 2.7166192 | AH73: 2.825751 | AI73: 2.9401906 | AJ73: 3.0604408 | AK73: 3.0615649

Sheet Energy_Mix
A1: _date_ | B1: 42005 | C1: 42370 | D1: 42736 | E1: 43101 | F1: 43466 | G1: 43831 | H1: 44197 | I1: 44562 | J1: 44927 | K1: 45292 | L1: 45658 | M1: 46023 | N1: 46388 | O1: 46753 | P1: 47119 | Q1: 47484 | R1: 47849 | S1: 48214 | T1: 48580 | U1: 48945 | V1: 49310 | W1: 49675 | X1: 50041 | Y1: 50406 | Z1: 50771 | AA1: 51136 | AB1: 51502 | AC1: 51867 | AD1: 52232 | AE1: 52597 | AF1: 52963 | AG1: 53328 | AH1: 53693 | AI1: 54058 | AJ1: 54424 | AK1: 54789
A2: phiy_ccoa_smin_2 | B2: 0.20069089 | C2: 0.20069089 | D2: 0.20069089 | E2: 0.20069089 | F2: 0.20069089 | G2: 0.20069089 | H2: 0.20069089 | I2: 0.20069089 | J2: 0.20069089 | K2: 0.20069089 | L2: 0.20069089 | M2: 0.20069089 | N2: 0.20069089 | O2: 0.20069089 | P2: 0.20069089 | Q2: 0.20069089 | R2: 0.20069089 | S2: 0.20069089 | T2: 0.20069089 | U2: 0.20069089 | V2: 0.20069089 | W2: 0.20069089 | X2: 0.20069089 | Y2: 0.20069089 | Z2: 0.20069089 | AA2: 0.20069089 | AB2: 0.20069089 | AC2: 0.20069089 | AD2: 0.20069089 | AE2: 0.20069089 | AF2: 0.20069089 | AG2: 0.20069089 | AH2: 0.20069089 | AI2: 0.20069089 | AJ2: 0.20069089 | AK2: 0.20069089
A3: phiy_ccoa_soil_2 | B3: 0.79930911 | C3: 0.79930911 | D3: 0.79930911 | E3: 0.79930911 | F3: 0.79930911 | G3: 0.79930911 | H3: 0.79930911 | I3: 0.79930911 | J3: 0.79930911 | K3: 0.79930911 | L3: 0.79930911 | M3: 0.79930911 | N3: 0.79930911 | O3: 0.79930911 | P3: 0.79930911 | Q3: 0.79930911 | R3: 0.79930911 | S3: 0.79930911 | T3: 0.79930911 | U3: 0.79930911 | V3: 0.79930911 | W3: 0.79930911 | X3: 0.79930911 | Y3: 0.79930911 | Z3: 0.79930911 | AA3: 0.79930911 | AB3: 0.79930911 | AC3: 0.79930911 | AD3: 0.79930911 | AE3: 0.79930911 | AF3: 0.79930911 | AG3: 0.79930911 | AH3: 0.79930911 | AI3: 0.79930911 | AJ3: 0.79930911 | AK3: 0.79930911
A4: phiy_ccoi_smin_2 | B4: 0.7836667 | C4: 0.7836667 | D4: 0.7836667 | E4: 0.7836667 | F4: 0.7836667 | G4: 0.7836667 | H4: 0.7836667 | I4: 0.7836667 | J4: 0.7836667 | K4: 0.7836667 | L4: 0.7836667 | M4: 0.7836667 | N4: 0.7836667 | O4: 0.7836667 | P4: 0.7836667 | Q4: 0.7836667 | R4: 0.7836667 | S4: 0.7836667 | T4: 0.7836667 | U4: 0.7836667 | V4: 0.7836667 | W4: 0.7836667 | X4: 0.7836667 | Y4: 0.7836667 | Z4: 0.7836667 | AA4: 0.7836667 | AB4: 0.7836667 | AC4: 0.7836667 | AD4: 0.7836667 | AE4: 0.7836667 | AF4: 0.7836667 | AG4: 0.7836667 | AH4: 0.7836667 | AI4: 0.7836667 | AJ4: 0.7836667 | AK4: 0.7836667
A5: phiy_ccoi_soil_2 | B5: 0.2163333 | C5: 0.2163333 | D5: 0.2163333 | E5: 0.2163333 | F5: 0.2163333 | G5: 0.2163333 | H5: 0.2163333 | I5: 0.2163333 | J5: 0.2163333 | K5: 0.2163333 | L5: 0.2163333 | M5: 0.2163333 | N5: 0.2163333 | O5: 0.2163333 | P5: 0.2163333 | Q5: 0.2163333 | R5: 0.2163333 | S5: 0.2163333 | T5: 0.2163333 | U5: 0.2163333 | V5: 0.2163333 | W5: 0.2163333 | X5: 0.2163333 | Y5: 0.2163333 | Z5: 0.2163333 | AA5: 0.2163333 | AB5: 0.2163333 | AC5: 0.2163333 | AD5: 0.2163333 | AE5: 0.2163333 | AF5: 0.2163333 | AG5: 0.2163333 | AH5: 0.2163333 | AI5: 0.2163333 | AJ5: 0.2163333 | AK5: 0.2163333
A6: phiy_cfut_soil_2 | B6: 0.83809636 | C6: 0.83809636 | D6: 0.83809636 | E6: 0.83809636 | F6: 0.83809636 | G6: 0.83809636 | H6: 0.83809636 | I6: 0.80802017 | J6: 0.77827706 | K6: 0.74886151 | L6: 0.71976816 | M6: 0.69099173 | N6: 0.66252707 | O6: 0.63436915 | P6: 0.60651303 | Q6: 0.57895389 | R6: 0.551687 | S6: 0.52470774 | T6: 0.49801158 | U6: 0.47159409 | V6: 0.44545093 | W6: 0.41957784 | X6: 0.39397067 | Y6: 0.36862533 | Z6: 0.34353784 | AA6: 0.31870426 | AB6: 0.29412078 | AC6: 0.26978363 | AD6: 0.24568912 | AE6: 0.22183365 | AF6: 0.19821367 | AG6: 0.17482572 | AH6: 0.15166639 | AI6: 0.12873235 | AJ6: 0.10602033 | AK6: 0.083527115
A7: phiy_cfut_sbfu_2 | B7: 0.16190364 | C7: 0.16190364 | D7: 0.16190364 | E7: 0.16190364 | F7: 0.16190364 | G7: 0.16190364 | H7: 0.16190364 | I7: 0.19197983 | J7: 0.22172294 | K7: 0.25113849 | L7: 0.28023184 | M7: 0.30900827 | N7: 0.33747293 | O7: 0.36563085 | P7: 0.39348697 | Q7: 0.42104611 | R7: 0.448313 | S7: 0.47529226 | T7: 0.50198842 | U7: 0.52840591 | V7: 0.55454907 | W7: 0.58042216 | X7: 0.60602933 | Y7: 0.63137466 | Z7: 0.65646216 | AA7: 0.68129574 | AB7: 0.70587922 | AC7: 0.73021637 | AD7: 0.75431088 | AE7: 0.77816635 | AF7: 0.80178633 | AG7: 0.82517428 | AH7: 0.84833361 | AI7: 0.87126765 | AJ7: 0.89397967 | AK7: 0.91647289
A8: phiy_cfuh_soil_2 | B8: 1 | C8: 1 | D8: 1 | E8: 1 | F8: 1 | G8: 1 | H8: 1 | I8: 1 | J8: 1 | K8: 1 | L8: 1 | M8: 1 | N8: 1 | O8: 1 | P8: 1 | Q8: 1 | R8: 1 | S8: 1 | T8: 1 | U8: 1 | V8: 1 | W8: 1 | X8: 1 | Y8: 1 | Z8: 1 | AA8: 1 | AB8: 1 | AC8: 1 | AD8: 1 | AE8: 1 | AF8: 1 | AG8: 1 | AH8: 1 | AI8: 1 | AJ8: 1 | AK8: 1
A9: phiy_cgas_smet_2 | B9: 8.2704787e-05 | C9: 8.2704787e-05 | D9: 8.2704787e-05 | E9: 8.2704787e-05 | F9: 8.2704787e-05 | G9: 8.2704787e-05 | H9: 8.2704787e-05 | I9: 7.9265398e-05 | J9: 7.5876565e-05 | K9: 7.2537182e-05 | L9: 6.9246174e-05 | M9: 6.6002498e-05 | N9: 6.2805141e-05 | O9: 5.9653116e-05 | P9: 5.6545467e-05 | Q9: 5.3481263e-05 | R9: 5.04596e-05 | S9: 4.7479596e-05 | T9: 4.4540398e-05 | U9: 4.1641173e-05 | V9: 3.878111e-05 | W9: 3.5959421e-05 | X9: 3.317534e-05 | Y9: 3.0428119e-05 | Z9: 2.7717031e-05 | AA9: 2.5041368e-05 | AB9: 2.240044e-05 | AC9: 1.9793575e-05 | AD9: 1.7220119e-05 | AE9: 1.4679432e-05 | AF9: 1.2170894e-05 | AG9: 9.693898e-06 | AH9: 7.2478523e-06 | AI9: 4.8321807e-06 | AJ9: 2.4463211e-06 | AK9: 8.9724848e-08
A10: phiy_cgas_soil_2 | B10: 0.64531662 | C10: 0.64531662 | D10: 0.64531662 | E10: 0.64531662 | F10: 0.64531662 | G10: 0.64531662 | H10: 0.64531662 | I10: 0.61961611 | J10: 0.59429337 | K10: 0.56934014 | L10: 0.54474839 | M10: 0.52051033 | N10: 0.49661837 | O10: 0.47306516 | P10: 0.44984354 | Q10: 0.42694656 | R10: 0.40436746 | S10: 0.38209967 | T10: 0.36013679 | U10: 0.33847259 | V10: 0.31710104 | W10: 0.29601623 | X10: 0.27521244 | Y10: 0.25468409 | Z10: 0.23442574 | AA10: 0.2144321 | AB10: 0.19469801 | AC10: 0.17521846 | AD10: 0.15598854 | AE10: 0.1370035 | AF10: 0.11825868 | AG10: 0.099749558 | AH10: 0.08147171 | AI10: 0.063420829 | AJ10: 0.045592715 | AK10: 0.027983269
A11: phiy_cgas_sgas_2 | B11: 0.14751433 | C11: 0.14751433 | D11: 0.14751433 | E11: 0.14751433 | F11: 0.14751433 | G11: 0.14751433 | H11: 0.14751433 | I11: 0.14137727 | J11: 0.13533043 | K11: 0.12937182 | L11: 0.12349953 | M11: 0.11771169 | N11: 0.1120065 | O11: 0.1063822 | P11: 0.10083709 | Q11: 0.095369489 | R11: 0.089977799 | S11: 0.084660446 | T11: 0.079415904 | U11: 0.074242686 | V11: 0.069139347 | W11: 0.064104482 | X11: 0.059136721 | Y11: 0.054234731 | Z11: 0.049397216 | AA11: 0.044622911 | AB11: 0.039910585 | AC11: 0.035259039 | AD11: 0.030667106 | AE11: 0.026133645 | AF11: 0.021657548 | AG11: 0.017237733 | AH11: 0.012873144 | AI11: 0.0085627532 | AJ11: 0.004305557 | AK11: 0.00010057686
A12: phiy_cgas_sbga_2 | B12: 0.20708634 | C12: 0.20708634 | D12: 0.20708634 | E12: 0.20708634 | F12: 0.20708634 | G12: 0.20708634 | H12: 0.20708634 | I12: 0.23892735 | J12: 0.27030033 | K12: 0.30121551 | L12: 0.33168284 | M12: 0.36171198 | N12: 0.39131232 | O12: 0.42049299 | P12: 0.44926283 | Q12: 0.47763047 | R12: 0.50560428 | S12: 0.53319241 | T12: 0.56040277 | U12: 0.58724308 | V12: 0.61372083 | W12: 0.63984333 | X12: 0.66561766 | Y12: 0.69105075 | Z12: 0.71614933 | AA12: 0.74091995 | AB12: 0.76536901 | AC12: 0.78950271 | AD12: 0.81332713 | AE12: 0.83684818 | AF12: 0.8600716 | AG12: 0.88300302 | AH12: 0.9056479 | AI12: 0.92801159 | AJ12: 0.95009928 | AK12: 0.97191606
... A51: phiy_cote_spub_0 | B51: 0.00010273909 | C51: 0.00010273909 | D51: 0.00010273909 | E51: 0.00010273909 | F51: 0.00010273909 | G51: 0.00010273909 | H51: 0.00010273909 | I51: 0.00010273909 | J51: 0.00010273909 | K51: 0.00010273909 | L51: 0.00010273909 | M51: 0.00010273909 | N51: 0.00010273909 | O51: 0.00010273909 | P51: 0.00010273909 | Q51: 0.00010273909 | R51: 0.00010273909 | S51: 0.00010273909 | T51: 0.00010273909 | U51: 0.00010273909 | V51: 0.00010273909 | W51: 0.00010273909 | X51: 0.00010273909 | Y51: 0.00010273909 | Z51: 0.00010273909 | AA51: 0.00010273909 | AB51: 0.00010273909 | AC51: 0.00010273909 | AD51: 0.00010273909 | AE51: 0.00010273909 | AF51: 0.00010273909 | AG51: 0.00010273909 | AH51: 0.00010273909 | AI51: 0.00010273909 | AJ51: 0.00010273909 | AK51: 0.00010273909

Sheet Transports
A1: _date_ | B1: 42005 | C1: 42370 | D1: 42736 | E1: 43101 | F1: 43466 | G1: 43831 | H1: 44197 | I1: 44562 | J1: 44927 | K1: 45292 | L1: 45658 | M1: 46023 | N1: 46388 | O1: 46753 | P1: 47119 | Q1: 47484 | R1: 47849 | S1: 48214 | T1: 48580 | U1: 48945 | V1: 49310 | W1: 49675 | X1: 50041 | Y1: 50406 | Z1: 50771 | AA1: 51136 | AB1: 51502 | AC1: 51867 | AD1: 52232 | AE1: 52597 | AF1: 52963 | AG1: 53328 | AH1: 53693 | AI1: 54058 | AJ1: 54424 | AK1: 54789
A2: km_traveler_cair_2 | B2: 291099.78 | C2: 297847.09 | D2: 306012.36 | E2: 315024.54 | F2: 325498.68 | G2: 337351.56 | H2: 349973.32 | I2: 355868.02 | J2: 361027.45 | K2: 367477.31 | L2: 375294.64 | M2: 385048.74 | N2: 396818.59 | O2: 409128.11 | P2: 421322.12 | Q2: 433166.89 | R2: 443718.84 | S2: 452930.16 | T2: 461654.54 | U2: 470346.02 | V2: 479034.76 | W2: 488386.72 | X2: 498371.06 | Y2: 509402.18 | Z2: 521710 | AA2: 534654.99 | AB2: 549078.98 | AC2: 564487.75 | AD2: 581607.07 | AE2: 600824.78 | AF2: 622280.6 | AG2: 645734.57 | AH2: 670951.21 | AI2: 698076.45 | AJ2: 727141.66 | AK2: 727140.09
A3: km_trav_auto_ld_2+km_trav_auto_sd_2 | B3: 724102.94 | C3: 715177.19 | D3: 711607.93 | E3: 711644.69 | F3: 714702.09 | G3: 719921.78 | H3: 726525.58 | I3: 731791.17 | J3: 737088.14 | K3: 743073.91 | L3: 749923.66 | M3: 758054.27 | N3: 766959.36 | O3: 776096.2 | P3: 785084.57 | Q3: 793700.58 | R3: 801545.95 | S3: 808772.31 | T3: 815557.15 | U3: 822045.76 | V3: 828301.99 | W3: 834531.18 | X3: 840841.75 | Y3: 847358.95 | Z3: 854193.84 | AA3: 861271.4 | AB3: 868826.37 | AC3: 876932.88 | AD3: 885707.34 | AE3: 895267.32 | AF3: 905686.15 | AG3: 916980.63 | AH3: 929129.66 | AI3: 942103.74 | AJ3: 955865.66 | AK3: 955869.5
A4: km_traveler_sd_2 | B4: 624600.34 | C4: 618848.47 | D4: 616815.18 | E4: 617320.37 | F4: 619952.58 | G4: 624138.44 | H4: 629301.63 | I4: 633521.76 | J4: 637674.93 | K4: 642344.44 | L4: 647651.36 | M4: 653820.58 | N4: 660515.79 | O4: 667329.87 | P4: 673989.2 | Q4: 680340.44 | R4: 686124.74 | S4: 691445.94 | T4: 696444.97 | U4: 701234.81 | V4: 705858.55 | W4: 710485.91 | X4: 715188.92 | Y4: 720060.31 | Z4: 725179.6 | AA4: 730467.49 | AB4: 736128.9 | AC4: 742201.39 | AD4: 748768.37 | AE4: 755909.43 | AF4: 763668.7 | AG4: 772048.55 | AH4: 781024.96 | AI4: 790568.91 | AJ4: 800646.04 | AK4: 800647.43
A5: km_trav_auto_sd_2 | B5: 554271.64 | C5: 547742.24 | D5: 545015.86 | E5: 544850 | F5: 546830.78 | G5: 550340.85 | H5: 554829.6 | I5: 558365.01 | J5: 561922.23 | K5: 565940.81 | L5: 570547.37 | M5: 576063.31 | N5: 582125.73 | O5: 588358.42 | P5: 594495.1 | Q5: 600377.62 | R5: 605722.13 | S5: 610636.4 | T5: 615240.93 | U5: 619634.85 | V5: 623864.9 | W5: 628064.56 | X5: 632310.8 | Y5: 636687.69 | Z5: 641270.69 | AA5: 646017.73 | AB5: 651074.44 | AC5: 656495.95 | AD5: 662357.87 | AE5: 668738.08 | AF5: 675685.74 | AG5: 683212.39 | AH5: 691303.42 | AI5: 699937.41 | AJ5: 709088.08 | AK5: 709089.87
A6: km_traveler_croa_2 | B6: 70328.7 | C6: 70404.734 | D6: 70674.379 | E6: 71077.65 | F6: 71579.52 | G6: 72170.25 | H6: 72805.336 | I6: 73404.263 | J6: 73947.703 | K6: 74547.482 | L6: 75205.443 | M6: 75872.282 | N6: 76549.93 | O6: 77202.678 | P6: 77814.91 | Q6: 78383.143 | R6: 78910.044 | S6: 79397.45 | T6: 79863.408 | U6: 80320.828 | V6: 80769.441 | W6: 81237.694 | X6: 81726.137 | Y6: 82244.068 | Z6: 82797.653 | AA6: 83362.328 | AB6: 83981.085 | AC6: 84646.123 | AD6: 85365.962 | AE6: 86145.609 | AF6: 86984.625 | AG6: 87878.264 | AH6: 88820.388 | AI6: 89805.708 | AJ6: 90828.496 | AK6: 90828.357
A7: km_traveler_ld_2 | B7: 275159.81 | C7: 270729.89 | D7: 269008.92 | E7: 269098.08 | F7: 270701.12 | G7: 273386.32 | H7: 276770.78 | I7: 279488.31 | J7: 282252.94 | K7: 285386.62 | L7: 288975.54 | M7: 293222.93 | N7: 297871.14 | O7: 302645.46 | P7: 307352.37 | Q7: 311876.57 | R7: 316010.86 | S7: 319832.59 | T7: 323431.76 | U7: 326882.37 | V7: 330215.56 | W7: 333540.43 | X7: 336913.28 | Y7: 340401.3 | Z7: 344064.11 | AA7: 347860.22 | AB7: 351918.92 | AC7: 356280.34 | AD7: 361011 | AE7: 366178.24 | AF7: 371825.59 | AG7: 377965.93 | AH7: 384592.04 | AI7: 391692.91 | AJ7: 399253.04 | AK7: 399254.91
A8: km_trav_auto_ld_2 | B8: 169831.3 | C8: 167434.95 | D8: 166592.08 | E8: 166794.69 | F8: 167871.32 | G8: 169580.92 | H8: 171695.98 | I8: 173426.16 | J8: 175165.91 | K8: 177133.11 | L8: 179376.29 | M8: 181990.96 | N8: 184833.63 | O8: 187737.78 | P8: 190589.47 | Q8: 193322.96 | R8: 195823.82 | S8: 198135.91 | T8: 200316.23 | U8: 202410.91 | V8: 204437.09 | W8: 206466.62 | X8: 208530.95 | Y8: 210671.25 | Z8: 212923.16 | AA8: 215253.67 | AB8: 217751.93 | AC8: 220436.93 | AD8: 223349.46 | AE8: 226529.24 | AF8: 230000.41 | AG8: 233768.24 | AH8: 237826.24 | AI8: 242166.33 | AJ8: 246777.58 | AK8: 246779.63
A9: km_traveler_crai_2 | B9: 105328.51 | C9: 106821.64 | D9: 108362.76 | E9: 109938.07 | F9: 111483.87 | G9: 113073.69 | H9: 114645.81 | I9: 116260.66 | J9: 117680.39 | K9: 119237.67 | L9: 120912.43 | M9: 122444.38 | N9: 123912.86 | O9: 125251.86 | P9: 126453.51 | Q9: 127536.07 | R9: 128565.67 | S9: 129526.89 | T9: 130467.47 | U9: 131418.44 | V9: 132368.63 | W9: 133404.88 | X9: 134513.85 | Y9: 135717.3 | Z9: 137025.73 | AA9: 138348.31 | AB9: 139828.89 | AC9: 141424.25 | AD9: 143157.3 | AE9: 145034.99 | AF9: 147047.22 | AG9: 149172.49 | AH9: 151388.97 | AI9: 153681.17 | AJ9: 156032.04 | AK9: 156041.5
A10: km_traveler_cair_0 | B10: 291099.78 | C10: 297847.09 | D10: 306012.36 | E10: 315024.54 | F10: 325498.67 | G10: 337351.55 | H10: 349705.53 | I10: 362686.01 | J10: 376281.97 | K10: 390500.33 | L10: 405499.21 | M10: 419842.83 | N10: 433517.05 | O10: 446271.81 | P10: 457998.29 | Q10: 468748.14 | R10: 479125.79 | S10: 489221.32 | T10: 499170.48 | U10: 509140.72 | V10: 519024.14 | W10: 529656.25 | X10: 540989.85 | Y10: 553264.07 | Z10: 566627.14 | AA10: 580316.81 | AB10: 595858.71 | AC10: 613017.06 | AD10: 632062.57 | AE10: 653219.24 | AF10: 676538.82 | AG10: 701971.93 | AH10: 729410.68 | AI10: 758705.15 | AJ10: 789676.78 | AK10: 789675.22
A11: km_trav_auto_ld_0+km_trav_auto_sd_0 | B11: 724102.94 | C11: 715177.19 | D11: 711607.93 | E11: 711644.69 | F11: 714702.09 | G11: 719921.78 | H11: 726292.53 | I11: 733329.2 | J11: 740849.87 | K11: 748776.35 | L11: 757095.4 | M11: 765449.28 | N11: 773625.32 | O11: 781435.93 | P11: 788738.86 | Q11: 795454.62 | R11: 801936.56 | S11: 808298.81 | T11: 814537.47 | U11: 820635.85 | V11: 826544.46 | W11: 832399.92 | X11: 838274.33 | Y11: 844263.79 | Z11: 850458.79 | AA11: 856780 | AB11: 863477.61 | AC11: 870652.55 | AD11: 878411.91 | AE11: 886851.21 | AF11: 896023.32 | AG11: 905933.72 | AH11: 916549.14 | AI11: 927807.12 | AJ11: 939625.14 | AK11: 939629.73
A12: km_traveler_sd_0 | B12: 624600.34 | C12: 618848.47 | D12: 616815.18 | E12: 617320.37 | F12: 619952.58 | G12: 624138.44 | H12: 629119.94 | I12: 634558.23 | J12: 640323.2 | K12: 646361.58 | L12: 652672.33 | M12: 658948.23 | N12: 665044.59 | O12: 670827.25 | P12: 676201.26 | Q12: 681121.06 | R12: 685868.41 | S12: 690533.59 | T12: 695119.41 | U12: 699618.39 | V12: 703989.59 | W12: 708353.56 | X12: 712754.36 | Y12: 717262.58 | Z12: 721942.09 | AA12: 726708.65 | AB12: 731780.02 | AC12: 737210.84 | AD12: 743076.04 | AE12: 749438.91 | AF12: 756329.22 | AG12: 763742.04 | AH12: 771645.28 | AI12: 779986.85 | AJ12: 788701.49 | AK12: 788703.15
... A17: km_traveler_crai_0 | B17: 105328.51 | C17: 106821.64 | D17: 108362.76 | E17: 109938.07 | F17: 111483.87 | G17: 113073.69 | H17: 114592.37 | I17: 116085.56 | J17: 117560.63 | K17: 119029.01 | L17: 120522.05 | M17: 121853.75 | N17: 123045.41 | O17: 124088.35 | P17: 124994.49 | Q17: 125790.79 | R17: 126579.74 | S17: 127382.23 | T17: 128213.59 | U17: 129087.21 | V17: 129981.97 | W17: 130982.38 | X17: 132070.29 | Y17: 133260.73 | Z17: 134560.07 | AA17: 135874.79 | AB17: 137356.25 | AC17: 138961.32 | AD17: 140700.87 | AE17: 142575.85 | AF17: 144573.4 | AG17: 146673.77 | AH17: 148854.9 | AI17: 151094.16 | AJ17: 153369.52 | AK17: 153381.01

Sheet Hybrid
A1: _date_ | B1: 42005 | C1: 42370 | D1: 42736 | E1: 43101 | F1: 43466 | G1: 43831 | H1: 44197 | I1: 44562 | J1: 44927 | K1: 45292 | L1: 45658 | M1: 46023 | N1: 46388 | O1: 46753 | P1: 47119 | Q1: 47484 | R1: 47849 | S1: 48214 | T1: 48580 | U1: 48945 | V1: 49310 | W1: 49675 | X1: 50041 | Y1: 50406 | Z1: 50771 | AA1: 51136 | AB1: 51502 | AC1: 51867 | AD1: 52232 | AE1: 52597 | AF1: 52963 | AG1: 53328 | AH1: 53693 | AI1: 54058 | AJ1: 54424 | AK1: 54789
A2: auto_2 | B2: 32317.941 | C2: 31918.631 | D2: 31759.311 | E2: 31761.553 | F2: 31899.124 | G2: 32133.592 | H2: 32430.086 | I2: 32666.633 | J2: 32904.587 | K2: 33173.488 | L2: 33481.177 | M2: 33846.254 | N2: 34246.04 | O2: 34656.192 | P2: 35059.663 | Q2: 35446.419 | R2: 35798.619 | S2: 36123.057 | T2: 36427.702 | U2: 36719.075 | V2: 37000.033 | W2: 37279.814 | X2: 37563.277 | Y2: 37856.046 | Z2: 38163.111 | AA2: 38481.072 | AB2: 38820.515 | AC2: 39184.751 | AD2: 39579.018 | AE2: 40008.603 | AF2: 40476.798 | AG2: 40984.357 | AH2: 41530.335 | AI2: 42113.41 | AJ2: 42731.916 | AK2: 42732.091
A3: auto_cfut_2 | B3: 32271.24 | C3: 31853.75 | D3: 31674.362 | E3: 31654.909 | F3: 31769.037 | G3: 31978.673 | H3: 32249.27 | I3: 32459.098 | J3: 32665.007 | K3: 32892.46 | L3: 33144.696 | M3: 33436.655 | N3: 33745.972 | O3: 34049.03 | P3: 34329.52 | Q3: 34578.008 | R3: 34777.39 | S3: 34933.396 | T3: 35053.015 | U3: 35141.93 | V3: 35202.462 | W3: 35242.682 | X3: 35266.539 | Y3: 35278.534 | Z3: 35282.438 | AA3: 35274.612 | AB3: 35263.396 | AC3: 35250.565 | AD3: 35239.286 | AE3: 35232.494 | AF3: 35231.235 | AG3: 35234.312 | AH3: 35239.084 | AI3: 35242.58 | AJ3: 35241.566 | AK3: 35009.221
A4: auto_cele_2 | B4: 44.765 | C4: 62.889352 | D4: 82.889294 | E4: 104.50723 | F4: 127.86793 | G4: 152.61341 | H4: 178.42191 | I4: 205.06274 | J4: 237.03271 | K4: 278.40746 | L4: 333.78759 | M4: 406.83242 | N4: 497.23021 | O4: 604.255 | P4: 727.17196 | Q4: 865.38025 | R4: 1018.1453 | S4: 1186.5291 | T4: 1371.5117 | U4: 1573.932 | V4: 1794.3247 | W4: 2033.8552 | X4: 2293.433 | Y4: 2574.1819 | Z4: 2877.3198 | AA4: 3203.0866 | AB4: 3553.7263 | AC4: 3930.7766 | AD4: 4336.3066 | AE4: 4772.6663 | AF4: 5242.1059 | AG4: 5746.5731 | AH4: 6287.7656 | AI4: 6867.3323 | AJ4: 7486.8407 | AK4: 8081.4317
A5: auto_cgas_2 | B5: 1.936 | C5: 1.9909099 | D5: 2.0596615 | E5: 2.1363797 | F5: 2.2193981 | G5: 2.3059977 | H5: 2.3936768 | I5: 2.4725398 | J5: 2.5475164 | K5: 2.6209632 | L5: 2.6933886 | M5: 2.7662736 | N5: 2.8379704 | O5: 2.9066826 | P5: 2.9711856 | Q5: 3.0308025 | R5: 3.0841924 | S5: 3.131905 | T5: 3.1745985 | U5: 3.2128262 | V5: 3.2468616 | W5: 3.277459 | X5: 3.3050324 | Y5: 3.330042 | Z5: 3.352887 | AA5: 3.3733444 | AB5: 3.3921872 | AC5: 3.4096432 | AD5: 3.4260549 | AE5: 3.441744 | AF5: 3.4568729 | AG5: 3.4714124 | AH5: 3.4852056 | AI5: 3.4980608 | AJ5: 3.5097564 | AK5: 3.5012802
A6: newauto_2 | B6: 1886.229 | C6: 2113.9817 | D6: 2322.2115 | E6: 2470.6168 | F6: 2605.3024 | G6: 2712.0199 | H6: 2791.3552 | I6: 2753.5043 | J6: 2772.311 | K6: 2820.5657 | L6: 2878.7136 | M6: 2957.9499 | N6: 3018.3071 | O6: 3056.364 | P6: 3077.553 | Q6: 3087.5866 | R6: 3077.9003 | S6: 3071.7681 | T6: 3070.8538 | U6: 3074.293 | V6: 3078.8972 | W6: 3091.2482 | X6: 3107.6426 | Y6: 3129.1912 | Z6: 3155.6509 | AA6: 3178.9792 | AB6: 3212.8825 | AC6: 3250.8304 | AD6: 3294.9464 | AE6: 3345.6074 | AF6: 3401.1451 | AG6: 3459.19 | AH6: 3518.0276 | AI6: 3577.1449 | AJ6: 3636.0311 | AK6: 3042.4024
A7: newauto_cfut_2 | B7: 1868.6748 | C7: 2093.8909 | D7: 2299.5028 | E7: 2445.4778 | F7: 2577.5448 | G7: 2681.9344 | H7: 2759.2104 | I7: 2719.4982 | J7: 2731.909 | K7: 2769.477 | L7: 2811.9609 | M7: 2871.3124 | N7: 2911.3915 | O7: 2929.2039 | P7: 2930.2196 | Q7: 2920.0461 | R7: 2890.2772 | S7: 2862.418 | T7: 2838.1716 | U7: 2816.7756 | V7: 2795.3124 | W7: 2779.711 | X7: 2766.4783 | Y7: 2756.4734 | Z7: 2749.3147 | AA7: 2737.8895 | AB7: 2733.8897 | AC7: 2731.4016 | AD7: 2731.9558 | AE7: 2735.5656 | AF7: 2740.5686 | AG7: 2744.8081 | AH7: 2746.7414 | AI7: 2745.8369 | AJ7: 2741.599 | AK7: 2510.1899
A8: newauto_cele_2 | B8: 17.397214 | C8: 19.914952 | D8: 22.515516 | E8: 24.933506 | F8: 27.54099 | G8: 29.860195 | H8: 31.913043 | I8: 33.777701 | J8: 40.172482 | K8: 50.856053 | L8: 66.516436 | M8: 86.396326 | N8: 106.67109 | O8: 126.914 | P8: 147.08716 | Q8: 167.29517 | R8: 187.38029 | S8: 209.10959 | T8: 232.44379 | U8: 257.28071 | V8: 283.34996 | W8: 311.30358 | X8: 340.93192 | Y8: 372.48624 | Z8: 406.10518 | AA8: 440.85965 | AB8: 478.76308 | AC8: 519.19935 | AD8: 562.76109 | AE8: 609.812 | AF8: 660.34625 | AG8: 714.15137 | AH8: 771.05543 | AI8: 831.07732 | AJ8: 894.20173 | AK8: 894.06436
A9: newauto_cgas_2 | B9: 0.15698923 | C9: 0.17590986 | D9: 0.19318352 | E9: 0.20544703 | F9: 0.21654211 | G9: 0.22531198 | H9: 0.23180401 | I9: 0.22846775 | J9: 0.22951039 | K9: 0.23266652 | L9: 0.23623564 | M9: 0.24122181 | N9: 0.24458889 | O9: 0.24608534 | P9: 0.24617067 | Q9: 0.24531598 | R9: 0.24281506 | S9: 0.24047459 | T9: 0.23843762 | U9: 0.23664012 | V9: 0.23483697 | W9: 0.23352629 | X9: 0.23241459 | Y9: 0.23157407 | Z9: 0.23097267 | AA9: 0.23001282 | AB9: 0.2296768 | AC9: 0.22946777 | AD9: 0.22951433 | AE9: 0.22981758 | AF9: 0.2302379 | AG9: 0.23059406 | AH9: 0.23075648 | AI9: 0.23068049 | AJ9: 0.23032446 | AK9: 0.21088355
A10: auto_0 | B10: 32317.941 | C10: 31918.631 | D10: 31759.311 | E10: 31761.553 | F10: 31899.124 | G10: 32133.592 | H10: 32419.623 | I10: 32735.512 | J10: 33073.114 | K10: 33428.933 | L10: 33802.388 | M10: 34177.378 | N10: 34544.377 | O10: 34894.969 | P10: 35222.773 | Q10: 35524.23 | R10: 35815.211 | S10: 36100.833 | T10: 36380.926 | U10: 36654.746 | V10: 36920.068 | W10: 37183.05 | X10: 37446.92 | Y10: 37715.997 | Z10: 37994.341 | AA10: 38278.363 | AB10: 38579.342 | AC10: 38901.792 | AD10: 39250.528 | AE10: 39629.841 | AF10: 40042.104 | AG10: 40487.563 | AH10: 40964.725 | AI10: 41470.785 | AJ10: 42002.038 | AK10: 42002.247
A11: auto_cfut_0 | B11: 32271.24 | C11: 31853.75 | D11: 31674.362 | E11: 31654.909 | F11: 31769.037 | G11: 31978.673 | H11: 32238.864 | I11: 32527.868 | J11: 32837.249 | K11: 33163.109 | L11: 33504.395 | M11: 33844.748 | N11: 34174.321 | O11: 34484.403 | P11: 34768.323 | Q11: 35022.206 | R11: 35261.327 | S11: 35490.64 | T11: 35709.999 | U11: 35918.676 | V11: 36114.448 | W11: 36303.139 | X11: 36487.63 | Y11: 36671.758 | Z11: 36859.014 | AA11: 37045.473 | AB11: 37241.351 | AC11: 37450.257 | AD11: 37675.959 | AE11: 37921.607 | AF11: 38188.422 | AG11: 38475.53 | AH11: 38780.357 | AI11: 39099.061 | AJ11: 39426.942 | AK11: 39537.676
A12: auto_cele_0 | B12: 44.765 | C12: 62.889352 | D12: 82.889294 | E12: 104.50723 | F12: 127.86793 | G12: 152.61341 | H12: 178.36635 | I12: 205.16507 | J12: 233.30361 | K12: 263.18022 | L12: 295.26829 | M12: 329.82876 | N12: 367.18066 | O12: 407.62065 | P12: 451.43993 | Q12: 498.95303 | R12: 550.75636 | S12: 607.01049 | T12: 667.69233 | U12: 732.78701 | V12: 802.29048 | W12: 876.53808 | X12: 955.87557 | Y12: 1040.783 | Z12: 1131.8323 | AA12: 1229.3564 | AB12: 1334.4192 | AC12: 1447.9268 | AD12: 1570.9224 | AE12: 1704.5479 | AF12: 1849.9557 | AG12: 2008.2663 | AH12: 2180.5599 | AI12: 2367.8733 | AJ12: 2571.2021 | AK12: 2766.3372
... A121: buil_des_0 | B121: 1.1716777 | C121: 1.1716777 | D121: 1.1565402 | E121: 1.1416083 | F121: 1.1268791 | G121: 1.1123494 | H121: 1.0980163 | I121: 1.083877 | J121: 1.0699286 | K121: 1.0561683 | L121: 1.0425934 | M121: 1.0292012 | N121: 1.0159892 | O121: 1.0029547 | P121: 0.99009523 | Q121: 0.97740825 | R121: 0.96489133 | S121: 0.95254204 | T121: 0.940358 | U121: 0.92833689 | V121: 0.91647639 | W121: 0.90477425 | X121: 0.89322823 | Y121: 0.88183615 | Z121: 0.87059586 | AA121: 0.85950523 | AB121: 0.84856218 | AC121: 0.83776466 | AD121: 0.82711064 | AE121: 0.81659814 | AF121: 0.8062252 | AG121: 0.7959899 | AH121: 0.78589034 | AI121: 0.77592465 | AJ121: 0.766091 | AK121: 0.75638758

Sheet Tab-macro
B1: en écart au scénario de référence (%)
B2: ThreeME
B3: 2021 | C3: 2022 | D3: 2023 | E3: 2025 | F3: 2030 | G3: 2050
A4: PIB en volume | B4: =Macro!H2 -> 0.025887996 | C4: =Macro!I2 -> -0.15653445 | D4: =Macro!J2 -> -0.32832622 | E4: =Macro!L2 -> 0.097871895 | F4: =Macro!Q2 -> 0.86757901 | G4: =Macro!AK2 -> 0.78740373
A5: Consommation des ménages | B5: =Macro!H3 -> 0.027131081 | C5: =Macro!I3 -> -0.21018256 | D5: =Macro!J3 -> -0.42700646 | E5: =Macro!L3 -> 0.072534547 | F5: =Macro!Q3 -> 0.77539039 | G5: =Macro!AK3 -> 0.38160327
A6: Investissement | B6: =Macro!H4 -> 0.028626392 | C6: =Macro!I4 -> 0.049720796 | D6: =Macro!J4 -> 0.05367967 | E6: =Macro!L4 -> 0.29336926 | F6: =Macro!Q4 -> 1.5201906 | G6: =Macro!AK4 -> 1.5116947
A7: Exportations | B7: =Macro!H5 -> 0.0071433221 | C7: =Macro!I5 -> -0.049597888 | D7: =Macro!J5 -> -0.089314496 | E7: =Macro!L5 -> -0.093603016 | F7: =Macro!Q5 -> 0.053028096 | G7: =Macro!AK5 -> -0.045335632
A8: Importations | B8: =Macro!H6 -> 0 | C8: =Macro!I6 -> 0 | D8: =Macro!J6 -> 0 | E8: =Macro!L6 -> 0 | F8: =Macro!Q6 -> 0 | G8: =Macro!AK6 -> 0
A9: Revenu disponible (réel) des ménages | B9: =Macro!H7 -> 0.0049931368 | C9: =Macro!I7 -> -0.043341997 | D9: =Macro!J7 -> -0.10680165 | E9: =Macro!L7 -> -0.095533645 | F9: =Macro!Q7 -> 0.11126984 | G9: =Macro!AK7 -> 1.0672568
A10: Taux d'épargne (en pts) | B10: =Macro!H8 -> 0 | C10: =Macro!I8 -> 0 | D10: =Macro!J8 -> 0 | E10: =Macro!L8 -> 0 | F10: =Macro!Q8 -> 0 | G10: =Macro!AK8 -> 0
A11: Prix de la consommation des ménages | B11: =Macro!H9 -> -0.0077315216 | C11: =Macro!I9 -> -0.16291323 | D11: =Macro!J9 -> -0.27520425 | E11: =Macro!L9 -> -0.099963688 | F11: =Macro!Q9 -> -0.76388142 | G11: =Macro!AK9 -> -1.7915479
A12: Prix de la production | B12: =Macro!H10 -> 0.028123087 | C12: =Macro!I10 -> 0.049664181 | D12: =Macro!J10 -> 0.055246569 | E12: =Macro!L10 -> 0.29537416 | F12: =Macro!Q10 -> 1.5070228 | G12: =Macro!AK10 -> 1.495822
A13: Prix de la valeur ajoutée | B13: =Macro!H11 -> 0.0054964422 | C13: =Macro!I11 -> -0.043285382 | D13: =Macro!J11 -> -0.10836855 | E13: =Macro!L11 -> -0.097538545 | F13: =Macro!Q11 -> 0.1244376 | G13: =Macro!AK11 -> 1.0831296
A14: Prix des consommations intermédiaires | B14: =Macro!H12 -> 0.0046750578 | C14: =Macro!I12 -> -0.04094693 | D14: =Macro!J12 -> -0.1015419 | E14: =Macro!L12 -> -0.087128152 | F14: =Macro!Q12 -> 0.11458703 | G14: =Macro!AK12 -> 1.038833
A15: Prix des exportations | B15: =Macro!H13 -> 0.00050330543 | C15: =Macro!I13 -> 5.6615525e-05 | D15: =Macro!J13 -> -0.0015668984 | E15: =Macro!L13 -> -0.0020049007 | F15: =Macro!Q13 -> 0.013167767 | G15: =Macro!AK13 -> 0.01587275
... A24: Emissions de CO2 | B24: =Macro!H22 -> 0.05213813 | C24: =Macro!I22 -> 0.092014675 | D24: =Macro!J22 -> 0.10229975 | E24: =Macro!L22 -> 0.5459191 | F24: =Macro!Q22 -> 2.7560793 | G24: =Macro!AK22 -> 2.9350044
B26: % deviation from baseline
B27: ThreeME
B28: 2021 | C28: 2022 | D28: 2023 | E28: 2025 | F28: 2030 | G28: 2050
A29: GDP in volume | B29: =B4 -> 0.025887996 | C29: =C4 -> -0.15653445 | D29: =D4 -> -0.32832622 | E29: =E4 -> 0.097871895 | F29: =F4 -> 0.86757901 | G29: =G4 -> 0.78740373
A30: Household consumption | B30: =B5 -> 0.027131081 | C30: =C5 -> -0.21018256 | D30: =D5 -> -0.42700646 | E30: =E5 -> 0.072534547 | F30: =F5 -> 0.77539039 | G30: =G5 -> 0.38160327
A31: Investment | B31: =B6 -> 0.028626392 | C31: =C6 -> 0.049720796 | D31: =D6 -> 0.05367967 | E31: =E6 -> 0.29336926 | F31: =F6 -> 1.5201906 | G31: =G6 -> 1.5116947
A32: Exports | B32: =B7 -> 0.0071433221 | C32: =C7 -> -0.049597888 | D32: =D7 -> -0.089314496 | E32: =E7 -> -0.093603016 | F32: =F7 -> 0.053028096 | G32: =G7 -> -0.045335632
A33: Imports | B33: =B8 -> 0 | C33: =C8 -> 0 | D33: =D8 -> 0 | E33: =E8 -> 0 | F33: =F8 -> 0 | G33: =G8 -> 0
A34: Household disposable income (real) | B34: =B9 -> 0.0049931368 | C34: =C9 -> -0.043341997 | D34: =D9 -> -0.10680165 | E34: =E9 -> -0.095533645 | F34: =F9 -> 0.11126984 | G34: =G9 -> 1.0672568
A35: Saving rate (in points) | B35: =B10 -> 0 | C35: =C10 -> 0 | D35: =D10 -> 0 | E35: =E10 -> 0 | F35: =F10 -> 0 | G35: =G10 -> 0
A36: Household consumption price index | B36: =B11 -> -0.0077315216 | C36: =C11 -> -0.16291323 | D36: =D11 -> -0.27520425 | E36: =E11 -> -0.099963688 | F36: =F11 -> -0.76388142 | G36: =G11 -> -1.7915479
A37: Production price index | B37: =B12 -> 0.028123087 | C37: =C12 -> 0.049664181 | D37: =D12 -> 0.055246569 | E37: =E12 -> 0.29537416 | F37: =F12 -> 1.5070228 | G37: =G12 -> 1.495822
A38: Added value price index | B38: =B13 -> 0.0054964422 | C38: =C13 -> -0.043285382 | D38: =D13 -> -0.10836855 | E38: =E13 -> -0.097538545 | F38: =F13 -> 0.1244376 | G38: =G13 -> 1.0831296
A39: Intermediate consumption price index | B39: =B14 -> 0.0046750578 | C39: =C14 -> -0.04094693 | D39: =D14 -> -0.1015419 | E39: =E14 -> -0.087128152 | F39: =F14 -> 0.11458703 | G39: =G14 -> 1.038833
A40: Export price index | B40: =B15 -> 0.00050330543 | C40: =C15 -> 5.6615525e-05 | D40: =D15 -> -0.0015668984 | E40: =E15 -> -0.0020049007 | F40: =F15 -> 0.013167767 | G40: =G15 -> 0.01587275
... A49: CO2 emissions | B49: =B24 -> 0.05213813 | C49: =C24 -> 0.092014675 | D49: =D24 -> 0.10229975 | E49: =E24 -> 0.5459191 | F49: =F24 -> 2.7560793 | G49: =G24 -> 2.9350044

Sheet Tab-baseline
C1: 8 | D1: 9 | E1: 10 | F1: 12 | G1: 17 | H1: 37
C2: ThreeME
C3: 2021 | D3: 2022 | E3: 2023 | F3: 2025 | G3: 2030 | H3: 2050
