Workbook
Name formatResults: [1]ResultsEXR10!$A$50

Sheet Results
A1: NB : on crée ici une liste : - globale, qui fusionne les sorties des reportings 1, 2 et 3 - "rationalisée" : suppression des doublons, et regroupements par thématique On continue par la suite à avoir 2 Excels de reporting (un "energie", fusion des reportings 1 et 2), et un "économie" (reporting 3)), dans lesquels on copiera cet onglet "results" (généré automatiquement par EViews). --> puis voir à la fin si on peut pas importer les graphs et tableaux dans l'excel automatiquement généré (éviterait les copiés collés, mais à voir si ça prend trop de temps, et si c'est pas trop gros comme excel)
A2: Nom du bloc de variables utilisé dans le code | B2: Sous-bloc de variables pour plus de lisibilité dans le Excel | E2: Year | F2: =date!B3 -> 2015 | G2: =date!C3 -> 2016 | H2: =date!D3 -> 2017 | I2: =date!E3 -> 2018 | J2: =date!F3 -> 2019 | K2: =date!G3 -> 2020 | L2: =date!H3 -> 2021 | M2: =date!I3 -> 2022 | ... AO2: =date!AK3 -> 2050
A3: HYBRID | B3: AUTOMOBILES (thousands) | C3: TOTAL STOCK SHOCK | E3: AUTO_2 | F3: =VLOOKUP($E3,Hybrid!$1:$1048576,MATCH(DATE(F$2,1,1),Hybrid!$A$1:$LI$1),FALSE) -> 32317.941 | G3: =VLOOKUP($E3,Hybrid!$1:$1048576,MATCH(DATE(G$2,1,1),Hybrid!$A$1:$LI$1),FALSE) -> 31911.217 | H3: =VLOOKUP($E3,Hybrid!$1:$1048576,MATCH(DATE(H$2,1,1),Hybrid!$A$1:$LI$1),FALSE) -> 31732.935 | I3: =VLOOKUP($E3,Hybrid!$1:$1048576,MATCH(DATE(I$2,1,1),Hybrid!$A$1:$LI$1),FALSE) -> 31702.286 | J3: =VLOOKUP($E3,Hybrid!$1:$1048576,MATCH(DATE(J$2,1,1),Hybrid!$A$1:$LI$1),FALSE) -> 31792.126 | K3: =VLOOKUP($E3,Hybrid!$1:$1048576,MATCH(DATE(K$2,1,1),Hybrid!$A$1:$LI$1),FALSE) -> 31964.155 | L3: =VLOOKUP($E3,Hybrid!$1:$1048576,MATCH(DATE(L$2,1,1),Hybrid!$A$1:$LI$1),FALSE) -> 32183.571 | M3: =VLOOKUP($E3,Hybrid!$1:$1048576,MATCH(DATE(M$2,1,1),Hybrid!$A$1:$LI$1),FALSE) -> 32332.233 | ... AO3: =VLOOKUP($E3,Hybrid!$1:$1048576,MATCH(DATE(AO$2,1,1),Hybrid!$A$1:$LI$1),FALSE) -> 43625.428
C4: OIL | E4: AUTO_cfut_2 | F4: =VLOOKUP($E4,Hybrid!$1:$1048576,MATCH(DATE(F$2,1,1),Hybrid!$A$1:$LI$1),FALSE) -> 32271.24 | G4: =VLOOKUP($E4,Hybrid!$1:$1048576,MATCH(DATE(G$2,1,1),Hybrid!$A$1:$LI$1),FALSE) -> 31846.407 | H4: =VLOOKUP($E4,Hybrid!$1:$1048576,MATCH(DATE(H$2,1,1),Hybrid!$A$1:$LI$1),FALSE) -> 31648.242 | I4: =VLOOKUP($E4,Hybrid!$1:$1048576,MATCH(DATE(I$2,1,1),Hybrid!$A$1:$LI$1),FALSE) -> 31596.228 | J4: =VLOOKUP($E4,Hybrid!$1:$1048576,MATCH(DATE(J$2,1,1),Hybrid!$A$1:$LI$1),FALSE) -> 31663.113 | K4: =VLOOKUP($E4,Hybrid!$1:$1048576,MATCH(DATE(K$2,1,1),Hybrid!$A$1:$LI$1),FALSE) -> 31810.955 | L4: =VLOOKUP($E4,Hybrid!$1:$1048576,MATCH(DATE(L$2,1,1),Hybrid!$A$1:$LI$1),FALSE) -> 32005.277 | M4: =VLOOKUP($E4,Hybrid!$1:$1048576,MATCH(DATE(M$2,1,1),Hybrid!$A$1:$LI$1),FALSE) -> 32128.171 | ... AO4: =VLOOKUP($E4,Hybrid!$1:$1048576,MATCH(DATE(AO$2,1,1),Hybrid!$A$1:$LI$1),FALSE) -> 35733.333
D5: class A | E5: AUTO_ca_cfut_2 | F5: =VLOOKUP($E5,Hybrid!$1:$1048576,MATCH(DATE(F$2,1,1),Hybrid!$A$1:$LI$1),FALSE) -> 7095.7005 | G5: =VLOOKUP($E5,Hybrid!$1:$1048576,MATCH(DATE(G$2,1,1),Hybrid!$A$1:$LI$1),FALSE) -> 7136.7578 | H5: =VLOOKUP($E5,Hybrid!$1:$1048576,MATCH(DATE(H$2,1,1),Hybrid!$A$1:$LI$1),FALSE) -> 7234.0597 | I5: =VLOOKUP($E5,Hybrid!$1:$1048576,MATCH(DATE(I$2,1,1),Hybrid!$A$1:$LI$1),FALSE) -> 7366.577 | J5: =VLOOKUP($E5,Hybrid!$1:$1048576,MATCH(DATE(J$2,1,1),Hybrid!$A$1:$LI$1),FALSE) -> 7527.8349 | K5: =VLOOKUP($E5,Hybrid!$1:$1048576,MATCH(DATE(K$2,1,1),Hybrid!$A$1:$LI$1),FALSE) -> 7707.4422 | L5: =VLOOKUP($E5,Hybrid!$1:$1048576,MATCH(DATE(L$2,1,1),Hybrid!$A$1:$LI$1),FALSE) -> 7895.9502 | M5: =VLOOKUP($E5,Hybrid!$1:$1048576,MATCH(DATE(M$2,1,1),Hybrid!$A$1:$LI$1),FALSE) -> 8060.2894 | ... AO5: =VLOOKUP($E5,Hybrid!$1:$1048576,MATCH(DATE(AO$2,1,1),Hybrid!$A$1:$LI$1),FALSE) -> 11833.93
D6: class B | E6: AUTO_cb_cfut_2 | F6: =VLOOKUP($E6,Hybrid!$1:$1048576,MATCH(DATE(F$2,1,1),Hybrid!$A$1:$LI$1),FALSE) -> 8251.2564 | G6: =VLOOKUP($E6,Hybrid!$1:$1048576,MATCH(DATE(G$2,1,1),Hybrid!$A$1:$LI$1),FALSE) -> 8178.01 | H6: =VLOOKUP($E6,Hybrid!$1:$1048576,MATCH(DATE(H$2,1,1),Hybrid!$A$1:$LI$1),FALSE) -> 8166.4716 | I6: =VLOOKUP($E6,Hybrid!$1:$1048576,MATCH(DATE(I$2,1,1),Hybrid!$A$1:$LI$1),FALSE) -> 8195.5437 | J6: =VLOOKUP($E6,Hybrid!$1:$1048576,MATCH(DATE(J$2,1,1),Hybrid!$A$1:$LI$1),FALSE) -> 8258.2796 | K6: =VLOOKUP($E6,Hybrid!$1:$1048576,MATCH(DATE(K$2,1,1),Hybrid!$A$1:$LI$1),FALSE) -> 8344.2948 | L6: =VLOOKUP($E6,Hybrid!$1:$1048576,MATCH(DATE(L$2,1,1),Hybrid!$A$1:$LI$1),FALSE) -> 8444.0797 | M6: =VLOOKUP($E6,Hybrid!$1:$1048576,MATCH(DATE(M$2,1,1),Hybrid!$A$1:$LI$1),FALSE) -> 8525.0965 | ... AO6: =VLOOKUP($E6,Hybrid!$1:$1048576,MATCH(DATE(AO$2,1,1),Hybrid!$A$1:$LI$1),FALSE) -> 10676.915
D7: class C | E7: AUTO_cc_cfut_2 | F7: =VLOOKUP($E7,Hybrid!$1:$1048576,MATCH(DATE(F$2,1,1),Hybrid!$A$1:$LI$1),FALSE) -> 6777.6025 | G7: =VLOOKUP($E7,Hybrid!$1:$1048576,MATCH(DATE(G$2,1,1),Hybrid!$A$1:$LI$1),FALSE) -> 6643.4662 | H7: =VLOOKUP($E7,Hybrid!$1:$1048576,MATCH(DATE(H$2,1,1),Hybrid!$A$1:$LI$1),FALSE) -> 6557.8115 | I7: =VLOOKUP($E7,Hybrid!$1:$1048576,MATCH(DATE(I$2,1,1),Hybrid!$A$1:$LI$1),FALSE) -> 6505.379 | J7: =VLOOKUP($E7,Hybrid!$1:$1048576,MATCH(DATE(J$2,1,1),Hybrid!$A$1:$LI$1),FALSE) -> 6480.8301 | K7: =VLOOKUP($E7,Hybrid!$1:$1048576,MATCH(DATE(K$2,1,1),Hybrid!$A$1:$LI$1),FALSE) -> 6476.6688 | L7: =VLOOKUP($E7,Hybrid!$1:$1048576,MATCH(DATE(L$2,1,1),Hybrid!$A$1:$LI$1),FALSE) -> 6485.987 | M7: =VLOOKUP($E7,Hybrid!$1:$1048576,MATCH(DATE(M$2,1,1),Hybrid!$A$1:$LI$1),FALSE) -> 6485.7063 | ... AO7: =VLOOKUP($E7,Hybrid!$1:$1048576,MATCH(DATE(AO$2,1,1),Hybrid!$A$1:$LI$1),FALSE) -> 6974.9365
D8: class D | E8: AUTO_cd_cfut_2 | F8: =VLOOKUP($E8,Hybrid!$1:$1048576,MATCH(DATE(F$2,1,1),Hybrid!$A$1:$LI$1),FALSE) -> 4159.6639 | G8: =VLOOKUP($E8,Hybrid!$1:$1048576,MATCH(DATE(G$2,1,1),Hybrid!$A$1:$LI$1),FALSE) -> 4053.0059 | H8: =VLOOKUP($E8,Hybrid!$1:$1048576,MATCH(DATE(H$2,1,1),Hybrid!$A$1:$LI$1),FALSE) -> 3974.2092 | I8: =VLOOKUP($E8,Hybrid!$1:$1048576,MATCH(DATE(I$2,1,1),Hybrid!$A$1:$LI$1),FALSE) -> 3914.3493 | J8: =VLOOKUP($E8,Hybrid!$1:$1048576,MATCH(DATE(J$2,1,1),Hybrid!$A$1:$LI$1),FALSE) -> 3870.1372 | K8: =VLOOKUP($E8,Hybrid!$1:$1048576,MATCH(DATE(K$2,1,1),Hybrid!$A$1:$LI$1),FALSE) -> 3837.333 | L8: =VLOOKUP($E8,Hybrid!$1:$1048576,MATCH(DATE(L$2,1,1),Hybrid!$A$1:$LI$1),FALSE) -> 3812.0522 | M8: =VLOOKUP($E8,Hybrid!$1:$1048576,MATCH(DATE(M$2,1,1),Hybrid!$A$1:$LI$1),FALSE) -> 3781.6082 | ... AO8: =VLOOKUP($E8,Hybrid!$1:$1048576,MATCH(DATE(AO$2,1,1),Hybrid!$A$1:$LI$1),FALSE) -> 3474.7833
D9: class E | E9: AUTO_ce_cfut_2 | F9: =VLOOKUP($E9,Hybrid!$1:$1048576,MATCH(DATE(F$2,1,1),Hybrid!$A$1:$LI$1),FALSE) -> 2503.7292 | G9: =VLOOKUP($E9,Hybrid!$1:$1048576,MATCH(DATE(G$2,1,1),Hybrid!$A$1:$LI$1),FALSE) -> 2441.8639 | H9: =VLOOKUP($E9,Hybrid!$1:$1048576,MATCH(DATE(H$2,1,1),Hybrid!$A$1:$LI$1),FALSE) -> 2395.9826 | I9: =VLOOKUP($E9,Hybrid!$1:$1048576,MATCH(DATE(I$2,1,1),Hybrid!$A$1:$LI$1),FALSE) -> 2360.47 | J9: =VLOOKUP($E9,Hybrid!$1:$1048576,MATCH(DATE(J$2,1,1),Hybrid!$A$1:$LI$1),FALSE) -> 2333.2493 | K9: =VLOOKUP($E9,Hybrid!$1:$1048576,MATCH(DATE(K$2,1,1),Hybrid!$A$1:$LI$1),FALSE) -> 2311.7997 | L9: =VLOOKUP($E9,Hybrid!$1:$1048576,MATCH(DATE(L$2,1,1),Hybrid!$A$1:$LI$1),FALSE) -> 2293.8231 | M9: =VLOOKUP($E9,Hybrid!$1:$1048576,MATCH(DATE(M$2,1,1),Hybrid!$A$1:$LI$1),FALSE) -> 2271.6501 | ... AO9: =VLOOKUP($E9,Hybrid!$1:$1048576,MATCH(DATE(AO$2,1,1),Hybrid!$A$1:$LI$1),FALSE) -> 1736.8109
D10: class F | E10: AUTO_cf_cfut_2 | F10: =VLOOKUP($E10,Hybrid!$1:$1048576,MATCH(DATE(F$2,1,1),Hybrid!$A$1:$LI$1),FALSE) -> 1243.6668 | G10: =VLOOKUP($E10,Hybrid!$1:$1048576,MATCH(DATE(G$2,1,1),Hybrid!$A$1:$LI$1),FALSE) -> 1210.3171 | H10: =VLOOKUP($E10,Hybrid!$1:$1048576,MATCH(DATE(H$2,1,1),Hybrid!$A$1:$LI$1),FALSE) -> 1183.5844 | I10: =VLOOKUP($E10,Hybrid!$1:$1048576,MATCH(DATE(I$2,1,1),Hybrid!$A$1:$LI$1),FALSE) -> 1160.542 | J10: =VLOOKUP($E10,Hybrid!$1:$1048576,MATCH(DATE(J$2,1,1),Hybrid!$A$1:$LI$1),FALSE) -> 1140.0916 | K10: =VLOOKUP($E10,Hybrid!$1:$1048576,MATCH(DATE(K$2,1,1),Hybrid!$A$1:$LI$1),FALSE) -> 1121.1101 | L10: =VLOOKUP($E10,Hybrid!$1:$1048576,MATCH(DATE(L$2,1,1),Hybrid!$A$1:$LI$1),FALSE) -> 1102.6233 | M10: =VLOOKUP($E10,Hybrid!$1:$1048576,MATCH(DATE(M$2,1,1),Hybrid!$A$1:$LI$1),FALSE) -> 1081.2936 | ... AO10: =VLOOKUP($E10,Hybrid!$1:$1048576,MATCH(DATE(AO$2,1,1),Hybrid!$A$1:$LI$1),FALSE) -> 471.44891
D11: class G | E11: AUTO_cg_cfut_2 | F11: =VLOOKUP($E11,Hybrid!$1:$1048576,MATCH(DATE(F$2,1,1),Hybrid!$A$1:$LI$1),FALSE) -> 2239.6206 | G11: =VLOOKUP($E11,Hybrid!$1:$1048576,MATCH(DATE(G$2,1,1),Hybrid!$A$1:$LI$1),FALSE) -> 2182.9863 | H11: =VLOOKUP($E11,Hybrid!$1:$1048576,MATCH(DATE(H$2,1,1),Hybrid!$A$1:$LI$1),FALSE) -> 2136.1231 | I11: =VLOOKUP($E11,Hybrid!$1:$1048576,MATCH(DATE(I$2,1,1),Hybrid!$A$1:$LI$1),FALSE) -> 2093.3668 | J11: =VLOOKUP($E11,Hybrid!$1:$1048576,MATCH(DATE(J$2,1,1),Hybrid!$A$1:$LI$1),FALSE) -> 2052.69 | K11: =VLOOKUP($E11,Hybrid!$1:$1048576,MATCH(DATE(K$2,1,1),Hybrid!$A$1:$LI$1),FALSE) -> 2012.3066 | L11: =VLOOKUP($E11,Hybrid!$1:$1048576,MATCH(DATE(L$2,1,1),Hybrid!$A$1:$LI$1),FALSE) -> 1970.7611 | M11: =VLOOKUP($E11,Hybrid!$1:$1048576,MATCH(DATE(M$2,1,1),Hybrid!$A$1:$LI$1),FALSE) -> 1922.5273 | ... AO11: =VLOOKUP($E11,Hybrid!$1:$1048576,MATCH(DATE(AO$2,1,1),Hybrid!$A$1:$LI$1),FALSE) -> 564.50811
C12: ELEC | E12: AUTO_cele_2 | F12: =VLOOKUP($E12,Hybrid!$1:$1048576,MATCH(DATE(F$2,1,1),Hybrid!$A$1:$LI$1),FALSE) -> 44.765 | G12: =VLOOKUP($E12,Hybrid!$1:$1048576,MATCH(DATE(G$2,1,1),Hybrid!$A$1:$LI$1),FALSE) -> 62.819188 | H12: =VLOOKUP($E12,Hybrid!$1:$1048576,MATCH(DATE(H$2,1,1),Hybrid!$A$1:$LI$1),FALSE) -> 82.635226 | I12: =VLOOKUP($E12,Hybrid!$1:$1048576,MATCH(DATE(I$2,1,1),Hybrid!$A$1:$LI$1),FALSE) -> 103.92645 | J12: =VLOOKUP($E12,Hybrid!$1:$1048576,MATCH(DATE(J$2,1,1),Hybrid!$A$1:$LI$1),FALSE) -> 126.8031 | K12: =VLOOKUP($E12,Hybrid!$1:$1048576,MATCH(DATE(K$2,1,1),Hybrid!$A$1:$LI$1),FALSE) -> 150.90795 | L12: =VLOOKUP($E12,Hybrid!$1:$1048576,MATCH(DATE(L$2,1,1),Hybrid!$A$1:$LI$1),FALSE) -> 175.92151 | M12: =VLOOKUP($E12,Hybrid!$1:$1048576,MATCH(DATE(M$2,1,1),Hybrid!$A$1:$LI$1),FALSE) -> 201.61753 | ... AO12: =VLOOKUP($E12,Hybrid!$1:$1048576,MATCH(DATE(AO$2,1,1),Hybrid!$A$1:$LI$1),FALSE) -> 7888.5377
D13: class A | E13: AUTO_ca_cele_2 | F13: =VLOOKUP($E13,Hybrid!$1:$1048576,MATCH(DATE(F$2,1,1),Hybrid!$A$1:$LI$1),FALSE) -> 9.8427899 | G13: =VLOOKUP($E13,Hybrid!$1:$1048576,MATCH(DATE(G$2,1,1),Hybrid!$A$1:$LI$1),FALSE) -> 15.102615 | H13: =VLOOKUP($E13,Hybrid!$1:$1048576,MATCH(DATE(H$2,1,1),Hybrid!$A$1:$LI$1),FALSE) -> 20.915324 | I13: =VLOOKUP($E13,Hybrid!$1:$1048576,MATCH(DATE(I$2,1,1),Hybrid!$A$1:$LI$1),FALSE) -> 27.220552 | J13: =VLOOKUP($E13,Hybrid!$1:$1048576,MATCH(DATE(J$2,1,1),Hybrid!$A$1:$LI$1),FALSE) -> 34.066405 | K13: =VLOOKUP($E13,Hybrid!$1:$1048576,MATCH(DATE(K$2,1,1),Hybrid!$A$1:$LI$1),FALSE) -> 41.350772 | L13: =VLOOKUP($E13,Hybrid!$1:$1048576,MATCH(DATE(L$2,1,1),Hybrid!$A$1:$LI$1),FALSE) -> 48.982806 | M13: =VLOOKUP($E13,Hybrid!$1:$1048576,MATCH(DATE(M$2,1,1),Hybrid!$A$1:$LI$1),FALSE) -> 56.933502 | ... AO13: =VLOOKUP($E13,Hybrid!$1:$1048576,MATCH(DATE(AO$2,1,1),Hybrid!$A$1:$LI$1),FALSE) -> 2809.468
D14: class B | E14: AUTO_cb_cele_2 | F14: =VLOOKUP($E14,Hybrid!$1:$1048576,MATCH(DATE(F$2,1,1),Hybrid!$A$1:$LI$1),FALSE) -> 11.445717 | G14: =VLOOKUP($E14,Hybrid!$1:$1048576,MATCH(DATE(G$2,1,1),Hybrid!$A$1:$LI$1),FALSE) -> 16.422266 | H14: =VLOOKUP($E14,Hybrid!$1:$1048576,MATCH(DATE(H$2,1,1),Hybrid!$A$1:$LI$1),FALSE) -> 21.938274 | I14: =VLOOKUP($E14,Hybrid!$1:$1048576,MATCH(DATE(I$2,1,1),Hybrid!$A$1:$LI$1),FALSE) -> 27.939833 | J14: =VLOOKUP($E14,Hybrid!$1:$1048576,MATCH(DATE(J$2,1,1),Hybrid!$A$1:$LI$1),FALSE) -> 34.476478 | K14: =VLOOKUP($E14,Hybrid!$1:$1048576,MATCH(DATE(K$2,1,1),Hybrid!$A$1:$LI$1),FALSE) -> 41.448912 | L14: =VLOOKUP($E14,Hybrid!$1:$1048576,MATCH(DATE(L$2,1,1),Hybrid!$A$1:$LI$1),FALSE) -> 48.768487 | M14: =VLOOKUP($E14,Hybrid!$1:$1048576,MATCH(DATE(M$2,1,1),Hybrid!$A$1:$LI$1),FALSE) -> 56.41555 | ... AO14: =VLOOKUP($E14,Hybrid!$1:$1048576,MATCH(DATE(AO$2,1,1),Hybrid!$A$1:$LI$1),FALSE) -> 2642.7441
D15: class C | E15: AUTO_cc_cele_2 | F15: =VLOOKUP($E15,Hybrid!$1:$1048576,MATCH(DATE(F$2,1,1),Hybrid!$A$1:$LI$1),FALSE) -> 9.4015406 | G15: =VLOOKUP($E15,Hybrid!$1:$1048576,MATCH(DATE(G$2,1,1),Hybrid!$A$1:$LI$1),FALSE) -> 12.791178 | H15: =VLOOKUP($E15,Hybrid!$1:$1048576,MATCH(DATE(H$2,1,1),Hybrid!$A$1:$LI$1),FALSE) -> 16.559687 | I15: =VLOOKUP($E15,Hybrid!$1:$1048576,MATCH(DATE(I$2,1,1),Hybrid!$A$1:$LI$1),FALSE) -> 20.67215 | J15: =VLOOKUP($E15,Hybrid!$1:$1048576,MATCH(DATE(J$2,1,1),Hybrid!$A$1:$LI$1),FALSE) -> 25.164793 | K15: =VLOOKUP($E15,Hybrid!$1:$1048576,MATCH(DATE(K$2,1,1),Hybrid!$A$1:$LI$1),FALSE) -> 29.968027 | L15: =VLOOKUP($E15,Hybrid!$1:$1048576,MATCH(DATE(L$2,1,1),Hybrid!$A$1:$LI$1),FALSE) -> 35.019504 | M15: =VLOOKUP($E15,Hybrid!$1:$1048576,MATCH(DATE(M$2,1,1),Hybrid!$A$1:$LI$1),FALSE) -> 40.310082 | ... AO15: =VLOOKUP($E15,Hybrid!$1:$1048576,MATCH(DATE(AO$2,1,1),Hybrid!$A$1:$LI$1),FALSE) -> 1784.7622
D16: class D | E16: AUTO_cd_cele_2 | F16: =VLOOKUP($E16,Hybrid!$1:$1048576,MATCH(DATE(F$2,1,1),Hybrid!$A$1:$LI$1),FALSE) -> 5.7700713 | G16: =VLOOKUP($E16,Hybrid!$1:$1048576,MATCH(DATE(G$2,1,1),Hybrid!$A$1:$LI$1),FALSE) -> 7.5799114 | H16: =VLOOKUP($E16,Hybrid!$1:$1048576,MATCH(DATE(H$2,1,1),Hybrid!$A$1:$LI$1),FALSE) -> 9.5402273 | I16: =VLOOKUP($E16,Hybrid!$1:$1048576,MATCH(DATE(I$2,1,1),Hybrid!$A$1:$LI$1),FALSE) -> 11.603567 | J16: =VLOOKUP($E16,Hybrid!$1:$1048576,MATCH(DATE(J$2,1,1),Hybrid!$A$1:$LI$1),FALSE) -> 13.766447 | K16: =VLOOKUP($E16,Hybrid!$1:$1048576,MATCH(DATE(K$2,1,1),Hybrid!$A$1:$LI$1),FALSE) -> 15.993768 | L16: =VLOOKUP($E16,Hybrid!$1:$1048576,MATCH(DATE(L$2,1,1),Hybrid!$A$1:$LI$1),FALSE) -> 18.252981 | M16: =VLOOKUP($E16,Hybrid!$1:$1048576,MATCH(DATE(M$2,1,1),Hybrid!$A$1:$LI$1),FALSE) -> 20.477844 | ... AO16: =VLOOKUP($E16,Hybrid!$1:$1048576,MATCH(DATE(AO$2,1,1),Hybrid!$A$1:$LI$1),FALSE) -> 393.15514
D17: class E | E17: AUTO_ce_cele_2 | F17: =VLOOKUP($E17,Hybrid!$1:$1048576,MATCH(DATE(F$2,1,1),Hybrid!$A$1:$LI$1),FALSE) -> 3.4730441 | G17: =VLOOKUP($E17,Hybrid!$1:$1048576,MATCH(DATE(G$2,1,1),Hybrid!$A$1:$LI$1),FALSE) -> 4.5874377 | H17: =VLOOKUP($E17,Hybrid!$1:$1048576,MATCH(DATE(H$2,1,1),Hybrid!$A$1:$LI$1),FALSE) -> 5.7895749 | I17: =VLOOKUP($E17,Hybrid!$1:$1048576,MATCH(DATE(I$2,1,1),Hybrid!$A$1:$LI$1),FALSE) -> 7.0494691 | J17: =VLOOKUP($E17,Hybrid!$1:$1048576,MATCH(DATE(J$2,1,1),Hybrid!$A$1:$LI$1),FALSE) -> 8.3642148 | K17: =VLOOKUP($E17,Hybrid!$1:$1048576,MATCH(DATE(K$2,1,1),Hybrid!$A$1:$LI$1),FALSE) -> 9.7114329 | L17: =VLOOKUP($E17,Hybrid!$1:$1048576,MATCH(DATE(L$2,1,1),Hybrid!$A$1:$LI$1),FALSE) -> 11.070498 | M17: =VLOOKUP($E17,Hybrid!$1:$1048576,MATCH(DATE(M$2,1,1),Hybrid!$A$1:$LI$1),FALSE) -> 12.401866 | ... AO17: =VLOOKUP($E17,Hybrid!$1:$1048576,MATCH(DATE(AO$2,1,1),Hybrid!$A$1:$LI$1),FALSE) -> 200.41277
D18: class F | E18: AUTO_cf_cele_2 | F18: =VLOOKUP($E18,Hybrid!$1:$1048576,MATCH(DATE(F$2,1,1),Hybrid!$A$1:$LI$1),FALSE) -> 1.7251505 | G18: =VLOOKUP($E18,Hybrid!$1:$1048576,MATCH(DATE(G$2,1,1),Hybrid!$A$1:$LI$1),FALSE) -> 2.2500569 | H18: =VLOOKUP($E18,Hybrid!$1:$1048576,MATCH(DATE(H$2,1,1),Hybrid!$A$1:$LI$1),FALSE) -> 2.7997473 | I18: =VLOOKUP($E18,Hybrid!$1:$1048576,MATCH(DATE(I$2,1,1),Hybrid!$A$1:$LI$1),FALSE) -> 3.3544502 | J18: =VLOOKUP($E18,Hybrid!$1:$1048576,MATCH(DATE(J$2,1,1),Hybrid!$A$1:$LI$1),FALSE) -> 3.9088075 | K18: =VLOOKUP($E18,Hybrid!$1:$1048576,MATCH(DATE(K$2,1,1),Hybrid!$A$1:$LI$1),FALSE) -> 4.4525897 | L18: =VLOOKUP($E18,Hybrid!$1:$1048576,MATCH(DATE(L$2,1,1),Hybrid!$A$1:$LI$1),FALSE) -> 4.9767519 | M18: =VLOOKUP($E18,Hybrid!$1:$1048576,MATCH(DATE(M$2,1,1),Hybrid!$A$1:$LI$1),FALSE) -> 5.4580834 | ... AO18: =VLOOKUP($E18,Hybrid!$1:$1048576,MATCH(DATE(AO$2,1,1),Hybrid!$A$1:$LI$1),FALSE) -> 28.407643
D19: class G | E19: AUTO_cg_cele_2 | F19: =VLOOKUP($E19,Hybrid!$1:$1048576,MATCH(DATE(F$2,1,1),Hybrid!$A$1:$LI$1),FALSE) -> 3.1066862 | G19: =VLOOKUP($E19,Hybrid!$1:$1048576,MATCH(DATE(G$2,1,1),Hybrid!$A$1:$LI$1),FALSE) -> 4.0857232 | H19: =VLOOKUP($E19,Hybrid!$1:$1048576,MATCH(DATE(H$2,1,1),Hybrid!$A$1:$LI$1),FALSE) -> 5.0923917 | I19: =VLOOKUP($E19,Hybrid!$1:$1048576,MATCH(DATE(I$2,1,1),Hybrid!$A$1:$LI$1),FALSE) -> 6.0864298 | J19: =VLOOKUP($E19,Hybrid!$1:$1048576,MATCH(DATE(J$2,1,1),Hybrid!$A$1:$LI$1),FALSE) -> 7.055959 | K19: =VLOOKUP($E19,Hybrid!$1:$1048576,MATCH(DATE(K$2,1,1),Hybrid!$A$1:$LI$1),FALSE) -> 7.982451 | L19: =VLOOKUP($E19,Hybrid!$1:$1048576,MATCH(DATE(L$2,1,1),Hybrid!$A$1:$LI$1),FALSE) -> 8.850481 | M19: =VLOOKUP($E19,Hybrid!$1:$1048576,MATCH(DATE(M$2,1,1),Hybrid!$A$1:$LI$1),FALSE) -> 9.620605 | ... AO19: =VLOOKUP($E19,Hybrid!$1:$1048576,MATCH(DATE(AO$2,1,1),Hybrid!$A$1:$LI$1),FALSE) -> 29.587833
C20: GAS | E20: AUTO_cgas_2 | F20: =VLOOKUP($E20,Hybrid!$1:$1048576,MATCH(DATE(F$2,1,1),Hybrid!$A$1:$LI$1),FALSE) -> 1.936 | G20: =VLOOKUP($E20,Hybrid!$1:$1048576,MATCH(DATE(G$2,1,1),Hybrid!$A$1:$LI$1),FALSE) -> 1.990293 | H20: =VLOOKUP($E20,Hybrid!$1:$1048576,MATCH(DATE(H$2,1,1),Hybrid!$A$1:$LI$1),FALSE) -> 2.0574577 | I20: =VLOOKUP($E20,Hybrid!$1:$1048576,MATCH(DATE(I$2,1,1),Hybrid!$A$1:$LI$1),FALSE) -> 2.1314073 | J20: =VLOOKUP($E20,Hybrid!$1:$1048576,MATCH(DATE(J$2,1,1),Hybrid!$A$1:$LI$1),FALSE) -> 2.2103839 | K20: =VLOOKUP($E20,Hybrid!$1:$1048576,MATCH(DATE(K$2,1,1),Hybrid!$A$1:$LI$1),FALSE) -> 2.2916631 | L20: =VLOOKUP($E20,Hybrid!$1:$1048576,MATCH(DATE(L$2,1,1),Hybrid!$A$1:$LI$1),FALSE) -> 2.3727336 | M20: =VLOOKUP($E20,Hybrid!$1:$1048576,MATCH(DATE(M$2,1,1),Hybrid!$A$1:$LI$1),FALSE) -> 2.444007 | ... AO20: =VLOOKUP($E20,Hybrid!$1:$1048576,MATCH(DATE(AO$2,1,1),Hybrid!$A$1:$LI$1),FALSE) -> 3.5575264
D21: class A | E21: AUTO_ca_cgas_2 | F21: =VLOOKUP($E21,Hybrid!$1:$1048576,MATCH(DATE(F$2,1,1),Hybrid!$A$1:$LI$1),FALSE) -> 0.4256817 | G21: =VLOOKUP($E21,Hybrid!$1:$1048576,MATCH(DATE(G$2,1,1),Hybrid!$A$1:$LI$1),FALSE) -> 0.44891627 | H21: =VLOOKUP($E21,Hybrid!$1:$1048576,MATCH(DATE(H$2,1,1),Hybrid!$A$1:$LI$1),FALSE) -> 0.47569228 | I21: =VLOOKUP($E21,Hybrid!$1:$1048576,MATCH(DATE(I$2,1,1),Hybrid!$A$1:$LI$1),FALSE) -> 0.5043894 | J21: =VLOOKUP($E21,Hybrid!$1:$1048576,MATCH(DATE(J$2,1,1),Hybrid!$A$1:$LI$1),FALSE) -> 0.53457386 | K21: =VLOOKUP($E21,Hybrid!$1:$1048576,MATCH(DATE(K$2,1,1),Hybrid!$A$1:$LI$1),FALSE) -> 0.56546762 | L21: =VLOOKUP($E21,Hybrid!$1:$1048576,MATCH(DATE(L$2,1,1),Hybrid!$A$1:$LI$1),FALSE) -> 0.59635251 | M21: =VLOOKUP($E21,Hybrid!$1:$1048576,MATCH(DATE(M$2,1,1),Hybrid!$A$1:$LI$1),FALSE) -> 0.62450908 | ... AO21: =VLOOKUP($E21,Hybrid!$1:$1048576,MATCH(DATE(AO$2,1,1),Hybrid!$A$1:$LI$1),FALSE) -> 1.169003
D22: class B | E22: AUTO_cb_cgas_2 | F22: =VLOOKUP($E22,Hybrid!$1:$1048576,MATCH(DATE(F$2,1,1),Hybrid!$A$1:$LI$1),FALSE) -> 0.49500523 | G22: =VLOOKUP($E22,Hybrid!$1:$1048576,MATCH(DATE(G$2,1,1),Hybrid!$A$1:$LI$1),FALSE) -> 0.51185913 | H22: =VLOOKUP($E22,Hybrid!$1:$1048576,MATCH(DATE(H$2,1,1),Hybrid!$A$1:$LI$1),FALSE) -> 0.53236494 | I22: =VLOOKUP($E22,Hybrid!$1:$1048576,MATCH(DATE(I$2,1,1),Hybrid!$A$1:$LI$1),FALSE) -> 0.55492544 | J22: =VLOOKUP($E22,Hybrid!$1:$1048576,MATCH(DATE(J$2,1,1),Hybrid!$A$1:$LI$1),FALSE) -> 0.5790941 | K22: =VLOOKUP($E22,Hybrid!$1:$1048576,MATCH(DATE(K$2,1,1),Hybrid!$A$1:$LI$1),FALSE) -> 0.60411809 | L22: =VLOOKUP($E22,Hybrid!$1:$1048576,MATCH(DATE(L$2,1,1),Hybrid!$A$1:$LI$1),FALSE) -> 0.62929724 | M22: =VLOOKUP($E22,Hybrid!$1:$1048576,MATCH(DATE(M$2,1,1),Hybrid!$A$1:$LI$1),FALSE) -> 0.65197834 | ... AO22: =VLOOKUP($E22,Hybrid!$1:$1048576,MATCH(DATE(AO$2,1,1),Hybrid!$A$1:$LI$1),FALSE) -> 1.0591591
D23: class C | E23: AUTO_cc_cgas_2 | F23: =VLOOKUP($E23,Hybrid!$1:$1048576,MATCH(DATE(F$2,1,1),Hybrid!$A$1:$LI$1),FALSE) -> 0.40659852 | G23: =VLOOKUP($E23,Hybrid!$1:$1048576,MATCH(DATE(G$2,1,1),Hybrid!$A$1:$LI$1),FALSE) -> 0.41422794 | H23: =VLOOKUP($E23,Hybrid!$1:$1048576,MATCH(DATE(H$2,1,1),Hybrid!$A$1:$LI$1),FALSE) -> 0.42457655 | I23: =VLOOKUP($E23,Hybrid!$1:$1048576,MATCH(DATE(I$2,1,1),Hybrid!$A$1:$LI$1),FALSE) -> 0.4365094 | J23: =VLOOKUP($E23,Hybrid!$1:$1048576,MATCH(DATE(J$2,1,1),Hybrid!$A$1:$LI$1),FALSE) -> 0.44969619 | K23: =VLOOKUP($E23,Hybrid!$1:$1048576,MATCH(DATE(K$2,1,1),Hybrid!$A$1:$LI$1),FALSE) -> 0.46361108 | L23: =VLOOKUP($E23,Hybrid!$1:$1048576,MATCH(DATE(L$2,1,1),Hybrid!$A$1:$LI$1),FALSE) -> 0.47776152 | M23: =VLOOKUP($E23,Hybrid!$1:$1048576,MATCH(DATE(M$2,1,1),Hybrid!$A$1:$LI$1),FALSE) -> 0.49028207 | ... AO23: =VLOOKUP($E23,Hybrid!$1:$1048576,MATCH(DATE(AO$2,1,1),Hybrid!$A$1:$LI$1),FALSE) -> 0.69482125
D24: class D | E24: AUTO_cd_cgas_2 | F24: =VLOOKUP($E24,Hybrid!$1:$1048576,MATCH(DATE(F$2,1,1),Hybrid!$A$1:$LI$1),FALSE) -> 0.24954447 | G24: =VLOOKUP($E24,Hybrid!$1:$1048576,MATCH(DATE(G$2,1,1),Hybrid!$A$1:$LI$1),FALSE) -> 0.25218263 | H24: =VLOOKUP($E24,Hybrid!$1:$1048576,MATCH(DATE(H$2,1,1),Hybrid!$A$1:$LI$1),FALSE) -> 0.25629925 | I24: =VLOOKUP($E24,Hybrid!$1:$1048576,MATCH(DATE(I$2,1,1),Hybrid!$A$1:$LI$1),FALSE) -> 0.26123432 | J24: =VLOOKUP($E24,Hybrid!$1:$1048576,MATCH(DATE(J$2,1,1),Hybrid!$A$1:$LI$1),FALSE) -> 0.26678419 | K24: =VLOOKUP($E24,Hybrid!$1:$1048576,MATCH(DATE(K$2,1,1),Hybrid!$A$1:$LI$1),FALSE) -> 0.27265652 | L24: =VLOOKUP($E24,Hybrid!$1:$1048576,MATCH(DATE(L$2,1,1),Hybrid!$A$1:$LI$1),FALSE) -> 0.27857942 | M24: =VLOOKUP($E24,Hybrid!$1:$1048576,MATCH(DATE(M$2,1,1),Hybrid!$A$1:$LI$1),FALSE) -> 0.28353309 | ... AO24: =VLOOKUP($E24,Hybrid!$1:$1048576,MATCH(DATE(AO$2,1,1),Hybrid!$A$1:$LI$1),FALSE) -> 0.3474707
D25: class E | E25: AUTO_ce_cgas_2 | F25: =VLOOKUP($E25,Hybrid!$1:$1048576,MATCH(DATE(F$2,1,1),Hybrid!$A$1:$LI$1),FALSE) -> 0.15020247 | G25: =VLOOKUP($E25,Hybrid!$1:$1048576,MATCH(DATE(G$2,1,1),Hybrid!$A$1:$LI$1),FALSE) -> 0.15198637 | H25: =VLOOKUP($E25,Hybrid!$1:$1048576,MATCH(DATE(H$2,1,1),Hybrid!$A$1:$LI$1),FALSE) -> 0.15459716 | I25: =VLOOKUP($E25,Hybrid!$1:$1048576,MATCH(DATE(I$2,1,1),Hybrid!$A$1:$LI$1),FALSE) -> 0.15761589 | J25: =VLOOKUP($E25,Hybrid!$1:$1048576,MATCH(DATE(J$2,1,1),Hybrid!$A$1:$LI$1),FALSE) -> 0.1609104 | K25: =VLOOKUP($E25,Hybrid!$1:$1048576,MATCH(DATE(K$2,1,1),Hybrid!$A$1:$LI$1),FALSE) -> 0.16430586 | L25: =VLOOKUP($E25,Hybrid!$1:$1048576,MATCH(DATE(L$2,1,1),Hybrid!$A$1:$LI$1),FALSE) -> 0.16764064 | M25: =VLOOKUP($E25,Hybrid!$1:$1048576,MATCH(DATE(M$2,1,1),Hybrid!$A$1:$LI$1),FALSE) -> 0.17029692 | ... AO25: =VLOOKUP($E25,Hybrid!$1:$1048576,MATCH(DATE(AO$2,1,1),Hybrid!$A$1:$LI$1),FALSE) -> 0.17582948
D26: class F | E26: AUTO_cf_cgas_2 | F26: =VLOOKUP($E26,Hybrid!$1:$1048576,MATCH(DATE(F$2,1,1),Hybrid!$A$1:$LI$1),FALSE) -> 0.074609436 | G26: =VLOOKUP($E26,Hybrid!$1:$1048576,MATCH(DATE(G$2,1,1),Hybrid!$A$1:$LI$1),FALSE) -> 0.075275469 | H26: =VLOOKUP($E26,Hybrid!$1:$1048576,MATCH(DATE(H$2,1,1),Hybrid!$A$1:$LI$1),FALSE) -> 0.076237746 | I26: =VLOOKUP($E26,Hybrid!$1:$1048576,MATCH(DATE(I$2,1,1),Hybrid!$A$1:$LI$1),FALSE) -> 0.077275137 | J26: =VLOOKUP($E26,Hybrid!$1:$1048576,MATCH(DATE(J$2,1,1),Hybrid!$A$1:$LI$1),FALSE) -> 0.078314797 | K26: =VLOOKUP($E26,Hybrid!$1:$1048576,MATCH(DATE(K$2,1,1),Hybrid!$A$1:$LI$1),FALSE) -> 0.079279187 | L26: =VLOOKUP($E26,Hybrid!$1:$1048576,MATCH(DATE(L$2,1,1),Hybrid!$A$1:$LI$1),FALSE) -> 0.080100755 | M26: =VLOOKUP($E26,Hybrid!$1:$1048576,MATCH(DATE(M$2,1,1),Hybrid!$A$1:$LI$1),FALSE) -> 0.080511285 | ... AO26: =VLOOKUP($E26,Hybrid!$1:$1048576,MATCH(DATE(AO$2,1,1),Hybrid!$A$1:$LI$1),FALSE) -> 0.049645857
D27: class G | E27: AUTO_cg_cgas_2 | F27: =VLOOKUP($E27,Hybrid!$1:$1048576,MATCH(DATE(F$2,1,1),Hybrid!$A$1:$LI$1),FALSE) -> 0.13435819 | G27: =VLOOKUP($E27,Hybrid!$1:$1048576,MATCH(DATE(G$2,1,1),Hybrid!$A$1:$LI$1),FALSE) -> 0.13584514 | H27: =VLOOKUP($E27,Hybrid!$1:$1048576,MATCH(DATE(H$2,1,1),Hybrid!$A$1:$LI$1),FALSE) -> 0.13768976 | I27: =VLOOKUP($E27,Hybrid!$1:$1048576,MATCH(DATE(I$2,1,1),Hybrid!$A$1:$LI$1),FALSE) -> 0.13945774 | J27: =VLOOKUP($E27,Hybrid!$1:$1048576,MATCH(DATE(J$2,1,1),Hybrid!$A$1:$LI$1),FALSE) -> 0.14101039 | K27: =VLOOKUP($E27,Hybrid!$1:$1048576,MATCH(DATE(K$2,1,1),Hybrid!$A$1:$LI$1),FALSE) -> 0.14222471 | L27: =VLOOKUP($E27,Hybrid!$1:$1048576,MATCH(DATE(L$2,1,1),Hybrid!$A$1:$LI$1),FALSE) -> 0.14300149 | M27: =VLOOKUP($E27,Hybrid!$1:$1048576,MATCH(DATE(M$2,1,1),Hybrid!$A$1:$LI$1),FALSE) -> 0.14289621 | ... AO27: =VLOOKUP($E27,Hybrid!$1:$1048576,MATCH(DATE(AO$2,1,1),Hybrid!$A$1:$LI$1),FALSE) -> 0.06159694
C28: TOTAL STOCK BASELINE | E28: AUTO_0 | F28: =VLOOKUP($E28,Hybrid!$1:$1048576,MATCH(DATE(F$2,1,1),Hybrid!$A$1:$LI$1),FALSE) -> 32317.941 | G28: =VLOOKUP($E28,Hybrid!$1:$1048576,MATCH(DATE(G$2,1,1),Hybrid!$A$1:$LI$1),FALSE) -> 31911.217 | H28: =VLOOKUP($E28,Hybrid!$1:$1048576,MATCH(DATE(H$2,1,1),Hybrid!$A$1:$LI$1),FALSE) -> 31732.935 | I28: =VLOOKUP($E28,Hybrid!$1:$1048576,MATCH(DATE(I$2,1,1),Hybrid!$A$1:$LI$1),FALSE) -> 31702.286 | J28: =VLOOKUP($E28,Hybrid!$1:$1048576,MATCH(DATE(J$2,1,1),Hybrid!$A$1:$LI$1),FALSE) -> 31792.126 | K28: =VLOOKUP($E28,Hybrid!$1:$1048576,MATCH(DATE(K$2,1,1),Hybrid!$A$1:$LI$1),FALSE) -> 31964.155 | L28: =VLOOKUP($E28,Hybrid!$1:$1048576,MATCH(DATE(L$2,1,1),Hybrid!$A$1:$LI$1),FALSE) -> 32173.16 | M28: =VLOOKUP($E28,Hybrid!$1:$1048576,MATCH(DATE(M$2,1,1),Hybrid!$A$1:$LI$1),FALSE) -> 32399.008 | ... AO28: =VLOOKUP($E28,Hybrid!$1:$1048576,MATCH(DATE(AO$2,1,1),Hybrid!$A$1:$LI$1),FALSE) -> 42106.337
C29: OIL | E29: AUTO_cfut_0 | F29: =VLOOKUP($E29,Hybrid!$1:$1048576,MATCH(DATE(F$2,1,1),Hybrid!$A$1:$LI$1),FALSE) -> 32271.24 | G29: =VLOOKUP($E29,Hybrid!$1:$1048576,MATCH(DATE(G$2,1,1),Hybrid!$A$1:$LI$1),FALSE) -> 31846.407 | H29: =VLOOKUP($E29,Hybrid!$1:$1048576,MATCH(DATE(H$2,1,1),Hybrid!$A$1:$LI$1),FALSE) -> 31648.242 | I29: =VLOOKUP($E29,Hybrid!$1:$1048576,MATCH(DATE(I$2,1,1),Hybrid!$A$1:$LI$1),FALSE) -> 31596.228 | J29: =VLOOKUP($E29,Hybrid!$1:$1048576,MATCH(DATE(J$2,1,1),Hybrid!$A$1:$LI$1),FALSE) -> 31663.113 | K29: =VLOOKUP($E29,Hybrid!$1:$1048576,MATCH(DATE(K$2,1,1),Hybrid!$A$1:$LI$1),FALSE) -> 31810.955 | L29: =VLOOKUP($E29,Hybrid!$1:$1048576,MATCH(DATE(L$2,1,1),Hybrid!$A$1:$LI$1),FALSE) -> 31994.923 | M29: =VLOOKUP($E29,Hybrid!$1:$1048576,MATCH(DATE(M$2,1,1),Hybrid!$A$1:$LI$1),FALSE) -> 32194.829 | ... AO29: =VLOOKUP($E29,Hybrid!$1:$1048576,MATCH(DATE(AO$2,1,1),Hybrid!$A$1:$LI$1),FALSE) -> 39079.453
D30: class A | E30: AUTO_ca_cfut_0 | F30: =VLOOKUP($E30,Hybrid!$1:$1048576,MATCH(DATE(F$2,1,1),Hybrid!$A$1:$LI$1),FALSE) -> 7095.7005 | G30: =VLOOKUP($E30,Hybrid!$1:$1048576,MATCH(DATE(G$2,1,1),Hybrid!$A$1:$LI$1),FALSE) -> 7136.7578 | H30: =VLOOKUP($E30,Hybrid!$1:$1048576,MATCH(DATE(H$2,1,1),Hybrid!$A$1:$LI$1),FALSE) -> 7234.0597 | I30: =VLOOKUP($E30,Hybrid!$1:$1048576,MATCH(DATE(I$2,1,1),Hybrid!$A$1:$LI$1),FALSE) -> 7366.577 | J30: =VLOOKUP($E30,Hybrid!$1:$1048576,MATCH(DATE(J$2,1,1),Hybrid!$A$1:$LI$1),FALSE) -> 7527.8349 | K30: =VLOOKUP($E30,Hybrid!$1:$1048576,MATCH(DATE(K$2,1,1),Hybrid!$A$1:$LI$1),FALSE) -> 7707.4422 | L30: =VLOOKUP($E30,Hybrid!$1:$1048576,MATCH(DATE(L$2,1,1),Hybrid!$A$1:$LI$1),FALSE) -> 7893.0002 | M30: =VLOOKUP($E30,Hybrid!$1:$1048576,MATCH(DATE(M$2,1,1),Hybrid!$A$1:$LI$1),FALSE) -> 8079.383 | ... AO30: =VLOOKUP($E30,Hybrid!$1:$1048576,MATCH(DATE(AO$2,1,1),Hybrid!$A$1:$LI$1),FALSE) -> 12827.333
D31: class B | E31: AUTO_cb_cfut_0 | F31: =VLOOKUP($E31,Hybrid!$1:$1048576,MATCH(DATE(F$2,1,1),Hybrid!$A$1:$LI$1),FALSE) -> 8251.2564 | G31: =VLOOKUP($E31,Hybrid!$1:$1048576,MATCH(DATE(G$2,1,1),Hybrid!$A$1:$LI$1),FALSE) -> 8178.01 | H31: =VLOOKUP($E31,Hybrid!$1:$1048576,MATCH(DATE(H$2,1,1),Hybrid!$A$1:$LI$1),FALSE) -> 8166.4716 | I31: =VLOOKUP($E31,Hybrid!$1:$1048576,MATCH(DATE(I$2,1,1),Hybrid!$A$1:$LI$1),FALSE) -> 8195.5437 | J31: =VLOOKUP($E31,Hybrid!$1:$1048576,MATCH(DATE(J$2,1,1),Hybrid!$A$1:$LI$1),FALSE) -> 8258.2796 | K31: =VLOOKUP($E31,Hybrid!$1:$1048576,MATCH(DATE(K$2,1,1),Hybrid!$A$1:$LI$1),FALSE) -> 8344.2948 | L31: =VLOOKUP($E31,Hybrid!$1:$1048576,MATCH(DATE(L$2,1,1),Hybrid!$A$1:$LI$1),FALSE) -> 8441.2299 | M31: =VLOOKUP($E31,Hybrid!$1:$1048576,MATCH(DATE(M$2,1,1),Hybrid!$A$1:$LI$1),FALSE) -> 8543.5831 | ... AO31: =VLOOKUP($E31,Hybrid!$1:$1048576,MATCH(DATE(AO$2,1,1),Hybrid!$A$1:$LI$1),FALSE) -> 11732.141
D32: class C | E32: AUTO_cc_cfut_0 | F32: =VLOOKUP($E32,Hybrid!$1:$1048576,MATCH(DATE(F$2,1,1),Hybrid!$A$1:$LI$1),FALSE) -> 6777.6025 | G32: =VLOOKUP($E32,Hybrid!$1:$1048576,MATCH(DATE(G$2,1,1),Hybrid!$A$1:$LI$1),FALSE) -> 6643.4662 | H32: =VLOOKUP($E32,Hybrid!$1:$1048576,MATCH(DATE(H$2,1,1),Hybrid!$A$1:$LI$1),FALSE) -> 6557.8115 | I32: =VLOOKUP($E32,Hybrid!$1:$1048576,MATCH(DATE(I$2,1,1),Hybrid!$A$1:$LI$1),FALSE) -> 6505.379 | J32: =VLOOKUP($E32,Hybrid!$1:$1048576,MATCH(DATE(J$2,1,1),Hybrid!$A$1:$LI$1),FALSE) -> 6480.8301 | K32: =VLOOKUP($E32,Hybrid!$1:$1048576,MATCH(DATE(K$2,1,1),Hybrid!$A$1:$LI$1),FALSE) -> 6476.6688 | L32: =VLOOKUP($E32,Hybrid!$1:$1048576,MATCH(DATE(L$2,1,1),Hybrid!$A$1:$LI$1),FALSE) -> 6484.0027 | M32: =VLOOKUP($E32,Hybrid!$1:$1048576,MATCH(DATE(M$2,1,1),Hybrid!$A$1:$LI$1),FALSE) -> 6498.6046 | ... AO32: =VLOOKUP($E32,Hybrid!$1:$1048576,MATCH(DATE(AO$2,1,1),Hybrid!$A$1:$LI$1),FALSE) -> 7758.1666
D33: class D | E33: AUTO_cd_cfut_0 | F33: =VLOOKUP($E33,Hybrid!$1:$1048576,MATCH(DATE(F$2,1,1),Hybrid!$A$1:$LI$1),FALSE) -> 4159.6639 | G33: =VLOOKUP($E33,Hybrid!$1:$1048576,MATCH(DATE(G$2,1,1),Hybrid!$A$1:$LI$1),FALSE) -> 4053.0059 | H33: =VLOOKUP($E33,Hybrid!$1:$1048576,MATCH(DATE(H$2,1,1),Hybrid!$A$1:$LI$1),FALSE) -> 3974.2092 | I33: =VLOOKUP($E33,Hybrid!$1:$1048576,MATCH(DATE(I$2,1,1),Hybrid!$A$1:$LI$1),FALSE) -> 3914.3493 | J33: =VLOOKUP($E33,Hybrid!$1:$1048576,MATCH(DATE(J$2,1,1),Hybrid!$A$1:$LI$1),FALSE) -> 3870.1372 | K33: =VLOOKUP($E33,Hybrid!$1:$1048576,MATCH(DATE(K$2,1,1),Hybrid!$A$1:$LI$1),FALSE) -> 3837.333 | L33: =VLOOKUP($E33,Hybrid!$1:$1048576,MATCH(DATE(L$2,1,1),Hybrid!$A$1:$LI$1),FALSE) -> 3810.9678 | M33: =VLOOKUP($E33,Hybrid!$1:$1048576,MATCH(DATE(M$2,1,1),Hybrid!$A$1:$LI$1),FALSE) -> 3788.5845 | ... AO33: =VLOOKUP($E33,Hybrid!$1:$1048576,MATCH(DATE(AO$2,1,1),Hybrid!$A$1:$LI$1),FALSE) -> 3679.0785
D34: class E | E34: AUTO_ce_cfut_0 | F34: =VLOOKUP($E34,Hybrid!$1:$1048576,MATCH(DATE(F$2,1,1),Hybrid!$A$1:$LI$1),FALSE) -> 2503.7292 | G34: =VLOOKUP($E34,Hybrid!$1:$1048576,MATCH(DATE(G$2,1,1),Hybrid!$A$1:$LI$1),FALSE) -> 2441.8639 | H34: =VLOOKUP($E34,Hybrid!$1:$1048576,MATCH(DATE(H$2,1,1),Hybrid!$A$1:$LI$1),FALSE) -> 2395.9826 | I34: =VLOOKUP($E34,Hybrid!$1:$1048576,MATCH(DATE(I$2,1,1),Hybrid!$A$1:$LI$1),FALSE) -> 2360.47 | J34: =VLOOKUP($E34,Hybrid!$1:$1048576,MATCH(DATE(J$2,1,1),Hybrid!$A$1:$LI$1),FALSE) -> 2333.2493 | K34: =VLOOKUP($E34,Hybrid!$1:$1048576,MATCH(DATE(K$2,1,1),Hybrid!$A$1:$LI$1),FALSE) -> 2311.7997 | L34: =VLOOKUP($E34,Hybrid!$1:$1048576,MATCH(DATE(L$2,1,1),Hybrid!$A$1:$LI$1),FALSE) -> 2293.1629 | M34: =VLOOKUP($E34,Hybrid!$1:$1048576,MATCH(DATE(M$2,1,1),Hybrid!$A$1:$LI$1),FALSE) -> 2275.8689 | ... AO34: =VLOOKUP($E34,Hybrid!$1:$1048576,MATCH(DATE(AO$2,1,1),Hybrid!$A$1:$LI$1),FALSE) -> 1889.3761
D35: class F | E35: AUTO_cf_cfut_0 | F35: =VLOOKUP($E35,Hybrid!$1:$1048576,MATCH(DATE(F$2,1,1),Hybrid!$A$1:$LI$1),FALSE) -> 1243.6668 | G35: =VLOOKUP($E35,Hybrid!$1:$1048576,MATCH(DATE(G$2,1,1),Hybrid!$A$1:$LI$1),FALSE) -> 1210.3171 | H35: =VLOOKUP($E35,Hybrid!$1:$1048576,MATCH(DATE(H$2,1,1),Hybrid!$A$1:$LI$1),FALSE) -> 1183.5844 | I35: =VLOOKUP($E35,Hybrid!$1:$1048576,MATCH(DATE(I$2,1,1),Hybrid!$A$1:$LI$1),FALSE) -> 1160.542 | J35: =VLOOKUP($E35,Hybrid!$1:$1048576,MATCH(DATE(J$2,1,1),Hybrid!$A$1:$LI$1),FALSE) -> 1140.0916 | K35: =VLOOKUP($E35,Hybrid!$1:$1048576,MATCH(DATE(K$2,1,1),Hybrid!$A$1:$LI$1),FALSE) -> 1121.1101 | L35: =VLOOKUP($E35,Hybrid!$1:$1048576,MATCH(DATE(L$2,1,1),Hybrid!$A$1:$LI$1),FALSE) -> 1102.3247 | M35: =VLOOKUP($E35,Hybrid!$1:$1048576,MATCH(DATE(M$2,1,1),Hybrid!$A$1:$LI$1),FALSE) -> 1083.1332 | ... AO35: =VLOOKUP($E35,Hybrid!$1:$1048576,MATCH(DATE(AO$2,1,1),Hybrid!$A$1:$LI$1),FALSE) -> 533.03049
D36: class G | E36: AUTO_cg_cfut_0 | F36: =VLOOKUP($E36,Hybrid!$1:$1048576,MATCH(DATE(F$2,1,1),Hybrid!$A$1:$LI$1),FALSE) -> 2239.6206 | G36: =VLOOKUP($E36,Hybrid!$1:$1048576,MATCH(DATE(G$2,1,1),Hybrid!$A$1:$LI$1),FALSE) -> 2182.9863 | H36: =VLOOKUP($E36,Hybrid!$1:$1048576,MATCH(DATE(H$2,1,1),Hybrid!$A$1:$LI$1),FALSE) -> 2136.1231 | I36: =VLOOKUP($E36,Hybrid!$1:$1048576,MATCH(DATE(I$2,1,1),Hybrid!$A$1:$LI$1),FALSE) -> 2093.3668 | J36: =VLOOKUP($E36,Hybrid!$1:$1048576,MATCH(DATE(J$2,1,1),Hybrid!$A$1:$LI$1),FALSE) -> 2052.69 | K36: =VLOOKUP($E36,Hybrid!$1:$1048576,MATCH(DATE(K$2,1,1),Hybrid!$A$1:$LI$1),FALSE) -> 2012.3066 | L36: =VLOOKUP($E36,Hybrid!$1:$1048576,MATCH(DATE(L$2,1,1),Hybrid!$A$1:$LI$1),FALSE) -> 1970.2347 | M36: =VLOOKUP($E36,Hybrid!$1:$1048576,MATCH(DATE(M$2,1,1),Hybrid!$A$1:$LI$1),FALSE) -> 1925.6713 | ... AO36: =VLOOKUP($E36,Hybrid!$1:$1048576,MATCH(DATE(AO$2,1,1),Hybrid!$A$1:$LI$1),FALSE) -> 660.32725
C37: ELEC | E37: AUTO_cele_0 | F37: =VLOOKUP($E37,Hybrid!$1:$1048576,MATCH(DATE(F$2,1,1),Hybrid!$A$1:$LI$1),FALSE) -> 44.765 | G37: =VLOOKUP($E37,Hybrid!$1:$1048576,MATCH(DATE(G$2,1,1),Hybrid!$A$1:$LI$1),FALSE) -> 62.819188 | H37: =VLOOKUP($E37,Hybrid!$1:$1048576,MATCH(DATE(H$2,1,1),Hybrid!$A$1:$LI$1),FALSE) -> 82.635226 | I37: =VLOOKUP($E37,Hybrid!$1:$1048576,MATCH(DATE(I$2,1,1),Hybrid!$A$1:$LI$1),FALSE) -> 103.92645 | J37: =VLOOKUP($E37,Hybrid!$1:$1048576,MATCH(DATE(J$2,1,1),Hybrid!$A$1:$LI$1),FALSE) -> 126.8031 | K37: =VLOOKUP($E37,Hybrid!$1:$1048576,MATCH(DATE(K$2,1,1),Hybrid!$A$1:$LI$1),FALSE) -> 150.90795 | L37: =VLOOKUP($E37,Hybrid!$1:$1048576,MATCH(DATE(L$2,1,1),Hybrid!$A$1:$LI$1),FALSE) -> 175.86538 | M37: =VLOOKUP($E37,Hybrid!$1:$1048576,MATCH(DATE(M$2,1,1),Hybrid!$A$1:$LI$1),FALSE) -> 201.72995 | ... AO37: =VLOOKUP($E37,Hybrid!$1:$1048576,MATCH(DATE(AO$2,1,1),Hybrid!$A$1:$LI$1),FALSE) -> 3023.0184
D38: class A | E38: AUTO_ca_cele_0 | F38: =VLOOKUP($E38,Hybrid!$1:$1048576,MATCH(DATE(F$2,1,1),Hybrid!$A$1:$LI$1),FALSE) -> 9.8427899 | G38: =VLOOKUP($E38,Hybrid!$1:$1048576,MATCH(DATE(G$2,1,1),Hybrid!$A$1:$LI$1),FALSE) -> 15.102615 | H38: =VLOOKUP($E38,Hybrid!$1:$1048576,MATCH(DATE(H$2,1,1),Hybrid!$A$1:$LI$1),FALSE) -> 20.915324 | I38: =VLOOKUP($E38,Hybrid!$1:$1048576,MATCH(DATE(I$2,1,1),Hybrid!$A$1:$LI$1),FALSE) -> 27.220552 | J38: =VLOOKUP($E38,Hybrid!$1:$1048576,MATCH(DATE(J$2,1,1),Hybrid!$A$1:$LI$1),FALSE) -> 34.066405 | K38: =VLOOKUP($E38,Hybrid!$1:$1048576,MATCH(DATE(K$2,1,1),Hybrid!$A$1:$LI$1),FALSE) -> 41.350772 | L38: =VLOOKUP($E38,Hybrid!$1:$1048576,MATCH(DATE(L$2,1,1),Hybrid!$A$1:$LI$1),FALSE) -> 48.968229 | M38: =VLOOKUP($E38,Hybrid!$1:$1048576,MATCH(DATE(M$2,1,1),Hybrid!$A$1:$LI$1),FALSE) -> 56.946203 | ... AO38: =VLOOKUP($E38,Hybrid!$1:$1048576,MATCH(DATE(AO$2,1,1),Hybrid!$A$1:$LI$1),FALSE) -> 1037.1553
D39: class B | E39: AUTO_cb_cele_0 | F39: =VLOOKUP($E39,Hybrid!$1:$1048576,MATCH(DATE(F$2,1,1),Hybrid!$A$1:$LI$1),FALSE) -> 11.445717 | G39: =VLOOKUP($E39,Hybrid!$1:$1048576,MATCH(DATE(G$2,1,1),Hybrid!$A$1:$LI$1),FALSE) -> 16.422266 | H39: =VLOOKUP($E39,Hybrid!$1:$1048576,MATCH(DATE(H$2,1,1),Hybrid!$A$1:$LI$1),FALSE) -> 21.938274 | I39: =VLOOKUP($E39,Hybrid!$1:$1048576,MATCH(DATE(I$2,1,1),Hybrid!$A$1:$LI$1),FALSE) -> 27.939833 | J39: =VLOOKUP($E39,Hybrid!$1:$1048576,MATCH(DATE(J$2,1,1),Hybrid!$A$1:$LI$1),FALSE) -> 34.476478 | K39: =VLOOKUP($E39,Hybrid!$1:$1048576,MATCH(DATE(K$2,1,1),Hybrid!$A$1:$LI$1),FALSE) -> 41.448912 | L39: =VLOOKUP($E39,Hybrid!$1:$1048576,MATCH(DATE(L$2,1,1),Hybrid!$A$1:$LI$1),FALSE) -> 48.754923 | M39: =VLOOKUP($E39,Hybrid!$1:$1048576,MATCH(DATE(M$2,1,1),Hybrid!$A$1:$LI$1),FALSE) -> 56.422093 | ... AO39: =VLOOKUP($E39,Hybrid!$1:$1048576,MATCH(DATE(AO$2,1,1),Hybrid!$A$1:$LI$1),FALSE) -> 1001.755
D40: class C | E40: AUTO_cc_cele_0 | F40: =VLOOKUP($E40,Hybrid!$1:$1048576,MATCH(DATE(F$2,1,1),Hybrid!$A$1:$LI$1),FALSE) -> 9.4015406 | G40: =VLOOKUP($E40,Hybrid!$1:$1048576,MATCH(DATE(G$2,1,1),Hybrid!$A$1:$LI$1),FALSE) -> 12.791178 | H40: =VLOOKUP($E40,Hybrid!$1:$1048576,MATCH(DATE(H$2,1,1),Hybrid!$A$1:$LI$1),FALSE) -> 16.559687 | I40: =VLOOKUP($E40,Hybrid!$1:$1048576,MATCH(DATE(I$2,1,1),Hybrid!$A$1:$LI$1),FALSE) -> 20.67215 | J40: =VLOOKUP($E40,Hybrid!$1:$1048576,MATCH(DATE(J$2,1,1),Hybrid!$A$1:$LI$1),FALSE) -> 25.164793 | K40: =VLOOKUP($E40,Hybrid!$1:$1048576,MATCH(DATE(K$2,1,1),Hybrid!$A$1:$LI$1),FALSE) -> 29.968027 | L40: =VLOOKUP($E40,Hybrid!$1:$1048576,MATCH(DATE(L$2,1,1),Hybrid!$A$1:$LI$1),FALSE) -> 35.010357 | M40: =VLOOKUP($E40,Hybrid!$1:$1048576,MATCH(DATE(M$2,1,1),Hybrid!$A$1:$LI$1),FALSE) -> 40.311398 | ... AO40: =VLOOKUP($E40,Hybrid!$1:$1048576,MATCH(DATE(AO$2,1,1),Hybrid!$A$1:$LI$1),FALSE) -> 693.35391
D41: class D | E41: AUTO_cd_cele_0 | F41: =VLOOKUP($E41,Hybrid!$1:$1048576,MATCH(DATE(F$2,1,1),Hybrid!$A$1:$LI$1),FALSE) -> 5.7700713 | G41: =VLOOKUP($E41,Hybrid!$1:$1048576,MATCH(DATE(G$2,1,1),Hybrid!$A$1:$LI$1),FALSE) -> 7.5799114 | H41: =VLOOKUP($E41,Hybrid!$1:$1048576,MATCH(DATE(H$2,1,1),Hybrid!$A$1:$LI$1),FALSE) -> 9.5402273 | I41: =VLOOKUP($E41,Hybrid!$1:$1048576,MATCH(DATE(I$2,1,1),Hybrid!$A$1:$LI$1),FALSE) -> 11.603567 | J41: =VLOOKUP($E41,Hybrid!$1:$1048576,MATCH(DATE(J$2,1,1),Hybrid!$A$1:$LI$1),FALSE) -> 13.766447 | K41: =VLOOKUP($E41,Hybrid!$1:$1048576,MATCH(DATE(K$2,1,1),Hybrid!$A$1:$LI$1),FALSE) -> 15.993768 | L41: =VLOOKUP($E41,Hybrid!$1:$1048576,MATCH(DATE(L$2,1,1),Hybrid!$A$1:$LI$1),FALSE) -> 18.245263 | M41: =VLOOKUP($E41,Hybrid!$1:$1048576,MATCH(DATE(M$2,1,1),Hybrid!$A$1:$LI$1),FALSE) -> 20.51434 | ... AO41: =VLOOKUP($E41,Hybrid!$1:$1048576,MATCH(DATE(AO$2,1,1),Hybrid!$A$1:$LI$1),FALSE) -> 164.82658
D42: class E | E42: AUTO_ce_cele_0 | F42: =VLOOKUP($E42,Hybrid!$1:$1048576,MATCH(DATE(F$2,1,1),Hybrid!$A$1:$LI$1),FALSE) -> 3.4730441 | G42: =VLOOKUP($E42,Hybrid!$1:$1048576,MATCH(DATE(G$2,1,1),Hybrid!$A$1:$LI$1),FALSE) -> 4.5874377 | H42: =VLOOKUP($E42,Hybrid!$1:$1048576,MATCH(DATE(H$2,1,1),Hybrid!$A$1:$LI$1),FALSE) -> 5.7895749 | I42: =VLOOKUP($E42,Hybrid!$1:$1048576,MATCH(DATE(I$2,1,1),Hybrid!$A$1:$LI$1),FALSE) -> 7.0494691 | J42: =VLOOKUP($E42,Hybrid!$1:$1048576,MATCH(DATE(J$2,1,1),Hybrid!$A$1:$LI$1),FALSE) -> 8.3642148 | K42: =VLOOKUP($E42,Hybrid!$1:$1048576,MATCH(DATE(K$2,1,1),Hybrid!$A$1:$LI$1),FALSE) -> 9.7114329 | L42: =VLOOKUP($E42,Hybrid!$1:$1048576,MATCH(DATE(L$2,1,1),Hybrid!$A$1:$LI$1),FALSE) -> 11.06589 | M42: =VLOOKUP($E42,Hybrid!$1:$1048576,MATCH(DATE(M$2,1,1),Hybrid!$A$1:$LI$1),FALSE) -> 12.423106 | ... AO42: =VLOOKUP($E42,Hybrid!$1:$1048576,MATCH(DATE(AO$2,1,1),Hybrid!$A$1:$LI$1),FALSE) -> 89.910774
D43: class F | E43: AUTO_cf_cele_0 | F43: =VLOOKUP($E43,Hybrid!$1:$1048576,MATCH(DATE(F$2,1,1),Hybrid!$A$1:$LI$1),FALSE) -> 1.7251505 | G43: =VLOOKUP($E43,Hybrid!$1:$1048576,MATCH(DATE(G$2,1,1),Hybrid!$A$1:$LI$1),FALSE) -> 2.2500569 | H43: =VLOOKUP($E43,Hybrid!$1:$1048576,MATCH(DATE(H$2,1,1),Hybrid!$A$1:$LI$1),FALSE) -> 2.7997473 | I43: =VLOOKUP($E43,Hybrid!$1:$1048576,MATCH(DATE(I$2,1,1),Hybrid!$A$1:$LI$1),FALSE) -> 3.3544502 | J43: =VLOOKUP($E43,Hybrid!$1:$1048576,MATCH(DATE(J$2,1,1),Hybrid!$A$1:$LI$1),FALSE) -> 3.9088075 | K43: =VLOOKUP($E43,Hybrid!$1:$1048576,MATCH(DATE(K$2,1,1),Hybrid!$A$1:$LI$1),FALSE) -> 4.4525897 | L43: =VLOOKUP($E43,Hybrid!$1:$1048576,MATCH(DATE(L$2,1,1),Hybrid!$A$1:$LI$1),FALSE) -> 4.9743938 | M43: =VLOOKUP($E43,Hybrid!$1:$1048576,MATCH(DATE(M$2,1,1),Hybrid!$A$1:$LI$1),FALSE) -> 5.4706762 | ... AO43: =VLOOKUP($E43,Hybrid!$1:$1048576,MATCH(DATE(AO$2,1,1),Hybrid!$A$1:$LI$1),FALSE) -> 16.341276
D44: class G | E44: AUTO_cg_cele_0 | F44: =VLOOKUP($E44,Hybrid!$1:$1048576,MATCH(DATE(F$2,1,1),Hybrid!$A$1:$LI$1),FALSE) -> 3.1066862 | G44: =VLOOKUP($E44,Hybrid!$1:$1048576,MATCH(DATE(G$2,1,1),Hybrid!$A$1:$LI$1),FALSE) -> 4.0857232 | H44: =VLOOKUP($E44,Hybrid!$1:$1048576,MATCH(DATE(H$2,1,1),Hybrid!$A$1:$LI$1),FALSE) -> 5.0923917 | I44: =VLOOKUP($E44,Hybrid!$1:$1048576,MATCH(DATE(I$2,1,1),Hybrid!$A$1:$LI$1),FALSE) -> 6.0864298 | J44: =VLOOKUP($E44,Hybrid!$1:$1048576,MATCH(DATE(J$2,1,1),Hybrid!$A$1:$LI$1),FALSE) -> 7.055959 | K44: =VLOOKUP($E44,Hybrid!$1:$1048576,MATCH(DATE(K$2,1,1),Hybrid!$A$1:$LI$1),FALSE) -> 7.982451 | L44: =VLOOKUP($E44,Hybrid!$1:$1048576,MATCH(DATE(L$2,1,1),Hybrid!$A$1:$LI$1),FALSE) -> 8.8463232 | M44: =VLOOKUP($E44,Hybrid!$1:$1048576,MATCH(DATE(M$2,1,1),Hybrid!$A$1:$LI$1),FALSE) -> 9.6421382 | ... AO44: =VLOOKUP($E44,Hybrid!$1:$1048576,MATCH(DATE(AO$2,1,1),Hybrid!$A$1:$LI$1),FALSE) -> 19.675526
C45: GAS | E45: AUTO_cgas_0 | F45: =VLOOKUP($E45,Hybrid!$1:$1048576,MATCH(DATE(F$2,1,1),Hybrid!$A$1:$LI$1),FALSE) -> 1.936 | G45: =VLOOKUP($E45,Hybrid!$1:$1048576,MATCH(DATE(G$2,1,1),Hybrid!$A$1:$LI$1),FALSE) -> 1.990293 | H45: =VLOOKUP($E45,Hybrid!$1:$1048576,MATCH(DATE(H$2,1,1),Hybrid!$A$1:$LI$1),FALSE) -> 2.0574577 | I45: =VLOOKUP($E45,Hybrid!$1:$1048576,MATCH(DATE(I$2,1,1),Hybrid!$A$1:$LI$1),FALSE) -> 2.1314073 | J45: =VLOOKUP($E45,Hybrid!$1:$1048576,MATCH(DATE(J$2,1,1),Hybrid!$A$1:$LI$1),FALSE) -> 2.2103839 | K45: =VLOOKUP($E45,Hybrid!$1:$1048576,MATCH(DATE(K$2,1,1),Hybrid!$A$1:$LI$1),FALSE) -> 2.2916631 | L45: =VLOOKUP($E45,Hybrid!$1:$1048576,MATCH(DATE(L$2,1,1),Hybrid!$A$1:$LI$1),FALSE) -> 2.3718638 | M45: =VLOOKUP($E45,Hybrid!$1:$1048576,MATCH(DATE(M$2,1,1),Hybrid!$A$1:$LI$1),FALSE) -> 2.4495936 | ... AO45: =VLOOKUP($E45,Hybrid!$1:$1048576,MATCH(DATE(AO$2,1,1),Hybrid!$A$1:$LI$1),FALSE) -> 3.8659259
D46: class A | E46: AUTO_ca_cgas_0 | F46: =VLOOKUP($E46,Hybrid!$1:$1048576,MATCH(DATE(F$2,1,1),Hybrid!$A$1:$LI$1),FALSE) -> 0.4256817 | G46: =VLOOKUP($E46,Hybrid!$1:$1048576,MATCH(DATE(G$2,1,1),Hybrid!$A$1:$LI$1),FALSE) -> 0.44891627 | H46: =VLOOKUP($E46,Hybrid!$1:$1048576,MATCH(DATE(H$2,1,1),Hybrid!$A$1:$LI$1),FALSE) -> 0.47569228 | I46: =VLOOKUP($E46,Hybrid!$1:$1048576,MATCH(DATE(I$2,1,1),Hybrid!$A$1:$LI$1),FALSE) -> 0.5043894 | J46: =VLOOKUP($E46,Hybrid!$1:$1048576,MATCH(DATE(J$2,1,1),Hybrid!$A$1:$LI$1),FALSE) -> 0.53457386 | K46: =VLOOKUP($E46,Hybrid!$1:$1048576,MATCH(DATE(K$2,1,1),Hybrid!$A$1:$LI$1),FALSE) -> 0.56546762 | L46: =VLOOKUP($E46,Hybrid!$1:$1048576,MATCH(DATE(L$2,1,1),Hybrid!$A$1:$LI$1),FALSE) -> 0.59610468 | M46: =VLOOKUP($E46,Hybrid!$1:$1048576,MATCH(DATE(M$2,1,1),Hybrid!$A$1:$LI$1),FALSE) -> 0.62610936 | ... AO46: =VLOOKUP($E46,Hybrid!$1:$1048576,MATCH(DATE(AO$2,1,1),Hybrid!$A$1:$LI$1),FALSE) -> 1.2590638
D47: class B | E47: AUTO_cb_cgas_0 | F47: =VLOOKUP($E47,Hybrid!$1:$1048576,MATCH(DATE(F$2,1,1),Hybrid!$A$1:$LI$1),FALSE) -> 0.49500523 | G47: =VLOOKUP($E47,Hybrid!$1:$1048576,MATCH(DATE(G$2,1,1),Hybrid!$A$1:$LI$1),FALSE) -> 0.51185913 | H47: =VLOOKUP($E47,Hybrid!$1:$1048576,MATCH(DATE(H$2,1,1),Hybrid!$A$1:$LI$1),FALSE) -> 0.53236494 | I47: =VLOOKUP($E47,Hybrid!$1:$1048576,MATCH(DATE(I$2,1,1),Hybrid!$A$1:$LI$1),FALSE) -> 0.55492544 | J47: =VLOOKUP($E47,Hybrid!$1:$1048576,MATCH(DATE(J$2,1,1),Hybrid!$A$1:$LI$1),FALSE) -> 0.5790941 | K47: =VLOOKUP($E47,Hybrid!$1:$1048576,MATCH(DATE(K$2,1,1),Hybrid!$A$1:$LI$1),FALSE) -> 0.60411809 | L47: =VLOOKUP($E47,Hybrid!$1:$1048576,MATCH(DATE(L$2,1,1),Hybrid!$A$1:$LI$1),FALSE) -> 0.62905782 | M47: =VLOOKUP($E47,Hybrid!$1:$1048576,MATCH(DATE(M$2,1,1),Hybrid!$A$1:$LI$1),FALSE) -> 0.65352776 | ... AO47: =VLOOKUP($E47,Hybrid!$1:$1048576,MATCH(DATE(AO$2,1,1),Hybrid!$A$1:$LI$1),FALSE) -> 1.1556812
D48: class C | E48: AUTO_cc_cgas_0 | F48: =VLOOKUP($E48,Hybrid!$1:$1048576,MATCH(DATE(F$2,1,1),Hybrid!$A$1:$LI$1),FALSE) -> 0.40659852 | G48: =VLOOKUP($E48,Hybrid!$1:$1048576,MATCH(DATE(G$2,1,1),Hybrid!$A$1:$LI$1),FALSE) -> 0.41422794 | H48: =VLOOKUP($E48,Hybrid!$1:$1048576,MATCH(DATE(H$2,1,1),Hybrid!$A$1:$LI$1),FALSE) -> 0.42457655 | I48: =VLOOKUP($E48,Hybrid!$1:$1048576,MATCH(DATE(I$2,1,1),Hybrid!$A$1:$LI$1),FALSE) -> 0.4365094 | J48: =VLOOKUP($E48,Hybrid!$1:$1048576,MATCH(DATE(J$2,1,1),Hybrid!$A$1:$LI$1),FALSE) -> 0.44969619 | K48: =VLOOKUP($E48,Hybrid!$1:$1048576,MATCH(DATE(K$2,1,1),Hybrid!$A$1:$LI$1),FALSE) -> 0.46361108 | L48: =VLOOKUP($E48,Hybrid!$1:$1048576,MATCH(DATE(L$2,1,1),Hybrid!$A$1:$LI$1),FALSE) -> 0.47759482 | M48: =VLOOKUP($E48,Hybrid!$1:$1048576,MATCH(DATE(M$2,1,1),Hybrid!$A$1:$LI$1),FALSE) -> 0.49136311 | ... AO48: =VLOOKUP($E48,Hybrid!$1:$1048576,MATCH(DATE(AO$2,1,1),Hybrid!$A$1:$LI$1),FALSE) -> 0.76696872
D49: class D | E49: AUTO_cd_cgas_0 | F49: =VLOOKUP($E49,Hybrid!$1:$1048576,MATCH(DATE(F$2,1,1),Hybrid!$A$1:$LI$1),FALSE) -> 0.24954447 | G49: =VLOOKUP($E49,Hybrid!$1:$1048576,MATCH(DATE(G$2,1,1),Hybrid!$A$1:$LI$1),FALSE) -> 0.25218263 | H49: =VLOOKUP($E49,Hybrid!$1:$1048576,MATCH(DATE(H$2,1,1),Hybrid!$A$1:$LI$1),FALSE) -> 0.25629925 | I49: =VLOOKUP($E49,Hybrid!$1:$1048576,MATCH(DATE(I$2,1,1),Hybrid!$A$1:$LI$1),FALSE) -> 0.26123432 | J49: =VLOOKUP($E49,Hybrid!$1:$1048576,MATCH(DATE(J$2,1,1),Hybrid!$A$1:$LI$1),FALSE) -> 0.26678419 | K49: =VLOOKUP($E49,Hybrid!$1:$1048576,MATCH(DATE(K$2,1,1),Hybrid!$A$1:$LI$1),FALSE) -> 0.27265652 | L49: =VLOOKUP($E49,Hybrid!$1:$1048576,MATCH(DATE(L$2,1,1),Hybrid!$A$1:$LI$1),FALSE) -> 0.27848833 | M49: =VLOOKUP($E49,Hybrid!$1:$1048576,MATCH(DATE(M$2,1,1),Hybrid!$A$1:$LI$1),FALSE) -> 0.28411778 | ... AO49: =VLOOKUP($E49,Hybrid!$1:$1048576,MATCH(DATE(AO$2,1,1),Hybrid!$A$1:$LI$1),FALSE) -> 0.36684899
D50: class E | E50: AUTO_ce_cgas_0 | F50: =VLOOKUP($E50,Hybrid!$1:$1048576,MATCH(DATE(F$2,1,1),Hybrid!$A$1:$LI$1),FALSE) -> 0.15020247 | G50: =VLOOKUP($E50,Hybrid!$1:$1048576,MATCH(DATE(G$2,1,1),Hybrid!$A$1:$LI$1),FALSE) -> 0.15198637 | H50: =VLOOKUP($E50,Hybrid!$1:$1048576,MATCH(DATE(H$2,1,1),Hybrid!$A$1:$LI$1),FALSE) -> 0.15459716 | I50: =VLOOKUP($E50,Hybrid!$1:$1048576,MATCH(DATE(I$2,1,1),Hybrid!$A$1:$LI$1),FALSE) -> 0.15761589 | J50: =VLOOKUP($E50,Hybrid!$1:$1048576,MATCH(DATE(J$2,1,1),Hybrid!$A$1:$LI$1),FALSE) -> 0.1609104 | K50: =VLOOKUP($E50,Hybrid!$1:$1048576,MATCH(DATE(K$2,1,1),Hybrid!$A$1:$LI$1),FALSE) -> 0.16430586 | L50: =VLOOKUP($E50,Hybrid!$1:$1048576,MATCH(DATE(L$2,1,1),Hybrid!$A$1:$LI$1),FALSE) -> 0.16758517 | M50: =VLOOKUP($E50,Hybrid!$1:$1048576,MATCH(DATE(M$2,1,1),Hybrid!$A$1:$LI$1),FALSE) -> 0.1706505 | ... AO50: =VLOOKUP($E50,Hybrid!$1:$1048576,MATCH(DATE(AO$2,1,1),Hybrid!$A$1:$LI$1),FALSE) -> 0.19042777
D51: class F | E51: AUTO_cf_cgas_0 | F51: =VLOOKUP($E51,Hybrid!$1:$1048576,MATCH(DATE(F$2,1,1),Hybrid!$A$1:$LI$1),FALSE) -> 0.074609436 | G51: =VLOOKUP($E51,Hybrid!$1:$1048576,MATCH(DATE(G$2,1,1),Hybrid!$A$1:$LI$1),FALSE) -> 0.075275469 | H51: =VLOOKUP($E51,Hybrid!$1:$1048576,MATCH(DATE(H$2,1,1),Hybrid!$A$1:$LI$1),FALSE) -> 0.076237746 | I51: =VLOOKUP($E51,Hybrid!$1:$1048576,MATCH(DATE(I$2,1,1),Hybrid!$A$1:$LI$1),FALSE) -> 0.077275137 | J51: =VLOOKUP($E51,Hybrid!$1:$1048576,MATCH(DATE(J$2,1,1),Hybrid!$A$1:$LI$1),FALSE) -> 0.078314797 | K51: =VLOOKUP($E51,Hybrid!$1:$1048576,MATCH(DATE(K$2,1,1),Hybrid!$A$1:$LI$1),FALSE) -> 0.079279187 | L51: =VLOOKUP($E51,Hybrid!$1:$1048576,MATCH(DATE(L$2,1,1),Hybrid!$A$1:$LI$1),FALSE) -> 0.080075674 | M51: =VLOOKUP($E51,Hybrid!$1:$1048576,MATCH(DATE(M$2,1,1),Hybrid!$A$1:$LI$1),FALSE) -> 0.080665448 | ... AO51: =VLOOKUP($E51,Hybrid!$1:$1048576,MATCH(DATE(AO$2,1,1),Hybrid!$A$1:$LI$1),FALSE) -> 0.055718057
D52: class G | E52: AUTO_cg_cgas_0 | F52: =VLOOKUP($E52,Hybrid!$1:$1048576,MATCH(DATE(F$2,1,1),Hybrid!$A$1:$LI$1),FALSE) -> 0.13435819 | G52: =VLOOKUP($E52,Hybrid!$1:$1048576,MATCH(DATE(G$2,1,1),Hybrid!$A$1:$LI$1),FALSE) -> 0.13584514 | H52: =VLOOKUP($E52,Hybrid!$1:$1048576,MATCH(DATE(H$2,1,1),Hybrid!$A$1:$LI$1),FALSE) -> 0.13768976 | I52: =VLOOKUP($E52,Hybrid!$1:$1048576,MATCH(DATE(I$2,1,1),Hybrid!$A$1:$LI$1),FALSE) -> 0.13945774 | J52: =VLOOKUP($E52,Hybrid!$1:$1048576,MATCH(DATE(J$2,1,1),Hybrid!$A$1:$LI$1),FALSE) -> 0.14101039 | K52: =VLOOKUP($E52,Hybrid!$1:$1048576,MATCH(DATE(K$2,1,1),Hybrid!$A$1:$LI$1),FALSE) -> 0.14222471 | L52: =VLOOKUP($E52,Hybrid!$1:$1048576,MATCH(DATE(L$2,1,1),Hybrid!$A$1:$LI$1),FALSE) -> 0.14295727 | M52: =VLOOKUP($E52,Hybrid!$1:$1048576,MATCH(DATE(M$2,1,1),Hybrid!$A$1:$LI$1),FALSE) -> 0.14315966 | ... AO52: =VLOOKUP($E52,Hybrid!$1:$1048576,MATCH(DATE(AO$2,1,1),Hybrid!$A$1:$LI$1),FALSE) -> 0.071217428
C53: TOTAL SALES SHOCK | E53: NEWAUTO_2 | F53: =VLOOKUP($E53,Hybrid!$1:$1048576,MATCH(DATE(F$2,1,1),Hybrid!$A$1:$LI$1),FALSE) -> 1886.229 | G53: =VLOOKUP($E53,Hybrid!$1:$1048576,MATCH(DATE(G$2,1,1),Hybrid!$A$1:$LI$1),FALSE) -> 2106.5678 | H53: =VLOOKUP($E53,Hybrid!$1:$1048576,MATCH(DATE(H$2,1,1),Hybrid!$A$1:$LI$1),FALSE) -> 2302.6748 | I53: =VLOOKUP($E53,Hybrid!$1:$1048576,MATCH(DATE(I$2,1,1),Hybrid!$A$1:$LI$1),FALSE) -> 2435.6831 | J53: =VLOOKUP($E53,Hybrid!$1:$1048576,MATCH(DATE(J$2,1,1),Hybrid!$A$1:$LI$1),FALSE) -> 2552.9813 | K53: =VLOOKUP($E53,Hybrid!$1:$1048576,MATCH(DATE(K$2,1,1),Hybrid!$A$1:$LI$1),FALSE) -> 2641.2942 | L53: =VLOOKUP($E53,Hybrid!$1:$1048576,MATCH(DATE(L$2,1,1),Hybrid!$A$1:$LI$1),FALSE) -> 2701.1564 | M53: =VLOOKUP($E53,Hybrid!$1:$1048576,MATCH(DATE(M$2,1,1),Hybrid!$A$1:$LI$1),FALSE) -> 2646.5302 | ... AO53: =VLOOKUP($E53,Hybrid!$1:$1048576,MATCH(DATE(AO$2,1,1),Hybrid!$A$1:$LI$1),FALSE) -> 3795.5218
C54: OIL | E54: NEWAUTO_cfut_2 | F54: =VLOOKUP($E54,Hybrid!$1:$1048576,MATCH(DATE(F$2,1,1),Hybrid!$A$1:$LI$1),FALSE) -> 1868.6749 | G54: =VLOOKUP($E54,Hybrid!$1:$1048576,MATCH(DATE(G$2,1,1),Hybrid!$A$1:$LI$1),FALSE) -> 2086.5477 | H54: =VLOOKUP($E54,Hybrid!$1:$1048576,MATCH(DATE(H$2,1,1),Hybrid!$A$1:$LI$1),FALSE) -> 2280.1545 | I54: =VLOOKUP($E54,Hybrid!$1:$1048576,MATCH(DATE(I$2,1,1),Hybrid!$A$1:$LI$1),FALSE) -> 2410.8839 | J54: =VLOOKUP($E54,Hybrid!$1:$1048576,MATCH(DATE(J$2,1,1),Hybrid!$A$1:$LI$1),FALSE) -> 2525.7354 | K54: =VLOOKUP($E54,Hybrid!$1:$1048576,MATCH(DATE(K$2,1,1),Hybrid!$A$1:$LI$1),FALSE) -> 2611.8978 | L54: =VLOOKUP($E54,Hybrid!$1:$1048576,MATCH(DATE(L$2,1,1),Hybrid!$A$1:$LI$1),FALSE) -> 2669.8822 | M54: =VLOOKUP($E54,Hybrid!$1:$1048576,MATCH(DATE(M$2,1,1),Hybrid!$A$1:$LI$1),FALSE) -> 2613.5778 | ... AO54: =VLOOKUP($E54,Hybrid!$1:$1048576,MATCH(DATE(AO$2,1,1),Hybrid!$A$1:$LI$1),FALSE) -> 2862.1779
D55: class A | E55: NEWAUTO_ca_cfut_2 | F55: =VLOOKUP($E55,Hybrid!$1:$1048576,MATCH(DATE(F$2,1,1),Hybrid!$A$1:$LI$1),FALSE) -> 528.64569 | G55: =VLOOKUP($E55,Hybrid!$1:$1048576,MATCH(DATE(G$2,1,1),Hybrid!$A$1:$LI$1),FALSE) -> 593.25182 | H55: =VLOOKUP($E55,Hybrid!$1:$1048576,MATCH(DATE(H$2,1,1),Hybrid!$A$1:$LI$1),FALSE) -> 652.69167 | I55: =VLOOKUP($E55,Hybrid!$1:$1048576,MATCH(DATE(I$2,1,1),Hybrid!$A$1:$LI$1),FALSE) -> 695.47911 | J55: =VLOOKUP($E55,Hybrid!$1:$1048576,MATCH(DATE(J$2,1,1),Hybrid!$A$1:$LI$1),FALSE) -> 734.53236 | K55: =VLOOKUP($E55,Hybrid!$1:$1048576,MATCH(DATE(K$2,1,1),Hybrid!$A$1:$LI$1),FALSE) -> 765.43106 | L55: =VLOOKUP($E55,Hybrid!$1:$1048576,MATCH(DATE(L$2,1,1),Hybrid!$A$1:$LI$1),FALSE) -> 788.30899 | M55: =VLOOKUP($E55,Hybrid!$1:$1048576,MATCH(DATE(M$2,1,1),Hybrid!$A$1:$LI$1),FALSE) -> 778.80996 | ... AO55: =VLOOKUP($E55,Hybrid!$1:$1048576,MATCH(DATE(AO$2,1,1),Hybrid!$A$1:$LI$1),FALSE) -> 1019.3042
D56: class B | E56: NEWAUTO_cb_cfut_2 | F56: =VLOOKUP($E56,Hybrid!$1:$1048576,MATCH(DATE(F$2,1,1),Hybrid!$A$1:$LI$1),FALSE) -> 507.5268 | G56: =VLOOKUP($E56,Hybrid!$1:$1048576,MATCH(DATE(G$2,1,1),Hybrid!$A$1:$LI$1),FALSE) -> 568.87473 | H56: =VLOOKUP($E56,Hybrid!$1:$1048576,MATCH(DATE(H$2,1,1),Hybrid!$A$1:$LI$1),FALSE) -> 624.88258 | I56: =VLOOKUP($E56,Hybrid!$1:$1048576,MATCH(DATE(I$2,1,1),Hybrid!$A$1:$LI$1),FALSE) -> 664.59522 | J56: =VLOOKUP($E56,Hybrid!$1:$1048576,MATCH(DATE(J$2,1,1),Hybrid!$A$1:$LI$1),FALSE) -> 700.52142 | K56: =VLOOKUP($E56,Hybrid!$1:$1048576,MATCH(DATE(K$2,1,1),Hybrid!$A$1:$LI$1),FALSE) -> 728.68279 | L56: =VLOOKUP($E56,Hybrid!$1:$1048576,MATCH(DATE(L$2,1,1),Hybrid!$A$1:$LI$1),FALSE) -> 749.1464 | M56: =VLOOKUP($E56,Hybrid!$1:$1048576,MATCH(DATE(M$2,1,1),Hybrid!$A$1:$LI$1),FALSE) -> 738.14362 | ... AO56: =VLOOKUP($E56,Hybrid!$1:$1048576,MATCH(DATE(AO$2,1,1),Hybrid!$A$1:$LI$1),FALSE) -> 879.9615
D57: class C | E57: NEWAUTO_cc_cfut_2 | F57: =VLOOKUP($E57,Hybrid!$1:$1048576,MATCH(DATE(F$2,1,1),Hybrid!$A$1:$LI$1),FALSE) -> 351.30528 | G57: =VLOOKUP($E57,Hybrid!$1:$1048576,MATCH(DATE(G$2,1,1),Hybrid!$A$1:$LI$1),FALSE) -> 393.30365 | H57: =VLOOKUP($E57,Hybrid!$1:$1048576,MATCH(DATE(H$2,1,1),Hybrid!$A$1:$LI$1),FALSE) -> 431.34653 | I57: =VLOOKUP($E57,Hybrid!$1:$1048576,MATCH(DATE(I$2,1,1),Hybrid!$A$1:$LI$1),FALSE) -> 457.90304 | J57: =VLOOKUP($E57,Hybrid!$1:$1048576,MATCH(DATE(J$2,1,1),Hybrid!$A$1:$LI$1),FALSE) -> 481.70631 | K57: =VLOOKUP($E57,Hybrid!$1:$1048576,MATCH(DATE(K$2,1,1),Hybrid!$A$1:$LI$1),FALSE) -> 500.18338 | L57: =VLOOKUP($E57,Hybrid!$1:$1048576,MATCH(DATE(L$2,1,1),Hybrid!$A$1:$LI$1),FALSE) -> 513.33913 | M57: =VLOOKUP($E57,Hybrid!$1:$1048576,MATCH(DATE(M$2,1,1),Hybrid!$A$1:$LI$1),FALSE) -> 504.46541 | ... AO57: =VLOOKUP($E57,Hybrid!$1:$1048576,MATCH(DATE(AO$2,1,1),Hybrid!$A$1:$LI$1),FALSE) -> 549.55786
D58: class D | E58: NEWAUTO_cd_cfut_2 | F58: =VLOOKUP($E58,Hybrid!$1:$1048576,MATCH(DATE(F$2,1,1),Hybrid!$A$1:$LI$1),FALSE) -> 194.72119 | G58: =VLOOKUP($E58,Hybrid!$1:$1048576,MATCH(DATE(G$2,1,1),Hybrid!$A$1:$LI$1),FALSE) -> 217.05129 | H58: =VLOOKUP($E58,Hybrid!$1:$1048576,MATCH(DATE(H$2,1,1),Hybrid!$A$1:$LI$1),FALSE) -> 236.61225 | I58: =VLOOKUP($E58,Hybrid!$1:$1048576,MATCH(DATE(I$2,1,1),Hybrid!$A$1:$LI$1),FALSE) -> 249.41709 | J58: =VLOOKUP($E58,Hybrid!$1:$1048576,MATCH(DATE(J$2,1,1),Hybrid!$A$1:$LI$1),FALSE) -> 260.40654 | K58: =VLOOKUP($E58,Hybrid!$1:$1048576,MATCH(DATE(K$2,1,1),Hybrid!$A$1:$LI$1),FALSE) -> 268.37377 | L58: =VLOOKUP($E58,Hybrid!$1:$1048576,MATCH(DATE(L$2,1,1),Hybrid!$A$1:$LI$1),FALSE) -> 273.34435 | M58: =VLOOKUP($E58,Hybrid!$1:$1048576,MATCH(DATE(M$2,1,1),Hybrid!$A$1:$LI$1),FALSE) -> 266.2138 | ... AO58: =VLOOKUP($E58,Hybrid!$1:$1048576,MATCH(DATE(AO$2,1,1),Hybrid!$A$1:$LI$1),FALSE) -> 265.21276
D59: class E | E59: NEWAUTO_ce_cfut_2 | F59: =VLOOKUP($E59,Hybrid!$1:$1048576,MATCH(DATE(F$2,1,1),Hybrid!$A$1:$LI$1),FALSE) -> 119.78455 | G59: =VLOOKUP($E59,Hybrid!$1:$1048576,MATCH(DATE(G$2,1,1),Hybrid!$A$1:$LI$1),FALSE) -> 132.97739 | H59: =VLOOKUP($E59,Hybrid!$1:$1048576,MATCH(DATE(H$2,1,1),Hybrid!$A$1:$LI$1),FALSE) -> 144.14706 | I59: =VLOOKUP($E59,Hybrid!$1:$1048576,MATCH(DATE(I$2,1,1),Hybrid!$A$1:$LI$1),FALSE) -> 150.94512 | J59: =VLOOKUP($E59,Hybrid!$1:$1048576,MATCH(DATE(J$2,1,1),Hybrid!$A$1:$LI$1),FALSE) -> 156.47354 | K59: =VLOOKUP($E59,Hybrid!$1:$1048576,MATCH(DATE(K$2,1,1),Hybrid!$A$1:$LI$1),FALSE) -> 160.12617 | L59: =VLOOKUP($E59,Hybrid!$1:$1048576,MATCH(DATE(L$2,1,1),Hybrid!$A$1:$LI$1),FALSE) -> 161.93002 | M59: =VLOOKUP($E59,Hybrid!$1:$1048576,MATCH(DATE(M$2,1,1),Hybrid!$A$1:$LI$1),FALSE) -> 156.33457 | ... AO59: =VLOOKUP($E59,Hybrid!$1:$1048576,MATCH(DATE(AO$2,1,1),Hybrid!$A$1:$LI$1),FALSE) -> 115.82386
D60: class F | E60: NEWAUTO_cf_cfut_2 | F60: =VLOOKUP($E60,Hybrid!$1:$1048576,MATCH(DATE(F$2,1,1),Hybrid!$A$1:$LI$1),FALSE) -> 57.931007 | G60: =VLOOKUP($E60,Hybrid!$1:$1048576,MATCH(DATE(G$2,1,1),Hybrid!$A$1:$LI$1),FALSE) -> 63.433633 | H60: =VLOOKUP($E60,Hybrid!$1:$1048576,MATCH(DATE(H$2,1,1),Hybrid!$A$1:$LI$1),FALSE) -> 67.455387 | I60: =VLOOKUP($E60,Hybrid!$1:$1048576,MATCH(DATE(I$2,1,1),Hybrid!$A$1:$LI$1),FALSE) -> 69.065361 | J60: =VLOOKUP($E60,Hybrid!$1:$1048576,MATCH(DATE(J$2,1,1),Hybrid!$A$1:$LI$1),FALSE) -> 69.86414 | K60: =VLOOKUP($E60,Hybrid!$1:$1048576,MATCH(DATE(K$2,1,1),Hybrid!$A$1:$LI$1),FALSE) -> 69.741647 | L60: =VLOOKUP($E60,Hybrid!$1:$1048576,MATCH(DATE(L$2,1,1),Hybrid!$A$1:$LI$1),FALSE) -> 68.759059 | M60: =VLOOKUP($E60,Hybrid!$1:$1048576,MATCH(DATE(M$2,1,1),Hybrid!$A$1:$LI$1),FALSE) -> 64.477598 | ... AO60: =VLOOKUP($E60,Hybrid!$1:$1048576,MATCH(DATE(AO$2,1,1),Hybrid!$A$1:$LI$1),FALSE) -> 19.314119
D61: class G | E61: NEWAUTO_cg_cfut_2 | F61: =VLOOKUP($E61,Hybrid!$1:$1048576,MATCH(DATE(F$2,1,1),Hybrid!$A$1:$LI$1),FALSE) -> 108.76034 | G61: =VLOOKUP($E61,Hybrid!$1:$1048576,MATCH(DATE(G$2,1,1),Hybrid!$A$1:$LI$1),FALSE) -> 117.6552 | H61: =VLOOKUP($E61,Hybrid!$1:$1048576,MATCH(DATE(H$2,1,1),Hybrid!$A$1:$LI$1),FALSE) -> 123.01899 | I61: =VLOOKUP($E61,Hybrid!$1:$1048576,MATCH(DATE(I$2,1,1),Hybrid!$A$1:$LI$1),FALSE) -> 123.47895 | J61: =VLOOKUP($E61,Hybrid!$1:$1048576,MATCH(DATE(J$2,1,1),Hybrid!$A$1:$LI$1),FALSE) -> 122.23112 | K61: =VLOOKUP($E61,Hybrid!$1:$1048576,MATCH(DATE(K$2,1,1),Hybrid!$A$1:$LI$1),FALSE) -> 119.35902 | L61: =VLOOKUP($E61,Hybrid!$1:$1048576,MATCH(DATE(L$2,1,1),Hybrid!$A$1:$LI$1),FALSE) -> 115.05429 | M61: =VLOOKUP($E61,Hybrid!$1:$1048576,MATCH(DATE(M$2,1,1),Hybrid!$A$1:$LI$1),FALSE) -> 105.1328 | ... AO61: =VLOOKUP($E61,Hybrid!$1:$1048576,MATCH(DATE(AO$2,1,1),Hybrid!$A$1:$LI$1),FALSE) -> 13.003635
C62: ELEC | E62: NEWAUTO_cele_2 | F62: =VLOOKUP($E62,Hybrid!$1:$1048576,MATCH(DATE(F$2,1,1),Hybrid!$A$1:$LI$1),FALSE) -> 17.397156 | G62: =VLOOKUP($E62,Hybrid!$1:$1048576,MATCH(DATE(G$2,1,1),Hybrid!$A$1:$LI$1),FALSE) -> 19.844788 | H62: =VLOOKUP($E62,Hybrid!$1:$1048576,MATCH(DATE(H$2,1,1),Hybrid!$A$1:$LI$1),FALSE) -> 22.328806 | I62: =VLOOKUP($E62,Hybrid!$1:$1048576,MATCH(DATE(I$2,1,1),Hybrid!$A$1:$LI$1),FALSE) -> 24.596635 | J62: =VLOOKUP($E62,Hybrid!$1:$1048576,MATCH(DATE(J$2,1,1),Hybrid!$A$1:$LI$1),FALSE) -> 27.033711 | K62: =VLOOKUP($E62,Hybrid!$1:$1048576,MATCH(DATE(K$2,1,1),Hybrid!$A$1:$LI$1),FALSE) -> 29.176972 | L62: =VLOOKUP($E62,Hybrid!$1:$1048576,MATCH(DATE(L$2,1,1),Hybrid!$A$1:$LI$1),FALSE) -> 31.049875 | M62: =VLOOKUP($E62,Hybrid!$1:$1048576,MATCH(DATE(M$2,1,1),Hybrid!$A$1:$LI$1),FALSE) -> 32.732885 | ... AO62: =VLOOKUP($E62,Hybrid!$1:$1048576,MATCH(DATE(AO$2,1,1),Hybrid!$A$1:$LI$1),FALSE) -> 933.10346
D63: class A | E63: NEWAUTO_ca_cele_2 | F63: =VLOOKUP($E63,Hybrid!$1:$1048576,MATCH(DATE(F$2,1,1),Hybrid!$A$1:$LI$1),FALSE) -> 4.9240804 | G63: =VLOOKUP($E63,Hybrid!$1:$1048576,MATCH(DATE(G$2,1,1),Hybrid!$A$1:$LI$1),FALSE) -> 5.6535364 | H63: =VLOOKUP($E63,Hybrid!$1:$1048576,MATCH(DATE(H$2,1,1),Hybrid!$A$1:$LI$1),FALSE) -> 6.4168136 | I63: =VLOOKUP($E63,Hybrid!$1:$1048576,MATCH(DATE(I$2,1,1),Hybrid!$A$1:$LI$1),FALSE) -> 7.1418413 | J63: =VLOOKUP($E63,Hybrid!$1:$1048576,MATCH(DATE(J$2,1,1),Hybrid!$A$1:$LI$1),FALSE) -> 7.9346752 | K63: =VLOOKUP($E63,Hybrid!$1:$1048576,MATCH(DATE(K$2,1,1),Hybrid!$A$1:$LI$1),FALSE) -> 8.6470226 | L63: =VLOOKUP($E63,Hybrid!$1:$1048576,MATCH(DATE(L$2,1,1),Hybrid!$A$1:$LI$1),FALSE) -> 9.286065 | M63: =VLOOKUP($E63,Hybrid!$1:$1048576,MATCH(DATE(M$2,1,1),Hybrid!$A$1:$LI$1),FALSE) -> 9.9100088 | ... AO63: =VLOOKUP($E63,Hybrid!$1:$1048576,MATCH(DATE(AO$2,1,1),Hybrid!$A$1:$LI$1),FALSE) -> 342.95536
D64: class B | E64: NEWAUTO_cb_cele_2 | F64: =VLOOKUP($E64,Hybrid!$1:$1048576,MATCH(DATE(F$2,1,1),Hybrid!$A$1:$LI$1),FALSE) -> 4.7303633 | G64: =VLOOKUP($E64,Hybrid!$1:$1048576,MATCH(DATE(G$2,1,1),Hybrid!$A$1:$LI$1),FALSE) -> 5.4343775 | H64: =VLOOKUP($E64,Hybrid!$1:$1048576,MATCH(DATE(H$2,1,1),Hybrid!$A$1:$LI$1),FALSE) -> 6.1728984 | I64: =VLOOKUP($E64,Hybrid!$1:$1048576,MATCH(DATE(I$2,1,1),Hybrid!$A$1:$LI$1),FALSE) -> 6.8790903 | J64: =VLOOKUP($E64,Hybrid!$1:$1048576,MATCH(DATE(J$2,1,1),Hybrid!$A$1:$LI$1),FALSE) -> 7.6542383 | K64: =VLOOKUP($E64,Hybrid!$1:$1048576,MATCH(DATE(K$2,1,1),Hybrid!$A$1:$LI$1),FALSE) -> 8.3514932 | L64: =VLOOKUP($E64,Hybrid!$1:$1048576,MATCH(DATE(L$2,1,1),Hybrid!$A$1:$LI$1),FALSE) -> 8.9775309 | M64: =VLOOKUP($E64,Hybrid!$1:$1048576,MATCH(DATE(M$2,1,1),Hybrid!$A$1:$LI$1),FALSE) -> 9.597803 | ... AO64: =VLOOKUP($E64,Hybrid!$1:$1048576,MATCH(DATE(AO$2,1,1),Hybrid!$A$1:$LI$1),FALSE) -> 315.29252
D65: class C | E65: NEWAUTO_cc_cele_2 | F65: =VLOOKUP($E65,Hybrid!$1:$1048576,MATCH(DATE(F$2,1,1),Hybrid!$A$1:$LI$1),FALSE) -> 3.2762546 | G65: =VLOOKUP($E65,Hybrid!$1:$1048576,MATCH(DATE(G$2,1,1),Hybrid!$A$1:$LI$1),FALSE) -> 3.7656985 | H65: =VLOOKUP($E65,Hybrid!$1:$1048576,MATCH(DATE(H$2,1,1),Hybrid!$A$1:$LI$1),FALSE) -> 4.2801564 | I65: =VLOOKUP($E65,Hybrid!$1:$1048576,MATCH(DATE(I$2,1,1),Hybrid!$A$1:$LI$1),FALSE) -> 4.7748504 | J65: =VLOOKUP($E65,Hybrid!$1:$1048576,MATCH(DATE(J$2,1,1),Hybrid!$A$1:$LI$1),FALSE) -> 5.3195293 | K65: =VLOOKUP($E65,Hybrid!$1:$1048576,MATCH(DATE(K$2,1,1),Hybrid!$A$1:$LI$1),FALSE) -> 5.8098257 | L65: =VLOOKUP($E65,Hybrid!$1:$1048576,MATCH(DATE(L$2,1,1),Hybrid!$A$1:$LI$1),FALSE) -> 6.2501983 | M65: =VLOOKUP($E65,Hybrid!$1:$1048576,MATCH(DATE(M$2,1,1),Hybrid!$A$1:$LI$1),FALSE) -> 6.6913579 | ... AO65: =VLOOKUP($E65,Hybrid!$1:$1048576,MATCH(DATE(AO$2,1,1),Hybrid!$A$1:$LI$1),FALSE) -> 208.2114
D66: class D | E66: NEWAUTO_cd_cele_2 | F66: =VLOOKUP($E66,Hybrid!$1:$1048576,MATCH(DATE(F$2,1,1),Hybrid!$A$1:$LI$1),FALSE) -> 1.8075174 | G66: =VLOOKUP($E66,Hybrid!$1:$1048576,MATCH(DATE(G$2,1,1),Hybrid!$A$1:$LI$1),FALSE) -> 2.040643 | H66: =VLOOKUP($E66,Hybrid!$1:$1048576,MATCH(DATE(H$2,1,1),Hybrid!$A$1:$LI$1),FALSE) -> 2.2635124 | I66: =VLOOKUP($E66,Hybrid!$1:$1048576,MATCH(DATE(I$2,1,1),Hybrid!$A$1:$LI$1),FALSE) -> 2.4449492 | J66: =VLOOKUP($E66,Hybrid!$1:$1048576,MATCH(DATE(J$2,1,1),Hybrid!$A$1:$LI$1),FALSE) -> 2.6270223 | K66: =VLOOKUP($E66,Hybrid!$1:$1048576,MATCH(DATE(K$2,1,1),Hybrid!$A$1:$LI$1),FALSE) -> 2.7779785 | L66: =VLOOKUP($E66,Hybrid!$1:$1048576,MATCH(DATE(L$2,1,1),Hybrid!$A$1:$LI$1),FALSE) -> 2.8989642 | M66: =VLOOKUP($E66,Hybrid!$1:$1048576,MATCH(DATE(M$2,1,1),Hybrid!$A$1:$LI$1),FALSE) -> 2.9549825 | ... AO66: =VLOOKUP($E66,Hybrid!$1:$1048576,MATCH(DATE(AO$2,1,1),Hybrid!$A$1:$LI$1),FALSE) -> 43.250592
D67: class E | E67: NEWAUTO_ce_cele_2 | F67: =VLOOKUP($E67,Hybrid!$1:$1048576,MATCH(DATE(F$2,1,1),Hybrid!$A$1:$LI$1),FALSE) -> 1.1126671 | G67: =VLOOKUP($E67,Hybrid!$1:$1048576,MATCH(DATE(G$2,1,1),Hybrid!$A$1:$LI$1),FALSE) -> 1.2533153 | H67: =VLOOKUP($E67,Hybrid!$1:$1048576,MATCH(DATE(H$2,1,1),Hybrid!$A$1:$LI$1),FALSE) -> 1.3856347 | I67: =VLOOKUP($E67,Hybrid!$1:$1048576,MATCH(DATE(I$2,1,1),Hybrid!$A$1:$LI$1),FALSE) -> 1.4914772 | J67: =VLOOKUP($E67,Hybrid!$1:$1048576,MATCH(DATE(J$2,1,1),Hybrid!$A$1:$LI$1),FALSE) -> 1.5967245 | K67: =VLOOKUP($E67,Hybrid!$1:$1048576,MATCH(DATE(K$2,1,1),Hybrid!$A$1:$LI$1),FALSE) -> 1.6817867 | L67: =VLOOKUP($E67,Hybrid!$1:$1048576,MATCH(DATE(L$2,1,1),Hybrid!$A$1:$LI$1),FALSE) -> 1.7475226 | M67: =VLOOKUP($E67,Hybrid!$1:$1048576,MATCH(DATE(M$2,1,1),Hybrid!$A$1:$LI$1),FALSE) -> 1.7741875 | ... AO67: =VLOOKUP($E67,Hybrid!$1:$1048576,MATCH(DATE(AO$2,1,1),Hybrid!$A$1:$LI$1),FALSE) -> 20.149498
D68: class F | E68: NEWAUTO_cf_cele_2 | F68: =VLOOKUP($E68,Hybrid!$1:$1048576,MATCH(DATE(F$2,1,1),Hybrid!$A$1:$LI$1),FALSE) -> 0.53722538 | G68: =VLOOKUP($E68,Hybrid!$1:$1048576,MATCH(DATE(G$2,1,1),Hybrid!$A$1:$LI$1),FALSE) -> 0.59391241 | H68: =VLOOKUP($E68,Hybrid!$1:$1048576,MATCH(DATE(H$2,1,1),Hybrid!$A$1:$LI$1),FALSE) -> 0.63969269 | I68: =VLOOKUP($E68,Hybrid!$1:$1048576,MATCH(DATE(I$2,1,1),Hybrid!$A$1:$LI$1),FALSE) -> 0.66669276 | J68: =VLOOKUP($E68,Hybrid!$1:$1048576,MATCH(DATE(J$2,1,1),Hybrid!$A$1:$LI$1),FALSE) -> 0.68853529 | K68: =VLOOKUP($E68,Hybrid!$1:$1048576,MATCH(DATE(K$2,1,1),Hybrid!$A$1:$LI$1),FALSE) -> 0.70013447 | L68: =VLOOKUP($E68,Hybrid!$1:$1048576,MATCH(DATE(L$2,1,1),Hybrid!$A$1:$LI$1),FALSE) -> 0.7022658 | M68: =VLOOKUP($E68,Hybrid!$1:$1048576,MATCH(DATE(M$2,1,1),Hybrid!$A$1:$LI$1),FALSE) -> 0.68040163 | ... AO68: =VLOOKUP($E68,Hybrid!$1:$1048576,MATCH(DATE(AO$2,1,1),Hybrid!$A$1:$LI$1),FALSE) -> 1.9082038
D69: class G | E69: NEWAUTO_cg_cele_2 | F69: =VLOOKUP($E69,Hybrid!$1:$1048576,MATCH(DATE(F$2,1,1),Hybrid!$A$1:$LI$1),FALSE) -> 1.0090476 | G69: =VLOOKUP($E69,Hybrid!$1:$1048576,MATCH(DATE(G$2,1,1),Hybrid!$A$1:$LI$1),FALSE) -> 1.1033044 | H69: =VLOOKUP($E69,Hybrid!$1:$1048576,MATCH(DATE(H$2,1,1),Hybrid!$A$1:$LI$1),FALSE) -> 1.1700975 | I69: =VLOOKUP($E69,Hybrid!$1:$1048576,MATCH(DATE(I$2,1,1),Hybrid!$A$1:$LI$1),FALSE) -> 1.1977337 | J69: =VLOOKUP($E69,Hybrid!$1:$1048576,MATCH(DATE(J$2,1,1),Hybrid!$A$1:$LI$1),FALSE) -> 1.2129864 | K69: =VLOOKUP($E69,Hybrid!$1:$1048576,MATCH(DATE(K$2,1,1),Hybrid!$A$1:$LI$1),FALSE) -> 1.2087304 | L69: =VLOOKUP($E69,Hybrid!$1:$1048576,MATCH(DATE(L$2,1,1),Hybrid!$A$1:$LI$1),FALSE) -> 1.187328 | M69: =VLOOKUP($E69,Hybrid!$1:$1048576,MATCH(DATE(M$2,1,1),Hybrid!$A$1:$LI$1),FALSE) -> 1.1241432 | ... AO69: =VLOOKUP($E69,Hybrid!$1:$1048576,MATCH(DATE(AO$2,1,1),Hybrid!$A$1:$LI$1),FALSE) -> 1.3358737
C70: GAS | E70: NEWAUTO_cgas_2 | F70: =VLOOKUP($E70,Hybrid!$1:$1048576,MATCH(DATE(F$2,1,1),Hybrid!$A$1:$LI$1),FALSE) -> 0.15698923 | G70: =VLOOKUP($E70,Hybrid!$1:$1048576,MATCH(DATE(G$2,1,1),Hybrid!$A$1:$LI$1),FALSE) -> 0.17529295 | H70: =VLOOKUP($E70,Hybrid!$1:$1048576,MATCH(DATE(H$2,1,1),Hybrid!$A$1:$LI$1),FALSE) -> 0.19155805 | I70: =VLOOKUP($E70,Hybrid!$1:$1048576,MATCH(DATE(I$2,1,1),Hybrid!$A$1:$LI$1),FALSE) -> 0.20254075 | J70: =VLOOKUP($E70,Hybrid!$1:$1048576,MATCH(DATE(J$2,1,1),Hybrid!$A$1:$LI$1),FALSE) -> 0.21218955 | K70: =VLOOKUP($E70,Hybrid!$1:$1048576,MATCH(DATE(K$2,1,1),Hybrid!$A$1:$LI$1),FALSE) -> 0.21942814 | L70: =VLOOKUP($E70,Hybrid!$1:$1048576,MATCH(DATE(L$2,1,1),Hybrid!$A$1:$LI$1),FALSE) -> 0.22429946 | M70: =VLOOKUP($E70,Hybrid!$1:$1048576,MATCH(DATE(M$2,1,1),Hybrid!$A$1:$LI$1),FALSE) -> 0.21956927 | ... AO70: =VLOOKUP($E70,Hybrid!$1:$1048576,MATCH(DATE(AO$2,1,1),Hybrid!$A$1:$LI$1),FALSE) -> 0.24045442
D71: class A | E71: NEWAUTO_ca_cgas_2 | F71: =VLOOKUP($E71,Hybrid!$1:$1048576,MATCH(DATE(F$2,1,1),Hybrid!$A$1:$LI$1),FALSE) -> 0.044412051 | G71: =VLOOKUP($E71,Hybrid!$1:$1048576,MATCH(DATE(G$2,1,1),Hybrid!$A$1:$LI$1),FALSE) -> 0.049839676 | H71: =VLOOKUP($E71,Hybrid!$1:$1048576,MATCH(DATE(H$2,1,1),Hybrid!$A$1:$LI$1),FALSE) -> 0.054833277 | I71: =VLOOKUP($E71,Hybrid!$1:$1048576,MATCH(DATE(I$2,1,1),Hybrid!$A$1:$LI$1),FALSE) -> 0.058427892 | J71: =VLOOKUP($E71,Hybrid!$1:$1048576,MATCH(DATE(J$2,1,1),Hybrid!$A$1:$LI$1),FALSE) -> 0.061708794 | K71: =VLOOKUP($E71,Hybrid!$1:$1048576,MATCH(DATE(K$2,1,1),Hybrid!$A$1:$LI$1),FALSE) -> 0.064304625 | L71: =VLOOKUP($E71,Hybrid!$1:$1048576,MATCH(DATE(L$2,1,1),Hybrid!$A$1:$LI$1),FALSE) -> 0.066226622 | M71: =VLOOKUP($E71,Hybrid!$1:$1048576,MATCH(DATE(M$2,1,1),Hybrid!$A$1:$LI$1),FALSE) -> 0.0654286 | ... AO71: =VLOOKUP($E71,Hybrid!$1:$1048576,MATCH(DATE(AO$2,1,1),Hybrid!$A$1:$LI$1),FALSE) -> 0.085632762
D72: class B | E72: NEWAUTO_cb_cgas_2 | F72: =VLOOKUP($E72,Hybrid!$1:$1048576,MATCH(DATE(F$2,1,1),Hybrid!$A$1:$LI$1),FALSE) -> 0.042637831 | G72: =VLOOKUP($E72,Hybrid!$1:$1048576,MATCH(DATE(G$2,1,1),Hybrid!$A$1:$LI$1),FALSE) -> 0.047791732 | H72: =VLOOKUP($E72,Hybrid!$1:$1048576,MATCH(DATE(H$2,1,1),Hybrid!$A$1:$LI$1),FALSE) -> 0.052497008 | I72: =VLOOKUP($E72,Hybrid!$1:$1048576,MATCH(DATE(I$2,1,1),Hybrid!$A$1:$LI$1),FALSE) -> 0.055833306 | J72: =VLOOKUP($E72,Hybrid!$1:$1048576,MATCH(DATE(J$2,1,1),Hybrid!$A$1:$LI$1),FALSE) -> 0.058851501 | K72: =VLOOKUP($E72,Hybrid!$1:$1048576,MATCH(DATE(K$2,1,1),Hybrid!$A$1:$LI$1),FALSE) -> 0.061217366 | L72: =VLOOKUP($E72,Hybrid!$1:$1048576,MATCH(DATE(L$2,1,1),Hybrid!$A$1:$LI$1),FALSE) -> 0.062936535 | M72: =VLOOKUP($E72,Hybrid!$1:$1048576,MATCH(DATE(M$2,1,1),Hybrid!$A$1:$LI$1),FALSE) -> 0.06201218 | ... AO72: =VLOOKUP($E72,Hybrid!$1:$1048576,MATCH(DATE(AO$2,1,1),Hybrid!$A$1:$LI$1),FALSE) -> 0.073926441
D73: class C | E73: NEWAUTO_cc_cgas_2 | F73: =VLOOKUP($E73,Hybrid!$1:$1048576,MATCH(DATE(F$2,1,1),Hybrid!$A$1:$LI$1),FALSE) -> 0.029513507 | G73: =VLOOKUP($E73,Hybrid!$1:$1048576,MATCH(DATE(G$2,1,1),Hybrid!$A$1:$LI$1),FALSE) -> 0.033041831 | H73: =VLOOKUP($E73,Hybrid!$1:$1048576,MATCH(DATE(H$2,1,1),Hybrid!$A$1:$LI$1),FALSE) -> 0.036237851 | I73: =VLOOKUP($E73,Hybrid!$1:$1048576,MATCH(DATE(I$2,1,1),Hybrid!$A$1:$LI$1),FALSE) -> 0.03846889 | J73: =VLOOKUP($E73,Hybrid!$1:$1048576,MATCH(DATE(J$2,1,1),Hybrid!$A$1:$LI$1),FALSE) -> 0.040468626 | K73: =VLOOKUP($E73,Hybrid!$1:$1048576,MATCH(DATE(K$2,1,1),Hybrid!$A$1:$LI$1),FALSE) -> 0.042020904 | L73: =VLOOKUP($E73,Hybrid!$1:$1048576,MATCH(DATE(L$2,1,1),Hybrid!$A$1:$LI$1),FALSE) -> 0.043126131 | M73: =VLOOKUP($E73,Hybrid!$1:$1048576,MATCH(DATE(M$2,1,1),Hybrid!$A$1:$LI$1),FALSE) -> 0.042380641 | ... AO73: =VLOOKUP($E73,Hybrid!$1:$1048576,MATCH(DATE(AO$2,1,1),Hybrid!$A$1:$LI$1),FALSE) -> 0.046168903
D74: class D | E74: NEWAUTO_cd_cgas_2 | F74: =VLOOKUP($E74,Hybrid!$1:$1048576,MATCH(DATE(F$2,1,1),Hybrid!$A$1:$LI$1),FALSE) -> 0.016358721 | G74: =VLOOKUP($E74,Hybrid!$1:$1048576,MATCH(DATE(G$2,1,1),Hybrid!$A$1:$LI$1),FALSE) -> 0.018234695 | H74: =VLOOKUP($E74,Hybrid!$1:$1048576,MATCH(DATE(H$2,1,1),Hybrid!$A$1:$LI$1),FALSE) -> 0.019878031 | I74: =VLOOKUP($E74,Hybrid!$1:$1048576,MATCH(DATE(I$2,1,1),Hybrid!$A$1:$LI$1),FALSE) -> 0.020953778 | J74: =VLOOKUP($E74,Hybrid!$1:$1048576,MATCH(DATE(J$2,1,1),Hybrid!$A$1:$LI$1),FALSE) -> 0.021877013 | K74: =VLOOKUP($E74,Hybrid!$1:$1048576,MATCH(DATE(K$2,1,1),Hybrid!$A$1:$LI$1),FALSE) -> 0.022546347 | L74: =VLOOKUP($E74,Hybrid!$1:$1048576,MATCH(DATE(L$2,1,1),Hybrid!$A$1:$LI$1),FALSE) -> 0.022963931 | M74: =VLOOKUP($E74,Hybrid!$1:$1048576,MATCH(DATE(M$2,1,1),Hybrid!$A$1:$LI$1),FALSE) -> 0.022364886 | ... AO74: =VLOOKUP($E74,Hybrid!$1:$1048576,MATCH(DATE(AO$2,1,1),Hybrid!$A$1:$LI$1),FALSE) -> 0.022280788
D75: class E | E75: NEWAUTO_ce_cgas_2 | F75: =VLOOKUP($E75,Hybrid!$1:$1048576,MATCH(DATE(F$2,1,1),Hybrid!$A$1:$LI$1),FALSE) -> 0.010063219 | G75: =VLOOKUP($E75,Hybrid!$1:$1048576,MATCH(DATE(G$2,1,1),Hybrid!$A$1:$LI$1),FALSE) -> 0.011171563 | H75: =VLOOKUP($E75,Hybrid!$1:$1048576,MATCH(DATE(H$2,1,1),Hybrid!$A$1:$LI$1),FALSE) -> 0.012109938 | I75: =VLOOKUP($E75,Hybrid!$1:$1048576,MATCH(DATE(I$2,1,1),Hybrid!$A$1:$LI$1),FALSE) -> 0.01268105 | J75: =VLOOKUP($E75,Hybrid!$1:$1048576,MATCH(DATE(J$2,1,1),Hybrid!$A$1:$LI$1),FALSE) -> 0.013145498 | K75: =VLOOKUP($E75,Hybrid!$1:$1048576,MATCH(DATE(K$2,1,1),Hybrid!$A$1:$LI$1),FALSE) -> 0.013452359 | L75: =VLOOKUP($E75,Hybrid!$1:$1048576,MATCH(DATE(L$2,1,1),Hybrid!$A$1:$LI$1),FALSE) -> 0.013603902 | M75: =VLOOKUP($E75,Hybrid!$1:$1048576,MATCH(DATE(M$2,1,1),Hybrid!$A$1:$LI$1),FALSE) -> 0.013133823 | ... AO75: =VLOOKUP($E75,Hybrid!$1:$1048576,MATCH(DATE(AO$2,1,1),Hybrid!$A$1:$LI$1),FALSE) -> 0.0097304774
D76: class F | E76: NEWAUTO_cf_cgas_2 | F76: =VLOOKUP($E76,Hybrid!$1:$1048576,MATCH(DATE(F$2,1,1),Hybrid!$A$1:$LI$1),FALSE) -> 0.0048668415 | G76: =VLOOKUP($E76,Hybrid!$1:$1048576,MATCH(DATE(G$2,1,1),Hybrid!$A$1:$LI$1),FALSE) -> 0.0053291226 | H76: =VLOOKUP($E76,Hybrid!$1:$1048576,MATCH(DATE(H$2,1,1),Hybrid!$A$1:$LI$1),FALSE) -> 0.0056669942 | I76: =VLOOKUP($E76,Hybrid!$1:$1048576,MATCH(DATE(I$2,1,1),Hybrid!$A$1:$LI$1),FALSE) -> 0.0058022498 | J76: =VLOOKUP($E76,Hybrid!$1:$1048576,MATCH(DATE(J$2,1,1),Hybrid!$A$1:$LI$1),FALSE) -> 0.0058693559 | K76: =VLOOKUP($E76,Hybrid!$1:$1048576,MATCH(DATE(K$2,1,1),Hybrid!$A$1:$LI$1),FALSE) -> 0.0058590652 | L76: =VLOOKUP($E76,Hybrid!$1:$1048576,MATCH(DATE(L$2,1,1),Hybrid!$A$1:$LI$1),FALSE) -> 0.005776517 | M76: =VLOOKUP($E76,Hybrid!$1:$1048576,MATCH(DATE(M$2,1,1),Hybrid!$A$1:$LI$1),FALSE) -> 0.0054168271 | ... AO76: =VLOOKUP($E76,Hybrid!$1:$1048576,MATCH(DATE(AO$2,1,1),Hybrid!$A$1:$LI$1),FALSE) -> 0.0016225983
D77: class G | E77: NEWAUTO_cg_cgas_2 | F77: =VLOOKUP($E77,Hybrid!$1:$1048576,MATCH(DATE(F$2,1,1),Hybrid!$A$1:$LI$1),FALSE) -> 0.0091370647 | G77: =VLOOKUP($E77,Hybrid!$1:$1048576,MATCH(DATE(G$2,1,1),Hybrid!$A$1:$LI$1),FALSE) -> 0.0098843308 | H77: =VLOOKUP($E77,Hybrid!$1:$1048576,MATCH(DATE(H$2,1,1),Hybrid!$A$1:$LI$1),FALSE) -> 0.010334948 | I77: =VLOOKUP($E77,Hybrid!$1:$1048576,MATCH(DATE(I$2,1,1),Hybrid!$A$1:$LI$1),FALSE) -> 0.01037359 | J77: =VLOOKUP($E77,Hybrid!$1:$1048576,MATCH(DATE(J$2,1,1),Hybrid!$A$1:$LI$1),FALSE) -> 0.010268758 | K77: =VLOOKUP($E77,Hybrid!$1:$1048576,MATCH(DATE(K$2,1,1),Hybrid!$A$1:$LI$1),FALSE) -> 0.01002747 | L77: =VLOOKUP($E77,Hybrid!$1:$1048576,MATCH(DATE(L$2,1,1),Hybrid!$A$1:$LI$1),FALSE) -> 0.0096658256 | M77: =VLOOKUP($E77,Hybrid!$1:$1048576,MATCH(DATE(M$2,1,1),Hybrid!$A$1:$LI$1),FALSE) -> 0.0088323113 | ... AO77: =VLOOKUP($E77,Hybrid!$1:$1048576,MATCH(DATE(AO$2,1,1),Hybrid!$A$1:$LI$1),FALSE) -> 0.0010924483
C78: TOTAL SALES BASELINE | E78: NEWAUTO_0 | F78: =VLOOKUP($E78,Hybrid!$1:$1048576,MATCH(DATE(F$2,1,1),Hybrid!$A$1:$LI$1),FALSE) -> 1886.229 | G78: =VLOOKUP($E78,Hybrid!$1:$1048576,MATCH(DATE(G$2,1,1),Hybrid!$A$1:$LI$1),FALSE) -> 2106.5678 | H78: =VLOOKUP($E78,Hybrid!$1:$1048576,MATCH(DATE(H$2,1,1),Hybrid!$A$1:$LI$1),FALSE) -> 2302.6748 | I78: =VLOOKUP($E78,Hybrid!$1:$1048576,MATCH(DATE(I$2,1,1),Hybrid!$A$1:$LI$1),FALSE) -> 2435.6831 | J78: =VLOOKUP($E78,Hybrid!$1:$1048576,MATCH(DATE(J$2,1,1),Hybrid!$A$1:$LI$1),FALSE) -> 2552.9813 | K78: =VLOOKUP($E78,Hybrid!$1:$1048576,MATCH(DATE(K$2,1,1),Hybrid!$A$1:$LI$1),FALSE) -> 2641.2942 | L78: =VLOOKUP($E78,Hybrid!$1:$1048576,MATCH(DATE(L$2,1,1),Hybrid!$A$1:$LI$1),FALSE) -> 2690.7457 | M78: =VLOOKUP($E78,Hybrid!$1:$1048576,MATCH(DATE(M$2,1,1),Hybrid!$A$1:$LI$1),FALSE) -> 2722.9083 | ... AO78: =VLOOKUP($E78,Hybrid!$1:$1048576,MATCH(DATE(AO$2,1,1),Hybrid!$A$1:$LI$1),FALSE) -> 3670.5827
C79: OIL | E79: NEWAUTO_cfut_0 | F79: =VLOOKUP($E79,Hybrid!$1:$1048576,MATCH(DATE(F$2,1,1),Hybrid!$A$1:$LI$1),FALSE) -> 1868.6749 | G79: =VLOOKUP($E79,Hybrid!$1:$1048576,MATCH(DATE(G$2,1,1),Hybrid!$A$1:$LI$1),FALSE) -> 2086.5477 | H79: =VLOOKUP($E79,Hybrid!$1:$1048576,MATCH(DATE(H$2,1,1),Hybrid!$A$1:$LI$1),FALSE) -> 2280.1545 | I79: =VLOOKUP($E79,Hybrid!$1:$1048576,MATCH(DATE(I$2,1,1),Hybrid!$A$1:$LI$1),FALSE) -> 2410.8839 | J79: =VLOOKUP($E79,Hybrid!$1:$1048576,MATCH(DATE(J$2,1,1),Hybrid!$A$1:$LI$1),FALSE) -> 2525.7354 | K79: =VLOOKUP($E79,Hybrid!$1:$1048576,MATCH(DATE(K$2,1,1),Hybrid!$A$1:$LI$1),FALSE) -> 2611.8978 | L79: =VLOOKUP($E79,Hybrid!$1:$1048576,MATCH(DATE(L$2,1,1),Hybrid!$A$1:$LI$1),FALSE) -> 2659.5285 | M79: =VLOOKUP($E79,Hybrid!$1:$1048576,MATCH(DATE(M$2,1,1),Hybrid!$A$1:$LI$1),FALSE) -> 2689.7831 | ... AO79: =VLOOKUP($E79,Hybrid!$1:$1048576,MATCH(DATE(AO$2,1,1),Hybrid!$A$1:$LI$1),FALSE) -> 3318.329
D80: class A | E80: NEWAUTO_ca_cfut_0 | F80: =VLOOKUP($E80,Hybrid!$1:$1048576,MATCH(DATE(F$2,1,1),Hybrid!$A$1:$LI$1),FALSE) -> 528.64569 | G80: =VLOOKUP($E80,Hybrid!$1:$1048576,MATCH(DATE(G$2,1,1),Hybrid!$A$1:$LI$1),FALSE) -> 593.25182 | H80: =VLOOKUP($E80,Hybrid!$1:$1048576,MATCH(DATE(H$2,1,1),Hybrid!$A$1:$LI$1),FALSE) -> 652.69167 | I80: =VLOOKUP($E80,Hybrid!$1:$1048576,MATCH(DATE(I$2,1,1),Hybrid!$A$1:$LI$1),FALSE) -> 695.47911 | J80: =VLOOKUP($E80,Hybrid!$1:$1048576,MATCH(DATE(J$2,1,1),Hybrid!$A$1:$LI$1),FALSE) -> 734.53236 | K80: =VLOOKUP($E80,Hybrid!$1:$1048576,MATCH(DATE(K$2,1,1),Hybrid!$A$1:$LI$1),FALSE) -> 765.43106 | L80: =VLOOKUP($E80,Hybrid!$1:$1048576,MATCH(DATE(L$2,1,1),Hybrid!$A$1:$LI$1),FALSE) -> 785.35895 | M80: =VLOOKUP($E80,Hybrid!$1:$1048576,MATCH(DATE(M$2,1,1),Hybrid!$A$1:$LI$1),FALSE) -> 800.62409 | ... AO80: =VLOOKUP($E80,Hybrid!$1:$1048576,MATCH(DATE(AO$2,1,1),Hybrid!$A$1:$LI$1),FALSE) -> 1176.3513
D81: class B | E81: NEWAUTO_cb_cfut_0 | F81: =VLOOKUP($E81,Hybrid!$1:$1048576,MATCH(DATE(F$2,1,1),Hybrid!$A$1:$LI$1),FALSE) -> 507.5268 | G81: =VLOOKUP($E81,Hybrid!$1:$1048576,MATCH(DATE(G$2,1,1),Hybrid!$A$1:$LI$1),FALSE) -> 568.87473 | H81: =VLOOKUP($E81,Hybrid!$1:$1048576,MATCH(DATE(H$2,1,1),Hybrid!$A$1:$LI$1),FALSE) -> 624.88258 | I81: =VLOOKUP($E81,Hybrid!$1:$1048576,MATCH(DATE(I$2,1,1),Hybrid!$A$1:$LI$1),FALSE) -> 664.59522 | J81: =VLOOKUP($E81,Hybrid!$1:$1048576,MATCH(DATE(J$2,1,1),Hybrid!$A$1:$LI$1),FALSE) -> 700.52142 | K81: =VLOOKUP($E81,Hybrid!$1:$1048576,MATCH(DATE(K$2,1,1),Hybrid!$A$1:$LI$1),FALSE) -> 728.68279 | L81: =VLOOKUP($E81,Hybrid!$1:$1048576,MATCH(DATE(L$2,1,1),Hybrid!$A$1:$LI$1),FALSE) -> 746.29656 | M81: =VLOOKUP($E81,Hybrid!$1:$1048576,MATCH(DATE(M$2,1,1),Hybrid!$A$1:$LI$1),FALSE) -> 759.25833 | ... AO81: =VLOOKUP($E81,Hybrid!$1:$1048576,MATCH(DATE(AO$2,1,1),Hybrid!$A$1:$LI$1),FALSE) -> 1034.1522
D82: class C | E82: NEWAUTO_cc_cfut_0 | F82: =VLOOKUP($E82,Hybrid!$1:$1048576,MATCH(DATE(F$2,1,1),Hybrid!$A$1:$LI$1),FALSE) -> 351.30528 | G82: =VLOOKUP($E82,Hybrid!$1:$1048576,MATCH(DATE(G$2,1,1),Hybrid!$A$1:$LI$1),FALSE) -> 393.30365 | H82: =VLOOKUP($E82,Hybrid!$1:$1048576,MATCH(DATE(H$2,1,1),Hybrid!$A$1:$LI$1),FALSE) -> 431.34653 | I82: =VLOOKUP($E82,Hybrid!$1:$1048576,MATCH(DATE(I$2,1,1),Hybrid!$A$1:$LI$1),FALSE) -> 457.90304 | J82: =VLOOKUP($E82,Hybrid!$1:$1048576,MATCH(DATE(J$2,1,1),Hybrid!$A$1:$LI$1),FALSE) -> 481.70631 | K82: =VLOOKUP($E82,Hybrid!$1:$1048576,MATCH(DATE(K$2,1,1),Hybrid!$A$1:$LI$1),FALSE) -> 500.18338 | L82: =VLOOKUP($E82,Hybrid!$1:$1048576,MATCH(DATE(L$2,1,1),Hybrid!$A$1:$LI$1),FALSE) -> 511.35481 | M82: =VLOOKUP($E82,Hybrid!$1:$1048576,MATCH(DATE(M$2,1,1),Hybrid!$A$1:$LI$1),FALSE) -> 519.19363 | ... AO82: =VLOOKUP($E82,Hybrid!$1:$1048576,MATCH(DATE(AO$2,1,1),Hybrid!$A$1:$LI$1),FALSE) -> 656.58346
D83: class D | E83: NEWAUTO_cd_cfut_0 | F83: =VLOOKUP($E83,Hybrid!$1:$1048576,MATCH(DATE(F$2,1,1),Hybrid!$A$1:$LI$1),FALSE) -> 194.72119 | G83: =VLOOKUP($E83,Hybrid!$1:$1048576,MATCH(DATE(G$2,1,1),Hybrid!$A$1:$LI$1),FALSE) -> 217.05129 | H83: =VLOOKUP($E83,Hybrid!$1:$1048576,MATCH(DATE(H$2,1,1),Hybrid!$A$1:$LI$1),FALSE) -> 236.61225 | I83: =VLOOKUP($E83,Hybrid!$1:$1048576,MATCH(DATE(I$2,1,1),Hybrid!$A$1:$LI$1),FALSE) -> 249.41709 | J83: =VLOOKUP($E83,Hybrid!$1:$1048576,MATCH(DATE(J$2,1,1),Hybrid!$A$1:$LI$1),FALSE) -> 260.40654 | K83: =VLOOKUP($E83,Hybrid!$1:$1048576,MATCH(DATE(K$2,1,1),Hybrid!$A$1:$LI$1),FALSE) -> 268.37377 | L83: =VLOOKUP($E83,Hybrid!$1:$1048576,MATCH(DATE(L$2,1,1),Hybrid!$A$1:$LI$1),FALSE) -> 272.26001 | M83: =VLOOKUP($E83,Hybrid!$1:$1048576,MATCH(DATE(M$2,1,1),Hybrid!$A$1:$LI$1),FALSE) -> 274.19001 | ... AO83: =VLOOKUP($E83,Hybrid!$1:$1048576,MATCH(DATE(AO$2,1,1),Hybrid!$A$1:$LI$1),FALSE) -> 283.44054
D84: class E | E84: NEWAUTO_ce_cfut_0 | F84: =VLOOKUP($E84,Hybrid!$1:$1048576,MATCH(DATE(F$2,1,1),Hybrid!$A$1:$LI$1),FALSE) -> 119.78455 | G84: =VLOOKUP($E84,Hybrid!$1:$1048576,MATCH(DATE(G$2,1,1),Hybrid!$A$1:$LI$1),FALSE) -> 132.97739 | H84: =VLOOKUP($E84,Hybrid!$1:$1048576,MATCH(DATE(H$2,1,1),Hybrid!$A$1:$LI$1),FALSE) -> 144.14706 | I84: =VLOOKUP($E84,Hybrid!$1:$1048576,MATCH(DATE(I$2,1,1),Hybrid!$A$1:$LI$1),FALSE) -> 150.94512 | J84: =VLOOKUP($E84,Hybrid!$1:$1048576,MATCH(DATE(J$2,1,1),Hybrid!$A$1:$LI$1),FALSE) -> 156.47354 | K84: =VLOOKUP($E84,Hybrid!$1:$1048576,MATCH(DATE(K$2,1,1),Hybrid!$A$1:$LI$1),FALSE) -> 160.12617 | L84: =VLOOKUP($E84,Hybrid!$1:$1048576,MATCH(DATE(L$2,1,1),Hybrid!$A$1:$LI$1),FALSE) -> 161.26977 | M84: =VLOOKUP($E84,Hybrid!$1:$1048576,MATCH(DATE(M$2,1,1),Hybrid!$A$1:$LI$1),FALSE) -> 161.1623 | ... AO84: =VLOOKUP($E84,Hybrid!$1:$1048576,MATCH(DATE(AO$2,1,1),Hybrid!$A$1:$LI$1),FALSE) -> 128.43143
D85: class F | E85: NEWAUTO_cf_cfut_0 | F85: =VLOOKUP($E85,Hybrid!$1:$1048576,MATCH(DATE(F$2,1,1),Hybrid!$A$1:$LI$1),FALSE) -> 57.931007 | G85: =VLOOKUP($E85,Hybrid!$1:$1048576,MATCH(DATE(G$2,1,1),Hybrid!$A$1:$LI$1),FALSE) -> 63.433633 | H85: =VLOOKUP($E85,Hybrid!$1:$1048576,MATCH(DATE(H$2,1,1),Hybrid!$A$1:$LI$1),FALSE) -> 67.455387 | I85: =VLOOKUP($E85,Hybrid!$1:$1048576,MATCH(DATE(I$2,1,1),Hybrid!$A$1:$LI$1),FALSE) -> 69.065361 | J85: =VLOOKUP($E85,Hybrid!$1:$1048576,MATCH(DATE(J$2,1,1),Hybrid!$A$1:$LI$1),FALSE) -> 69.86414 | K85: =VLOOKUP($E85,Hybrid!$1:$1048576,MATCH(DATE(K$2,1,1),Hybrid!$A$1:$LI$1),FALSE) -> 69.741647 | L85: =VLOOKUP($E85,Hybrid!$1:$1048576,MATCH(DATE(L$2,1,1),Hybrid!$A$1:$LI$1),FALSE) -> 68.460519 | M85: =VLOOKUP($E85,Hybrid!$1:$1048576,MATCH(DATE(M$2,1,1),Hybrid!$A$1:$LI$1),FALSE) -> 66.592515 | ... AO85: =VLOOKUP($E85,Hybrid!$1:$1048576,MATCH(DATE(AO$2,1,1),Hybrid!$A$1:$LI$1),FALSE) -> 22.555903
D86: class G | E86: NEWAUTO_cg_cfut_0 | F86: =VLOOKUP($E86,Hybrid!$1:$1048576,MATCH(DATE(F$2,1,1),Hybrid!$A$1:$LI$1),FALSE) -> 108.76034 | G86: =VLOOKUP($E86,Hybrid!$1:$1048576,MATCH(DATE(G$2,1,1),Hybrid!$A$1:$LI$1),FALSE) -> 117.6552 | H86: =VLOOKUP($E86,Hybrid!$1:$1048576,MATCH(DATE(H$2,1,1),Hybrid!$A$1:$LI$1),FALSE) -> 123.01899 | I86: =VLOOKUP($E86,Hybrid!$1:$1048576,MATCH(DATE(I$2,1,1),Hybrid!$A$1:$LI$1),FALSE) -> 123.47895 | J86: =VLOOKUP($E86,Hybrid!$1:$1048576,MATCH(DATE(J$2,1,1),Hybrid!$A$1:$LI$1),FALSE) -> 122.23112 | K86: =VLOOKUP($E86,Hybrid!$1:$1048576,MATCH(DATE(K$2,1,1),Hybrid!$A$1:$LI$1),FALSE) -> 119.35902 | L86: =VLOOKUP($E86,Hybrid!$1:$1048576,MATCH(DATE(L$2,1,1),Hybrid!$A$1:$LI$1),FALSE) -> 114.52786 | M86: =VLOOKUP($E86,Hybrid!$1:$1048576,MATCH(DATE(M$2,1,1),Hybrid!$A$1:$LI$1),FALSE) -> 108.76224 | ... AO86: =VLOOKUP($E86,Hybrid!$1:$1048576,MATCH(DATE(AO$2,1,1),Hybrid!$A$1:$LI$1),FALSE) -> 16.814167
C87: ELEC | E87: NEWAUTO_cele_0 | F87: =VLOOKUP($E87,Hybrid!$1:$1048576,MATCH(DATE(F$2,1,1),Hybrid!$A$1:$LI$1),FALSE) -> 17.397156 | G87: =VLOOKUP($E87,Hybrid!$1:$1048576,MATCH(DATE(G$2,1,1),Hybrid!$A$1:$LI$1),FALSE) -> 19.844788 | H87: =VLOOKUP($E87,Hybrid!$1:$1048576,MATCH(DATE(H$2,1,1),Hybrid!$A$1:$LI$1),FALSE) -> 22.328806 | I87: =VLOOKUP($E87,Hybrid!$1:$1048576,MATCH(DATE(I$2,1,1),Hybrid!$A$1:$LI$1),FALSE) -> 24.596635 | J87: =VLOOKUP($E87,Hybrid!$1:$1048576,MATCH(DATE(J$2,1,1),Hybrid!$A$1:$LI$1),FALSE) -> 27.033711 | K87: =VLOOKUP($E87,Hybrid!$1:$1048576,MATCH(DATE(K$2,1,1),Hybrid!$A$1:$LI$1),FALSE) -> 29.176972 | L87: =VLOOKUP($E87,Hybrid!$1:$1048576,MATCH(DATE(L$2,1,1),Hybrid!$A$1:$LI$1),FALSE) -> 30.993745 | M87: =VLOOKUP($E87,Hybrid!$1:$1048576,MATCH(DATE(M$2,1,1),Hybrid!$A$1:$LI$1),FALSE) -> 32.89919 | ... AO87: =VLOOKUP($E87,Hybrid!$1:$1048576,MATCH(DATE(AO$2,1,1),Hybrid!$A$1:$LI$1),FALSE) -> 351.97497
D88: class A | E88: NEWAUTO_ca_cele_0 | F88: =VLOOKUP($E88,Hybrid!$1:$1048576,MATCH(DATE(F$2,1,1),Hybrid!$A$1:$LI$1),FALSE) -> 4.9240804 | G88: =VLOOKUP($E88,Hybrid!$1:$1048576,MATCH(DATE(G$2,1,1),Hybrid!$A$1:$LI$1),FALSE) -> 5.6535364 | H88: =VLOOKUP($E88,Hybrid!$1:$1048576,MATCH(DATE(H$2,1,1),Hybrid!$A$1:$LI$1),FALSE) -> 6.4168136 | I88: =VLOOKUP($E88,Hybrid!$1:$1048576,MATCH(DATE(I$2,1,1),Hybrid!$A$1:$LI$1),FALSE) -> 7.1418413 | J88: =VLOOKUP($E88,Hybrid!$1:$1048576,MATCH(DATE(J$2,1,1),Hybrid!$A$1:$LI$1),FALSE) -> 7.9346752 | K88: =VLOOKUP($E88,Hybrid!$1:$1048576,MATCH(DATE(K$2,1,1),Hybrid!$A$1:$LI$1),FALSE) -> 8.6470226 | L88: =VLOOKUP($E88,Hybrid!$1:$1048576,MATCH(DATE(L$2,1,1),Hybrid!$A$1:$LI$1),FALSE) -> 9.2714882 | M88: =VLOOKUP($E88,Hybrid!$1:$1048576,MATCH(DATE(M$2,1,1),Hybrid!$A$1:$LI$1),FALSE) -> 9.9367032 | ... AO88: =VLOOKUP($E88,Hybrid!$1:$1048576,MATCH(DATE(AO$2,1,1),Hybrid!$A$1:$LI$1),FALSE) -> 125.80389
D89: class B | E89: NEWAUTO_cb_cele_0 | F89: =VLOOKUP($E89,Hybrid!$1:$1048576,MATCH(DATE(F$2,1,1),Hybrid!$A$1:$LI$1),FALSE) -> 4.7303633 | G89: =VLOOKUP($E89,Hybrid!$1:$1048576,MATCH(DATE(G$2,1,1),Hybrid!$A$1:$LI$1),FALSE) -> 5.4343775 | H89: =VLOOKUP($E89,Hybrid!$1:$1048576,MATCH(DATE(H$2,1,1),Hybrid!$A$1:$LI$1),FALSE) -> 6.1728984 | I89: =VLOOKUP($E89,Hybrid!$1:$1048576,MATCH(DATE(I$2,1,1),Hybrid!$A$1:$LI$1),FALSE) -> 6.8790903 | J89: =VLOOKUP($E89,Hybrid!$1:$1048576,MATCH(DATE(J$2,1,1),Hybrid!$A$1:$LI$1),FALSE) -> 7.6542383 | K89: =VLOOKUP($E89,Hybrid!$1:$1048576,MATCH(DATE(K$2,1,1),Hybrid!$A$1:$LI$1),FALSE) -> 8.3514932 | L89: =VLOOKUP($E89,Hybrid!$1:$1048576,MATCH(DATE(L$2,1,1),Hybrid!$A$1:$LI$1),FALSE) -> 8.9639668 | M89: =VLOOKUP($E89,Hybrid!$1:$1048576,MATCH(DATE(M$2,1,1),Hybrid!$A$1:$LI$1),FALSE) -> 9.6173674 | ... AO89: =VLOOKUP($E89,Hybrid!$1:$1048576,MATCH(DATE(AO$2,1,1),Hybrid!$A$1:$LI$1),FALSE) -> 119.33416
D90: class C | E90: NEWAUTO_cc_cele_0 | F90: =VLOOKUP($E90,Hybrid!$1:$1048576,MATCH(DATE(F$2,1,1),Hybrid!$A$1:$LI$1),FALSE) -> 3.2762546 | G90: =VLOOKUP($E90,Hybrid!$1:$1048576,MATCH(DATE(G$2,1,1),Hybrid!$A$1:$LI$1),FALSE) -> 3.7656985 | H90: =VLOOKUP($E90,Hybrid!$1:$1048576,MATCH(DATE(H$2,1,1),Hybrid!$A$1:$LI$1),FALSE) -> 4.2801564 | I90: =VLOOKUP($E90,Hybrid!$1:$1048576,MATCH(DATE(I$2,1,1),Hybrid!$A$1:$LI$1),FALSE) -> 4.7748504 | J90: =VLOOKUP($E90,Hybrid!$1:$1048576,MATCH(DATE(J$2,1,1),Hybrid!$A$1:$LI$1),FALSE) -> 5.3195294 | K90: =VLOOKUP($E90,Hybrid!$1:$1048576,MATCH(DATE(K$2,1,1),Hybrid!$A$1:$LI$1),FALSE) -> 5.8098257 | L90: =VLOOKUP($E90,Hybrid!$1:$1048576,MATCH(DATE(L$2,1,1),Hybrid!$A$1:$LI$1),FALSE) -> 6.2410511 | M90: =VLOOKUP($E90,Hybrid!$1:$1048576,MATCH(DATE(M$2,1,1),Hybrid!$A$1:$LI$1),FALSE) -> 6.7014549 | ... AO90: =VLOOKUP($E90,Hybrid!$1:$1048576,MATCH(DATE(AO$2,1,1),Hybrid!$A$1:$LI$1),FALSE) -> 81.06444
D91: class D | E91: NEWAUTO_cd_cele_0 | F91: =VLOOKUP($E91,Hybrid!$1:$1048576,MATCH(DATE(F$2,1,1),Hybrid!$A$1:$LI$1),FALSE) -> 1.8075174 | G91: =VLOOKUP($E91,Hybrid!$1:$1048576,MATCH(DATE(G$2,1,1),Hybrid!$A$1:$LI$1),FALSE) -> 2.040643 | H91: =VLOOKUP($E91,Hybrid!$1:$1048576,MATCH(DATE(H$2,1,1),Hybrid!$A$1:$LI$1),FALSE) -> 2.2635124 | I91: =VLOOKUP($E91,Hybrid!$1:$1048576,MATCH(DATE(I$2,1,1),Hybrid!$A$1:$LI$1),FALSE) -> 2.4449492 | J91: =VLOOKUP($E91,Hybrid!$1:$1048576,MATCH(DATE(J$2,1,1),Hybrid!$A$1:$LI$1),FALSE) -> 2.6270223 | K91: =VLOOKUP($E91,Hybrid!$1:$1048576,MATCH(DATE(K$2,1,1),Hybrid!$A$1:$LI$1),FALSE) -> 2.7779785 | L91: =VLOOKUP($E91,Hybrid!$1:$1048576,MATCH(DATE(L$2,1,1),Hybrid!$A$1:$LI$1),FALSE) -> 2.8912462 | M91: =VLOOKUP($E91,Hybrid!$1:$1048576,MATCH(DATE(M$2,1,1),Hybrid!$A$1:$LI$1),FALSE) -> 2.9988878 | ... AO91: =VLOOKUP($E91,Hybrid!$1:$1048576,MATCH(DATE(AO$2,1,1),Hybrid!$A$1:$LI$1),FALSE) -> 16.135147
D92: class E | E92: NEWAUTO_ce_cele_0 | F92: =VLOOKUP($E92,Hybrid!$1:$1048576,MATCH(DATE(F$2,1,1),Hybrid!$A$1:$LI$1),FALSE) -> 1.1126671 | G92: =VLOOKUP($E92,Hybrid!$1:$1048576,MATCH(DATE(G$2,1,1),Hybrid!$A$1:$LI$1),FALSE) -> 1.2533153 | H92: =VLOOKUP($E92,Hybrid!$1:$1048576,MATCH(DATE(H$2,1,1),Hybrid!$A$1:$LI$1),FALSE) -> 1.3856347 | I92: =VLOOKUP($E92,Hybrid!$1:$1048576,MATCH(DATE(I$2,1,1),Hybrid!$A$1:$LI$1),FALSE) -> 1.4914772 | J92: =VLOOKUP($E92,Hybrid!$1:$1048576,MATCH(DATE(J$2,1,1),Hybrid!$A$1:$LI$1),FALSE) -> 1.5967245 | K92: =VLOOKUP($E92,Hybrid!$1:$1048576,MATCH(DATE(K$2,1,1),Hybrid!$A$1:$LI$1),FALSE) -> 1.6817867 | L92: =VLOOKUP($E92,Hybrid!$1:$1048576,MATCH(DATE(L$2,1,1),Hybrid!$A$1:$LI$1),FALSE) -> 1.7429148 | M92: =VLOOKUP($E92,Hybrid!$1:$1048576,MATCH(DATE(M$2,1,1),Hybrid!$A$1:$LI$1),FALSE) -> 1.7998508 | ... AO92: =VLOOKUP($E92,Hybrid!$1:$1048576,MATCH(DATE(AO$2,1,1),Hybrid!$A$1:$LI$1),FALSE) -> 8.0816722
D93: class F | E93: NEWAUTO_cf_cele_0 | F93: =VLOOKUP($E93,Hybrid!$1:$1048576,MATCH(DATE(F$2,1,1),Hybrid!$A$1:$LI$1),FALSE) -> 0.53722538 | G93: =VLOOKUP($E93,Hybrid!$1:$1048576,MATCH(DATE(G$2,1,1),Hybrid!$A$1:$LI$1),FALSE) -> 0.59391241 | H93: =VLOOKUP($E93,Hybrid!$1:$1048576,MATCH(DATE(H$2,1,1),Hybrid!$A$1:$LI$1),FALSE) -> 0.63969269 | I93: =VLOOKUP($E93,Hybrid!$1:$1048576,MATCH(DATE(I$2,1,1),Hybrid!$A$1:$LI$1),FALSE) -> 0.66669276 | J93: =VLOOKUP($E93,Hybrid!$1:$1048576,MATCH(DATE(J$2,1,1),Hybrid!$A$1:$LI$1),FALSE) -> 0.68853529 | K93: =VLOOKUP($E93,Hybrid!$1:$1048576,MATCH(DATE(K$2,1,1),Hybrid!$A$1:$LI$1),FALSE) -> 0.70013448 | L93: =VLOOKUP($E93,Hybrid!$1:$1048576,MATCH(DATE(L$2,1,1),Hybrid!$A$1:$LI$1),FALSE) -> 0.69990772 | M93: =VLOOKUP($E93,Hybrid!$1:$1048576,MATCH(DATE(M$2,1,1),Hybrid!$A$1:$LI$1),FALSE) -> 0.69525821 | ... AO93: =VLOOKUP($E93,Hybrid!$1:$1048576,MATCH(DATE(AO$2,1,1),Hybrid!$A$1:$LI$1),FALSE) -> 0.86593831
D94: class G | E94: NEWAUTO_cg_cele_0 | F94: =VLOOKUP($E94,Hybrid!$1:$1048576,MATCH(DATE(F$2,1,1),Hybrid!$A$1:$LI$1),FALSE) -> 1.0090476 | G94: =VLOOKUP($E94,Hybrid!$1:$1048576,MATCH(DATE(G$2,1,1),Hybrid!$A$1:$LI$1),FALSE) -> 1.1033044 | H94: =VLOOKUP($E94,Hybrid!$1:$1048576,MATCH(DATE(H$2,1,1),Hybrid!$A$1:$LI$1),FALSE) -> 1.1700975 | I94: =VLOOKUP($E94,Hybrid!$1:$1048576,MATCH(DATE(I$2,1,1),Hybrid!$A$1:$LI$1),FALSE) -> 1.1977337 | J94: =VLOOKUP($E94,Hybrid!$1:$1048576,MATCH(DATE(J$2,1,1),Hybrid!$A$1:$LI$1),FALSE) -> 1.2129864 | K94: =VLOOKUP($E94,Hybrid!$1:$1048576,MATCH(DATE(K$2,1,1),Hybrid!$A$1:$LI$1),FALSE) -> 1.2087304 | L94: =VLOOKUP($E94,Hybrid!$1:$1048576,MATCH(DATE(L$2,1,1),Hybrid!$A$1:$LI$1),FALSE) -> 1.1831702 | M94: =VLOOKUP($E94,Hybrid!$1:$1048576,MATCH(DATE(M$2,1,1),Hybrid!$A$1:$LI$1),FALSE) -> 1.149668 | ... AO94: =VLOOKUP($E94,Hybrid!$1:$1048576,MATCH(DATE(AO$2,1,1),Hybrid!$A$1:$LI$1),FALSE) -> 0.68973045
C95: GAS | E95: NEWAUTO_cgas_0 | F95: =VLOOKUP($E95,Hybrid!$1:$1048576,MATCH(DATE(F$2,1,1),Hybrid!$A$1:$LI$1),FALSE) -> 0.15698923 | G95: =VLOOKUP($E95,Hybrid!$1:$1048576,MATCH(DATE(G$2,1,1),Hybrid!$A$1:$LI$1),FALSE) -> 0.17529295 | H95: =VLOOKUP($E95,Hybrid!$1:$1048576,MATCH(DATE(H$2,1,1),Hybrid!$A$1:$LI$1),FALSE) -> 0.19155805 | I95: =VLOOKUP($E95,Hybrid!$1:$1048576,MATCH(DATE(I$2,1,1),Hybrid!$A$1:$LI$1),FALSE) -> 0.20254075 | J95: =VLOOKUP($E95,Hybrid!$1:$1048576,MATCH(DATE(J$2,1,1),Hybrid!$A$1:$LI$1),FALSE) -> 0.21218955 | K95: =VLOOKUP($E95,Hybrid!$1:$1048576,MATCH(DATE(K$2,1,1),Hybrid!$A$1:$LI$1),FALSE) -> 0.21942814 | L95: =VLOOKUP($E95,Hybrid!$1:$1048576,MATCH(DATE(L$2,1,1),Hybrid!$A$1:$LI$1),FALSE) -> 0.22342963 | M95: =VLOOKUP($E95,Hybrid!$1:$1048576,MATCH(DATE(M$2,1,1),Hybrid!$A$1:$LI$1),FALSE) -> 0.22597136 | ... AO95: =VLOOKUP($E95,Hybrid!$1:$1048576,MATCH(DATE(AO$2,1,1),Hybrid!$A$1:$LI$1),FALSE) -> 0.27877612
D96: class A | E96: NEWAUTO_ca_cgas_0 | F96: =VLOOKUP($E96,Hybrid!$1:$1048576,MATCH(DATE(F$2,1,1),Hybrid!$A$1:$LI$1),FALSE) -> 0.044412051 | G96: =VLOOKUP($E96,Hybrid!$1:$1048576,MATCH(DATE(G$2,1,1),Hybrid!$A$1:$LI$1),FALSE) -> 0.049839676 | H96: =VLOOKUP($E96,Hybrid!$1:$1048576,MATCH(DATE(H$2,1,1),Hybrid!$A$1:$LI$1),FALSE) -> 0.054833277 | I96: =VLOOKUP($E96,Hybrid!$1:$1048576,MATCH(DATE(I$2,1,1),Hybrid!$A$1:$LI$1),FALSE) -> 0.058427892 | J96: =VLOOKUP($E96,Hybrid!$1:$1048576,MATCH(DATE(J$2,1,1),Hybrid!$A$1:$LI$1),FALSE) -> 0.061708794 | K96: =VLOOKUP($E96,Hybrid!$1:$1048576,MATCH(DATE(K$2,1,1),Hybrid!$A$1:$LI$1),FALSE) -> 0.064304625 | L96: =VLOOKUP($E96,Hybrid!$1:$1048576,MATCH(DATE(L$2,1,1),Hybrid!$A$1:$LI$1),FALSE) -> 0.065978787 | M96: =VLOOKUP($E96,Hybrid!$1:$1048576,MATCH(DATE(M$2,1,1),Hybrid!$A$1:$LI$1),FALSE) -> 0.067261226 | ... AO96: =VLOOKUP($E96,Hybrid!$1:$1048576,MATCH(DATE(AO$2,1,1),Hybrid!$A$1:$LI$1),FALSE) -> 0.09882644
D97: class B | E97: NEWAUTO_cb_cgas_0 | F97: =VLOOKUP($E97,Hybrid!$1:$1048576,MATCH(DATE(F$2,1,1),Hybrid!$A$1:$LI$1),FALSE) -> 0.042637831 | G97: =VLOOKUP($E97,Hybrid!$1:$1048576,MATCH(DATE(G$2,1,1),Hybrid!$A$1:$LI$1),FALSE) -> 0.047791732 | H97: =VLOOKUP($E97,Hybrid!$1:$1048576,MATCH(DATE(H$2,1,1),Hybrid!$A$1:$LI$1),FALSE) -> 0.052497008 | I97: =VLOOKUP($E97,Hybrid!$1:$1048576,MATCH(DATE(I$2,1,1),Hybrid!$A$1:$LI$1),FALSE) -> 0.055833306 | J97: =VLOOKUP($E97,Hybrid!$1:$1048576,MATCH(DATE(J$2,1,1),Hybrid!$A$1:$LI$1),FALSE) -> 0.058851501 | K97: =VLOOKUP($E97,Hybrid!$1:$1048576,MATCH(DATE(K$2,1,1),Hybrid!$A$1:$LI$1),FALSE) -> 0.061217366 | L97: =VLOOKUP($E97,Hybrid!$1:$1048576,MATCH(DATE(L$2,1,1),Hybrid!$A$1:$LI$1),FALSE) -> 0.062697117 | M97: =VLOOKUP($E97,Hybrid!$1:$1048576,MATCH(DATE(M$2,1,1),Hybrid!$A$1:$LI$1),FALSE) -> 0.063786048 | ... AO97: =VLOOKUP($E97,Hybrid!$1:$1048576,MATCH(DATE(AO$2,1,1),Hybrid!$A$1:$LI$1),FALSE) -> 0.086880157
D98: class C | E98: NEWAUTO_cc_cgas_0 | F98: =VLOOKUP($E98,Hybrid!$1:$1048576,MATCH(DATE(F$2,1,1),Hybrid!$A$1:$LI$1),FALSE) -> 0.029513507 | G98: =VLOOKUP($E98,Hybrid!$1:$1048576,MATCH(DATE(G$2,1,1),Hybrid!$A$1:$LI$1),FALSE) -> 0.033041831 | H98: =VLOOKUP($E98,Hybrid!$1:$1048576,MATCH(DATE(H$2,1,1),Hybrid!$A$1:$LI$1),FALSE) -> 0.036237851 | I98: =VLOOKUP($E98,Hybrid!$1:$1048576,MATCH(DATE(I$2,1,1),Hybrid!$A$1:$LI$1),FALSE) -> 0.03846889 | J98: =VLOOKUP($E98,Hybrid!$1:$1048576,MATCH(DATE(J$2,1,1),Hybrid!$A$1:$LI$1),FALSE) -> 0.040468626 | K98: =VLOOKUP($E98,Hybrid!$1:$1048576,MATCH(DATE(K$2,1,1),Hybrid!$A$1:$LI$1),FALSE) -> 0.042020904 | L98: =VLOOKUP($E98,Hybrid!$1:$1048576,MATCH(DATE(L$2,1,1),Hybrid!$A$1:$LI$1),FALSE) -> 0.042959427 | M98: =VLOOKUP($E98,Hybrid!$1:$1048576,MATCH(DATE(M$2,1,1),Hybrid!$A$1:$LI$1),FALSE) -> 0.043617974 | ... AO98: =VLOOKUP($E98,Hybrid!$1:$1048576,MATCH(DATE(AO$2,1,1),Hybrid!$A$1:$LI$1),FALSE) -> 0.05516023
D99: class D | E99: NEWAUTO_cd_cgas_0 | F99: =VLOOKUP($E99,Hybrid!$1:$1048576,MATCH(DATE(F$2,1,1),Hybrid!$A$1:$LI$1),FALSE) -> 0.016358721 | G99: =VLOOKUP($E99,Hybrid!$1:$1048576,MATCH(DATE(G$2,1,1),Hybrid!$A$1:$LI$1),FALSE) -> 0.018234695 | H99: =VLOOKUP($E99,Hybrid!$1:$1048576,MATCH(DATE(H$2,1,1),Hybrid!$A$1:$LI$1),FALSE) -> 0.019878031 | I99: =VLOOKUP($E99,Hybrid!$1:$1048576,MATCH(DATE(I$2,1,1),Hybrid!$A$1:$LI$1),FALSE) -> 0.020953778 | J99: =VLOOKUP($E99,Hybrid!$1:$1048576,MATCH(DATE(J$2,1,1),Hybrid!$A$1:$LI$1),FALSE) -> 0.021877012 | K99: =VLOOKUP($E99,Hybrid!$1:$1048576,MATCH(DATE(K$2,1,1),Hybrid!$A$1:$LI$1),FALSE) -> 0.022546347 | L99: =VLOOKUP($E99,Hybrid!$1:$1048576,MATCH(DATE(L$2,1,1),Hybrid!$A$1:$LI$1),FALSE) -> 0.022872834 | M99: =VLOOKUP($E99,Hybrid!$1:$1048576,MATCH(DATE(M$2,1,1),Hybrid!$A$1:$LI$1),FALSE) -> 0.023034975 | ... AO99: =VLOOKUP($E99,Hybrid!$1:$1048576,MATCH(DATE(AO$2,1,1),Hybrid!$A$1:$LI$1),FALSE) -> 0.023812122
D100: class E | E100: NEWAUTO_ce_cgas_0 | F100: =VLOOKUP($E100,Hybrid!$1:$1048576,MATCH(DATE(F$2,1,1),Hybrid!$A$1:$LI$1),FALSE) -> 0.010063219 | G100: =VLOOKUP($E100,Hybrid!$1:$1048576,MATCH(DATE(G$2,1,1),Hybrid!$A$1:$LI$1),FALSE) -> 0.011171563 | H100: =VLOOKUP($E100,Hybrid!$1:$1048576,MATCH(DATE(H$2,1,1),Hybrid!$A$1:$LI$1),FALSE) -> 0.012109938 | I100: =VLOOKUP($E100,Hybrid!$1:$1048576,MATCH(DATE(I$2,1,1),Hybrid!$A$1:$LI$1),FALSE) -> 0.01268105 | J100: =VLOOKUP($E100,Hybrid!$1:$1048576,MATCH(DATE(J$2,1,1),Hybrid!$A$1:$LI$1),FALSE) -> 0.013145498 | K100: =VLOOKUP($E100,Hybrid!$1:$1048576,MATCH(DATE(K$2,1,1),Hybrid!$A$1:$LI$1),FALSE) -> 0.013452359 | L100: =VLOOKUP($E100,Hybrid!$1:$1048576,MATCH(DATE(L$2,1,1),Hybrid!$A$1:$LI$1),FALSE) -> 0.013548434 | M100: =VLOOKUP($E100,Hybrid!$1:$1048576,MATCH(DATE(M$2,1,1),Hybrid!$A$1:$LI$1),FALSE) -> 0.013539405 | ... AO100: =VLOOKUP($E100,Hybrid!$1:$1048576,MATCH(DATE(AO$2,1,1),Hybrid!$A$1:$LI$1),FALSE) -> 0.010789652
...

Sheet date
A1: =Hybrid!A1 -> _date_ | B1: =Hybrid!B1 -> 42005 | C1: =Hybrid!C1 -> 42370 | D1: =Hybrid!D1 -> 42736 | E1: =Hybrid!E1 -> 43101 | F1: =Hybrid!F1 -> 43466 | G1: =Hybrid!G1 -> 43831 | H1: =Hybrid!H1 -> 44197 | ... AK1: =Hybrid!AK1 -> 54789
B2: =TEXT(B1,"jj mm aaaa") -> 01 01 2015 | C2: =TEXT(C1,"jj mm aaaa") -> 01 01 2016 | D2: =TEXT(D1,"jj mm aaaa") -> 01 01 2017 | E2: =TEXT(E1,"jj mm aaaa") -> 01 01 2018 | F2: =TEXT(F1,"jj mm aaaa") -> 01 01 2019 | G2: =TEXT(G1,"jj mm aaaa") -> 01 01 2020 | H2: =TEXT(H1,"jj mm aaaa") -> 01 01 2021 | I2: =TEXT(I1,"jj mm aaaa") -> 01 01 2022 | ... AK2: =TEXT(AK1,"jj mm aaaa") -> 01 01 2050
B3: =RIGHT(B2,4) -> 2015 | C3: =RIGHT(C2,4) -> 2016 | D3: =RIGHT(D2,4) -> 2017 | E3: =RIGHT(E2,4) -> 2018 | F3: =RIGHT(F2,4) -> 2019 | G3: =RIGHT(G2,4) -> 2020 | H3: =RIGHT(H2,4) -> 2021 | I3: =RIGHT(I2,4) -> 2022 | ... AK3: =RIGHT(AK2,4) -> 2050

Sheet Emissions
A1: _date_ | B1: 42005 | C1: 42370 | D1: 42736 | E1: 43101 | F1: 43466 | G1: 43831 | H1: 44197 | I1: 44562 | J1: 44927 | K1: 45292 | L1: 45658 | M1: 46023 | N1: 46388 | O1: 46753 | P1: 47119 | Q1: 47484 | R1: 47849 | S1: 48214 | T1: 48580 | U1: 48945 | V1: 49310 | W1: 49675 | X1: 50041 | Y1: 50406 | Z1: 50771 | AA1: 51136 | AB1: 51502 | AC1: 51867 | AD1: 52232 | AE1: 52597 | AF1: 52963 | AG1: 53328 | AH1: 53693 | AI1: 54058 | AJ1: 54424 | AK1: 54789
A2: ems_2 | B2: 470.0039 | C2: 472.83603 | D2: 474.82849 | E2: 476.66484 | F2: 478.51486 | G2: 480.33131 | H2: 482.16006 | I2: 484.12721 | J2: 486.25674 | K2: 488.51337 | L2: 490.83035 | M2: 493.12615 | N2: 495.31487 | O2: 497.3136 | P2: 499.04795 | Q2: 500.45607 | R2: 501.58207 | S2: 502.54725 | T2: 503.43464 | U2: 504.29792 | V2: 505.17101 | W2: 506.07484 | X2: 507.02175 | Y2: 508.01828 | Z2: 509.06703 | AA2: 510.16788 | AB2: 511.31884 | AC2: 512.51662 | AD2: 513.75711 | AE2: 515.03572 | AF2: 516.34759 | AG2: 517.68791 | AH2: 519.05204 | AI2: 520.43573 | AJ2: 521.83525 | AK2: 523.24755
A3: ems_ch_2 | B3: 129.15358 | C3: 128.76844 | D3: 127.85718 | E3: 126.91251 | F3: 126.06444 | G3: 125.30537 | H3: 124.64342 | I3: 124.10122 | J3: 123.65738 | K3: 123.2774 | L3: 122.92597 | M3: 122.57142 | N3: 122.18707 | O3: 121.75145 | P3: 121.24819 | Q3: 120.66572 | R3: 120.02815 | S3: 119.37662 | T3: 118.72805 | U3: 118.08762 | V3: 117.45493 | W3: 116.82711 | X3: 116.2002 | Y3: 115.56979 | Z3: 114.93135 | AA3: 114.28022 | AB3: 113.61173 | AC3: 112.92114 | AD3: 112.20369 | AE3: 111.45462 | AF3: 110.66921 | AG3: 109.84283 | AH3: 108.97107 | AI3: 108.04978 | AJ3: 107.07523 | AK3: 106.04417
A4: ems_ch_2+ems_ci_2 | B4: 349.86054 | C4: 351.43208 | D4: 352.17187 | E4: 352.71574 | F4: 353.21997 | G4: 353.63894 | H4: 354.02606 | I4: 354.51518 | J4: 355.13547 | K4: 355.85521 | L4: 356.61034 | M4: 357.32151 | N4: 357.90489 | O4: 358.27969 | P4: 358.37381 | Q4: 358.12797 | R4: 357.58984 | S4: 356.88392 | T4: 356.09414 | U4: 355.27393 | V4: 354.45639 | W4: 353.66131 | X4: 352.89986 | Y4: 352.17746 | Z4: 351.49574 | AA4: 350.85375 | AB4: 350.24886 | AC4: 349.67728 | AD4: 349.13452 | AE4: 348.61565 | AF4: 348.1156 | AG4: 347.6293 | AH4: 347.15189 | AI4: 346.67884 | AJ4: 346.20613 | AK4: 345.73036
A5: ems_ci_2 | B5: 220.70697 | C5: 222.66364 | D5: 224.3147 | E5: 225.80323 | F5: 227.15553 | G5: 228.33357 | H5: 229.38264 | I5: 230.41397 | J5: 231.47809 | K5: 232.5778 | L5: 233.68436 | M5: 234.75009 | N5: 235.71782 | O5: 236.52825 | P5: 237.12563 | Q5: 237.46225 | R5: 237.56169 | S5: 237.5073 | T5: 237.36609 | U5: 237.18632 | V5: 237.00145 | W5: 236.8342 | X5: 236.69967 | Y5: 236.60767 | Z5: 236.56439 | AA5: 236.57353 | AB5: 236.63713 | AC5: 236.75614 | AD5: 236.93083 | AE5: 237.16103 | AF5: 237.4464 | AG5: 237.78647 | AH5: 238.18082 | AI5: 238.62905 | AJ5: 239.1309 | AK5: 239.68619
A6: ems_mat_2 | B6: 27.950294 | C6: 28.262122 | D6: 28.572597 | E6: 28.885878 | F6: 29.203763 | G6: 29.526446 | H6: 29.853693 | I6: 30.185514 | J6: 30.521966 | K6: 30.862957 | L6: 31.208203 | M6: 31.557239 | N6: 31.909441 | O6: 32.264058 | P6: 32.620235 | Q6: 32.977041 | R6: 33.333859 | S6: 33.690692 | T6: 34.04791 | U6: 34.405998 | V6: 34.765443 | W6: 35.126696 | X6: 35.490154 | Y6: 35.856157 | Z6: 36.224992 | AA6: 36.596898 | AB6: 36.972074 | AC6: 37.350687 | AD6: 37.73288 | AE6: 38.118775 | AF6: 38.508484 | AG6: 38.90211 | AH6: 39.299752 | AI6: 39.701508 | AJ6: 40.107477 | AK6: 40.51776
A7: ems_y_2 | B7: 92.193058 | C7: 93.141822 | D7: 94.084019 | E7: 95.06322 | F7: 96.091134 | G7: 97.165928 | H7: 98.28031 | I7: 99.426511 | J7: 100.59931 | K7: 101.7952 | L7: 103.01181 | M7: 104.2474 | N7: 105.50053 | O7: 106.76985 | P7: 108.0539 | Q7: 109.35106 | R7: 110.65837 | S7: 111.97263 | T7: 113.29259 | U7: 114.61799 | V7: 115.94918 | W7: 117.28684 | X7: 118.63174 | Y7: 119.98466 | Z7: 121.3463 | AA7: 122.71723 | AB7: 124.0979 | AC7: 125.48865 | AD7: 126.88972 | AE7: 128.30129 | AF7: 129.72351 | AG7: 131.1565 | AH7: 132.6004 | AI7: 134.05538 | AJ7: 135.52164 | AK7: 136.99943
A8: ems_sec_2 | B8: 340.85032 | C8: 344.06758 | D8: 346.97131 | E8: 349.75233 | F8: 352.45042 | G8: 355.02594 | H8: 357.51665 | I8: 360.02599 | J8: 362.59936 | K8: 365.23596 | L8: 367.90438 | M8: 370.55473 | N8: 373.1278 | O8: 375.56215 | P8: 377.79976 | Q8: 379.79036 | R8: 381.55391 | S8: 383.17063 | T8: 384.70658 | U8: 386.2103 | V8: 387.71607 | W8: 389.24773 | X8: 390.82156 | Y8: 392.44849 | Z8: 394.13568 | AA8: 395.88766 | AB8: 397.70711 | AC8: 399.59548 | AD8: 401.55342 | AE8: 403.5811 | AF8: 405.67839 | AG8: 407.84508 | AH8: 410.08097 | AI8: 412.38594 | AJ8: 414.76002 | AK8: 417.20338
A9: ems_ets_2 | B9: 126.91621 | C9: 128.03575 | D9: 128.97055 | E9: 129.80991 | F9: 130.57505 | G9: 131.24779 | H9: 131.8479 | I9: 132.4314 | J9: 133.02733 | K9: 133.63954 | L9: 134.25401 | M9: 134.84546 | N9: 135.38274 | O9: 135.83304 | P9: 136.16528 | Q9: 136.35275 | R9: 136.4057 | S9: 136.36751 | T9: 136.27583 | U9: 136.15873 | V9: 136.03587 | W9: 135.92057 | X9: 135.8216 | Y9: 135.74462 | Z9: 135.69319 | AA9: 135.66944 | AB9: 135.67462 | AC9: 135.70941 | AD9: 135.77413 | AE9: 135.86892 | AF9: 135.99383 | AG9: 136.14887 | AH9: 136.3341 | AI9: 136.54958 | AJ9: 136.79547 | AK9: 137.07197
A10: ems_nets_2 | B10: 213.93412 | C10: 216.03183 | D10: 218.00076 | E10: 219.94241 | F10: 221.87537 | G10: 223.77815 | H10: 225.66875 | I10: 227.59459 | J10: 229.57203 | K10: 231.59643 | L10: 233.65037 | M10: 235.70926 | N10: 237.74505 | O10: 239.72912 | P10: 241.63448 | Q10: 243.4376 | R10: 245.14821 | S10: 246.80312 | T10: 248.43075 | U10: 250.05157 | V10: 251.6802 | W10: 253.32717 | X10: 254.99996 | Y10: 256.70386 | Z10: 258.44249 | AA10: 260.21822 | AB10: 262.03248 | AC10: 263.88607 | AD10: 265.77929 | AE10: 267.71217 | AF10: 269.68455 | AG10: 271.6962 | AH10: 273.74687 | AI10: 275.83636 | AJ10: 277.96455 | AK10: 280.13141
A11: ems_netsi_2 | B11: 25.647636 | C11: 25.890505 | D11: 26.110082 | E11: 26.318111 | F11: 26.516486 | G11: 26.702008 | H11: 26.87982 | I11: 27.060347 | J11: 27.24744 | K11: 27.440549 | L11: 27.636482 | M11: 27.830557 | N11: 28.017372 | O11: 28.191366 | P11: 28.347265 | Q11: 28.480431 | R11: 28.592984 | S11: 28.692565 | T11: 28.784965 | U11: 28.874271 | V11: 28.963357 | W11: 29.054257 | X11: 29.148414 | Y11: 29.246839 | Z11: 29.350231 | AA11: 29.459052 | AB11: 29.57359 | AC11: 29.694006 | AD11: 29.820369 | AE11: 29.952686 | AF11: 30.090923 | AG11: 30.235019 | AH11: 30.3849 | AI11: 30.54049 | AJ11: 30.701713 | AK11: 30.8685
A12: ems_trsp_2-ems_sair_2 | B12: 24.99273 | C12: 25.238692 | D12: 25.465247 | E12: 25.684389 | F12: 25.899206 | G12: 26.107879 | H12: 26.311582 | I12: 26.515047 | J12: 26.720616 | K12: 26.928295 | L12: 27.136346 | M12: 27.341801 | N12: 27.54085 | O12: 27.729159 | P12: 27.902126 | Q12: 28.05512 | R12: 28.187882 | S12: 28.304685 | T12: 28.409396 | U12: 28.505062 | V12: 28.594034 | W12: 28.678132 | X12: 28.758775 | Y12: 28.837082 | Z12: 28.913944 | AA12: 28.990087 | AB12: 29.066107 | AC12: 29.14251 | AD12: 29.219734 | AE12: 29.298167 | AF12: 29.378163 | AG12: 29.46005 | AH12: 29.544141 | AI12: 29.630734 | AJ12: 29.720123 | AK12: 29.812594
... A819: ems_ch_cbio_0+ems_ci_cbio_0 | B819: 31.971027 | C819: 32.007879 | D819: 31.913715 | E819: 31.777071 | F819: 31.634471 | G819: 31.499044 | H819: 31.374108 | I819: 31.259284 | J819: 31.153102 | K819: 31.054017 | L819: 30.96074 | M819: 30.872295 | N819: 30.787979 | O819: 30.707301 | P819: 30.629922 | Q819: 30.555608 | R819: 30.484203 | S819: 30.415596 | T819: 30.349705 | U819: 30.286408 | V819: 30.225638 | W819: 30.167359 | X819: 30.111552 | Y819: 30.058202 | Z819: 30.007304 | AA819: 29.958849 | AB819: 29.912833 | AC819: 29.869249 | AD819: 29.828093 | AE819: 29.789358 | AF819: 29.75304 | AG819: 29.719132 | AH819: 29.68763 | AI819: 29.658527 | AJ819: 29.63182 | AK819: 29.607503

Sheet Consumption
A1: _date_ | B1: 42005 | C1: 42370 | D1: 42736 | E1: 43101 | F1: 43466 | G1: 43831 | H1: 44197 | I1: 44562 | J1: 44927 | K1: 45292 | L1: 45658 | M1: 46023 | N1: 46388 | O1: 46753 | P1: 47119 | Q1: 47484 | R1: 47849 | S1: 48214 | T1: 48580 | U1: 48945 | V1: 49310 | W1: 49675 | X1: 50041 | Y1: 50406 | Z1: 50771 | AA1: 51136 | AB1: 51502 | AC1: 51867 | AD1: 52232 | AE1: 52597 | AF1: 52963 | AG1: 53328 | AH1: 53693 | AI1: 54058 | AJ1: 54424 | AK1: 54789
A2: ch_2 | B2: 1202071.8 | C2: 1215690.3 | D2: 1229310.3 | E2: 1243013.1 | F2: 1256875.5 | G2: 1270997.6 | H2: 1285460.8 | I2: 1300296.3 | J2: 1315499.9 | K2: 1331056.7 | L2: 1346957.4 | M2: 1363202.4 | N2: 1379801.2 | O2: 1396770.3 | P2: 1414130.4 | Q2: 1431905 | R2: 1450101.3 | S2: 1468696.7 | T2: 1487656 | U2: 1506945.7 | V2: 1526542.6 | W2: 1546433.3 | X2: 1566610.7 | Y2: 1587071 | Z2: 1607810.9 | AA2: 1628826.1 | AB2: 1650110.2 | AC2: 1671655.2 | AD2: 1693451 | AE2: 1715486.1 | AF2: 1737748.4 | AG2: 1760225.1 | AH2: 1782903.7 | AI2: 1805772 | AJ2: 1828818.9 | AK2: 1852033.8
A3: ch_0 | B3: 1202071.8 | C3: 1215641.6 | D3: 1229141.5 | E3: 1242648.3 | F3: 1256238.1 | G3: 1270001.2 | H3: 1284016.1 | I3: 1298333 | J3: 1312973.1 | K3: 1327935.9 | L3: 1343208.5 | M3: 1358772.9 | N3: 1374610.8 | O3: 1390705.9 | P3: 1407045.5 | Q3: 1423620.3 | R3: 1440423.8 | S3: 1457451.5 | T3: 1474700.5 | U3: 1492169 | V3: 1509855.2 | W3: 1527757.7 | X3: 1545875.1 | Y3: 1564206 | Z3: 1582749 | AA3: 1601502.9 | AB3: 1620466.6 | AC3: 1639639.4 | AD3: 1659020.8 | AE3: 1678610.9 | AF3: 1698410.1 | AG3: 1718419.4 | AH3: 1738640.1 | AI3: 1759074.1 | AJ3: 1779723.6 | AK3: 1800591.2
A4: pch_2 | B4: 1 | C4: 1.0202623 | D4: 1.0408444 | E4: 1.0618446 | F4: 1.083382 | G4: 1.1055795 | H4: 1.1283896 | I4: 1.151736 | J4: 1.1756836 | K4: 1.2002924 | L4: 1.2256236 | M4: 1.2517441 | N4: 1.2787299 | O4: 1.306668 | P4: 1.3356569 | Q4: 1.3658072 | R4: 1.3970906 | S4: 1.4294313 | T4: 1.4628618 | U4: 1.4974028 | V4: 1.5330655 | W4: 1.5698545 | X4: 1.6077702 | Y4: 1.6468101 | Z4: 1.6869697 | AA4: 1.7282423 | AB4: 1.7706198 | AC4: 1.8140921 | AD4: 1.8586473 | AE4: 1.9042716 | AF4: 1.9509492 | AG4: 1.9986623 | AH4: 2.0473909 | AI4: 2.0971133 | AJ4: 2.1478055 | AK4: 2.1994422
A5: pch_0 | B5: 1 | C5: 1.0198987 | D5: 1.0400695 | E5: 1.0605437 | F5: 1.0813678 | G5: 1.1025858 | H5: 1.1242353 | I5: 1.146347 | J5: 1.1689465 | K5: 1.1920554 | L5: 1.2156926 | M5: 1.2398742 | N5: 1.2646147 | O5: 1.2899264 | P5: 1.3158205 | Q5: 1.3423069 | R5: 1.3693946 | S5: 1.397092 | T5: 1.4254069 | U5: 1.454347 | V5: 1.4839199 | W5: 1.5141329 | X5: 1.5449937 | Y5: 1.5765098 | Z5: 1.6086892 | AA5: 1.64154 | AB5: 1.6750706 | AC5: 1.7092899 | AD5: 1.744207 | AE5: 1.7798315 | AF5: 1.8161737 | AG5: 1.8532442 | AH5: 1.891054 | AI5: 1.9296152 | AJ5: 1.9689399 | AK5: 2.0090411
A6: ch_cagr_2 | B6: 31638 | C6: 31926.31 | D6: 32213.197 | E6: 32523.423 | F6: 32862.586 | G6: 33229.322 | H6: 33619.294 | I6: 34027.869 | J6: 34452.106 | K6: 34890.056 | L6: 35340.462 | M6: 35802.578 | N6: 36276.021 | O6: 36760.672 | P6: 37256.589 | Q6: 37763.954 | R6: 38281.902 | S6: 38809.112 | T6: 39345.253 | U6: 39890.278 | V6: 40444.218 | W6: 41007.104 | X6: 41578.934 | Y6: 42159.649 | Z6: 42749.123 | AA6: 43347.155 | AB6: 43953.48 | AC6: 44567.773 | AD6: 45189.661 | AE6: 45818.735 | AF6: 46454.567 | AG6: 47096.717 | AH6: 47744.75 | AI6: 48398.241 | AJ6: 49056.784 | AK6: 49720
A7: ch_cagr_0 | B7: 31638 | C7: 31923.619 | D7: 32206.85 | E7: 32512.452 | F7: 32845.535 | G7: 33204.073 | H7: 33584.186 | I7: 33982.118 | J7: 34394.806 | K7: 34819.912 | L7: 35255.709 | M7: 35700.938 | N7: 36154.696 | O7: 36616.348 | P7: 37085.459 | Q7: 37561.74 | R7: 38045 | S7: 38535.116 | T7: 39032.007 | U7: 39535.611 | V7: 40045.87 | W7: 40562.729 | X7: 41086.129 | Y7: 41616.009 | Z7: 42152.303 | AA7: 42694.952 | AB7: 43243.898 | AC7: 43799.093 | AD7: 44360.5 | AE7: 44928.092 | AF7: 45501.861 | AG7: 46081.809 | AH7: 46667.955 | AI7: 47260.332 | AJ7: 47858.988 | AK7: 48463.982
A8: pch_cagr_2 | B8: 1 | C8: 1.0200639 | D8: 1.0405389 | E8: 1.0614615 | F8: 1.0829052 | G8: 1.1049599 | H8: 1.1276481 | I8: 1.1509345 | J8: 1.1748158 | K8: 1.199313 | L8: 1.2244675 | M8: 1.2503383 | N8: 1.2769998 | O8: 1.3045398 | P8: 1.3330584 | Q8: 1.3626678 | R8: 1.3934134 | S8: 1.4252695 | T8: 1.4582214 | U8: 1.4922613 | V8: 1.5273867 | W8: 1.5635984 | X8: 1.6008996 | Y8: 1.6392947 | Z8: 1.6787882 | AA8: 1.7193843 | AB8: 1.761086 | AC8: 1.8038952 | AD8: 1.8478127 | AE8: 1.8928376 | AF8: 1.9389678 | AG8: 1.9861998 | AH8: 2.0345289 | AI8: 2.0839489 | AJ8: 2.1344525 | AK8: 2.1860311
A9: pch_cagr_0 | B9: 1 | C9: 1.0199097 | D9: 1.0401102 | E9: 1.0606346 | F9: 1.0815269 | G9: 1.1028261 | H9: 1.1245631 | I9: 1.1467626 | J9: 1.1694451 | K9: 1.1926287 | L9: 1.2163293 | M9: 1.2405618 | N9: 1.2653394 | O9: 1.2906742 | P9: 1.3165769 | Q9: 1.3430574 | R9: 1.3701249 | S9: 1.3977879 | T9: 1.4260546 | U9: 1.454933 | V9: 1.484431 | W9: 1.5145566 | X9: 1.545318 | Y9: 1.5767236 | Z9: 1.6087819 | AA9: 1.6415018 | AB9: 1.6748927 | AC9: 1.7089641 | AD9: 1.743726 | AE9: 1.7791888 | AF9: 1.8153636 | AG9: 1.8522615 | AH9: 1.8898946 | AI9: 1.9282753 | AJ9: 1.9674164 | AK9: 2.0073314
A10: ch_cfoo_2 | B10: 175065 | C10: 176666.16 | D10: 178264.86 | E10: 179996.63 | F10: 181891.89 | G10: 183943.73 | H10: 186127.19 | I10: 188413.71 | J10: 190785.17 | K10: 193230.44 | L10: 195743.51 | M10: 198321.9 | N10: 200965.57 | O10: 203676.02 | P10: 206455.7 | Q10: 209307.62 | R10: 212226.59 | S10: 215202.14 | T10: 218229.36 | U10: 221305.91 | V10: 224430.76 | W10: 227603.65 | X10: 230824.58 | Y10: 234093.49 | Z10: 237410.01 | AA10: 240773.44 | AB10: 244182.66 | AC10: 247636.18 | AD10: 251132.22 | AE10: 254668.74 | AF10: 258243.57 | AG10: 261854.44 | AH10: 265499.09 | AI10: 269175.31 | AJ10: 272880.98 | AK10: 276614.12
A11: ch_cfoo_0 | B11: 175065 | C11: 176646.38 | D11: 178215.6 | E11: 179909.34 | F11: 181755.53 | G11: 183742.79 | H11: 185849.61 | I11: 188055.15 | J11: 190342.38 | K11: 192698.21 | L11: 195112.91 | M11: 197579.31 | N11: 200092.24 | O11: 202648.04 | P11: 205244.23 | Q11: 207879.16 | R11: 210551.78 | S11: 213261.44 | T11: 216007.75 | U11: 218790.43 | V11: 221609.24 | W11: 224463.97 | X11: 227354.36 | Y11: 230280.16 | Z11: 233241.08 | AA11: 236236.84 | AB11: 239267.21 | AC11: 242331.96 | AD11: 245430.95 | AE11: 248564.07 | AF11: 251731.31 | AG11: 254932.73 | AH11: 258168.46 | AI11: 261438.72 | AJ11: 264743.79 | AK11: 268084.01
A12: pch_cfoo_2 | B12: 1 | C12: 1.0199649 | D12: 1.0402867 | E12: 1.061021 | F12: 1.0822382 | G12: 1.104012 | H12: 1.1263853 | I12: 1.1493667 | J12: 1.1729656 | K12: 1.1971968 | L12: 1.2220847 | M12: 1.2476654 | N12: 1.2739879 | O12: 1.3011135 | P12: 1.329116 | Q12: 1.3580812 | R12: 1.3880724 | S12: 1.4191165 | T12: 1.4512298 | U12: 1.484421 | V12: 1.5186944 | W12: 1.5540522 | X12: 1.590496 | Y12: 1.6280268 | Z12: 1.666645 | AA12: 1.7063505 | AB12: 1.7471425 | AC12: 1.7890191 | AD12: 1.8319773 | AE12: 1.8760131 | AF12: 1.9211212 | AG12: 1.9672951 | AH12: 2.014527 | AI12: 2.062808 | AJ12: 2.1121278 | AK12: 2.1624752
... A105: pch_cbio_0 | B105: 1 | C105: 1.0194853 | D105: 1.0388851 | E105: 1.0584794 | F105: 1.0785234 | G105: 1.0991574 | H105: 1.1204202 | I105: 1.1422939 | J105: 1.1647423 | K105: 1.1877351 | L105: 1.2112565 | M105: 1.2353062 | N105: 1.2598952 | O105: 1.2850411 | P105: 1.3107638 | Q105: 1.337083 | R105: 1.3640167 | S105: 1.3915798 | T105: 1.4197853 | U105: 1.4486433 | V105: 1.4781629 | W105: 1.5083515 | X105: 1.5392164 | Y105: 1.5707642 | Z105: 1.6030015 | AA105: 1.635935 | AB105: 1.6695716 | AC105: 1.7039186 | AD105: 1.7389836 | AE105: 1.7747749 | AF105: 1.811301 | AG105: 1.8485712 | AH105: 1.8865955 | AI105: 1.9253844 | AJ105: 1.964949 | AK105: 2.0053012

Sheet Value_Added
A1: _date_ | B1: 42005 | C1: 42370 | D1: 42736 | E1: 43101 | F1: 43466 | G1: 43831 | H1: 44197 | I1: 44562 | J1: 44927 | K1: 45292 | L1: 45658 | M1: 46023 | N1: 46388 | O1: 46753 | P1: 47119 | Q1: 47484 | R1: 47849 | S1: 48214 | T1: 48580 | U1: 48945 | V1: 49310 | W1: 49675 | X1: 50041 | Y1: 50406 | Z1: 50771 | AA1: 51136 | AB1: 51502 | AC1: 51867 | AD1: 52232 | AE1: 52597 | AF1: 52963 | AG1: 53328 | AH1: 53693 | AI1: 54058 | AJ1: 54424 | AK1: 54789
A2: va_2 | B2: 1965592.2 | C2: 1986968.8 | D2: 2008413.6 | E2: 2030342 | F2: 2052886.4 | G2: 2076074.3 | H2: 2099860.4 | I2: 2124162.5 | J2: 2148918.1 | K2: 2174086.1 | L2: 2199645.8 | M2: 2225591.9 | N2: 2251928.9 | O2: 2278665.6 | P2: 2305811.5 | Q2: 2333373.8 | R2: 2361326.1 | S2: 2389613.7 | T2: 2418196.2 | U2: 2447047.2 | V2: 2476153.4 | W2: 2505512.1 | X2: 2535127.5 | Y2: 2565007.8 | Z2: 2595162 | AA2: 2625599.3 | AB2: 2656327.6 | AC2: 2687353.6 | AD2: 2718682.7 | AE2: 2750319.1 | AF2: 2782266.5 | AG2: 2814528 | AH2: 2847106.6 | AI2: 2880005.5 | AJ2: 2913228.1 | AK2: 2946778.5
A3: va_0 | B3: 1965592.2 | C3: 1986885.6 | D3: 2008191.4 | E3: 2029937.4 | F3: 2052257.8 | G3: 2075171.5 | H3: 2098653.7 | I3: 2122664 | J3: 2147158.9 | K3: 2172097.9 | L3: 2197445.8 | M3: 2223174.1 | N3: 2249260.8 | O3: 2275690.3 | P3: 2302452.2 | Q3: 2329540.4 | R3: 2356952 | S3: 2384686.5 | T3: 2412744.9 | U3: 2441129.2 | V3: 2469841.7 | W3: 2498885 | X3: 2528261.8 | Y3: 2557974.8 | Z3: 2588026.6 | AA3: 2618419.7 | AB3: 2649156.8 | AC3: 2680240.9 | AD3: 2711674.8 | AE3: 2743461.8 | AF3: 2775605.2 | AG3: 2808108.9 | AH3: 2840976.6 | AI3: 2874212.5 | AJ3: 2907821.1 | AK3: 2941806.7
A4: va_sagr_2 | B4: 30790.815 | C4: 31102.121 | D4: 31419.057 | E4: 31754.134 | F4: 32109.395 | G4: 32483.963 | H4: 32874.552 | I4: 33277.044 | J4: 33689.089 | K4: 34109.509 | L4: 34537.901 | M4: 34974.344 | N4: 35419.185 | O4: 35872.871 | P4: 36335.826 | Q4: 36808.35 | R4: 37289.07 | S4: 37775.573 | T4: 38266.453 | U4: 38760.893 | V4: 39258.455 | W4: 39758.947 | X4: 40262.325 | Y4: 40768.62 | Z4: 41277.892 | AA4: 41790.209 | AB4: 42305.626 | AC4: 42824.186 | AD4: 43345.921 | AE4: 43870.853 | AF4: 44399 | AG4: 44930.385 | AH4: 45465.039 | AI4: 46003.005 | AJ4: 46544.343 | AK4: 47089.131
A5: va_sagr_0 | B5: 30790.815 | C5: 31097.824 | D5: 31408.103 | E5: 31734.666 | F5: 32079.262 | G5: 32440.277 | H5: 32815.402 | I5: 33202.492 | J5: 33599.776 | K5: 34005.861 | L5: 34419.667 | M5: 34840.376 | N5: 35267.383 | O5: 35700.251 | P5: 36138.684 | Q5: 36582.491 | R5: 37031.564 | S5: 37485.852 | T5: 37945.343 | U5: 38410.05 | V5: 38880 | W5: 39355.225 | X5: 39835.764 | Y5: 40321.654 | Z5: 40812.934 | AA5: 41309.645 | AB5: 41811.83 | AC5: 42319.535 | AD5: 42832.812 | AE5: 43351.717 | AF5: 43876.312 | AG5: 44406.665 | AH5: 44942.85 | AI5: 45484.945 | AJ5: 46033.034 | AK5: 46587.204
A6: va_sfor_2 | B6: 5288.8126 | C6: 5297.6409 | D6: 5287.0242 | E6: 5269.4674 | F6: 5249.0738 | G6: 5226.4599 | H6: 5203.6412 | I6: 5183.1236 | J6: 5164.983 | K6: 5148.4161 | L6: 5132.3637 | M6: 5115.7675 | N6: 5097.6778 | O6: 5077.3026 | P6: 5054.0352 | Q6: 5027.4696 | R6: 4998.888 | S6: 4970.3273 | T6: 4942.6378 | U6: 4916.1591 | V6: 4891.0102 | W6: 4867.2183 | X6: 4844.7753 | Y6: 4823.6611 | Z6: 4803.8527 | AA6: 4785.3279 | AB6: 4768.0665 | AC6: 4752.0504 | AD6: 4737.2637 | AE6: 4723.6927 | AF6: 4711.3259 | AG6: 4700.1536 | AH6: 4690.1678 | AI6: 4681.3618 | AJ6: 4673.7304 | AK6: 4667.2688
A7: va_sfor_0 | B7: 5288.8126 | C7: 5304.0347 | D7: 5302.0192 | E7: 5294.5751 | F7: 5286.4854 | G7: 5279.4506 | H7: 5273.8914 | I7: 5269.7509 | J7: 5266.835 | K7: 5264.9431 | L7: 5263.9093 | M7: 5263.6084 | N7: 5263.9504 | O7: 5264.872 | P7: 5266.329 | Q7: 5268.2912 | R7: 5270.738 | S7: 5273.6553 | T7: 5277.0329 | U7: 5280.8561 | V7: 5285.1182 | W7: 5289.8172 | X7: 5294.9534 | Y7: 5300.5286 | Z7: 5306.5452 | AA7: 5313.0062 | AB7: 5319.9145 | AC7: 5327.2731 | AD7: 5335.0852 | AE7: 5343.3539 | AF7: 5352.0818 | AG7: 5361.2718 | AH7: 5370.9267 | AI7: 5381.049 | AJ7: 5391.6415 | AK7: 5402.7065
A8: va_sfoo_2 | B8: 43654.88 | C8: 44079.936 | D8: 44521.727 | E8: 44993.424 | F8: 45494.719 | G8: 46023.142 | H8: 46573.909 | I8: 47141.713 | J8: 47723.764 | K8: 48318.566 | L8: 48925.513 | M8: 49544.597 | N8: 50176.168 | O8: 50820.758 | P8: 51478.946 | Q8: 52151.259 | R8: 52835.967 | S8: 53530.077 | T8: 54232.126 | U8: 54941.241 | V8: 55656.953 | W8: 56379.069 | X8: 57107.556 | Y8: 57842.463 | Z8: 58583.858 | AA8: 59331.792 | AB8: 60086.291 | AC8: 60847.343 | AD8: 61614.904 | AE8: 62388.908 | AF8: 63169.273 | AG8: 63955.913 | AH8: 64748.748 | AI8: 65547.712 | AJ8: 66352.755 | AK8: 67163.854
A9: va_sfoo_0 | B9: 43654.88 | C9: 44074.319 | D9: 44508.113 | E9: 44969.764 | F9: 45458.475 | G9: 45970.837 | H9: 46503.401 | I9: 47053.24 | J9: 47617.99 | K9: 48195.765 | L9: 48785.077 | M9: 49384.768 | N9: 49993.956 | O9: 50611.993 | P9: 51238.424 | Q9: 51872.946 | R9: 52515.37 | S9: 53165.593 | T9: 53823.57 | U9: 54489.29 | V9: 55162.761 | W9: 55844.004 | X9: 56533.043 | Y9: 57229.907 | Z9: 57934.625 | AA9: 58647.231 | AB9: 59367.763 | AC9: 60096.266 | AD9: 60832.792 | AE9: 61577.404 | AF9: 62330.173 | AG9: 63091.181 | AH9: 63860.521 | AI9: 64638.292 | AJ9: 65424.606 | AK9: 66219.579
A10: va_sveh_2 | B10: 29847.895 | C10: 30404.587 | D10: 30932.187 | E10: 31407.735 | F10: 31839.728 | G10: 32241.105 | H10: 32625.553 | I10: 33003.168 | J10: 33377.546 | K10: 33750.08 | L10: 34121.255 | M10: 34491.104 | N10: 34859.407 | O10: 35225.772 | P10: 35589.677 | Q10: 35950.485 | R10: 36310.352 | S10: 36671.833 | T10: 37034.291 | U10: 37396.91 | V10: 37759.181 | W10: 38120.88 | X10: 38481.977 | Y10: 38842.569 | Z10: 39202.823 | AA10: 39562.948 | AB10: 39923.177 | AC10: 40283.761 | AD10: 40644.964 | AE10: 41007.063 | AF10: 41370.349 | AG10: 41735.131 | AH10: 42101.732 | AI10: 42470.491 | AJ10: 42841.762 | AK10: 43215.914
A11: va_sveh_0 | B11: 29847.895 | C11: 30410.564 | D11: 30943.516 | E11: 31424.184 | F11: 31862.492 | G11: 32272.71 | H11: 32666.675 | I11: 33052.509 | J11: 33435.21 | K11: 33817.628 | L11: 34201.287 | M11: 34586.961 | N11: 34975.033 | O11: 35365.692 | P11: 35759.05 | Q11: 36155.19 | R11: 36554.191 | S11: 36956.134 | T11: 37361.107 | U11: 37769.204 | V11: 38180.52 | W11: 38595.157 | X11: 39013.219 | Y11: 39434.812 | Z11: 39860.048 | AA11: 40289.04 | AB11: 40721.904 | AC11: 41158.757 | AD11: 41599.719 | AE11: 42044.908 | AF11: 42494.445 | AG11: 42948.446 | AH11: 43407.029 | AI11: 43870.308 | AJ11: 44338.393 | AK11: 44811.394
A12: va_sgla_2 | B12: 7902.1978 | C12: 7989.9781 | D12: 8077.9673 | E12: 8167.4463 | F12: 8259.0631 | G12: 8353.0815 | H12: 8449.1995 | I12: 8546.8972 | J12: 8645.9433 | K12: 8746.2661 | L12: 8847.8532 | M12: 8950.6893 | N12: 9054.7153 | O12: 9159.7968 | P12: 9265.6991 | Q12: 9372.0664 | R12: 9478.3521 | S12: 9584.0627 | T12: 9688.973 | U12: 9793.024 | V12: 9896.2505 | W12: 9998.7375 | X12: 10100.594 | Y12: 10201.936 | Z12: 10302.88 | AA12: 10403.535 | AB12: 10504.006 | AC12: 10604.387 | AD12: 10704.768 | AE12: 10805.231 | AF12: 10905.857 | AG12: 11006.72 | AH12: 11107.896 | AI12: 11209.455 | AJ12: 11311.471 | AK12: 11414.014
... A79: va_ser_0 | B79: 1510944.6 | C79: 1527318.9 | D79: 1543784 | E79: 1560667.8 | F79: 1578055.3 | G79: 1595942.4 | H79: 1614295.5 | I79: 1633073.9 | J79: 1652238.4 | K79: 1671754.4 | L79: 1691592.8 | M79: 1711730.4 | N79: 1732149.6 | O79: 1752837.7 | P79: 1773786.4 | Q79: 1794990.5 | R79: 1816447.6 | S79: 1838157 | T79: 1860119.3 | U79: 1882335.7 | V79: 1904807.8 | W79: 1927537.5 | X79: 1950526.5 | Y79: 1973776.7 | Z79: 1997289.9 | AA79: 2021067.8 | AB79: 2045112.5 | AC79: 2069426 | AD79: 2094010.5 | AE79: 2118868.4 | AF79: 2144002.3 | AG79: 2169415.2 | AH79: 2195110 | AI79: 2221090 | AJ79: 2247358.8 | AK79: 2273919.9

Sheet INV
A1: _date_ | B1: 42005 | C1: 42370 | D1: 42736 | E1: 43101 | F1: 43466 | G1: 43831 | H1: 44197 | I1: 44562 | J1: 44927 | K1: 45292 | L1: 45658 | M1: 46023 | N1: 46388 | O1: 46753 | P1: 47119 | Q1: 47484 | R1: 47849 | S1: 48214 | T1: 48580 | U1: 48945 | V1: 49310 | W1: 49675 | X1: 50041 | Y1: 50406 | Z1: 50771 | AA1: 51136 | AB1: 51502 | AC1: 51867 | AD1: 52232 | AE1: 52597 | AF1: 52963 | AG1: 53328 | AH1: 53693 | AI1: 54058 | AJ1: 54424 | AK1: 54789
A2: ia_2 | B2: 472647 | C2: 478019.4 | D2: 483383.02 | E2: 488765.23 | F2: 494190.78 | G2: 499675.43 | H2: 505236.8 | I2: 510891.29 | J2: 516642.91 | K2: 522488.85 | L2: 528423.65 | M2: 534441.35 | N2: 540536.13 | O2: 546702.37 | P2: 552934.37 | Q2: 559226.23 | R2: 565579.52 | S2: 572000.88 | T2: 578492.4 | U2: 585054.38 | V2: 591687.29 | W2: 598392.57 | X2: 605172.52 | Y2: 612029.89 | Z2: 618967.37 | AA2: 625987.28 | AB2: 633091.27 | AC2: 640280.33 | AD2: 647554.73 | AE2: 654914.12 | AF2: 662357.64 | AG2: 669884.02 | AH2: 677491.71 | AI2: 685178.97 | AJ2: 692943.93 | AK2: 700784.7
A3: ia_0 | B3: 472647 | C3: 478041.55 | D3: 483438.29 | E3: 488861.72 | F3: 494339.57 | G3: 499893.34 | H3: 505536.92 | I3: 511277.46 | J3: 517117.16 | K3: 523055.07 | L3: 529088.68 | M3: 535215.11 | N3: 541431.74 | O3: 547736.65 | P3: 554128.65 | Q3: 560607.27 | R3: 567172.56 | S3: 573824.98 | T3: 580565.17 | U3: 587393.88 | V3: 594311.81 | W3: 601319.58 | X3: 608417.66 | Y3: 615606.41 | Z3: 622886.05 | AA3: 630256.67 | AB3: 637718.3 | AC3: 645270.89 | AD3: 652914.38 | AE3: 660648.67 | AF3: 668473.69 | AG3: 676389.4 | AH3: 684395.78 | AI3: 692492.88 | AJ3: 700680.78 | AK3: 708959.66
A4: ia_sagr_2 | B4: 4271.7493 | C4: 4316.7096 | D4: 4359.9715 | E4: 4403.7215 | F4: 4449.0584 | G4: 4496.2419 | H4: 4545.1965 | I4: 4595.7611 | J4: 4647.7303 | K4: 4700.9187 | L4: 4755.1656 | M4: 4810.3252 | N4: 4866.256 | O4: 4922.8133 | P4: 4979.846 | Q4: 5037.1969 | R4: 5094.7575 | S4: 5152.4716 | T4: 5210.3059 | U4: 5268.2618 | V4: 5326.3668 | W4: 5384.6627 | X4: 5443.1973 | Y4: 5502.0171 | Z4: 5561.1639 | AA4: 5620.6724 | AB4: 5680.5697 | AC4: 5740.876 | AD4: 5801.6056 | AE4: 5862.7681 | AF4: 5924.3701 | AG4: 5986.4163 | AH4: 6048.9107 | AI4: 6111.8578 | AJ4: 6175.2633 | AK4: 6239.1344
A5: ia_sagr_0 | B5: 4271.7493 | C5: 4316.9191 | D5: 4360.566 | E5: 4404.9143 | F5: 4451.1227 | G5: 4499.5274 | H5: 4550.0535 | I5: 4602.4822 | J5: 4656.5777 | K5: 4712.1351 | L5: 4768.9904 | M5: 4827.0178 | N5: 4886.1226 | O5: 4946.2347 | P5: 5007.3037 | Q5: 5069.2935 | R5: 5132.1794 | S5: 5195.9442 | T5: 5260.5762 | U5: 5326.0669 | V5: 5392.4095 | W5: 5459.5978 | X5: 5527.6258 | Y5: 5596.4876 | Z5: 5666.1769 | AA5: 5736.6876 | AB5: 5808.0139 | AC5: 5880.1505 | AD5: 5953.0927 | AE5: 6026.8372 | AF5: 6101.3814 | AG5: 6176.7244 | AH5: 6252.8665 | AI5: 6329.8095 | AJ5: 6407.5565 | AK5: 6486.112
A6: ia_sfor_2 | B6: 166.90527 | C6: 167.66273 | D6: 167.53761 | E6: 166.89591 | F6: 165.94733 | G6: 164.77096 | H6: 163.44791 | I6: 162.07868 | J6: 160.70813 | K6: 159.33944 | L6: 157.95352 | M6: 156.52185 | N6: 155.01357 | O6: 153.3995 | P6: 151.6547 | Q6: 149.76011 | R6: 147.74315 | S6: 145.66777 | T6: 143.58093 | U6: 141.51185 | V6: 139.47832 | W6: 137.49155 | X6: 135.55908 | Y6: 133.68627 | Z6: 131.87707 | AA6: 130.13447 | AB6: 128.46073 | AC6: 126.85751 | AD6: 125.32602 | AE6: 123.86707 | AF6: 122.48118 | AG6: 121.16856 | AH6: 119.92923 | AI6: 118.76301 | AJ6: 117.66956 | AK6: 116.64838
A7: ia_sfor_0 | B7: 166.90527 | C7: 167.83885 | D7: 168.02018 | E7: 167.78375 | F7: 167.34781 | G7: 166.825 | H7: 166.26615 | I7: 165.69193 | J7: 165.1102 | K7: 164.52429 | L7: 163.93643 | M7: 163.34897 | N7: 162.76463 | O7: 162.18645 | P7: 161.61757 | Q7: 161.06114 | R7: 160.52017 | S7: 159.99749 | T7: 159.49567 | U7: 159.01687 | V7: 158.56304 | W7: 158.13598 | X7: 157.7373 | Y7: 157.36842 | Z7: 157.03058 | AA7: 156.72481 | AB7: 156.452 | AC7: 156.21287 | AD7: 156.00797 | AE7: 155.83776 | AF7: 155.70255 | AG7: 155.60254 | AH7: 155.53783 | AI7: 155.50847 | AJ7: 155.51438 | AK7: 155.55545
A8: ia_sfoo_2 | B8: 6742.5992 | C8: 6812.5373 | D8: 6879.7436 | E8: 6948.0473 | F8: 7019.2166 | G8: 7093.6077 | H8: 7171.0809 | I8: 7251.3764 | J8: 7334.1298 | K8: 7419.0043 | L8: 7505.7123 | M8: 7594.0036 | N8: 7683.6462 | O8: 7774.4099 | P8: 7866.056 | Q8: 7958.3332 | R8: 8051.0963 | S8: 8144.2918 | T8: 8237.8571 | U8: 8331.7653 | V8: 8426.0239 | W8: 8520.6654 | X8: 8615.7342 | Y8: 8711.2762 | Z8: 8807.331 | AA8: 8903.9278 | AB8: 9001.0839 | AC8: 9098.805 | AD8: 9197.0869 | AE8: 9295.9174 | AF8: 9395.2792 | AG8: 9495.1519 | AH8: 9595.5143 | AI8: 9696.3466 | AJ8: 9797.6313 | AK8: 9899.3546
A9: ia_sfoo_0 | B9: 6742.5992 | C9: 6812.918 | D9: 6880.7425 | E9: 6949.9349 | F9: 7022.3561 | G9: 7098.4844 | H9: 7178.1486 | I9: 7260.9658 | J9: 7346.5408 | K9: 7434.5354 | L9: 7524.6818 | M9: 7616.7752 | N9: 7710.662 | O9: 7806.229 | P9: 7903.3949 | Q9: 8002.1017 | R9: 8102.309 | S9: 8203.9889 | T9: 8307.1212 | U9: 8411.6904 | V9: 8517.6829 | W9: 8625.0857 | X9: 8733.8854 | Y9: 8844.0679 | Z9: 8955.6185 | AA9: 9068.5224 | AB9: 9182.7648 | AC9: 9298.3317 | AD9: 9415.2105 | AE9: 9533.3901 | AF9: 9652.8617 | AG9: 9773.6184 | AH9: 9895.6561 | AI9: 10018.973 | AJ9: 10143.57 | AK9: 10269.45
A10: ia_sveh_2 | B10: 36330.779 | C10: 36892.942 | D10: 37526.468 | E10: 38158.801 | F10: 38755.612 | G10: 39309.742 | H10: 39828.945 | I10: 40325.527 | J10: 40808.622 | K10: 41283.532 | L10: 41752.811 | M10: 42217.352 | N10: 42677.119 | O10: 43131.574 | P10: 43579.903 | Q10: 44021.124 | R10: 44456.363 | S10: 44888.381 | T10: 45318.431 | U10: 45746.632 | V10: 46172.716 | W10: 46596.448 | X10: 47017.775 | Y10: 47436.821 | Z10: 47853.844 | AA10: 48269.188 | AB10: 48683.248 | AC10: 49096.444 | AD10: 49509.218 | AE10: 49922.024 | AF10: 50335.33 | AG10: 50749.622 | AH10: 51165.401 | AI10: 51583.189 | AJ10: 52003.525 | AK10: 52426.966
A11: ia_sveh_0 | B11: 36330.779 | C11: 36897.67 | D11: 37538.383 | E11: 38179.071 | F11: 38785.78 | G11: 39352.655 | H11: 39886.731 | I11: 40398.196 | J11: 40895.934 | K11: 41386.273 | L11: 41873.185 | M11: 42358.932 | N11: 42844.703 | O11: 43331.081 | P11: 43818.353 | Q11: 44306.685 | R11: 44796.209 | S11: 45287.066 | T11: 45779.416 | U11: 46273.439 | V11: 46769.334 | W11: 47267.315 | X11: 47767.605 | Y11: 48270.436 | Z11: 48776.045 | AA11: 49284.675 | AB11: 49796.575 | AC11: 50311.993 | AD11: 50831.181 | AE11: 51354.391 | AF11: 51881.875 | AG11: 52413.881 | AH11: 52950.655 | AI11: 53492.438 | AJ11: 54039.466 | AK11: 54591.969
A12: ia_sgla_2 | B12: 1455.1731 | C12: 1471.1513 | D12: 1486.6169 | E12: 1501.7673 | F12: 1516.7126 | G12: 1531.4382 | H12: 1545.9808 | I12: 1560.4684 | J12: 1574.9832 | K12: 1589.5514 | L12: 1604.1432 | M12: 1618.6789 | N12: 1633.0376 | O12: 1647.0672 | P12: 1660.5935 | Q12: 1673.4295 | R12: 1685.4934 | S12: 1696.8387 | T12: 1707.5528 | U12: 1717.7333 | V12: 1727.4753 | W12: 1736.8655 | X12: 1745.9804 | Y12: 1754.8868 | Z12: 1763.6424 | AA12: 1772.2975 | AB12: 1780.8958 | AC12: 1789.4757 | AD12: 1798.0715 | AE12: 1806.714 | AF12: 1815.4312 | AG12: 1824.2489 | AH12: 1833.191 | AI12: 1842.2802 | AJ12: 1851.5377 | AK12: 1860.9836
... A79: ia_ser_0 | B79: 219461.28 | C79: 221888.44 | D79: 224292.96 | E79: 226729.35 | F79: 229226.27 | G79: 231793.06 | H79: 234429.3 | I79: 237130.78 | J79: 239892.4 | K79: 242709.38 | L79: 245577.67 | M79: 248494.04 | N79: 251456.09 | O79: 254462.06 | P79: 257510.8 | Q79: 260601.59 | R79: 263734.05 | S79: 266908 | T79: 270123.41 | U79: 273380.28 | V79: 276678.63 | W79: 280018.46 | X79: 283399.71 | Y79: 286822.29 | Z79: 290286.1 | AA79: 293790.98 | AB79: 297336.8 | AC79: 300923.4 | AD79: 304550.68 | AE79: 308218.55 | AF79: 311926.95 | AG79: 315675.89 | AH79: 319465.43 | AI79: 323295.66 | AJ79: 327166.76 | AK79: 331078.93

Sheet Labor
A1: _date_ | B1: 42005 | C1: 42370 | D1: 42736 | E1: 43101 | F1: 43466 | G1: 43831 | H1: 44197 | I1: 44562 | J1: 44927 | K1: 45292 | L1: 45658 | M1: 46023 | N1: 46388 | O1: 46753 | P1: 47119 | Q1: 47484 | R1: 47849 | S1: 48214 | T1: 48580 | U1: 48945 | V1: 49310 | W1: 49675 | X1: 50041 | Y1: 50406 | Z1: 50771 | AA1: 51136 | AB1: 51502 | AC1: 51867 | AD1: 52232 | AE1: 52597 | AF1: 52963 | AG1: 53328 | AH1: 53693 | AI1: 54058 | AJ1: 54424 | AK1: 54789
A2: f_l_2 | B2: 27390.88 | C2: 27450.174 | D2: 27503.566 | E2: 27556.49 | F2: 27613.073 | G2: 27675.654 | H2: 27744.658 | I2: 27819.069 | J2: 27897.548 | K2: 27978.951 | L2: 28062.513 | M2: 28147.868 | N2: 28234.974 | O2: 28324.012 | P2: 28415.29 | Q2: 28509.16 | R2: 28605.493 | S2: 28703.505 | T2: 28802.308 | U2: 28901.143 | V2: 28999.468 | W2: 29096.964 | X2: 29193.491 | Y2: 29289.039 | Z2: 29383.677 | AA2: 29477.506 | AB2: 29570.634 | AC2: 29663.158 | AD2: 29755.155 | AE2: 29846.68 | AF2: 29937.768 | AG2: 30028.438 | AH2: 30118.701 | AI2: 30208.56 | AJ2: 30298.018 | AK2: 30387.076
A3: f_l_0 | B3: 27390.88 | C3: 27448.862 | D3: 27499.539 | E3: 27548.51 | F3: 27599.973 | G3: 27656.135 | H3: 27717.672 | I3: 27784.329 | J3: 27855.384 | K3: 27929.95 | L3: 28007.151 | M3: 28086.22 | N3: 28166.532 | O3: 28247.612 | P3: 28329.119 | Q3: 28410.825 | R3: 28492.59 | S3: 28574.336 | T3: 28656.032 | U3: 28737.669 | V3: 28819.257 | W3: 28900.808 | X3: 28982.338 | Y3: 29063.857 | Z3: 29145.376 | AA3: 29226.899 | AB3: 29308.431 | AC3: 29389.972 | AD3: 29471.523 | AE3: 29553.086 | AF3: 29634.662 | AG3: 29716.255 | AH3: 29797.868 | AI3: 29879.506 | AJ3: 29961.176 | AK3: 30042.885
A4: f_l_sagr_2 | B4: 732.13 | C4: 733.53268 | D4: 734.74367 | E4: 736.10273 | F4: 737.85588 | G4: 740.14183 | H4: 742.95251 | I4: 746.15883 | J4: 749.62815 | K4: 753.26911 | L4: 757.0411 | M4: 760.94854 | N4: 765.02987 | O4: 769.34625 | P4: 773.97192 | Q4: 778.98656 | R4: 784.40725 | S4: 790.16517 | T4: 796.17248 | U4: 802.35009 | V4: 808.63628 | W4: 814.98691 | X4: 821.37235 | Y4: 827.7736 | Z4: 834.17879 | AA4: 840.58038 | AB4: 846.97323 | AC4: 853.35333 | AD4: 859.71706 | AE4: 866.06082 | AF4: 872.38092 | AG4: 878.67356 | AH4: 884.93497 | AI4: 891.16149 | AJ4: 897.34967 | AK4: 903.49638
A5: f_l_sagr_0 | B5: 732.13 | C5: 733.35856 | D5: 734.20074 | E5: 735.0077 | F5: 736.0202 | G5: 737.34214 | H5: 738.98236 | I5: 740.90022 | J5: 743.03725 | K5: 745.33488 | L5: 747.74248 | M5: 750.21993 | N5: 752.73732 | O5: 755.27355 | P5: 757.81456 | Q5: 760.35165 | R5: 762.87995 | S5: 765.39723 | T5: 767.90295 | U5: 770.39754 | V5: 772.8819 | W5: 775.35709 | X5: 777.82412 | Y5: 780.28388 | Z5: 782.73708 | AA5: 785.18432 | AB5: 787.62605 | AC5: 790.06269 | AD5: 792.49463 | AE5: 794.92225 | AF5: 797.34598 | AG5: 799.76628 | AH5: 802.18366 | AI5: 804.59868 | AJ5: 807.01191 | AK5: 809.42397
A6: f_l_sfor_2 | B6: 29.08 | C6: 28.987581 | D6: 28.749051 | E6: 28.421798 | F6: 28.052146 | G6: 27.66653 | H6: 27.283069 | I6: 26.916018 | J6: 26.570698 | K6: 26.245682 | L6: 25.935992 | M6: 25.6355 | N6: 25.338373 | O6: 25.039805 | P6: 24.736325 | Q6: 24.425862 | R6: 24.111142 | S6: 23.798728 | T6: 23.49378 | U6: 23.199184 | V6: 22.916059 | W6: 22.644446 | X6: 22.383852 | Y6: 22.133587 | Z6: 21.892942 | AA6: 21.661277 | AB6: 21.438039 | AC6: 21.222769 | AD6: 21.015082 | AE6: 20.814656 | AF6: 20.621216 | AG6: 20.434524 | AH6: 20.254368 | AI6: 20.080557 | AJ6: 19.912915 | AK6: 19.751277
A7: f_l_sfor_0 | B7: 29.08 | C7: 29.005618 | D7: 28.799733 | E7: 28.51501 | F7: 28.196878 | G7: 27.874071 | H7: 27.561229 | I7: 27.263898 | J7: 26.982674 | K7: 26.715933 | L7: 26.461367 | M7: 26.216745 | N7: 25.980209 | O7: 25.750339 | P7: 25.526105 | Q7: 25.306793 | R7: 25.091918 | S7: 24.881155 | T7: 24.674289 | U7: 24.471151 | V7: 24.271621 | W7: 24.075618 | X7: 23.883085 | Y7: 23.69398 | Z7: 23.508268 | AA7: 23.325914 | AB7: 23.146886 | AC7: 22.97115 | AD7: 22.798668 | AE7: 22.629401 | AF7: 22.463308 | AG7: 22.300347 | AH7: 22.140474 | AI7: 21.983643 | AJ7: 21.829809 | AK7: 21.678924
A8: f_l_sfoo_2 | B8: 618.62 | C8: 619.64984 | D8: 620.40811 | E8: 621.21783 | F8: 622.29155 | G8: 623.72675 | H8: 625.51685 | I8: 627.58699 | J8: 629.85654 | K8: 632.26336 | L8: 634.76973 | M8: 637.36009 | N8: 640.03584 | O8: 642.8098 | P8: 645.7014 | Q8: 648.73307 | R8: 651.90265 | S8: 655.1757 | T8: 658.51415 | U8: 661.88657 | V8: 665.27066 | W8: 668.65245 | X8: 672.02438 | Y8: 675.38311 | Z8: 678.72771 | AA8: 682.05832 | AB8: 685.3753 | AC8: 688.67867 | AD8: 691.96795 | AE8: 695.24214 | AF8: 698.4998 | AG8: 701.73917 | AH8: 704.95838 | AI8: 708.15556 | AJ8: 711.32897 | AK8: 714.47708
A9: f_l_sfoo_0 | B9: 618.62 | C9: 619.58096 | D9: 620.19799 | E9: 620.80189 | F9: 621.60558 | G9: 622.69515 | H9: 624.07325 | I9: 625.70096 | J9: 627.52547 | K9: 629.49501 | L9: 631.56538 | M9: 633.70176 | N9: 635.87829 | O9: 638.07672 | P9: 640.28485 | Q9: 642.49501 | R9: 644.7028 | S9: 646.90604 | T9: 649.10393 | U9: 651.29649 | V9: 653.48407 | W9: 655.66713 | X9: 657.84606 | Y9: 660.02113 | Z9: 662.19247 | AA9: 664.3601 | AB9: 666.52395 | AC9: 668.68392 | AD9: 670.83993 | AE9: 672.99195 | AF9: 675.13999 | AG9: 677.28416 | AH9: 679.42464 | AI9: 681.5617 | AJ9: 683.69566 | AK9: 685.82691
A10: f_l_sveh_2 | B10: 185.81 | C10: 186.90529 | D10: 188.36292 | E10: 189.83317 | F10: 191.10318 | G10: 192.10321 | H10: 192.85802 | I10: 193.43216 | J10: 193.88812 | K10: 194.2718 | L10: 194.61157 | M10: 194.9222 | N10: 195.20939 | O10: 195.47338 | P10: 195.71139 | Q10: 195.91906 | R10: 196.09646 | S10: 196.24766 | T10: 196.37331 | U10: 196.47099 | V10: 196.53734 | W10: 196.56976 | X10: 196.56709 | Y10: 196.52967 | Z10: 196.45909 | AA10: 196.35786 | AB10: 196.229 | AC10: 196.07584 | AD10: 195.90181 | AE10: 195.71034 | AF10: 195.50474 | AG10: 195.28827 | AH10: 195.06403 | AI10: 194.83502 | AJ10: 194.60416 | AK10: 194.37422
A11: f_l_sveh_0 | B11: 185.81 | C11: 186.91608 | D11: 188.39081 | E11: 189.88115 | F11: 191.17536 | G11: 192.20807 | H11: 193.00441 | I11: 193.62576 | J11: 194.13548 | K11: 194.58348 | L11: 195.00281 | M11: 195.41213 | N11: 195.81987 | O11: 196.22828 | P11: 196.63639 | Q11: 197.04198 | R11: 197.44272 | S11: 197.83673 | T11: 198.22269 | U11: 198.59992 | V11: 198.96823 | W11: 199.32783 | X11: 199.67917 | Y11: 200.02293 | Z11: 200.35986 | AA11: 200.69079 | AB11: 201.01656 | AC11: 201.33802 | AD11: 201.65597 | AE11: 201.97119 | AF11: 202.28442 | AG11: 202.59635 | AH11: 202.90759 | AI11: 203.21872 | AJ11: 203.53027 | AK11: 203.84269
A12: f_l_sgla_2 | B12: 98.04 | C12: 98.276365 | D12: 98.505875 | E12: 98.739175 | F12: 98.98968 | G12: 99.269662 | H12: 99.580784 | I12: 99.914226 | J12: 100.26179 | K12: 100.61896 | L12: 100.985 | M12: 101.36207 | N12: 101.75423 | O12: 102.16652 | P12: 102.60431 | Q12: 103.07266 | R12: 103.57006 | S12: 104.08751 | T12: 104.61594 | U12: 105.14836 | V12: 105.68007 | W12: 106.2082 | X12: 106.73121 | Y12: 107.24838 | Z12: 107.75949 | AA12: 108.26457 | AB12: 108.76375 | AC12: 109.25722 | AD12: 109.74512 | AE12: 110.22759 | AF12: 110.70471 | AG12: 111.17658 | AH12: 111.64324 | AI12: 112.10477 | AJ12: 112.56122 | AK12: 113.01267
... A79: f_l_ser_0 | B79: 21284.868 | C79: 21330.075 | D79: 21370.068 | E79: 21409.305 | F79: 21450.968 | G79: 21496.614 | H79: 21546.611 | I79: 21600.64 | J79: 21658.063 | K79: 21718.152 | L79: 21780.218 | M79: 21843.669 | N79: 21908.031 | O79: 21972.949 | P79: 22038.17 | Q79: 22103.528 | R79: 22168.918 | S79: 22234.285 | T79: 22299.605 | U79: 22364.871 | V79: 22430.088 | W79: 22495.264 | X79: 22560.407 | Y79: 22625.523 | Z79: 22690.617 | AA79: 22755.689 | AB79: 22820.741 | AC79: 22885.773 | AD79: 22950.783 | AE79: 23015.774 | AF79: 23080.745 | AG79: 23145.699 | AH79: 23210.642 | AI79: 23275.578 | AJ79: 23340.514 | AK79: 23405.458

Sheet Final_nrj
A1: _date_ | B1: 42005 | C1: 42370 | D1: 42736 | E1: 43101 | F1: 43466 | G1: 43831 | H1: 44197 | I1: 44562 | J1: 44927 | K1: 45292 | L1: 45658 | M1: 46023 | N1: 46388 | O1: 46753 | P1: 47119 | Q1: 47484 | R1: 47849 | S1: 48214 | T1: 48580 | U1: 48945 | V1: 49310 | W1: 49675 | X1: 50041 | Y1: 50406 | Z1: 50771 | AA1: 51136 | AB1: 51502 | AC1: 51867 | AD1: 52232 | AE1: 52597 | AF1: 52963 | AG1: 53328 | AH1: 53693 | AI1: 54058 | AJ1: 54424 | AK1: 54789
A2: cf_toe_2 | B2: 161.69428 | C2: 162.00032 | D2: 162.18906 | E2: 162.30169 | F2: 162.93754 | G2: 164.00585 | H2: 165.3825 | I2: 164.86224 | J2: 164.06499 | K2: 163.69381 | L2: 163.48425 | M2: 163.54713 | N2: 163.79613 | O2: 164.13652 | P2: 164.61511 | Q2: 165.25795 | R2: 165.94909 | S2: 166.72131 | T2: 167.62318 | U2: 168.69693 | V2: 169.94349 | W2: 171.46837 | X2: 173.30271 | Y2: 175.47362 | Z2: 177.9999 | AA2: 180.78154 | AB2: 183.97044 | AC2: 187.6229 | AD2: 191.77182 | AE2: 196.41792 | AF2: 201.5533 | AG2: 207.19316 | AH2: 213.38371 | AI2: 220.19885 | AJ2: 227.76202 | AK2: 236.28394
A3: ch_toe_2 | B3: 64.30144 | C3: 63.916926 | D3: 63.417062 | E3: 62.919764 | F3: 62.649374 | G3: 62.537234 | H3: 62.517708 | I3: 61.981808 | J3: 61.408004 | K3: 60.784545 | L3: 60.135343 | M3: 59.545006 | N3: 59.035826 | O3: 58.621502 | P3: 58.29997 | Q3: 58.059953 | R3: 57.842968 | S3: 57.642623 | T3: 57.455626 | U3: 57.283701 | V3: 57.114277 | W3: 56.981124 | X3: 56.880426 | Y3: 56.813382 | Z3: 56.784099 | AA3: 56.747707 | AB3: 56.759053 | AC3: 56.81902 | AD3: 56.929874 | AE3: 57.094329 | AF3: 57.314716 | AG3: 57.592528 | AH3: 57.928685 | AI3: 58.325602 | AJ3: 58.788111 | AK3: 59.324629
A4: ch_hous_toe_2 | B4: 42520877 | C4: 42433005 | D4: 42077798 | E4: 41627286 | F4: 41324126 | G4: 41125067 | H4: 40987528 | I4: 40381018 | J4: 39744252 | K4: 39046074 | L4: 38302552 | M4: 37580716 | N4: 36910923 | O4: 36319255 | P4: 35813324 | Q4: 35388371 | R4: 34997669 | S4: 34632651 | T4: 34287213 | U4: 33961061 | V4: 33642498 | W4: 33360644 | X4: 33109959 | Y4: 32889391 | Z4: 32701051 | AA4: 32505181 | AB4: 32350396 | AC4: 32235996 | AD4: 32161473 | AE4: 32126591 | AF4: 32131736 | AG4: 32177783 | AH4: 32265836 | AI4: 32398441 | AJ4: 32580389 | AK4: 32819810
A5: ch_auto_toe_2 | B5: 21780563 | C5: 21483922 | D5: 21339263 | E5: 21292478 | F5: 21325248 | G5: 21412167 | H5: 21530180 | I5: 21600790 | J5: 21663752 | K5: 21738472 | L5: 21832791 | M5: 21964290 | N5: 22124903 | O5: 22302247 | P5: 22486646 | Q5: 22671582 | R5: 22845299 | S5: 23009973 | T5: 23168413 | U5: 23322640 | V5: 23471778 | W5: 23620479 | X5: 23770467 | Y5: 23923992 | Z5: 24083048 | AA5: 24242526 | AB5: 24408657 | AC5: 24583024 | AD5: 24768401 | AE5: 24967738 | AF5: 25182980 | AG5: 25414745 | AH5: 25662849 | AI5: 25927161 | AJ5: 26207722 | AK5: 26504818
A6: cf_toe_0 | B6: 161.69428 | C6: 162.00032 | D6: 162.18906 | E6: 162.30169 | F6: 162.93754 | G6: 164.00585 | H6: 165.04981 | I6: 166.0686 | J6: 167.06643 | K6: 168.05868 | L6: 169.12674 | M6: 170.18294 | N6: 171.20517 | O6: 172.1049 | P6: 172.92614 | Q6: 173.72678 | R6: 174.76683 | S6: 176.06238 | T6: 177.62062 | U6: 179.43764 | V6: 181.4701 | W6: 183.78562 | X6: 186.39391 | Y6: 189.3086 | Z6: 192.52955 | AA6: 195.93044 | AB6: 199.63696 | AC6: 203.65994 | AD6: 208.00196 | AE6: 212.62713 | AF6: 217.47858 | AG6: 222.5012 | AH6: 227.648 | AI6: 232.87513 | AJ6: 238.13923 | AK6: 243.39644
A7: ch_toe_0 | B7: 64.30144 | C7: 63.916926 | D7: 63.417062 | E7: 62.919765 | F7: 62.649374 | G7: 62.537235 | H7: 62.373026 | I7: 62.192818 | J7: 62.013502 | K7: 61.844335 | L7: 61.715362 | M7: 61.585567 | N7: 61.461166 | O7: 61.346178 | P7: 61.240763 | Q7: 61.142803 | R7: 61.140934 | S7: 61.193917 | T7: 61.275339 | U7: 61.368571 | V7: 61.447589 | W7: 61.536212 | X7: 61.634782 | Y7: 61.748776 | Z7: 61.879612 | AA7: 61.977811 | AB7: 62.092469 | AC7: 62.221903 | AD7: 62.366379 | AE7: 62.527541 | AF7: 62.706661 | AG7: 62.902975 | AH7: 63.11467 | AI7: 63.339445 | AJ7: 63.574445 | AK7: 63.816333
A8: ch_hous_toe_0 | B8: 42520877 | C8: 42433005 | D8: 42077799 | E8: 41627286 | F8: 41324126 | G8: 41125067 | H8: 40849755 | I8: 40547698 | J8: 40240758 | K8: 39939485 | L8: 39670582 | M8: 39396734 | N8: 39124173 | O8: 38859214 | P8: 38604848 | Q8: 38361319 | R8: 38208189 | S8: 38102461 | T8: 38019656 | U8: 37945535 | V8: 37858134 | W8: 37778545 | X8: 37706483 | Y8: 37646097 | Z8: 37597540 | AA8: 37516929 | AB8: 37446838 | AC8: 37383525 | AD8: 37325014 | AE8: 37270938 | AF8: 37221617 | AG8: 37176548 | AH8: 37135181 | AI8: 37097252 | AJ8: 37062494 | AK8: 37030550
A9: ch_auto_toe_0 | B9: 21780563 | C9: 21483922 | D9: 21339263 | E9: 21292478 | F9: 21325248 | G9: 21412167 | H9: 21523271 | I9: 21645119 | J9: 21772744 | K9: 21904850 | L9: 22044780 | M9: 22188833 | N9: 22336993 | O9: 22486964 | P9: 22635915 | Q9: 22781485 | R9: 22932745 | S9: 23091456 | T9: 23255682 | U9: 23423036 | V9: 23589455 | W9: 23757667 | X9: 23928299 | Y9: 24102679 | Z9: 24282072 | AA9: 24460882 | AB9: 24645630 | AC9: 24838378 | AD9: 25041364 | AE9: 25256603 | AF9: 25485044 | AG9: 25726427 | AH9: 25979489 | AI9: 26242194 | AJ9: 26511952 | AK9: 26785783
A10: cf_toe_ccoa_2 | B10: 5.4028819 | C10: 5.4011148 | D10: 5.3958203 | E10: 5.3712029 | F10: 5.3828505 | G10: 5.4222658 | H10: 5.478815 | I10: 5.3372404 | J10: 5.1691073 | K10: 5.0323781 | L10: 4.9079325 | M10: 4.8203906 | N10: 4.7548021 | O10: 4.7001749 | P10: 4.6568956 | Q10: 4.6251162 | R10: 4.5916777 | S10: 4.5610622 | T10: 4.536906 | U10: 4.5211511 | V10: 4.5145699 | W10: 4.5187627 | X10: 4.5347587 | Y10: 4.5628347 | Z10: 4.6026316 | AA10: 4.6524015 | AB10: 4.713213 | AC10: 4.7867428 | AD10: 4.8729279 | AE10: 4.9701131 | AF10: 5.0762422 | AG10: 5.1901368 | AH10: 5.3115071 | AI10: 5.4403383 | AJ10: 5.5771703 | AK10: 5.7234461
A11: cf_toe_ccoa_0 | B11: 5.4028819 | C11: 5.4011148 | D11: 5.3958203 | E11: 5.3712029 | F11: 5.3828505 | G11: 5.4222658 | H11: 5.4715862 | I11: 5.5218077 | J11: 5.569914 | K11: 5.6162364 | L11: 5.6630365 | M11: 5.7099167 | N11: 5.7547145 | O11: 5.7914031 | P11: 5.8237096 | Q11: 5.8559867 | R11: 5.9013405 | S11: 5.9644242 | T11: 6.0465245 | U11: 6.1469367 | V11: 6.2640443 | W11: 6.3978917 | X11: 6.5485544 | Y11: 6.7158903 | Z11: 6.8991325 | AA11: 7.0956642 | AB11: 7.3070475 | AC11: 7.5344192 | AD11: 7.7779344 | AE11: 8.0351896 | AF11: 8.3026827 | AG11: 8.5775104 | AH11: 8.8576197 | AI11: 9.1412875 | AJ11: 9.4268527 | AK11: 9.7126015
A12: cf_toe_ccoi_2 | B12: 0.08395362 | C12: 0.083997829 | D12: 0.083941881 | E12: 0.083645996 | F12: 0.083822487 | G12: 0.084387731 | H12: 0.085057577 | I12: 0.083326416 | J12: 0.081193401 | K12: 0.079444266 | L12: 0.077916659 | M12: 0.076896169 | N12: 0.076185879 | O12: 0.075622914 | P12: 0.07519407 | Q12: 0.074892576 | R12: 0.074667226 | S12: 0.074522814 | T12: 0.07448425 | U12: 0.074570495 | V12: 0.074784725 | W12: 0.075165837 | X12: 0.075731636 | Y12: 0.07649222 | Z12: 0.077449105 | AA12: 0.078563729 | AB12: 0.079886554 | AC12: 0.081449763 | AD12: 0.083264937 | AE12: 0.085319678 | AF12: 0.0875948 | AG12: 0.090086375 | AH12: 0.092809579 | AI12: 0.095792724 | AJ12: 0.099089831 | AK12: 0.10280218
... A737: ci_toe_cfuel_ser_0 | B737: 2.8654882 | C737: 2.8967075 | D737: 2.9278608 | E737: 2.9597623 | F737: 2.9926616 | G737: 3.0265472 | H737: 3.0613249 | I737: 3.0968928 | J737: 3.1331649 | K737: 3.170076 | L737: 3.2075792 | M737: 3.2456425 | N737: 3.2842451 | O737: 3.3233755 | P737: 3.363028 | Q737: 3.4032016 | R737: 3.443898 | S737: 3.4851202 | T737: 3.5268716 | U737: 3.5691552 | V737: 3.6119734 | W737: 3.6553275 | X737: 3.6992182 | Y737: 3.7436452 | Z737: 3.7886078 | AA737: 3.8341054 | AB737: 3.8801368 | AC737: 3.9267016 | AD737: 3.9737996 | AE737: 4.021431 | AF737: 4.0695968 | AG737: 4.1182989 | AH737: 4.1675396 | AI737: 4.2173221 | AJ737: 4.2676504 | AK737: 4.3185291

Sheet Primary_nrj
A1: _date_ | B1: 42005 | C1: 42370 | D1: 42736 | E1: 43101 | F1: 43466 | G1: 43831 | H1: 44197 | I1: 44562 | J1: 44927 | K1: 45292 | L1: 45658 | M1: 46023 | N1: 46388 | O1: 46753 | P1: 47119 | Q1: 47484 | R1: 47849 | S1: 48214 | T1: 48580 | U1: 48945 | V1: 49310 | W1: 49675 | X1: 50041 | Y1: 50406 | Z1: 50771 | AA1: 51136 | AB1: 51502 | AC1: 51867 | AD1: 52232 | AE1: 52597 | AF1: 52963 | AG1: 53328 | AH1: 53693 | AI1: 54058 | AJ1: 54424 | AK1: 54789
A2: yg_toe_2 | B2: 148.56082 | C2: 149.66963 | D2: 150.66914 | E2: 151.72017 | F2: 152.92185 | G2: 154.31153 | H2: 155.83472 | I2: 158.30282 | J2: 161.03545 | K2: 164.47703 | L2: 168.08202 | M2: 171.65662 | N2: 175.22567 | O2: 178.78365 | P2: 182.49988 | Q2: 186.47924 | R2: 190.54468 | S2: 194.96934 | T2: 199.81297 | U2: 205.14417 | V2: 211.01142 | W2: 217.58223 | X2: 224.98267 | Y2: 233.3418 | Z2: 242.79623 | AA2: 253.38402 | AB2: 265.54184 | AC2: 279.52873 | AD2: 295.68914 | AE2: 314.39879 | AF2: 336.13051 | AG2: 361.5628 | AH2: 391.67332 | AI2: 427.84522 | AJ2: 472.11235 | AK2: 527.58747
A3: yg_toe_0 | B3: 148.56082 | C3: 149.66963 | D3: 150.66914 | E3: 151.72016 | F3: 152.92185 | G3: 154.31153 | H3: 155.81162 | I3: 157.38336 | J3: 158.99628 | K3: 160.63432 | L3: 162.34422 | M3: 164.04524 | N3: 165.70193 | O3: 167.22254 | P3: 168.65808 | Q3: 170.06776 | R3: 171.52804 | S3: 173.11372 | T3: 174.87132 | U3: 176.82197 | V3: 178.94756 | W3: 181.31248 | X3: 183.93443 | Y3: 186.82848 | Z3: 189.99401 | AA3: 193.32934 | AB3: 196.9344 | AC3: 200.82153 | AD3: 204.98962 | AE3: 209.39776 | AF3: 213.98737 | AG3: 218.7064 | AH3: 223.51361 | AI3: 228.37214 | AJ3: 233.24662 | AK3: 238.10205
A4: yg_toe_ccoa_2 | B4: 2.3689359 | C4: 2.3707004 | D4: 2.3703506 | E4: 2.3635461 | F4: 2.3708653 | G4: 2.3892947 | H4: 2.4147907 | I4: 2.3456895 | J4: 2.2637434 | K4: 2.1945963 | L4: 2.1306487 | M4: 2.081842 | N4: 2.041708 | O4: 2.0053086 | P4: 1.9725209 | Q4: 1.9432778 | R4: 1.9110157 | S4: 1.8787299 | T4: 1.8480242 | U4: 1.8195858 | V4: 1.793695 | W4: 1.7705734 | X4: 1.7504397 | Y4: 1.7332868 | Z4: 1.7188886 | AA4: 1.7069303 | AB4: 1.6978468 | AC4: 1.6918094 | AD4: 1.6888699 | AE4: 1.6886384 | AF4: 1.6907116 | AG4: 1.6951666 | AH4: 1.702658 | AI4: 1.7143733 | AJ4: 1.7323747 | AK4: 1.7604351
A5: yg_toe_ccoa_0 | B5: 2.3689359 | C5: 2.3707004 | D5: 2.3703506 | E5: 2.3635461 | F5: 2.3708653 | G5: 2.3892947 | H5: 2.4113444 | I5: 2.4334552 | J5: 2.4544804 | K5: 2.4746325 | L5: 2.49468 | M5: 2.5148763 | N5: 2.5344621 | O5: 2.5512063 | P5: 2.5664506 | Q5: 2.5817675 | R5: 2.6022157 | S5: 2.6294475 | T5: 2.6637799 | U5: 2.7047612 | V5: 2.7517448 | W5: 2.8044333 | X5: 2.8628101 | Y5: 2.9267846 | Z5: 2.9960425 | AA5: 3.0699681 | AB5: 3.1487886 | AC5: 3.2329976 | AD5: 3.3227303 | AE5: 3.4171939 | AF5: 3.5151863 | AG5: 3.6157265 | AH5: 3.7181463 | AI5: 3.8218906 | AJ5: 3.9264092 | AK5: 4.0311098
A6: yg_toe_ccoi_2 | B6: 1.0946754 | C6: 1.1012928 | D6: 1.106706 | E6: 1.112429 | F6: 1.1204086 | G6: 1.1307075 | H6: 1.1426338 | I6: 1.1307582 | J6: 1.1161216 | K6: 1.1047639 | L6: 1.0937869 | M6: 1.0830033 | N6: 1.0718497 | O6: 1.0596561 | P6: 1.0469283 | Q6: 1.0339884 | R6: 1.019511 | S6: 1.004604 | T6: 0.98954573 | U6: 0.97442646 | V6: 0.9592104 | W6: 0.94406592 | X6: 0.92905762 | Y6: 0.91416879 | Z6: 0.89928894 | AA6: 0.88406078 | AB6: 0.86899196 | AC6: 0.85385007 | AD6: 0.83850323 | AE6: 0.82261632 | AF6: 0.80575735 | AG6: 0.78755415 | AH6: 0.76770975 | AI6: 0.74593609 | AJ6: 0.72194172 | AK6: 0.69542898
A7: yg_toe_ccoi_0 | B7: 1.0946754 | C7: 1.1012928 | D7: 1.106706 | E7: 1.112429 | F7: 1.1204086 | G7: 1.1307075 | H7: 1.1421073 | I7: 1.1538805 | J7: 1.1656828 | K7: 1.1774379 | L7: 1.1893874 | M7: 1.2013634 | N7: 1.21312 | O7: 1.2240059 | P7: 1.234293 | Q7: 1.2443874 | R7: 1.2551817 | S7: 1.2672814 | T7: 1.2809454 | U7: 1.2961962 | V7: 1.3128855 | W7: 1.3311584 | X7: 1.3511064 | Y7: 1.3727877 | Z7: 1.396175 | AA7: 1.4208771 | AB7: 1.4472043 | AC7: 1.4753428 | AD7: 1.5053561 | AE7: 1.5370338 | AF7: 1.5700155 | AG7: 1.6039691 | AH7: 1.6386318 | AI7: 1.6737662 | AJ7: 1.7091339 | AK7: 1.7444851
A8: yg_toe_cfut_2 | B8: 42.288297 | C8: 42.459371 | D8: 42.59523 | E8: 42.759565 | F8: 43.02638 | G8: 43.385579 | H8: 43.807512 | I8: 44.524593 | J8: 45.282094 | K8: 46.141238 | L8: 47.057294 | M8: 48.050346 | N8: 49.103452 | O8: 50.194147 | P8: 51.325418 | Q8: 52.500103 | R8: 53.698459 | S8: 54.932118 | T8: 56.214132 | U8: 57.555484 | V8: 58.96053 | W8: 60.447986 | X8: 62.030221 | Y8: 63.718301 | Z8: 65.521393 | AA8: 67.430282 | AB8: 69.473646 | AC8: 71.671573 | AD8: 74.041307 | AE8: 76.594354 | AF8: 79.340132 | AG8: 82.292869 | AH8: 85.474435 | AI8: 88.914292 | AJ8: 92.65521 | AK8: 96.763633
A9: yg_toe_cfut_0 | B9: 42.288297 | C9: 42.459371 | D9: 42.59523 | E9: 42.759565 | F9: 43.02638 | G9: 43.385579 | H9: 43.799341 | I9: 44.235743 | J9: 44.678572 | K9: 45.122469 | L9: 45.57571 | M9: 46.028838 | N9: 46.477109 | O9: 46.904969 | P9: 47.317409 | Q9: 47.722227 | R9: 48.140509 | S9: 48.591535 | T9: 49.083818 | U9: 49.618801 | V9: 50.190379 | W9: 50.805833 | X9: 51.466768 | Y9: 52.174924 | Z9: 52.930569 | AA9: 53.717432 | AB9: 54.550631 | AC9: 55.434428 | AD9: 56.371087 | AE9: 57.356475 | AF9: 58.3825 | AG9: 59.440791 | AH9: 60.523638 | AI9: 61.623243 | AJ9: 62.731437 | AK9: 63.839648
A10: yg_toe_cfuh_2 | B10: 7.9213452 | C10: 7.9566754 | D10: 7.9842468 | E10: 8.0057628 | F10: 8.0438683 | G10: 8.096092 | H10: 8.1549257 | I10: 7.86407 | J10: 7.5529568 | K10: 7.2456216 | L10: 6.9360722 | M10: 6.6352445 | N10: 6.3447464 | O10: 6.063786 | P10: 5.7937783 | Q10: 5.5342863 | R10: 5.281328 | S10: 5.0339838 | T10: 4.7915999 | U10: 4.553601 | V10: 4.3183893 | W10: 4.0873925 | X10: 3.8595402 | Y10: 3.6338629 | Z10: 3.4091498 | AA10: 3.181699 | AB10: 2.9529886 | AC10: 2.7216708 | AD10: 2.486123 | AE10: 2.2442749 | AF10: 1.9939233 | AG10: 1.7329872 | AH10: 1.4594828 | AI10: 1.171374 | AJ10: 0.86641249 | AK10: 0.54188645
A11: yg_toe_cfuh_0 | B11: 7.9213452 | C11: 7.9566754 | D11: 7.9842468 | E11: 8.0057628 | F11: 8.0438683 | G11: 8.096092 | H11: 8.1482865 | I11: 8.1967251 | J11: 8.2416869 | K11: 8.2847655 | L11: 8.3307813 | M11: 8.3757214 | N11: 8.4193635 | O11: 8.4586482 | P11: 8.4951964 | Q11: 8.5311406 | R11: 8.5761861 | S11: 8.6334805 | T11: 8.7027431 | U11: 8.7829426 | V11: 8.8712641 | W11: 8.9709395 | X11: 9.0822202 | Y11: 9.20568 | Z11: 9.3413238 | AA11: 9.4825936 | AB11: 9.6360599 | AC11: 9.8020775 | AD11: 9.9807887 | AE11: 10.170982 | AF11: 10.370611 | AG11: 10.577589 | AH11: 10.790067 | AI11: 11.006356 | AJ11: 11.224799 | AK11: 11.443714
A12: yg_toe_cgas_2 | B12: 6.6386593 | C12: 6.5613083 | D12: 6.5090564 | E12: 6.462288 | F12: 6.4606659 | G12: 6.4694575 | H12: 6.4718946 | I12: 6.3101836 | J12: 6.2069292 | K12: 6.109208 | L12: 6.0303635 | M12: 5.9797979 | N12: 5.9365091 | O12: 5.896763 | P12: 5.8538231 | Q12: 5.804849 | R12: 5.7417926 | S12: 5.6716238 | T12: 5.5944502 | U12: 5.5089277 | V12: 5.4125893 | W12: 5.3050302 | X12: 5.1820132 | Y12: 5.0408389 | Z12: 4.8804404 | AA12: 4.6981408 | AB12: 4.4944795 | AC12: 4.2654891 | AD12: 4.0082525 | AE12: 3.7210821 | AF12: 3.401903 | AG12: 3.0462634 | AH12: 2.6466469 | AI12: 2.1921732 | AJ12: 1.6665323 | AK12: 1.0442492
... A73: yg_toe_cote_spub_0 | B73: 1.2271805 | C73: 1.2458089 | D73: 1.2646327 | E73: 1.2835965 | F73: 1.3040604 | G73: 1.3262037 | H73: 1.3496476 | I73: 1.3734572 | J73: 1.3972524 | K73: 1.4209869 | L73: 1.4450217 | M73: 1.469125 | N73: 1.4925243 | O73: 1.5133283 | P73: 1.5327944 | Q73: 1.5520984 | R73: 1.5724358 | S73: 1.5952414 | T73: 1.6212575 | U73: 1.6506745 | V73: 1.6834579 | W73: 1.7199024 | X73: 1.7602768 | Y73: 1.8046858 | Z73: 1.8529671 | AA73: 1.9045858 | AB73: 1.9600586 | AC73: 2.0197919 | AD73: 2.0838407 | AE73: 2.1514788 | AF73: 2.2217064 | AG73: 2.2937647 | AH73: 2.3671546 | AI73: 2.4414521 | AJ73: 2.5162384 | AK73: 2.5910691

Sheet Energy_Mix
A1: _date_ | B1: 42005 | C1: 42370 | D1: 42736 | E1: 43101 | F1: 43466 | G1: 43831 | H1: 44197 | I1: 44562 | J1: 44927 | K1: 45292 | L1: 45658 | M1: 46023 | N1: 46388 | O1: 46753 | P1: 47119 | Q1: 47484 | R1: 47849 | S1: 48214 | T1: 48580 | U1: 48945 | V1: 49310 | W1: 49675 | X1: 50041 | Y1: 50406 | Z1: 50771 | AA1: 51136 | AB1: 51502 | AC1: 51867 | AD1: 52232 | AE1: 52597 | AF1: 52963 | AG1: 53328 | AH1: 53693 | AI1: 54058 | AJ1: 54424 | AK1: 54789
A2: phiy_ccoa_smin_2 | B2: 0.20069089 | C2: 0.20069089 | D2: 0.20069089 | E2: 0.20069089 | F2: 0.20069089 | G2: 0.20069089 | H2: 0.20069089 | I2: 0.20069089 | J2: 0.20069089 | K2: 0.20069089 | L2: 0.20069089 | M2: 0.20069089 | N2: 0.20069089 | O2: 0.20069089 | P2: 0.20069089 | Q2: 0.20069089 | R2: 0.20069089 | S2: 0.20069089 | T2: 0.20069089 | U2: 0.20069089 | V2: 0.20069089 | W2: 0.20069089 | X2: 0.20069089 | Y2: 0.20069089 | Z2: 0.20069089 | AA2: 0.20069089 | AB2: 0.20069089 | AC2: 0.20069089 | AD2: 0.20069089 | AE2: 0.20069089 | AF2: 0.20069089 | AG2: 0.20069089 | AH2: 0.20069089 | AI2: 0.20069089 | AJ2: 0.20069089 | AK2: 0.20069089
A3: phiy_ccoa_soil_2 | B3: 0.79930911 | C3: 0.79930911 | D3: 0.79930911 | E3: 0.79930911 | F3: 0.79930911 | G3: 0.79930911 | H3: 0.79930911 | I3: 0.79930911 | J3: 0.79930911 | K3: 0.79930911 | L3: 0.79930911 | M3: 0.79930911 | N3: 0.79930911 | O3: 0.79930911 | P3: 0.79930911 | Q3: 0.79930911 | R3: 0.79930911 | S3: 0.79930911 | T3: 0.79930911 | U3: 0.79930911 | V3: 0.79930911 | W3: 0.79930911 | X3: 0.79930911 | Y3: 0.79930911 | Z3: 0.79930911 | AA3: 0.79930911 | AB3: 0.79930911 | AC3: 0.79930911 | AD3: 0.79930911 | AE3: 0.79930911 | AF3: 0.79930911 | AG3: 0.79930911 | AH3: 0.79930911 | AI3: 0.79930911 | AJ3: 0.79930911 | AK3: 0.79930911
A4: phiy_ccoi_smin_2 | B4: 0.7836667 | C4: 0.7836667 | D4: 0.7836667 | E4: 0.7836667 | F4: 0.7836667 | G4: 0.7836667 | H4: 0.7836667 | I4: 0.7836667 | J4: 0.7836667 | K4: 0.7836667 | L4: 0.7836667 | M4: 0.7836667 | N4: 0.7836667 | O4: 0.7836667 | P4: 0.7836667 | Q4: 0.7836667 | R4: 0.7836667 | S4: 0.7836667 | T4: 0.7836667 | U4: 0.7836667 | V4: 0.7836667 | W4: 0.7836667 | X4: 0.7836667 | Y4: 0.7836667 | Z4: 0.7836667 | AA4: 0.7836667 | AB4: 0.7836667 | AC4: 0.7836667 | AD4: 0.7836667 | AE4: 0.7836667 | AF4: 0.7836667 | AG4: 0.7836667 | AH4: 0.7836667 | AI4: 0.7836667 | AJ4: 0.7836667 | AK4: 0.7836667
A5: phiy_ccoi_soil_2 | B5: 0.2163333 | C5: 0.2163333 | D5: 0.2163333 | E5: 0.2163333 | F5: 0.2163333 | G5: 0.2163333 | H5: 0.2163333 | I5: 0.2163333 | J5: 0.2163333 | K5: 0.2163333 | L5: 0.2163333 | M5: 0.2163333 | N5: 0.2163333 | O5: 0.2163333 | P5: 0.2163333 | Q5: 0.2163333 | R5: 0.2163333 | S5: 0.2163333 | T5: 0.2163333 | U5: 0.2163333 | V5: 0.2163333 | W5: 0.2163333 | X5: 0.2163333 | Y5: 0.2163333 | Z5: 0.2163333 | AA5: 0.2163333 | AB5: 0.2163333 | AC5: 0.2163333 | AD5: 0.2163333 | AE5: 0.2163333 | AF5: 0.2163333 | AG5: 0.2163333 | AH5: 0.2163333 | AI5: 0.2163333 | AJ5: 0.2163333 | AK5: 0.2163333
A6: phiy_cfut_soil_2 | B6: 0.83809636 | C6: 0.83809636 | D6: 0.83809636 | E6: 0.83809636 | F6: 0.83809636 | G6: 0.83809636 | H6: 0.83809636 | I6: 0.8060615 | J6: 0.77440437 | K6: 0.74311833 | L6: 0.7121969 | M6: 0.68163373 | N6: 0.65142263 | O6: 0.62155757 | P6: 0.59203262 | Q6: 0.56284201 | R6: 0.53398009 | S6: 0.50544134 | T6: 0.47722036 | U6: 0.44931188 | V6: 0.42171074 | W6: 0.39441188 | X6: 0.36741036 | Y6: 0.34070136 | Z6: 0.31428014 | AA6: 0.28814209 | AB6: 0.26228266 | AC6: 0.23669744 | AD6: 0.21138208 | AE6: 0.18633233 | AF6: 0.16154405 | AG6: 0.13701314 | AH6: 0.11273563 | AI6: 0.088707613 | AJ6: 0.064925259 | AK6: 0.04138482
A7: phiy_cfut_sbfu_2 | B7: 0.16190364 | C7: 0.16190364 | D7: 0.16190364 | E7: 0.16190364 | F7: 0.16190364 | G7: 0.16190364 | H7: 0.16190364 | I7: 0.1939385 | J7: 0.22559563 | K7: 0.25688167 | L7: 0.2878031 | M7: 0.31836627 | N7: 0.34857737 | O7: 0.37844243 | P7: 0.40796738 | Q7: 0.43715799 | R7: 0.46601991 | S7: 0.49455866 | T7: 0.52277964 | U7: 0.55068812 | V7: 0.57828926 | W7: 0.60558812 | X7: 0.63258964 | Y7: 0.65929864 | Z7: 0.68571986 | AA7: 0.71185791 | AB7: 0.73771734 | AC7: 0.76330256 | AD7: 0.78861792 | AE7: 0.81366767 | AF7: 0.83845595 | AG7: 0.86298686 | AH7: 0.88726437 | AI7: 0.91129239 | AJ7: 0.93507474 | AK7: 0.95861518
A8: phiy_cfuh_soil_2 | B8: 1 | C8: 1 | D8: 1 | E8: 1 | F8: 1 | G8: 1 | H8: 1 | I8: 1 | J8: 1 | K8: 1 | L8: 1 | M8: 1 | N8: 1 | O8: 1 | P8: 1 | Q8: 1 | R8: 1 | S8: 1 | T8: 1 | U8: 1 | V8: 1 | W8: 1 | X8: 1 | Y8: 1 | Z8: 1 | AA8: 1 | AB8: 1 | AC8: 1 | AD8: 1 | AE8: 1 | AF8: 1 | AG8: 1 | AH8: 1 | AI8: 1 | AJ8: 1 | AK8: 1
A9: phiy_cgas_smet_2 | B9: 8.2704787e-05 | C9: 8.2704787e-05 | D9: 8.2704787e-05 | E9: 8.2704787e-05 | F9: 8.2704787e-05 | G9: 8.2704787e-05 | H9: 8.2704787e-05 | I9: 7.9449517e-05 | J9: 7.6240696e-05 | K9: 7.3077337e-05 | L9: 6.9958481e-05 | M9: 6.6883194e-05 | N9: 6.3850571e-05 | O9: 6.0859729e-05 | P9: 5.7909812e-05 | Q9: 5.4999984e-05 | R9: 5.2129435e-05 | S9: 4.9297374e-05 | T9: 4.6503032e-05 | U9: 4.374566e-05 | V9: 4.1024531e-05 | W9: 3.8338933e-05 | X9: 3.5688176e-05 | Y9: 3.3071586e-05 | Z9: 3.0488506e-05 | AA9: 2.7938298e-05 | AB9: 2.5420336e-05 | AC9: 2.2934015e-05 | AD9: 2.047874e-05 | AE9: 1.8053934e-05 | AF9: 1.5659033e-05 | AG9: 1.3293488e-05 | AH9: 1.0956763e-05 | AI9: 8.6483323e-06 | AJ9: 6.3676868e-06 | AK9: 4.1143274e-06
A10: phiy_cgas_soil_2 | B10: 0.64531662 | C10: 0.64531662 | D10: 0.64531662 | E10: 0.64531662 | F10: 0.64531662 | G10: 0.64531662 | H10: 0.64531662 | I10: 0.61991689 | J10: 0.59487958 | K10: 0.57019699 | L10: 0.54586164 | M10: 0.52186625 | N10: 0.49820375 | O10: 0.47486725 | P10: 0.45185008 | Q10: 0.42914571 | R10: 0.40674781 | S10: 0.38465022 | T10: 0.36284695 | U10: 0.34133214 | V10: 0.32010011 | W10: 0.29914533 | X10: 0.2784624 | Y10: 0.25804606 | Z10: 0.23789119 | AA10: 0.2179928 | AB10: 0.19834602 | AC10: 0.17894612 | AD10: 0.15978847 | AE10: 0.14086855 | AF10: 0.12218198 | AG10: 0.10372446 | AH10: 0.085491799 | AI10: 0.067479922 | AJ10: 0.04968484 | AK10: 0.032102662
A11: phiy_cgas_sgas_2 | B11: 0.14751433 | C11: 0.14751433 | D11: 0.14751433 | E11: 0.14751433 | F11: 0.14751433 | G11: 0.14751433 | H11: 0.14751433 | I11: 0.14170815 | J11: 0.13598482 | K11: 0.13034257 | L11: 0.1247797 | M11: 0.11929454 | N11: 0.11388548 | O11: 0.10855094 | P11: 0.10328939 | Q11: 0.098099351 | R11: 0.092979367 | S11: 0.087928031 | T11: 0.082943973 | U11: 0.078025856 | V11: 0.073172382 | W11: 0.068382283 | X11: 0.063654326 | Y11: 0.05898731 | Z11: 0.054380064 | AA11: 0.049831448 | AB11: 0.045340349 | AC11: 0.040905683 | AD11: 0.036526393 | AE11: 0.032201449 | AF11: 0.027929844 | AG11: 0.023710599 | AH11: 0.019542756 | AI11: 0.015425382 | AJ11: 0.011357566 | AK11: 0.0073384174
A12: phiy_cgas_sbga_2 | B12: 0.20708634 | C12: 0.20708634 | D12: 0.20708634 | E12: 0.20708634 | F12: 0.20708634 | G12: 0.20708634 | H12: 0.20708634 | I12: 0.23829551 | J12: 0.26905937 | K12: 0.29938737 | L12: 0.32928871 | M12: 0.35877233 | N12: 0.38784692 | O12: 0.41652095 | P12: 0.44480262 | Q12: 0.47269994 | R12: 0.50022069 | S12: 0.52737245 | T12: 0.55416258 | U12: 0.58059826 | V12: 0.60668648 | W12: 0.63243405 | X12: 0.65784759 | Y12: 0.68293356 | Z12: 0.70769826 | AA12: 0.73214782 | AB12: 0.75628821 | AC12: 0.78012526 | AD12: 0.80366466 | AE12: 0.82691194 | AF12: 0.84987252 | AG12: 0.87255165 | AH12: 0.89495449 | AI12: 0.91708605 | AJ12: 0.93895123 | AK12: 0.96055481
... A51: phiy_cote_spub_0 | B51: 0.00010273909 | C51: 0.00010273909 | D51: 0.00010273909 | E51: 0.00010273909 | F51: 0.00010273909 | G51: 0.00010273909 | H51: 0.00010273909 | I51: 0.00010273909 | J51: 0.00010273909 | K51: 0.00010273909 | L51: 0.00010273909 | M51: 0.00010273909 | N51: 0.00010273909 | O51: 0.00010273909 | P51: 0.00010273909 | Q51: 0.00010273909 | R51: 0.00010273909 | S51: 0.00010273909 | T51: 0.00010273909 | U51: 0.00010273909 | V51: 0.00010273909 | W51: 0.00010273909 | X51: 0.00010273909 | Y51: 0.00010273909 | Z51: 0.00010273909 | AA51: 0.00010273909 | AB51: 0.00010273909 | AC51: 0.00010273909 | AD51: 0.00010273909 | AE51: 0.00010273909 | AF51: 0.00010273909 | AG51: 0.00010273909 | AH51: 0.00010273909 | AI51: 0.00010273909 | AJ51: 0.00010273909 | AK51: 0.00010273909

Sheet Transports
A1: _date_ | B1: 42005 | C1: 42370 | D1: 42736 | E1: 43101 | F1: 43466 | G1: 43831 | H1: 44197 | I1: 44562 | J1: 44927 | K1: 45292 | L1: 45658 | M1: 46023 | N1: 46388 | O1: 46753 | P1: 47119 | Q1: 47484 | R1: 47849 | S1: 48214 | T1: 48580 | U1: 48945 | V1: 49310 | W1: 49675 | X1: 50041 | Y1: 50406 | Z1: 50771 | AA1: 51136 | AB1: 51502 | AC1: 51867 | AD1: 52232 | AE1: 52597 | AF1: 52963 | AG1: 53328 | AH1: 53693 | AI1: 54058 | AJ1: 54424 | AK1: 54789
A2: km_traveler_cair_2 | B2: 291099.78 | C2: 297261.27 | D2: 304288.83 | E2: 311628.57 | F2: 319912.29 | G2: 329077.85 | H2: 338487.83 | I2: 341058.51 | J2: 342769.71 | K2: 345539.56 | L2: 349770.62 | M2: 356473.93 | N2: 365975.14 | O2: 376847.98 | P2: 388423.35 | Q2: 400399.9 | R2: 411796.16 | S2: 422443.2 | T2: 433020.86 | U2: 443859.8 | V2: 454798.69 | W2: 466552.73 | X2: 479033.25 | Y2: 492601.29 | Z2: 507460.06 | AA2: 522640.36 | AB2: 539206.19 | AC2: 556671.62 | AD2: 575764.97 | AE2: 596911.33 | AF2: 620319.4 | AG2: 645844.93 | AH2: 673375.61 | AI2: 703226.46 | AJ2: 735669.75 | AK2: 771032.24
A3: km_trav_auto_ld_2+km_trav_auto_sd_2 | B3: 724102.94 | C3: 715012.52 | D3: 711021.41 | E3: 710325.94 | F3: 712320.36 | G3: 716149.25 | H3: 721036.1 | I3: 724343.91 | J3: 727464.33 | K3: 731083.36 | L3: 735502.7 | M3: 741345.48 | N3: 748328.08 | O3: 756018.73 | P3: 764077.74 | Q3: 772274.33 | R3: 780199.66 | S3: 787934.54 | T3: 795579.93 | U3: 803209.14 | V3: 810794.48 | W3: 818503.42 | X3: 826402.95 | Y3: 834580.13 | Z3: 843114.92 | AA3: 851834.55 | AB3: 860972.46 | AC3: 870599.82 | AD3: 880832.47 | AE3: 891794.73 | AF3: 903576.19 | AG3: 916219.27 | AH3: 929737.84 | AI3: 944148.53 | AJ3: 959475.24 | AK3: 975752.23
A4: km_traveler_sd_2 | B4: 624600.34 | C4: 618699.62 | D4: 616312 | E4: 616223.57 | F4: 618011.75 | G4: 621109.39 | H4: 624942.64 | I4: 627657.96 | J4: 630151.68 | K4: 633026.96 | L4: 636509.66 | M4: 640993.19 | N4: 646308.8 | O4: 652122.14 | P4: 658180.6 | Q4: 664317.09 | R4: 670253.7 | S4: 676037.62 | T4: 681749.67 | U4: 687447.58 | V4: 693103.18 | W4: 698862.2 | X4: 704765.92 | Y4: 710879.42 | Z4: 717260.25 | AA4: 723750.99 | AB4: 730564.2 | AC4: 737736.31 | AD4: 745351.43 | AE4: 753495.55 | AF4: 762226.07 | AG4: 771565.17 | AH4: 781515.11 | AI4: 792081.2 | AJ4: 803274.28 | AK4: 815113.34
A5: km_trav_auto_sd_2 | B5: 554271.64 | C5: 547636.95 | D5: 544631.09 | E5: 543972.51 | F5: 545232.53 | G5: 547796.05 | H5: 551114.78 | I5: 553314.95 | J5: 555385.56 | K5: 557788.38 | L5: 560734.85 | M5: 564684.77 | N5: 569428.64 | O5: 574668.63 | P5: 580166.81 | Q5: 585760.3 | R5: 591157.94 | S5: 596419.01 | T5: 601611.7 | U5: 606785.87 | V5: 611926.48 | W5: 617139.55 | X5: 622473.86 | Y5: 627987.37 | Z5: 633734.02 | AA5: 639607.95 | AB5: 645750.81 | AC5: 652215.66 | AD5: 659077.57 | AE5: 666418.63 | AF5: 674298.42 | AG5: 682745.14 | AH5: 691766.93 | AI5: 701372.38 | AJ5: 711574.76 | AK5: 722393.73
A6: km_traveler_croa_2 | B6: 70328.7 | C6: 70374.244 | D6: 70584.444 | E6: 70900.766 | F6: 71290.57 | G6: 71747.248 | H6: 72226.742 | I6: 72655.942 | J6: 73021.158 | K6: 73433.528 | L6: 73911.76 | M6: 74432.309 | N6: 75012.295 | O6: 75615.143 | P6: 76221.337 | Q6: 76821.399 | R6: 77410.951 | S6: 77984.709 | T6: 78553.78 | U6: 79125.352 | V6: 79690.419 | W6: 80278.754 | X6: 80887.85 | Y6: 81524.837 | Z6: 82194.494 | AA6: 82860.076 | AB6: 83571.979 | AC6: 84322.64 | AD6: 85121.303 | AE6: 85974.472 | AF6: 86883.956 | AG6: 87847.81 | AH6: 88863.251 | AI6: 89929.195 | AJ6: 91045.411 | AK6: 92213.155
A7: km_traveler_ld_2 | B7: 275159.81 | C7: 270644.03 | D7: 268706.23 | E7: 268421.27 | F7: 269481.95 | G7: 271456.36 | H7: 273960.39 | I7: 275671.55 | J7: 277315.13 | K7: 279225.25 | L7: 281552.23 | M7: 284603.86 | N7: 288236.55 | O7: 292233.84 | P7: 296425.94 | Q7: 300697.32 | R7: 304839.77 | S7: 308895.33 | T7: 312915.33 | U7: 316937.07 | V7: 320944.13 | W7: 325026.31 | X7: 329218.11 | Y7: 333566.58 | Z7: 338114.94 | AA7: 342769.18 | AB7: 347658.41 | AC7: 352820.86 | AD7: 358322.54 | AE7: 364234.32 | AF7: 370608.58 | AG7: 377472.41 | AH7: 384838.09 | AI7: 392720.61 | AJ7: 401139.13 | AK7: 410118.96
A8: km_trav_auto_ld_2 | B8: 169831.3 | C8: 167375.56 | D8: 166390.33 | E8: 166353.43 | F8: 167087.82 | G8: 168353.19 | H8: 169921.32 | I8: 171028.96 | J8: 172078.77 | K8: 173294.98 | L8: 174767.85 | M8: 176660.71 | N8: 178899.43 | O8: 181350.09 | P8: 183910.93 | Q8: 186514.03 | R8: 189041.72 | S8: 191515.53 | T8: 193968.23 | U8: 196423.27 | V8: 198868 | W8: 201363.87 | X8: 203929.09 | Y8: 206592.77 | Z8: 209380.9 | AA8: 212226.6 | AB8: 215221.64 | AC8: 218384.16 | AD8: 221754.9 | AE8: 225376.1 | AF8: 229277.77 | AG8: 233474.13 | AH8: 237970.91 | AI8: 242776.15 | AJ8: 247900.48 | AK8: 253358.5
A9: km_traveler_crai_2 | B9: 105328.51 | C9: 106727.46 | D9: 108096.76 | E9: 109434.91 | F9: 110690.21 | G9: 111947.24 | H9: 113145.29 | I9: 114359.75 | J9: 115374.63 | K9: 116513.57 | L9: 117805.69 | M9: 119067 | N9: 120405.03 | O9: 121735.35 | P9: 123029.67 | Q9: 124284.19 | R9: 125539.6 | S9: 126762.71 | T9: 127984.58 | U9: 129223.66 | V9: 130446.48 | W9: 131750.84 | X9: 133116.79 | Y9: 134562.56 | Z9: 136097.27 | AA9: 137593.28 | AB9: 139225.35 | AC9: 140951.29 | AD9: 142796.79 | AE9: 144773.81 | AF9: 146879.22 | AG9: 149099.64 | AH9: 151422.6 | AI9: 153844.15 | AJ9: 156362.46 | AK9: 158980.44
A10: km_traveler_cair_0 | B10: 291099.78 | C10: 297261.27 | D10: 304288.83 | E10: 311628.57 | F10: 319912.29 | G10: 329077.85 | H10: 338226.25 | I10: 347553.87 | J10: 357090.83 | K10: 366886.04 | L10: 377479.43 | M10: 388093.85 | N10: 399058.99 | O10: 410114.28 | P10: 421095.73 | Q10: 431946.71 | R10: 443100.44 | S10: 454504.02 | T10: 466156.1 | U10: 478102.97 | V10: 490026.71 | W10: 502797.2 | X10: 516293.34 | Y10: 530688.71 | Z10: 546086.57 | AA10: 561356.37 | AB10: 578215.46 | AC10: 596409.93 | AD10: 616182.02 | AE10: 637740.55 | AF10: 661135.95 | AG10: 686322.11 | AH10: 713192.82 | AI10: 741595.5 | AJ10: 771340.43 | AK10: 802202.7
A11: km_trav_auto_ld_0+km_trav_auto_sd_0 | B11: 724102.94 | C11: 715012.52 | D11: 711021.41 | E11: 710325.94 | F11: 712320.36 | G11: 716149.25 | H11: 720804.19 | I11: 725835.1 | J11: 731078.63 | K11: 736495.14 | L11: 742201.46 | M11: 748075.57 | N11: 754118.29 | O11: 760252.34 | P11: 766381.7 | Q11: 772426.46 | R11: 778696.32 | S11: 785249.08 | T11: 792016.29 | U11: 798915.9 | V11: 805810.37 | W11: 812796.74 | X11: 819902.34 | Y11: 827179.8 | Z11: 834681.06 | AA11: 842222.02 | AB11: 850037.39 | AC11: 858209.98 | AD11: 866829.17 | AE11: 875977 | AF11: 885698.69 | AG11: 895997.13 | AH11: 906839.81 | AI11: 918166.69 | AJ11: 929897.65 | AK11: 941938.14
A12: km_traveler_sd_0 | B12: 624600.34 | C12: 618699.62 | D12: 616312 | E12: 616223.57 | F12: 618011.75 | G12: 621109.39 | H12: 624761.66 | I12: 628658.87 | J12: 632689.79 | K12: 636831.47 | L12: 641191.69 | M12: 645650.96 | N12: 650223.89 | O12: 654847.03 | P12: 659449.79 | Q12: 663977 | R12: 668671.78 | S12: 673577.54 | T12: 678644.89 | U12: 683814.89 | V12: 688977.03 | W12: 694226.12 | X12: 699573.06 | Y12: 705057.04 | Z12: 710714.82 | AA12: 716379.43 | AB12: 722266.28 | AC12: 728419 | AD12: 734901.38 | AE12: 741768.92 | AF12: 749047.78 | AG12: 756732.86 | AH12: 764793.94 | AI12: 773181.75 | AJ12: 781833.57 | AK12: 790677.32
... A17: km_traveler_crai_0 | B17: 105328.51 | C17: 106727.46 | D17: 108096.76 | E17: 109434.91 | F17: 110690.21 | G17: 111947.24 | H17: 113092.1 | I17: 114180.73 | J17: 115235.61 | K17: 116274.78 | L17: 117382.05 | M17: 118444.35 | N17: 119510.82 | O17: 120551.12 | P17: 121554.95 | Q17: 122525.52 | R17: 123542.16 | S17: 124605.87 | T17: 125715.03 | U17: 126869.79 | V17: 128025.99 | W17: 129278.57 | X17: 130602.35 | Y17: 132008.4 | Z17: 133501.21 | AA17: 134950.22 | AB17: 136536.82 | AC17: 138218.3 | AD17: 140006.72 | AE17: 141905.42 | AF17: 143904.79 | AG17: 145988.32 | AH17: 148136.73 | AI17: 150329.55 | AJ17: 152546.08 | AK17: 154765.78

Sheet Hybrid
A1: _date_ | B1: 42005 | C1: 42370 | D1: 42736 | E1: 43101 | F1: 43466 | G1: 43831 | H1: 44197 | I1: 44562 | J1: 44927 | K1: 45292 | L1: 45658 | M1: 46023 | N1: 46388 | O1: 46753 | P1: 47119 | Q1: 47484 | R1: 47849 | S1: 48214 | T1: 48580 | U1: 48945 | V1: 49310 | W1: 49675 | X1: 50041 | Y1: 50406 | Z1: 50771 | AA1: 51136 | AB1: 51502 | AC1: 51867 | AD1: 52232 | AE1: 52597 | AF1: 52963 | AG1: 53328 | AH1: 53693 | AI1: 54058 | AJ1: 54424 | AK1: 54789
A2: auto_2 | B2: 32317.941 | C2: 31911.217 | D2: 31732.935 | E2: 31702.286 | F2: 31792.126 | G2: 31964.155 | H2: 32183.571 | I2: 32332.233 | J2: 32472.488 | K2: 32635.15 | L2: 32833.745 | M2: 33096.138 | N2: 33409.646 | O2: 33754.897 | P2: 34116.664 | Q2: 34484.601 | R2: 34840.395 | S2: 35187.66 | T2: 35530.931 | U2: 35873.499 | V2: 36214.109 | W2: 36560.304 | X2: 36915.081 | Y2: 37282.355 | Z2: 37665.714 | AA2: 38057.367 | AB2: 38467.848 | AC2: 38900.337 | AD2: 39360.046 | AE2: 39852.565 | AF2: 40381.92 | AG2: 40950.018 | AH2: 41557.485 | AI2: 42205.076 | AJ2: 42893.874 | AK2: 43625.428
A3: auto_cfut_2 | B3: 32271.24 | C3: 31846.407 | D3: 31648.242 | E3: 31596.228 | F3: 31663.113 | G3: 31810.955 | H3: 32005.277 | I3: 32128.171 | J3: 32237.637 | K3: 32360.627 | L3: 32506.312 | M3: 32698.95 | N3: 32925.863 | O3: 33168.14 | P3: 33411.081 | Q3: 33644.806 | R3: 33851.648 | S3: 34034.314 | T3: 34196.539 | U3: 34340.956 | V3: 34466.048 | W3: 34578.3 | X3: 34679.92 | Y3: 34773.821 | Z3: 34862.48 | AA3: 34938.344 | AB3: 35009.765 | AC3: 35078.423 | AD3: 35147.499 | AE3: 35220.221 | AF3: 35298.24 | AG3: 35381.248 | AH3: 35467.734 | AI3: 35556.156 | AJ3: 35645.092 | AK3: 35733.333
A4: auto_cele_2 | B4: 44.765 | C4: 62.819188 | D4: 82.635226 | E4: 103.92645 | F4: 126.8031 | G4: 150.90795 | H4: 175.92151 | I4: 201.61753 | J4: 232.34003 | K4: 271.94795 | L4: 324.79548 | M4: 394.48636 | N4: 481.01754 | O4: 583.92944 | P4: 702.69365 | Q4: 836.84851 | R4: 985.74742 | S4: 1150.2974 | T4: 1331.2979 | U4: 1529.4071 | V4: 1744.8852 | W4: 1978.7917 | X4: 2231.9152 | Y4: 2505.2561 | Z4: 2799.9266 | AA4: 3115.6878 | AB4: 3454.7218 | AC4: 3818.5286 | AD4: 4209.1377 | AE4: 4628.9127 | AF4: 5080.2261 | AG4: 5565.294 | AH4: 6086.2534 | AI4: 6645.402 | AJ4: 7245.244 | AK4: 7888.5377
A5: auto_cgas_2 | B5: 1.936 | C5: 1.990293 | D5: 2.0574577 | E5: 2.1314073 | F5: 2.2103839 | G5: 2.2916631 | H5: 2.3727336 | I5: 2.444007 | J5: 2.5105011 | K5: 2.5746912 | L5: 2.6375801 | M5: 2.7014355 | N5: 2.7654388 | O5: 2.8282162 | P5: 2.8887098 | Q5: 2.9462366 | R5: 2.9994375 | S5: 3.0486346 | T5: 3.0942339 | U5: 3.1365477 | V5: 3.1755376 | W5: 3.2118297 | X5: 3.2456943 | Y5: 3.2774582 | Z5: 3.3074104 | AA5: 3.3349953 | AB5: 3.3609789 | AC5: 3.3855733 | AD5: 3.4091146 | AE5: 3.4319423 | AF5: 3.4542639 | AG5: 3.4761196 | AH5: 3.4974441 | AI5: 3.518164 | AJ5: 3.5382101 | AK5: 3.5575264
A6: newauto_2 | B6: 1886.229 | C6: 2106.5678 | D6: 2302.6748 | E6: 2435.6831 | F6: 2552.9813 | G6: 2641.2942 | H6: 2701.1564 | I6: 2646.5302 | J6: 2648.7191 | K6: 2680.8782 | L6: 2727.9709 | M6: 2805.2234 | N6: 2874.1216 | O6: 2926.9892 | P6: 2966.4782 | Q6: 2996.3097 | R6: 3007.725 | S6: 3021.2524 | T6: 3038.058 | U6: 3057.2227 | V6: 3074.43 | W6: 3098.3713 | X6: 3125.0483 | Y6: 3155.5792 | Z6: 3189.9086 | AA6: 3216.8903 | AB6: 3254.2539 | AC6: 3295.3832 | AD6: 3342.5004 | AE6: 3396.3116 | AF6: 3455.5992 | AG6: 3518.4676 | AH6: 3583.7004 | AI6: 3651.3947 | AJ6: 3721.8502 | AK6: 3795.5218
A7: newauto_cfut_2 | B7: 1868.6749 | C7: 2086.5477 | D7: 2280.1545 | E7: 2410.8839 | F7: 2525.7354 | G7: 2611.8978 | H7: 2669.8822 | I7: 2613.5778 | J7: 2609.7127 | K7: 2631.7556 | L7: 2664.0216 | M7: 2722.312 | N7: 2771.5781 | O7: 2804.601 | P7: 2824.1196 | Q7: 2833.809 | R7: 2825.1148 | S7: 2817.0358 | T7: 2810.8095 | U7: 2805.6259 | V7: 2797.5406 | W7: 2794.4346 | X7: 2792.5385 | Y7: 2792.7271 | Z7: 2794.793 | AA7: 2788.8978 | AB7: 2790.358 | AC7: 2793.1529 | AD7: 2798.915 | AE7: 2807.9352 | AF7: 2818.8925 | AG7: 2829.953 | AH7: 2839.8907 | AI7: 2848.5567 | AJ7: 2855.9523 | AK7: 2862.1779
A8: newauto_cele_2 | B8: 17.397156 | C8: 19.844788 | D8: 22.328806 | E8: 24.596635 | F8: 27.033711 | G8: 29.176972 | H8: 31.049875 | I8: 32.732885 | J8: 38.787199 | K8: 48.901525 | L8: 63.725444 | M8: 82.682694 | N8: 102.31064 | O8: 122.1526 | P8: 142.12138 | Q8: 162.26261 | R8: 182.37285 | S8: 203.97989 | T8: 227.01241 | U8: 251.36111 | V8: 276.65438 | W8: 303.70191 | X8: 332.27519 | Y8: 362.61747 | Z8: 394.88076 | AA8: 427.75825 | AB8: 463.66155 | AC8: 501.99565 | AD8: 543.35025 | AE8: 588.14044 | AF8: 636.46996 | AG8: 688.2769 | AH8: 743.57119 | AI8: 802.59875 | AJ8: 865.65806 | AK8: 933.10346
A9: newauto_cgas_2 | B9: 0.15698923 | C9: 0.17529295 | D9: 0.19155805 | E9: 0.20254075 | F9: 0.21218955 | G9: 0.21942814 | H9: 0.22429946 | I9: 0.21956927 | J9: 0.21924456 | K9: 0.2210964 | L9: 0.22380711 | M9: 0.22870414 | N9: 0.23284303 | O9: 0.23561732 | P9: 0.2372571 | Q9: 0.23807112 | R9: 0.23734071 | S9: 0.23666198 | T9: 0.2361389 | U9: 0.23570343 | V9: 0.23502417 | W9: 0.23476323 | X9: 0.23460394 | Y9: 0.23461978 | Z9: 0.23479334 | AA9: 0.23429808 | AB9: 0.23442075 | AC9: 0.23465555 | AD9: 0.23513964 | AE9: 0.23589743 | AF9: 0.23681796 | AG9: 0.23774716 | AH9: 0.23858204 | AI9: 0.23931008 | AJ9: 0.23993139 | AK9: 0.24045442
A10: auto_0 | B10: 32317.941 | C10: 31911.217 | D10: 31732.935 | E10: 31702.286 | F10: 31792.126 | G10: 31964.155 | H10: 32173.16 | I10: 32399.008 | J10: 32634.391 | K10: 32877.538 | L10: 33133.714 | M10: 33397.411 | N10: 33668.683 | O10: 33944.056 | P10: 34219.22 | Q10: 34490.594 | R10: 34772.085 | S10: 35066.281 | T10: 35370.114 | U10: 35679.906 | V10: 35989.48 | W10: 36303.222 | X10: 36622.35 | Y10: 36949.23 | Z10: 37286.196 | AA10: 37624.944 | AB10: 37976.069 | AC10: 38343.273 | AD10: 38730.572 | AE10: 39141.654 | AF10: 39578.549 | AG10: 40041.386 | AH10: 40528.705 | AI10: 41037.81 | AJ10: 41565.104 | AK10: 42106.337
A11: auto_cfut_0 | B11: 32271.24 | C11: 31846.407 | D11: 31648.242 | E11: 31596.228 | F11: 31663.113 | G11: 31810.955 | H11: 31994.923 | I11: 32194.829 | J11: 32403.053 | K11: 32617.374 | L11: 32842.463 | M11: 33072.342 | N11: 33306.522 | O11: 33541.054 | P11: 33771.202 | Q11: 33992.964 | R11: 34219.57 | S11: 34453.408 | T11: 34691.436 | U11: 34930.011 | V11: 35163.03 | W11: 35394.534 | X11: 35625.401 | Y11: 35857.521 | Z11: 36092.656 | AA11: 36322.355 | AB11: 36556.102 | AC11: 36796.681 | AD11: 37047.05 | AE11: 37309.729 | AF11: 37585.568 | AG11: 37873.542 | AH11: 38171.077 | AI11: 38474.414 | AJ11: 38778.94 | AK11: 39079.453
A12: auto_cele_0 | B12: 44.765 | C12: 62.819188 | D12: 82.635226 | E12: 103.92645 | F12: 126.8031 | G12: 150.90795 | H12: 175.86538 | I12: 201.72995 | J12: 228.81361 | K12: 257.56694 | L12: 288.58453 | M12: 322.3347 | N12: 359.36258 | O12: 400.14024 | P12: 445.09687 | Q12: 494.65141 | R12: 549.48236 | S12: 609.78595 | T12: 675.53815 | U12: 746.70526 | V12: 823.2112 | W12: 905.40244 | X12: 993.6182 | Y12: 1088.334 | Z12: 1190.1217 | AA12: 1299.1298 | AB12: 1416.4663 | AC12: 1543.0505 | AD12: 1679.9407 | AE12: 1828.3026 | AF12: 1989.3181 | AG12: 2164.1407 | AH12: 2353.8829 | AI12: 2559.6103 | AJ12: 2782.3369 | AK12: 3023.0184
... A121: buil_des_0 | B121: 1.1716777 | C121: 1.1716777 | D121: 1.1565402 | E121: 1.1416083 | F121: 1.1268791 | G121: 1.1123494 | H121: 1.0980163 | I121: 1.083877 | J121: 1.0699286 | K121: 1.0561683 | L121: 1.0425934 | M121: 1.0292012 | N121: 1.0159892 | O121: 1.0029547 | P121: 0.99009523 | Q121: 0.97740825 | R121: 0.96489133 | S121: 0.95254204 | T121: 0.940358 | U121: 0.92833689 | V121: 0.91647639 | W121: 0.90477425 | X121: 0.89322823 | Y121: 0.88183615 | Z121: 0.87059586 | AA121: 0.85950523 | AB121: 0.84856218 | AC121: 0.83776466 | AD121: 0.82711064 | AE121: 0.81659814 | AF121: 0.8062252 | AG121: 0.7959899 | AH121: 0.78589034 | AI121: 0.77592465 | AJ121: 0.766091 | AK121: 0.75638758

Sheet Tab-macro
B1: en écart au scénario de référence (%)
B2: ThreeME
B3: 2021 | C3: 2022 | D3: 2023 | E3: 2025 | F3: 2030 | G3: 2050
A4: PIB en volume | B4: =Macro!H2 -> 0.048738572 | C4: =Macro!I2 -> 0.060095859 | D4: =Macro!J2 -> 0.070015107 | E4: =Macro!L2 -> 0.085962983 | F4: =Macro!Q2 -> 0.14265241 | G4: =Macro!AK2 -> 0.14504591
A5: Consommation des ménages | B5: =Macro!H3 -> 0.063591595 | C5: =Macro!I3 -> 0.077928064 | D5: =Macro!J3 -> 0.090208724 | E5: =Macro!L3 -> 0.1094652 | F5: =Macro!Q3 -> 0.17703503 | G5: =Macro!AK3 -> 0.12232402
A6: Investissement | B6: =Macro!H4 -> 0.061611156 | C6: =Macro!I4 -> 0.08278401 | D6: =Macro!J4 -> 0.10533605 | E6: =Macro!L4 -> 0.15272541 | F6: =Macro!Q4 -> 0.31843771 | G6: =Macro!AK4 -> 1.5666395
A7: Exportations | B7: =Macro!H5 -> -0.024587398 | C7: =Macro!I5 -> -0.027517752 | D7: =Macro!J5 -> -0.029270488 | E7: =Macro!L5 -> -0.033062862 | F7: =Macro!Q5 -> -0.071051222 | G7: =Macro!AK5 -> -0.31031219
A8: Importations | B8: =Macro!H6 -> 0 | C8: =Macro!I6 -> 0 | D8: =Macro!J6 -> 0 | E8: =Macro!L6 -> 0 | F8: =Macro!Q6 -> 0 | G8: =Macro!AK6 -> 0
A9: Revenu disponible (réel) des ménages | B9: =Macro!H7 -> -0.012798614 | C9: =Macro!I7 -> -0.016283169 | D9: =Macro!J7 -> -0.019770476 | E9: =Macro!L7 -> -0.027092237 | F9: =Macro!Q7 -> -0.053082546 | G9: =Macro!AK7 -> -0.24896132
A10: Taux d'épargne (en pts) | B10: =Macro!H8 -> 0 | C10: =Macro!I8 -> 0 | D10: =Macro!J8 -> 0 | E10: =Macro!L8 -> 0 | F10: =Macro!Q8 -> 0 | G10: =Macro!AK8 -> 0
A11: Prix de la consommation des ménages | B11: =Macro!H9 -> -7.3934973e-05 | C11: =Macro!I9 -> -0.0064049649 | D11: =Macro!J9 -> -0.015550473 | E11: =Macro!L9 -> -0.039670205 | F11: =Macro!Q9 -> -0.12270277 | G11: =Macro!AK9 -> -1.1726323
A12: Prix de la production | B12: =Macro!H10 -> 0.060548092 | C12: =Macro!I10 -> 0.081405037 | D12: =Macro!J10 -> 0.1036274 | E12: =Macro!L10 -> 0.1502951 | F12: =Macro!Q10 -> 0.31317578 | G12: =Macro!AK10 -> 1.5416795
A13: Prix de la valeur ajoutée | B13: =Macro!H11 -> -0.011735551 | C13: =Macro!I11 -> -0.014904197 | D13: =Macro!J11 -> -0.018061834 | E13: =Macro!L11 -> -0.024661926 | F13: =Macro!Q11 -> -0.047820621 | G13: =Macro!AK11 -> -0.2240013
A14: Prix des consommations intermédiaires | B14: =Macro!H12 -> -0.011136824 | C14: =Macro!I12 -> -0.014171638 | D14: =Macro!J12 -> -0.017215766 | E14: =Macro!L12 -> -0.023646689 | F14: =Macro!Q12 -> -0.046521399 | G14: =Macro!AK12 -> -0.21942615
A15: Prix des exportations | B15: =Macro!H13 -> 0.0010630635 | C15: =Macro!I13 -> 0.0013789727 | D15: =Macro!J13 -> 0.0017086427 | E15: =Macro!L13 -> 0.0024303114 | F15: =Macro!Q13 -> 0.0052619252 | G15: =Macro!AK13 -> 0.024960015
... A24: Emissions de CO2 | B24: =Macro!H22 -> 0.11223714 | C24: =Macro!I22 -> 0.15093497 | D24: =Macro!J22 -> 0.19217887 | E24: =Macro!L22 -> 0.2788085 | F24: =Macro!Q22 -> 0.58101383 | G24: =Macro!AK22 -> 2.8548709
B26: % deviation from baseline
B27: ThreeME
B28: 2021 | C28: 2022 | D28: 2023 | E28: 2025 | F28: 2030 | G28: 2050
A29: GDP in volume | B29: =B4 -> 0.048738572 | C29: =C4 -> 0.060095859 | D29: =D4 -> 0.070015107 | E29: =E4 -> 0.085962983 | F29: =F4 -> 0.14265241 | G29: =G4 -> 0.14504591
A30: Household consumption | B30: =B5 -> 0.063591595 | C30: =C5 -> 0.077928064 | D30: =D5 -> 0.090208724 | E30: =E5 -> 0.1094652 | F30: =F5 -> 0.17703503 | G30: =G5 -> 0.12232402
A31: Investment | B31: =B6 -> 0.061611156 | C31: =C6 -> 0.08278401 | D31: =D6 -> 0.10533605 | E31: =E6 -> 0.15272541 | F31: =F6 -> 0.31843771 | G31: =G6 -> 1.5666395
A32: Exports | B32: =B7 -> -0.024587398 | C32: =C7 -> -0.027517752 | D32: =D7 -> -0.029270488 | E32: =E7 -> -0.033062862 | F32: =F7 -> -0.071051222 | G32: =G7 -> -0.31031219
A33: Imports | B33: =B8 -> 0 | C33: =C8 -> 0 | D33: =D8 -> 0 | E33: =E8 -> 0 | F33: =F8 -> 0 | G33: =G8 -> 0
A34: Household disposable income (real) | B34: =B9 -> -0.012798614 | C34: =C9 -> -0.016283169 | D34: =D9 -> -0.019770476 | E34: =E9 -> -0.027092237 | F34: =F9 -> -0.053082546 | G34: =G9 -> -0.24896132
A35: Saving rate (in points) | B35: =B10 -> 0 | C35: =C10 -> 0 | D35: =D10 -> 0 | E35: =E10 -> 0 | F35: =F10 -> 0 | G35: =G10 -> 0
A36: Household consumption price index | B36: =B11 -> -7.3934973e-05 | C36: =C11 -> -0.0064049649 | D36: =D11 -> -0.015550473 | E36: =E11 -> -0.039670205 | F36: =F11 -> -0.12270277 | G36: =G11 -> -1.1726323
A37: Production price index | B37: =B12 -> 0.060548092 | C37: =C12 -> 0.081405037 | D37: =D12 -> 0.1036274 | E37: =E12 -> 0.1502951 | F37: =F12 -> 0.31317578 | G37: =G12 -> 1.5416795
A38: Added value price index | B38: =B13 -> -0.011735551 | C38: =C13 -> -0.014904197 | D38: =D13 -> -0.018061834 | E38: =E13 -> -0.024661926 | F38: =F13 -> -0.047820621 | G38: =G13 -> -0.2240013
A39: Intermediate consumption price index | B39: =B14 -> -0.011136824 | C39: =C14 -> -0.014171638 | D39: =D14 -> -0.017215766 | E39: =E14 -> -0.023646689 | F39: =F14 -> -0.046521399 | G39: =G14 -> -0.21942615
A40: Export price index | B40: =B15 -> 0.0010630635 | C40: =C15 -> 0.0013789727 | D40: =D15 -> 0.0017086427 | E40: =E15 -> 0.0024303114 | F40: =F15 -> 0.0052619252 | G40: =G15 -> 0.024960015
... A49: CO2 emissions | B49: =B24 -> 0.11223714 | C49: =C24 -> 0.15093497 | D49: =D24 -> 0.19217887 | E49: =E24 -> 0.2788085 | F49: =F24 -> 0.58101383 | G49: =G24 -> 2.8548709

Sheet Tab-baseline
C1: 8 | D1: 9 | E1: 10 | F1: 12 | G1: 17 | H1: 37
C2: ThreeME
C3: 2021 | D3: 2022 | E3: 2023 | F3: 2025 | G3: 2030 | H3: 2050
A4: Taux de croissance du PIB | B4: @pch(gdp_0) | C4: =VLOOKUP($B4,Baseline!$A$1:$AT$50,C$1,FALSE) -> 0.011252093 | D4: =VLOOKUP($B4,Baseline!$A$1:$AT$50,D$1,FALSE) -> 0.011375472 | E4: =VLOOKUP($B4,Baseline!$A$1:$AT$50,E$1,FALSE) -> 0.011476237 | F4: =VLOOKUP($B4,Baseline!$A$1:$AT$50,F$1,FALSE) -> 0.011614092 | G4: =VLOOKUP($B4,Baseline!$A$1:$AT$50,G$1,FALSE) -> 0.011726136 | H4: =VLOOKUP($B4,Baseline!$A$1:$AT$50,H$1,FALSE) -> 0.011660368
A5: Prix de la consommation des ménages | B5: @pch(pch_0) | C5: =VLOOKUP($B5,Baseline!$A$1:$AT$50,C$1,FALSE) -> 0.019635207 | D5: =VLOOKUP($B5,Baseline!$A$1:$AT$50,D$1,FALSE) -> 0.019668197 | E5: =VLOOKUP($B5,Baseline!$A$1:$AT$50,E$1,FALSE) -> 0.019714318 | F5: =VLOOKUP($B5,Baseline!$A$1:$AT$50,F$1,FALSE) -> 0.019828898 | G5: =VLOOKUP($B5,Baseline!$A$1:$AT$50,G$1,FALSE) -> 0.020129185 | H5: =VLOOKUP($B5,Baseline!$A$1:$AT$50,H$1,FALSE) -> 0.020366929
A6: Taux de chômage | B6: unr_0 | C6: =VLOOKUP($B6,Baseline!$A$1:$AT$50,C$1,FALSE) -> 0.14415906 | D6: =VLOOKUP($B6,Baseline!$A$1:$AT$50,D$1,FALSE) -> 0.14419204 | E6: =VLOOKUP($B6,Baseline!$A$1:$AT$50,E$1,FALSE) -> 0.14412979 | F6: =VLOOKUP($B6,Baseline!$A$1:$AT$50,F$1,FALSE) -> 0.14381068 | G6: =VLOOKUP($B6,Baseline!$A$1:$AT$50,G$1,FALSE) -> 0.14261895 | H6: =VLOOKUP($B6,Baseline!$A$1:$AT$50,H$1,FALSE) -> 0.13887513
A7: Dette publique (en pts de PIB) | B7: rdebt_g_val_0 | C7: =VLOOKUP($B7,Baseline!$A$1:$AT$50,C$1,FALSE) -> 0.97004802 | D7: =VLOOKUP($B7,Baseline!$A$1:$AT$50,D$1,FALSE) -> 0.97258712 | E7: =VLOOKUP($B7,Baseline!$A$1:$AT$50,E$1,FALSE) -> 0.97503146 | F7: =VLOOKUP($B7,Baseline!$A$1:$AT$50,F$1,FALSE) -> 0.97946806 | G7: =VLOOKUP($B7,Baseline!$A$1:$AT$50,G$1,FALSE) -> 0.98723106 | H7: =VLOOKUP($B7,Baseline!$A$1:$AT$50,H$1,FALSE) -> 0.97986829
A8: Solde primaire public (en pts de PIB) | B8: rbal_g_prim_val_0 | C8: =VLOOKUP($B8,Baseline!$A$1:$AT$50,C$1,FALSE) -> -0.011460252 | D8: =VLOOKUP($B8,Baseline!$A$1:$AT$50,D$1,FALSE) -> -0.011637089 | E8: =VLOOKUP($B8,Baseline!$A$1:$AT$50,E$1,FALSE) -> -0.011732353 | F8: =VLOOKUP($B8,Baseline!$A$1:$AT$50,F$1,FALSE) -> -0.011733134 | G8: =VLOOKUP($B8,Baseline!$A$1:$AT$50,G$1,FALSE) -> -0.011177481 | H8: =VLOOKUP($B8,Baseline!$A$1:$AT$50,H$1,FALSE) -> -0.00849113
A9: Balance commerciale (en pts de PIB) | B9: rbal_trade_val_0 | C9: =VLOOKUP($B9,Baseline!$A$1:$AT$50,C$1,FALSE) -> -0.01277292 | D9: =VLOOKUP($B9,Baseline!$A$1:$AT$50,D$1,FALSE) -> -0.012784957 | E9: =VLOOKUP($B9,Baseline!$A$1:$AT$50,E$1,FALSE) -> -0.012769054 | F9: =VLOOKUP($B9,Baseline!$A$1:$AT$50,F$1,FALSE) -> -0.012698368 | G9: =VLOOKUP($B9,Baseline!$A$1:$AT$50,G$1,FALSE) -> -0.012442025 | H9: =VLOOKUP($B9,Baseline!$A$1:$AT$50,H$1,FALSE) -> -0.011138905
A10: Emissions de CO2 (en Kt CO2) | B10: ems_co2_0 | C10: =VLOOKUP($B10,Baseline!$A$1:$AT$50,C$1,FALSE) -> 362.04263 | D10: =VLOOKUP($B10,Baseline!$A$1:$AT$50,D$1,FALSE) -> 364.51423 | E10: =VLOOKUP($B10,Baseline!$A$1:$AT$50,E$1,FALSE) -> 367.1103 | F10: =VLOOKUP($B10,Baseline!$A$1:$AT$50,F$1,FALSE) -> 372.57878 | G10: =VLOOKUP($B10,Baseline!$A$1:$AT$50,G$1,FALSE) -> 387.32088 | H10: =VLOOKUP($B10,Baseline!$A$1:$AT$50,H$1,FALSE) -> 457.40889
C33: ThreeME
C34: 2021 | D34: 2022 | E34: 2023 | F34: 2025 | G34: 2030 | H34: 2050
A35: GDP growth rate | C35: =C4 -> 0.011252093 | D35: =D4 -> 0.011375472 | E35: =E4 -> 0.011476237 | F35: =F4 -> 0.011614092 | G35: =G4 -> 0.011726136 | H35: =H4 -> 0.011660368
A36: Household consumption price | C36: =C5 -> 0.019635207 | D36: =D5 -> 0.019668197 | E36: =E5 -> 0.019714318 | F36: =F5 -> 0.019828898 | G36: =G5 -> 0.020129185 | H36: =H5 -> 0.020366929
A37: unemployment rate | C37: =C6 -> 0.14415906 | D37: =D6 -> 0.14419204 | E37: =E6 -> 0.14412979 | F37: =F6 -> 0.14381068 | G37: =G6 -> 0.14261895 | H37: =H6 -> 0.13887513
A38: Public debt (in points of GDP) | C38: =C7 -> 0.97004802 | D38: =D7 -> 0.97258712 | E38: =E7 -> 0.97503146 | F38: =F7 -> 0.97946806 | G38: =G7 -> 0.98723106 | H38: =H7 -> 0.97986829
A39: Public budget balance (in points of GDP) | C39: =C8 -> -0.011460252 | D39: =D8 -> -0.011637089 | E39: =E8 -> -0.011732353 | F39: =F8 -> -0.011733134 | G39: =G8 -> -0.011177481 | H39: =H8 -> -0.00849113
A40: Trade balance (in points of GDP) | C40: =C9 -> -0.01277292 | D40: =D9 -> -0.012784957 | E40: =E9 -> -0.012769054 | F40: =F9 -> -0.012698368 | G40: =G9 -> -0.012442025 | H40: =H9 -> -0.011138905
A41: CO2 emissions (In Kt og CO2) | C41: =C10 -> 362.04263 | D41: =D10 -> 364.51423 | E41: =E10 -> 367.1103 | F41: =F10 -> 372.57878 | G41: =G10 -> 387.32088 | H41: =H10 -> 457.40889

Sheet Macro
A1: _date_ | B1: 42005 | C1: 42370 | D1: 42736 | E1: 43101 | F1: 43466 | G1: 43831 | H1: 44197 | I1: 44562 | J1: 44927 | K1: 45292 | L1: 45658 | M1: 46023 | N1: 46388 | O1: 46753 | P1: 47119 | Q1: 47484 | R1: 47849 | S1: 48214 | T1: 48580 | U1: 48945 | V1: 49310 | W1: 49675 | X1: 50041 | Y1: 50406 | Z1: 50771 | AA1: 51136 | AB1: 51502 | AC1: 51867 | AD1: 52232 | AE1: 52597 | AF1: 52963 | AG1: 53328 | AH1: 53693 | AI1: 54058 | AJ1: 54424 | AK1: 54789
A2: 100*(gdp_2/gdp_0-1) | B2: 0 | C2: 0.0033641188 | D2: 0.009082291 | E2: 0.016620143 | F2: 0.02577382 | G2: 0.036754288 | H2: 0.048738572 | I2: 0.060095859 | J2: 0.070015107 | K2: 0.078444433 | L2: 0.085962983 | M2: 0.093517875 | N2: 0.10215197 | O2: 0.11279884 | P2: 0.12615999 | Q2: 0.14265241 | R2: 0.16135001 | S2: 0.18024887 | T2: 0.19776238 | U2: 0.21281822 | V2: 0.22488159 | W2: 0.2338464 | X2: 0.23987807 | Y2: 0.24327291 | Z2: 0.24435604 | AA2: 0.24341917 | AB2: 0.24069009 | AC2: 0.23632354 | AD2: 0.2304066 | AE2: 0.22297109 | AF2: 0.214009 | AG2: 0.20348859 | AH2: 0.1913679 | AI2: 0.17760612 | AJ2: 0.16217138 | AK2: 0.14504591
A3: 100*((va_2-va_spub_2)/(va_0-va_spub_0)-1) | B3: 0 | C3: 0.0046308167 | D3: 0.012257928 | E3: 0.022103622 | F3: 0.033966861 | G3: 0.048189737 | H3: 0.063591595 | I3: 0.077928064 | J3: 0.090208724 | K3: 0.10045819 | L3: 0.1094652 | M3: 0.1184394 | N3: 0.1286842 | O3: 0.14135391 | P3: 0.15730604 | Q3: 0.17703503 | R3: 0.19924261 | S3: 0.22128363 | T3: 0.24119395 | U3: 0.25769971 | V3: 0.27018273 | W3: 0.27853429 | X3: 0.28297033 | Y3: 0.28387016 | Z3: 0.28165927 | AA3: 0.27673714 | AB3: 0.26944028 | AC3: 0.26002941 | AD3: 0.24869328 | AE3: 0.23555983 | AF3: 0.2207121 | AG3: 0.20420388 | AH3: 0.18607388 | AI3: 0.16635677 | AJ3: 0.14509112 | AK3: 0.12232402
A4: 100*((ch_2-ch_0)/gdp_0) | B4: 0 | C4: 0.0021929801 | D4: 0.0075184546 | E4: 0.016082427 | F4: 0.027795421 | G4: 0.042970977 | H4: 0.061611156 | I4: 0.08278401 | J4: 0.10533605 | K4: 0.12861584 | L4: 0.15272541 | M4: 0.17837011 | N4: 0.20660031 | O4: 0.23859334 | P4: 0.27551309 | Q4: 0.31843771 | R4: 0.36765925 | S4: 0.42226695 | T4: 0.48084151 | U4: 0.54207887 | V4: 0.60507623 | W4: 0.6693145 | X4: 0.7345283 | Y4: 0.80057285 | Z4: 0.867326 | AA4: 0.9346302 | AB4: 1.0022654 | AC4: 1.0699443 | AD4: 1.1373208 | AE4: 1.2040053 | AF4: 1.2695832 | AG4: 1.3336324 | AH4: 1.3957396 | AI4: 1.4555121 | AJ4: 1.5125876 | AK4: 1.5666395
A5: 100*((ch_cveh_2-ch_cveh_0)/gdp_0) | B5: 0 | C5: -0.0038211489 | D5: -0.0078287774 | E5: -0.011437917 | F5: -0.01522218 | G5: -0.019979752 | H5: -0.024587398 | I5: -0.027517752 | J5: -0.029270488 | K5: -0.030830207 | L5: -0.033062862 | M5: -0.036601617 | N5: -0.041888144 | O5: -0.049238324 | P5: -0.05889336 | Q5: -0.071051222 | R5: -0.084293783 | S5: -0.096698207 | T5: -0.10805854 | U5: -0.11869867 | V5: -0.12898095 | W5: -0.13917584 | X5: -0.14945748 | Y5: -0.15993074 | Z5: -0.17065773 | AA5: -0.18167635 | AB5: -0.1930112 | AC5: -0.20467918 | AD5: -0.21669179 | AE5: -0.22905573 | AF5: -0.24177268 | AG5: -0.25483882 | AH5: -0.26824449 | AI5: -0.28197399 | AJ5: -0.29600566 | AK5: -0.31031219
A6: 100*((g_2-g_0)/gdp_0) | B6: 0 | C6: 0 | D6: 0 | E6: 0 | F6: 0 | G6: 0 | H6: 0 | I6: 0 | J6: 0 | K6: 0 | L6: 0 | M6: 0 | N6: 0 | O6: 0 | P6: 0 | Q6: 0 | R6: 0 | S6: 0 | T6: 0 | U6: 0 | V6: 0 | W6: 0 | X6: 0 | Y6: 0 | Z6: 0 | AA6: 0 | AB6: 0 | AC6: 0 | AD6: 0 | AE6: 0 | AF6: 0 | AG6: 0 | AH6: 0 | AI6: 0 | AJ6: 0 | AK6: 0
A7: 100*((i_2-i_0)/gdp_0) | B7: 0 | C7: -0.00099763414 | D7: -0.0024626904 | E7: -0.0042537118 | F7: -0.006488056 | G7: -0.0093974964 | H7: -0.012798614 | I7: -0.016283169 | J7: -0.019770476 | K7: -0.023334814 | L7: -0.027092237 | M7: -0.031158351 | N7: -0.035648547 | O7: -0.040691922 | P7: -0.046442581 | Q7: -0.053082546 | R7: -0.060521407 | S7: -0.068495847 | T7: -0.076931207 | U7: -0.085824172 | V7: -0.09516352 | W7: -0.10490086 | X7: -0.11495415 | Y7: -0.12522463 | Z7: -0.13561465 | AA7: -0.1460409 | AB7: -0.15644188 | AC7: -0.16678054 | AD7: -0.17704333 | AE7: -0.18723733 | AF7: -0.19738627 | AG7: -0.20752639 | AH7: -0.2177026 | AI7: -0.2279651 | AJ7: -0.2383668 | AK7: -0.24896132
A8: 100*((ds_2-ds_0)/gdp_0) | B8: 0 | C8: 0 | D8: 0 | E8: 0 | F8: 0 | G8: 0 | H8: 0 | I8: 0 | J8: 0 | K8: 0 | L8: 0 | M8: 0 | N8: 0 | O8: 0 | P8: 0 | Q8: 0 | R8: 0 | S8: 0 | T8: 0 | U8: 0 | V8: 0 | W8: 0 | X8: 0 | Y8: 0 | Z8: 0 | AA8: 0 | AB8: 0 | AC8: 0 | AD8: 0 | AE8: 0 | AF8: 0 | AG8: 0 | AH8: 0 | AI8: 0 | AJ8: 0 | AK8: 0
A9: 100*((x_2-x_0)/gdp_0)-100*((m_2-m_0)/gdp_0) | B9: 0 | C9: 0.0021687728 | D9: 0.0040265624 | E9: 0.0047914326 | F9: 0.0044664595 | G9: 0.0031807909 | H9: -7.3934973e-05 | I9: -0.0064049649 | J9: -0.015550473 | K9: -0.026836629 | L9: -0.039670205 | M9: -0.053693879 | N9: -0.068799796 | O9: -0.085102591 | P9: -0.10291054 | Q9: -0.12270277 | R9: -0.14578786 | S9: -0.17352223 | T9: -0.20614789 | U9: -0.24343649 | V9: -0.28503111 | W9: -0.33056725 | X9: -0.37969609 | Y9: -0.4320753 | Z9: -0.48735534 | AA9: -0.54517011 | AB9: -0.60513344 | AC9: -0.66684025 | AD9: -0.72987085 | AE9: -0.7937969 | AF9: -0.85818789 | AG9: -0.92261745 | AH9: -0.98666908 | AI9: -1.0499409 | AJ9: -1.1120494 | AK9: -1.1726323
A10: 100*((ch_2-ch_ccon_2-(ch_0-ch_ccon_0))/gdp_0) | B10: 0 | C10: 0.0021207018 | D10: 0.007337823 | E10: 0.015756902 | F10: 0.027279421 | G10: 0.0422047 | H10: 0.060548092 | I10: 0.081405037 | J10: 0.1036274 | K10: 0.12656015 | L10: 0.1502951 | M10: 0.17552297 | N10: 0.20327748 | O10: 0.2347194 | P10: 0.27099731 | Q10: 0.31317578 | R10: 0.36156279 | S10: 0.41528178 | T10: 0.47293042 | U10: 0.53321458 | V10: 0.59523666 | W10: 0.65847952 | X10: 0.72267832 | Y10: 0.78768907 | Z10: 0.85339154 | AA10: 0.91963167 | AB10: 0.98619446 | AC10: 1.0527988 | AD10: 1.1191057 | AE10: 1.1847329 | AF10: 1.2492735 | AG10: 1.3123126 | AH10: 1.3734436 | AI10: 1.4322804 | AJ10: 1.4884661 | AK10: 1.5416795
A11: 100*((i_2+ch_ccon_2-(i_0+ch_ccon_0))/gdp_0) | B11: 0 | C11: -0.00092535583 | D11: -0.0022820587 | E11: -0.0039281872 | F11: -0.0059720563 | G11: -0.00863122 | H11: -0.011735551 | I11: -0.014904197 | J11: -0.018061834 | K11: -0.021279116 | L11: -0.024661926 | M11: -0.02831121 | N11: -0.032325719 | O11: -0.036817978 | P11: -0.041926806 | Q11: -0.047820621 | R11: -0.054424942 | S11: -0.061510685 | T11: -0.069020114 | U11: -0.076959883 | V11: -0.08532395 | W11: -0.094065871 | X11: -0.10310417 | Y11: -0.11234085 | Z11: -0.12168019 | AA11: -0.13104237 | AB11: -0.14037094 | AC11: -0.14963504 | AD11: -0.1588282 | AE11: -0.16796496 | AF11: -0.17707654 | AG11: -0.18620651 | AH11: -0.19540661 | AI11: -0.20473337 | AJ11: -0.21424538 | AK11: -0.2240013
A12: 100*((i_2-ia_spub_2-(i_0-ia_spub_0))/gdp_0) | B12: 0 | C12: -0.00087466774 | D12: -0.0021557973 | E12: -0.0037131923 | F12: -0.0056511184 | G12: -0.0081779994 | H12: -0.011136824 | I12: -0.014171638 | J12: -0.017215766 | K12: -0.020339604 | L12: -0.023646689 | M12: -0.027235156 | N12: -0.031199408 | O12: -0.035644881 | P12: -0.040700252 | Q12: -0.046521399 | R12: -0.05302878 | S12: -0.059995985 | T12: -0.067367641 | U12: -0.075153307 | V12: -0.083352677 | W12: -0.091927434 | X12: -0.10080455 | Y12: -0.10989271 | Z12: -0.11909977 | AA12: -0.12834595 | AB12: -0.13757141 | AC12: -0.14673913 | AD12: -0.15583433 | AE12: -0.16486182 | AF12: -0.17384244 | AG12: -0.18280907 | AH12: -0.19180304 | AI12: -0.20087087 | AJ12: -0.21006188 | AK12: -0.21942615
... A55: pop | B55: 66422.5 | C55: 66588.556 | D55: 66755.028 | E55: 66921.915 | F55: 67089.22 | G55: 67256.943 | H55: 67425.085 | I55: 67593.648 | J55: 67762.632 | K55: 67932.039 | L55: 68101.869 | M55: 68272.124 | N55: 68442.804 | O55: 68613.911 | P55: 68785.446 | Q55: 68957.409 | R55: 69129.803 | S55: 69302.627 | T55: 69475.884 | U55: 69649.574 | V55: 69823.698 | W55: 69998.257 | X55: 70173.252 | Y55: 70348.686 | Z55: 70524.557 | AA55: 70700.869 | AB55: 70877.621 | AC55: 71054.815 | AD55: 71232.452 | AE55: 71410.533 | AF55: 71589.059 | AG55: 71768.032 | AH55: 71947.452 | AI55: 72127.321 | AJ55: 72307.639 | AK55: 72488.408

Sheet Baseline
A1: @date | B1: 42005 | C1: 42370 | D1: 42736 | E1: 43101 | F1: 43466 | G1: 43831 | H1: 44197 | I1: 44562 | J1: 44927 | K1: 45292 | L1: 45658 | M1: 46023 | N1: 46388 | O1: 46753 | P1: 47119 | Q1: 47484 | R1: 47849 | S1: 48214 | T1: 48580 | U1: 48945 | V1: 49310 | W1: 49675 | X1: 50041 | Y1: 50406 | Z1: 50771 | AA1: 51136 | AB1: 51502 | AC1: 51867 | AD1: 52232 | AE1: 52597 | AF1: 52963 | AG1: 53328 | AH1: 53693 | AI1: 54058 | AJ1: 54424 | AK1: 54789
A2: @pch(gdp_0) | B2: 0.0115225 | C2: 0.010855574 | D2: 0.010728383 | E2: 0.010808991 | F2: 0.010953896 | G2: 0.011108712 | H2: 0.011252093 | I2: 0.011375472 | J2: 0.011476237 | K2: 0.011554988 | L2: 0.011614092 | M2: 0.011656738 | N2: 0.011686315 | O2: 0.011706004 | P2: 0.011718548 | Q2: 0.011726136 | R2: 0.011730408 | S2: 0.011732513 | T2: 0.011733198 | U2: 0.011732909 | V2: 0.011731877 | W2: 0.011730202 | X2: 0.011727914 | Y2: 0.011725016 | Z2: 0.011721512 | AA2: 0.011717423 | AB2: 0.011712793 | AC2: 0.011707687 | AD2: 0.011702187 | AE2: 0.011696385 | AF2: 0.01169038 | AG2: 0.011684266 | AH2: 0.011678133 | AI2: 0.011672062 | AJ2: 0.011666122 | AK2: 0.011660368
A3: @pch(pch_0) | B3: 0.02 | C3: 0.019898733 | D3: 0.019777199 | E3: 0.01968545 | F3: 0.019635261 | G3: 0.019621524 | H3: 0.019635207 | I3: 0.019668197 | J3: 0.019714318 | K3: 0.019769024 | L3: 0.019828898 | M3: 0.019891268 | N3: 0.019953995 | O3: 0.020015379 | P3: 0.0200741 | Q3: 0.020129185 | R3: 0.020179956 | S3: 0.020225984 | T3: 0.020267047 | U3: 0.020303072 | V3: 0.020334107 | W3: 0.020360285 | X3: 0.020381796 | Y3: 0.020398879 | Z3: 0.020411799 | AA3: 0.020420845 | AB3: 0.020426324 | AC3: 0.020428547 | AD3: 0.020427835 | AE3: 0.020424509 | AF3: 0.020418888 | AG3: 0.020411284 | AH3: 0.020402003 | AI3: 0.020391335 | AJ3: 0.020379558 | AK3: 0.020366929
A4: unr_0 | B4: 0.14211338 | C4: 0.14239253 | D4: 0.14284801 | E4: 0.14332745 | F4: 0.14372958 | G4: 0.14400924 | H4: 0.14415906 | I4: 0.14419204 | J4: 0.14412979 | K4: 0.14399556 | L4: 0.14381068 | M4: 0.14359297 | N4: 0.14335631 | O4: 0.14311086 | P4: 0.1428636 | Q4: 0.14261895 | R4: 0.14237946 | S4: 0.14214634 | T4: 0.14191994 | U4: 0.14170015 | V4: 0.1414866 | W4: 0.14127888 | X4: 0.1410766 | Y4: 0.14087947 | Z4: 0.14068727 | AA4: 0.14049986 | AB4: 0.14031716 | AC4: 0.14013913 | AD4: 0.13996573 | AE4: 0.13979691 | AF4: 0.13963262 | AG4: 0.13947277 | AH4: 0.13931725 | AI4: 0.13916591 | AJ4: 0.13901859 | AK4: 0.13887513
A5: rdebt_g_val_0 | B5: 0.958 | C5: 0.95897527 | D5: 0.96058315 | E5: 0.96263011 | F5: 0.96497124 | G5: 0.96748013 | H5: 0.97004802 | I5: 0.97258712 | J5: 0.97503146 | K5: 0.97733498 | L5: 0.97946806 | M5: 0.98141366 | N5: 0.98316355 | O5: 0.98471535 | P5: 0.98607015 | Q5: 0.98723106 | R5: 0.98820224 | S5: 0.98898846 | T5: 0.98959494 | U5: 0.99002734 | V5: 0.99029187 | W5: 0.99039536 | X5: 0.99034531 | Y5: 0.99014987 | Z5: 0.98981782 | AA5: 0.98935842 | AB5: 0.9887813 | AC5: 0.98809631 | AD5: 0.98731335 | AE5: 0.98644222 | AF5: 0.98549246 | AG5: 0.98447327 | AH5: 0.98339337 | AI5: 0.98226095 | AJ5: 0.9810836 | AK5: 0.97986829
A6: rbal_g_prim_val_0 | B6: -0.0092851685 | C6: -0.0095358179 | D6: -0.0099463988 | E6: -0.010405279 | F6: -0.01083516 | G6: -0.011192718 | H6: -0.011460252 | I6: -0.011637089 | J6: -0.011732353 | K6: -0.011759578 | L6: -0.011733134 | M6: -0.011666163 | N6: -0.011569624 | O6: -0.011452069 | P6: -0.011319842 | Q6: -0.011177481 | R6: -0.011028163 | S6: -0.010874133 | T6: -0.010717037 | U6: -0.01055818 | V6: -0.01039869 | W6: -0.010239614 | X6: -0.010081963 | Y6: -0.0099267197 | Z6: -0.0097748207 | AA6: -0.0096271357 | AB6: -0.0094844412 | AC6: -0.0093473998 | AD6: -0.0092165451 | AE6: -0.0090922747 | AF6: -0.0089748501 | AG6: -0.0088644026 | AH6: -0.0087609442 | AI6: -0.0086643811 | AJ6: -0.0085745291 | AK6: -0.00849113
A7: rbal_trade_val_0 | B7: -0.01081433 | C7: -0.011339149 | D7: -0.011886849 | E7: -0.012303141 | F7: -0.012567896 | G7: -0.012711325 | H7: -0.01277292 | I7: -0.012784957 | J7: -0.012769054 | K7: -0.012737939 | L7: -0.012698368 | M7: -0.012653596 | N7: -0.012605063 | O7: -0.0125534 | P7: -0.012498953 | Q7: -0.012442025 | R7: -0.012382953 | S7: -0.012322107 | T7: -0.012259858 | U7: -0.012196549 | V7: -0.012132469 | W7: -0.012067848 | X7: -0.012002849 | Y7: -0.011937583 | Z7: -0.011872113 | AA7: -0.011806466 | AB7: -0.01174065 | AC7: -0.011674654 | AD7: -0.011608464 | AE7: -0.011542065 | AF7: -0.011475444 | AG7: -0.011408593 | AH7: -0.011341509 | AI7: -0.011274195 | AJ7: -0.011206656 | AK7: -0.011138905
A8: ems_co2_0 | B8: 350.29271 | C8: 352.43131 | D8: 354.06052 | E8: 355.7321 | F8: 357.61599 | G8: 359.72996 | H8: 362.04263 | I8: 364.51423 | J8: 367.1103 | K8: 369.80468 | L8: 372.57878 | M8: 375.41988 | N8: 378.31942 | O8: 381.27176 | P8: 384.27304 | Q8: 387.32088 | R8: 390.41383 | S8: 393.55096 | T8: 396.73175 | U8: 399.95582 | V8: 403.22297 | W8: 406.53308 | X8: 409.88608 | Y8: 413.28196 | Z8: 416.72071 | AA8: 420.20234 | AB8: 423.72691 | AC8: 427.29449 | AD8: 430.90523 | AE8: 434.55929 | AF8: 438.25689 | AG8: 441.9983 | AH8: 445.78382 | AI8: 449.61382 | AJ8: 453.4887 | AK8: 457.40889
A9: pop | B9: 66422.5 | C9: 66588.556 | D9: 66755.028 | E9: 66921.915 | F9: 67089.22 | G9: 67256.943 | H9: 67425.085 | I9: 67593.648 | J9: 67762.632 | K9: 67932.039 | L9: 68101.869 | M9: 68272.124 | N9: 68442.804 | O9: 68613.911 | P9: 68785.446 | Q9: 68957.409 | R9: 69129.803 | S9: 69302.627 | T9: 69475.884 | U9: 69649.574 | V9: 69823.698 | W9: 69998.257 | X9: 70173.252 | Y9: 70348.686 | Z9: 70524.557 | AA9: 70700.869 | AB9: 70877.621 | AC9: 71054.815 | AD9: 71232.452 | AE9: 71410.533 | AF9: 71589.059 | AG9: 71768.032 | AH9: 71947.452 | AI9: 72127.321 | AJ9: 72307.639 | AK9: 72488.408
A10: gdp_0 | B10: 2196558.3 | C10: 2220403.2 | D10: 2244224.5 | E10: 2268482.3 | F10: 2293331 | G10: 2318807 | H10: 2344898.4 | I10: 2371572.7 | J10: 2398789.5 | K10: 2426507.4 | L10: 2454689.1 | M10: 2483302.8 | N10: 2512323.4 | O10: 2541732.7 | P10: 2571518.1 | Q10: 2601672.1 | R10: 2632190.8 | S10: 2663073 | T10: 2694319.4 | U10: 2725931.6 | V10: 2757911.9 | W10: 2790262.7 | X10: 2822986.7 | Y10: 2856086.2 | Z10: 2889563.9 | AA10: 2923422.1 | AB10: 2957663.6 | AC10: 2992291 | AD10: 3027307.3 | AE10: 3062715.9 | AF10: 3098520.2 | AG10: 3134724.1 | AH10: 3171331.8 | AI10: 3208347.8 | AJ10: 3245776.8 | AK10: 3283623.8
A11: pch_0 | B11: 1 | C11: 1.0198987 | D11: 1.0400695 | E11: 1.0605437 | F11: 1.0813678 | G11: 1.1025858 | H11: 1.1242353 | I11: 1.146347 | J11: 1.1689465 | K11: 1.1920554 | L11: 1.2156926 | M11: 1.2398742 | N11: 1.2646147 | O11: 1.2899264 | P11: 1.3158205 | Q11: 1.3423069 | R11: 1.3693946 | S11: 1.397092 | T11: 1.4254069 | U11: 1.454347 | V11: 1.4839199 | W11: 1.5141329 | X11: 1.5449937 | Y11: 1.5765098 | Z11: 1.6086892 | AA11: 1.64154 | AB11: 1.6750706 | AC11: 1.7092899 | AD11: 1.744207 | AE11: 1.7798315 | AF11: 1.8161737 | AG11: 1.8532442 | AH11: 1.891054 | AI11: 1.9296152 | AJ11: 1.9689399 | AK11: 2.0090411
A12: ems_ch_co2_0 | B12: 119.49049 | C12: 119.25476 | D12: 118.5914 | E12: 117.94146 | F12: 117.43342 | G12: 117.07744 | H12: 116.84707 | I12: 116.7106 | J12: 116.64129 | K12: 116.61924 | L12: 116.63059 | M12: 116.66599 | N12: 116.71922 | O12: 116.78609 | P12: 116.86366 | Q12: 116.94993 | R12: 117.04357 | S12: 117.1436 | T12: 117.24929 | U12: 117.36001 | V12: 117.4753 | W12: 117.59479 | X12: 117.71816 | Y12: 117.84518 | Z12: 117.97565 | AA12: 118.10939 | AB12: 118.24629 | AC12: 118.38623 | AD12: 118.52913 | AE12: 118.67492 | AF12: 118.82357 | AG12: 118.97505 | AH12: 119.12935 | AI12: 119.28646 | AJ12: 119.44639 | AK12: 119.60915
... A28: ems_co2_cote_0 | B28: 17.86536 | C28: 18.049747 | D28: 18.22732 | E28: 18.406258 | F28: 18.589806 | G28: 18.778708 | H28: 18.972724 | I28: 19.17133 | J28: 19.373997 | K28: 19.580285 | L28: 19.789857 | M28: 20.002471 | N28: 20.217959 | O28: 20.436215 | P28: 20.657178 | Q28: 20.880819 | R28: 21.107135 | S28: 21.336135 | T28: 21.567842 | U28: 21.802281 | V28: 22.039486 | W28: 22.279487 | X28: 22.522317 | Y28: 22.768007 | Z28: 23.016586 | AA28: 23.268084 | AB28: 23.52253 | AC28: 23.779952 | AD28: 24.040379 | AE28: 24.303843 | AF28: 24.570373 | AG28: 24.840001 | AH28: 25.112761 | AI28: 25.388689 | AJ28: 25.667821 | AK28: 25.950193

Sheet produits-secteurs V2-V3
B1: ThreeME V3 | M1: ThreeME V2
B2: Produits | C2: V3 | E2: V2 | G2: Secteurs | H2: V3 | I2: V2 | K2: commentaires | M2: Produits | P2: secteurs
B3: Products of agriculture, Hunting, and Fishing | C3: cagr | E3: 1 | G3: Agriculture and fishing | H3: sagr | I3: 1 | M3: Agriculture, sylviculture et pêche | N3: 1 | P3: Agriculture, sylviculture et pêche | Q3: 1
B4: Products of Forestry | C4: cfor | G4: Forestry | H4: sfor | M4: Industrie agro-alimentaire | N4: 2 | P4: Industrie agro-alimentaire | Q4: 2
B5: Food products and beverages | C5: cfoo | E5: 2 | G5: Manufacture of food products and beverages | H5: sfoo | I5: 2 | M5: Automobile | N5: 3 | P5: Automobile | Q5: 3
B6: Motor vehicles, trailers and semi-trailers | C6: cveh | E6: 3 | G6: Manufacture of motor vehicles, trailers and semi-trailers | H6: sveh | I6: 3 | M6: FABRICATION DE VERRE ET D ARTICLES EN VE | N6: 4 | P6: FABRICATION DE VERRE ET D ARTICLES EN VE | Q6: 4
B7: Glass and ceramic products | C7: cgla | E7: 4 e t 5 | G7: Manufacture of glass, ceramic and ciment products | H7: sgla | I7: 4 et 5 | K7: ETS | M7: FABRICATION DE PRODUITS CERAMIQUES ET DE | N7: 5 | P7: FABRICATION DE PRODUITS CERAMIQUES ET DE | Q7: 5
B8: Paper and paperboard | C8: cpap | E8: 6 | G8: Manufacture of paper and paperboard | H8: spap | I8: 6 | K8: ETS | M8: Papier ert carton | N8: 6 | P8: Papier ert carton | Q8: 6
B9: Chemicals | C9: cche | E9: 7 et 8 | G9: Manufacture of chemicals | H9: sche | I9: 7 et 8 | K9: ETS | M9: INDUSTRIE CHIMIQUE MINERALE | N9: 7 | P9: INDUSTRIE CHIMIQUE MINERALE | Q9: 7
