Workbook
Name formatResults: [1]ResultsEXR10!$A$50

Sheet Export
A1: _date_ | B1: 42005 | C1: 42370 | D1: 42736 | E1: 43101 | F1: 43466 | G1: 43831 | H1: 44197 | I1: 44562 | J1: 44927 | K1: 45292 | L1: 45658 | M1: 46023 | N1: 46388 | O1: 46753 | P1: 47119 | Q1: 47484 | R1: 47849 | S1: 48214 | T1: 48580 | U1: 48945 | V1: 49310 | W1: 49675 | X1: 50041 | Y1: 50406 | Z1: 50771 | AA1: 51136 | AB1: 51502 | AC1: 51867 | AD1: 52232 | AE1: 52597 | AF1: 52963 | AG1: 53328 | AH1: 53693 | AI1: 54058 | AJ1: 54424 | AK1: 54789
A2: x_2 | B2: 641440.93 | C2: 656549 | D2: 672089.72 | E2: 688109.81 | F2: 704772.14 | G2: 721948.72 | H2: 739239.18 | I2: 746134.7 | J2: 752317.16 | K2: 767039.96 | L2: 780590.88 | M2: 793499.2 | N2: 805506.71 | O2: 816228.54 | P2: 827765.8 | Q2: 840654.2 | R2: 854029.84 | S2: 868237.84 | T2: 883256.14 | U2: 899190.25 | V2: 916570.48 | W2: 936063.75 | X2: 958404.52 | Y2: 983802.61 | Z2: 1011860.7 | AA2: 1041973.6 | AB2: 1073645.3 | AC2: 1106673.4 | AD2: 1140894 | AE2: 1176124.6 | AF2: 1212454.2 | AG2: 1250277.4 | AH2: 1289830.1 | AI2: 1330776.6 | AJ2: 1372369.7 | AK2: 1413753.1
A3: x_0 | B3: 641440.93 | C3: 656549 | D3: 672089.72 | E3: 688109.81 | F3: 704772.14 | G3: 721948.72 | H3: 738857.91 | I3: 754935.79 | J3: 770047.91 | K3: 784535.12 | L3: 798996.96 | M3: 813973.37 | N3: 829037.75 | O3: 842670.72 | P3: 856062.18 | Q3: 869905.93 | R3: 884459.9 | S3: 900782.21 | T3: 919117.49 | U3: 939316.15 | V3: 961204.04 | W3: 984568.76 | X3: 1009525.2 | Y3: 1036208.3 | Z3: 1064689.9 | AA3: 1095221.7 | AB3: 1128048.2 | AC3: 1163469.4 | AD3: 1201285.8 | AE3: 1240609.4 | AF3: 1280538 | AG3: 1320658.9 | AH3: 1360988.5 | AI3: 1401683 | AJ3: 1442847.2 | AK3: 1484419.3
A4: x_cagr_2 | B4: 15794.537 | C4: 16161.639 | D4: 16546.562 | E4: 16945.424 | F4: 17363.002 | G4: 17792.648 | H4: 18217.526 | I4: 18358.705 | J4: 18439.829 | K4: 18702.695 | L4: 18929.432 | M4: 19158.021 | N4: 19395 | O4: 19631.81 | P4: 19910.952 | Q4: 20233.81 | R4: 20586.363 | S4: 20948.185 | T4: 21316.274 | U4: 21697.167 | V4: 22111.91 | W4: 22584.748 | X4: 23138.482 | Y4: 23778.397 | Z4: 24489.747 | AA4: 25249.525 | AB4: 26024.039 | AC4: 26814.423 | AD4: 27620.543 | AE4: 28449.113 | AF4: 29315.4 | AG4: 30237.583 | AH4: 31222.199 | AI4: 32255.505 | AJ4: 33310.556 | AK4: 34359.14
A5: x_cagr_0 | B5: 15794.537 | C5: 16161.639 | D5: 16546.562 | E5: 16945.424 | F5: 17363.002 | G5: 17792.648 | H5: 18201.852 | I5: 18570.473 | J5: 18896.79 | K5: 19197.309 | L5: 19496.59 | M5: 19815.502 | N5: 20147.363 | O5: 20455.075 | P5: 20764.265 | Q5: 21086.598 | R5: 21443.021 | S5: 21847.628 | T5: 22304.328 | U5: 22805.481 | V5: 23342.502 | W5: 23907.224 | X5: 24502.446 | Y5: 25134.228 | Z5: 25808.439 | AA5: 26534.967 | AB5: 27321.432 | AC5: 28174.209 | AD5: 29085.331 | AE5: 30029.947 | AF5: 30985.197 | AG5: 31943.32 | AH5: 32909.035 | AI5: 33890.377 | AJ5: 34892.283 | AK5: 35913.119
A6: x_cfor_2 | B6: 374.1272 | C6: 383.03443 | D6: 392.59543 | E6: 402.7843 | F6: 413.60973 | G6: 424.80938 | H6: 435.89146 | I6: 440.41118 | J6: 443.57714 | K6: 451.13683 | L6: 457.83734 | M6: 464.51663 | N6: 471.35807 | O6: 478.20034 | P6: 486.10253 | Q6: 495.08059 | R6: 504.76862 | S6: 514.62098 | T6: 524.48654 | U6: 534.46792 | V6: 545.06767 | W6: 556.91147 | X6: 570.61549 | Y6: 586.36171 | Z6: 603.81339 | AA6: 622.38985 | AB6: 641.20057 | AC6: 660.20342 | AD6: 679.32033 | AE6: 698.67977 | AF6: 718.68089 | AG6: 739.84219 | AH6: 762.40748 | AI6: 786.09529 | AJ6: 810.2532 | AK6: 834.1561
A7: x_cfor_0 | B7: 374.1272 | C7: 383.03443 | D7: 392.59543 | E7: 402.7843 | F7: 413.60973 | G7: 424.80938 | H7: 435.54698 | I7: 445.24283 | J7: 453.78537 | K7: 461.54918 | L7: 469.15704 | M7: 477.17334 | N7: 485.50202 | O7: 493.2957 | P7: 501.19187 | Q7: 509.46419 | R7: 518.53622 | S7: 528.70454 | T7: 540.04346 | U7: 552.35523 | V7: 565.41553 | W7: 579.00362 | X7: 593.16427 | Y7: 608.03219 | Z7: 623.75744 | AA7: 640.60506 | AB7: 658.79235 | AC7: 678.49866 | AD7: 699.53848 | AE7: 721.29759 | AF7: 743.20063 | AG7: 765.04253 | AH7: 786.93762 | AI7: 809.10183 | AJ7: 831.6912 | AK7: 854.70598
A8: x_cfoo_2 | B8: 45266.685 | C8: 46330.649 | D8: 47423.04 | E8: 48549.16 | F8: 49718.616 | G8: 50923.949 | H8: 52138.843 | I8: 52582.328 | J8: 52924.573 | K8: 53753.584 | L8: 54450.794 | M8: 55075.85 | N8: 55646.053 | O8: 56158.465 | P8: 56758.361 | Q8: 57483.681 | R8: 58332.46 | S8: 59256.323 | T8: 60245.548 | U8: 61300.473 | V8: 62452.919 | W8: 63746.147 | X8: 65231.842 | Y8: 66930.845 | Z8: 68823.365 | AA8: 70872.907 | AB8: 72956.91 | AC8: 75125.291 | AD8: 77360.583 | AE8: 79647.582 | AF8: 81993.596 | AG8: 84427.183 | AH8: 86967.365 | AI8: 89598.814 | AJ8: 92276.753 | AK8: 94944.692
A9: x_cfoo_0 | B9: 45266.685 | C9: 46330.649 | D9: 47423.04 | E9: 48549.16 | F9: 49718.616 | G9: 50923.949 | H9: 52112.599 | I9: 53240.782 | J9: 54292.205 | K9: 55285.063 | L9: 56260.077 | M9: 57257.901 | N9: 58253.948 | O9: 59147.657 | P9: 60028.358 | Q9: 60948.425 | R9: 61962.698 | S9: 63113.278 | T9: 64419.389 | U9: 65870.865 | V9: 67454.376 | W9: 69151.96 | X9: 70968.159 | Y9: 72908.705 | Z9: 74976.059 | AA9: 77187.936 | AB9: 79563.675 | AC9: 82127.807 | AD9: 84867.965 | AE9: 87719.169 | AF9: 90613.026 | AG9: 93515.732 | AH9: 96425.623 | AI9: 99353.437 | AJ9: 102308.54 | AK9: 105289.66
A10: x_cveh_2 | B10: 111187.03 | C10: 113831.37 | D10: 116551 | E10: 119368.07 | F10: 122297.3 | G10: 125316.63 | H10: 128367.14 | I10: 129899 | J10: 131287.03 | K10: 134290.5 | L10: 136976.14 | M10: 139452.2 | N10: 141727.58 | O10: 143757.05 | P10: 145969.31 | Q10: 148490.45 | R10: 150968.35 | S10: 153635.9 | T10: 156488.3 | U10: 159538.24 | V10: 162868.48 | W10: 166577.92 | X10: 170785.23 | Y10: 175535.86 | Z10: 180779.38 | AA10: 186436.82 | AB10: 192573.46 | AC10: 198989.47 | AD10: 205655.33 | AE10: 212525.05 | AF10: 219594.51 | AG10: 226905.09 | AH10: 234474.36 | AI10: 242245.95 | AJ10: 250101.13 | AK10: 257900.94
A11: x_cveh_0 | B11: 111187.03 | C11: 113831.37 | D11: 116551 | E11: 119368.07 | F11: 122297.3 | G11: 125316.63 | H11: 128316.87 | I11: 131212.87 | J11: 133979.53 | K11: 136661.27 | L11: 139344.57 | M11: 142110.16 | N11: 144877.93 | O11: 147383.47 | P11: 149839.8 | Q11: 152375.2 | R11: 155116 | S11: 158161 | T11: 161558.75 | U11: 165291.67 | V11: 169340.35 | W11: 173676.49 | X11: 178325.88 | Y11: 183311 | Z11: 188638.39 | AA11: 194347.71 | AB11: 200481.69 | AC11: 207099.56 | AD11: 214173.64 | AE11: 221549.74 | AF11: 229066.33 | AG11: 236645.02 | AH11: 244281.4 | AI11: 251995.7 | AJ11: 259801.06 | AK11: 267683.84
A12: x_cgla_2 | B12: 5205.4847 | C12: 5314.2639 | D12: 5419.3546 | E12: 5521.5934 | F12: 5630.2929 | G12: 5747.9847 | H12: 5872.2816 | I12: 5888.9434 | J12: 5883.2053 | K12: 5913.6596 | L12: 5925.2559 | M12: 5932.4503 | N12: 5938.2536 | O12: 5942.6598 | P12: 5958.4224 | Q12: 5988.0512 | R12: 6042.1964 | S12: 6101.2378 | T12: 6164.4073 | U12: 6231.871 | V12: 6306.6599 | W12: 6392.9629 | X12: 6495.7788 | Y12: 6616.8599 | Z12: 6754.326 | AA12: 6905.0914 | AB12: 7056.6098 | AC12: 7217.7049 | AD12: 7386.0247 | AE12: 7558.3549 | AF12: 7733.4523 | AG12: 7913.1957 | AH12: 8099.7878 | AI12: 8292.4933 | AJ12: 8488.0887 | AK12: 8682.0335
... A55: x_cote_0 | B55: 3756.2823 | C55: 3850.1893 | D55: 3946.4441 | E55: 4045.1052 | F55: 4146.2328 | G55: 4249.8886 | H55: 4356.1358 | I55: 4465.0392 | J55: 4576.6652 | K55: 4691.0819 | L55: 4808.3589 | M55: 4928.5679 | N55: 5046.9409 | O55: 5153.074 | P55: 5254.1739 | Q55: 5355.6199 | R55: 5461.6808 | S55: 5576.1005 | T55: 5701.3721 | U55: 5838.2997 | V55: 5988.1004 | W55: 6151.6507 | X55: 6331.0422 | Y55: 6527.163 | Z55: 6739.2829 | AA55: 6967.6224 | AB55: 7213.0106 | AC55: 7477.9745 | AD55: 7762.982 | AE55: 8064.4734 | AF55: 8377.8015 | AG55: 8699.8993 | AH55: 9029.0744 | AI55: 9363.8817 | AJ55: 9702.7829 | AK55: 10043.989

Sheet Import
A1: _date_ | B1: 42005 | C1: 42370 | D1: 42736 | E1: 43101 | F1: 43466 | G1: 43831 | H1: 44197 | I1: 44562 | J1: 44927 | K1: 45292 | L1: 45658 | M1: 46023 | N1: 46388 | O1: 46753 | P1: 47119 | Q1: 47484 | R1: 47849 | S1: 48214 | T1: 48580 | U1: 48945 | V1: 49310 | W1: 49675 | X1: 50041 | Y1: 50406 | Z1: 50771 | AA1: 51136 | AB1: 51502 | AC1: 51867 | AD1: 52232 | AE1: 52597 | AF1: 52963 | AG1: 53328 | AH1: 53693 | AI1: 54058 | AJ1: 54424 | AK1: 54789
A2: m_2 | B2: 663562.85 | C2: 676353.27 | D2: 692053.41 | E2: 708531.73 | F2: 724767.31 | G2: 740386.17 | H2: 755073.21 | I2: 763354.82 | J2: 770526.01 | K2: 781575.84 | L2: 794961.3 | M2: 810910.78 | N2: 828719.24 | O2: 847043 | P2: 865370.4 | Q2: 883221.07 | R2: 900264.59 | S2: 916406.77 | T2: 932177.49 | U2: 948390.91 | V2: 965910.9 | W2: 985313.36 | X2: 1006824.3 | Y2: 1030253.5 | Z2: 1055009.6 | AA2: 1080470.2 | AB2: 1106192 | AC2: 1132291.4 | AD2: 1159575.8 | AE2: 1188968.6 | AF2: 1221021 | AG2: 1255653.2 | AH2: 1292182.3 | AI2: 1329618.8 | AJ2: 1366978.5 | AK2: 1403558.9
A3: m_0 | B3: 663562.85 | C3: 676353.27 | D3: 692053.41 | E3: 708531.73 | F3: 724767.31 | G3: 740386.17 | H3: 754229.69 | I3: 766921.99 | J3: 779329.36 | K3: 792303.99 | L3: 806400.2 | M3: 821840.47 | N3: 838252.36 | O3: 854658.85 | P3: 870836.41 | Q3: 886688.63 | R3: 902860.37 | S3: 919606.64 | T3: 936923.85 | U3: 954722.99 | V3: 972992.65 | W3: 991862.9 | X3: 1011704.5 | Y3: 1032955.7 | Z3: 1055916.2 | AA3: 1080762.7 | AB3: 1107497 | AC3: 1136054.5 | AD3: 1166245.4 | AE3: 1197812.2 | AF3: 1230574.4 | AG3: 1264533.9 | AH3: 1299778.1 | AI3: 1336307.5 | AJ3: 1373950.4 | AK3: 1412373.5
A4: m_cagr_2 | B4: 12976.62 | C4: 13416.446 | D4: 13911.052 | E4: 14482.082 | F4: 15052.528 | G4: 15593.451 | H4: 16091.973 | I4: 16505.41 | J4: 16871.661 | K4: 17284.689 | L4: 17764.743 | M4: 18320.484 | N4: 18955.193 | O4: 19628.33 | P4: 20298.351 | Q4: 20932.545 | R4: 21517.924 | S4: 22048.183 | T4: 22546.321 | U4: 23044.809 | V4: 23572.621 | W4: 24144.524 | X4: 24760.774 | Y4: 25410.983 | Z4: 26076.976 | AA4: 26743.554 | AB4: 27399.433 | AC4: 28055.515 | AD4: 28744.66 | AE4: 29502.278 | AF4: 30346.064 | AG4: 31265.941 | AH4: 32230.611 | AI4: 33204.707 | AJ4: 34160.906 | AK4: 35088.837
A5: m_cagr_0 | B5: 12976.62 | C5: 13416.446 | D5: 13911.052 | E5: 14482.082 | F5: 15052.528 | G5: 15593.451 | H5: 16081.408 | I5: 16522.967 | J5: 16945.944 | K5: 17380.192 | L5: 17845.284 | M5: 18348.093 | N5: 18880.014 | O5: 19419.182 | P5: 19948.531 | Q5: 20456.277 | R5: 20952.282 | S5: 21444.038 | T5: 21932.981 | U5: 22418.279 | V5: 22901.807 | W5: 23390.927 | X5: 23899.405 | Y5: 24442.795 | Z5: 25031.521 | AA5: 25669.328 | AB5: 26352.906 | AC5: 27076.272 | AD5: 27832.88 | AE5: 28620.502 | AF5: 29441.051 | AG5: 30299.43 | AH5: 31199.376 | AI5: 32138.839 | AJ5: 33108.846 | AK5: 34095.703
A6: m_cfor_2 | B6: 212.32328 | C6: 203.11362 | D6: 195.91847 | E6: 190.26107 | F6: 186.04786 | G6: 183.12429 | H6: 181.35982 | I6: 179.44611 | J6: 178.38328 | K6: 179.03118 | L6: 180.4375 | M6: 182.30186 | N6: 184.27275 | O6: 186.13314 | P6: 188.02987 | Q6: 190.09593 | R6: 192.30047 | S6: 194.79263 | T6: 197.65641 | U6: 200.91757 | V6: 204.58656 | W6: 208.66302 | X6: 213.15987 | Y6: 218.07199 | Z6: 223.36714 | AA6: 229.03154 | AB6: 235.06465 | AC6: 241.56336 | AD6: 248.57664 | AE6: 256.06709 | AF6: 263.9428 | AG6: 272.11822 | AH6: 280.53037 | AI6: 289.12157 | AJ6: 297.84086 | AK6: 306.65201
A7: m_cfor_0 | B7: 212.32328 | C7: 203.11362 | D7: 195.91847 | E7: 190.26107 | F7: 186.04786 | G7: 183.12429 | H7: 181.37375 | I7: 180.66343 | J7: 180.85084 | K7: 181.7852 | L7: 183.31829 | M7: 185.32612 | N7: 187.63436 | O7: 189.98694 | P7: 192.39575 | Q7: 194.92244 | R7: 197.62447 | S7: 200.58217 | T7: 203.85143 | U7: 207.45601 | V7: 211.42191 | W7: 215.77369 | X7: 220.55159 | Y7: 225.77547 | Z7: 231.42772 | AA7: 237.49514 | AB7: 243.97476 | AC7: 250.89527 | AD7: 258.26888 | AE7: 266.05002 | AF7: 274.16059 | AG7: 282.53299 | AH7: 291.11564 | AI7: 299.86094 | AJ7: 308.72102 | AK7: 317.64688
A8: m_cfoo_2 | B8: 38715.482 | C8: 38700.694 | D8: 39053.612 | E8: 39759.438 | F8: 40602.85 | G8: 41488.672 | H8: 42360.49 | I8: 43084.095 | J8: 43739.489 | K8: 44564.058 | L8: 45587.149 | M8: 46830.89 | N8: 48298.444 | O8: 49891.141 | P8: 51508.893 | Q8: 53063.648 | R8: 54512.183 | S8: 55829.988 | T8: 57063.063 | U8: 58287.14 | V8: 59577.117 | W8: 60978.152 | X8: 62499.151 | Y8: 64116.283 | Z8: 65780.249 | AA8: 67444.212 | AB8: 69072.669 | AC8: 70690.761 | AD8: 72375.507 | AE8: 74217.749 | AF8: 76271.898 | AG8: 78528.26 | AH8: 80921.142 | AI8: 83363.627 | AJ8: 85780.762 | AK8: 88136.596
A9: m_cfoo_0 | B9: 38715.482 | C9: 38700.694 | D9: 39053.612 | E9: 39759.438 | F9: 40602.85 | G9: 41488.672 | H9: 42331.023 | I9: 43121.305 | J9: 43910.597 | K9: 44764.141 | L9: 45728.177 | M9: 46819.578 | N9: 48015.081 | O9: 49255.429 | P9: 50497.141 | Q9: 51706.262 | R9: 52902.684 | S9: 54102.232 | T9: 55305.046 | U9: 56504.154 | V9: 57698.778 | W9: 58902.232 | X9: 60146.319 | Y9: 61470.007 | Z9: 62901.989 | AA9: 64455.743 | AB9: 66126.554 | AC9: 67901.028 | AD9: 69761.097 | AE9: 71696.574 | AF9: 73708.769 | AG9: 75809.929 | AH9: 78012.718 | AI9: 80317.08 | AJ9: 82705.417 | AK9: 85146.407
A10: m_cveh_2 | B10: 81984.742 | C10: 85343.897 | D10: 89291.6 | E10: 92792.086 | F10: 95880.614 | G10: 98437.143 | H10: 100369.25 | I10: 100564.4 | J10: 100822.09 | K10: 102143.3 | L10: 104140.01 | M10: 106845.11 | N10: 109664.34 | O10: 112120.31 | P10: 114100.6 | Q10: 115640.37 | R10: 116857.29 | S10: 117867.83 | T10: 118842.84 | U10: 119961.82 | V10: 121369.7 | W10: 123130.73 | X10: 125232.91 | Y10: 127598.53 | Z10: 130104.73 | AA10: 132646.74 | AB10: 135199.73 | AC10: 137786.36 | AD10: 140557.35 | AE10: 143671.25 | AF10: 147196.75 | AG10: 151076.33 | AH10: 155152.54 | AI10: 159242.24 | AJ10: 163206.31 | AK10: 166994.25
A11: m_cveh_0 | B11: 81984.742 | C11: 85343.897 | D11: 89291.6 | E11: 92792.086 | F11: 95880.614 | G11: 98437.143 | H11: 99954.404 | I11: 101032.43 | J11: 102081.7 | K11: 103347.21 | L11: 104896 | M11: 106680.23 | N11: 108548.57 | O11: 110280.06 | P11: 111807.13 | Q11: 113127.76 | R11: 114698.67 | S11: 116305.86 | T11: 117866.96 | U11: 119378.33 | V11: 120879.06 | W11: 122430.93 | X11: 124120.78 | Y11: 126028.79 | Z11: 128196.46 | AA11: 130633.52 | AB11: 133317.27 | AC11: 136216.7 | AD11: 139290.2 | AE11: 142496.18 | AF11: 145813.32 | AG11: 149249.41 | AH11: 152820.17 | AI11: 156521.03 | AJ11: 160317.64 | AK11: 164154.3
A12: m_cgla_2 | B12: 6982.6807 | C12: 7254.524 | D12: 7570.3071 | E12: 7822.5186 | F12: 8014.2634 | G12: 8173.0776 | H12: 8314.184 | I12: 8418.3838 | J12: 8523.8827 | K12: 8681.7374 | L12: 8889.016 | M12: 9141.6701 | N12: 9427.7885 | O12: 9731.8141 | P12: 10043.094 | Q12: 10350.108 | R12: 10648.464 | S12: 10934.021 | T12: 11209.732 | U12: 11485.621 | V12: 11776.073 | W12: 12093.306 | X12: 12443.292 | Y12: 12823.567 | Z12: 13222.637 | AA12: 13625.787 | AB12: 14018.476 | AC12: 14398.206 | AD12: 14778.269 | AE12: 15180.128 | AF12: 15622.907 | AG12: 16114.478 | AH12: 16648.432 | AI12: 17208.634 | AJ12: 17776.112 | AK12: 18337.528
... A55: m_cote_0 | B55: 2416.4373 | C55: 2623.8173 | D55: 2786.1625 | E55: 2914.5229 | F55: 3026.0223 | G55: 3129.4035 | H55: 3237.4038 | I55: 3347.2903 | J55: 3451.1002 | K55: 3540.653 | L55: 3610.8103 | M55: 3660.8945 | N55: 3692.944 | O55: 3709.2983 | P55: 3718.5969 | Q55: 3728.9424 | R55: 3730.8869 | S55: 3737.8347 | T55: 3754.7768 | U55: 3784.7534 | V55: 3829.5782 | W55: 3889.1633 | X55: 3961.6522 | Y55: 4043.6567 | Z55: 4131.6767 | AA55: 4223.7663 | AB55: 4320.3683 | AC55: 4424.1231 | AD55: 4537.7771 | AE55: 4661.3161 | AF55: 4791.6924 | AG55: 4924.072 | AH55: 5053.7006 | AI55: 5177.5546 | AJ55: 5295.1044 | AK55: 5407.8464

Sheet Carbontax
A1: _date_ | B1: 42005 | C1: 42370 | D1: 42736 | E1: 43101 | F1: 43466 | G1: 43831 | H1: 44197 | I1: 44562 | J1: 44927 | K1: 45292 | L1: 45658 | M1: 46023 | N1: 46388 | O1: 46753 | P1: 47119 | Q1: 47484 | R1: 47849 | S1: 48214 | T1: 48580 | U1: 48945 | V1: 49310 | W1: 49675 | X1: 50041 | Y1: 50406 | Z1: 50771 | AA1: 51136 | AB1: 51502 | AC1: 51867 | AD1: 52232 | AE1: 52597 | AF1: 52963 | AG1: 53328 | AH1: 53693 | AI1: 54058 | AJ1: 54424 | AK1: 54789
A2: t2val_ch_0 | B2: 1672.0229 | C2: 2522.4473 | D2: 3467.3396 | E2: 5025.2893 | F2: 4989.5769 | G2: 4957.9556 | H2: 4916.4945 | I2: 4816.7927 | J2: 4857.0977 | K2: 4891.386 | L2: 4903.6546 | M2: 4883.2646 | N2: 4826.6627 | O2: 4737.9595 | P2: 4626.0165 | Q2: 4502.2019 | R2: 4381.7028 | S2: 4258.3475 | T2: 4139.0071 | U2: 4028.1189 | V2: 3929.7878 | W2: 3846.7624 | X2: 3779.3423 | Y2: 3725.4331 | Z2: 3681.6018 | AA2: 3644.9574 | AB2: 3614.1768 | AC2: 3590.0664 | AD2: 3574.8851 | AE2: 3570.8578 | AF2: 3578.2693 | AG2: 3595.3533 | AH2: 3618.9144 | AI2: 3645.6984 | AJ2: 3673.5554 | AK2: 3701.8444
A3: t2val_ch_2 | B3: 1672.0229 | C3: 2522.4473 | D3: 3467.3396 | E3: 5025.2893 | F3: 4989.5769 | G3: 4957.9556 | H3: 4924.3047 | I3: 10679.996 | J3: 14316.36 | K3: 17780.573 | L3: 20947.014 | M3: 21559.266 | N3: 21790.436 | O3: 21705.64 | P3: 21396.481 | Q3: 20961.563 | R3: 21395.742 | S3: 21715.565 | T3: 21965.779 | U3: 22148.008 | V3: 22236.586 | W3: 22199.482 | X3: 22022.43 | Y3: 21716.378 | Z3: 21314.875 | AA3: 20867.53 | AB3: 20419.11 | AC3: 20001.327 | AD3: 19609.679 | AE3: 19195.118 | AF3: 18696.1 | AG3: 18070.238 | AH3: 17311.036 | AI3: 16438.679 | AJ3: 15476.69 | AK3: 14436.609
A4: t2val_sec_0 | B4: 3418.5604 | C4: 5212.8645 | D4: 7264.1581 | E4: 10659.357 | F4: 10717.045 | G4: 10805.091 | H4: 10920.64 | I4: 10951.489 | J4: 11339.972 | K4: 11756.444 | L4: 12162.068 | M4: 12531.617 | N4: 12851.505 | O4: 13117.271 | P4: 13349.923 | Q4: 13577.128 | R4: 13817.975 | S4: 14061.807 | T4: 14331.759 | U4: 14644.76 | V4: 15018.637 | W4: 15466.674 | X4: 15993.545 | Y4: 16592.599 | Z4: 17249.735 | AA4: 17954.698 | AB4: 18707.311 | AC4: 19522.096 | AD4: 20421.342 | AE4: 21422.108 | AF4: 22524.731 | AG4: 23713.952 | AH4: 24964.295 | AI4: 26250.453 | AJ4: 27557.044 | AK4: 28882.1
A5: t2val_sec_2 | B5: 3418.5604 | C5: 5212.8645 | D5: 7264.1581 | E5: 10659.357 | F5: 10717.045 | G5: 10805.091 | H5: 10926.716 | I5: 24416.273 | J5: 33819.661 | K5: 43738.441 | L5: 53936.124 | M5: 58404.374 | N5: 62357.131 | O5: 65807.803 | P5: 68932.358 | Q5: 71946.579 | R5: 78432.354 | S5: 85128.657 | T5: 92137.465 | U5: 99403.288 | V5: 106755.98 | W5: 113998 | X5: 121032.59 | Y5: 127905.4 | Z5: 134792.61 | AA5: 141986.69 | AB5: 149801.89 | AC5: 158527.46 | AD5: 168166.58 | AE5: 178300.5 | AF5: 188328.61 | AG5: 197799.65 | AH5: 206620.18 | AI5: 214979.47 | AJ5: 223118.45 | AK5: 231148.95
A6: t2val_ci_0 | B6: 2666.2635 | C6: 4049.2226 | D6: 5615.3361 | E6: 8202.0515 | F6: 8218.4861 | G6: 8266.8185 | H6: 8344.9529 | I6: 8365.8445 | J6: 8663.0201 | K6: 8979.9156 | L6: 9282.8991 | M6: 9550.665 | N6: 9773.3029 | O6: 9949.7639 | P6: 10098.926 | Q6: 10244.724 | R6: 10403.407 | S6: 10567.255 | T6: 10754.836 | U6: 10980.393 | V6: 11258.599 | W6: 11599.741 | X6: 12006.267 | Y6: 12470.964 | Z6: 12980.805 | AA6: 13526.362 | AB6: 14107.328 | AC6: 14736.066 | AD6: 15431.609 | AE6: 16208.219 | AF6: 17065.654 | AG6: 17989.953 | AH6: 18958.522 | AI6: 19949.438 | AJ6: 20949.904 | AK6: 21959.079
A7: t2val_ci_2 | B7: 2666.2635 | C7: 4049.2226 | D7: 5615.3361 | E7: 8202.0515 | F7: 8218.4861 | G7: 8266.8185 | H7: 8349.1077 | I7: 18477.306 | J7: 25337.42 | K7: 32413.767 | L7: 39486.938 | M7: 42192.787 | N7: 44396.646 | O7: 46130.534 | P7: 47553.462 | Q7: 48848.766 | R7: 52409.498 | S7: 56008.52 | T7: 59706.02 | U7: 63431.569 | V7: 67027.357 | W7: 70326.512 | X7: 73250.402 | Y7: 75835.558 | Z7: 78218.289 | AA7: 80601.501 | AB7: 83183.687 | AC7: 86088.981 | AD7: 89206.507 | AE7: 92146.997 | AF7: 94435.772 | AG7: 95744.716 | AH7: 96004.074 | AI7: 95309.39 | AJ7: 93745.339 | AK7: 91250.706
A8: t2val_y_0 | B8: 39.83797 | C8: 59.908039 | D8: 83.025417 | E8: 122.42371 | F8: 124.03777 | G8: 125.96318 | H8: 127.82913 | I8: 128.27261 | J8: 132.74167 | K8: 137.72028 | L8: 143.0496 | M8: 148.58237 | N8: 154.12632 | O8: 159.46306 | P8: 164.59308 | Q8: 169.58953 | R8: 174.74388 | S8: 179.75661 | T8: 184.81858 | U8: 190.03893 | V8: 195.56625 | W8: 201.56806 | X8: 208.2074 | Y8: 215.58322 | Z8: 223.70434 | AA8: 232.56318 | AB8: 242.16022 | AC8: 252.57346 | AD8: 263.92651 | AE8: 276.34976 | AF8: 289.89793 | AG8: 304.55717 | AH8: 320.23396 | AI8: 336.78026 | AJ8: 354.04698 | AK8: 371.92511
A9: t2val_y_2 | B9: 39.83797 | C9: 59.908039 | D9: 83.025417 | E9: 122.42371 | F9: 124.03777 | G9: 125.96318 | H9: 127.96261 | I9: 291.85421 | J9: 412.19863 | K9: 545.23662 | L9: 691.40649 | M9: 774.01454 | N9: 859.27863 | O9: 946.25633 | P9: 1034.893 | Q9: 1125.5001 | R9: 1273.9153 | S9: 1430.0367 | T9: 1596.0857 | U9: 1773.7644 | V9: 1963.9554 | W9: 2166.5049 | X9: 2381.2525 | Y9: 2608.5289 | Z9: 2849.2707 | AA9: 3106.4594 | AB9: 3384.0707 | AC9: 3690.1439 | AD9: 4032.3416 | AE9: 4412.9005 | AF9: 4829.2021 | AG9: 5276.612 | AH9: 5752.4649 | AI9: 6257.9886 | AJ9: 6797.0613 | AK9: 7375.5755
A10: t2val_mat_0 | B10: 712.45889 | C10: 1103.7338 | D10: 1565.7966 | E10: 2334.8818 | F10: 2374.5216 | G10: 2412.3094 | H10: 2447.8581 | I10: 2457.3721 | J10: 2544.2098 | K10: 2638.8081 | L10: 2736.1194 | M10: 2832.3692 | N10: 2924.0755 | O10: 3008.0439 | P10: 3086.4036 | Q10: 3162.8146 | R10: 3239.8242 | S10: 3314.7963 | T10: 3392.1044 | U10: 3474.3273 | V10: 3564.4722 | W10: 3665.3648 | X10: 3779.0708 | Y10: 3906.0517 | Z10: 4045.2254 | AA10: 4195.7735 | AB10: 4357.8226 | AC10: 4533.4562 | AD10: 4725.8066 | AE10: 4937.5396 | AF10: 5169.1788 | AG10: 5419.4415 | AH10: 5685.5392 | AI10: 5964.2354 | AJ10: 6253.0928 | AK10: 6551.095
A11: t2val_mat_2 | B11: 712.45889 | C11: 1103.7338 | D11: 1565.7966 | E11: 2334.8818 | F11: 2374.5216 | G11: 2412.3094 | H11: 2449.6454 | I11: 5647.1133 | J11: 8070.0417 | K11: 10779.438 | L11: 13757.779 | M11: 15437.572 | N11: 17101.207 | O11: 18731.013 | P11: 20344.003 | Q11: 21972.312 | R11: 24748.94 | S11: 27690.101 | T11: 30835.359 | U11: 34197.954 | V11: 37764.666 | W11: 41504.982 | X11: 45400.93 | Y11: 49461.314 | Z11: 53725.046 | AA11: 58278.73 | AB11: 63234.132 | AC11: 68748.338 | AD11: 74927.727 | AE11: 81740.607 | AF11: 89063.634 | AG11: 96778.327 | AH11: 104863.64 | AI11: 113412.09 | AJ11: 122576.05 | AK11: 132522.67

Sheet Production
A1: _date_ | B1: 42005 | C1: 42370 | D1: 42736 | E1: 43101 | F1: 43466 | G1: 43831 | H1: 44197 | I1: 44562 | J1: 44927 | K1: 45292 | L1: 45658 | M1: 46023 | N1: 46388 | O1: 46753 | P1: 47119 | Q1: 47484 | R1: 47849 | S1: 48214 | T1: 48580 | U1: 48945 | V1: 49310 | W1: 49675 | X1: 50041 | Y1: 50406 | Z1: 50771 | AA1: 51136 | AB1: 51502 | AC1: 51867 | AD1: 52232 | AE1: 52597 | AF1: 52963 | AG1: 53328 | AH1: 53693 | AI1: 54058 | AJ1: 54424 | AK1: 54789
A2: y_2 | B2: 3862067 | C2: 3904759.4 | D2: 3966686.3 | E2: 4034936.1 | F2: 4105156.5 | G2: 4176446.6 | H2: 4246260.1 | I2: 4288914.7 | J2: 4320825.3 | K2: 4368704.5 | L2: 4426263.4 | M2: 4497850.2 | N2: 4583461.7 | O2: 4678390.5 | P2: 4779964.3 | Q2: 4883365.4 | R2: 4983107.8 | S2: 5076583.5 | T2: 5164571.7 | U2: 5251195.2 | V2: 5342525.4 | W2: 5443871.8 | X2: 5558208.1 | Y2: 5684891.4 | Z2: 5819666.2 | AA2: 5956795.9 | AB2: 6091257.1 | AC2: 6221717.5 | AD2: 6351840.1 | AE2: 6488046.9 | AF2: 6636356.2 | AG2: 6799621 | AH2: 6976135.1 | AI2: 7160473.1 | AJ2: 7345993.5 | AK2: 7527752
A3: y_0 | B3: 3862067 | C3: 3904759.4 | D3: 3966686.3 | E3: 4034936.1 | F3: 4105156.5 | G3: 4176446.6 | H3: 4242272.2 | I3: 4300967.5 | J3: 4355265.6 | K3: 4410518.5 | L3: 4471966.3 | M3: 4542908.7 | N3: 4622734.6 | O3: 4706868.8 | P3: 4793917.7 | Q3: 4882063.9 | R3: 4973390.7 | S3: 5069593.8 | T3: 5170312.1 | U3: 5273836.5 | V3: 5378459.2 | W3: 5483379.9 | X3: 5589789.5 | Y3: 5700135.5 | Z3: 5816894.6 | AA3: 5942027.8 | AB3: 6076132.6 | AC3: 6218637.3 | AD3: 6367605.9 | AE3: 6520496.2 | AF3: 6675832.3 | AG3: 6834044 | AH3: 6996728.7 | AI3: 7165292 | AJ3: 7340025 | AK3: 7519866.7
A4: y_sagr_2 | B4: 81700.733 | C4: 80785.703 | D4: 80589.843 | E4: 81146.049 | F4: 82136.107 | G4: 83357.704 | H4: 84645.528 | I4: 85321.957 | J4: 85684.211 | K4: 86361.314 | L4: 87222.523 | M4: 88413.381 | N4: 90001.934 | O4: 91879.686 | P4: 93960.418 | Q4: 96103.072 | R4: 98183.229 | S4: 100091.56 | T4: 101846.88 | U4: 103552.63 | V4: 105357.63 | W4: 107389.69 | X4: 109721.47 | Y4: 112341.88 | Z4: 115156.37 | AA4: 118036 | AB4: 120837.42 | AC4: 123548.83 | AD4: 126254.13 | AE4: 129102.99 | AF4: 132236.34 | AG4: 135718 | AH4: 139503.23 | AI4: 143461.56 | AJ4: 147435.15 | AK4: 151305.56
A5: y_sagr_0 | B5: 81700.733 | C5: 80785.703 | D5: 80589.843 | E5: 81146.049 | F5: 82136.107 | G5: 83357.704 | H5: 84558.415 | I5: 85628.631 | J5: 86604.022 | K5: 87603.424 | L5: 88752.211 | M5: 90130.028 | N5: 91719.708 | O5: 93406.635 | P5: 95155.315 | Q5: 96919.104 | R5: 98754.928 | S5: 100702.35 | T5: 102758.55 | U5: 104885.79 | V5: 107045.02 | W5: 109216.99 | X5: 111430.23 | Y5: 113743 | Z5: 116213.87 | AA5: 118888.79 | AB5: 121780.94 | AC5: 124877.31 | AD5: 128129.84 | AE5: 131474.18 | AF5: 134870.44 | AG5: 138325.44 | AH5: 141875.76 | AI5: 145553.07 | AJ5: 149361.32 | AK5: 153271.36
A6: y_sfor_2 | B6: 6530.3134 | C6: 6365.6895 | D6: 6238.3688 | E6: 6137.84 | F6: 6076.1501 | G6: 6044.3111 | H6: 6034.5438 | I6: 5968.6101 | J6: 5901.3911 | K6: 5859.8547 | L6: 5821.2231 | M6: 5794.9838 | N6: 5777.0099 | O6: 5766.5731 | P6: 5769.3378 | Q6: 5786.4739 | R6: 5807.9843 | S6: 5835.2313 | T6: 5867.0404 | U6: 5903.2879 | V6: 5946.1342 | W6: 5998.9667 | X6: 6065.2438 | Y6: 6146.1572 | Z6: 6239.9502 | AA6: 6343.0395 | AB6: 6451.5951 | AC6: 6563.9853 | AD6: 6679.5715 | AE6: 6799.0208 | AF6: 6924.4797 | AG6: 7058.9577 | AH6: 7204.1811 | AI6: 7358.7476 | AJ6: 7518.8906 | AK6: 7680.2954
A7: y_sfor_0 | B7: 6530.3134 | C7: 6365.6895 | D7: 6238.3688 | E7: 6137.84 | F7: 6076.1501 | G7: 6044.3111 | H7: 6032.7572 | I7: 6033.4531 | J7: 6041.7044 | K7: 6056.4537 | L7: 6078.751 | M7: 6110.1875 | N7: 6149.7228 | O7: 6192.5709 | P7: 6239.8525 | Q7: 6292.1619 | R7: 6350.6948 | S7: 6417.7263 | T7: 6493.9785 | U7: 6578.3844 | V7: 6669.3458 | W7: 6765.2731 | X7: 6865.9154 | Y7: 6971.8217 | Z7: 7083.8367 | AA7: 7203.3383 | AB7: 7331.4936 | AC7: 7469.1284 | AD7: 7615.3686 | AE7: 7767.1392 | AF7: 7921.2328 | AG7: 8076.1131 | AH7: 8231.979 | AI7: 8389.8157 | AJ7: 8550.4784 | AK7: 8714.0662
A8: y_sfoo_2 | B8: 157606.73 | C8: 156822 | D8: 157473.36 | E8: 159502.46 | F8: 162186.04 | G8: 165162.83 | H8: 168161.24 | I8: 170138.54 | J8: 171539.46 | K8: 173430.98 | L8: 175691.6 | M8: 178554.49 | N8: 182155.69 | O8: 186273.26 | P8: 190706.52 | Q8: 195186.07 | R8: 199507.56 | S8: 203480.83 | T8: 207164.2 | U8: 210764.01 | V8: 214554.71 | W8: 218759.82 | X8: 223496.13 | Y8: 228734.36 | Z8: 234302.73 | AA8: 239975.57 | AB8: 245493.39 | AC8: 250860.69 | AD8: 256249.39 | AE8: 261944.83 | AF8: 268195.82 | AG8: 275090.44 | AH8: 282516.2 | AI8: 290220.42 | AJ8: 297918.02 | AK8: 305407.8
A9: y_sfoo_0 | B9: 157606.73 | C9: 156822 | D9: 157473.36 | E9: 159502.46 | F9: 162186.04 | G9: 165162.83 | H9: 168002.15 | I9: 170546.2 | J9: 172899.57 | K9: 175296.94 | L9: 177967.26 | M9: 181047.73 | N9: 184503.54 | O9: 188131.38 | P9: 191850.71 | Q9: 195568.72 | R9: 199389.16 | S9: 203385.67 | T9: 207554.9 | U9: 211835.9 | V9: 216168.21 | W9: 220529.36 | X9: 224980.91 | Y9: 229635.09 | Z9: 234599.55 | AA9: 239952.17 | AB9: 245708.73 | AC9: 251838.84 | AD9: 258256.03 | AE9: 264855.3 | AF9: 271576.38 | AG9: 278435.78 | AH9: 285494.81 | AI9: 292799.56 | AJ9: 300344.35 | AK9: 308066.51
A10: y_sveh_2 | B10: 125562.3 | C10: 126911.73 | D10: 128913.4 | E10: 131133.36 | F10: 133535.59 | G10: 136005.43 | H10: 138408.29 | I10: 139084.62 | J10: 139653.44 | K10: 141778.99 | L10: 143928.58 | M10: 146228.44 | N10: 148508.08 | O10: 150585.16 | P10: 152732.14 | Q10: 155031.65 | R10: 157232.91 | S10: 159504.64 | T10: 161877.98 | U10: 164422.79 | V10: 167267.1 | W10: 170529.95 | X10: 174313.25 | Y10: 178629.06 | Z10: 183386.56 | AA10: 188464.1 | AB10: 193862.97 | AC10: 199416.27 | AD10: 205147.72 | AE10: 211097.5 | AF10: 217322.04 | AG10: 223865.95 | AH10: 230704.99 | AI10: 237730.36 | AJ10: 244787.5 | AK10: 251736.27
A11: y_sveh_0 | B11: 125562.3 | C11: 126911.73 | D11: 128913.4 | E11: 131133.36 | F11: 133535.59 | G11: 136005.43 | H11: 138201.6 | I11: 140222.66 | J11: 142171.29 | K11: 144168.29 | L11: 146316.01 | M11: 148670.31 | N11: 151125.57 | O11: 153408.09 | P11: 155642.25 | Q11: 157907 | R11: 160454.61 | S11: 163277.29 | T11: 166372.31 | U11: 169710.56 | V11: 173273.15 | W11: 177044.61 | X11: 181065.87 | Y11: 185383.54 | Z11: 190027.27 | AA11: 195040.69 | AB11: 200453.46 | AC11: 206295.4 | AD11: 212520.98 | AE11: 218988.4 | AF11: 225563.77 | AG11: 232194.85 | AH11: 238895.53 | AI11: 245694.58 | AJ11: 252603.07 | AK11: 259599.15
A12: y_sgla_2 | B12: 22075.609 | C12: 22960.239 | D12: 23926.007 | E12: 24600.446 | F12: 25064.546 | G12: 25442.145 | H12: 25787.554 | I12: 25889.365 | J12: 25889.673 | K12: 25964.918 | L12: 26101.985 | M12: 26347.498 | N12: 26688.313 | O12: 27100.206 | P12: 27569.414 | Q12: 28066.233 | R12: 28560.316 | S12: 29015.54 | T12: 29426.279 | U12: 29812.407 | V12: 30213.19 | W12: 30668.515 | X12: 31203.567 | Y12: 31817.291 | Z12: 32481.318 | AA12: 33153.861 | AB12: 33788.808 | AC12: 34378.904 | AD12: 34943.518 | AE12: 35525.152 | AF12: 36169.733 | AG12: 36906.53 | AH12: 37734.141 | AI12: 38621.974 | AJ12: 39526.13 | AK12: 40409.625
... A67: y_seot_0 | B67: 54.518525 | C67: 55.064713 | D67: 55.509473 | E67: 56.05587 | F67: 56.605373 | G67: 57.262791 | H67: 58.163175 | I67: 59.263851 | J67: 60.510344 | K67: 61.838549 | L67: 63.221722 | M67: 64.665049 | N67: 66.173852 | O67: 67.727354 | P67: 69.356366 | Q67: 71.075633 | R67: 72.807016 | S67: 74.575946 | T67: 76.403249 | U67: 78.303658 | V67: 80.285295 | W67: 82.340618 | X67: 84.452824 | Y67: 86.596693 | Z67: 88.751642 | AA67: 90.916991 | AB67: 93.113523 | AC67: 95.377863 | AD67: 97.734716 | AE67: 100.16867 | AF67: 102.63485 | AG67: 105.08173 | AH67: 107.4706 | AI67: 109.78593 | AJ67: 112.03569 | AK67: 114.24035

Sheet Capital
A1: _date_ | B1: 42005 | C1: 42370 | D1: 42736 | E1: 43101 | F1: 43466 | G1: 43831 | H1: 44197 | I1: 44562 | J1: 44927 | K1: 45292 | L1: 45658 | M1: 46023 | N1: 46388 | O1: 46753 | P1: 47119 | Q1: 47484 | R1: 47849 | S1: 48214 | T1: 48580 | U1: 48945 | V1: 49310 | W1: 49675 | X1: 50041 | Y1: 50406 | Z1: 50771 | AA1: 51136 | AB1: 51502 | AC1: 51867 | AD1: 52232 | AE1: 52597 | AF1: 52963 | AG1: 53328 | AH1: 53693 | AI1: 54058 | AJ1: 54424 | AK1: 54789
A2: f_k_2 | B2: 8840569 | C2: 8941012 | D2: 9043664.2 | E2: 9150399.9 | F2: 9262528.1 | G2: 9380418.9 | H2: 9503400.2 | I2: 9626346.9 | J2: 9746464.2 | K2: 9864717.1 | L2: 9983145.8 | M2: 10105077 | N2: 10234168 | O2: 10373412 | P2: 10524773 | Q2: 10688804 | R2: 10864488 | S2: 11049788 | T2: 11242655 | U2: 11441926 | V2: 11647782 | W2: 11861607 | X2: 12085419 | Y2: 12321077 | Z2: 12569418 | AA2: 12829842 | AB2: 13100434 | AC2: 13378896 | AD2: 13663890 | AE2: 13955803 | AF2: 14256649 | AG2: 14569266 | AH2: 14896201 | AI2: 15238823 | AJ2: 15596996 | AK2: 15969490
A3: f_k_0 | B3: 8840569 | C3: 8941012 | D3: 9043664.2 | E3: 9150399.9 | F3: 9262528.1 | G3: 9380418.9 | H3: 9502537 | I3: 9626950.2 | J3: 9752348.1 | K3: 9878634.2 | L3: 10006884 | M3: 10138963 | N3: 10276876 | O3: 10422093 | P3: 10575490 | Q3: 10737263 | R3: 10907949 | S3: 11088080 | T3: 11277894 | U3: 11477097 | V3: 11684865 | W3: 11900123 | X3: 12122021 | Y3: 12350302 | Z3: 12585358 | AA3: 12828070 | AB3: 13079458 | AC3: 13340348 | AD3: 13611134 | AE3: 13891814 | AF3: 14182274 | AG3: 14482656 | AH3: 14793563 | AI3: 15116001 | AJ3: 15451112 | AK3: 15799857
A4: f_k_sagr_2 | B4: 181347.23 | C4: 183282.38 | D4: 185117.57 | E4: 186941.91 | F4: 188822.34 | G4: 190794.4 | H4: 192862.35 | I4: 194946.78 | J4: 196989 | K4: 199017.72 | L4: 201085.57 | M4: 203268.76 | N4: 205658.71 | O4: 208332.07 | P4: 211338.8 | Q4: 214691.55 | R4: 218367.76 | S4: 222314.43 | T4: 226476.07 | U4: 230819.01 | V4: 235344.25 | W4: 240084.23 | X4: 245088.54 | Y4: 250403.34 | Z4: 256049.32 | AA4: 262010.69 | AB4: 268234.24 | AC4: 274656.76 | AD4: 281238.84 | AE4: 287985.07 | AF4: 294942.03 | AG4: 302176.65 | AH4: 309745.94 | AI4: 317673.21 | AJ4: 325939.37 | AK4: 334493.02
A5: f_k_sagr_0 | B5: 181347.23 | C5: 183282.38 | D5: 185117.57 | E5: 186941.91 | F5: 188822.34 | G5: 190794.4 | H5: 192848.46 | I5: 194954.96 | J5: 197092.69 | K5: 199265.45 | L5: 201503.96 | M5: 203857.74 | N5: 206378.98 | O5: 209105.05 | P5: 212058.19 | Q5: 215243.86 | R5: 218668.83 | S5: 222341.34 | T5: 226264.87 | U5: 230431.96 | V5: 234823.57 | W5: 239415.1 | X5: 244187.53 | Y5: 249136.41 | Z5: 254273.53 | AA5: 259623.24 | AB5: 265213.76 | AC5: 271068.81 | AD5: 277200.94 | AE5: 283611.33 | AF5: 290296.51 | AG5: 297258.17 | AH5: 304509.25 | AI5: 312072.76 | AJ5: 319974.96 | AK5: 328236.78
A6: f_k_sfor_2 | B6: 14496.423 | C6: 14640.969 | D6: 14762.436 | E6: 14862.972 | F6: 14947.093 | G6: 15018.897 | H6: 15081.248 | I6: 15128.209 | J6: 15157.982 | K6: 15173.521 | L6: 15177.406 | M6: 15173.149 | N6: 15164.02 | O6: 15152.654 | P6: 15141.408 | Q6: 15132.091 | R6: 15125.058 | S6: 15120.131 | T6: 15117.12 | U6: 15116.237 | V6: 15118.4 | W6: 15125.23 | X6: 15138.813 | Y6: 15161.22 | Z6: 15193.922 | AA6: 15237.489 | AB6: 15291.62 | AC6: 15355.728 | AD6: 15429.589 | AE6: 15513.697 | AF6: 15609.277 | AG6: 15718.031 | AH6: 15841.665 | AI6: 15981.345 | AJ6: 16137.384 | AK6: 16309.305
A7: f_k_sfor_0 | B7: 14496.423 | C7: 14640.969 | D7: 14762.436 | E7: 14862.972 | F7: 14947.093 | G7: 15018.897 | H7: 15080.6 | I7: 15133.506 | J7: 15178.764 | K7: 15217.888 | L7: 15252.891 | M7: 15286.154 | N7: 15319.956 | O7: 15355.862 | P7: 15395.007 | Q7: 15438.14 | R7: 15486.241 | S7: 15540.365 | T7: 15601.447 | U7: 15670.061 | V7: 15746.379 | W7: 15830.318 | X7: 15921.86 | Y7: 16021.293 | Z7: 16129.259 | AA7: 16246.712 | AB7: 16374.742 | AC7: 16514.411 | AD7: 16666.54 | AE7: 16831.579 | AF7: 17009.677 | AG7: 17200.94 | AH7: 17405.643 | AI7: 17624.286 | AJ7: 17857.495 | AK7: 18105.833
A8: f_k_sfoo_2 | B8: 75628.285 | C8: 76442.345 | D8: 77236.937 | E8: 78063.884 | F8: 78954.822 | G8: 79921.685 | H8: 80957.735 | I8: 82017.738 | J8: 83069.032 | K8: 84126.545 | L8: 85221.893 | M8: 86398.476 | N8: 87706.606 | O8: 89185.155 | P8: 90854.324 | Q8: 92711.446 | R8: 94737.394 | S8: 96896.819 | T8: 99155.001 | U8: 101491.65 | V8: 103907.23 | W8: 106419.56 | X8: 109054.33 | Y8: 111833.19 | Z8: 114761.81 | AA8: 117825 | AB8: 120986.99 | AC8: 124208.83 | AD8: 127468.56 | AE8: 130772.24 | AF8: 134150.33 | AG8: 137642.49 | AH8: 141279.07 | AI8: 145068.65 | AJ8: 148995.57 | AK8: 153028.56
A9: f_k_sfoo_0 | B9: 75628.285 | C9: 76442.345 | D9: 77236.937 | E9: 78063.884 | F9: 78954.822 | G9: 79921.685 | H9: 80949.573 | I9: 82015.573 | J9: 83104.847 | K9: 84218.802 | L9: 85374.454 | M9: 86598.537 | N9: 87917.992 | O9: 89350.506 | P9: 90904.071 | Q9: 92576.542 | R9: 94367.736 | S9: 96277.566 | T9: 98302.974 | U9: 100435.05 | V9: 102659.27 | W9: 104959.26 | X9: 107323.03 | Y9: 109747.7 | Z9: 112239.81 | AA9: 114812.47 | AB9: 117480.07 | AC9: 120253.53 | AD9: 123137.15 | AE9: 126129.48 | AF9: 129227.62 | AG9: 132432.4 | AH9: 135751.04 | AI9: 139195.6 | AJ9: 142778.78 | AK9: 146509.14
A10: f_k_sveh_2 | B10: 124562 | C10: 125994.3 | D10: 127497.58 | E10: 129102.87 | F10: 130828.42 | G10: 132676.53 | H10: 134631.04 | I10: 136534.3 | J10: 138329.43 | K10: 140129.56 | L10: 141981.72 | M10: 143922.02 | N10: 145967.52 | O10: 148109.53 | P10: 150346.68 | Q10: 152681.35 | R10: 155094.87 | S10: 157573.82 | T10: 160111.97 | U10: 162715.13 | V10: 165406.61 | W10: 168225.62 | X10: 171222.29 | Y10: 174446.64 | Z10: 177935.3 | AA10: 181705.7 | AB10: 185765.85 | AC10: 190108.16 | AD10: 194727.76 | AE10: 199630.57 | AF10: 204834.45 | AG10: 210363.72 | AH10: 216237.79 | AI10: 222459.46 | AJ10: 229008.99 | AK10: 235847.25
A11: f_k_sveh_0 | B11: 124562 | C11: 125994.3 | D11: 127497.58 | E11: 129102.87 | F11: 130828.42 | G11: 132676.53 | H11: 134611.65 | I11: 136598.97 | J11: 138618.01 | K11: 140667.65 | L11: 142763.5 | M11: 144930.82 | N11: 147187.65 | O11: 149525.7 | P11: 151935.4 | Q11: 154410.58 | R11: 156968.33 | S11: 159629.64 | T11: 162413.8 | U11: 165334.74 | V11: 168401.55 | W11: 171620.46 | X11: 175001.37 | Y11: 178560.97 | Z11: 182321.58 | AA11: 186310.64 | AB11: 190557.79 | AC11: 195092.93 | AD11: 199939.59 | AE11: 205106.75 | AF11: 210589 | AG11: 216374.54 | AH11: 222453.11 | AI11: 228818.5 | AJ11: 235466.39 | AK11: 242389.79
A12: f_k_sgla_2 | B12: 17701.909 | C12: 17940.264 | D12: 18232.939 | E12: 18570.45 | F12: 18937.368 | G12: 19322.099 | H12: 19716.018 | I12: 20099.405 | J12: 20460.483 | K12: 20803.176 | L12: 21137.259 | M12: 21476.702 | N12: 21835.834 | O12: 22225.678 | P12: 22652.773 | Q12: 23117.985 | R12: 23617.611 | S12: 24143.037 | T12: 24684.983 | U12: 25237.445 | V12: 25800.016 | W12: 26377.516 | X12: 26977.539 | Y12: 27606.861 | Z12: 28267.655 | AA12: 28955.645 | AB12: 29660.18 | AC12: 30369.147 | AD12: 31074.866 | AE12: 31777.58 | AF12: 32485.034 | AG12: 33208.76 | AH12: 33959.032 | AI12: 34740.931 | AJ12: 35552.97 | AK12: 36388.906
... A67: f_k_seot_0 | B67: 102.42834 | C67: 103.61115 | D67: 104.78541 | E67: 105.95663 | F67: 107.12665 | G67: 108.3071 | H67: 109.52682 | I67: 110.81506 | J67: 112.19477 | K67: 113.67974 | L67: 115.27773 | M67: 116.995 | N67: 118.8377 | O67: 120.80962 | P67: 122.91687 | Q67: 125.16772 | R67: 127.56259 | S67: 130.10188 | T67: 132.78814 | U67: 135.62608 | V67: 138.6218 | W67: 141.78079 | X67: 145.10632 | Y67: 148.59792 | Z67: 152.25152 | AA67: 156.0616 | AB67: 160.02444 | AC67: 164.1409 | AD67: 168.41594 | AE67: 172.8539 | AF67: 177.4536 | AG67: 182.20601 | AH67: 187.09503 | AI67: 192.10054 | AJ67: 197.20213 | AK67: 202.38192

Sheet Results
A1: NB : on crée ici une liste : - globale, qui fusionne les sorties des reportings 1, 2 et 3 - "rationalisée" : suppression des doublons, et regroupements par thématique On continue par la suite à avoir 2 Excels de reporting (un "energie", fusion des reportings 1 et 2), et un "économie" (reporting 3)), dans lesquels on copiera cet onglet "results" (généré automatiquement par EViews). --> puis voir à la fin si on peut pas importer les graphs et tableaux dans l'excel automatiquement généré (éviterait les copiés collés, mais à voir si ça prend trop de temps, et si c'est pas trop gros comme excel)
A2: Nom du bloc de variables utilisé dans le code | B2: Sous-bloc de variables pour plus de lisibilité dans le Excel | E2: Year | F2: =date!B3 -> 2015 | G2: =date!C3 -> 2016 | H2: =date!D3 -> 2017 | I2: =date!E3 -> 2018 | J2: =date!F3 -> 2019 | K2: =date!G3 -> 2020 | L2: =date!H3 -> 2021 | M2: =date!I3 -> 2022 | ... AO2: =date!AK3 -> 2050
A3: HYBRID | B3: AUTOMOBILES (thousands) | C3: TOTAL STOCK SHOCK | E3: AUTO_2 | F3: =VLOOKUP($E3,Hybrid!$1:$1048576,MATCH(DATE(F$2,1,1),Hybrid!$A$1:$LI$1),FALSE) -> 32317.941 | G3: =VLOOKUP($E3,Hybrid!$1:$1048576,MATCH(DATE(G$2,1,1),Hybrid!$A$1:$LI$1),FALSE) -> 31929.011 | H3: =VLOOKUP($E3,Hybrid!$1:$1048576,MATCH(DATE(H$2,1,1),Hybrid!$A$1:$LI$1),FALSE) -> 31777.192 | I3: =VLOOKUP($E3,Hybrid!$1:$1048576,MATCH(DATE(I$2,1,1),Hybrid!$A$1:$LI$1),FALSE) -> 31765.1 | J3: =VLOOKUP($E3,Hybrid!$1:$1048576,MATCH(DATE(J$2,1,1),Hybrid!$A$1:$LI$1),FALSE) -> 31863.287 | K3: =VLOOKUP($E3,Hybrid!$1:$1048576,MATCH(DATE(K$2,1,1),Hybrid!$A$1:$LI$1),FALSE) -> 32030.775 | L3: =VLOOKUP($E3,Hybrid!$1:$1048576,MATCH(DATE(L$2,1,1),Hybrid!$A$1:$LI$1),FALSE) -> 32226.803 | M3: =VLOOKUP($E3,Hybrid!$1:$1048576,MATCH(DATE(M$2,1,1),Hybrid!$A$1:$LI$1),FALSE) -> 32345.894 | ... AO3: =VLOOKUP($E3,Hybrid!$1:$1048576,MATCH(DATE(AO$2,1,1),Hybrid!$A$1:$LI$1),FALSE) -> 49426.385
C4: OIL | E4: AUTO_cfut_2 | F4: =VLOOKUP($E4,Hybrid!$1:$1048576,MATCH(DATE(F$2,1,1),Hybrid!$A$1:$LI$1),FALSE) -> 32271.24 | G4: =VLOOKUP($E4,Hybrid!$1:$1048576,MATCH(DATE(G$2,1,1),Hybrid!$A$1:$LI$1),FALSE) -> 31831.204 | H4: =VLOOKUP($E4,Hybrid!$1:$1048576,MATCH(DATE(H$2,1,1),Hybrid!$A$1:$LI$1),FALSE) -> 31580.437 | I4: =VLOOKUP($E4,Hybrid!$1:$1048576,MATCH(DATE(I$2,1,1),Hybrid!$A$1:$LI$1),FALSE) -> 31395.068 | J4: =VLOOKUP($E4,Hybrid!$1:$1048576,MATCH(DATE(J$2,1,1),Hybrid!$A$1:$LI$1),FALSE) -> 31223.074 | K4: =VLOOKUP($E4,Hybrid!$1:$1048576,MATCH(DATE(K$2,1,1),Hybrid!$A$1:$LI$1),FALSE) -> 31025.722 | L4: =VLOOKUP($E4,Hybrid!$1:$1048576,MATCH(DATE(L$2,1,1),Hybrid!$A$1:$LI$1),FALSE) -> 30764.008 | M4: =VLOOKUP($E4,Hybrid!$1:$1048576,MATCH(DATE(M$2,1,1),Hybrid!$A$1:$LI$1),FALSE) -> 30298.828 | ... AO4: =VLOOKUP($E4,Hybrid!$1:$1048576,MATCH(DATE(AO$2,1,1),Hybrid!$A$1:$LI$1),FALSE) -> 3970.1504
D5: class A | E5: AUTO_ca_cfut_2 | F5: =VLOOKUP($E5,Hybrid!$1:$1048576,MATCH(DATE(F$2,1,1),Hybrid!$A$1:$LI$1),FALSE) -> 7095.7005 | G5: =VLOOKUP($E5,Hybrid!$1:$1048576,MATCH(DATE(G$2,1,1),Hybrid!$A$1:$LI$1),FALSE) -> 7132.8398 | H5: =VLOOKUP($E5,Hybrid!$1:$1048576,MATCH(DATE(H$2,1,1),Hybrid!$A$1:$LI$1),FALSE) -> 7215.3669 | I5: =VLOOKUP($E5,Hybrid!$1:$1048576,MATCH(DATE(I$2,1,1),Hybrid!$A$1:$LI$1),FALSE) -> 7309.0323 | J5: =VLOOKUP($E5,Hybrid!$1:$1048576,MATCH(DATE(J$2,1,1),Hybrid!$A$1:$LI$1),FALSE) -> 7399.4848 | K5: =VLOOKUP($E5,Hybrid!$1:$1048576,MATCH(DATE(K$2,1,1),Hybrid!$A$1:$LI$1),FALSE) -> 7475.5486 | L5: =VLOOKUP($E5,Hybrid!$1:$1048576,MATCH(DATE(L$2,1,1),Hybrid!$A$1:$LI$1),FALSE) -> 7526.2884 | M5: =VLOOKUP($E5,Hybrid!$1:$1048576,MATCH(DATE(M$2,1,1),Hybrid!$A$1:$LI$1),FALSE) -> 7512.2081 | ... AO5: =VLOOKUP($E5,Hybrid!$1:$1048576,MATCH(DATE(AO$2,1,1),Hybrid!$A$1:$LI$1),FALSE) -> 990.41518
D6: class B | E6: AUTO_cb_cfut_2 | F6: =VLOOKUP($E6,Hybrid!$1:$1048576,MATCH(DATE(F$2,1,1),Hybrid!$A$1:$LI$1),FALSE) -> 8251.2564 | G6: =VLOOKUP($E6,Hybrid!$1:$1048576,MATCH(DATE(G$2,1,1),Hybrid!$A$1:$LI$1),FALSE) -> 8172.8155 | H6: =VLOOKUP($E6,Hybrid!$1:$1048576,MATCH(DATE(H$2,1,1),Hybrid!$A$1:$LI$1),FALSE) -> 8143.908 | I6: =VLOOKUP($E6,Hybrid!$1:$1048576,MATCH(DATE(I$2,1,1),Hybrid!$A$1:$LI$1),FALSE) -> 8130.1181 | J6: =VLOOKUP($E6,Hybrid!$1:$1048576,MATCH(DATE(J$2,1,1),Hybrid!$A$1:$LI$1),FALSE) -> 8116.6371 | K6: =VLOOKUP($E6,Hybrid!$1:$1048576,MATCH(DATE(K$2,1,1),Hybrid!$A$1:$LI$1),FALSE) -> 8092.9022 | L6: =VLOOKUP($E6,Hybrid!$1:$1048576,MATCH(DATE(L$2,1,1),Hybrid!$A$1:$LI$1),FALSE) -> 8048.4436 | M6: =VLOOKUP($E6,Hybrid!$1:$1048576,MATCH(DATE(M$2,1,1),Hybrid!$A$1:$LI$1),FALSE) -> 7944.4223 | ... AO6: =VLOOKUP($E6,Hybrid!$1:$1048576,MATCH(DATE(AO$2,1,1),Hybrid!$A$1:$LI$1),FALSE) -> 998.58361
D7: class C | E7: AUTO_cc_cfut_2 | F7: =VLOOKUP($E7,Hybrid!$1:$1048576,MATCH(DATE(F$2,1,1),Hybrid!$A$1:$LI$1),FALSE) -> 6777.6025 | G7: =VLOOKUP($E7,Hybrid!$1:$1048576,MATCH(DATE(G$2,1,1),Hybrid!$A$1:$LI$1),FALSE) -> 6638.5946 | H7: =VLOOKUP($E7,Hybrid!$1:$1048576,MATCH(DATE(H$2,1,1),Hybrid!$A$1:$LI$1),FALSE) -> 6538.0811 | I7: =VLOOKUP($E7,Hybrid!$1:$1048576,MATCH(DATE(I$2,1,1),Hybrid!$A$1:$LI$1),FALSE) -> 6451.0457 | J7: =VLOOKUP($E7,Hybrid!$1:$1048576,MATCH(DATE(J$2,1,1),Hybrid!$A$1:$LI$1),FALSE) -> 6366.48 | K7: =VLOOKUP($E7,Hybrid!$1:$1048576,MATCH(DATE(K$2,1,1),Hybrid!$A$1:$LI$1),FALSE) -> 6277.287 | L7: =VLOOKUP($E7,Hybrid!$1:$1048576,MATCH(DATE(L$2,1,1),Hybrid!$A$1:$LI$1),FALSE) -> 6176.3486 | M7: =VLOOKUP($E7,Hybrid!$1:$1048576,MATCH(DATE(M$2,1,1),Hybrid!$A$1:$LI$1),FALSE) -> 6036.2982 | ... AO7: =VLOOKUP($E7,Hybrid!$1:$1048576,MATCH(DATE(AO$2,1,1),Hybrid!$A$1:$LI$1),FALSE) -> 728.12782
D8: class D | E8: AUTO_cd_cfut_2 | F8: =VLOOKUP($E8,Hybrid!$1:$1048576,MATCH(DATE(F$2,1,1),Hybrid!$A$1:$LI$1),FALSE) -> 4159.6639 | G8: =VLOOKUP($E8,Hybrid!$1:$1048576,MATCH(DATE(G$2,1,1),Hybrid!$A$1:$LI$1),FALSE) -> 4052.5069 | H8: =VLOOKUP($E8,Hybrid!$1:$1048576,MATCH(DATE(H$2,1,1),Hybrid!$A$1:$LI$1),FALSE) -> 3970.8964 | I8: =VLOOKUP($E8,Hybrid!$1:$1048576,MATCH(DATE(I$2,1,1),Hybrid!$A$1:$LI$1),FALSE) -> 3902.3818 | J8: =VLOOKUP($E8,Hybrid!$1:$1048576,MATCH(DATE(J$2,1,1),Hybrid!$A$1:$LI$1),FALSE) -> 3841.8525 | K8: =VLOOKUP($E8,Hybrid!$1:$1048576,MATCH(DATE(K$2,1,1),Hybrid!$A$1:$LI$1),FALSE) -> 3784.8111 | L8: =VLOOKUP($E8,Hybrid!$1:$1048576,MATCH(DATE(L$2,1,1),Hybrid!$A$1:$LI$1),FALSE) -> 3726.6655 | M8: =VLOOKUP($E8,Hybrid!$1:$1048576,MATCH(DATE(M$2,1,1),Hybrid!$A$1:$LI$1),FALSE) -> 3653.245 | ... AO8: =VLOOKUP($E8,Hybrid!$1:$1048576,MATCH(DATE(AO$2,1,1),Hybrid!$A$1:$LI$1),FALSE) -> 511.06273
D9: class E | E9: AUTO_ce_cfut_2 | F9: =VLOOKUP($E9,Hybrid!$1:$1048576,MATCH(DATE(F$2,1,1),Hybrid!$A$1:$LI$1),FALSE) -> 2503.7292 | G9: =VLOOKUP($E9,Hybrid!$1:$1048576,MATCH(DATE(G$2,1,1),Hybrid!$A$1:$LI$1),FALSE) -> 2441.4545 | H9: =VLOOKUP($E9,Hybrid!$1:$1048576,MATCH(DATE(H$2,1,1),Hybrid!$A$1:$LI$1),FALSE) -> 2393.7453 | I9: =VLOOKUP($E9,Hybrid!$1:$1048576,MATCH(DATE(I$2,1,1),Hybrid!$A$1:$LI$1),FALSE) -> 2352.9276 | J9: =VLOOKUP($E9,Hybrid!$1:$1048576,MATCH(DATE(J$2,1,1),Hybrid!$A$1:$LI$1),FALSE) -> 2315.905 | K9: =VLOOKUP($E9,Hybrid!$1:$1048576,MATCH(DATE(K$2,1,1),Hybrid!$A$1:$LI$1),FALSE) -> 2280.1025 | L9: =VLOOKUP($E9,Hybrid!$1:$1048576,MATCH(DATE(L$2,1,1),Hybrid!$A$1:$LI$1),FALSE) -> 2242.8305 | M9: =VLOOKUP($E9,Hybrid!$1:$1048576,MATCH(DATE(M$2,1,1),Hybrid!$A$1:$LI$1),FALSE) -> 2195.4681 | ... AO9: =VLOOKUP($E9,Hybrid!$1:$1048576,MATCH(DATE(AO$2,1,1),Hybrid!$A$1:$LI$1),FALSE) -> 304.594
D10: class F | E10: AUTO_cf_cfut_2 | F10: =VLOOKUP($E10,Hybrid!$1:$1048576,MATCH(DATE(F$2,1,1),Hybrid!$A$1:$LI$1),FALSE) -> 1243.6668 | G10: =VLOOKUP($E10,Hybrid!$1:$1048576,MATCH(DATE(G$2,1,1),Hybrid!$A$1:$LI$1),FALSE) -> 1210.3024 | H10: =VLOOKUP($E10,Hybrid!$1:$1048576,MATCH(DATE(H$2,1,1),Hybrid!$A$1:$LI$1),FALSE) -> 1183.3249 | I10: =VLOOKUP($E10,Hybrid!$1:$1048576,MATCH(DATE(I$2,1,1),Hybrid!$A$1:$LI$1),FALSE) -> 1159.1944 | J10: =VLOOKUP($E10,Hybrid!$1:$1048576,MATCH(DATE(J$2,1,1),Hybrid!$A$1:$LI$1),FALSE) -> 1136.5697 | K10: =VLOOKUP($E10,Hybrid!$1:$1048576,MATCH(DATE(K$2,1,1),Hybrid!$A$1:$LI$1),FALSE) -> 1114.3086 | L10: =VLOOKUP($E10,Hybrid!$1:$1048576,MATCH(DATE(L$2,1,1),Hybrid!$A$1:$LI$1),FALSE) -> 1091.169 | M10: =VLOOKUP($E10,Hybrid!$1:$1048576,MATCH(DATE(M$2,1,1),Hybrid!$A$1:$LI$1),FALSE) -> 1063.3045 | ... AO10: =VLOOKUP($E10,Hybrid!$1:$1048576,MATCH(DATE(AO$2,1,1),Hybrid!$A$1:$LI$1),FALSE) -> 164.08592
D11: class G | E11: AUTO_cg_cfut_2 | F11: =VLOOKUP($E11,Hybrid!$1:$1048576,MATCH(DATE(F$2,1,1),Hybrid!$A$1:$LI$1),FALSE) -> 2239.6206 | G11: =VLOOKUP($E11,Hybrid!$1:$1048576,MATCH(DATE(G$2,1,1),Hybrid!$A$1:$LI$1),FALSE) -> 2182.69 | H11: =VLOOKUP($E11,Hybrid!$1:$1048576,MATCH(DATE(H$2,1,1),Hybrid!$A$1:$LI$1),FALSE) -> 2135.1141 | I11: =VLOOKUP($E11,Hybrid!$1:$1048576,MATCH(DATE(I$2,1,1),Hybrid!$A$1:$LI$1),FALSE) -> 2090.3679 | J11: =VLOOKUP($E11,Hybrid!$1:$1048576,MATCH(DATE(J$2,1,1),Hybrid!$A$1:$LI$1),FALSE) -> 2046.1446 | K11: =VLOOKUP($E11,Hybrid!$1:$1048576,MATCH(DATE(K$2,1,1),Hybrid!$A$1:$LI$1),FALSE) -> 2000.7616 | L11: =VLOOKUP($E11,Hybrid!$1:$1048576,MATCH(DATE(L$2,1,1),Hybrid!$A$1:$LI$1),FALSE) -> 1952.2623 | M11: =VLOOKUP($E11,Hybrid!$1:$1048576,MATCH(DATE(M$2,1,1),Hybrid!$A$1:$LI$1),FALSE) -> 1893.8814 | ... AO11: =VLOOKUP($E11,Hybrid!$1:$1048576,MATCH(DATE(AO$2,1,1),Hybrid!$A$1:$LI$1),FALSE) -> 273.28115
C12: ELEC | E12: AUTO_cele_2 | F12: =VLOOKUP($E12,Hybrid!$1:$1048576,MATCH(DATE(F$2,1,1),Hybrid!$A$1:$LI$1),FALSE) -> 44.765 | G12: =VLOOKUP($E12,Hybrid!$1:$1048576,MATCH(DATE(G$2,1,1),Hybrid!$A$1:$LI$1),FALSE) -> 95.818005 | H12: =VLOOKUP($E12,Hybrid!$1:$1048576,MATCH(DATE(H$2,1,1),Hybrid!$A$1:$LI$1),FALSE) -> 194.70329 | I12: =VLOOKUP($E12,Hybrid!$1:$1048576,MATCH(DATE(I$2,1,1),Hybrid!$A$1:$LI$1),FALSE) -> 367.91774 | J12: =VLOOKUP($E12,Hybrid!$1:$1048576,MATCH(DATE(J$2,1,1),Hybrid!$A$1:$LI$1),FALSE) -> 638.04027 | K12: =VLOOKUP($E12,Hybrid!$1:$1048576,MATCH(DATE(K$2,1,1),Hybrid!$A$1:$LI$1),FALSE) -> 1002.8291 | L12: =VLOOKUP($E12,Hybrid!$1:$1048576,MATCH(DATE(L$2,1,1),Hybrid!$A$1:$LI$1),FALSE) -> 1460.5286 | M12: =VLOOKUP($E12,Hybrid!$1:$1048576,MATCH(DATE(M$2,1,1),Hybrid!$A$1:$LI$1),FALSE) -> 2044.7799 | ... AO12: =VLOOKUP($E12,Hybrid!$1:$1048576,MATCH(DATE(AO$2,1,1),Hybrid!$A$1:$LI$1),FALSE) -> 45455.755
D13: class A | E13: AUTO_ca_cele_2 | F13: =VLOOKUP($E13,Hybrid!$1:$1048576,MATCH(DATE(F$2,1,1),Hybrid!$A$1:$LI$1),FALSE) -> 9.8427899 | G13: =VLOOKUP($E13,Hybrid!$1:$1048576,MATCH(DATE(G$2,1,1),Hybrid!$A$1:$LI$1),FALSE) -> 24.308529 | H13: =VLOOKUP($E13,Hybrid!$1:$1048576,MATCH(DATE(H$2,1,1),Hybrid!$A$1:$LI$1),FALSE) -> 52.397495 | I13: =VLOOKUP($E13,Hybrid!$1:$1048576,MATCH(DATE(I$2,1,1),Hybrid!$A$1:$LI$1),FALSE) -> 101.94149 | J13: =VLOOKUP($E13,Hybrid!$1:$1048576,MATCH(DATE(J$2,1,1),Hybrid!$A$1:$LI$1),FALSE) -> 179.82206 | K13: =VLOOKUP($E13,Hybrid!$1:$1048576,MATCH(DATE(K$2,1,1),Hybrid!$A$1:$LI$1),FALSE) -> 285.67404 | L13: =VLOOKUP($E13,Hybrid!$1:$1048576,MATCH(DATE(L$2,1,1),Hybrid!$A$1:$LI$1),FALSE) -> 419.35426 | M13: =VLOOKUP($E13,Hybrid!$1:$1048576,MATCH(DATE(M$2,1,1),Hybrid!$A$1:$LI$1),FALSE) -> 592.1942 | ... AO13: =VLOOKUP($E13,Hybrid!$1:$1048576,MATCH(DATE(AO$2,1,1),Hybrid!$A$1:$LI$1),FALSE) -> 14151.931
D14: class B | E14: AUTO_cb_cele_2 | F14: =VLOOKUP($E14,Hybrid!$1:$1048576,MATCH(DATE(F$2,1,1),Hybrid!$A$1:$LI$1),FALSE) -> 11.445717 | G14: =VLOOKUP($E14,Hybrid!$1:$1048576,MATCH(DATE(G$2,1,1),Hybrid!$A$1:$LI$1),FALSE) -> 26.55309 | H14: =VLOOKUP($E14,Hybrid!$1:$1048576,MATCH(DATE(H$2,1,1),Hybrid!$A$1:$LI$1),FALSE) -> 56.492548 | I14: =VLOOKUP($E14,Hybrid!$1:$1048576,MATCH(DATE(I$2,1,1),Hybrid!$A$1:$LI$1),FALSE) -> 109.67056 | J14: =VLOOKUP($E14,Hybrid!$1:$1048576,MATCH(DATE(J$2,1,1),Hybrid!$A$1:$LI$1),FALSE) -> 193.30399 | K14: =VLOOKUP($E14,Hybrid!$1:$1048576,MATCH(DATE(K$2,1,1),Hybrid!$A$1:$LI$1),FALSE) -> 306.82052 | L14: =VLOOKUP($E14,Hybrid!$1:$1048576,MATCH(DATE(L$2,1,1),Hybrid!$A$1:$LI$1),FALSE) -> 449.81011 | M14: =VLOOKUP($E14,Hybrid!$1:$1048576,MATCH(DATE(M$2,1,1),Hybrid!$A$1:$LI$1),FALSE) -> 633.18261 | ... AO14: =VLOOKUP($E14,Hybrid!$1:$1048576,MATCH(DATE(AO$2,1,1),Hybrid!$A$1:$LI$1),FALSE) -> 13801.752
D15: class C | E15: AUTO_cc_cele_2 | F15: =VLOOKUP($E15,Hybrid!$1:$1048576,MATCH(DATE(F$2,1,1),Hybrid!$A$1:$LI$1),FALSE) -> 9.4015406 | G15: =VLOOKUP($E15,Hybrid!$1:$1048576,MATCH(DATE(G$2,1,1),Hybrid!$A$1:$LI$1),FALSE) -> 20.942646 | H15: =VLOOKUP($E15,Hybrid!$1:$1048576,MATCH(DATE(H$2,1,1),Hybrid!$A$1:$LI$1),FALSE) -> 44.274219 | I15: =VLOOKUP($E15,Hybrid!$1:$1048576,MATCH(DATE(I$2,1,1),Hybrid!$A$1:$LI$1),FALSE) -> 85.956733 | J15: =VLOOKUP($E15,Hybrid!$1:$1048576,MATCH(DATE(J$2,1,1),Hybrid!$A$1:$LI$1),FALSE) -> 151.46397 | K15: =VLOOKUP($E15,Hybrid!$1:$1048576,MATCH(DATE(K$2,1,1),Hybrid!$A$1:$LI$1),FALSE) -> 240.16919 | L15: =VLOOKUP($E15,Hybrid!$1:$1048576,MATCH(DATE(L$2,1,1),Hybrid!$A$1:$LI$1),FALSE) -> 351.51294 | M15: =VLOOKUP($E15,Hybrid!$1:$1048576,MATCH(DATE(M$2,1,1),Hybrid!$A$1:$LI$1),FALSE) -> 492.93276 | ... AO15: =VLOOKUP($E15,Hybrid!$1:$1048576,MATCH(DATE(AO$2,1,1),Hybrid!$A$1:$LI$1),FALSE) -> 9795.0789
D16: class D | E16: AUTO_cd_cele_2 | F16: =VLOOKUP($E16,Hybrid!$1:$1048576,MATCH(DATE(F$2,1,1),Hybrid!$A$1:$LI$1),FALSE) -> 5.7700713 | G16: =VLOOKUP($E16,Hybrid!$1:$1048576,MATCH(DATE(G$2,1,1),Hybrid!$A$1:$LI$1),FALSE) -> 9.8900605 | H16: =VLOOKUP($E16,Hybrid!$1:$1048576,MATCH(DATE(H$2,1,1),Hybrid!$A$1:$LI$1),FALSE) -> 17.317962 | I16: =VLOOKUP($E16,Hybrid!$1:$1048576,MATCH(DATE(I$2,1,1),Hybrid!$A$1:$LI$1),FALSE) -> 29.785459 | J16: =VLOOKUP($E16,Hybrid!$1:$1048576,MATCH(DATE(J$2,1,1),Hybrid!$A$1:$LI$1),FALSE) -> 48.781217 | K16: =VLOOKUP($E16,Hybrid!$1:$1048576,MATCH(DATE(K$2,1,1),Hybrid!$A$1:$LI$1),FALSE) -> 74.139577 | L16: =VLOOKUP($E16,Hybrid!$1:$1048576,MATCH(DATE(L$2,1,1),Hybrid!$A$1:$LI$1),FALSE) -> 105.73738 | M16: =VLOOKUP($E16,Hybrid!$1:$1048576,MATCH(DATE(M$2,1,1),Hybrid!$A$1:$LI$1),FALSE) -> 145.87217 | ... AO16: =VLOOKUP($E16,Hybrid!$1:$1048576,MATCH(DATE(AO$2,1,1),Hybrid!$A$1:$LI$1),FALSE) -> 3783.3041
D17: class E | E17: AUTO_ce_cele_2 | F17: =VLOOKUP($E17,Hybrid!$1:$1048576,MATCH(DATE(F$2,1,1),Hybrid!$A$1:$LI$1),FALSE) -> 3.4730441 | G17: =VLOOKUP($E17,Hybrid!$1:$1048576,MATCH(DATE(G$2,1,1),Hybrid!$A$1:$LI$1),FALSE) -> 6.1197834 | H17: =VLOOKUP($E17,Hybrid!$1:$1048576,MATCH(DATE(H$2,1,1),Hybrid!$A$1:$LI$1),FALSE) -> 10.922182 | I17: =VLOOKUP($E17,Hybrid!$1:$1048576,MATCH(DATE(I$2,1,1),Hybrid!$A$1:$LI$1),FALSE) -> 18.974748 | J17: =VLOOKUP($E17,Hybrid!$1:$1048576,MATCH(DATE(J$2,1,1),Hybrid!$A$1:$LI$1),FALSE) -> 31.189098 | K17: =VLOOKUP($E17,Hybrid!$1:$1048576,MATCH(DATE(K$2,1,1),Hybrid!$A$1:$LI$1),FALSE) -> 47.425313 | L17: =VLOOKUP($E17,Hybrid!$1:$1048576,MATCH(DATE(L$2,1,1),Hybrid!$A$1:$LI$1),FALSE) -> 67.555193 | M17: =VLOOKUP($E17,Hybrid!$1:$1048576,MATCH(DATE(M$2,1,1),Hybrid!$A$1:$LI$1),FALSE) -> 92.81412 | ... AO17: =VLOOKUP($E17,Hybrid!$1:$1048576,MATCH(DATE(AO$2,1,1),Hybrid!$A$1:$LI$1),FALSE) -> 2255.55
D18: class F | E18: AUTO_cf_cele_2 | F18: =VLOOKUP($E18,Hybrid!$1:$1048576,MATCH(DATE(F$2,1,1),Hybrid!$A$1:$LI$1),FALSE) -> 1.7251505 | G18: =VLOOKUP($E18,Hybrid!$1:$1048576,MATCH(DATE(G$2,1,1),Hybrid!$A$1:$LI$1),FALSE) -> 2.7749683 | H18: =VLOOKUP($E18,Hybrid!$1:$1048576,MATCH(DATE(H$2,1,1),Hybrid!$A$1:$LI$1),FALSE) -> 4.5165418 | I18: =VLOOKUP($E18,Hybrid!$1:$1048576,MATCH(DATE(I$2,1,1),Hybrid!$A$1:$LI$1),FALSE) -> 7.249672 | J18: =VLOOKUP($E18,Hybrid!$1:$1048576,MATCH(DATE(J$2,1,1),Hybrid!$A$1:$LI$1),FALSE) -> 11.200749 | K18: =VLOOKUP($E18,Hybrid!$1:$1048576,MATCH(DATE(K$2,1,1),Hybrid!$A$1:$LI$1),FALSE) -> 16.271969 | L18: =VLOOKUP($E18,Hybrid!$1:$1048576,MATCH(DATE(L$2,1,1),Hybrid!$A$1:$LI$1),FALSE) -> 22.363051 | M18: =VLOOKUP($E18,Hybrid!$1:$1048576,MATCH(DATE(M$2,1,1),Hybrid!$A$1:$LI$1),FALSE) -> 29.704176 | ... AO18: =VLOOKUP($E18,Hybrid!$1:$1048576,MATCH(DATE(AO$2,1,1),Hybrid!$A$1:$LI$1),FALSE) -> 628.41253
D19: class G | E19: AUTO_cg_cele_2 | F19: =VLOOKUP($E19,Hybrid!$1:$1048576,MATCH(DATE(F$2,1,1),Hybrid!$A$1:$LI$1),FALSE) -> 3.1066862 | G19: =VLOOKUP($E19,Hybrid!$1:$1048576,MATCH(DATE(G$2,1,1),Hybrid!$A$1:$LI$1),FALSE) -> 5.2289267 | H19: =VLOOKUP($E19,Hybrid!$1:$1048576,MATCH(DATE(H$2,1,1),Hybrid!$A$1:$LI$1),FALSE) -> 8.7823369 | I19: =VLOOKUP($E19,Hybrid!$1:$1048576,MATCH(DATE(I$2,1,1),Hybrid!$A$1:$LI$1),FALSE) -> 14.339075 | J19: =VLOOKUP($E19,Hybrid!$1:$1048576,MATCH(DATE(J$2,1,1),Hybrid!$A$1:$LI$1),FALSE) -> 22.279182 | K19: =VLOOKUP($E19,Hybrid!$1:$1048576,MATCH(DATE(K$2,1,1),Hybrid!$A$1:$LI$1),FALSE) -> 32.328482 | L19: =VLOOKUP($E19,Hybrid!$1:$1048576,MATCH(DATE(L$2,1,1),Hybrid!$A$1:$LI$1),FALSE) -> 44.195707 | M19: =VLOOKUP($E19,Hybrid!$1:$1048576,MATCH(DATE(M$2,1,1),Hybrid!$A$1:$LI$1),FALSE) -> 58.079827 | ... AO19: =VLOOKUP($E19,Hybrid!$1:$1048576,MATCH(DATE(AO$2,1,1),Hybrid!$A$1:$LI$1),FALSE) -> 1039.7265
C20: GAS | E20: AUTO_cgas_2 | F20: =VLOOKUP($E20,Hybrid!$1:$1048576,MATCH(DATE(F$2,1,1),Hybrid!$A$1:$LI$1),FALSE) -> 1.936 | G20: =VLOOKUP($E20,Hybrid!$1:$1048576,MATCH(DATE(G$2,1,1),Hybrid!$A$1:$LI$1),FALSE) -> 1.9890157 | H20: =VLOOKUP($E20,Hybrid!$1:$1048576,MATCH(DATE(H$2,1,1),Hybrid!$A$1:$LI$1),FALSE) -> 2.0517417 | I20: =VLOOKUP($E20,Hybrid!$1:$1048576,MATCH(DATE(I$2,1,1),Hybrid!$A$1:$LI$1),FALSE) -> 2.1144021 | J20: =VLOOKUP($E20,Hybrid!$1:$1048576,MATCH(DATE(J$2,1,1),Hybrid!$A$1:$LI$1),FALSE) -> 2.1730579 | K20: =VLOOKUP($E20,Hybrid!$1:$1048576,MATCH(DATE(K$2,1,1),Hybrid!$A$1:$LI$1),FALSE) -> 2.2247929 | L20: =VLOOKUP($E20,Hybrid!$1:$1048576,MATCH(DATE(L$2,1,1),Hybrid!$A$1:$LI$1),FALSE) -> 2.2665971 | M20: =VLOOKUP($E20,Hybrid!$1:$1048576,MATCH(DATE(M$2,1,1),Hybrid!$A$1:$LI$1),FALSE) -> 2.2869841 | ... AO20: =VLOOKUP($E20,Hybrid!$1:$1048576,MATCH(DATE(AO$2,1,1),Hybrid!$A$1:$LI$1),FALSE) -> 0.47873566
D21: class A | E21: AUTO_ca_cgas_2 | F21: =VLOOKUP($E21,Hybrid!$1:$1048576,MATCH(DATE(F$2,1,1),Hybrid!$A$1:$LI$1),FALSE) -> 0.4256817 | G21: =VLOOKUP($E21,Hybrid!$1:$1048576,MATCH(DATE(G$2,1,1),Hybrid!$A$1:$LI$1),FALSE) -> 0.44858712 | H21: =VLOOKUP($E21,Hybrid!$1:$1048576,MATCH(DATE(H$2,1,1),Hybrid!$A$1:$LI$1),FALSE) -> 0.47411683 | I21: =VLOOKUP($E21,Hybrid!$1:$1048576,MATCH(DATE(I$2,1,1),Hybrid!$A$1:$LI$1),FALSE) -> 0.49952623 | J21: =VLOOKUP($E21,Hybrid!$1:$1048576,MATCH(DATE(J$2,1,1),Hybrid!$A$1:$LI$1),FALSE) -> 0.52368998 | K21: =VLOOKUP($E21,Hybrid!$1:$1048576,MATCH(DATE(K$2,1,1),Hybrid!$A$1:$LI$1),FALSE) -> 0.54572606 | L21: =VLOOKUP($E21,Hybrid!$1:$1048576,MATCH(DATE(L$2,1,1),Hybrid!$A$1:$LI$1),FALSE) -> 0.56475468 | M21: =VLOOKUP($E21,Hybrid!$1:$1048576,MATCH(DATE(M$2,1,1),Hybrid!$A$1:$LI$1),FALSE) -> 0.57748014 | ... AO21: =VLOOKUP($E21,Hybrid!$1:$1048576,MATCH(DATE(AO$2,1,1),Hybrid!$A$1:$LI$1),FALSE) -> 0.12169248
D22: class B | E22: AUTO_cb_cgas_2 | F22: =VLOOKUP($E22,Hybrid!$1:$1048576,MATCH(DATE(F$2,1,1),Hybrid!$A$1:$LI$1),FALSE) -> 0.49500523 | G22: =VLOOKUP($E22,Hybrid!$1:$1048576,MATCH(DATE(G$2,1,1),Hybrid!$A$1:$LI$1),FALSE) -> 0.51142274 | H22: =VLOOKUP($E22,Hybrid!$1:$1048576,MATCH(DATE(H$2,1,1),Hybrid!$A$1:$LI$1),FALSE) -> 0.53046267 | I22: =VLOOKUP($E22,Hybrid!$1:$1048576,MATCH(DATE(I$2,1,1),Hybrid!$A$1:$LI$1),FALSE) -> 0.54939366 | J22: =VLOOKUP($E22,Hybrid!$1:$1048576,MATCH(DATE(J$2,1,1),Hybrid!$A$1:$LI$1),FALSE) -> 0.56707726 | K22: =VLOOKUP($E22,Hybrid!$1:$1048576,MATCH(DATE(K$2,1,1),Hybrid!$A$1:$LI$1),FALSE) -> 0.58270605 | L22: =VLOOKUP($E22,Hybrid!$1:$1048576,MATCH(DATE(L$2,1,1),Hybrid!$A$1:$LI$1),FALSE) -> 0.59546186 | M22: =VLOOKUP($E22,Hybrid!$1:$1048576,MATCH(DATE(M$2,1,1),Hybrid!$A$1:$LI$1),FALSE) -> 0.60212583 | ... AO22: =VLOOKUP($E22,Hybrid!$1:$1048576,MATCH(DATE(AO$2,1,1),Hybrid!$A$1:$LI$1),FALSE) -> 0.12119679
D23: class C | E23: AUTO_cc_cgas_2 | F23: =VLOOKUP($E23,Hybrid!$1:$1048576,MATCH(DATE(F$2,1,1),Hybrid!$A$1:$LI$1),FALSE) -> 0.40659852 | G23: =VLOOKUP($E23,Hybrid!$1:$1048576,MATCH(DATE(G$2,1,1),Hybrid!$A$1:$LI$1),FALSE) -> 0.41381867 | H23: =VLOOKUP($E23,Hybrid!$1:$1048576,MATCH(DATE(H$2,1,1),Hybrid!$A$1:$LI$1),FALSE) -> 0.4229127 | I23: =VLOOKUP($E23,Hybrid!$1:$1048576,MATCH(DATE(I$2,1,1),Hybrid!$A$1:$LI$1),FALSE) -> 0.43191353 | J23: =VLOOKUP($E23,Hybrid!$1:$1048576,MATCH(DATE(J$2,1,1),Hybrid!$A$1:$LI$1),FALSE) -> 0.43999027 | K23: =VLOOKUP($E23,Hybrid!$1:$1048576,MATCH(DATE(K$2,1,1),Hybrid!$A$1:$LI$1),FALSE) -> 0.44662059 | L23: =VLOOKUP($E23,Hybrid!$1:$1048576,MATCH(DATE(L$2,1,1),Hybrid!$A$1:$LI$1),FALSE) -> 0.45126665 | M23: =VLOOKUP($E23,Hybrid!$1:$1048576,MATCH(DATE(M$2,1,1),Hybrid!$A$1:$LI$1),FALSE) -> 0.45167657 | ... AO23: =VLOOKUP($E23,Hybrid!$1:$1048576,MATCH(DATE(AO$2,1,1),Hybrid!$A$1:$LI$1),FALSE) -> 0.087294879
D24: class D | E24: AUTO_cd_cgas_2 | F24: =VLOOKUP($E24,Hybrid!$1:$1048576,MATCH(DATE(F$2,1,1),Hybrid!$A$1:$LI$1),FALSE) -> 0.24954447 | G24: =VLOOKUP($E24,Hybrid!$1:$1048576,MATCH(DATE(G$2,1,1),Hybrid!$A$1:$LI$1),FALSE) -> 0.2521407 | H24: =VLOOKUP($E24,Hybrid!$1:$1048576,MATCH(DATE(H$2,1,1),Hybrid!$A$1:$LI$1),FALSE) -> 0.25602029 | I24: =VLOOKUP($E24,Hybrid!$1:$1048576,MATCH(DATE(I$2,1,1),Hybrid!$A$1:$LI$1),FALSE) -> 0.26022406 | J24: =VLOOKUP($E24,Hybrid!$1:$1048576,MATCH(DATE(J$2,1,1),Hybrid!$A$1:$LI$1),FALSE) -> 0.26438799 | K24: =VLOOKUP($E24,Hybrid!$1:$1048576,MATCH(DATE(K$2,1,1),Hybrid!$A$1:$LI$1),FALSE) -> 0.26818899 | L24: =VLOOKUP($E24,Hybrid!$1:$1048576,MATCH(DATE(L$2,1,1),Hybrid!$A$1:$LI$1),FALSE) -> 0.27128672 | M24: =VLOOKUP($E24,Hybrid!$1:$1048576,MATCH(DATE(M$2,1,1),Hybrid!$A$1:$LI$1),FALSE) -> 0.27252744 | ... AO24: =VLOOKUP($E24,Hybrid!$1:$1048576,MATCH(DATE(AO$2,1,1),Hybrid!$A$1:$LI$1),FALSE) -> 0.06096558
D25: class E | E25: AUTO_ce_cgas_2 | F25: =VLOOKUP($E25,Hybrid!$1:$1048576,MATCH(DATE(F$2,1,1),Hybrid!$A$1:$LI$1),FALSE) -> 0.15020247 | G25: =VLOOKUP($E25,Hybrid!$1:$1048576,MATCH(DATE(G$2,1,1),Hybrid!$A$1:$LI$1),FALSE) -> 0.15195198 | H25: =VLOOKUP($E25,Hybrid!$1:$1048576,MATCH(DATE(H$2,1,1),Hybrid!$A$1:$LI$1),FALSE) -> 0.15440868 | I25: =VLOOKUP($E25,Hybrid!$1:$1048576,MATCH(DATE(I$2,1,1),Hybrid!$A$1:$LI$1),FALSE) -> 0.15697887 | J25: =VLOOKUP($E25,Hybrid!$1:$1048576,MATCH(DATE(J$2,1,1),Hybrid!$A$1:$LI$1),FALSE) -> 0.15944041 | K25: =VLOOKUP($E25,Hybrid!$1:$1048576,MATCH(DATE(K$2,1,1),Hybrid!$A$1:$LI$1),FALSE) -> 0.16160855 | L25: =VLOOKUP($E25,Hybrid!$1:$1048576,MATCH(DATE(L$2,1,1),Hybrid!$A$1:$LI$1),FALSE) -> 0.16328366 | M25: =VLOOKUP($E25,Hybrid!$1:$1048576,MATCH(DATE(M$2,1,1),Hybrid!$A$1:$LI$1),FALSE) -> 0.16376269 | ... AO25: =VLOOKUP($E25,Hybrid!$1:$1048576,MATCH(DATE(AO$2,1,1),Hybrid!$A$1:$LI$1),FALSE) -> 0.036307907
D26: class F | E26: AUTO_cf_cgas_2 | F26: =VLOOKUP($E26,Hybrid!$1:$1048576,MATCH(DATE(F$2,1,1),Hybrid!$A$1:$LI$1),FALSE) -> 0.074609436 | G26: =VLOOKUP($E26,Hybrid!$1:$1048576,MATCH(DATE(G$2,1,1),Hybrid!$A$1:$LI$1),FALSE) -> 0.075274234 | H26: =VLOOKUP($E26,Hybrid!$1:$1048576,MATCH(DATE(H$2,1,1),Hybrid!$A$1:$LI$1),FALSE) -> 0.076215928 | I26: =VLOOKUP($E26,Hybrid!$1:$1048576,MATCH(DATE(I$2,1,1),Hybrid!$A$1:$LI$1),FALSE) -> 0.077161577 | J26: =VLOOKUP($E26,Hybrid!$1:$1048576,MATCH(DATE(J$2,1,1),Hybrid!$A$1:$LI$1),FALSE) -> 0.078016858 | K26: =VLOOKUP($E26,Hybrid!$1:$1048576,MATCH(DATE(K$2,1,1),Hybrid!$A$1:$LI$1),FALSE) -> 0.078701315 | L26: =VLOOKUP($E26,Hybrid!$1:$1048576,MATCH(DATE(L$2,1,1),Hybrid!$A$1:$LI$1),FALSE) -> 0.079123651 | M26: =VLOOKUP($E26,Hybrid!$1:$1048576,MATCH(DATE(M$2,1,1),Hybrid!$A$1:$LI$1),FALSE) -> 0.078971364 | ... AO26: =VLOOKUP($E26,Hybrid!$1:$1048576,MATCH(DATE(AO$2,1,1),Hybrid!$A$1:$LI$1),FALSE) -> 0.019241264
D27: class G | E27: AUTO_cg_cgas_2 | F27: =VLOOKUP($E27,Hybrid!$1:$1048576,MATCH(DATE(F$2,1,1),Hybrid!$A$1:$LI$1),FALSE) -> 0.13435819 | G27: =VLOOKUP($E27,Hybrid!$1:$1048576,MATCH(DATE(G$2,1,1),Hybrid!$A$1:$LI$1),FALSE) -> 0.13582025 | H27: =VLOOKUP($E27,Hybrid!$1:$1048576,MATCH(DATE(H$2,1,1),Hybrid!$A$1:$LI$1),FALSE) -> 0.13760462 | I27: =VLOOKUP($E27,Hybrid!$1:$1048576,MATCH(DATE(I$2,1,1),Hybrid!$A$1:$LI$1),FALSE) -> 0.13920415 | J27: =VLOOKUP($E27,Hybrid!$1:$1048576,MATCH(DATE(J$2,1,1),Hybrid!$A$1:$LI$1),FALSE) -> 0.1404551 | K27: =VLOOKUP($E27,Hybrid!$1:$1048576,MATCH(DATE(K$2,1,1),Hybrid!$A$1:$LI$1),FALSE) -> 0.14124131 | L27: =VLOOKUP($E27,Hybrid!$1:$1048576,MATCH(DATE(L$2,1,1),Hybrid!$A$1:$LI$1),FALSE) -> 0.14141987 | M27: =VLOOKUP($E27,Hybrid!$1:$1048576,MATCH(DATE(M$2,1,1),Hybrid!$A$1:$LI$1),FALSE) -> 0.14044004 | ... AO27: =VLOOKUP($E27,Hybrid!$1:$1048576,MATCH(DATE(AO$2,1,1),Hybrid!$A$1:$LI$1),FALSE) -> 0.032036765
C28: TOTAL STOCK BASELINE | E28: AUTO_0 | F28: =VLOOKUP($E28,Hybrid!$1:$1048576,MATCH(DATE(F$2,1,1),Hybrid!$A$1:$LI$1),FALSE) -> 32317.941 | G28: =VLOOKUP($E28,Hybrid!$1:$1048576,MATCH(DATE(G$2,1,1),Hybrid!$A$1:$LI$1),FALSE) -> 31929.011 | H28: =VLOOKUP($E28,Hybrid!$1:$1048576,MATCH(DATE(H$2,1,1),Hybrid!$A$1:$LI$1),FALSE) -> 31777.192 | I28: =VLOOKUP($E28,Hybrid!$1:$1048576,MATCH(DATE(I$2,1,1),Hybrid!$A$1:$LI$1),FALSE) -> 31765.1 | J28: =VLOOKUP($E28,Hybrid!$1:$1048576,MATCH(DATE(J$2,1,1),Hybrid!$A$1:$LI$1),FALSE) -> 31863.287 | K28: =VLOOKUP($E28,Hybrid!$1:$1048576,MATCH(DATE(K$2,1,1),Hybrid!$A$1:$LI$1),FALSE) -> 32030.775 | L28: =VLOOKUP($E28,Hybrid!$1:$1048576,MATCH(DATE(L$2,1,1),Hybrid!$A$1:$LI$1),FALSE) -> 32187.627 | M28: =VLOOKUP($E28,Hybrid!$1:$1048576,MATCH(DATE(M$2,1,1),Hybrid!$A$1:$LI$1),FALSE) -> 32343.292 | ... AO28: =VLOOKUP($E28,Hybrid!$1:$1048576,MATCH(DATE(AO$2,1,1),Hybrid!$A$1:$LI$1),FALSE) -> 47889.317
C29: OIL | E29: AUTO_cfut_0 | F29: =VLOOKUP($E29,Hybrid!$1:$1048576,MATCH(DATE(F$2,1,1),Hybrid!$A$1:$LI$1),FALSE) -> 32271.24 | G29: =VLOOKUP($E29,Hybrid!$1:$1048576,MATCH(DATE(G$2,1,1),Hybrid!$A$1:$LI$1),FALSE) -> 31831.204 | H29: =VLOOKUP($E29,Hybrid!$1:$1048576,MATCH(DATE(H$2,1,1),Hybrid!$A$1:$LI$1),FALSE) -> 31580.437 | I29: =VLOOKUP($E29,Hybrid!$1:$1048576,MATCH(DATE(I$2,1,1),Hybrid!$A$1:$LI$1),FALSE) -> 31395.068 | J29: =VLOOKUP($E29,Hybrid!$1:$1048576,MATCH(DATE(J$2,1,1),Hybrid!$A$1:$LI$1),FALSE) -> 31223.074 | K29: =VLOOKUP($E29,Hybrid!$1:$1048576,MATCH(DATE(K$2,1,1),Hybrid!$A$1:$LI$1),FALSE) -> 31025.722 | L29: =VLOOKUP($E29,Hybrid!$1:$1048576,MATCH(DATE(L$2,1,1),Hybrid!$A$1:$LI$1),FALSE) -> 30717.437 | M29: =VLOOKUP($E29,Hybrid!$1:$1048576,MATCH(DATE(M$2,1,1),Hybrid!$A$1:$LI$1),FALSE) -> 30262.289 | ... AO29: =VLOOKUP($E29,Hybrid!$1:$1048576,MATCH(DATE(AO$2,1,1),Hybrid!$A$1:$LI$1),FALSE) -> 4324.5578
D30: class A | E30: AUTO_ca_cfut_0 | F30: =VLOOKUP($E30,Hybrid!$1:$1048576,MATCH(DATE(F$2,1,1),Hybrid!$A$1:$LI$1),FALSE) -> 7095.7005 | G30: =VLOOKUP($E30,Hybrid!$1:$1048576,MATCH(DATE(G$2,1,1),Hybrid!$A$1:$LI$1),FALSE) -> 7132.8398 | H30: =VLOOKUP($E30,Hybrid!$1:$1048576,MATCH(DATE(H$2,1,1),Hybrid!$A$1:$LI$1),FALSE) -> 7215.3669 | I30: =VLOOKUP($E30,Hybrid!$1:$1048576,MATCH(DATE(I$2,1,1),Hybrid!$A$1:$LI$1),FALSE) -> 7309.0323 | J30: =VLOOKUP($E30,Hybrid!$1:$1048576,MATCH(DATE(J$2,1,1),Hybrid!$A$1:$LI$1),FALSE) -> 7399.4848 | K30: =VLOOKUP($E30,Hybrid!$1:$1048576,MATCH(DATE(K$2,1,1),Hybrid!$A$1:$LI$1),FALSE) -> 7475.5486 | L30: =VLOOKUP($E30,Hybrid!$1:$1048576,MATCH(DATE(L$2,1,1),Hybrid!$A$1:$LI$1),FALSE) -> 7512.8901 | M30: =VLOOKUP($E30,Hybrid!$1:$1048576,MATCH(DATE(M$2,1,1),Hybrid!$A$1:$LI$1),FALSE) -> 7501.6244 | ... AO30: =VLOOKUP($E30,Hybrid!$1:$1048576,MATCH(DATE(AO$2,1,1),Hybrid!$A$1:$LI$1),FALSE) -> 1083.5165
D31: class B | E31: AUTO_cb_cfut_0 | F31: =VLOOKUP($E31,Hybrid!$1:$1048576,MATCH(DATE(F$2,1,1),Hybrid!$A$1:$LI$1),FALSE) -> 8251.2564 | G31: =VLOOKUP($E31,Hybrid!$1:$1048576,MATCH(DATE(G$2,1,1),Hybrid!$A$1:$LI$1),FALSE) -> 8172.8155 | H31: =VLOOKUP($E31,Hybrid!$1:$1048576,MATCH(DATE(H$2,1,1),Hybrid!$A$1:$LI$1),FALSE) -> 8143.908 | I31: =VLOOKUP($E31,Hybrid!$1:$1048576,MATCH(DATE(I$2,1,1),Hybrid!$A$1:$LI$1),FALSE) -> 8130.1181 | J31: =VLOOKUP($E31,Hybrid!$1:$1048576,MATCH(DATE(J$2,1,1),Hybrid!$A$1:$LI$1),FALSE) -> 8116.6371 | K31: =VLOOKUP($E31,Hybrid!$1:$1048576,MATCH(DATE(K$2,1,1),Hybrid!$A$1:$LI$1),FALSE) -> 8092.9022 | L31: =VLOOKUP($E31,Hybrid!$1:$1048576,MATCH(DATE(L$2,1,1),Hybrid!$A$1:$LI$1),FALSE) -> 8035.3803 | M31: =VLOOKUP($E31,Hybrid!$1:$1048576,MATCH(DATE(M$2,1,1),Hybrid!$A$1:$LI$1),FALSE) -> 7933.3136 | ... AO31: =VLOOKUP($E31,Hybrid!$1:$1048576,MATCH(DATE(AO$2,1,1),Hybrid!$A$1:$LI$1),FALSE) -> 1075.59
D32: class C | E32: AUTO_cc_cfut_0 | F32: =VLOOKUP($E32,Hybrid!$1:$1048576,MATCH(DATE(F$2,1,1),Hybrid!$A$1:$LI$1),FALSE) -> 6777.6025 | G32: =VLOOKUP($E32,Hybrid!$1:$1048576,MATCH(DATE(G$2,1,1),Hybrid!$A$1:$LI$1),FALSE) -> 6638.5946 | H32: =VLOOKUP($E32,Hybrid!$1:$1048576,MATCH(DATE(H$2,1,1),Hybrid!$A$1:$LI$1),FALSE) -> 6538.0811 | I32: =VLOOKUP($E32,Hybrid!$1:$1048576,MATCH(DATE(I$2,1,1),Hybrid!$A$1:$LI$1),FALSE) -> 6451.0457 | J32: =VLOOKUP($E32,Hybrid!$1:$1048576,MATCH(DATE(J$2,1,1),Hybrid!$A$1:$LI$1),FALSE) -> 6366.48 | K32: =VLOOKUP($E32,Hybrid!$1:$1048576,MATCH(DATE(K$2,1,1),Hybrid!$A$1:$LI$1),FALSE) -> 6277.287 | L32: =VLOOKUP($E32,Hybrid!$1:$1048576,MATCH(DATE(L$2,1,1),Hybrid!$A$1:$LI$1),FALSE) -> 6167.1736 | M32: =VLOOKUP($E32,Hybrid!$1:$1048576,MATCH(DATE(M$2,1,1),Hybrid!$A$1:$LI$1),FALSE) -> 6027.9074 | ... AO32: =VLOOKUP($E32,Hybrid!$1:$1048576,MATCH(DATE(AO$2,1,1),Hybrid!$A$1:$LI$1),FALSE) -> 773.20496
D33: class D | E33: AUTO_cd_cfut_0 | F33: =VLOOKUP($E33,Hybrid!$1:$1048576,MATCH(DATE(F$2,1,1),Hybrid!$A$1:$LI$1),FALSE) -> 4159.6639 | G33: =VLOOKUP($E33,Hybrid!$1:$1048576,MATCH(DATE(G$2,1,1),Hybrid!$A$1:$LI$1),FALSE) -> 4052.5069 | H33: =VLOOKUP($E33,Hybrid!$1:$1048576,MATCH(DATE(H$2,1,1),Hybrid!$A$1:$LI$1),FALSE) -> 3970.8964 | I33: =VLOOKUP($E33,Hybrid!$1:$1048576,MATCH(DATE(I$2,1,1),Hybrid!$A$1:$LI$1),FALSE) -> 3902.3818 | J33: =VLOOKUP($E33,Hybrid!$1:$1048576,MATCH(DATE(J$2,1,1),Hybrid!$A$1:$LI$1),FALSE) -> 3841.8525 | K33: =VLOOKUP($E33,Hybrid!$1:$1048576,MATCH(DATE(K$2,1,1),Hybrid!$A$1:$LI$1),FALSE) -> 3784.8111 | L33: =VLOOKUP($E33,Hybrid!$1:$1048576,MATCH(DATE(L$2,1,1),Hybrid!$A$1:$LI$1),FALSE) -> 3722.0334 | M33: =VLOOKUP($E33,Hybrid!$1:$1048576,MATCH(DATE(M$2,1,1),Hybrid!$A$1:$LI$1),FALSE) -> 3650.4191 | ... AO33: =VLOOKUP($E33,Hybrid!$1:$1048576,MATCH(DATE(AO$2,1,1),Hybrid!$A$1:$LI$1),FALSE) -> 565.82989
D34: class E | E34: AUTO_ce_cfut_0 | F34: =VLOOKUP($E34,Hybrid!$1:$1048576,MATCH(DATE(F$2,1,1),Hybrid!$A$1:$LI$1),FALSE) -> 2503.7292 | G34: =VLOOKUP($E34,Hybrid!$1:$1048576,MATCH(DATE(G$2,1,1),Hybrid!$A$1:$LI$1),FALSE) -> 2441.4545 | H34: =VLOOKUP($E34,Hybrid!$1:$1048576,MATCH(DATE(H$2,1,1),Hybrid!$A$1:$LI$1),FALSE) -> 2393.7453 | I34: =VLOOKUP($E34,Hybrid!$1:$1048576,MATCH(DATE(I$2,1,1),Hybrid!$A$1:$LI$1),FALSE) -> 2352.9276 | J34: =VLOOKUP($E34,Hybrid!$1:$1048576,MATCH(DATE(J$2,1,1),Hybrid!$A$1:$LI$1),FALSE) -> 2315.905 | K34: =VLOOKUP($E34,Hybrid!$1:$1048576,MATCH(DATE(K$2,1,1),Hybrid!$A$1:$LI$1),FALSE) -> 2280.1025 | L34: =VLOOKUP($E34,Hybrid!$1:$1048576,MATCH(DATE(L$2,1,1),Hybrid!$A$1:$LI$1),FALSE) -> 2240.0049 | M34: =VLOOKUP($E34,Hybrid!$1:$1048576,MATCH(DATE(M$2,1,1),Hybrid!$A$1:$LI$1),FALSE) -> 2193.6875 | ... AO34: =VLOOKUP($E34,Hybrid!$1:$1048576,MATCH(DATE(AO$2,1,1),Hybrid!$A$1:$LI$1),FALSE) -> 335.59245
D35: class F | E35: AUTO_cf_cfut_0 | F35: =VLOOKUP($E35,Hybrid!$1:$1048576,MATCH(DATE(F$2,1,1),Hybrid!$A$1:$LI$1),FALSE) -> 1243.6668 | G35: =VLOOKUP($E35,Hybrid!$1:$1048576,MATCH(DATE(G$2,1,1),Hybrid!$A$1:$LI$1),FALSE) -> 1210.3024 | H35: =VLOOKUP($E35,Hybrid!$1:$1048576,MATCH(DATE(H$2,1,1),Hybrid!$A$1:$LI$1),FALSE) -> 1183.3249 | I35: =VLOOKUP($E35,Hybrid!$1:$1048576,MATCH(DATE(I$2,1,1),Hybrid!$A$1:$LI$1),FALSE) -> 1159.1944 | J35: =VLOOKUP($E35,Hybrid!$1:$1048576,MATCH(DATE(J$2,1,1),Hybrid!$A$1:$LI$1),FALSE) -> 1136.5697 | K35: =VLOOKUP($E35,Hybrid!$1:$1048576,MATCH(DATE(K$2,1,1),Hybrid!$A$1:$LI$1),FALSE) -> 1114.3086 | L35: =VLOOKUP($E35,Hybrid!$1:$1048576,MATCH(DATE(L$2,1,1),Hybrid!$A$1:$LI$1),FALSE) -> 1089.9235 | M35: =VLOOKUP($E35,Hybrid!$1:$1048576,MATCH(DATE(M$2,1,1),Hybrid!$A$1:$LI$1),FALSE) -> 1062.6731 | ... AO35: =VLOOKUP($E35,Hybrid!$1:$1048576,MATCH(DATE(AO$2,1,1),Hybrid!$A$1:$LI$1),FALSE) -> 184.36955
D36: class G | E36: AUTO_cg_cfut_0 | F36: =VLOOKUP($E36,Hybrid!$1:$1048576,MATCH(DATE(F$2,1,1),Hybrid!$A$1:$LI$1),FALSE) -> 2239.6206 | G36: =VLOOKUP($E36,Hybrid!$1:$1048576,MATCH(DATE(G$2,1,1),Hybrid!$A$1:$LI$1),FALSE) -> 2182.69 | H36: =VLOOKUP($E36,Hybrid!$1:$1048576,MATCH(DATE(H$2,1,1),Hybrid!$A$1:$LI$1),FALSE) -> 2135.1141 | I36: =VLOOKUP($E36,Hybrid!$1:$1048576,MATCH(DATE(I$2,1,1),Hybrid!$A$1:$LI$1),FALSE) -> 2090.3679 | J36: =VLOOKUP($E36,Hybrid!$1:$1048576,MATCH(DATE(J$2,1,1),Hybrid!$A$1:$LI$1),FALSE) -> 2046.1446 | K36: =VLOOKUP($E36,Hybrid!$1:$1048576,MATCH(DATE(K$2,1,1),Hybrid!$A$1:$LI$1),FALSE) -> 2000.7616 | L36: =VLOOKUP($E36,Hybrid!$1:$1048576,MATCH(DATE(L$2,1,1),Hybrid!$A$1:$LI$1),FALSE) -> 1950.0316 | M36: =VLOOKUP($E36,Hybrid!$1:$1048576,MATCH(DATE(M$2,1,1),Hybrid!$A$1:$LI$1),FALSE) -> 1892.664 | ... AO36: =VLOOKUP($E36,Hybrid!$1:$1048576,MATCH(DATE(AO$2,1,1),Hybrid!$A$1:$LI$1),FALSE) -> 306.45445
C37: ELEC | E37: AUTO_cele_0 | F37: =VLOOKUP($E37,Hybrid!$1:$1048576,MATCH(DATE(F$2,1,1),Hybrid!$A$1:$LI$1),FALSE) -> 44.765 | G37: =VLOOKUP($E37,Hybrid!$1:$1048576,MATCH(DATE(G$2,1,1),Hybrid!$A$1:$LI$1),FALSE) -> 95.818005 | H37: =VLOOKUP($E37,Hybrid!$1:$1048576,MATCH(DATE(H$2,1,1),Hybrid!$A$1:$LI$1),FALSE) -> 194.70329 | I37: =VLOOKUP($E37,Hybrid!$1:$1048576,MATCH(DATE(I$2,1,1),Hybrid!$A$1:$LI$1),FALSE) -> 367.91774 | J37: =VLOOKUP($E37,Hybrid!$1:$1048576,MATCH(DATE(J$2,1,1),Hybrid!$A$1:$LI$1),FALSE) -> 638.04027 | K37: =VLOOKUP($E37,Hybrid!$1:$1048576,MATCH(DATE(K$2,1,1),Hybrid!$A$1:$LI$1),FALSE) -> 1002.8291 | L37: =VLOOKUP($E37,Hybrid!$1:$1048576,MATCH(DATE(L$2,1,1),Hybrid!$A$1:$LI$1),FALSE) -> 1467.9273 | M37: =VLOOKUP($E37,Hybrid!$1:$1048576,MATCH(DATE(M$2,1,1),Hybrid!$A$1:$LI$1),FALSE) -> 2078.719 | ... AO37: =VLOOKUP($E37,Hybrid!$1:$1048576,MATCH(DATE(AO$2,1,1),Hybrid!$A$1:$LI$1),FALSE) -> 43564.238
D38: class A | E38: AUTO_ca_cele_0 | F38: =VLOOKUP($E38,Hybrid!$1:$1048576,MATCH(DATE(F$2,1,1),Hybrid!$A$1:$LI$1),FALSE) -> 9.8427899 | G38: =VLOOKUP($E38,Hybrid!$1:$1048576,MATCH(DATE(G$2,1,1),Hybrid!$A$1:$LI$1),FALSE) -> 24.308529 | H38: =VLOOKUP($E38,Hybrid!$1:$1048576,MATCH(DATE(H$2,1,1),Hybrid!$A$1:$LI$1),FALSE) -> 52.397495 | I38: =VLOOKUP($E38,Hybrid!$1:$1048576,MATCH(DATE(I$2,1,1),Hybrid!$A$1:$LI$1),FALSE) -> 101.94149 | J38: =VLOOKUP($E38,Hybrid!$1:$1048576,MATCH(DATE(J$2,1,1),Hybrid!$A$1:$LI$1),FALSE) -> 179.82206 | K38: =VLOOKUP($E38,Hybrid!$1:$1048576,MATCH(DATE(K$2,1,1),Hybrid!$A$1:$LI$1),FALSE) -> 285.67404 | L38: =VLOOKUP($E38,Hybrid!$1:$1048576,MATCH(DATE(L$2,1,1),Hybrid!$A$1:$LI$1),FALSE) -> 421.70377 | M38: =VLOOKUP($E38,Hybrid!$1:$1048576,MATCH(DATE(M$2,1,1),Hybrid!$A$1:$LI$1),FALSE) -> 602.56081 | ... AO38: =VLOOKUP($E38,Hybrid!$1:$1048576,MATCH(DATE(AO$2,1,1),Hybrid!$A$1:$LI$1),FALSE) -> 13418.522
D39: class B | E39: AUTO_cb_cele_0 | F39: =VLOOKUP($E39,Hybrid!$1:$1048576,MATCH(DATE(F$2,1,1),Hybrid!$A$1:$LI$1),FALSE) -> 11.445717 | G39: =VLOOKUP($E39,Hybrid!$1:$1048576,MATCH(DATE(G$2,1,1),Hybrid!$A$1:$LI$1),FALSE) -> 26.55309 | H39: =VLOOKUP($E39,Hybrid!$1:$1048576,MATCH(DATE(H$2,1,1),Hybrid!$A$1:$LI$1),FALSE) -> 56.492548 | I39: =VLOOKUP($E39,Hybrid!$1:$1048576,MATCH(DATE(I$2,1,1),Hybrid!$A$1:$LI$1),FALSE) -> 109.67056 | J39: =VLOOKUP($E39,Hybrid!$1:$1048576,MATCH(DATE(J$2,1,1),Hybrid!$A$1:$LI$1),FALSE) -> 193.30399 | K39: =VLOOKUP($E39,Hybrid!$1:$1048576,MATCH(DATE(K$2,1,1),Hybrid!$A$1:$LI$1),FALSE) -> 306.82052 | L39: =VLOOKUP($E39,Hybrid!$1:$1048576,MATCH(DATE(L$2,1,1),Hybrid!$A$1:$LI$1),FALSE) -> 452.17159 | M39: =VLOOKUP($E39,Hybrid!$1:$1048576,MATCH(DATE(M$2,1,1),Hybrid!$A$1:$LI$1),FALSE) -> 643.87129 | ... AO39: =VLOOKUP($E39,Hybrid!$1:$1048576,MATCH(DATE(AO$2,1,1),Hybrid!$A$1:$LI$1),FALSE) -> 13164.097
D40: class C | E40: AUTO_cc_cele_0 | F40: =VLOOKUP($E40,Hybrid!$1:$1048576,MATCH(DATE(F$2,1,1),Hybrid!$A$1:$LI$1),FALSE) -> 9.4015406 | G40: =VLOOKUP($E40,Hybrid!$1:$1048576,MATCH(DATE(G$2,1,1),Hybrid!$A$1:$LI$1),FALSE) -> 20.942646 | H40: =VLOOKUP($E40,Hybrid!$1:$1048576,MATCH(DATE(H$2,1,1),Hybrid!$A$1:$LI$1),FALSE) -> 44.274219 | I40: =VLOOKUP($E40,Hybrid!$1:$1048576,MATCH(DATE(I$2,1,1),Hybrid!$A$1:$LI$1),FALSE) -> 85.956733 | J40: =VLOOKUP($E40,Hybrid!$1:$1048576,MATCH(DATE(J$2,1,1),Hybrid!$A$1:$LI$1),FALSE) -> 151.46397 | K40: =VLOOKUP($E40,Hybrid!$1:$1048576,MATCH(DATE(K$2,1,1),Hybrid!$A$1:$LI$1),FALSE) -> 240.16919 | L40: =VLOOKUP($E40,Hybrid!$1:$1048576,MATCH(DATE(L$2,1,1),Hybrid!$A$1:$LI$1),FALSE) -> 353.21642 | M40: =VLOOKUP($E40,Hybrid!$1:$1048576,MATCH(DATE(M$2,1,1),Hybrid!$A$1:$LI$1),FALSE) -> 500.89672 | ... AO40: =VLOOKUP($E40,Hybrid!$1:$1048576,MATCH(DATE(AO$2,1,1),Hybrid!$A$1:$LI$1),FALSE) -> 9402.6182
D41: class D | E41: AUTO_cd_cele_0 | F41: =VLOOKUP($E41,Hybrid!$1:$1048576,MATCH(DATE(F$2,1,1),Hybrid!$A$1:$LI$1),FALSE) -> 5.7700713 | G41: =VLOOKUP($E41,Hybrid!$1:$1048576,MATCH(DATE(G$2,1,1),Hybrid!$A$1:$LI$1),FALSE) -> 9.8900605 | H41: =VLOOKUP($E41,Hybrid!$1:$1048576,MATCH(DATE(H$2,1,1),Hybrid!$A$1:$LI$1),FALSE) -> 17.317962 | I41: =VLOOKUP($E41,Hybrid!$1:$1048576,MATCH(DATE(I$2,1,1),Hybrid!$A$1:$LI$1),FALSE) -> 29.785459 | J41: =VLOOKUP($E41,Hybrid!$1:$1048576,MATCH(DATE(J$2,1,1),Hybrid!$A$1:$LI$1),FALSE) -> 48.781217 | K41: =VLOOKUP($E41,Hybrid!$1:$1048576,MATCH(DATE(K$2,1,1),Hybrid!$A$1:$LI$1),FALSE) -> 74.139577 | L41: =VLOOKUP($E41,Hybrid!$1:$1048576,MATCH(DATE(L$2,1,1),Hybrid!$A$1:$LI$1),FALSE) -> 106.23463 | M41: =VLOOKUP($E41,Hybrid!$1:$1048576,MATCH(DATE(M$2,1,1),Hybrid!$A$1:$LI$1),FALSE) -> 148.21494 | ... AO41: =VLOOKUP($E41,Hybrid!$1:$1048576,MATCH(DATE(AO$2,1,1),Hybrid!$A$1:$LI$1),FALSE) -> 3624.8624
D42: class E | E42: AUTO_ce_cele_0 | F42: =VLOOKUP($E42,Hybrid!$1:$1048576,MATCH(DATE(F$2,1,1),Hybrid!$A$1:$LI$1),FALSE) -> 3.4730441 | G42: =VLOOKUP($E42,Hybrid!$1:$1048576,MATCH(DATE(G$2,1,1),Hybrid!$A$1:$LI$1),FALSE) -> 6.1197834 | H42: =VLOOKUP($E42,Hybrid!$1:$1048576,MATCH(DATE(H$2,1,1),Hybrid!$A$1:$LI$1),FALSE) -> 10.922182 | I42: =VLOOKUP($E42,Hybrid!$1:$1048576,MATCH(DATE(I$2,1,1),Hybrid!$A$1:$LI$1),FALSE) -> 18.974748 | J42: =VLOOKUP($E42,Hybrid!$1:$1048576,MATCH(DATE(J$2,1,1),Hybrid!$A$1:$LI$1),FALSE) -> 31.189098 | K42: =VLOOKUP($E42,Hybrid!$1:$1048576,MATCH(DATE(K$2,1,1),Hybrid!$A$1:$LI$1),FALSE) -> 47.425313 | L42: =VLOOKUP($E42,Hybrid!$1:$1048576,MATCH(DATE(L$2,1,1),Hybrid!$A$1:$LI$1),FALSE) -> 67.843735 | M42: =VLOOKUP($E42,Hybrid!$1:$1048576,MATCH(DATE(M$2,1,1),Hybrid!$A$1:$LI$1),FALSE) -> 94.242526 | ... AO42: =VLOOKUP($E42,Hybrid!$1:$1048576,MATCH(DATE(AO$2,1,1),Hybrid!$A$1:$LI$1),FALSE) -> 2190.7862
D43: class F | E43: AUTO_cf_cele_0 | F43: =VLOOKUP($E43,Hybrid!$1:$1048576,MATCH(DATE(F$2,1,1),Hybrid!$A$1:$LI$1),FALSE) -> 1.7251505 | G43: =VLOOKUP($E43,Hybrid!$1:$1048576,MATCH(DATE(G$2,1,1),Hybrid!$A$1:$LI$1),FALSE) -> 2.7749683 | H43: =VLOOKUP($E43,Hybrid!$1:$1048576,MATCH(DATE(H$2,1,1),Hybrid!$A$1:$LI$1),FALSE) -> 4.5165418 | I43: =VLOOKUP($E43,Hybrid!$1:$1048576,MATCH(DATE(I$2,1,1),Hybrid!$A$1:$LI$1),FALSE) -> 7.249672 | J43: =VLOOKUP($E43,Hybrid!$1:$1048576,MATCH(DATE(J$2,1,1),Hybrid!$A$1:$LI$1),FALSE) -> 11.200749 | K43: =VLOOKUP($E43,Hybrid!$1:$1048576,MATCH(DATE(K$2,1,1),Hybrid!$A$1:$LI$1),FALSE) -> 16.271969 | L43: =VLOOKUP($E43,Hybrid!$1:$1048576,MATCH(DATE(L$2,1,1),Hybrid!$A$1:$LI$1),FALSE) -> 22.437544 | M43: =VLOOKUP($E43,Hybrid!$1:$1048576,MATCH(DATE(M$2,1,1),Hybrid!$A$1:$LI$1),FALSE) -> 30.108705 | ... AO43: =VLOOKUP($E43,Hybrid!$1:$1048576,MATCH(DATE(AO$2,1,1),Hybrid!$A$1:$LI$1),FALSE) -> 631.71435
D44: class G | E44: AUTO_cg_cele_0 | F44: =VLOOKUP($E44,Hybrid!$1:$1048576,MATCH(DATE(F$2,1,1),Hybrid!$A$1:$LI$1),FALSE) -> 3.1066862 | G44: =VLOOKUP($E44,Hybrid!$1:$1048576,MATCH(DATE(G$2,1,1),Hybrid!$A$1:$LI$1),FALSE) -> 5.2289267 | H44: =VLOOKUP($E44,Hybrid!$1:$1048576,MATCH(DATE(H$2,1,1),Hybrid!$A$1:$LI$1),FALSE) -> 8.7823369 | I44: =VLOOKUP($E44,Hybrid!$1:$1048576,MATCH(DATE(I$2,1,1),Hybrid!$A$1:$LI$1),FALSE) -> 14.339075 | J44: =VLOOKUP($E44,Hybrid!$1:$1048576,MATCH(DATE(J$2,1,1),Hybrid!$A$1:$LI$1),FALSE) -> 22.279182 | K44: =VLOOKUP($E44,Hybrid!$1:$1048576,MATCH(DATE(K$2,1,1),Hybrid!$A$1:$LI$1),FALSE) -> 32.328482 | L44: =VLOOKUP($E44,Hybrid!$1:$1048576,MATCH(DATE(L$2,1,1),Hybrid!$A$1:$LI$1),FALSE) -> 44.31965 | M44: =VLOOKUP($E44,Hybrid!$1:$1048576,MATCH(DATE(M$2,1,1),Hybrid!$A$1:$LI$1),FALSE) -> 58.824034 | ... AO44: =VLOOKUP($E44,Hybrid!$1:$1048576,MATCH(DATE(AO$2,1,1),Hybrid!$A$1:$LI$1),FALSE) -> 1131.6376
C45: GAS | E45: AUTO_cgas_0 | F45: =VLOOKUP($E45,Hybrid!$1:$1048576,MATCH(DATE(F$2,1,1),Hybrid!$A$1:$LI$1),FALSE) -> 1.936 | G45: =VLOOKUP($E45,Hybrid!$1:$1048576,MATCH(DATE(G$2,1,1),Hybrid!$A$1:$LI$1),FALSE) -> 1.9890157 | H45: =VLOOKUP($E45,Hybrid!$1:$1048576,MATCH(DATE(H$2,1,1),Hybrid!$A$1:$LI$1),FALSE) -> 2.0517417 | I45: =VLOOKUP($E45,Hybrid!$1:$1048576,MATCH(DATE(I$2,1,1),Hybrid!$A$1:$LI$1),FALSE) -> 2.1144021 | J45: =VLOOKUP($E45,Hybrid!$1:$1048576,MATCH(DATE(J$2,1,1),Hybrid!$A$1:$LI$1),FALSE) -> 2.1730579 | K45: =VLOOKUP($E45,Hybrid!$1:$1048576,MATCH(DATE(K$2,1,1),Hybrid!$A$1:$LI$1),FALSE) -> 2.2247929 | L45: =VLOOKUP($E45,Hybrid!$1:$1048576,MATCH(DATE(L$2,1,1),Hybrid!$A$1:$LI$1),FALSE) -> 2.2626847 | M45: =VLOOKUP($E45,Hybrid!$1:$1048576,MATCH(DATE(M$2,1,1),Hybrid!$A$1:$LI$1),FALSE) -> 2.2838545 | ... AO45: =VLOOKUP($E45,Hybrid!$1:$1048576,MATCH(DATE(AO$2,1,1),Hybrid!$A$1:$LI$1),FALSE) -> 0.5204878
D46: class A | E46: AUTO_ca_cgas_0 | F46: =VLOOKUP($E46,Hybrid!$1:$1048576,MATCH(DATE(F$2,1,1),Hybrid!$A$1:$LI$1),FALSE) -> 0.4256817 | G46: =VLOOKUP($E46,Hybrid!$1:$1048576,MATCH(DATE(G$2,1,1),Hybrid!$A$1:$LI$1),FALSE) -> 0.44858712 | H46: =VLOOKUP($E46,Hybrid!$1:$1048576,MATCH(DATE(H$2,1,1),Hybrid!$A$1:$LI$1),FALSE) -> 0.47411683 | I46: =VLOOKUP($E46,Hybrid!$1:$1048576,MATCH(DATE(I$2,1,1),Hybrid!$A$1:$LI$1),FALSE) -> 0.49952623 | J46: =VLOOKUP($E46,Hybrid!$1:$1048576,MATCH(DATE(J$2,1,1),Hybrid!$A$1:$LI$1),FALSE) -> 0.52368998 | K46: =VLOOKUP($E46,Hybrid!$1:$1048576,MATCH(DATE(K$2,1,1),Hybrid!$A$1:$LI$1),FALSE) -> 0.54572606 | L46: =VLOOKUP($E46,Hybrid!$1:$1048576,MATCH(DATE(L$2,1,1),Hybrid!$A$1:$LI$1),FALSE) -> 0.56362908 | M46: =VLOOKUP($E46,Hybrid!$1:$1048576,MATCH(DATE(M$2,1,1),Hybrid!$A$1:$LI$1),FALSE) -> 0.57657374 | ... AO46: =VLOOKUP($E46,Hybrid!$1:$1048576,MATCH(DATE(AO$2,1,1),Hybrid!$A$1:$LI$1),FALSE) -> 0.13295218
D47: class B | E47: AUTO_cb_cgas_0 | F47: =VLOOKUP($E47,Hybrid!$1:$1048576,MATCH(DATE(F$2,1,1),Hybrid!$A$1:$LI$1),FALSE) -> 0.49500523 | G47: =VLOOKUP($E47,Hybrid!$1:$1048576,MATCH(DATE(G$2,1,1),Hybrid!$A$1:$LI$1),FALSE) -> 0.51142274 | H47: =VLOOKUP($E47,Hybrid!$1:$1048576,MATCH(DATE(H$2,1,1),Hybrid!$A$1:$LI$1),FALSE) -> 0.53046267 | I47: =VLOOKUP($E47,Hybrid!$1:$1048576,MATCH(DATE(I$2,1,1),Hybrid!$A$1:$LI$1),FALSE) -> 0.54939366 | J47: =VLOOKUP($E47,Hybrid!$1:$1048576,MATCH(DATE(J$2,1,1),Hybrid!$A$1:$LI$1),FALSE) -> 0.56707726 | K47: =VLOOKUP($E47,Hybrid!$1:$1048576,MATCH(DATE(K$2,1,1),Hybrid!$A$1:$LI$1),FALSE) -> 0.58270605 | L47: =VLOOKUP($E47,Hybrid!$1:$1048576,MATCH(DATE(L$2,1,1),Hybrid!$A$1:$LI$1),FALSE) -> 0.59436439 | M47: =VLOOKUP($E47,Hybrid!$1:$1048576,MATCH(DATE(M$2,1,1),Hybrid!$A$1:$LI$1),FALSE) -> 0.60117577 | ... AO47: =VLOOKUP($E47,Hybrid!$1:$1048576,MATCH(DATE(AO$2,1,1),Hybrid!$A$1:$LI$1),FALSE) -> 0.13057268
D48: class C | E48: AUTO_cc_cgas_0 | F48: =VLOOKUP($E48,Hybrid!$1:$1048576,MATCH(DATE(F$2,1,1),Hybrid!$A$1:$LI$1),FALSE) -> 0.40659852 | G48: =VLOOKUP($E48,Hybrid!$1:$1048576,MATCH(DATE(G$2,1,1),Hybrid!$A$1:$LI$1),FALSE) -> 0.41381867 | H48: =VLOOKUP($E48,Hybrid!$1:$1048576,MATCH(DATE(H$2,1,1),Hybrid!$A$1:$LI$1),FALSE) -> 0.4229127 | I48: =VLOOKUP($E48,Hybrid!$1:$1048576,MATCH(DATE(I$2,1,1),Hybrid!$A$1:$LI$1),FALSE) -> 0.43191353 | J48: =VLOOKUP($E48,Hybrid!$1:$1048576,MATCH(DATE(J$2,1,1),Hybrid!$A$1:$LI$1),FALSE) -> 0.43999027 | K48: =VLOOKUP($E48,Hybrid!$1:$1048576,MATCH(DATE(K$2,1,1),Hybrid!$A$1:$LI$1),FALSE) -> 0.44662059 | L48: =VLOOKUP($E48,Hybrid!$1:$1048576,MATCH(DATE(L$2,1,1),Hybrid!$A$1:$LI$1),FALSE) -> 0.45049584 | M48: =VLOOKUP($E48,Hybrid!$1:$1048576,MATCH(DATE(M$2,1,1),Hybrid!$A$1:$LI$1),FALSE) -> 0.45095983 | ... AO48: =VLOOKUP($E48,Hybrid!$1:$1048576,MATCH(DATE(AO$2,1,1),Hybrid!$A$1:$LI$1),FALSE) -> 0.092817238
D49: class D | E49: AUTO_cd_cgas_0 | F49: =VLOOKUP($E49,Hybrid!$1:$1048576,MATCH(DATE(F$2,1,1),Hybrid!$A$1:$LI$1),FALSE) -> 0.24954447 | G49: =VLOOKUP($E49,Hybrid!$1:$1048576,MATCH(DATE(G$2,1,1),Hybrid!$A$1:$LI$1),FALSE) -> 0.2521407 | H49: =VLOOKUP($E49,Hybrid!$1:$1048576,MATCH(DATE(H$2,1,1),Hybrid!$A$1:$LI$1),FALSE) -> 0.25602029 | I49: =VLOOKUP($E49,Hybrid!$1:$1048576,MATCH(DATE(I$2,1,1),Hybrid!$A$1:$LI$1),FALSE) -> 0.26022406 | J49: =VLOOKUP($E49,Hybrid!$1:$1048576,MATCH(DATE(J$2,1,1),Hybrid!$A$1:$LI$1),FALSE) -> 0.26438799 | K49: =VLOOKUP($E49,Hybrid!$1:$1048576,MATCH(DATE(K$2,1,1),Hybrid!$A$1:$LI$1),FALSE) -> 0.26818899 | L49: =VLOOKUP($E49,Hybrid!$1:$1048576,MATCH(DATE(L$2,1,1),Hybrid!$A$1:$LI$1),FALSE) -> 0.27089758 | M49: =VLOOKUP($E49,Hybrid!$1:$1048576,MATCH(DATE(M$2,1,1),Hybrid!$A$1:$LI$1),FALSE) -> 0.27228408 | ... AO49: =VLOOKUP($E49,Hybrid!$1:$1048576,MATCH(DATE(AO$2,1,1),Hybrid!$A$1:$LI$1),FALSE) -> 0.067222079
D50: class E | E50: AUTO_ce_cgas_0 | F50: =VLOOKUP($E50,Hybrid!$1:$1048576,MATCH(DATE(F$2,1,1),Hybrid!$A$1:$LI$1),FALSE) -> 0.15020247 | G50: =VLOOKUP($E50,Hybrid!$1:$1048576,MATCH(DATE(G$2,1,1),Hybrid!$A$1:$LI$1),FALSE) -> 0.15195198 | H50: =VLOOKUP($E50,Hybrid!$1:$1048576,MATCH(DATE(H$2,1,1),Hybrid!$A$1:$LI$1),FALSE) -> 0.15440868 | I50: =VLOOKUP($E50,Hybrid!$1:$1048576,MATCH(DATE(I$2,1,1),Hybrid!$A$1:$LI$1),FALSE) -> 0.15697887 | J50: =VLOOKUP($E50,Hybrid!$1:$1048576,MATCH(DATE(J$2,1,1),Hybrid!$A$1:$LI$1),FALSE) -> 0.15944041 | K50: =VLOOKUP($E50,Hybrid!$1:$1048576,MATCH(DATE(K$2,1,1),Hybrid!$A$1:$LI$1),FALSE) -> 0.16160855 | L50: =VLOOKUP($E50,Hybrid!$1:$1048576,MATCH(DATE(L$2,1,1),Hybrid!$A$1:$LI$1),FALSE) -> 0.16304628 | M50: =VLOOKUP($E50,Hybrid!$1:$1048576,MATCH(DATE(M$2,1,1),Hybrid!$A$1:$LI$1),FALSE) -> 0.16360946 | ... AO50: =VLOOKUP($E50,Hybrid!$1:$1048576,MATCH(DATE(AO$2,1,1),Hybrid!$A$1:$LI$1),FALSE) -> 0.039847964
D51: class F | E51: AUTO_cf_cgas_0 | F51: =VLOOKUP($E51,Hybrid!$1:$1048576,MATCH(DATE(F$2,1,1),Hybrid!$A$1:$LI$1),FALSE) -> 0.074609436 | G51: =VLOOKUP($E51,Hybrid!$1:$1048576,MATCH(DATE(G$2,1,1),Hybrid!$A$1:$LI$1),FALSE) -> 0.075274234 | H51: =VLOOKUP($E51,Hybrid!$1:$1048576,MATCH(DATE(H$2,1,1),Hybrid!$A$1:$LI$1),FALSE) -> 0.076215928 | I51: =VLOOKUP($E51,Hybrid!$1:$1048576,MATCH(DATE(I$2,1,1),Hybrid!$A$1:$LI$1),FALSE) -> 0.077161577 | J51: =VLOOKUP($E51,Hybrid!$1:$1048576,MATCH(DATE(J$2,1,1),Hybrid!$A$1:$LI$1),FALSE) -> 0.078016858 | K51: =VLOOKUP($E51,Hybrid!$1:$1048576,MATCH(DATE(K$2,1,1),Hybrid!$A$1:$LI$1),FALSE) -> 0.078701315 | L51: =VLOOKUP($E51,Hybrid!$1:$1048576,MATCH(DATE(L$2,1,1),Hybrid!$A$1:$LI$1),FALSE) -> 0.079019016 | M51: =VLOOKUP($E51,Hybrid!$1:$1048576,MATCH(DATE(M$2,1,1),Hybrid!$A$1:$LI$1),FALSE) -> 0.078916722 | ... AO51: =VLOOKUP($E51,Hybrid!$1:$1048576,MATCH(DATE(AO$2,1,1),Hybrid!$A$1:$LI$1),FALSE) -> 0.02144062
D52: class G | E52: AUTO_cg_cgas_0 | F52: =VLOOKUP($E52,Hybrid!$1:$1048576,MATCH(DATE(F$2,1,1),Hybrid!$A$1:$LI$1),FALSE) -> 0.13435819 | G52: =VLOOKUP($E52,Hybrid!$1:$1048576,MATCH(DATE(G$2,1,1),Hybrid!$A$1:$LI$1),FALSE) -> 0.13582025 | H52: =VLOOKUP($E52,Hybrid!$1:$1048576,MATCH(DATE(H$2,1,1),Hybrid!$A$1:$LI$1),FALSE) -> 0.13760462 | I52: =VLOOKUP($E52,Hybrid!$1:$1048576,MATCH(DATE(I$2,1,1),Hybrid!$A$1:$LI$1),FALSE) -> 0.13920415 | J52: =VLOOKUP($E52,Hybrid!$1:$1048576,MATCH(DATE(J$2,1,1),Hybrid!$A$1:$LI$1),FALSE) -> 0.1404551 | K52: =VLOOKUP($E52,Hybrid!$1:$1048576,MATCH(DATE(K$2,1,1),Hybrid!$A$1:$LI$1),FALSE) -> 0.14124131 | L52: =VLOOKUP($E52,Hybrid!$1:$1048576,MATCH(DATE(L$2,1,1),Hybrid!$A$1:$LI$1),FALSE) -> 0.14123247 | M52: =VLOOKUP($E52,Hybrid!$1:$1048576,MATCH(DATE(M$2,1,1),Hybrid!$A$1:$LI$1),FALSE) -> 0.14033489 | ... AO52: =VLOOKUP($E52,Hybrid!$1:$1048576,MATCH(DATE(AO$2,1,1),Hybrid!$A$1:$LI$1),FALSE) -> 0.035635037
C53: TOTAL SALES SHOCK | E53: NEWAUTO_2 | F53: =VLOOKUP($E53,Hybrid!$1:$1048576,MATCH(DATE(F$2,1,1),Hybrid!$A$1:$LI$1),FALSE) -> 1886.229 | G53: =VLOOKUP($E53,Hybrid!$1:$1048576,MATCH(DATE(G$2,1,1),Hybrid!$A$1:$LI$1),FALSE) -> 2124.3618 | H53: =VLOOKUP($E53,Hybrid!$1:$1048576,MATCH(DATE(H$2,1,1),Hybrid!$A$1:$LI$1),FALSE) -> 2329.2745 | I53: =VLOOKUP($E53,Hybrid!$1:$1048576,MATCH(DATE(I$2,1,1),Hybrid!$A$1:$LI$1),FALSE) -> 2453.4461 | J53: =VLOOKUP($E53,Hybrid!$1:$1048576,MATCH(DATE(J$2,1,1),Hybrid!$A$1:$LI$1),FALSE) -> 2556.2319 | K53: =VLOOKUP($E53,Hybrid!$1:$1048576,MATCH(DATE(K$2,1,1),Hybrid!$A$1:$LI$1),FALSE) -> 2622.9571 | L53: =VLOOKUP($E53,Hybrid!$1:$1048576,MATCH(DATE(L$2,1,1),Hybrid!$A$1:$LI$1),FALSE) -> 2650.733 | M53: =VLOOKUP($E53,Hybrid!$1:$1048576,MATCH(DATE(M$2,1,1),Hybrid!$A$1:$LI$1),FALSE) -> 2571.7402 | ... AO53: =VLOOKUP($E53,Hybrid!$1:$1048576,MATCH(DATE(AO$2,1,1),Hybrid!$A$1:$LI$1),FALSE) -> 2861.1583
C54: OIL | E54: NEWAUTO_cfut_2 | F54: =VLOOKUP($E54,Hybrid!$1:$1048576,MATCH(DATE(F$2,1,1),Hybrid!$A$1:$LI$1),FALSE) -> 1861.6951 | G54: =VLOOKUP($E54,Hybrid!$1:$1048576,MATCH(DATE(G$2,1,1),Hybrid!$A$1:$LI$1),FALSE) -> 2071.3442 | H54: =VLOOKUP($E54,Hybrid!$1:$1048576,MATCH(DATE(H$2,1,1),Hybrid!$A$1:$LI$1),FALSE) -> 2226.3695 | I54: =VLOOKUP($E54,Hybrid!$1:$1048576,MATCH(DATE(I$2,1,1),Hybrid!$A$1:$LI$1),FALSE) -> 2272.2526 | J54: =VLOOKUP($E54,Hybrid!$1:$1048576,MATCH(DATE(J$2,1,1),Hybrid!$A$1:$LI$1),FALSE) -> 2271.2019 | K54: =VLOOKUP($E54,Hybrid!$1:$1048576,MATCH(DATE(K$2,1,1),Hybrid!$A$1:$LI$1),FALSE) -> 2232.4591 | L54: =VLOOKUP($E54,Hybrid!$1:$1048576,MATCH(DATE(L$2,1,1),Hybrid!$A$1:$LI$1),FALSE) -> 2152.7394 | M54: =VLOOKUP($E54,Hybrid!$1:$1048576,MATCH(DATE(M$2,1,1),Hybrid!$A$1:$LI$1),FALSE) -> 1928.9058 | ... AO54: =VLOOKUP($E54,Hybrid!$1:$1048576,MATCH(DATE(AO$2,1,1),Hybrid!$A$1:$LI$1),FALSE) -> 1.7768503
D55: class A | E55: NEWAUTO_ca_cfut_2 | F55: =VLOOKUP($E55,Hybrid!$1:$1048576,MATCH(DATE(F$2,1,1),Hybrid!$A$1:$LI$1),FALSE) -> 526.72343 | G55: =VLOOKUP($E55,Hybrid!$1:$1048576,MATCH(DATE(G$2,1,1),Hybrid!$A$1:$LI$1),FALSE) -> 589.33388 | H55: =VLOOKUP($E55,Hybrid!$1:$1048576,MATCH(DATE(H$2,1,1),Hybrid!$A$1:$LI$1),FALSE) -> 637.61185 | I55: =VLOOKUP($E55,Hybrid!$1:$1048576,MATCH(DATE(I$2,1,1),Hybrid!$A$1:$LI$1),FALSE) -> 655.17258 | J55: =VLOOKUP($E55,Hybrid!$1:$1048576,MATCH(DATE(J$2,1,1),Hybrid!$A$1:$LI$1),FALSE) -> 659.24877 | K55: =VLOOKUP($E55,Hybrid!$1:$1048576,MATCH(DATE(K$2,1,1),Hybrid!$A$1:$LI$1),FALSE) -> 651.8992 | L55: =VLOOKUP($E55,Hybrid!$1:$1048576,MATCH(DATE(L$2,1,1),Hybrid!$A$1:$LI$1),FALSE) -> 632.49457 | M55: =VLOOKUP($E55,Hybrid!$1:$1048576,MATCH(DATE(M$2,1,1),Hybrid!$A$1:$LI$1),FALSE) -> 571.62308 | ... AO55: =VLOOKUP($E55,Hybrid!$1:$1048576,MATCH(DATE(AO$2,1,1),Hybrid!$A$1:$LI$1),FALSE) -> 0.039199376
D56: class B | E56: NEWAUTO_cb_cfut_2 | F56: =VLOOKUP($E56,Hybrid!$1:$1048576,MATCH(DATE(F$2,1,1),Hybrid!$A$1:$LI$1),FALSE) -> 505.4013 | G56: =VLOOKUP($E56,Hybrid!$1:$1048576,MATCH(DATE(G$2,1,1),Hybrid!$A$1:$LI$1),FALSE) -> 563.68023 | H56: =VLOOKUP($E56,Hybrid!$1:$1048576,MATCH(DATE(H$2,1,1),Hybrid!$A$1:$LI$1),FALSE) -> 607.10929 | I56: =VLOOKUP($E56,Hybrid!$1:$1048576,MATCH(DATE(I$2,1,1),Hybrid!$A$1:$LI$1),FALSE) -> 619.9772 | J56: =VLOOKUP($E56,Hybrid!$1:$1048576,MATCH(DATE(J$2,1,1),Hybrid!$A$1:$LI$1),FALSE) -> 619.21305 | K56: =VLOOKUP($E56,Hybrid!$1:$1048576,MATCH(DATE(K$2,1,1),Hybrid!$A$1:$LI$1),FALSE) -> 607.90995 | L56: =VLOOKUP($E56,Hybrid!$1:$1048576,MATCH(DATE(L$2,1,1),Hybrid!$A$1:$LI$1),FALSE) -> 585.3393 | M56: =VLOOKUP($E56,Hybrid!$1:$1048576,MATCH(DATE(M$2,1,1),Hybrid!$A$1:$LI$1),FALSE) -> 522.31666 | ... AO56: =VLOOKUP($E56,Hybrid!$1:$1048576,MATCH(DATE(AO$2,1,1),Hybrid!$A$1:$LI$1),FALSE) -> 0.017297923
D57: class C | E57: NEWAUTO_cc_cfut_2 | F57: =VLOOKUP($E57,Hybrid!$1:$1048576,MATCH(DATE(F$2,1,1),Hybrid!$A$1:$LI$1),FALSE) -> 349.58537 | G57: =VLOOKUP($E57,Hybrid!$1:$1048576,MATCH(DATE(G$2,1,1),Hybrid!$A$1:$LI$1),FALSE) -> 388.43199 | H57: =VLOOKUP($E57,Hybrid!$1:$1048576,MATCH(DATE(H$2,1,1),Hybrid!$A$1:$LI$1),FALSE) -> 416.10866 | I57: =VLOOKUP($E57,Hybrid!$1:$1048576,MATCH(DATE(I$2,1,1),Hybrid!$A$1:$LI$1),FALSE) -> 421.76469 | J57: =VLOOKUP($E57,Hybrid!$1:$1048576,MATCH(DATE(J$2,1,1),Hybrid!$A$1:$LI$1),FALSE) -> 417.46122 | K57: =VLOOKUP($E57,Hybrid!$1:$1048576,MATCH(DATE(K$2,1,1),Hybrid!$A$1:$LI$1),FALSE) -> 406.25292 | L57: =VLOOKUP($E57,Hybrid!$1:$1048576,MATCH(DATE(L$2,1,1),Hybrid!$A$1:$LI$1),FALSE) -> 387.56646 | M57: =VLOOKUP($E57,Hybrid!$1:$1048576,MATCH(DATE(M$2,1,1),Hybrid!$A$1:$LI$1),FALSE) -> 340.59929 | ... AO57: =VLOOKUP($E57,Hybrid!$1:$1048576,MATCH(DATE(AO$2,1,1),Hybrid!$A$1:$LI$1),FALSE) -> 0.0048320219
D58: class D | E58: NEWAUTO_cd_cfut_2 | F58: =VLOOKUP($E58,Hybrid!$1:$1048576,MATCH(DATE(F$2,1,1),Hybrid!$A$1:$LI$1),FALSE) -> 194.22503 | G58: =VLOOKUP($E58,Hybrid!$1:$1048576,MATCH(DATE(G$2,1,1),Hybrid!$A$1:$LI$1),FALSE) -> 216.55224 | H58: =VLOOKUP($E58,Hybrid!$1:$1048576,MATCH(DATE(H$2,1,1),Hybrid!$A$1:$LI$1),FALSE) -> 233.75967 | I58: =VLOOKUP($E58,Hybrid!$1:$1048576,MATCH(DATE(I$2,1,1),Hybrid!$A$1:$LI$1),FALSE) -> 240.50463 | J58: =VLOOKUP($E58,Hybrid!$1:$1048576,MATCH(DATE(J$2,1,1),Hybrid!$A$1:$LI$1),FALSE) -> 243.15792 | K58: =VLOOKUP($E58,Hybrid!$1:$1048576,MATCH(DATE(K$2,1,1),Hybrid!$A$1:$LI$1),FALSE) -> 241.93549 | L58: =VLOOKUP($E58,Hybrid!$1:$1048576,MATCH(DATE(L$2,1,1),Hybrid!$A$1:$LI$1),FALSE) -> 236.39219 | M58: =VLOOKUP($E58,Hybrid!$1:$1048576,MATCH(DATE(M$2,1,1),Hybrid!$A$1:$LI$1),FALSE) -> 216.59237 | ... AO58: =VLOOKUP($E58,Hybrid!$1:$1048576,MATCH(DATE(AO$2,1,1),Hybrid!$A$1:$LI$1),FALSE) -> 0.35613789
D59: class E | E59: NEWAUTO_ce_cfut_2 | F59: =VLOOKUP($E59,Hybrid!$1:$1048576,MATCH(DATE(F$2,1,1),Hybrid!$A$1:$LI$1),FALSE) -> 119.45246 | G59: =VLOOKUP($E59,Hybrid!$1:$1048576,MATCH(DATE(G$2,1,1),Hybrid!$A$1:$LI$1),FALSE) -> 132.56802 | H59: =VLOOKUP($E59,Hybrid!$1:$1048576,MATCH(DATE(H$2,1,1),Hybrid!$A$1:$LI$1),FALSE) -> 142.28728 | I59: =VLOOKUP($E59,Hybrid!$1:$1048576,MATCH(DATE(I$2,1,1),Hybrid!$A$1:$LI$1),FALSE) -> 145.46591 | J59: =VLOOKUP($E59,Hybrid!$1:$1048576,MATCH(DATE(J$2,1,1),Hybrid!$A$1:$LI$1),FALSE) -> 146.08461 | K59: =VLOOKUP($E59,Hybrid!$1:$1048576,MATCH(DATE(K$2,1,1),Hybrid!$A$1:$LI$1),FALSE) -> 144.42357 | L59: =VLOOKUP($E59,Hybrid!$1:$1048576,MATCH(DATE(L$2,1,1),Hybrid!$A$1:$LI$1),FALSE) -> 140.16794 | M59: =VLOOKUP($E59,Hybrid!$1:$1048576,MATCH(DATE(M$2,1,1),Hybrid!$A$1:$LI$1),FALSE) -> 127.17688 | ... AO59: =VLOOKUP($E59,Hybrid!$1:$1048576,MATCH(DATE(AO$2,1,1),Hybrid!$A$1:$LI$1),FALSE) -> 0.20997065
D60: class F | E60: NEWAUTO_cf_cfut_2 | F60: =VLOOKUP($E60,Hybrid!$1:$1048576,MATCH(DATE(F$2,1,1),Hybrid!$A$1:$LI$1),FALSE) -> 57.812175 | G60: =VLOOKUP($E60,Hybrid!$1:$1048576,MATCH(DATE(G$2,1,1),Hybrid!$A$1:$LI$1),FALSE) -> 63.418931 | H60: =VLOOKUP($E60,Hybrid!$1:$1048576,MATCH(DATE(H$2,1,1),Hybrid!$A$1:$LI$1),FALSE) -> 67.209458 | I60: =VLOOKUP($E60,Hybrid!$1:$1048576,MATCH(DATE(I$2,1,1),Hybrid!$A$1:$LI$1),FALSE) -> 67.957114 | J60: =VLOOKUP($E60,Hybrid!$1:$1048576,MATCH(DATE(J$2,1,1),Hybrid!$A$1:$LI$1),FALSE) -> 67.584966 | K60: =VLOOKUP($E60,Hybrid!$1:$1048576,MATCH(DATE(K$2,1,1),Hybrid!$A$1:$LI$1),FALSE) -> 66.187884 | L60: =VLOOKUP($E60,Hybrid!$1:$1048576,MATCH(DATE(L$2,1,1),Hybrid!$A$1:$LI$1),FALSE) -> 63.577015 | M60: =VLOOKUP($E60,Hybrid!$1:$1048576,MATCH(DATE(M$2,1,1),Hybrid!$A$1:$LI$1),FALSE) -> 57.051356 | ... AO60: =VLOOKUP($E60,Hybrid!$1:$1048576,MATCH(DATE(AO$2,1,1),Hybrid!$A$1:$LI$1),FALSE) -> 0.47980585
D61: class G | E61: NEWAUTO_cg_cfut_2 | F61: =VLOOKUP($E61,Hybrid!$1:$1048576,MATCH(DATE(F$2,1,1),Hybrid!$A$1:$LI$1),FALSE) -> 108.49532 | G61: =VLOOKUP($E61,Hybrid!$1:$1048576,MATCH(DATE(G$2,1,1),Hybrid!$A$1:$LI$1),FALSE) -> 117.35892 | H61: =VLOOKUP($E61,Hybrid!$1:$1048576,MATCH(DATE(H$2,1,1),Hybrid!$A$1:$LI$1),FALSE) -> 122.28329 | I61: =VLOOKUP($E61,Hybrid!$1:$1048576,MATCH(DATE(I$2,1,1),Hybrid!$A$1:$LI$1),FALSE) -> 121.41046 | J61: =VLOOKUP($E61,Hybrid!$1:$1048576,MATCH(DATE(J$2,1,1),Hybrid!$A$1:$LI$1),FALSE) -> 118.45131 | K61: =VLOOKUP($E61,Hybrid!$1:$1048576,MATCH(DATE(K$2,1,1),Hybrid!$A$1:$LI$1),FALSE) -> 113.85006 | L61: =VLOOKUP($E61,Hybrid!$1:$1048576,MATCH(DATE(L$2,1,1),Hybrid!$A$1:$LI$1),FALSE) -> 107.20192 | M61: =VLOOKUP($E61,Hybrid!$1:$1048576,MATCH(DATE(M$2,1,1),Hybrid!$A$1:$LI$1),FALSE) -> 93.546192 | ... AO61: =VLOOKUP($E61,Hybrid!$1:$1048576,MATCH(DATE(AO$2,1,1),Hybrid!$A$1:$LI$1),FALSE) -> 0.66960661
C62: ELEC | E62: NEWAUTO_cele_2 | F62: =VLOOKUP($E62,Hybrid!$1:$1048576,MATCH(DATE(F$2,1,1),Hybrid!$A$1:$LI$1),FALSE) -> 24.377505 | G62: =VLOOKUP($E62,Hybrid!$1:$1048576,MATCH(DATE(G$2,1,1),Hybrid!$A$1:$LI$1),FALSE) -> 52.843605 | H62: =VLOOKUP($E62,Hybrid!$1:$1048576,MATCH(DATE(H$2,1,1),Hybrid!$A$1:$LI$1),FALSE) -> 102.718 | I62: =VLOOKUP($E62,Hybrid!$1:$1048576,MATCH(DATE(I$2,1,1),Hybrid!$A$1:$LI$1),FALSE) -> 181.00259 | J62: =VLOOKUP($E62,Hybrid!$1:$1048576,MATCH(DATE(J$2,1,1),Hybrid!$A$1:$LI$1),FALSE) -> 284.83924 | K62: =VLOOKUP($E62,Hybrid!$1:$1048576,MATCH(DATE(K$2,1,1),Hybrid!$A$1:$LI$1),FALSE) -> 390.31043 | L62: =VLOOKUP($E62,Hybrid!$1:$1048576,MATCH(DATE(L$2,1,1),Hybrid!$A$1:$LI$1),FALSE) -> 497.81272 | M62: =VLOOKUP($E62,Hybrid!$1:$1048576,MATCH(DATE(M$2,1,1),Hybrid!$A$1:$LI$1),FALSE) -> 642.67238 | ... AO62: =VLOOKUP($E62,Hybrid!$1:$1048576,MATCH(DATE(AO$2,1,1),Hybrid!$A$1:$LI$1),FALSE) -> 2859.3813
D63: class A | E63: NEWAUTO_ca_cele_2 | F63: =VLOOKUP($E63,Hybrid!$1:$1048576,MATCH(DATE(F$2,1,1),Hybrid!$A$1:$LI$1),FALSE) -> 6.846501 | G63: =VLOOKUP($E63,Hybrid!$1:$1048576,MATCH(DATE(G$2,1,1),Hybrid!$A$1:$LI$1),FALSE) -> 14.859451 | H63: =VLOOKUP($E63,Hybrid!$1:$1048576,MATCH(DATE(H$2,1,1),Hybrid!$A$1:$LI$1),FALSE) -> 29.061308 | I63: =VLOOKUP($E63,Hybrid!$1:$1048576,MATCH(DATE(I$2,1,1),Hybrid!$A$1:$LI$1),FALSE) -> 51.639899 | J63: =VLOOKUP($E63,Hybrid!$1:$1048576,MATCH(DATE(J$2,1,1),Hybrid!$A$1:$LI$1),FALSE) -> 81.95823 | K63: =VLOOKUP($E63,Hybrid!$1:$1048576,MATCH(DATE(K$2,1,1),Hybrid!$A$1:$LI$1),FALSE) -> 113.04486 | L63: =VLOOKUP($E63,Hybrid!$1:$1048576,MATCH(DATE(L$2,1,1),Hybrid!$A$1:$LI$1),FALSE) -> 145.10718 | M63: =VLOOKUP($E63,Hybrid!$1:$1048576,MATCH(DATE(M$2,1,1),Hybrid!$A$1:$LI$1),FALSE) -> 189.61411 | ... AO63: =VLOOKUP($E63,Hybrid!$1:$1048576,MATCH(DATE(AO$2,1,1),Hybrid!$A$1:$LI$1),FALSE) -> 910.45133
D64: class B | E64: NEWAUTO_cb_cele_2 | F64: =VLOOKUP($E64,Hybrid!$1:$1048576,MATCH(DATE(F$2,1,1),Hybrid!$A$1:$LI$1),FALSE) -> 6.8560367 | G64: =VLOOKUP($E64,Hybrid!$1:$1048576,MATCH(DATE(G$2,1,1),Hybrid!$A$1:$LI$1),FALSE) -> 15.565202 | H64: =VLOOKUP($E64,Hybrid!$1:$1048576,MATCH(DATE(H$2,1,1),Hybrid!$A$1:$LI$1),FALSE) -> 31.001581 | I64: =VLOOKUP($E64,Hybrid!$1:$1048576,MATCH(DATE(I$2,1,1),Hybrid!$A$1:$LI$1),FALSE) -> 55.437715 | J64: =VLOOKUP($E64,Hybrid!$1:$1048576,MATCH(DATE(J$2,1,1),Hybrid!$A$1:$LI$1),FALSE) -> 88.02025 | K64: =VLOOKUP($E64,Hybrid!$1:$1048576,MATCH(DATE(K$2,1,1),Hybrid!$A$1:$LI$1),FALSE) -> 121.24869 | L64: =VLOOKUP($E64,Hybrid!$1:$1048576,MATCH(DATE(L$2,1,1),Hybrid!$A$1:$LI$1),FALSE) -> 155.26241 | M64: =VLOOKUP($E64,Hybrid!$1:$1048576,MATCH(DATE(M$2,1,1),Hybrid!$A$1:$LI$1),FALSE) -> 201.3649 | ... AO64: =VLOOKUP($E64,Hybrid!$1:$1048576,MATCH(DATE(AO$2,1,1),Hybrid!$A$1:$LI$1),FALSE) -> 883.44743
D65: class C | E65: NEWAUTO_cc_cele_2 | F65: =VLOOKUP($E65,Hybrid!$1:$1048576,MATCH(DATE(F$2,1,1),Hybrid!$A$1:$LI$1),FALSE) -> 4.9963127 | G65: =VLOOKUP($E65,Hybrid!$1:$1048576,MATCH(DATE(G$2,1,1),Hybrid!$A$1:$LI$1),FALSE) -> 11.917167 | H65: =VLOOKUP($E65,Hybrid!$1:$1048576,MATCH(DATE(H$2,1,1),Hybrid!$A$1:$LI$1),FALSE) -> 24.169279 | I65: =VLOOKUP($E65,Hybrid!$1:$1048576,MATCH(DATE(I$2,1,1),Hybrid!$A$1:$LI$1),FALSE) -> 43.453483 | J65: =VLOOKUP($E65,Hybrid!$1:$1048576,MATCH(DATE(J$2,1,1),Hybrid!$A$1:$LI$1),FALSE) -> 68.94551 | K65: =VLOOKUP($E65,Hybrid!$1:$1048576,MATCH(DATE(K$2,1,1),Hybrid!$A$1:$LI$1),FALSE) -> 94.763773 | L65: =VLOOKUP($E65,Hybrid!$1:$1048576,MATCH(DATE(L$2,1,1),Hybrid!$A$1:$LI$1),FALSE) -> 120.95052 | M65: =VLOOKUP($E65,Hybrid!$1:$1048576,MATCH(DATE(M$2,1,1),Hybrid!$A$1:$LI$1),FALSE) -> 155.48034 | ... AO65: =VLOOKUP($E65,Hybrid!$1:$1048576,MATCH(DATE(AO$2,1,1),Hybrid!$A$1:$LI$1),FALSE) -> 626.25985
D66: class D | E66: NEWAUTO_cd_cele_2 | F66: =VLOOKUP($E66,Hybrid!$1:$1048576,MATCH(DATE(F$2,1,1),Hybrid!$A$1:$LI$1),FALSE) -> 2.3037098 | G66: =VLOOKUP($E66,Hybrid!$1:$1048576,MATCH(DATE(G$2,1,1),Hybrid!$A$1:$LI$1),FALSE) -> 4.3507921 | H66: =VLOOKUP($E66,Hybrid!$1:$1048576,MATCH(DATE(H$2,1,1),Hybrid!$A$1:$LI$1),FALSE) -> 7.8235043 | I66: =VLOOKUP($E66,Hybrid!$1:$1048576,MATCH(DATE(I$2,1,1),Hybrid!$A$1:$LI$1),FALSE) -> 13.160215 | J66: =VLOOKUP($E66,Hybrid!$1:$1048576,MATCH(DATE(J$2,1,1),Hybrid!$A$1:$LI$1),FALSE) -> 20.187176 | K66: =VLOOKUP($E66,Hybrid!$1:$1048576,MATCH(DATE(K$2,1,1),Hybrid!$A$1:$LI$1),FALSE) -> 27.309609 | L66: =VLOOKUP($E66,Hybrid!$1:$1048576,MATCH(DATE(L$2,1,1),Hybrid!$A$1:$LI$1),FALSE) -> 34.563385 | M66: =VLOOKUP($E66,Hybrid!$1:$1048576,MATCH(DATE(M$2,1,1),Hybrid!$A$1:$LI$1),FALSE) -> 44.364291 | ... AO66: =VLOOKUP($E66,Hybrid!$1:$1048576,MATCH(DATE(AO$2,1,1),Hybrid!$A$1:$LI$1),FALSE) -> 222.66686
D67: class E | E67: NEWAUTO_ce_cele_2 | F67: =VLOOKUP($E67,Hybrid!$1:$1048576,MATCH(DATE(F$2,1,1),Hybrid!$A$1:$LI$1),FALSE) -> 1.4447796 | G67: =VLOOKUP($E67,Hybrid!$1:$1048576,MATCH(DATE(G$2,1,1),Hybrid!$A$1:$LI$1),FALSE) -> 2.785661 | H67: =VLOOKUP($E67,Hybrid!$1:$1048576,MATCH(DATE(H$2,1,1),Hybrid!$A$1:$LI$1),FALSE) -> 5.0471901 | I67: =VLOOKUP($E67,Hybrid!$1:$1048576,MATCH(DATE(I$2,1,1),Hybrid!$A$1:$LI$1),FALSE) -> 8.4894535 | J67: =VLOOKUP($E67,Hybrid!$1:$1048576,MATCH(DATE(J$2,1,1),Hybrid!$A$1:$LI$1),FALSE) -> 12.973339 | K67: =VLOOKUP($E67,Hybrid!$1:$1048576,MATCH(DATE(K$2,1,1),Hybrid!$A$1:$LI$1),FALSE) -> 17.483779 | L67: =VLOOKUP($E67,Hybrid!$1:$1048576,MATCH(DATE(L$2,1,1),Hybrid!$A$1:$LI$1),FALSE) -> 22.026892 | M67: =VLOOKUP($E67,Hybrid!$1:$1048576,MATCH(DATE(M$2,1,1),Hybrid!$A$1:$LI$1),FALSE) -> 27.961135 | ... AO67: =VLOOKUP($E67,Hybrid!$1:$1048576,MATCH(DATE(AO$2,1,1),Hybrid!$A$1:$LI$1),FALSE) -> 130.16798
D68: class F | E68: NEWAUTO_cf_cele_2 | F68: =VLOOKUP($E68,Hybrid!$1:$1048576,MATCH(DATE(F$2,1,1),Hybrid!$A$1:$LI$1),FALSE) -> 0.65606728 | G68: =VLOOKUP($E68,Hybrid!$1:$1048576,MATCH(DATE(G$2,1,1),Hybrid!$A$1:$LI$1),FALSE) -> 1.1188238 | H68: =VLOOKUP($E68,Hybrid!$1:$1048576,MATCH(DATE(H$2,1,1),Hybrid!$A$1:$LI$1),FALSE) -> 1.8525722 | I68: =VLOOKUP($E68,Hybrid!$1:$1048576,MATCH(DATE(I$2,1,1),Hybrid!$A$1:$LI$1),FALSE) -> 2.9137919 | J68: =VLOOKUP($E68,Hybrid!$1:$1048576,MATCH(DATE(J$2,1,1),Hybrid!$A$1:$LI$1),FALSE) -> 4.2410634 | K68: =VLOOKUP($E68,Hybrid!$1:$1048576,MATCH(DATE(K$2,1,1),Hybrid!$A$1:$LI$1),FALSE) -> 5.51925 | L68: =VLOOKUP($E68,Hybrid!$1:$1048576,MATCH(DATE(L$2,1,1),Hybrid!$A$1:$LI$1),FALSE) -> 6.7419611 | M68: =VLOOKUP($E68,Hybrid!$1:$1048576,MATCH(DATE(M$2,1,1),Hybrid!$A$1:$LI$1),FALSE) -> 8.2356474 | ... AO68: =VLOOKUP($E68,Hybrid!$1:$1048576,MATCH(DATE(AO$2,1,1),Hybrid!$A$1:$LI$1),FALSE) -> 32.462182
D69: class G | E69: NEWAUTO_cg_cele_2 | F69: =VLOOKUP($E69,Hybrid!$1:$1048576,MATCH(DATE(F$2,1,1),Hybrid!$A$1:$LI$1),FALSE) -> 1.2740979 | G69: =VLOOKUP($E69,Hybrid!$1:$1048576,MATCH(DATE(G$2,1,1),Hybrid!$A$1:$LI$1),FALSE) -> 2.246508 | H69: =VLOOKUP($E69,Hybrid!$1:$1048576,MATCH(DATE(H$2,1,1),Hybrid!$A$1:$LI$1),FALSE) -> 3.7625672 | I69: =VLOOKUP($E69,Hybrid!$1:$1048576,MATCH(DATE(I$2,1,1),Hybrid!$A$1:$LI$1),FALSE) -> 5.9080317 | J69: =VLOOKUP($E69,Hybrid!$1:$1048576,MATCH(DATE(J$2,1,1),Hybrid!$A$1:$LI$1),FALSE) -> 8.5136702 | K69: =VLOOKUP($E69,Hybrid!$1:$1048576,MATCH(DATE(K$2,1,1),Hybrid!$A$1:$LI$1),FALSE) -> 10.940467 | L69: =VLOOKUP($E69,Hybrid!$1:$1048576,MATCH(DATE(L$2,1,1),Hybrid!$A$1:$LI$1),FALSE) -> 13.160364 | M69: =VLOOKUP($E69,Hybrid!$1:$1048576,MATCH(DATE(M$2,1,1),Hybrid!$A$1:$LI$1),FALSE) -> 15.651948 | ... AO69: =VLOOKUP($E69,Hybrid!$1:$1048576,MATCH(DATE(AO$2,1,1),Hybrid!$A$1:$LI$1),FALSE) -> 53.925717
C70: GAS | E70: NEWAUTO_cgas_2 | F70: =VLOOKUP($E70,Hybrid!$1:$1048576,MATCH(DATE(F$2,1,1),Hybrid!$A$1:$LI$1),FALSE) -> 0.15640286 | G70: =VLOOKUP($E70,Hybrid!$1:$1048576,MATCH(DATE(G$2,1,1),Hybrid!$A$1:$LI$1),FALSE) -> 0.17401569 | H70: =VLOOKUP($E70,Hybrid!$1:$1048576,MATCH(DATE(H$2,1,1),Hybrid!$A$1:$LI$1),FALSE) -> 0.18703952 | I70: =VLOOKUP($E70,Hybrid!$1:$1048576,MATCH(DATE(I$2,1,1),Hybrid!$A$1:$LI$1),FALSE) -> 0.1908942 | J70: =VLOOKUP($E70,Hybrid!$1:$1048576,MATCH(DATE(J$2,1,1),Hybrid!$A$1:$LI$1),FALSE) -> 0.19080593 | K70: =VLOOKUP($E70,Hybrid!$1:$1048576,MATCH(DATE(K$2,1,1),Hybrid!$A$1:$LI$1),FALSE) -> 0.18755111 | L70: =VLOOKUP($E70,Hybrid!$1:$1048576,MATCH(DATE(L$2,1,1),Hybrid!$A$1:$LI$1),FALSE) -> 0.18085378 | M70: =VLOOKUP($E70,Hybrid!$1:$1048576,MATCH(DATE(M$2,1,1),Hybrid!$A$1:$LI$1),FALSE) -> 0.1620493 | ... AO70: =VLOOKUP($E70,Hybrid!$1:$1048576,MATCH(DATE(AO$2,1,1),Hybrid!$A$1:$LI$1),FALSE) -> 0.00014927496
D71: class A | E71: NEWAUTO_ca_cgas_2 | F71: =VLOOKUP($E71,Hybrid!$1:$1048576,MATCH(DATE(F$2,1,1),Hybrid!$A$1:$LI$1),FALSE) -> 0.04425056 | G71: =VLOOKUP($E71,Hybrid!$1:$1048576,MATCH(DATE(G$2,1,1),Hybrid!$A$1:$LI$1),FALSE) -> 0.049510526 | H71: =VLOOKUP($E71,Hybrid!$1:$1048576,MATCH(DATE(H$2,1,1),Hybrid!$A$1:$LI$1),FALSE) -> 0.053566406 | I71: =VLOOKUP($E71,Hybrid!$1:$1048576,MATCH(DATE(I$2,1,1),Hybrid!$A$1:$LI$1),FALSE) -> 0.0550417 | J71: =VLOOKUP($E71,Hybrid!$1:$1048576,MATCH(DATE(J$2,1,1),Hybrid!$A$1:$LI$1),FALSE) -> 0.055384146 | K71: =VLOOKUP($E71,Hybrid!$1:$1048576,MATCH(DATE(K$2,1,1),Hybrid!$A$1:$LI$1),FALSE) -> 0.054766701 | L71: =VLOOKUP($E71,Hybrid!$1:$1048576,MATCH(DATE(L$2,1,1),Hybrid!$A$1:$LI$1),FALSE) -> 0.053136498 | M71: =VLOOKUP($E71,Hybrid!$1:$1048576,MATCH(DATE(M$2,1,1),Hybrid!$A$1:$LI$1),FALSE) -> 0.048022624 | ... AO71: =VLOOKUP($E71,Hybrid!$1:$1048576,MATCH(DATE(AO$2,1,1),Hybrid!$A$1:$LI$1),FALSE) -> 3.2931786e-06
D72: class B | E72: NEWAUTO_cb_cgas_2 | F72: =VLOOKUP($E72,Hybrid!$1:$1048576,MATCH(DATE(F$2,1,1),Hybrid!$A$1:$LI$1),FALSE) -> 0.042459266 | G72: =VLOOKUP($E72,Hybrid!$1:$1048576,MATCH(DATE(G$2,1,1),Hybrid!$A$1:$LI$1),FALSE) -> 0.047355337 | H72: =VLOOKUP($E72,Hybrid!$1:$1048576,MATCH(DATE(H$2,1,1),Hybrid!$A$1:$LI$1),FALSE) -> 0.051003856 | I72: =VLOOKUP($E72,Hybrid!$1:$1048576,MATCH(DATE(I$2,1,1),Hybrid!$A$1:$LI$1),FALSE) -> 0.052084902 | J72: =VLOOKUP($E72,Hybrid!$1:$1048576,MATCH(DATE(J$2,1,1),Hybrid!$A$1:$LI$1),FALSE) -> 0.052020705 | K72: =VLOOKUP($E72,Hybrid!$1:$1048576,MATCH(DATE(K$2,1,1),Hybrid!$A$1:$LI$1),FALSE) -> 0.05107112 | L72: =VLOOKUP($E72,Hybrid!$1:$1048576,MATCH(DATE(L$2,1,1),Hybrid!$A$1:$LI$1),FALSE) -> 0.049174937 | M72: =VLOOKUP($E72,Hybrid!$1:$1048576,MATCH(DATE(M$2,1,1),Hybrid!$A$1:$LI$1),FALSE) -> 0.043880343 | ... AO72: =VLOOKUP($E72,Hybrid!$1:$1048576,MATCH(DATE(AO$2,1,1),Hybrid!$A$1:$LI$1),FALSE) -> 1.4532158e-06
D73: class C | E73: NEWAUTO_cc_cgas_2 | F73: =VLOOKUP($E73,Hybrid!$1:$1048576,MATCH(DATE(F$2,1,1),Hybrid!$A$1:$LI$1),FALSE) -> 0.029369015 | G73: =VLOOKUP($E73,Hybrid!$1:$1048576,MATCH(DATE(G$2,1,1),Hybrid!$A$1:$LI$1),FALSE) -> 0.032632558 | H73: =VLOOKUP($E73,Hybrid!$1:$1048576,MATCH(DATE(H$2,1,1),Hybrid!$A$1:$LI$1),FALSE) -> 0.034957703 | I73: =VLOOKUP($E73,Hybrid!$1:$1048576,MATCH(DATE(I$2,1,1),Hybrid!$A$1:$LI$1),FALSE) -> 0.035432871 | J73: =VLOOKUP($E73,Hybrid!$1:$1048576,MATCH(DATE(J$2,1,1),Hybrid!$A$1:$LI$1),FALSE) -> 0.035071333 | K73: =VLOOKUP($E73,Hybrid!$1:$1048576,MATCH(DATE(K$2,1,1),Hybrid!$A$1:$LI$1),FALSE) -> 0.034129712 | L73: =VLOOKUP($E73,Hybrid!$1:$1048576,MATCH(DATE(L$2,1,1),Hybrid!$A$1:$LI$1),FALSE) -> 0.032559844 | M73: =VLOOKUP($E73,Hybrid!$1:$1048576,MATCH(DATE(M$2,1,1),Hybrid!$A$1:$LI$1),FALSE) -> 0.028614085 | ... AO73: =VLOOKUP($E73,Hybrid!$1:$1048576,MATCH(DATE(AO$2,1,1),Hybrid!$A$1:$LI$1),FALSE) -> 4.0594297e-07
D74: class D | E74: NEWAUTO_cd_cgas_2 | F74: =VLOOKUP($E74,Hybrid!$1:$1048576,MATCH(DATE(F$2,1,1),Hybrid!$A$1:$LI$1),FALSE) -> 0.016317038 | G74: =VLOOKUP($E74,Hybrid!$1:$1048576,MATCH(DATE(G$2,1,1),Hybrid!$A$1:$LI$1),FALSE) -> 0.018192769 | H74: =VLOOKUP($E74,Hybrid!$1:$1048576,MATCH(DATE(H$2,1,1),Hybrid!$A$1:$LI$1),FALSE) -> 0.019638383 | I74: =VLOOKUP($E74,Hybrid!$1:$1048576,MATCH(DATE(I$2,1,1),Hybrid!$A$1:$LI$1),FALSE) -> 0.020205034 | J74: =VLOOKUP($E74,Hybrid!$1:$1048576,MATCH(DATE(J$2,1,1),Hybrid!$A$1:$LI$1),FALSE) -> 0.020427939 | K74: =VLOOKUP($E74,Hybrid!$1:$1048576,MATCH(DATE(K$2,1,1),Hybrid!$A$1:$LI$1),FALSE) -> 0.020325241 | L74: =VLOOKUP($E74,Hybrid!$1:$1048576,MATCH(DATE(L$2,1,1),Hybrid!$A$1:$LI$1),FALSE) -> 0.019859544 | M74: =VLOOKUP($E74,Hybrid!$1:$1048576,MATCH(DATE(M$2,1,1),Hybrid!$A$1:$LI$1),FALSE) -> 0.01819614 | ... AO74: =VLOOKUP($E74,Hybrid!$1:$1048576,MATCH(DATE(AO$2,1,1),Hybrid!$A$1:$LI$1),FALSE) -> 2.9919498e-05
D75: class E | E75: NEWAUTO_ce_cgas_2 | F75: =VLOOKUP($E75,Hybrid!$1:$1048576,MATCH(DATE(F$2,1,1),Hybrid!$A$1:$LI$1),FALSE) -> 0.01003532 | G75: =VLOOKUP($E75,Hybrid!$1:$1048576,MATCH(DATE(G$2,1,1),Hybrid!$A$1:$LI$1),FALSE) -> 0.011137172 | H75: =VLOOKUP($E75,Hybrid!$1:$1048576,MATCH(DATE(H$2,1,1),Hybrid!$A$1:$LI$1),FALSE) -> 0.011953696 | I75: =VLOOKUP($E75,Hybrid!$1:$1048576,MATCH(DATE(I$2,1,1),Hybrid!$A$1:$LI$1),FALSE) -> 0.012220736 | J75: =VLOOKUP($E75,Hybrid!$1:$1048576,MATCH(DATE(J$2,1,1),Hybrid!$A$1:$LI$1),FALSE) -> 0.012272714 | K75: =VLOOKUP($E75,Hybrid!$1:$1048576,MATCH(DATE(K$2,1,1),Hybrid!$A$1:$LI$1),FALSE) -> 0.012133167 | L75: =VLOOKUP($E75,Hybrid!$1:$1048576,MATCH(DATE(L$2,1,1),Hybrid!$A$1:$LI$1),FALSE) -> 0.011775648 | M75: =VLOOKUP($E75,Hybrid!$1:$1048576,MATCH(DATE(M$2,1,1),Hybrid!$A$1:$LI$1),FALSE) -> 0.010684256 | ... AO75: =VLOOKUP($E75,Hybrid!$1:$1048576,MATCH(DATE(AO$2,1,1),Hybrid!$A$1:$LI$1),FALSE) -> 1.7639843e-05
D76: class F | E76: NEWAUTO_cf_cgas_2 | F76: =VLOOKUP($E76,Hybrid!$1:$1048576,MATCH(DATE(F$2,1,1),Hybrid!$A$1:$LI$1),FALSE) -> 0.0048568583 | G76: =VLOOKUP($E76,Hybrid!$1:$1048576,MATCH(DATE(G$2,1,1),Hybrid!$A$1:$LI$1),FALSE) -> 0.0053278875 | H76: =VLOOKUP($E76,Hybrid!$1:$1048576,MATCH(DATE(H$2,1,1),Hybrid!$A$1:$LI$1),FALSE) -> 0.0056463334 | I76: =VLOOKUP($E76,Hybrid!$1:$1048576,MATCH(DATE(I$2,1,1),Hybrid!$A$1:$LI$1),FALSE) -> 0.0057091448 | J76: =VLOOKUP($E76,Hybrid!$1:$1048576,MATCH(DATE(J$2,1,1),Hybrid!$A$1:$LI$1),FALSE) -> 0.0056778802 | K76: =VLOOKUP($E76,Hybrid!$1:$1048576,MATCH(DATE(K$2,1,1),Hybrid!$A$1:$LI$1),FALSE) -> 0.00556051 | L76: =VLOOKUP($E76,Hybrid!$1:$1048576,MATCH(DATE(L$2,1,1),Hybrid!$A$1:$LI$1),FALSE) -> 0.0053411683 | M76: =VLOOKUP($E76,Hybrid!$1:$1048576,MATCH(DATE(M$2,1,1),Hybrid!$A$1:$LI$1),FALSE) -> 0.0047929412 | ... AO76: =VLOOKUP($E76,Hybrid!$1:$1048576,MATCH(DATE(AO$2,1,1),Hybrid!$A$1:$LI$1),FALSE) -> 4.0308967e-05
D77: class G | E77: NEWAUTO_cg_cgas_2 | F77: =VLOOKUP($E77,Hybrid!$1:$1048576,MATCH(DATE(F$2,1,1),Hybrid!$A$1:$LI$1),FALSE) -> 0.0091147994 | G77: =VLOOKUP($E77,Hybrid!$1:$1048576,MATCH(DATE(G$2,1,1),Hybrid!$A$1:$LI$1),FALSE) -> 0.0098594397 | H77: =VLOOKUP($E77,Hybrid!$1:$1048576,MATCH(DATE(H$2,1,1),Hybrid!$A$1:$LI$1),FALSE) -> 0.010273141 | I77: =VLOOKUP($E77,Hybrid!$1:$1048576,MATCH(DATE(I$2,1,1),Hybrid!$A$1:$LI$1),FALSE) -> 0.010199814 | J77: =VLOOKUP($E77,Hybrid!$1:$1048576,MATCH(DATE(J$2,1,1),Hybrid!$A$1:$LI$1),FALSE) -> 0.0099512128 | K77: =VLOOKUP($E77,Hybrid!$1:$1048576,MATCH(DATE(K$2,1,1),Hybrid!$A$1:$LI$1),FALSE) -> 0.0095646571 | L77: =VLOOKUP($E77,Hybrid!$1:$1048576,MATCH(DATE(L$2,1,1),Hybrid!$A$1:$LI$1),FALSE) -> 0.0090061404 | M77: =VLOOKUP($E77,Hybrid!$1:$1048576,MATCH(DATE(M$2,1,1),Hybrid!$A$1:$LI$1),FALSE) -> 0.0078589087 | ... AO77: =VLOOKUP($E77,Hybrid!$1:$1048576,MATCH(DATE(AO$2,1,1),Hybrid!$A$1:$LI$1),FALSE) -> 5.6254318e-05
C78: TOTAL SALES BASELINE | E78: NEWAUTO_0 | F78: =VLOOKUP($E78,Hybrid!$1:$1048576,MATCH(DATE(F$2,1,1),Hybrid!$A$1:$LI$1),FALSE) -> 1886.229 | G78: =VLOOKUP($E78,Hybrid!$1:$1048576,MATCH(DATE(G$2,1,1),Hybrid!$A$1:$LI$1),FALSE) -> 2124.3618 | H78: =VLOOKUP($E78,Hybrid!$1:$1048576,MATCH(DATE(H$2,1,1),Hybrid!$A$1:$LI$1),FALSE) -> 2329.2745 | I78: =VLOOKUP($E78,Hybrid!$1:$1048576,MATCH(DATE(I$2,1,1),Hybrid!$A$1:$LI$1),FALSE) -> 2453.4461 | J78: =VLOOKUP($E78,Hybrid!$1:$1048576,MATCH(DATE(J$2,1,1),Hybrid!$A$1:$LI$1),FALSE) -> 2556.2319 | K78: =VLOOKUP($E78,Hybrid!$1:$1048576,MATCH(DATE(K$2,1,1),Hybrid!$A$1:$LI$1),FALSE) -> 2622.9571 | L78: =VLOOKUP($E78,Hybrid!$1:$1048576,MATCH(DATE(L$2,1,1),Hybrid!$A$1:$LI$1),FALSE) -> 2611.5572 | M78: =VLOOKUP($E78,Hybrid!$1:$1048576,MATCH(DATE(M$2,1,1),Hybrid!$A$1:$LI$1),FALSE) -> 2604.9851 | ... AO78: =VLOOKUP($E78,Hybrid!$1:$1048576,MATCH(DATE(AO$2,1,1),Hybrid!$A$1:$LI$1),FALSE) -> 2800.3413
C79: OIL | E79: NEWAUTO_cfut_0 | F79: =VLOOKUP($E79,Hybrid!$1:$1048576,MATCH(DATE(F$2,1,1),Hybrid!$A$1:$LI$1),FALSE) -> 1861.6951 | G79: =VLOOKUP($E79,Hybrid!$1:$1048576,MATCH(DATE(G$2,1,1),Hybrid!$A$1:$LI$1),FALSE) -> 2071.3442 | H79: =VLOOKUP($E79,Hybrid!$1:$1048576,MATCH(DATE(H$2,1,1),Hybrid!$A$1:$LI$1),FALSE) -> 2226.3695 | I79: =VLOOKUP($E79,Hybrid!$1:$1048576,MATCH(DATE(I$2,1,1),Hybrid!$A$1:$LI$1),FALSE) -> 2272.2526 | J79: =VLOOKUP($E79,Hybrid!$1:$1048576,MATCH(DATE(J$2,1,1),Hybrid!$A$1:$LI$1),FALSE) -> 2271.2019 | K79: =VLOOKUP($E79,Hybrid!$1:$1048576,MATCH(DATE(K$2,1,1),Hybrid!$A$1:$LI$1),FALSE) -> 2232.4591 | L79: =VLOOKUP($E79,Hybrid!$1:$1048576,MATCH(DATE(L$2,1,1),Hybrid!$A$1:$LI$1),FALSE) -> 2106.1689 | M79: =VLOOKUP($E79,Hybrid!$1:$1048576,MATCH(DATE(M$2,1,1),Hybrid!$A$1:$LI$1),FALSE) -> 1935.3138 | ... AO79: =VLOOKUP($E79,Hybrid!$1:$1048576,MATCH(DATE(AO$2,1,1),Hybrid!$A$1:$LI$1),FALSE) -> 3.1638015
D80: class A | E80: NEWAUTO_ca_cfut_0 | F80: =VLOOKUP($E80,Hybrid!$1:$1048576,MATCH(DATE(F$2,1,1),Hybrid!$A$1:$LI$1),FALSE) -> 526.72343 | G80: =VLOOKUP($E80,Hybrid!$1:$1048576,MATCH(DATE(G$2,1,1),Hybrid!$A$1:$LI$1),FALSE) -> 589.33388 | H80: =VLOOKUP($E80,Hybrid!$1:$1048576,MATCH(DATE(H$2,1,1),Hybrid!$A$1:$LI$1),FALSE) -> 637.61185 | I80: =VLOOKUP($E80,Hybrid!$1:$1048576,MATCH(DATE(I$2,1,1),Hybrid!$A$1:$LI$1),FALSE) -> 655.17258 | J80: =VLOOKUP($E80,Hybrid!$1:$1048576,MATCH(DATE(J$2,1,1),Hybrid!$A$1:$LI$1),FALSE) -> 659.24877 | K80: =VLOOKUP($E80,Hybrid!$1:$1048576,MATCH(DATE(K$2,1,1),Hybrid!$A$1:$LI$1),FALSE) -> 651.8992 | L80: =VLOOKUP($E80,Hybrid!$1:$1048576,MATCH(DATE(L$2,1,1),Hybrid!$A$1:$LI$1),FALSE) -> 619.09632 | M80: =VLOOKUP($E80,Hybrid!$1:$1048576,MATCH(DATE(M$2,1,1),Hybrid!$A$1:$LI$1),FALSE) -> 573.39492 | ... AO80: =VLOOKUP($E80,Hybrid!$1:$1048576,MATCH(DATE(AO$2,1,1),Hybrid!$A$1:$LI$1),FALSE) -> 0.10648623
D81: class B | E81: NEWAUTO_cb_cfut_0 | F81: =VLOOKUP($E81,Hybrid!$1:$1048576,MATCH(DATE(F$2,1,1),Hybrid!$A$1:$LI$1),FALSE) -> 505.4013 | G81: =VLOOKUP($E81,Hybrid!$1:$1048576,MATCH(DATE(G$2,1,1),Hybrid!$A$1:$LI$1),FALSE) -> 563.68023 | H81: =VLOOKUP($E81,Hybrid!$1:$1048576,MATCH(DATE(H$2,1,1),Hybrid!$A$1:$LI$1),FALSE) -> 607.10929 | I81: =VLOOKUP($E81,Hybrid!$1:$1048576,MATCH(DATE(I$2,1,1),Hybrid!$A$1:$LI$1),FALSE) -> 619.9772 | J81: =VLOOKUP($E81,Hybrid!$1:$1048576,MATCH(DATE(J$2,1,1),Hybrid!$A$1:$LI$1),FALSE) -> 619.21305 | K81: =VLOOKUP($E81,Hybrid!$1:$1048576,MATCH(DATE(K$2,1,1),Hybrid!$A$1:$LI$1),FALSE) -> 607.90995 | L81: =VLOOKUP($E81,Hybrid!$1:$1048576,MATCH(DATE(L$2,1,1),Hybrid!$A$1:$LI$1),FALSE) -> 572.27594 | M81: =VLOOKUP($E81,Hybrid!$1:$1048576,MATCH(DATE(M$2,1,1),Hybrid!$A$1:$LI$1),FALSE) -> 523.25478 | ... AO81: =VLOOKUP($E81,Hybrid!$1:$1048576,MATCH(DATE(AO$2,1,1),Hybrid!$A$1:$LI$1),FALSE) -> 0.047801401
D82: class C | E82: NEWAUTO_cc_cfut_0 | F82: =VLOOKUP($E82,Hybrid!$1:$1048576,MATCH(DATE(F$2,1,1),Hybrid!$A$1:$LI$1),FALSE) -> 349.58537 | G82: =VLOOKUP($E82,Hybrid!$1:$1048576,MATCH(DATE(G$2,1,1),Hybrid!$A$1:$LI$1),FALSE) -> 388.43199 | H82: =VLOOKUP($E82,Hybrid!$1:$1048576,MATCH(DATE(H$2,1,1),Hybrid!$A$1:$LI$1),FALSE) -> 416.10866 | I82: =VLOOKUP($E82,Hybrid!$1:$1048576,MATCH(DATE(I$2,1,1),Hybrid!$A$1:$LI$1),FALSE) -> 421.76469 | J82: =VLOOKUP($E82,Hybrid!$1:$1048576,MATCH(DATE(J$2,1,1),Hybrid!$A$1:$LI$1),FALSE) -> 417.46122 | K82: =VLOOKUP($E82,Hybrid!$1:$1048576,MATCH(DATE(K$2,1,1),Hybrid!$A$1:$LI$1),FALSE) -> 406.25292 | L82: =VLOOKUP($E82,Hybrid!$1:$1048576,MATCH(DATE(L$2,1,1),Hybrid!$A$1:$LI$1),FALSE) -> 378.39145 | M82: =VLOOKUP($E82,Hybrid!$1:$1048576,MATCH(DATE(M$2,1,1),Hybrid!$A$1:$LI$1),FALSE) -> 340.66945 | ... AO82: =VLOOKUP($E82,Hybrid!$1:$1048576,MATCH(DATE(AO$2,1,1),Hybrid!$A$1:$LI$1),FALSE) -> 0.013575649
D83: class D | E83: NEWAUTO_cd_cfut_0 | F83: =VLOOKUP($E83,Hybrid!$1:$1048576,MATCH(DATE(F$2,1,1),Hybrid!$A$1:$LI$1),FALSE) -> 194.22503 | G83: =VLOOKUP($E83,Hybrid!$1:$1048576,MATCH(DATE(G$2,1,1),Hybrid!$A$1:$LI$1),FALSE) -> 216.55224 | H83: =VLOOKUP($E83,Hybrid!$1:$1048576,MATCH(DATE(H$2,1,1),Hybrid!$A$1:$LI$1),FALSE) -> 233.75967 | I83: =VLOOKUP($E83,Hybrid!$1:$1048576,MATCH(DATE(I$2,1,1),Hybrid!$A$1:$LI$1),FALSE) -> 240.50463 | J83: =VLOOKUP($E83,Hybrid!$1:$1048576,MATCH(DATE(J$2,1,1),Hybrid!$A$1:$LI$1),FALSE) -> 243.15792 | K83: =VLOOKUP($E83,Hybrid!$1:$1048576,MATCH(DATE(K$2,1,1),Hybrid!$A$1:$LI$1),FALSE) -> 241.93549 | L83: =VLOOKUP($E83,Hybrid!$1:$1048576,MATCH(DATE(L$2,1,1),Hybrid!$A$1:$LI$1),FALSE) -> 231.76015 | M83: =VLOOKUP($E83,Hybrid!$1:$1048576,MATCH(DATE(M$2,1,1),Hybrid!$A$1:$LI$1),FALSE) -> 218.03811 | ... AO83: =VLOOKUP($E83,Hybrid!$1:$1048576,MATCH(DATE(AO$2,1,1),Hybrid!$A$1:$LI$1),FALSE) -> 0.70996577
D84: class E | E84: NEWAUTO_ce_cfut_0 | F84: =VLOOKUP($E84,Hybrid!$1:$1048576,MATCH(DATE(F$2,1,1),Hybrid!$A$1:$LI$1),FALSE) -> 119.45246 | G84: =VLOOKUP($E84,Hybrid!$1:$1048576,MATCH(DATE(G$2,1,1),Hybrid!$A$1:$LI$1),FALSE) -> 132.56802 | H84: =VLOOKUP($E84,Hybrid!$1:$1048576,MATCH(DATE(H$2,1,1),Hybrid!$A$1:$LI$1),FALSE) -> 142.28728 | I84: =VLOOKUP($E84,Hybrid!$1:$1048576,MATCH(DATE(I$2,1,1),Hybrid!$A$1:$LI$1),FALSE) -> 145.46591 | J84: =VLOOKUP($E84,Hybrid!$1:$1048576,MATCH(DATE(J$2,1,1),Hybrid!$A$1:$LI$1),FALSE) -> 146.08461 | K84: =VLOOKUP($E84,Hybrid!$1:$1048576,MATCH(DATE(K$2,1,1),Hybrid!$A$1:$LI$1),FALSE) -> 144.42357 | L84: =VLOOKUP($E84,Hybrid!$1:$1048576,MATCH(DATE(L$2,1,1),Hybrid!$A$1:$LI$1),FALSE) -> 137.34227 | M84: =VLOOKUP($E84,Hybrid!$1:$1048576,MATCH(DATE(M$2,1,1),Hybrid!$A$1:$LI$1),FALSE) -> 128.00204 | ... AO84: =VLOOKUP($E84,Hybrid!$1:$1048576,MATCH(DATE(AO$2,1,1),Hybrid!$A$1:$LI$1),FALSE) -> 0.39950574
D85: class F | E85: NEWAUTO_cf_cfut_0 | F85: =VLOOKUP($E85,Hybrid!$1:$1048576,MATCH(DATE(F$2,1,1),Hybrid!$A$1:$LI$1),FALSE) -> 57.812175 | G85: =VLOOKUP($E85,Hybrid!$1:$1048576,MATCH(DATE(G$2,1,1),Hybrid!$A$1:$LI$1),FALSE) -> 63.418931 | H85: =VLOOKUP($E85,Hybrid!$1:$1048576,MATCH(DATE(H$2,1,1),Hybrid!$A$1:$LI$1),FALSE) -> 67.209458 | I85: =VLOOKUP($E85,Hybrid!$1:$1048576,MATCH(DATE(I$2,1,1),Hybrid!$A$1:$LI$1),FALSE) -> 67.957114 | J85: =VLOOKUP($E85,Hybrid!$1:$1048576,MATCH(DATE(J$2,1,1),Hybrid!$A$1:$LI$1),FALSE) -> 67.584966 | K85: =VLOOKUP($E85,Hybrid!$1:$1048576,MATCH(DATE(K$2,1,1),Hybrid!$A$1:$LI$1),FALSE) -> 66.187884 | L85: =VLOOKUP($E85,Hybrid!$1:$1048576,MATCH(DATE(L$2,1,1),Hybrid!$A$1:$LI$1),FALSE) -> 62.331521 | M85: =VLOOKUP($E85,Hybrid!$1:$1048576,MATCH(DATE(M$2,1,1),Hybrid!$A$1:$LI$1),FALSE) -> 57.568588 | ... AO85: =VLOOKUP($E85,Hybrid!$1:$1048576,MATCH(DATE(AO$2,1,1),Hybrid!$A$1:$LI$1),FALSE) -> 0.76943696
D86: class G | E86: NEWAUTO_cg_cfut_0 | F86: =VLOOKUP($E86,Hybrid!$1:$1048576,MATCH(DATE(F$2,1,1),Hybrid!$A$1:$LI$1),FALSE) -> 108.49532 | G86: =VLOOKUP($E86,Hybrid!$1:$1048576,MATCH(DATE(G$2,1,1),Hybrid!$A$1:$LI$1),FALSE) -> 117.35892 | H86: =VLOOKUP($E86,Hybrid!$1:$1048576,MATCH(DATE(H$2,1,1),Hybrid!$A$1:$LI$1),FALSE) -> 122.28329 | I86: =VLOOKUP($E86,Hybrid!$1:$1048576,MATCH(DATE(I$2,1,1),Hybrid!$A$1:$LI$1),FALSE) -> 121.41046 | J86: =VLOOKUP($E86,Hybrid!$1:$1048576,MATCH(DATE(J$2,1,1),Hybrid!$A$1:$LI$1),FALSE) -> 118.45131 | K86: =VLOOKUP($E86,Hybrid!$1:$1048576,MATCH(DATE(K$2,1,1),Hybrid!$A$1:$LI$1),FALSE) -> 113.85006 | L86: =VLOOKUP($E86,Hybrid!$1:$1048576,MATCH(DATE(L$2,1,1),Hybrid!$A$1:$LI$1),FALSE) -> 104.97122 | M86: =VLOOKUP($E86,Hybrid!$1:$1048576,MATCH(DATE(M$2,1,1),Hybrid!$A$1:$LI$1),FALSE) -> 94.385886 | ... AO86: =VLOOKUP($E86,Hybrid!$1:$1048576,MATCH(DATE(AO$2,1,1),Hybrid!$A$1:$LI$1),FALSE) -> 1.1170298
C87: ELEC | E87: NEWAUTO_cele_0 | F87: =VLOOKUP($E87,Hybrid!$1:$1048576,MATCH(DATE(F$2,1,1),Hybrid!$A$1:$LI$1),FALSE) -> 24.377505 | G87: =VLOOKUP($E87,Hybrid!$1:$1048576,MATCH(DATE(G$2,1,1),Hybrid!$A$1:$LI$1),FALSE) -> 52.843605 | H87: =VLOOKUP($E87,Hybrid!$1:$1048576,MATCH(DATE(H$2,1,1),Hybrid!$A$1:$LI$1),FALSE) -> 102.718 | I87: =VLOOKUP($E87,Hybrid!$1:$1048576,MATCH(DATE(I$2,1,1),Hybrid!$A$1:$LI$1),FALSE) -> 181.00259 | J87: =VLOOKUP($E87,Hybrid!$1:$1048576,MATCH(DATE(J$2,1,1),Hybrid!$A$1:$LI$1),FALSE) -> 284.83924 | K87: =VLOOKUP($E87,Hybrid!$1:$1048576,MATCH(DATE(K$2,1,1),Hybrid!$A$1:$LI$1),FALSE) -> 390.31043 | L87: =VLOOKUP($E87,Hybrid!$1:$1048576,MATCH(DATE(L$2,1,1),Hybrid!$A$1:$LI$1),FALSE) -> 505.21141 | M87: =VLOOKUP($E87,Hybrid!$1:$1048576,MATCH(DATE(M$2,1,1),Hybrid!$A$1:$LI$1),FALSE) -> 669.50878 | ... AO87: =VLOOKUP($E87,Hybrid!$1:$1048576,MATCH(DATE(AO$2,1,1),Hybrid!$A$1:$LI$1),FALSE) -> 2797.1773
D88: class A | E88: NEWAUTO_ca_cele_0 | F88: =VLOOKUP($E88,Hybrid!$1:$1048576,MATCH(DATE(F$2,1,1),Hybrid!$A$1:$LI$1),FALSE) -> 6.846501 | G88: =VLOOKUP($E88,Hybrid!$1:$1048576,MATCH(DATE(G$2,1,1),Hybrid!$A$1:$LI$1),FALSE) -> 14.859451 | H88: =VLOOKUP($E88,Hybrid!$1:$1048576,MATCH(DATE(H$2,1,1),Hybrid!$A$1:$LI$1),FALSE) -> 29.061308 | I88: =VLOOKUP($E88,Hybrid!$1:$1048576,MATCH(DATE(I$2,1,1),Hybrid!$A$1:$LI$1),FALSE) -> 51.639899 | J88: =VLOOKUP($E88,Hybrid!$1:$1048576,MATCH(DATE(J$2,1,1),Hybrid!$A$1:$LI$1),FALSE) -> 81.95823 | K88: =VLOOKUP($E88,Hybrid!$1:$1048576,MATCH(DATE(K$2,1,1),Hybrid!$A$1:$LI$1),FALSE) -> 113.04486 | L88: =VLOOKUP($E88,Hybrid!$1:$1048576,MATCH(DATE(L$2,1,1),Hybrid!$A$1:$LI$1),FALSE) -> 147.45669 | M88: =VLOOKUP($E88,Hybrid!$1:$1048576,MATCH(DATE(M$2,1,1),Hybrid!$A$1:$LI$1),FALSE) -> 197.72519 | ... AO88: =VLOOKUP($E88,Hybrid!$1:$1048576,MATCH(DATE(AO$2,1,1),Hybrid!$A$1:$LI$1),FALSE) -> 883.98891
D89: class B | E89: NEWAUTO_cb_cele_0 | F89: =VLOOKUP($E89,Hybrid!$1:$1048576,MATCH(DATE(F$2,1,1),Hybrid!$A$1:$LI$1),FALSE) -> 6.8560367 | G89: =VLOOKUP($E89,Hybrid!$1:$1048576,MATCH(DATE(G$2,1,1),Hybrid!$A$1:$LI$1),FALSE) -> 15.565202 | H89: =VLOOKUP($E89,Hybrid!$1:$1048576,MATCH(DATE(H$2,1,1),Hybrid!$A$1:$LI$1),FALSE) -> 31.001581 | I89: =VLOOKUP($E89,Hybrid!$1:$1048576,MATCH(DATE(I$2,1,1),Hybrid!$A$1:$LI$1),FALSE) -> 55.437715 | J89: =VLOOKUP($E89,Hybrid!$1:$1048576,MATCH(DATE(J$2,1,1),Hybrid!$A$1:$LI$1),FALSE) -> 88.02025 | K89: =VLOOKUP($E89,Hybrid!$1:$1048576,MATCH(DATE(K$2,1,1),Hybrid!$A$1:$LI$1),FALSE) -> 121.24869 | L89: =VLOOKUP($E89,Hybrid!$1:$1048576,MATCH(DATE(L$2,1,1),Hybrid!$A$1:$LI$1),FALSE) -> 157.62389 | M89: =VLOOKUP($E89,Hybrid!$1:$1048576,MATCH(DATE(M$2,1,1),Hybrid!$A$1:$LI$1),FALSE) -> 209.78657 | ... AO89: =VLOOKUP($E89,Hybrid!$1:$1048576,MATCH(DATE(AO$2,1,1),Hybrid!$A$1:$LI$1),FALSE) -> 860.03549
D90: class C | E90: NEWAUTO_cc_cele_0 | F90: =VLOOKUP($E90,Hybrid!$1:$1048576,MATCH(DATE(F$2,1,1),Hybrid!$A$1:$LI$1),FALSE) -> 4.9963127 | G90: =VLOOKUP($E90,Hybrid!$1:$1048576,MATCH(DATE(G$2,1,1),Hybrid!$A$1:$LI$1),FALSE) -> 11.917167 | H90: =VLOOKUP($E90,Hybrid!$1:$1048576,MATCH(DATE(H$2,1,1),Hybrid!$A$1:$LI$1),FALSE) -> 24.169279 | I90: =VLOOKUP($E90,Hybrid!$1:$1048576,MATCH(DATE(I$2,1,1),Hybrid!$A$1:$LI$1),FALSE) -> 43.453483 | J90: =VLOOKUP($E90,Hybrid!$1:$1048576,MATCH(DATE(J$2,1,1),Hybrid!$A$1:$LI$1),FALSE) -> 68.94551 | K90: =VLOOKUP($E90,Hybrid!$1:$1048576,MATCH(DATE(K$2,1,1),Hybrid!$A$1:$LI$1),FALSE) -> 94.763773 | L90: =VLOOKUP($E90,Hybrid!$1:$1048576,MATCH(DATE(L$2,1,1),Hybrid!$A$1:$LI$1),FALSE) -> 122.654 | M90: =VLOOKUP($E90,Hybrid!$1:$1048576,MATCH(DATE(M$2,1,1),Hybrid!$A$1:$LI$1),FALSE) -> 161.80895 | ... AO90: =VLOOKUP($E90,Hybrid!$1:$1048576,MATCH(DATE(AO$2,1,1),Hybrid!$A$1:$LI$1),FALSE) -> 611.40401
D91: class D | E91: NEWAUTO_cd_cele_0 | F91: =VLOOKUP($E91,Hybrid!$1:$1048576,MATCH(DATE(F$2,1,1),Hybrid!$A$1:$LI$1),FALSE) -> 2.3037098 | G91: =VLOOKUP($E91,Hybrid!$1:$1048576,MATCH(DATE(G$2,1,1),Hybrid!$A$1:$LI$1),FALSE) -> 4.3507921 | H91: =VLOOKUP($E91,Hybrid!$1:$1048576,MATCH(DATE(H$2,1,1),Hybrid!$A$1:$LI$1),FALSE) -> 7.8235043 | I91: =VLOOKUP($E91,Hybrid!$1:$1048576,MATCH(DATE(I$2,1,1),Hybrid!$A$1:$LI$1),FALSE) -> 13.160215 | J91: =VLOOKUP($E91,Hybrid!$1:$1048576,MATCH(DATE(J$2,1,1),Hybrid!$A$1:$LI$1),FALSE) -> 20.187176 | K91: =VLOOKUP($E91,Hybrid!$1:$1048576,MATCH(DATE(K$2,1,1),Hybrid!$A$1:$LI$1),FALSE) -> 27.309609 | L91: =VLOOKUP($E91,Hybrid!$1:$1048576,MATCH(DATE(L$2,1,1),Hybrid!$A$1:$LI$1),FALSE) -> 35.060632 | M91: =VLOOKUP($E91,Hybrid!$1:$1048576,MATCH(DATE(M$2,1,1),Hybrid!$A$1:$LI$1),FALSE) -> 46.229699 | ... AO91: =VLOOKUP($E91,Hybrid!$1:$1048576,MATCH(DATE(AO$2,1,1),Hybrid!$A$1:$LI$1),FALSE) -> 219.09401
D92: class E | E92: NEWAUTO_ce_cele_0 | F92: =VLOOKUP($E92,Hybrid!$1:$1048576,MATCH(DATE(F$2,1,1),Hybrid!$A$1:$LI$1),FALSE) -> 1.4447796 | G92: =VLOOKUP($E92,Hybrid!$1:$1048576,MATCH(DATE(G$2,1,1),Hybrid!$A$1:$LI$1),FALSE) -> 2.785661 | H92: =VLOOKUP($E92,Hybrid!$1:$1048576,MATCH(DATE(H$2,1,1),Hybrid!$A$1:$LI$1),FALSE) -> 5.0471901 | I92: =VLOOKUP($E92,Hybrid!$1:$1048576,MATCH(DATE(I$2,1,1),Hybrid!$A$1:$LI$1),FALSE) -> 8.4894535 | J92: =VLOOKUP($E92,Hybrid!$1:$1048576,MATCH(DATE(J$2,1,1),Hybrid!$A$1:$LI$1),FALSE) -> 12.973339 | K92: =VLOOKUP($E92,Hybrid!$1:$1048576,MATCH(DATE(K$2,1,1),Hybrid!$A$1:$LI$1),FALSE) -> 17.483779 | L92: =VLOOKUP($E92,Hybrid!$1:$1048576,MATCH(DATE(L$2,1,1),Hybrid!$A$1:$LI$1),FALSE) -> 22.315435 | M92: =VLOOKUP($E92,Hybrid!$1:$1048576,MATCH(DATE(M$2,1,1),Hybrid!$A$1:$LI$1),FALSE) -> 29.11254 | ... AO92: =VLOOKUP($E92,Hybrid!$1:$1048576,MATCH(DATE(AO$2,1,1),Hybrid!$A$1:$LI$1),FALSE) -> 129.6544
D93: class F | E93: NEWAUTO_cf_cele_0 | F93: =VLOOKUP($E93,Hybrid!$1:$1048576,MATCH(DATE(F$2,1,1),Hybrid!$A$1:$LI$1),FALSE) -> 0.65606728 | G93: =VLOOKUP($E93,Hybrid!$1:$1048576,MATCH(DATE(G$2,1,1),Hybrid!$A$1:$LI$1),FALSE) -> 1.1188238 | H93: =VLOOKUP($E93,Hybrid!$1:$1048576,MATCH(DATE(H$2,1,1),Hybrid!$A$1:$LI$1),FALSE) -> 1.8525722 | I93: =VLOOKUP($E93,Hybrid!$1:$1048576,MATCH(DATE(I$2,1,1),Hybrid!$A$1:$LI$1),FALSE) -> 2.9137919 | J93: =VLOOKUP($E93,Hybrid!$1:$1048576,MATCH(DATE(J$2,1,1),Hybrid!$A$1:$LI$1),FALSE) -> 4.2410634 | K93: =VLOOKUP($E93,Hybrid!$1:$1048576,MATCH(DATE(K$2,1,1),Hybrid!$A$1:$LI$1),FALSE) -> 5.51925 | L93: =VLOOKUP($E93,Hybrid!$1:$1048576,MATCH(DATE(L$2,1,1),Hybrid!$A$1:$LI$1),FALSE) -> 6.8164538 | M93: =VLOOKUP($E93,Hybrid!$1:$1048576,MATCH(DATE(M$2,1,1),Hybrid!$A$1:$LI$1),FALSE) -> 8.5686626 | ... AO93: =VLOOKUP($E93,Hybrid!$1:$1048576,MATCH(DATE(AO$2,1,1),Hybrid!$A$1:$LI$1),FALSE) -> 33.343422
D94: class G | E94: NEWAUTO_cg_cele_0 | F94: =VLOOKUP($E94,Hybrid!$1:$1048576,MATCH(DATE(F$2,1,1),Hybrid!$A$1:$LI$1),FALSE) -> 1.2740979 | G94: =VLOOKUP($E94,Hybrid!$1:$1048576,MATCH(DATE(G$2,1,1),Hybrid!$A$1:$LI$1),FALSE) -> 2.246508 | H94: =VLOOKUP($E94,Hybrid!$1:$1048576,MATCH(DATE(H$2,1,1),Hybrid!$A$1:$LI$1),FALSE) -> 3.7625672 | I94: =VLOOKUP($E94,Hybrid!$1:$1048576,MATCH(DATE(I$2,1,1),Hybrid!$A$1:$LI$1),FALSE) -> 5.9080317 | J94: =VLOOKUP($E94,Hybrid!$1:$1048576,MATCH(DATE(J$2,1,1),Hybrid!$A$1:$LI$1),FALSE) -> 8.5136702 | K94: =VLOOKUP($E94,Hybrid!$1:$1048576,MATCH(DATE(K$2,1,1),Hybrid!$A$1:$LI$1),FALSE) -> 10.940467 | L94: =VLOOKUP($E94,Hybrid!$1:$1048576,MATCH(DATE(L$2,1,1),Hybrid!$A$1:$LI$1),FALSE) -> 13.284307 | M94: =VLOOKUP($E94,Hybrid!$1:$1048576,MATCH(DATE(M$2,1,1),Hybrid!$A$1:$LI$1),FALSE) -> 16.27717 | ... AO94: =VLOOKUP($E94,Hybrid!$1:$1048576,MATCH(DATE(AO$2,1,1),Hybrid!$A$1:$LI$1),FALSE) -> 59.65701
C95: GAS | E95: NEWAUTO_cgas_0 | F95: =VLOOKUP($E95,Hybrid!$1:$1048576,MATCH(DATE(F$2,1,1),Hybrid!$A$1:$LI$1),FALSE) -> 0.15640286 | G95: =VLOOKUP($E95,Hybrid!$1:$1048576,MATCH(DATE(G$2,1,1),Hybrid!$A$1:$LI$1),FALSE) -> 0.17401569 | H95: =VLOOKUP($E95,Hybrid!$1:$1048576,MATCH(DATE(H$2,1,1),Hybrid!$A$1:$LI$1),FALSE) -> 0.18703952 | I95: =VLOOKUP($E95,Hybrid!$1:$1048576,MATCH(DATE(I$2,1,1),Hybrid!$A$1:$LI$1),FALSE) -> 0.1908942 | J95: =VLOOKUP($E95,Hybrid!$1:$1048576,MATCH(DATE(J$2,1,1),Hybrid!$A$1:$LI$1),FALSE) -> 0.19080593 | K95: =VLOOKUP($E95,Hybrid!$1:$1048576,MATCH(DATE(K$2,1,1),Hybrid!$A$1:$LI$1),FALSE) -> 0.18755111 | L95: =VLOOKUP($E95,Hybrid!$1:$1048576,MATCH(DATE(L$2,1,1),Hybrid!$A$1:$LI$1),FALSE) -> 0.17694134 | M95: =VLOOKUP($E95,Hybrid!$1:$1048576,MATCH(DATE(M$2,1,1),Hybrid!$A$1:$LI$1),FALSE) -> 0.16258764 | ... AO95: =VLOOKUP($E95,Hybrid!$1:$1048576,MATCH(DATE(AO$2,1,1),Hybrid!$A$1:$LI$1),FALSE) -> 0.00026579411
D96: class A | E96: NEWAUTO_ca_cgas_0 | F96: =VLOOKUP($E96,Hybrid!$1:$1048576,MATCH(DATE(F$2,1,1),Hybrid!$A$1:$LI$1),FALSE) -> 0.04425056 | G96: =VLOOKUP($E96,Hybrid!$1:$1048576,MATCH(DATE(G$2,1,1),Hybrid!$A$1:$LI$1),FALSE) -> 0.049510526 | H96: =VLOOKUP($E96,Hybrid!$1:$1048576,MATCH(DATE(H$2,1,1),Hybrid!$A$1:$LI$1),FALSE) -> 0.053566406 | I96: =VLOOKUP($E96,Hybrid!$1:$1048576,MATCH(DATE(I$2,1,1),Hybrid!$A$1:$LI$1),FALSE) -> 0.0550417 | J96: =VLOOKUP($E96,Hybrid!$1:$1048576,MATCH(DATE(J$2,1,1),Hybrid!$A$1:$LI$1),FALSE) -> 0.055384146 | K96: =VLOOKUP($E96,Hybrid!$1:$1048576,MATCH(DATE(K$2,1,1),Hybrid!$A$1:$LI$1),FALSE) -> 0.054766701 | L96: =VLOOKUP($E96,Hybrid!$1:$1048576,MATCH(DATE(L$2,1,1),Hybrid!$A$1:$LI$1),FALSE) -> 0.052010898 | M96: =VLOOKUP($E96,Hybrid!$1:$1048576,MATCH(DATE(M$2,1,1),Hybrid!$A$1:$LI$1),FALSE) -> 0.048171478 | ... AO96: =VLOOKUP($E96,Hybrid!$1:$1048576,MATCH(DATE(AO$2,1,1),Hybrid!$A$1:$LI$1),FALSE) -> 8.946014e-06
D97: class B | E97: NEWAUTO_cb_cgas_0 | F97: =VLOOKUP($E97,Hybrid!$1:$1048576,MATCH(DATE(F$2,1,1),Hybrid!$A$1:$LI$1),FALSE) -> 0.042459266 | G97: =VLOOKUP($E97,Hybrid!$1:$1048576,MATCH(DATE(G$2,1,1),Hybrid!$A$1:$LI$1),FALSE) -> 0.047355337 | H97: =VLOOKUP($E97,Hybrid!$1:$1048576,MATCH(DATE(H$2,1,1),Hybrid!$A$1:$LI$1),FALSE) -> 0.051003856 | I97: =VLOOKUP($E97,Hybrid!$1:$1048576,MATCH(DATE(I$2,1,1),Hybrid!$A$1:$LI$1),FALSE) -> 0.052084902 | J97: =VLOOKUP($E97,Hybrid!$1:$1048576,MATCH(DATE(J$2,1,1),Hybrid!$A$1:$LI$1),FALSE) -> 0.052020705 | K97: =VLOOKUP($E97,Hybrid!$1:$1048576,MATCH(DATE(K$2,1,1),Hybrid!$A$1:$LI$1),FALSE) -> 0.05107112 | L97: =VLOOKUP($E97,Hybrid!$1:$1048576,MATCH(DATE(L$2,1,1),Hybrid!$A$1:$LI$1),FALSE) -> 0.048077472 | M97: =VLOOKUP($E97,Hybrid!$1:$1048576,MATCH(DATE(M$2,1,1),Hybrid!$A$1:$LI$1),FALSE) -> 0.043959155 | ... AO97: =VLOOKUP($E97,Hybrid!$1:$1048576,MATCH(DATE(AO$2,1,1),Hybrid!$A$1:$LI$1),FALSE) -> 4.0158433e-06
D98: class C | E98: NEWAUTO_cc_cgas_0 | F98: =VLOOKUP($E98,Hybrid!$1:$1048576,MATCH(DATE(F$2,1,1),Hybrid!$A$1:$LI$1),FALSE) -> 0.029369015 | G98: =VLOOKUP($E98,Hybrid!$1:$1048576,MATCH(DATE(G$2,1,1),Hybrid!$A$1:$LI$1),FALSE) -> 0.032632558 | H98: =VLOOKUP($E98,Hybrid!$1:$1048576,MATCH(DATE(H$2,1,1),Hybrid!$A$1:$LI$1),FALSE) -> 0.034957703 | I98: =VLOOKUP($E98,Hybrid!$1:$1048576,MATCH(DATE(I$2,1,1),Hybrid!$A$1:$LI$1),FALSE) -> 0.035432871 | J98: =VLOOKUP($E98,Hybrid!$1:$1048576,MATCH(DATE(J$2,1,1),Hybrid!$A$1:$LI$1),FALSE) -> 0.035071333 | K98: =VLOOKUP($E98,Hybrid!$1:$1048576,MATCH(DATE(K$2,1,1),Hybrid!$A$1:$LI$1),FALSE) -> 0.034129712 | L98: =VLOOKUP($E98,Hybrid!$1:$1048576,MATCH(DATE(L$2,1,1),Hybrid!$A$1:$LI$1),FALSE) -> 0.031789042 | M98: =VLOOKUP($E98,Hybrid!$1:$1048576,MATCH(DATE(M$2,1,1),Hybrid!$A$1:$LI$1),FALSE) -> 0.028619979 | ... AO98: =VLOOKUP($E98,Hybrid!$1:$1048576,MATCH(DATE(AO$2,1,1),Hybrid!$A$1:$LI$1),FALSE) -> 1.1405038e-06
D99: class D | E99: NEWAUTO_cd_cgas_0 | F99: =VLOOKUP($E99,Hybrid!$1:$1048576,MATCH(DATE(F$2,1,1),Hybrid!$A$1:$LI$1),FALSE) -> 0.016317038 | G99: =VLOOKUP($E99,Hybrid!$1:$1048576,MATCH(DATE(G$2,1,1),Hybrid!$A$1:$LI$1),FALSE) -> 0.018192769 | H99: =VLOOKUP($E99,Hybrid!$1:$1048576,MATCH(DATE(H$2,1,1),Hybrid!$A$1:$LI$1),FALSE) -> 0.019638383 | I99: =VLOOKUP($E99,Hybrid!$1:$1048576,MATCH(DATE(I$2,1,1),Hybrid!$A$1:$LI$1),FALSE) -> 0.020205034 | J99: =VLOOKUP($E99,Hybrid!$1:$1048576,MATCH(DATE(J$2,1,1),Hybrid!$A$1:$LI$1),FALSE) -> 0.020427939 | K99: =VLOOKUP($E99,Hybrid!$1:$1048576,MATCH(DATE(K$2,1,1),Hybrid!$A$1:$LI$1),FALSE) -> 0.020325241 | L99: =VLOOKUP($E99,Hybrid!$1:$1048576,MATCH(DATE(L$2,1,1),Hybrid!$A$1:$LI$1),FALSE) -> 0.019470401 | M99: =VLOOKUP($E99,Hybrid!$1:$1048576,MATCH(DATE(M$2,1,1),Hybrid!$A$1:$LI$1),FALSE) -> 0.018317598 | ... AO99: =VLOOKUP($E99,Hybrid!$1:$1048576,MATCH(DATE(AO$2,1,1),Hybrid!$A$1:$LI$1),FALSE) -> 5.9644931e-05
D100: class E | E100: NEWAUTO_ce_cgas_0 | F100: =VLOOKUP($E100,Hybrid!$1:$1048576,MATCH(DATE(F$2,1,1),Hybrid!$A$1:$LI$1),FALSE) -> 0.01003532 | G100: =VLOOKUP($E100,Hybrid!$1:$1048576,MATCH(DATE(G$2,1,1),Hybrid!$A$1:$LI$1),FALSE) -> 0.011137172 | H100: =VLOOKUP($E100,Hybrid!$1:$1048576,MATCH(DATE(H$2,1,1),Hybrid!$A$1:$LI$1),FALSE) -> 0.011953696 | I100: =VLOOKUP($E100,Hybrid!$1:$1048576,MATCH(DATE(I$2,1,1),Hybrid!$A$1:$LI$1),FALSE) -> 0.012220736 | J100: =VLOOKUP($E100,Hybrid!$1:$1048576,MATCH(DATE(J$2,1,1),Hybrid!$A$1:$LI$1),FALSE) -> 0.012272714 | K100: =VLOOKUP($E100,Hybrid!$1:$1048576,MATCH(DATE(K$2,1,1),Hybrid!$A$1:$LI$1),FALSE) -> 0.012133167 | L100: =VLOOKUP($E100,Hybrid!$1:$1048576,MATCH(DATE(L$2,1,1),Hybrid!$A$1:$LI$1),FALSE) -> 0.011538261 | M100: =VLOOKUP($E100,Hybrid!$1:$1048576,MATCH(DATE(M$2,1,1),Hybrid!$A$1:$LI$1),FALSE) -> 0.010753579 | ... AO100: =VLOOKUP($E100,Hybrid!$1:$1048576,MATCH(DATE(AO$2,1,1),Hybrid!$A$1:$LI$1),FALSE) -> 3.3562875e-05
...

Sheet date
A1: =Hybrid!A1 -> _date_ | B1: =Hybrid!B1 -> 42005 | C1: =Hybrid!C1 -> 42370 | D1: =Hybrid!D1 -> 42736 | E1: =Hybrid!E1 -> 43101 | F1: =Hybrid!F1 -> 43466 | G1: =Hybrid!G1 -> 43831 | H1: =Hybrid!H1 -> 44197 | ... AK1: =Hybrid!AK1 -> 54789
B2: =TEXT(B1,"jj mm aaaa") -> 01 01 2015 | C2: =TEXT(C1,"jj mm aaaa") -> 01 01 2016 | D2: =TEXT(D1,"jj mm aaaa") -> 01 01 2017 | E2: =TEXT(E1,"jj mm aaaa") -> 01 01 2018 | F2: =TEXT(F1,"jj mm aaaa") -> 01 01 2019 | G2: =TEXT(G1,"jj mm aaaa") -> 01 01 2020 | H2: =TEXT(H1,"jj mm aaaa") -> 01 01 2021 | I2: =TEXT(I1,"jj mm aaaa") -> 01 01 2022 | ... AK2: =TEXT(AK1,"jj mm aaaa") -> 01 01 2050
B3: =RIGHT(B2,4) -> 2015 | C3: =RIGHT(C2,4) -> 2016 | D3: =RIGHT(D2,4) -> 2017 | E3: =RIGHT(E2,4) -> 2018 | F3: =RIGHT(F2,4) -> 2019 | G3: =RIGHT(G2,4) -> 2020 | H3: =RIGHT(H2,4) -> 2021 | I3: =RIGHT(I2,4) -> 2022 | ... AK3: =RIGHT(AK2,4) -> 2050

Sheet Emissions
A1: _date_ | B1: 42005 | C1: 42370 | D1: 42736 | E1: 43101 | F1: 43466 | G1: 43831 | H1: 44197 | I1: 44562 | J1: 44927 | K1: 45292 | L1: 45658 | M1: 46023 | N1: 46388 | O1: 46753 | P1: 47119 | Q1: 47484 | R1: 47849 | S1: 48214 | T1: 48580 | U1: 48945 | V1: 49310 | W1: 49675 | X1: 50041 | Y1: 50406 | Z1: 50771 | AA1: 51136 | AB1: 51502 | AC1: 51867 | AD1: 52232 | AE1: 52597 | AF1: 52963 | AG1: 53328 | AH1: 53693 | AI1: 54058 | AJ1: 54424 | AK1: 54789
A2: ems_2 | B2: 469.07576 | C2: 469.00124 | D2: 469.39889 | E2: 470.14113 | F2: 472.02735 | G2: 474.9534 | H2: 478.67718 | I2: 472.16174 | J2: 464.31584 | K2: 456.5632 | L2: 447.84378 | M2: 438.99573 | N2: 430.32475 | O2: 422.09667 | P2: 414.76482 | Q2: 408.45264 | R2: 403.04095 | S2: 398.23902 | T2: 393.89128 | U2: 389.91343 | V2: 386.33735 | W2: 383.27397 | X2: 380.8696 | Y2: 379.19097 | Z2: 378.1834 | AA2: 377.69803 | AB2: 377.52656 | AC2: 377.55548 | AD2: 377.68237 | AE2: 377.85767 | AF2: 378.10462 | AG2: 378.49664 | AH2: 379.06418 | AI2: 379.71139 | AJ2: 380.23406 | AK2: 380.39004
A3: ems_ch_2 | B3: 124.6337 | C3: 123.95233 | D3: 122.92697 | E3: 121.86722 | F3: 121.03572 | G3: 120.31562 | H3: 119.56594 | I3: 114.96023 | J3: 109.98206 | K3: 104.55274 | L3: 98.660013 | M3: 92.579856 | N3: 86.504043 | O3: 80.634063 | P3: 75.112235 | Q3: 70.012989 | R3: 65.323485 | S3: 61.034031 | T3: 57.108903 | U3: 53.506651 | V3: 50.19059 | W3: 47.130498 | X3: 44.301439 | Y3: 41.680703 | Z3: 39.250598 | AA3: 36.99604 | AB3: 34.902098 | AC3: 32.952401 | AD3: 31.129822 | AE3: 29.418825 | AF3: 27.806349 | AG3: 26.28144 | AH3: 24.83466 | AI3: 23.457772 | AJ3: 22.142593 | AK3: 20.88036
A4: ems_ch_2+ems_ci_2 | B4: 311.78714 | C4: 311.26993 | D4: 310.288 | E4: 309.00314 | F4: 308.53363 | G4: 308.90517 | H4: 310.02218 | I4: 301.29526 | J4: 291.71701 | K4: 281.74561 | L4: 270.64142 | M4: 259.04605 | N4: 247.1886 | O4: 235.47279 | P4: 224.41161 | Q4: 214.28732 | R4: 205.06322 | S4: 196.66888 | T4: 188.94112 | U4: 181.65868 | V4: 174.63814 | W4: 167.79238 | X4: 161.14145 | Y4: 154.75277 | Z4: 148.70362 | AA4: 143.03565 | AB4: 137.74674 | AC4: 132.7483 | AD4: 127.83196 | AE4: 122.75135 | AF4: 117.33396 | AG4: 111.54581 | AH4: 105.45298 | AI4: 99.125211 | AJ4: 92.575767 | AK4: 85.735254
A5: ems_ci_2 | B5: 187.15344 | C5: 187.3176 | D5: 187.36103 | E5: 187.13592 | F5: 187.49791 | G5: 188.58955 | H5: 190.45624 | I5: 186.33504 | J5: 181.73495 | K5: 177.19287 | L5: 171.98141 | M5: 166.4662 | N5: 160.68455 | O5: 154.83873 | P5: 149.29937 | Q5: 144.27433 | R5: 139.73974 | S5: 135.63485 | T5: 131.83222 | U5: 128.15203 | V5: 124.44755 | W5: 120.66188 | X5: 116.84001 | Y5: 113.07207 | Z5: 109.45302 | AA5: 106.03961 | AB5: 102.84464 | AC5: 99.795903 | AD5: 96.702136 | AE5: 93.332527 | AF5: 89.527616 | AG5: 85.264367 | AH5: 80.618319 | AI5: 75.66744 | AJ5: 70.433173 | AK5: 64.854894
A6: ems_mat_2 | B6: 66.838806 | C6: 68.057405 | D6: 69.454022 | E6: 70.734855 | F6: 71.910722 | G6: 73.056259 | H6: 74.195611 | I6: 75.612939 | J6: 76.888326 | K6: 78.29403 | L6: 79.657092 | M6: 81.020528 | N6: 82.395135 | O6: 83.763632 | P6: 85.158357 | Q6: 86.572202 | R6: 88.060077 | S6: 89.515005 | T6: 90.923262 | U6: 92.30851 | V6: 93.722994 | W6: 95.224449 | X6: 96.859381 | Y6: 98.639926 | Z6: 100.53896 | AA6: 102.50868 | AB6: 104.49665 | AC6: 106.49281 | AD6: 108.51075 | AE6: 110.58291 | AF6: 112.75044 | AG6: 115.05025 | AH6: 117.4951 | AI6: 120.06262 | AJ6: 122.70887 | AK6: 125.39122
A7: ems_y_2 | B7: 90.449821 | C7: 89.673909 | D7: 89.656862 | E7: 90.403131 | F7: 91.582996 | G7: 92.991968 | H7: 94.459392 | I7: 95.253533 | J7: 95.710501 | K7: 96.523556 | L7: 97.545272 | M7: 98.929149 | N7: 100.74101 | O7: 102.86025 | P7: 105.19486 | Q7: 107.59312 | R7: 109.91765 | S7: 112.05514 | T7: 114.0269 | U7: 115.94623 | V7: 117.97621 | W7: 120.25715 | X7: 122.86876 | Y7: 125.79827 | Z7: 128.94082 | AA7: 132.1537 | AB7: 135.28318 | AC7: 138.31437 | AD7: 141.33966 | AE7: 144.52342 | AF7: 148.02021 | AG7: 151.90058 | AH7: 156.1161 | AI7: 160.52355 | AJ7: 164.94943 | AK7: 169.26357
A8: ems_sec_2 | B8: 344.44206 | C8: 345.04891 | D8: 346.47192 | E8: 348.27391 | F8: 350.99163 | G8: 354.63777 | H8: 359.11124 | I8: 357.20151 | J8: 354.33378 | K8: 352.01046 | L8: 349.18377 | M8: 346.41587 | N8: 343.8207 | O8: 341.46261 | P8: 339.65259 | Q8: 338.43965 | R8: 337.71746 | S8: 337.20499 | T8: 336.78238 | U8: 336.40677 | V8: 336.14676 | W8: 336.14347 | X8: 336.56816 | Y8: 337.51026 | Z8: 338.9328 | AA8: 340.70199 | AB8: 342.62446 | AC8: 344.60308 | AD8: 346.55254 | AE8: 348.43885 | AF8: 350.29827 | AG8: 352.2152 | AH8: 354.22952 | AI8: 356.25362 | AJ8: 358.09147 | AK8: 359.50968
A9: ems_ets_2 | B9: 121.03612 | C9: 122.8654 | D9: 124.86961 | E9: 126.57085 | F9: 128.22663 | G9: 129.98278 | H9: 131.86648 | I9: 131.68043 | J9: 131.05564 | K9: 130.65949 | L9: 130.01264 | M9: 129.248 | N9: 128.36981 | O9: 127.37385 | P9: 126.38918 | Q9: 125.45459 | R9: 124.6729 | S9: 123.86585 | T9: 122.99602 | U9: 122.06517 | V9: 121.11702 | W9: 120.21693 | X9: 119.43234 | Y9: 118.79056 | Z9: 118.26926 | AA9: 117.81654 | AB9: 117.37684 | AC9: 116.92301 | AD9: 116.42901 | AE9: 115.87923 | AF9: 115.28215 | AG9: 114.66969 | AH9: 114.06529 | AI9: 113.4515 | AJ9: 112.77552 | AK9: 111.96882
A10: ems_nets_2 | B10: 223.40594 | C10: 222.18352 | D10: 221.6023 | E10: 221.70306 | F10: 222.765 | G10: 224.65499 | H10: 227.24476 | I10: 225.52108 | J10: 223.27814 | K10: 221.35097 | L10: 219.17113 | M10: 217.16787 | N10: 215.45089 | O10: 214.08876 | P10: 213.26341 | Q10: 212.98505 | R10: 213.04457 | S10: 213.33914 | T10: 213.78636 | U10: 214.3416 | V10: 215.02974 | W10: 215.92655 | X10: 217.13582 | Y10: 218.7197 | Z10: 220.66355 | AA10: 222.88545 | AB10: 225.24762 | AC10: 227.68006 | AD10: 230.12354 | AE10: 232.55962 | AF10: 235.01612 | AG10: 237.54551 | AH10: 240.16422 | AI10: 242.80212 | AJ10: 245.31595 | AK10: 247.54086
A11: ems_netsi_2 | B11: 26.593168 | C11: 26.89773 | D11: 27.245463 | E11: 27.383886 | F11: 27.508687 | G11: 27.684606 | H11: 27.933897 | I11: 27.135581 | J11: 26.233471 | K11: 25.395764 | L11: 24.582194 | M11: 23.890444 | N11: 23.291591 | O11: 22.767581 | P11: 22.322764 | Q11: 21.949079 | R11: 21.594833 | S11: 21.258157 | T11: 20.931169 | U11: 20.60822 | V11: 20.291526 | W11: 19.989577 | X11: 19.713266 | Y11: 19.468223 | Z11: 19.25172 | AA11: 19.054128 | AB11: 18.861035 | AC11: 18.661898 | AD11: 18.445406 | AE11: 18.204032 | AF11: 17.936679 | AG11: 17.646861 | AH11: 17.335665 | AI11: 16.995839 | AJ11: 16.612422 | AK11: 16.166436
A12: ems_trsp_2-ems_sair_2 | B12: 27.188223 | C12: 27.095595 | D12: 27.049391 | E12: 27.061733 | F12: 27.191839 | G12: 27.414014 | H12: 27.689649 | I12: 26.826153 | J12: 25.900377 | K12: 25.087009 | L12: 24.300468 | M12: 23.578272 | N12: 22.896095 | O12: 22.231576 | P12: 21.592402 | Q12: 20.973863 | R12: 20.359987 | S12: 19.74457 | T12: 19.12353 | U12: 18.495108 | V12: 17.862795 | W12: 17.23256 | X12: 16.609625 | Y12: 15.991778 | Z12: 15.369641 | AA12: 14.730681 | AB12: 14.064878 | AC12: 13.365976 | AD12: 12.626377 | AE12: 11.839826 | AF12: 11.002908 | AG12: 10.11436 | AH12: 9.170659 | AI12: 8.1627521 | AJ12: 7.078533 | AK12: 5.9054397
... A887: ems_mat_co2_sgla_0 | B887: 13.759076 | C887: 14.277108 | D887: 14.881603 | E887: 15.326016 | F887: 15.630043 | G887: 15.868878 | H887: 16.065441 | I887: 16.228301 | J887: 16.369544 | K887: 16.510915 | L887: 16.676674 | M887: 16.885224 | N887: 17.139224 | O887: 17.423159 | P887: 17.729541 | Q887: 18.04899 | R887: 18.390019 | S887: 18.758011 | T887: 19.150818 | U887: 19.558924 | V887: 19.971298 | W887: 20.380605 | X887: 20.78836 | Y887: 21.203381 | Z887: 21.636987 | AA887: 22.099974 | AB887: 22.597856 | AC887: 23.129634 | AD887: 23.687724 | AE887: 24.260891 | AF887: 24.842019 | AG887: 25.432586 | AH887: 26.040246 | AI887: 26.673383 | AJ887: 27.336327 | AK887: 28.027159

Sheet Consumption
A1: _date_ | B1: 42005 | C1: 42370 | D1: 42736 | E1: 43101 | F1: 43466 | G1: 43831 | H1: 44197 | I1: 44562 | J1: 44927 | K1: 45292 | L1: 45658 | M1: 46023 | N1: 46388 | O1: 46753 | P1: 47119 | Q1: 47484 | R1: 47849 | S1: 48214 | T1: 48580 | U1: 48945 | V1: 49310 | W1: 49675 | X1: 50041 | Y1: 50406 | Z1: 50771 | AA1: 51136 | AB1: 51502 | AC1: 51867 | AD1: 52232 | AE1: 52597 | AF1: 52963 | AG1: 53328 | AH1: 53693 | AI1: 54058 | AJ1: 54424 | AK1: 54789
A2: ch_2 | B2: 1206688.2 | C2: 1218330.4 | D2: 1242081.4 | E2: 1267244.5 | F2: 1290489.9 | G2: 1311917.2 | H2: 1330951.1 | I2: 1342916.6 | J2: 1351830.6 | K2: 1364702.1 | L2: 1385095.3 | M2: 1414323.7 | N2: 1451172.5 | O2: 1491830 | P2: 1532317.3 | Q2: 1569647.1 | R2: 1602766.1 | S2: 1630947.9 | T2: 1655715.1 | U2: 1679819.3 | V2: 1706049.4 | W2: 1736087.2 | X2: 1770100 | Y2: 1806980 | Z2: 1844682.9 | AA2: 1881172.6 | AB2: 1915000 | AC2: 1946533.3 | AD2: 1978620.2 | AE2: 2014961 | AF2: 2058008.9 | AG2: 2107682.6 | AH2: 2161634.5 | AI2: 2216681 | AJ2: 2270104.4 | AK2: 2320692.3
A3: ch_0 | B3: 1206688.2 | C3: 1218330.4 | D3: 1242081.4 | E3: 1267244.5 | F3: 1290489.9 | G3: 1311917.2 | H3: 1328799.2 | I3: 1342362.6 | J3: 1355300.1 | K3: 1370491.9 | L3: 1389822.1 | M3: 1413839.1 | N3: 1441739.7 | O3: 1471730.6 | P3: 1501882.8 | Q3: 1530690.9 | R3: 1559671.3 | S3: 1588686.5 | T3: 1617313.4 | U3: 1645065.4 | V3: 1671705.3 | W3: 1697560.3 | X3: 1723615.7 | Y3: 1751228.9 | Z3: 1781513.9 | AA3: 1814983.2 | AB3: 1851391.2 | AC3: 1889978.6 | AD3: 1929901.6 | AE3: 1970820.4 | AF3: 2013018.8 | AG3: 2057214.7 | AH3: 2104093.1 | AI3: 2153856.6 | AJ3: 2206054.2 | AK3: 2259736.7
A4: pch_2 | B4: 1.0033221 | C4: 1.0202343 | D4: 1.0342978 | E4: 1.0487172 | F4: 1.0609475 | G4: 1.0739406 | H4: 1.0901462 | I4: 1.1268116 | J4: 1.1688356 | K4: 1.2129786 | L4: 1.2552477 | M4: 1.2877973 | N4: 1.3114587 | O4: 1.3283029 | P4: 1.3414568 | Q4: 1.3540676 | R4: 1.3693405 | S4: 1.3886866 | T4: 1.4113867 | U4: 1.4352733 | V4: 1.4577891 | W4: 1.4773778 | X4: 1.4941125 | Y4: 1.5095505 | Z4: 1.5265788 | AA4: 1.5482434 | AB4: 1.57732 | AC4: 1.6144629 | AD4: 1.6569444 | AE4: 1.7005122 | AF4: 1.7417336 | AG4: 1.7797953 | AH4: 1.8164473 | AI4: 1.8544547 | AJ4: 1.8963634 | AK4: 1.9432702
A5: pch_0 | B5: 1.0033221 | C5: 1.0202343 | D5: 1.0342978 | E5: 1.0487172 | F5: 1.0609475 | G5: 1.0739406 | H5: 1.0937659 | I5: 1.1188855 | J5: 1.1473813 | K5: 1.1761277 | L5: 1.2027151 | M5: 1.2257343 | N5: 1.2450108 | O5: 1.2611913 | P5: 1.2755967 | Q5: 1.2897384 | R5: 1.3009386 | S5: 1.310734 | T5: 1.3204166 | U5: 1.3314739 | V5: 1.3451657 | W5: 1.3620468 | X5: 1.3818311 | Y5: 1.4036333 | Z5: 1.4266421 | AA5: 1.4505144 | AB5: 1.4756898 | AC5: 1.5032277 | AD5: 1.5343207 | AE5: 1.5693851 | AF5: 1.6079226 | AG5: 1.6487155 | AH5: 1.6904019 | AI5: 1.7320319 | AJ5: 1.7733195 | AK5: 1.8145441
A6: ch_cagr_2 | B6: 31626.626 | C6: 31220.395 | D6: 31249.146 | E6: 31666.765 | F6: 32243.393 | G6: 32873.2 | H6: 33484.909 | I6: 33933.325 | J6: 34252.267 | K6: 34631.156 | L6: 35187.224 | M6: 35982.106 | N6: 37038.612 | O6: 38261.677 | P6: 39529.838 | Q6: 40740.01 | R6: 41833.062 | S6: 42773.438 | T6: 43604.576 | U6: 44406.5 | V6: 45259.469 | W6: 46211.976 | X6: 47271.496 | Y6: 48411.296 | Z6: 49578.068 | AA6: 50717.845 | AB6: 51790.534 | AC6: 52806.782 | AD6: 53845.95 | AE6: 55010.336 | AF6: 56367.131 | AG6: 57913.367 | AH6: 59584.323 | AI6: 61292.876 | AJ6: 62964.071 | AK6: 64563.913
A7: ch_cagr_0 | B7: 31626.626 | C7: 31220.395 | D7: 31249.146 | E7: 31666.765 | F7: 32243.393 | G7: 32873.2 | H7: 33443.833 | I7: 33938.196 | J7: 34410.131 | K7: 34933.669 | L7: 35563.148 | M7: 36319.354 | N7: 37185.837 | O7: 38116.831 | P7: 39058.889 | Q7: 39967.474 | R7: 40866.765 | S7: 41767.59 | T7: 42662.899 | U7: 43538.938 | V7: 44387.545 | W7: 45216.625 | X7: 46053.816 | Y7: 46937.851 | Z7: 47900.436 | AA7: 48956.022 | AB7: 50097.901 | AC7: 51306.269 | AD7: 52558.139 | AE7: 53845.033 | AF7: 55174.839 | AG7: 56567.126 | AH7: 58040.888 | AI7: 59601.228 | AJ7: 61234.472 | AK7: 62912.511
A8: pch_cagr_2 | B8: 1.0024795 | C8: 1.0175553 | D8: 1.0295943 | E8: 1.0420635 | F8: 1.0537651 | G8: 1.0664279 | H8: 1.0820378 | I8: 1.1161579 | J8: 1.1568839 | K8: 1.1993894 | L8: 1.2398339 | M8: 1.2711047 | N8: 1.2928717 | O8: 1.3078905 | P8: 1.3197028 | Q8: 1.331531 | R8: 1.346612 | S8: 1.3661438 | T8: 1.3889403 | U8: 1.4126762 | V8: 1.434864 | W8: 1.4541729 | X8: 1.4708624 | Y8: 1.4864942 | Z8: 1.5038286 | AA8: 1.5255856 | AB8: 1.5542848 | AC8: 1.5903149 | AD8: 1.6307092 | AE8: 1.6713011 | AF8: 1.7089979 | AG8: 1.7433935 | AH8: 1.7764352 | AI8: 1.810736 | AJ8: 1.8485502 | AK8: 1.8906684
A9: pch_cagr_0 | B9: 1.0024795 | C9: 1.0175553 | D9: 1.0295943 | E9: 1.0420635 | F9: 1.0537651 | G9: 1.0664279 | H9: 1.084646 | I9: 1.1078471 | J9: 1.1339428 | K9: 1.159981 | L9: 1.1837584 | M9: 1.2040329 | N9: 1.2208167 | O9: 1.2349155 | P9: 1.2477501 | Q9: 1.2608034 | R9: 1.2721022 | S9: 1.2822543 | T9: 1.2924515 | U9: 1.3040551 | V9: 1.3181578 | W9: 1.3351451 | X9: 1.3546328 | Y9: 1.3757341 | Z9: 1.3977345 | AA9: 1.4203728 | AB9: 1.4441278 | AC9: 1.4700053 | AD9: 1.4990714 | AE9: 1.5315595 | AF9: 1.5669012 | AG9: 1.6039224 | AH9: 1.6413945 | AI9: 1.6785368 | AJ9: 1.7152111 | AK9: 1.7517891
A10: ch_cfoo_2 | B10: 175055.13 | C10: 172757.36 | D10: 172812.18 | E10: 175034.95 | F10: 178139.19 | G10: 181564.58 | H10: 184948.79 | I10: 187791.42 | J10: 190011.88 | K10: 192477.66 | L10: 195763.02 | M10: 200116.92 | N10: 205704.44 | O10: 212114.43 | P10: 218792.61 | Q10: 225252.02 | R10: 231226.4 | S10: 236512.92 | T10: 241277.56 | U10: 245874.86 | V10: 250684.57 | W10: 255959.75 | X10: 261768.96 | Y10: 268010.53 | Z10: 274442.76 | AA10: 280799.7 | AB10: 286875.23 | AC10: 292694.95 | AD10: 298600.28 | AE10: 305062.97 | AF10: 312416.45 | AG10: 320682.87 | AH10: 329590.89 | AI10: 338737.38 | AJ10: 347751.6 | AK10: 356437.59
A11: ch_cfoo_0 | B11: 175055.13 | C11: 172757.36 | D11: 172812.18 | E11: 175034.95 | F11: 178139.19 | G11: 181564.58 | H11: 184754.91 | I11: 187586.87 | J11: 190291.73 | K11: 193213.74 | L11: 196624.56 | M11: 200644.52 | N11: 205215.39 | O11: 210129.24 | P11: 215136.31 | Q11: 220022.98 | R11: 224887.1 | S11: 229784.98 | T11: 234690.21 | U11: 239539.25 | V11: 244287.25 | W11: 248959.32 | X11: 253675.4 | Y11: 258614.98 | Z11: 263933.96 | AA11: 269711.97 | AB11: 275929.73 | AC11: 282502.53 | AD11: 289321.28 | AE11: 296333.41 | AF11: 303558.86 | AG11: 311076.47 | AH11: 318971.94 | AI11: 327274.19 | AJ11: 335927.85 | AK11: 344808.26
A12: pch_cfoo_2 | B12: 1.0015859 | C12: 1.0178685 | D12: 1.0313692 | E12: 1.0446357 | F12: 1.0572366 | G12: 1.0703554 | H12: 1.0856245 | I12: 1.1135787 | J12: 1.1488198 | K12: 1.1877005 | L12: 1.2266484 | M12: 1.2599797 | N12: 1.285965 | O12: 1.3054021 | P12: 1.3205474 | Q12: 1.3341021 | R12: 1.3489278 | S12: 1.3667652 | T12: 1.3875589 | U12: 1.4098812 | V12: 1.4317091 | W12: 1.4515476 | X12: 1.4691202 | Y12: 1.4854313 | Z12: 1.5027114 | AA12: 1.5235306 | AB12: 1.5503553 | AC12: 1.584156 | AD12: 1.6232744 | AE12: 1.6644461 | AF12: 1.704625 | AG12: 1.7425406 | AH12: 1.7790105 | AI12: 1.816 | AJ12: 1.8556223 | AK12: 1.8990764
... A105: pch_cbio_0 | B105: 1.0658525 | C105: 1.1145233 | D105: 1.1632549 | E105: 1.2360212 | F105: 1.246014 | G105: 1.2572502 | H105: 1.2746586 | I105: 1.2963218 | J105: 1.3282845 | K105: 1.3615757 | L105: 1.3928996 | M105: 1.420227 | N105: 1.443043 | O105: 1.4619555 | P105: 1.4785035 | Q105: 1.4946114 | R105: 1.5089637 | S105: 1.5216513 | T105: 1.5341354 | U105: 1.5481269 | V105: 1.5651997 | W105: 1.5861953 | X105: 1.6109482 | Y105: 1.6384727 | Z105: 1.6676668 | AA105: 1.6979266 | AB105: 1.7295656 | AC105: 1.7637568 | AD105: 1.8019894 | AE105: 1.8450351 | AF105: 1.8925117 | AG105: 1.9430512 | AH105: 1.9949323 | AI105: 2.0467986 | AJ105: 2.0980773 | AK105: 2.1489628

Sheet Value_Added
A1: _date_ | B1: 42005 | C1: 42370 | D1: 42736 | E1: 43101 | F1: 43466 | G1: 43831 | H1: 44197 | I1: 44562 | J1: 44927 | K1: 45292 | L1: 45658 | M1: 46023 | N1: 46388 | O1: 46753 | P1: 47119 | Q1: 47484 | R1: 47849 | S1: 48214 | T1: 48580 | U1: 48945 | V1: 49310 | W1: 49675 | X1: 50041 | Y1: 50406 | Z1: 50771 | AA1: 51136 | AB1: 51502 | AC1: 51867 | AD1: 52232 | AE1: 52597 | AF1: 52963 | AG1: 53328 | AH1: 53693 | AI1: 54058 | AJ1: 54424 | AK1: 54789
A2: va_2 | B2: 1956934.8 | C2: 1976791 | D2: 2007555 | E2: 2042148.2 | F2: 2078164.8 | G2: 2114793.2 | H2: 2150372.3 | I2: 2172092.8 | J2: 2189226.9 | K2: 2215098.3 | L2: 2245999.8 | M2: 2284674.3 | N2: 2331042.5 | O2: 2382331.4 | P2: 2436804.3 | Q2: 2491630.4 | R2: 2543887.5 | S2: 2592402.9 | T2: 2637850 | U2: 2682632.5 | V2: 2730011.5 | W2: 2782631.4 | X2: 2841772.6 | Y2: 2906809.8 | Z2: 2975320.4 | AA2: 3044285.7 | AB2: 3111176.8 | AC2: 3175560.4 | AD2: 3239729.3 | AE2: 3307327.9 | AF2: 3381548.9 | AG2: 3463649.9 | AH2: 3552381 | AI2: 3644689.2 | AJ2: 3737171.1 | AK2: 3827650.2
A3: va_0 | B3: 1956934.8 | C3: 1976791 | D3: 2007555 | E3: 2042148.2 | F3: 2078164.8 | G3: 2114793.2 | H3: 2148198.1 | I3: 2177761.3 | J3: 2205267.8 | K3: 2233733 | L3: 2265882 | M3: 2303262.5 | N3: 2345359.6 | O3: 2389739.5 | P3: 2435615.3 | Q3: 2481851.9 | R3: 2529742.9 | S3: 2579893 | T3: 2631927.1 | U3: 2684881.3 | V3: 2737890.6 | W3: 2790640.2 | X3: 2843888.3 | Y3: 2899016.1 | Z3: 2957353 | AA3: 3019879.6 | AB3: 3086787.5 | AC3: 3157639.9 | AD3: 3231343.2 | AE3: 3306662.8 | AF3: 3383064.8 | AG3: 3461018.6 | AH3: 3541496.4 | AI3: 3625237.3 | AJ3: 3712310.8 | AK3: 3802063.2
A4: va_sagr_2 | B4: 31815.932 | C4: 31413.994 | D4: 31453.636 | E4: 31797.396 | F4: 32273.552 | G4: 32807.347 | H4: 33337.39 | I4: 33589.163 | J4: 33736.23 | K4: 34060.101 | L4: 34477.049 | M4: 35055.061 | N4: 35814.851 | O4: 36692.999 | P4: 37643.05 | Q4: 38594.664 | R4: 39493.552 | S4: 40293.469 | T4: 41013.067 | U4: 41707.717 | V4: 42449.544 | W4: 43294.83 | X4: 44269.678 | Y4: 45359.42 | Z4: 46511.71 | AA4: 47662.832 | AB4: 48746.884 | AC4: 49766.003 | AD4: 50769.654 | AE4: 51837.669 | AF4: 53039.247 | AG4: 54398.675 | AH4: 55884.009 | AI4: 57424.812 | AJ4: 58943.587 | AK4: 60387.969
A5: va_sagr_0 | B5: 31815.932 | C5: 31413.994 | D5: 31453.636 | E5: 31797.396 | F5: 32273.552 | G5: 32807.347 | H5: 33296.754 | I5: 33712.087 | J5: 34088.947 | K5: 34492.42 | L5: 34981.067 | M5: 35586.073 | N5: 36292.011 | O5: 37042.031 | P5: 37818.403 | Q5: 38594.328 | R5: 39394.879 | S5: 40232.68 | T5: 41101.01 | U5: 41979.417 | V5: 42849.896 | W5: 43706.265 | X5: 44566.241 | Y5: 45460.773 | Z5: 46419.137 | AA5: 47462.511 | AB5: 48594.216 | AC5: 49804.255 | AD5: 51067.334 | AE5: 52355.684 | AF5: 53657.93 | AG5: 54985.732 | AH5: 56361.953 | AI5: 57803.082 | AJ5: 59309.624 | AK5: 60865.56
A6: va_sfor_2 | B6: 3332.4366 | C6: 3241.0374 | D6: 3181.4153 | E6: 3135.3639 | F6: 3108.3103 | G6: 3094.9069 | H6: 3091.4368 | I6: 3056.2301 | J6: 3022.848 | K6: 3004.0968 | L6: 2986.1487 | M6: 2975.1237 | N6: 2968.3562 | O6: 2965.4145 | P6: 2969.2466 | Q6: 2980.0652 | R6: 2992.2341 | S6: 3006.9569 | T6: 3023.6494 | U6: 3042.4621 | V6: 3064.7761 | W6: 3092.473 | X6: 3127.3074 | Y6: 3169.6848 | Z6: 3218.4245 | AA6: 3271.4798 | AB6: 3326.7975 | AC6: 3383.6626 | AD6: 3441.959 | AE6: 3502.3198 | AF6: 3566.0857 | AG6: 3634.8491 | AH6: 3709.2839 | AI6: 3788.3089 | AJ6: 3869.6892 | AK6: 3951.0737
A7: va_sfor_0 | B7: 3332.4366 | C7: 3241.0374 | D7: 3181.4153 | E7: 3135.3639 | F7: 3108.3103 | G7: 3094.9069 | H7: 3090.345 | I7: 3090.9392 | J7: 3094.9362 | K7: 3102.3774 | L7: 3114.1448 | M7: 3131.1372 | N7: 3152.6214 | O7: 3175.8405 | P7: 3201.4505 | Q7: 3229.5688 | R7: 3260.8145 | S7: 3296.3474 | T7: 3336.3988 | U7: 3380.2757 | V7: 3427.1032 | W7: 3476.0938 | X7: 3527.2627 | Y7: 3581.0469 | Z7: 3637.9991 | AA7: 3698.9045 | AB7: 3764.3356 | AC7: 3834.6268 | AD7: 3909.1747 | AE7: 3986.295 | AF7: 4064.4157 | AG7: 4142.9547 | AH7: 4222.2104 | AI7: 4302.7802 | AJ7: 4385.0796 | AK7: 4469.0581
A8: va_sfoo_2 | B8: 43216.892 | C8: 42884.487 | D8: 43219.034 | E8: 43927.455 | F8: 44738.567 | G8: 45583.948 | H8: 46402.037 | I8: 46886.265 | J8: 47256.723 | K8: 47851.718 | L8: 48558.678 | M8: 49454.688 | N8: 50568.748 | O8: 51809.682 | P8: 53116.888 | Q8: 54407.522 | R8: 55631.967 | S8: 56738.034 | T8: 57760.981 | U8: 58772.528 | V8: 59856.884 | W8: 61073.316 | X8: 62444.295 | Y8: 63946.946 | Z8: 65518.029 | AA8: 67086.593 | AB8: 68576.417 | AC8: 70008.625 | AD8: 71450.606 | AE8: 72998.705 | AF8: 74725.175 | AG8: 76642.162 | AH8: 78697.981 | AI8: 80805.378 | AJ8: 82878.334 | AK8: 84867.48
A9: va_sfoo_0 | B9: 43216.892 | C9: 42884.487 | D9: 43219.034 | E9: 43927.455 | F9: 44738.567 | G9: 45583.948 | H9: 46348.047 | I9: 47015.097 | J9: 47642.111 | K9: 48308.855 | L9: 49079.579 | M9: 49984.028 | N9: 50997.785 | O9: 52050.809 | P9: 53125.684 | Q9: 54192.821 | R9: 55292.692 | S9: 56440.501 | T9: 57626.594 | U9: 58827.819 | V9: 60026.714 | W9: 61220.871 | X9: 62435.821 | Y9: 63709.651 | Z9: 65074.685 | AA9: 66551.664 | AB9: 68140.02 | AC9: 69826.111 | AD9: 71580.479 | AE9: 73373.677 | AF9: 75195.613 | AG9: 77060.694 | AH9: 78992.531 | AI9: 81004.197 | AJ9: 83089.819 | AK9: 85226.26
A10: va_sveh_2 | B10: 29816.948 | C10: 30147.121 | D10: 30683.195 | E10: 31240.322 | F10: 31831.119 | G10: 32425.155 | H10: 32988.897 | I10: 33040.882 | J10: 33189.988 | K10: 33826.476 | L10: 34363.674 | M10: 34945.132 | N10: 35518.947 | O10: 36037.451 | P10: 36590.633 | Q10: 37179.379 | R10: 37720.188 | S10: 38281.455 | T10: 38863.142 | U10: 39486.26 | V10: 40187.589 | W10: 40995.584 | X10: 41932.15 | Y10: 42991.98 | Z10: 44144.513 | AA10: 45357.968 | AB10: 46640.769 | AC10: 47943.223 | AD10: 49288.005 | AE10: 50690.971 | AF10: 52169.574 | AG10: 53733.203 | AH10: 55367.973 | AI10: 57038.324 | AJ10: 58702.172 | AK10: 60327.838
A11: va_sveh_0 | B11: 29816.948 | C11: 30147.121 | D11: 30683.195 | E11: 31240.322 | F11: 31831.119 | G11: 32425.155 | H11: 32925.541 | I11: 33389.327 | J11: 33845.689 | K11: 34326.861 | L11: 34856.996 | M11: 35445.606 | N11: 36055.353 | O11: 36609.564 | P11: 37163.298 | Q11: 37729.177 | R11: 38375.899 | S11: 39081.092 | T11: 39842.841 | U11: 40652.642 | V11: 41507.237 | W11: 42404.346 | X11: 43359.171 | Y11: 44385.014 | Z11: 45489.268 | AA11: 46684.011 | AB11: 47974.915 | AC11: 49367.597 | AD11: 50844.824 | AE11: 52367.135 | AF11: 53906.485 | AG11: 55460.004 | AH11: 57038.124 | AI11: 58649.145 | AJ11: 60293.27 | AK11: 61961.163
A12: va_sgla_2 | B12: 7283.8254 | C12: 7620.3956 | D12: 7950.012 | E12: 8163.6555 | F12: 8315.7756 | G12: 8447.9758 | H12: 8570.0857 | I12: 8602.8646 | J12: 8612.3428 | K12: 8661.0704 | L12: 8733.946 | M12: 8847.6033 | N12: 8993.9677 | O12: 9162.6811 | P12: 9347.6905 | Q12: 9536.1944 | R12: 9718.3376 | S12: 9881.1134 | T12: 10025.45 | U12: 10161.588 | V12: 10305.84 | W12: 10472.568 | X12: 10668.919 | Y12: 10891.478 | Z12: 11126.93 | AA12: 11358.497 | AB12: 11569.258 | AC12: 11759.692 | AD12: 11940.663 | AE12: 12131.233 | AF12: 12349.232 | AG12: 12603.369 | AH12: 12889.254 | AI12: 13192.245 | AJ12: 13494.913 | AK12: 13785.1
... A79: va_ser_0 | B79: 1517459 | C79: 1526637.4 | D79: 1545924.1 | E79: 1571778.5 | F79: 1600253.8 | G79: 1629564.5 | H79: 1656399 | I79: 1680135.4 | J79: 1702180.8 | K79: 1724899.1 | L79: 1750391.9 | M79: 1779820.3 | N79: 1812839.5 | O79: 1847716.8 | P79: 1883624.3 | Q79: 1919624.1 | R79: 1956654.8 | S79: 1995160.4 | T79: 2034896.4 | U79: 2075172.2 | V79: 2115359.3 | W79: 2155255.5 | X79: 2195455.5 | Y79: 2237043.3 | Z79: 2281060.6 | AA79: 2328228.9 | AB79: 2378649.2 | AC79: 2431934.6 | AD79: 2487245.3 | AE79: 2543716.8 | AF79: 2601015.5 | AG79: 2659530.9 | AH79: 2720008.5 | AI79: 2782995.7 | AJ79: 2848517.6 | AK79: 2916051.2

Sheet INV
A1: _date_ | B1: 42005 | C1: 42370 | D1: 42736 | E1: 43101 | F1: 43466 | G1: 43831 | H1: 44197 | I1: 44562 | J1: 44927 | K1: 45292 | L1: 45658 | M1: 46023 | N1: 46388 | O1: 46753 | P1: 47119 | Q1: 47484 | R1: 47849 | S1: 48214 | T1: 48580 | U1: 48945 | V1: 49310 | W1: 49675 | X1: 50041 | Y1: 50406 | Z1: 50771 | AA1: 51136 | AB1: 51502 | AC1: 51867 | AD1: 52232 | AE1: 52597 | AF1: 52963 | AG1: 53328 | AH1: 53693 | AI1: 54058 | AJ1: 54424 | AK1: 54789
A2: ia_2 | B2: 472269.51 | C2: 476650.75 | D2: 483141.81 | E2: 491612.93 | F2: 501574.35 | G2: 512137.73 | H2: 522274.24 | I2: 527502.91 | J2: 529929.99 | K2: 533196.57 | L2: 538438.84 | M2: 547037.06 | N2: 559464.65 | O2: 575206.68 | P2: 593355.05 | Q2: 612576.62 | R2: 631326.12 | S2: 648536.35 | T2: 664112.76 | U2: 678854.6 | V2: 694059.64 | W2: 710937.16 | X2: 730186.18 | Y2: 751735.72 | Z2: 774649.54 | AA2: 797529.76 | AB2: 819041.02 | AC2: 838719.67 | AD2: 857432.91 | AE2: 876847.15 | AF2: 898606.28 | AG2: 923618.83 | AH2: 951713.98 | AI2: 981820.47 | AJ2: 1012493.2 | AK2: 1042631.9
A3: ia_0 | B3: 472269.51 | C3: 476650.75 | D3: 483141.81 | E3: 491612.93 | F3: 501574.35 | G3: 512137.73 | H3: 521411.03 | I3: 528932.35 | J3: 535241.64 | K3: 541496.95 | L3: 548866.28 | M3: 558184.92 | N3: 569674.44 | O3: 582884.76 | P3: 597281.16 | Q3: 612217.8 | R3: 628044.89 | S3: 644779.54 | T3: 662156.1 | U3: 679653.51 | V3: 696732.71 | W3: 713113.57 | X3: 728977.98 | Y3: 744884.18 | Z3: 761474.97 | AA3: 779257.56 | AB3: 798411.76 | AC3: 818789.42 | AD3: 839997.2 | AE3: 861660.25 | AF3: 883667.68 | AG3: 906268.6 | AH3: 929928.76 | AI3: 955070.68 | AJ3: 981870.81 | AK3: 1010191.3
A4: ia_sagr_2 | B4: 11272.937 | C4: 11247.539 | D4: 11246.95 | E4: 11330.344 | F4: 11480.108 | G4: 11668.312 | H4: 11865.458 | I4: 11988.134 | J4: 12052.96 | K4: 12144.327 | L4: 12287.64 | M4: 12509.164 | N4: 12828.034 | O4: 13234.178 | P4: 13704.819 | Q4: 14205.239 | R4: 14700.865 | S4: 15160.104 | T4: 15577.748 | U4: 15972.745 | V4: 16378.064 | W4: 16825.178 | X4: 17332.902 | Y4: 17900.378 | Z4: 18504.483 | AA4: 19109.795 | AB4: 19678.104 | AC4: 20196.656 | AD4: 20686.016 | AE4: 21188.167 | AF4: 21745.33 | AG4: 22380.231 | AH4: 23086.41 | AI4: 23833.079 | AJ4: 24579.044 | AK4: 25291.007
A5: ia_sagr_0 | B5: 11272.937 | C5: 11247.539 | D5: 11246.95 | E5: 11330.344 | F5: 11480.108 | G5: 11668.312 | H5: 11851.566 | I5: 12009.489 | J5: 12148.891 | K5: 12293.699 | L5: 12471.017 | M5: 12701.237 | N5: 12989.579 | O5: 13323.863 | P5: 13690.925 | Q5: 14075.1 | R5: 14477.993 | S5: 14901.399 | T5: 15341.02 | U5: 15786.044 | V5: 16224.558 | W5: 16649.993 | X5: 17066.671 | Y5: 17488.184 | Z5: 17930.567 | AA5: 18406.946 | AB5: 18922.467 | AC5: 19474.087 | AD5: 20051.825 | AE5: 20644.973 | AF5: 21248.948 | AG5: 21868.719 | AH5: 22515.626 | AI5: 23200.41 | AJ5: 23927.499 | AK5: 24692.9
A6: ia_sfor_2 | B6: 900.80042 | C6: 888.9543 | D6: 873.2975 | E6: 858.60343 | F6: 847.35243 | G6: 839.35423 | H6: 833.58829 | I6: 821.40016 | J6: 806.62455 | K6: 793.9184 | L6: 783.06268 | M6: 775.12006 | N6: 770.02971 | O6: 767.32414 | P6: 766.86042 | Q6: 768.21095 | R6: 770.01725 | S6: 771.76282 | T6: 773.42442 | U6: 775.39836 | V6: 778.39917 | W6: 783.17736 | X6: 790.2816 | Y6: 799.80185 | Z6: 811.24834 | AA6: 823.79255 | AB6: 836.59368 | AC6: 849.34949 | AD6: 862.39595 | AE6: 876.43522 | AF6: 892.22526 | AG6: 910.30887 | AH6: 930.77267 | AI6: 953.16793 | AJ6: 976.69956 | AK6: 1000.5935
A7: ia_sfor_0 | B7: 900.80042 | C7: 888.9543 | D7: 873.2975 | E7: 858.60343 | F7: 847.35243 | G7: 839.35423 | H7: 832.94071 | I7: 827.31229 | J7: 822.38015 | K7: 818.57118 | L7: 816.45873 | M7: 816.51683 | N7: 818.76337 | O7: 822.60347 | P7: 827.68618 | Q7: 833.68438 | R7: 840.86702 | S7: 849.36074 | T7: 859.09732 | U7: 869.76602 | V7: 880.99387 | W7: 892.534 | X7: 904.44668 | Y7: 917.03841 | Z7: 930.67851 | AA7: 945.70841 | AB7: 962.31759 | AC7: 980.53062 | AD7: 1000.1633 | AE7: 1020.8845 | AF7: 1042.4196 | AG7: 1064.7291 | AH7: 1087.9905 | AI7: 1112.4433 | AJ7: 1138.2363 | AK7: 1165.3406
A8: ia_sfoo_2 | B8: 6401.327 | C8: 6416.1896 | D8: 6457.0223 | E8: 6548.2361 | F8: 6673.483 | G8: 6815.4039 | H8: 6956.2102 | I8: 7056.909 | J8: 7126.7186 | K8: 7210.8123 | L8: 7326.9816 | M8: 7489.3535 | N8: 7708.0562 | O8: 7975.3744 | P8: 8275.5164 | Q8: 8587.1129 | R8: 8893.5042 | S8: 9177.0525 | T8: 9435.7673 | U8: 9681.5055 | V8: 9933.5281 | W8: 10209.207 | X8: 10517.75 | Y8: 10857.004 | Z8: 11212.616 | AA8: 11564.113 | AB8: 11889.824 | AC8: 12183.887 | AD8: 12460.443 | AE8: 12745.851 | AF8: 13064.982 | AG8: 13429.286 | AH8: 13832.38 | AI8: 14254.761 | AJ8: 14672.811 | AK8: 15069.766
A9: ia_sfoo_0 | B9: 6401.327 | C9: 6416.1896 | D9: 6457.0223 | E9: 6548.2361 | F9: 6673.483 | G9: 6815.4039 | H9: 6948.0479 | I9: 7062.301 | J9: 7164.5386 | K9: 7269.9072 | L9: 7394.1193 | M9: 7548.1556 | N9: 7734.1994 | O9: 7944.998 | P9: 8172.1608 | Q9: 8406.1469 | R9: 8648.7574 | S9: 8900.0747 | T9: 9157.1231 | U9: 9413.8171 | V9: 9663.8992 | W9: 9904.4278 | X9: 10138.58 | Y9: 10374.572 | Z9: 10621.616 | AA9: 10886.773 | AB9: 11172.279 | AC9: 11475.743 | AD9: 11791.337 | AE9: 12113.655 | AF9: 12441.121 | AG9: 12777.259 | AH9: 13128.501 | AI9: 13500.261 | AJ9: 13894.028 | AK9: 14306.628
A10: ia_sveh_2 | B10: 13632.889 | C10: 13789.891 | D10: 14002.971 | E10: 14254.123 | F10: 14533.628 | G10: 14827.384 | H10: 15117.135 | I10: 15259.793 | J10: 15340.473 | K10: 15523.569 | L10: 15754.185 | M10: 16026.08 | N10: 16323.771 | O10: 16623.205 | P10: 16930.86 | Q10: 17250.323 | R10: 17560.781 | S10: 17865.661 | T10: 18170.795 | U10: 18487.608 | V10: 18834.186 | W10: 19228.728 | X10: 19686.063 | Y10: 20211.034 | Z10: 20795.233 | AA10: 21423.068 | AB10: 22086.875 | AC10: 22771.842 | AD10: 23479.917 | AE10: 24221.441 | AF10: 25008.905 | AG10: 25850.564 | AH10: 26743.91 | AI10: 27674.271 | AJ10: 28619.367 | AK10: 29557.872
A11: ia_sveh_0 | B11: 13632.889 | C11: 13789.891 | D11: 14002.971 | E11: 14254.123 | F11: 14533.628 | G11: 14827.384 | H11: 15097.75 | I11: 15341.92 | J11: 15570.803 | K11: 15801.71 | L11: 16051.257 | M11: 16330.653 | N11: 16635.18 | O11: 16940.301 | P11: 17243.902 | Q11: 17548.444 | R11: 17876.574 | S11: 18233.882 | T11: 18620.758 | U11: 19033.75 | V11: 19469.4 | W11: 19925.75 | X11: 20407.1 | Y11: 20921.203 | Z11: 21475.358 | AA11: 22076.883 | AB11: 22730.723 | AC11: 23440.074 | AD11: 24201.507 | AE11: 25002.843 | AF11: 25830.559 | AG11: 26677.734 | AH11: 27544.734 | AI11: 28434.607 | AJ11: 29348.602 | AK11: 30283.634
A12: ia_sgla_2 | B12: 1575.3575 | C12: 1628.5461 | D12: 1701.5858 | E12: 1769.4066 | F12: 1825.3197 | G12: 1871.9472 | H12: 1911.3504 | I12: 1931.7535 | J12: 1939.5535 | K12: 1949.5246 | L12: 1967.8283 | M12: 1999.4248 | N12: 2045.7717 | O12: 2104.6871 | P12: 2172.5538 | Q12: 2244.2121 | R12: 2315.1605 | S12: 2380.1989 | T12: 2437.9819 | U12: 2491.0585 | V12: 2544.554 | W12: 2603.6641 | X12: 2671.5398 | Y12: 2747.9619 | Z12: 2828.8558 | AA12: 2907.9456 | AB12: 2978.5213 | AC12: 3038.2829 | AD12: 3090.7125 | AE12: 3143.131 | AF12: 3203.056 | AG12: 3274.8876 | AH12: 3358.2702 | AI12: 3448.8186 | AJ12: 3540.3641 | AK12: 3628.0327
... A79: ia_ser_0 | B79: 366465.73 | C79: 369550.82 | D79: 374351.6 | E79: 380933.56 | F79: 388904.35 | G79: 397414.47 | H79: 404761.98 | I79: 410551.78 | J79: 415271.43 | K79: 419936.85 | L79: 425550.94 | M79: 432816.76 | N79: 441932.04 | O79: 452561.26 | P79: 464219.05 | Q79: 476309.85 | R79: 489123.14 | S79: 502635.84 | T79: 516589.17 | U79: 530518.05 | V79: 543951.34 | W79: 556653.95 | X79: 568789.49 | Y79: 580846.91 | Z79: 593386.1 | AA79: 606836.83 | AB79: 621336.21 | AC79: 636730.9 | AD79: 652672.56 | AE79: 668867.75 | AF79: 685272.2 | AG79: 702144.93 | AH79: 719911.9 | AI79: 738944.94 | AJ79: 759395.21 | AK79: 781143.64

Sheet Labor
A1: _date_ | B1: 42005 | C1: 42370 | D1: 42736 | E1: 43101 | F1: 43466 | G1: 43831 | H1: 44197 | I1: 44562 | J1: 44927 | K1: 45292 | L1: 45658 | M1: 46023 | N1: 46388 | O1: 46753 | P1: 47119 | Q1: 47484 | R1: 47849 | S1: 48214 | T1: 48580 | U1: 48945 | V1: 49310 | W1: 49675 | X1: 50041 | Y1: 50406 | Z1: 50771 | AA1: 51136 | AB1: 51502 | AC1: 51867 | AD1: 52232 | AE1: 52597 | AF1: 52963 | AG1: 53328 | AH1: 53693 | AI1: 54058 | AJ1: 54424 | AK1: 54789
A2: f_l_2 | B2: 27376.17 | C2: 27390.529 | D2: 27453.031 | E2: 27566.661 | F2: 27704.965 | G2: 27855.365 | H2: 28008.443 | I2: 28115.156 | J2: 28172.14 | K2: 28247.908 | L2: 28349.721 | M2: 28477.761 | N2: 28632.76 | O2: 28806.471 | P2: 28994.211 | Q2: 29187.475 | R2: 29374.084 | S2: 29544.091 | T2: 29693.897 | U2: 29828.99 | V2: 29963.151 | W2: 30113.223 | X2: 30293.811 | Y2: 30511.631 | Z2: 30762.579 | AA2: 31034.042 | AB2: 31310.073 | AC2: 31579.145 | AD2: 31838.832 | AE2: 32095.139 | AF2: 32358.364 | AG2: 32637.617 | AH2: 32935.341 | AI2: 33244.551 | AJ2: 33550.975 | AK2: 33838.752
A3: f_l_0 | B3: 27376.17 | C3: 27390.529 | D3: 27453.031 | E3: 27566.661 | F3: 27704.965 | G3: 27855.365 | H3: 28002.282 | I3: 28131.142 | J3: 28238.477 | K3: 28332.131 | L3: 28426.604 | M3: 28536.094 | N3: 28665.506 | O3: 28805.335 | P3: 28949.349 | Q3: 29092.767 | R3: 29236.626 | S3: 29387.567 | T3: 29550.574 | U3: 29725.976 | V3: 29910.91 | W3: 30101.79 | X3: 30298.051 | Y3: 30502.539 | Z3: 30719.726 | AA3: 30954.4 | AB3: 31209.575 | AC3: 31485.714 | AD3: 31779.128 | AE3: 32081.519 | AF3: 32383.365 | AG3: 32678.076 | AH3: 32963.408 | AI3: 33239.916 | AJ3: 33508.436 | AK3: 33768.133
A4: f_l_sagr_2 | B4: 731.60708 | C4: 722.54194 | D4: 711.99606 | E4: 705.00283 | F4: 702.03705 | G4: 702.30402 | H4: 704.63702 | I4: 706.29669 | J4: 706.43199 | K4: 707.15282 | L4: 708.45582 | M4: 710.44595 | N4: 713.52123 | O4: 717.60266 | P4: 722.57759 | Q4: 728.06979 | R4: 733.64596 | S4: 738.74612 | T4: 743.13142 | U4: 746.94994 | V4: 750.67872 | W4: 754.91674 | X4: 760.19957 | Y4: 766.79673 | Z4: 774.60854 | AA4: 783.24606 | AB4: 792.09536 | AC4: 800.79929 | AD4: 809.2664 | AE4: 817.66508 | AF4: 826.31074 | AG4: 835.48847 | AH4: 845.26691 | AI4: 855.40269 | AJ4: 865.40873 | AK4: 874.73671
A5: f_l_sagr_0 | B5: 731.60708 | C5: 722.54194 | D5: 711.99606 | E5: 705.00283 | F5: 702.03705 | G5: 702.30402 | H5: 704.46202 | I5: 707.17962 | J5: 709.73364 | K5: 712.04133 | L5: 714.44553 | M5: 717.38828 | N5: 721.00897 | O5: 724.92242 | P5: 728.91971 | Q5: 732.85208 | R5: 736.76549 | S5: 740.92707 | T5: 745.55484 | U5: 750.69321 | V5: 756.26453 | W5: 762.15 | X5: 768.33177 | Y5: 774.9058 | Z5: 782.02051 | AA5: 789.83763 | AB5: 798.45986 | AC5: 807.9125 | AD5: 818.06517 | AE5: 828.60341 | AF5: 839.15357 | AG5: 849.44693 | AH5: 859.38124 | AI5: 868.96223 | AJ5: 878.2093 | AK5: 887.08381
A6: f_l_sfor_2 | B6: 29.056014 | C6: 28.447158 | D6: 27.610282 | E6: 26.759923 | F6: 26.024156 | G6: 25.441014 | H6: 25.007067 | I6: 24.562123 | J6: 24.126362 | K6: 23.75372 | L6: 23.399783 | M6: 23.048086 | N6: 22.684804 | O6: 22.313271 | P6: 21.96177 | Q6: 21.65741 | R6: 21.398554 | S6: 21.188739 | T6: 21.022833 | U6: 20.890221 | V6: 20.782055 | W6: 20.695726 | X6: 20.635905 | Y6: 20.609634 | Z6: 20.621585 | AA6: 20.671734 | AB6: 20.755865 | AC6: 20.867681 | AD6: 20.995856 | AE6: 21.126466 | AF6: 21.249337 | AG6: 21.363388 | AH6: 21.475082 | AI6: 21.59117 | AJ6: 21.713617 | AK6: 21.838237
A7: f_l_sfor_0 | B7: 29.056014 | C7: 28.447158 | D7: 27.610282 | E7: 26.759923 | F7: 26.024156 | G7: 25.441014 | H7: 25.011246 | I7: 24.705678 | J7: 24.485213 | K7: 24.313744 | L7: 24.166313 | M7: 24.030624 | N7: 23.899743 | O7: 23.763994 | P7: 23.62772 | Q7: 23.500665 | R7: 23.386835 | S7: 23.294919 | T7: 23.233196 | U7: 23.205809 | V7: 23.212647 | W7: 23.249527 | X7: 23.310801 | Y7: 23.390319 | Z7: 23.482633 | AA7: 23.585354 | AB7: 23.699448 | AC7: 23.828513 | AD7: 23.974493 | AE7: 24.132729 | AF7: 24.293102 | AG7: 24.444734 | AH7: 24.579877 | AI7: 24.695267 | AJ7: 24.791499 | AK7: 24.871167
A8: f_l_sfoo_2 | B8: 618.10018 | C8: 612.78438 | D8: 607.66848 | E8: 605.97524 | F8: 607.42281 | G8: 610.97403 | H8: 615.44679 | I8: 618.33489 | J8: 619.13665 | K8: 619.84814 | L8: 621.13416 | M8: 623.61212 | N8: 627.82777 | O8: 633.58766 | P8: 640.40718 | Q8: 647.54657 | R8: 654.32164 | S8: 660.06747 | T8: 664.59533 | U8: 668.21246 | V8: 671.56915 | W8: 675.36761 | X8: 680.12945 | Y8: 686.02634 | Z8: 692.82183 | AA8: 700.00505 | AB8: 706.89077 | AC8: 713.15712 | AD8: 718.91027 | AE8: 724.62062 | AF8: 730.86039 | AG8: 738.00001 | AH8: 746.01685 | AI8: 754.50216 | AJ8: 762.83178 | AK8: 770.42002
A9: f_l_sfoo_0 | B9: 618.10018 | C9: 612.78438 | D9: 607.66848 | E9: 605.97524 | F9: 607.42281 | G9: 610.97403 | H9: 615.16488 | I9: 618.88849 | J9: 621.80625 | K9: 624.23121 | L9: 626.78368 | M9: 630.03324 | N9: 634.16399 | O9: 638.83428 | P9: 643.71629 | Q9: 648.48653 | R9: 653.15374 | S9: 657.88329 | T9: 662.7722 | U9: 667.77122 | V9: 672.7542 | W9: 677.61896 | X9: 682.41579 | Y9: 687.3461 | Z9: 692.66565 | AA9: 698.60036 | AB9: 705.25688 | AC9: 712.61105 | AD9: 720.48674 | AE9: 728.6017 | AF9: 736.69334 | AG9: 744.63408 | AH9: 752.43878 | AI9: 760.17428 | AJ9: 767.86009 | AK9: 775.41539
A10: f_l_sveh_2 | B10: 185.64237 | C10: 185.75397 | D10: 186.29266 | E10: 187.20736 | F10: 188.40875 | G10: 189.76815 | H10: 191.1207 | I10: 191.15248 | J10: 190.46741 | K10: 190.68565 | L10: 191.30891 | M10: 192.09629 | N10: 192.78747 | O10: 193.14757 | P10: 193.32487 | Q10: 193.50648 | R10: 193.63491 | S10: 193.81768 | T10: 194.11846 | U10: 194.58746 | V10: 195.30182 | W10: 196.35077 | X10: 197.82898 | Y10: 199.78412 | Z10: 202.18256 | AA10: 204.93517 | AB10: 208.00508 | AC10: 211.25947 | AD10: 214.61593 | AE10: 218.01605 | AF10: 221.43036 | AG10: 224.85927 | AH10: 228.30097 | AI10: 231.71542 | AJ10: 235.01872 | AK10: 238.10605
A11: f_l_sveh_0 | B11: 185.64237 | C11: 185.75397 | D11: 186.29266 | E11: 187.20736 | F11: 188.40875 | G11: 189.76815 | H11: 190.97656 | I11: 191.96159 | J11: 192.7581 | K11: 193.45363 | L11: 194.14851 | M11: 194.92096 | N11: 195.72396 | O11: 196.33235 | P11: 196.75181 | Q11: 197.07117 | R11: 197.5125 | S11: 198.18072 | T11: 199.1245 | U11: 200.34567 | V11: 201.82773 | W11: 203.54218 | X11: 205.48622 | Y11: 207.66771 | Z11: 210.0878 | AA11: 212.75812 | AB11: 215.69384 | AC11: 218.9178 | AD11: 222.41058 | AE11: 226.06715 | AF11: 229.74074 | AG11: 233.31317 | AH11: 236.72457 | AI11: 239.95982 | AJ11: 243.02303 | AK11: 245.91477
A12: f_l_sgla_2 | B12: 97.915623 | C12: 99.672489 | D12: 102.41061 | E12: 104.83127 | F12: 106.44815 | G12: 107.3759 | H12: 107.8598 | I12: 107.63695 | J12: 106.87272 | K12: 106.06173 | L12: 105.38635 | M12: 104.98544 | N12: 104.88298 | O12: 105.03481 | P12: 105.39689 | Q12: 105.89233 | R12: 106.43565 | S12: 106.91022 | T12: 107.24509 | U12: 107.44226 | V12: 107.57817 | W12: 107.76696 | X12: 108.11187 | Y12: 108.65874 | Z12: 109.37381 | AA12: 110.16099 | AB12: 110.88786 | AC12: 111.47745 | AD12: 111.92267 | AE12: 112.288 | AF12: 112.67847 | AG12: 113.19231 | AH12: 113.87415 | AI12: 114.6938 | AJ12: 115.5632 | AK12: 116.37863
... A79: f_l_ser_0 | B79: 21283.083 | C79: 21246.435 | D79: 21227.056 | E79: 21266.041 | F79: 21351.011 | G79: 21465.843 | H79: 21592.038 | I79: 21712.888 | J79: 21821.439 | K79: 21919.784 | L79: 22015.53 | M79: 22116.879 | N79: 22226.631 | O79: 22338.647 | P79: 22449.262 | Q79: 22556.282 | R79: 22660.518 | S79: 22767.416 | T79: 22881.685 | U79: 23005.046 | V79: 23136.91 | W79: 23275.735 | X79: 23421.377 | Y79: 23575.401 | Z79: 23740.092 | AA79: 23917.805 | AB79: 24109.878 | AC79: 24316.34 | AD79: 24534.721 | AE79: 24759.462 | AF79: 24983.877 | AG79: 25202.874 | AH79: 25414.107 | AI79: 25617.167 | AJ79: 25812.084 | AK79: 25998.116

Sheet Final_nrj
A1: _date_ | B1: 42005 | C1: 42370 | D1: 42736 | E1: 43101 | F1: 43466 | G1: 43831 | H1: 44197 | I1: 44562 | J1: 44927 | K1: 45292 | L1: 45658 | M1: 46023 | N1: 46388 | O1: 46753 | P1: 47119 | Q1: 47484 | R1: 47849 | S1: 48214 | T1: 48580 | U1: 48945 | V1: 49310 | W1: 49675 | X1: 50041 | Y1: 50406 | Z1: 50771 | AA1: 51136 | AB1: 51502 | AC1: 51867 | AD1: 52232 | AE1: 52597 | AF1: 52963 | AG1: 53328 | AH1: 53693 | AI1: 54058 | AJ1: 54424 | AK1: 54789
A2: cf_toe_2 | B2: 150.52492 | C2: 150.68963 | D2: 150.57472 | E2: 150.41187 | F2: 150.47976 | G2: 150.87091 | H2: 151.61806 | I2: 151.95457 | J2: 152.00961 | K2: 151.84757 | L2: 151.01955 | M2: 149.60908 | N2: 147.80572 | O2: 145.88929 | P2: 144.2021 | Q2: 142.96392 | R2: 142.24508 | S2: 142.02177 | T2: 142.19398 | U2: 142.61329 | V2: 143.15287 | W2: 143.76012 | X2: 144.47728 | Y2: 145.40271 | Z2: 146.66277 | AA2: 148.36429 | AB2: 150.56072 | AC2: 153.24061 | AD2: 156.2404 | AE2: 159.32572 | AF2: 162.32122 | AG2: 165.21067 | AH2: 168.1237 | AI2: 171.23093 | AJ2: 174.65601 | AK2: 178.41621
A3: ch_toe_2 | B3: 73.965463 | C3: 73.736471 | D3: 73.284366 | E3: 72.834188 | F3: 72.478692 | G3: 72.195158 | H3: 71.926856 | I3: 71.472682 | J3: 70.840842 | K3: 69.987196 | L3: 68.89447 | M3: 67.636404 | N3: 66.315108 | O3: 65.016081 | P3: 63.793667 | Q3: 62.676424 | R3: 61.684651 | S3: 60.799125 | T3: 60.001079 | U3: 59.277515 | V3: 58.623457 | W3: 58.037792 | X3: 57.518219 | Y3: 57.058112 | Z3: 56.652077 | AA3: 56.296291 | AB3: 55.987363 | AC3: 55.722548 | AD3: 55.501994 | AE3: 55.329466 | AF3: 55.208722 | AG3: 55.138848 | AH3: 55.114031 | AI3: 55.127563 | AJ3: 55.172157 | AK3: 55.239251
A4: ch_hous_toe_2 | B4: 39923462 | C4: 40164469 | D4: 39964612 | E4: 39667075 | F4: 39409477 | G4: 39210282 | H4: 39054156 | I4: 38870973 | J4: 38672355 | K4: 38398171 | L4: 38013032 | M4: 37525336 | N4: 36985889 | O4: 36452126 | P4: 35963067 | Q4: 35539517 | R4: 35194616 | S4: 34908563 | T4: 34660846 | U4: 34435818 | V4: 34226140 | W4: 34030205 | X4: 33847851 | Y4: 33676854 | Z4: 33517685 | AA4: 33372310 | AB4: 33241903 | AC4: 33125545 | AD4: 33021427 | AE4: 32929180 | AF4: 32849690 | AG4: 32783069 | AH4: 32728708 | AI4: 32687304 | AJ4: 32658761 | AK4: 32639622
A5: ch_auto_toe_2 | B5: 34042000 | C5: 33572002 | D5: 33319754 | E5: 33167113 | F5: 33069216 | G5: 32984875 | H5: 32872700 | I5: 32601709 | J5: 32168487 | K5: 31589025 | L5: 30881438 | M5: 30111068 | N5: 29329219 | O5: 28563955 | P5: 27830601 | Q5: 27136907 | R5: 26490035 | S5: 25890562 | T5: 25340232 | U5: 24841697 | V5: 24397317 | W5: 24007586 | X5: 23670368 | Y5: 23381258 | Z5: 23134392 | AA5: 22923981 | AB5: 22745460 | AC5: 22597003 | AD5: 22480567 | AE5: 22400286 | AF5: 22359032 | AG5: 22355779 | AH5: 22385323 | AI5: 22440259 | AJ5: 22513396 | AK5: 22599629
A6: cf_toe_0 | B6: 150.52492 | C6: 150.68963 | D6: 150.57472 | E6: 150.41187 | F6: 150.47976 | G6: 150.87091 | H6: 151.55094 | I6: 152.40008 | J6: 153.20636 | K6: 153.76803 | L6: 153.97169 | M6: 153.81333 | N6: 153.35569 | O6: 152.66978 | P6: 151.94092 | Q6: 151.33716 | R6: 150.97702 | S6: 150.94007 | T6: 151.2847 | U6: 152.04653 | V6: 153.24054 | W6: 154.84246 | X6: 156.79517 | Y6: 159.01384 | Z6: 161.41805 | AA6: 163.96922 | AB6: 166.68505 | AC6: 169.63065 | AD6: 172.86345 | AE6: 176.36426 | AF6: 180.04347 | AG6: 183.78023 | AH6: 187.46759 | AI6: 191.04525 | AJ6: 194.50984 | AK6: 197.89801
A7: ch_toe_0 | B7: 73.965463 | C7: 73.736471 | D7: 73.284366 | E7: 72.834188 | F7: 72.478692 | G7: 72.195158 | H7: 71.830458 | I7: 71.360309 | J7: 70.781966 | K7: 70.098854 | L7: 69.318655 | M7: 68.454184 | N7: 67.524256 | O7: 66.552826 | P7: 65.56652 | Q7: 64.590521 | R7: 63.705463 | S7: 62.914901 | T7: 62.20875 | U7: 61.572997 | V7: 60.99627 | W7: 60.470983 | X7: 59.992633 | Y7: 59.559133 | Z7: 59.169719 | AA7: 58.82347 | AB7: 58.519242 | AC7: 58.255132 | AD7: 58.028542 | AE7: 57.835535 | AF7: 57.673403 | AG7: 57.540788 | AH7: 57.437033 | AI7: 57.361224 | AJ7: 57.311274 | AK7: 57.283154
A8: ch_hous_toe_0 | B8: 39923462 | C8: 40164469 | D8: 39964612 | E8: 39667075 | F8: 39409477 | G8: 39210282 | H8: 39003103 | I8: 38782507 | J8: 38553237 | K8: 38319228 | L8: 38084594 | M8: 37852376 | N8: 37623935 | O8: 37399506 | P8: 37178631 | Q8: 36961135 | R8: 36787762 | S8: 36652827 | T8: 36546103 | U8: 36456170 | V8: 36374508 | W8: 36295562 | X8: 36215731 | Y8: 36133144 | Z8: 36047532 | AA8: 35959345 | AB8: 35869917 | AC8: 35780557 | AD8: 35691995 | AE8: 35602980 | AF8: 35512651 | AG8: 35420895 | AH8: 35328306 | AI8: 35235918 | AJ8: 35144627 | AK8: 35054235
A9: ch_auto_toe_0 | B9: 34042000 | C9: 33572002 | D9: 33319754 | E9: 33167113 | F9: 33069216 | G9: 32984875 | H9: 32827355 | I9: 32577802 | J9: 32228729 | K9: 31779626 | L9: 31234060 | M9: 30601808 | N9: 29900321 | O9: 29153320 | P9: 28387889 | Q9: 27629386 | R9: 26917700 | S9: 26262074 | T9: 25662647 | U9: 25116827 | V9: 24621761 | W9: 24175421 | X9: 23776901 | Y9: 23425989 | Z9: 23122187 | AA9: 22864125 | AB9: 22649325 | AC9: 22474575 | AD9: 22336546 | AE9: 22232555 | AF9: 22160752 | AG9: 22119893 | AH9: 22108727 | AI9: 22125306 | AJ9: 22166648 | AK9: 22228918
A10: cf_toe_ccoa_2 | B10: 7.5111545 | C10: 7.8321346 | D10: 8.1410379 | E10: 8.3752296 | F10: 8.5835134 | G10: 8.7818115 | H10: 8.9771864 | I10: 8.9868711 | J10: 8.9399637 | K10: 8.9134319 | L10: 8.871963 | M10: 8.8428128 | N10: 8.8229255 | O10: 8.8107405 | P10: 8.8173106 | Q10: 8.8459321 | R10: 8.9073607 | S10: 8.9805884 | T10: 9.0608157 | U10: 9.1459874 | V10: 9.2381599 | W10: 9.342483 | X10: 9.4661224 | Y10: 9.6135342 | Z10: 9.7848232 | AA10: 9.9770272 | AB10: 10.179162 | AC10: 10.39381 | AD10: 10.616619 | AE10: 10.842743 | AF10: 11.071027 | AG10: 11.305443 | AH10: 11.551293 | AI10: 11.809962 | AJ10: 12.07798 | AK10: 12.34812
A11: cf_toe_ccoa_0 | B11: 7.5111545 | C11: 7.8321346 | D11: 8.1410379 | E11: 8.3752296 | F11: 8.5835134 | G11: 8.7818115 | H11: 8.9667841 | I11: 9.1384768 | J11: 9.2922233 | K11: 9.4295329 | L11: 9.5555462 | M11: 9.6767905 | N11: 9.7936511 | O11: 9.897432 | P11: 9.9974424 | Q11: 10.101622 | R11: 10.229966 | S11: 10.387259 | T11: 10.574886 | U11: 10.790951 | V11: 11.032842 | W11: 11.29728 | X11: 11.582892 | Y11: 11.88869 | Z11: 12.213771 | AA11: 12.55943 | AB11: 12.928275 | AC11: 13.324132 | AD11: 13.747387 | AE11: 14.191679 | AF11: 14.648169 | AG11: 15.110427 | AH11: 15.575667 | AI11: 16.043605 | AJ11: 16.515034 | AK11: 16.990351
A12: cf_toe_ccoi_2 | B12: 0 | C12: 0 | D12: 0 | E12: 0 | F12: 0 | G12: 0 | H12: 0 | I12: 0 | J12: 0 | K12: 0 | L12: 0 | M12: 0 | N12: 0 | O12: 0 | P12: 0 | Q12: 0 | R12: 0 | S12: 0 | T12: 0 | U12: 0 | V12: 0 | W12: 0 | X12: 0 | Y12: 0 | Z12: 0 | AA12: 0 | AB12: 0 | AC12: 0 | AD12: 0 | AE12: 0 | AF12: 0 | AG12: 0 | AH12: 0 | AI12: 0 | AJ12: 0 | AK12: 0
... A737: ci_toe_cfuel_ser_0 | B737: 2.8654882 | C737: 2.8967075 | D737: 2.9278608 | E737: 2.9597623 | F737: 2.9926616 | G737: 3.0265472 | H737: 3.0613249 | I737: 3.0968928 | J737: 3.1331649 | K737: 3.170076 | L737: 3.2075792 | M737: 3.2456425 | N737: 3.2842451 | O737: 3.3233755 | P737: 3.363028 | Q737: 3.4032016 | R737: 3.443898 | S737: 3.4851202 | T737: 3.5268716 | U737: 3.5691552 | V737: 3.6119734 | W737: 3.6553275 | X737: 3.6992182 | Y737: 3.7436452 | Z737: 3.7886078 | AA737: 3.8341054 | AB737: 3.8801368 | AC737: 3.9267016 | AD737: 3.9737996 | AE737: 4.021431 | AF737: 4.0695968 | AG737: 4.1182989 | AH737: 4.1675396 | AI737: 4.2173221 | AJ737: 4.2676504 | AK737: 4.3185291

Sheet Primary_nrj
A1: _date_ | B1: 42005 | C1: 42370 | D1: 42736 | E1: 43101 | F1: 43466 | G1: 43831 | H1: 44197 | I1: 44562 | J1: 44927 | K1: 45292 | L1: 45658 | M1: 46023 | N1: 46388 | O1: 46753 | P1: 47119 | Q1: 47484 | R1: 47849 | S1: 48214 | T1: 48580 | U1: 48945 | V1: 49310 | W1: 49675 | X1: 50041 | Y1: 50406 | Z1: 50771 | AA1: 51136 | AB1: 51502 | AC1: 51867 | AD1: 52232 | AE1: 52597 | AF1: 52963 | AG1: 53328 | AH1: 53693 | AI1: 54058 | AJ1: 54424 | AK1: 54789
A2: yg_toe_2 | B2: 141.53346 | C2: 144.15926 | D2: 146.27004 | E2: 148.27736 | F2: 150.32749 | G2: 152.51638 | H2: 154.89817 | I2: 155.87036 | J2: 156.88217 | K2: 158.08878 | L2: 158.82473 | M2: 159.0213 | N2: 158.80004 | O2: 158.35754 | P2: 158.02031 | Q2: 157.97919 | R2: 158.40952 | S2: 159.20605 | T2: 160.27817 | U2: 161.50479 | V2: 162.79347 | W2: 164.1202 | X2: 165.54156 | Y2: 167.15099 | Z2: 169.05583 | AA2: 171.34359 | AB2: 174.1608 | AC2: 177.43277 | AD2: 181.02662 | AE2: 184.75199 | AF2: 188.48276 | AG2: 192.25475 | AH2: 196.25428 | AI2: 200.7333 | AJ2: 205.98763 | AK2: 212.44538
A3: yg_toe_0 | B3: 141.53346 | C3: 144.15926 | D3: 146.27004 | E3: 148.27736 | F3: 150.32749 | G3: 152.51638 | H3: 154.93717 | I3: 157.49961 | J3: 160.05974 | K3: 162.47741 | L3: 164.68346 | M3: 166.68841 | N3: 168.49396 | O3: 170.03837 | P3: 171.52324 | Q3: 173.1106 | R3: 174.20192 | S3: 175.46667 | T3: 176.96645 | U3: 178.7376 | V3: 180.799 | W3: 183.13638 | X3: 185.71261 | Y3: 188.46839 | Z3: 191.34761 | AA3: 194.33025 | AB3: 197.43986 | AC3: 200.73639 | AD3: 204.26482 | AE3: 207.9998 | AF3: 211.86036 | AG3: 215.74798 | AH3: 219.58168 | AI3: 223.31993 | AJ3: 226.96545 | AK3: 230.54917
A4: yg_toe_ccoa_2 | B4: 2.2577821 | C4: 1.6276759 | D4: 1.1065339 | E4: 0.68852988 | F4: 0.3550056 | G4: 0.086333078 | H4: -0.13180376 | I4: -0.32963912 | J4: -0.4922768 | K4: -0.63696175 | L4: -0.76136125 | M4: -0.87199307 | N4: -0.97123423 | O4: -1.0603961 | P4: -1.1427086 | Q4: -1.2197615 | R4: -1.2949643 | S4: -1.3657518 | T4: -1.4322928 | U4: -1.4954199 | V4: -1.5567416 | W4: -1.6182115 | X4: -1.6818415 | Y4: -1.74872 | Z4: -1.8187642 | AA4: -1.8912072 | AB4: -1.9629296 | AC4: -2.0353501 | AD4: -2.1081769 | AE4: -2.181079 | AF4: -2.2543814 | AG4: -2.3291983 | AH4: -2.4065997 | AI4: -2.4866164 | AJ4: -2.5682153 | AK4: -2.6496715
A5: yg_toe_ccoa_0 | B5: 2.2577821 | C5: 1.6276759 | D5: 1.1065339 | E5: 0.68852988 | F5: 0.3550056 | G5: 0.086333078 | H5: -0.12901302 | I5: -0.30165106 | J5: -0.4406074 | K5: -0.55394331 | L5: -0.64870945 | M5: -0.73045583 | N5: -0.80221213 | O5: -0.86445123 | P5: -0.91946359 | Q5: -0.96885509 | R5: -1.024064 | S5: -1.0809845 | T5: -1.139552 | U5: -1.1994586 | V5: -1.2603416 | W5: -1.3218866 | X5: -1.3844449 | Y5: -1.4486304 | Z5: -1.515028 | AA5: -1.5844544 | AB5: -1.6576194 | AC5: -1.735143 | AD5: -1.8167755 | AE5: -1.9010769 | AF5: -1.9865055 | AG5: -2.0723901 | AH5: -2.1589133 | AI5: -2.2465644 | AJ5: -2.3356787 | AK5: -2.4261676
A6: yg_toe_ccoi_2 | B6: 1.2014456 | C6: 0.96352326 | D6: 0.77318228 | E6: 0.62091101 | F6: 0.49911102 | G6: 0.40169205 | H6: 0.32377008 | I6: 0.26101069 | J6: 0.21063696 | K6: 0.17023492 | L6: 0.13777942 | M6: 0.11168342 | N6: 0.090685595 | O6: 0.073781326 | P6: 0.060174939 | Q6: 0.049225079 | R6: 0.040402719 | S6: 0.033300813 | T6: 0.027577988 | U6: 0.022961217 | V6: 0.019231098 | W6: 0.016212193 | X6: 0.013765833 | Y6: 0.011782298 | Z6: 0.01017435 | AA6: 0.0088725076 | AB6: 0.007826191 | AC6: 0.0069860072 | AD6: 0.0063121333 | AE6: 0.0057692651 | AF6: 0.0053280483 | AG6: 0.0049670522 | AH6: 0.0046718714 | AI6: 0.0044321303 | AJ6: 0.0042390902 | AK6: 0.004084235
A7: yg_toe_ccoi_0 | B7: 1.2014456 | C7: 0.96352326 | D7: 0.77318228 | E7: 0.62091101 | F7: 0.49911102 | G7: 0.40169205 | H7: 0.32375811 | I7: 0.26140656 | J7: 0.21151069 | K7: 0.17156662 | L7: 0.13957213 | M7: 0.11393004 | N7: 0.093364992 | O7: 0.076855773 | P7: 0.063600438 | Q7: 0.052962072 | R7: 0.044405823 | S7: 0.037538665 | T7: 0.032039151 | U7: 0.027641584 | V7: 0.024132028 | W7: 0.021338313 | X7: 0.019121809 | Y7: 0.017369727 | Z7: 0.015990223 | AA7: 0.014910025 | AB7: 0.014071994 | AC7: 0.013432686 | AD7: 0.012957722 | AE7: 0.012617097 | AF7: 0.012383944 | AG7: 0.012234814 | AH7: 0.012150165 | AI7: 0.012114769 | AJ7: 0.012117747 | AK7: 0.012151714
A8: yg_toe_cfut_2 | B8: 54.269135 | C8: 55.970182 | D8: 57.394589 | E8: 58.648616 | F8: 59.836644 | G8: 60.985552 | H8: 62.093187 | I8: 61.601687 | J8: 60.939343 | K8: 60.063984 | L8: 58.906392 | M8: 57.523958 | N8: 55.974987 | O8: 54.330418 | P8: 52.667657 | Q8: 51.040283 | R8: 49.854829 | S8: 48.755911 | T8: 47.734288 | U8: 46.774479 | V8: 45.860943 | W8: 44.985868 | X8: 44.153516 | Y8: 43.376167 | Z8: 42.670309 | AA8: 42.051127 | AB8: 41.53131 | AC8: 41.111927 | AD8: 40.774636 | AE8: 40.488811 | AF8: 40.229197 | AG8: 39.99248 | AH8: 39.798473 | AI8: 39.676759 | AJ8: 39.655241 | AK8: 39.752473
A9: yg_toe_cfut_0 | B9: 54.269135 | C9: 55.970182 | D9: 57.394589 | E9: 58.648616 | F9: 59.836644 | G9: 60.985552 | H9: 62.063491 | I9: 63.049329 | J9: 63.910289 | K9: 64.621589 | L9: 65.173869 | M9: 65.577892 | N9: 65.823897 | O9: 65.867274 | P9: 65.815773 | Q9: 65.761823 | R9: 65.194676 | S9: 64.699375 | T9: 64.295925 | U9: 63.991844 | V9: 63.78858 | W9: 63.681413 | X9: 63.661211 | Y9: 63.714992 | Z9: 63.829625 | AA9: 63.996864 | AB9: 64.215417 | AC9: 64.490528 | AD9: 64.827297 | AE9: 65.222167 | AF9: 65.662987 | AG9: 66.133442 | AH9: 66.618288 | AI9: 67.107414 | AJ9: 67.597532 | AK9: 68.090703
A10: yg_toe_cfuh_2 | B10: 5.0056371 | C10: 4.8841466 | D10: 4.7694024 | E10: 4.6651439 | F10: 4.5836766 | G10: 4.5236762 | H10: 4.4759609 | I10: 4.2623245 | J10: 4.0528052 | K10: 3.8449092 | L10: 3.6288053 | M10: 3.4098983 | N10: 3.1931944 | O10: 2.9850247 | P10: 2.7910802 | Q10: 2.614041 | R10: 2.457428 | S10: 2.3158727 | T10: 2.1846931 | U10: 2.0596437 | V10: 1.9377825 | W10: 1.8175855 | X10: 1.6987737 | Y10: 1.5817817 | Z10: 1.4672472 | AA10: 1.3555285 | AB10: 1.246448 | AC10: 1.1391336 | AD10: 1.0319971 | AE10: 0.9232981 | AF10: 0.811834 | AG10: 0.69722158 | AH10: 0.57958329 | AI10: 0.45897321 | AJ10: 0.33501088 | AK10: 0.20680269
A11: yg_toe_cfuh_0 | B11: 5.0056371 | C11: 4.8841466 | D11: 4.7694024 | E11: 4.6651439 | F11: 4.5836766 | G11: 4.5236762 | H11: 4.4593722 | I11: 4.4001028 | J11: 4.3466233 | K11: 4.2966612 | L11: 4.2475636 | M11: 4.1981001 | N11: 4.1482904 | O11: 4.0985461 | P11: 4.0512345 | Q11: 4.0087001 | R11: 3.9843696 | S11: 3.9732037 | T11: 3.9723517 | U11: 3.9804515 | V11: 3.9968657 | W11: 4.0208111 | X11: 4.0509554 | Y11: 4.085437 | Z11: 4.1225983 | AA11: 4.1613005 | AB11: 4.2015603 | AC11: 4.2444704 | AD11: 4.2912955 | AE11: 4.3419336 | AF11: 4.3952172 | AG11: 4.4493561 | AH11: 4.5025841 | AI11: 4.5537344 | AJ11: 4.6024599 | AK11: 4.6490359
A12: yg_toe_cgas_2 | B12: 2.4234393 | C12: 4.2711219 | D12: 5.6469312 | E12: 6.7495935 | F12: 7.6751239 | G12: 8.458201 | H12: 9.1375802 | I12: 9.6285632 | J12: 10.072182 | K12: 10.446289 | L12: 10.733526 | M12: 10.965359 | N12: 11.142413 | O12: 11.283115 | P12: 11.410303 | Q12: 11.539155 | R12: 11.629027 | S12: 11.730454 | T12: 11.841154 | U12: 11.954063 | V12: 12.063184 | W12: 12.168267 | X12: 12.276473 | Y12: 12.398227 | Z12: 12.548533 | AA12: 12.742911 | AB12: 12.995328 | AC12: 13.31521 | AD12: 13.702731 | AE12: 14.157306 | AF12: 14.690543 | AG12: 15.339599 | AH12: 16.177121 | AI12: 17.324785 | AJ12: 18.995113 | AK12: 21.613885
... A73: yg_toe_cote_spub_0 | B73: 1.617373 | C73: 1.5616871 | D73: 1.525768 | E73: 1.5025002 | F73: 1.4910487 | G73: 1.4892705 | H73: 1.4970119 | I73: 1.5118398 | J73: 1.5308483 | K73: 1.5515956 | L73: 1.5724423 | M73: 1.5927022 | N73: 1.6114553 | O73: 1.6269488 | P73: 1.6415705 | Q73: 1.6573933 | R73: 1.6725596 | S73: 1.6904727 | T73: 1.7123799 | U73: 1.7388445 | V73: 1.7702781 | W73: 1.8067248 | X73: 1.848146 | Y73: 1.8940743 | Z73: 1.9437824 | AA73: 1.9969725 | AB73: 2.0538522 | AC73: 2.1152672 | AD73: 2.1817355 | AE73: 2.2526411 | AF73: 2.3266796 | AG73: 2.4025162 | AH73: 2.4790733 | AI73: 2.5556204 | AJ73: 2.631835 | AK73: 2.7076868

Sheet Energy_Mix
A1: _date_ | B1: 42005 | C1: 42370 | D1: 42736 | E1: 43101 | F1: 43466 | G1: 43831 | H1: 44197 | I1: 44562 | J1: 44927 | K1: 45292 | L1: 45658 | M1: 46023 | N1: 46388 | O1: 46753 | P1: 47119 | Q1: 47484 | R1: 47849 | S1: 48214 | T1: 48580 | U1: 48945 | V1: 49310 | W1: 49675 | X1: 50041 | Y1: 50406 | Z1: 50771 | AA1: 51136 | AB1: 51502 | AC1: 51867 | AD1: 52232 | AE1: 52597 | AF1: 52963 | AG1: 53328 | AH1: 53693 | AI1: 54058 | AJ1: 54424 | AK1: 54789
A2: phiy_ccoa_smin_2 | B2: 1 | C2: 1 | D2: 1 | E2: 1 | F2: 1 | G2: 1 | H2: 1 | I2: 1 | J2: 1 | K2: 1 | L2: 1 | M2: 1 | N2: 1 | O2: 1 | P2: 1 | Q2: 1 | R2: 1 | S2: 1 | T2: 1 | U2: 1 | V2: 1 | W2: 1 | X2: 1 | Y2: 1 | Z2: 1 | AA2: 1 | AB2: 1 | AC2: 1 | AD2: 1 | AE2: 1 | AF2: 1 | AG2: 1 | AH2: 1 | AI2: 1 | AJ2: 1 | AK2: 1
A3: phiy_ccoa_soil_2 | B3: 0 | C3: 0 | D3: 0 | E3: 0 | F3: 0 | G3: 0 | H3: 0 | I3: 0 | J3: 0 | K3: 0 | L3: 0 | M3: 0 | N3: 0 | O3: 0 | P3: 0 | Q3: 0 | R3: 0 | S3: 0 | T3: 0 | U3: 0 | V3: 0 | W3: 0 | X3: 0 | Y3: 0 | Z3: 0 | AA3: 0 | AB3: 0 | AC3: 0 | AD3: 0 | AE3: 0 | AF3: 0 | AG3: 0 | AH3: 0 | AI3: 0 | AJ3: 0 | AK3: 0
A4: phiy_ccoi_smin_2 | B4: 0.70786223 | C4: 0.70786223 | D4: 0.70786223 | E4: 0.70786223 | F4: 0.70786223 | G4: 0.70786223 | H4: 0.70786223 | I4: 0.70786223 | J4: 0.70786223 | K4: 0.70786223 | L4: 0.70786223 | M4: 0.70786223 | N4: 0.70786223 | O4: 0.70786223 | P4: 0.70786223 | Q4: 0.70786223 | R4: 0.70786223 | S4: 0.70786223 | T4: 0.70786223 | U4: 0.70786223 | V4: 0.70786223 | W4: 0.70786223 | X4: 0.70786223 | Y4: 0.70786223 | Z4: 0.70786223 | AA4: 0.70786223 | AB4: 0.70786223 | AC4: 0.70786223 | AD4: 0.70786223 | AE4: 0.70786223 | AF4: 0.70786223 | AG4: 0.70786223 | AH4: 0.70786223 | AI4: 0.70786223 | AJ4: 0.70786223 | AK4: 0.70786223
A5: phiy_ccoi_soil_2 | B5: 0.29213777 | C5: 0.29213777 | D5: 0.29213777 | E5: 0.29213777 | F5: 0.29213777 | G5: 0.29213777 | H5: 0.29213777 | I5: 0.29213777 | J5: 0.29213777 | K5: 0.29213777 | L5: 0.29213777 | M5: 0.29213777 | N5: 0.29213777 | O5: 0.29213777 | P5: 0.29213777 | Q5: 0.29213777 | R5: 0.29213777 | S5: 0.29213777 | T5: 0.29213777 | U5: 0.29213777 | V5: 0.29213777 | W5: 0.29213777 | X5: 0.29213777 | Y5: 0.29213777 | Z5: 0.29213777 | AA5: 0.29213777 | AB5: 0.29213777 | AC5: 0.29213777 | AD5: 0.29213777 | AE5: 0.29213777 | AF5: 0.29213777 | AG5: 0.29213777 | AH5: 0.29213777 | AI5: 0.29213777 | AJ5: 0.29213777 | AK5: 0.29213777
A6: phiy_cfut_soil_2 | B6: 0.90159755 | C6: 0.90159755 | D6: 0.90159755 | E6: 0.90159755 | F6: 0.90159755 | G6: 0.90159755 | H6: 0.90159755 | I6: 0.8746518 | J6: 0.84755723 | K6: 0.82031259 | L6: 0.79291664 | M6: 0.76536812 | N6: 0.73766573 | O6: 0.7098082 | P6: 0.68179421 | Q6: 0.65362245 | R6: 0.62529158 | S6: 0.59680023 | T6: 0.56814706 | U6: 0.53933067 | V6: 0.51034967 | W6: 0.48120264 | X6: 0.45188815 | Y6: 0.42240475 | Z6: 0.39275098 | AA6: 0.36292536 | AB6: 0.33292639 | AC6: 0.30275256 | AD6: 0.27240233 | AE6: 0.24187414 | AF6: 0.21116644 | AG6: 0.18027763 | AH6: 0.1492061 | AI6: 0.11795024 | AJ6: 0.086508382 | AK6: 0.054878878
A7: phiy_cfut_sbfu_2 | B7: 0.098402448 | C7: 0.098402448 | D7: 0.098402448 | E7: 0.098402448 | F7: 0.098402448 | G7: 0.098402448 | H7: 0.098402448 | I7: 0.1253482 | J7: 0.15244277 | K7: 0.17968741 | L7: 0.20708336 | M7: 0.23463189 | N7: 0.26233427 | O7: 0.2901918 | P7: 0.31820579 | Q7: 0.34637755 | R7: 0.37470842 | S7: 0.40319977 | T7: 0.43185294 | U7: 0.46066933 | V7: 0.48965033 | W7: 0.51879736 | X7: 0.54811185 | Y7: 0.57759525 | Z7: 0.60724902 | AA7: 0.63707464 | AB7: 0.66707361 | AC7: 0.69724744 | AD7: 0.72759767 | AE7: 0.75812586 | AF7: 0.78883356 | AG7: 0.81972237 | AH7: 0.8507939 | AI7: 0.88204976 | AJ7: 0.91349162 | AK7: 0.94512112
A8: phiy_cfuh_soil_2 | B8: 1 | C8: 1 | D8: 1 | E8: 1 | F8: 1 | G8: 1 | H8: 1 | I8: 1 | J8: 1 | K8: 1 | L8: 1 | M8: 1 | N8: 1 | O8: 1 | P8: 1 | Q8: 1 | R8: 1 | S8: 1 | T8: 1 | U8: 1 | V8: 1 | W8: 1 | X8: 1 | Y8: 1 | Z8: 1 | AA8: 1 | AB8: 1 | AC8: 1 | AD8: 1 | AE8: 1 | AF8: 1 | AG8: 1 | AH8: 1 | AI8: 1 | AJ8: 1 | AK8: 1
A9: phiy_cgas_smet_2 | B9: 0 | C9: 0 | D9: 0 | E9: 0 | F9: 0 | G9: 0 | H9: 0 | I9: 0 | J9: 0 | K9: 0 | L9: 0 | M9: 0 | N9: 0 | O9: 0 | P9: 0 | Q9: 0 | R9: 0 | S9: 0 | T9: 0 | U9: 0 | V9: 0 | W9: 0 | X9: 0 | Y9: 0 | Z9: 0 | AA9: 0 | AB9: 0 | AC9: 0 | AD9: 0 | AE9: 0 | AF9: 0 | AG9: 0 | AH9: 0 | AI9: 0 | AJ9: 0 | AK9: 0
A10: phiy_cgas_soil_2 | B10: 0 | C10: 0 | D10: 0 | E10: 0 | F10: 0 | G10: 0 | H10: 0 | I10: 0 | J10: 0 | K10: 0 | L10: 0 | M10: 0 | N10: 0 | O10: 0 | P10: 0 | Q10: 0 | R10: 0 | S10: 0 | T10: 0 | U10: 0 | V10: 0 | W10: 0 | X10: 0 | Y10: 0 | Z10: 0 | AA10: 0 | AB10: 0 | AC10: 0 | AD10: 0 | AE10: 0 | AF10: 0 | AG10: 0 | AH10: 0 | AI10: 0 | AJ10: 0 | AK10: 0
A11: phiy_cgas_sgas_2 | B11: 0.97162429 | C11: 0.97162429 | D11: 0.97162429 | E11: 0.97162429 | F11: 0.97162429 | G11: 0.97162429 | H11: 0.97162429 | I11: 0.97014521 | J11: 0.96856923 | K11: 0.96688652 | L11: 0.96508584 | M11: 0.96315434 | N11: 0.96107724 | O11: 0.95883741 | P11: 0.95641496 | Q11: 0.9537866 | R11: 0.95092492 | S11: 0.9477974 | T11: 0.94436519 | U11: 0.9405815 | V11: 0.93638942 | W11: 0.93171905 | X11: 0.92648359 | Y11: 0.92057387 | Z11: 0.91385068 | AA11: 0.90613365 | AB11: 0.8971848 | AC11: 0.88668363 | AD11: 0.87418787 | AE11: 0.85906959 | AF11: 0.84040642 | AG11: 0.81678598 | AH11: 0.78593066 | AI11: 0.74391532 | AJ11: 0.68334857 | AK11: 0.58846261
A12: phiy_cgas_sbga_2 | B12: 0.016515327 | C12: 0.016515327 | D12: 0.016515327 | E12: 0.016515327 | F12: 0.016515327 | G12: 0.016515327 | H12: 0.016515327 | I12: 0.017999459 | J12: 0.019580817 | K12: 0.021269278 | L12: 0.023076105 | M12: 0.025014196 | N12: 0.027098394 | O12: 0.02934587 | P12: 0.031776592 | Q12: 0.034413923 | R12: 0.037285375 | S12: 0.040423572 | T12: 0.043867493 | U12: 0.047664101 | V12: 0.051870497 | W12: 0.056556812 | X12: 0.061810147 | Y12: 0.06774004 | Z12: 0.074486182 | AA12: 0.082229565 | AB12: 0.091208961 | AC12: 0.10174598 | AD12: 0.11428441 | AE12: 0.1294543 | AF12: 0.14818119 | AG12: 0.17188227 | AH12: 0.20284293 | AI12: 0.24500171 | AJ12: 0.30577524 | AK12: 0.40098514
... A51: phiy_cote_spub_0 | B51: 2.561371e-06 | C51: 2.561371e-06 | D51: 2.561371e-06 | E51: 2.561371e-06 | F51: 2.561371e-06 | G51: 2.561371e-06 | H51: 2.561371e-06 | I51: 2.561371e-06 | J51: 2.561371e-06 | K51: 2.561371e-06 | L51: 2.561371e-06 | M51: 2.561371e-06 | N51: 2.561371e-06 | O51: 2.561371e-06 | P51: 2.561371e-06 | Q51: 2.561371e-06 | R51: 2.561371e-06 | S51: 2.561371e-06 | T51: 2.561371e-06 | U51: 2.561371e-06 | V51: 2.561371e-06 | W51: 2.561371e-06 | X51: 2.561371e-06 | Y51: 2.561371e-06 | Z51: 2.561371e-06 | AA51: 2.561371e-06 | AB51: 2.561371e-06 | AC51: 2.561371e-06 | AD51: 2.561371e-06 | AE51: 2.561371e-06 | AF51: 2.561371e-06 | AG51: 2.561371e-06 | AH51: 2.561371e-06 | AI51: 2.561371e-06 | AJ51: 2.561371e-06 | AK51: 2.561371e-06

Sheet Transports
A1: _date_ | B1: 42005 | C1: 42370 | D1: 42736 | E1: 43101 | F1: 43466 | G1: 43831 | H1: 44197 | I1: 44562 | J1: 44927 | K1: 45292 | L1: 45658 | M1: 46023 | N1: 46388 | O1: 46753 | P1: 47119 | Q1: 47484 | R1: 47849 | S1: 48214 | T1: 48580 | U1: 48945 | V1: 49310 | W1: 49675 | X1: 50041 | Y1: 50406 | Z1: 50771 | AA1: 51136 | AB1: 51502 | AC1: 51867 | AD1: 52232 | AE1: 52597 | AF1: 52963 | AG1: 53328 | AH1: 53693 | AI1: 54058 | AJ1: 54424 | AK1: 54789
A2: km_traveler_cair_2 | B2: 291099.78 | C2: 296732.25 | D2: 303399.75 | E2: 310101.24 | F2: 317201.73 | G2: 324502.44 | H2: 331466.81 | I2: 330987.02 | J2: 329983 | K2: 331087.49 | L2: 334613.57 | M2: 342029.93 | N2: 352830.56 | O2: 364949.34 | P2: 377115.09 | Q2: 388674.46 | R2: 398916.65 | S2: 407637.08 | T2: 415988.29 | U2: 424941.11 | V2: 435200 | W2: 446925.63 | X2: 459970.77 | Y2: 474108.44 | Z2: 488883.5 | AA2: 503983.55 | AB2: 518856.13 | AC2: 533742.9 | AD2: 550149.3 | AE2: 569281.4 | AF2: 591601.53 | AG2: 616490.48 | AH2: 642834.38 | AI2: 669878.95 | AJ2: 697147.93 | AK2: 724722.63
A3: km_trav_auto_ld_2+km_trav_auto_sd_2 | B3: 724102.94 | C3: 715372.59 | D3: 711949.8 | E3: 711655.24 | F3: 713830.4 | G3: 717557.01 | H3: 721923.45 | I3: 724572.17 | J3: 727368.81 | K3: 731775.25 | L3: 738587.8 | M3: 748696.14 | N3: 761491.39 | O3: 775947.81 | P3: 791112.29 | Q3: 806288.82 | R3: 821244.06 | S3: 835743.72 | T3: 849823.88 | U3: 863687.66 | V3: 877583.48 | W3: 891687.57 | X3: 906045.37 | Y3: 920582.89 | Z3: 935147.09 | AA3: 949587.45 | AB3: 963816.98 | AC3: 977891.05 | AD3: 992060.4 | AE3: 1006681.7 | AF3: 1022030.1 | AG3: 1038156.6 | AH3: 1054875.3 | AI3: 1071872.9 | AJ3: 1088842.8 | AK3: 1105587.5
A4: km_traveler_sd_2 | B4: 624600.34 | C4: 617920.74 | D4: 615319.64 | E4: 615114.49 | F4: 616809.66 | G4: 619693.8 | H4: 623054.41 | I4: 625024.24 | J4: 627085.81 | K4: 630404.43 | L4: 635601.08 | M4: 643363.58 | N4: 653201.33 | O4: 664298.13 | P4: 675899.9 | Q4: 687459.36 | R4: 698788.72 | S4: 709714.12 | T4: 720276.5 | U4: 730648.42 | V4: 741033.76 | W4: 751572.57 | X4: 762295.08 | Y4: 773133.86 | Z4: 783959.26 | AA4: 794647.22 | AB4: 805129.57 | AC4: 815456.93 | AD4: 825838.17 | AE4: 836561.95 | AF4: 847842.13 | AG4: 859707.6 | AH4: 871999.32 | AI4: 884464.5 | AJ4: 896865.48 | AK4: 909059.59
A5: km_trav_auto_sd_2 | B5: 554271.64 | C5: 547356.54 | D5: 544431.44 | E5: 543865.49 | F5: 545173.66 | G5: 547650.94 | H5: 550623.44 | I5: 552368.89 | J5: 554247.44 | K5: 557250.08 | L5: 561969.39 | M5: 569079.94 | N5: 578137.21 | O5: 588423.51 | P5: 599256.31 | Q5: 610128.4 | R5: 620852.52 | S5: 631263.2 | T5: 641362.1 | U5: 651275.01 | V5: 661167.98 | W5: 671166.74 | X5: 681310.42 | Y5: 691554.52 | Z5: 701799.57 | AA5: 711942.48 | AB5: 721922.65 | AC5: 731767.19 | AD5: 741628.58 | AE5: 751745.03 | AF5: 762317.21 | AG5: 773404.14 | AH5: 784898.97 | AI5: 796593.02 | AJ5: 808270.26 | AK5: 819780.36
A6: km_traveler_croa_2 | B6: 70328.7 | C6: 70332.042 | D6: 70540.846 | E6: 70842.651 | F6: 71203.326 | G6: 71599.449 | H6: 71985.452 | I6: 72208.972 | J6: 72397.198 | K6: 72719.286 | L6: 73208.896 | M6: 73888.897 | N6: 74716.347 | O6: 75599.58 | P6: 76471.458 | Q6: 77293.49 | R6: 78064.533 | S6: 78775.765 | T6: 79457.485 | U6: 80146.311 | V6: 80872.014 | W6: 81646.172 | X6: 82461.989 | Y6: 83301.018 | Z6: 84138.843 | AA6: 84957.497 | AB6: 85749.656 | AC6: 86530.895 | AD6: 87341.552 | AE6: 88221.606 | AF6: 89187.386 | AG6: 90223.904 | AH6: 91295.972 | AI6: 92368.187 | AJ6: 93417.413 | AK6: 94439.832
A7: km_traveler_ld_2 | B7: 275159.81 | C7: 270742.59 | D7: 269045.03 | E7: 268933.63 | F7: 270072.88 | G7: 271986.63 | H7: 274210.66 | I7: 275516.22 | J7: 276913.52 | K7: 279157.34 | L7: 282667.43 | M7: 287917.33 | N7: 294601.45 | O7: 302197.2 | P7: 310209.06 | Q7: 318266.83 | R7: 326241.06 | S7: 334001.81 | T7: 341570.48 | U7: 349063.77 | V7: 356624.63 | W7: 364353.49 | X7: 372273.84 | Y7: 380338.31 | Z7: 388450.84 | AA7: 396516.45 | AB7: 404477.64 | AC7: 412366.42 | AD7: 420338.31 | AE7: 428614.34 | AF7: 437366.3 | AG7: 446628.79 | AH7: 456290.14 | AI7: 466159.23 | AJ7: 476046.71 | AK7: 485829.67
A8: km_trav_auto_ld_2 | B8: 169831.3 | C8: 168016.05 | D8: 167518.36 | E8: 167789.75 | F8: 168656.74 | G8: 169906.07 | H8: 171300.01 | I8: 172203.29 | J8: 173121.37 | K8: 174525.17 | L8: 176618.41 | M8: 179616.2 | N8: 183354.18 | O8: 187524.3 | P8: 191855.98 | Q8: 196160.42 | R8: 200391.55 | S8: 204480.53 | T8: 208461.78 | U8: 212412.65 | V8: 216415.5 | W8: 220520.83 | X8: 224734.95 | Y8: 229028.37 | Z8: 233347.52 | AA8: 237644.97 | AB8: 241894.33 | AC8: 246123.86 | AD8: 250431.82 | AE8: 254936.71 | AF8: 259712.9 | AG8: 264752.49 | AH8: 269976.31 | AI8: 275279.85 | AJ8: 280572.56 | AK8: 285807.1
A9: km_traveler_crai_2 | B9: 105328.51 | C9: 106325.39 | D9: 107397.03 | E9: 108458.36 | F9: 109436.2 | G9: 110393.44 | H9: 111311.65 | I9: 112136.97 | J9: 112857.22 | K9: 113775.12 | L9: 114862.32 | M9: 116046.02 | N9: 117318.4 | O9: 118562.74 | P9: 119734.39 | Q9: 120833.1 | R9: 121914.09 | S9: 122956.17 | T9: 124017.98 | U9: 125147.73 | V9: 126375.71 | W9: 127705.36 | X9: 129122.27 | Y9: 130605.54 | Z9: 132129.71 | AA9: 133680.85 | AB9: 135253.16 | AC9: 136872.24 | AD9: 138596.26 | AE9: 140467.18 | AF9: 142483.6 | AG9: 144601.36 | AH9: 146761.88 | AI9: 148923.47 | AJ9: 151067.73 | AK9: 153201.97
A10: km_traveler_cair_0 | B10: 291099.78 | C10: 296732.25 | D10: 303399.75 | E10: 310101.24 | F10: 317201.73 | G10: 324502.44 | H10: 330635.35 | I10: 336433.31 | J10: 342691.74 | K10: 350098.8 | L10: 358933.34 | M10: 369130.28 | N10: 380265.35 | O10: 391683.6 | P10: 402855.01 | Q10: 413483.29 | R10: 424595.2 | S10: 435911.92 | T10: 447265.33 | U10: 458546.12 | V10: 469791.13 | W10: 481245.88 | X10: 493332.71 | Y10: 506504.08 | Z10: 521012.34 | AA10: 536902.98 | AB10: 554004.82 | AC10: 572085.52 | AD10: 590983.81 | AE10: 610797.26 | AF10: 631759.91 | AG10: 654147.92 | AH10: 678108.48 | AI10: 703545.52 | AJ10: 730135.33 | AK10: 757441.47
A11: km_trav_auto_ld_0+km_trav_auto_sd_0 | B11: 724102.94 | C11: 715372.59 | D11: 711949.8 | E11: 711655.24 | F11: 713830.4 | G11: 717557.01 | H11: 721048.96 | I11: 724515.31 | J11: 728414.17 | K11: 733272.32 | L11: 739458.31 | M11: 747123.76 | N11: 756185.97 | O11: 766356.76 | P11: 777279.84 | Q11: 788631.83 | R11: 801027.98 | S11: 814038.14 | T11: 827282.65 | U11: 840513.29 | V11: 853610.37 | W11: 866570.67 | X11: 879485.97 | Y11: 892500.03 | Z11: 905745.18 | AA11: 919304.94 | AB11: 933198.03 | AC11: 947397.43 | AD11: 961862.8 | AE11: 976580.56 | AF11: 991573.28 | AG11: 1006886.7 | AH11: 1022556.8 | AI11: 1038572.4 | AJ11: 1054858.1 | AK11: 1071285.3
A12: km_traveler_sd_0 | B12: 624600.34 | C12: 617920.74 | D12: 615319.64 | E12: 615114.49 | F12: 616809.66 | G12: 619693.8 | H12: 622371.16 | I12: 625006.58 | J12: 627968.27 | K12: 631675.5 | L12: 636416.82 | M12: 642304.44 | N12: 649264.6 | O12: 657064.41 | P12: 665419.78 | Q12: 674074.72 | R12: 683503.33 | S12: 693375.45 | T12: 703396.04 | U12: 713372.07 | V12: 723211.25 | W12: 732913.73 | X12: 742555.25 | Y12: 752251.91 | Z12: 762108.4 | AA12: 772187.68 | AB12: 782498.97 | AC12: 793014.51 | AD12: 803697.6 | AE12: 814536.76 | AF12: 825552.96 | AG12: 836786.92 | AH12: 848270.31 | AI12: 859995.48 | AJ12: 871902.97 | AK12: 883892.03
