Workbook
Name formatResults: [1]ResultsEXR10!$A$50

Sheet Export
A1: _date_ | B1: 42005 | C1: 42370 | D1: 42736 | E1: 43101 | F1: 43466 | G1: 43831 | H1: 44197 | I1: 44562 | J1: 44927 | K1: 45292 | L1: 45658 | M1: 46023 | N1: 46388 | O1: 46753 | P1: 47119 | Q1: 47484 | R1: 47849 | S1: 48214 | T1: 48580 | U1: 48945 | V1: 49310 | W1: 49675 | X1: 50041 | Y1: 50406 | Z1: 50771 | AA1: 51136 | AB1: 51502 | AC1: 51867 | AD1: 52232 | AE1: 52597 | AF1: 52963 | AG1: 53328 | AH1: 53693 | AI1: 54058 | AJ1: 54424 | AK1: 54789 | AL1: 55154 | AM1: 55519 | AN1: 55885 | AO1: 56250 | AP1: 56615 | AQ1: 56980 | AR1: 57346 | AS1: 57711 | AT1: 58076 | AU1: 58441 | AV1: 58807 | AW1: 59172 | AX1: 59537 | AY1: 59902 | AZ1: 60268 | BA1: 60633 | BB1: 60998 | BC1: 61363 | BD1: 61729 | BE1: 62094
A2: x_2 | B2: 632182.57 | C2: 640933.12 | D2: 650559.77 | E2: 660455.93 | F2: 670638.53 | G2: 681062.54 | H2: 691091.28 | I2: 701347.5 | J2: 711803.29 | K2: 722437.09 | L2: 734370.39 | M2: 745322.01 | N2: 756428.53 | O2: 767702.3 | P2: 779161.49 | Q2: 790827.42 | R2: 802721.7 | S2: 814868.83 | T2: 827293.16 | U2: 840017.19 | V2: 852220.36 | W2: 865613.96 | X2: 879375.92 | Y2: 893522.04 | Z2: 908068.79 | AA2: 920577.08 | AB2: 934805.24 | AC2: 949477.15 | AD2: 964608.5 | AE2: 980213.61 | AF2: 996306.67 | AG2: 1012901 | AH2: 1030007.7 | AI2: 1047638 | AJ2: 1065803.4 | AK2: 1084512.9 | AL2: 1102970.5 | AM2: 1121769.7 | AN2: 1140907.9 | AO2: 1160387.1 | AP2: 1180214 | AQ2: 1200399.4 | AR2: 1220956.4 | AS2: 1241899 | AT2: 1263241 | AU2: 1284996.4 | AV2: 1307237.1 | AW2: 1329919.7 | AX2: 1353055.8 | AY2: 1376655.8 | AZ2: 1400729.7 | BA2: 1425287.5 | BB2: 1450338.8 | BC2: 1475891.8 | BD2: 1501954.2 | BE2: 1528533.2
A3: x_0 | B3: 632182.57 | C3: 640933.08 | D3: 650559.62 | E3: 660455.58 | F3: 670637.91 | G3: 681061.56 | H3: 691089.46 | I3: 701344.12 | J3: 711797.5 | K3: 722428.06 | L3: 734357.27 | M3: 745305.94 | N3: 756411.84 | O3: 767687.79 | P3: 779152.03 | Q3: 790825.72 | R3: 802733.63 | S3: 814902.11 | T3: 827356.17 | U3: 840118.3 | V3: 852367.46 | W3: 865817.57 | X3: 879647.83 | Y3: 893874.5 | Z3: 908513.99 | AA3: 921125.44 | AB3: 935469.57 | AC3: 950269.9 | AD3: 965542.23 | AE3: 981300.9 | AF3: 997560.08 | AG3: 1014333.9 | AH3: 1031633.9 | AI3: 1049471.6 | AJ3: 1067858.7 | AK3: 1086804.7 | AL3: 1105510.4 | AM3: 1124570.2 | AN3: 1143981.3 | AO3: 1163745.8 | AP3: 1183870.5 | AQ3: 1204366.6 | AR3: 1225247.4 | AS3: 1246527 | AT3: 1268219.8 | AU3: 1290339.7 | AV3: 1312958.1 | AW3: 1336030.6 | AX3: 1359568.9 | AY3: 1383583.7 | AZ3: 1408085.5 | BA3: 1433083.3 | BB3: 1458585.9 | BC3: 1484601.8 | BD3: 1511139.2 | BE3: 1538205.6
A4: x_cagr_2 | B4: 15830.016 | C4: 16048.837 | D4: 16290.019 | E4: 16538.338 | F4: 16794.007 | G4: 17055.655 | H4: 17307.094 | I4: 17563.779 | J4: 17824.953 | K4: 18090.064 | L4: 18387.248 | M4: 18659.315 | N4: 18934.682 | O4: 19213.65 | P4: 19496.691 | Q4: 19784.369 | R4: 20077.245 | S4: 20375.971 | T4: 20681.208 | U4: 20993.577 | V4: 21292.6 | W4: 21621.148 | X4: 21958.759 | Y4: 22305.885 | Z4: 22662.974 | AA4: 22969.079 | AB4: 23318.103 | AC4: 23678.3 | AD4: 24050.13 | AE4: 24433.986 | AF4: 24830.232 | AG4: 25239.204 | AH4: 25661.172 | AI4: 26096.397 | AJ4: 26545.146 | AK4: 27007.622 | AL4: 27464.018 | AM4: 27929.119 | AN4: 28402.825 | AO4: 28885.125 | AP4: 29376.123 | AQ4: 29876.049 | AR4: 30385.2 | AS4: 30903.912 | AT4: 31432.542 | AU4: 31971.446 | AV4: 32522.489 | AW4: 33084.637 | AX4: 33658.204 | AY4: 34243.47 | AZ4: 34840.686 | BA4: 35450.138 | BB4: 36072.068 | BC4: 36706.685 | BD4: 37354.171 | BE4: 38014.692
A5: x_cagr_0 | B5: 15830.016 | C5: 16048.835 | D5: 16290.009 | E5: 16538.316 | F5: 16793.969 | G5: 17055.595 | H5: 17306.984 | I5: 17563.576 | J5: 17824.611 | K5: 18089.537 | L5: 18386.494 | M5: 18658.415 | N5: 18933.784 | O5: 19212.924 | P5: 19496.305 | Q5: 19784.474 | R5: 20078.175 | S5: 20378.147 | T5: 20685.071 | U5: 20999.549 | V5: 21301.056 | W5: 21632.599 | X5: 21973.764 | Y5: 22325.005 | Z5: 22686.745 | AA5: 22997.926 | AB5: 23352.561 | AC5: 23718.871 | AD5: 24097.304 | AE5: 24488.24 | AF5: 24892.032 | AG5: 25309.05 | AH5: 25739.583 | AI5: 26183.901 | AJ5: 26642.273 | AK5: 27114.905 | AL5: 27581.858 | AM5: 28057.94 | AN5: 28543.039 | AO5: 29037.145 | AP5: 29540.372 | AQ5: 30052.956 | AR5: 30575.205 | AS5: 31107.468 | AT5: 31650.114 | AU5: 32203.511 | AV5: 32769.476 | AW5: 33346.937 | AX5: 33936.209 | AY5: 34537.588 | AZ5: 35151.349 | BA5: 35777.716 | BB5: 36416.909 | BC5: 37069.144 | BD5: 37734.626 | BE5: 38413.552
A6: x_cfor_2 | B6: 41.818509 | C6: 42.3722 | D6: 42.991501 | E6: 43.638451 | F6: 44.311845 | G6: 45.005282 | H6: 45.673341 | I6: 46.354934 | J6: 47.04719 | K6: 47.748588 | L6: 48.53412 | M6: 49.253258 | N6: 49.981346 | O6: 50.719312 | P6: 51.468331 | Q6: 52.229694 | R6: 53.004535 | S6: 53.794274 | T6: 54.600392 | U6: 55.424312 | V6: 56.211593 | W6: 57.075331 | X6: 57.961507 | Y6: 58.871369 | Z6: 59.806175 | AA6: 60.604608 | AB6: 61.514369 | AC6: 62.451669 | AD6: 63.417829 | AE6: 64.414084 | AF6: 65.441634 | AG6: 66.501618 | AH6: 67.594932 | AI6: 68.72239 | AJ6: 69.884766 | AK6: 71.082629 | AL6: 72.263905 | AM6: 73.467399 | AN6: 74.692748 | AO6: 75.939877 | AP6: 77.209044 | AQ6: 78.500903 | AR6: 79.81623 | AS6: 81.155876 | AT6: 82.520719 | AU6: 83.911634 | AV6: 85.333715 | AW6: 86.784284 | AX6: 88.264155 | AY6: 89.774026 | AZ6: 91.314517 | BA6: 92.886517 | BB6: 94.490689 | BC6: 96.127562 | BD6: 97.797585 | BE6: 99.50116
A7: x_cfor_0 | B7: 41.818509 | C7: 42.372188 | D7: 42.991459 | E7: 43.638361 | F7: 44.311687 | G7: 45.005042 | H7: 45.672907 | I7: 46.354157 | J7: 47.045894 | K7: 47.746575 | L7: 48.531177 | M7: 49.249725 | N7: 49.977809 | O7: 50.716464 | P7: 51.4669 | Q7: 52.230388 | R7: 53.008954 | S7: 53.804343 | T7: 54.618092 | U7: 55.451554 | V7: 56.250115 | W7: 57.12754 | X7: 58.029941 | Y7: 58.958524 | Z7: 59.914423 | AA7: 60.735809 | AB7: 61.670904 | AC7: 62.635724 | AD7: 63.631512 | AE7: 64.659428 | AF7: 65.720616 | AG7: 66.81638 | AH7: 67.947686 | AI7: 69.115381 | AJ7: 70.320264 | AK7: 71.562925 | AL7: 72.790633 | AM7: 74.042297 | AN7: 75.317508 | AO7: 76.616204 | AP7: 77.938684 | AQ7: 79.285632 | AR7: 80.65788 | AS7: 82.056344 | AT7: 83.481978 | AU7: 84.935729 | AV7: 86.422386 | AW7: 87.939118 | AX7: 89.486758 | AY7: 91.06609 | AZ7: 92.677852 | BA7: 94.322575 | BB7: 96.000842 | BC7: 97.713245 | BD7: 99.460369 | BE7: 101.24277
A8: x_cfoo_2 | B8: 45348.86 | C8: 45979.169 | D8: 46673.414 | E8: 47387.894 | F8: 48123.562 | G8: 48876.922 | H8: 49601.871 | I8: 50342.812 | J8: 51097.552 | K8: 51864.4 | L8: 52723.992 | M8: 53512.213 | N8: 54310.361 | O8: 55119.139 | P8: 55939.765 | Q8: 56773.758 | R8: 57622.72 | S8: 58488.499 | T8: 59372.971 | U8: 60277.91 | V8: 61144.428 | W8: 62095.651 | X8: 63072.887 | Y8: 64077.489 | Z8: 65110.79 | AA8: 65997.48 | AB8: 67007.286 | AC8: 68049.037 | AD8: 69124.124 | AE8: 70233.756 | AF8: 71379.063 | AG8: 72561.066 | AH8: 73780.602 | AI8: 75038.484 | AJ8: 76335.534 | AK8: 77672.383 | AL8: 78991.831 | AM8: 80336.286 | AN8: 81705.431 | AO8: 83099.233 | AP8: 84517.99 | AQ8: 85962.319 | AR8: 87433.053 | AS8: 88931.156 | AT8: 90457.663 | AU8: 92013.626 | AV8: 93604.331 | AW8: 95226.791 | AX8: 96881.96 | AY8: 98570.704 | AZ8: 100293.81 | BA8: 102052.09 | BB8: 103846.25 | BC8: 105676.95 | BD8: 107544.74 | BE8: 109450.18
A9: x_cfoo_0 | B9: 45348.86 | C9: 45979.166 | D9: 46673.402 | E9: 47387.866 | F9: 48123.51 | G9: 48876.839 | H9: 49601.719 | I9: 50342.531 | J9: 51097.069 | K9: 51863.64 | L9: 52722.877 | M9: 53510.811 | N9: 54308.85 | O9: 55117.755 | P9: 55938.767 | Q9: 56773.406 | R9: 57623.503 | S9: 58491.071 | T9: 59378.067 | U9: 60286.283 | V9: 61156.804 | W9: 62112.943 | X9: 63096.109 | Y9: 64107.706 | Z9: 65149.07 | AA9: 66044.741 | AB9: 67064.634 | AC9: 68117.535 | AD9: 69204.836 | AE9: 70327.74 | AF9: 71487.369 | AG9: 72684.79 | AH9: 73920.878 | AI9: 75196.474 | AJ9: 76512.418 | AK9: 77869.356 | AL9: 79209.874 | AM9: 80576.428 | AN9: 81968.676 | AO9: 83386.583 | AP9: 84830.456 | AQ9: 86300.924 | AR9: 87798.837 | AS9: 89325.182 | AT9: 90881.017 | AU9: 92467.422 | AV9: 94089.628 | AW9: 95744.589 | AX9: 97433.25 | AY9: 99156.494 | AZ9: 100915.15 | BA9: 102709.93 | BB9: 104541.53 | BC9: 106410.58 | BD9: 108317.69 | BE9: 110263.42
A10: x_cveh_2 | B10: 111357.6 | C10: 112878.7 | D10: 114544.56 | E10: 116250.45 | F10: 118001.78 | G10: 119792.74 | H10: 121514.05 | I10: 123277.26 | J10: 125078.67 | K10: 126915.13 | L10: 128982.19 | M10: 130879.95 | N10: 132809.25 | O10: 134773.24 | P10: 136775.71 | Q10: 138820.65 | R10: 140911.76 | S10: 143052.97 | T10: 145248.07 | U10: 147500.36 | V10: 149666.34 | W10: 152045.28 | X10: 154491.36 | Y10: 157006.06 | Z10: 159591.32 | AA10: 161821.55 | AB10: 164357.3 | AC10: 166973.11 | AD10: 169670.18 | AE10: 172449.52 | AF10: 175312.37 | AG10: 178260.13 | AH10: 181294.11 | AI10: 184415.85 | AJ10: 187627.16 | AK10: 190929.62 | AL10: 194184.29 | AM10: 197496.68 | AN10: 200867.14 | AO10: 204296.74 | AP10: 207787.39 | AQ10: 211341.67 | AR10: 214962.34 | AS10: 218652.1 | AT10: 222413.38 | AU10: 226248.37 | AV10: 230169.42 | AW10: 234168.41 | AX10: 238246.84 | AY10: 242406.09 | AZ10: 246647.45 | BA10: 250972.41 | BB10: 255382.33 | BC10: 259878.46 | BD10: 264461.91 | BE10: 269133.78
A11: x_cveh_0 | B11: 111357.6 | C11: 112878.69 | D11: 114544.53 | E11: 116250.37 | F11: 118001.64 | G11: 119792.53 | H11: 121513.65 | I11: 123276.52 | J11: 125077.41 | K11: 126913.18 | L11: 128979.4 | M11: 130876.65 | N11: 132806.04 | O11: 134770.78 | P11: 136774.61 | Q11: 138821.43 | R11: 140915.62 | S11: 143061.53 | T11: 145262.98 | U11: 147523.18 | V11: 149698.41 | W11: 152088.53 | X11: 154547.94 | Y11: 157078.19 | Z11: 159681.11 | AA11: 161930.7 | AB11: 164487.95 | AC11: 167127.35 | AD11: 169850.1 | AE11: 172657.22 | AF11: 175549.92 | AG11: 178529.8 | AH11: 181598.28 | AI11: 184756.94 | AJ11: 188007.64 | AK11: 191351.97 | AL11: 194650.4 | AM11: 198008.53 | AN11: 201426.67 | AO11: 204905.95 | AP11: 208448.37 | AQ11: 212056.57 | AR11: 215733.39 | AS11: 219481.57 | AT11: 223303.61 | AU11: 227201.74 | AV11: 231188.06 | AW11: 235254.26 | AX11: 239401.88 | AY11: 243632.37 | AZ11: 247947.16 | BA11: 252347.46 | BB11: 256834.52 | BC11: 261409.6 | BD11: 266073.96 | BE11: 270828.81
A12: x_cgla_2 | B12: 5221.1985 | C12: 5293.7284 | D12: 5373.6419 | E12: 5455.9248 | F12: 5540.6932 | G12: 5627.5384 | H12: 5711.1403 | I12: 5796.5992 | J12: 5883.6522 | K12: 5972.0968 | L12: 6071.2176 | M12: 6162.114 | N12: 6254.1489 | O12: 6347.4058 | P12: 6442.0279 | Q12: 6538.1927 | R12: 6636.086 | S12: 6735.9217 | T12: 6837.9147 | U12: 6942.2669 | V12: 7042.1898 | W12: 7151.8624 | X12: 7264.5224 | Y12: 7380.3227 | Z12: 7499.4149 | AA12: 7601.5967 | AB12: 7717.9369 | AC12: 7837.9377 | AD12: 7961.7642 | AE12: 8089.5611 | AF12: 8221.4642 | AG12: 8357.5955 | AH12: 8498.0544 | AI12: 8642.9359 | AJ12: 8792.3358 | AK12: 8946.3274 | AL12: 9098.3098 | AM12: 9253.16 | AN12: 9410.8454 | AO12: 9571.374 | AP12: 9734.7955 | AQ12: 9901.1949 | AR12: 10070.678 | AS12: 10243.361 | AT12: 10419.365 | AU12: 10598.81 | AV12: 10782.301 | AW12: 10969.49 | AX12: 11160.482 | AY12: 11355.373 | AZ12: 11554.254 | BA12: 11757.217 | BB12: 11964.342 | BC12: 12175.706 | BD12: 12391.375 | BE12: 12611.411
... A55: x_cote_0 | B55: 4461.1306 | C55: 4523.3374 | D55: 4591.1779 | E55: 4660.3034 | F55: 4730.9845 | G55: 4803.1653 | H55: 4872.5758 | I55: 4943.7961 | J55: 5016.7866 | K55: 5091.5243 | L55: 5176.0925 | M55: 5254.4811 | N55: 5334.7212 | O55: 5416.8932 | P55: 5501.0973 | Q55: 5587.4382 | R55: 5676.0146 | S55: 5766.9349 | T55: 5860.3011 | U55: 5956.202 | V55: 6048.6867 | W55: 6149.8373 | X55: 6253.7839 | Y55: 6360.6045 | Z55: 6470.3857 | AA55: 6565.5355 | AB55: 6672.7441 | AC55: 6782.8668 | AD55: 6895.9829 | AE55: 7012.174 | AF55: 7131.5316 | AG55: 7254.15 | AH55: 7380.1199 | AI55: 7509.542 | AJ55: 7642.5281 | AK55: 7779.179 | AL55: 7913.8314 | AM55: 8050.8146 | AN55: 8190.1689 | AO55: 8331.9353 | AP55: 8476.1556 | AQ55: 8622.8723 | AR55: 8772.1285 | AS55: 8923.9682 | AT55: 9078.4363 | AU55: 9235.578 | AV55: 9395.8581 | AW55: 9558.9198 | AX55: 9724.8114 | AY55: 9893.5819 | AZ55: 10065.281 | BA55: 10239.961 | BB55: 10417.672 | BC55: 10598.466 | BD55: 10782.399 | BE55: 10969.524

Sheet Import
A1: _date_ | B1: 42005 | C1: 42370 | D1: 42736 | E1: 43101 | F1: 43466 | G1: 43831 | H1: 44197 | I1: 44562 | J1: 44927 | K1: 45292 | L1: 45658 | M1: 46023 | N1: 46388 | O1: 46753 | P1: 47119 | Q1: 47484 | R1: 47849 | S1: 48214 | T1: 48580 | U1: 48945 | V1: 49310 | W1: 49675 | X1: 50041 | Y1: 50406 | Z1: 50771 | AA1: 51136 | AB1: 51502 | AC1: 51867 | AD1: 52232 | AE1: 52597 | AF1: 52963 | AG1: 53328 | AH1: 53693 | AI1: 54058 | AJ1: 54424 | AK1: 54789 | AL1: 55154 | AM1: 55519 | AN1: 55885 | AO1: 56250 | AP1: 56615 | AQ1: 56980 | AR1: 57346 | AS1: 57711 | AT1: 58076 | AU1: 58441 | AV1: 58807 | AW1: 59172 | AX1: 59537 | AY1: 59902 | AZ1: 60268 | BA1: 60633 | BB1: 60998 | BC1: 61363 | BD1: 61729 | BE1: 62094
A2: m_2 | B2: 655454.5 | C2: 662236.08 | D2: 670200.99 | E2: 678711.23 | F2: 687595.77 | G2: 696828.93 | H2: 706038.37 | I2: 715511.08 | J2: 725325.2 | K2: 735511.93 | L2: 746824.87 | M2: 758087.44 | N2: 769619.33 | O2: 781461.33 | P2: 793624.78 | Q2: 806116.41 | R2: 818942.17 | S2: 832109.89 | T2: 845628.05 | U2: 859504.68 | V2: 873193.03 | W2: 887575.87 | X2: 902419.76 | Y2: 917698.49 | Z2: 933409.66 | AA2: 947937.32 | AB2: 963059.96 | AC2: 978509.8 | AD2: 994295.31 | AE2: 1010446.3 | AF2: 1026992.5 | AG2: 1043959.3 | AH2: 1061367 | AI2: 1079233 | AJ2: 1097573 | AK2: 1116401 | AL2: 1135231.3 | AM2: 1154258.9 | AN2: 1173520.4 | AO2: 1193035.8 | AP2: 1212821.3 | AQ2: 1232890 | AR2: 1253251.1 | AS2: 1273910 | AT2: 1294869.9 | AU2: 1316132.4 | AV2: 1337737.6 | AW2: 1359666.1 | AX2: 1381914.7 | AY2: 1404483.4 | AZ2: 1427374.2 | BA2: 1450591.3 | BB2: 1474139.4 | BC2: 1498024.2 | BD2: 1522251.9 | BE2: 1546830
A3: m_0 | B3: 655454.5 | C3: 662236.05 | D3: 670200.92 | E3: 678711.09 | F3: 687595.57 | G3: 696828.69 | H3: 706037.88 | I3: 715510.19 | J3: 725323.87 | K3: 735510.22 | L3: 746822.88 | M3: 758086.54 | N3: 769620.9 | O3: 781466.09 | P3: 793632.85 | Q3: 806127.44 | R3: 818957.87 | S3: 832131.9 | T3: 845656.9 | U3: 859539.73 | V3: 873232.81 | W3: 887620.49 | X3: 902469.17 | Y3: 917751.65 | Z3: 933464.52 | AA3: 947990.79 | AB3: 963109.38 | AC3: 978552.39 | AD3: 994327.89 | AE3: 1010465.3 | AF3: 1026994 | AG3: 1043939.8 | AH3: 1061322.6 | AI3: 1079159.3 | AJ3: 1097465.2 | AK3: 1116253.9 | AL3: 1135038.1 | AM3: 1154012.7 | AN3: 1173214.4 | AO3: 1192663.3 | AP3: 1212375.6 | AQ3: 1232364.3 | AR3: 1252638.2 | AS3: 1273202.8 | AT3: 1294060.9 | AU3: 1315214.1 | AV3: 1336701.3 | AW3: 1358502.8 | AX3: 1380616 | AY3: 1403041.3 | AZ3: 1425780.9 | BA3: 1448837.8 | BB3: 1472216.9 | BC3: 1495924.4 | BD3: 1519967.1 | BE3: 1544353
A4: m_cagr_2 | B4: 12975.415 | C4: 13062.869 | D4: 13167.825 | E4: 13296.077 | F4: 13447.344 | G4: 13619.419 | H4: 13803.121 | I4: 13998.293 | J4: 14204.27 | K4: 14420.434 | L4: 14657.936 | M4: 14901.405 | N4: 15151.874 | O4: 15409.244 | P4: 15673.351 | Q4: 15944.118 | R4: 16221.563 | S4: 16505.718 | T4: 16796.651 | U4: 17094.434 | V4: 17390.366 | W4: 17695.673 | X4: 18009.38 | Y4: 18331.398 | Z4: 18661.739 | AA4: 18974.737 | AB4: 19290.673 | AC4: 19609.584 | AD4: 19932.669 | AE4: 20261.157 | AF4: 20596.097 | AG4: 20938.312 | AH4: 21288.438 | AI4: 21646.961 | AJ4: 22014.275 | AK4: 22390.709 | AL4: 22769.007 | AM4: 23150.181 | AN4: 23534.678 | AO4: 23922.971 | AP4: 24315.539 | AQ4: 24712.778 | AR4: 25114.967 | AS4: 25522.254 | AT4: 25934.698 | AU4: 26352.306 | AV4: 26775.666 | AW4: 27204.635 | AX4: 27639.148 | AY4: 28079.182 | AZ4: 28524.767 | BA4: 28975.986 | BB4: 29432.968 | BC4: 29895.864 | BD4: 30364.859 | BE4: 30840.165
A5: m_cagr_0 | B5: 12975.415 | C5: 13062.873 | D5: 13167.834 | E5: 13296.092 | F5: 13447.369 | G5: 13619.458 | H5: 13803.217 | I5: 13998.466 | J5: 14204.528 | K5: 14420.781 | L5: 14658.382 | M5: 14901.864 | N5: 15152.316 | O5: 15409.64 | P5: 15673.661 | Q5: 15944.292 | R5: 16221.415 | S5: 16505.137 | T5: 16795.526 | U5: 17092.632 | V5: 17387.74 | W5: 17691.983 | X5: 18004.441 | Y5: 18325.025 | Z5: 18653.727 | AA5: 18964.88 | AB5: 19278.736 | AC5: 19595.357 | AD5: 19915.947 | AE5: 20241.736 | AF5: 20573.774 | AG5: 20912.87 | AH5: 21259.671 | AI5: 21614.659 | AJ5: 21978.222 | AK5: 22350.687 | AL5: 22724.799 | AM5: 23101.572 | AN5: 23481.465 | AO5: 23864.967 | AP5: 24252.566 | AQ5: 24644.662 | AR5: 25041.534 | AS5: 25443.336 | AT5: 25850.127 | AU5: 26261.919 | AV5: 26679.302 | AW5: 27102.136 | AX5: 27530.374 | AY5: 27964.015 | AZ5: 28403.101 | BA5: 28847.725 | BB5: 29298.014 | BC5: 29754.142 | BD5: 30216.313 | BE5: 30684.753
A6: m_cfor_2 | B6: 118.88748 | C6: 117.52236 | D6: 116.374 | E6: 115.53625 | F6: 115.01168 | G6: 114.76077 | H6: 114.71783 | I6: 114.89266 | J6: 115.26125 | K6: 115.79424 | L6: 116.56245 | M6: 117.38723 | N6: 118.29337 | O6: 119.27923 | P6: 120.33977 | Q6: 121.47004 | R6: 122.66301 | S6: 123.91718 | T6: 125.23127 | U6: 126.60391 | V6: 127.96285 | W6: 129.41995 | X6: 130.94516 | Y6: 132.53114 | Z6: 134.17525 | AA6: 135.67097 | AB6: 137.24723 | AC6: 138.87395 | AD6: 140.54749 | AE6: 142.26813 | AF6: 144.03728 | AG6: 145.85731 | AH6: 147.72951 | AI6: 149.65536 | AJ6: 151.6366 | AK6: 153.67497 | AL6: 155.71645 | AM6: 157.78409 | AN6: 159.88277 | AO6: 162.01459 | AP6: 164.1809 | AQ6: 166.38356 | AR6: 168.62269 | AS6: 170.89832 | AT6: 173.21046 | AU6: 175.5591 | AV6: 177.95164 | AW6: 180.38352 | AX6: 182.85285 | AY6: 185.35889 | AZ6: 187.90156 | BA6: 190.48271 | BB6: 193.1016 | BC6: 195.75804 | BD6: 198.45236 | BE6: 201.18519
A7: m_cfor_0 | B7: 118.88748 | C7: 117.52203 | D7: 116.37317 | E7: 115.53486 | F7: 115.00963 | G7: 114.75792 | H7: 114.70994 | I7: 114.8777 | J7: 115.2392 | K7: 115.76596 | L7: 116.52907 | M7: 117.36013 | N7: 118.27781 | O7: 119.27638 | P7: 120.34892 | Q7: 121.48978 | R7: 122.70758 | S7: 123.99195 | T7: 125.33587 | U7: 126.73558 | V7: 128.11807 | W7: 129.60686 | X7: 131.16567 | Y7: 132.78323 | Z7: 134.45536 | AA7: 135.97494 | AB7: 137.57458 | AC7: 139.22271 | AD7: 140.91479 | AE7: 142.65082 | AF7: 144.43221 | AG7: 146.26392 | AH7: 148.14589 | AI7: 150.0787 | AJ7: 152.0637 | AK7: 154.10246 | AL7: 156.1392 | AM7: 158.19819 | AN7: 160.28515 | AO7: 162.40252 | AP7: 164.55175 | AQ7: 166.73466 | AR7: 168.9513 | AS7: 171.20159 | AT7: 173.48541 | AU7: 175.80262 | AV7: 178.15799 | AW7: 180.54851 | AX7: 182.97327 | AY7: 185.43193 | AZ7: 187.92442 | BA7: 190.44967 | BB7: 193.00873 | BC7: 195.60252 | BD7: 198.23175 | BE7: 200.89707
A8: m_cfoo_2 | B8: 38720.704 | C8: 39029.707 | D8: 39387.145 | E8: 39805.175 | F8: 40283.362 | G8: 40816.319 | H8: 41376.82 | I8: 41967.783 | J8: 42588.151 | K8: 43236.766 | L8: 43949.897 | M8: 44675.956 | N8: 45422.359 | O8: 46189.349 | P8: 46976.759 | Q8: 47784.567 | R8: 48612.952 | S8: 49462.084 | T8: 50332.198 | U8: 51223.508 | V8: 52108.234 | W8: 53024.482 | X8: 53966.386 | Y8: 54933.498 | Z8: 55925.798 | AA8: 56861.368 | AB8: 57811.781 | AC8: 58772.523 | AD8: 59746.658 | AE8: 60737.518 | AF8: 61747.981 | AG8: 62780.339 | AH8: 63836.371 | AI8: 64917.473 | AJ8: 66024.804 | AK8: 67159.358 | AL8: 68297.631 | AM8: 69444.929 | AN8: 70602.759 | AO8: 71772.567 | AP8: 72955.762 | AQ8: 74153.489 | AR8: 75366.539 | AS8: 76595.324 | AT8: 77839.981 | AU8: 79100.497 | AV8: 80378.707 | AW8: 81673.968 | AX8: 82986.045 | AY8: 84314.844 | AZ8: 85660.417 | BA8: 87022.966 | BB8: 88402.847 | BC8: 89800.484 | BD8: 91216.393 | BE8: 92651.174
A9: m_cfoo_0 | B9: 38720.704 | C9: 39029.717 | D9: 39387.168 | E9: 39805.215 | F9: 40283.426 | G9: 40816.416 | H9: 41377.073 | I9: 41968.236 | J9: 42588.816 | K9: 43237.65 | L9: 43951.012 | M9: 44677.06 | N9: 45423.393 | O9: 46190.276 | P9: 46977.514 | Q9: 47785.054 | R9: 48612.69 | S9: 49460.84 | T9: 50329.753 | U9: 51219.582 | V9: 52102.491 | W9: 53016.311 | X9: 53955.349 | Y9: 54919.153 | Z9: 55907.651 | AA9: 56838.891 | AB9: 57784.355 | AC9: 58739.589 | AD9: 59707.664 | AE9: 60691.908 | AF9: 61695.194 | AG9: 62719.764 | AH9: 63767.436 | AI9: 64839.594 | AJ9: 65937.382 | AK9: 67061.774 | AL9: 68189.278 | AM9: 69325.177 | AN9: 70471.009 | AO9: 71628.258 | AP9: 72798.359 | AQ9: 73982.468 | AR9: 75181.383 | AS9: 76395.523 | AT9: 77625.035 | AU9: 78869.916 | AV9: 80132.015 | AW9: 81410.672 | AX9: 82705.703 | AY9: 84017.066 | AZ9: 85344.854 | BA9: 86689.302 | BB9: 88050.749 | BC9: 89429.673 | BD9: 90826.651 | BE9: 92242.328
A10: m_cveh_2 | B10: 82042.191 | C10: 83964.324 | D10: 86327.584 | E10: 88510.103 | F10: 90362.375 | G10: 91924.876 | H10: 93225.379 | I10: 94397.701 | J10: 95519.538 | K10: 96636.199 | L10: 97893.534 | M10: 99101.235 | N10: 100316.74 | O10: 101552.95 | P10: 102814.16 | Q10: 104102.06 | R10: 105417.42 | S10: 106760.85 | T10: 108133.05 | U10: 109534.63 | V10: 110877.01 | W10: 112308.83 | X10: 113790.85 | Y10: 115314.56 | Z10: 116877.1 | AA10: 118220.71 | AB10: 119648.45 | AC10: 121123.15 | AD10: 122642.69 | AE10: 124208.22 | AF10: 125820.8 | AG10: 127481.01 | AH10: 129188.97 | AI10: 130944.71 | AJ10: 132748.48 | AK10: 134600.65 | AL10: 136426.6 | AM10: 138260.95 | AN10: 140113.66 | AO10: 141990.13 | AP10: 143893.76 | AQ10: 145826.56 | AR10: 147789.46 | AS10: 149782.74 | AT10: 151806.48 | AU10: 153860.79 | AV10: 155951.78 | AW10: 158076.34 | AX10: 160233.97 | AY10: 162424.93 | AZ10: 164649.89 | BA10: 166909.9 | BB10: 169205.99 | BC10: 171539.13 | BD10: 173910.34 | BE10: 176320.67
A11: m_cveh_0 | B11: 82042.191 | C11: 83964.322 | D11: 86327.576 | E11: 88510.092 | F11: 90362.365 | G11: 91924.871 | H11: 93225.362 | I11: 94397.649 | J11: 95519.456 | K11: 96636.102 | L11: 97893.437 | M11: 99101.322 | N11: 100317.19 | O11: 101553.76 | P11: 102815.2 | Q11: 104103.24 | R11: 105418.98 | S11: 106763.15 | T11: 108136.13 | U11: 109538.39 | V11: 110881.31 | W11: 112313.9 | X11: 113797.03 | Y11: 115321.99 | Z11: 116885.78 | AA11: 118230.54 | AB11: 119659.54 | AC11: 121135.68 | AD11: 122656.78 | AE11: 124223.98 | AF11: 125838.33 | AG11: 127500.48 | AH11: 129210.54 | AI11: 130968.49 | AJ11: 132774.53 | AK11: 134629 | AL11: 136457.09 | AM11: 138293.4 | AN11: 140148.01 | AO11: 142026.37 | AP11: 143931.89 | AQ11: 145866.54 | AR11: 147831.2 | AS11: 149826.15 | AT11: 151851.44 | AU11: 153907.18 | AV11: 155999.28 | AW11: 158124.6 | AX11: 160282.74 | AY11: 162474.05 | AZ11: 164699.19 | BA11: 166958.96 | BB11: 169254.34 | BC11: 171586.39 | BD11: 173956.18 | BE11: 176364.75
A12: m_cgla_2 | B12: 6981.7019 | C12: 7058.979 | D12: 7142.4194 | E12: 7232.4182 | F12: 7329.1165 | G12: 7432.2248 | H12: 7537.9431 | I12: 7647.5832 | J12: 7761.464 | K12: 7879.7178 | L12: 8008.7448 | M12: 8139.6448 | N12: 8274.2112 | O12: 8412.8539 | P12: 8555.7794 | Q12: 8703.1575 | R12: 8855.1458 | S12: 9011.9047 | T12: 9173.5954 | U12: 9340.3694 | V12: 9507.6272 | W12: 9682.1931 | X12: 9862.9172 | Y12: 10049.679 | Z12: 10242.522 | AA12: 10427.614 | AB12: 10617.922 | AC12: 10812.385 | AD12: 11011.217 | AE12: 11214.775 | AF12: 11423.409 | AG12: 11637.43 | AH12: 11857.099 | AI12: 12082.644 | AJ12: 12314.273 | AK12: 12552.171 | AL12: 12792.135 | AM12: 13035.122 | AN12: 13281.301 | AO12: 13530.759 | AP12: 13783.579 | AQ12: 14039.842 | AR12: 14299.598 | AS12: 14562.858 | AT12: 14829.597 | AU12: 15099.763 | AV12: 15373.634 | AW12: 15651.02 | AX12: 15931.804 | AY12: 16215.89 | AZ12: 16503.194 | BA12: 16793.663 | BB12: 17087.257 | BC12: 17383.943 | BD12: 17683.704 | BE12: 17986.537
... A55: m_cote_0 | B55: 2283.934 | C55: 2308.8687 | D55: 2335.259 | E55: 2363.2665 | F55: 2393.2172 | G55: 2424.9928 | H55: 2456.7352 | I55: 2489.6495 | J55: 2523.7103 | K55: 2558.8173 | L55: 2597.9756 | M55: 2635.6128 | N55: 2673.8403 | O55: 2712.8462 | P55: 2752.6848 | Q55: 2793.3976 | R55: 2835.0592 | S55: 2877.7127 | T55: 2921.4082 | U55: 2966.1979 | V55: 3009.8401 | W55: 3056.5373 | X55: 3104.7365 | Y55: 3154.336 | Z55: 3205.3541 | AA55: 3251.1303 | AB55: 3300.5156 | AC55: 3351.3717 | AD55: 3403.614 | AE55: 3457.2979 | AF55: 3512.4982 | AG55: 3569.2935 | AH55: 3627.7408 | AI55: 3687.8922 | AJ55: 3749.7979 | AK55: 3813.4995 | AL55: 3876.8996 | AM55: 3941.2175 | AN55: 4006.5664 | AO55: 4072.9736 | AP55: 4140.4589 | AQ55: 4209.049 | AR55: 4278.7713 | AS55: 4349.6553 | AT55: 4421.7309 | AU55: 4495.0273 | AV55: 4569.7312 | AW55: 4645.7484 | AX55: 4723.0924 | AY55: 4801.7856 | AZ55: 4881.8527 | BA55: 4963.3152 | BB55: 5046.1997 | BC55: 5130.5326 | BD55: 5216.3404 | BE55: 5303.6498

Sheet Carbontax
A1: _date_ | B1: 42005 | C1: 42370 | D1: 42736 | E1: 43101 | F1: 43466 | G1: 43831 | H1: 44197 | I1: 44562 | J1: 44927 | K1: 45292 | L1: 45658 | M1: 46023 | N1: 46388 | O1: 46753 | P1: 47119 | Q1: 47484 | R1: 47849 | S1: 48214 | T1: 48580 | U1: 48945 | V1: 49310 | W1: 49675 | X1: 50041 | Y1: 50406 | Z1: 50771 | AA1: 51136 | AB1: 51502 | AC1: 51867 | AD1: 52232 | AE1: 52597 | AF1: 52963 | AG1: 53328 | AH1: 53693 | AI1: 54058 | AJ1: 54424 | AK1: 54789 | AL1: 55154 | AM1: 55519 | AN1: 55885 | AO1: 56250 | AP1: 56615 | AQ1: 56980 | AR1: 57346 | AS1: 57711 | AT1: 58076 | AU1: 58441 | AV1: 58807 | AW1: 59172 | AX1: 59537 | AY1: 59902 | AZ1: 60268 | BA1: 60633 | BB1: 60998 | BC1: 61363 | BD1: 61729 | BE1: 62094
A2: t2val_ch_0 | B2: 0 | C2: 0 | D2: 0 | E2: 0 | F2: 0 | G2: 0 | H2: 0 | I2: 0 | J2: 0 | K2: 0 | L2: 0 | M2: 0 | N2: 0 | O2: 0 | P2: 0 | Q2: 0 | R2: 0 | S2: 0 | T2: 0 | U2: 0 | V2: 0 | W2: 0 | X2: 0 | Y2: 0 | Z2: 0 | AA2: 0 | AB2: 0 | AC2: 0 | AD2: 0 | AE2: 0 | AF2: 0 | AG2: 0 | AH2: 0 | AI2: 0 | AJ2: 0 | AK2: 0 | AL2: 0 | AM2: 0 | AN2: 0 | AO2: 0 | AP2: 0 | AQ2: 0 | AR2: 0 | AS2: 0 | AT2: 0 | AU2: 0 | AV2: 0 | AW2: 0 | AX2: 0 | AY2: 0 | AZ2: 0 | BA2: 0 | BB2: 0 | BC2: 0 | BD2: 0 | BE2: 0
A3: t2val_ch_2 | B3: 0 | C3: 0 | D3: 0 | E3: 0 | F3: 0 | G3: 0 | H3: 0 | I3: 0 | J3: 0 | K3: 0 | L3: 0 | M3: 0 | N3: 0 | O3: 0 | P3: 0 | Q3: 0 | R3: 0 | S3: 0 | T3: 0 | U3: 0 | V3: 0 | W3: 0 | X3: 0 | Y3: 0 | Z3: 0 | AA3: 0 | AB3: 0 | AC3: 0 | AD3: 0 | AE3: 0 | AF3: 0 | AG3: 0 | AH3: 0 | AI3: 0 | AJ3: 0 | AK3: 0 | AL3: 0 | AM3: 0 | AN3: 0 | AO3: 0 | AP3: 0 | AQ3: 0 | AR3: 0 | AS3: 0 | AT3: 0 | AU3: 0 | AV3: 0 | AW3: 0 | AX3: 0 | AY3: 0 | AZ3: 0 | BA3: 0 | BB3: 0 | BC3: 0 | BD3: 0 | BE3: 0
A4: t2val_sec_0 | B4: 0 | C4: 0 | D4: 0 | E4: 0 | F4: 0 | G4: 0 | H4: 0 | I4: 0 | J4: 0 | K4: 0 | L4: 0 | M4: 0 | N4: 0 | O4: 0 | P4: 0 | Q4: 0 | R4: 0 | S4: 0 | T4: 0 | U4: 0 | V4: 0 | W4: 0 | X4: 0 | Y4: 0 | Z4: 0 | AA4: 0 | AB4: 0 | AC4: 0 | AD4: 0 | AE4: 0 | AF4: 0 | AG4: 0 | AH4: 0 | AI4: 0 | AJ4: 0 | AK4: 0 | AL4: 0 | AM4: 0 | AN4: 0 | AO4: 0 | AP4: 0 | AQ4: 0 | AR4: 0 | AS4: 0 | AT4: 0 | AU4: 0 | AV4: 0 | AW4: 0 | AX4: 0 | AY4: 0 | AZ4: 0 | BA4: 0 | BB4: 0 | BC4: 0 | BD4: 0 | BE4: 0
A5: t2val_sec_2 | B5: 0 | C5: 0 | D5: 0 | E5: 0 | F5: 0 | G5: 0 | H5: 0 | I5: 0 | J5: 0 | K5: 0 | L5: 0 | M5: 0 | N5: 0 | O5: 0 | P5: 0 | Q5: 0 | R5: 0 | S5: 0 | T5: 0 | U5: 0 | V5: 0 | W5: 0 | X5: 0 | Y5: 0 | Z5: 0 | AA5: 0 | AB5: 0 | AC5: 0 | AD5: 0 | AE5: 0 | AF5: 0 | AG5: 0 | AH5: 0 | AI5: 0 | AJ5: 0 | AK5: 0 | AL5: 0 | AM5: 0 | AN5: 0 | AO5: 0 | AP5: 0 | AQ5: 0 | AR5: 0 | AS5: 0 | AT5: 0 | AU5: 0 | AV5: 0 | AW5: 0 | AX5: 0 | AY5: 0 | AZ5: 0 | BA5: 0 | BB5: 0 | BC5: 0 | BD5: 0 | BE5: 0
A6: t2val_ci_0 | B6: 0 | C6: 0 | D6: 0 | E6: 0 | F6: 0 | G6: 0 | H6: 0 | I6: 0 | J6: 0 | K6: 0 | L6: 0 | M6: 0 | N6: 0 | O6: 0 | P6: 0 | Q6: 0 | R6: 0 | S6: 0 | T6: 0 | U6: 0 | V6: 0 | W6: 0 | X6: 0 | Y6: 0 | Z6: 0 | AA6: 0 | AB6: 0 | AC6: 0 | AD6: 0 | AE6: 0 | AF6: 0 | AG6: 0 | AH6: 0 | AI6: 0 | AJ6: 0 | AK6: 0 | AL6: 0 | AM6: 0 | AN6: 0 | AO6: 0 | AP6: 0 | AQ6: 0 | AR6: 0 | AS6: 0 | AT6: 0 | AU6: 0 | AV6: 0 | AW6: 0 | AX6: 0 | AY6: 0 | AZ6: 0 | BA6: 0 | BB6: 0 | BC6: 0 | BD6: 0 | BE6: 0
A7: t2val_ci_2 | B7: 0 | C7: 0 | D7: 0 | E7: 0 | F7: 0 | G7: 0 | H7: 0 | I7: 0 | J7: 0 | K7: 0 | L7: 0 | M7: 0 | N7: 0 | O7: 0 | P7: 0 | Q7: 0 | R7: 0 | S7: 0 | T7: 0 | U7: 0 | V7: 0 | W7: 0 | X7: 0 | Y7: 0 | Z7: 0 | AA7: 0 | AB7: 0 | AC7: 0 | AD7: 0 | AE7: 0 | AF7: 0 | AG7: 0 | AH7: 0 | AI7: 0 | AJ7: 0 | AK7: 0 | AL7: 0 | AM7: 0 | AN7: 0 | AO7: 0 | AP7: 0 | AQ7: 0 | AR7: 0 | AS7: 0 | AT7: 0 | AU7: 0 | AV7: 0 | AW7: 0 | AX7: 0 | AY7: 0 | AZ7: 0 | BA7: 0 | BB7: 0 | BC7: 0 | BD7: 0 | BE7: 0
A8: t2val_y_0 | B8: 0 | C8: 0 | D8: 0 | E8: 0 | F8: 0 | G8: 0 | H8: 0 | I8: 0 | J8: 0 | K8: 0 | L8: 0 | M8: 0 | N8: 0 | O8: 0 | P8: 0 | Q8: 0 | R8: 0 | S8: 0 | T8: 0 | U8: 0 | V8: 0 | W8: 0 | X8: 0 | Y8: 0 | Z8: 0 | AA8: 0 | AB8: 0 | AC8: 0 | AD8: 0 | AE8: 0 | AF8: 0 | AG8: 0 | AH8: 0 | AI8: 0 | AJ8: 0 | AK8: 0 | AL8: 0 | AM8: 0 | AN8: 0 | AO8: 0 | AP8: 0 | AQ8: 0 | AR8: 0 | AS8: 0 | AT8: 0 | AU8: 0 | AV8: 0 | AW8: 0 | AX8: 0 | AY8: 0 | AZ8: 0 | BA8: 0 | BB8: 0 | BC8: 0 | BD8: 0 | BE8: 0
A9: t2val_y_2 | B9: 0 | C9: 0 | D9: 0 | E9: 0 | F9: 0 | G9: 0 | H9: 0 | I9: 0 | J9: 0 | K9: 0 | L9: 0 | M9: 0 | N9: 0 | O9: 0 | P9: 0 | Q9: 0 | R9: 0 | S9: 0 | T9: 0 | U9: 0 | V9: 0 | W9: 0 | X9: 0 | Y9: 0 | Z9: 0 | AA9: 0 | AB9: 0 | AC9: 0 | AD9: 0 | AE9: 0 | AF9: 0 | AG9: 0 | AH9: 0 | AI9: 0 | AJ9: 0 | AK9: 0 | AL9: 0 | AM9: 0 | AN9: 0 | AO9: 0 | AP9: 0 | AQ9: 0 | AR9: 0 | AS9: 0 | AT9: 0 | AU9: 0 | AV9: 0 | AW9: 0 | AX9: 0 | AY9: 0 | AZ9: 0 | BA9: 0 | BB9: 0 | BC9: 0 | BD9: 0 | BE9: 0
A10: t2val_mat_0 | B10: 0 | C10: 0 | D10: 0 | E10: 0 | F10: 0 | G10: 0 | H10: 0 | I10: 0 | J10: 0 | K10: 0 | L10: 0 | M10: 0 | N10: 0 | O10: 0 | P10: 0 | Q10: 0 | R10: 0 | S10: 0 | T10: 0 | U10: 0 | V10: 0 | W10: 0 | X10: 0 | Y10: 0 | Z10: 0 | AA10: 0 | AB10: 0 | AC10: 0 | AD10: 0 | AE10: 0 | AF10: 0 | AG10: 0 | AH10: 0 | AI10: 0 | AJ10: 0 | AK10: 0 | AL10: 0 | AM10: 0 | AN10: 0 | AO10: 0 | AP10: 0 | AQ10: 0 | AR10: 0 | AS10: 0 | AT10: 0 | AU10: 0 | AV10: 0 | AW10: 0 | AX10: 0 | AY10: 0 | AZ10: 0 | BA10: 0 | BB10: 0 | BC10: 0 | BD10: 0 | BE10: 0
A11: t2val_mat_2 | B11: 0 | C11: 0 | D11: 0 | E11: 0 | F11: 0 | G11: 0 | H11: 0 | I11: 0 | J11: 0 | K11: 0 | L11: 0 | M11: 0 | N11: 0 | O11: 0 | P11: 0 | Q11: 0 | R11: 0 | S11: 0 | T11: 0 | U11: 0 | V11: 0 | W11: 0 | X11: 0 | Y11: 0 | Z11: 0 | AA11: 0 | AB11: 0 | AC11: 0 | AD11: 0 | AE11: 0 | AF11: 0 | AG11: 0 | AH11: 0 | AI11: 0 | AJ11: 0 | AK11: 0 | AL11: 0 | AM11: 0 | AN11: 0 | AO11: 0 | AP11: 0 | AQ11: 0 | AR11: 0 | AS11: 0 | AT11: 0 | AU11: 0 | AV11: 0 | AW11: 0 | AX11: 0 | AY11: 0 | AZ11: 0 | BA11: 0 | BB11: 0 | BC11: 0 | BD11: 0 | BE11: 0

Sheet Production
A1: _date_ | B1: 42005 | C1: 42370 | D1: 42736 | E1: 43101 | F1: 43466 | G1: 43831 | H1: 44197 | I1: 44562 | J1: 44927 | K1: 45292 | L1: 45658 | M1: 46023 | N1: 46388 | O1: 46753 | P1: 47119 | Q1: 47484 | R1: 47849 | S1: 48214 | T1: 48580 | U1: 48945 | V1: 49310 | W1: 49675 | X1: 50041 | Y1: 50406 | Z1: 50771 | AA1: 51136 | AB1: 51502 | AC1: 51867 | AD1: 52232 | AE1: 52597 | AF1: 52963 | AG1: 53328 | AH1: 53693 | AI1: 54058 | AJ1: 54424 | AK1: 54789 | AL1: 55154 | AM1: 55519 | AN1: 55885 | AO1: 56250 | AP1: 56615 | AQ1: 56980 | AR1: 57346 | AS1: 57711 | AT1: 58076 | AU1: 58441 | AV1: 58807 | AW1: 59172 | AX1: 59537 | AY1: 59902 | AZ1: 60268 | BA1: 60633 | BB1: 60998 | BC1: 61363 | BD1: 61729 | BE1: 62094
A2: y_2 | B2: 3854754.7 | C2: 3897709.5 | D2: 3945032.4 | E2: 3995958.7 | F2: 4050429.8 | G2: 4108101.8 | H2: 4166197 | I2: 4226197.2 | J2: 4288121.1 | K2: 4351916.6 | L2: 4422069.3 | M2: 4490979.4 | N2: 4561178.5 | O2: 4632823.6 | P2: 4705999.1 | Q2: 4780790.1 | R2: 4857284.5 | S2: 4935585.1 | T2: 5015798.6 | U2: 5098026 | V2: 5178980.3 | W2: 5264371.9 | X2: 5352392 | Y2: 5443007.9 | Z2: 5536259 | AA2: 5622320.4 | AB2: 5712879.2 | AC2: 5805482.3 | AD2: 5900281.6 | AE2: 5997485.2 | AF2: 6097285.9 | AG2: 6199845.8 | AH2: 6305290.8 | AI2: 6413723.2 | AJ2: 6525231.9 | AK2: 6639889.6 | AL2: 6754635.2 | AM2: 6870848.1 | AN2: 6988621.5 | AO2: 7108026.3 | AP2: 7229144.4 | AQ2: 7352063.7 | AR2: 7476860.8 | AS2: 7603597.2 | AT2: 7732320 | AU2: 7863066 | AV2: 7996109.3 | AW2: 8131334.2 | AX2: 8268746.7 | AY2: 8408359.6 | AZ2: 8550190.9 | BA2: 8694272.5 | BB2: 8840634.7 | BC2: 8989308.8 | BD2: 9140327.6 | BE2: 9293727.1
A3: y_0 | B3: 3854754.7 | C3: 3897709.2 | D3: 3945031.5 | E3: 3995956.9 | F3: 4050426.8 | G3: 4108097.5 | H3: 4166189.4 | I3: 4226182.9 | J3: 4288096.5 | K3: 4351878.4 | L3: 4422014.6 | M3: 4490918.3 | N3: 4561126.7 | O3: 4632796.2 | P3: 4706008.5 | Q3: 4780845.7 | R3: 4857416.3 | S3: 4935830.9 | T3: 5016193.7 | U3: 5098599.9 | V3: 5179756.3 | W3: 5265389.1 | X3: 5353693.9 | Y3: 5444635.3 | Z3: 5538247 | AA3: 5624693.6 | AB3: 5715668.3 | AC3: 5808716.8 | AD3: 5903989.2 | AE3: 6001691.1 | AF3: 6102013 | AG3: 6205120.4 | AH3: 6311139.6 | AI3: 6420171.1 | AJ3: 6532301.7 | AK3: 6647601.8 | AL3: 6762995.1 | AM3: 6879857.7 | AN3: 6998281.9 | AO3: 7118339.1 | AP3: 7240111.8 | AQ3: 7363686.9 | AR3: 7489140.5 | AS3: 7616533.6 | AT3: 7745912.9 | AU3: 7877314.9 | AV3: 8011002.6 | AW3: 8146856.2 | AX3: 8284883.1 | AY3: 8425099 | AZ3: 8567524.9 | BA3: 8712181.9 | BB3: 8859098.2 | BC3: 9008308 | BD3: 9159849.1 | BE3: 9313761.8
A4: y_sagr_2 | B4: 81770.816 | C4: 82352.926 | D4: 83061.719 | E4: 83911.757 | F4: 84897.839 | G4: 86002.299 | H4: 87157.556 | I4: 88376.851 | J4: 89653.773 | K4: 90982.356 | L4: 92446.697 | M4: 93904.671 | N4: 95391.87 | O4: 96909.127 | P4: 98456.509 | Q4: 100034.66 | R4: 101644.72 | S4: 103288.23 | T4: 104967.01 | U4: 106682.9 | V4: 108371.61 | W4: 110137.59 | X4: 111954.16 | Y4: 113820.88 | Z4: 115738.52 | AA4: 117515.19 | AB4: 119357.91 | AC4: 121233.96 | AD4: 123148.64 | AE4: 125108.05 | AF4: 127117.46 | AG4: 129181.05 | AH4: 131301.91 | AI4: 133482.33 | AJ4: 135724.14 | AK4: 138028.71 | AL4: 140337.68 | AM4: 142672.16 | AN4: 145034.28 | AO4: 147425.91 | AP4: 149849.26 | AQ4: 152306.61 | AR4: 154800.01 | AS4: 157331.08 | AT4: 159901.11 | AU4: 162511.14 | AV4: 165166.83 | AW4: 167866.91 | AX4: 170611.79 | AY4: 173402 | AZ4: 176238.18 | BA4: 179121.3 | BB4: 182052.39 | BC4: 185032.44 | BD4: 188062.5 | BE4: 191143.62
A5: y_sagr_0 | B5: 81770.816 | C5: 82352.93 | D5: 83061.719 | E5: 83911.743 | F5: 84897.804 | G5: 86002.242 | H5: 87157.555 | I5: 88376.836 | J5: 89653.6 | K5: 90981.875 | L5: 92445.772 | M5: 93903.212 | N5: 95390.265 | O5: 96907.908 | P5: 98456.17 | Q5: 100035.6 | R5: 101647.42 | S5: 103293.8 | T5: 104976.71 | U5: 106697.86 | V5: 108392.74 | W5: 110165.85 | X5: 111990.92 | Y5: 113867.58 | Z5: 115796.42 | AA5: 117585.22 | AB5: 119441.07 | AC5: 121331.26 | AD5: 123261.1 | AE5: 125236.61 | AF5: 127263.02 | AG5: 129344.55 | AH5: 131484.4 | AI5: 133684.89 | AJ5: 135947.82 | AK5: 138274.55 | AL5: 140606.37 | AM5: 142964.3 | AN5: 145350.46 | AO5: 147766.78 | AP5: 150215.53 | AQ5: 152699.04 | AR5: 155219.39 | AS5: 157778.26 | AT5: 160376.98 | AU5: 163016.65 | AV5: 165702.75 | AW5: 168433.87 | AX5: 171210.47 | AY5: 174033.2 | AZ5: 176902.84 | BA5: 179820.19 | BB5: 182786.15 | BC5: 185801.83 | BD5: 188868.42 | BE5: 191987.15
A6: y_sfor_2 | B6: 6535.3702 | C6: 6519.1746 | D6: 6486.1068 | E6: 6451.9393 | F6: 6421.995 | G6: 6396.1814 | H6: 6374.7714 | I6: 6359.9158 | J6: 6350.8975 | K6: 6346.5173 | L6: 6350.3644 | M6: 6353.5489 | N6: 6357.9272 | O6: 6363.7364 | P6: 6370.9787 | Q6: 6379.5871 | R6: 6389.0767 | S6: 6399.6333 | T6: 6411.3332 | U6: 6424.2039 | V6: 6435.0518 | W6: 6449.2438 | X6: 6465.2453 | Y6: 6482.7325 | Z6: 6501.584 | AA6: 6512.7809 | AB6: 6527.2583 | AC6: 6543.3376 | AD6: 6560.8185 | AE6: 6579.6448 | AF6: 6599.8176 | AG6: 6621.4544 | AH6: 6644.5241 | AI6: 6669.0261 | AJ6: 6694.9735 | AK6: 6722.3815 | AL6: 6749.7467 | AM6: 6777.8944 | AN6: 6806.902 | AO6: 6836.7873 | AP6: 6867.5565 | AQ6: 6899.349 | AR6: 6932.1 | AS6: 6965.7876 | AT6: 7000.4117 | AU6: 7035.9822 | AV6: 7073.1304 | AW6: 7111.5023 | AX6: 7150.9686 | AY6: 7191.483 | AZ6: 7233.0361 | BA6: 7275.901 | BB6: 7319.9399 | BC6: 7365.0971 | BD6: 7411.3575 | BE6: 7458.7241
A7: y_sfor_0 | B7: 6535.3702 | C7: 6519.1283 | D7: 6485.9932 | E7: 6451.7479 | F7: 6421.7099 | G7: 6395.7817 | H7: 6373.6833 | I7: 6357.9025 | J7: 6347.941 | K7: 6342.6872 | L7: 6345.7446 | M7: 6349.6813 | N7: 6355.4627 | O7: 6362.9058 | P7: 6371.8332 | Q7: 6382.1105 | R7: 6395.4748 | S7: 6410.7899 | T7: 6427.5238 | U7: 6445.4534 | V7: 6461.2861 | W7: 6482.0224 | X7: 6505.172 | Y7: 6529.9768 | Z7: 6556.1406 | AA7: 6574.5138 | AB7: 6596.5589 | AC7: 6620.3273 | AD7: 6645.5017 | AE7: 6671.9833 | AF7: 6699.7642 | AG7: 6729.3262 | AH7: 6760.4351 | AI7: 6792.9996 | AJ7: 6826.9982 | AK7: 6862.4365 | AL7: 6897.5022 | AM7: 6933.1917 | AN7: 6969.6648 | AO7: 7006.9759 | AP7: 7045.1466 | AQ7: 7084.3183 | AR7: 7124.4289 | AS7: 7165.457 | AT7: 7207.4021 | AU7: 7250.2738 | AV7: 7294.3121 | AW7: 7339.3801 | AX7: 7385.4511 | AY7: 7432.5237 | AZ7: 7480.6077 | BA7: 7529.532 | BB7: 7579.4214 | BC7: 7630.3427 | BD7: 7682.3332 | BE7: 7735.417
A8: y_sfoo_2 | B8: 157694.98 | C8: 159128.24 | D8: 160764.14 | E8: 162630.67 | F8: 164724.77 | G8: 167020.8 | H8: 169396.48 | I8: 171878.42 | J8: 174458.67 | K8: 177129.59 | L8: 180053.28 | M8: 182969.52 | N8: 185940.54 | O8: 188967.67 | P8: 192051.46 | Q8: 195193.61 | R8: 198396.92 | S8: 201664.56 | T8: 205000.2 | U8: 208407.49 | V8: 211764.47 | W8: 215264.26 | X8: 218861.19 | Y8: 222555.46 | Z8: 226348.66 | AA8: 229876.44 | AB8: 233516.84 | AC8: 237214.98 | AD8: 240983.39 | AE8: 244835.13 | AF8: 248781.26 | AG8: 252830.44 | AH8: 256989.1 | AI8: 261262.03 | AJ8: 265652.97 | AK8: 270164.81 | AL8: 274687.78 | AM8: 279258 | AN8: 283879.12 | AO8: 288555.06 | AP8: 293290.47 | AQ8: 298089.95 | AR8: 302957.47 | AS8: 307896.08 | AT8: 312908.08 | AU8: 317995.28 | AV8: 323168.03 | AW8: 328424.04 | AX8: 333764.01 | AY8: 339188.85 | AZ8: 344699.74 | BA8: 350298.37 | BB8: 355986.73 | BC8: 361766.78 | BD8: 367640.62 | BE8: 373610.45
A9: y_sfoo_0 | B9: 157694.98 | C9: 159128.26 | D9: 160764.18 | E9: 162630.73 | F9: 164724.84 | G9: 167020.9 | H9: 169396.91 | I9: 171879.18 | J9: 174459.58 | K9: 177130.43 | L9: 180053.89 | M9: 182969.23 | N9: 185939.66 | O9: 188966.79 | P9: 192051.15 | Q9: 195194.33 | R9: 198398.44 | S9: 201668.02 | T9: 205007.06 | U9: 208419.05 | V9: 211781.76 | W9: 215287.84 | X9: 218892.57 | Y9: 222596.26 | Z9: 226400.34 | AA9: 229940.04 | AB9: 233593.29 | AC9: 237305.41 | AD9: 241088.91 | AE9: 244956.82 | AF9: 248920.12 | AG9: 252987.43 | AH9: 257165.4 | AI9: 261458.85 | AJ9: 265871.51 | AK9: 270406.22 | AL9: 274952.83 | AM9: 279547.26 | AN9: 284193.18 | AO9: 288894.63 | AP9: 293656.34 | AQ9: 298482.98 | AR9: 303378.58 | AS9: 308346.28 | AT9: 313388.45 | AU9: 318506.98 | AV9: 323712.08 | AW9: 329001.22 | AX9: 334375.21 | AY9: 339835.15 | AZ9: 345382.44 | BA9: 351018.65 | BB9: 356745.56 | BC9: 362565.28 | BD9: 368480.18 | BE9: 374492.71
A10: y_sveh_2 | B10: 125718.96 | C10: 127855.06 | D10: 130282.43 | E10: 132655.27 | F10: 134914.79 | G10: 137074.21 | H10: 139058.94 | I10: 141015.45 | J10: 142975.26 | K10: 144955.77 | L10: 147174.88 | M10: 149233.47 | N10: 151314.67 | O10: 153428.09 | P10: 155579.65 | Q10: 157774.1 | R10: 160015.36 | S10: 162307.46 | T10: 164654.22 | U10: 167059 | V10: 169370.58 | W10: 171890.3 | X10: 174486.82 | Y10: 177157.01 | Z10: 179900.92 | AA10: 182271.3 | AB10: 184921.73 | AC10: 187660.53 | AD10: 190486.95 | AE10: 193401.81 | AF10: 196406.14 | AG10: 199501 | AH10: 202687.18 | AI10: 205965.64 | AJ10: 209337.7 | AK10: 212804.54 | AL10: 216223.58 | AM10: 219692.4 | AN10: 223215.78 | AO10: 226797.12 | AP10: 230439.8 | AQ10: 234147.35 | AR10: 237922.97 | AS10: 241769.47 | AT10: 245689.24 | AU10: 249684.34 | AV10: 253767.5 | AW10: 257931.1 | AX10: 262176.11 | AY10: 266503.67 | AZ10: 270915.04 | BA10: 275411.87 | BB10: 279995.67 | BC10: 284667.76 | BD10: 289429.4 | BE10: 294281.8
A11: y_sveh_0 | B11: 125718.96 | C11: 127855.05 | D11: 130282.38 | E11: 132655.17 | F11: 134914.62 | G11: 137073.95 | H11: 139058.47 | I11: 141014.56 | J11: 142973.75 | K11: 144953.45 | L11: 147171.59 | M11: 149229.67 | N11: 151311.17 | O11: 153425.67 | P11: 155578.96 | Q11: 157775.68 | R11: 160020.75 | S11: 162318.65 | T11: 164673.16 | U11: 167087.41 | V11: 169409.9 | W11: 171942.8 | X11: 174555.08 | Y11: 177243.55 | Z11: 180008.1 | AA11: 182400.92 | AB11: 185076.18 | AC11: 187842.13 | AD11: 190698.03 | AE11: 193644.66 | AF11: 196683.03 | AG11: 199814.43 | AH11: 203039.78 | AI11: 206360.07 | AJ11: 209776.61 | AK11: 213290.57 | AL11: 216758.66 | AM11: 220278.47 | AN11: 223854.79 | AO11: 227491.12 | AP11: 231190.95 | AQ11: 234957.83 | AR11: 238795.06 | AS11: 242705.47 | AT11: 246691.51 | AU11: 250755.3 | AV11: 254909.15 | AW11: 259145.24 | AX11: 263464.6 | AY11: 267868.51 | AZ11: 272358.36 | BA11: 276935.38 | BB11: 281600.92 | BC11: 286356.39 | BD11: 291203.18 | BE11: 296142.67
A12: y_sgla_2 | B12: 22109.365 | C12: 22351.361 | D12: 22617.56 | E12: 22906.274 | F12: 23217.518 | G12: 23549.367 | H12: 23888.128 | I12: 24238.981 | J12: 24601.921 | K12: 24976.692 | L12: 25384.54 | M12: 25792.056 | N12: 26208.598 | O12: 26635.19 | P12: 27072.559 | Q12: 27521.433 | R12: 27982.543 | S12: 28456.69 | T12: 28944.705 | U12: 29447.392 | V12: 29949.514 | W12: 30476.539 | X12: 31022.27 | Y12: 31586.759 | Z12: 32170.379 | AA12: 32726.766 | AB12: 33305.929 | AC12: 33899.938 | AD12: 34509.766 | AE12: 35136.567 | AF12: 35781.419 | AG12: 36445.263 | AH12: 37128.86 | AI12: 37832.844 | AJ12: 38557.765 | AK12: 39304.081 | AL12: 40057.075 | AM12: 40821.261 | AN12: 41596.66 | AO12: 42383.277 | AP12: 43181.275 | AQ12: 43990.938 | AR12: 44812.554 | AS12: 45646.345 | AT12: 46492.451 | AU12: 47350.927 | AV12: 48222.967 | AW12: 49108.006 | AX12: 50005.867 | AY12: 50916.376 | AZ12: 51839.369 | BA12: 52774.763 | BB12: 53722.473 | BC12: 54682.407 | BD12: 55654.486 | BE12: 56638.647
... A67: y_seot_0 | B67: 109.70735 | C67: 110.42493 | D67: 110.92897 | E67: 111.4125 | F67: 111.95372 | G67: 112.56348 | H67: 113.20826 | I67: 113.9177 | J67: 114.68515 | K67: 115.5003 | L67: 116.44954 | M67: 117.38496 | N67: 118.33921 | O67: 119.3162 | P67: 120.31654 | Q67: 121.34076 | R67: 122.40533 | S67: 123.50341 | T67: 124.63282 | U67: 125.79389 | V67: 126.91935 | W67: 128.13563 | X67: 129.40741 | Y67: 130.72726 | Z67: 132.0938 | AA67: 133.30938 | AB67: 134.6044 | AC67: 135.94593 | AD67: 137.33173 | AE67: 138.76411 | AF67: 140.24624 | AG67: 141.78475 | AH67: 143.38014 | AI67: 145.03338 | AJ67: 146.74562 | AK67: 148.51783 | AL67: 150.29687 | AM67: 152.10544 | AN67: 153.94683 | AO67: 155.82109 | AP67: 157.72786 | AQ67: 159.66813 | AR67: 161.64173 | AS67: 163.64911 | AT67: 165.69095 | AU67: 167.76806 | AV67: 169.88618 | AW67: 172.04348 | AX67: 174.24017 | AY67: 176.47687 | AZ67: 178.75427 | BA67: 181.07161 | BB67: 183.43028 | BC67: 185.83128 | BD67: 188.2754 | BE67: 190.76332

Sheet Capital
A1: _date_ | B1: 42005 | C1: 42370 | D1: 42736 | E1: 43101 | F1: 43466 | G1: 43831 | H1: 44197 | I1: 44562 | J1: 44927 | K1: 45292 | L1: 45658 | M1: 46023 | N1: 46388 | O1: 46753 | P1: 47119 | Q1: 47484 | R1: 47849 | S1: 48214 | T1: 48580 | U1: 48945 | V1: 49310 | W1: 49675 | X1: 50041 | Y1: 50406 | Z1: 50771 | AA1: 51136 | AB1: 51502 | AC1: 51867 | AD1: 52232 | AE1: 52597 | AF1: 52963 | AG1: 53328 | AH1: 53693 | AI1: 54058 | AJ1: 54424 | AK1: 54789 | AL1: 55154 | AM1: 55519 | AN1: 55885 | AO1: 56250 | AP1: 56615 | AQ1: 56980 | AR1: 57346 | AS1: 57711 | AT1: 58076 | AU1: 58441 | AV1: 58807 | AW1: 59172 | AX1: 59537 | AY1: 59902 | AZ1: 60268 | BA1: 60633 | BB1: 60998 | BC1: 61363 | BD1: 61729 | BE1: 62094
A2: f_k_2 | B2: 5222033.8 | C2: 5280606.7 | D2: 5340340.3 | E2: 5401585.7 | F2: 5464654.4 | G2: 5529804.6 | H2: 5597063.2 | I2: 5666493.7 | J2: 5738182.2 | K2: 5812222.6 | L2: 5889053 | M2: 5968653.2 | N2: 6051037.6 | O2: 6136248.3 | P2: 6224344.8 | Q2: 6315399.3 | R2: 6409486.3 | S2: 6506698.3 | T2: 6607137.2 | U2: 6710913 | V2: 6817885.1 | W2: 6928255 | X2: 7042207.6 | Y2: 7159910.6 | Z2: 7281523.4 | AA2: 7406444.1 | AB2: 7534694.2 | AC2: 7666331.3 | AD2: 7801428.8 | AE2: 7940076.4 | AF2: 8082379.4 | AG2: 8228458.9 | AH2: 8378441.9 | AI2: 8532461 | AJ2: 8690652.5 | AK2: 8853154.4 | AL2: 9019887.2 | AM2: 9190748.3 | AN2: 9365643.9 | AO2: 9544486.9 | AP2: 9727199.4 | AQ2: 9913719.5 | AR2: 10103989 | AS2: 10297958 | AT2: 10495578 | AU2: 10696805 | AV2: 10901633 | AW2: 11110034 | AX2: 11321969 | AY2: 11537398 | AZ2: 11756275 | BA2: 11978568 | BB2: 12204228 | BC2: 12433207 | BD2: 12665454 | BE2: 12900920
A3: f_k_0 | B3: 5222033.8 | C3: 5280606.1 | D3: 5340338.5 | E3: 5401582 | F3: 5464648.2 | G3: 5529795.1 | H3: 5597044.3 | I3: 5666459 | J3: 5738124.5 | K3: 5812134.5 | L3: 5888926.6 | M3: 5968506.7 | N3: 6050891.7 | O3: 6136126.5 | P3: 6224272.5 | Q3: 6315403.4 | R3: 6409640.5 | S3: 6507081.2 | T3: 6607832 | U3: 6712005.8 | V3: 6819463.6 | W3: 6930445.4 | X3: 7045139.7 | Y3: 7163716.7 | Z3: 7286337 | AA3: 7412396.3 | AB3: 7541926.4 | AC3: 7674983.3 | AD3: 7811637.9 | AE3: 7951977.2 | AF3: 8096102.6 | AG3: 8244141.4 | AH3: 8396216.8 | AI3: 8552457.7 | AJ3: 8712995.8 | AK3: 8877964 | AL3: 9047260.1 | AM3: 9220771.9 | AN3: 9398395.2 | AO3: 9580032.9 | AP3: 9765597.1 | AQ3: 9955014.7 | AR3: 10148218 | AS3: 10345145 | AT3: 10545741 | AU3: 10749950 | AV3: 10957736 | AW3: 11169058 | AX3: 11383868 | AY3: 11602114 | AZ3: 11823740 | BA3: 12048683 | BB3: 12276884 | BC3: 12508283 | BD3: 12742824 | BE3: 12980452
A4: f_k_sagr_2 | B4: 47194.662 | C4: 47708.334 | D4: 48216.502 | E4: 48725.067 | F4: 49240.686 | G4: 49769.239 | H4: 50313.721 | I4: 50876.656 | J4: 51460.159 | K4: 52065.966 | L4: 52698.638 | M4: 53358.36 | N4: 54045.314 | O4: 54759.734 | P4: 55501.882 | Q4: 56272.046 | R4: 57070.45 | S4: 57897.477 | T4: 58753.581 | U4: 59639.276 | V4: 60552.764 | W4: 61495.303 | X4: 62468.114 | Y4: 63472.298 | Z4: 64508.895 | AA4: 65571.939 | AB4: 66660.963 | AC4: 67776.023 | AD4: 68917.472 | AE4: 70085.938 | AF4: 71282.291 | AG4: 72507.62 | AH4: 73763.096 | AI4: 75049.96 | AJ4: 76369.484 | AK4: 77722.95 | AL4: 79109.745 | AM4: 80528.9 | AN4: 81979.563 | AO4: 83461.019 | AP4: 84972.722 | AQ4: 86514.37 | AR4: 88085.749 | AS4: 89686.765 | AT4: 91317.414 | AU4: 92977.754 | AV4: 94668.326 | AW4: 96389.416 | AX4: 98141.293 | AY4: 99924.214 | AZ4: 101738.43 | BA4: 103584.39 | BB4: 105462.39 | BC4: 107372.73 | BD4: 109315.73 | BE4: 111291.75
A5: f_k_sagr_0 | B5: 47194.662 | C5: 47708.327 | D5: 48216.479 | E5: 48725.021 | F5: 49240.61 | G5: 49769.127 | H5: 50313.5 | I5: 50876.254 | J5: 51459.505 | K5: 52064.989 | L5: 52697.274 | M5: 53356.887 | N5: 54044.035 | O5: 54758.968 | P5: 55501.949 | Q5: 56273.254 | R5: 57073.668 | S5: 57903.575 | T5: 58763.399 | U5: 59653.596 | V5: 60572.282 | W5: 61521.095 | X5: 62501.162 | Y5: 63513.467 | Z5: 64558.905 | AA5: 65631.321 | AB5: 66730.215 | AC5: 67855.458 | AD5: 69007.206 | AE5: 70185.888 | AF5: 71392.171 | AG5: 72627.068 | AH5: 73891.556 | AI5: 75186.682 | AJ5: 76513.522 | AK5: 77873.165 | AL5: 79264.619 | AM5: 80686.703 | AN5: 82138.364 | AO5: 83618.704 | AP5: 85127.008 | AQ5: 86662.803 | AR5: 88225.732 | AS5: 89815.569 | AT5: 91432.185 | AU5: 93075.527 | AV5: 94745.784 | AW5: 96443.126 | AX5: 98167.725 | AY5: 99919.762 | AZ5: 101699.43 | BA5: 103506.86 | BB5: 105342.27 | BC5: 107205.96 | BD5: 109098.23 | BE5: 111019.45
A6: f_k_sfor_2 | B6: 1843.172 | C6: 1861.286 | D6: 1877.3589 | E6: 1891.291 | F6: 1903.2201 | G6: 1913.3372 | H6: 1921.8443 | I6: 1928.981 | J6: 1934.9796 | K6: 1940.0435 | L6: 1944.4217 | M6: 1948.2133 | N6: 1951.5093 | O6: 1954.4004 | P6: 1956.976 | Q6: 1959.3217 | R6: 1961.504 | S6: 1963.5938 | T6: 1965.6603 | U6: 1967.7706 | V6: 1969.935 | W6: 1972.2356 | X6: 1974.7472 | Y6: 1977.5323 | Z6: 1980.645 | AA6: 1983.984 | AB6: 1987.5897 | AC6: 1991.5123 | AD6: 1995.7983 | AE6: 2000.4888 | AF6: 2005.6209 | AG6: 2011.2323 | AH6: 2017.3555 | AI6: 2024.0201 | AJ6: 2031.2535 | AK6: 2039.0808 | AL6: 2047.5176 | AM6: 2056.5648 | AN6: 2066.2245 | AO6: 2076.4991 | AP6: 2087.3915 | AQ6: 2098.9104 | AR6: 2111.0612 | AS6: 2123.8483 | AT6: 2137.2753 | AU6: 2151.3452 | AV6: 2166.0836 | AW6: 2181.5008 | AX6: 2197.6017 | AY6: 2214.3876 | AZ6: 2231.858 | BA6: 2250.0237 | BB6: 2268.8863 | BC6: 2288.4448 | BD6: 2308.6961 | BE6: 2329.6365
A7: f_k_sfor_0 | B7: 1843.172 | C7: 1861.2846 | D7: 1877.354 | E7: 1891.2802 | F7: 1903.201 | G7: 1913.3069 | H7: 1921.7847 | I7: 1928.8671 | J7: 1934.7855 | K7: 1939.7456 | L7: 1944.0004 | M7: 1947.7023 | N7: 1950.9634 | O7: 1953.8826 | P7: 1956.5493 | Q7: 1959.0444 | R7: 1961.5047 | S7: 1964.0206 | T7: 1966.6622 | U7: 1969.4851 | V7: 1972.4825 | W7: 1975.7741 | X7: 1979.435 | Y7: 1983.5146 | Z7: 1988.0457 | AA7: 1992.9001 | AB7: 1998.1089 | AC7: 2003.7023 | AD7: 2009.7042 | AE7: 2016.1317 | AF7: 2022.9981 | AG7: 2030.3309 | AH7: 2038.1452 | AI7: 2046.4513 | AJ7: 2055.2563 | AK7: 2064.5655 | AL7: 2074.362 | AM7: 2084.6241 | AN7: 2095.335 | AO7: 2106.4814 | AP7: 2118.0522 | AQ7: 2130.0432 | AR7: 2142.4484 | AS7: 2155.262 | AT7: 2168.4784 | AU7: 2182.092 | AV7: 2196.1027 | AW7: 2210.508 | AX7: 2225.3043 | AY7: 2240.4874 | AZ7: 2256.053 | BA7: 2271.9894 | BB7: 2288.2904 | BC7: 2304.9517 | BD7: 2321.9705 | BE7: 2339.3449
A8: f_k_sfoo_2 | B8: 74494.565 | C8: 75316.819 | D8: 76141.187 | E8: 76975.424 | F8: 77827.974 | G8: 78706.243 | H8: 79613.468 | I8: 80552.333 | J8: 81525.114 | K8: 82533.714 | L8: 83584.602 | M8: 84677.853 | N8: 85813.453 | O8: 86991.456 | P8: 88211.963 | Q8: 89475.146 | R8: 90781.148 | S8: 92130.331 | T8: 93523.164 | U8: 94960.221 | V8: 96438.492 | W8: 97959.54 | X8: 99524.979 | Y8: 101136.3 | Z8: 102794.94 | AA8: 104491.48 | AB8: 106224.54 | AC8: 107993.66 | AD8: 109798.94 | AE8: 111641 | AF8: 113520.9 | AG8: 115440.07 | AH8: 117400.12 | AI8: 119402.79 | AJ8: 121449.89 | AK8: 123543.27 | AL8: 125681.76 | AM8: 127863.73 | AN8: 130087.71 | AO8: 132352.44 | AP8: 134656.97 | AQ8: 137000.71 | AR8: 139383.23 | AS8: 141804.29 | AT8: 144263.8 | AU8: 146761.74 | AV8: 149298.7 | AW8: 151875 | AX8: 154490.93 | AY8: 157146.77 | AZ8: 159842.81 | BA8: 162579.53 | BB8: 165357.27 | BC8: 168176.41 | BD8: 171037.35 | BE8: 173940.54
A9: f_k_sfoo_0 | B9: 74494.565 | C9: 75316.812 | D9: 76141.165 | E9: 76975.38 | F9: 77827.899 | G9: 78706.13 | H9: 79613.245 | I9: 80551.927 | J9: 81524.446 | K9: 82532.697 | L9: 83583.144 | M9: 84676.203 | N9: 85811.881 | O9: 86990.259 | P9: 88211.462 | Q9: 89475.67 | R9: 90783.656 | S9: 92135.821 | T9: 93532.682 | U9: 94974.841 | V9: 96459.298 | W9: 97988.132 | X9: 99562.981 | Y9: 101185.36 | Z9: 102856.71 | AA9: 104567.57 | AB9: 106316.71 | AC9: 108103.63 | AD9: 109928.41 | AE9: 111791.65 | AF9: 113694.36 | AG9: 115638.09 | AH9: 117624.42 | AI9: 119655.07 | AJ9: 121731.83 | AK9: 123856.53 | AL9: 126027.74 | AM9: 128243.76 | AN9: 130503.06 | AO9: 132804.33 | AP9: 135146.57 | AQ9: 137529.13 | AR9: 139951.57 | AS9: 142413.64 | AT9: 144915.2 | AU9: 147456.25 | AV9: 150037.1 | AW9: 152658.03 | AX9: 155319.34 | AY9: 158021.31 | AZ9: 160764.24 | BA9: 163548.34 | BB9: 166373.96 | BC9: 169241.5 | BD9: 172151.43 | BE9: 175104.24
A10: f_k_sveh_2 | B10: 401415.55 | C10: 406073.96 | D10: 411028.57 | E10: 416288.16 | F10: 421821.45 | G10: 427587.44 | H10: 433527.96 | I10: 439610.52 | J10: 445818.19 | K10: 452142.9 | L10: 458623.51 | M10: 465231.74 | N10: 471956.2 | O10: 478793.67 | P10: 485744.78 | Q10: 492812.35 | R10: 500000.09 | S10: 507313.47 | T10: 514759.01 | U10: 522344.02 | V10: 530045.12 | W10: 537891.07 | X10: 545899.77 | Y10: 554084.03 | Z10: 562454.66 | AA10: 570930.3 | AB10: 579536.35 | AC10: 588292.33 | AD10: 597214.34 | AE10: 606316.99 | AF10: 615614.15 | AG10: 625119.34 | AH10: 634845.31 | AI10: 644804.34 | AJ10: 655008.31 | AK10: 665468.73 | AL10: 676169.24 | AM10: 687101.91 | AN10: 698263.53 | AO10: 709653.08 | AP10: 721270.91 | AQ10: 733118.91 | AR10: 745199.5 | AS10: 757515.79 | AT10: 770071.44 | AU10: 782870.46 | AV10: 795920.88 | AW10: 809228.06 | AX10: 822796.83 | AY10: 836631.79 | AZ10: 850737.41 | BA10: 865119.22 | BB10: 879781.68 | BC10: 894729.22 | BD10: 909966.19 | BE10: 925496.89
A11: f_k_sveh_0 | B11: 401415.55 | C11: 406073.92 | D11: 411028.43 | E11: 416287.88 | F11: 421820.96 | G11: 427586.69 | H11: 433526.47 | I11: 439607.76 | J11: 445813.59 | K11: 452135.84 | L11: 458613.34 | M11: 465219.79 | N11: 471944.05 | O11: 478783.09 | P11: 485737.72 | Q11: 492810.88 | R11: 500009.92 | S11: 507340.74 | T11: 514810.25 | U11: 522426.04 | V11: 530164.91 | W11: 538058.67 | X11: 546125.6 | Y11: 554378.79 | Z11: 562829.31 | AA11: 571395.71 | AB11: 580104.37 | AC11: 588974.89 | AD11: 598023.41 | AE11: 607264.59 | AF11: 616712.3 | AG11: 626380.83 | AH11: 636283 | AI11: 646431.15 | AJ11: 656837.23 | AK11: 667512.81 | AL11: 678440.27 | AM11: 689611.42 | AN11: 701022.81 | AO11: 712673.21 | AP11: 724562.79 | AQ11: 736693.2 | AR11: 749066.72 | AS11: 761686.39 | AT11: 774555.79 | AU11: 787678.86 | AV11: 801062.11 | AW11: 814710.72 | AX11: 828629.37 | AY11: 842822.55 | AZ11: 857294.69 | BA11: 872049.65 | BB11: 887091.75 | BC11: 902425.34 | BD11: 918054.74 | BE11: 933984.27
A12: f_k_sgla_2 | B12: 16077.268 | C12: 16256.584 | D12: 16438.552 | E12: 16624.444 | F12: 16815.475 | G12: 17012.662 | H12: 17216.3 | I12: 17426.694 | J12: 17644.159 | K12: 17868.998 | L12: 18102.458 | M12: 18344.538 | N12: 18595.289 | O12: 18854.843 | P12: 19123.385 | Q12: 19401.154 | R12: 19688.402 | S12: 19985.447 | T12: 20292.647 | U12: 20610.393 | V12: 20938.388 | W12: 21277.263 | X12: 21627.642 | Y12: 21990.111 | Z12: 22365.234 | AA12: 22751.457 | AB12: 23148.866 | AC12: 23557.694 | AD12: 23978.231 | AE12: 24410.818 | AF12: 24855.834 | AG12: 25313.703 | AH12: 25784.862 | AI12: 26269.758 | AJ12: 26768.845 | AK12: 27282.575 | AL12: 27810.778 | AM12: 28353.151 | AN12: 28909.385 | AO12: 29479.18 | AP12: 30062.255 | AQ12: 30658.379 | AR12: 31267.336 | AS12: 31888.93 | AT12: 32522.981 | AU12: 33169.317 | AV12: 33827.886 | AW12: 34498.558 | AX12: 35181.183 | AY12: 35875.593 | AZ12: 36581.598 | BA12: 37299.047 | BB12: 38027.734 | BC12: 38767.44 | BD12: 39517.941 | BE12: 40279.008
... A67: f_k_seot_0 | B67: 65.148869 | C67: 65.867158 | D67: 66.567225 | E67: 67.24415 | F67: 67.899242 | G67: 68.536124 | H67: 69.157734 | I67: 69.767989 | J67: 70.370759 | K67: 70.969432 | L67: 71.570408 | M67: 72.175565 | N67: 72.786088 | O67: 73.403206 | P67: 74.028155 | Q67: 74.66215 | R67: 75.307393 | S67: 75.96533 | T67: 76.637241 | U67: 77.324324 | V67: 78.025171 | W67: 78.742736 | X67: 79.479253 | Y67: 80.236536 | Z67: 81.016168 | AA67: 81.81209 | AB67: 82.624842 | AC67: 83.455565 | AD67: 84.305497 | AE67: 85.175955 | AF67: 86.06836 | AG67: 86.984506 | AH67: 87.926037 | AI67: 88.894597 | AJ67: 89.891826 | AK67: 90.919342 | AL67: 91.976819 | AM67: 93.063854 | AN67: 94.180239 | AO67: 95.325816 | AP67: 96.500407 | AQ67: 97.703896 | AR67: 98.93609 | AS67: 100.1968 | AT67: 101.48584 | AU67: 102.80308 | AV67: 104.1486 | AW67: 105.52245 | AX67: 106.92467 | AY67: 108.35532 | AZ67: 109.81445 | BA67: 111.30203 | BB67: 112.81816 | BC67: 114.36297 | BD67: 115.93662 | BE67: 117.53929

Sheet Results
A1: NB : on crée ici une liste : - globale, qui fusionne les sorties des reportings 1, 2 et 3 - "rationalisée" : suppression des doublons, et regroupements par thématique On continue par la suite à avoir 2 Excels de reporting (un "energie", fusion des reportings 1 et 2), et un "économie" (reporting 3)), dans lesquels on copiera cet onglet "results" (généré automatiquement par EViews). --> puis voir à la fin si on peut pas importer les graphs et tableaux dans l'excel automatiquement généré (éviterait les copiés collés, mais à voir si ça prend trop de temps, et si c'est pas trop gros comme excel)
A2: Nom du bloc de variables utilisé dans le code | B2: Sous-bloc de variables pour plus de lisibilité dans le Excel | E2: Year | F2: =date!B3 -> rdag | G2: =date!C3 -> jdag | H2: =date!D3 -> ndag | I2: =date!E3 -> ndag | J2: =date!F3 -> sdag | K2: =date!G3 -> sdag | L2: =date!H3 -> jdag | M2: =date!I3 -> rdag | ... BI2: =date!BE3 -> sdag
A3: HYBRID | B3: AUTOMOBILES (thousands) | C3: TOTAL STOCK SHOCK | E3: AUTO_2 | F3: =VLOOKUP($E3,Hybrid!$1:$1048576,MATCH(DATE(F$2,1,1),Hybrid!$A$1:$LI$1),FALSE) -> #VALUE! | G3: =VLOOKUP($E3,Hybrid!$1:$1048576,MATCH(DATE(G$2,1,1),Hybrid!$A$1:$LI$1),FALSE) -> #VALUE! | H3: =VLOOKUP($E3,Hybrid!$1:$1048576,MATCH(DATE(H$2,1,1),Hybrid!$A$1:$LI$1),FALSE) -> #VALUE! | I3: =VLOOKUP($E3,Hybrid!$1:$1048576,MATCH(DATE(I$2,1,1),Hybrid!$A$1:$LI$1),FALSE) -> #VALUE! | J3: =VLOOKUP($E3,Hybrid!$1:$1048576,MATCH(DATE(J$2,1,1),Hybrid!$A$1:$LI$1),FALSE) -> #VALUE! | K3: =VLOOKUP($E3,Hybrid!$1:$1048576,MATCH(DATE(K$2,1,1),Hybrid!$A$1:$LI$1),FALSE) -> #VALUE! | L3: =VLOOKUP($E3,Hybrid!$1:$1048576,MATCH(DATE(L$2,1,1),Hybrid!$A$1:$LI$1),FALSE) -> #VALUE! | M3: =VLOOKUP($E3,Hybrid!$1:$1048576,MATCH(DATE(M$2,1,1),Hybrid!$A$1:$LI$1),FALSE) -> #VALUE! | ... BI3: =VLOOKUP($E3,Hybrid!$1:$1048576,MATCH(DATE(BI$2,1,1),Hybrid!$A$1:$LI$1),FALSE) -> #VALUE!
C4: OIL | E4: AUTO_cfut_2 | F4: =VLOOKUP($E4,Hybrid!$1:$1048576,MATCH(DATE(F$2,1,1),Hybrid!$A$1:$LI$1),FALSE) -> #VALUE! | G4: =VLOOKUP($E4,Hybrid!$1:$1048576,MATCH(DATE(G$2,1,1),Hybrid!$A$1:$LI$1),FALSE) -> #VALUE! | H4: =VLOOKUP($E4,Hybrid!$1:$1048576,MATCH(DATE(H$2,1,1),Hybrid!$A$1:$LI$1),FALSE) -> #VALUE! | I4: =VLOOKUP($E4,Hybrid!$1:$1048576,MATCH(DATE(I$2,1,1),Hybrid!$A$1:$LI$1),FALSE) -> #VALUE! | J4: =VLOOKUP($E4,Hybrid!$1:$1048576,MATCH(DATE(J$2,1,1),Hybrid!$A$1:$LI$1),FALSE) -> #VALUE! | K4: =VLOOKUP($E4,Hybrid!$1:$1048576,MATCH(DATE(K$2,1,1),Hybrid!$A$1:$LI$1),FALSE) -> #VALUE! | L4: =VLOOKUP($E4,Hybrid!$1:$1048576,MATCH(DATE(L$2,1,1),Hybrid!$A$1:$LI$1),FALSE) -> #VALUE! | M4: =VLOOKUP($E4,Hybrid!$1:$1048576,MATCH(DATE(M$2,1,1),Hybrid!$A$1:$LI$1),FALSE) -> #VALUE! | ... BI4: =VLOOKUP($E4,Hybrid!$1:$1048576,MATCH(DATE(BI$2,1,1),Hybrid!$A$1:$LI$1),FALSE) -> #VALUE!
D5: class A | E5: AUTO_ca_cfut_2 | F5: =VLOOKUP($E5,Hybrid!$1:$1048576,MATCH(DATE(F$2,1,1),Hybrid!$A$1:$LI$1),FALSE) -> #VALUE! | G5: =VLOOKUP($E5,Hybrid!$1:$1048576,MATCH(DATE(G$2,1,1),Hybrid!$A$1:$LI$1),FALSE) -> #VALUE! | H5: =VLOOKUP($E5,Hybrid!$1:$1048576,MATCH(DATE(H$2,1,1),Hybrid!$A$1:$LI$1),FALSE) -> #VALUE! | I5: =VLOOKUP($E5,Hybrid!$1:$1048576,MATCH(DATE(I$2,1,1),Hybrid!$A$1:$LI$1),FALSE) -> #VALUE! | J5: =VLOOKUP($E5,Hybrid!$1:$1048576,MATCH(DATE(J$2,1,1),Hybrid!$A$1:$LI$1),FALSE) -> #VALUE! | K5: =VLOOKUP($E5,Hybrid!$1:$1048576,MATCH(DATE(K$2,1,1),Hybrid!$A$1:$LI$1),FALSE) -> #VALUE! | L5: =VLOOKUP($E5,Hybrid!$1:$1048576,MATCH(DATE(L$2,1,1),Hybrid!$A$1:$LI$1),FALSE) -> #VALUE! | M5: =VLOOKUP($E5,Hybrid!$1:$1048576,MATCH(DATE(M$2,1,1),Hybrid!$A$1:$LI$1),FALSE) -> #VALUE! | ... BI5: =VLOOKUP($E5,Hybrid!$1:$1048576,MATCH(DATE(BI$2,1,1),Hybrid!$A$1:$LI$1),FALSE) -> #VALUE!
D6: class B | E6: AUTO_cb_cfut_2 | F6: =VLOOKUP($E6,Hybrid!$1:$1048576,MATCH(DATE(F$2,1,1),Hybrid!$A$1:$LI$1),FALSE) -> #VALUE! | G6: =VLOOKUP($E6,Hybrid!$1:$1048576,MATCH(DATE(G$2,1,1),Hybrid!$A$1:$LI$1),FALSE) -> #VALUE! | H6: =VLOOKUP($E6,Hybrid!$1:$1048576,MATCH(DATE(H$2,1,1),Hybrid!$A$1:$LI$1),FALSE) -> #VALUE! | I6: =VLOOKUP($E6,Hybrid!$1:$1048576,MATCH(DATE(I$2,1,1),Hybrid!$A$1:$LI$1),FALSE) -> #VALUE! | J6: =VLOOKUP($E6,Hybrid!$1:$1048576,MATCH(DATE(J$2,1,1),Hybrid!$A$1:$LI$1),FALSE) -> #VALUE! | K6: =VLOOKUP($E6,Hybrid!$1:$1048576,MATCH(DATE(K$2,1,1),Hybrid!$A$1:$LI$1),FALSE) -> #VALUE! | L6: =VLOOKUP($E6,Hybrid!$1:$1048576,MATCH(DATE(L$2,1,1),Hybrid!$A$1:$LI$1),FALSE) -> #VALUE! | M6: =VLOOKUP($E6,Hybrid!$1:$1048576,MATCH(DATE(M$2,1,1),Hybrid!$A$1:$LI$1),FALSE) -> #VALUE! | ... BI6: =VLOOKUP($E6,Hybrid!$1:$1048576,MATCH(DATE(BI$2,1,1),Hybrid!$A$1:$LI$1),FALSE) -> #VALUE!
D7: class C | E7: AUTO_cc_cfut_2 | F7: =VLOOKUP($E7,Hybrid!$1:$1048576,MATCH(DATE(F$2,1,1),Hybrid!$A$1:$LI$1),FALSE) -> #VALUE! | G7: =VLOOKUP($E7,Hybrid!$1:$1048576,MATCH(DATE(G$2,1,1),Hybrid!$A$1:$LI$1),FALSE) -> #VALUE! | H7: =VLOOKUP($E7,Hybrid!$1:$1048576,MATCH(DATE(H$2,1,1),Hybrid!$A$1:$LI$1),FALSE) -> #VALUE! | I7: =VLOOKUP($E7,Hybrid!$1:$1048576,MATCH(DATE(I$2,1,1),Hybrid!$A$1:$LI$1),FALSE) -> #VALUE! | J7: =VLOOKUP($E7,Hybrid!$1:$1048576,MATCH(DATE(J$2,1,1),Hybrid!$A$1:$LI$1),FALSE) -> #VALUE! | K7: =VLOOKUP($E7,Hybrid!$1:$1048576,MATCH(DATE(K$2,1,1),Hybrid!$A$1:$LI$1),FALSE) -> #VALUE! | L7: =VLOOKUP($E7,Hybrid!$1:$1048576,MATCH(DATE(L$2,1,1),Hybrid!$A$1:$LI$1),FALSE) -> #VALUE! | M7: =VLOOKUP($E7,Hybrid!$1:$1048576,MATCH(DATE(M$2,1,1),Hybrid!$A$1:$LI$1),FALSE) -> #VALUE! | ... BI7: =VLOOKUP($E7,Hybrid!$1:$1048576,MATCH(DATE(BI$2,1,1),Hybrid!$A$1:$LI$1),FALSE) -> #VALUE!
D8: class D | E8: AUTO_cd_cfut_2 | F8: =VLOOKUP($E8,Hybrid!$1:$1048576,MATCH(DATE(F$2,1,1),Hybrid!$A$1:$LI$1),FALSE) -> #VALUE! | G8: =VLOOKUP($E8,Hybrid!$1:$1048576,MATCH(DATE(G$2,1,1),Hybrid!$A$1:$LI$1),FALSE) -> #VALUE! | H8: =VLOOKUP($E8,Hybrid!$1:$1048576,MATCH(DATE(H$2,1,1),Hybrid!$A$1:$LI$1),FALSE) -> #VALUE! | I8: =VLOOKUP($E8,Hybrid!$1:$1048576,MATCH(DATE(I$2,1,1),Hybrid!$A$1:$LI$1),FALSE) -> #VALUE! | J8: =VLOOKUP($E8,Hybrid!$1:$1048576,MATCH(DATE(J$2,1,1),Hybrid!$A$1:$LI$1),FALSE) -> #VALUE! | K8: =VLOOKUP($E8,Hybrid!$1:$1048576,MATCH(DATE(K$2,1,1),Hybrid!$A$1:$LI$1),FALSE) -> #VALUE! | L8: =VLOOKUP($E8,Hybrid!$1:$1048576,MATCH(DATE(L$2,1,1),Hybrid!$A$1:$LI$1),FALSE) -> #VALUE! | M8: =VLOOKUP($E8,Hybrid!$1:$1048576,MATCH(DATE(M$2,1,1),Hybrid!$A$1:$LI$1),FALSE) -> #VALUE! | ... BI8: =VLOOKUP($E8,Hybrid!$1:$1048576,MATCH(DATE(BI$2,1,1),Hybrid!$A$1:$LI$1),FALSE) -> #VALUE!
D9: class E | E9: AUTO_ce_cfut_2 | F9: =VLOOKUP($E9,Hybrid!$1:$1048576,MATCH(DATE(F$2,1,1),Hybrid!$A$1:$LI$1),FALSE) -> #VALUE! | G9: =VLOOKUP($E9,Hybrid!$1:$1048576,MATCH(DATE(G$2,1,1),Hybrid!$A$1:$LI$1),FALSE) -> #VALUE! | H9: =VLOOKUP($E9,Hybrid!$1:$1048576,MATCH(DATE(H$2,1,1),Hybrid!$A$1:$LI$1),FALSE) -> #VALUE! | I9: =VLOOKUP($E9,Hybrid!$1:$1048576,MATCH(DATE(I$2,1,1),Hybrid!$A$1:$LI$1),FALSE) -> #VALUE! | J9: =VLOOKUP($E9,Hybrid!$1:$1048576,MATCH(DATE(J$2,1,1),Hybrid!$A$1:$LI$1),FALSE) -> #VALUE! | K9: =VLOOKUP($E9,Hybrid!$1:$1048576,MATCH(DATE(K$2,1,1),Hybrid!$A$1:$LI$1),FALSE) -> #VALUE! | L9: =VLOOKUP($E9,Hybrid!$1:$1048576,MATCH(DATE(L$2,1,1),Hybrid!$A$1:$LI$1),FALSE) -> #VALUE! | M9: =VLOOKUP($E9,Hybrid!$1:$1048576,MATCH(DATE(M$2,1,1),Hybrid!$A$1:$LI$1),FALSE) -> #VALUE! | ... BI9: =VLOOKUP($E9,Hybrid!$1:$1048576,MATCH(DATE(BI$2,1,1),Hybrid!$A$1:$LI$1),FALSE) -> #VALUE!
D10: class F | E10: AUTO_cf_cfut_2 | F10: =VLOOKUP($E10,Hybrid!$1:$1048576,MATCH(DATE(F$2,1,1),Hybrid!$A$1:$LI$1),FALSE) -> #VALUE! | G10: =VLOOKUP($E10,Hybrid!$1:$1048576,MATCH(DATE(G$2,1,1),Hybrid!$A$1:$LI$1),FALSE) -> #VALUE! | H10: =VLOOKUP($E10,Hybrid!$1:$1048576,MATCH(DATE(H$2,1,1),Hybrid!$A$1:$LI$1),FALSE) -> #VALUE! | I10: =VLOOKUP($E10,Hybrid!$1:$1048576,MATCH(DATE(I$2,1,1),Hybrid!$A$1:$LI$1),FALSE) -> #VALUE! | J10: =VLOOKUP($E10,Hybrid!$1:$1048576,MATCH(DATE(J$2,1,1),Hybrid!$A$1:$LI$1),FALSE) -> #VALUE! | K10: =VLOOKUP($E10,Hybrid!$1:$1048576,MATCH(DATE(K$2,1,1),Hybrid!$A$1:$LI$1),FALSE) -> #VALUE! | L10: =VLOOKUP($E10,Hybrid!$1:$1048576,MATCH(DATE(L$2,1,1),Hybrid!$A$1:$LI$1),FALSE) -> #VALUE! | M10: =VLOOKUP($E10,Hybrid!$1:$1048576,MATCH(DATE(M$2,1,1),Hybrid!$A$1:$LI$1),FALSE) -> #VALUE! | ... BI10: =VLOOKUP($E10,Hybrid!$1:$1048576,MATCH(DATE(BI$2,1,1),Hybrid!$A$1:$LI$1),FALSE) -> #VALUE!
D11: class G | E11: AUTO_cg_cfut_2 | F11: =VLOOKUP($E11,Hybrid!$1:$1048576,MATCH(DATE(F$2,1,1),Hybrid!$A$1:$LI$1),FALSE) -> #VALUE! | G11: =VLOOKUP($E11,Hybrid!$1:$1048576,MATCH(DATE(G$2,1,1),Hybrid!$A$1:$LI$1),FALSE) -> #VALUE! | H11: =VLOOKUP($E11,Hybrid!$1:$1048576,MATCH(DATE(H$2,1,1),Hybrid!$A$1:$LI$1),FALSE) -> #VALUE! | I11: =VLOOKUP($E11,Hybrid!$1:$1048576,MATCH(DATE(I$2,1,1),Hybrid!$A$1:$LI$1),FALSE) -> #VALUE! | J11: =VLOOKUP($E11,Hybrid!$1:$1048576,MATCH(DATE(J$2,1,1),Hybrid!$A$1:$LI$1),FALSE) -> #VALUE! | K11: =VLOOKUP($E11,Hybrid!$1:$1048576,MATCH(DATE(K$2,1,1),Hybrid!$A$1:$LI$1),FALSE) -> #VALUE! | L11: =VLOOKUP($E11,Hybrid!$1:$1048576,MATCH(DATE(L$2,1,1),Hybrid!$A$1:$LI$1),FALSE) -> #VALUE! | M11: =VLOOKUP($E11,Hybrid!$1:$1048576,MATCH(DATE(M$2,1,1),Hybrid!$A$1:$LI$1),FALSE) -> #VALUE! | ... BI11: =VLOOKUP($E11,Hybrid!$1:$1048576,MATCH(DATE(BI$2,1,1),Hybrid!$A$1:$LI$1),FALSE) -> #VALUE!
C12: ELEC | E12: AUTO_cele_2 | F12: =VLOOKUP($E12,Hybrid!$1:$1048576,MATCH(DATE(F$2,1,1),Hybrid!$A$1:$LI$1),FALSE) -> #VALUE! | G12: =VLOOKUP($E12,Hybrid!$1:$1048576,MATCH(DATE(G$2,1,1),Hybrid!$A$1:$LI$1),FALSE) -> #VALUE! | H12: =VLOOKUP($E12,Hybrid!$1:$1048576,MATCH(DATE(H$2,1,1),Hybrid!$A$1:$LI$1),FALSE) -> #VALUE! | I12: =VLOOKUP($E12,Hybrid!$1:$1048576,MATCH(DATE(I$2,1,1),Hybrid!$A$1:$LI$1),FALSE) -> #VALUE! | J12: =VLOOKUP($E12,Hybrid!$1:$1048576,MATCH(DATE(J$2,1,1),Hybrid!$A$1:$LI$1),FALSE) -> #VALUE! | K12: =VLOOKUP($E12,Hybrid!$1:$1048576,MATCH(DATE(K$2,1,1),Hybrid!$A$1:$LI$1),FALSE) -> #VALUE! | L12: =VLOOKUP($E12,Hybrid!$1:$1048576,MATCH(DATE(L$2,1,1),Hybrid!$A$1:$LI$1),FALSE) -> #VALUE! | M12: =VLOOKUP($E12,Hybrid!$1:$1048576,MATCH(DATE(M$2,1,1),Hybrid!$A$1:$LI$1),FALSE) -> #VALUE! | ... BI12: =VLOOKUP($E12,Hybrid!$1:$1048576,MATCH(DATE(BI$2,1,1),Hybrid!$A$1:$LI$1),FALSE) -> #VALUE!
D13: class A | E13: AUTO_ca_cele_2 | F13: =VLOOKUP($E13,Hybrid!$1:$1048576,MATCH(DATE(F$2,1,1),Hybrid!$A$1:$LI$1),FALSE) -> #VALUE! | G13: =VLOOKUP($E13,Hybrid!$1:$1048576,MATCH(DATE(G$2,1,1),Hybrid!$A$1:$LI$1),FALSE) -> #VALUE! | H13: =VLOOKUP($E13,Hybrid!$1:$1048576,MATCH(DATE(H$2,1,1),Hybrid!$A$1:$LI$1),FALSE) -> #VALUE! | I13: =VLOOKUP($E13,Hybrid!$1:$1048576,MATCH(DATE(I$2,1,1),Hybrid!$A$1:$LI$1),FALSE) -> #VALUE! | J13: =VLOOKUP($E13,Hybrid!$1:$1048576,MATCH(DATE(J$2,1,1),Hybrid!$A$1:$LI$1),FALSE) -> #VALUE! | K13: =VLOOKUP($E13,Hybrid!$1:$1048576,MATCH(DATE(K$2,1,1),Hybrid!$A$1:$LI$1),FALSE) -> #VALUE! | L13: =VLOOKUP($E13,Hybrid!$1:$1048576,MATCH(DATE(L$2,1,1),Hybrid!$A$1:$LI$1),FALSE) -> #VALUE! | M13: =VLOOKUP($E13,Hybrid!$1:$1048576,MATCH(DATE(M$2,1,1),Hybrid!$A$1:$LI$1),FALSE) -> #VALUE! | ... BI13: =VLOOKUP($E13,Hybrid!$1:$1048576,MATCH(DATE(BI$2,1,1),Hybrid!$A$1:$LI$1),FALSE) -> #VALUE!
D14: class B | E14: AUTO_cb_cele_2 | F14: =VLOOKUP($E14,Hybrid!$1:$1048576,MATCH(DATE(F$2,1,1),Hybrid!$A$1:$LI$1),FALSE) -> #VALUE! | G14: =VLOOKUP($E14,Hybrid!$1:$1048576,MATCH(DATE(G$2,1,1),Hybrid!$A$1:$LI$1),FALSE) -> #VALUE! | H14: =VLOOKUP($E14,Hybrid!$1:$1048576,MATCH(DATE(H$2,1,1),Hybrid!$A$1:$LI$1),FALSE) -> #VALUE! | I14: =VLOOKUP($E14,Hybrid!$1:$1048576,MATCH(DATE(I$2,1,1),Hybrid!$A$1:$LI$1),FALSE) -> #VALUE! | J14: =VLOOKUP($E14,Hybrid!$1:$1048576,MATCH(DATE(J$2,1,1),Hybrid!$A$1:$LI$1),FALSE) -> #VALUE! | K14: =VLOOKUP($E14,Hybrid!$1:$1048576,MATCH(DATE(K$2,1,1),Hybrid!$A$1:$LI$1),FALSE) -> #VALUE! | L14: =VLOOKUP($E14,Hybrid!$1:$1048576,MATCH(DATE(L$2,1,1),Hybrid!$A$1:$LI$1),FALSE) -> #VALUE! | M14: =VLOOKUP($E14,Hybrid!$1:$1048576,MATCH(DATE(M$2,1,1),Hybrid!$A$1:$LI$1),FALSE) -> #VALUE! | ... BI14: =VLOOKUP($E14,Hybrid!$1:$1048576,MATCH(DATE(BI$2,1,1),Hybrid!$A$1:$LI$1),FALSE) -> #VALUE!
D15: class C | E15: AUTO_cc_cele_2 | F15: =VLOOKUP($E15,Hybrid!$1:$1048576,MATCH(DATE(F$2,1,1),Hybrid!$A$1:$LI$1),FALSE) -> #VALUE! | G15: =VLOOKUP($E15,Hybrid!$1:$1048576,MATCH(DATE(G$2,1,1),Hybrid!$A$1:$LI$1),FALSE) -> #VALUE! | H15: =VLOOKUP($E15,Hybrid!$1:$1048576,MATCH(DATE(H$2,1,1),Hybrid!$A$1:$LI$1),FALSE) -> #VALUE! | I15: =VLOOKUP($E15,Hybrid!$1:$1048576,MATCH(DATE(I$2,1,1),Hybrid!$A$1:$LI$1),FALSE) -> #VALUE! | J15: =VLOOKUP($E15,Hybrid!$1:$1048576,MATCH(DATE(J$2,1,1),Hybrid!$A$1:$LI$1),FALSE) -> #VALUE! | K15: =VLOOKUP($E15,Hybrid!$1:$1048576,MATCH(DATE(K$2,1,1),Hybrid!$A$1:$LI$1),FALSE) -> #VALUE! | L15: =VLOOKUP($E15,Hybrid!$1:$1048576,MATCH(DATE(L$2,1,1),Hybrid!$A$1:$LI$1),FALSE) -> #VALUE! | M15: =VLOOKUP($E15,Hybrid!$1:$1048576,MATCH(DATE(M$2,1,1),Hybrid!$A$1:$LI$1),FALSE) -> #VALUE! | ... BI15: =VLOOKUP($E15,Hybrid!$1:$1048576,MATCH(DATE(BI$2,1,1),Hybrid!$A$1:$LI$1),FALSE) -> #VALUE!
D16: class D | E16: AUTO_cd_cele_2 | F16: =VLOOKUP($E16,Hybrid!$1:$1048576,MATCH(DATE(F$2,1,1),Hybrid!$A$1:$LI$1),FALSE) -> #VALUE! | G16: =VLOOKUP($E16,Hybrid!$1:$1048576,MATCH(DATE(G$2,1,1),Hybrid!$A$1:$LI$1),FALSE) -> #VALUE! | H16: =VLOOKUP($E16,Hybrid!$1:$1048576,MATCH(DATE(H$2,1,1),Hybrid!$A$1:$LI$1),FALSE) -> #VALUE! | I16: =VLOOKUP($E16,Hybrid!$1:$1048576,MATCH(DATE(I$2,1,1),Hybrid!$A$1:$LI$1),FALSE) -> #VALUE! | J16: =VLOOKUP($E16,Hybrid!$1:$1048576,MATCH(DATE(J$2,1,1),Hybrid!$A$1:$LI$1),FALSE) -> #VALUE! | K16: =VLOOKUP($E16,Hybrid!$1:$1048576,MATCH(DATE(K$2,1,1),Hybrid!$A$1:$LI$1),FALSE) -> #VALUE! | L16: =VLOOKUP($E16,Hybrid!$1:$1048576,MATCH(DATE(L$2,1,1),Hybrid!$A$1:$LI$1),FALSE) -> #VALUE! | M16: =VLOOKUP($E16,Hybrid!$1:$1048576,MATCH(DATE(M$2,1,1),Hybrid!$A$1:$LI$1),FALSE) -> #VALUE! | ... BI16: =VLOOKUP($E16,Hybrid!$1:$1048576,MATCH(DATE(BI$2,1,1),Hybrid!$A$1:$LI$1),FALSE) -> #VALUE!
D17: class E | E17: AUTO_ce_cele_2 | F17: =VLOOKUP($E17,Hybrid!$1:$1048576,MATCH(DATE(F$2,1,1),Hybrid!$A$1:$LI$1),FALSE) -> #VALUE! | G17: =VLOOKUP($E17,Hybrid!$1:$1048576,MATCH(DATE(G$2,1,1),Hybrid!$A$1:$LI$1),FALSE) -> #VALUE! | H17: =VLOOKUP($E17,Hybrid!$1:$1048576,MATCH(DATE(H$2,1,1),Hybrid!$A$1:$LI$1),FALSE) -> #VALUE! | I17: =VLOOKUP($E17,Hybrid!$1:$1048576,MATCH(DATE(I$2,1,1),Hybrid!$A$1:$LI$1),FALSE) -> #VALUE! | J17: =VLOOKUP($E17,Hybrid!$1:$1048576,MATCH(DATE(J$2,1,1),Hybrid!$A$1:$LI$1),FALSE) -> #VALUE! | K17: =VLOOKUP($E17,Hybrid!$1:$1048576,MATCH(DATE(K$2,1,1),Hybrid!$A$1:$LI$1),FALSE) -> #VALUE! | L17: =VLOOKUP($E17,Hybrid!$1:$1048576,MATCH(DATE(L$2,1,1),Hybrid!$A$1:$LI$1),FALSE) -> #VALUE! | M17: =VLOOKUP($E17,Hybrid!$1:$1048576,MATCH(DATE(M$2,1,1),Hybrid!$A$1:$LI$1),FALSE) -> #VALUE! | ... BI17: =VLOOKUP($E17,Hybrid!$1:$1048576,MATCH(DATE(BI$2,1,1),Hybrid!$A$1:$LI$1),FALSE) -> #VALUE!
D18: class F | E18: AUTO_cf_cele_2 | F18: =VLOOKUP($E18,Hybrid!$1:$1048576,MATCH(DATE(F$2,1,1),Hybrid!$A$1:$LI$1),FALSE) -> #VALUE! | G18: =VLOOKUP($E18,Hybrid!$1:$1048576,MATCH(DATE(G$2,1,1),Hybrid!$A$1:$LI$1),FALSE) -> #VALUE! | H18: =VLOOKUP($E18,Hybrid!$1:$1048576,MATCH(DATE(H$2,1,1),Hybrid!$A$1:$LI$1),FALSE) -> #VALUE! | I18: =VLOOKUP($E18,Hybrid!$1:$1048576,MATCH(DATE(I$2,1,1),Hybrid!$A$1:$LI$1),FALSE) -> #VALUE! | J18: =VLOOKUP($E18,Hybrid!$1:$1048576,MATCH(DATE(J$2,1,1),Hybrid!$A$1:$LI$1),FALSE) -> #VALUE! | K18: =VLOOKUP($E18,Hybrid!$1:$1048576,MATCH(DATE(K$2,1,1),Hybrid!$A$1:$LI$1),FALSE) -> #VALUE! | L18: =VLOOKUP($E18,Hybrid!$1:$1048576,MATCH(DATE(L$2,1,1),Hybrid!$A$1:$LI$1),FALSE) -> #VALUE! | M18: =VLOOKUP($E18,Hybrid!$1:$1048576,MATCH(DATE(M$2,1,1),Hybrid!$A$1:$LI$1),FALSE) -> #VALUE! | ... BI18: =VLOOKUP($E18,Hybrid!$1:$1048576,MATCH(DATE(BI$2,1,1),Hybrid!$A$1:$LI$1),FALSE) -> #VALUE!
D19: class G | E19: AUTO_cg_cele_2 | F19: =VLOOKUP($E19,Hybrid!$1:$1048576,MATCH(DATE(F$2,1,1),Hybrid!$A$1:$LI$1),FALSE) -> #VALUE! | G19: =VLOOKUP($E19,Hybrid!$1:$1048576,MATCH(DATE(G$2,1,1),Hybrid!$A$1:$LI$1),FALSE) -> #VALUE! | H19: =VLOOKUP($E19,Hybrid!$1:$1048576,MATCH(DATE(H$2,1,1),Hybrid!$A$1:$LI$1),FALSE) -> #VALUE! | I19: =VLOOKUP($E19,Hybrid!$1:$1048576,MATCH(DATE(I$2,1,1),Hybrid!$A$1:$LI$1),FALSE) -> #VALUE! | J19: =VLOOKUP($E19,Hybrid!$1:$1048576,MATCH(DATE(J$2,1,1),Hybrid!$A$1:$LI$1),FALSE) -> #VALUE! | K19: =VLOOKUP($E19,Hybrid!$1:$1048576,MATCH(DATE(K$2,1,1),Hybrid!$A$1:$LI$1),FALSE) -> #VALUE! | L19: =VLOOKUP($E19,Hybrid!$1:$1048576,MATCH(DATE(L$2,1,1),Hybrid!$A$1:$LI$1),FALSE) -> #VALUE! | M19: =VLOOKUP($E19,Hybrid!$1:$1048576,MATCH(DATE(M$2,1,1),Hybrid!$A$1:$LI$1),FALSE) -> #VALUE! | ... BI19: =VLOOKUP($E19,Hybrid!$1:$1048576,MATCH(DATE(BI$2,1,1),Hybrid!$A$1:$LI$1),FALSE) -> #VALUE!
C20: GAS | E20: AUTO_cgas_2 | F20: =VLOOKUP($E20,Hybrid!$1:$1048576,MATCH(DATE(F$2,1,1),Hybrid!$A$1:$LI$1),FALSE) -> #VALUE! | G20: =VLOOKUP($E20,Hybrid!$1:$1048576,MATCH(DATE(G$2,1,1),Hybrid!$A$1:$LI$1),FALSE) -> #VALUE! | H20: =VLOOKUP($E20,Hybrid!$1:$1048576,MATCH(DATE(H$2,1,1),Hybrid!$A$1:$LI$1),FALSE) -> #VALUE! | I20: =VLOOKUP($E20,Hybrid!$1:$1048576,MATCH(DATE(I$2,1,1),Hybrid!$A$1:$LI$1),FALSE) -> #VALUE! | J20: =VLOOKUP($E20,Hybrid!$1:$1048576,MATCH(DATE(J$2,1,1),Hybrid!$A$1:$LI$1),FALSE) -> #VALUE! | K20: =VLOOKUP($E20,Hybrid!$1:$1048576,MATCH(DATE(K$2,1,1),Hybrid!$A$1:$LI$1),FALSE) -> #VALUE! | L20: =VLOOKUP($E20,Hybrid!$1:$1048576,MATCH(DATE(L$2,1,1),Hybrid!$A$1:$LI$1),FALSE) -> #VALUE! | M20: =VLOOKUP($E20,Hybrid!$1:$1048576,MATCH(DATE(M$2,1,1),Hybrid!$A$1:$LI$1),FALSE) -> #VALUE! | ... BI20: =VLOOKUP($E20,Hybrid!$1:$1048576,MATCH(DATE(BI$2,1,1),Hybrid!$A$1:$LI$1),FALSE) -> #VALUE!
D21: class A | E21: AUTO_ca_cgas_2 | F21: =VLOOKUP($E21,Hybrid!$1:$1048576,MATCH(DATE(F$2,1,1),Hybrid!$A$1:$LI$1),FALSE) -> #VALUE! | G21: =VLOOKUP($E21,Hybrid!$1:$1048576,MATCH(DATE(G$2,1,1),Hybrid!$A$1:$LI$1),FALSE) -> #VALUE! | H21: =VLOOKUP($E21,Hybrid!$1:$1048576,MATCH(DATE(H$2,1,1),Hybrid!$A$1:$LI$1),FALSE) -> #VALUE! | I21: =VLOOKUP($E21,Hybrid!$1:$1048576,MATCH(DATE(I$2,1,1),Hybrid!$A$1:$LI$1),FALSE) -> #VALUE! | J21: =VLOOKUP($E21,Hybrid!$1:$1048576,MATCH(DATE(J$2,1,1),Hybrid!$A$1:$LI$1),FALSE) -> #VALUE! | K21: =VLOOKUP($E21,Hybrid!$1:$1048576,MATCH(DATE(K$2,1,1),Hybrid!$A$1:$LI$1),FALSE) -> #VALUE! | L21: =VLOOKUP($E21,Hybrid!$1:$1048576,MATCH(DATE(L$2,1,1),Hybrid!$A$1:$LI$1),FALSE) -> #VALUE! | M21: =VLOOKUP($E21,Hybrid!$1:$1048576,MATCH(DATE(M$2,1,1),Hybrid!$A$1:$LI$1),FALSE) -> #VALUE! | ... BI21: =VLOOKUP($E21,Hybrid!$1:$1048576,MATCH(DATE(BI$2,1,1),Hybrid!$A$1:$LI$1),FALSE) -> #VALUE!
D22: class B | E22: AUTO_cb_cgas_2 | F22: =VLOOKUP($E22,Hybrid!$1:$1048576,MATCH(DATE(F$2,1,1),Hybrid!$A$1:$LI$1),FALSE) -> #VALUE! | G22: =VLOOKUP($E22,Hybrid!$1:$1048576,MATCH(DATE(G$2,1,1),Hybrid!$A$1:$LI$1),FALSE) -> #VALUE! | H22: =VLOOKUP($E22,Hybrid!$1:$1048576,MATCH(DATE(H$2,1,1),Hybrid!$A$1:$LI$1),FALSE) -> #VALUE! | I22: =VLOOKUP($E22,Hybrid!$1:$1048576,MATCH(DATE(I$2,1,1),Hybrid!$A$1:$LI$1),FALSE) -> #VALUE! | J22: =VLOOKUP($E22,Hybrid!$1:$1048576,MATCH(DATE(J$2,1,1),Hybrid!$A$1:$LI$1),FALSE) -> #VALUE! | K22: =VLOOKUP($E22,Hybrid!$1:$1048576,MATCH(DATE(K$2,1,1),Hybrid!$A$1:$LI$1),FALSE) -> #VALUE! | L22: =VLOOKUP($E22,Hybrid!$1:$1048576,MATCH(DATE(L$2,1,1),Hybrid!$A$1:$LI$1),FALSE) -> #VALUE! | M22: =VLOOKUP($E22,Hybrid!$1:$1048576,MATCH(DATE(M$2,1,1),Hybrid!$A$1:$LI$1),FALSE) -> #VALUE! | ... BI22: =VLOOKUP($E22,Hybrid!$1:$1048576,MATCH(DATE(BI$2,1,1),Hybrid!$A$1:$LI$1),FALSE) -> #VALUE!
D23: class C | E23: AUTO_cc_cgas_2 | F23: =VLOOKUP($E23,Hybrid!$1:$1048576,MATCH(DATE(F$2,1,1),Hybrid!$A$1:$LI$1),FALSE) -> #VALUE! | G23: =VLOOKUP($E23,Hybrid!$1:$1048576,MATCH(DATE(G$2,1,1),Hybrid!$A$1:$LI$1),FALSE) -> #VALUE! | H23: =VLOOKUP($E23,Hybrid!$1:$1048576,MATCH(DATE(H$2,1,1),Hybrid!$A$1:$LI$1),FALSE) -> #VALUE! | I23: =VLOOKUP($E23,Hybrid!$1:$1048576,MATCH(DATE(I$2,1,1),Hybrid!$A$1:$LI$1),FALSE) -> #VALUE! | J23: =VLOOKUP($E23,Hybrid!$1:$1048576,MATCH(DATE(J$2,1,1),Hybrid!$A$1:$LI$1),FALSE) -> #VALUE! | K23: =VLOOKUP($E23,Hybrid!$1:$1048576,MATCH(DATE(K$2,1,1),Hybrid!$A$1:$LI$1),FALSE) -> #VALUE! | L23: =VLOOKUP($E23,Hybrid!$1:$1048576,MATCH(DATE(L$2,1,1),Hybrid!$A$1:$LI$1),FALSE) -> #VALUE! | M23: =VLOOKUP($E23,Hybrid!$1:$1048576,MATCH(DATE(M$2,1,1),Hybrid!$A$1:$LI$1),FALSE) -> #VALUE! | ... BI23: =VLOOKUP($E23,Hybrid!$1:$1048576,MATCH(DATE(BI$2,1,1),Hybrid!$A$1:$LI$1),FALSE) -> #VALUE!
D24: class D | E24: AUTO_cd_cgas_2 | F24: =VLOOKUP($E24,Hybrid!$1:$1048576,MATCH(DATE(F$2,1,1),Hybrid!$A$1:$LI$1),FALSE) -> #VALUE! | G24: =VLOOKUP($E24,Hybrid!$1:$1048576,MATCH(DATE(G$2,1,1),Hybrid!$A$1:$LI$1),FALSE) -> #VALUE! | H24: =VLOOKUP($E24,Hybrid!$1:$1048576,MATCH(DATE(H$2,1,1),Hybrid!$A$1:$LI$1),FALSE) -> #VALUE! | I24: =VLOOKUP($E24,Hybrid!$1:$1048576,MATCH(DATE(I$2,1,1),Hybrid!$A$1:$LI$1),FALSE) -> #VALUE! | J24: =VLOOKUP($E24,Hybrid!$1:$1048576,MATCH(DATE(J$2,1,1),Hybrid!$A$1:$LI$1),FALSE) -> #VALUE! | K24: =VLOOKUP($E24,Hybrid!$1:$1048576,MATCH(DATE(K$2,1,1),Hybrid!$A$1:$LI$1),FALSE) -> #VALUE! | L24: =VLOOKUP($E24,Hybrid!$1:$1048576,MATCH(DATE(L$2,1,1),Hybrid!$A$1:$LI$1),FALSE) -> #VALUE! | M24: =VLOOKUP($E24,Hybrid!$1:$1048576,MATCH(DATE(M$2,1,1),Hybrid!$A$1:$LI$1),FALSE) -> #VALUE! | ... BI24: =VLOOKUP($E24,Hybrid!$1:$1048576,MATCH(DATE(BI$2,1,1),Hybrid!$A$1:$LI$1),FALSE) -> #VALUE!
D25: class E | E25: AUTO_ce_cgas_2 | F25: =VLOOKUP($E25,Hybrid!$1:$1048576,MATCH(DATE(F$2,1,1),Hybrid!$A$1:$LI$1),FALSE) -> #VALUE! | G25: =VLOOKUP($E25,Hybrid!$1:$1048576,MATCH(DATE(G$2,1,1),Hybrid!$A$1:$LI$1),FALSE) -> #VALUE! | H25: =VLOOKUP($E25,Hybrid!$1:$1048576,MATCH(DATE(H$2,1,1),Hybrid!$A$1:$LI$1),FALSE) -> #VALUE! | I25: =VLOOKUP($E25,Hybrid!$1:$1048576,MATCH(DATE(I$2,1,1),Hybrid!$A$1:$LI$1),FALSE) -> #VALUE! | J25: =VLOOKUP($E25,Hybrid!$1:$1048576,MATCH(DATE(J$2,1,1),Hybrid!$A$1:$LI$1),FALSE) -> #VALUE! | K25: =VLOOKUP($E25,Hybrid!$1:$1048576,MATCH(DATE(K$2,1,1),Hybrid!$A$1:$LI$1),FALSE) -> #VALUE! | L25: =VLOOKUP($E25,Hybrid!$1:$1048576,MATCH(DATE(L$2,1,1),Hybrid!$A$1:$LI$1),FALSE) -> #VALUE! | M25: =VLOOKUP($E25,Hybrid!$1:$1048576,MATCH(DATE(M$2,1,1),Hybrid!$A$1:$LI$1),FALSE) -> #VALUE! | ... BI25: =VLOOKUP($E25,Hybrid!$1:$1048576,MATCH(DATE(BI$2,1,1),Hybrid!$A$1:$LI$1),FALSE) -> #VALUE!
D26: class F | E26: AUTO_cf_cgas_2 | F26: =VLOOKUP($E26,Hybrid!$1:$1048576,MATCH(DATE(F$2,1,1),Hybrid!$A$1:$LI$1),FALSE) -> #VALUE! | G26: =VLOOKUP($E26,Hybrid!$1:$1048576,MATCH(DATE(G$2,1,1),Hybrid!$A$1:$LI$1),FALSE) -> #VALUE! | H26: =VLOOKUP($E26,Hybrid!$1:$1048576,MATCH(DATE(H$2,1,1),Hybrid!$A$1:$LI$1),FALSE) -> #VALUE! | I26: =VLOOKUP($E26,Hybrid!$1:$1048576,MATCH(DATE(I$2,1,1),Hybrid!$A$1:$LI$1),FALSE) -> #VALUE! | J26: =VLOOKUP($E26,Hybrid!$1:$1048576,MATCH(DATE(J$2,1,1),Hybrid!$A$1:$LI$1),FALSE) -> #VALUE! | K26: =VLOOKUP($E26,Hybrid!$1:$1048576,MATCH(DATE(K$2,1,1),Hybrid!$A$1:$LI$1),FALSE) -> #VALUE! | L26: =VLOOKUP($E26,Hybrid!$1:$1048576,MATCH(DATE(L$2,1,1),Hybrid!$A$1:$LI$1),FALSE) -> #VALUE! | M26: =VLOOKUP($E26,Hybrid!$1:$1048576,MATCH(DATE(M$2,1,1),Hybrid!$A$1:$LI$1),FALSE) -> #VALUE! | ... BI26: =VLOOKUP($E26,Hybrid!$1:$1048576,MATCH(DATE(BI$2,1,1),Hybrid!$A$1:$LI$1),FALSE) -> #VALUE!
D27: class G | E27: AUTO_cg_cgas_2 | F27: =VLOOKUP($E27,Hybrid!$1:$1048576,MATCH(DATE(F$2,1,1),Hybrid!$A$1:$LI$1),FALSE) -> #VALUE! | G27: =VLOOKUP($E27,Hybrid!$1:$1048576,MATCH(DATE(G$2,1,1),Hybrid!$A$1:$LI$1),FALSE) -> #VALUE! | H27: =VLOOKUP($E27,Hybrid!$1:$1048576,MATCH(DATE(H$2,1,1),Hybrid!$A$1:$LI$1),FALSE) -> #VALUE! | I27: =VLOOKUP($E27,Hybrid!$1:$1048576,MATCH(DATE(I$2,1,1),Hybrid!$A$1:$LI$1),FALSE) -> #VALUE! | J27: =VLOOKUP($E27,Hybrid!$1:$1048576,MATCH(DATE(J$2,1,1),Hybrid!$A$1:$LI$1),FALSE) -> #VALUE! | K27: =VLOOKUP($E27,Hybrid!$1:$1048576,MATCH(DATE(K$2,1,1),Hybrid!$A$1:$LI$1),FALSE) -> #VALUE! | L27: =VLOOKUP($E27,Hybrid!$1:$1048576,MATCH(DATE(L$2,1,1),Hybrid!$A$1:$LI$1),FALSE) -> #VALUE! | M27: =VLOOKUP($E27,Hybrid!$1:$1048576,MATCH(DATE(M$2,1,1),Hybrid!$A$1:$LI$1),FALSE) -> #VALUE! | ... BI27: =VLOOKUP($E27,Hybrid!$1:$1048576,MATCH(DATE(BI$2,1,1),Hybrid!$A$1:$LI$1),FALSE) -> #VALUE!
C28: TOTAL STOCK BASELINE | E28: AUTO_0 | F28: =VLOOKUP($E28,Hybrid!$1:$1048576,MATCH(DATE(F$2,1,1),Hybrid!$A$1:$LI$1),FALSE) -> #VALUE! | G28: =VLOOKUP($E28,Hybrid!$1:$1048576,MATCH(DATE(G$2,1,1),Hybrid!$A$1:$LI$1),FALSE) -> #VALUE! | H28: =VLOOKUP($E28,Hybrid!$1:$1048576,MATCH(DATE(H$2,1,1),Hybrid!$A$1:$LI$1),FALSE) -> #VALUE! | I28: =VLOOKUP($E28,Hybrid!$1:$1048576,MATCH(DATE(I$2,1,1),Hybrid!$A$1:$LI$1),FALSE) -> #VALUE! | J28: =VLOOKUP($E28,Hybrid!$1:$1048576,MATCH(DATE(J$2,1,1),Hybrid!$A$1:$LI$1),FALSE) -> #VALUE! | K28: =VLOOKUP($E28,Hybrid!$1:$1048576,MATCH(DATE(K$2,1,1),Hybrid!$A$1:$LI$1),FALSE) -> #VALUE! | L28: =VLOOKUP($E28,Hybrid!$1:$1048576,MATCH(DATE(L$2,1,1),Hybrid!$A$1:$LI$1),FALSE) -> #VALUE! | M28: =VLOOKUP($E28,Hybrid!$1:$1048576,MATCH(DATE(M$2,1,1),Hybrid!$A$1:$LI$1),FALSE) -> #VALUE! | ... BI28: =VLOOKUP($E28,Hybrid!$1:$1048576,MATCH(DATE(BI$2,1,1),Hybrid!$A$1:$LI$1),FALSE) -> #VALUE!
C29: OIL | E29: AUTO_cfut_0 | F29: =VLOOKUP($E29,Hybrid!$1:$1048576,MATCH(DATE(F$2,1,1),Hybrid!$A$1:$LI$1),FALSE) -> #VALUE! | G29: =VLOOKUP($E29,Hybrid!$1:$1048576,MATCH(DATE(G$2,1,1),Hybrid!$A$1:$LI$1),FALSE) -> #VALUE! | H29: =VLOOKUP($E29,Hybrid!$1:$1048576,MATCH(DATE(H$2,1,1),Hybrid!$A$1:$LI$1),FALSE) -> #VALUE! | I29: =VLOOKUP($E29,Hybrid!$1:$1048576,MATCH(DATE(I$2,1,1),Hybrid!$A$1:$LI$1),FALSE) -> #VALUE! | J29: =VLOOKUP($E29,Hybrid!$1:$1048576,MATCH(DATE(J$2,1,1),Hybrid!$A$1:$LI$1),FALSE) -> #VALUE! | K29: =VLOOKUP($E29,Hybrid!$1:$1048576,MATCH(DATE(K$2,1,1),Hybrid!$A$1:$LI$1),FALSE) -> #VALUE! | L29: =VLOOKUP($E29,Hybrid!$1:$1048576,MATCH(DATE(L$2,1,1),Hybrid!$A$1:$LI$1),FALSE) -> #VALUE! | M29: =VLOOKUP($E29,Hybrid!$1:$1048576,MATCH(DATE(M$2,1,1),Hybrid!$A$1:$LI$1),FALSE) -> #VALUE! | ... BI29: =VLOOKUP($E29,Hybrid!$1:$1048576,MATCH(DATE(BI$2,1,1),Hybrid!$A$1:$LI$1),FALSE) -> #VALUE!
D30: class A | E30: AUTO_ca_cfut_0 | F30: =VLOOKUP($E30,Hybrid!$1:$1048576,MATCH(DATE(F$2,1,1),Hybrid!$A$1:$LI$1),FALSE) -> #VALUE! | G30: =VLOOKUP($E30,Hybrid!$1:$1048576,MATCH(DATE(G$2,1,1),Hybrid!$A$1:$LI$1),FALSE) -> #VALUE! | H30: =VLOOKUP($E30,Hybrid!$1:$1048576,MATCH(DATE(H$2,1,1),Hybrid!$A$1:$LI$1),FALSE) -> #VALUE! | I30: =VLOOKUP($E30,Hybrid!$1:$1048576,MATCH(DATE(I$2,1,1),Hybrid!$A$1:$LI$1),FALSE) -> #VALUE! | J30: =VLOOKUP($E30,Hybrid!$1:$1048576,MATCH(DATE(J$2,1,1),Hybrid!$A$1:$LI$1),FALSE) -> #VALUE! | K30: =VLOOKUP($E30,Hybrid!$1:$1048576,MATCH(DATE(K$2,1,1),Hybrid!$A$1:$LI$1),FALSE) -> #VALUE! | L30: =VLOOKUP($E30,Hybrid!$1:$1048576,MATCH(DATE(L$2,1,1),Hybrid!$A$1:$LI$1),FALSE) -> #VALUE! | M30: =VLOOKUP($E30,Hybrid!$1:$1048576,MATCH(DATE(M$2,1,1),Hybrid!$A$1:$LI$1),FALSE) -> #VALUE! | ... BI30: =VLOOKUP($E30,Hybrid!$1:$1048576,MATCH(DATE(BI$2,1,1),Hybrid!$A$1:$LI$1),FALSE) -> #VALUE!
D31: class B | E31: AUTO_cb_cfut_0 | F31: =VLOOKUP($E31,Hybrid!$1:$1048576,MATCH(DATE(F$2,1,1),Hybrid!$A$1:$LI$1),FALSE) -> #VALUE! | G31: =VLOOKUP($E31,Hybrid!$1:$1048576,MATCH(DATE(G$2,1,1),Hybrid!$A$1:$LI$1),FALSE) -> #VALUE! | H31: =VLOOKUP($E31,Hybrid!$1:$1048576,MATCH(DATE(H$2,1,1),Hybrid!$A$1:$LI$1),FALSE) -> #VALUE! | I31: =VLOOKUP($E31,Hybrid!$1:$1048576,MATCH(DATE(I$2,1,1),Hybrid!$A$1:$LI$1),FALSE) -> #VALUE! | J31: =VLOOKUP($E31,Hybrid!$1:$1048576,MATCH(DATE(J$2,1,1),Hybrid!$A$1:$LI$1),FALSE) -> #VALUE! | K31: =VLOOKUP($E31,Hybrid!$1:$1048576,MATCH(DATE(K$2,1,1),Hybrid!$A$1:$LI$1),FALSE) -> #VALUE! | L31: =VLOOKUP($E31,Hybrid!$1:$1048576,MATCH(DATE(L$2,1,1),Hybrid!$A$1:$LI$1),FALSE) -> #VALUE! | M31: =VLOOKUP($E31,Hybrid!$1:$1048576,MATCH(DATE(M$2,1,1),Hybrid!$A$1:$LI$1),FALSE) -> #VALUE! | ... BI31: =VLOOKUP($E31,Hybrid!$1:$1048576,MATCH(DATE(BI$2,1,1),Hybrid!$A$1:$LI$1),FALSE) -> #VALUE!
D32: class C | E32: AUTO_cc_cfut_0 | F32: =VLOOKUP($E32,Hybrid!$1:$1048576,MATCH(DATE(F$2,1,1),Hybrid!$A$1:$LI$1),FALSE) -> #VALUE! | G32: =VLOOKUP($E32,Hybrid!$1:$1048576,MATCH(DATE(G$2,1,1),Hybrid!$A$1:$LI$1),FALSE) -> #VALUE! | H32: =VLOOKUP($E32,Hybrid!$1:$1048576,MATCH(DATE(H$2,1,1),Hybrid!$A$1:$LI$1),FALSE) -> #VALUE! | I32: =VLOOKUP($E32,Hybrid!$1:$1048576,MATCH(DATE(I$2,1,1),Hybrid!$A$1:$LI$1),FALSE) -> #VALUE! | J32: =VLOOKUP($E32,Hybrid!$1:$1048576,MATCH(DATE(J$2,1,1),Hybrid!$A$1:$LI$1),FALSE) -> #VALUE! | K32: =VLOOKUP($E32,Hybrid!$1:$1048576,MATCH(DATE(K$2,1,1),Hybrid!$A$1:$LI$1),FALSE) -> #VALUE! | L32: =VLOOKUP($E32,Hybrid!$1:$1048576,MATCH(DATE(L$2,1,1),Hybrid!$A$1:$LI$1),FALSE) -> #VALUE! | M32: =VLOOKUP($E32,Hybrid!$1:$1048576,MATCH(DATE(M$2,1,1),Hybrid!$A$1:$LI$1),FALSE) -> #VALUE! | ... BI32: =VLOOKUP($E32,Hybrid!$1:$1048576,MATCH(DATE(BI$2,1,1),Hybrid!$A$1:$LI$1),FALSE) -> #VALUE!
D33: class D | E33: AUTO_cd_cfut_0 | F33: =VLOOKUP($E33,Hybrid!$1:$1048576,MATCH(DATE(F$2,1,1),Hybrid!$A$1:$LI$1),FALSE) -> #VALUE! | G33: =VLOOKUP($E33,Hybrid!$1:$1048576,MATCH(DATE(G$2,1,1),Hybrid!$A$1:$LI$1),FALSE) -> #VALUE! | H33: =VLOOKUP($E33,Hybrid!$1:$1048576,MATCH(DATE(H$2,1,1),Hybrid!$A$1:$LI$1),FALSE) -> #VALUE! | I33: =VLOOKUP($E33,Hybrid!$1:$1048576,MATCH(DATE(I$2,1,1),Hybrid!$A$1:$LI$1),FALSE) -> #VALUE! | J33: =VLOOKUP($E33,Hybrid!$1:$1048576,MATCH(DATE(J$2,1,1),Hybrid!$A$1:$LI$1),FALSE) -> #VALUE! | K33: =VLOOKUP($E33,Hybrid!$1:$1048576,MATCH(DATE(K$2,1,1),Hybrid!$A$1:$LI$1),FALSE) -> #VALUE! | L33: =VLOOKUP($E33,Hybrid!$1:$1048576,MATCH(DATE(L$2,1,1),Hybrid!$A$1:$LI$1),FALSE) -> #VALUE! | M33: =VLOOKUP($E33,Hybrid!$1:$1048576,MATCH(DATE(M$2,1,1),Hybrid!$A$1:$LI$1),FALSE) -> #VALUE! | ... BI33: =VLOOKUP($E33,Hybrid!$1:$1048576,MATCH(DATE(BI$2,1,1),Hybrid!$A$1:$LI$1),FALSE) -> #VALUE!
D34: class E | E34: AUTO_ce_cfut_0 | F34: =VLOOKUP($E34,Hybrid!$1:$1048576,MATCH(DATE(F$2,1,1),Hybrid!$A$1:$LI$1),FALSE) -> #VALUE! | G34: =VLOOKUP($E34,Hybrid!$1:$1048576,MATCH(DATE(G$2,1,1),Hybrid!$A$1:$LI$1),FALSE) -> #VALUE! | H34: =VLOOKUP($E34,Hybrid!$1:$1048576,MATCH(DATE(H$2,1,1),Hybrid!$A$1:$LI$1),FALSE) -> #VALUE! | I34: =VLOOKUP($E34,Hybrid!$1:$1048576,MATCH(DATE(I$2,1,1),Hybrid!$A$1:$LI$1),FALSE) -> #VALUE! | J34: =VLOOKUP($E34,Hybrid!$1:$1048576,MATCH(DATE(J$2,1,1),Hybrid!$A$1:$LI$1),FALSE) -> #VALUE! | K34: =VLOOKUP($E34,Hybrid!$1:$1048576,MATCH(DATE(K$2,1,1),Hybrid!$A$1:$LI$1),FALSE) -> #VALUE! | L34: =VLOOKUP($E34,Hybrid!$1:$1048576,MATCH(DATE(L$2,1,1),Hybrid!$A$1:$LI$1),FALSE) -> #VALUE! | M34: =VLOOKUP($E34,Hybrid!$1:$1048576,MATCH(DATE(M$2,1,1),Hybrid!$A$1:$LI$1),FALSE) -> #VALUE! | ... BI34: =VLOOKUP($E34,Hybrid!$1:$1048576,MATCH(DATE(BI$2,1,1),Hybrid!$A$1:$LI$1),FALSE) -> #VALUE!
D35: class F | E35: AUTO_cf_cfut_0 | F35: =VLOOKUP($E35,Hybrid!$1:$1048576,MATCH(DATE(F$2,1,1),Hybrid!$A$1:$LI$1),FALSE) -> #VALUE! | G35: =VLOOKUP($E35,Hybrid!$1:$1048576,MATCH(DATE(G$2,1,1),Hybrid!$A$1:$LI$1),FALSE) -> #VALUE! | H35: =VLOOKUP($E35,Hybrid!$1:$1048576,MATCH(DATE(H$2,1,1),Hybrid!$A$1:$LI$1),FALSE) -> #VALUE! | I35: =VLOOKUP($E35,Hybrid!$1:$1048576,MATCH(DATE(I$2,1,1),Hybrid!$A$1:$LI$1),FALSE) -> #VALUE! | J35: =VLOOKUP($E35,Hybrid!$1:$1048576,MATCH(DATE(J$2,1,1),Hybrid!$A$1:$LI$1),FALSE) -> #VALUE! | K35: =VLOOKUP($E35,Hybrid!$1:$1048576,MATCH(DATE(K$2,1,1),Hybrid!$A$1:$LI$1),FALSE) -> #VALUE! | L35: =VLOOKUP($E35,Hybrid!$1:$1048576,MATCH(DATE(L$2,1,1),Hybrid!$A$1:$LI$1),FALSE) -> #VALUE! | M35: =VLOOKUP($E35,Hybrid!$1:$1048576,MATCH(DATE(M$2,1,1),Hybrid!$A$1:$LI$1),FALSE) -> #VALUE! | ... BI35: =VLOOKUP($E35,Hybrid!$1:$1048576,MATCH(DATE(BI$2,1,1),Hybrid!$A$1:$LI$1),FALSE) -> #VALUE!
D36: class G | E36: AUTO_cg_cfut_0 | F36: =VLOOKUP($E36,Hybrid!$1:$1048576,MATCH(DATE(F$2,1,1),Hybrid!$A$1:$LI$1),FALSE) -> #VALUE! | G36: =VLOOKUP($E36,Hybrid!$1:$1048576,MATCH(DATE(G$2,1,1),Hybrid!$A$1:$LI$1),FALSE) -> #VALUE! | H36: =VLOOKUP($E36,Hybrid!$1:$1048576,MATCH(DATE(H$2,1,1),Hybrid!$A$1:$LI$1),FALSE) -> #VALUE! | I36: =VLOOKUP($E36,Hybrid!$1:$1048576,MATCH(DATE(I$2,1,1),Hybrid!$A$1:$LI$1),FALSE) -> #VALUE! | J36: =VLOOKUP($E36,Hybrid!$1:$1048576,MATCH(DATE(J$2,1,1),Hybrid!$A$1:$LI$1),FALSE) -> #VALUE! | K36: =VLOOKUP($E36,Hybrid!$1:$1048576,MATCH(DATE(K$2,1,1),Hybrid!$A$1:$LI$1),FALSE) -> #VALUE! | L36: =VLOOKUP($E36,Hybrid!$1:$1048576,MATCH(DATE(L$2,1,1),Hybrid!$A$1:$LI$1),FALSE) -> #VALUE! | M36: =VLOOKUP($E36,Hybrid!$1:$1048576,MATCH(DATE(M$2,1,1),Hybrid!$A$1:$LI$1),FALSE) -> #VALUE! | ... BI36: =VLOOKUP($E36,Hybrid!$1:$1048576,MATCH(DATE(BI$2,1,1),Hybrid!$A$1:$LI$1),FALSE) -> #VALUE!
C37: ELEC | E37: AUTO_cele_0 | F37: =VLOOKUP($E37,Hybrid!$1:$1048576,MATCH(DATE(F$2,1,1),Hybrid!$A$1:$LI$1),FALSE) -> #VALUE! | G37: =VLOOKUP($E37,Hybrid!$1:$1048576,MATCH(DATE(G$2,1,1),Hybrid!$A$1:$LI$1),FALSE) -> #VALUE! | H37: =VLOOKUP($E37,Hybrid!$1:$1048576,MATCH(DATE(H$2,1,1),Hybrid!$A$1:$LI$1),FALSE) -> #VALUE! | I37: =VLOOKUP($E37,Hybrid!$1:$1048576,MATCH(DATE(I$2,1,1),Hybrid!$A$1:$LI$1),FALSE) -> #VALUE! | J37: =VLOOKUP($E37,Hybrid!$1:$1048576,MATCH(DATE(J$2,1,1),Hybrid!$A$1:$LI$1),FALSE) -> #VALUE! | K37: =VLOOKUP($E37,Hybrid!$1:$1048576,MATCH(DATE(K$2,1,1),Hybrid!$A$1:$LI$1),FALSE) -> #VALUE! | L37: =VLOOKUP($E37,Hybrid!$1:$1048576,MATCH(DATE(L$2,1,1),Hybrid!$A$1:$LI$1),FALSE) -> #VALUE! | M37: =VLOOKUP($E37,Hybrid!$1:$1048576,MATCH(DATE(M$2,1,1),Hybrid!$A$1:$LI$1),FALSE) -> #VALUE! | ... BI37: =VLOOKUP($E37,Hybrid!$1:$1048576,MATCH(DATE(BI$2,1,1),Hybrid!$A$1:$LI$1),FALSE) -> #VALUE!
D38: class A | E38: AUTO_ca_cele_0 | F38: =VLOOKUP($E38,Hybrid!$1:$1048576,MATCH(DATE(F$2,1,1),Hybrid!$A$1:$LI$1),FALSE) -> #VALUE! | G38: =VLOOKUP($E38,Hybrid!$1:$1048576,MATCH(DATE(G$2,1,1),Hybrid!$A$1:$LI$1),FALSE) -> #VALUE! | H38: =VLOOKUP($E38,Hybrid!$1:$1048576,MATCH(DATE(H$2,1,1),Hybrid!$A$1:$LI$1),FALSE) -> #VALUE! | I38: =VLOOKUP($E38,Hybrid!$1:$1048576,MATCH(DATE(I$2,1,1),Hybrid!$A$1:$LI$1),FALSE) -> #VALUE! | J38: =VLOOKUP($E38,Hybrid!$1:$1048576,MATCH(DATE(J$2,1,1),Hybrid!$A$1:$LI$1),FALSE) -> #VALUE! | K38: =VLOOKUP($E38,Hybrid!$1:$1048576,MATCH(DATE(K$2,1,1),Hybrid!$A$1:$LI$1),FALSE) -> #VALUE! | L38: =VLOOKUP($E38,Hybrid!$1:$1048576,MATCH(DATE(L$2,1,1),Hybrid!$A$1:$LI$1),FALSE) -> #VALUE! | M38: =VLOOKUP($E38,Hybrid!$1:$1048576,MATCH(DATE(M$2,1,1),Hybrid!$A$1:$LI$1),FALSE) -> #VALUE! | ... BI38: =VLOOKUP($E38,Hybrid!$1:$1048576,MATCH(DATE(BI$2,1,1),Hybrid!$A$1:$LI$1),FALSE) -> #VALUE!
D39: class B | E39: AUTO_cb_cele_0 | F39: =VLOOKUP($E39,Hybrid!$1:$1048576,MATCH(DATE(F$2,1,1),Hybrid!$A$1:$LI$1),FALSE) -> #VALUE! | G39: =VLOOKUP($E39,Hybrid!$1:$1048576,MATCH(DATE(G$2,1,1),Hybrid!$A$1:$LI$1),FALSE) -> #VALUE! | H39: =VLOOKUP($E39,Hybrid!$1:$1048576,MATCH(DATE(H$2,1,1),Hybrid!$A$1:$LI$1),FALSE) -> #VALUE! | I39: =VLOOKUP($E39,Hybrid!$1:$1048576,MATCH(DATE(I$2,1,1),Hybrid!$A$1:$LI$1),FALSE) -> #VALUE! | J39: =VLOOKUP($E39,Hybrid!$1:$1048576,MATCH(DATE(J$2,1,1),Hybrid!$A$1:$LI$1),FALSE) -> #VALUE! | K39: =VLOOKUP($E39,Hybrid!$1:$1048576,MATCH(DATE(K$2,1,1),Hybrid!$A$1:$LI$1),FALSE) -> #VALUE! | L39: =VLOOKUP($E39,Hybrid!$1:$1048576,MATCH(DATE(L$2,1,1),Hybrid!$A$1:$LI$1),FALSE) -> #VALUE! | M39: =VLOOKUP($E39,Hybrid!$1:$1048576,MATCH(DATE(M$2,1,1),Hybrid!$A$1:$LI$1),FALSE) -> #VALUE! | ... BI39: =VLOOKUP($E39,Hybrid!$1:$1048576,MATCH(DATE(BI$2,1,1),Hybrid!$A$1:$LI$1),FALSE) -> #VALUE!
D40: class C | E40: AUTO_cc_cele_0 | F40: =VLOOKUP($E40,Hybrid!$1:$1048576,MATCH(DATE(F$2,1,1),Hybrid!$A$1:$LI$1),FALSE) -> #VALUE! | G40: =VLOOKUP($E40,Hybrid!$1:$1048576,MATCH(DATE(G$2,1,1),Hybrid!$A$1:$LI$1),FALSE) -> #VALUE! | H40: =VLOOKUP($E40,Hybrid!$1:$1048576,MATCH(DATE(H$2,1,1),Hybrid!$A$1:$LI$1),FALSE) -> #VALUE! | I40: =VLOOKUP($E40,Hybrid!$1:$1048576,MATCH(DATE(I$2,1,1),Hybrid!$A$1:$LI$1),FALSE) -> #VALUE! | J40: =VLOOKUP($E40,Hybrid!$1:$1048576,MATCH(DATE(J$2,1,1),Hybrid!$A$1:$LI$1),FALSE) -> #VALUE! | K40: =VLOOKUP($E40,Hybrid!$1:$1048576,MATCH(DATE(K$2,1,1),Hybrid!$A$1:$LI$1),FALSE) -> #VALUE! | L40: =VLOOKUP($E40,Hybrid!$1:$1048576,MATCH(DATE(L$2,1,1),Hybrid!$A$1:$LI$1),FALSE) -> #VALUE! | M40: =VLOOKUP($E40,Hybrid!$1:$1048576,MATCH(DATE(M$2,1,1),Hybrid!$A$1:$LI$1),FALSE) -> #VALUE! | ... BI40: =VLOOKUP($E40,Hybrid!$1:$1048576,MATCH(DATE(BI$2,1,1),Hybrid!$A$1:$LI$1),FALSE) -> #VALUE!
D41: class D | E41: AUTO_cd_cele_0 | F41: =VLOOKUP($E41,Hybrid!$1:$1048576,MATCH(DATE(F$2,1,1),Hybrid!$A$1:$LI$1),FALSE) -> #VALUE! | G41: =VLOOKUP($E41,Hybrid!$1:$1048576,MATCH(DATE(G$2,1,1),Hybrid!$A$1:$LI$1),FALSE) -> #VALUE! | H41: =VLOOKUP($E41,Hybrid!$1:$1048576,MATCH(DATE(H$2,1,1),Hybrid!$A$1:$LI$1),FALSE) -> #VALUE! | I41: =VLOOKUP($E41,Hybrid!$1:$1048576,MATCH(DATE(I$2,1,1),Hybrid!$A$1:$LI$1),FALSE) -> #VALUE! | J41: =VLOOKUP($E41,Hybrid!$1:$1048576,MATCH(DATE(J$2,1,1),Hybrid!$A$1:$LI$1),FALSE) -> #VALUE! | K41: =VLOOKUP($E41,Hybrid!$1:$1048576,MATCH(DATE(K$2,1,1),Hybrid!$A$1:$LI$1),FALSE) -> #VALUE! | L41: =VLOOKUP($E41,Hybrid!$1:$1048576,MATCH(DATE(L$2,1,1),Hybrid!$A$1:$LI$1),FALSE) -> #VALUE! | M41: =VLOOKUP($E41,Hybrid!$1:$1048576,MATCH(DATE(M$2,1,1),Hybrid!$A$1:$LI$1),FALSE) -> #VALUE! | ... BI41: =VLOOKUP($E41,Hybrid!$1:$1048576,MATCH(DATE(BI$2,1,1),Hybrid!$A$1:$LI$1),FALSE) -> #VALUE!
D42: class E | E42: AUTO_ce_cele_0 | F42: =VLOOKUP($E42,Hybrid!$1:$1048576,MATCH(DATE(F$2,1,1),Hybrid!$A$1:$LI$1),FALSE) -> #VALUE! | G42: =VLOOKUP($E42,Hybrid!$1:$1048576,MATCH(DATE(G$2,1,1),Hybrid!$A$1:$LI$1),FALSE) -> #VALUE! | H42: =VLOOKUP($E42,Hybrid!$1:$1048576,MATCH(DATE(H$2,1,1),Hybrid!$A$1:$LI$1),FALSE) -> #VALUE! | I42: =VLOOKUP($E42,Hybrid!$1:$1048576,MATCH(DATE(I$2,1,1),Hybrid!$A$1:$LI$1),FALSE) -> #VALUE! | J42: =VLOOKUP($E42,Hybrid!$1:$1048576,MATCH(DATE(J$2,1,1),Hybrid!$A$1:$LI$1),FALSE) -> #VALUE! | K42: =VLOOKUP($E42,Hybrid!$1:$1048576,MATCH(DATE(K$2,1,1),Hybrid!$A$1:$LI$1),FALSE) -> #VALUE! | L42: =VLOOKUP($E42,Hybrid!$1:$1048576,MATCH(DATE(L$2,1,1),Hybrid!$A$1:$LI$1),FALSE) -> #VALUE! | M42: =VLOOKUP($E42,Hybrid!$1:$1048576,MATCH(DATE(M$2,1,1),Hybrid!$A$1:$LI$1),FALSE) -> #VALUE! | ... BI42: =VLOOKUP($E42,Hybrid!$1:$1048576,MATCH(DATE(BI$2,1,1),Hybrid!$A$1:$LI$1),FALSE) -> #VALUE!
D43: class F | E43: AUTO_cf_cele_0 | F43: =VLOOKUP($E43,Hybrid!$1:$1048576,MATCH(DATE(F$2,1,1),Hybrid!$A$1:$LI$1),FALSE) -> #VALUE! | G43: =VLOOKUP($E43,Hybrid!$1:$1048576,MATCH(DATE(G$2,1,1),Hybrid!$A$1:$LI$1),FALSE) -> #VALUE! | H43: =VLOOKUP($E43,Hybrid!$1:$1048576,MATCH(DATE(H$2,1,1),Hybrid!$A$1:$LI$1),FALSE) -> #VALUE! | I43: =VLOOKUP($E43,Hybrid!$1:$1048576,MATCH(DATE(I$2,1,1),Hybrid!$A$1:$LI$1),FALSE) -> #VALUE! | J43: =VLOOKUP($E43,Hybrid!$1:$1048576,MATCH(DATE(J$2,1,1),Hybrid!$A$1:$LI$1),FALSE) -> #VALUE! | K43: =VLOOKUP($E43,Hybrid!$1:$1048576,MATCH(DATE(K$2,1,1),Hybrid!$A$1:$LI$1),FALSE) -> #VALUE! | L43: =VLOOKUP($E43,Hybrid!$1:$1048576,MATCH(DATE(L$2,1,1),Hybrid!$A$1:$LI$1),FALSE) -> #VALUE! | M43: =VLOOKUP($E43,Hybrid!$1:$1048576,MATCH(DATE(M$2,1,1),Hybrid!$A$1:$LI$1),FALSE) -> #VALUE! | ... BI43: =VLOOKUP($E43,Hybrid!$1:$1048576,MATCH(DATE(BI$2,1,1),Hybrid!$A$1:$LI$1),FALSE) -> #VALUE!
D44: class G | E44: AUTO_cg_cele_0 | F44: =VLOOKUP($E44,Hybrid!$1:$1048576,MATCH(DATE(F$2,1,1),Hybrid!$A$1:$LI$1),FALSE) -> #VALUE! | G44: =VLOOKUP($E44,Hybrid!$1:$1048576,MATCH(DATE(G$2,1,1),Hybrid!$A$1:$LI$1),FALSE) -> #VALUE! | H44: =VLOOKUP($E44,Hybrid!$1:$1048576,MATCH(DATE(H$2,1,1),Hybrid!$A$1:$LI$1),FALSE) -> #VALUE! | I44: =VLOOKUP($E44,Hybrid!$1:$1048576,MATCH(DATE(I$2,1,1),Hybrid!$A$1:$LI$1),FALSE) -> #VALUE! | J44: =VLOOKUP($E44,Hybrid!$1:$1048576,MATCH(DATE(J$2,1,1),Hybrid!$A$1:$LI$1),FALSE) -> #VALUE! | K44: =VLOOKUP($E44,Hybrid!$1:$1048576,MATCH(DATE(K$2,1,1),Hybrid!$A$1:$LI$1),FALSE) -> #VALUE! | L44: =VLOOKUP($E44,Hybrid!$1:$1048576,MATCH(DATE(L$2,1,1),Hybrid!$A$1:$LI$1),FALSE) -> #VALUE! | M44: =VLOOKUP($E44,Hybrid!$1:$1048576,MATCH(DATE(M$2,1,1),Hybrid!$A$1:$LI$1),FALSE) -> #VALUE! | ... BI44: =VLOOKUP($E44,Hybrid!$1:$1048576,MATCH(DATE(BI$2,1,1),Hybrid!$A$1:$LI$1),FALSE) -> #VALUE!
C45: GAS | E45: AUTO_cgas_0 | F45: =VLOOKUP($E45,Hybrid!$1:$1048576,MATCH(DATE(F$2,1,1),Hybrid!$A$1:$LI$1),FALSE) -> #VALUE! | G45: =VLOOKUP($E45,Hybrid!$1:$1048576,MATCH(DATE(G$2,1,1),Hybrid!$A$1:$LI$1),FALSE) -> #VALUE! | H45: =VLOOKUP($E45,Hybrid!$1:$1048576,MATCH(DATE(H$2,1,1),Hybrid!$A$1:$LI$1),FALSE) -> #VALUE! | I45: =VLOOKUP($E45,Hybrid!$1:$1048576,MATCH(DATE(I$2,1,1),Hybrid!$A$1:$LI$1),FALSE) -> #VALUE! | J45: =VLOOKUP($E45,Hybrid!$1:$1048576,MATCH(DATE(J$2,1,1),Hybrid!$A$1:$LI$1),FALSE) -> #VALUE! | K45: =VLOOKUP($E45,Hybrid!$1:$1048576,MATCH(DATE(K$2,1,1),Hybrid!$A$1:$LI$1),FALSE) -> #VALUE! | L45: =VLOOKUP($E45,Hybrid!$1:$1048576,MATCH(DATE(L$2,1,1),Hybrid!$A$1:$LI$1),FALSE) -> #VALUE! | M45: =VLOOKUP($E45,Hybrid!$1:$1048576,MATCH(DATE(M$2,1,1),Hybrid!$A$1:$LI$1),FALSE) -> #VALUE! | ... BI45: =VLOOKUP($E45,Hybrid!$1:$1048576,MATCH(DATE(BI$2,1,1),Hybrid!$A$1:$LI$1),FALSE) -> #VALUE!
D46: class A | E46: AUTO_ca_cgas_0 | F46: =VLOOKUP($E46,Hybrid!$1:$1048576,MATCH(DATE(F$2,1,1),Hybrid!$A$1:$LI$1),FALSE) -> #VALUE! | G46: =VLOOKUP($E46,Hybrid!$1:$1048576,MATCH(DATE(G$2,1,1),Hybrid!$A$1:$LI$1),FALSE) -> #VALUE! | H46: =VLOOKUP($E46,Hybrid!$1:$1048576,MATCH(DATE(H$2,1,1),Hybrid!$A$1:$LI$1),FALSE) -> #VALUE! | I46: =VLOOKUP($E46,Hybrid!$1:$1048576,MATCH(DATE(I$2,1,1),Hybrid!$A$1:$LI$1),FALSE) -> #VALUE! | J46: =VLOOKUP($E46,Hybrid!$1:$1048576,MATCH(DATE(J$2,1,1),Hybrid!$A$1:$LI$1),FALSE) -> #VALUE! | K46: =VLOOKUP($E46,Hybrid!$1:$1048576,MATCH(DATE(K$2,1,1),Hybrid!$A$1:$LI$1),FALSE) -> #VALUE! | L46: =VLOOKUP($E46,Hybrid!$1:$1048576,MATCH(DATE(L$2,1,1),Hybrid!$A$1:$LI$1),FALSE) -> #VALUE! | M46: =VLOOKUP($E46,Hybrid!$1:$1048576,MATCH(DATE(M$2,1,1),Hybrid!$A$1:$LI$1),FALSE) -> #VALUE! | ... BI46: =VLOOKUP($E46,Hybrid!$1:$1048576,MATCH(DATE(BI$2,1,1),Hybrid!$A$1:$LI$1),FALSE) -> #VALUE!
D47: class B | E47: AUTO_cb_cgas_0 | F47: =VLOOKUP($E47,Hybrid!$1:$1048576,MATCH(DATE(F$2,1,1),Hybrid!$A$1:$LI$1),FALSE) -> #VALUE! | G47: =VLOOKUP($E47,Hybrid!$1:$1048576,MATCH(DATE(G$2,1,1),Hybrid!$A$1:$LI$1),FALSE) -> #VALUE! | H47: =VLOOKUP($E47,Hybrid!$1:$1048576,MATCH(DATE(H$2,1,1),Hybrid!$A$1:$LI$1),FALSE) -> #VALUE! | I47: =VLOOKUP($E47,Hybrid!$1:$1048576,MATCH(DATE(I$2,1,1),Hybrid!$A$1:$LI$1),FALSE) -> #VALUE! | J47: =VLOOKUP($E47,Hybrid!$1:$1048576,MATCH(DATE(J$2,1,1),Hybrid!$A$1:$LI$1),FALSE) -> #VALUE! | K47: =VLOOKUP($E47,Hybrid!$1:$1048576,MATCH(DATE(K$2,1,1),Hybrid!$A$1:$LI$1),FALSE) -> #VALUE! | L47: =VLOOKUP($E47,Hybrid!$1:$1048576,MATCH(DATE(L$2,1,1),Hybrid!$A$1:$LI$1),FALSE) -> #VALUE! | M47: =VLOOKUP($E47,Hybrid!$1:$1048576,MATCH(DATE(M$2,1,1),Hybrid!$A$1:$LI$1),FALSE) -> #VALUE! | ... BI47: =VLOOKUP($E47,Hybrid!$1:$1048576,MATCH(DATE(BI$2,1,1),Hybrid!$A$1:$LI$1),FALSE) -> #VALUE!
D48: class C | E48: AUTO_cc_cgas_0 | F48: =VLOOKUP($E48,Hybrid!$1:$1048576,MATCH(DATE(F$2,1,1),Hybrid!$A$1:$LI$1),FALSE) -> #VALUE! | G48: =VLOOKUP($E48,Hybrid!$1:$1048576,MATCH(DATE(G$2,1,1),Hybrid!$A$1:$LI$1),FALSE) -> #VALUE! | H48: =VLOOKUP($E48,Hybrid!$1:$1048576,MATCH(DATE(H$2,1,1),Hybrid!$A$1:$LI$1),FALSE) -> #VALUE! | I48: =VLOOKUP($E48,Hybrid!$1:$1048576,MATCH(DATE(I$2,1,1),Hybrid!$A$1:$LI$1),FALSE) -> #VALUE! | J48: =VLOOKUP($E48,Hybrid!$1:$1048576,MATCH(DATE(J$2,1,1),Hybrid!$A$1:$LI$1),FALSE) -> #VALUE! | K48: =VLOOKUP($E48,Hybrid!$1:$1048576,MATCH(DATE(K$2,1,1),Hybrid!$A$1:$LI$1),FALSE) -> #VALUE! | L48: =VLOOKUP($E48,Hybrid!$1:$1048576,MATCH(DATE(L$2,1,1),Hybrid!$A$1:$LI$1),FALSE) -> #VALUE! | M48: =VLOOKUP($E48,Hybrid!$1:$1048576,MATCH(DATE(M$2,1,1),Hybrid!$A$1:$LI$1),FALSE) -> #VALUE! | ... BI48: =VLOOKUP($E48,Hybrid!$1:$1048576,MATCH(DATE(BI$2,1,1),Hybrid!$A$1:$LI$1),FALSE) -> #VALUE!
D49: class D | E49: AUTO_cd_cgas_0 | F49: =VLOOKUP($E49,Hybrid!$1:$1048576,MATCH(DATE(F$2,1,1),Hybrid!$A$1:$LI$1),FALSE) -> #VALUE! | G49: =VLOOKUP($E49,Hybrid!$1:$1048576,MATCH(DATE(G$2,1,1),Hybrid!$A$1:$LI$1),FALSE) -> #VALUE! | H49: =VLOOKUP($E49,Hybrid!$1:$1048576,MATCH(DATE(H$2,1,1),Hybrid!$A$1:$LI$1),FALSE) -> #VALUE! | I49: =VLOOKUP($E49,Hybrid!$1:$1048576,MATCH(DATE(I$2,1,1),Hybrid!$A$1:$LI$1),FALSE) -> #VALUE! | J49: =VLOOKUP($E49,Hybrid!$1:$1048576,MATCH(DATE(J$2,1,1),Hybrid!$A$1:$LI$1),FALSE) -> #VALUE! | K49: =VLOOKUP($E49,Hybrid!$1:$1048576,MATCH(DATE(K$2,1,1),Hybrid!$A$1:$LI$1),FALSE) -> #VALUE! | L49: =VLOOKUP($E49,Hybrid!$1:$1048576,MATCH(DATE(L$2,1,1),Hybrid!$A$1:$LI$1),FALSE) -> #VALUE! | M49: =VLOOKUP($E49,Hybrid!$1:$1048576,MATCH(DATE(M$2,1,1),Hybrid!$A$1:$LI$1),FALSE) -> #VALUE! | ... BI49: =VLOOKUP($E49,Hybrid!$1:$1048576,MATCH(DATE(BI$2,1,1),Hybrid!$A$1:$LI$1),FALSE) -> #VALUE!
D50: class E | E50: AUTO_ce_cgas_0 | F50: =VLOOKUP($E50,Hybrid!$1:$1048576,MATCH(DATE(F$2,1,1),Hybrid!$A$1:$LI$1),FALSE) -> #VALUE! | G50: =VLOOKUP($E50,Hybrid!$1:$1048576,MATCH(DATE(G$2,1,1),Hybrid!$A$1:$LI$1),FALSE) -> #VALUE! | H50: =VLOOKUP($E50,Hybrid!$1:$1048576,MATCH(DATE(H$2,1,1),Hybrid!$A$1:$LI$1),FALSE) -> #VALUE! | I50: =VLOOKUP($E50,Hybrid!$1:$1048576,MATCH(DATE(I$2,1,1),Hybrid!$A$1:$LI$1),FALSE) -> #VALUE! | J50: =VLOOKUP($E50,Hybrid!$1:$1048576,MATCH(DATE(J$2,1,1),Hybrid!$A$1:$LI$1),FALSE) -> #VALUE! | K50: =VLOOKUP($E50,Hybrid!$1:$1048576,MATCH(DATE(K$2,1,1),Hybrid!$A$1:$LI$1),FALSE) -> #VALUE! | L50: =VLOOKUP($E50,Hybrid!$1:$1048576,MATCH(DATE(L$2,1,1),Hybrid!$A$1:$LI$1),FALSE) -> #VALUE! | M50: =VLOOKUP($E50,Hybrid!$1:$1048576,MATCH(DATE(M$2,1,1),Hybrid!$A$1:$LI$1),FALSE) -> #VALUE! | ... BI50: =VLOOKUP($E50,Hybrid!$1:$1048576,MATCH(DATE(BI$2,1,1),Hybrid!$A$1:$LI$1),FALSE) -> #VALUE!
D51: class F | E51: AUTO_cf_cgas_0 | F51: =VLOOKUP($E51,Hybrid!$1:$1048576,MATCH(DATE(F$2,1,1),Hybrid!$A$1:$LI$1),FALSE) -> #VALUE! | G51: =VLOOKUP($E51,Hybrid!$1:$1048576,MATCH(DATE(G$2,1,1),Hybrid!$A$1:$LI$1),FALSE) -> #VALUE! | H51: =VLOOKUP($E51,Hybrid!$1:$1048576,MATCH(DATE(H$2,1,1),Hybrid!$A$1:$LI$1),FALSE) -> #VALUE! | I51: =VLOOKUP($E51,Hybrid!$1:$1048576,MATCH(DATE(I$2,1,1),Hybrid!$A$1:$LI$1),FALSE) -> #VALUE! | J51: =VLOOKUP($E51,Hybrid!$1:$1048576,MATCH(DATE(J$2,1,1),Hybrid!$A$1:$LI$1),FALSE) -> #VALUE! | K51: =VLOOKUP($E51,Hybrid!$1:$1048576,MATCH(DATE(K$2,1,1),Hybrid!$A$1:$LI$1),FALSE) -> #VALUE! | L51: =VLOOKUP($E51,Hybrid!$1:$1048576,MATCH(DATE(L$2,1,1),Hybrid!$A$1:$LI$1),FALSE) -> #VALUE! | M51: =VLOOKUP($E51,Hybrid!$1:$1048576,MATCH(DATE(M$2,1,1),Hybrid!$A$1:$LI$1),FALSE) -> #VALUE! | ... BI51: =VLOOKUP($E51,Hybrid!$1:$1048576,MATCH(DATE(BI$2,1,1),Hybrid!$A$1:$LI$1),FALSE) -> #VALUE!
D52: class G | E52: AUTO_cg_cgas_0 | F52: =VLOOKUP($E52,Hybrid!$1:$1048576,MATCH(DATE(F$2,1,1),Hybrid!$A$1:$LI$1),FALSE) -> #VALUE! | G52: =VLOOKUP($E52,Hybrid!$1:$1048576,MATCH(DATE(G$2,1,1),Hybrid!$A$1:$LI$1),FALSE) -> #VALUE! | H52: =VLOOKUP($E52,Hybrid!$1:$1048576,MATCH(DATE(H$2,1,1),Hybrid!$A$1:$LI$1),FALSE) -> #VALUE! | I52: =VLOOKUP($E52,Hybrid!$1:$1048576,MATCH(DATE(I$2,1,1),Hybrid!$A$1:$LI$1),FALSE) -> #VALUE! | J52: =VLOOKUP($E52,Hybrid!$1:$1048576,MATCH(DATE(J$2,1,1),Hybrid!$A$1:$LI$1),FALSE) -> #VALUE! | K52: =VLOOKUP($E52,Hybrid!$1:$1048576,MATCH(DATE(K$2,1,1),Hybrid!$A$1:$LI$1),FALSE) -> #VALUE! | L52: =VLOOKUP($E52,Hybrid!$1:$1048576,MATCH(DATE(L$2,1,1),Hybrid!$A$1:$LI$1),FALSE) -> #VALUE! | M52: =VLOOKUP($E52,Hybrid!$1:$1048576,MATCH(DATE(M$2,1,1),Hybrid!$A$1:$LI$1),FALSE) -> #VALUE! | ... BI52: =VLOOKUP($E52,Hybrid!$1:$1048576,MATCH(DATE(BI$2,1,1),Hybrid!$A$1:$LI$1),FALSE) -> #VALUE!
C53: TOTAL SALES SHOCK | E53: NEWAUTO_2 | F53: =VLOOKUP($E53,Hybrid!$1:$1048576,MATCH(DATE(F$2,1,1),Hybrid!$A$1:$LI$1),FALSE) -> #VALUE! | G53: =VLOOKUP($E53,Hybrid!$1:$1048576,MATCH(DATE(G$2,1,1),Hybrid!$A$1:$LI$1),FALSE) -> #VALUE! | H53: =VLOOKUP($E53,Hybrid!$1:$1048576,MATCH(DATE(H$2,1,1),Hybrid!$A$1:$LI$1),FALSE) -> #VALUE! | I53: =VLOOKUP($E53,Hybrid!$1:$1048576,MATCH(DATE(I$2,1,1),Hybrid!$A$1:$LI$1),FALSE) -> #VALUE! | J53: =VLOOKUP($E53,Hybrid!$1:$1048576,MATCH(DATE(J$2,1,1),Hybrid!$A$1:$LI$1),FALSE) -> #VALUE! | K53: =VLOOKUP($E53,Hybrid!$1:$1048576,MATCH(DATE(K$2,1,1),Hybrid!$A$1:$LI$1),FALSE) -> #VALUE! | L53: =VLOOKUP($E53,Hybrid!$1:$1048576,MATCH(DATE(L$2,1,1),Hybrid!$A$1:$LI$1),FALSE) -> #VALUE! | M53: =VLOOKUP($E53,Hybrid!$1:$1048576,MATCH(DATE(M$2,1,1),Hybrid!$A$1:$LI$1),FALSE) -> #VALUE! | ... BI53: =VLOOKUP($E53,Hybrid!$1:$1048576,MATCH(DATE(BI$2,1,1),Hybrid!$A$1:$LI$1),FALSE) -> #VALUE!
C54: OIL | E54: NEWAUTO_cfut_2 | F54: =VLOOKUP($E54,Hybrid!$1:$1048576,MATCH(DATE(F$2,1,1),Hybrid!$A$1:$LI$1),FALSE) -> #VALUE! | G54: =VLOOKUP($E54,Hybrid!$1:$1048576,MATCH(DATE(G$2,1,1),Hybrid!$A$1:$LI$1),FALSE) -> #VALUE! | H54: =VLOOKUP($E54,Hybrid!$1:$1048576,MATCH(DATE(H$2,1,1),Hybrid!$A$1:$LI$1),FALSE) -> #VALUE! | I54: =VLOOKUP($E54,Hybrid!$1:$1048576,MATCH(DATE(I$2,1,1),Hybrid!$A$1:$LI$1),FALSE) -> #VALUE! | J54: =VLOOKUP($E54,Hybrid!$1:$1048576,MATCH(DATE(J$2,1,1),Hybrid!$A$1:$LI$1),FALSE) -> #VALUE! | K54: =VLOOKUP($E54,Hybrid!$1:$1048576,MATCH(DATE(K$2,1,1),Hybrid!$A$1:$LI$1),FALSE) -> #VALUE! | L54: =VLOOKUP($E54,Hybrid!$1:$1048576,MATCH(DATE(L$2,1,1),Hybrid!$A$1:$LI$1),FALSE) -> #VALUE! | M54: =VLOOKUP($E54,Hybrid!$1:$1048576,MATCH(DATE(M$2,1,1),Hybrid!$A$1:$LI$1),FALSE) -> #VALUE! | ... BI54: =VLOOKUP($E54,Hybrid!$1:$1048576,MATCH(DATE(BI$2,1,1),Hybrid!$A$1:$LI$1),FALSE) -> #VALUE!
D55: class A | E55: NEWAUTO_ca_cfut_2 | F55: =VLOOKUP($E55,Hybrid!$1:$1048576,MATCH(DATE(F$2,1,1),Hybrid!$A$1:$LI$1),FALSE) -> #VALUE! | G55: =VLOOKUP($E55,Hybrid!$1:$1048576,MATCH(DATE(G$2,1,1),Hybrid!$A$1:$LI$1),FALSE) -> #VALUE! | H55: =VLOOKUP($E55,Hybrid!$1:$1048576,MATCH(DATE(H$2,1,1),Hybrid!$A$1:$LI$1),FALSE) -> #VALUE! | I55: =VLOOKUP($E55,Hybrid!$1:$1048576,MATCH(DATE(I$2,1,1),Hybrid!$A$1:$LI$1),FALSE) -> #VALUE! | J55: =VLOOKUP($E55,Hybrid!$1:$1048576,MATCH(DATE(J$2,1,1),Hybrid!$A$1:$LI$1),FALSE) -> #VALUE! | K55: =VLOOKUP($E55,Hybrid!$1:$1048576,MATCH(DATE(K$2,1,1),Hybrid!$A$1:$LI$1),FALSE) -> #VALUE! | L55: =VLOOKUP($E55,Hybrid!$1:$1048576,MATCH(DATE(L$2,1,1),Hybrid!$A$1:$LI$1),FALSE) -> #VALUE! | M55: =VLOOKUP($E55,Hybrid!$1:$1048576,MATCH(DATE(M$2,1,1),Hybrid!$A$1:$LI$1),FALSE) -> #VALUE! | ... BI55: =VLOOKUP($E55,Hybrid!$1:$1048576,MATCH(DATE(BI$2,1,1),Hybrid!$A$1:$LI$1),FALSE) -> #VALUE!
D56: class B | E56: NEWAUTO_cb_cfut_2 | F56: =VLOOKUP($E56,Hybrid!$1:$1048576,MATCH(DATE(F$2,1,1),Hybrid!$A$1:$LI$1),FALSE) -> #VALUE! | G56: =VLOOKUP($E56,Hybrid!$1:$1048576,MATCH(DATE(G$2,1,1),Hybrid!$A$1:$LI$1),FALSE) -> #VALUE! | H56: =VLOOKUP($E56,Hybrid!$1:$1048576,MATCH(DATE(H$2,1,1),Hybrid!$A$1:$LI$1),FALSE) -> #VALUE! | I56: =VLOOKUP($E56,Hybrid!$1:$1048576,MATCH(DATE(I$2,1,1),Hybrid!$A$1:$LI$1),FALSE) -> #VALUE! | J56: =VLOOKUP($E56,Hybrid!$1:$1048576,MATCH(DATE(J$2,1,1),Hybrid!$A$1:$LI$1),FALSE) -> #VALUE! | K56: =VLOOKUP($E56,Hybrid!$1:$1048576,MATCH(DATE(K$2,1,1),Hybrid!$A$1:$LI$1),FALSE) -> #VALUE! | L56: =VLOOKUP($E56,Hybrid!$1:$1048576,MATCH(DATE(L$2,1,1),Hybrid!$A$1:$LI$1),FALSE) -> #VALUE! | M56: =VLOOKUP($E56,Hybrid!$1:$1048576,MATCH(DATE(M$2,1,1),Hybrid!$A$1:$LI$1),FALSE) -> #VALUE! | ... BI56: =VLOOKUP($E56,Hybrid!$1:$1048576,MATCH(DATE(BI$2,1,1),Hybrid!$A$1:$LI$1),FALSE) -> #VALUE!
D57: class C | E57: NEWAUTO_cc_cfut_2 | F57: =VLOOKUP($E57,Hybrid!$1:$1048576,MATCH(DATE(F$2,1,1),Hybrid!$A$1:$LI$1),FALSE) -> #VALUE! | G57: =VLOOKUP($E57,Hybrid!$1:$1048576,MATCH(DATE(G$2,1,1),Hybrid!$A$1:$LI$1),FALSE) -> #VALUE! | H57: =VLOOKUP($E57,Hybrid!$1:$1048576,MATCH(DATE(H$2,1,1),Hybrid!$A$1:$LI$1),FALSE) -> #VALUE! | I57: =VLOOKUP($E57,Hybrid!$1:$1048576,MATCH(DATE(I$2,1,1),Hybrid!$A$1:$LI$1),FALSE) -> #VALUE! | J57: =VLOOKUP($E57,Hybrid!$1:$1048576,MATCH(DATE(J$2,1,1),Hybrid!$A$1:$LI$1),FALSE) -> #VALUE! | K57: =VLOOKUP($E57,Hybrid!$1:$1048576,MATCH(DATE(K$2,1,1),Hybrid!$A$1:$LI$1),FALSE) -> #VALUE! | L57: =VLOOKUP($E57,Hybrid!$1:$1048576,MATCH(DATE(L$2,1,1),Hybrid!$A$1:$LI$1),FALSE) -> #VALUE! | M57: =VLOOKUP($E57,Hybrid!$1:$1048576,MATCH(DATE(M$2,1,1),Hybrid!$A$1:$LI$1),FALSE) -> #VALUE! | ... BI57: =VLOOKUP($E57,Hybrid!$1:$1048576,MATCH(DATE(BI$2,1,1),Hybrid!$A$1:$LI$1),FALSE) -> #VALUE!
D58: class D | E58: NEWAUTO_cd_cfut_2 | F58: =VLOOKUP($E58,Hybrid!$1:$1048576,MATCH(DATE(F$2,1,1),Hybrid!$A$1:$LI$1),FALSE) -> #VALUE! | G58: =VLOOKUP($E58,Hybrid!$1:$1048576,MATCH(DATE(G$2,1,1),Hybrid!$A$1:$LI$1),FALSE) -> #VALUE! | H58: =VLOOKUP($E58,Hybrid!$1:$1048576,MATCH(DATE(H$2,1,1),Hybrid!$A$1:$LI$1),FALSE) -> #VALUE! | I58: =VLOOKUP($E58,Hybrid!$1:$1048576,MATCH(DATE(I$2,1,1),Hybrid!$A$1:$LI$1),FALSE) -> #VALUE! | J58: =VLOOKUP($E58,Hybrid!$1:$1048576,MATCH(DATE(J$2,1,1),Hybrid!$A$1:$LI$1),FALSE) -> #VALUE! | K58: =VLOOKUP($E58,Hybrid!$1:$1048576,MATCH(DATE(K$2,1,1),Hybrid!$A$1:$LI$1),FALSE) -> #VALUE! | L58: =VLOOKUP($E58,Hybrid!$1:$1048576,MATCH(DATE(L$2,1,1),Hybrid!$A$1:$LI$1),FALSE) -> #VALUE! | M58: =VLOOKUP($E58,Hybrid!$1:$1048576,MATCH(DATE(M$2,1,1),Hybrid!$A$1:$LI$1),FALSE) -> #VALUE! | ... BI58: =VLOOKUP($E58,Hybrid!$1:$1048576,MATCH(DATE(BI$2,1,1),Hybrid!$A$1:$LI$1),FALSE) -> #VALUE!
D59: class E | E59: NEWAUTO_ce_cfut_2 | F59: =VLOOKUP($E59,Hybrid!$1:$1048576,MATCH(DATE(F$2,1,1),Hybrid!$A$1:$LI$1),FALSE) -> #VALUE! | G59: =VLOOKUP($E59,Hybrid!$1:$1048576,MATCH(DATE(G$2,1,1),Hybrid!$A$1:$LI$1),FALSE) -> #VALUE! | H59: =VLOOKUP($E59,Hybrid!$1:$1048576,MATCH(DATE(H$2,1,1),Hybrid!$A$1:$LI$1),FALSE) -> #VALUE! | I59: =VLOOKUP($E59,Hybrid!$1:$1048576,MATCH(DATE(I$2,1,1),Hybrid!$A$1:$LI$1),FALSE) -> #VALUE! | J59: =VLOOKUP($E59,Hybrid!$1:$1048576,MATCH(DATE(J$2,1,1),Hybrid!$A$1:$LI$1),FALSE) -> #VALUE! | K59: =VLOOKUP($E59,Hybrid!$1:$1048576,MATCH(DATE(K$2,1,1),Hybrid!$A$1:$LI$1),FALSE) -> #VALUE! | L59: =VLOOKUP($E59,Hybrid!$1:$1048576,MATCH(DATE(L$2,1,1),Hybrid!$A$1:$LI$1),FALSE) -> #VALUE! | M59: =VLOOKUP($E59,Hybrid!$1:$1048576,MATCH(DATE(M$2,1,1),Hybrid!$A$1:$LI$1),FALSE) -> #VALUE! | ... BI59: =VLOOKUP($E59,Hybrid!$1:$1048576,MATCH(DATE(BI$2,1,1),Hybrid!$A$1:$LI$1),FALSE) -> #VALUE!
D60: class F | E60: NEWAUTO_cf_cfut_2 | F60: =VLOOKUP($E60,Hybrid!$1:$1048576,MATCH(DATE(F$2,1,1),Hybrid!$A$1:$LI$1),FALSE) -> #VALUE! | G60: =VLOOKUP($E60,Hybrid!$1:$1048576,MATCH(DATE(G$2,1,1),Hybrid!$A$1:$LI$1),FALSE) -> #VALUE! | H60: =VLOOKUP($E60,Hybrid!$1:$1048576,MATCH(DATE(H$2,1,1),Hybrid!$A$1:$LI$1),FALSE) -> #VALUE! | I60: =VLOOKUP($E60,Hybrid!$1:$1048576,MATCH(DATE(I$2,1,1),Hybrid!$A$1:$LI$1),FALSE) -> #VALUE! | J60: =VLOOKUP($E60,Hybrid!$1:$1048576,MATCH(DATE(J$2,1,1),Hybrid!$A$1:$LI$1),FALSE) -> #VALUE! | K60: =VLOOKUP($E60,Hybrid!$1:$1048576,MATCH(DATE(K$2,1,1),Hybrid!$A$1:$LI$1),FALSE) -> #VALUE! | L60: =VLOOKUP($E60,Hybrid!$1:$1048576,MATCH(DATE(L$2,1,1),Hybrid!$A$1:$LI$1),FALSE) -> #VALUE! | M60: =VLOOKUP($E60,Hybrid!$1:$1048576,MATCH(DATE(M$2,1,1),Hybrid!$A$1:$LI$1),FALSE) -> #VALUE! | ... BI60: =VLOOKUP($E60,Hybrid!$1:$1048576,MATCH(DATE(BI$2,1,1),Hybrid!$A$1:$LI$1),FALSE) -> #VALUE!
D61: class G | E61: NEWAUTO_cg_cfut_2 | F61: =VLOOKUP($E61,Hybrid!$1:$1048576,MATCH(DATE(F$2,1,1),Hybrid!$A$1:$LI$1),FALSE) -> #VALUE! | G61: =VLOOKUP($E61,Hybrid!$1:$1048576,MATCH(DATE(G$2,1,1),Hybrid!$A$1:$LI$1),FALSE) -> #VALUE! | H61: =VLOOKUP($E61,Hybrid!$1:$1048576,MATCH(DATE(H$2,1,1),Hybrid!$A$1:$LI$1),FALSE) -> #VALUE! | I61: =VLOOKUP($E61,Hybrid!$1:$1048576,MATCH(DATE(I$2,1,1),Hybrid!$A$1:$LI$1),FALSE) -> #VALUE! | J61: =VLOOKUP($E61,Hybrid!$1:$1048576,MATCH(DATE(J$2,1,1),Hybrid!$A$1:$LI$1),FALSE) -> #VALUE! | K61: =VLOOKUP($E61,Hybrid!$1:$1048576,MATCH(DATE(K$2,1,1),Hybrid!$A$1:$LI$1),FALSE) -> #VALUE! | L61: =VLOOKUP($E61,Hybrid!$1:$1048576,MATCH(DATE(L$2,1,1),Hybrid!$A$1:$LI$1),FALSE) -> #VALUE! | M61: =VLOOKUP($E61,Hybrid!$1:$1048576,MATCH(DATE(M$2,1,1),Hybrid!$A$1:$LI$1),FALSE) -> #VALUE! | ... BI61: =VLOOKUP($E61,Hybrid!$1:$1048576,MATCH(DATE(BI$2,1,1),Hybrid!$A$1:$LI$1),FALSE) -> #VALUE!
C62: ELEC | E62: NEWAUTO_cele_2 | F62: =VLOOKUP($E62,Hybrid!$1:$1048576,MATCH(DATE(F$2,1,1),Hybrid!$A$1:$LI$1),FALSE) -> #VALUE! | G62: =VLOOKUP($E62,Hybrid!$1:$1048576,MATCH(DATE(G$2,1,1),Hybrid!$A$1:$LI$1),FALSE) -> #VALUE! | H62: =VLOOKUP($E62,Hybrid!$1:$1048576,MATCH(DATE(H$2,1,1),Hybrid!$A$1:$LI$1),FALSE) -> #VALUE! | I62: =VLOOKUP($E62,Hybrid!$1:$1048576,MATCH(DATE(I$2,1,1),Hybrid!$A$1:$LI$1),FALSE) -> #VALUE! | J62: =VLOOKUP($E62,Hybrid!$1:$1048576,MATCH(DATE(J$2,1,1),Hybrid!$A$1:$LI$1),FALSE) -> #VALUE! | K62: =VLOOKUP($E62,Hybrid!$1:$1048576,MATCH(DATE(K$2,1,1),Hybrid!$A$1:$LI$1),FALSE) -> #VALUE! | L62: =VLOOKUP($E62,Hybrid!$1:$1048576,MATCH(DATE(L$2,1,1),Hybrid!$A$1:$LI$1),FALSE) -> #VALUE! | M62: =VLOOKUP($E62,Hybrid!$1:$1048576,MATCH(DATE(M$2,1,1),Hybrid!$A$1:$LI$1),FALSE) -> #VALUE! | ... BI62: =VLOOKUP($E62,Hybrid!$1:$1048576,MATCH(DATE(BI$2,1,1),Hybrid!$A$1:$LI$1),FALSE) -> #VALUE!
D63: class A | E63: NEWAUTO_ca_cele_2 | F63: =VLOOKUP($E63,Hybrid!$1:$1048576,MATCH(DATE(F$2,1,1),Hybrid!$A$1:$LI$1),FALSE) -> #VALUE! | G63: =VLOOKUP($E63,Hybrid!$1:$1048576,MATCH(DATE(G$2,1,1),Hybrid!$A$1:$LI$1),FALSE) -> #VALUE! | H63: =VLOOKUP($E63,Hybrid!$1:$1048576,MATCH(DATE(H$2,1,1),Hybrid!$A$1:$LI$1),FALSE) -> #VALUE! | I63: =VLOOKUP($E63,Hybrid!$1:$1048576,MATCH(DATE(I$2,1,1),Hybrid!$A$1:$LI$1),FALSE) -> #VALUE! | J63: =VLOOKUP($E63,Hybrid!$1:$1048576,MATCH(DATE(J$2,1,1),Hybrid!$A$1:$LI$1),FALSE) -> #VALUE! | K63: =VLOOKUP($E63,Hybrid!$1:$1048576,MATCH(DATE(K$2,1,1),Hybrid!$A$1:$LI$1),FALSE) -> #VALUE! | L63: =VLOOKUP($E63,Hybrid!$1:$1048576,MATCH(DATE(L$2,1,1),Hybrid!$A$1:$LI$1),FALSE) -> #VALUE! | M63: =VLOOKUP($E63,Hybrid!$1:$1048576,MATCH(DATE(M$2,1,1),Hybrid!$A$1:$LI$1),FALSE) -> #VALUE! | ... BI63: =VLOOKUP($E63,Hybrid!$1:$1048576,MATCH(DATE(BI$2,1,1),Hybrid!$A$1:$LI$1),FALSE) -> #VALUE!
D64: class B | E64: NEWAUTO_cb_cele_2 | F64: =VLOOKUP($E64,Hybrid!$1:$1048576,MATCH(DATE(F$2,1,1),Hybrid!$A$1:$LI$1),FALSE) -> #VALUE! | G64: =VLOOKUP($E64,Hybrid!$1:$1048576,MATCH(DATE(G$2,1,1),Hybrid!$A$1:$LI$1),FALSE) -> #VALUE! | H64: =VLOOKUP($E64,Hybrid!$1:$1048576,MATCH(DATE(H$2,1,1),Hybrid!$A$1:$LI$1),FALSE) -> #VALUE! | I64: =VLOOKUP($E64,Hybrid!$1:$1048576,MATCH(DATE(I$2,1,1),Hybrid!$A$1:$LI$1),FALSE) -> #VALUE! | J64: =VLOOKUP($E64,Hybrid!$1:$1048576,MATCH(DATE(J$2,1,1),Hybrid!$A$1:$LI$1),FALSE) -> #VALUE! | K64: =VLOOKUP($E64,Hybrid!$1:$1048576,MATCH(DATE(K$2,1,1),Hybrid!$A$1:$LI$1),FALSE) -> #VALUE! | L64: =VLOOKUP($E64,Hybrid!$1:$1048576,MATCH(DATE(L$2,1,1),Hybrid!$A$1:$LI$1),FALSE) -> #VALUE! | M64: =VLOOKUP($E64,Hybrid!$1:$1048576,MATCH(DATE(M$2,1,1),Hybrid!$A$1:$LI$1),FALSE) -> #VALUE! | ... BI64: =VLOOKUP($E64,Hybrid!$1:$1048576,MATCH(DATE(BI$2,1,1),Hybrid!$A$1:$LI$1),FALSE) -> #VALUE!
D65: class C | E65: NEWAUTO_cc_cele_2 | F65: =VLOOKUP($E65,Hybrid!$1:$1048576,MATCH(DATE(F$2,1,1),Hybrid!$A$1:$LI$1),FALSE) -> #VALUE! | G65: =VLOOKUP($E65,Hybrid!$1:$1048576,MATCH(DATE(G$2,1,1),Hybrid!$A$1:$LI$1),FALSE) -> #VALUE! | H65: =VLOOKUP($E65,Hybrid!$1:$1048576,MATCH(DATE(H$2,1,1),Hybrid!$A$1:$LI$1),FALSE) -> #VALUE! | I65: =VLOOKUP($E65,Hybrid!$1:$1048576,MATCH(DATE(I$2,1,1),Hybrid!$A$1:$LI$1),FALSE) -> #VALUE! | J65: =VLOOKUP($E65,Hybrid!$1:$1048576,MATCH(DATE(J$2,1,1),Hybrid!$A$1:$LI$1),FALSE) -> #VALUE! | K65: =VLOOKUP($E65,Hybrid!$1:$1048576,MATCH(DATE(K$2,1,1),Hybrid!$A$1:$LI$1),FALSE) -> #VALUE! | L65: =VLOOKUP($E65,Hybrid!$1:$1048576,MATCH(DATE(L$2,1,1),Hybrid!$A$1:$LI$1),FALSE) -> #VALUE! | M65: =VLOOKUP($E65,Hybrid!$1:$1048576,MATCH(DATE(M$2,1,1),Hybrid!$A$1:$LI$1),FALSE) -> #VALUE! | ... BI65: =VLOOKUP($E65,Hybrid!$1:$1048576,MATCH(DATE(BI$2,1,1),Hybrid!$A$1:$LI$1),FALSE) -> #VALUE!
D66: class D | E66: NEWAUTO_cd_cele_2 | F66: =VLOOKUP($E66,Hybrid!$1:$1048576,MATCH(DATE(F$2,1,1),Hybrid!$A$1:$LI$1),FALSE) -> #VALUE! | G66: =VLOOKUP($E66,Hybrid!$1:$1048576,MATCH(DATE(G$2,1,1),Hybrid!$A$1:$LI$1),FALSE) -> #VALUE! | H66: =VLOOKUP($E66,Hybrid!$1:$1048576,MATCH(DATE(H$2,1,1),Hybrid!$A$1:$LI$1),FALSE) -> #VALUE! | I66: =VLOOKUP($E66,Hybrid!$1:$1048576,MATCH(DATE(I$2,1,1),Hybrid!$A$1:$LI$1),FALSE) -> #VALUE! | J66: =VLOOKUP($E66,Hybrid!$1:$1048576,MATCH(DATE(J$2,1,1),Hybrid!$A$1:$LI$1),FALSE) -> #VALUE! | K66: =VLOOKUP($E66,Hybrid!$1:$1048576,MATCH(DATE(K$2,1,1),Hybrid!$A$1:$LI$1),FALSE) -> #VALUE! | L66: =VLOOKUP($E66,Hybrid!$1:$1048576,MATCH(DATE(L$2,1,1),Hybrid!$A$1:$LI$1),FALSE) -> #VALUE! | M66: =VLOOKUP($E66,Hybrid!$1:$1048576,MATCH(DATE(M$2,1,1),Hybrid!$A$1:$LI$1),FALSE) -> #VALUE! | ... BI66: =VLOOKUP($E66,Hybrid!$1:$1048576,MATCH(DATE(BI$2,1,1),Hybrid!$A$1:$LI$1),FALSE) -> #VALUE!
D67: class E | E67: NEWAUTO_ce_cele_2 | F67: =VLOOKUP($E67,Hybrid!$1:$1048576,MATCH(DATE(F$2,1,1),Hybrid!$A$1:$LI$1),FALSE) -> #VALUE! | G67: =VLOOKUP($E67,Hybrid!$1:$1048576,MATCH(DATE(G$2,1,1),Hybrid!$A$1:$LI$1),FALSE) -> #VALUE! | H67: =VLOOKUP($E67,Hybrid!$1:$1048576,MATCH(DATE(H$2,1,1),Hybrid!$A$1:$LI$1),FALSE) -> #VALUE! | I67: =VLOOKUP($E67,Hybrid!$1:$1048576,MATCH(DATE(I$2,1,1),Hybrid!$A$1:$LI$1),FALSE) -> #VALUE! | J67: =VLOOKUP($E67,Hybrid!$1:$1048576,MATCH(DATE(J$2,1,1),Hybrid!$A$1:$LI$1),FALSE) -> #VALUE! | K67: =VLOOKUP($E67,Hybrid!$1:$1048576,MATCH(DATE(K$2,1,1),Hybrid!$A$1:$LI$1),FALSE) -> #VALUE! | L67: =VLOOKUP($E67,Hybrid!$1:$1048576,MATCH(DATE(L$2,1,1),Hybrid!$A$1:$LI$1),FALSE) -> #VALUE! | M67: =VLOOKUP($E67,Hybrid!$1:$1048576,MATCH(DATE(M$2,1,1),Hybrid!$A$1:$LI$1),FALSE) -> #VALUE! | ... BI67: =VLOOKUP($E67,Hybrid!$1:$1048576,MATCH(DATE(BI$2,1,1),Hybrid!$A$1:$LI$1),FALSE) -> #VALUE!
D68: class F | E68: NEWAUTO_cf_cele_2 | F68: =VLOOKUP($E68,Hybrid!$1:$1048576,MATCH(DATE(F$2,1,1),Hybrid!$A$1:$LI$1),FALSE) -> #VALUE! | G68: =VLOOKUP($E68,Hybrid!$1:$1048576,MATCH(DATE(G$2,1,1),Hybrid!$A$1:$LI$1),FALSE) -> #VALUE! | H68: =VLOOKUP($E68,Hybrid!$1:$1048576,MATCH(DATE(H$2,1,1),Hybrid!$A$1:$LI$1),FALSE) -> #VALUE! | I68: =VLOOKUP($E68,Hybrid!$1:$1048576,MATCH(DATE(I$2,1,1),Hybrid!$A$1:$LI$1),FALSE) -> #VALUE! | J68: =VLOOKUP($E68,Hybrid!$1:$1048576,MATCH(DATE(J$2,1,1),Hybrid!$A$1:$LI$1),FALSE) -> #VALUE! | K68: =VLOOKUP($E68,Hybrid!$1:$1048576,MATCH(DATE(K$2,1,1),Hybrid!$A$1:$LI$1),FALSE) -> #VALUE! | L68: =VLOOKUP($E68,Hybrid!$1:$1048576,MATCH(DATE(L$2,1,1),Hybrid!$A$1:$LI$1),FALSE) -> #VALUE! | M68: =VLOOKUP($E68,Hybrid!$1:$1048576,MATCH(DATE(M$2,1,1),Hybrid!$A$1:$LI$1),FALSE) -> #VALUE! | ... BI68: =VLOOKUP($E68,Hybrid!$1:$1048576,MATCH(DATE(BI$2,1,1),Hybrid!$A$1:$LI$1),FALSE) -> #VALUE!
D69: class G | E69: NEWAUTO_cg_cele_2 | F69: =VLOOKUP($E69,Hybrid!$1:$1048576,MATCH(DATE(F$2,1,1),Hybrid!$A$1:$LI$1),FALSE) -> #VALUE! | G69: =VLOOKUP($E69,Hybrid!$1:$1048576,MATCH(DATE(G$2,1,1),Hybrid!$A$1:$LI$1),FALSE) -> #VALUE! | H69: =VLOOKUP($E69,Hybrid!$1:$1048576,MATCH(DATE(H$2,1,1),Hybrid!$A$1:$LI$1),FALSE) -> #VALUE! | I69: =VLOOKUP($E69,Hybrid!$1:$1048576,MATCH(DATE(I$2,1,1),Hybrid!$A$1:$LI$1),FALSE) -> #VALUE! | J69: =VLOOKUP($E69,Hybrid!$1:$1048576,MATCH(DATE(J$2,1,1),Hybrid!$A$1:$LI$1),FALSE) -> #VALUE! | K69: =VLOOKUP($E69,Hybrid!$1:$1048576,MATCH(DATE(K$2,1,1),Hybrid!$A$1:$LI$1),FALSE) -> #VALUE! | L69: =VLOOKUP($E69,Hybrid!$1:$1048576,MATCH(DATE(L$2,1,1),Hybrid!$A$1:$LI$1),FALSE) -> #VALUE! | M69: =VLOOKUP($E69,Hybrid!$1:$1048576,MATCH(DATE(M$2,1,1),Hybrid!$A$1:$LI$1),FALSE) -> #VALUE! | ... BI69: =VLOOKUP($E69,Hybrid!$1:$1048576,MATCH(DATE(BI$2,1,1),Hybrid!$A$1:$LI$1),FALSE) -> #VALUE!
C70: GAS | E70: NEWAUTO_cgas_2 | F70: =VLOOKUP($E70,Hybrid!$1:$1048576,MATCH(DATE(F$2,1,1),Hybrid!$A$1:$LI$1),FALSE) -> #VALUE! | G70: =VLOOKUP($E70,Hybrid!$1:$1048576,MATCH(DATE(G$2,1,1),Hybrid!$A$1:$LI$1),FALSE) -> #VALUE! | H70: =VLOOKUP($E70,Hybrid!$1:$1048576,MATCH(DATE(H$2,1,1),Hybrid!$A$1:$LI$1),FALSE) -> #VALUE! | I70: =VLOOKUP($E70,Hybrid!$1:$1048576,MATCH(DATE(I$2,1,1),Hybrid!$A$1:$LI$1),FALSE) -> #VALUE! | J70: =VLOOKUP($E70,Hybrid!$1:$1048576,MATCH(DATE(J$2,1,1),Hybrid!$A$1:$LI$1),FALSE) -> #VALUE! | K70: =VLOOKUP($E70,Hybrid!$1:$1048576,MATCH(DATE(K$2,1,1),Hybrid!$A$1:$LI$1),FALSE) -> #VALUE! | L70: =VLOOKUP($E70,Hybrid!$1:$1048576,MATCH(DATE(L$2,1,1),Hybrid!$A$1:$LI$1),FALSE) -> #VALUE! | M70: =VLOOKUP($E70,Hybrid!$1:$1048576,MATCH(DATE(M$2,1,1),Hybrid!$A$1:$LI$1),FALSE) -> #VALUE! | ... BI70: =VLOOKUP($E70,Hybrid!$1:$1048576,MATCH(DATE(BI$2,1,1),Hybrid!$A$1:$LI$1),FALSE) -> #VALUE!
D71: class A | E71: NEWAUTO_ca_cgas_2 | F71: =VLOOKUP($E71,Hybrid!$1:$1048576,MATCH(DATE(F$2,1,1),Hybrid!$A$1:$LI$1),FALSE) -> #VALUE! | G71: =VLOOKUP($E71,Hybrid!$1:$1048576,MATCH(DATE(G$2,1,1),Hybrid!$A$1:$LI$1),FALSE) -> #VALUE! | H71: =VLOOKUP($E71,Hybrid!$1:$1048576,MATCH(DATE(H$2,1,1),Hybrid!$A$1:$LI$1),FALSE) -> #VALUE! | I71: =VLOOKUP($E71,Hybrid!$1:$1048576,MATCH(DATE(I$2,1,1),Hybrid!$A$1:$LI$1),FALSE) -> #VALUE! | J71: =VLOOKUP($E71,Hybrid!$1:$1048576,MATCH(DATE(J$2,1,1),Hybrid!$A$1:$LI$1),FALSE) -> #VALUE! | K71: =VLOOKUP($E71,Hybrid!$1:$1048576,MATCH(DATE(K$2,1,1),Hybrid!$A$1:$LI$1),FALSE) -> #VALUE! | L71: =VLOOKUP($E71,Hybrid!$1:$1048576,MATCH(DATE(L$2,1,1),Hybrid!$A$1:$LI$1),FALSE) -> #VALUE! | M71: =VLOOKUP($E71,Hybrid!$1:$1048576,MATCH(DATE(M$2,1,1),Hybrid!$A$1:$LI$1),FALSE) -> #VALUE! | ... BI71: =VLOOKUP($E71,Hybrid!$1:$1048576,MATCH(DATE(BI$2,1,1),Hybrid!$A$1:$LI$1),FALSE) -> #VALUE!
D72: class B | E72: NEWAUTO_cb_cgas_2 | F72: =VLOOKUP($E72,Hybrid!$1:$1048576,MATCH(DATE(F$2,1,1),Hybrid!$A$1:$LI$1),FALSE) -> #VALUE! | G72: =VLOOKUP($E72,Hybrid!$1:$1048576,MATCH(DATE(G$2,1,1),Hybrid!$A$1:$LI$1),FALSE) -> #VALUE! | H72: =VLOOKUP($E72,Hybrid!$1:$1048576,MATCH(DATE(H$2,1,1),Hybrid!$A$1:$LI$1),FALSE) -> #VALUE! | I72: =VLOOKUP($E72,Hybrid!$1:$1048576,MATCH(DATE(I$2,1,1),Hybrid!$A$1:$LI$1),FALSE) -> #VALUE! | J72: =VLOOKUP($E72,Hybrid!$1:$1048576,MATCH(DATE(J$2,1,1),Hybrid!$A$1:$LI$1),FALSE) -> #VALUE! | K72: =VLOOKUP($E72,Hybrid!$1:$1048576,MATCH(DATE(K$2,1,1),Hybrid!$A$1:$LI$1),FALSE) -> #VALUE! | L72: =VLOOKUP($E72,Hybrid!$1:$1048576,MATCH(DATE(L$2,1,1),Hybrid!$A$1:$LI$1),FALSE) -> #VALUE! | M72: =VLOOKUP($E72,Hybrid!$1:$1048576,MATCH(DATE(M$2,1,1),Hybrid!$A$1:$LI$1),FALSE) -> #VALUE! | ... BI72: =VLOOKUP($E72,Hybrid!$1:$1048576,MATCH(DATE(BI$2,1,1),Hybrid!$A$1:$LI$1),FALSE) -> #VALUE!
D73: class C | E73: NEWAUTO_cc_cgas_2 | F73: =VLOOKUP($E73,Hybrid!$1:$1048576,MATCH(DATE(F$2,1,1),Hybrid!$A$1:$LI$1),FALSE) -> #VALUE! | G73: =VLOOKUP($E73,Hybrid!$1:$1048576,MATCH(DATE(G$2,1,1),Hybrid!$A$1:$LI$1),FALSE) -> #VALUE! | H73: =VLOOKUP($E73,Hybrid!$1:$1048576,MATCH(DATE(H$2,1,1),Hybrid!$A$1:$LI$1),FALSE) -> #VALUE! | I73: =VLOOKUP($E73,Hybrid!$1:$1048576,MATCH(DATE(I$2,1,1),Hybrid!$A$1:$LI$1),FALSE) -> #VALUE! | J73: =VLOOKUP($E73,Hybrid!$1:$1048576,MATCH(DATE(J$2,1,1),Hybrid!$A$1:$LI$1),FALSE) -> #VALUE! | K73: =VLOOKUP($E73,Hybrid!$1:$1048576,MATCH(DATE(K$2,1,1),Hybrid!$A$1:$LI$1),FALSE) -> #VALUE! | L73: =VLOOKUP($E73,Hybrid!$1:$1048576,MATCH(DATE(L$2,1,1),Hybrid!$A$1:$LI$1),FALSE) -> #VALUE! | M73: =VLOOKUP($E73,Hybrid!$1:$1048576,MATCH(DATE(M$2,1,1),Hybrid!$A$1:$LI$1),FALSE) -> #VALUE! | ... BI73: =VLOOKUP($E73,Hybrid!$1:$1048576,MATCH(DATE(BI$2,1,1),Hybrid!$A$1:$LI$1),FALSE) -> #VALUE!
D74: class D | E74: NEWAUTO_cd_cgas_2 | F74: =VLOOKUP($E74,Hybrid!$1:$1048576,MATCH(DATE(F$2,1,1),Hybrid!$A$1:$LI$1),FALSE) -> #VALUE! | G74: =VLOOKUP($E74,Hybrid!$1:$1048576,MATCH(DATE(G$2,1,1),Hybrid!$A$1:$LI$1),FALSE) -> #VALUE! | H74: =VLOOKUP($E74,Hybrid!$1:$1048576,MATCH(DATE(H$2,1,1),Hybrid!$A$1:$LI$1),FALSE) -> #VALUE! | I74: =VLOOKUP($E74,Hybrid!$1:$1048576,MATCH(DATE(I$2,1,1),Hybrid!$A$1:$LI$1),FALSE) -> #VALUE! | J74: =VLOOKUP($E74,Hybrid!$1:$1048576,MATCH(DATE(J$2,1,1),Hybrid!$A$1:$LI$1),FALSE) -> #VALUE! | K74: =VLOOKUP($E74,Hybrid!$1:$1048576,MATCH(DATE(K$2,1,1),Hybrid!$A$1:$LI$1),FALSE) -> #VALUE! | L74: =VLOOKUP($E74,Hybrid!$1:$1048576,MATCH(DATE(L$2,1,1),Hybrid!$A$1:$LI$1),FALSE) -> #VALUE! | M74: =VLOOKUP($E74,Hybrid!$1:$1048576,MATCH(DATE(M$2,1,1),Hybrid!$A$1:$LI$1),FALSE) -> #VALUE! | ... BI74: =VLOOKUP($E74,Hybrid!$1:$1048576,MATCH(DATE(BI$2,1,1),Hybrid!$A$1:$LI$1),FALSE) -> #VALUE!
D75: class E | E75: NEWAUTO_ce_cgas_2 | F75: =VLOOKUP($E75,Hybrid!$1:$1048576,MATCH(DATE(F$2,1,1),Hybrid!$A$1:$LI$1),FALSE) -> #VALUE! | G75: =VLOOKUP($E75,Hybrid!$1:$1048576,MATCH(DATE(G$2,1,1),Hybrid!$A$1:$LI$1),FALSE) -> #VALUE! | H75: =VLOOKUP($E75,Hybrid!$1:$1048576,MATCH(DATE(H$2,1,1),Hybrid!$A$1:$LI$1),FALSE) -> #VALUE! | I75: =VLOOKUP($E75,Hybrid!$1:$1048576,MATCH(DATE(I$2,1,1),Hybrid!$A$1:$LI$1),FALSE) -> #VALUE! | J75: =VLOOKUP($E75,Hybrid!$1:$1048576,MATCH(DATE(J$2,1,1),Hybrid!$A$1:$LI$1),FALSE) -> #VALUE! | K75: =VLOOKUP($E75,Hybrid!$1:$1048576,MATCH(DATE(K$2,1,1),Hybrid!$A$1:$LI$1),FALSE) -> #VALUE! | L75: =VLOOKUP($E75,Hybrid!$1:$1048576,MATCH(DATE(L$2,1,1),Hybrid!$A$1:$LI$1),FALSE) -> #VALUE! | M75: =VLOOKUP($E75,Hybrid!$1:$1048576,MATCH(DATE(M$2,1,1),Hybrid!$A$1:$LI$1),FALSE) -> #VALUE! | ... BI75: =VLOOKUP($E75,Hybrid!$1:$1048576,MATCH(DATE(BI$2,1,1),Hybrid!$A$1:$LI$1),FALSE) -> #VALUE!
D76: class F | E76: NEWAUTO_cf_cgas_2 | F76: =VLOOKUP($E76,Hybrid!$1:$1048576,MATCH(DATE(F$2,1,1),Hybrid!$A$1:$LI$1),FALSE) -> #VALUE! | G76: =VLOOKUP($E76,Hybrid!$1:$1048576,MATCH(DATE(G$2,1,1),Hybrid!$A$1:$LI$1),FALSE) -> #VALUE! | H76: =VLOOKUP($E76,Hybrid!$1:$1048576,MATCH(DATE(H$2,1,1),Hybrid!$A$1:$LI$1),FALSE) -> #VALUE! | I76: =VLOOKUP($E76,Hybrid!$1:$1048576,MATCH(DATE(I$2,1,1),Hybrid!$A$1:$LI$1),FALSE) -> #VALUE! | J76: =VLOOKUP($E76,Hybrid!$1:$1048576,MATCH(DATE(J$2,1,1),Hybrid!$A$1:$LI$1),FALSE) -> #VALUE! | K76: =VLOOKUP($E76,Hybrid!$1:$1048576,MATCH(DATE(K$2,1,1),Hybrid!$A$1:$LI$1),FALSE) -> #VALUE! | L76: =VLOOKUP($E76,Hybrid!$1:$1048576,MATCH(DATE(L$2,1,1),Hybrid!$A$1:$LI$1),FALSE) -> #VALUE! | M76: =VLOOKUP($E76,Hybrid!$1:$1048576,MATCH(DATE(M$2,1,1),Hybrid!$A$1:$LI$1),FALSE) -> #VALUE! | ... BI76: =VLOOKUP($E76,Hybrid!$1:$1048576,MATCH(DATE(BI$2,1,1),Hybrid!$A$1:$LI$1),FALSE) -> #VALUE!
D77: class G | E77: NEWAUTO_cg_cgas_2 | F77: =VLOOKUP($E77,Hybrid!$1:$1048576,MATCH(DATE(F$2,1,1),Hybrid!$A$1:$LI$1),FALSE) -> #VALUE! | G77: =VLOOKUP($E77,Hybrid!$1:$1048576,MATCH(DATE(G$2,1,1),Hybrid!$A$1:$LI$1),FALSE) -> #VALUE! | H77: =VLOOKUP($E77,Hybrid!$1:$1048576,MATCH(DATE(H$2,1,1),Hybrid!$A$1:$LI$1),FALSE) -> #VALUE! | I77: =VLOOKUP($E77,Hybrid!$1:$1048576,MATCH(DATE(I$2,1,1),Hybrid!$A$1:$LI$1),FALSE) -> #VALUE! | J77: =VLOOKUP($E77,Hybrid!$1:$1048576,MATCH(DATE(J$2,1,1),Hybrid!$A$1:$LI$1),FALSE) -> #VALUE! | K77: =VLOOKUP($E77,Hybrid!$1:$1048576,MATCH(DATE(K$2,1,1),Hybrid!$A$1:$LI$1),FALSE) -> #VALUE! | L77: =VLOOKUP($E77,Hybrid!$1:$1048576,MATCH(DATE(L$2,1,1),Hybrid!$A$1:$LI$1),FALSE) -> #VALUE! | M77: =VLOOKUP($E77,Hybrid!$1:$1048576,MATCH(DATE(M$2,1,1),Hybrid!$A$1:$LI$1),FALSE) -> #VALUE! | ... BI77: =VLOOKUP($E77,Hybrid!$1:$1048576,MATCH(DATE(BI$2,1,1),Hybrid!$A$1:$LI$1),FALSE) -> #VALUE!
C78: TOTAL SALES BASELINE | E78: NEWAUTO_0 | F78: =VLOOKUP($E78,Hybrid!$1:$1048576,MATCH(DATE(F$2,1,1),Hybrid!$A$1:$LI$1),FALSE) -> #VALUE! | G78: =VLOOKUP($E78,Hybrid!$1:$1048576,MATCH(DATE(G$2,1,1),Hybrid!$A$1:$LI$1),FALSE) -> #VALUE! | H78: =VLOOKUP($E78,Hybrid!$1:$1048576,MATCH(DATE(H$2,1,1),Hybrid!$A$1:$LI$1),FALSE) -> #VALUE! | I78: =VLOOKUP($E78,Hybrid!$1:$1048576,MATCH(DATE(I$2,1,1),Hybrid!$A$1:$LI$1),FALSE) -> #VALUE! | J78: =VLOOKUP($E78,Hybrid!$1:$1048576,MATCH(DATE(J$2,1,1),Hybrid!$A$1:$LI$1),FALSE) -> #VALUE! | K78: =VLOOKUP($E78,Hybrid!$1:$1048576,MATCH(DATE(K$2,1,1),Hybrid!$A$1:$LI$1),FALSE) -> #VALUE! | L78: =VLOOKUP($E78,Hybrid!$1:$1048576,MATCH(DATE(L$2,1,1),Hybrid!$A$1:$LI$1),FALSE) -> #VALUE! | M78: =VLOOKUP($E78,Hybrid!$1:$1048576,MATCH(DATE(M$2,1,1),Hybrid!$A$1:$LI$1),FALSE) -> #VALUE! | ... BI78: =VLOOKUP($E78,Hybrid!$1:$1048576,MATCH(DATE(BI$2,1,1),Hybrid!$A$1:$LI$1),FALSE) -> #VALUE!
C79: OIL | E79: NEWAUTO_cfut_0 | F79: =VLOOKUP($E79,Hybrid!$1:$1048576,MATCH(DATE(F$2,1,1),Hybrid!$A$1:$LI$1),FALSE) -> #VALUE! | G79: =VLOOKUP($E79,Hybrid!$1:$1048576,MATCH(DATE(G$2,1,1),Hybrid!$A$1:$LI$1),FALSE) -> #VALUE! | H79: =VLOOKUP($E79,Hybrid!$1:$1048576,MATCH(DATE(H$2,1,1),Hybrid!$A$1:$LI$1),FALSE) -> #VALUE! | I79: =VLOOKUP($E79,Hybrid!$1:$1048576,MATCH(DATE(I$2,1,1),Hybrid!$A$1:$LI$1),FALSE) -> #VALUE! | J79: =VLOOKUP($E79,Hybrid!$1:$1048576,MATCH(DATE(J$2,1,1),Hybrid!$A$1:$LI$1),FALSE) -> #VALUE! | K79: =VLOOKUP($E79,Hybrid!$1:$1048576,MATCH(DATE(K$2,1,1),Hybrid!$A$1:$LI$1),FALSE) -> #VALUE! | L79: =VLOOKUP($E79,Hybrid!$1:$1048576,MATCH(DATE(L$2,1,1),Hybrid!$A$1:$LI$1),FALSE) -> #VALUE! | M79: =VLOOKUP($E79,Hybrid!$1:$1048576,MATCH(DATE(M$2,1,1),Hybrid!$A$1:$LI$1),FALSE) -> #VALUE! | ... BI79: =VLOOKUP($E79,Hybrid!$1:$1048576,MATCH(DATE(BI$2,1,1),Hybrid!$A$1:$LI$1),FALSE) -> #VALUE!
D80: class A | E80: NEWAUTO_ca_cfut_0 | F80: =VLOOKUP($E80,Hybrid!$1:$1048576,MATCH(DATE(F$2,1,1),Hybrid!$A$1:$LI$1),FALSE) -> #VALUE! | G80: =VLOOKUP($E80,Hybrid!$1:$1048576,MATCH(DATE(G$2,1,1),Hybrid!$A$1:$LI$1),FALSE) -> #VALUE! | H80: =VLOOKUP($E80,Hybrid!$1:$1048576,MATCH(DATE(H$2,1,1),Hybrid!$A$1:$LI$1),FALSE) -> #VALUE! | I80: =VLOOKUP($E80,Hybrid!$1:$1048576,MATCH(DATE(I$2,1,1),Hybrid!$A$1:$LI$1),FALSE) -> #VALUE! | J80: =VLOOKUP($E80,Hybrid!$1:$1048576,MATCH(DATE(J$2,1,1),Hybrid!$A$1:$LI$1),FALSE) -> #VALUE! | K80: =VLOOKUP($E80,Hybrid!$1:$1048576,MATCH(DATE(K$2,1,1),Hybrid!$A$1:$LI$1),FALSE) -> #VALUE! | L80: =VLOOKUP($E80,Hybrid!$1:$1048576,MATCH(DATE(L$2,1,1),Hybrid!$A$1:$LI$1),FALSE) -> #VALUE! | M80: =VLOOKUP($E80,Hybrid!$1:$1048576,MATCH(DATE(M$2,1,1),Hybrid!$A$1:$LI$1),FALSE) -> #VALUE! | ... BI80: =VLOOKUP($E80,Hybrid!$1:$1048576,MATCH(DATE(BI$2,1,1),Hybrid!$A$1:$LI$1),FALSE) -> #VALUE!
D81: class B | E81: NEWAUTO_cb_cfut_0 | F81: =VLOOKUP($E81,Hybrid!$1:$1048576,MATCH(DATE(F$2,1,1),Hybrid!$A$1:$LI$1),FALSE) -> #VALUE! | G81: =VLOOKUP($E81,Hybrid!$1:$1048576,MATCH(DATE(G$2,1,1),Hybrid!$A$1:$LI$1),FALSE) -> #VALUE! | H81: =VLOOKUP($E81,Hybrid!$1:$1048576,MATCH(DATE(H$2,1,1),Hybrid!$A$1:$LI$1),FALSE) -> #VALUE! | I81: =VLOOKUP($E81,Hybrid!$1:$1048576,MATCH(DATE(I$2,1,1),Hybrid!$A$1:$LI$1),FALSE) -> #VALUE! | J81: =VLOOKUP($E81,Hybrid!$1:$1048576,MATCH(DATE(J$2,1,1),Hybrid!$A$1:$LI$1),FALSE) -> #VALUE! | K81: =VLOOKUP($E81,Hybrid!$1:$1048576,MATCH(DATE(K$2,1,1),Hybrid!$A$1:$LI$1),FALSE) -> #VALUE! | L81: =VLOOKUP($E81,Hybrid!$1:$1048576,MATCH(DATE(L$2,1,1),Hybrid!$A$1:$LI$1),FALSE) -> #VALUE! | M81: =VLOOKUP($E81,Hybrid!$1:$1048576,MATCH(DATE(M$2,1,1),Hybrid!$A$1:$LI$1),FALSE) -> #VALUE! | ... BI81: =VLOOKUP($E81,Hybrid!$1:$1048576,MATCH(DATE(BI$2,1,1),Hybrid!$A$1:$LI$1),FALSE) -> #VALUE!
D82: class C | E82: NEWAUTO_cc_cfut_0 | F82: =VLOOKUP($E82,Hybrid!$1:$1048576,MATCH(DATE(F$2,1,1),Hybrid!$A$1:$LI$1),FALSE) -> #VALUE! | G82: =VLOOKUP($E82,Hybrid!$1:$1048576,MATCH(DATE(G$2,1,1),Hybrid!$A$1:$LI$1),FALSE) -> #VALUE! | H82: =VLOOKUP($E82,Hybrid!$1:$1048576,MATCH(DATE(H$2,1,1),Hybrid!$A$1:$LI$1),FALSE) -> #VALUE! | I82: =VLOOKUP($E82,Hybrid!$1:$1048576,MATCH(DATE(I$2,1,1),Hybrid!$A$1:$LI$1),FALSE) -> #VALUE! | J82: =VLOOKUP($E82,Hybrid!$1:$1048576,MATCH(DATE(J$2,1,1),Hybrid!$A$1:$LI$1),FALSE) -> #VALUE! | K82: =VLOOKUP($E82,Hybrid!$1:$1048576,MATCH(DATE(K$2,1,1),Hybrid!$A$1:$LI$1),FALSE) -> #VALUE! | L82: =VLOOKUP($E82,Hybrid!$1:$1048576,MATCH(DATE(L$2,1,1),Hybrid!$A$1:$LI$1),FALSE) -> #VALUE! | M82: =VLOOKUP($E82,Hybrid!$1:$1048576,MATCH(DATE(M$2,1,1),Hybrid!$A$1:$LI$1),FALSE) -> #VALUE! | ... BI82: =VLOOKUP($E82,Hybrid!$1:$1048576,MATCH(DATE(BI$2,1,1),Hybrid!$A$1:$LI$1),FALSE) -> #VALUE!
D83: class D | E83: NEWAUTO_cd_cfut_0 | F83: =VLOOKUP($E83,Hybrid!$1:$1048576,MATCH(DATE(F$2,1,1),Hybrid!$A$1:$LI$1),FALSE) -> #VALUE! | G83: =VLOOKUP($E83,Hybrid!$1:$1048576,MATCH(DATE(G$2,1,1),Hybrid!$A$1:$LI$1),FALSE) -> #VALUE! | H83: =VLOOKUP($E83,Hybrid!$1:$1048576,MATCH(DATE(H$2,1,1),Hybrid!$A$1:$LI$1),FALSE) -> #VALUE! | I83: =VLOOKUP($E83,Hybrid!$1:$1048576,MATCH(DATE(I$2,1,1),Hybrid!$A$1:$LI$1),FALSE) -> #VALUE! | J83: =VLOOKUP($E83,Hybrid!$1:$1048576,MATCH(DATE(J$2,1,1),Hybrid!$A$1:$LI$1),FALSE) -> #VALUE! | K83: =VLOOKUP($E83,Hybrid!$1:$1048576,MATCH(DATE(K$2,1,1),Hybrid!$A$1:$LI$1),FALSE) -> #VALUE! | L83: =VLOOKUP($E83,Hybrid!$1:$1048576,MATCH(DATE(L$2,1,1),Hybrid!$A$1:$LI$1),FALSE) -> #VALUE! | M83: =VLOOKUP($E83,Hybrid!$1:$1048576,MATCH(DATE(M$2,1,1),Hybrid!$A$1:$LI$1),FALSE) -> #VALUE! | ... BI83: =VLOOKUP($E83,Hybrid!$1:$1048576,MATCH(DATE(BI$2,1,1),Hybrid!$A$1:$LI$1),FALSE) -> #VALUE!
D84: class E | E84: NEWAUTO_ce_cfut_0 | F84: =VLOOKUP($E84,Hybrid!$1:$1048576,MATCH(DATE(F$2,1,1),Hybrid!$A$1:$LI$1),FALSE) -> #VALUE! | G84: =VLOOKUP($E84,Hybrid!$1:$1048576,MATCH(DATE(G$2,1,1),Hybrid!$A$1:$LI$1),FALSE) -> #VALUE! | H84: =VLOOKUP($E84,Hybrid!$1:$1048576,MATCH(DATE(H$2,1,1),Hybrid!$A$1:$LI$1),FALSE) -> #VALUE! | I84: =VLOOKUP($E84,Hybrid!$1:$1048576,MATCH(DATE(I$2,1,1),Hybrid!$A$1:$LI$1),FALSE) -> #VALUE! | J84: =VLOOKUP($E84,Hybrid!$1:$1048576,MATCH(DATE(J$2,1,1),Hybrid!$A$1:$LI$1),FALSE) -> #VALUE! | K84: =VLOOKUP($E84,Hybrid!$1:$1048576,MATCH(DATE(K$2,1,1),Hybrid!$A$1:$LI$1),FALSE) -> #VALUE! | L84: =VLOOKUP($E84,Hybrid!$1:$1048576,MATCH(DATE(L$2,1,1),Hybrid!$A$1:$LI$1),FALSE) -> #VALUE! | M84: =VLOOKUP($E84,Hybrid!$1:$1048576,MATCH(DATE(M$2,1,1),Hybrid!$A$1:$LI$1),FALSE) -> #VALUE! | ... BI84: =VLOOKUP($E84,Hybrid!$1:$1048576,MATCH(DATE(BI$2,1,1),Hybrid!$A$1:$LI$1),FALSE) -> #VALUE!
D85: class F | E85: NEWAUTO_cf_cfut_0 | F85: =VLOOKUP($E85,Hybrid!$1:$1048576,MATCH(DATE(F$2,1,1),Hybrid!$A$1:$LI$1),FALSE) -> #VALUE! | G85: =VLOOKUP($E85,Hybrid!$1:$1048576,MATCH(DATE(G$2,1,1),Hybrid!$A$1:$LI$1),FALSE) -> #VALUE! | H85: =VLOOKUP($E85,Hybrid!$1:$1048576,MATCH(DATE(H$2,1,1),Hybrid!$A$1:$LI$1),FALSE) -> #VALUE! | I85: =VLOOKUP($E85,Hybrid!$1:$1048576,MATCH(DATE(I$2,1,1),Hybrid!$A$1:$LI$1),FALSE) -> #VALUE! | J85: =VLOOKUP($E85,Hybrid!$1:$1048576,MATCH(DATE(J$2,1,1),Hybrid!$A$1:$LI$1),FALSE) -> #VALUE! | K85: =VLOOKUP($E85,Hybrid!$1:$1048576,MATCH(DATE(K$2,1,1),Hybrid!$A$1:$LI$1),FALSE) -> #VALUE! | L85: =VLOOKUP($E85,Hybrid!$1:$1048576,MATCH(DATE(L$2,1,1),Hybrid!$A$1:$LI$1),FALSE) -> #VALUE! | M85: =VLOOKUP($E85,Hybrid!$1:$1048576,MATCH(DATE(M$2,1,1),Hybrid!$A$1:$LI$1),FALSE) -> #VALUE! | ... BI85: =VLOOKUP($E85,Hybrid!$1:$1048576,MATCH(DATE(BI$2,1,1),Hybrid!$A$1:$LI$1),FALSE) -> #VALUE!
D86: class G | E86: NEWAUTO_cg_cfut_0 | F86: =VLOOKUP($E86,Hybrid!$1:$1048576,MATCH(DATE(F$2,1,1),Hybrid!$A$1:$LI$1),FALSE) -> #VALUE! | G86: =VLOOKUP($E86,Hybrid!$1:$1048576,MATCH(DATE(G$2,1,1),Hybrid!$A$1:$LI$1),FALSE) -> #VALUE! | H86: =VLOOKUP($E86,Hybrid!$1:$1048576,MATCH(DATE(H$2,1,1),Hybrid!$A$1:$LI$1),FALSE) -> #VALUE! | I86: =VLOOKUP($E86,Hybrid!$1:$1048576,MATCH(DATE(I$2,1,1),Hybrid!$A$1:$LI$1),FALSE) -> #VALUE! | J86: =VLOOKUP($E86,Hybrid!$1:$1048576,MATCH(DATE(J$2,1,1),Hybrid!$A$1:$LI$1),FALSE) -> #VALUE! | K86: =VLOOKUP($E86,Hybrid!$1:$1048576,MATCH(DATE(K$2,1,1),Hybrid!$A$1:$LI$1),FALSE) -> #VALUE! | L86: =VLOOKUP($E86,Hybrid!$1:$1048576,MATCH(DATE(L$2,1,1),Hybrid!$A$1:$LI$1),FALSE) -> #VALUE! | M86: =VLOOKUP($E86,Hybrid!$1:$1048576,MATCH(DATE(M$2,1,1),Hybrid!$A$1:$LI$1),FALSE) -> #VALUE! | ... BI86: =VLOOKUP($E86,Hybrid!$1:$1048576,MATCH(DATE(BI$2,1,1),Hybrid!$A$1:$LI$1),FALSE) -> #VALUE!
C87: ELEC | E87: NEWAUTO_cele_0 | F87: =VLOOKUP($E87,Hybrid!$1:$1048576,MATCH(DATE(F$2,1,1),Hybrid!$A$1:$LI$1),FALSE) -> #VALUE! | G87: =VLOOKUP($E87,Hybrid!$1:$1048576,MATCH(DATE(G$2,1,1),Hybrid!$A$1:$LI$1),FALSE) -> #VALUE! | H87: =VLOOKUP($E87,Hybrid!$1:$1048576,MATCH(DATE(H$2,1,1),Hybrid!$A$1:$LI$1),FALSE) -> #VALUE! | I87: =VLOOKUP($E87,Hybrid!$1:$1048576,MATCH(DATE(I$2,1,1),Hybrid!$A$1:$LI$1),FALSE) -> #VALUE! | J87: =VLOOKUP($E87,Hybrid!$1:$1048576,MATCH(DATE(J$2,1,1),Hybrid!$A$1:$LI$1),FALSE) -> #VALUE! | K87: =VLOOKUP($E87,Hybrid!$1:$1048576,MATCH(DATE(K$2,1,1),Hybrid!$A$1:$LI$1),FALSE) -> #VALUE! | L87: =VLOOKUP($E87,Hybrid!$1:$1048576,MATCH(DATE(L$2,1,1),Hybrid!$A$1:$LI$1),FALSE) -> #VALUE! | M87: =VLOOKUP($E87,Hybrid!$1:$1048576,MATCH(DATE(M$2,1,1),Hybrid!$A$1:$LI$1),FALSE) -> #VALUE! | ... BI87: =VLOOKUP($E87,Hybrid!$1:$1048576,MATCH(DATE(BI$2,1,1),Hybrid!$A$1:$LI$1),FALSE) -> #VALUE!
D88: class A | E88: NEWAUTO_ca_cele_0 | F88: =VLOOKUP($E88,Hybrid!$1:$1048576,MATCH(DATE(F$2,1,1),Hybrid!$A$1:$LI$1),FALSE) -> #VALUE! | G88: =VLOOKUP($E88,Hybrid!$1:$1048576,MATCH(DATE(G$2,1,1),Hybrid!$A$1:$LI$1),FALSE) -> #VALUE! | H88: =VLOOKUP($E88,Hybrid!$1:$1048576,MATCH(DATE(H$2,1,1),Hybrid!$A$1:$LI$1),FALSE) -> #VALUE! | I88: =VLOOKUP($E88,Hybrid!$1:$1048576,MATCH(DATE(I$2,1,1),Hybrid!$A$1:$LI$1),FALSE) -> #VALUE! | J88: =VLOOKUP($E88,Hybrid!$1:$1048576,MATCH(DATE(J$2,1,1),Hybrid!$A$1:$LI$1),FALSE) -> #VALUE! | K88: =VLOOKUP($E88,Hybrid!$1:$1048576,MATCH(DATE(K$2,1,1),Hybrid!$A$1:$LI$1),FALSE) -> #VALUE! | L88: =VLOOKUP($E88,Hybrid!$1:$1048576,MATCH(DATE(L$2,1,1),Hybrid!$A$1:$LI$1),FALSE) -> #VALUE! | M88: =VLOOKUP($E88,Hybrid!$1:$1048576,MATCH(DATE(M$2,1,1),Hybrid!$A$1:$LI$1),FALSE) -> #VALUE! | ... BI88: =VLOOKUP($E88,Hybrid!$1:$1048576,MATCH(DATE(BI$2,1,1),Hybrid!$A$1:$LI$1),FALSE) -> #VALUE!
D89: class B | E89: NEWAUTO_cb_cele_0 | F89: =VLOOKUP($E89,Hybrid!$1:$1048576,MATCH(DATE(F$2,1,1),Hybrid!$A$1:$LI$1),FALSE) -> #VALUE! | G89: =VLOOKUP($E89,Hybrid!$1:$1048576,MATCH(DATE(G$2,1,1),Hybrid!$A$1:$LI$1),FALSE) -> #VALUE! | H89: =VLOOKUP($E89,Hybrid!$1:$1048576,MATCH(DATE(H$2,1,1),Hybrid!$A$1:$LI$1),FALSE) -> #VALUE! | I89: =VLOOKUP($E89,Hybrid!$1:$1048576,MATCH(DATE(I$2,1,1),Hybrid!$A$1:$LI$1),FALSE) -> #VALUE! | J89: =VLOOKUP($E89,Hybrid!$1:$1048576,MATCH(DATE(J$2,1,1),Hybrid!$A$1:$LI$1),FALSE) -> #VALUE! | K89: =VLOOKUP($E89,Hybrid!$1:$1048576,MATCH(DATE(K$2,1,1),Hybrid!$A$1:$LI$1),FALSE) -> #VALUE! | L89: =VLOOKUP($E89,Hybrid!$1:$1048576,MATCH(DATE(L$2,1,1),Hybrid!$A$1:$LI$1),FALSE) -> #VALUE! | M89: =VLOOKUP($E89,Hybrid!$1:$1048576,MATCH(DATE(M$2,1,1),Hybrid!$A$1:$LI$1),FALSE) -> #VALUE! | ... BI89: =VLOOKUP($E89,Hybrid!$1:$1048576,MATCH(DATE(BI$2,1,1),Hybrid!$A$1:$LI$1),FALSE) -> #VALUE!
D90: class C | E90: NEWAUTO_cc_cele_0 | F90: =VLOOKUP($E90,Hybrid!$1:$1048576,MATCH(DATE(F$2,1,1),Hybrid!$A$1:$LI$1),FALSE) -> #VALUE! | G90: =VLOOKUP($E90,Hybrid!$1:$1048576,MATCH(DATE(G$2,1,1),Hybrid!$A$1:$LI$1),FALSE) -> #VALUE! | H90: =VLOOKUP($E90,Hybrid!$1:$1048576,MATCH(DATE(H$2,1,1),Hybrid!$A$1:$LI$1),FALSE) -> #VALUE! | I90: =VLOOKUP($E90,Hybrid!$1:$1048576,MATCH(DATE(I$2,1,1),Hybrid!$A$1:$LI$1),FALSE) -> #VALUE! | J90: =VLOOKUP($E90,Hybrid!$1:$1048576,MATCH(DATE(J$2,1,1),Hybrid!$A$1:$LI$1),FALSE) -> #VALUE! | K90: =VLOOKUP($E90,Hybrid!$1:$1048576,MATCH(DATE(K$2,1,1),Hybrid!$A$1:$LI$1),FALSE) -> #VALUE! | L90: =VLOOKUP($E90,Hybrid!$1:$1048576,MATCH(DATE(L$2,1,1),Hybrid!$A$1:$LI$1),FALSE) -> #VALUE! | M90: =VLOOKUP($E90,Hybrid!$1:$1048576,MATCH(DATE(M$2,1,1),Hybrid!$A$1:$LI$1),FALSE) -> #VALUE! | ... BI90: =VLOOKUP($E90,Hybrid!$1:$1048576,MATCH(DATE(BI$2,1,1),Hybrid!$A$1:$LI$1),FALSE) -> #VALUE!
D91: class D | E91: NEWAUTO_cd_cele_0 | F91: =VLOOKUP($E91,Hybrid!$1:$1048576,MATCH(DATE(F$2,1,1),Hybrid!$A$1:$LI$1),FALSE) -> #VALUE! | G91: =VLOOKUP($E91,Hybrid!$1:$1048576,MATCH(DATE(G$2,1,1),Hybrid!$A$1:$LI$1),FALSE) -> #VALUE! | H91: =VLOOKUP($E91,Hybrid!$1:$1048576,MATCH(DATE(H$2,1,1),Hybrid!$A$1:$LI$1),FALSE) -> #VALUE! | I91: =VLOOKUP($E91,Hybrid!$1:$1048576,MATCH(DATE(I$2,1,1),Hybrid!$A$1:$LI$1),FALSE) -> #VALUE! | J91: =VLOOKUP($E91,Hybrid!$1:$1048576,MATCH(DATE(J$2,1,1),Hybrid!$A$1:$LI$1),FALSE) -> #VALUE! | K91: =VLOOKUP($E91,Hybrid!$1:$1048576,MATCH(DATE(K$2,1,1),Hybrid!$A$1:$LI$1),FALSE) -> #VALUE! | L91: =VLOOKUP($E91,Hybrid!$1:$1048576,MATCH(DATE(L$2,1,1),Hybrid!$A$1:$LI$1),FALSE) -> #VALUE! | M91: =VLOOKUP($E91,Hybrid!$1:$1048576,MATCH(DATE(M$2,1,1),Hybrid!$A$1:$LI$1),FALSE) -> #VALUE! | ... BI91: =VLOOKUP($E91,Hybrid!$1:$1048576,MATCH(DATE(BI$2,1,1),Hybrid!$A$1:$LI$1),FALSE) -> #VALUE!
D92: class E | E92: NEWAUTO_ce_cele_0 | F92: =VLOOKUP($E92,Hybrid!$1:$1048576,MATCH(DATE(F$2,1,1),Hybrid!$A$1:$LI$1),FALSE) -> #VALUE! | G92: =VLOOKUP($E92,Hybrid!$1:$1048576,MATCH(DATE(G$2,1,1),Hybrid!$A$1:$LI$1),FALSE) -> #VALUE! | H92: =VLOOKUP($E92,Hybrid!$1:$1048576,MATCH(DATE(H$2,1,1),Hybrid!$A$1:$LI$1),FALSE) -> #VALUE! | I92: =VLOOKUP($E92,Hybrid!$1:$1048576,MATCH(DATE(I$2,1,1),Hybrid!$A$1:$LI$1),FALSE) -> #VALUE! | J92: =VLOOKUP($E92,Hybrid!$1:$1048576,MATCH(DATE(J$2,1,1),Hybrid!$A$1:$LI$1),FALSE) -> #VALUE! | K92: =VLOOKUP($E92,Hybrid!$1:$1048576,MATCH(DATE(K$2,1,1),Hybrid!$A$1:$LI$1),FALSE) -> #VALUE! | L92: =VLOOKUP($E92,Hybrid!$1:$1048576,MATCH(DATE(L$2,1,1),Hybrid!$A$1:$LI$1),FALSE) -> #VALUE! | M92: =VLOOKUP($E92,Hybrid!$1:$1048576,MATCH(DATE(M$2,1,1),Hybrid!$A$1:$LI$1),FALSE) -> #VALUE! | ... BI92: =VLOOKUP($E92,Hybrid!$1:$1048576,MATCH(DATE(BI$2,1,1),Hybrid!$A$1:$LI$1),FALSE) -> #VALUE!
D93: class F | E93: NEWAUTO_cf_cele_0 | F93: =VLOOKUP($E93,Hybrid!$1:$1048576,MATCH(DATE(F$2,1,1),Hybrid!$A$1:$LI$1),FALSE) -> #VALUE! | G93: =VLOOKUP($E93,Hybrid!$1:$1048576,MATCH(DATE(G$2,1,1),Hybrid!$A$1:$LI$1),FALSE) -> #VALUE! | H93: =VLOOKUP($E93,Hybrid!$1:$1048576,MATCH(DATE(H$2,1,1),Hybrid!$A$1:$LI$1),FALSE) -> #VALUE! | I93: =VLOOKUP($E93,Hybrid!$1:$1048576,MATCH(DATE(I$2,1,1),Hybrid!$A$1:$LI$1),FALSE) -> #VALUE! | J93: =VLOOKUP($E93,Hybrid!$1:$1048576,MATCH(DATE(J$2,1,1),Hybrid!$A$1:$LI$1),FALSE) -> #VALUE! | K93: =VLOOKUP($E93,Hybrid!$1:$1048576,MATCH(DATE(K$2,1,1),Hybrid!$A$1:$LI$1),FALSE) -> #VALUE! | L93: =VLOOKUP($E93,Hybrid!$1:$1048576,MATCH(DATE(L$2,1,1),Hybrid!$A$1:$LI$1),FALSE) -> #VALUE! | M93: =VLOOKUP($E93,Hybrid!$1:$1048576,MATCH(DATE(M$2,1,1),Hybrid!$A$1:$LI$1),FALSE) -> #VALUE! | ... BI93: =VLOOKUP($E93,Hybrid!$1:$1048576,MATCH(DATE(BI$2,1,1),Hybrid!$A$1:$LI$1),FALSE) -> #VALUE!
D94: class G | E94: NEWAUTO_cg_cele_0 | F94: =VLOOKUP($E94,Hybrid!$1:$1048576,MATCH(DATE(F$2,1,1),Hybrid!$A$1:$LI$1),FALSE) -> #VALUE! | G94: =VLOOKUP($E94,Hybrid!$1:$1048576,MATCH(DATE(G$2,1,1),Hybrid!$A$1:$LI$1),FALSE) -> #VALUE! | H94: =VLOOKUP($E94,Hybrid!$1:$1048576,MATCH(DATE(H$2,1,1),Hybrid!$A$1:$LI$1),FALSE) -> #VALUE! | I94: =VLOOKUP($E94,Hybrid!$1:$1048576,MATCH(DATE(I$2,1,1),Hybrid!$A$1:$LI$1),FALSE) -> #VALUE! | J94: =VLOOKUP($E94,Hybrid!$1:$1048576,MATCH(DATE(J$2,1,1),Hybrid!$A$1:$LI$1),FALSE) -> #VALUE! | K94: =VLOOKUP($E94,Hybrid!$1:$1048576,MATCH(DATE(K$2,1,1),Hybrid!$A$1:$LI$1),FALSE) -> #VALUE! | L94: =VLOOKUP($E94,Hybrid!$1:$1048576,MATCH(DATE(L$2,1,1),Hybrid!$A$1:$LI$1),FALSE) -> #VALUE! | M94: =VLOOKUP($E94,Hybrid!$1:$1048576,MATCH(DATE(M$2,1,1),Hybrid!$A$1:$LI$1),FALSE) -> #VALUE! | ... BI94: =VLOOKUP($E94,Hybrid!$1:$1048576,MATCH(DATE(BI$2,1,1),Hybrid!$A$1:$LI$1),FALSE) -> #VALUE!
C95: GAS | E95: NEWAUTO_cgas_0 | F95: =VLOOKUP($E95,Hybrid!$1:$1048576,MATCH(DATE(F$2,1,1),Hybrid!$A$1:$LI$1),FALSE) -> #VALUE! | G95: =VLOOKUP($E95,Hybrid!$1:$1048576,MATCH(DATE(G$2,1,1),Hybrid!$A$1:$LI$1),FALSE) -> #VALUE! | H95: =VLOOKUP($E95,Hybrid!$1:$1048576,MATCH(DATE(H$2,1,1),Hybrid!$A$1:$LI$1),FALSE) -> #VALUE! | I95: =VLOOKUP($E95,Hybrid!$1:$1048576,MATCH(DATE(I$2,1,1),Hybrid!$A$1:$LI$1),FALSE) -> #VALUE! | J95: =VLOOKUP($E95,Hybrid!$1:$1048576,MATCH(DATE(J$2,1,1),Hybrid!$A$1:$LI$1),FALSE) -> #VALUE! | K95: =VLOOKUP($E95,Hybrid!$1:$1048576,MATCH(DATE(K$2,1,1),Hybrid!$A$1:$LI$1),FALSE) -> #VALUE! | L95: =VLOOKUP($E95,Hybrid!$1:$1048576,MATCH(DATE(L$2,1,1),Hybrid!$A$1:$LI$1),FALSE) -> #VALUE! | M95: =VLOOKUP($E95,Hybrid!$1:$1048576,MATCH(DATE(M$2,1,1),Hybrid!$A$1:$LI$1),FALSE) -> #VALUE! | ... BI95: =VLOOKUP($E95,Hybrid!$1:$1048576,MATCH(DATE(BI$2,1,1),Hybrid!$A$1:$LI$1),FALSE) -> #VALUE!
D96: class A | E96: NEWAUTO_ca_cgas_0 | F96: =VLOOKUP($E96,Hybrid!$1:$1048576,MATCH(DATE(F$2,1,1),Hybrid!$A$1:$LI$1),FALSE) -> #VALUE! | G96: =VLOOKUP($E96,Hybrid!$1:$1048576,MATCH(DATE(G$2,1,1),Hybrid!$A$1:$LI$1),FALSE) -> #VALUE! | H96: =VLOOKUP($E96,Hybrid!$1:$1048576,MATCH(DATE(H$2,1,1),Hybrid!$A$1:$LI$1),FALSE) -> #VALUE! | I96: =VLOOKUP($E96,Hybrid!$1:$1048576,MATCH(DATE(I$2,1,1),Hybrid!$A$1:$LI$1),FALSE) -> #VALUE! | J96: =VLOOKUP($E96,Hybrid!$1:$1048576,MATCH(DATE(J$2,1,1),Hybrid!$A$1:$LI$1),FALSE) -> #VALUE! | K96: =VLOOKUP($E96,Hybrid!$1:$1048576,MATCH(DATE(K$2,1,1),Hybrid!$A$1:$LI$1),FALSE) -> #VALUE! | L96: =VLOOKUP($E96,Hybrid!$1:$1048576,MATCH(DATE(L$2,1,1),Hybrid!$A$1:$LI$1),FALSE) -> #VALUE! | M96: =VLOOKUP($E96,Hybrid!$1:$1048576,MATCH(DATE(M$2,1,1),Hybrid!$A$1:$LI$1),FALSE) -> #VALUE! | ... BI96: =VLOOKUP($E96,Hybrid!$1:$1048576,MATCH(DATE(BI$2,1,1),Hybrid!$A$1:$LI$1),FALSE) -> #VALUE!
D97: class B | E97: NEWAUTO_cb_cgas_0 | F97: =VLOOKUP($E97,Hybrid!$1:$1048576,MATCH(DATE(F$2,1,1),Hybrid!$A$1:$LI$1),FALSE) -> #VALUE! | G97: =VLOOKUP($E97,Hybrid!$1:$1048576,MATCH(DATE(G$2,1,1),Hybrid!$A$1:$LI$1),FALSE) -> #VALUE! | H97: =VLOOKUP($E97,Hybrid!$1:$1048576,MATCH(DATE(H$2,1,1),Hybrid!$A$1:$LI$1),FALSE) -> #VALUE! | I97: =VLOOKUP($E97,Hybrid!$1:$1048576,MATCH(DATE(I$2,1,1),Hybrid!$A$1:$LI$1),FALSE) -> #VALUE! | J97: =VLOOKUP($E97,Hybrid!$1:$1048576,MATCH(DATE(J$2,1,1),Hybrid!$A$1:$LI$1),FALSE) -> #VALUE! | K97: =VLOOKUP($E97,Hybrid!$1:$1048576,MATCH(DATE(K$2,1,1),Hybrid!$A$1:$LI$1),FALSE) -> #VALUE! | L97: =VLOOKUP($E97,Hybrid!$1:$1048576,MATCH(DATE(L$2,1,1),Hybrid!$A$1:$LI$1),FALSE) -> #VALUE! | M97: =VLOOKUP($E97,Hybrid!$1:$1048576,MATCH(DATE(M$2,1,1),Hybrid!$A$1:$LI$1),FALSE) -> #VALUE! | ... BI97: =VLOOKUP($E97,Hybrid!$1:$1048576,MATCH(DATE(BI$2,1,1),Hybrid!$A$1:$LI$1),FALSE) -> #VALUE!
D98: class C | E98: NEWAUTO_cc_cgas_0 | F98: =VLOOKUP($E98,Hybrid!$1:$1048576,MATCH(DATE(F$2,1,1),Hybrid!$A$1:$LI$1),FALSE) -> #VALUE! | G98: =VLOOKUP($E98,Hybrid!$1:$1048576,MATCH(DATE(G$2,1,1),Hybrid!$A$1:$LI$1),FALSE) -> #VALUE! | H98: =VLOOKUP($E98,Hybrid!$1:$1048576,MATCH(DATE(H$2,1,1),Hybrid!$A$1:$LI$1),FALSE) -> #VALUE! | I98: =VLOOKUP($E98,Hybrid!$1:$1048576,MATCH(DATE(I$2,1,1),Hybrid!$A$1:$LI$1),FALSE) -> #VALUE! | J98: =VLOOKUP($E98,Hybrid!$1:$1048576,MATCH(DATE(J$2,1,1),Hybrid!$A$1:$LI$1),FALSE) -> #VALUE! | K98: =VLOOKUP($E98,Hybrid!$1:$1048576,MATCH(DATE(K$2,1,1),Hybrid!$A$1:$LI$1),FALSE) -> #VALUE! | L98: =VLOOKUP($E98,Hybrid!$1:$1048576,MATCH(DATE(L$2,1,1),Hybrid!$A$1:$LI$1),FALSE) -> #VALUE! | M98: =VLOOKUP($E98,Hybrid!$1:$1048576,MATCH(DATE(M$2,1,1),Hybrid!$A$1:$LI$1),FALSE) -> #VALUE! | ... BI98: =VLOOKUP($E98,Hybrid!$1:$1048576,MATCH(DATE(BI$2,1,1),Hybrid!$A$1:$LI$1),FALSE) -> #VALUE!
D99: class D | E99: NEWAUTO_cd_cgas_0 | F99: =VLOOKUP($E99,Hybrid!$1:$1048576,MATCH(DATE(F$2,1,1),Hybrid!$A$1:$LI$1),FALSE) -> #VALUE! | G99: =VLOOKUP($E99,Hybrid!$1:$1048576,MATCH(DATE(G$2,1,1),Hybrid!$A$1:$LI$1),FALSE) -> #VALUE! | H99: =VLOOKUP($E99,Hybrid!$1:$1048576,MATCH(DATE(H$2,1,1),Hybrid!$A$1:$LI$1),FALSE) -> #VALUE! | I99: =VLOOKUP($E99,Hybrid!$1:$1048576,MATCH(DATE(I$2,1,1),Hybrid!$A$1:$LI$1),FALSE) -> #VALUE! | J99: =VLOOKUP($E99,Hybrid!$1:$1048576,MATCH(DATE(J$2,1,1),Hybrid!$A$1:$LI$1),FALSE) -> #VALUE! | K99: =VLOOKUP($E99,Hybrid!$1:$1048576,MATCH(DATE(K$2,1,1),Hybrid!$A$1:$LI$1),FALSE) -> #VALUE! | L99: =VLOOKUP($E99,Hybrid!$1:$1048576,MATCH(DATE(L$2,1,1),Hybrid!$A$1:$LI$1),FALSE) -> #VALUE! | M99: =VLOOKUP($E99,Hybrid!$1:$1048576,MATCH(DATE(M$2,1,1),Hybrid!$A$1:$LI$1),FALSE) -> #VALUE! | ... BI99: =VLOOKUP($E99,Hybrid!$1:$1048576,MATCH(DATE(BI$2,1,1),Hybrid!$A$1:$LI$1),FALSE) -> #VALUE!
D100: class E | E100: NEWAUTO_ce_cgas_0 | F100: =VLOOKUP($E100,Hybrid!$1:$1048576,MATCH(DATE(F$2,1,1),Hybrid!$A$1:$LI$1),FALSE) -> #VALUE! | G100: =VLOOKUP($E100,Hybrid!$1:$1048576,MATCH(DATE(G$2,1,1),Hybrid!$A$1:$LI$1),FALSE) -> #VALUE! | H100: =VLOOKUP($E100,Hybrid!$1:$1048576,MATCH(DATE(H$2,1,1),Hybrid!$A$1:$LI$1),FALSE) -> #VALUE! | I100: =VLOOKUP($E100,Hybrid!$1:$1048576,MATCH(DATE(I$2,1,1),Hybrid!$A$1:$LI$1),FALSE) -> #VALUE! | J100: =VLOOKUP($E100,Hybrid!$1:$1048576,MATCH(DATE(J$2,1,1),Hybrid!$A$1:$LI$1),FALSE) -> #VALUE! | K100: =VLOOKUP($E100,Hybrid!$1:$1048576,MATCH(DATE(K$2,1,1),Hybrid!$A$1:$LI$1),FALSE) -> #VALUE! | L100: =VLOOKUP($E100,Hybrid!$1:$1048576,MATCH(DATE(L$2,1,1),Hybrid!$A$1:$LI$1),FALSE) -> #VALUE! | M100: =VLOOKUP($E100,Hybrid!$1:$1048576,MATCH(DATE(M$2,1,1),Hybrid!$A$1:$LI$1),FALSE) -> #VALUE! | ... BI100: =VLOOKUP($E100,Hybrid!$1:$1048576,MATCH(DATE(BI$2,1,1),Hybrid!$A$1:$LI$1),FALSE) -> #VALUE!
...

Sheet date
A1: =Hybrid!A1 -> _date_ | B1: =Hybrid!B1 -> 42005 | C1: =Hybrid!C1 -> 42370 | D1: =Hybrid!D1 -> 42736 | E1: =Hybrid!E1 -> 43101 | F1: =Hybrid!F1 -> 43466 | G1: =Hybrid!G1 -> 43831 | H1: =Hybrid!H1 -> 44197 | ... BE1: =Hybrid!BE1 -> 62094
B2: =TEXT(B1,"jj mm aaaa") -> 15 01 donderdag | C2: =TEXT(C1,"jj mm aaaa") -> 16 01 vrijdag | D2: =TEXT(D1,"jj mm aaaa") -> 17 01 zondag | E2: =TEXT(E1,"jj mm aaaa") -> 18 01 maandag | F2: =TEXT(F1,"jj mm aaaa") -> 19 01 dinsdag | G2: =TEXT(G1,"jj mm aaaa") -> 20 01 woensdag | H2: =TEXT(H1,"jj mm aaaa") -> 21 01 vrijdag | I2: =TEXT(I1,"jj mm aaaa") -> 22 01 zaterdag | ... BE2: =TEXT(BE1,"jj mm aaaa") -> 70 01 woensdag
B3: =RIGHT(B2,4) -> rdag | C3: =RIGHT(C2,4) -> jdag | D3: =RIGHT(D2,4) -> ndag | E3: =RIGHT(E2,4) -> ndag | F3: =RIGHT(F2,4) -> sdag | G3: =RIGHT(G2,4) -> sdag | H3: =RIGHT(H2,4) -> jdag | I3: =RIGHT(I2,4) -> rdag | ... BE3: =RIGHT(BE2,4) -> sdag

Sheet Emissions
A1: _date_ | B1: 42005 | C1: 42370 | D1: 42736 | E1: 43101 | F1: 43466 | G1: 43831 | H1: 44197 | I1: 44562 | J1: 44927 | K1: 45292 | L1: 45658 | M1: 46023 | N1: 46388 | O1: 46753 | P1: 47119 | Q1: 47484 | R1: 47849 | S1: 48214 | T1: 48580 | U1: 48945 | V1: 49310 | W1: 49675 | X1: 50041 | Y1: 50406 | Z1: 50771 | AA1: 51136 | AB1: 51502 | AC1: 51867 | AD1: 52232 | AE1: 52597 | AF1: 52963 | AG1: 53328 | AH1: 53693 | AI1: 54058 | AJ1: 54424 | AK1: 54789 | AL1: 55154 | AM1: 55519 | AN1: 55885 | AO1: 56250 | AP1: 56615 | AQ1: 56980 | AR1: 57346 | AS1: 57711 | AT1: 58076 | AU1: 58441 | AV1: 58807 | AW1: 59172 | AX1: 59537 | AY1: 59902 | AZ1: 60268 | BA1: 60633 | BB1: 60998 | BC1: 61363 | BD1: 61729 | BE1: 62094
A2: ems_2 | B2: 471.14325 | C2: 473.45288 | D2: 475.2163 | E2: 477.15632 | F2: 479.77221 | G2: 483.2801 | H2: 487.42698 | I2: 492.14919 | J2: 497.21811 | K2: 502.39676 | L2: 507.93519 | M2: 513.12067 | N2: 518.09618 | O2: 522.93622 | P2: 527.71584 | Q2: 532.4941 | R2: 537.31363 | S2: 542.18497 | T2: 547.11334 | U2: 552.10521 | V2: 556.86538 | W2: 561.8801 | X2: 567.05351 | Y2: 572.37902 | Z2: 577.8509 | AA2: 582.58429 | AB2: 587.49447 | AC2: 592.46606 | AD2: 597.5107 | AE2: 602.64814 | AF2: 607.8941 | AG2: 613.25357 | AH2: 618.72566 | AI2: 624.302 | AJ2: 629.97142 | AK2: 635.72397 | AL2: 641.33283 | AM2: 646.92527 | AN2: 652.54501 | AO2: 658.22244 | AP2: 663.97962 | AQ2: 669.82684 | AR2: 675.77028 | AS2: 681.80754 | AT2: 687.93192 | AU2: 694.13601 | AV2: 700.42351 | AW2: 706.79076 | AX2: 713.23912 | AY2: 719.77034 | AZ2: 726.38509 | BA2: 888.74598 | BB2: 901.54208 | BC2: 914.53853 | BD2: 927.73983 | BE2: 941.15101
A3: ems_ch_2 | B3: 124.6337 | C3: 124.34567 | D3: 123.67784 | E3: 123.08257 | F3: 122.66884 | G3: 122.42734 | H3: 122.29711 | I3: 122.25287 | J3: 122.27554 | K3: 122.35668 | L3: 122.53353 | M3: 122.74634 | N3: 122.9956 | O3: 123.27751 | P3: 123.58461 | Q3: 123.90925 | R3: 124.24525 | S3: 124.58846 | T3: 124.9367 | U3: 125.28887 | V3: 125.61675 | W3: 125.95795 | X3: 126.30741 | Y3: 126.66153 | Z3: 127.01857 | AA3: 127.30241 | AB3: 127.58289 | AC3: 127.86262 | AD3: 128.14216 | AE3: 128.42204 | AF3: 128.70271 | AG3: 128.98464 | AH3: 129.26849 | AI3: 129.55501 | AJ3: 129.84508 | AK3: 130.13946 | AL3: 130.42242 | AM3: 130.70049 | AN3: 130.97686 | AO3: 131.25269 | AP3: 131.52819 | AQ3: 131.8033 | AR3: 132.07809 | AS3: 132.35278 | AT3: 132.62775 | AU3: 132.90343 | AV3: 133.1815 | AW3: 133.46158 | AX3: 133.74299 | AY3: 134.02497 | AZ3: 134.30675 | BA3: 134.21728 | BB3: 134.56101 | BC3: 134.9141 | BD3: 135.27674 | BE3: 135.64951
A4: ems_ch_2+ems_ci_2 | B4: 313.46133 | C4: 315.24795 | D4: 316.18051 | E4: 316.95128 | F4: 318.03936 | G4: 319.74318 | H4: 322.04906 | I4: 324.94364 | J4: 328.25546 | K4: 331.76339 | L4: 335.5123 | M4: 339.08635 | N4: 342.52138 | O4: 345.86973 | P4: 349.18972 | Q4: 352.52438 | R4: 355.9004 | S4: 359.31028 | T4: 362.74149 | U4: 366.18567 | V4: 369.47445 | W4: 372.86461 | X4: 376.33252 | Y4: 379.88884 | Z4: 383.5445 | AA4: 386.81182 | AB4: 390.14953 | AC4: 393.51981 | AD4: 396.92946 | AE4: 400.39709 | AF4: 403.94169 | AG4: 407.57333 | AH4: 411.29614 | AI4: 415.10505 | AJ4: 418.98999 | AK4: 422.94022 | AL4: 426.81032 | AM4: 430.66031 | AN4: 434.51586 | AO4: 438.39898 | AP4: 442.32955 | AQ4: 446.31852 | AR4: 450.37456 | AS4: 454.49794 | AT4: 458.68417 | AU4: 462.92723 | AV4: 467.22108 | AW4: 471.56613 | AX4: 475.96448 | AY4: 480.41945 | AZ4: 484.93338 | BA4: 621.04365 | BB4: 629.37653 | BC4: 637.83682 | BD4: 646.42775 | BE4: 655.15295
A5: ems_ci_2 | B5: 188.82763 | C5: 190.90228 | D5: 192.50266 | E5: 193.8687 | F5: 195.37052 | G5: 197.31583 | H5: 199.75195 | I5: 202.69077 | J5: 205.97992 | K5: 209.40671 | L5: 212.97877 | M5: 216.34001 | N5: 219.52578 | O5: 222.59222 | P5: 225.60511 | Q5: 228.61513 | R5: 231.65515 | S5: 234.72182 | T5: 237.80479 | U5: 240.89681 | V5: 243.8577 | W5: 246.90666 | X5: 250.02511 | Y5: 253.22732 | Z5: 256.52594 | AA5: 259.5094 | AB5: 262.56663 | AC5: 265.65718 | AD5: 268.7873 | AE5: 271.97506 | AF5: 275.23899 | AG5: 278.58868 | AH5: 282.02765 | AI5: 285.55003 | AJ5: 289.14491 | AK5: 292.80076 | AL5: 296.3879 | AM5: 299.95982 | AN5: 303.53899 | AO5: 307.14629 | AP5: 310.80136 | AQ5: 314.51522 | AR5: 318.29646 | AS5: 322.14516 | AT5: 326.05642 | AU5: 330.0238 | AV5: 334.03958 | AW5: 338.10456 | AX5: 342.22149 | AY5: 346.39448 | AZ5: 350.62663 | BA5: 486.82637 | BB5: 494.81552 | BC5: 502.92273 | BD5: 511.15101 | BE5: 519.50344
A6: ems_mat_2 | B6: 66.974354 | C6: 67.780101 | D6: 68.655846 | E6: 69.637271 | F6: 70.723371 | G6: 71.880251 | H6: 73.013936 | I6: 74.126496 | J6: 75.213259 | K6: 76.284472 | L6: 77.445461 | M6: 78.563225 | N6: 79.698034 | O6: 80.860731 | P6: 82.049477 | Q6: 83.259007 | R6: 84.484373 | S6: 85.723893 | T6: 86.97895 | U6: 88.252634 | V6: 89.484554 | W6: 90.787935 | X6: 92.126244 | Y6: 93.491692 | Z6: 94.880609 | AA6: 96.10732 | AB6: 97.405274 | AC6: 98.732555 | AD6: 100.08462 | AE6: 101.46079 | AF6: 102.85975 | AG6: 104.27977 | AH6: 105.71919 | AI6: 107.17714 | AJ6: 108.65362 | AK6: 110.14933 | AL6: 111.62251 | AM6: 113.1074 | AN6: 114.61169 | AO6: 116.13724 | AP6: 117.68372 | AQ6: 119.25018 | AR6: 120.83556 | AS6: 122.43928 | AT6: 124.06147 | AU6: 125.70277 | AV6: 127.36905 | AW6: 129.05844 | AX6: 130.77069 | AY6: 132.5053 | AZ6: 134.26163 | BA6: 65.0266 | BB6: 66.162537 | BC6: 67.315857 | BD6: 68.486723 | BE6: 69.675314
A7: ems_y_2 | B7: 90.707568 | C7: 90.424825 | D7: 90.379944 | E7: 90.567769 | F7: 91.009474 | G7: 91.656667 | H7: 92.363988 | I7: 93.079057 | J7: 93.749386 | K7: 94.348897 | L7: 94.977429 | M7: 95.471099 | N7: 95.876767 | O7: 96.20576 | P7: 96.476643 | Q7: 96.710706 | R7: 96.928857 | S7: 97.150795 | T7: 97.392901 | U7: 97.666903 | V7: 97.906377 | W7: 98.227556 | X7: 98.594754 | Y7: 98.998492 | Z7: 99.425791 | AA7: 99.665159 | AB7: 99.939669 | AC7: 100.2137 | AD7: 100.49662 | AE7: 100.79025 | AF7: 101.09265 | AG7: 101.40048 | AH7: 101.71033 | AI7: 102.01981 | AJ7: 102.32781 | AK7: 102.63442 | AL7: 102.90001 | AM7: 103.15756 | AN7: 103.41747 | AO7: 103.68621 | AP7: 103.96635 | AQ7: 104.25814 | AR7: 104.56017 | AS7: 104.87032 | AT7: 105.18629 | AU7: 105.50601 | AV7: 105.83338 | AW7: 106.16619 | AX7: 106.50395 | AY7: 106.84559 | AZ7: 107.19008 | BA7: 202.67573 | BB7: 206.00301 | BC7: 209.38585 | BD7: 212.82536 | BE7: 216.32274
A8: ems_sec_2 | B8: 346.50956 | C8: 349.10721 | D8: 351.53845 | E8: 354.07374 | F8: 357.10337 | G8: 360.85275 | H8: 365.12987 | I8: 369.89632 | J8: 374.94256 | K8: 380.04008 | L8: 385.40166 | M8: 390.37433 | N8: 395.10058 | O8: 399.65871 | P8: 404.13123 | Q8: 408.58484 | R8: 413.06838 | S8: 417.59651 | T8: 422.17664 | U8: 426.81635 | V8: 431.24864 | W8: 435.92215 | X8: 440.7461 | Y8: 445.7175 | Z8: 450.83234 | AA8: 455.28188 | AB8: 459.91158 | AC8: 464.60343 | AD8: 469.36854 | AE8: 474.2261 | AF8: 479.19139 | AG8: 484.26892 | AH8: 489.45717 | AI8: 494.74698 | AJ8: 500.12634 | AK8: 505.58452 | AL8: 510.91041 | AM8: 516.22478 | AN8: 521.56815 | AO8: 526.96974 | AP8: 532.45143 | AQ8: 538.02353 | AR8: 543.69219 | AS8: 549.45477 | AT8: 555.30417 | AU8: 561.23258 | AV8: 567.24201 | AW8: 573.32919 | AX8: 579.49613 | AY8: 585.74537 | AZ8: 592.07834 | BA8: 754.5287 | BB8: 766.98107 | BC8: 779.62443 | BD8: 792.46309 | BE8: 805.50149
A9: ems_ets_2 | B9: 121.98747 | C9: 123.5931 | D9: 125.16981 | E9: 126.81773 | F9: 128.6049 | G9: 130.5328 | H9: 132.47819 | I9: 134.43951 | J9: 136.38825 | K9: 138.31239 | L9: 140.36228 | M9: 142.31942 | N9: 144.27131 | O9: 146.24445 | P9: 148.24635 | Q9: 150.27623 | R9: 152.33057 | S9: 154.4062 | T9: 156.50368 | U9: 158.62689 | V9: 160.67612 | W9: 162.83283 | X9: 165.0495 | Y9: 167.31691 | Z9: 169.63107 | AA9: 171.68487 | AB9: 173.83979 | AC9: 176.04217 | AD9: 178.28723 | AE9: 180.57629 | AF9: 182.90961 | AG9: 185.28561 | AH9: 187.70191 | AI9: 190.1561 | AJ9: 192.64654 | AK9: 195.17267 | AL9: 197.66151 | AM9: 200.16477 | AN9: 202.69714 | AO9: 205.26459 | AP9: 207.8693 | AQ9: 210.51129 | AR9: 213.18985 | AS9: 215.90394 | AT9: 218.653 | AU9: 221.43716 | AV9: 224.26397 | AW9: 227.13123 | AX9: 230.03901 | AY9: 232.98714 | AZ9: 235.97498 | BA9: 271.14099 | BB9: 275.62389 | BC9: 280.1819 | BD9: 284.81612 | BE9: 289.52771
A10: ems_nets_2 | B10: 224.52209 | C10: 225.51411 | D10: 226.36864 | E10: 227.25601 | F10: 228.49846 | G10: 230.31996 | H10: 232.65168 | I10: 235.45681 | J10: 238.55431 | K10: 241.72769 | L10: 245.03938 | M10: 248.05491 | N10: 250.82927 | O10: 253.41426 | P10: 255.88488 | Q10: 258.30862 | R10: 260.73781 | S10: 263.19031 | T10: 265.67297 | U10: 268.18946 | V10: 270.57252 | W10: 273.08932 | X10: 275.6966 | Y10: 278.40058 | Z10: 281.20126 | AA10: 283.59702 | AB10: 286.07179 | AC10: 288.56126 | AD10: 291.08132 | AE10: 293.64982 | AF10: 296.28179 | AG10: 298.98332 | AH10: 301.75526 | AI10: 304.59089 | AJ10: 307.4798 | AK10: 310.41184 | AL10: 313.2489 | AM10: 316.06001 | AN10: 318.87101 | AO10: 321.70516 | AP10: 324.58213 | AQ10: 327.51224 | AR10: 330.50234 | AS10: 333.55083 | AT10: 336.65117 | AU10: 339.79542 | AV10: 342.97804 | AW10: 346.19795 | AX10: 349.45712 | AY10: 352.75823 | AZ10: 356.10336 | BA10: 483.38771 | BB10: 491.35718 | BC10: 499.44253 | BD10: 507.64697 | BE10: 515.97378
A11: ems_netsi_2 | B11: 26.807228 | C11: 26.951563 | D11: 27.062602 | E11: 27.184503 | F11: 27.347956 | G11: 27.565763 | H11: 27.818676 | I11: 28.0995 | J11: 28.39411 | K11: 28.689833 | L11: 29.007205 | M11: 29.30613 | N11: 29.595807 | O11: 29.882852 | P11: 30.172543 | Q11: 30.467753 | R11: 30.769402 | S11: 31.076817 | T11: 31.389377 | U11: 31.707058 | V11: 32.010872 | W11: 32.330292 | X11: 32.661626 | Y11: 33.004005 | Z11: 33.356297 | AA11: 33.661845 | AB11: 33.974153 | AC11: 34.291167 | AD11: 34.614567 | AE11: 34.945444 | AF11: 35.284188 | AG11: 35.630443 | AH11: 35.983415 | AI11: 36.342056 | AJ11: 36.705378 | AK11: 37.07268 | AL11: 37.430798 | AM11: 37.786605 | AN11: 38.143576 | AO11: 38.503937 | AP11: 38.868915 | AQ11: 39.238898 | AR11: 39.613824 | AS11: 39.993259 | AT11: 40.376676 | AU11: 40.763662 | AV11: 41.155124 | AW11: 41.551015 | AX11: 41.951452 | AY11: 42.356424 | AZ11: 42.765789 | BA11: 64.018523 | BB11: 65.095606 | BC11: 66.179514 | BD11: 67.27078 | BE11: 68.369931
A12: ems_trsp_2-ems_sair_2 | B12: 27.323753 | C12: 27.373058 | D12: 27.445791 | E12: 27.583997 | F12: 27.791158 | G12: 28.057835 | H12: 28.352417 | I12: 28.669835 | J12: 29.000969 | K12: 29.340494 | L12: 29.716216 | M12: 30.081597 | N12: 30.451748 | O12: 30.829958 | P12: 31.216306 | Q12: 31.609654 | R12: 32.008676 | S12: 32.412477 | T12: 32.821033 | U12: 33.235005 | V12: 33.63427 | W12: 34.054919 | X12: 34.487377 | Y12: 34.929693 | Z12: 35.380961 | AA12: 35.77992 | AB12: 36.198463 | AC12: 36.626038 | AD12: 37.061796 | AE12: 37.506017 | AF12: 37.958733 | AG12: 38.419619 | AH12: 38.888177 | AI12: 39.363906 | AJ12: 39.846456 | AK12: 40.335676 | AL12: 40.817229 | AM12: 41.301218 | AN12: 41.790473 | AO12: 42.286146 | AP12: 42.788672 | AQ12: 43.298096 | AR12: 43.814304 | AS12: 44.337123 | AT12: 44.866456 | AU12: 45.402324 | AV12: 45.946236 | AW12: 46.497692 | AX12: 47.056643 | AY12: 47.623009 | AZ12: 48.196637 | BA12: 52.31314 | BB12: 53.134216 | BC12: 53.969182 | BD12: 54.81831 | BE12: 55.681871
... A887: ems_mat_co2_sgla_0 | B887: 13.794958 | C887: 13.942765 | D887: 14.120201 | E887: 14.344049 | F887: 14.608228 | G887: 14.893011 | H887: 15.167457 | I887: 15.421217 | J887: 15.653768 | K887: 15.87376 | L887: 16.108231 | M887: 16.344578 | N887: 16.592339 | O887: 16.853418 | P887: 17.125325 | Q887: 17.404277 | R887: 17.687427 | S887: 17.97384 | T887: 18.26428 | U887: 18.560303 | V887: 18.852517 | W887: 19.158346 | X887: 19.474307 | Y887: 19.797868 | Z887: 20.126995 | AA887: 20.429263 | AB887: 20.738189 | AC887: 21.053395 | AD887: 21.375183 | AE887: 21.703407 | AF887: 22.037267 | AG887: 22.375651 | AH887: 22.717605 | AI887: 23.062665 | AJ887: 23.410927 | AK887: 23.76288 | AL887: 24.111587 | AM887: 24.46167 | AN887: 24.815377 | AO887: 25.173597 | AP887: 25.536354 | AQ887: 25.903212 | AR887: 26.273641 | AS887: 26.647298 | AT887: 27.024136 | AU887: 27.404371 | AV887: 27.789019 | AW887: 28.178008 | AX887: 28.57133 | AY887: 28.96893 | AZ887: 29.370726 | BA887: 26.210755 | BB887: 26.679564 | BC887: 27.154032 | BD887: 27.634126 | BE887: 28.119832

Sheet Consumption
A1: _date_ | B1: 42005 | C1: 42370 | D1: 42736 | E1: 43101 | F1: 43466 | G1: 43831 | H1: 44197 | I1: 44562 | J1: 44927 | K1: 45292 | L1: 45658 | M1: 46023 | N1: 46388 | O1: 46753 | P1: 47119 | Q1: 47484 | R1: 47849 | S1: 48214 | T1: 48580 | U1: 48945 | V1: 49310 | W1: 49675 | X1: 50041 | Y1: 50406 | Z1: 50771 | AA1: 51136 | AB1: 51502 | AC1: 51867 | AD1: 52232 | AE1: 52597 | AF1: 52963 | AG1: 53328 | AH1: 53693 | AI1: 54058 | AJ1: 54424 | AK1: 54789 | AL1: 55154 | AM1: 55519 | AN1: 55885 | AO1: 56250 | AP1: 56615 | AQ1: 56980 | AR1: 57346 | AS1: 57711 | AT1: 58076 | AU1: 58441 | AV1: 58807 | AW1: 59172 | AX1: 59537 | AY1: 59902 | AZ1: 60268 | BA1: 60633 | BB1: 60998 | BC1: 61363 | BD1: 61729 | BE1: 62094
A2: ch_2 | B2: 1207658.6 | C2: 1218890 | D2: 1233465.7 | E2: 1250851.6 | F2: 1269570.6 | G2: 1288090.1 | H2: 1304818.8 | I2: 1320138.8 | J2: 1334989.5 | K2: 1350572.4 | L2: 1368934.5 | M2: 1388661.4 | N2: 1409986.7 | O2: 1432478.6 | P2: 1455608.8 | Q2: 1478977.3 | R2: 1502350.5 | S2: 1525750.4 | T2: 1549283.2 | U2: 1573058.9 | V2: 1596323.4 | W2: 1620303.2 | X2: 1644651.7 | Y2: 1669227.8 | Z2: 1693952.6 | AA2: 1716512 | AB2: 1739426.9 | AC2: 1762541.6 | AD2: 1785901.6 | AE2: 1809502.2 | AF2: 1833308 | AG2: 1857307.7 | AH2: 1881508.3 | AI2: 1905958.4 | AJ2: 1930726.3 | AK2: 1955877 | AL2: 1981027.5 | AM2: 2006404.9 | AN2: 2032056.4 | AO2: 2057957.3 | AP2: 2084059.2 | AQ2: 2110348.3 | AR2: 2136818.9 | AS2: 2163506.5 | AT2: 2190467.9 | AU2: 2217761.5 | AV2: 2245546 | AW2: 2273784.9 | AX2: 2302448.1 | AY2: 2331496.1 | AZ2: 2360897.4 | BA2: 2578303.1 | BB2: 2616559.4 | BC2: 2655344.6 | BD2: 2694674.9 | BE2: 2734568.9
A3: ch_0 | B3: 1207915.5 | C3: 1219950.3 | D3: 1235455.6 | E3: 1253709.2 | F3: 1273090.9 | G3: 1291973.6 | H3: 1308746.3 | I3: 1323857.4 | J3: 1338402.1 | K3: 1353760 | L3: 1372108.1 | M3: 1392092.9 | N3: 1413865.3 | O3: 1436885.5 | P3: 1460524.8 | Q3: 1484326.3 | R3: 1508099 | S3: 1531876 | T3: 1555799.2 | U3: 1580001.2 | V3: 1603719.3 | W3: 1628170.1 | X3: 1652985.9 | Y3: 1678004.8 | Z3: 1703139.9 | AA3: 1726058.3 | AB3: 1749296.2 | AC3: 1772746.3 | AD3: 1796475.1 | AE3: 1820481.7 | AF3: 1844722 | AG3: 1869157.8 | AH3: 1893790.8 | AI3: 1918668.2 | AJ3: 1943865.1 | AK3: 1969455 | AL3: 1994936.7 | AM3: 2020599.2 | AN3: 2046526.2 | AO3: 2072728.9 | AP3: 2099182.8 | AQ3: 2125860.4 | AR3: 2152754 | AS3: 2179884.6 | AT3: 2207295.1 | AU3: 2235035.1 | AV3: 2263193.5 | AW3: 2291768.4 | AX3: 2320754.1 | AY3: 2350138 | AZ3: 2379908.2 | BA3: 2577085.9 | BB3: 2615222.8 | BC3: 2653889.3 | BD3: 2693104.5 | BE3: 2732888.7
A4: pch_2 | B4: 0.99882422 | C4: 1.0228177 | D4: 1.0402221 | E4: 1.0550312 | F4: 1.0691845 | G4: 1.0848554 | H4: 1.1037925 | I4: 1.1260824 | J4: 1.1512439 | K4: 1.178176 | L4: 1.2055886 | M4: 1.233902 | N4: 1.2622004 | O4: 1.2908226 | P4: 1.3200386 | Q4: 1.3500374 | R4: 1.3809447 | S4: 1.4125964 | T4: 1.4448291 | U4: 1.4774908 | V4: 1.510675 | W4: 1.5437576 | X4: 1.5774032 | Y4: 1.6116914 | Z4: 1.646784 | AA4: 1.6832033 | AB4: 1.7192476 | AC4: 1.7558158 | AD4: 1.7927858 | AE4: 1.8302955 | AF4: 1.8685212 | AG4: 1.907587 | AH4: 1.9476013 | AI4: 1.9885879 | AJ4: 2.0305276 | AK4: 2.0733833 | AL4: 2.1169457 | AM4: 2.1610264 | AN4: 2.2056824 | AO4: 2.2510179 | AP4: 2.2971789 | AQ4: 2.344255 | AR4: 2.392363 | AS4: 2.4415369 | AT4: 2.491778 | AU4: 2.543071 | AV4: 2.5952306 | AW4: 2.6483932 | AX4: 2.7025883 | AY4: 2.7578919 | AZ4: 2.8143732 | BA4: 2.8079159 | BB4: 2.8628385 | BC4: 2.9186835 | BD4: 2.9754759 | BE4: 3.0332421
A5: pch_0 | B5: 0.99828005 | C5: 1.0207176 | D5: 1.0362845 | E5: 1.0490304 | F5: 1.0611011 | G5: 1.0748567 | H5: 1.0921418 | I5: 1.1130528 | J5: 1.1369862 | K5: 1.1626802 | L5: 1.1887195 | M5: 1.2153939 | N5: 1.2418952 | O5: 1.2686304 | P5: 1.2959552 | Q5: 1.3241089 | R5: 1.3531252 | S5: 1.3828598 | T5: 1.4130958 | U5: 1.4436566 | V5: 1.474638 | W5: 1.5054535 | X5: 1.5367707 | Y5: 1.5687037 | Z5: 1.6014276 | AA5: 1.6354641 | AB5: 1.6691966 | AC5: 1.7034025 | AD5: 1.737956 | AE5: 1.7729824 | AF5: 1.808657 | AG5: 1.8451376 | AH5: 1.8825212 | AI5: 1.9208323 | AJ5: 1.9600402 | AK5: 2.0000937 | AL5: 2.0410435 | AM5: 2.0825547 | AN5: 2.1246708 | AO5: 2.1674416 | AP5: 2.2109637 | AQ5: 2.2553436 | AR5: 2.3006647 | AS5: 2.3469715 | AT5: 2.3942727 | AU5: 2.4425577 | AV5: 2.4918107 | AW5: 2.5420662 | AX5: 2.593347 | AY5: 2.6456888 | AZ5: 2.6991249 | BA5: 2.7865972 | BB5: 2.8403225 | BC5: 2.8949394 | BD5: 2.9504706 | BE5: 3.0069409
A6: ch_cagr_2 | B6: 31690.37 | C6: 31592.956 | D6: 31649.989 | E6: 31825.194 | F6: 32077.898 | G6: 32369.135 | H6: 32637.851 | I6: 32884.354 | J6: 33105.567 | K6: 33304.834 | L6: 33536.554 | M6: 33720.203 | N6: 33885.728 | O6: 34038.344 | P6: 34181.461 | Q6: 34318.518 | R6: 34451.821 | S6: 34586.372 | T6: 34725.319 | U6: 34870.559 | V6: 34990.152 | W6: 35138.717 | X6: 35296.478 | Y6: 35458.189 | Z6: 35620.02 | AA6: 35691.173 | AB6: 35781.747 | AC6: 35872.154 | AD6: 35961.825 | AE6: 36050.029 | AF6: 36135.819 | AG6: 36218.81 | AH6: 36298.359 | AI6: 36374.589 | AJ6: 36447.956 | AK6: 36519.068 | AL6: 36573.347 | AM6: 36622.21 | AN6: 36669.153 | AO6: 36715.513 | AP6: 36761.442 | AQ6: 36807.13 | AR6: 36851.686 | AS6: 36894.744 | AT6: 36936.059 | AU6: 36975.497 | AV6: 37016.397 | AW6: 37056.265 | AX6: 37094.844 | AY6: 37131.891 | AZ6: 37167.244 | BA6: 70921.145 | BB6: 72022.173 | BC6: 73137.824 | BD6: 74268.544 | BE6: 75414.848
A7: ch_cagr_0 | B7: 31690.37 | C7: 31616.893 | D7: 31707.055 | E7: 31921.459 | F7: 32215.817 | G7: 32547.556 | H7: 32852.922 | I7: 33130.643 | J7: 33377.918 | K7: 33599.489 | L7: 33851.883 | M7: 34056.559 | N7: 34243.24 | O7: 34417.398 | P7: 34582.448 | Q7: 34741.922 | R7: 34899.984 | S7: 35060.943 | T7: 35228.307 | U7: 35403.968 | V7: 35555.095 | W7: 35736.515 | X7: 35927.61 | Y7: 36122.504 | Z7: 36316.966 | AA7: 36418.237 | AB7: 36537.751 | AC7: 36656.435 | AD7: 36773.871 | AE7: 36889.49 | AF7: 37002.489 | AG7: 37112.202 | AH7: 37218.388 | AI7: 37321.3 | AJ7: 37421.554 | AK7: 37519.904 | AL7: 37597.803 | AM7: 37669.587 | AN7: 37738.802 | AO7: 37807.05 | AP7: 37874.822 | AQ7: 37942.024 | AR7: 38008.342 | AS7: 38073.463 | AT7: 38137.165 | AU7: 38199.31 | AV7: 38261.352 | AW7: 38322.102 | AX7: 38381.236 | AY7: 38438.602 | AZ7: 38494.195 | BA7: 70867.417 | BB7: 71964.44 | BC7: 73076.078 | BD7: 74202.866 | BE7: 75345.39
A8: pch_cagr_2 | B8: 1.0003877 | C8: 1.094609 | D8: 1.1083858 | E8: 1.1123389 | F8: 1.1097826 | G8: 1.1043075 | H8: 1.1001193 | I8: 1.097831 | J8: 1.0999079 | K8: 1.1067624 | L8: 1.1168524 | M8: 1.1344554 | N8: 1.1537601 | O8: 1.1760237 | P8: 1.2003804 | Q8: 1.2259784 | R8: 1.2524317 | S8: 1.2787344 | T8: 1.3046378 | U8: 1.3299525 | V8: 1.3557191 | W8: 1.3786587 | X8: 1.4028474 | Y8: 1.4271986 | Z8: 1.4521746 | AA8: 1.4811183 | AB8: 1.5054906 | AC8: 1.5333275 | AD8: 1.5621614 | AE8: 1.5920856 | AF8: 1.6232564 | AG8: 1.6557017 | AH8: 1.6896612 | AI8: 1.725138 | AJ8: 1.7621365 | AK8: 1.8006247 | AL8: 1.8401097 | AM8: 1.8800831 | AN8: 1.9210191 | AO8: 1.9628636 | AP8: 2.0056789 | AQ8: 2.0494021 | AR8: 2.0944549 | AS8: 2.1409412 | AT8: 2.1890395 | AU8: 2.2388992 | AV8: 2.2897818 | AW8: 2.3428274 | AX8: 2.3976665 | AY8: 2.4543717 | AZ8: 2.5130105 | BA8: 2.8058701 | BB8: 2.8611339 | BC8: 2.9173664 | BD8: 2.9745939 | BE8: 3.0328433
A9: pch_cagr_0 | B9: 0.99762047 | C9: 1.0864455 | D9: 1.0948859 | E9: 1.0926586 | F9: 1.08371 | G9: 1.0721518 | H9: 1.0623856 | I9: 1.0552485 | J9: 1.0530627 | K9: 1.0560719 | L9: 1.0626081 | M9: 1.0762297 | N9: 1.091573 | O9: 1.1095707 | P9: 1.1293072 | Q9: 1.1499132 | R9: 1.1706385 | S9: 1.1909033 | T9: 1.2103435 | U9: 1.2288303 | V9: 1.2473947 | W9: 1.2631269 | X9: 1.2798472 | Y9: 1.2966279 | Z9: 1.313929 | AA9: 1.3347661 | AB9: 1.3516396 | AC9: 1.3715506 | AD9: 1.392335 | AE9: 1.4140295 | AF9: 1.4367216 | AG9: 1.4604891 | AH9: 1.4853774 | AI9: 1.5113901 | AJ9: 1.5384924 | AK9: 1.5666254 | AL9: 1.5963472 | AM9: 1.6260532 | AN9: 1.6565708 | AO9: 1.6878061 | AP9: 1.7197414 | AQ9: 1.7524286 | AR9: 1.7859636 | AS9: 1.8204614 | AT9: 1.8560371 | AU9: 1.8927936 | AV9: 1.9307583 | AW9: 1.9701412 | AX9: 2.0109031 | AY9: 2.053077 | AZ9: 2.0966764 | BA9: 2.7819417 | BB9: 2.8359668 | BC9: 2.890933 | BD9: 2.9468625 | BE9: 3.0037793
A10: ch_cfoo_2 | B10: 175354.78 | C10: 175960.21 | D10: 176581.66 | E10: 177333.22 | F10: 178160.42 | G10: 178942.88 | H10: 179416 | I10: 179664.88 | J10: 179762.63 | K10: 179799.04 | L10: 180116.59 | M10: 180287.91 | N10: 180449.39 | O10: 180612.85 | P10: 180773.04 | Q10: 180925.93 | R10: 181065.65 | S10: 181204.75 | T10: 181352.29 | U10: 181514.01 | V10: 181518.06 | W10: 181651.44 | X10: 181822.62 | Y10: 182003.17 | Z10: 182176.09 | AA10: 181871.51 | AB10: 181661.45 | AC10: 181475.38 | AD10: 181309.69 | AE10: 181157.83 | AF10: 181010.88 | AG10: 180862.84 | AH10: 180707.49 | AI10: 180542.78 | AJ10: 180368.92 | AK10: 180187.13 | AL10: 179922.39 | AM10: 179632.53 | AN10: 179337.27 | AO10: 179043.03 | AP10: 178749.63 | AQ10: 178457.47 | AR10: 178162.77 | AS10: 177864.23 | AT10: 177561.37 | AU10: 177254.16 | AV10: 176959.57 | AW10: 176667.43 | AX10: 176375.14 | AY10: 176080.18 | AZ10: 175780.63 | BA10: 392498.23 | BB10: 398606.43 | BC10: 404797.44 | BD10: 411073.79 | BE10: 417438.32
A11: ch_cfoo_0 | B11: 175354.78 | C11: 176094.92 | D11: 176908.69 | E11: 177893.12 | F11: 178973.79 | G11: 180010.83 | H11: 180726.31 | I11: 181199.63 | J11: 181508.17 | K11: 181750.38 | L11: 182279.25 | M11: 182672.89 | N11: 183061.66 | O11: 183452.31 | P11: 183834.63 | Q11: 184202.21 | R11: 184558.85 | S11: 184915.98 | T11: 185285.99 | U11: 185676.04 | V11: 185909.43 | W11: 186277.34 | X11: 186684.38 | Y11: 187099.52 | Z11: 187504.45 | AA11: 187415.31 | AB11: 187416.35 | AC11: 187439.42 | AD11: 187481.81 | AE11: 187537.46 | AF11: 187597.42 | AG11: 187653.38 | AH11: 187700.01 | AI11: 187735.54 | AJ11: 187760.86 | AK11: 187777.96 | AL11: 187689.96 | AM11: 187566.54 | AN11: 187429.3 | AO11: 187287.5 | AP11: 187143.87 | AQ11: 186998.08 | AR11: 186848.97 | AS11: 186695.83 | AT11: 186538.55 | AU11: 186377.4 | AV11: 186220.22 | AW11: 186061.45 | AX11: 185898.84 | AY11: 185731.05 | AZ11: 185557.45 | BA11: 392026.24 | BB11: 398108.8 | BC11: 404274.29 | BD11: 410525.62 | BE11: 416865.93
A12: pch_cfoo_2 | B12: 0.99827818 | C12: 1.0232887 | D12: 1.0385057 | E12: 1.0531336 | F12: 1.0681731 | G12: 1.0850108 | H12: 1.1051587 | I12: 1.1278993 | J12: 1.1534148 | K12: 1.1811579 | L12: 1.209769 | M12: 1.24184 | N12: 1.2745214 | O12: 1.3085883 | P12: 1.3438718 | Q12: 1.3801596 | R12: 1.417498 | S12: 1.4554949 | T12: 1.4941178 | U12: 1.5333498 | V12: 1.5739495 | W12: 1.6138412 | X12: 1.655281 | Y12: 1.6977942 | Z12: 1.7415999 | AA12: 1.7889311 | AB12: 1.8340112 | AC12: 1.8811187 | AD12: 1.9290479 | AE12: 1.9779352 | AF12: 2.0280133 | AG12: 2.0794145 | AH12: 2.1324022 | AI12: 2.1870877 | AJ12: 2.2435693 | AK12: 2.3019174 | AL12: 2.3618042 | AM12: 2.4228291 | AN12: 2.4852411 | AO12: 2.5490733 | AP12: 2.6144366 | AQ12: 2.6813114 | AR12: 2.7499978 | AS12: 2.8205962 | AT12: 2.8932446 | AU12: 2.9680682 | AV12: 3.0444667 | AW12: 3.1232137 | AX12: 3.2041866 | AY12: 3.2875156 | AZ12: 3.3733221 | BA12: 2.8049115 | BB12: 2.8599435 | BC12: 2.9159151 | BD12: 2.9728518 | BE12: 3.0307803
... A105: pch_cbio_0 | B105: 0.99836407 | C105: 1.0173314 | D105: 1.0312619 | E105: 1.0417764 | F105: 1.0515599 | G105: 1.0633806 | H105: 1.0792727 | I105: 1.0995673 | J105: 1.1234784 | K105: 1.1495116 | L105: 1.1760997 | M105: 1.2029106 | N105: 1.2294318 | O105: 1.2559348 | P105: 1.2828868 | Q105: 1.3106644 | R105: 1.3394051 | S105: 1.3690109 | T105: 1.399256 | U105: 1.4299219 | V105: 1.4609567 | W105: 1.4920176 | X105: 1.5234677 | Y105: 1.5555274 | Z105: 1.5883802 | AA105: 1.6222773 | AB105: 1.65627 | AC105: 1.6905705 | AD105: 1.7252051 | AE105: 1.7602946 | AF105: 1.7960148 | AG105: 1.8325321 | AH105: 1.8699531 | AI105: 1.9083058 | AJ105: 1.9475555 | AK105: 1.9876397 | AL105: 2.0285306 | AM105: 2.0700006 | AN105: 2.1120234 | AO105: 2.1546524 | AP105: 2.1979925 | AQ105: 2.242161 | AR105: 2.2872512 | AS105: 2.3333127 | AT105: 2.3803533 | AU105: 2.428356 | AV105: 2.4773011 | AW105: 2.5272042 | AX105: 2.5780875 | AY105: 2.6299843 | AZ105: 2.682929 | BA105: 2.8142368 | BB105: 2.8683276 | BC105: 2.9232911 | BD105: 2.979147 | BE105: 3.0359177

Sheet Value_Added
A1: _date_ | B1: 42005 | C1: 42370 | D1: 42736 | E1: 43101 | F1: 43466 | G1: 43831 | H1: 44197 | I1: 44562 | J1: 44927 | K1: 45292 | L1: 45658 | M1: 46023 | N1: 46388 | O1: 46753 | P1: 47119 | Q1: 47484 | R1: 47849 | S1: 48214 | T1: 48580 | U1: 48945 | V1: 49310 | W1: 49675 | X1: 50041 | Y1: 50406 | Z1: 50771 | AA1: 51136 | AB1: 51502 | AC1: 51867 | AD1: 52232 | AE1: 52597 | AF1: 52963 | AG1: 53328 | AH1: 53693 | AI1: 54058 | AJ1: 54424 | AK1: 54789 | AL1: 55154 | AM1: 55519 | AN1: 55885 | AO1: 56250 | AP1: 56615 | AQ1: 56980 | AR1: 57346 | AS1: 57711 | AT1: 58076 | AU1: 58441 | AV1: 58807 | AW1: 59172 | AX1: 59537 | AY1: 59902 | AZ1: 60268 | BA1: 60633 | BB1: 60998 | BC1: 61363 | BD1: 61729 | BE1: 62094
A2: va_2 | B2: 1960182 | C2: 1976758.4 | D2: 1999395.2 | E2: 2027383 | F2: 2059288.9 | G2: 2092846.6 | H2: 2124480.5 | I2: 2154522.2 | J2: 2183299.4 | K2: 2211880.9 | L2: 2244095.2 | M2: 2275651 | N2: 2308835.2 | O2: 2343433.5 | P2: 2379039 | Q2: 2415273.5 | R2: 2451872.5 | S2: 2488831.8 | T2: 2526268.2 | U2: 2564334.5 | V2: 2601178.1 | W2: 2640466.7 | X2: 2680604.1 | Y2: 2721443.1 | Z2: 2762843.6 | AA2: 2799095.8 | AB2: 2838046 | AC2: 2877582.7 | AD2: 2917798.3 | AE2: 2958672.1 | AF2: 3000123.9 | AG2: 3042084 | AH2: 3084501 | AI2: 3127378.4 | AJ2: 3170761 | AK2: 3214711.8 | AL2: 3258074.6 | AM2: 3301997.8 | AN2: 3346554.7 | AO2: 3391734.6 | AP2: 3437473.6 | AQ2: 3483723.9 | AR2: 3530438.8 | AS2: 3577617.1 | AT2: 3625292.3 | AU2: 3673515 | AV2: 3722537 | AW2: 3772267.4 | AX2: 3822690.7 | AY2: 3873769.6 | AZ2: 3925466.2 | BA2: 4435341.8 | BB2: 4509946.5 | BC2: 4585737.2 | BD2: 4662731.3 | BE2: 4740947.9
A3: va_0 | B3: 1960604.2 | C3: 1978269.4 | D3: 2002429.9 | E3: 2032193.2 | F3: 2065908.6 | G3: 2101086.4 | H3: 2133987.3 | I3: 2164910.9 | J3: 2194304.2 | K3: 2223438.2 | L3: 2256344 | M3: 2288844.5 | N3: 2323209.1 | O3: 2359135.9 | P3: 2396105.2 | Q3: 2433652.7 | R3: 2471538.1 | S3: 2509766.3 | T3: 2548497.5 | U3: 2587920.7 | V3: 2626172.9 | W3: 2666944 | X3: 2708602.5 | Y3: 2750968.5 | Z3: 2793879 | AA3: 2831541.2 | AB3: 2871875.1 | AC3: 2912798.2 | AD3: 2954432 | AE3: 2996769.4 | AF3: 3039727.5 | AG3: 3083209.1 | AH3: 3127153.3 | AI3: 3171559.2 | AJ3: 3216478 | AK3: 3261984.8 | AL3: 3306769.3 | AM3: 3352033.7 | AN3: 3397884.6 | AO3: 3444356.2 | AP3: 3491424.9 | AQ3: 3539042.6 | AR3: 3587170.9 | AS3: 3635800.6 | AT3: 3684954.3 | AU3: 3734674.2 | AV3: 3785128.3 | AW3: 3836242.8 | AX3: 3888021.5 | AY3: 3940457.5 | AZ3: 3993542.8 | BA3: 4443934.9 | BB3: 4518812.6 | BC3: 4594869.4 | BD3: 4672125.4 | BE3: 4750601.9
A4: va_sagr_2 | B4: 31702.271 | C4: 31364.307 | D4: 31247.587 | E4: 31232.561 | F4: 31310.887 | G4: 31452.733 | H4: 31594.771 | I4: 31722.169 | J4: 31819.089 | K4: 31882.179 | L4: 31956.143 | M4: 31969.015 | N4: 31952.369 | O4: 31909.072 | P4: 31845.181 | Q4: 31767.885 | R4: 31679.161 | S4: 31591.173 | T4: 31510.653 | U4: 31441.907 | V4: 31359.534 | W4: 31310.809 | X4: 31275.515 | Y4: 31250.505 | Z4: 31230.591 | AA4: 31137.924 | AB4: 31069.504 | AC4: 30998.795 | AD4: 30929.942 | AE4: 30862.826 | AF4: 30796.18 | AG4: 30729.922 | AH4: 30661.635 | AI4: 30590.541 | AJ4: 30516.526 | AK4: 30439.913 | AL4: 30359.457 | AM4: 30278.6 | AN4: 30198.406 | AO4: 30120.339 | AP4: 30044.734 | AQ4: 29973.327 | AR4: 29903.693 | AS4: 29834.87 | AT4: 29766.084 | AU4: 29696.715 | AV4: 29634.978 | AW4: 29573.984 | AX4: 29512.959 | AY4: 29451.407 | AZ4: 29388.973 | BA4: 67172.114 | BB4: 68268.616 | BC4: 69383.552 | BD4: 70517.275 | BE4: 71670.165
A5: va_sagr_0 | B5: 31880.126 | C5: 31641.075 | D5: 31630.864 | E5: 31741.553 | F5: 31961.003 | G5: 32253.301 | H5: 32549.697 | I5: 32829.616 | J5: 33074.293 | K5: 33279.516 | L5: 33492.145 | M5: 33644.08 | N5: 33764.011 | O5: 33854.948 | P5: 33923.457 | Q5: 33977.568 | R5: 34026.495 | S5: 34079.483 | T5: 34144.274 | U5: 34225.836 | V5: 34296.504 | W5: 34406.114 | X5: 34532.715 | Y5: 34672.102 | Z5: 34818.005 | AA5: 34883.963 | AB5: 34971.822 | AC5: 35055.881 | AD5: 35141.094 | AE5: 35227.758 | AF5: 35314.868 | AG5: 35400.994 | AH5: 35484.973 | AI5: 35566.281 | AJ5: 35645.058 | AK5: 35721.905 | AL5: 35779.741 | AM5: 35833.702 | AN5: 35886.077 | AO5: 35939.253 | AP5: 35994.493 | AQ5: 36052.141 | AR5: 36111.962 | AS5: 36173.447 | AT5: 36236.015 | AU5: 36299.106 | AV5: 36363.682 | AW5: 36428.059 | AX5: 36491.757 | AY5: 36554.398 | AZ5: 36615.843 | BA5: 67585.328 | BB5: 68702.047 | BC5: 69837.617 | BD5: 70992.484 | BE5: 72167.112
A6: va_sfor_2 | B6: 3191.294 | C6: 3059.9296 | D6: 2976.6871 | E6: 2918.2962 | F6: 2877.7648 | G6: 2850.3114 | H6: 2829.9922 | I6: 2814.9749 | J6: 2803.4992 | K6: 2794.6895 | L6: 2791.0408 | M6: 2786.7743 | N6: 2784.1246 | O6: 2783.1757 | P6: 2783.6141 | Q6: 2785.0462 | R6: 2786.1918 | S6: 2787.5107 | T6: 2789.0283 | U6: 2790.7523 | V6: 2790.8296 | W6: 2792.6713 | X6: 2794.9419 | Y6: 2797.3527 | Z6: 2799.7102 | AA6: 2796.7346 | AB6: 2795.9186 | AC6: 2795.2627 | AD6: 2794.5403 | AE6: 2793.6561 | AF6: 2792.4962 | AG6: 2791.2648 | AH6: 2789.6052 | AI6: 2787.3845 | AJ6: 2784.5365 | AK6: 2781.0265 | AL6: 2779.0885 | AM6: 2777.2195 | AN6: 2775.0853 | AO6: 2772.585 | AP6: 2769.6275 | AQ6: 2766.7198 | AR6: 2763.3257 | AS6: 2759.2884 | AT6: 2754.5397 | AU6: 2749.0415 | AV6: 2745.1798 | AW6: 2741.1578 | AX6: 2736.6069 | AY6: 2731.4053 | AZ6: 2725.4726 | BA6: 5874.255 | BB6: 5909.5567 | BC6: 5945.76 | BD6: 5982.8525 | BE6: 6020.836
A7: va_sfor_0 | B7: 3336.8299 | C7: 3245.1914 | D7: 3179.7634 | E7: 3134.5321 | F7: 3105.7418 | G7: 3089.8588 | H7: 3081.7497 | I7: 3079.8816 | J7: 3082.5104 | K7: 3088.6836 | L7: 3101.0987 | M7: 3114.2221 | N7: 3129.5759 | O7: 3146.9263 | P7: 3166.3166 | Q7: 3187.6099 | R7: 3210.5381 | S7: 3234.8699 | T7: 3260.4989 | U7: 3287.413 | V7: 3313.4459 | W7: 3342.4284 | X7: 3372.9465 | Y7: 3404.6494 | Z7: 3437.2906 | AA7: 3464.4793 | AB7: 3494.2013 | AC7: 3524.8838 | AD7: 3556.4368 | AE7: 3588.8342 | AF7: 3622.0057 | AG7: 3655.8481 | AH7: 3690.2601 | AI7: 3725.1733 | AJ7: 3760.5647 | AK7: 3796.4509 | AL7: 3831.4039 | AM7: 3866.5957 | AN7: 3902.2843 | AO7: 3938.5722 | AP7: 3975.4839 | AQ7: 4012.9979 | AR7: 4051.0746 | AS7: 4089.6802 | AT7: 4128.7999 | AU7: 4168.4404 | AV7: 4208.751 | AW7: 4249.6523 | AX7: 4291.1405 | AY7: 4333.2147 | AZ7: 4375.8722 | BA7: 6087.6811 | BB7: 6128.0492 | BC7: 6169.2545 | BD7: 6211.3268 | BE7: 6254.2851
A8: va_sfoo_2 | B8: 43312.513 | C8: 43277.398 | D8: 43391.701 | E8: 43566.954 | F8: 43785.723 | G8: 44014.841 | H8: 44183.015 | I8: 44311.144 | J8: 44404.466 | K8: 44478.795 | L8: 44617.823 | M8: 44700.108 | N8: 44781.855 | O8: 44859.031 | P8: 44931.837 | Q8: 45001.178 | R8: 45067.931 | S8: 45135.614 | T8: 45207.066 | U8: 45284.378 | V8: 45322.94 | W8: 45406.249 | X8: 45495.72 | Y8: 45589.92 | Z8: 45684.872 | AA8: 45655.894 | AB8: 45676.096 | AC8: 45696.029 | AD8: 45722.394 | AE8: 45754.308 | AF8: 45789.802 | AG8: 45827.128 | AH8: 45864.585 | AI8: 45901.251 | AJ8: 45936.674 | AK8: 45970.755 | AL8: 45981.028 | AM8: 45990.395 | AN8: 46000.713 | AO8: 46013.143 | AP8: 46027.568 | AQ8: 46043.844 | AR8: 46061.2 | AS8: 46079.169 | AT8: 46097.313 | AU8: 46115.32 | AV8: 46136.782 | AW8: 46159.453 | AX8: 46183.201 | AY8: 46207.258 | AZ8: 46231.016 | BA8: 96965.867 | BB8: 98541.798 | BC8: 100143.18 | BD8: 101770.58 | BE8: 103424.59
A9: va_sfoo_0 | B9: 43304.308 | C9: 43292.737 | D9: 43448.792 | E9: 43683.814 | F9: 43974.305 | G9: 44281.118 | H9: 44528.13 | I9: 44733.619 | J9: 44902.486 | K9: 45051.527 | L9: 45266.525 | M9: 45425.826 | N9: 45585.501 | O9: 45740.53 | P9: 45889.944 | Q9: 46034.145 | R9: 46175.841 | S9: 46319.234 | T9: 46468.385 | U9: 46625.771 | V9: 46745.184 | W9: 46912.279 | X9: 47086.53 | Y9: 47265.986 | Z9: 47446.261 | AA9: 47497.478 | AB9: 47599.32 | AC9: 47700.314 | AD9: 47807.636 | AE9: 47920.643 | AF9: 48037.452 | AG9: 48155.953 | AH9: 48274.505 | AI9: 48392.217 | AJ9: 48508.851 | AK9: 48624.537 | AL9: 48712.06 | AM9: 48796.163 | AN9: 48878.313 | AO9: 48960.583 | AP9: 49043.806 | AQ9: 49128.089 | AR9: 49213.256 | AS9: 49299.112 | AT9: 49385.53 | AU9: 49472.421 | AV9: 49561.891 | AW9: 49651.724 | AX9: 49741.585 | AY9: 49831.095 | AZ9: 49920.059 | BA9: 97166.535 | BB9: 98753.341 | BC9: 100365.95 | BD9: 102005.01 | BE9: 103671.19
A10: va_sveh_2 | B10: 29902.765 | C10: 30017.437 | D10: 30375.799 | E10: 30781.787 | F10: 31209.714 | G10: 31645.618 | H10: 32041.04 | I10: 32430.394 | J10: 32811.493 | K10: 33192.738 | L10: 33645.414 | M10: 34040.772 | N10: 34460.864 | O10: 34895.702 | P10: 35340.248 | Q10: 35791.521 | R10: 36247.879 | S10: 36710.088 | T10: 37180.022 | U10: 37659.564 | V10: 38105.328 | W10: 38615.764 | X10: 39131.009 | Y10: 39655.552 | Z10: 40189.082 | AA10: 40602.812 | AB10: 41117.494 | AC10: 41634.723 | AD10: 42162.326 | AE10: 42701.072 | AF10: 43249.855 | AG10: 43807.52 | AH10: 44373.12 | AI10: 44946.257 | AJ10: 45527.038 | AK10: 46115.814 | AL10: 46683.818 | AM10: 47267.551 | AN10: 47862.36 | AO10: 48467.252 | AP10: 49081.38 | AQ10: 49704.13 | AR10: 50334.893 | AS10: 50973.442 | AT10: 51619.93 | AU10: 52274.689 | AV10: 52941.671 | AW10: 53617.743 | AX10: 54303.117 | AY10: 54997.542 | AZ10: 55700.682 | BA10: 65498.841 | BB10: 66590.703 | BC10: 67703.293 | BD10: 68836.852 | BE10: 69991.633
A11: va_sveh_0 | B11: 29905.682 | C11: 30032.842 | D11: 30409.116 | E11: 30836.435 | F11: 31287.519 | G11: 31746.247 | H11: 32162.109 | I11: 32568.695 | J11: 32964.464 | K11: 33359.546 | L11: 33827.314 | M11: 34239.744 | N11: 34679.039 | O11: 35134.234 | P11: 35599.303 | Q11: 36070.522 | R11: 36546.601 | S11: 37028.501 | T11: 37518.46 | U11: 38018.763 | V11: 38485.699 | W11: 39018.497 | X11: 39556.565 | Y11: 40104.141 | Z11: 40660.667 | AA11: 41095.692 | AB11: 41632.16 | AC11: 42171.071 | AD11: 42720.711 | AE11: 43281.942 | AF11: 43853.619 | AG11: 44434.3 | AH11: 45022.926 | AI11: 45619.079 | AJ11: 46222.925 | AK11: 46834.946 | AL11: 47424.522 | AM11: 48028.845 | AN11: 48643.663 | AO11: 49268.353 | AP11: 49902.452 | AQ11: 50545.344 | AR11: 51196.497 | AS11: 51855.66 | AT11: 52522.897 | AU11: 53198.483 | AV11: 53885.537 | AW11: 54580.961 | AX11: 55285.229 | AY11: 55998.339 | AZ11: 56720.229 | BA11: 65824.513 | BB11: 66933.933 | BC11: 68064.483 | BD11: 69216.46 | BE11: 70390.153
A12: va_sgla_2 | B12: 7304.584 | C12: 7371.084 | D12: 7464.0713 | E12: 7583.7097 | F12: 7722.3809 | G12: 7867.6181 | H12: 8002.1122 | I12: 8124.848 | J12: 8237.3239 | K12: 8345.3622 | L12: 8465.4473 | M12: 8583.5852 | N12: 8708.9439 | O12: 8841.1314 | P12: 8978.3703 | Q12: 9118.8236 | R12: 9261.1465 | S12: 9405.2304 | T12: 9551.6568 | U12: 9701.2215 | V12: 9847.3219 | W12: 10003.472 | X12: 10163.91 | Y12: 10327.701 | Z12: 10494.008 | AA12: 10641.673 | AB12: 10799.477 | AC12: 10960.359 | AD12: 11124.516 | AE12: 11291.705 | AF12: 11461.365 | AG12: 11632.981 | AH12: 11806.165 | AI12: 11980.832 | AJ12: 12157.16 | AK12: 12335.458 | AL12: 12511.733 | AM12: 12690.358 | AN12: 12871.756 | AO12: 13055.824 | AP12: 13242.137 | AQ12: 13430.319 | AR12: 13620.026 | AS12: 13811.154 | AT12: 14003.81 | AU12: 14198.223 | AV12: 14395.48 | AW12: 14595.332 | AX12: 14797.703 | AY12: 15002.394 | AZ12: 15209.191 | BA12: 18849.052 | BB12: 19187.774 | BC12: 19530.907 | BD12: 19878.417 | BE12: 20230.281
... A79: va_ser_0 | B79: 1520099.7 | C79: 1536591.1 | D79: 1557434.4 | E79: 1582383.3 | F79: 1610153.3 | G79: 1638816.9 | H79: 1665543.2 | I79: 1690625.2 | J79: 1714528.6 | K79: 1738329.8 | L79: 1765181.8 | M79: 1791936.3 | N79: 1820249.2 | O79: 1849866.8 | P79: 1880338.4 | Q79: 1911267 | R79: 1942445.9 | S79: 1973871.3 | T79: 2005667.2 | U79: 2037981.4 | V79: 2069380.2 | W79: 2102676.7 | X79: 2136660.4 | Y79: 2171176.6 | Z79: 2206104.3 | AA79: 2236982.2 | AB79: 2269849.8 | AC79: 2303206.9 | AD79: 2337123.7 | AE79: 2371592.7 | AF79: 2406550.9 | AG79: 2441926.5 | AH79: 2477678.3 | AI79: 2513813 | AJ79: 2550377.2 | AK79: 2587434.6 | AL79: 2623971.8 | AM79: 2660898.5 | AN79: 2698308.3 | AO79: 2736225.1 | AP79: 2774627.1 | AQ79: 2813475.7 | AR79: 2852742.3 | AS79: 2892423.2 | AT79: 2932540.5 | AU79: 2973131.3 | AV79: 3014329.7 | AW79: 3056082.2 | AX79: 3098391.2 | AY79: 3141251.5 | AZ79: 3184656.5 | BA79: 3421146.1 | BB79: 3478549.8 | BC79: 3536883.8 | BD79: 3596166.6 | BE79: 3656417.6

Sheet INV
A1: _date_ | B1: 42005 | C1: 42370 | D1: 42736 | E1: 43101 | F1: 43466 | G1: 43831 | H1: 44197 | I1: 44562 | J1: 44927 | K1: 45292 | L1: 45658 | M1: 46023 | N1: 46388 | O1: 46753 | P1: 47119 | Q1: 47484 | R1: 47849 | S1: 48214 | T1: 48580 | U1: 48945 | V1: 49310 | W1: 49675 | X1: 50041 | Y1: 50406 | Z1: 50771 | AA1: 51136 | AB1: 51502 | AC1: 51867 | AD1: 52232 | AE1: 52597 | AF1: 52963 | AG1: 53328 | AH1: 53693 | AI1: 54058 | AJ1: 54424 | AK1: 54789 | AL1: 55154 | AM1: 55519 | AN1: 55885 | AO1: 56250 | AP1: 56615 | AQ1: 56980 | AR1: 57346 | AS1: 57711 | AT1: 58076 | AU1: 58441 | AV1: 58807 | AW1: 59172 | AX1: 59537 | AY1: 59902 | AZ1: 60268 | BA1: 60633 | BB1: 60998 | BC1: 61363 | BD1: 61729 | BE1: 62094
A2: ia_2 | B2: 473359.89 | C2: 477606.76 | D2: 482931.79 | E2: 489918.11 | F2: 498265.2 | G2: 507166.58 | H2: 515520.14 | I2: 522997.07 | J2: 529688.09 | K2: 536005.95 | L2: 542889.97 | M2: 550017.62 | N2: 557672.98 | O2: 565887.59 | P2: 574561.48 | Q2: 583562.76 | R2: 592779.44 | S2: 602183.89 | T2: 611800.39 | U2: 621675.97 | V2: 631525.9 | W2: 641850.77 | X2: 652544.57 | Y2: 663517.67 | Z2: 674693.36 | AA2: 685094.13 | AB2: 695697.7 | AC2: 706510.72 | AD2: 717540.68 | AE2: 728766.16 | AF2: 740144.61 | AG2: 751635.6 | AH2: 763207.13 | AI2: 774850.07 | AJ2: 786575.74 | AK2: 798407.34 | AL2: 810193.98 | AM2: 822065.73 | AN2: 834082.81 | AO2: 846251.09 | AP2: 858543.36 | AQ2: 870930.59 | AR2: 883383.37 | AS2: 895889.98 | AT2: 908455.3 | AU2: 921094.97 | AV2: 933876.31 | AW2: 946800.53 | AX2: 959863.35 | AY2: 973050.95 | AZ2: 986347.16 | BA2: 1177882.7 | BB2: 1199509.8 | BC2: 1221370.1 | BD2: 1243459.7 | BE2: 1265775.4
A3: ia_0 | B3: 473424.03 | C3: 478026.45 | D3: 483933.8 | E3: 491660.22 | F3: 500804.69 | G3: 510439.99 | H3: 519364.79 | I3: 527217.87 | J3: 534132.01 | K3: 540604.54 | L3: 547664.23 | M3: 555049.34 | N3: 563052.44 | O3: 571681.32 | P3: 580795.13 | Q3: 590224.99 | R3: 599858.61 | S3: 609669.35 | T3: 619696.65 | U3: 630002.56 | V3: 640303.48 | W3: 651104.27 | X3: 662289.03 | Y3: 673753.53 | Z3: 685409.15 | AA3: 696253.61 | AB3: 707274.11 | AC3: 718494.24 | AD3: 729933.71 | AE3: 741578.09 | AF3: 753385.34 | AG3: 765305.5 | AH3: 777301.51 | AI3: 789361.39 | AJ3: 801497.99 | AK3: 813739.1 | AL3: 825884.11 | AM3: 838071.23 | AN3: 850371.48 | AO3: 862808.25 | AP3: 875372.18 | AQ3: 888038.16 | AR3: 900781.34 | AS3: 913588.03 | AT3: 926459.01 | AU3: 939406.09 | AV3: 952465.75 | AW3: 965640.43 | AX3: 978930.82 | AY3: 992334.59 | AZ3: 1005848.5 | BA3: 1178106.1 | BB3: 1199473.1 | BC3: 1221043.8 | BD3: 1242814.7 | BE3: 1264783.3
A4: ia_sagr_2 | B4: 11295.413 | C4: 11292.574 | D4: 11275.665 | E4: 11280.572 | F4: 11314.742 | G4: 11370.437 | H4: 11428.54 | I4: 11479.382 | J4: 11518.041 | K4: 11544.264 | L4: 11569.682 | M4: 11583.03 | N4: 11585.804 | O4: 11578.119 | P4: 11560.75 | Q4: 11535.451 | R4: 11504.617 | S4: 11471.492 | T4: 11439.148 | U4: 11410.088 | V4: 11379.59 | W4: 11356.611 | X4: 11340.157 | Y4: 11329.034 | Z4: 11321.588 | AA4: 11299.376 | AB4: 11276.522 | AC4: 11253.527 | AD4: 11231.512 | AE4: 11210.818 | AF4: 11191.194 | AG4: 11172.209 | AH4: 11153.402 | AI4: 11134.534 | AJ4: 11115.579 | AK4: 11096.678 | AL4: 11075.166 | AM4: 11052.755 | AN4: 11030.808 | AO4: 11010.182 | AP4: 10991.242 | AQ4: 10974.104 | AR4: 10958.623 | AS4: 10944.632 | AT4: 10931.945 | AU4: 10920.382 | AV4: 10910.38 | AW4: 10901.718 | AX4: 10894.296 | AY4: 10887.942 | AZ4: 10882.482 | BA4: 10115.605 | BB4: 10299.337 | BC4: 10486.053 | BD4: 10675.801 | BE4: 10868.635
A5: ia_sagr_0 | B5: 11289.598 | C5: 11286.963 | D5: 11278.653 | E5: 11300.219 | F5: 11357.149 | G5: 11438.824 | H5: 11523.27 | I5: 11598.859 | J5: 11659.869 | K5: 11706.099 | L5: 11749.765 | M5: 11779.977 | N5: 11798.387 | O5: 11805.154 | P5: 11800.999 | Q5: 11787.724 | R5: 11768.312 | S5: 11746.481 | T5: 11725.908 | U5: 11709.469 | V5: 11692.321 | W5: 11683.521 | X5: 11681.681 | Y5: 11685.168 | Z5: 11691.949 | AA5: 11682.667 | AB5: 11671.86 | AC5: 11660.054 | AD5: 11648.39 | AE5: 11637.25 | AF5: 11626.425 | AG5: 11615.457 | AH5: 11603.946 | AI5: 11591.729 | AJ5: 11578.913 | AK5: 11565.791 | AL5: 11549.039 | AM5: 11530.481 | AN5: 11511.38 | AO5: 11492.673 | AP5: 11474.925 | AQ5: 11458.39 | AR5: 11443.122 | AS5: 11429.082 | AT5: 11416.203 | AU5: 11404.408 | AV5: 11393.902 | AW5: 11384.451 | AX5: 11375.856 | AY5: 11367.956 | AZ5: 11360.655 | BA5: 10005.858 | BB5: 10179.346 | BC5: 10355.366 | BD5: 10533.98 | BE5: 10715.259
A6: ia_sfor_2 | B6: 917.31609 | C6: 914.07458 | D6: 900.76732 | E6: 888.16475 | F6: 879.29749 | G6: 874.11165 | H6: 871.34866 | I6: 870.25273 | J6: 870.3953 | K6: 871.66172 | L6: 874.68517 | M6: 878.83055 | N6: 884.15005 | O6: 890.63669 | P6: 898.21693 | Q6: 906.78567 | R6: 916.3389 | S6: 926.78714 | T6: 938.08966 | U6: 950.25742 | V6: 962.90317 | W6: 976.61747 | X6: 991.37939 | Y6: 1007.1231 | Z6: 1023.7876 | AA6: 1040.1179 | AB6: 1057.1243 | AC6: 1074.9822 | AD6: 1093.7511 | AE6: 1113.4375 | AF6: 1134.0241 | AG6: 1155.449 | AH6: 1177.7042 | AI6: 1200.7919 | AJ6: 1224.7209 | AK6: 1249.5099 | AL6: 1274.4931 | AM6: 1299.9597 | AN6: 1326.1585 | AO6: 1353.1957 | AP6: 1381.0956 | AQ6: 1409.774 | AR6: 1439.2395 | AS6: 1469.5016 | AT6: 1500.5651 | AU6: 1532.439 | AV6: 1564.8763 | AW6: 1598.0047 | AX6: 1631.9298 | AY6: 1666.6863 | AZ6: 1702.2764 | BA6: 199.57863 | BB6: 201.78804 | BC6: 204.05383 | BD6: 206.37422 | BE6: 208.74816
A7: ia_sfor_0 | B7: 901.89303 | C7: 889.1757 | D7: 871.51773 | E7: 855.8205 | F7: 843.55374 | G7: 834.24694 | H7: 826.65963 | I7: 820.21885 | J7: 814.66988 | K7: 810.02097 | L7: 806.93512 | M7: 804.72565 | N7: 803.42938 | O7: 802.97502 | P7: 803.29846 | Q7: 804.33237 | R7: 806.01264 | S7: 808.2992 | T7: 811.1844 | U7: 814.67967 | V7: 818.43104 | W7: 822.94527 | X7: 828.1527 | Y7: 833.95162 | Z7: 840.25065 | AA7: 845.96549 | AB7: 852.02843 | AC7: 858.53308 | AD7: 865.49392 | AE7: 872.89486 | AF7: 880.70238 | AG7: 888.87573 | AH7: 897.37852 | AI7: 906.18757 | AJ7: 915.29556 | AK7: 924.70756 | AL7: 934.19583 | AM7: 943.86618 | AN7: 953.79809 | AO7: 964.02948 | AP7: 974.56656 | AQ7: 985.39699 | AR7: 996.50181 | AS7: 1007.8643 | AT7: 1019.4746 | AU7: 1031.3298 | AV7: 1043.4525 | AW7: 1055.8358 | AX7: 1068.4725 | AY7: 1081.3553 | AZ7: 1094.4768 | BA7: 197.80669 | BB7: 199.45136 | BC7: 201.12123 | BD7: 202.81739 | BE7: 204.54058
A8: ia_sfoo_2 | B8: 6409.783 | C8: 6435.8717 | D8: 6455.3029 | E8: 6480.1825 | F8: 6510.6856 | G8: 6540.6135 | H8: 6559.1829 | I8: 6564.3115 | J8: 6557.7574 | K8: 6543.9782 | L8: 6533.8231 | M8: 6521.5271 | N8: 6509.1313 | O8: 6496.697 | P8: 6483.821 | Q8: 6470.218 | R8: 6455.8072 | S8: 6441.1708 | T8: 6427.0363 | U8: 6414.0474 | V8: 6398.7119 | W8: 6386.4553 | X8: 6376.4258 | Y8: 6367.8727 | Z8: 6360.0292 | AA8: 6342.1811 | AB8: 6324.0211 | AC8: 6306.2315 | AD8: 6289.5102 | AE8: 6273.9678 | AF8: 6259.3713 | AG8: 6245.4384 | AH8: 6231.8995 | AI8: 6218.6258 | AJ8: 6205.6059 | AK8: 6192.8982 | AL8: 6178.9698 | AM8: 6164.7946 | AN8: 6151.0239 | AO8: 6137.97 | AP8: 6125.6755 | AQ8: 6114.1176 | AR8: 6103.1883 | AS8: 6092.8252 | AT8: 6083.0012 | AU8: 6073.7107 | AV8: 6065.3427 | AW8: 6057.8244 | AX8: 6051.0881 | AY8: 6045.0104 | AZ8: 6039.4645 | BA8: 15729.282 | BB8: 15995.347 | BC8: 16265.227 | BD8: 16538.998 | BE8: 16816.744
A9: ia_sfoo_0 | B9: 6409.8967 | C9: 6440.0728 | D9: 6467.1861 | E9: 6503.1208 | F9: 6547.0935 | G9: 6591.5645 | H9: 6624.5389 | I9: 6643.296 | J9: 6649.6469 | K9: 6648.5159 | L9: 6651.3684 | M9: 6652.7221 | N9: 6654.5211 | O9: 6656.5284 | P9: 6657.9618 | Q9: 6658.2697 | R9: 6657.5541 | S9: 6656.5326 | T9: 6656.1814 | U9: 6657.3141 | V9: 6656.3101 | W9: 6658.7493 | X9: 6663.6078 | Y9: 6669.9564 | Z9: 6676.8914 | AA9: 6673.0639 | AB9: 6668.6205 | AC9: 6664.3457 | AD9: 6661.0143 | AE9: 6658.7745 | AF9: 6657.3893 | AG9: 6656.4975 | AH9: 6655.8076 | AI9: 6655.1896 | AJ9: 6654.6693 | AK9: 6654.361 | AL9: 6652.1557 | AM9: 6649.108 | AN9: 6645.8929 | AO9: 6642.934 | AP9: 6640.4153 | AQ9: 6638.3679 | AR9: 6636.7661 | AS9: 6635.5938 | AT9: 6634.867 | AU9: 6634.6213 | AV9: 6635.0633 | AW9: 6636.1195 | AX9: 6637.7129 | AY9: 6639.7664 | AZ9: 6642.2226 | BA9: 15744.006 | BB9: 16009.638 | BC9: 16279.013 | BD9: 16552.219 | BE9: 16829.359
A10: ia_sveh_2 | B10: 13657.1 | C10: 13763.82 | D10: 13897.865 | E10: 14064.969 | F10: 14254.82 | G10: 14455.652 | H10: 14648.292 | I10: 14831.977 | J10: 15008.105 | K10: 15180.817 | L10: 15371.289 | M10: 15558.328 | N10: 15749.167 | O10: 15946.302 | P10: 16149.388 | Q10: 16357.222 | R10: 16568.651 | S10: 16783.459 | T10: 17002.133 | U10: 17225.488 | V10: 17442.756 | W10: 17672.82 | X10: 17911.917 | Y10: 18157.782 | Z10: 18409.074 | AA10: 18631.987 | AB10: 18863.731 | AC10: 19102.939 | AD10: 19348.648 | AE10: 19600.253 | AF10: 19857.072 | AG10: 20118.441 | AH10: 20383.767 | AI10: 20652.697 | AJ10: 20925.144 | AK10: 21201.213 | AL10: 21473.777 | AM10: 21747.821 | AN10: 22025.556 | AO10: 22307.675 | AP10: 22594.127 | AQ10: 22884.66 | AR10: 23178.923 | AS10: 23476.701 | AT10: 23777.957 | AU10: 24082.799 | AV10: 24392.442 | AW10: 24706.66 | AX10: 25025.307 | AY10: 25348.213 | AZ10: 25675.19 | BA10: 83532.613 | BB10: 84996.056 | BC10: 86487.327 | BD10: 88006.746 | BE10: 89554.625
A11: ia_sveh_0 | B11: 13658.389 | C11: 13770.311 | D11: 13912.949 | E11: 14091.308 | F11: 14294.095 | G11: 14508.312 | H11: 14713.571 | I11: 14908.359 | J11: 15094.064 | K11: 15275.453 | L11: 15474.68 | M11: 15671.261 | N11: 15872.676 | O11: 16081.219 | P11: 16296.105 | Q11: 16515.679 | R11: 16738.75 | S11: 16965.109 | T11: 17195.393 | U11: 17430.606 | V11: 17659.946 | W11: 17902.499 | X11: 18154.393 | Y11: 18413.195 | Z11: 18677.407 | AA11: 18912.609 | AB11: 19156.36 | AC11: 19407.424 | AD11: 19664.984 | AE11: 19928.53 | AF11: 20197.405 | AG11: 20470.845 | AH11: 20748.184 | AI11: 21029.028 | AJ11: 21313.294 | AK11: 21601.136 | AL11: 21884.748 | AM11: 22169.138 | AN11: 22456.644 | AO11: 22748.158 | AP11: 23043.851 | AQ11: 23343.548 | AR11: 23646.976 | AS11: 23953.932 | AT11: 24264.359 | AU11: 24578.334 | AV11: 24896.731 | AW11: 25219.263 | AX11: 25545.822 | AY11: 25876.35 | AZ11: 26210.809 | BA11: 83865.215 | BB11: 85340.07 | BC11: 86842.389 | BD11: 88372.522 | BE11: 89930.811
A12: ia_sgla_2 | B12: 1578.4707 | C12: 1593.7095 | D12: 1613.1893 | E12: 1639.0586 | F12: 1670.3936 | G12: 1704.2505 | H12: 1736.4745 | I12: 1765.2968 | J12: 1790.641 | K12: 1813.852 | L12: 1838.1954 | M12: 1863.1259 | N12: 1889.733 | O12: 1918.2683 | P12: 1948.4654 | Q12: 1979.8735 | R12: 2012.0651 | S12: 2044.9037 | T12: 2078.4556 | U12: 2112.8913 | V12: 2147.3638 | W12: 2183.3978 | X12: 2220.7501 | Y12: 2259.1232 | Z12: 2298.218 | AA12: 2334.9491 | AB12: 2372.1537 | AC12: 2410.0262 | AD12: 2448.6626 | AE12: 2488.0013 | AF12: 2527.8791 | AG12: 2568.1264 | AH12: 2608.5982 | AI12: 2649.2343 | AJ12: 2690.0575 | AK12: 2731.1453 | AL12: 2772.0835 | AM12: 2813.2646 | AN12: 2854.9176 | AO12: 2897.0878 | AP12: 2939.6867 | AQ12: 2982.6028 | AR12: 3025.7139 | AS12: 3068.959 | AT12: 3112.3422 | AU12: 3155.9145 | AV12: 3199.9148 | AW12: 3244.3724 | AX12: 3289.2861 | AY12: 3334.6123 | AZ12: 3380.2931 | BA12: 3690.9251 | BB12: 3761.0731 | BC12: 3831.946 | BD12: 3903.5198 | BE12: 3975.7724
... A79: ia_ser_0 | B79: 367437.95 | C79: 371326.72 | D79: 376444.41 | E79: 383119.08 | F79: 390948.61 | G79: 399100.06 | H79: 406551.77 | I79: 413006.99 | J79: 418616.31 | K79: 423847.96 | L79: 429579.23 | M79: 435649.84 | N79: 442305.78 | O79: 449540.86 | P79: 457218.69 | Q79: 465181.08 | R79: 473323.23 | S79: 481618.2 | T79: 490098.39 | U79: 498816.15 | V79: 507551.85 | W79: 516700.65 | X79: 526164.06 | Y79: 535852.82 | Z79: 545691.29 | AA79: 554891.75 | AB79: 564237.67 | AC79: 573749.51 | AD79: 583444.11 | AE79: 593307.2 | AF79: 603300.52 | AG79: 613379.81 | AH79: 623513.3 | AI79: 633692.07 | AJ79: 643929.27 | AK79: 654250.81 | AL79: 664501.92 | AM79: 674794.78 | AN79: 685185.65 | AO79: 695690.75 | AP79: 706298.58 | AQ79: 716984.86 | AR79: 727726.67 | AS79: 738511.86 | AT79: 749341.6 | AU79: 760227.01 | AV79: 771198.88 | AW79: 782260.47 | AX79: 793412.76 | AY79: 804653.73 | AZ79: 815980.31 | BA79: 521119.84 | BB79: 530169.71 | BC79: 539346.77 | BD79: 548653.06 | BE79: 558090.89

Sheet Labor
A1: _date_ | B1: 42005 | C1: 42370 | D1: 42736 | E1: 43101 | F1: 43466 | G1: 43831 | H1: 44197 | I1: 44562 | J1: 44927 | K1: 45292 | L1: 45658 | M1: 46023 | N1: 46388 | O1: 46753 | P1: 47119 | Q1: 47484 | R1: 47849 | S1: 48214 | T1: 48580 | U1: 48945 | V1: 49310 | W1: 49675 | X1: 50041 | Y1: 50406 | Z1: 50771 | AA1: 51136 | AB1: 51502 | AC1: 51867 | AD1: 52232 | AE1: 52597 | AF1: 52963 | AG1: 53328 | AH1: 53693 | AI1: 54058 | AJ1: 54424 | AK1: 54789 | AL1: 55154 | AM1: 55519 | AN1: 55885 | AO1: 56250 | AP1: 56615 | AQ1: 56980 | AR1: 57346 | AS1: 57711 | AT1: 58076 | AU1: 58441 | AV1: 58807 | AW1: 59172 | AX1: 59537 | AY1: 59902 | AZ1: 60268 | BA1: 60633 | BB1: 60998 | BC1: 61363 | BD1: 61729 | BE1: 62094
A2: f_l_2 | B2: 27372.557 | C2: 27356.102 | D2: 27328.719 | E2: 27324.639 | F2: 27358.782 | G2: 27429.345 | H2: 27513.824 | I2: 27601.584 | J2: 27686.077 | K2: 27765.996 | L2: 27862.282 | M2: 27955.789 | N2: 28048.705 | O2: 28142.483 | P2: 28236.921 | Q2: 28330.781 | R2: 28422.714 | S2: 28511.965 | T2: 28598.711 | U2: 28683.823 | V2: 28756.345 | W2: 28832.295 | X2: 28912.429 | Y2: 28996.183 | Z2: 29082.545 | AA2: 29137.739 | AB2: 29186.727 | AC2: 29233.73 | AD2: 29281.101 | AE2: 29330.013 | AF2: 29380.78 | AG2: 29433.185 | AH2: 29486.793 | AI2: 29541.172 | AJ2: 29596.025 | AK2: 29651.218 | AL2: 29699.916 | AM2: 29744.128 | AN2: 29785.784 | AO2: 29826.198 | AP2: 29866.044 | AQ2: 29905.557 | AR2: 29944.754 | AS2: 29983.58 | AT2: 30022.016 | AU2: 30060.108 | AV2: 30098.573 | AW2: 30137.478 | AX2: 30176.752 | AY2: 30216.209 | AZ2: 30255.609 | BA2: 31151.286 | BB2: 31189.763 | BC2: 31227.69 | BD2: 31265.09 | BE2: 31301.985
A3: f_l_0 | B3: 27367.649 | C3: 27350.906 | D3: 27328.532 | E3: 27333.982 | F3: 27380.803 | G3: 27465.509 | H3: 27563.91 | I3: 27664.169 | J3: 27759.341 | K3: 27848.523 | L3: 27953.576 | M3: 28056.192 | N3: 28159.145 | O3: 28263.955 | P3: 28370.038 | Q3: 28475.595 | R3: 28578.868 | S3: 28679.008 | T3: 28776.287 | U3: 28871.772 | V3: 28954.594 | W3: 29040.943 | X3: 29131.57 | Y3: 29225.806 | Z3: 29322.505 | AA3: 29387.482 | AB3: 29445.809 | AC3: 29501.765 | AD3: 29557.827 | AE3: 29615.288 | AF3: 29674.536 | AG3: 29735.353 | AH3: 29797.246 | AI3: 29859.733 | AJ3: 29922.503 | AK3: 29985.442 | AL3: 30041.537 | AM3: 30092.587 | AN3: 30140.471 | AO3: 30186.592 | AP3: 30231.797 | AQ3: 30276.472 | AR3: 30320.722 | AS3: 30364.531 | AT3: 30407.887 | AU3: 30450.828 | AV3: 30493.993 | AW3: 30537.314 | AX3: 30580.674 | AY3: 30623.936 | AZ3: 30666.96 | BA3: 31107.65 | BB3: 31143.854 | BC3: 31179.418 | BD3: 31214.358 | BE3: 31248.703
A4: f_l_sagr_2 | B4: 733.92661 | C4: 729.04189 | D4: 720.75609 | E4: 711.86475 | F4: 704.11241 | G4: 698.30696 | H4: 694.2509 | I4: 691.47654 | J4: 689.32345 | K4: 687.12836 | L4: 684.81538 | M4: 681.66679 | N4: 677.45052 | O4: 672.17879 | P4: 666.04404 | Q4: 659.32463 | R4: 652.35201 | S4: 645.34953 | T4: 638.49042 | U4: 631.89269 | V4: 625.34618 | W4: 619.15851 | X4: 613.36687 | Y4: 607.95062 | Z4: 602.84239 | AA4: 597.23379 | AB4: 591.45226 | AC4: 585.59167 | AD4: 579.7465 | AE4: 573.97903 | AF4: 568.31882 | AG4: 562.76034 | AH4: 557.2957 | AI4: 551.9072 | AJ4: 546.57516 | AK4: 541.28382 | AL4: 535.81232 | AM4: 530.2307 | AN4: 524.61727 | AO4: 519.04187 | AP4: 513.55462 | AQ4: 508.17148 | AR4: 502.90665 | AS4: 497.75621 | AT4: 492.70468 | AU4: 487.73183 | AV4: 482.79336 | AW4: 477.89809 | AX4: 473.05038 | AY4: 468.25094 | AZ4: 463.49863 | BA4: 804.6154 | BB4: 805.23381 | BC4: 805.85808 | BD4: 806.48952 | BE4: 807.12938
A5: f_l_sagr_0 | B5: 731.43452 | C5: 724.58881 | D5: 714.97622 | E5: 705.38915 | F5: 697.48013 | G5: 691.92177 | H5: 688.36194 | I5: 686.20021 | J5: 684.65719 | K5: 682.97578 | L5: 681.019 | M5: 678.00847 | N5: 673.75786 | O5: 668.33754 | P5: 661.99636 | Q5: 655.0584 | R5: 647.84447 | S5: 640.62512 | T5: 633.60054 | U5: 626.89844 | V5: 620.30843 | W5: 614.12901 | X5: 608.38016 | Y5: 603.02462 | Z5: 597.98052 | AA5: 592.43326 | AB5: 586.72303 | AC5: 580.92038 | AD5: 575.106 | AE5: 569.33785 | AF5: 563.64844 | AG5: 558.04808 | AH5: 552.53142 | AI5: 547.08486 | AJ5: 541.69334 | AK5: 536.3452 | AL5: 530.89637 | AM5: 525.36633 | AN5: 519.79768 | AO5: 514.24129 | AP5: 508.742 | AQ5: 503.3311 | AR5: 498.02421 | AS5: 492.82308 | AT5: 487.71936 | AU5: 482.69924 | AV5: 477.75764 | AW5: 472.87914 | AX5: 468.05067 | AY5: 463.26286 | AZ5: 458.51053 | BA5: 804.36164 | BB5: 804.98395 | BC5: 805.61211 | BD5: 806.24712 | BE5: 806.89037
