Workbook
Name formatResults: [1]ResultsEXR10!$A$50

Sheet Export
A1: _date_ | B1: 42005 | C1: 42370 | D1: 42736 | E1: 43101 | F1: 43466 | G1: 43831 | H1: 44197 | I1: 44562 | J1: 44927 | K1: 45292 | L1: 45658 | M1: 46023 | N1: 46388 | O1: 46753 | P1: 47119 | Q1: 47484 | R1: 47849 | S1: 48214 | T1: 48580 | U1: 48945 | V1: 49310 | W1: 49675 | X1: 50041 | Y1: 50406 | Z1: 50771 | AA1: 51136 | AB1: 51502 | AC1: 51867 | AD1: 52232 | AE1: 52597 | AF1: 52963 | AG1: 53328 | AH1: 53693 | AI1: 54058 | AJ1: 54424 | AK1: 54789 | AL1: 55154 | AM1: 55519 | AN1: 55885 | AO1: 56250 | AP1: 56615 | AQ1: 56980 | AR1: 57346 | AS1: 57711 | AT1: 58076 | AU1: 58441 | AV1: 58807 | AW1: 59172 | AX1: 59537 | AY1: 59902 | AZ1: 60268 | BA1: 60633 | BB1: 60998 | BC1: 61363 | BD1: 61729 | BE1: 62094
A2: x_2 | B2: 594956.81 | C2: 602646.73 | D2: 611511.06 | E2: 620789.33 | F2: 630339.16 | G2: 640050.09 | H2: 649186.33 | I2: 658341.84 | J2: 667481.26 | K2: 676580.08 | L2: 686684.1 | M2: 695487.73 | N2: 704223.43 | O2: 712900.1 | P2: 721531.21 | Q2: 730134.05 | R2: 738562.1 | S2: 747008.78 | T2: 755498.26 | U2: 764054.59 | V2: 771936.6 | W2: 780708.27 | X2: 789616.47 | Y2: 798677.42 | Z2: 807905.74 | AA2: 815142.41 | AB2: 823812.9 | AC2: 832692.45 | AD2: 841788.88 | AE2: 851107.33 | AF2: 860650.64 | AG2: 870456.83 | AH2: 880487.21 | AI2: 890738.79 | AJ2: 901207.29 | AK2: 911887.54 | AL2: 922588.47 | AM2: 933487.45 | AN2: 944580.32 | AO2: 955862.11 | AP2: 967327.88 | AQ2: 979025.82 | AR2: 990899.73 | AS2: 1002946 | AT2: 1015161.4 | AU2: 1027543.1 | AV2: 1040313.9 | AW2: 1053249.7 | AX2: 1066348 | AY2: 1079606.9 | AZ2: 1093025.3 | BA2: 1106715.1 | BB2: 1120566.8 | BC2: 1134581 | BD2: 1148759 | BE2: 1163102.5
A3: x_0 | B3: 633304.83 | C3: 643304.69 | D3: 654245.97 | E3: 665443.41 | F3: 676840.23 | G3: 688384.13 | H3: 699373.2 | I3: 710430.17 | J3: 721541.69 | K3: 732702.11 | L3: 745064.18 | M3: 756324.52 | N3: 767641.28 | O3: 779029.2 | P3: 790504.74 | Q3: 802085.67 | R3: 813790.63 | S3: 825638.72 | T3: 837648.92 | U3: 849839.59 | V3: 861374.88 | W3: 873980.56 | X3: 886820.02 | Y3: 899904.42 | Z3: 913243.68 | AA3: 924382.53 | AB3: 937093.78 | AC3: 950084.63 | AD3: 963361.56 | AE3: 976928.88 | AF3: 990788.92 | AG3: 1004942.1 | AH3: 1019387.2 | AI3: 1034121.2 | AJ3: 1049140.2 | AK3: 1064439.4 | AL3: 1079413.7 | AM3: 1094651.8 | AN3: 1110152.5 | AO3: 1125913.8 | AP3: 1141933.6 | AQ3: 1158209.5 | AR3: 1174739.1 | AS3: 1191520.1 | AT3: 1208550.2 | AU3: 1225827.1 | AV3: 1243403.8 | AW3: 1261224 | AX3: 1279285.8 | AY3: 1297588.1 | AZ3: 1316129.9 | BA3: 1334911 | BB3: 1353931.8 | BC3: 1373193.1 | BD3: 1392696.5 | BE3: 1412443.6
A4: x_cagr_2 | B4: 14890.888 | C4: 15079.39 | D4: 15299.137 | E4: 15531.921 | F4: 15773.942 | G4: 16021.697 | H4: 16255.888 | I4: 16490.66 | J4: 16724.619 | K4: 16956.83 | L4: 17213.374 | M4: 17436.264 | N4: 17656.33 | O4: 17873.798 | P4: 18089.06 | Q4: 18302.635 | R4: 18510.9 | S4: 18718.822 | T4: 18927.124 | U4: 19136.538 | V4: 19328.599 | W4: 19542.641 | X4: 19759.94 | Y4: 19981.009 | Z4: 20206.293 | AA4: 20381.772 | AB4: 20593.263 | AC4: 20810.244 | AD4: 21032.992 | AE4: 21261.675 | AF4: 21496.375 | AG4: 21738.051 | AH4: 21985.715 | AI4: 22239.271 | AJ4: 22498.58 | AK4: 22763.477 | AL4: 23029.255 | AM4: 23300.288 | AN4: 23576.457 | AO4: 23857.602 | AP4: 24143.555 | AQ4: 24435.488 | AR4: 24731.948 | AS4: 25032.798 | AT4: 25337.917 | AU4: 25647.203 | AV4: 25966.256 | AW4: 26289.452 | AX4: 26616.714 | AY4: 26947.966 | AZ4: 27283.153 | BA4: 27625.09 | BB4: 27971.015 | BC4: 28320.934 | BD4: 28674.86 | BE4: 29032.821
A5: x_cagr_0 | B5: 15858.384 | C5: 16109.495 | D5: 16385.528 | E5: 16669.199 | F5: 16958.621 | G5: 17251.939 | H5: 17531.066 | I5: 17811.277 | J5: 18092.068 | K5: 18373.238 | L5: 18683.757 | M5: 18965.854 | N5: 19248.596 | O5: 19532.42 | P5: 19817.823 | Q5: 20105.343 | R5: 20395.541 | S5: 20688.984 | T5: 20986.236 | U5: 21287.84 | V5: 21572.902 | W5: 21884.764 | X5: 22202.564 | Y5: 22526.648 | Z5: 22857.308 | AA5: 23133.018 | AB5: 23448.298 | AC5: 23770.891 | AD5: 24101.029 | AE5: 24438.856 | AF5: 24784.442 | AG5: 25137.798 | AH5: 25498.878 | AI5: 25867.59 | AJ5: 26243.812 | AK5: 26627.394 | AL5: 27003.139 | AM5: 27385.739 | AN5: 27775.147 | AO5: 28171.305 | AP5: 28574.14 | AQ5: 28983.576 | AR5: 29399.532 | AS5: 29821.926 | AT5: 30250.681 | AU5: 30685.719 | AV5: 31128.345 | AW5: 31577.136 | AX5: 32032.026 | AY5: 32492.964 | AZ5: 32959.913 | BA5: 33432.854 | BB5: 33911.781 | BC5: 34396.706 | BD5: 34887.656 | BE5: 35384.668
A6: x_cfor_2 | B6: 39.330702 | C6: 39.793151 | D6: 40.341458 | E6: 40.932481 | F6: 41.556552 | G6: 42.20284 | H6: 42.818466 | I6: 43.439115 | J6: 44.060067 | K6: 44.678168 | L6: 45.361933 | M6: 45.957977 | N6: 46.546996 | O6: 47.1291 | P6: 47.704904 | Q6: 48.275429 | R6: 48.830743 | S6: 49.383704 | T6: 49.936054 | U6: 50.489595 | V6: 50.995341 | W6: 51.557044 | X6: 52.12534 | Y6: 52.701661 | Z6: 53.287285 | AA6: 53.739383 | AB6: 54.284244 | AC6: 54.841422 | AD6: 55.411799 | AE6: 55.996063 | AF6: 56.594716 | AG6: 57.210577 | AH6: 57.841285 | AI6: 58.486752 | AJ6: 59.146736 | AK6: 59.820883 | AL6: 60.497133 | AM6: 61.187025 | AN6: 61.890206 | AO6: 62.606233 | AP6: 63.334662 | AQ6: 64.07865 | AR6: 64.834422 | AS6: 65.60164 | AT6: 66.379993 | AU6: 67.169197 | AV6: 67.984146 | AW6: 68.810152 | AX6: 69.646988 | AY6: 70.494411 | AZ6: 71.352216 | BA6: 72.22786 | BB6: 73.114098 | BC6: 74.010875 | BD6: 74.918151 | BE6: 75.835928
A7: x_cfor_0 | B7: 41.916677 | C7: 42.587807 | D7: 43.331387 | E7: 44.099879 | F7: 44.885596 | G7: 45.68117 | H7: 46.436894 | I7: 47.192494 | J7: 47.946856 | K7: 48.700229 | L7: 49.530678 | M7: 50.285799 | N7: 51.043044 | O7: 51.803634 | P7: 52.568713 | Q7: 53.339392 | R7: 54.116801 | S7: 54.902119 | T7: 55.696568 | U7: 56.50139 | V7: 57.26078 | W7: 58.089745 | X7: 58.932983 | Y7: 59.79153 | Z7: 60.666316 | AA7: 61.393581 | AB7: 62.224105 | AC7: 63.072315 | AD7: 63.939005 | AE7: 64.824842 | AF7: 65.730335 | AG7: 66.655812 | AH7: 67.601408 | AI7: 68.567077 | AJ7: 69.552628 | AK7: 70.557761 | AL7: 71.542131 | AM7: 72.544584 | AN7: 73.564931 | AO7: 74.602998 | AP7: 75.658637 | AQ7: 76.731722 | AR7: 77.822141 | AS7: 78.929775 | AT7: 80.054496 | AU7: 81.196177 | AV7: 82.358377 | AW7: 83.537433 | AX7: 84.733219 | AY7: 85.945562 | AZ7: 87.174265 | BA7: 88.41916 | BB7: 89.680149 | BC7: 90.957219 | BD7: 92.250436 | BE7: 93.559921
A8: x_cfoo_2 | B8: 42654.999 | C8: 43192.528 | D8: 43819.051 | E8: 44483.698 | F8: 45176.637 | G8: 45888.431 | H8: 46563.885 | I8: 47243.259 | J8: 47922.134 | K8: 48597.355 | L8: 49343.334 | M8: 49993.475 | N8: 50635.777 | O8: 51270.599 | P8: 51898.849 | Q8: 52521.854 | R8: 53129.158 | S8: 53734.967 | T8: 54341.342 | U8: 54950.382 | V8: 55509.019 | W8: 56130.269 | X8: 56760.456 | Y8: 57401.147 | Z8: 58053.711 | AA8: 58562.804 | AB8: 59174.985 | AC8: 59802.639 | AD8: 60446.657 | AE8: 61107.625 | AF8: 61785.878 | AG8: 62484.238 | AH8: 63199.942 | AI8: 63932.765 | AJ8: 64682.36 | AK8: 65448.286 | AL8: 66216.857 | AM8: 67000.574 | AN8: 67799.073 | AO8: 68611.917 | AP8: 69438.646 | AQ8: 70282.638 | AR8: 71139.718 | AS8: 72009.51 | AT8: 72891.676 | AU8: 73785.926 | AV8: 74708.307 | AW8: 75642.61 | AX8: 76588.615 | AY8: 77546.12 | AZ8: 78514.981 | BA8: 79503.253 | BB8: 80502.978 | BC8: 81514.173 | BD8: 82536.885 | BE8: 83571.208
A9: x_cfoo_0 | B9: 45427.619 | C9: 46146.189 | D9: 46935.236 | E9: 47745.879 | F9: 48573.446 | G9: 49413.162 | H9: 50213.395 | I9: 51017.835 | J9: 51824.825 | K9: 52633.517 | L9: 53526.737 | M9: 54338.711 | N9: 55152.48 | O9: 55969.119 | P9: 56789.947 | Q9: 57616.445 | R9: 58450.191 | S9: 59292.816 | T9: 60145.949 | U9: 61011.179 | V9: 61828.582 | W9: 62722.446 | X9: 63633.06 | Y9: 64561.483 | Z9: 65508.617 | AA9: 66297.952 | AB9: 67200.385 | AC9: 68123.52 | AD9: 69068.089 | AE9: 70034.576 | AF9: 71023.252 | AG9: 72034.198 | AH9: 73067.336 | AI9: 74122.45 | AJ9: 75199.216 | AK9: 76297.236 | AL9: 77372.913 | AM9: 78468.312 | AN9: 79583.275 | AO9: 80717.618 | AP9: 81871.133 | AQ9: 83043.596 | AR9: 84234.775 | AS9: 85444.441 | AT9: 86672.368 | AU9: 87918.339 | AV9: 89186.1 | AW9: 90471.576 | AX9: 91774.579 | AY9: 93094.956 | AZ9: 94432.597 | BA9: 95787.437 | BB9: 97159.456 | BC9: 98548.677 | BD9: 99955.164 | BE9: 101379.02
A10: x_cveh_2 | B10: 104832.82 | C10: 106266.98 | D10: 107905.81 | E10: 109590.41 | F10: 111283.03 | G10: 112962.46 | H10: 114505.38 | I10: 116026.49 | J10: 117529.57 | K10: 119019.01 | L10: 120683.84 | M10: 122124.48 | N10: 123562.43 | O10: 125002.26 | P10: 126447.94 | Q10: 127903 | R10: 129341.59 | S10: 130797.04 | T10: 132272.45 | U10: 133770.58 | V10: 135161.2 | W10: 136716.02 | X10: 138300.84 | Y10: 139916.43 | Z10: 141563.62 | AA10: 142866.05 | AB10: 144423.2 | AC10: 146018.61 | AD10: 147651.7 | AE10: 149321.61 | AF10: 151027.44 | AG10: 152774.86 | AH10: 154556.34 | AI10: 156371.01 | AJ10: 158217.98 | AK10: 160096.44 | AL10: 161973.89 | AM10: 163881.75 | AN10: 165819.71 | AO10: 167787.18 | AP10: 169783.53 | AQ10: 171817.47 | AR10: 173879.34 | AS10: 175968.82 | AT10: 178085.7 | AU10: 180229.88 | AV10: 182440.7 | AW10: 184678.83 | AX10: 186944.1 | AY10: 189236.48 | AZ10: 191556.12 | BA10: 193923.03 | BB10: 196318.16 | BC10: 198741.9 | BD10: 201194.7 | BE10: 203677.07
A11: x_cveh_0 | B11: 111565.34 | C11: 113320.18 | D11: 115227.35 | E11: 117163.59 | F11: 119120.43 | G11: 121092.62 | H11: 122962.62 | I11: 124845.38 | J11: 126742.64 | K11: 128656.17 | L11: 130788.16 | M11: 132735.63 | N11: 134703.09 | O11: 136693.68 | P11: 138710.17 | Q11: 140755.13 | R11: 142830.93 | S11: 144939.84 | T11: 147084.03 | U11: 149265.51 | V11: 151337.53 | W11: 153601.62 | X11: 155909.02 | Y11: 158260.13 | Z11: 160655.49 | AA11: 162665.98 | AB11: 164955.11 | AC11: 167294.1 | AD11: 169682.44 | AE11: 172119.3 | AF11: 174603.81 | AG11: 177135.11 | AH11: 179712.33 | AI11: 182334.63 | AJ11: 185001.2 | AK11: 187711.3 | AL11: 190359.37 | AM11: 193050.2 | AN11: 195784.12 | AO11: 198561.02 | AP11: 201380.52 | AQ11: 204242.2 | AR11: 207145.61 | AS11: 210090.4 | AT11: 213076.24 | AU11: 216102.9 | AV11: 219179.79 | AW11: 222297.22 | AX11: 225455.09 | AY11: 228653.47 | AZ11: 231892.53 | BA11: 235172.57 | BB11: 238493.94 | BC11: 241857.1 | BD11: 245262.52 | BE11: 248710.75
A12: x_cgla_2 | B12: 4911.4179 | C12: 4973.7951 | D12: 5046.3349 | E12: 5123.0717 | F12: 5202.8837 | G12: 5284.7535 | H12: 5362.4025 | I12: 5440.5273 | J12: 5518.6532 | K12: 5596.4281 | L12: 5682.4212 | M12: 5757.4369 | N12: 5831.5984 | O12: 5904.9381 | P12: 5977.5526 | Q12: 6049.5889 | R12: 6119.8385 | S12: 6189.9345 | T12: 6260.1094 | U12: 6330.5991 | V12: 6395.2799 | W12: 6467.1666 | X12: 6540.07 | Y12: 6614.1649 | Z12: 6689.6052 | AA12: 6748.4799 | AB12: 6819.2014 | AC12: 6891.6751 | AD12: 6966.0074 | AE12: 7042.2713 | AF12: 7120.5114 | AG12: 7201.0586 | AH12: 7283.5984 | AI12: 7368.1083 | AJ12: 7454.5509 | AK12: 7542.8781 | AL12: 7631.5123 | AM12: 7721.8931 | AN12: 7813.9793 | AO12: 7907.7241 | AP12: 8003.08 | AQ12: 8100.4421 | AR12: 8199.3342 | AS12: 8299.7163 | AT12: 8401.5517 | AU12: 8504.8078 | AV12: 8611.3342 | AW12: 8719.2594 | AX12: 8828.5542 | AY12: 8939.1929 | AZ12: 9051.1571 | BA12: 9165.3746 | BB12: 9280.926 | BC12: 9397.811 | BD12: 9516.0334 | BE12: 9635.6031
... A55: x_cote_0 | B55: 4467.7306 | C55: 4536.5339 | D55: 4611.047 | E55: 4686.784 | F55: 4763.7649 | G55: 4842.0103 | H55: 4916.8504 | I55: 4992.8473 | J55: 5070.0189 | K55: 5148.3832 | L55: 5236.1362 | M55: 5317.0682 | N55: 5399.251 | O55: 5482.7041 | P55: 5567.447 | Q55: 5653.4998 | R55: 5740.8827 | S55: 5829.6162 | T55: 5919.7212 | U55: 6011.2188 | V55: 6098.032 | W55: 6192.2857 | X55: 6287.9963 | Y55: 6385.1862 | Z55: 6483.8783 | AA55: 6566.4246 | AB55: 6659.5192 | AC55: 6753.9337 | AD55: 6849.6867 | AE55: 6946.7972 | AF55: 7045.2846 | AG55: 7145.1682 | AH55: 7246.4679 | AI55: 7349.2037 | AJ55: 7453.3961 | AK55: 7559.0656 | AL55: 7661.9329 | AM55: 7766.2001 | AN55: 7871.8862 | AO55: 7979.0105 | AP55: 8087.5926 | AQ55: 8197.6523 | AR55: 8309.2098 | AS55: 8422.2854 | AT55: 8536.8998 | AU55: 8653.0739 | AV55: 8771.2195 | AW55: 8890.9782 | AX55: 9012.3721 | AY55: 9135.4234 | AZ55: 9260.1548 | BA55: 9386.5892 | BB55: 9514.75 | BC55: 9644.6605 | BD55: 9776.3449 | BE55: 9909.8271

Sheet Import
A1: _date_ | B1: 42005 | C1: 42370 | D1: 42736 | E1: 43101 | F1: 43466 | G1: 43831 | H1: 44197 | I1: 44562 | J1: 44927 | K1: 45292 | L1: 45658 | M1: 46023 | N1: 46388 | O1: 46753 | P1: 47119 | Q1: 47484 | R1: 47849 | S1: 48214 | T1: 48580 | U1: 48945 | V1: 49310 | W1: 49675 | X1: 50041 | Y1: 50406 | Z1: 50771 | AA1: 51136 | AB1: 51502 | AC1: 51867 | AD1: 52232 | AE1: 52597 | AF1: 52963 | AG1: 53328 | AH1: 53693 | AI1: 54058 | AJ1: 54424 | AK1: 54789 | AL1: 55154 | AM1: 55519 | AN1: 55885 | AO1: 56250 | AP1: 56615 | AQ1: 56980 | AR1: 57346 | AS1: 57711 | AT1: 58076 | AU1: 58441 | AV1: 58807 | AW1: 59172 | AX1: 59537 | AY1: 59902 | AZ1: 60268 | BA1: 60633 | BB1: 60998 | BC1: 61363 | BD1: 61729 | BE1: 62094
A2: m_2 | B2: 642620.03 | C2: 645092.66 | D2: 649948.18 | E2: 655825.33 | F2: 662390.66 | G2: 669563.59 | H2: 676901.25 | I2: 684633.64 | J2: 692791.87 | K2: 701366.27 | L2: 711040.7 | M2: 720604.6 | N2: 730376.64 | O2: 740379.68 | P2: 750605.87 | Q2: 761043.36 | R2: 771623.54 | S2: 782378.31 | T2: 793306.27 | U2: 804402.62 | V2: 815142.32 | W2: 826340.26 | X2: 837766.24 | Y2: 849383.41 | Z2: 861177.5 | AA2: 871648.54 | AB2: 882455.8 | AC2: 893331.33 | AD2: 904272.96 | AE2: 915299.74 | AF2: 926430.53 | AG2: 937692.94 | AH2: 949088.26 | AI2: 960622.02 | AJ2: 972298.44 | AK2: 984120.79 | AL2: 995850.25 | AM2: 1007609 | AN2: 1019435 | AO2: 1031352.2 | AP2: 1043380.1 | AQ2: 1055552.9 | AR2: 1067870.7 | AS2: 1080340.9 | AT2: 1092969.6 | AU2: 1105761.1 | AV2: 1118811.8 | AW2: 1132063.1 | AX2: 1145504.8 | AY2: 1159132.4 | AZ2: 1172944.2 | BA2: 1186977.9 | BB2: 1201207.1 | BC2: 1215627.9 | BD2: 1230239.3 | BE2: 1245042
A3: m_0 | B3: 656032.07 | C3: 663598.77 | D3: 672404.68 | E3: 681762.79 | F3: 691480.48 | G3: 701542.06 | H3: 711551.21 | I3: 721782.39 | J3: 732305.06 | K3: 743141.56 | L3: 755043.56 | M3: 766811.84 | N3: 778756.2 | O3: 790903.63 | P3: 803250.77 | Q3: 815789.95 | R3: 828514.53 | S3: 841419.58 | T3: 854501.58 | U3: 867757.99 | V3: 880626.44 | W3: 893988.8 | X3: 907600.87 | Y3: 921428.03 | Z3: 935459.16 | AA3: 948066.4 | AB3: 961029.54 | AC3: 974073.82 | AD3: 987201.4 | AE3: 1000435.2 | AF3: 1013796.9 | AG3: 1027302.9 | AH3: 1040964.6 | AI3: 1054789.7 | AJ3: 1068783.3 | AK3: 1082948.9 | AL3: 1096897.5 | AM3: 1110853.4 | AN3: 1124873 | AO3: 1138989 | AP3: 1153226.3 | AQ3: 1167605.3 | AR3: 1182142.1 | AS3: 1196849.7 | AT3: 1211737.7 | AU3: 1226813.7 | AV3: 1242119 | AW3: 1257638.7 | AX3: 1273372.2 | AY3: 1289321.3 | AZ3: 1305488.4 | BA3: 1321875.9 | BB3: 1338486.6 | BC3: 1355324.1 | BD3: 1372392.2 | BE3: 1389695.1
A4: m_cagr_2 | B4: 12840.617 | C4: 12834.562 | D4: 12857.745 | E4: 12913.147 | F4: 13000.141 | G4: 13116.319 | H4: 13252.19 | I4: 13406.687 | J4: 13577.877 | K4: 13763.767 | L4: 13973.713 | M4: 14191.17 | N4: 14416.312 | O4: 14648.247 | P4: 14886.133 | Q4: 15129.289 | R4: 15376.645 | S4: 15627.923 | T4: 15882.773 | U4: 16140.873 | V4: 16393.579 | W4: 16651.248 | X4: 16912.642 | Y4: 17177.367 | Z4: 17445.149 | AA4: 17691.601 | AB4: 17936.001 | AC4: 18178.269 | AD4: 18419.412 | AE4: 18660.476 | AF4: 18902.341 | AG4: 19145.811 | AH4: 19391.348 | AI4: 19639.302 | AJ4: 19889.93 | AK4: 20143.431 | AL4: 20395.248 | AM4: 20646.684 | AN4: 20898.61 | AO4: 21151.789 | AP4: 21406.926 | AQ4: 21664.815 | AR4: 21925.908 | AS4: 22190.576 | AT4: 22459.088 | AU4: 22731.632 | AV4: 23009.437 | AW4: 23292.233 | AX4: 23579.906 | AY4: 23872.357 | AZ4: 24169.51 | BA4: 24471.681 | BB4: 24778.698 | BC4: 25090.485 | BD4: 25406.992 | BE4: 25728.193
A5: m_cagr_0 | B5: 12985.152 | C5: 13084.944 | D5: 13202.325 | E5: 13342.891 | F5: 13506.662 | G5: 13691.531 | H5: 13888.342 | I5: 14096.709 | J5: 14315.612 | K5: 14544.045 | L5: 14792.842 | M5: 15046.08 | N5: 15304.382 | O5: 15567.221 | P5: 15834.032 | Q5: 16104.377 | R5: 16377.944 | S5: 16654.511 | T5: 16933.915 | U5: 17216.03 | V5: 17491.911 | W5: 17772.734 | X5: 18057.4 | Y5: 18345.708 | Z5: 18637.557 | AA5: 18907.145 | AB5: 19174.819 | AC5: 19440.605 | AD5: 19705.683 | AE5: 19971.251 | AF5: 20238.301 | AG5: 20507.583 | AH5: 20779.642 | AI5: 21054.86 | AJ5: 21333.513 | AK5: 21615.804 | AL5: 21895.676 | AM5: 22174.915 | AN5: 22454.57 | AO5: 22735.563 | AP5: 23018.741 | AQ5: 23304.842 | AR5: 23594.479 | AS5: 23888.136 | AT5: 24186.182 | AU5: 24488.895 | AV5: 24797.06 | AW5: 25110.721 | AX5: 25429.944 | AY5: 25754.705 | AZ5: 26084.969 | BA5: 26420.737 | BB5: 26762.037 | BC5: 27108.914 | BD5: 27461.425 | BE5: 27819.634
A6: m_cfor_2 | B6: 117.112 | C6: 115.20484 | D6: 113.69719 | E6: 112.54321 | F6: 111.71799 | G6: 111.18288 | H6: 110.83224 | I6: 110.65783 | J6: 110.64068 | K6: 110.76468 | L6: 111.10848 | M6: 111.50326 | N6: 111.982 | O6: 112.54441 | P6: 113.18411 | Q6: 113.89346 | R6: 114.65481 | S6: 115.46906 | T6: 116.33243 | U6: 117.24065 | V6: 118.12391 | W6: 119.0829 | X6: 120.08778 | Y6: 121.12948 | Z6: 122.20347 | AA6: 123.11997 | AB6: 124.08853 | AC6: 125.07897 | AD6: 126.08626 | AE6: 127.10929 | AF6: 128.14809 | AG6: 129.20526 | AH6: 130.27957 | AI6: 131.37097 | AJ6: 132.47973 | AK6: 133.60623 | AL6: 134.72695 | AM6: 135.85257 | AN6: 136.987 | AO6: 138.1326 | AP6: 139.2912 | AQ6: 140.46749 | AR6: 141.66046 | AS6: 142.87055 | AT6: 144.0984 | AU6: 145.34463 | AV6: 146.62413 | AW6: 147.92736 | AX6: 149.25201 | AY6: 150.59742 | AZ6: 151.96358 | BA6: 153.35717 | BB6: 154.77367 | BC6: 156.2122 | BD6: 157.67268 | BE6: 159.15533
A7: m_cfor_0 | B7: 118.88216 | C7: 117.4818 | D7: 116.34471 | E7: 115.54394 | F7: 115.06457 | G7: 114.8996 | H7: 114.96629 | I7: 115.25832 | J7: 115.74402 | K7: 116.38956 | L7: 117.26377 | M7: 118.18774 | N7: 119.18297 | O7: 120.24501 | P7: 121.36663 | Q7: 122.54101 | R7: 123.76242 | S7: 125.02614 | T7: 126.32828 | U7: 127.66561 | V7: 128.96375 | W7: 130.33394 | X7: 131.74482 | Y7: 133.18784 | Z7: 134.65911 | AA7: 135.95069 | AB7: 137.28966 | AC7: 138.64609 | AD7: 140.01598 | AE7: 141.39885 | AF7: 142.79509 | AG7: 144.20523 | AH7: 145.62976 | AI7: 147.06919 | AJ7: 148.52399 | AK7: 149.99466 | AL7: 151.43273 | AM7: 152.86712 | AN7: 154.30661 | AO7: 155.75546 | AP7: 157.21635 | AQ7: 158.6912 | AR7: 160.18155 | AS7: 161.68862 | AT7: 163.21325 | AU7: 164.75566 | AV7: 166.31788 | AW7: 167.89698 | AX7: 169.49363 | AY7: 171.11009 | AZ7: 172.74874 | BA7: 174.41107 | BB7: 176.09774 | BC7: 177.80904 | BD7: 179.54517 | BE7: 181.30641
A8: m_cfoo_2 | B8: 38255.786 | C8: 38297.152 | D8: 38418.225 | E8: 38622.572 | F8: 38908.469 | G8: 39270.271 | H8: 39680.18 | I8: 40139.048 | J8: 40642.81 | K8: 41186.93 | L8: 41802.719 | M8: 42435.696 | N8: 43091.206 | O8: 43767.364 | P8: 44462.103 | Q8: 45173.673 | R8: 45898.746 | S8: 46636.902 | T8: 47387.082 | U8: 48148.257 | V8: 48892.974 | W8: 49656.186 | X8: 50431.347 | Y8: 51216.998 | Z8: 52012.172 | AA8: 52739.523 | AB8: 53466.428 | AC8: 54188.128 | AD8: 54907.03 | AE8: 55625.848 | AF8: 56346.902 | AG8: 57072.427 | AH8: 57803.571 | AI8: 58541.288 | AJ8: 59286.301 | AK8: 60039.193 | AL8: 60785.855 | AM8: 61531.321 | AN8: 62278.206 | AO8: 63028.711 | AP8: 63784.854 | AQ8: 64549.017 | AR8: 65322.393 | AS8: 66106.069 | AT8: 66900.852 | AU8: 67707.311 | AV8: 68529.529 | AW8: 69366.221 | AX8: 70217.109 | AY8: 71081.972 | AZ8: 71960.645 | BA8: 72854.301 | BB8: 73762.257 | BC8: 74684.333 | BD8: 75620.419 | BE8: 76570.468
A9: m_cfoo_0 | B9: 38751.185 | C9: 39097.99 | D9: 39493.323 | E9: 39948.706 | F9: 40464.457 | G9: 41035.619 | H9: 41634.966 | I9: 42264.901 | J9: 42923.545 | K9: 43608.761 | L9: 44356.028 | M9: 45112.113 | N9: 45883.256 | O9: 46668.417 | P9: 47466.173 | Q9: 48275.353 | R9: 49095.072 | S9: 49924.654 | T9: 50763.559 | U9: 51611.337 | V9: 52439.357 | W9: 53285.563 | X9: 54143.609 | Y9: 55012.65 | Z9: 55892.274 | AA9: 56700.075 | AB9: 57507.815 | AC9: 58310.866 | AD9: 59112.192 | AE9: 59914.998 | AF9: 60721.968 | AG9: 61535.154 | AH9: 62356.056 | AI9: 63185.756 | AJ9: 64025.047 | AK9: 64874.547 | AL9: 65714.903 | AM9: 66553.485 | AN9: 67393.418 | AO9: 68237.351 | AP9: 69087.691 | AQ9: 69946.546 | AR9: 70815.672 | AS9: 71696.467 | AT9: 72590.011 | AU9: 73497.13 | AV9: 74420.292 | AW9: 75359.467 | AX9: 76314.878 | AY9: 77286.508 | AZ9: 78274.322 | BA9: 79278.373 | BB9: 80298.788 | BC9: 81335.742 | BD9: 82389.437 | BE9: 83460.086
A10: m_cveh_2 | B10: 80281.342 | C10: 81579.014 | D10: 83442.943 | E10: 85220.165 | F10: 86765.23 | G10: 88108.503 | H10: 89252.34 | I10: 90304.48 | J10: 91321.233 | K10: 92332.476 | L10: 93469.145 | M10: 94533.698 | N10: 95584.626 | O10: 96634.362 | P10: 97686.829 | Q10: 98743.437 | R10: 99795.353 | S10: 100849.44 | T10: 101907.41 | U10: 102970.06 | V10: 103953.41 | W10: 104998.18 | X10: 106067 | Y10: 107151.34 | Z10: 108248.08 | AA10: 109116.27 | AB10: 110043.79 | AC10: 110993.69 | AD10: 111962.86 | AE10: 112951.61 | AF10: 113960.23 | AG10: 114990.56 | AH10: 116040.48 | AI10: 117108.83 | AJ10: 118194.7 | AK10: 119297.37 | AL10: 120378.99 | AM10: 121462.68 | AN10: 122556.44 | AO10: 123664.15 | AP10: 124787.95 | AQ10: 125931.87 | AR10: 127094.27 | AS10: 128274.48 | AT10: 129471.83 | AU10: 130685.64 | AV10: 131929.94 | AW10: 133194.17 | AX10: 134475.22 | AY10: 135771.57 | AZ10: 137082.52 | BA10: 138413.88 | BB10: 139761.28 | BC10: 141123.66 | BD10: 142500.6 | BE10: 143892.04
A11: m_cveh_0 | B11: 82103.234 | C11: 84149.12 | D11: 86629.265 | E11: 88919.606 | F11: 90873.939 | G11: 92537.095 | H11: 93933.871 | I11: 95194.732 | J11: 96394.664 | K11: 97577.066 | L11: 98887.549 | M11: 100133.5 | N11: 101372.05 | O11: 102615.54 | P11: 103867.72 | Q11: 105129.87 | R11: 106402.51 | S11: 107685.94 | T11: 108980.43 | U11: 110286.29 | V11: 111513.89 | W11: 112812.65 | X11: 114142.72 | Y11: 115495.17 | Z11: 116866.61 | AA11: 117998.18 | AB11: 119193.77 | AC11: 120415.73 | AD11: 121661.41 | AE11: 122931.33 | AF11: 124225.71 | AG11: 125544.13 | AH11: 126885.75 | AI11: 128249.58 | AJ11: 129634.7 | AK11: 131040.36 | AL11: 132405.41 | AM11: 133769.12 | AN11: 135143.47 | AO11: 136534.18 | AP11: 137944.31 | AQ11: 139375.47 | AR11: 140828.3 | AS11: 142302.85 | AT11: 143798.86 | AU11: 145315.89 | AV11: 146858.86 | AW11: 148423.91 | AX11: 150009.7 | AY11: 151615.53 | AZ11: 153241.01 | BA11: 154885.94 | BB11: 156550.34 | BC11: 158234.29 | BD11: 159937.98 | BE11: 161661.61
A12: m_cgla_2 | B12: 6877.6774 | C12: 6910.4362 | D12: 6961.8034 | E12: 7024.4208 | F12: 7095.959 | G12: 7175.2214 | H12: 7257.8811 | I12: 7344.9781 | J12: 7436.6546 | K12: 7532.8694 | L12: 7639.5515 | M12: 7747.5243 | N12: 7858.5468 | O12: 7972.853 | P12: 8090.4391 | Q12: 8211.2518 | R12: 8334.7713 | S12: 8461.2087 | T12: 8590.556 | U12: 8722.7672 | V12: 8853.3342 | W12: 8988.4625 | X12: 9126.8856 | Y12: 9268.2871 | Z12: 9412.5055 | AA12: 9546.6014 | AB12: 9682.6066 | AC12: 9819.3176 | AD12: 9956.7647 | AE12: 10095.12 | AF12: 10234.549 | AG12: 10375.286 | AH12: 10517.36 | AI12: 10660.814 | AJ12: 10805.672 | AK12: 10951.948 | AL12: 11097.481 | AM12: 11242.953 | AN12: 11388.667 | AO12: 11534.833 | AP12: 11681.629 | AQ12: 11829.361 | AR12: 11978.082 | AS12: 12127.885 | AT12: 12278.852 | AU12: 12431.045 | AV12: 12585.292 | AW12: 12741.246 | AX12: 12898.836 | AY12: 13058.038 | AZ12: 13218.845 | BA12: 13381.581 | BB12: 13546.092 | BC12: 13712.365 | BD12: 13880.414 | BE12: 14050.267
... A55: m_cote_0 | B55: 2286.3479 | C55: 2314.2348 | D55: 2344.0602 | E55: 2375.7199 | F55: 2409.2906 | G55: 2444.5815 | H55: 2479.5575 | I55: 2515.3804 | J55: 2552.0225 | K55: 2589.3822 | L55: 2630.501 | M55: 2669.7107 | N55: 2709.1398 | O55: 2748.9656 | P55: 2789.2215 | Q55: 2829.9247 | R55: 2871.0971 | S55: 2912.7666 | T55: 2954.9654 | U55: 2997.7277 | V55: 3038.766 | W55: 3082.2764 | X55: 3126.6792 | Y55: 3171.8577 | Z55: 3217.8086 | AA55: 3257.8353 | AB55: 3300.793 | AC55: 3344.5152 | AD55: 3388.8935 | AE55: 3433.9555 | AF55: 3479.7428 | AG55: 3526.2895 | AH55: 3573.6187 | AI55: 3621.7435 | AJ55: 3670.6689 | AK55: 3720.3946 | AL55: 3769.2883 | AM55: 3818.6164 | AN55: 3868.5277 | AO55: 3919.0715 | AP55: 3970.2781 | AQ55: 4022.1717 | AR55: 4074.7726 | AS55: 4128.0971 | AT55: 4182.1579 | AU55: 4236.9648 | AV55: 4292.6731 | AW55: 4349.1509 | AX55: 4406.3802 | AY55: 4464.3686 | AZ55: 4523.1277 | BA55: 4582.6655 | BB55: 4642.9876 | BC55: 4704.0995 | BD55: 4766.0076 | BE55: 4828.7205

Sheet Carbontax
A1: _date_ | B1: 42005 | C1: 42370 | D1: 42736 | E1: 43101 | F1: 43466 | G1: 43831 | H1: 44197 | I1: 44562 | J1: 44927 | K1: 45292 | L1: 45658 | M1: 46023 | N1: 46388 | O1: 46753 | P1: 47119 | Q1: 47484 | R1: 47849 | S1: 48214 | T1: 48580 | U1: 48945 | V1: 49310 | W1: 49675 | X1: 50041 | Y1: 50406 | Z1: 50771 | AA1: 51136 | AB1: 51502 | AC1: 51867 | AD1: 52232 | AE1: 52597 | AF1: 52963 | AG1: 53328 | AH1: 53693 | AI1: 54058 | AJ1: 54424 | AK1: 54789 | AL1: 55154 | AM1: 55519 | AN1: 55885 | AO1: 56250 | AP1: 56615 | AQ1: 56980 | AR1: 57346 | AS1: 57711 | AT1: 58076 | AU1: 58441 | AV1: 58807 | AW1: 59172 | AX1: 59537 | AY1: 59902 | AZ1: 60268 | BA1: 60633 | BB1: 60998 | BC1: 61363 | BD1: 61729 | BE1: 62094
A2: t2val_ch_0 | B2: 0 | C2: 0 | D2: 0 | E2: 0 | F2: 0 | G2: 0 | H2: 0 | I2: 0 | J2: 0 | K2: 0 | L2: 0 | M2: 0 | N2: 0 | O2: 0 | P2: 0 | Q2: 0 | R2: 0 | S2: 0 | T2: 0 | U2: 0 | V2: 0 | W2: 0 | X2: 0 | Y2: 0 | Z2: 0 | AA2: 0 | AB2: 0 | AC2: 0 | AD2: 0 | AE2: 0 | AF2: 0 | AG2: 0 | AH2: 0 | AI2: 0 | AJ2: 0 | AK2: 0 | AL2: 0 | AM2: 0 | AN2: 0 | AO2: 0 | AP2: 0 | AQ2: 0 | AR2: 0 | AS2: 0 | AT2: 0 | AU2: 0 | AV2: 0 | AW2: 0 | AX2: 0 | AY2: 0 | AZ2: 0 | BA2: 0 | BB2: 0 | BC2: 0 | BD2: 0 | BE2: 0
A3: t2val_ch_2 | B3: 0 | C3: 0 | D3: 0 | E3: 0 | F3: 0 | G3: 0 | H3: 0 | I3: 0 | J3: 0 | K3: 0 | L3: 0 | M3: 0 | N3: 0 | O3: 0 | P3: 0 | Q3: 0 | R3: 0 | S3: 0 | T3: 0 | U3: 0 | V3: 0 | W3: 0 | X3: 0 | Y3: 0 | Z3: 0 | AA3: 0 | AB3: 0 | AC3: 0 | AD3: 0 | AE3: 0 | AF3: 0 | AG3: 0 | AH3: 0 | AI3: 0 | AJ3: 0 | AK3: 0 | AL3: 0 | AM3: 0 | AN3: 0 | AO3: 0 | AP3: 0 | AQ3: 0 | AR3: 0 | AS3: 0 | AT3: 0 | AU3: 0 | AV3: 0 | AW3: 0 | AX3: 0 | AY3: 0 | AZ3: 0 | BA3: 0 | BB3: 0 | BC3: 0 | BD3: 0 | BE3: 0
A4: t2val_sec_0 | B4: 0 | C4: 0 | D4: 0 | E4: 0 | F4: 0 | G4: 0 | H4: 0 | I4: 0 | J4: 0 | K4: 0 | L4: 0 | M4: 0 | N4: 0 | O4: 0 | P4: 0 | Q4: 0 | R4: 0 | S4: 0 | T4: 0 | U4: 0 | V4: 0 | W4: 0 | X4: 0 | Y4: 0 | Z4: 0 | AA4: 0 | AB4: 0 | AC4: 0 | AD4: 0 | AE4: 0 | AF4: 0 | AG4: 0 | AH4: 0 | AI4: 0 | AJ4: 0 | AK4: 0 | AL4: 0 | AM4: 0 | AN4: 0 | AO4: 0 | AP4: 0 | AQ4: 0 | AR4: 0 | AS4: 0 | AT4: 0 | AU4: 0 | AV4: 0 | AW4: 0 | AX4: 0 | AY4: 0 | AZ4: 0 | BA4: 0 | BB4: 0 | BC4: 0 | BD4: 0 | BE4: 0
A5: t2val_sec_2 | B5: 0 | C5: 0 | D5: 0 | E5: 0 | F5: 0 | G5: 0 | H5: 0 | I5: 0 | J5: 0 | K5: 0 | L5: 0 | M5: 0 | N5: 0 | O5: 0 | P5: 0 | Q5: 0 | R5: 0 | S5: 0 | T5: 0 | U5: 0 | V5: 0 | W5: 0 | X5: 0 | Y5: 0 | Z5: 0 | AA5: 0 | AB5: 0 | AC5: 0 | AD5: 0 | AE5: 0 | AF5: 0 | AG5: 0 | AH5: 0 | AI5: 0 | AJ5: 0 | AK5: 0 | AL5: 0 | AM5: 0 | AN5: 0 | AO5: 0 | AP5: 0 | AQ5: 0 | AR5: 0 | AS5: 0 | AT5: 0 | AU5: 0 | AV5: 0 | AW5: 0 | AX5: 0 | AY5: 0 | AZ5: 0 | BA5: 0 | BB5: 0 | BC5: 0 | BD5: 0 | BE5: 0
A6: t2val_ci_0 | B6: 0 | C6: 0 | D6: 0 | E6: 0 | F6: 0 | G6: 0 | H6: 0 | I6: 0 | J6: 0 | K6: 0 | L6: 0 | M6: 0 | N6: 0 | O6: 0 | P6: 0 | Q6: 0 | R6: 0 | S6: 0 | T6: 0 | U6: 0 | V6: 0 | W6: 0 | X6: 0 | Y6: 0 | Z6: 0 | AA6: 0 | AB6: 0 | AC6: 0 | AD6: 0 | AE6: 0 | AF6: 0 | AG6: 0 | AH6: 0 | AI6: 0 | AJ6: 0 | AK6: 0 | AL6: 0 | AM6: 0 | AN6: 0 | AO6: 0 | AP6: 0 | AQ6: 0 | AR6: 0 | AS6: 0 | AT6: 0 | AU6: 0 | AV6: 0 | AW6: 0 | AX6: 0 | AY6: 0 | AZ6: 0 | BA6: 0 | BB6: 0 | BC6: 0 | BD6: 0 | BE6: 0
A7: t2val_ci_2 | B7: 0 | C7: 0 | D7: 0 | E7: 0 | F7: 0 | G7: 0 | H7: 0 | I7: 0 | J7: 0 | K7: 0 | L7: 0 | M7: 0 | N7: 0 | O7: 0 | P7: 0 | Q7: 0 | R7: 0 | S7: 0 | T7: 0 | U7: 0 | V7: 0 | W7: 0 | X7: 0 | Y7: 0 | Z7: 0 | AA7: 0 | AB7: 0 | AC7: 0 | AD7: 0 | AE7: 0 | AF7: 0 | AG7: 0 | AH7: 0 | AI7: 0 | AJ7: 0 | AK7: 0 | AL7: 0 | AM7: 0 | AN7: 0 | AO7: 0 | AP7: 0 | AQ7: 0 | AR7: 0 | AS7: 0 | AT7: 0 | AU7: 0 | AV7: 0 | AW7: 0 | AX7: 0 | AY7: 0 | AZ7: 0 | BA7: 0 | BB7: 0 | BC7: 0 | BD7: 0 | BE7: 0
A8: t2val_y_0 | B8: 0 | C8: 0 | D8: 0 | E8: 0 | F8: 0 | G8: 0 | H8: 0 | I8: 0 | J8: 0 | K8: 0 | L8: 0 | M8: 0 | N8: 0 | O8: 0 | P8: 0 | Q8: 0 | R8: 0 | S8: 0 | T8: 0 | U8: 0 | V8: 0 | W8: 0 | X8: 0 | Y8: 0 | Z8: 0 | AA8: 0 | AB8: 0 | AC8: 0 | AD8: 0 | AE8: 0 | AF8: 0 | AG8: 0 | AH8: 0 | AI8: 0 | AJ8: 0 | AK8: 0 | AL8: 0 | AM8: 0 | AN8: 0 | AO8: 0 | AP8: 0 | AQ8: 0 | AR8: 0 | AS8: 0 | AT8: 0 | AU8: 0 | AV8: 0 | AW8: 0 | AX8: 0 | AY8: 0 | AZ8: 0 | BA8: 0 | BB8: 0 | BC8: 0 | BD8: 0 | BE8: 0
A9: t2val_y_2 | B9: 0 | C9: 0 | D9: 0 | E9: 0 | F9: 0 | G9: 0 | H9: 0 | I9: 0 | J9: 0 | K9: 0 | L9: 0 | M9: 0 | N9: 0 | O9: 0 | P9: 0 | Q9: 0 | R9: 0 | S9: 0 | T9: 0 | U9: 0 | V9: 0 | W9: 0 | X9: 0 | Y9: 0 | Z9: 0 | AA9: 0 | AB9: 0 | AC9: 0 | AD9: 0 | AE9: 0 | AF9: 0 | AG9: 0 | AH9: 0 | AI9: 0 | AJ9: 0 | AK9: 0 | AL9: 0 | AM9: 0 | AN9: 0 | AO9: 0 | AP9: 0 | AQ9: 0 | AR9: 0 | AS9: 0 | AT9: 0 | AU9: 0 | AV9: 0 | AW9: 0 | AX9: 0 | AY9: 0 | AZ9: 0 | BA9: 0 | BB9: 0 | BC9: 0 | BD9: 0 | BE9: 0
A10: t2val_mat_0 | B10: 0 | C10: 0 | D10: 0 | E10: 0 | F10: 0 | G10: 0 | H10: 0 | I10: 0 | J10: 0 | K10: 0 | L10: 0 | M10: 0 | N10: 0 | O10: 0 | P10: 0 | Q10: 0 | R10: 0 | S10: 0 | T10: 0 | U10: 0 | V10: 0 | W10: 0 | X10: 0 | Y10: 0 | Z10: 0 | AA10: 0 | AB10: 0 | AC10: 0 | AD10: 0 | AE10: 0 | AF10: 0 | AG10: 0 | AH10: 0 | AI10: 0 | AJ10: 0 | AK10: 0 | AL10: 0 | AM10: 0 | AN10: 0 | AO10: 0 | AP10: 0 | AQ10: 0 | AR10: 0 | AS10: 0 | AT10: 0 | AU10: 0 | AV10: 0 | AW10: 0 | AX10: 0 | AY10: 0 | AZ10: 0 | BA10: 0 | BB10: 0 | BC10: 0 | BD10: 0 | BE10: 0
A11: t2val_mat_2 | B11: 0 | C11: 0 | D11: 0 | E11: 0 | F11: 0 | G11: 0 | H11: 0 | I11: 0 | J11: 0 | K11: 0 | L11: 0 | M11: 0 | N11: 0 | O11: 0 | P11: 0 | Q11: 0 | R11: 0 | S11: 0 | T11: 0 | U11: 0 | V11: 0 | W11: 0 | X11: 0 | Y11: 0 | Z11: 0 | AA11: 0 | AB11: 0 | AC11: 0 | AD11: 0 | AE11: 0 | AF11: 0 | AG11: 0 | AH11: 0 | AI11: 0 | AJ11: 0 | AK11: 0 | AL11: 0 | AM11: 0 | AN11: 0 | AO11: 0 | AP11: 0 | AQ11: 0 | AR11: 0 | AS11: 0 | AT11: 0 | AU11: 0 | AV11: 0 | AW11: 0 | AX11: 0 | AY11: 0 | AZ11: 0 | BA11: 0 | BB11: 0 | BC11: 0 | BD11: 0 | BE11: 0

Sheet Production
A1: _date_ | B1: 42005 | C1: 42370 | D1: 42736 | E1: 43101 | F1: 43466 | G1: 43831 | H1: 44197 | I1: 44562 | J1: 44927 | K1: 45292 | L1: 45658 | M1: 46023 | N1: 46388 | O1: 46753 | P1: 47119 | Q1: 47484 | R1: 47849 | S1: 48214 | T1: 48580 | U1: 48945 | V1: 49310 | W1: 49675 | X1: 50041 | Y1: 50406 | Z1: 50771 | AA1: 51136 | AB1: 51502 | AC1: 51867 | AD1: 52232 | AE1: 52597 | AF1: 52963 | AG1: 53328 | AH1: 53693 | AI1: 54058 | AJ1: 54424 | AK1: 54789 | AL1: 55154 | AM1: 55519 | AN1: 55885 | AO1: 56250 | AP1: 56615 | AQ1: 56980 | AR1: 57346 | AS1: 57711 | AT1: 58076 | AU1: 58441 | AV1: 58807 | AW1: 59172 | AX1: 59537 | AY1: 59902 | AZ1: 60268 | BA1: 60633 | BB1: 60998 | BC1: 61363 | BD1: 61729 | BE1: 62094
A2: y_2 | B2: 3788485.2 | C2: 3815695.8 | D2: 3853138.6 | E2: 3896956.9 | F2: 3945914 | G2: 3999170.7 | H2: 4053454 | I2: 4109945.4 | J2: 4168430.4 | K2: 4228648.4 | L2: 4294778.9 | M2: 4358947.2 | N2: 4423709.9 | O2: 4489126.4 | P2: 4555185.8 | Q2: 4621888.1 | R2: 4688949.4 | S2: 4756643.5 | T2: 4825045.3 | U2: 4894220 | V2: 4960970.7 | W2: 5030767.2 | X2: 5101831.4 | Y2: 5174095.3 | Z2: 5247556.3 | AA2: 5312862 | AB2: 5381237.8 | AC2: 5450229.1 | AD2: 5519932.3 | AE2: 5590495.8 | AF2: 5662048.2 | AG2: 5734752.5 | AH2: 5808617.4 | AI2: 5883669.1 | AJ2: 5959916.7 | AK2: 6037357.6 | AL2: 6114349.7 | AM2: 6191878.8 | AN2: 6270091.2 | AO2: 6349082.6 | AP2: 6428932.5 | AQ2: 6509807.3 | AR2: 6591690.2 | AS2: 6674612.5 | AT2: 6758595.9 | AU2: 6843654 | AV2: 6930332.3 | AW2: 7018262.4 | AX2: 7107394.1 | AY2: 7197696.7 | AZ2: 7289151 | BA2: 7381959.5 | BB2: 7475969.8 | BC2: 7571165.5 | BD2: 7667542.7 | BE2: 7765106.1
A3: y_0 | B3: 3859362.9 | C3: 3908270.1 | D3: 3962069.2 | E3: 4019511.4 | F3: 4080255.5 | G3: 4143927.4 | H3: 4207559.5 | I3: 4272581.3 | J3: 4339001.5 | K3: 4406764.2 | L3: 4480406 | M3: 4552217.8 | N3: 4624727.4 | O3: 4698046.1 | P3: 4772200.3 | Q3: 4847214.2 | R3: 4923123.2 | S3: 4999973.1 | T3: 5077815 | U3: 5156701.1 | V3: 5233255.8 | W3: 5313205.6 | X3: 5394678.6 | Y3: 5477598.7 | Z3: 5561956.7 | AA3: 5637837.7 | AB3: 5716951.4 | AC3: 5796788.9 | AD3: 5877455.6 | AE3: 5959108.5 | AF3: 6041880.6 | AG3: 6125866.5 | AH3: 6211124.7 | AI3: 6297684.6 | AJ3: 6385555.4 | AK3: 6474733.5 | AL3: 6562799.7 | AM3: 6651295.6 | AN3: 6740437.6 | AO3: 6830366.7 | AP3: 6921197.2 | AQ3: 7013024.6 | AR3: 7105925.5 | AS3: 7199958.9 | AT3: 7295168.3 | AU3: 7391584.9 | AV3: 7489450.5 | AW3: 7588641.1 | AX3: 7689151.8 | AY3: 7790980.6 | AZ3: 7894128.4 | BA3: 7998601.1 | BB3: 8104409.9 | BC3: 8211571.1 | BD3: 8320104.9 | BE3: 8430035.3
A4: y_sagr_2 | B4: 79996.655 | C4: 80124.427 | D4: 80517.639 | E4: 81126.647 | F4: 81924.542 | G4: 82882.37 | H4: 83921.765 | I4: 85046.843 | J4: 86242.622 | K4: 87495.238 | L4: 88878.317 | M4: 90241.99 | N4: 91621.255 | O4: 93013.834 | P4: 94417.19 | Q4: 95829.873 | R4: 97243.578 | S4: 98664.678 | T4: 100094.44 | U4: 101534.15 | V4: 102922.45 | W4: 104357.62 | X4: 105814.55 | Y4: 107292.37 | Z4: 108791.31 | AA4: 110132.07 | AB4: 111509.95 | AC4: 112893.08 | AD4: 114285.99 | AE4: 115693.85 | AF4: 117120.93 | AG4: 118572.06 | AH4: 120047.94 | AI4: 121549.59 | AJ4: 123077.47 | AK4: 124631.68 | AL4: 126185.07 | AM4: 127748.29 | AN4: 129325.14 | AO4: 130918.51 | AP4: 132530.85 | AQ4: 134166.77 | AR4: 135826.04 | AS4: 137509.63 | AT4: 139218.15 | AU4: 140951.91 | AV4: 142723.53 | AW4: 144524.68 | AX4: 146354.11 | AY4: 148210.88 | AZ4: 150094.26 | BA4: 152009.2 | BB4: 153951.45 | BC4: 155920.41 | BD4: 157915.75 | BE4: 159937.31
A5: y_sagr_0 | B5: 81862.318 | C5: 82566.293 | D5: 83408.247 | E5: 84394.136 | F5: 85513.737 | G5: 86747.141 | H5: 88023.012 | I5: 89352.746 | J5: 90728.792 | K5: 92144.441 | L5: 93684.438 | M5: 95204.282 | N5: 96739.494 | O5: 98290.116 | P5: 99855.244 | Q5: 101434.54 | R5: 103028.35 | S5: 104637.47 | T5: 106263.03 | U5: 107906.26 | V5: 109501.37 | W5: 111153.59 | X5: 112835.39 | Y5: 114545.86 | Z5: 116285.19 | AA5: 117859.65 | AB5: 119477.61 | AC5: 121105.55 | AD5: 122748.32 | AE5: 124411.41 | AF5: 126099.31 | AG5: 127815.22 | AH5: 129561.19 | AI5: 131338.38 | AJ5: 133147.32 | AK5: 134988.12 | AL5: 136813.62 | AM5: 138648.99 | AN5: 140499.52 | AO5: 142369.18 | AP5: 144261.38 | AQ5: 146178.98 | AR5: 148124.3 | AS5: 150099.04 | AT5: 152104.4 | AU5: 154141.17 | AV5: 156214.19 | AW5: 158321.61 | AX5: 160463.21 | AY5: 162638.5 | AZ5: 164847.02 | BA5: 167088.5 | BB5: 169362.87 | BC5: 171670.18 | BD5: 174010.61 | BE5: 176384.41
A6: y_sfor_2 | B6: 6481.5653 | C6: 6456.0119 | D6: 6417.3768 | E6: 6379.6502 | F6: 6347.9714 | G6: 6322.6176 | H6: 6298.5844 | I6: 6275.9983 | J6: 6254.7581 | K6: 6235.0897 | L6: 6221.796 | M6: 6206.9598 | N6: 6193.1236 | O6: 6180.7461 | P6: 6169.8888 | Q6: 6160.4638 | R6: 6151.7212 | S6: 6143.9939 | T6: 6137.3191 | U6: 6131.6833 | V6: 6123.9797 | W6: 6119.3227 | X6: 6116.2496 | Y6: 6114.4263 | Z6: 6113.7228 | AA6: 6105.5578 | AB6: 6100.3561 | AC6: 6096.5044 | AD6: 6093.7812 | AE6: 6092.1087 | AF6: 6091.4658 | AG6: 6091.9895 | AH6: 6093.5815 | AI6: 6096.2098 | AJ6: 6099.8531 | AK6: 6104.4915 | AL6: 6109.42 | AM6: 6115.0059 | AN6: 6121.3198 | AO6: 6128.3824 | AP6: 6136.1991 | AQ6: 6144.9593 | AR6: 6154.5253 | AS6: 6164.8517 | AT6: 6175.9133 | AU6: 6187.6931 | AV6: 6200.9696 | AW6: 6215.1838 | AX6: 6230.1716 | AY6: 6245.8586 | AZ6: 6262.2111 | BA6: 6279.5998 | BB6: 6297.7486 | BC6: 6316.5792 | BD6: 6336.0597 | BE6: 6356.1791
A7: y_sfor_0 | B7: 6537.0436 | C7: 6520.5895 | D7: 6493.4032 | E7: 6466.5479 | F7: 6443.1968 | G7: 6427.5788 | H7: 6417.7671 | I7: 6414.4663 | J7: 6416.5245 | K7: 6422.5833 | L7: 6436.2886 | M7: 6449.061 | N7: 6462.5599 | O7: 6476.9383 | P7: 6492.1744 | Q7: 6508.2038 | R7: 6524.9661 | S7: 6542.4182 | T7: 6560.5348 | U7: 6579.3056 | V7: 6595.4416 | W7: 6614.4166 | X7: 6634.681 | Y7: 6655.905 | Z7: 6677.957 | AA7: 6691.564 | AB7: 6707.7075 | AC7: 6724.8185 | AD7: 6742.7439 | AE7: 6761.4379 | AF7: 6780.8924 | AG7: 6801.1092 | AH7: 6822.0895 | AI7: 6843.8305 | AJ7: 6866.3256 | AK7: 6889.5658 | AL7: 6911.4455 | AM7: 6933.3503 | AN7: 6955.645 | AO7: 6978.4909 | AP7: 7001.9661 | AQ7: 7026.1137 | AR7: 7050.9596 | AS7: 7076.5145 | AT7: 7102.7651 | AU7: 7129.6328 | AV7: 7156.9146 | AW7: 7184.3946 | AX7: 7212.1427 | AY7: 7240.3719 | AZ7: 7269.2772 | BA7: 7298.9347 | BB7: 7329.3326 | BC7: 7360.4266 | BD7: 7392.1751 | BE7: 7424.5521
A8: y_sfoo_2 | B8: 154885.44 | C8: 155474.78 | D8: 156465.47 | E8: 157825.1 | F8: 159521.17 | G8: 161509 | H8: 163647.4 | I8: 165945.05 | J8: 168376.19 | K8: 170916.5 | L8: 173707.65 | M8: 176473.74 | N8: 179273.19 | O8: 182100.33 | P8: 184950.03 | Q8: 187819.39 | R8: 190695.18 | S8: 193586.64 | T8: 196495.6 | U8: 199424.16 | V8: 202254.43 | W8: 205169.64 | X8: 208125.9 | Y8: 211122.14 | Z8: 214158.71 | AA8: 216891.09 | AB8: 219679.83 | AC8: 222471.35 | AD8: 225276.58 | AE8: 228106.81 | AF8: 230971.2 | AG8: 233879.2 | AH8: 236833.31 | AI8: 239836.04 | AJ8: 242888.69 | AK8: 245991.79 | AL8: 249087.76 | AM8: 252199.62 | AN8: 255335.46 | AO8: 258501.57 | AP8: 261703.45 | AQ8: 264949.81 | AR8: 268241.64 | AS8: 271581.36 | AT8: 274970.5 | AU8: 278409.91 | AV8: 281921.02 | AW8: 285490.96 | AX8: 289117.68 | AY8: 292799.46 | AZ8: 296534.9 | BA8: 300331.61 | BB8: 304183.14 | BC8: 308088.47 | BD8: 312046.96 | BE8: 316058.33
A9: y_sfoo_0 | B9: 157864.05 | C9: 159519.2 | D9: 161394.62 | E9: 163504.99 | F9: 165840.05 | G9: 168370.12 | H9: 170966.92 | I9: 173653.3 | J9: 176418.44 | K9: 179252.51 | L9: 182317.94 | M9: 185349.58 | N9: 188408.77 | O9: 191494.79 | P9: 194605.96 | Q9: 197741.83 | R9: 200903.23 | S9: 204091.86 | T9: 207309.9 | U9: 210559.72 | V9: 213716.66 | W9: 216974.95 | X9: 220287.46 | Y9: 223653.41 | Z9: 227073.33 | AA9: 230179.86 | AB9: 233353.09 | AC9: 236537.02 | AD9: 239743.34 | AE9: 242984.07 | AF9: 246268.87 | AG9: 249604.66 | AH9: 252995.94 | AI9: 256445.42 | AJ9: 259954.46 | AK9: 263523.6 | AL9: 267063.73 | AM9: 270619.23 | AN9: 274200.28 | AO9: 277815.17 | AP9: 281471.26 | AQ9: 285174.82 | AR9: 288930.87 | AS9: 292743.22 | AT9: 296614.56 | AU9: 300546.74 | AV9: 304549.22 | AW9: 308619.06 | AX9: 312756.05 | AY9: 316959.22 | AZ9: 321227.69 | BA9: 325560.97 | BB9: 329958.95 | BC9: 334421.79 | BD9: 338949.87 | BE9: 343543.71
A10: y_sveh_2 | B10: 119862.62 | C10: 121740.18 | D10: 124058.97 | E10: 126378.07 | F10: 128586.26 | G10: 130671.48 | H10: 132534.8 | I10: 134316.22 | J10: 136047.43 | K10: 137748.64 | L10: 139630.49 | M10: 141291.14 | N10: 142933.14 | O10: 144568.57 | P10: 146204.32 | Q10: 147845.36 | R10: 149468.81 | S10: 151105.15 | T10: 152758.7 | U10: 154432.85 | V10: 155988.13 | W10: 157702.69 | X10: 159454.71 | Y10: 161240.57 | Z10: 163059.44 | AA10: 164507.16 | AB10: 166186.35 | AC10: 167911.53 | AD10: 169679.95 | AE10: 171490.43 | AF10: 173341.85 | AG10: 175239.01 | AH10: 177174.63 | AI10: 179147.06 | AJ10: 181154.81 | AK10: 183196.58 | AL10: 185229.36 | AM10: 187288.49 | AN10: 189377.34 | AO10: 191496.98 | AP10: 193647.68 | AQ10: 195837.89 | AR10: 198059.17 | AS10: 200310.82 | AT10: 202592.27 | AU10: 204903.09 | AV10: 207280.55 | AW10: 209688.95 | AX10: 212126.49 | AY10: 214592.38 | AZ10: 217086.4 | BA10: 219626.99 | BB10: 222197.32 | BC10: 224797.2 | BD10: 227426.86 | BE10: 230086.74
A11: y_sveh_0 | B11: 125926.72 | C11: 128329.38 | D11: 131029.29 | E11: 133658.57 | F11: 136145.42 | G11: 138504.73 | H11: 140655.03 | I11: 142745.69 | J11: 144813.21 | K11: 146879.68 | L11: 149169.66 | M11: 151281.4 | N11: 153401.56 | O11: 155539.92 | P11: 157701.52 | Q11: 159889.83 | R11: 162107.69 | S11: 164357.63 | T11: 166641.98 | U11: 168962.89 | V11: 171165.93 | W11: 173554.74 | X11: 175995.34 | Y11: 178483.49 | Z11: 181017.9 | AA11: 183147.25 | AB11: 185528.4 | AC11: 187966.57 | AD11: 190459.27 | AE11: 193005.45 | AF11: 195603.95 | AG11: 198253.39 | AH11: 200952.28 | AI11: 203699.06 | AJ11: 206492.3 | AK11: 209330.69 | AL11: 212103.89 | AM11: 214911.71 | AN11: 217760.12 | AO11: 220651.5 | AP11: 223586.76 | AQ11: 226566.02 | AR11: 229589.01 | AS11: 232655.26 | AT11: 235764.22 | AU11: 238915.34 | AV11: 242118.09 | AW11: 245362.93 | AX11: 248649.08 | AY11: 251976.16 | AZ11: 255344.07 | BA11: 258752.95 | BB11: 262203.07 | BC11: 265694.83 | BD11: 269228.73 | BE11: 272805.3
A12: y_sgla_2 | B12: 21685.663 | C12: 21827.758 | D12: 22035.012 | E12: 22283.94 | F12: 22564.4 | G12: 22869.529 | H12: 23182.12 | I12: 23505.504 | J12: 23838.559 | K12: 24180.184 | L12: 24550.133 | M12: 24913.666 | N12: 25280.557 | O12: 25651.463 | P12: 26026.699 | Q12: 26406.594 | R12: 26789.601 | S12: 27177.702 | T12: 27571.591 | U12: 27971.88 | V12: 28363.941 | W12: 28771.683 | X12: 29189.077 | Y12: 29615.872 | Z12: 30052.088 | AA12: 30454.251 | AB12: 30869.45 | AC12: 31289.585 | AD12: 31715.125 | AE12: 32146.687 | AF12: 32584.778 | AG12: 33030.179 | AH12: 33482.73 | AI12: 33942.406 | AJ12: 34409.085 | AK12: 34882.569 | AL12: 35356.136 | AM12: 35832.073 | AN12: 36310.935 | AO12: 36793.025 | AP12: 37278.565 | AQ12: 37768.378 | AR12: 38262.167 | AS12: 38759.987 | AT12: 39261.871 | AU12: 39767.829 | AV12: 40280.977 | AW12: 40799.31 | AX12: 41322.519 | AY12: 41850.405 | AZ12: 42382.846 | BA12: 42921.168 | BB12: 43464.447 | BC12: 44012.625 | BD12: 44565.72 | BE12: 45123.81
... A67: y_seot_0 | B67: 109.765 | C67: 110.57054 | D67: 111.25226 | E67: 111.94529 | F67: 112.6958 | G67: 113.53938 | H67: 114.42397 | I67: 115.3675 | J67: 116.3592 | K67: 117.38543 | L67: 118.53191 | M67: 119.63719 | N67: 120.73875 | O67: 121.84272 | P67: 122.95069 | Q67: 124.06366 | R67: 125.1829 | S67: 126.31004 | T67: 127.44698 | U67: 128.59585 | V67: 129.68866 | W67: 130.84033 | X67: 132.02231 | Y67: 133.23046 | Z67: 134.46464 | AA67: 135.52484 | AB67: 136.63915 | AC67: 137.77696 | AD67: 138.93706 | AE67: 140.12188 | AF67: 141.33408 | AG67: 142.57578 | AH67: 143.84838 | AI67: 145.15263 | AJ67: 146.48876 | AK67: 147.85661 | AL67: 149.20796 | AM67: 150.57074 | AN67: 151.95205 | AO67: 153.355 | AP67: 154.78149 | AQ67: 156.2329 | AR67: 157.71023 | AS67: 159.21414 | AT67: 160.74495 | AU67: 162.30235 | AV67: 163.88833 | AW67: 165.49894 | AX67: 167.13151 | AY67: 168.78967 | AZ67: 170.47677 | BA67: 172.19375 | BB67: 173.94014 | BC67: 175.71517 | BD67: 177.51823 | BE67: 179.34911

Sheet Capital
A1: _date_ | B1: 42005 | C1: 42370 | D1: 42736 | E1: 43101 | F1: 43466 | G1: 43831 | H1: 44197 | I1: 44562 | J1: 44927 | K1: 45292 | L1: 45658 | M1: 46023 | N1: 46388 | O1: 46753 | P1: 47119 | Q1: 47484 | R1: 47849 | S1: 48214 | T1: 48580 | U1: 48945 | V1: 49310 | W1: 49675 | X1: 50041 | Y1: 50406 | Z1: 50771 | AA1: 51136 | AB1: 51502 | AC1: 51867 | AD1: 52232 | AE1: 52597 | AF1: 52963 | AG1: 53328 | AH1: 53693 | AI1: 54058 | AJ1: 54424 | AK1: 54789 | AL1: 55154 | AM1: 55519 | AN1: 55885 | AO1: 56250 | AP1: 56615 | AQ1: 56980 | AR1: 57346 | AS1: 57711 | AT1: 58076 | AU1: 58441 | AV1: 58807 | AW1: 59172 | AX1: 59537 | AY1: 59902 | AZ1: 60268 | BA1: 60633 | BB1: 60998 | BC1: 61363 | BD1: 61729 | BE1: 62094
A2: f_k_2 | B2: 5218727.8 | C2: 5271371 | D2: 5323901.4 | E2: 5377275.8 | F2: 5432055.7 | G2: 5488596.3 | H2: 5546947.6 | I2: 5607165.1 | J2: 5669314.4 | K2: 5733462.8 | L2: 5800006.9 | M2: 5868870.8 | N2: 5940012.6 | O2: 6013416.8 | P2: 6089081.6 | Q2: 6167012.2 | R2: 6247195.3 | S2: 6329633.7 | T2: 6414341.5 | U2: 6501339.4 | V2: 6590406 | W2: 6681646.1 | X2: 6775143.6 | Y2: 6870962.1 | Z2: 6969152.6 | AA2: 7069046.4 | AB2: 7170572.5 | AC2: 7273688.7 | AD2: 7378361.9 | AE2: 7484569 | AF2: 7592296.5 | AG2: 7701543.7 | AH2: 7812311.3 | AI2: 7924599.2 | AJ2: 8038405.5 | AK2: 8153725.2 | AL2: 8270428.8 | AM2: 8388413.1 | AN2: 8507596.1 | AO2: 8627910.3 | AP2: 8749300.4 | AQ2: 8871729.5 | AR2: 8995166.8 | AS2: 9119587.2 | AT2: 9244970.4 | AU2: 9371300.7 | AV2: 9498610.1 | AW2: 9626917.9 | AX2: 9756234.9 | AY2: 9886567.9 | AZ2: 10017922 | BA2: 10150319 | BB2: 10283777 | BC2: 10418311 | BD2: 10553936 | BE2: 10690666
A3: f_k_0 | B3: 5224351.6 | C3: 5285939.2 | D3: 5349468.3 | E3: 5415267.1 | F3: 5483570.5 | G3: 5554548.7 | H3: 5628133 | I3: 5704293 | J3: 5783028.1 | K3: 5864354.1 | L3: 5948646 | M3: 6035819.6 | N3: 6125820.8 | O3: 6218620.3 | P3: 6314200.2 | Q3: 6412547.9 | R3: 6513654.3 | S3: 6617512.9 | T3: 6724119.7 | U3: 6833472.4 | V3: 6945305.2 | W3: 7059698.9 | X3: 7176711.4 | Y3: 7296379.2 | Z3: 7418725.8 | AA3: 7542993.5 | AB3: 7669058.5 | AC3: 7796832.5 | AD3: 7926240.9 | AE3: 8057223.3 | AF3: 8189731.8 | AG3: 8323728.1 | AH3: 8459179.7 | AI3: 8596056.3 | AJ3: 8734328.3 | AK3: 8873964.4 | AL3: 9014742.2 | AM3: 9156493.5 | AN3: 9299090.3 | AO3: 9442431.8 | AP3: 9586438.2 | AQ3: 9731047 | AR3: 9876210.4 | AS3: 10021893 | AT3: 10168070 | AU3: 10314725 | AV3: 10461867 | AW3: 10609508 | AX3: 10757660 | AY3: 10906342 | AZ3: 11055573 | BA3: 11205379 | BB3: 11355791 | BC3: 11506843 | BD3: 11658579 | BE3: 11811044
A4: f_k_sagr_2 | B4: 47150.175 | C4: 47589.294 | D4: 48008.617 | E4: 48421.03 | F4: 48836.534 | G4: 49262.939 | H4: 49704.499 | I4: 50164.599 | J4: 50645.906 | K4: 51150.41 | L4: 51682.555 | M4: 52242.094 | N4: 52828.675 | O4: 53441.918 | P4: 54081.386 | Q4: 54746.601 | R4: 55436.763 | S4: 56151.276 | T4: 56889.657 | U4: 57651.507 | V4: 58434.242 | W4: 59238.187 | X4: 60063.64 | Y4: 60910.793 | Z4: 61779.779 | AA4: 62664.182 | AB4: 63562.833 | AC4: 64475.046 | AD4: 65400.401 | AE4: 66338.724 | AF4: 67290.055 | AG4: 68254.664 | AH4: 69232.877 | AI4: 70225.046 | AJ4: 71231.528 | AK4: 72252.659 | AL4: 73287.867 | AM4: 74336.559 | AN4: 75398.306 | AO4: 76472.836 | AP4: 77560.02 | AQ4: 78659.975 | AR4: 79772.861 | AS4: 80898.892 | AT4: 82038.319 | AU4: 83191.418 | AV4: 84359.021 | AW4: 85541.708 | AX4: 86739.921 | AY4: 87954.011 | AZ4: 89184.267 | BA4: 90431.193 | BB4: 91695.129 | BC4: 92976.337 | BD4: 94275.029 | BE4: 95591.397
A5: f_k_sagr_0 | B5: 47217.394 | C5: 47760.718 | D5: 48305.589 | E5: 48857.213 | F5: 49421.24 | G5: 50002.532 | H5: 50603.051 | I5: 51224.307 | J5: 51867.452 | K5: 52533.322 | L5: 53225.705 | M5: 53944.036 | N5: 54687.691 | O5: 55456.096 | P5: 56248.676 | Q5: 57064.861 | R5: 57904.098 | S5: 58765.877 | T5: 59649.738 | U5: 60555.279 | V5: 61479.729 | W5: 62423.455 | X5: 63386.78 | Y5: 64369.919 | Z5: 65373.034 | AA5: 66389.2 | AB5: 67417.082 | AC5: 68455.929 | AD5: 69505.307 | AE5: 70565.073 | AF5: 71635.327 | AG5: 72716.348 | AH5: 73808.522 | AI5: 74912.293 | AJ5: 76028.12 | AK5: 77156.452 | AL5: 78295.991 | AM5: 79445.869 | AN5: 80605.588 | AO5: 81774.931 | AP5: 82953.898 | AQ5: 84142.67 | AR5: 85341.568 | AS5: 86551.015 | AT5: 87771.499 | AU5: 89003.552 | AV5: 90247.882 | AW5: 91505.165 | AX5: 92776.043 | AY5: 94061.11 | AZ5: 95360.915 | BA5: 96675.967 | BB5: 98006.748 | BC5: 99353.72 | BD5: 100717.33 | BE5: 102098.01
A6: f_k_sfor_2 | B6: 1843.0431 | C6: 1860.8216 | D6: 1876.5864 | E6: 1890.2889 | F6: 1902.0591 | G6: 1912.0791 | H6: 1920.4597 | I6: 1927.3001 | J6: 1932.7012 | K6: 1936.7738 | L6: 1939.7171 | M6: 1941.6157 | N6: 1942.5711 | O6: 1942.6984 | P6: 1942.117 | Q6: 1940.9435 | R6: 1939.2743 | S6: 1937.2078 | T6: 1934.8394 | U6: 1932.2602 | V6: 1929.5039 | W6: 1926.6708 | X6: 1923.8517 | Y6: 1921.1235 | Z6: 1918.5524 | AA6: 1916.0544 | AB6: 1913.6793 | AC6: 1911.4844 | AD6: 1909.5211 | AE6: 1907.8336 | AF6: 1906.4606 | AG6: 1905.4396 | AH6: 1904.8023 | AI6: 1904.5759 | AJ6: 1904.7837 | AK6: 1905.446 | AL6: 1906.5797 | AM6: 1908.1923 | AN6: 1910.2908 | AO6: 1912.8804 | AP6: 1915.965 | AQ6: 1919.5526 | AR6: 1923.6469 | AS6: 1928.2495 | AT6: 1933.3605 | AU6: 1938.9789 | AV6: 1945.1235 | AW6: 1951.8007 | AX6: 1959.0105 | AY6: 1966.7492 | AZ6: 1975.011 | BA6: 1983.8008 | BB6: 1993.1159 | BC6: 2002.9508 | BD6: 2013.2982 | BE6: 2024.1501
A7: f_k_sfor_0 | B7: 1844.7471 | C7: 1864.5142 | D7: 1882.2706 | E7: 1897.8557 | F7: 1911.324 | G7: 1922.8723 | H7: 1932.7095 | I7: 1941.0626 | J7: 1948.144 | K7: 1954.137 | L7: 1959.2754 | M7: 1963.6571 | N7: 1967.3669 | O7: 1970.4882 | P7: 1973.102 | Q7: 1975.2857 | R7: 1977.1116 | S7: 1978.6477 | T7: 1979.9571 | U7: 1981.0989 | V7: 1982.074 | W7: 1982.9551 | X7: 1983.8075 | Y7: 1984.6846 | Z7: 1985.631 | AA7: 1986.5365 | AB7: 1987.426 | AC7: 1988.3386 | AD7: 1989.3111 | AE7: 1990.3766 | AF7: 1991.5643 | AG7: 1992.9003 | AH7: 1994.4077 | AI7: 1996.1073 | AJ7: 1998.0173 | AK7: 2000.1538 | AL7: 2002.4978 | AM7: 2005.0422 | AN7: 2007.7894 | AO7: 2010.7468 | AP7: 2013.924 | AQ7: 2017.331 | AR7: 2020.9777 | AS7: 2024.8736 | AT7: 2029.0272 | AU7: 2033.4446 | AV7: 2038.1275 | AW7: 2043.0724 | AX7: 2048.275 | AY7: 2053.734 | AZ7: 2059.4524 | BA7: 2065.4354 | BB7: 2071.6881 | BC7: 2078.2149 | BD7: 2085.0186 | BE7: 2092.1011
A8: f_k_sfoo_2 | B8: 74442.247 | C8: 75170.07 | D8: 75876.334 | E8: 76577.633 | F8: 77287.282 | G8: 78015.979 | H8: 78769.46 | I8: 79552.358 | J8: 80368.387 | K8: 81220.365 | L8: 82115.04 | M8: 83052.237 | N8: 84031.428 | O8: 85051.95 | P8: 86113.01 | Q8: 87213.732 | R8: 88352.859 | S8: 89529.322 | T8: 90742.177 | U8: 91990.577 | V8: 93270.233 | W8: 94581.24 | X8: 95923.719 | Y8: 97297.676 | Z8: 98703.034 | AA8: 100129.5 | AB8: 101574.5 | AC8: 103036.34 | AD8: 104513.89 | AE8: 106006.45 | AF8: 107513.76 | AG8: 109035.92 | AH8: 110573.2 | AI8: 112125.96 | AJ8: 113694.59 | AK8: 115279.5 | AL8: 116879.41 | AM8: 118493.18 | AN8: 120120.03 | AO8: 121759.46 | AP8: 123411.27 | AQ8: 125075.61 | AR8: 126752.82 | AS8: 128443.32 | AT8: 130147.65 | AU8: 131866.38 | AV8: 133600.79 | AW8: 135351.92 | AX8: 137120.64 | AY8: 138907.72 | AZ8: 140713.82 | BA8: 142539.83 | BB8: 144386.47 | BC8: 146254.35 | BD8: 148144.03 | BE8: 150056.02
A9: f_k_sfoo_0 | B9: 74528.113 | C9: 75393.603 | D9: 76271.233 | E9: 77167.949 | F9: 78091.028 | G9: 79046.729 | H9: 80037.143 | I9: 81063.833 | J9: 82127.996 | K9: 83230.494 | L9: 84376.895 | M9: 85566.315 | N9: 86797.691 | O9: 88069.983 | P9: 89382.128 | Q9: 90733.061 | R9: 92121.749 | S9: 93547.224 | T9: 95008.593 | U9: 96505.05 | V9: 98032.095 | W9: 99589.946 | X9: 101178.85 | Y9: 102798.97 | Z9: 104450.37 | AA9: 106122.12 | AB9: 107811.51 | AC9: 109516.83 | AD9: 111236.98 | AE9: 112971.39 | AF9: 114719.98 | AG9: 116482.96 | AH9: 118260.79 | AI9: 120054.02 | AJ9: 121863.3 | AK9: 123689.24 | AL9: 125529.81 | AM9: 127383.51 | AN9: 129249.44 | AO9: 131127.13 | AP9: 133016.52 | AQ9: 134917.86 | AR9: 136831.65 | AS9: 138758.61 | AT9: 140699.58 | AU9: 142655.48 | AV9: 144627.54 | AW9: 146616.95 | AX9: 148624.88 | AY9: 150652.41 | AZ9: 152700.58 | BA9: 154770.36 | BB9: 156862.66 | BC9: 158978.38 | BD9: 161118.41 | BE9: 163283.59
A10: f_k_sveh_2 | B10: 400375.64 | C10: 403619.02 | D10: 407077.48 | E10: 410856.54 | F10: 414951.41 | G10: 419321.77 | H10: 423898.41 | I10: 428633.72 | J10: 433495.3 | K10: 438460.81 | L10: 443554.17 | M10: 448732.97 | N10: 453975.72 | O10: 459271.32 | P10: 464613.72 | Q10: 469999.75 | R10: 475422.77 | S10: 480881.44 | T10: 486377.13 | U10: 491912.68 | V10: 497463.4 | W10: 503052.32 | X10: 508692.54 | Y10: 514392.47 | Z10: 520158.67 | AA10: 525915.94 | AB10: 531686.27 | AC10: 537484.79 | AD10: 543322.7 | AE10: 549209.32 | AF10: 555152.87 | AG10: 561161.79 | AH10: 567242.86 | AI10: 573401.65 | AJ10: 579642.86 | AK10: 585970.43 | AL10: 592379.36 | AM10: 598868.99 | AN10: 605440.66 | AO10: 612096.45 | AP10: 618838.56 | AQ10: 625670.89 | AR10: 632596.02 | AS10: 639615.86 | AT10: 646731.94 | AU10: 653945.49 | AV10: 661265.16 | AW10: 668694.42 | AX10: 676234.58 | AY10: 683886.06 | AZ10: 691648.9 | BA10: 699526.77 | BB10: 707520.93 | BC10: 715631.75 | BD10: 723859.31 | BE10: 732203.67
A11: f_k_sveh_0 | B11: 401602.76 | C11: 406515.04 | D11: 411794.98 | E11: 417445.86 | F11: 423425.57 | G11: 429681.67 | H11: 436143.54 | I11: 442767.01 | J11: 449525.24 | K11: 456402.17 | L11: 463431.24 | M11: 470579.14 | N11: 477830.08 | O11: 485176.91 | P11: 492616.38 | Q11: 500147.29 | R11: 507769.72 | S11: 515484.71 | T11: 523294.02 | U11: 531200.01 | V11: 539173.48 | W11: 547238.32 | X11: 555407.15 | Y11: 563687.35 | Z11: 572084.17 | AA11: 580509.15 | AB11: 588981.98 | AC11: 597516.39 | AD11: 606122.46 | AE11: 614808.62 | AF11: 623582.25 | AG11: 632449.86 | AH11: 641417.11 | AI11: 650488.87 | AJ11: 659669.26 | AK11: 668961.74 | AL11: 678346.69 | AM11: 687818.35 | AN11: 697376.93 | AO11: 707024.88 | AP11: 716765.45 | AQ11: 726602.07 | AR11: 736538.08 | AS11: 746576.58 | AT11: 756720.44 | AU11: 766972.21 | AV11: 777336.27 | AW11: 787815.44 | AX11: 798411.84 | AY11: 809127.18 | AZ11: 819963.04 | BA11: 830920.91 | BB11: 842002.28 | BC11: 853208.68 | BD11: 864541.69 | BE11: 876002.99
A12: f_k_sgla_2 | B12: 16064.666 | C12: 16222.883 | D12: 16380.432 | E12: 16540.79 | F12: 16705.949 | G12: 16877.086 | H12: 17054.37 | I12: 17237.886 | J12: 17427.7 | K12: 17623.876 | L12: 17827.397 | M12: 18037.967 | N12: 18255.369 | O12: 18479.478 | P12: 18710.232 | Q12: 18947.611 | R12: 19191.547 | S12: 19442.054 | T12: 19699.201 | U12: 19963.096 | V12: 20233.198 | W12: 20509.846 | X12: 20793.363 | Y12: 21084.031 | Z12: 21382.095 | AA12: 21685.817 | AB12: 21995.017 | AC12: 22309.634 | AD12: 22629.637 | AE12: 22955.022 | AF12: 23285.799 | AG12: 23622.012 | AH12: 23963.695 | AI12: 24310.864 | AJ12: 24663.522 | AK12: 25021.648 | AL12: 25384.912 | AM12: 25752.997 | AN12: 26125.618 | AO12: 26502.517 | AP12: 26883.461 | AQ12: 27268.271 | AR12: 27656.777 | AS12: 28048.82 | AT12: 28444.252 | AU12: 28842.939 | AV12: 29244.903 | AW12: 29650.126 | AX12: 30058.558 | AY12: 30470.137 | AZ12: 30884.794 | BA12: 31302.533 | BB12: 31723.338 | BC12: 32147.186 | BD12: 32574.058 | BE12: 33003.941
... A67: f_k_seot_0 | B67: 65.173576 | C67: 65.912331 | D67: 66.632457 | E67: 67.33126 | F67: 68.010473 | G67: 68.674498 | H67: 69.326516 | I67: 69.969922 | J67: 70.607719 | K67: 71.242211 | L67: 71.878645 | M67: 72.517025 | N67: 73.157089 | O67: 73.798765 | P67: 74.442098 | Q67: 75.08721 | R67: 75.734285 | S67: 76.383582 | T67: 77.035448 | U67: 77.690323 | V67: 78.346141 | W67: 79.004361 | X67: 79.666468 | Y67: 80.333741 | Z67: 81.007348 | AA67: 81.681 | AB67: 82.354644 | AC67: 83.029116 | AD67: 83.705418 | AE67: 84.384668 | AF67: 85.068084 | AG67: 85.756961 | AH67: 86.452632 | AI67: 87.156427 | AJ67: 87.869644 | AK67: 88.593521 | AL67: 89.327466 | AM67: 90.071341 | AN67: 90.825414 | AO67: 91.590177 | AP67: 92.366235 | AQ67: 93.154252 | AR67: 93.954921 | AS67: 94.768937 | AT67: 95.596978 | AU67: 96.439678 | AV67: 97.297698 | AW67: 98.171537 | AX67: 99.061516 | AY67: 99.968016 | AZ67: 100.89153 | BA67: 101.83261 | BB67: 102.79175 | BC67: 103.76941 | BD67: 104.76597 | BE67: 105.78175

Sheet Results
A1: NB : on crée ici une liste : - globale, qui fusionne les sorties des reportings 1, 2 et 3 - "rationalisée" : suppression des doublons, et regroupements par thématique On continue par la suite à avoir 2 Excels de reporting (un "energie", fusion des reportings 1 et 2), et un "économie" (reporting 3)), dans lesquels on copiera cet onglet "results" (généré automatiquement par EViews). --> puis voir à la fin si on peut pas importer les graphs et tableaux dans l'excel automatiquement généré (éviterait les copiés collés, mais à voir si ça prend trop de temps, et si c'est pas trop gros comme excel)
A2: Nom du bloc de variables utilisé dans le code | B2: Sous-bloc de variables pour plus de lisibilité dans le Excel | E2: Year | F2: =date!B3 -> 2015 | G2: =date!C3 -> 2016 | H2: =date!D3 -> 2017 | I2: =date!E3 -> 2018 | J2: =date!F3 -> 2019 | K2: =date!G3 -> 2020 | L2: =date!H3 -> 2021 | M2: =date!I3 -> 2022 | ... BI2: =date!BE3 -> 2070
A3: HYBRID | B3: AUTOMOBILES (thousands) | C3: TOTAL STOCK SHOCK | E3: AUTO_2 | F3: =VLOOKUP($E3,Hybrid!$1:$1048576,MATCH(DATE(F$2,1,1),Hybrid!$A$1:$LI$1),FALSE) -> 32317.941 | G3: =VLOOKUP($E3,Hybrid!$1:$1048576,MATCH(DATE(G$2,1,1),Hybrid!$A$1:$LI$1),FALSE) -> 31906.572 | H3: =VLOOKUP($E3,Hybrid!$1:$1048576,MATCH(DATE(H$2,1,1),Hybrid!$A$1:$LI$1),FALSE) -> 31679.015 | I3: =VLOOKUP($E3,Hybrid!$1:$1048576,MATCH(DATE(I$2,1,1),Hybrid!$A$1:$LI$1),FALSE) -> 31579.816 | J3: =VLOOKUP($E3,Hybrid!$1:$1048576,MATCH(DATE(J$2,1,1),Hybrid!$A$1:$LI$1),FALSE) -> 31572.523 | K3: =VLOOKUP($E3,Hybrid!$1:$1048576,MATCH(DATE(K$2,1,1),Hybrid!$A$1:$LI$1),FALSE) -> 31633.573 | L3: =VLOOKUP($E3,Hybrid!$1:$1048576,MATCH(DATE(L$2,1,1),Hybrid!$A$1:$LI$1),FALSE) -> 31743.622 | M3: =VLOOKUP($E3,Hybrid!$1:$1048576,MATCH(DATE(M$2,1,1),Hybrid!$A$1:$LI$1),FALSE) -> 31892.229 | ... BI3: =VLOOKUP($E3,Hybrid!$1:$1048576,MATCH(DATE(BI$2,1,1),Hybrid!$A$1:$LI$1),FALSE) -> 44185.292
C4: OIL | E4: AUTO_cfut_2 | F4: =VLOOKUP($E4,Hybrid!$1:$1048576,MATCH(DATE(F$2,1,1),Hybrid!$A$1:$LI$1),FALSE) -> 32271.24 | G4: =VLOOKUP($E4,Hybrid!$1:$1048576,MATCH(DATE(G$2,1,1),Hybrid!$A$1:$LI$1),FALSE) -> 31842.385 | H4: =VLOOKUP($E4,Hybrid!$1:$1048576,MATCH(DATE(H$2,1,1),Hybrid!$A$1:$LI$1),FALSE) -> 31596.647 | I4: =VLOOKUP($E4,Hybrid!$1:$1048576,MATCH(DATE(I$2,1,1),Hybrid!$A$1:$LI$1),FALSE) -> 31478.956 | J4: =VLOOKUP($E4,Hybrid!$1:$1048576,MATCH(DATE(J$2,1,1),Hybrid!$A$1:$LI$1),FALSE) -> 31453.091 | K4: =VLOOKUP($E4,Hybrid!$1:$1048576,MATCH(DATE(K$2,1,1),Hybrid!$A$1:$LI$1),FALSE) -> 31495.616 | L4: =VLOOKUP($E4,Hybrid!$1:$1048576,MATCH(DATE(L$2,1,1),Hybrid!$A$1:$LI$1),FALSE) -> 31587.292 | M4: =VLOOKUP($E4,Hybrid!$1:$1048576,MATCH(DATE(M$2,1,1),Hybrid!$A$1:$LI$1),FALSE) -> 31717.717 | ... BI4: =VLOOKUP($E4,Hybrid!$1:$1048576,MATCH(DATE(BI$2,1,1),Hybrid!$A$1:$LI$1),FALSE) -> 43190.487
D5: class A | E5: AUTO_ca_cfut_2 | F5: =VLOOKUP($E5,Hybrid!$1:$1048576,MATCH(DATE(F$2,1,1),Hybrid!$A$1:$LI$1),FALSE) -> 7095.7005 | G5: =VLOOKUP($E5,Hybrid!$1:$1048576,MATCH(DATE(G$2,1,1),Hybrid!$A$1:$LI$1),FALSE) -> 7135.4525 | H5: =VLOOKUP($E5,Hybrid!$1:$1048576,MATCH(DATE(H$2,1,1),Hybrid!$A$1:$LI$1),FALSE) -> 7219.1567 | I5: =VLOOKUP($E5,Hybrid!$1:$1048576,MATCH(DATE(I$2,1,1),Hybrid!$A$1:$LI$1),FALSE) -> 7333.1185 | J5: =VLOOKUP($E5,Hybrid!$1:$1048576,MATCH(DATE(J$2,1,1),Hybrid!$A$1:$LI$1),FALSE) -> 7468.4598 | K5: =VLOOKUP($E5,Hybrid!$1:$1048576,MATCH(DATE(K$2,1,1),Hybrid!$A$1:$LI$1),FALSE) -> 7619.5809 | L5: =VLOOKUP($E5,Hybrid!$1:$1048576,MATCH(DATE(L$2,1,1),Hybrid!$A$1:$LI$1),FALSE) -> 7781.7706 | M5: =VLOOKUP($E5,Hybrid!$1:$1048576,MATCH(DATE(M$2,1,1),Hybrid!$A$1:$LI$1),FALSE) -> 7952.6697 | ... BI5: =VLOOKUP($E5,Hybrid!$1:$1048576,MATCH(DATE(BI$2,1,1),Hybrid!$A$1:$LI$1),FALSE) -> 17418.49
D6: class B | E6: AUTO_cb_cfut_2 | F6: =VLOOKUP($E6,Hybrid!$1:$1048576,MATCH(DATE(F$2,1,1),Hybrid!$A$1:$LI$1),FALSE) -> 8251.2564 | G6: =VLOOKUP($E6,Hybrid!$1:$1048576,MATCH(DATE(G$2,1,1),Hybrid!$A$1:$LI$1),FALSE) -> 8176.9035 | H6: =VLOOKUP($E6,Hybrid!$1:$1048576,MATCH(DATE(H$2,1,1),Hybrid!$A$1:$LI$1),FALSE) -> 8152.584 | I6: =VLOOKUP($E6,Hybrid!$1:$1048576,MATCH(DATE(I$2,1,1),Hybrid!$A$1:$LI$1),FALSE) -> 8164.2487 | J6: =VLOOKUP($E6,Hybrid!$1:$1048576,MATCH(DATE(J$2,1,1),Hybrid!$A$1:$LI$1),FALSE) -> 8202.5934 | K6: =VLOOKUP($E6,Hybrid!$1:$1048576,MATCH(DATE(K$2,1,1),Hybrid!$A$1:$LI$1),FALSE) -> 8261.5505 | L6: =VLOOKUP($E6,Hybrid!$1:$1048576,MATCH(DATE(L$2,1,1),Hybrid!$A$1:$LI$1),FALSE) -> 8335.9889 | M6: =VLOOKUP($E6,Hybrid!$1:$1048576,MATCH(DATE(M$2,1,1),Hybrid!$A$1:$LI$1),FALSE) -> 8423.0907 | ... BI6: =VLOOKUP($E6,Hybrid!$1:$1048576,MATCH(DATE(BI$2,1,1),Hybrid!$A$1:$LI$1),FALSE) -> 14149.065
D7: class C | E7: AUTO_cc_cfut_2 | F7: =VLOOKUP($E7,Hybrid!$1:$1048576,MATCH(DATE(F$2,1,1),Hybrid!$A$1:$LI$1),FALSE) -> 6777.6025 | G7: =VLOOKUP($E7,Hybrid!$1:$1048576,MATCH(DATE(G$2,1,1),Hybrid!$A$1:$LI$1),FALSE) -> 6642.801 | H7: =VLOOKUP($E7,Hybrid!$1:$1048576,MATCH(DATE(H$2,1,1),Hybrid!$A$1:$LI$1),FALSE) -> 6548.4869 | I7: =VLOOKUP($E7,Hybrid!$1:$1048576,MATCH(DATE(I$2,1,1),Hybrid!$A$1:$LI$1),FALSE) -> 6484.2835 | J7: =VLOOKUP($E7,Hybrid!$1:$1048576,MATCH(DATE(J$2,1,1),Hybrid!$A$1:$LI$1),FALSE) -> 6443.1861 | K7: =VLOOKUP($E7,Hybrid!$1:$1048576,MATCH(DATE(K$2,1,1),Hybrid!$A$1:$LI$1),FALSE) -> 6420.4945 | L7: =VLOOKUP($E7,Hybrid!$1:$1048576,MATCH(DATE(L$2,1,1),Hybrid!$A$1:$LI$1),FALSE) -> 6412.2178 | M7: =VLOOKUP($E7,Hybrid!$1:$1048576,MATCH(DATE(M$2,1,1),Hybrid!$A$1:$LI$1),FALSE) -> 6416.0068 | ... BI7: =VLOOKUP($E7,Hybrid!$1:$1048576,MATCH(DATE(BI$2,1,1),Hybrid!$A$1:$LI$1),FALSE) -> 8328.0082
D8: class D | E8: AUTO_cd_cfut_2 | F8: =VLOOKUP($E8,Hybrid!$1:$1048576,MATCH(DATE(F$2,1,1),Hybrid!$A$1:$LI$1),FALSE) -> 4159.6639 | G8: =VLOOKUP($E8,Hybrid!$1:$1048576,MATCH(DATE(G$2,1,1),Hybrid!$A$1:$LI$1),FALSE) -> 4052.6266 | H8: =VLOOKUP($E8,Hybrid!$1:$1048576,MATCH(DATE(H$2,1,1),Hybrid!$A$1:$LI$1),FALSE) -> 3968.9284 | I8: =VLOOKUP($E8,Hybrid!$1:$1048576,MATCH(DATE(I$2,1,1),Hybrid!$A$1:$LI$1),FALSE) -> 3902.2666 | J8: =VLOOKUP($E8,Hybrid!$1:$1048576,MATCH(DATE(J$2,1,1),Hybrid!$A$1:$LI$1),FALSE) -> 3848.3587 | K8: =VLOOKUP($E8,Hybrid!$1:$1048576,MATCH(DATE(K$2,1,1),Hybrid!$A$1:$LI$1),FALSE) -> 3804.2965 | L8: =VLOOKUP($E8,Hybrid!$1:$1048576,MATCH(DATE(L$2,1,1),Hybrid!$A$1:$LI$1),FALSE) -> 3767.6537 | M8: =VLOOKUP($E8,Hybrid!$1:$1048576,MATCH(DATE(M$2,1,1),Hybrid!$A$1:$LI$1),FALSE) -> 3736.955 | ... BI8: =VLOOKUP($E8,Hybrid!$1:$1048576,MATCH(DATE(BI$2,1,1),Hybrid!$A$1:$LI$1),FALSE) -> 2317.7021
D9: class E | E9: AUTO_ce_cfut_2 | F9: =VLOOKUP($E9,Hybrid!$1:$1048576,MATCH(DATE(F$2,1,1),Hybrid!$A$1:$LI$1),FALSE) -> 2503.7292 | G9: =VLOOKUP($E9,Hybrid!$1:$1048576,MATCH(DATE(G$2,1,1),Hybrid!$A$1:$LI$1),FALSE) -> 2441.652 | H9: =VLOOKUP($E9,Hybrid!$1:$1048576,MATCH(DATE(H$2,1,1),Hybrid!$A$1:$LI$1),FALSE) -> 2392.7577 | I9: =VLOOKUP($E9,Hybrid!$1:$1048576,MATCH(DATE(I$2,1,1),Hybrid!$A$1:$LI$1),FALSE) -> 2353.0125 | J9: =VLOOKUP($E9,Hybrid!$1:$1048576,MATCH(DATE(J$2,1,1),Hybrid!$A$1:$LI$1),FALSE) -> 2319.7042 | K9: =VLOOKUP($E9,Hybrid!$1:$1048576,MATCH(DATE(K$2,1,1),Hybrid!$A$1:$LI$1),FALSE) -> 2291.0142 | L9: =VLOOKUP($E9,Hybrid!$1:$1048576,MATCH(DATE(L$2,1,1),Hybrid!$A$1:$LI$1),FALSE) -> 2265.464 | M9: =VLOOKUP($E9,Hybrid!$1:$1048576,MATCH(DATE(M$2,1,1),Hybrid!$A$1:$LI$1),FALSE) -> 2242.1777 | ... BI9: =VLOOKUP($E9,Hybrid!$1:$1048576,MATCH(DATE(BI$2,1,1),Hybrid!$A$1:$LI$1),FALSE) -> 802.88158
D10: class F | E10: AUTO_cf_cfut_2 | F10: =VLOOKUP($E10,Hybrid!$1:$1048576,MATCH(DATE(F$2,1,1),Hybrid!$A$1:$LI$1),FALSE) -> 1243.6668 | G10: =VLOOKUP($E10,Hybrid!$1:$1048576,MATCH(DATE(G$2,1,1),Hybrid!$A$1:$LI$1),FALSE) -> 1210.1988 | H10: =VLOOKUP($E10,Hybrid!$1:$1048576,MATCH(DATE(H$2,1,1),Hybrid!$A$1:$LI$1),FALSE) -> 1181.9055 | I10: =VLOOKUP($E10,Hybrid!$1:$1048576,MATCH(DATE(I$2,1,1),Hybrid!$A$1:$LI$1),FALSE) -> 1156.5684 | J10: =VLOOKUP($E10,Hybrid!$1:$1048576,MATCH(DATE(J$2,1,1),Hybrid!$A$1:$LI$1),FALSE) -> 1132.7654 | K10: =VLOOKUP($E10,Hybrid!$1:$1048576,MATCH(DATE(K$2,1,1),Hybrid!$A$1:$LI$1),FALSE) -> 1109.6063 | L10: =VLOOKUP($E10,Hybrid!$1:$1048576,MATCH(DATE(L$2,1,1),Hybrid!$A$1:$LI$1),FALSE) -> 1086.4484 | M10: =VLOOKUP($E10,Hybrid!$1:$1048576,MATCH(DATE(M$2,1,1),Hybrid!$A$1:$LI$1),FALSE) -> 1062.9756 | ... BI10: =VLOOKUP($E10,Hybrid!$1:$1048576,MATCH(DATE(BI$2,1,1),Hybrid!$A$1:$LI$1),FALSE) -> 88.835853
D11: class G | E11: AUTO_cg_cfut_2 | F11: =VLOOKUP($E11,Hybrid!$1:$1048576,MATCH(DATE(F$2,1,1),Hybrid!$A$1:$LI$1),FALSE) -> 2239.6206 | G11: =VLOOKUP($E11,Hybrid!$1:$1048576,MATCH(DATE(G$2,1,1),Hybrid!$A$1:$LI$1),FALSE) -> 2182.7503 | H11: =VLOOKUP($E11,Hybrid!$1:$1048576,MATCH(DATE(H$2,1,1),Hybrid!$A$1:$LI$1),FALSE) -> 2132.8279 | I11: =VLOOKUP($E11,Hybrid!$1:$1048576,MATCH(DATE(I$2,1,1),Hybrid!$A$1:$LI$1),FALSE) -> 2085.4582 | J11: =VLOOKUP($E11,Hybrid!$1:$1048576,MATCH(DATE(J$2,1,1),Hybrid!$A$1:$LI$1),FALSE) -> 2038.0231 | K11: =VLOOKUP($E11,Hybrid!$1:$1048576,MATCH(DATE(K$2,1,1),Hybrid!$A$1:$LI$1),FALSE) -> 1989.0729 | L11: =VLOOKUP($E11,Hybrid!$1:$1048576,MATCH(DATE(L$2,1,1),Hybrid!$A$1:$LI$1),FALSE) -> 1937.7482 | M11: =VLOOKUP($E11,Hybrid!$1:$1048576,MATCH(DATE(M$2,1,1),Hybrid!$A$1:$LI$1),FALSE) -> 1883.8411 | ... BI11: =VLOOKUP($E11,Hybrid!$1:$1048576,MATCH(DATE(BI$2,1,1),Hybrid!$A$1:$LI$1),FALSE) -> 85.503861
C12: ELEC | E12: AUTO_cele_2 | F12: =VLOOKUP($E12,Hybrid!$1:$1048576,MATCH(DATE(F$2,1,1),Hybrid!$A$1:$LI$1),FALSE) -> 44.765 | G12: =VLOOKUP($E12,Hybrid!$1:$1048576,MATCH(DATE(G$2,1,1),Hybrid!$A$1:$LI$1),FALSE) -> 62.197241 | H12: =VLOOKUP($E12,Hybrid!$1:$1048576,MATCH(DATE(H$2,1,1),Hybrid!$A$1:$LI$1),FALSE) -> 80.315188 | I12: =VLOOKUP($E12,Hybrid!$1:$1048576,MATCH(DATE(I$2,1,1),Hybrid!$A$1:$LI$1),FALSE) -> 98.738326 | J12: =VLOOKUP($E12,Hybrid!$1:$1048576,MATCH(DATE(J$2,1,1),Hybrid!$A$1:$LI$1),FALSE) -> 117.23989 | K12: =VLOOKUP($E12,Hybrid!$1:$1048576,MATCH(DATE(K$2,1,1),Hybrid!$A$1:$LI$1),FALSE) -> 135.69295 | L12: =VLOOKUP($E12,Hybrid!$1:$1048576,MATCH(DATE(L$2,1,1),Hybrid!$A$1:$LI$1),FALSE) -> 153.99329 | M12: =VLOOKUP($E12,Hybrid!$1:$1048576,MATCH(DATE(M$2,1,1),Hybrid!$A$1:$LI$1),FALSE) -> 172.1043 | ... BI12: =VLOOKUP($E12,Hybrid!$1:$1048576,MATCH(DATE(BI$2,1,1),Hybrid!$A$1:$LI$1),FALSE) -> 990.40052
D13: class A | E13: AUTO_ca_cele_2 | F13: =VLOOKUP($E13,Hybrid!$1:$1048576,MATCH(DATE(F$2,1,1),Hybrid!$A$1:$LI$1),FALSE) -> 9.8427899 | G13: =VLOOKUP($E13,Hybrid!$1:$1048576,MATCH(DATE(G$2,1,1),Hybrid!$A$1:$LI$1),FALSE) -> 14.913071 | H13: =VLOOKUP($E13,Hybrid!$1:$1048576,MATCH(DATE(H$2,1,1),Hybrid!$A$1:$LI$1),FALSE) -> 20.215422 | I13: =VLOOKUP($E13,Hybrid!$1:$1048576,MATCH(DATE(I$2,1,1),Hybrid!$A$1:$LI$1),FALSE) -> 25.653022 | J13: =VLOOKUP($E13,Hybrid!$1:$1048576,MATCH(DATE(J$2,1,1),Hybrid!$A$1:$LI$1),FALSE) -> 31.168875 | K13: =VLOOKUP($E13,Hybrid!$1:$1048576,MATCH(DATE(K$2,1,1),Hybrid!$A$1:$LI$1),FALSE) -> 36.73188 | L13: =VLOOKUP($E13,Hybrid!$1:$1048576,MATCH(DATE(L$2,1,1),Hybrid!$A$1:$LI$1),FALSE) -> 42.31518 | M13: =VLOOKUP($E13,Hybrid!$1:$1048576,MATCH(DATE(M$2,1,1),Hybrid!$A$1:$LI$1),FALSE) -> 47.910095 | ... BI13: =VLOOKUP($E13,Hybrid!$1:$1048576,MATCH(DATE(BI$2,1,1),Hybrid!$A$1:$LI$1),FALSE) -> 381.78197
D14: class B | E14: AUTO_cb_cele_2 | F14: =VLOOKUP($E14,Hybrid!$1:$1048576,MATCH(DATE(F$2,1,1),Hybrid!$A$1:$LI$1),FALSE) -> 11.445717 | G14: =VLOOKUP($E14,Hybrid!$1:$1048576,MATCH(DATE(G$2,1,1),Hybrid!$A$1:$LI$1),FALSE) -> 16.228471 | H14: =VLOOKUP($E14,Hybrid!$1:$1048576,MATCH(DATE(H$2,1,1),Hybrid!$A$1:$LI$1),FALSE) -> 21.229365 | I14: =VLOOKUP($E14,Hybrid!$1:$1048576,MATCH(DATE(I$2,1,1),Hybrid!$A$1:$LI$1),FALSE) -> 26.353805 | J14: =VLOOKUP($E14,Hybrid!$1:$1048576,MATCH(DATE(J$2,1,1),Hybrid!$A$1:$LI$1),FALSE) -> 31.546042 | K14: =VLOOKUP($E14,Hybrid!$1:$1048576,MATCH(DATE(K$2,1,1),Hybrid!$A$1:$LI$1),FALSE) -> 36.775415 | L14: =VLOOKUP($E14,Hybrid!$1:$1048576,MATCH(DATE(L$2,1,1),Hybrid!$A$1:$LI$1),FALSE) -> 42.015471 | M14: =VLOOKUP($E14,Hybrid!$1:$1048576,MATCH(DATE(M$2,1,1),Hybrid!$A$1:$LI$1),FALSE) -> 47.257156 | ... BI14: =VLOOKUP($E14,Hybrid!$1:$1048576,MATCH(DATE(BI$2,1,1),Hybrid!$A$1:$LI$1),FALSE) -> 332.66309
D15: class C | E15: AUTO_cc_cele_2 | F15: =VLOOKUP($E15,Hybrid!$1:$1048576,MATCH(DATE(F$2,1,1),Hybrid!$A$1:$LI$1),FALSE) -> 9.4015406 | G15: =VLOOKUP($E15,Hybrid!$1:$1048576,MATCH(DATE(G$2,1,1),Hybrid!$A$1:$LI$1),FALSE) -> 12.64946 | H15: =VLOOKUP($E15,Hybrid!$1:$1048576,MATCH(DATE(H$2,1,1),Hybrid!$A$1:$LI$1),FALSE) -> 16.045371 | I15: =VLOOKUP($E15,Hybrid!$1:$1048576,MATCH(DATE(I$2,1,1),Hybrid!$A$1:$LI$1),FALSE) -> 19.522673 | J15: =VLOOKUP($E15,Hybrid!$1:$1048576,MATCH(DATE(J$2,1,1),Hybrid!$A$1:$LI$1),FALSE) -> 23.042086 | K15: =VLOOKUP($E15,Hybrid!$1:$1048576,MATCH(DATE(K$2,1,1),Hybrid!$A$1:$LI$1),FALSE) -> 26.581847 | L15: =VLOOKUP($E15,Hybrid!$1:$1048576,MATCH(DATE(L$2,1,1),Hybrid!$A$1:$LI$1),FALSE) -> 30.123211 | M15: =VLOOKUP($E15,Hybrid!$1:$1048576,MATCH(DATE(M$2,1,1),Hybrid!$A$1:$LI$1),FALSE) -> 33.659439 | ... BI15: =VLOOKUP($E15,Hybrid!$1:$1048576,MATCH(DATE(BI$2,1,1),Hybrid!$A$1:$LI$1),FALSE) -> 208.59138
D16: class D | E16: AUTO_cd_cele_2 | F16: =VLOOKUP($E16,Hybrid!$1:$1048576,MATCH(DATE(F$2,1,1),Hybrid!$A$1:$LI$1),FALSE) -> 5.7700713 | G16: =VLOOKUP($E16,Hybrid!$1:$1048576,MATCH(DATE(G$2,1,1),Hybrid!$A$1:$LI$1),FALSE) -> 7.539709 | H16: =VLOOKUP($E16,Hybrid!$1:$1048576,MATCH(DATE(H$2,1,1),Hybrid!$A$1:$LI$1),FALSE) -> 9.376567 | I16: =VLOOKUP($E16,Hybrid!$1:$1048576,MATCH(DATE(I$2,1,1),Hybrid!$A$1:$LI$1),FALSE) -> 11.237616 | J16: =VLOOKUP($E16,Hybrid!$1:$1048576,MATCH(DATE(J$2,1,1),Hybrid!$A$1:$LI$1),FALSE) -> 13.095884 | K16: =VLOOKUP($E16,Hybrid!$1:$1048576,MATCH(DATE(K$2,1,1),Hybrid!$A$1:$LI$1),FALSE) -> 14.934985 | L16: =VLOOKUP($E16,Hybrid!$1:$1048576,MATCH(DATE(L$2,1,1),Hybrid!$A$1:$LI$1),FALSE) -> 16.74128 | M16: =VLOOKUP($E16,Hybrid!$1:$1048576,MATCH(DATE(M$2,1,1),Hybrid!$A$1:$LI$1),FALSE) -> 18.508433 | ... BI16: =VLOOKUP($E16,Hybrid!$1:$1048576,MATCH(DATE(BI$2,1,1),Hybrid!$A$1:$LI$1),FALSE) -> 44.066291
D17: class E | E17: AUTO_ce_cele_2 | F17: =VLOOKUP($E17,Hybrid!$1:$1048576,MATCH(DATE(F$2,1,1),Hybrid!$A$1:$LI$1),FALSE) -> 3.4730441 | G17: =VLOOKUP($E17,Hybrid!$1:$1048576,MATCH(DATE(G$2,1,1),Hybrid!$A$1:$LI$1),FALSE) -> 4.5597211 | H17: =VLOOKUP($E17,Hybrid!$1:$1048576,MATCH(DATE(H$2,1,1),Hybrid!$A$1:$LI$1),FALSE) -> 5.6796747 | I17: =VLOOKUP($E17,Hybrid!$1:$1048576,MATCH(DATE(I$2,1,1),Hybrid!$A$1:$LI$1),FALSE) -> 6.8046307 | J17: =VLOOKUP($E17,Hybrid!$1:$1048576,MATCH(DATE(J$2,1,1),Hybrid!$A$1:$LI$1),FALSE) -> 7.9168848 | K17: =VLOOKUP($E17,Hybrid!$1:$1048576,MATCH(DATE(K$2,1,1),Hybrid!$A$1:$LI$1),FALSE) -> 9.0056411 | L17: =VLOOKUP($E17,Hybrid!$1:$1048576,MATCH(DATE(L$2,1,1),Hybrid!$A$1:$LI$1),FALSE) -> 10.062148 | M17: =VLOOKUP($E17,Hybrid!$1:$1048576,MATCH(DATE(M$2,1,1),Hybrid!$A$1:$LI$1),FALSE) -> 11.082284 | ... BI17: =VLOOKUP($E17,Hybrid!$1:$1048576,MATCH(DATE(BI$2,1,1),Hybrid!$A$1:$LI$1),FALSE) -> 17.644234
D18: class F | E18: AUTO_cf_cele_2 | F18: =VLOOKUP($E18,Hybrid!$1:$1048576,MATCH(DATE(F$2,1,1),Hybrid!$A$1:$LI$1),FALSE) -> 1.7251505 | G18: =VLOOKUP($E18,Hybrid!$1:$1048576,MATCH(DATE(G$2,1,1),Hybrid!$A$1:$LI$1),FALSE) -> 2.2406265 | H18: =VLOOKUP($E18,Hybrid!$1:$1048576,MATCH(DATE(H$2,1,1),Hybrid!$A$1:$LI$1),FALSE) -> 2.7588792 | I18: =VLOOKUP($E18,Hybrid!$1:$1048576,MATCH(DATE(I$2,1,1),Hybrid!$A$1:$LI$1),FALSE) -> 3.2632147 | J18: =VLOOKUP($E18,Hybrid!$1:$1048576,MATCH(DATE(J$2,1,1),Hybrid!$A$1:$LI$1),FALSE) -> 3.7434055 | K18: =VLOOKUP($E18,Hybrid!$1:$1048576,MATCH(DATE(K$2,1,1),Hybrid!$A$1:$LI$1),FALSE) -> 4.1934804 | L18: =VLOOKUP($E18,Hybrid!$1:$1048576,MATCH(DATE(L$2,1,1),Hybrid!$A$1:$LI$1),FALSE) -> 4.6092837 | M18: =VLOOKUP($E18,Hybrid!$1:$1048576,MATCH(DATE(M$2,1,1),Hybrid!$A$1:$LI$1),FALSE) -> 4.9893064 | ... BI18: =VLOOKUP($E18,Hybrid!$1:$1048576,MATCH(DATE(BI$2,1,1),Hybrid!$A$1:$LI$1),FALSE) -> 2.6545848
D19: class G | E19: AUTO_cg_cele_2 | F19: =VLOOKUP($E19,Hybrid!$1:$1048576,MATCH(DATE(F$2,1,1),Hybrid!$A$1:$LI$1),FALSE) -> 3.1066862 | G19: =VLOOKUP($E19,Hybrid!$1:$1048576,MATCH(DATE(G$2,1,1),Hybrid!$A$1:$LI$1),FALSE) -> 4.0661821 | H19: =VLOOKUP($E19,Hybrid!$1:$1048576,MATCH(DATE(H$2,1,1),Hybrid!$A$1:$LI$1),FALSE) -> 5.0099104 | I19: =VLOOKUP($E19,Hybrid!$1:$1048576,MATCH(DATE(I$2,1,1),Hybrid!$A$1:$LI$1),FALSE) -> 5.9033651 | J19: =VLOOKUP($E19,Hybrid!$1:$1048576,MATCH(DATE(J$2,1,1),Hybrid!$A$1:$LI$1),FALSE) -> 6.7267154 | K19: =VLOOKUP($E19,Hybrid!$1:$1048576,MATCH(DATE(K$2,1,1),Hybrid!$A$1:$LI$1),FALSE) -> 7.4697042 | L19: =VLOOKUP($E19,Hybrid!$1:$1048576,MATCH(DATE(L$2,1,1),Hybrid!$A$1:$LI$1),FALSE) -> 8.1267146 | M19: =VLOOKUP($E19,Hybrid!$1:$1048576,MATCH(DATE(M$2,1,1),Hybrid!$A$1:$LI$1),FALSE) -> 8.6975903 | ... BI19: =VLOOKUP($E19,Hybrid!$1:$1048576,MATCH(DATE(BI$2,1,1),Hybrid!$A$1:$LI$1),FALSE) -> 2.9989761
C20: GAS | E20: AUTO_cgas_2 | F20: =VLOOKUP($E20,Hybrid!$1:$1048576,MATCH(DATE(F$2,1,1),Hybrid!$A$1:$LI$1),FALSE) -> 1.936 | G20: =VLOOKUP($E20,Hybrid!$1:$1048576,MATCH(DATE(G$2,1,1),Hybrid!$A$1:$LI$1),FALSE) -> 1.989955 | H20: =VLOOKUP($E20,Hybrid!$1:$1048576,MATCH(DATE(H$2,1,1),Hybrid!$A$1:$LI$1),FALSE) -> 2.053118 | I20: =VLOOKUP($E20,Hybrid!$1:$1048576,MATCH(DATE(I$2,1,1),Hybrid!$A$1:$LI$1),FALSE) -> 2.121484 | J20: =VLOOKUP($E20,Hybrid!$1:$1048576,MATCH(DATE(J$2,1,1),Hybrid!$A$1:$LI$1),FALSE) -> 2.192522 | K20: =VLOOKUP($E20,Hybrid!$1:$1048576,MATCH(DATE(K$2,1,1),Hybrid!$A$1:$LI$1),FALSE) -> 2.2646966 | L20: =VLOOKUP($E20,Hybrid!$1:$1048576,MATCH(DATE(L$2,1,1),Hybrid!$A$1:$LI$1),FALSE) -> 2.3367676 | M20: =VLOOKUP($E20,Hybrid!$1:$1048576,MATCH(DATE(M$2,1,1),Hybrid!$A$1:$LI$1),FALSE) -> 2.4081888 | ... BI20: =VLOOKUP($E20,Hybrid!$1:$1048576,MATCH(DATE(BI$2,1,1),Hybrid!$A$1:$LI$1),FALSE) -> 4.405035
D21: class A | E21: AUTO_ca_cgas_2 | F21: =VLOOKUP($E21,Hybrid!$1:$1048576,MATCH(DATE(F$2,1,1),Hybrid!$A$1:$LI$1),FALSE) -> 0.4256817 | G21: =VLOOKUP($E21,Hybrid!$1:$1048576,MATCH(DATE(G$2,1,1),Hybrid!$A$1:$LI$1),FALSE) -> 0.44880661 | H21: =VLOOKUP($E21,Hybrid!$1:$1048576,MATCH(DATE(H$2,1,1),Hybrid!$A$1:$LI$1),FALSE) -> 0.47443858 | I21: =VLOOKUP($E21,Hybrid!$1:$1048576,MATCH(DATE(I$2,1,1),Hybrid!$A$1:$LI$1),FALSE) -> 0.50155776 | J21: =VLOOKUP($E21,Hybrid!$1:$1048576,MATCH(DATE(J$2,1,1),Hybrid!$A$1:$LI$1),FALSE) -> 0.52952317 | K21: =VLOOKUP($E21,Hybrid!$1:$1048576,MATCH(DATE(K$2,1,1),Hybrid!$A$1:$LI$1),FALSE) -> 0.55795126 | L21: =VLOOKUP($E21,Hybrid!$1:$1048576,MATCH(DATE(L$2,1,1),Hybrid!$A$1:$LI$1),FALSE) -> 0.58652048 | M21: =VLOOKUP($E21,Hybrid!$1:$1048576,MATCH(DATE(M$2,1,1),Hybrid!$A$1:$LI$1),FALSE) -> 0.61509618 | ... BI21: =VLOOKUP($E21,Hybrid!$1:$1048576,MATCH(DATE(BI$2,1,1),Hybrid!$A$1:$LI$1),FALSE) -> 1.7494387
D22: class B | E22: AUTO_cb_cgas_2 | F22: =VLOOKUP($E22,Hybrid!$1:$1048576,MATCH(DATE(F$2,1,1),Hybrid!$A$1:$LI$1),FALSE) -> 0.49500523 | G22: =VLOOKUP($E22,Hybrid!$1:$1048576,MATCH(DATE(G$2,1,1),Hybrid!$A$1:$LI$1),FALSE) -> 0.51176617 | H22: =VLOOKUP($E22,Hybrid!$1:$1048576,MATCH(DATE(H$2,1,1),Hybrid!$A$1:$LI$1),FALSE) -> 0.53119681 | I22: =VLOOKUP($E22,Hybrid!$1:$1048576,MATCH(DATE(I$2,1,1),Hybrid!$A$1:$LI$1),FALSE) -> 0.5522771 | J22: =VLOOKUP($E22,Hybrid!$1:$1048576,MATCH(DATE(J$2,1,1),Hybrid!$A$1:$LI$1),FALSE) -> 0.57435756 | K22: =VLOOKUP($E22,Hybrid!$1:$1048576,MATCH(DATE(K$2,1,1),Hybrid!$A$1:$LI$1),FALSE) -> 0.59704034 | L22: =VLOOKUP($E22,Hybrid!$1:$1048576,MATCH(DATE(L$2,1,1),Hybrid!$A$1:$LI$1),FALSE) -> 0.61999149 | M22: =VLOOKUP($E22,Hybrid!$1:$1048576,MATCH(DATE(M$2,1,1),Hybrid!$A$1:$LI$1),FALSE) -> 0.64305873 | ... BI22: =VLOOKUP($E22,Hybrid!$1:$1048576,MATCH(DATE(BI$2,1,1),Hybrid!$A$1:$LI$1),FALSE) -> 1.4351453
D23: class C | E23: AUTO_cc_cgas_2 | F23: =VLOOKUP($E23,Hybrid!$1:$1048576,MATCH(DATE(F$2,1,1),Hybrid!$A$1:$LI$1),FALSE) -> 0.40659852 | G23: =VLOOKUP($E23,Hybrid!$1:$1048576,MATCH(DATE(G$2,1,1),Hybrid!$A$1:$LI$1),FALSE) -> 0.41417205 | H23: =VLOOKUP($E23,Hybrid!$1:$1048576,MATCH(DATE(H$2,1,1),Hybrid!$A$1:$LI$1),FALSE) -> 0.42379232 | I23: =VLOOKUP($E23,Hybrid!$1:$1048576,MATCH(DATE(I$2,1,1),Hybrid!$A$1:$LI$1),FALSE) -> 0.43472434 | J23: =VLOOKUP($E23,Hybrid!$1:$1048576,MATCH(DATE(J$2,1,1),Hybrid!$A$1:$LI$1),FALSE) -> 0.44649452 | K23: =VLOOKUP($E23,Hybrid!$1:$1048576,MATCH(DATE(K$2,1,1),Hybrid!$A$1:$LI$1),FALSE) -> 0.45880666 | L23: =VLOOKUP($E23,Hybrid!$1:$1048576,MATCH(DATE(L$2,1,1),Hybrid!$A$1:$LI$1),FALSE) -> 0.47141196 | M23: =VLOOKUP($E23,Hybrid!$1:$1048576,MATCH(DATE(M$2,1,1),Hybrid!$A$1:$LI$1),FALSE) -> 0.48418896 | ... BI23: =VLOOKUP($E23,Hybrid!$1:$1048576,MATCH(DATE(BI$2,1,1),Hybrid!$A$1:$LI$1),FALSE) -> 0.85360253
D24: class D | E24: AUTO_cd_cgas_2 | F24: =VLOOKUP($E24,Hybrid!$1:$1048576,MATCH(DATE(F$2,1,1),Hybrid!$A$1:$LI$1),FALSE) -> 0.24954447 | G24: =VLOOKUP($E24,Hybrid!$1:$1048576,MATCH(DATE(G$2,1,1),Hybrid!$A$1:$LI$1),FALSE) -> 0.25215076 | H24: =VLOOKUP($E24,Hybrid!$1:$1048576,MATCH(DATE(H$2,1,1),Hybrid!$A$1:$LI$1),FALSE) -> 0.25585512 | I24: =VLOOKUP($E24,Hybrid!$1:$1048576,MATCH(DATE(I$2,1,1),Hybrid!$A$1:$LI$1),FALSE) -> 0.26021199 | J24: =VLOOKUP($E24,Hybrid!$1:$1048576,MATCH(DATE(J$2,1,1),Hybrid!$A$1:$LI$1),FALSE) -> 0.2649322 | K24: =VLOOKUP($E24,Hybrid!$1:$1048576,MATCH(DATE(K$2,1,1),Hybrid!$A$1:$LI$1),FALSE) -> 0.26983211 | L24: =VLOOKUP($E24,Hybrid!$1:$1048576,MATCH(DATE(L$2,1,1),Hybrid!$A$1:$LI$1),FALSE) -> 0.27476101 | M24: =VLOOKUP($E24,Hybrid!$1:$1048576,MATCH(DATE(M$2,1,1),Hybrid!$A$1:$LI$1),FALSE) -> 0.27964166 | ... BI24: =VLOOKUP($E24,Hybrid!$1:$1048576,MATCH(DATE(BI$2,1,1),Hybrid!$A$1:$LI$1),FALSE) -> 0.24984013
D25: class E | E25: AUTO_ce_cgas_2 | F25: =VLOOKUP($E25,Hybrid!$1:$1048576,MATCH(DATE(F$2,1,1),Hybrid!$A$1:$LI$1),FALSE) -> 0.15020247 | G25: =VLOOKUP($E25,Hybrid!$1:$1048576,MATCH(DATE(G$2,1,1),Hybrid!$A$1:$LI$1),FALSE) -> 0.15196857 | H25: =VLOOKUP($E25,Hybrid!$1:$1048576,MATCH(DATE(H$2,1,1),Hybrid!$A$1:$LI$1),FALSE) -> 0.15432596 | I25: =VLOOKUP($E25,Hybrid!$1:$1048576,MATCH(DATE(I$2,1,1),Hybrid!$A$1:$LI$1),FALSE) -> 0.15698498 | J25: =VLOOKUP($E25,Hybrid!$1:$1048576,MATCH(DATE(J$2,1,1),Hybrid!$A$1:$LI$1),FALSE) -> 0.15975872 | K25: =VLOOKUP($E25,Hybrid!$1:$1048576,MATCH(DATE(K$2,1,1),Hybrid!$A$1:$LI$1),FALSE) -> 0.16252934 | L25: =VLOOKUP($E25,Hybrid!$1:$1048576,MATCH(DATE(L$2,1,1),Hybrid!$A$1:$LI$1),FALSE) -> 0.165203 | M25: =VLOOKUP($E25,Hybrid!$1:$1048576,MATCH(DATE(M$2,1,1),Hybrid!$A$1:$LI$1),FALSE) -> 0.1677327 | ... BI25: =VLOOKUP($E25,Hybrid!$1:$1048576,MATCH(DATE(BI$2,1,1),Hybrid!$A$1:$LI$1),FALSE) -> 0.091405412
D26: class F | E26: AUTO_cf_cgas_2 | F26: =VLOOKUP($E26,Hybrid!$1:$1048576,MATCH(DATE(F$2,1,1),Hybrid!$A$1:$LI$1),FALSE) -> 0.074609436 | G26: =VLOOKUP($E26,Hybrid!$1:$1048576,MATCH(DATE(G$2,1,1),Hybrid!$A$1:$LI$1),FALSE) -> 0.075265529 | H26: =VLOOKUP($E26,Hybrid!$1:$1048576,MATCH(DATE(H$2,1,1),Hybrid!$A$1:$LI$1),FALSE) -> 0.07609655 | I26: =VLOOKUP($E26,Hybrid!$1:$1048576,MATCH(DATE(I$2,1,1),Hybrid!$A$1:$LI$1),FALSE) -> 0.076939006 | J26: =VLOOKUP($E26,Hybrid!$1:$1048576,MATCH(DATE(J$2,1,1),Hybrid!$A$1:$LI$1),FALSE) -> 0.077692043 | K26: =VLOOKUP($E26,Hybrid!$1:$1048576,MATCH(DATE(K$2,1,1),Hybrid!$A$1:$LI$1),FALSE) -> 0.078296485 | L26: =VLOOKUP($E26,Hybrid!$1:$1048576,MATCH(DATE(L$2,1,1),Hybrid!$A$1:$LI$1),FALSE) -> 0.07871185 | M26: =VLOOKUP($E26,Hybrid!$1:$1048576,MATCH(DATE(M$2,1,1),Hybrid!$A$1:$LI$1),FALSE) -> 0.078923392 | ... BI26: =VLOOKUP($E26,Hybrid!$1:$1048576,MATCH(DATE(BI$2,1,1),Hybrid!$A$1:$LI$1),FALSE) -> 0.012398183
D27: class G | E27: AUTO_cg_cgas_2 | F27: =VLOOKUP($E27,Hybrid!$1:$1048576,MATCH(DATE(F$2,1,1),Hybrid!$A$1:$LI$1),FALSE) -> 0.13435819 | G27: =VLOOKUP($E27,Hybrid!$1:$1048576,MATCH(DATE(G$2,1,1),Hybrid!$A$1:$LI$1),FALSE) -> 0.13582532 | H27: =VLOOKUP($E27,Hybrid!$1:$1048576,MATCH(DATE(H$2,1,1),Hybrid!$A$1:$LI$1),FALSE) -> 0.13741263 | I27: =VLOOKUP($E27,Hybrid!$1:$1048576,MATCH(DATE(I$2,1,1),Hybrid!$A$1:$LI$1),FALSE) -> 0.13878881 | J27: =VLOOKUP($E27,Hybrid!$1:$1048576,MATCH(DATE(J$2,1,1),Hybrid!$A$1:$LI$1),FALSE) -> 0.13976379 | K27: =VLOOKUP($E27,Hybrid!$1:$1048576,MATCH(DATE(K$2,1,1),Hybrid!$A$1:$LI$1),FALSE) -> 0.14024043 | L27: =VLOOKUP($E27,Hybrid!$1:$1048576,MATCH(DATE(L$2,1,1),Hybrid!$A$1:$LI$1),FALSE) -> 0.14016777 | M27: =VLOOKUP($E27,Hybrid!$1:$1048576,MATCH(DATE(M$2,1,1),Hybrid!$A$1:$LI$1),FALSE) -> 0.13954714 | ... BI27: =VLOOKUP($E27,Hybrid!$1:$1048576,MATCH(DATE(BI$2,1,1),Hybrid!$A$1:$LI$1),FALSE) -> 0.013204767
C28: TOTAL STOCK BASELINE | E28: AUTO_0 | F28: =VLOOKUP($E28,Hybrid!$1:$1048576,MATCH(DATE(F$2,1,1),Hybrid!$A$1:$LI$1),FALSE) -> 32317.941 | G28: =VLOOKUP($E28,Hybrid!$1:$1048576,MATCH(DATE(G$2,1,1),Hybrid!$A$1:$LI$1),FALSE) -> 31939.281 | H28: =VLOOKUP($E28,Hybrid!$1:$1048576,MATCH(DATE(H$2,1,1),Hybrid!$A$1:$LI$1),FALSE) -> 31767.456 | I28: =VLOOKUP($E28,Hybrid!$1:$1048576,MATCH(DATE(I$2,1,1),Hybrid!$A$1:$LI$1),FALSE) -> 31736.001 | J28: =VLOOKUP($E28,Hybrid!$1:$1048576,MATCH(DATE(J$2,1,1),Hybrid!$A$1:$LI$1),FALSE) -> 31800.975 | K28: =VLOOKUP($E28,Hybrid!$1:$1048576,MATCH(DATE(K$2,1,1),Hybrid!$A$1:$LI$1),FALSE) -> 31933.821 | L28: =VLOOKUP($E28,Hybrid!$1:$1048576,MATCH(DATE(L$2,1,1),Hybrid!$A$1:$LI$1),FALSE) -> 32112.092 | M28: =VLOOKUP($E28,Hybrid!$1:$1048576,MATCH(DATE(M$2,1,1),Hybrid!$A$1:$LI$1),FALSE) -> 32323.606 | ... BI28: =VLOOKUP($E28,Hybrid!$1:$1048576,MATCH(DATE(BI$2,1,1),Hybrid!$A$1:$LI$1),FALSE) -> 45357.122
C29: OIL | E29: AUTO_cfut_0 | F29: =VLOOKUP($E29,Hybrid!$1:$1048576,MATCH(DATE(F$2,1,1),Hybrid!$A$1:$LI$1),FALSE) -> 32271.24 | G29: =VLOOKUP($E29,Hybrid!$1:$1048576,MATCH(DATE(G$2,1,1),Hybrid!$A$1:$LI$1),FALSE) -> 31874.761 | H29: =VLOOKUP($E29,Hybrid!$1:$1048576,MATCH(DATE(H$2,1,1),Hybrid!$A$1:$LI$1),FALSE) -> 31684.176 | I29: =VLOOKUP($E29,Hybrid!$1:$1048576,MATCH(DATE(I$2,1,1),Hybrid!$A$1:$LI$1),FALSE) -> 31633.508 | J29: =VLOOKUP($E29,Hybrid!$1:$1048576,MATCH(DATE(J$2,1,1),Hybrid!$A$1:$LI$1),FALSE) -> 31679.119 | K29: =VLOOKUP($E29,Hybrid!$1:$1048576,MATCH(DATE(K$2,1,1),Hybrid!$A$1:$LI$1),FALSE) -> 31792.64 | L29: =VLOOKUP($E29,Hybrid!$1:$1048576,MATCH(DATE(L$2,1,1),Hybrid!$A$1:$LI$1),FALSE) -> 31951.768 | M29: =VLOOKUP($E29,Hybrid!$1:$1048576,MATCH(DATE(M$2,1,1),Hybrid!$A$1:$LI$1),FALSE) -> 32144.386 | ... BI29: =VLOOKUP($E29,Hybrid!$1:$1048576,MATCH(DATE(BI$2,1,1),Hybrid!$A$1:$LI$1),FALSE) -> 44408.96
D30: class A | E30: AUTO_ca_cfut_0 | F30: =VLOOKUP($E30,Hybrid!$1:$1048576,MATCH(DATE(F$2,1,1),Hybrid!$A$1:$LI$1),FALSE) -> 7095.7005 | G30: =VLOOKUP($E30,Hybrid!$1:$1048576,MATCH(DATE(G$2,1,1),Hybrid!$A$1:$LI$1),FALSE) -> 7145.1881 | H30: =VLOOKUP($E30,Hybrid!$1:$1048576,MATCH(DATE(H$2,1,1),Hybrid!$A$1:$LI$1),FALSE) -> 7246.0535 | I30: =VLOOKUP($E30,Hybrid!$1:$1048576,MATCH(DATE(I$2,1,1),Hybrid!$A$1:$LI$1),FALSE) -> 7381.6109 | J30: =VLOOKUP($E30,Hybrid!$1:$1048576,MATCH(DATE(J$2,1,1),Hybrid!$A$1:$LI$1),FALSE) -> 7540.773 | K30: =VLOOKUP($E30,Hybrid!$1:$1048576,MATCH(DATE(K$2,1,1),Hybrid!$A$1:$LI$1),FALSE) -> 7716.3455 | L30: =VLOOKUP($E30,Hybrid!$1:$1048576,MATCH(DATE(L$2,1,1),Hybrid!$A$1:$LI$1),FALSE) -> 7902.5358 | M30: =VLOOKUP($E30,Hybrid!$1:$1048576,MATCH(DATE(M$2,1,1),Hybrid!$A$1:$LI$1),FALSE) -> 8096.3143 | ... BI30: =VLOOKUP($E30,Hybrid!$1:$1048576,MATCH(DATE(BI$2,1,1),Hybrid!$A$1:$LI$1),FALSE) -> 17985.679
D31: class B | E31: AUTO_cb_cfut_0 | F31: =VLOOKUP($E31,Hybrid!$1:$1048576,MATCH(DATE(F$2,1,1),Hybrid!$A$1:$LI$1),FALSE) -> 8251.2564 | G31: =VLOOKUP($E31,Hybrid!$1:$1048576,MATCH(DATE(G$2,1,1),Hybrid!$A$1:$LI$1),FALSE) -> 8186.1345 | H31: =VLOOKUP($E31,Hybrid!$1:$1048576,MATCH(DATE(H$2,1,1),Hybrid!$A$1:$LI$1),FALSE) -> 8177.9675 | I31: =VLOOKUP($E31,Hybrid!$1:$1048576,MATCH(DATE(I$2,1,1),Hybrid!$A$1:$LI$1),FALSE) -> 8209.799 | J31: =VLOOKUP($E31,Hybrid!$1:$1048576,MATCH(DATE(J$2,1,1),Hybrid!$A$1:$LI$1),FALSE) -> 8270.2093 | K31: =VLOOKUP($E31,Hybrid!$1:$1048576,MATCH(DATE(K$2,1,1),Hybrid!$A$1:$LI$1),FALSE) -> 8351.6251 | L31: =VLOOKUP($E31,Hybrid!$1:$1048576,MATCH(DATE(L$2,1,1),Hybrid!$A$1:$LI$1),FALSE) -> 8447.9103 | M31: =VLOOKUP($E31,Hybrid!$1:$1048576,MATCH(DATE(M$2,1,1),Hybrid!$A$1:$LI$1),FALSE) -> 8555.634 | ... BI31: =VLOOKUP($E31,Hybrid!$1:$1048576,MATCH(DATE(BI$2,1,1),Hybrid!$A$1:$LI$1),FALSE) -> 14572.354
D32: class C | E32: AUTO_cc_cfut_0 | F32: =VLOOKUP($E32,Hybrid!$1:$1048576,MATCH(DATE(F$2,1,1),Hybrid!$A$1:$LI$1),FALSE) -> 6777.6025 | G32: =VLOOKUP($E32,Hybrid!$1:$1048576,MATCH(DATE(G$2,1,1),Hybrid!$A$1:$LI$1),FALSE) -> 6649.1114 | H32: =VLOOKUP($E32,Hybrid!$1:$1048576,MATCH(DATE(H$2,1,1),Hybrid!$A$1:$LI$1),FALSE) -> 6565.7579 | I32: =VLOOKUP($E32,Hybrid!$1:$1048576,MATCH(DATE(I$2,1,1),Hybrid!$A$1:$LI$1),FALSE) -> 6515.1295 | J32: =VLOOKUP($E32,Hybrid!$1:$1048576,MATCH(DATE(J$2,1,1),Hybrid!$A$1:$LI$1),FALSE) -> 6488.7622 | K32: =VLOOKUP($E32,Hybrid!$1:$1048576,MATCH(DATE(K$2,1,1),Hybrid!$A$1:$LI$1),FALSE) -> 6480.9324 | L32: =VLOOKUP($E32,Hybrid!$1:$1048576,MATCH(DATE(L$2,1,1),Hybrid!$A$1:$LI$1),FALSE) -> 6486.977 | M32: =VLOOKUP($E32,Hybrid!$1:$1048576,MATCH(DATE(M$2,1,1),Hybrid!$A$1:$LI$1),FALSE) -> 6504.1444 | ... BI32: =VLOOKUP($E32,Hybrid!$1:$1048576,MATCH(DATE(BI$2,1,1),Hybrid!$A$1:$LI$1),FALSE) -> 8555.5879
D33: class D | E33: AUTO_cd_cfut_0 | F33: =VLOOKUP($E33,Hybrid!$1:$1048576,MATCH(DATE(F$2,1,1),Hybrid!$A$1:$LI$1),FALSE) -> 4159.6639 | G33: =VLOOKUP($E33,Hybrid!$1:$1048576,MATCH(DATE(G$2,1,1),Hybrid!$A$1:$LI$1),FALSE) -> 4055.93 | H33: =VLOOKUP($E33,Hybrid!$1:$1048576,MATCH(DATE(H$2,1,1),Hybrid!$A$1:$LI$1),FALSE) -> 3977.7672 | I33: =VLOOKUP($E33,Hybrid!$1:$1048576,MATCH(DATE(I$2,1,1),Hybrid!$A$1:$LI$1),FALSE) -> 3917.6933 | J33: =VLOOKUP($E33,Hybrid!$1:$1048576,MATCH(DATE(J$2,1,1),Hybrid!$A$1:$LI$1),FALSE) -> 3870.637 | K33: =VLOOKUP($E33,Hybrid!$1:$1048576,MATCH(DATE(K$2,1,1),Hybrid!$A$1:$LI$1),FALSE) -> 3833.1759 | L33: =VLOOKUP($E33,Hybrid!$1:$1048576,MATCH(DATE(L$2,1,1),Hybrid!$A$1:$LI$1),FALSE) -> 3802.5754 | M33: =VLOOKUP($E33,Hybrid!$1:$1048576,MATCH(DATE(M$2,1,1),Hybrid!$A$1:$LI$1),FALSE) -> 3777.1955 | ... BI33: =VLOOKUP($E33,Hybrid!$1:$1048576,MATCH(DATE(BI$2,1,1),Hybrid!$A$1:$LI$1),FALSE) -> 2329.2454
D34: class E | E34: AUTO_ce_cfut_0 | F34: =VLOOKUP($E34,Hybrid!$1:$1048576,MATCH(DATE(F$2,1,1),Hybrid!$A$1:$LI$1),FALSE) -> 2503.7292 | G34: =VLOOKUP($E34,Hybrid!$1:$1048576,MATCH(DATE(G$2,1,1),Hybrid!$A$1:$LI$1),FALSE) -> 2443.5756 | H34: =VLOOKUP($E34,Hybrid!$1:$1048576,MATCH(DATE(H$2,1,1),Hybrid!$A$1:$LI$1),FALSE) -> 2397.7907 | I34: =VLOOKUP($E34,Hybrid!$1:$1048576,MATCH(DATE(I$2,1,1),Hybrid!$A$1:$LI$1),FALSE) -> 2361.5943 | J34: =VLOOKUP($E34,Hybrid!$1:$1048576,MATCH(DATE(J$2,1,1),Hybrid!$A$1:$LI$1),FALSE) -> 2331.8075 | K34: =VLOOKUP($E34,Hybrid!$1:$1048576,MATCH(DATE(K$2,1,1),Hybrid!$A$1:$LI$1),FALSE) -> 2306.3318 | L34: =VLOOKUP($E34,Hybrid!$1:$1048576,MATCH(DATE(L$2,1,1),Hybrid!$A$1:$LI$1),FALSE) -> 2283.54 | M34: =VLOOKUP($E34,Hybrid!$1:$1048576,MATCH(DATE(M$2,1,1),Hybrid!$A$1:$LI$1),FALSE) -> 2262.4909 | ... BI34: =VLOOKUP($E34,Hybrid!$1:$1048576,MATCH(DATE(BI$2,1,1),Hybrid!$A$1:$LI$1),FALSE) -> 797.65346
D35: class F | E35: AUTO_cf_cfut_0 | F35: =VLOOKUP($E35,Hybrid!$1:$1048576,MATCH(DATE(F$2,1,1),Hybrid!$A$1:$LI$1),FALSE) -> 1243.6668 | G35: =VLOOKUP($E35,Hybrid!$1:$1048576,MATCH(DATE(G$2,1,1),Hybrid!$A$1:$LI$1),FALSE) -> 1210.9489 | H35: =VLOOKUP($E35,Hybrid!$1:$1048576,MATCH(DATE(H$2,1,1),Hybrid!$A$1:$LI$1),FALSE) -> 1183.6826 | I35: =VLOOKUP($E35,Hybrid!$1:$1048576,MATCH(DATE(I$2,1,1),Hybrid!$A$1:$LI$1),FALSE) -> 1159.2757 | J35: =VLOOKUP($E35,Hybrid!$1:$1048576,MATCH(DATE(J$2,1,1),Hybrid!$A$1:$LI$1),FALSE) -> 1136.133 | K35: =VLOOKUP($E35,Hybrid!$1:$1048576,MATCH(DATE(K$2,1,1),Hybrid!$A$1:$LI$1),FALSE) -> 1113.3057 | L35: =VLOOKUP($E35,Hybrid!$1:$1048576,MATCH(DATE(L$2,1,1),Hybrid!$A$1:$LI$1),FALSE) -> 1090.158 | M35: =VLOOKUP($E35,Hybrid!$1:$1048576,MATCH(DATE(M$2,1,1),Hybrid!$A$1:$LI$1),FALSE) -> 1066.4084 | ... BI35: =VLOOKUP($E35,Hybrid!$1:$1048576,MATCH(DATE(BI$2,1,1),Hybrid!$A$1:$LI$1),FALSE) -> 86.016548
D36: class G | E36: AUTO_cg_cfut_0 | F36: =VLOOKUP($E36,Hybrid!$1:$1048576,MATCH(DATE(F$2,1,1),Hybrid!$A$1:$LI$1),FALSE) -> 2239.6206 | G36: =VLOOKUP($E36,Hybrid!$1:$1048576,MATCH(DATE(G$2,1,1),Hybrid!$A$1:$LI$1),FALSE) -> 2183.8729 | H36: =VLOOKUP($E36,Hybrid!$1:$1048576,MATCH(DATE(H$2,1,1),Hybrid!$A$1:$LI$1),FALSE) -> 2135.1571 | I36: =VLOOKUP($E36,Hybrid!$1:$1048576,MATCH(DATE(I$2,1,1),Hybrid!$A$1:$LI$1),FALSE) -> 2088.4049 | J36: =VLOOKUP($E36,Hybrid!$1:$1048576,MATCH(DATE(J$2,1,1),Hybrid!$A$1:$LI$1),FALSE) -> 2040.7976 | K36: =VLOOKUP($E36,Hybrid!$1:$1048576,MATCH(DATE(K$2,1,1),Hybrid!$A$1:$LI$1),FALSE) -> 1990.924 | L36: =VLOOKUP($E36,Hybrid!$1:$1048576,MATCH(DATE(L$2,1,1),Hybrid!$A$1:$LI$1),FALSE) -> 1938.0714 | M36: =VLOOKUP($E36,Hybrid!$1:$1048576,MATCH(DATE(M$2,1,1),Hybrid!$A$1:$LI$1),FALSE) -> 1882.1987 | ... BI36: =VLOOKUP($E36,Hybrid!$1:$1048576,MATCH(DATE(BI$2,1,1),Hybrid!$A$1:$LI$1),FALSE) -> 82.423488
C37: ELEC | E37: AUTO_cele_0 | F37: =VLOOKUP($E37,Hybrid!$1:$1048576,MATCH(DATE(F$2,1,1),Hybrid!$A$1:$LI$1),FALSE) -> 44.765 | G37: =VLOOKUP($E37,Hybrid!$1:$1048576,MATCH(DATE(G$2,1,1),Hybrid!$A$1:$LI$1),FALSE) -> 62.527371 | H37: =VLOOKUP($E37,Hybrid!$1:$1048576,MATCH(DATE(H$2,1,1),Hybrid!$A$1:$LI$1),FALSE) -> 81.219026 | I37: =VLOOKUP($E37,Hybrid!$1:$1048576,MATCH(DATE(I$2,1,1),Hybrid!$A$1:$LI$1),FALSE) -> 100.35871 | J37: =VLOOKUP($E37,Hybrid!$1:$1048576,MATCH(DATE(J$2,1,1),Hybrid!$A$1:$LI$1),FALSE) -> 119.64368 | K37: =VLOOKUP($E37,Hybrid!$1:$1048576,MATCH(DATE(K$2,1,1),Hybrid!$A$1:$LI$1),FALSE) -> 138.89068 | L37: =VLOOKUP($E37,Hybrid!$1:$1048576,MATCH(DATE(L$2,1,1),Hybrid!$A$1:$LI$1),FALSE) -> 157.95549 | M37: =VLOOKUP($E37,Hybrid!$1:$1048576,MATCH(DATE(M$2,1,1),Hybrid!$A$1:$LI$1),FALSE) -> 176.77435 | ... BI37: =VLOOKUP($E37,Hybrid!$1:$1048576,MATCH(DATE(BI$2,1,1),Hybrid!$A$1:$LI$1),FALSE) -> 943.63486
D38: class A | E38: AUTO_ca_cele_0 | F38: =VLOOKUP($E38,Hybrid!$1:$1048576,MATCH(DATE(F$2,1,1),Hybrid!$A$1:$LI$1),FALSE) -> 9.8427899 | G38: =VLOOKUP($E38,Hybrid!$1:$1048576,MATCH(DATE(G$2,1,1),Hybrid!$A$1:$LI$1),FALSE) -> 15.012032 | H38: =VLOOKUP($E38,Hybrid!$1:$1048576,MATCH(DATE(H$2,1,1),Hybrid!$A$1:$LI$1),FALSE) -> 20.491657 | I38: =VLOOKUP($E38,Hybrid!$1:$1048576,MATCH(DATE(I$2,1,1),Hybrid!$A$1:$LI$1),FALSE) -> 26.157428 | J38: =VLOOKUP($E38,Hybrid!$1:$1048576,MATCH(DATE(J$2,1,1),Hybrid!$A$1:$LI$1),FALSE) -> 31.929987 | K38: =VLOOKUP($E38,Hybrid!$1:$1048576,MATCH(DATE(K$2,1,1),Hybrid!$A$1:$LI$1),FALSE) -> 37.760552 | L38: =VLOOKUP($E38,Hybrid!$1:$1048576,MATCH(DATE(L$2,1,1),Hybrid!$A$1:$LI$1),FALSE) -> 43.608929 | M38: =VLOOKUP($E38,Hybrid!$1:$1048576,MATCH(DATE(M$2,1,1),Hybrid!$A$1:$LI$1),FALSE) -> 49.456913 | ... BI38: =VLOOKUP($E38,Hybrid!$1:$1048576,MATCH(DATE(BI$2,1,1),Hybrid!$A$1:$LI$1),FALSE) -> 369.44515
D39: class B | E39: AUTO_cb_cele_0 | F39: =VLOOKUP($E39,Hybrid!$1:$1048576,MATCH(DATE(F$2,1,1),Hybrid!$A$1:$LI$1),FALSE) -> 11.445717 | G39: =VLOOKUP($E39,Hybrid!$1:$1048576,MATCH(DATE(G$2,1,1),Hybrid!$A$1:$LI$1),FALSE) -> 16.322968 | H39: =VLOOKUP($E39,Hybrid!$1:$1048576,MATCH(DATE(H$2,1,1),Hybrid!$A$1:$LI$1),FALSE) -> 21.491824 | I39: =VLOOKUP($E39,Hybrid!$1:$1048576,MATCH(DATE(I$2,1,1),Hybrid!$A$1:$LI$1),FALSE) -> 26.830588 | J39: =VLOOKUP($E39,Hybrid!$1:$1048576,MATCH(DATE(J$2,1,1),Hybrid!$A$1:$LI$1),FALSE) -> 32.261549 | K39: =VLOOKUP($E39,Hybrid!$1:$1048576,MATCH(DATE(K$2,1,1),Hybrid!$A$1:$LI$1),FALSE) -> 37.736755 | L39: =VLOOKUP($E39,Hybrid!$1:$1048576,MATCH(DATE(L$2,1,1),Hybrid!$A$1:$LI$1),FALSE) -> 43.216769 | M39: =VLOOKUP($E39,Hybrid!$1:$1048576,MATCH(DATE(M$2,1,1),Hybrid!$A$1:$LI$1),FALSE) -> 48.683248 | ... BI39: =VLOOKUP($E39,Hybrid!$1:$1048576,MATCH(DATE(BI$2,1,1),Hybrid!$A$1:$LI$1),FALSE) -> 311.85698
D40: class C | E40: AUTO_cc_cele_0 | F40: =VLOOKUP($E40,Hybrid!$1:$1048576,MATCH(DATE(F$2,1,1),Hybrid!$A$1:$LI$1),FALSE) -> 9.4015406 | G40: =VLOOKUP($E40,Hybrid!$1:$1048576,MATCH(DATE(G$2,1,1),Hybrid!$A$1:$LI$1),FALSE) -> 12.714483 | H40: =VLOOKUP($E40,Hybrid!$1:$1048576,MATCH(DATE(H$2,1,1),Hybrid!$A$1:$LI$1),FALSE) -> 16.225058 | I40: =VLOOKUP($E40,Hybrid!$1:$1048576,MATCH(DATE(I$2,1,1),Hybrid!$A$1:$LI$1),FALSE) -> 19.847384 | J40: =VLOOKUP($E40,Hybrid!$1:$1048576,MATCH(DATE(J$2,1,1),Hybrid!$A$1:$LI$1),FALSE) -> 23.526649 | K40: =VLOOKUP($E40,Hybrid!$1:$1048576,MATCH(DATE(K$2,1,1),Hybrid!$A$1:$LI$1),FALSE) -> 27.228932 | L40: =VLOOKUP($E40,Hybrid!$1:$1048576,MATCH(DATE(L$2,1,1),Hybrid!$A$1:$LI$1),FALSE) -> 30.926392 | M40: =VLOOKUP($E40,Hybrid!$1:$1048576,MATCH(DATE(M$2,1,1),Hybrid!$A$1:$LI$1),FALSE) -> 34.605791 | ... BI40: =VLOOKUP($E40,Hybrid!$1:$1048576,MATCH(DATE(BI$2,1,1),Hybrid!$A$1:$LI$1),FALSE) -> 189.86671
D41: class D | E41: AUTO_cd_cele_0 | F41: =VLOOKUP($E41,Hybrid!$1:$1048576,MATCH(DATE(F$2,1,1),Hybrid!$A$1:$LI$1),FALSE) -> 5.7700713 | G41: =VLOOKUP($E41,Hybrid!$1:$1048576,MATCH(DATE(G$2,1,1),Hybrid!$A$1:$LI$1),FALSE) -> 7.5724919 | H41: =VLOOKUP($E41,Hybrid!$1:$1048576,MATCH(DATE(H$2,1,1),Hybrid!$A$1:$LI$1),FALSE) -> 9.4657033 | I41: =VLOOKUP($E41,Hybrid!$1:$1048576,MATCH(DATE(I$2,1,1),Hybrid!$A$1:$LI$1),FALSE) -> 11.396266 | J41: =VLOOKUP($E41,Hybrid!$1:$1048576,MATCH(DATE(J$2,1,1),Hybrid!$A$1:$LI$1),FALSE) -> 13.329768 | K41: =VLOOKUP($E41,Hybrid!$1:$1048576,MATCH(DATE(K$2,1,1),Hybrid!$A$1:$LI$1),FALSE) -> 15.244613 | L41: =VLOOKUP($E41,Hybrid!$1:$1048576,MATCH(DATE(L$2,1,1),Hybrid!$A$1:$LI$1),FALSE) -> 17.123719 | M41: =VLOOKUP($E41,Hybrid!$1:$1048576,MATCH(DATE(M$2,1,1),Hybrid!$A$1:$LI$1),FALSE) -> 18.95863 | ... BI41: =VLOOKUP($E41,Hybrid!$1:$1048576,MATCH(DATE(BI$2,1,1),Hybrid!$A$1:$LI$1),FALSE) -> 48.123494
D42: class E | E42: AUTO_ce_cele_0 | F42: =VLOOKUP($E42,Hybrid!$1:$1048576,MATCH(DATE(F$2,1,1),Hybrid!$A$1:$LI$1),FALSE) -> 3.4730441 | G42: =VLOOKUP($E42,Hybrid!$1:$1048576,MATCH(DATE(G$2,1,1),Hybrid!$A$1:$LI$1),FALSE) -> 4.5791175 | H42: =VLOOKUP($E42,Hybrid!$1:$1048576,MATCH(DATE(H$2,1,1),Hybrid!$A$1:$LI$1),FALSE) -> 5.7313471 | I42: =VLOOKUP($E42,Hybrid!$1:$1048576,MATCH(DATE(I$2,1,1),Hybrid!$A$1:$LI$1),FALSE) -> 6.8947232 | J42: =VLOOKUP($E42,Hybrid!$1:$1048576,MATCH(DATE(J$2,1,1),Hybrid!$A$1:$LI$1),FALSE) -> 8.0469704 | K42: =VLOOKUP($E42,Hybrid!$1:$1048576,MATCH(DATE(K$2,1,1),Hybrid!$A$1:$LI$1),FALSE) -> 9.1742724 | L42: =VLOOKUP($E42,Hybrid!$1:$1048576,MATCH(DATE(L$2,1,1),Hybrid!$A$1:$LI$1),FALSE) -> 10.266017 | M42: =VLOOKUP($E42,Hybrid!$1:$1048576,MATCH(DATE(M$2,1,1),Hybrid!$A$1:$LI$1),FALSE) -> 11.317029 | ... BI42: =VLOOKUP($E42,Hybrid!$1:$1048576,MATCH(DATE(BI$2,1,1),Hybrid!$A$1:$LI$1),FALSE) -> 18.657326
D43: class F | E43: AUTO_cf_cele_0 | F43: =VLOOKUP($E43,Hybrid!$1:$1048576,MATCH(DATE(F$2,1,1),Hybrid!$A$1:$LI$1),FALSE) -> 1.7251505 | G43: =VLOOKUP($E43,Hybrid!$1:$1048576,MATCH(DATE(G$2,1,1),Hybrid!$A$1:$LI$1),FALSE) -> 2.2482443 | H43: =VLOOKUP($E43,Hybrid!$1:$1048576,MATCH(DATE(H$2,1,1),Hybrid!$A$1:$LI$1),FALSE) -> 2.7774999 | I43: =VLOOKUP($E43,Hybrid!$1:$1048576,MATCH(DATE(I$2,1,1),Hybrid!$A$1:$LI$1),FALSE) -> 3.2928145 | J43: =VLOOKUP($E43,Hybrid!$1:$1048576,MATCH(DATE(J$2,1,1),Hybrid!$A$1:$LI$1),FALSE) -> 3.7822146 | K43: =VLOOKUP($E43,Hybrid!$1:$1048576,MATCH(DATE(K$2,1,1),Hybrid!$A$1:$LI$1),FALSE) -> 4.2389796 | L43: =VLOOKUP($E43,Hybrid!$1:$1048576,MATCH(DATE(L$2,1,1),Hybrid!$A$1:$LI$1),FALSE) -> 4.6588006 | M43: =VLOOKUP($E43,Hybrid!$1:$1048576,MATCH(DATE(M$2,1,1),Hybrid!$A$1:$LI$1),FALSE) -> 5.0403093 | ... BI43: =VLOOKUP($E43,Hybrid!$1:$1048576,MATCH(DATE(BI$2,1,1),Hybrid!$A$1:$LI$1),FALSE) -> 2.7249537
D44: class G | E44: AUTO_cg_cele_0 | F44: =VLOOKUP($E44,Hybrid!$1:$1048576,MATCH(DATE(F$2,1,1),Hybrid!$A$1:$LI$1),FALSE) -> 3.1066862 | G44: =VLOOKUP($E44,Hybrid!$1:$1048576,MATCH(DATE(G$2,1,1),Hybrid!$A$1:$LI$1),FALSE) -> 4.0780346 | H44: =VLOOKUP($E44,Hybrid!$1:$1048576,MATCH(DATE(H$2,1,1),Hybrid!$A$1:$LI$1),FALSE) -> 5.0359358 | I44: =VLOOKUP($E44,Hybrid!$1:$1048576,MATCH(DATE(I$2,1,1),Hybrid!$A$1:$LI$1),FALSE) -> 5.9395011 | J44: =VLOOKUP($E44,Hybrid!$1:$1048576,MATCH(DATE(J$2,1,1),Hybrid!$A$1:$LI$1),FALSE) -> 6.7665366 | K44: =VLOOKUP($E44,Hybrid!$1:$1048576,MATCH(DATE(K$2,1,1),Hybrid!$A$1:$LI$1),FALSE) -> 7.5065764 | L44: =VLOOKUP($E44,Hybrid!$1:$1048576,MATCH(DATE(L$2,1,1),Hybrid!$A$1:$LI$1),FALSE) -> 8.1548645 | M44: =VLOOKUP($E44,Hybrid!$1:$1048576,MATCH(DATE(M$2,1,1),Hybrid!$A$1:$LI$1),FALSE) -> 8.7124313 | ... BI44: =VLOOKUP($E44,Hybrid!$1:$1048576,MATCH(DATE(BI$2,1,1),Hybrid!$A$1:$LI$1),FALSE) -> 2.9602536
C45: GAS | E45: AUTO_cgas_0 | F45: =VLOOKUP($E45,Hybrid!$1:$1048576,MATCH(DATE(F$2,1,1),Hybrid!$A$1:$LI$1),FALSE) -> 1.936 | G45: =VLOOKUP($E45,Hybrid!$1:$1048576,MATCH(DATE(G$2,1,1),Hybrid!$A$1:$LI$1),FALSE) -> 1.992675 | H45: =VLOOKUP($E45,Hybrid!$1:$1048576,MATCH(DATE(H$2,1,1),Hybrid!$A$1:$LI$1),FALSE) -> 2.0605131 | I45: =VLOOKUP($E45,Hybrid!$1:$1048576,MATCH(DATE(I$2,1,1),Hybrid!$A$1:$LI$1),FALSE) -> 2.1346197 | J45: =VLOOKUP($E45,Hybrid!$1:$1048576,MATCH(DATE(J$2,1,1),Hybrid!$A$1:$LI$1),FALSE) -> 2.2118521 | K45: =VLOOKUP($E45,Hybrid!$1:$1048576,MATCH(DATE(K$2,1,1),Hybrid!$A$1:$LI$1),FALSE) -> 2.2902607 | L45: =VLOOKUP($E45,Hybrid!$1:$1048576,MATCH(DATE(L$2,1,1),Hybrid!$A$1:$LI$1),FALSE) -> 2.3683425 | M45: =VLOOKUP($E45,Hybrid!$1:$1048576,MATCH(DATE(M$2,1,1),Hybrid!$A$1:$LI$1),FALSE) -> 2.4453981 | ... BI45: =VLOOKUP($E45,Hybrid!$1:$1048576,MATCH(DATE(BI$2,1,1),Hybrid!$A$1:$LI$1),FALSE) -> 4.5277336
D46: class A | E46: AUTO_ca_cgas_0 | F46: =VLOOKUP($E46,Hybrid!$1:$1048576,MATCH(DATE(F$2,1,1),Hybrid!$A$1:$LI$1),FALSE) -> 0.4256817 | G46: =VLOOKUP($E46,Hybrid!$1:$1048576,MATCH(DATE(G$2,1,1),Hybrid!$A$1:$LI$1),FALSE) -> 0.44962451 | H46: =VLOOKUP($E46,Hybrid!$1:$1048576,MATCH(DATE(H$2,1,1),Hybrid!$A$1:$LI$1),FALSE) -> 0.47671074 | I46: =VLOOKUP($E46,Hybrid!$1:$1048576,MATCH(DATE(I$2,1,1),Hybrid!$A$1:$LI$1),FALSE) -> 0.50567803 | J46: =VLOOKUP($E46,Hybrid!$1:$1048576,MATCH(DATE(J$2,1,1),Hybrid!$A$1:$LI$1),FALSE) -> 0.53570417 | K46: =VLOOKUP($E46,Hybrid!$1:$1048576,MATCH(DATE(K$2,1,1),Hybrid!$A$1:$LI$1),FALSE) -> 0.5662729 | L46: =VLOOKUP($E46,Hybrid!$1:$1048576,MATCH(DATE(L$2,1,1),Hybrid!$A$1:$LI$1),FALSE) -> 0.59697096 | M46: =VLOOKUP($E46,Hybrid!$1:$1048576,MATCH(DATE(M$2,1,1),Hybrid!$A$1:$LI$1),FALSE) -> 0.62760516 | ... BI46: =VLOOKUP($E46,Hybrid!$1:$1048576,MATCH(DATE(BI$2,1,1),Hybrid!$A$1:$LI$1),FALSE) -> 1.8060573
D47: class B | E47: AUTO_cb_cgas_0 | F47: =VLOOKUP($E47,Hybrid!$1:$1048576,MATCH(DATE(F$2,1,1),Hybrid!$A$1:$LI$1),FALSE) -> 0.49500523 | G47: =VLOOKUP($E47,Hybrid!$1:$1048576,MATCH(DATE(G$2,1,1),Hybrid!$A$1:$LI$1),FALSE) -> 0.51254167 | H47: =VLOOKUP($E47,Hybrid!$1:$1048576,MATCH(DATE(H$2,1,1),Hybrid!$A$1:$LI$1),FALSE) -> 0.53334118 | I47: =VLOOKUP($E47,Hybrid!$1:$1048576,MATCH(DATE(I$2,1,1),Hybrid!$A$1:$LI$1),FALSE) -> 0.55614764 | J47: =VLOOKUP($E47,Hybrid!$1:$1048576,MATCH(DATE(J$2,1,1),Hybrid!$A$1:$LI$1),FALSE) -> 0.58013773 | K47: =VLOOKUP($E47,Hybrid!$1:$1048576,MATCH(DATE(K$2,1,1),Hybrid!$A$1:$LI$1),FALSE) -> 0.60478809 | L47: =VLOOKUP($E47,Hybrid!$1:$1048576,MATCH(DATE(L$2,1,1),Hybrid!$A$1:$LI$1),FALSE) -> 0.62967928 | M47: =VLOOKUP($E47,Hybrid!$1:$1048576,MATCH(DATE(M$2,1,1),Hybrid!$A$1:$LI$1),FALSE) -> 0.65460523 | ... BI47: =VLOOKUP($E47,Hybrid!$1:$1048576,MATCH(DATE(BI$2,1,1),Hybrid!$A$1:$LI$1),FALSE) -> 1.477753
D48: class C | E48: AUTO_cc_cgas_0 | F48: =VLOOKUP($E48,Hybrid!$1:$1048576,MATCH(DATE(F$2,1,1),Hybrid!$A$1:$LI$1),FALSE) -> 0.40659852 | G48: =VLOOKUP($E48,Hybrid!$1:$1048576,MATCH(DATE(G$2,1,1),Hybrid!$A$1:$LI$1),FALSE) -> 0.4147022 | H48: =VLOOKUP($E48,Hybrid!$1:$1048576,MATCH(DATE(H$2,1,1),Hybrid!$A$1:$LI$1),FALSE) -> 0.4252514 | I48: =VLOOKUP($E48,Hybrid!$1:$1048576,MATCH(DATE(I$2,1,1),Hybrid!$A$1:$LI$1),FALSE) -> 0.43734559 | J48: =VLOOKUP($E48,Hybrid!$1:$1048576,MATCH(DATE(J$2,1,1),Hybrid!$A$1:$LI$1),FALSE) -> 0.45039109 | K48: =VLOOKUP($E48,Hybrid!$1:$1048576,MATCH(DATE(K$2,1,1),Hybrid!$A$1:$LI$1),FALSE) -> 0.46400622 | L48: =VLOOKUP($E48,Hybrid!$1:$1048576,MATCH(DATE(L$2,1,1),Hybrid!$A$1:$LI$1),FALSE) -> 0.47788483 | M48: =VLOOKUP($E48,Hybrid!$1:$1048576,MATCH(DATE(M$2,1,1),Hybrid!$A$1:$LI$1),FALSE) -> 0.49186996 | ... BI48: =VLOOKUP($E48,Hybrid!$1:$1048576,MATCH(DATE(BI$2,1,1),Hybrid!$A$1:$LI$1),FALSE) -> 0.87670987
D49: class D | E49: AUTO_cd_cgas_0 | F49: =VLOOKUP($E49,Hybrid!$1:$1048576,MATCH(DATE(F$2,1,1),Hybrid!$A$1:$LI$1),FALSE) -> 0.24954447 | G49: =VLOOKUP($E49,Hybrid!$1:$1048576,MATCH(DATE(G$2,1,1),Hybrid!$A$1:$LI$1),FALSE) -> 0.25242828 | H49: =VLOOKUP($E49,Hybrid!$1:$1048576,MATCH(DATE(H$2,1,1),Hybrid!$A$1:$LI$1),FALSE) -> 0.25660192 | I49: =VLOOKUP($E49,Hybrid!$1:$1048576,MATCH(DATE(I$2,1,1),Hybrid!$A$1:$LI$1),FALSE) -> 0.26152336 | J49: =VLOOKUP($E49,Hybrid!$1:$1048576,MATCH(DATE(J$2,1,1),Hybrid!$A$1:$LI$1),FALSE) -> 0.26683808 | K49: =VLOOKUP($E49,Hybrid!$1:$1048576,MATCH(DATE(K$2,1,1),Hybrid!$A$1:$LI$1),FALSE) -> 0.27231909 | L49: =VLOOKUP($E49,Hybrid!$1:$1048576,MATCH(DATE(L$2,1,1),Hybrid!$A$1:$LI$1),FALSE) -> 0.27778898 | M49: =VLOOKUP($E49,Hybrid!$1:$1048576,MATCH(DATE(M$2,1,1),Hybrid!$A$1:$LI$1),FALSE) -> 0.28315554 | ... BI49: =VLOOKUP($E49,Hybrid!$1:$1048576,MATCH(DATE(BI$2,1,1),Hybrid!$A$1:$LI$1),FALSE) -> 0.25138283
D50: class E | E50: AUTO_ce_cgas_0 | F50: =VLOOKUP($E50,Hybrid!$1:$1048576,MATCH(DATE(F$2,1,1),Hybrid!$A$1:$LI$1),FALSE) -> 0.15020247 | G50: =VLOOKUP($E50,Hybrid!$1:$1048576,MATCH(DATE(G$2,1,1),Hybrid!$A$1:$LI$1),FALSE) -> 0.15213017 | H50: =VLOOKUP($E50,Hybrid!$1:$1048576,MATCH(DATE(H$2,1,1),Hybrid!$A$1:$LI$1),FALSE) -> 0.15475126 | I50: =VLOOKUP($E50,Hybrid!$1:$1048576,MATCH(DATE(I$2,1,1),Hybrid!$A$1:$LI$1),FALSE) -> 0.15771474 | J50: =VLOOKUP($E50,Hybrid!$1:$1048576,MATCH(DATE(J$2,1,1),Hybrid!$A$1:$LI$1),FALSE) -> 0.16079483 | K50: =VLOOKUP($E50,Hybrid!$1:$1048576,MATCH(DATE(K$2,1,1),Hybrid!$A$1:$LI$1),FALSE) -> 0.16384985 | L50: =VLOOKUP($E50,Hybrid!$1:$1048576,MATCH(DATE(L$2,1,1),Hybrid!$A$1:$LI$1),FALSE) -> 0.16677286 | M50: =VLOOKUP($E50,Hybrid!$1:$1048576,MATCH(DATE(M$2,1,1),Hybrid!$A$1:$LI$1),FALSE) -> 0.16951058 | ... BI50: =VLOOKUP($E50,Hybrid!$1:$1048576,MATCH(DATE(BI$2,1,1),Hybrid!$A$1:$LI$1),FALSE) -> 0.090995603
D51: class F | E51: AUTO_cf_cgas_0 | F51: =VLOOKUP($E51,Hybrid!$1:$1048576,MATCH(DATE(F$2,1,1),Hybrid!$A$1:$LI$1),FALSE) -> 0.074609436 | G51: =VLOOKUP($E51,Hybrid!$1:$1048576,MATCH(DATE(G$2,1,1),Hybrid!$A$1:$LI$1),FALSE) -> 0.075328546 | H51: =VLOOKUP($E51,Hybrid!$1:$1048576,MATCH(DATE(H$2,1,1),Hybrid!$A$1:$LI$1),FALSE) -> 0.07624681 | I51: =VLOOKUP($E51,Hybrid!$1:$1048576,MATCH(DATE(I$2,1,1),Hybrid!$A$1:$LI$1),FALSE) -> 0.077169643 | J51: =VLOOKUP($E51,Hybrid!$1:$1048576,MATCH(DATE(J$2,1,1),Hybrid!$A$1:$LI$1),FALSE) -> 0.077981433 | K51: =VLOOKUP($E51,Hybrid!$1:$1048576,MATCH(DATE(K$2,1,1),Hybrid!$A$1:$LI$1),FALSE) -> 0.078617686 | L51: =VLOOKUP($E51,Hybrid!$1:$1048576,MATCH(DATE(L$2,1,1),Hybrid!$A$1:$LI$1),FALSE) -> 0.079038013 | M51: =VLOOKUP($E51,Hybrid!$1:$1048576,MATCH(DATE(M$2,1,1),Hybrid!$A$1:$LI$1),FALSE) -> 0.079230163 | ... BI51: =VLOOKUP($E51,Hybrid!$1:$1048576,MATCH(DATE(BI$2,1,1),Hybrid!$A$1:$LI$1),FALSE) -> 0.012061868
D52: class G | E52: AUTO_cg_cgas_0 | F52: =VLOOKUP($E52,Hybrid!$1:$1048576,MATCH(DATE(F$2,1,1),Hybrid!$A$1:$LI$1),FALSE) -> 0.13435819 | G52: =VLOOKUP($E52,Hybrid!$1:$1048576,MATCH(DATE(G$2,1,1),Hybrid!$A$1:$LI$1),FALSE) -> 0.13591962 | H52: =VLOOKUP($E52,Hybrid!$1:$1048576,MATCH(DATE(H$2,1,1),Hybrid!$A$1:$LI$1),FALSE) -> 0.13760976 | I52: =VLOOKUP($E52,Hybrid!$1:$1048576,MATCH(DATE(I$2,1,1),Hybrid!$A$1:$LI$1),FALSE) -> 0.13904072 | J52: =VLOOKUP($E52,Hybrid!$1:$1048576,MATCH(DATE(J$2,1,1),Hybrid!$A$1:$LI$1),FALSE) -> 0.14000476 | K52: =VLOOKUP($E52,Hybrid!$1:$1048576,MATCH(DATE(K$2,1,1),Hybrid!$A$1:$LI$1),FALSE) -> 0.1404069 | L52: =VLOOKUP($E52,Hybrid!$1:$1048576,MATCH(DATE(L$2,1,1),Hybrid!$A$1:$LI$1),FALSE) -> 0.14020757 | M52: =VLOOKUP($E52,Hybrid!$1:$1048576,MATCH(DATE(M$2,1,1),Hybrid!$A$1:$LI$1),FALSE) -> 0.13942144 | ... BI52: =VLOOKUP($E52,Hybrid!$1:$1048576,MATCH(DATE(BI$2,1,1),Hybrid!$A$1:$LI$1),FALSE) -> 0.012773169
C53: TOTAL SALES SHOCK | E53: NEWAUTO_2 | F53: =VLOOKUP($E53,Hybrid!$1:$1048576,MATCH(DATE(F$2,1,1),Hybrid!$A$1:$LI$1),FALSE) -> 1886.229 | G53: =VLOOKUP($E53,Hybrid!$1:$1048576,MATCH(DATE(G$2,1,1),Hybrid!$A$1:$LI$1),FALSE) -> 2101.923 | H53: =VLOOKUP($E53,Hybrid!$1:$1048576,MATCH(DATE(H$2,1,1),Hybrid!$A$1:$LI$1),FALSE) -> 2253.0624 | I53: =VLOOKUP($E53,Hybrid!$1:$1048576,MATCH(DATE(I$2,1,1),Hybrid!$A$1:$LI$1),FALSE) -> 2363.0246 | J53: =VLOOKUP($E53,Hybrid!$1:$1048576,MATCH(DATE(J$2,1,1),Hybrid!$A$1:$LI$1),FALSE) -> 2446.5133 | K53: =VLOOKUP($E53,Hybrid!$1:$1048576,MATCH(DATE(K$2,1,1),Hybrid!$A$1:$LI$1),FALSE) -> 2513.5883 | L53: =VLOOKUP($E53,Hybrid!$1:$1048576,MATCH(DATE(L$2,1,1),Hybrid!$A$1:$LI$1),FALSE) -> 2566.6384 | M53: =VLOOKUP($E53,Hybrid!$1:$1048576,MATCH(DATE(M$2,1,1),Hybrid!$A$1:$LI$1),FALSE) -> 2613.0681 | ... BI53: =VLOOKUP($E53,Hybrid!$1:$1048576,MATCH(DATE(BI$2,1,1),Hybrid!$A$1:$LI$1),FALSE) -> 3636.6264
C54: OIL | E54: NEWAUTO_cfut_2 | F54: =VLOOKUP($E54,Hybrid!$1:$1048576,MATCH(DATE(F$2,1,1),Hybrid!$A$1:$LI$1),FALSE) -> 1868.8108 | G54: =VLOOKUP($E54,Hybrid!$1:$1048576,MATCH(DATE(G$2,1,1),Hybrid!$A$1:$LI$1),FALSE) -> 2082.5252 | H54: =VLOOKUP($E54,Hybrid!$1:$1048576,MATCH(DATE(H$2,1,1),Hybrid!$A$1:$LI$1),FALSE) -> 2232.269 | I54: =VLOOKUP($E54,Hybrid!$1:$1048576,MATCH(DATE(I$2,1,1),Hybrid!$A$1:$LI$1),FALSE) -> 2341.1922 | J54: =VLOOKUP($E54,Hybrid!$1:$1048576,MATCH(DATE(J$2,1,1),Hybrid!$A$1:$LI$1),FALSE) -> 2423.8586 | K54: =VLOOKUP($E54,Hybrid!$1:$1048576,MATCH(DATE(K$2,1,1),Hybrid!$A$1:$LI$1),FALSE) -> 2490.2364 | L54: =VLOOKUP($E54,Hybrid!$1:$1048576,MATCH(DATE(L$2,1,1),Hybrid!$A$1:$LI$1),FALSE) -> 2542.6967 | M54: =VLOOKUP($E54,Hybrid!$1:$1048576,MATCH(DATE(M$2,1,1),Hybrid!$A$1:$LI$1),FALSE) -> 2588.5799 | ... BI54: =VLOOKUP($E54,Hybrid!$1:$1048576,MATCH(DATE(BI$2,1,1),Hybrid!$A$1:$LI$1),FALSE) -> 3568.1192
D55: class A | E55: NEWAUTO_ca_cfut_2 | F55: =VLOOKUP($E55,Hybrid!$1:$1048576,MATCH(DATE(F$2,1,1),Hybrid!$A$1:$LI$1),FALSE) -> 528.68661 | G55: =VLOOKUP($E55,Hybrid!$1:$1048576,MATCH(DATE(G$2,1,1),Hybrid!$A$1:$LI$1),FALSE) -> 591.94654 | H55: =VLOOKUP($E55,Hybrid!$1:$1048576,MATCH(DATE(H$2,1,1),Hybrid!$A$1:$LI$1),FALSE) -> 638.99233 | I55: =VLOOKUP($E55,Hybrid!$1:$1048576,MATCH(DATE(I$2,1,1),Hybrid!$A$1:$LI$1),FALSE) -> 675.76386 | J55: =VLOOKUP($E55,Hybrid!$1:$1048576,MATCH(DATE(J$2,1,1),Hybrid!$A$1:$LI$1),FALSE) -> 706.012 | K55: =VLOOKUP($E55,Hybrid!$1:$1048576,MATCH(DATE(K$2,1,1),Hybrid!$A$1:$LI$1),FALSE) -> 732.32421 | L55: =VLOOKUP($E55,Hybrid!$1:$1048576,MATCH(DATE(L$2,1,1),Hybrid!$A$1:$LI$1),FALSE) -> 755.15325 | M55: =VLOOKUP($E55,Hybrid!$1:$1048576,MATCH(DATE(M$2,1,1),Hybrid!$A$1:$LI$1),FALSE) -> 776.48437 | ... BI55: =VLOOKUP($E55,Hybrid!$1:$1048576,MATCH(DATE(BI$2,1,1),Hybrid!$A$1:$LI$1),FALSE) -> 1554.2572
D56: class B | E56: NEWAUTO_cb_cfut_2 | F56: =VLOOKUP($E56,Hybrid!$1:$1048576,MATCH(DATE(F$2,1,1),Hybrid!$A$1:$LI$1),FALSE) -> 507.56917 | G56: =VLOOKUP($E56,Hybrid!$1:$1048576,MATCH(DATE(G$2,1,1),Hybrid!$A$1:$LI$1),FALSE) -> 567.76824 | H56: =VLOOKUP($E56,Hybrid!$1:$1048576,MATCH(DATE(H$2,1,1),Hybrid!$A$1:$LI$1),FALSE) -> 612.01541 | I56: =VLOOKUP($E56,Hybrid!$1:$1048576,MATCH(DATE(I$2,1,1),Hybrid!$A$1:$LI$1),FALSE) -> 646.10697 | J56: =VLOOKUP($E56,Hybrid!$1:$1048576,MATCH(DATE(J$2,1,1),Hybrid!$A$1:$LI$1),FALSE) -> 673.69486 | K56: =VLOOKUP($E56,Hybrid!$1:$1048576,MATCH(DATE(K$2,1,1),Hybrid!$A$1:$LI$1),FALSE) -> 697.29118 | L56: =VLOOKUP($E56,Hybrid!$1:$1048576,MATCH(DATE(L$2,1,1),Hybrid!$A$1:$LI$1),FALSE) -> 717.36059 | M56: =VLOOKUP($E56,Hybrid!$1:$1048576,MATCH(DATE(M$2,1,1),Hybrid!$A$1:$LI$1),FALSE) -> 735.81692 | ... BI56: =VLOOKUP($E56,Hybrid!$1:$1048576,MATCH(DATE(BI$2,1,1),Hybrid!$A$1:$LI$1),FALSE) -> 1188.2606
D57: class C | E57: NEWAUTO_cc_cfut_2 | F57: =VLOOKUP($E57,Hybrid!$1:$1048576,MATCH(DATE(F$2,1,1),Hybrid!$A$1:$LI$1),FALSE) -> 351.33661 | G57: =VLOOKUP($E57,Hybrid!$1:$1048576,MATCH(DATE(G$2,1,1),Hybrid!$A$1:$LI$1),FALSE) -> 392.63839 | H57: =VLOOKUP($E57,Hybrid!$1:$1048576,MATCH(DATE(H$2,1,1),Hybrid!$A$1:$LI$1),FALSE) -> 422.63543 | I57: =VLOOKUP($E57,Hybrid!$1:$1048576,MATCH(DATE(I$2,1,1),Hybrid!$A$1:$LI$1),FALSE) -> 445.40646 | J57: =VLOOKUP($E57,Hybrid!$1:$1048576,MATCH(DATE(J$2,1,1),Hybrid!$A$1:$LI$1),FALSE) -> 463.51606 | K57: =VLOOKUP($E57,Hybrid!$1:$1048576,MATCH(DATE(K$2,1,1),Hybrid!$A$1:$LI$1),FALSE) -> 478.72371 | L57: =VLOOKUP($E57,Hybrid!$1:$1048576,MATCH(DATE(L$2,1,1),Hybrid!$A$1:$LI$1),FALSE) -> 491.37272 | M57: =VLOOKUP($E57,Hybrid!$1:$1048576,MATCH(DATE(M$2,1,1),Hybrid!$A$1:$LI$1),FALSE) -> 502.79424 | ... BI57: =VLOOKUP($E57,Hybrid!$1:$1048576,MATCH(DATE(BI$2,1,1),Hybrid!$A$1:$LI$1),FALSE) -> 656.60761
D58: class D | E58: NEWAUTO_cd_cfut_2 | F58: =VLOOKUP($E58,Hybrid!$1:$1048576,MATCH(DATE(F$2,1,1),Hybrid!$A$1:$LI$1),FALSE) -> 194.72987 | G58: =VLOOKUP($E58,Hybrid!$1:$1048576,MATCH(DATE(G$2,1,1),Hybrid!$A$1:$LI$1),FALSE) -> 216.67197 | H58: =VLOOKUP($E58,Hybrid!$1:$1048576,MATCH(DATE(H$2,1,1),Hybrid!$A$1:$LI$1),FALSE) -> 231.6813 | I58: =VLOOKUP($E58,Hybrid!$1:$1048576,MATCH(DATE(I$2,1,1),Hybrid!$A$1:$LI$1),FALSE) -> 242.20415 | J58: =VLOOKUP($E58,Hybrid!$1:$1048576,MATCH(DATE(J$2,1,1),Hybrid!$A$1:$LI$1),FALSE) -> 249.77047 | K58: =VLOOKUP($E58,Hybrid!$1:$1048576,MATCH(DATE(K$2,1,1),Hybrid!$A$1:$LI$1),FALSE) -> 255.42099 | L58: =VLOOKUP($E58,Hybrid!$1:$1048576,MATCH(DATE(L$2,1,1),Hybrid!$A$1:$LI$1),FALSE) -> 259.41137 | M58: =VLOOKUP($E58,Hybrid!$1:$1048576,MATCH(DATE(M$2,1,1),Hybrid!$A$1:$LI$1),FALSE) -> 262.50391 | ... BI58: =VLOOKUP($E58,Hybrid!$1:$1048576,MATCH(DATE(BI$2,1,1),Hybrid!$A$1:$LI$1),FALSE) -> 135.12709
D59: class E | E59: NEWAUTO_ce_cfut_2 | F59: =VLOOKUP($E59,Hybrid!$1:$1048576,MATCH(DATE(F$2,1,1),Hybrid!$A$1:$LI$1),FALSE) -> 119.7907 | G59: =VLOOKUP($E59,Hybrid!$1:$1048576,MATCH(DATE(G$2,1,1),Hybrid!$A$1:$LI$1),FALSE) -> 132.7655 | H59: =VLOOKUP($E59,Hybrid!$1:$1048576,MATCH(DATE(H$2,1,1),Hybrid!$A$1:$LI$1),FALSE) -> 141.11756 | I59: =VLOOKUP($E59,Hybrid!$1:$1048576,MATCH(DATE(I$2,1,1),Hybrid!$A$1:$LI$1),FALSE) -> 146.46162 | J59: =VLOOKUP($E59,Hybrid!$1:$1048576,MATCH(DATE(J$2,1,1),Hybrid!$A$1:$LI$1),FALSE) -> 149.80546 | K59: =VLOOKUP($E59,Hybrid!$1:$1048576,MATCH(DATE(K$2,1,1),Hybrid!$A$1:$LI$1),FALSE) -> 151.83172 | L59: =VLOOKUP($E59,Hybrid!$1:$1048576,MATCH(DATE(L$2,1,1),Hybrid!$A$1:$LI$1),FALSE) -> 152.73891 | M59: =VLOOKUP($E59,Hybrid!$1:$1048576,MATCH(DATE(M$2,1,1),Hybrid!$A$1:$LI$1),FALSE) -> 153.01438 | ... BI59: =VLOOKUP($E59,Hybrid!$1:$1048576,MATCH(DATE(BI$2,1,1),Hybrid!$A$1:$LI$1),FALSE) -> 33.198633
D60: class F | E60: NEWAUTO_cf_cfut_2 | F60: =VLOOKUP($E60,Hybrid!$1:$1048576,MATCH(DATE(F$2,1,1),Hybrid!$A$1:$LI$1),FALSE) -> 57.933085 | G60: =VLOOKUP($E60,Hybrid!$1:$1048576,MATCH(DATE(G$2,1,1),Hybrid!$A$1:$LI$1),FALSE) -> 63.315315 | H60: =VLOOKUP($E60,Hybrid!$1:$1048576,MATCH(DATE(H$2,1,1),Hybrid!$A$1:$LI$1),FALSE) -> 65.885618 | I60: =VLOOKUP($E60,Hybrid!$1:$1048576,MATCH(DATE(I$2,1,1),Hybrid!$A$1:$LI$1),FALSE) -> 66.639972 | J60: =VLOOKUP($E60,Hybrid!$1:$1048576,MATCH(DATE(J$2,1,1),Hybrid!$A$1:$LI$1),FALSE) -> 66.202351 | K60: =VLOOKUP($E60,Hybrid!$1:$1048576,MATCH(DATE(K$2,1,1),Hybrid!$A$1:$LI$1),FALSE) -> 64.993813 | L60: =VLOOKUP($E60,Hybrid!$1:$1048576,MATCH(DATE(L$2,1,1),Hybrid!$A$1:$LI$1),FALSE) -> 63.192862 | M60: =VLOOKUP($E60,Hybrid!$1:$1048576,MATCH(DATE(M$2,1,1),Hybrid!$A$1:$LI$1),FALSE) -> 61.075719 | ... BI60: =VLOOKUP($E60,Hybrid!$1:$1048576,MATCH(DATE(BI$2,1,1),Hybrid!$A$1:$LI$1),FALSE) -> 0.604516
D61: class G | E61: NEWAUTO_cg_cfut_2 | F61: =VLOOKUP($E61,Hybrid!$1:$1048576,MATCH(DATE(F$2,1,1),Hybrid!$A$1:$LI$1),FALSE) -> 108.76475 | G61: =VLOOKUP($E61,Hybrid!$1:$1048576,MATCH(DATE(G$2,1,1),Hybrid!$A$1:$LI$1),FALSE) -> 117.41928 | H61: =VLOOKUP($E61,Hybrid!$1:$1048576,MATCH(DATE(H$2,1,1),Hybrid!$A$1:$LI$1),FALSE) -> 119.94139 | I61: =VLOOKUP($E61,Hybrid!$1:$1048576,MATCH(DATE(I$2,1,1),Hybrid!$A$1:$LI$1),FALSE) -> 118.60913 | J61: =VLOOKUP($E61,Hybrid!$1:$1048576,MATCH(DATE(J$2,1,1),Hybrid!$A$1:$LI$1),FALSE) -> 114.85739 | K61: =VLOOKUP($E61,Hybrid!$1:$1048576,MATCH(DATE(K$2,1,1),Hybrid!$A$1:$LI$1),FALSE) -> 109.65078 | L61: =VLOOKUP($E61,Hybrid!$1:$1048576,MATCH(DATE(L$2,1,1),Hybrid!$A$1:$LI$1),FALSE) -> 103.467 | M61: =VLOOKUP($E61,Hybrid!$1:$1048576,MATCH(DATE(M$2,1,1),Hybrid!$A$1:$LI$1),FALSE) -> 96.890388 | ... BI61: =VLOOKUP($E61,Hybrid!$1:$1048576,MATCH(DATE(BI$2,1,1),Hybrid!$A$1:$LI$1),FALSE) -> 0.063520301
C62: ELEC | E62: NEWAUTO_cele_2 | F62: =VLOOKUP($E62,Hybrid!$1:$1048576,MATCH(DATE(F$2,1,1),Hybrid!$A$1:$LI$1),FALSE) -> 17.261212 | G62: =VLOOKUP($E62,Hybrid!$1:$1048576,MATCH(DATE(G$2,1,1),Hybrid!$A$1:$LI$1),FALSE) -> 19.222841 | H62: =VLOOKUP($E62,Hybrid!$1:$1048576,MATCH(DATE(H$2,1,1),Hybrid!$A$1:$LI$1),FALSE) -> 20.605837 | I62: =VLOOKUP($E62,Hybrid!$1:$1048576,MATCH(DATE(I$2,1,1),Hybrid!$A$1:$LI$1),FALSE) -> 21.635746 | J62: =VLOOKUP($E62,Hybrid!$1:$1048576,MATCH(DATE(J$2,1,1),Hybrid!$A$1:$LI$1),FALSE) -> 22.451099 | K62: =VLOOKUP($E62,Hybrid!$1:$1048576,MATCH(DATE(K$2,1,1),Hybrid!$A$1:$LI$1),FALSE) -> 23.142657 | L62: =VLOOKUP($E62,Hybrid!$1:$1048576,MATCH(DATE(L$2,1,1),Hybrid!$A$1:$LI$1),FALSE) -> 23.728054 | M62: =VLOOKUP($E62,Hybrid!$1:$1048576,MATCH(DATE(M$2,1,1),Hybrid!$A$1:$LI$1),FALSE) -> 24.270747 | ... BI62: =VLOOKUP($E62,Hybrid!$1:$1048576,MATCH(DATE(BI$2,1,1),Hybrid!$A$1:$LI$1),FALSE) -> 68.207529
D63: class A | E63: NEWAUTO_ca_cele_2 | F63: =VLOOKUP($E63,Hybrid!$1:$1048576,MATCH(DATE(F$2,1,1),Hybrid!$A$1:$LI$1),FALSE) -> 4.883159 | G63: =VLOOKUP($E63,Hybrid!$1:$1048576,MATCH(DATE(G$2,1,1),Hybrid!$A$1:$LI$1),FALSE) -> 5.463993 | H63: =VLOOKUP($E63,Hybrid!$1:$1048576,MATCH(DATE(H$2,1,1),Hybrid!$A$1:$LI$1),FALSE) -> 5.8988732 | I63: =VLOOKUP($E63,Hybrid!$1:$1048576,MATCH(DATE(I$2,1,1),Hybrid!$A$1:$LI$1),FALSE) -> 6.2462177 | J63: =VLOOKUP($E63,Hybrid!$1:$1048576,MATCH(DATE(J$2,1,1),Hybrid!$A$1:$LI$1),FALSE) -> 6.541973 | K63: =VLOOKUP($E63,Hybrid!$1:$1048576,MATCH(DATE(K$2,1,1),Hybrid!$A$1:$LI$1),FALSE) -> 6.8097605 | L63: =VLOOKUP($E63,Hybrid!$1:$1048576,MATCH(DATE(L$2,1,1),Hybrid!$A$1:$LI$1),FALSE) -> 7.0525747 | M63: =VLOOKUP($E63,Hybrid!$1:$1048576,MATCH(DATE(M$2,1,1),Hybrid!$A$1:$LI$1),FALSE) -> 7.2875223 | ... BI63: =VLOOKUP($E63,Hybrid!$1:$1048576,MATCH(DATE(BI$2,1,1),Hybrid!$A$1:$LI$1),FALSE) -> 28.327058
D64: class B | E64: NEWAUTO_cb_cele_2 | F64: =VLOOKUP($E64,Hybrid!$1:$1048576,MATCH(DATE(F$2,1,1),Hybrid!$A$1:$LI$1),FALSE) -> 4.6879892 | G64: =VLOOKUP($E64,Hybrid!$1:$1048576,MATCH(DATE(G$2,1,1),Hybrid!$A$1:$LI$1),FALSE) -> 5.240582 | H64: =VLOOKUP($E64,Hybrid!$1:$1048576,MATCH(DATE(H$2,1,1),Hybrid!$A$1:$LI$1),FALSE) -> 5.6500329 | I64: =VLOOKUP($E64,Hybrid!$1:$1048576,MATCH(DATE(I$2,1,1),Hybrid!$A$1:$LI$1),FALSE) -> 5.9736147 | J64: =VLOOKUP($E64,Hybrid!$1:$1048576,MATCH(DATE(J$2,1,1),Hybrid!$A$1:$LI$1),FALSE) -> 6.2463895 | K64: =VLOOKUP($E64,Hybrid!$1:$1048576,MATCH(DATE(K$2,1,1),Hybrid!$A$1:$LI$1),FALSE) -> 6.4912143 | L64: =VLOOKUP($E64,Hybrid!$1:$1048576,MATCH(DATE(L$2,1,1),Hybrid!$A$1:$LI$1),FALSE) -> 6.7110729 | M64: =VLOOKUP($E64,Hybrid!$1:$1048576,MATCH(DATE(M$2,1,1),Hybrid!$A$1:$LI$1),FALSE) -> 6.922304 | ... BI64: =VLOOKUP($E64,Hybrid!$1:$1048576,MATCH(DATE(BI$2,1,1),Hybrid!$A$1:$LI$1),FALSE) -> 23.780861
D65: class C | E65: NEWAUTO_cc_cele_2 | F65: =VLOOKUP($E65,Hybrid!$1:$1048576,MATCH(DATE(F$2,1,1),Hybrid!$A$1:$LI$1),FALSE) -> 3.244929 | G65: =VLOOKUP($E65,Hybrid!$1:$1048576,MATCH(DATE(G$2,1,1),Hybrid!$A$1:$LI$1),FALSE) -> 3.6239812 | H65: =VLOOKUP($E65,Hybrid!$1:$1048576,MATCH(DATE(H$2,1,1),Hybrid!$A$1:$LI$1),FALSE) -> 3.9018888 | I65: =VLOOKUP($E65,Hybrid!$1:$1048576,MATCH(DATE(I$2,1,1),Hybrid!$A$1:$LI$1),FALSE) -> 4.1191172 | J65: =VLOOKUP($E65,Hybrid!$1:$1048576,MATCH(DATE(J$2,1,1),Hybrid!$A$1:$LI$1),FALSE) -> 4.3003195 | K65: =VLOOKUP($E65,Hybrid!$1:$1048576,MATCH(DATE(K$2,1,1),Hybrid!$A$1:$LI$1),FALSE) -> 4.4614449 | L65: =VLOOKUP($E65,Hybrid!$1:$1048576,MATCH(DATE(L$2,1,1),Hybrid!$A$1:$LI$1),FALSE) -> 4.6046381 | M65: =VLOOKUP($E65,Hybrid!$1:$1048576,MATCH(DATE(M$2,1,1),Hybrid!$A$1:$LI$1),FALSE) -> 4.7411564 | ... BI65: =VLOOKUP($E65,Hybrid!$1:$1048576,MATCH(DATE(BI$2,1,1),Hybrid!$A$1:$LI$1),FALSE) -> 14.290231
D66: class D | E66: NEWAUTO_cd_cele_2 | F66: =VLOOKUP($E66,Hybrid!$1:$1048576,MATCH(DATE(F$2,1,1),Hybrid!$A$1:$LI$1),FALSE) -> 1.7988347 | G66: =VLOOKUP($E66,Hybrid!$1:$1048576,MATCH(DATE(G$2,1,1),Hybrid!$A$1:$LI$1),FALSE) -> 2.0004406 | H66: =VLOOKUP($E66,Hybrid!$1:$1048576,MATCH(DATE(H$2,1,1),Hybrid!$A$1:$LI$1),FALSE) -> 2.1384464 | I66: =VLOOKUP($E66,Hybrid!$1:$1048576,MATCH(DATE(I$2,1,1),Hybrid!$A$1:$LI$1),FALSE) -> 2.2361113 | J66: =VLOOKUP($E66,Hybrid!$1:$1048576,MATCH(DATE(J$2,1,1),Hybrid!$A$1:$LI$1),FALSE) -> 2.307773 | K66: =VLOOKUP($E66,Hybrid!$1:$1048576,MATCH(DATE(K$2,1,1),Hybrid!$A$1:$LI$1),FALSE) -> 2.3629367 | L66: =VLOOKUP($E66,Hybrid!$1:$1048576,MATCH(DATE(L$2,1,1),Hybrid!$A$1:$LI$1),FALSE) -> 2.4036941 | M66: =VLOOKUP($E66,Hybrid!$1:$1048576,MATCH(DATE(M$2,1,1),Hybrid!$A$1:$LI$1),FALSE) -> 2.4368041 | ... BI66: =VLOOKUP($E66,Hybrid!$1:$1048576,MATCH(DATE(BI$2,1,1),Hybrid!$A$1:$LI$1),FALSE) -> 1.4252899
D67: class E | E67: NEWAUTO_ce_cele_2 | F67: =VLOOKUP($E67,Hybrid!$1:$1048576,MATCH(DATE(F$2,1,1),Hybrid!$A$1:$LI$1),FALSE) -> 1.1065159 | G67: =VLOOKUP($E67,Hybrid!$1:$1048576,MATCH(DATE(G$2,1,1),Hybrid!$A$1:$LI$1),FALSE) -> 1.2255988 | H67: =VLOOKUP($E67,Hybrid!$1:$1048576,MATCH(DATE(H$2,1,1),Hybrid!$A$1:$LI$1),FALSE) -> 1.3023424 | I67: =VLOOKUP($E67,Hybrid!$1:$1048576,MATCH(DATE(I$2,1,1),Hybrid!$A$1:$LI$1),FALSE) -> 1.352143 | J67: =VLOOKUP($E67,Hybrid!$1:$1048576,MATCH(DATE(J$2,1,1),Hybrid!$A$1:$LI$1),FALSE) -> 1.3844393 | K67: =VLOOKUP($E67,Hybrid!$1:$1048576,MATCH(DATE(K$2,1,1),Hybrid!$A$1:$LI$1),FALSE) -> 1.4054317 | L67: =VLOOKUP($E67,Hybrid!$1:$1048576,MATCH(DATE(L$2,1,1),Hybrid!$A$1:$LI$1),FALSE) -> 1.416733 | M67: =VLOOKUP($E67,Hybrid!$1:$1048576,MATCH(DATE(M$2,1,1),Hybrid!$A$1:$LI$1),FALSE) -> 1.4226219 | ... BI67: =VLOOKUP($E67,Hybrid!$1:$1048576,MATCH(DATE(BI$2,1,1),Hybrid!$A$1:$LI$1),FALSE) -> 0.37948085
D68: class F | E68: NEWAUTO_cf_cele_2 | F68: =VLOOKUP($E68,Hybrid!$1:$1048576,MATCH(DATE(F$2,1,1),Hybrid!$A$1:$LI$1),FALSE) -> 0.53514662 | G68: =VLOOKUP($E68,Hybrid!$1:$1048576,MATCH(DATE(G$2,1,1),Hybrid!$A$1:$LI$1),FALSE) -> 0.58448203 | H68: =VLOOKUP($E68,Hybrid!$1:$1048576,MATCH(DATE(H$2,1,1),Hybrid!$A$1:$LI$1),FALSE) -> 0.60787775 | I68: =VLOOKUP($E68,Hybrid!$1:$1048576,MATCH(DATE(I$2,1,1),Hybrid!$A$1:$LI$1),FALSE) -> 0.61469064 | J68: =VLOOKUP($E68,Hybrid!$1:$1048576,MATCH(DATE(J$2,1,1),Hybrid!$A$1:$LI$1),FALSE) -> 0.61071937 | K68: =VLOOKUP($E68,Hybrid!$1:$1048576,MATCH(DATE(K$2,1,1),Hybrid!$A$1:$LI$1),FALSE) -> 0.59981119 | L68: =VLOOKUP($E68,Hybrid!$1:$1048576,MATCH(DATE(L$2,1,1),Hybrid!$A$1:$LI$1),FALSE) -> 0.58354251 | M68: =VLOOKUP($E68,Hybrid!$1:$1048576,MATCH(DATE(M$2,1,1),Hybrid!$A$1:$LI$1),FALSE) -> 0.564394 | ... BI68: =VLOOKUP($E68,Hybrid!$1:$1048576,MATCH(DATE(BI$2,1,1),Hybrid!$A$1:$LI$1),FALSE) -> 0.0041605321
D69: class G | E69: NEWAUTO_cg_cele_2 | F69: =VLOOKUP($E69,Hybrid!$1:$1048576,MATCH(DATE(F$2,1,1),Hybrid!$A$1:$LI$1),FALSE) -> 1.0046371 | G69: =VLOOKUP($E69,Hybrid!$1:$1048576,MATCH(DATE(G$2,1,1),Hybrid!$A$1:$LI$1),FALSE) -> 1.0837634 | H69: =VLOOKUP($E69,Hybrid!$1:$1048576,MATCH(DATE(H$2,1,1),Hybrid!$A$1:$LI$1),FALSE) -> 1.1063756 | I69: =VLOOKUP($E69,Hybrid!$1:$1048576,MATCH(DATE(I$2,1,1),Hybrid!$A$1:$LI$1),FALSE) -> 1.0938511 | J69: =VLOOKUP($E69,Hybrid!$1:$1048576,MATCH(DATE(J$2,1,1),Hybrid!$A$1:$LI$1),FALSE) -> 1.0594849 | K69: =VLOOKUP($E69,Hybrid!$1:$1048576,MATCH(DATE(K$2,1,1),Hybrid!$A$1:$LI$1),FALSE) -> 1.0120575 | L69: =VLOOKUP($E69,Hybrid!$1:$1048576,MATCH(DATE(L$2,1,1),Hybrid!$A$1:$LI$1),FALSE) -> 0.95579857 | M69: =VLOOKUP($E69,Hybrid!$1:$1048576,MATCH(DATE(M$2,1,1),Hybrid!$A$1:$LI$1),FALSE) -> 0.89594427 | ... BI69: =VLOOKUP($E69,Hybrid!$1:$1048576,MATCH(DATE(BI$2,1,1),Hybrid!$A$1:$LI$1),FALSE) -> 0.00044730488
C70: GAS | E70: NEWAUTO_cgas_2 | F70: =VLOOKUP($E70,Hybrid!$1:$1048576,MATCH(DATE(F$2,1,1),Hybrid!$A$1:$LI$1),FALSE) -> 0.15700065 | G70: =VLOOKUP($E70,Hybrid!$1:$1048576,MATCH(DATE(G$2,1,1),Hybrid!$A$1:$LI$1),FALSE) -> 0.17495502 | H70: =VLOOKUP($E70,Hybrid!$1:$1048576,MATCH(DATE(H$2,1,1),Hybrid!$A$1:$LI$1),FALSE) -> 0.18753514 | I70: =VLOOKUP($E70,Hybrid!$1:$1048576,MATCH(DATE(I$2,1,1),Hybrid!$A$1:$LI$1),FALSE) -> 0.19668588 | J70: =VLOOKUP($E70,Hybrid!$1:$1048576,MATCH(DATE(J$2,1,1),Hybrid!$A$1:$LI$1),FALSE) -> 0.20363077 | K70: =VLOOKUP($E70,Hybrid!$1:$1048576,MATCH(DATE(K$2,1,1),Hybrid!$A$1:$LI$1),FALSE) -> 0.20920724 | L70: =VLOOKUP($E70,Hybrid!$1:$1048576,MATCH(DATE(L$2,1,1),Hybrid!$A$1:$LI$1),FALSE) -> 0.21361448 | M70: =VLOOKUP($E70,Hybrid!$1:$1048576,MATCH(DATE(M$2,1,1),Hybrid!$A$1:$LI$1),FALSE) -> 0.21746918 | ... BI70: =VLOOKUP($E70,Hybrid!$1:$1048576,MATCH(DATE(BI$2,1,1),Hybrid!$A$1:$LI$1),FALSE) -> 0.29976124
D71: class A | E71: NEWAUTO_ca_cgas_2 | F71: =VLOOKUP($E71,Hybrid!$1:$1048576,MATCH(DATE(F$2,1,1),Hybrid!$A$1:$LI$1),FALSE) -> 0.044415488 | G71: =VLOOKUP($E71,Hybrid!$1:$1048576,MATCH(DATE(G$2,1,1),Hybrid!$A$1:$LI$1),FALSE) -> 0.049730018 | H71: =VLOOKUP($E71,Hybrid!$1:$1048576,MATCH(DATE(H$2,1,1),Hybrid!$A$1:$LI$1),FALSE) -> 0.053682382 | I71: =VLOOKUP($E71,Hybrid!$1:$1048576,MATCH(DATE(I$2,1,1),Hybrid!$A$1:$LI$1),FALSE) -> 0.056771595 | J71: =VLOOKUP($E71,Hybrid!$1:$1048576,MATCH(DATE(J$2,1,1),Hybrid!$A$1:$LI$1),FALSE) -> 0.059312771 | K71: =VLOOKUP($E71,Hybrid!$1:$1048576,MATCH(DATE(K$2,1,1),Hybrid!$A$1:$LI$1),FALSE) -> 0.061523285 | L71: =VLOOKUP($E71,Hybrid!$1:$1048576,MATCH(DATE(L$2,1,1),Hybrid!$A$1:$LI$1),FALSE) -> 0.063441176 | M71: =VLOOKUP($E71,Hybrid!$1:$1048576,MATCH(DATE(M$2,1,1),Hybrid!$A$1:$LI$1),FALSE) -> 0.065233225 | ... BI71: =VLOOKUP($E71,Hybrid!$1:$1048576,MATCH(DATE(BI$2,1,1),Hybrid!$A$1:$LI$1),FALSE) -> 0.1305747
D72: class B | E72: NEWAUTO_cb_cgas_2 | F72: =VLOOKUP($E72,Hybrid!$1:$1048576,MATCH(DATE(F$2,1,1),Hybrid!$A$1:$LI$1),FALSE) -> 0.042641391 | G72: =VLOOKUP($E72,Hybrid!$1:$1048576,MATCH(DATE(G$2,1,1),Hybrid!$A$1:$LI$1),FALSE) -> 0.047698775 | H72: =VLOOKUP($E72,Hybrid!$1:$1048576,MATCH(DATE(H$2,1,1),Hybrid!$A$1:$LI$1),FALSE) -> 0.051416023 | I72: =VLOOKUP($E72,Hybrid!$1:$1048576,MATCH(DATE(I$2,1,1),Hybrid!$A$1:$LI$1),FALSE) -> 0.054280089 | J72: =VLOOKUP($E72,Hybrid!$1:$1048576,MATCH(DATE(J$2,1,1),Hybrid!$A$1:$LI$1),FALSE) -> 0.056597776 | K72: =VLOOKUP($E72,Hybrid!$1:$1048576,MATCH(DATE(K$2,1,1),Hybrid!$A$1:$LI$1),FALSE) -> 0.058580126 | L72: =VLOOKUP($E72,Hybrid!$1:$1048576,MATCH(DATE(L$2,1,1),Hybrid!$A$1:$LI$1),FALSE) -> 0.060266177 | M72: =VLOOKUP($E72,Hybrid!$1:$1048576,MATCH(DATE(M$2,1,1),Hybrid!$A$1:$LI$1),FALSE) -> 0.061816711 | ... BI72: =VLOOKUP($E72,Hybrid!$1:$1048576,MATCH(DATE(BI$2,1,1),Hybrid!$A$1:$LI$1),FALSE) -> 0.099826952
D73: class C | E73: NEWAUTO_cc_cgas_2 | F73: =VLOOKUP($E73,Hybrid!$1:$1048576,MATCH(DATE(F$2,1,1),Hybrid!$A$1:$LI$1),FALSE) -> 0.029516138 | G73: =VLOOKUP($E73,Hybrid!$1:$1048576,MATCH(DATE(G$2,1,1),Hybrid!$A$1:$LI$1),FALSE) -> 0.032985942 | H73: =VLOOKUP($E73,Hybrid!$1:$1048576,MATCH(DATE(H$2,1,1),Hybrid!$A$1:$LI$1),FALSE) -> 0.035506023 | I73: =VLOOKUP($E73,Hybrid!$1:$1048576,MATCH(DATE(I$2,1,1),Hybrid!$A$1:$LI$1),FALSE) -> 0.03741904 | J73: =VLOOKUP($E73,Hybrid!$1:$1048576,MATCH(DATE(J$2,1,1),Hybrid!$A$1:$LI$1),FALSE) -> 0.038940446 | K73: =VLOOKUP($E73,Hybrid!$1:$1048576,MATCH(DATE(K$2,1,1),Hybrid!$A$1:$LI$1),FALSE) -> 0.040218055 | L73: =VLOOKUP($E73,Hybrid!$1:$1048576,MATCH(DATE(L$2,1,1),Hybrid!$A$1:$LI$1),FALSE) -> 0.041280711 | M73: =VLOOKUP($E73,Hybrid!$1:$1048576,MATCH(DATE(M$2,1,1),Hybrid!$A$1:$LI$1),FALSE) -> 0.042240244 | ... BI73: =VLOOKUP($E73,Hybrid!$1:$1048576,MATCH(DATE(BI$2,1,1),Hybrid!$A$1:$LI$1),FALSE) -> 0.055162258
D74: class D | E74: NEWAUTO_cd_cgas_2 | F74: =VLOOKUP($E74,Hybrid!$1:$1048576,MATCH(DATE(F$2,1,1),Hybrid!$A$1:$LI$1),FALSE) -> 0.01635945 | G74: =VLOOKUP($E74,Hybrid!$1:$1048576,MATCH(DATE(G$2,1,1),Hybrid!$A$1:$LI$1),FALSE) -> 0.018202828 | H74: =VLOOKUP($E74,Hybrid!$1:$1048576,MATCH(DATE(H$2,1,1),Hybrid!$A$1:$LI$1),FALSE) -> 0.019463777 | I74: =VLOOKUP($E74,Hybrid!$1:$1048576,MATCH(DATE(I$2,1,1),Hybrid!$A$1:$LI$1),FALSE) -> 0.020347812 | J74: =VLOOKUP($E74,Hybrid!$1:$1048576,MATCH(DATE(J$2,1,1),Hybrid!$A$1:$LI$1),FALSE) -> 0.020983466 | K74: =VLOOKUP($E74,Hybrid!$1:$1048576,MATCH(DATE(K$2,1,1),Hybrid!$A$1:$LI$1),FALSE) -> 0.021458172 | L74: =VLOOKUP($E74,Hybrid!$1:$1048576,MATCH(DATE(L$2,1,1),Hybrid!$A$1:$LI$1),FALSE) -> 0.021793407 | M74: =VLOOKUP($E74,Hybrid!$1:$1048576,MATCH(DATE(M$2,1,1),Hybrid!$A$1:$LI$1),FALSE) -> 0.022053215 | ... BI74: =VLOOKUP($E74,Hybrid!$1:$1048576,MATCH(DATE(BI$2,1,1),Hybrid!$A$1:$LI$1),FALSE) -> 0.011352162
D75: class E | E75: NEWAUTO_ce_cgas_2 | F75: =VLOOKUP($E75,Hybrid!$1:$1048576,MATCH(DATE(F$2,1,1),Hybrid!$A$1:$LI$1),FALSE) -> 0.010063736 | G75: =VLOOKUP($E75,Hybrid!$1:$1048576,MATCH(DATE(G$2,1,1),Hybrid!$A$1:$LI$1),FALSE) -> 0.011153762 | H75: =VLOOKUP($E75,Hybrid!$1:$1048576,MATCH(DATE(H$2,1,1),Hybrid!$A$1:$LI$1),FALSE) -> 0.011855426 | I75: =VLOOKUP($E75,Hybrid!$1:$1048576,MATCH(DATE(I$2,1,1),Hybrid!$A$1:$LI$1),FALSE) -> 0.012304386 | J75: =VLOOKUP($E75,Hybrid!$1:$1048576,MATCH(DATE(J$2,1,1),Hybrid!$A$1:$LI$1),FALSE) -> 0.012585306 | K75: =VLOOKUP($E75,Hybrid!$1:$1048576,MATCH(DATE(K$2,1,1),Hybrid!$A$1:$LI$1),FALSE) -> 0.012755534 | L75: =VLOOKUP($E75,Hybrid!$1:$1048576,MATCH(DATE(L$2,1,1),Hybrid!$A$1:$LI$1),FALSE) -> 0.012831748 | M75: =VLOOKUP($E75,Hybrid!$1:$1048576,MATCH(DATE(M$2,1,1),Hybrid!$A$1:$LI$1),FALSE) -> 0.01285489 | ... BI75: =VLOOKUP($E75,Hybrid!$1:$1048576,MATCH(DATE(BI$2,1,1),Hybrid!$A$1:$LI$1),FALSE) -> 0.0027890502
D76: class F | E76: NEWAUTO_cf_cgas_2 | F76: =VLOOKUP($E76,Hybrid!$1:$1048576,MATCH(DATE(F$2,1,1),Hybrid!$A$1:$LI$1),FALSE) -> 0.0048670162 | G76: =VLOOKUP($E76,Hybrid!$1:$1048576,MATCH(DATE(G$2,1,1),Hybrid!$A$1:$LI$1),FALSE) -> 0.0053191827 | H76: =VLOOKUP($E76,Hybrid!$1:$1048576,MATCH(DATE(H$2,1,1),Hybrid!$A$1:$LI$1),FALSE) -> 0.0055351163 | I76: =VLOOKUP($E76,Hybrid!$1:$1048576,MATCH(DATE(I$2,1,1),Hybrid!$A$1:$LI$1),FALSE) -> 0.0055984903 | J76: =VLOOKUP($E76,Hybrid!$1:$1048576,MATCH(DATE(J$2,1,1),Hybrid!$A$1:$LI$1),FALSE) -> 0.0055617254 | K76: =VLOOKUP($E76,Hybrid!$1:$1048576,MATCH(DATE(K$2,1,1),Hybrid!$A$1:$LI$1),FALSE) -> 0.0054601949 | L76: =VLOOKUP($E76,Hybrid!$1:$1048576,MATCH(DATE(L$2,1,1),Hybrid!$A$1:$LI$1),FALSE) -> 0.0053088952 | M76: =VLOOKUP($E76,Hybrid!$1:$1048576,MATCH(DATE(M$2,1,1),Hybrid!$A$1:$LI$1),FALSE) -> 0.0051310319 | ... BI76: =VLOOKUP($E76,Hybrid!$1:$1048576,MATCH(DATE(BI$2,1,1),Hybrid!$A$1:$LI$1),FALSE) -> 5.078599e-05
D77: class G | E77: NEWAUTO_cg_cgas_2 | F77: =VLOOKUP($E77,Hybrid!$1:$1048576,MATCH(DATE(F$2,1,1),Hybrid!$A$1:$LI$1),FALSE) -> 0.0091374352 | G77: =VLOOKUP($E77,Hybrid!$1:$1048576,MATCH(DATE(G$2,1,1),Hybrid!$A$1:$LI$1),FALSE) -> 0.0098645107 | H77: =VLOOKUP($E77,Hybrid!$1:$1048576,MATCH(DATE(H$2,1,1),Hybrid!$A$1:$LI$1),FALSE) -> 0.010076396 | I77: =VLOOKUP($E77,Hybrid!$1:$1048576,MATCH(DATE(I$2,1,1),Hybrid!$A$1:$LI$1),FALSE) -> 0.0099644712 | J77: =VLOOKUP($E77,Hybrid!$1:$1048576,MATCH(DATE(J$2,1,1),Hybrid!$A$1:$LI$1),FALSE) -> 0.0096492839 | K77: =VLOOKUP($E77,Hybrid!$1:$1048576,MATCH(DATE(K$2,1,1),Hybrid!$A$1:$LI$1),FALSE) -> 0.0092118712 | L77: =VLOOKUP($E77,Hybrid!$1:$1048576,MATCH(DATE(L$2,1,1),Hybrid!$A$1:$LI$1),FALSE) -> 0.0086923658 | M77: =VLOOKUP($E77,Hybrid!$1:$1048576,MATCH(DATE(M$2,1,1),Hybrid!$A$1:$LI$1),FALSE) -> 0.0081398579 | ... BI77: =VLOOKUP($E77,Hybrid!$1:$1048576,MATCH(DATE(BI$2,1,1),Hybrid!$A$1:$LI$1),FALSE) -> 5.3364037e-06
C78: TOTAL SALES BASELINE | E78: NEWAUTO_0 | F78: =VLOOKUP($E78,Hybrid!$1:$1048576,MATCH(DATE(F$2,1,1),Hybrid!$A$1:$LI$1),FALSE) -> 1886.229 | G78: =VLOOKUP($E78,Hybrid!$1:$1048576,MATCH(DATE(G$2,1,1),Hybrid!$A$1:$LI$1),FALSE) -> 2134.6325 | H78: =VLOOKUP($E78,Hybrid!$1:$1048576,MATCH(DATE(H$2,1,1),Hybrid!$A$1:$LI$1),FALSE) -> 2311.3263 | I78: =VLOOKUP($E78,Hybrid!$1:$1048576,MATCH(DATE(I$2,1,1),Hybrid!$A$1:$LI$1),FALSE) -> 2437.6173 | J78: =VLOOKUP($E78,Hybrid!$1:$1048576,MATCH(DATE(J$2,1,1),Hybrid!$A$1:$LI$1),FALSE) -> 2530.8734 | K78: =VLOOKUP($E78,Hybrid!$1:$1048576,MATCH(DATE(K$2,1,1),Hybrid!$A$1:$LI$1),FALSE) -> 2603.0714 | L78: =VLOOKUP($E78,Hybrid!$1:$1048576,MATCH(DATE(L$2,1,1),Hybrid!$A$1:$LI$1),FALSE) -> 2658.1047 | M78: =VLOOKUP($E78,Hybrid!$1:$1048576,MATCH(DATE(M$2,1,1),Hybrid!$A$1:$LI$1),FALSE) -> 2704.4994 | ... BI78: =VLOOKUP($E78,Hybrid!$1:$1048576,MATCH(DATE(BI$2,1,1),Hybrid!$A$1:$LI$1),FALSE) -> 3741.6433
C79: OIL | E79: NEWAUTO_cfut_0 | F79: =VLOOKUP($E79,Hybrid!$1:$1048576,MATCH(DATE(F$2,1,1),Hybrid!$A$1:$LI$1),FALSE) -> 1868.8017 | G79: =VLOOKUP($E79,Hybrid!$1:$1048576,MATCH(DATE(G$2,1,1),Hybrid!$A$1:$LI$1),FALSE) -> 2114.9019 | H79: =VLOOKUP($E79,Hybrid!$1:$1048576,MATCH(DATE(H$2,1,1),Hybrid!$A$1:$LI$1),FALSE) -> 2289.9412 | I79: =VLOOKUP($E79,Hybrid!$1:$1048576,MATCH(DATE(I$2,1,1),Hybrid!$A$1:$LI$1),FALSE) -> 2415.0259 | J79: =VLOOKUP($E79,Hybrid!$1:$1048576,MATCH(DATE(J$2,1,1),Hybrid!$A$1:$LI$1),FALSE) -> 2507.3634 | K79: =VLOOKUP($E79,Hybrid!$1:$1048576,MATCH(DATE(K$2,1,1),Hybrid!$A$1:$LI$1),FALSE) -> 2578.822 | L79: =VLOOKUP($E79,Hybrid!$1:$1048576,MATCH(DATE(L$2,1,1),Hybrid!$A$1:$LI$1),FALSE) -> 2633.263 | M79: =VLOOKUP($E79,Hybrid!$1:$1048576,MATCH(DATE(M$2,1,1),Hybrid!$A$1:$LI$1),FALSE) -> 2679.1372 | ... BI79: =VLOOKUP($E79,Hybrid!$1:$1048576,MATCH(DATE(BI$2,1,1),Hybrid!$A$1:$LI$1),FALSE) -> 3678.6313
D80: class A | E80: NEWAUTO_ca_cfut_0 | F80: =VLOOKUP($E80,Hybrid!$1:$1048576,MATCH(DATE(F$2,1,1),Hybrid!$A$1:$LI$1),FALSE) -> 528.68398 | G80: =VLOOKUP($E80,Hybrid!$1:$1048576,MATCH(DATE(G$2,1,1),Hybrid!$A$1:$LI$1),FALSE) -> 601.68218 | H80: =VLOOKUP($E80,Hybrid!$1:$1048576,MATCH(DATE(H$2,1,1),Hybrid!$A$1:$LI$1),FALSE) -> 656.91112 | I80: =VLOOKUP($E80,Hybrid!$1:$1048576,MATCH(DATE(I$2,1,1),Hybrid!$A$1:$LI$1),FALSE) -> 699.45264 | J80: =VLOOKUP($E80,Hybrid!$1:$1048576,MATCH(DATE(J$2,1,1),Hybrid!$A$1:$LI$1),FALSE) -> 733.60655 | K80: =VLOOKUP($E80,Hybrid!$1:$1048576,MATCH(DATE(K$2,1,1),Hybrid!$A$1:$LI$1),FALSE) -> 762.40305 | L80: =VLOOKUP($E80,Hybrid!$1:$1048576,MATCH(DATE(L$2,1,1),Hybrid!$A$1:$LI$1),FALSE) -> 786.68415 | M80: =VLOOKUP($E80,Hybrid!$1:$1048576,MATCH(DATE(M$2,1,1),Hybrid!$A$1:$LI$1),FALSE) -> 808.76185 | ... BI80: =VLOOKUP($E80,Hybrid!$1:$1048576,MATCH(DATE(BI$2,1,1),Hybrid!$A$1:$LI$1),FALSE) -> 1607.6275
D81: class B | E81: NEWAUTO_cb_cfut_0 | F81: =VLOOKUP($E81,Hybrid!$1:$1048576,MATCH(DATE(F$2,1,1),Hybrid!$A$1:$LI$1),FALSE) -> 507.56647 | G81: =VLOOKUP($E81,Hybrid!$1:$1048576,MATCH(DATE(G$2,1,1),Hybrid!$A$1:$LI$1),FALSE) -> 576.99918 | H81: =VLOOKUP($E81,Hybrid!$1:$1048576,MATCH(DATE(H$2,1,1),Hybrid!$A$1:$LI$1),FALSE) -> 628.88625 | I81: =VLOOKUP($E81,Hybrid!$1:$1048576,MATCH(DATE(I$2,1,1),Hybrid!$A$1:$LI$1),FALSE) -> 668.2492 | J81: =VLOOKUP($E81,Hybrid!$1:$1048576,MATCH(DATE(J$2,1,1),Hybrid!$A$1:$LI$1),FALSE) -> 699.30517 | K81: =VLOOKUP($E81,Hybrid!$1:$1048576,MATCH(DATE(K$2,1,1),Hybrid!$A$1:$LI$1),FALSE) -> 725.01186 | L81: =VLOOKUP($E81,Hybrid!$1:$1048576,MATCH(DATE(L$2,1,1),Hybrid!$A$1:$LI$1),FALSE) -> 746.21714 | M81: =VLOOKUP($E81,Hybrid!$1:$1048576,MATCH(DATE(M$2,1,1),Hybrid!$A$1:$LI$1),FALSE) -> 765.14866 | ... BI81: =VLOOKUP($E81,Hybrid!$1:$1048576,MATCH(DATE(BI$2,1,1),Hybrid!$A$1:$LI$1),FALSE) -> 1226.5822
D82: class C | E82: NEWAUTO_cc_cfut_0 | F82: =VLOOKUP($E82,Hybrid!$1:$1048576,MATCH(DATE(F$2,1,1),Hybrid!$A$1:$LI$1),FALSE) -> 351.33463 | G82: =VLOOKUP($E82,Hybrid!$1:$1048576,MATCH(DATE(G$2,1,1),Hybrid!$A$1:$LI$1),FALSE) -> 398.94887 | H82: =VLOOKUP($E82,Hybrid!$1:$1048576,MATCH(DATE(H$2,1,1),Hybrid!$A$1:$LI$1),FALSE) -> 434.08702 | I82: =VLOOKUP($E82,Hybrid!$1:$1048576,MATCH(DATE(I$2,1,1),Hybrid!$A$1:$LI$1),FALSE) -> 460.32555 | J82: =VLOOKUP($E82,Hybrid!$1:$1048576,MATCH(DATE(J$2,1,1),Hybrid!$A$1:$LI$1),FALSE) -> 480.64661 | K82: =VLOOKUP($E82,Hybrid!$1:$1048576,MATCH(DATE(K$2,1,1),Hybrid!$A$1:$LI$1),FALSE) -> 497.13224 | L82: =VLOOKUP($E82,Hybrid!$1:$1048576,MATCH(DATE(L$2,1,1),Hybrid!$A$1:$LI$1),FALSE) -> 510.39739 | M82: =VLOOKUP($E82,Hybrid!$1:$1048576,MATCH(DATE(M$2,1,1),Hybrid!$A$1:$LI$1),FALSE) -> 521.99047 | ... BI82: =VLOOKUP($E82,Hybrid!$1:$1048576,MATCH(DATE(BI$2,1,1),Hybrid!$A$1:$LI$1),FALSE) -> 676.48456
D83: class D | E83: NEWAUTO_cd_cfut_0 | F83: =VLOOKUP($E83,Hybrid!$1:$1048576,MATCH(DATE(F$2,1,1),Hybrid!$A$1:$LI$1),FALSE) -> 194.72922 | G83: =VLOOKUP($E83,Hybrid!$1:$1048576,MATCH(DATE(G$2,1,1),Hybrid!$A$1:$LI$1),FALSE) -> 219.97536 | H83: =VLOOKUP($E83,Hybrid!$1:$1048576,MATCH(DATE(H$2,1,1),Hybrid!$A$1:$LI$1),FALSE) -> 237.47373 | I83: =VLOOKUP($E83,Hybrid!$1:$1048576,MATCH(DATE(I$2,1,1),Hybrid!$A$1:$LI$1),FALSE) -> 249.48 | J83: =VLOOKUP($E83,Hybrid!$1:$1048576,MATCH(DATE(J$2,1,1),Hybrid!$A$1:$LI$1),FALSE) -> 257.82252 | K83: =VLOOKUP($E83,Hybrid!$1:$1048576,MATCH(DATE(K$2,1,1),Hybrid!$A$1:$LI$1),FALSE) -> 263.75581 | L83: =VLOOKUP($E83,Hybrid!$1:$1048576,MATCH(DATE(L$2,1,1),Hybrid!$A$1:$LI$1),FALSE) -> 267.70113 | M83: =VLOOKUP($E83,Hybrid!$1:$1048576,MATCH(DATE(M$2,1,1),Hybrid!$A$1:$LI$1),FALSE) -> 270.54036 | ... BI83: =VLOOKUP($E83,Hybrid!$1:$1048576,MATCH(DATE(BI$2,1,1),Hybrid!$A$1:$LI$1),FALSE) -> 134.74819
D84: class E | E84: NEWAUTO_ce_cfut_0 | F84: =VLOOKUP($E84,Hybrid!$1:$1048576,MATCH(DATE(F$2,1,1),Hybrid!$A$1:$LI$1),FALSE) -> 119.79023 | G84: =VLOOKUP($E84,Hybrid!$1:$1048576,MATCH(DATE(G$2,1,1),Hybrid!$A$1:$LI$1),FALSE) -> 134.68907 | H84: =VLOOKUP($E84,Hybrid!$1:$1048576,MATCH(DATE(H$2,1,1),Hybrid!$A$1:$LI$1),FALSE) -> 144.37663 | I84: =VLOOKUP($E84,Hybrid!$1:$1048576,MATCH(DATE(I$2,1,1),Hybrid!$A$1:$LI$1),FALSE) -> 150.40212 | J84: =VLOOKUP($E84,Hybrid!$1:$1048576,MATCH(DATE(J$2,1,1),Hybrid!$A$1:$LI$1),FALSE) -> 153.99482 | K84: =VLOOKUP($E84,Hybrid!$1:$1048576,MATCH(DATE(K$2,1,1),Hybrid!$A$1:$LI$1),FALSE) -> 155.98793 | L84: =VLOOKUP($E84,Hybrid!$1:$1048576,MATCH(DATE(L$2,1,1),Hybrid!$A$1:$LI$1),FALSE) -> 156.68924 | M84: =VLOOKUP($E84,Hybrid!$1:$1048576,MATCH(DATE(M$2,1,1),Hybrid!$A$1:$LI$1),FALSE) -> 156.65836 | ... BI84: =VLOOKUP($E84,Hybrid!$1:$1048576,MATCH(DATE(BI$2,1,1),Hybrid!$A$1:$LI$1),FALSE) -> 32.577475
D85: class F | E85: NEWAUTO_cf_cfut_0 | F85: =VLOOKUP($E85,Hybrid!$1:$1048576,MATCH(DATE(F$2,1,1),Hybrid!$A$1:$LI$1),FALSE) -> 57.932886 | G85: =VLOOKUP($E85,Hybrid!$1:$1048576,MATCH(DATE(G$2,1,1),Hybrid!$A$1:$LI$1),FALSE) -> 64.06542 | H85: =VLOOKUP($E85,Hybrid!$1:$1048576,MATCH(DATE(H$2,1,1),Hybrid!$A$1:$LI$1),FALSE) -> 66.970979 | I85: =VLOOKUP($E85,Hybrid!$1:$1048576,MATCH(DATE(I$2,1,1),Hybrid!$A$1:$LI$1),FALSE) -> 67.708496 | J85: =VLOOKUP($E85,Hybrid!$1:$1048576,MATCH(DATE(J$2,1,1),Hybrid!$A$1:$LI$1),FALSE) -> 67.073271 | K85: =VLOOKUP($E85,Hybrid!$1:$1048576,MATCH(DATE(K$2,1,1),Hybrid!$A$1:$LI$1),FALSE) -> 65.587763 | L85: =VLOOKUP($E85,Hybrid!$1:$1048576,MATCH(DATE(L$2,1,1),Hybrid!$A$1:$LI$1),FALSE) -> 63.490885 | M85: =VLOOKUP($E85,Hybrid!$1:$1048576,MATCH(DATE(M$2,1,1),Hybrid!$A$1:$LI$1),FALSE) -> 61.087541 | ... BI85: =VLOOKUP($E85,Hybrid!$1:$1048576,MATCH(DATE(BI$2,1,1),Hybrid!$A$1:$LI$1),FALSE) -> 0.5557917
D86: class G | E86: NEWAUTO_cg_cfut_0 | F86: =VLOOKUP($E86,Hybrid!$1:$1048576,MATCH(DATE(F$2,1,1),Hybrid!$A$1:$LI$1),FALSE) -> 108.76432 | G86: =VLOOKUP($E86,Hybrid!$1:$1048576,MATCH(DATE(G$2,1,1),Hybrid!$A$1:$LI$1),FALSE) -> 118.54179 | H86: =VLOOKUP($E86,Hybrid!$1:$1048576,MATCH(DATE(H$2,1,1),Hybrid!$A$1:$LI$1),FALSE) -> 121.23546 | I86: =VLOOKUP($E86,Hybrid!$1:$1048576,MATCH(DATE(I$2,1,1),Hybrid!$A$1:$LI$1),FALSE) -> 119.40791 | J86: =VLOOKUP($E86,Hybrid!$1:$1048576,MATCH(DATE(J$2,1,1),Hybrid!$A$1:$LI$1),FALSE) -> 114.91447 | K86: =VLOOKUP($E86,Hybrid!$1:$1048576,MATCH(DATE(K$2,1,1),Hybrid!$A$1:$LI$1),FALSE) -> 108.94335 | L86: =VLOOKUP($E86,Hybrid!$1:$1048576,MATCH(DATE(L$2,1,1),Hybrid!$A$1:$LI$1),FALSE) -> 102.08308 | M86: =VLOOKUP($E86,Hybrid!$1:$1048576,MATCH(DATE(M$2,1,1),Hybrid!$A$1:$LI$1),FALSE) -> 94.949983 | ... BI86: =VLOOKUP($E86,Hybrid!$1:$1048576,MATCH(DATE(BI$2,1,1),Hybrid!$A$1:$LI$1),FALSE) -> 0.055557949
C87: ELEC | E87: NEWAUTO_cele_0 | F87: =VLOOKUP($E87,Hybrid!$1:$1048576,MATCH(DATE(F$2,1,1),Hybrid!$A$1:$LI$1),FALSE) -> 17.270274 | G87: =VLOOKUP($E87,Hybrid!$1:$1048576,MATCH(DATE(G$2,1,1),Hybrid!$A$1:$LI$1),FALSE) -> 19.552971 | H87: =VLOOKUP($E87,Hybrid!$1:$1048576,MATCH(DATE(H$2,1,1),Hybrid!$A$1:$LI$1),FALSE) -> 21.19275 | I87: =VLOOKUP($E87,Hybrid!$1:$1048576,MATCH(DATE(I$2,1,1),Hybrid!$A$1:$LI$1),FALSE) -> 22.388441 | J87: =VLOOKUP($E87,Hybrid!$1:$1048576,MATCH(DATE(J$2,1,1),Hybrid!$A$1:$LI$1),FALSE) -> 23.299318 | K87: =VLOOKUP($E87,Hybrid!$1:$1048576,MATCH(DATE(K$2,1,1),Hybrid!$A$1:$LI$1),FALSE) -> 24.032752 | L87: =VLOOKUP($E87,Hybrid!$1:$1048576,MATCH(DATE(L$2,1,1),Hybrid!$A$1:$LI$1),FALSE) -> 24.620439 | M87: =VLOOKUP($E87,Hybrid!$1:$1048576,MATCH(DATE(M$2,1,1),Hybrid!$A$1:$LI$1),FALSE) -> 25.13708 | ... BI87: =VLOOKUP($E87,Hybrid!$1:$1048576,MATCH(DATE(BI$2,1,1),Hybrid!$A$1:$LI$1),FALSE) -> 62.702978
D88: class A | E88: NEWAUTO_ca_cele_0 | F88: =VLOOKUP($E88,Hybrid!$1:$1048576,MATCH(DATE(F$2,1,1),Hybrid!$A$1:$LI$1),FALSE) -> 4.8857927 | G88: =VLOOKUP($E88,Hybrid!$1:$1048576,MATCH(DATE(G$2,1,1),Hybrid!$A$1:$LI$1),FALSE) -> 5.5629533 | H88: =VLOOKUP($E88,Hybrid!$1:$1048576,MATCH(DATE(H$2,1,1),Hybrid!$A$1:$LI$1),FALSE) -> 6.0801069 | I88: =VLOOKUP($E88,Hybrid!$1:$1048576,MATCH(DATE(I$2,1,1),Hybrid!$A$1:$LI$1),FALSE) -> 6.4854367 | J88: =VLOOKUP($E88,Hybrid!$1:$1048576,MATCH(DATE(J$2,1,1),Hybrid!$A$1:$LI$1),FALSE) -> 6.8188562 | K88: =VLOOKUP($E88,Hybrid!$1:$1048576,MATCH(DATE(K$2,1,1),Hybrid!$A$1:$LI$1),FALSE) -> 7.1077642 | L88: =VLOOKUP($E88,Hybrid!$1:$1048576,MATCH(DATE(L$2,1,1),Hybrid!$A$1:$LI$1),FALSE) -> 7.3588 | M88: =VLOOKUP($E88,Hybrid!$1:$1048576,MATCH(DATE(M$2,1,1),Hybrid!$A$1:$LI$1),FALSE) -> 7.5923411 | ... BI88: =VLOOKUP($E88,Hybrid!$1:$1048576,MATCH(DATE(BI$2,1,1),Hybrid!$A$1:$LI$1),FALSE) -> 26.788719
D89: class B | E89: NEWAUTO_cb_cele_0 | F89: =VLOOKUP($E89,Hybrid!$1:$1048576,MATCH(DATE(F$2,1,1),Hybrid!$A$1:$LI$1),FALSE) -> 4.6906877 | G89: =VLOOKUP($E89,Hybrid!$1:$1048576,MATCH(DATE(G$2,1,1),Hybrid!$A$1:$LI$1),FALSE) -> 5.3350794 | H89: =VLOOKUP($E89,Hybrid!$1:$1048576,MATCH(DATE(H$2,1,1),Hybrid!$A$1:$LI$1),FALSE) -> 5.8217747 | I89: =VLOOKUP($E89,Hybrid!$1:$1048576,MATCH(DATE(I$2,1,1),Hybrid!$A$1:$LI$1),FALSE) -> 6.1984372 | J89: =VLOOKUP($E89,Hybrid!$1:$1048576,MATCH(DATE(J$2,1,1),Hybrid!$A$1:$LI$1),FALSE) -> 6.5041843 | K89: =VLOOKUP($E89,Hybrid!$1:$1048576,MATCH(DATE(K$2,1,1),Hybrid!$A$1:$LI$1),FALSE) -> 6.7656682 | L89: =VLOOKUP($E89,Hybrid!$1:$1048576,MATCH(DATE(L$2,1,1),Hybrid!$A$1:$LI$1),FALSE) -> 6.9894842 | M89: =VLOOKUP($E89,Hybrid!$1:$1048576,MATCH(DATE(M$2,1,1),Hybrid!$A$1:$LI$1),FALSE) -> 7.1951494 | ... BI89: =VLOOKUP($E89,Hybrid!$1:$1048576,MATCH(DATE(BI$2,1,1),Hybrid!$A$1:$LI$1),FALSE) -> 21.394542
D90: class C | E90: NEWAUTO_cc_cele_0 | F90: =VLOOKUP($E90,Hybrid!$1:$1048576,MATCH(DATE(F$2,1,1),Hybrid!$A$1:$LI$1),FALSE) -> 3.246902 | G90: =VLOOKUP($E90,Hybrid!$1:$1048576,MATCH(DATE(G$2,1,1),Hybrid!$A$1:$LI$1),FALSE) -> 3.6890039 | H90: =VLOOKUP($E90,Hybrid!$1:$1048576,MATCH(DATE(H$2,1,1),Hybrid!$A$1:$LI$1),FALSE) -> 4.0191548 | I90: =VLOOKUP($E90,Hybrid!$1:$1048576,MATCH(DATE(I$2,1,1),Hybrid!$A$1:$LI$1),FALSE) -> 4.2713283 | J90: =VLOOKUP($E90,Hybrid!$1:$1048576,MATCH(DATE(J$2,1,1),Hybrid!$A$1:$LI$1),FALSE) -> 4.4731605 | K90: =VLOOKUP($E90,Hybrid!$1:$1048576,MATCH(DATE(K$2,1,1),Hybrid!$A$1:$LI$1),FALSE) -> 4.6433483 | L90: =VLOOKUP($E90,Hybrid!$1:$1048576,MATCH(DATE(L$2,1,1),Hybrid!$A$1:$LI$1),FALSE) -> 4.7866173 | M90: =VLOOKUP($E90,Hybrid!$1:$1048576,MATCH(DATE(M$2,1,1),Hybrid!$A$1:$LI$1),FALSE) -> 4.9164546 | ... BI90: =VLOOKUP($E90,Hybrid!$1:$1048576,MATCH(DATE(BI$2,1,1),Hybrid!$A$1:$LI$1),FALSE) -> 12.263934
D91: class D | E91: NEWAUTO_cd_cele_0 | F91: =VLOOKUP($E91,Hybrid!$1:$1048576,MATCH(DATE(F$2,1,1),Hybrid!$A$1:$LI$1),FALSE) -> 1.7994863 | G91: =VLOOKUP($E91,Hybrid!$1:$1048576,MATCH(DATE(G$2,1,1),Hybrid!$A$1:$LI$1),FALSE) -> 2.0332235 | H91: =VLOOKUP($E91,Hybrid!$1:$1048576,MATCH(DATE(H$2,1,1),Hybrid!$A$1:$LI$1),FALSE) -> 2.196111 | I91: =VLOOKUP($E91,Hybrid!$1:$1048576,MATCH(DATE(I$2,1,1),Hybrid!$A$1:$LI$1),FALSE) -> 2.3091912 | J91: =VLOOKUP($E91,Hybrid!$1:$1048576,MATCH(DATE(J$2,1,1),Hybrid!$A$1:$LI$1),FALSE) -> 2.3893525 | K91: =VLOOKUP($E91,Hybrid!$1:$1048576,MATCH(DATE(K$2,1,1),Hybrid!$A$1:$LI$1),FALSE) -> 2.4480357 | L91: =VLOOKUP($E91,Hybrid!$1:$1048576,MATCH(DATE(L$2,1,1),Hybrid!$A$1:$LI$1),FALSE) -> 2.4888901 | M91: =VLOOKUP($E91,Hybrid!$1:$1048576,MATCH(DATE(M$2,1,1),Hybrid!$A$1:$LI$1),FALSE) -> 2.5198596 | ... BI91: =VLOOKUP($E91,Hybrid!$1:$1048576,MATCH(DATE(BI$2,1,1),Hybrid!$A$1:$LI$1),FALSE) -> 1.7888954
D92: class E | E92: NEWAUTO_ce_cele_0 | F92: =VLOOKUP($E92,Hybrid!$1:$1048576,MATCH(DATE(F$2,1,1),Hybrid!$A$1:$LI$1),FALSE) -> 1.1069866 | G92: =VLOOKUP($E92,Hybrid!$1:$1048576,MATCH(DATE(G$2,1,1),Hybrid!$A$1:$LI$1),FALSE) -> 1.2449952 | H92: =VLOOKUP($E92,Hybrid!$1:$1048576,MATCH(DATE(H$2,1,1),Hybrid!$A$1:$LI$1),FALSE) -> 1.3353942 | I92: =VLOOKUP($E92,Hybrid!$1:$1048576,MATCH(DATE(I$2,1,1),Hybrid!$A$1:$LI$1),FALSE) -> 1.39263 | J92: =VLOOKUP($E92,Hybrid!$1:$1048576,MATCH(DATE(J$2,1,1),Hybrid!$A$1:$LI$1),FALSE) -> 1.4280362 | K92: =VLOOKUP($E92,Hybrid!$1:$1048576,MATCH(DATE(K$2,1,1),Hybrid!$A$1:$LI$1),FALSE) -> 1.4491808 | L92: =VLOOKUP($E92,Hybrid!$1:$1048576,MATCH(DATE(L$2,1,1),Hybrid!$A$1:$LI$1),FALSE) -> 1.4587156 | M92: =VLOOKUP($E92,Hybrid!$1:$1048576,MATCH(DATE(M$2,1,1),Hybrid!$A$1:$LI$1),FALSE) -> 1.4616531 | ... BI92: =VLOOKUP($E92,Hybrid!$1:$1048576,MATCH(DATE(BI$2,1,1),Hybrid!$A$1:$LI$1),FALSE) -> 0.45915561
D93: class F | E93: NEWAUTO_cf_cele_0 | F93: =VLOOKUP($E93,Hybrid!$1:$1048576,MATCH(DATE(F$2,1,1),Hybrid!$A$1:$LI$1),FALSE) -> 0.53534589 | G93: =VLOOKUP($E93,Hybrid!$1:$1048576,MATCH(DATE(G$2,1,1),Hybrid!$A$1:$LI$1),FALSE) -> 0.5920998 | H93: =VLOOKUP($E93,Hybrid!$1:$1048576,MATCH(DATE(H$2,1,1),Hybrid!$A$1:$LI$1),FALSE) -> 0.61918533 | I93: =VLOOKUP($E93,Hybrid!$1:$1048576,MATCH(DATE(I$2,1,1),Hybrid!$A$1:$LI$1),FALSE) -> 0.62641465 | J93: =VLOOKUP($E93,Hybrid!$1:$1048576,MATCH(DATE(J$2,1,1),Hybrid!$A$1:$LI$1),FALSE) -> 0.62111262 | K93: =VLOOKUP($E93,Hybrid!$1:$1048576,MATCH(DATE(K$2,1,1),Hybrid!$A$1:$LI$1),FALSE) -> 0.60805362 | L93: =VLOOKUP($E93,Hybrid!$1:$1048576,MATCH(DATE(L$2,1,1),Hybrid!$A$1:$LI$1),FALSE) -> 0.58938017 | M93: =VLOOKUP($E93,Hybrid!$1:$1048576,MATCH(DATE(M$2,1,1),Hybrid!$A$1:$LI$1),FALSE) -> 0.5678607 | ... BI93: =VLOOKUP($E93,Hybrid!$1:$1048576,MATCH(DATE(BI$2,1,1),Hybrid!$A$1:$LI$1),FALSE) -> 0.0069974246
D94: class G | E94: NEWAUTO_cg_cele_0 | F94: =VLOOKUP($E94,Hybrid!$1:$1048576,MATCH(DATE(F$2,1,1),Hybrid!$A$1:$LI$1),FALSE) -> 1.005073 | G94: =VLOOKUP($E94,Hybrid!$1:$1048576,MATCH(DATE(G$2,1,1),Hybrid!$A$1:$LI$1),FALSE) -> 1.0956159 | H94: =VLOOKUP($E94,Hybrid!$1:$1048576,MATCH(DATE(H$2,1,1),Hybrid!$A$1:$LI$1),FALSE) -> 1.1210225 | I94: =VLOOKUP($E94,Hybrid!$1:$1048576,MATCH(DATE(I$2,1,1),Hybrid!$A$1:$LI$1),FALSE) -> 1.1050028 | J94: =VLOOKUP($E94,Hybrid!$1:$1048576,MATCH(DATE(J$2,1,1),Hybrid!$A$1:$LI$1),FALSE) -> 1.0646155 | K94: =VLOOKUP($E94,Hybrid!$1:$1048576,MATCH(DATE(K$2,1,1),Hybrid!$A$1:$LI$1),FALSE) -> 1.0107013 | L94: =VLOOKUP($E94,Hybrid!$1:$1048576,MATCH(DATE(L$2,1,1),Hybrid!$A$1:$LI$1),FALSE) -> 0.9485512 | M94: =VLOOKUP($E94,Hybrid!$1:$1048576,MATCH(DATE(M$2,1,1),Hybrid!$A$1:$LI$1),FALSE) -> 0.88376137 | ... BI94: =VLOOKUP($E94,Hybrid!$1:$1048576,MATCH(DATE(BI$2,1,1),Hybrid!$A$1:$LI$1),FALSE) -> 0.00073436539
C95: GAS | E95: NEWAUTO_cgas_0 | F95: =VLOOKUP($E95,Hybrid!$1:$1048576,MATCH(DATE(F$2,1,1),Hybrid!$A$1:$LI$1),FALSE) -> 0.15699989 | G95: =VLOOKUP($E95,Hybrid!$1:$1048576,MATCH(DATE(G$2,1,1),Hybrid!$A$1:$LI$1),FALSE) -> 0.17767501 | H95: =VLOOKUP($E95,Hybrid!$1:$1048576,MATCH(DATE(H$2,1,1),Hybrid!$A$1:$LI$1),FALSE) -> 0.19238024 | I95: =VLOOKUP($E95,Hybrid!$1:$1048576,MATCH(DATE(I$2,1,1),Hybrid!$A$1:$LI$1),FALSE) -> 0.20288873 | J95: =VLOOKUP($E95,Hybrid!$1:$1048576,MATCH(DATE(J$2,1,1),Hybrid!$A$1:$LI$1),FALSE) -> 0.2106461 | K95: =VLOOKUP($E95,Hybrid!$1:$1048576,MATCH(DATE(K$2,1,1),Hybrid!$A$1:$LI$1),FALSE) -> 0.2166494 | L95: =VLOOKUP($E95,Hybrid!$1:$1048576,MATCH(DATE(L$2,1,1),Hybrid!$A$1:$LI$1),FALSE) -> 0.22122305 | M95: =VLOOKUP($E95,Hybrid!$1:$1048576,MATCH(DATE(M$2,1,1),Hybrid!$A$1:$LI$1),FALSE) -> 0.22507698 | ... BI95: =VLOOKUP($E95,Hybrid!$1:$1048576,MATCH(DATE(BI$2,1,1),Hybrid!$A$1:$LI$1),FALSE) -> 0.30904548
D96: class A | E96: NEWAUTO_ca_cgas_0 | F96: =VLOOKUP($E96,Hybrid!$1:$1048576,MATCH(DATE(F$2,1,1),Hybrid!$A$1:$LI$1),FALSE) -> 0.044415267 | G96: =VLOOKUP($E96,Hybrid!$1:$1048576,MATCH(DATE(G$2,1,1),Hybrid!$A$1:$LI$1),FALSE) -> 0.050547919 | H96: =VLOOKUP($E96,Hybrid!$1:$1048576,MATCH(DATE(H$2,1,1),Hybrid!$A$1:$LI$1),FALSE) -> 0.055187757 | I96: =VLOOKUP($E96,Hybrid!$1:$1048576,MATCH(DATE(I$2,1,1),Hybrid!$A$1:$LI$1),FALSE) -> 0.058761713 | J96: =VLOOKUP($E96,Hybrid!$1:$1048576,MATCH(DATE(J$2,1,1),Hybrid!$A$1:$LI$1),FALSE) -> 0.061631017 | K96: =VLOOKUP($E96,Hybrid!$1:$1048576,MATCH(DATE(K$2,1,1),Hybrid!$A$1:$LI$1),FALSE) -> 0.064050239 | L96: =VLOOKUP($E96,Hybrid!$1:$1048576,MATCH(DATE(L$2,1,1),Hybrid!$A$1:$LI$1),FALSE) -> 0.066090118 | M96: =VLOOKUP($E96,Hybrid!$1:$1048576,MATCH(DATE(M$2,1,1),Hybrid!$A$1:$LI$1),FALSE) -> 0.067944888 | ... BI96: =VLOOKUP($E96,Hybrid!$1:$1048576,MATCH(DATE(BI$2,1,1),Hybrid!$A$1:$LI$1),FALSE) -> 0.13505839
D97: class B | E97: NEWAUTO_cb_cgas_0 | F97: =VLOOKUP($E97,Hybrid!$1:$1048576,MATCH(DATE(F$2,1,1),Hybrid!$A$1:$LI$1),FALSE) -> 0.042641164 | G97: =VLOOKUP($E97,Hybrid!$1:$1048576,MATCH(DATE(G$2,1,1),Hybrid!$A$1:$LI$1),FALSE) -> 0.048474275 | H97: =VLOOKUP($E97,Hybrid!$1:$1048576,MATCH(DATE(H$2,1,1),Hybrid!$A$1:$LI$1),FALSE) -> 0.05283336 | I97: =VLOOKUP($E97,Hybrid!$1:$1048576,MATCH(DATE(I$2,1,1),Hybrid!$A$1:$LI$1),FALSE) -> 0.05614028 | J97: =VLOOKUP($E97,Hybrid!$1:$1048576,MATCH(DATE(J$2,1,1),Hybrid!$A$1:$LI$1),FALSE) -> 0.058749323 | K97: =VLOOKUP($E97,Hybrid!$1:$1048576,MATCH(DATE(K$2,1,1),Hybrid!$A$1:$LI$1),FALSE) -> 0.060908968 | L97: =VLOOKUP($E97,Hybrid!$1:$1048576,MATCH(DATE(L$2,1,1),Hybrid!$A$1:$LI$1),FALSE) -> 0.062690444 | M97: =VLOOKUP($E97,Hybrid!$1:$1048576,MATCH(DATE(M$2,1,1),Hybrid!$A$1:$LI$1),FALSE) -> 0.0642809 | ... BI97: =VLOOKUP($E97,Hybrid!$1:$1048576,MATCH(DATE(BI$2,1,1),Hybrid!$A$1:$LI$1),FALSE) -> 0.10304639
D98: class C | E98: NEWAUTO_cc_cgas_0 | F98: =VLOOKUP($E98,Hybrid!$1:$1048576,MATCH(DATE(F$2,1,1),Hybrid!$A$1:$LI$1),FALSE) -> 0.029515972 | G98: =VLOOKUP($E98,Hybrid!$1:$1048576,MATCH(DATE(G$2,1,1),Hybrid!$A$1:$LI$1),FALSE) -> 0.033516092 | H98: =VLOOKUP($E98,Hybrid!$1:$1048576,MATCH(DATE(H$2,1,1),Hybrid!$A$1:$LI$1),FALSE) -> 0.036468083 | I98: =VLOOKUP($E98,Hybrid!$1:$1048576,MATCH(DATE(I$2,1,1),Hybrid!$A$1:$LI$1),FALSE) -> 0.038672408 | J98: =VLOOKUP($E98,Hybrid!$1:$1048576,MATCH(DATE(J$2,1,1),Hybrid!$A$1:$LI$1),FALSE) -> 0.0403796 | K98: =VLOOKUP($E98,Hybrid!$1:$1048576,MATCH(DATE(K$2,1,1),Hybrid!$A$1:$LI$1),FALSE) -> 0.041764574 | L98: =VLOOKUP($E98,Hybrid!$1:$1048576,MATCH(DATE(L$2,1,1),Hybrid!$A$1:$LI$1),FALSE) -> 0.042878993 | M98: =VLOOKUP($E98,Hybrid!$1:$1048576,MATCH(DATE(M$2,1,1),Hybrid!$A$1:$LI$1),FALSE) -> 0.043852939 | ... BI98: =VLOOKUP($E98,Hybrid!$1:$1048576,MATCH(DATE(BI$2,1,1),Hybrid!$A$1:$LI$1),FALSE) -> 0.056832141
D99: class D | E99: NEWAUTO_cd_cgas_0 | F99: =VLOOKUP($E99,Hybrid!$1:$1048576,MATCH(DATE(F$2,1,1),Hybrid!$A$1:$LI$1),FALSE) -> 0.016359395 | G99: =VLOOKUP($E99,Hybrid!$1:$1048576,MATCH(DATE(G$2,1,1),Hybrid!$A$1:$LI$1),FALSE) -> 0.018480349 | H99: =VLOOKUP($E99,Hybrid!$1:$1048576,MATCH(DATE(H$2,1,1),Hybrid!$A$1:$LI$1),FALSE) -> 0.019950405 | I99: =VLOOKUP($E99,Hybrid!$1:$1048576,MATCH(DATE(I$2,1,1),Hybrid!$A$1:$LI$1),FALSE) -> 0.020959063 | J99: =VLOOKUP($E99,Hybrid!$1:$1048576,MATCH(DATE(J$2,1,1),Hybrid!$A$1:$LI$1),FALSE) -> 0.021659926 | K99: =VLOOKUP($E99,Hybrid!$1:$1048576,MATCH(DATE(K$2,1,1),Hybrid!$A$1:$LI$1),FALSE) -> 0.022158388 | L99: =VLOOKUP($E99,Hybrid!$1:$1048576,MATCH(DATE(L$2,1,1),Hybrid!$A$1:$LI$1),FALSE) -> 0.022489839 | M99: =VLOOKUP($E99,Hybrid!$1:$1048576,MATCH(DATE(M$2,1,1),Hybrid!$A$1:$LI$1),FALSE) -> 0.022728365 | ... BI99: =VLOOKUP($E99,Hybrid!$1:$1048576,MATCH(DATE(BI$2,1,1),Hybrid!$A$1:$LI$1),FALSE) -> 0.01132033
D100: class E | E100: NEWAUTO_ce_cgas_0 | F100: =VLOOKUP($E100,Hybrid!$1:$1048576,MATCH(DATE(F$2,1,1),Hybrid!$A$1:$LI$1),FALSE) -> 0.010063696 | G100: =VLOOKUP($E100,Hybrid!$1:$1048576,MATCH(DATE(G$2,1,1),Hybrid!$A$1:$LI$1),FALSE) -> 0.011315363 | H100: =VLOOKUP($E100,Hybrid!$1:$1048576,MATCH(DATE(H$2,1,1),Hybrid!$A$1:$LI$1),FALSE) -> 0.012129225 | I100: =VLOOKUP($E100,Hybrid!$1:$1048576,MATCH(DATE(I$2,1,1),Hybrid!$A$1:$LI$1),FALSE) -> 0.012635432 | J100: =VLOOKUP($E100,Hybrid!$1:$1048576,MATCH(DATE(J$2,1,1),Hybrid!$A$1:$LI$1),FALSE) -> 0.012937258 | K100: =VLOOKUP($E100,Hybrid!$1:$1048576,MATCH(DATE(K$2,1,1),Hybrid!$A$1:$LI$1),FALSE) -> 0.013104701 | L100: =VLOOKUP($E100,Hybrid!$1:$1048576,MATCH(DATE(L$2,1,1),Hybrid!$A$1:$LI$1),FALSE) -> 0.013163619 | M100: =VLOOKUP($E100,Hybrid!$1:$1048576,MATCH(DATE(M$2,1,1),Hybrid!$A$1:$LI$1),FALSE) -> 0.013161025 | ... BI100: =VLOOKUP($E100,Hybrid!$1:$1048576,MATCH(DATE(BI$2,1,1),Hybrid!$A$1:$LI$1),FALSE) -> 0.0027368661
...

Sheet date
A1: =Hybrid!A1 -> _date_ | B1: =Hybrid!B1 -> 42005 | C1: =Hybrid!C1 -> 42370 | D1: =Hybrid!D1 -> 42736 | E1: =Hybrid!E1 -> 43101 | F1: =Hybrid!F1 -> 43466 | G1: =Hybrid!G1 -> 43831 | H1: =Hybrid!H1 -> 44197 | ... BE1: =Hybrid!BE1 -> 62094
B2: =TEXT(B1,"jj mm aaaa") -> 01 01 2015 | C2: =TEXT(C1,"jj mm aaaa") -> 01 01 2016 | D2: =TEXT(D1,"jj mm aaaa") -> 01 01 2017 | E2: =TEXT(E1,"jj mm aaaa") -> 01 01 2018 | F2: =TEXT(F1,"jj mm aaaa") -> 01 01 2019 | G2: =TEXT(G1,"jj mm aaaa") -> 01 01 2020 | H2: =TEXT(H1,"jj mm aaaa") -> 01 01 2021 | I2: =TEXT(I1,"jj mm aaaa") -> 01 01 2022 | ... BE2: =TEXT(BE1,"jj mm aaaa") -> 01 01 2070
B3: =RIGHT(B2,4) -> 2015 | C3: =RIGHT(C2,4) -> 2016 | D3: =RIGHT(D2,4) -> 2017 | E3: =RIGHT(E2,4) -> 2018 | F3: =RIGHT(F2,4) -> 2019 | G3: =RIGHT(G2,4) -> 2020 | H3: =RIGHT(H2,4) -> 2021 | I3: =RIGHT(I2,4) -> 2022 | ... BE3: =RIGHT(BE2,4) -> 2070

Sheet Emissions
A1: _date_ | B1: 42005 | C1: 42370 | D1: 42736 | E1: 43101 | F1: 43466 | G1: 43831 | H1: 44197 | I1: 44562 | J1: 44927 | K1: 45292 | L1: 45658 | M1: 46023 | N1: 46388 | O1: 46753 | P1: 47119 | Q1: 47484 | R1: 47849 | S1: 48214 | T1: 48580 | U1: 48945 | V1: 49310 | W1: 49675 | X1: 50041 | Y1: 50406 | Z1: 50771 | AA1: 51136 | AB1: 51502 | AC1: 51867 | AD1: 52232 | AE1: 52597 | AF1: 52963 | AG1: 53328 | AH1: 53693 | AI1: 54058 | AJ1: 54424 | AK1: 54789 | AL1: 55154 | AM1: 55519 | AN1: 55885 | AO1: 56250 | AP1: 56615 | AQ1: 56980 | AR1: 57346 | AS1: 57711 | AT1: 58076 | AU1: 58441 | AV1: 58807 | AW1: 59172 | AX1: 59537 | AY1: 59902 | AZ1: 60268 | BA1: 60633 | BB1: 60998 | BC1: 61363 | BD1: 61729 | BE1: 62094
A2: ems_2 | B2: 463.38278 | C2: 464.29333 | D2: 465.6735 | E2: 467.69495 | F2: 470.47471 | G2: 473.97485 | H2: 477.82464 | I2: 482.04118 | J2: 486.56683 | K2: 491.35086 | L2: 496.77019 | M2: 502.10983 | N2: 507.5357 | O2: 513.05948 | P2: 518.67086 | Q2: 524.35893 | R2: 530.08257 | S2: 535.85971 | T2: 541.69335 | U2: 547.58558 | V2: 553.23662 | W2: 559.1226 | X2: 565.12415 | Y2: 571.22387 | Z2: 577.42019 | AA2: 582.85119 | AB2: 588.46902 | AC2: 594.13945 | AD2: 599.86079 | AE2: 605.64766 | AF2: 611.51488 | AG2: 617.48152 | AH2: 623.55201 | AI2: 629.73163 | AJ2: 636.02404 | AK2: 642.43126 | AL2: 648.81068 | AM2: 655.23331 | AN2: 661.71968 | AO2: 668.281 | AP2: 674.92558 | AQ2: 681.6695 | AR2: 688.51158 | AS2: 695.45404 | AT2: 702.49864 | AU2: 709.64634 | AV2: 716.94711 | AW2: 724.37045 | AX2: 731.909 | AY2: 739.55915 | AZ2: 747.31843 | BA2: 755.20437 | BB2: 763.20322 | BC2: 771.31168 | BD2: 779.52849 | BE2: 787.85325
A3: ems_ch_2 | B3: 129.15358 | C3: 128.94922 | D3: 128.17662 | E3: 127.37428 | F3: 126.71189 | G3: 126.20639 | H3: 125.77922 | I3: 125.4015 | J3: 125.05849 | K3: 124.7485 | L3: 124.52419 | M3: 124.31258 | N3: 124.13017 | O3: 123.98153 | P3: 123.86479 | Q3: 123.77648 | R3: 123.70654 | S3: 123.65515 | T3: 123.6208 | U3: 123.60145 | V3: 123.56304 | W3: 123.55015 | X3: 123.55383 | Y3: 123.56961 | Z3: 123.59519 | AA3: 123.54225 | AB3: 123.4973 | AC3: 123.45605 | AD3: 123.41707 | AE3: 123.3804 | AF3: 123.34645 | AG3: 123.31727 | AH3: 123.29287 | AI3: 123.27371 | AJ3: 123.26037 | AK3: 123.25336 | AL3: 123.24666 | AM3: 123.2411 | AN3: 123.23745 | AO3: 123.23654 | AP3: 123.23923 | AQ3: 123.24823 | AR3: 123.2631 | AS3: 123.2839 | AT3: 123.31081 | AU3: 123.34401 | AV3: 123.39121 | AW3: 123.44808 | AX3: 123.51256 | AY3: 123.58366 | AZ3: 123.66085 | BA3: 123.74748 | BB3: 123.84104 | BC3: 123.94023 | BD3: 124.04435 | BE3: 124.15292
A4: ems_ch_2+ems_ci_2 | B4: 345.41027 | C4: 345.82855 | D4: 346.35159 | E4: 347.24818 | F4: 348.67542 | G4: 350.63141 | H4: 352.85661 | I4: 355.34832 | J4: 358.06365 | K4: 360.96704 | L4: 364.31543 | M4: 367.62853 | N4: 371.00844 | O4: 374.46595 | P4: 377.99275 | Q4: 381.57908 | R4: 385.1939 | S4: 388.84667 | T4: 392.53829 | U4: 396.26888 | V4: 399.8347 | W4: 403.55273 | X4: 407.34901 | Y4: 411.20909 | Z4: 415.13131 | AA4: 418.5346 | AB4: 422.04943 | AC4: 425.6003 | AD4: 429.18271 | AE4: 432.80546 | AF4: 436.47831 | AG4: 440.21437 | AH4: 444.01734 | AI4: 447.89137 | AJ4: 451.8396 | AK4: 455.86403 | AL4: 459.86941 | AM4: 463.90231 | AN4: 467.97723 | AO4: 472.1018 | AP4: 476.28136 | AQ4: 480.52624 | AR4: 484.83562 | AS4: 489.21059 | AT4: 493.65212 | AU4: 498.16075 | AV4: 502.76912 | AW4: 507.45819 | AX4: 512.22234 | AY4: 517.05911 | AZ4: 521.96683 | BA4: 526.95656 | BB4: 532.01977 | BC4: 537.15385 | BD4: 542.35782 | BE4: 547.63132
A5: ems_ci_2 | B5: 216.25669 | C5: 216.87932 | D5: 218.17496 | E5: 219.8739 | F5: 221.96352 | G5: 224.42501 | H5: 227.07739 | I5: 229.94682 | J5: 233.00515 | K5: 236.21854 | L5: 239.79124 | M5: 243.31595 | N5: 246.87827 | O5: 250.48441 | P5: 254.12796 | Q5: 257.80259 | R5: 261.48736 | S5: 265.19152 | T5: 268.91749 | U5: 272.66743 | V5: 276.27166 | W5: 280.00258 | X5: 283.79518 | Y5: 287.63948 | Z5: 291.53612 | AA5: 294.99235 | AB5: 298.55213 | AC5: 302.14425 | AD5: 305.76564 | AE5: 309.42507 | AF5: 313.13186 | AG5: 316.8971 | AH5: 320.72448 | AI5: 324.61766 | AJ5: 328.57923 | AK5: 332.61066 | AL5: 336.62275 | AM5: 340.6612 | AN5: 344.73978 | AO5: 348.86526 | AP5: 353.04212 | AQ5: 357.27801 | AR5: 361.57253 | AS5: 365.92669 | AT5: 370.34131 | AU5: 374.81674 | AV5: 379.37792 | AW5: 384.01012 | AX5: 388.70978 | AY5: 393.47544 | AZ5: 398.30598 | BA5: 403.20908 | BB5: 408.17874 | BC5: 413.21362 | BD5: 418.31347 | BE5: 423.4784
A6: ems_mat_2 | B6: 27.749091 | C6: 28.023596 | D6: 28.370662 | E6: 28.755107 | F6: 29.167251 | G6: 29.602021 | H6: 30.035438 | I6: 30.479069 | J6: 30.933463 | K6: 31.39784 | L6: 31.906538 | M6: 32.397711 | N6: 32.891936 | O6: 33.392065 | P6: 33.898595 | Q6: 34.411768 | R6: 34.930749 | S6: 35.456577 | T6: 35.989808 | U6: 36.530892 | V6: 37.054155 | W6: 37.604537 | X6: 38.167228 | Y6: 38.740315 | Z6: 39.323632 | AA6: 39.841939 | AB6: 40.388674 | AC6: 40.944761 | AD6: 41.50829 | AE6: 42.079559 | AF6: 42.65905 | AG6: 43.247399 | AH6: 43.844696 | AI6: 44.451021 | AJ6: 45.066386 | AK6: 45.690753 | AL6: 46.308081 | AM6: 46.929646 | AN6: 47.557256 | AO6: 48.191422 | AP6: 48.832458 | AQ6: 49.480995 | AR6: 50.137052 | AS6: 50.800753 | AT6: 51.47221 | AU6: 52.151506 | AV6: 52.841606 | AW6: 53.540717 | AX6: 54.24848 | AY6: 54.96478 | AZ6: 55.68958 | BA6: 56.423683 | BB6: 57.166715 | BC6: 57.918642 | BD6: 58.679518 | BE6: 59.449447
A7: ems_y_2 | B7: 90.223416 | C7: 90.441188 | D7: 90.951245 | E7: 91.691666 | F7: 92.632039 | G7: 93.741424 | H7: 94.932587 | I7: 96.213787 | J7: 97.569718 | K7: 98.985984 | L7: 100.54822 | M7: 102.08358 | N7: 103.63533 | O7: 105.20147 | P7: 106.77951 | Q7: 108.36808 | R7: 109.95791 | S7: 111.55646 | T7: 113.16526 | U7: 114.7858 | V7: 116.34777 | W7: 117.96533 | X7: 119.60791 | Y7: 121.27447 | Z7: 122.96525 | AA7: 124.47465 | AB7: 126.03092 | AC7: 127.59439 | AD7: 129.16978 | AE7: 130.76264 | AF7: 132.37752 | AG7: 134.01976 | AH7: 135.68997 | AI7: 137.38924 | AJ7: 139.11805 | AK7: 140.87648 | AL7: 142.63319 | AM7: 144.40136 | AN7: 146.18519 | AO7: 147.98778 | AP7: 149.81177 | AQ7: 151.66227 | AR7: 153.5389 | AS7: 155.4427 | AT7: 157.37431 | AU7: 159.33408 | AV7: 161.33638 | AW7: 163.37154 | AX7: 165.43817 | AY7: 167.53526 | AZ7: 169.66202 | BA7: 171.82413 | BB7: 174.01673 | BC7: 176.23919 | BD7: 178.49115 | BE7: 180.77248
A8: ems_sec_2 | B8: 334.2292 | C8: 335.34411 | D8: 337.49687 | E8: 340.32067 | F8: 343.76281 | G8: 347.76846 | H8: 352.04542 | I8: 356.63968 | J8: 361.50833 | K8: 366.60236 | L8: 372.246 | M8: 377.79724 | N8: 383.40553 | O8: 389.07795 | P8: 394.80607 | Q8: 400.58245 | R8: 406.37602 | S8: 412.20456 | T8: 418.07255 | U8: 423.98413 | V8: 429.67358 | W8: 435.57245 | X8: 441.57032 | Y8: 447.65426 | Z8: 453.825 | AA8: 459.30894 | AB8: 464.97172 | AC8: 470.6834 | AD8: 476.44372 | AE8: 482.26727 | AF8: 488.16843 | AG8: 494.16426 | AH8: 500.25914 | AI8: 506.45792 | AJ8: 512.76367 | AK8: 519.17789 | AL8: 525.56402 | AM8: 531.99221 | AN8: 538.48223 | AO8: 545.04446 | AP8: 551.68635 | AQ8: 558.42128 | AR8: 565.24848 | AS8: 572.17014 | AT8: 579.18783 | AU8: 586.30233 | AV8: 593.5559 | AW8: 600.92238 | AX8: 608.39643 | AY8: 615.97548 | AZ8: 623.65758 | BA8: 631.45689 | BB8: 639.36218 | BC8: 647.37144 | BD8: 655.48414 | BE8: 663.70033
A9: ems_ets_2 | B9: 123.89891 | C9: 124.34585 | D9: 125.25067 | E9: 126.36502 | F9: 127.65229 | G9: 129.09306 | H9: 130.58348 | I9: 132.14726 | J9: 133.77636 | K9: 135.4588 | L9: 137.31742 | M9: 139.11618 | N9: 140.91652 | O9: 142.72891 | P9: 144.55447 | Q9: 146.39319 | R9: 148.23111 | S9: 150.08031 | T9: 151.94484 | U9: 153.8275 | V9: 155.63389 | W9: 157.52182 | X9: 159.45228 | Y9: 161.4183 | Z9: 163.41945 | AA9: 165.17953 | AB9: 167.01597 | AC9: 168.884 | AD9: 170.77896 | AE9: 172.70344 | AF9: 174.66075 | AG9: 176.6568 | AH9: 178.69109 | AI9: 180.76417 | AJ9: 182.8763 | AK9: 185.02734 | AL9: 187.17926 | AM9: 189.3489 | AN9: 191.54219 | AO9: 193.76189 | AP9: 196.00974 | AQ9: 198.29154 | AR9: 200.60508 | AS9: 202.95036 | AT9: 205.32758 | AU9: 207.73682 | AV9: 210.1991 | AW9: 212.70015 | AX9: 215.23669 | AY9: 217.80748 | AZ9: 220.41182 | BA9: 223.05877 | BB9: 225.74148 | BC9: 228.45862 | BD9: 231.20996 | BE9: 233.99561
A10: ems_nets_2 | B10: 210.33029 | C10: 210.99825 | D10: 212.2462 | E10: 213.95565 | F10: 216.11052 | G10: 218.6754 | H10: 221.46194 | I10: 224.49242 | J10: 227.73197 | K10: 231.14356 | L10: 234.92858 | M10: 238.68106 | N10: 242.48901 | O10: 246.34904 | P10: 250.2516 | Q10: 254.18925 | R10: 258.14491 | S10: 262.12425 | T10: 266.12771 | U10: 270.15662 | V10: 274.03969 | W10: 278.05063 | X10: 282.11804 | Y10: 286.23596 | Z10: 290.40555 | AA10: 294.12941 | AB10: 297.95575 | AC10: 301.7994 | AD10: 305.66475 | AE10: 309.56383 | AF10: 313.50768 | AG10: 317.50746 | AH10: 321.56805 | AI10: 325.69375 | AJ10: 329.88737 | AK10: 334.15055 | AL10: 338.38476 | AM10: 342.64331 | AN10: 346.94004 | AO10: 351.28257 | AP10: 355.67661 | AQ10: 360.12973 | AR10: 364.6434 | AS10: 369.21979 | AT10: 373.86025 | AU10: 378.56551 | AV10: 383.3568 | AW10: 388.22222 | AX10: 393.15974 | AY10: 398.168 | AZ10: 403.24576 | BA10: 408.39812 | BB10: 413.6207 | BC10: 418.91282 | BD10: 424.27418 | BE10: 429.70472
A11: ems_netsi_2 | B11: 25.103578 | C11: 25.040722 | D11: 25.027852 | E11: 25.08298 | F11: 25.222152 | G11: 25.446604 | H11: 25.733866 | I11: 26.078043 | J11: 26.46909 | K11: 26.897691 | L11: 27.380546 | M11: 27.875291 | N11: 28.383925 | O11: 28.902627 | P11: 29.427855 | Q11: 29.956859 | R11: 30.485528 | S11: 31.013638 | T11: 31.540448 | U11: 32.065673 | V11: 32.570984 | W11: 33.082059 | X11: 33.594965 | Y11: 34.110141 | Z11: 34.628477 | AA11: 35.097684 | AB11: 35.566369 | AC11: 36.030365 | AD11: 36.491738 | AE11: 36.952951 | AF11: 37.416186 | AG11: 37.883662 | AH11: 38.35658 | AI11: 38.83607 | AJ11: 39.322968 | AK11: 39.817825 | AL11: 40.311781 | AM11: 40.807123 | AN11: 41.305276 | AO11: 41.807238 | AP11: 42.313636 | AQ11: 42.825339 | AR11: 43.342164 | AS11: 43.864178 | AT11: 44.391378 | AU11: 44.923681 | AV11: 45.463809 | AW11: 46.010128 | AX11: 46.562563 | AY11: 47.121052 | AZ11: 47.685396 | BA11: 48.256361 | BB11: 48.833007 | BC11: 49.415284 | BD11: 50.003201 | BE11: 50.596746
A12: ems_trsp_2-ems_sair_2 | B12: 24.435369 | C12: 24.559312 | D12: 24.769446 | E12: 25.018548 | F12: 25.298301 | G12: 25.604475 | H12: 25.9174 | I12: 26.243138 | J12: 26.580442 | K12: 26.927107 | L12: 27.307062 | M12: 27.673269 | N12: 28.039171 | O12: 28.406446 | P12: 28.775128 | Q12: 29.145168 | R12: 29.514072 | S12: 29.884162 | T12: 30.256142 | U12: 30.630517 | V12: 30.988827 | W12: 31.36277 | X12: 31.743501 | Y12: 32.129794 | Z12: 32.521645 | AA12: 32.865118 | AB12: 33.224866 | AC12: 33.589948 | AD12: 33.959541 | AE12: 34.334276 | AF12: 34.714869 | AG12: 35.10245 | AH12: 35.496927 | AI12: 35.898423 | AJ12: 36.306993 | AK12: 36.72262 | AL12: 37.137479 | AM12: 37.555617 | AN12: 37.978214 | AO12: 38.405815 | AP12: 38.838795 | AQ12: 39.278259 | AR12: 39.723793 | AS12: 40.175433 | AT12: 40.63323 | AU12: 41.097199 | AV12: 41.571256 | AW12: 42.05252 | AX12: 42.540421 | AY12: 43.034745 | AZ12: 43.535365 | BA12: 44.043941 | BB12: 44.559108 | BC12: 45.080632 | BD12: 45.608465 | BE12: 46.142616
... A887: ems_mat_co2_sgla_0 | B887: 10.966838 | C887: 11.106031 | D887: 11.258505 | E887: 11.423203 | F887: 11.598738 | G887: 11.783673 | H887: 11.971087 | I887: 12.162478 | J887: 12.35806 | K887: 12.557819 | L887: 12.771642 | M887: 12.98516 | N887: 13.201069 | O887: 13.420074 | P887: 13.642443 | Q887: 13.868353 | R887: 14.097977 | S887: 14.33149 | T887: 14.569074 | U887: 14.810899 | V887: 15.049717 | W887: 15.296291 | X887: 15.548727 | Y887: 15.806585 | Z887: 16.069734 | AA887: 16.316641 | AB887: 16.567754 | AC887: 16.821489 | AD887: 17.077838 | AE887: 17.33705 | AF887: 17.599348 | AG887: 17.864874 | AH887: 18.133676 | AI887: 18.405727 | AJ887: 18.68094 | AK887: 18.959195 | AL887: 19.235112 | AM887: 19.510729 | AN887: 19.786734 | AO887: 20.06348 | AP887: 20.341214 | AQ887: 20.620136 | AR887: 20.900406 | AS887: 21.182151 | AT887: 21.465472 | AU887: 21.75045 | AV887: 22.037632 | AW887: 22.326884 | AX887: 22.618199 | AY887: 22.911601 | AZ887: 23.207137 | BA887: 23.504878 | BB887: 23.804917 | BC887: 24.107371 | BD887: 24.412375 | BE887: 24.720084

Sheet Consumption
A1: _date_ | B1: 42005 | C1: 42370 | D1: 42736 | E1: 43101 | F1: 43466 | G1: 43831 | H1: 44197 | I1: 44562 | J1: 44927 | K1: 45292 | L1: 45658 | M1: 46023 | N1: 46388 | O1: 46753 | P1: 47119 | Q1: 47484 | R1: 47849 | S1: 48214 | T1: 48580 | U1: 48945 | V1: 49310 | W1: 49675 | X1: 50041 | Y1: 50406 | Z1: 50771 | AA1: 51136 | AB1: 51502 | AC1: 51867 | AD1: 52232 | AE1: 52597 | AF1: 52963 | AG1: 53328 | AH1: 53693 | AI1: 54058 | AJ1: 54424 | AK1: 54789 | AL1: 55154 | AM1: 55519 | AN1: 55885 | AO1: 56250 | AP1: 56615 | AQ1: 56980 | AR1: 57346 | AS1: 57711 | AT1: 58076 | AU1: 58441 | AV1: 58807 | AW1: 59172 | AX1: 59537 | AY1: 59902 | AZ1: 60268 | BA1: 60633 | BB1: 60998 | BC1: 61363 | BD1: 61729 | BE1: 62094
A2: ch_2 | B2: 1196135.9 | C2: 1203278.3 | D2: 1211950.8 | E2: 1222434.9 | F2: 1234742.5 | G2: 1248832.2 | H2: 1264023.5 | I2: 1280339.3 | J2: 1297719.1 | K2: 1316061.8 | L2: 1336281.2 | M2: 1356948.7 | N2: 1378028.5 | O2: 1399459.7 | P2: 1421191.1 | Q2: 1443186.1 | R2: 1465390.2 | S2: 1487781.8 | T2: 1510351.1 | U2: 1533091.3 | V2: 1555230.9 | W2: 1577715.5 | X2: 1600491.5 | Y2: 1623538 | Z2: 1646839.6 | AA2: 1668175.3 | AB2: 1689242.1 | AC2: 1710135.1 | AD2: 1730973.8 | AE2: 1751866.5 | AF2: 1772899.3 | AG2: 1794142.3 | AH2: 1815639.3 | AI2: 1837417.3 | AJ2: 1859493.2 | AK2: 1881878 | AL2: 1904117.3 | AM2: 1926345.1 | AN2: 1948645 | AO2: 1971087.9 | AP2: 1993738.3 | AQ2: 2016661.4 | AR2: 2039901.6 | AS2: 2063488.2 | AT2: 2087440.4 | AU2: 2111769.5 | AV2: 2136564.3 | AW2: 2161817.7 | AX2: 2187514.1 | AY2: 2213638 | AZ2: 2240177.7 | BA2: 2267147.7 | BB2: 2294543.2 | BC2: 2322355.1 | BD2: 2350576.7 | BE2: 2379203.9
A3: ch_0 | B3: 1202984.9 | C3: 1218429.1 | D3: 1234999 | E3: 1252452.6 | F3: 1270716.8 | G3: 1289816.5 | H3: 1309182.9 | I3: 1328965.3 | J3: 1349231.8 | K3: 1370000.7 | L3: 1392318.8 | M3: 1414841.3 | N3: 1437589.8 | O3: 1460541.1 | P3: 1483671.7 | Q3: 1506967.8 | R3: 1530424.7 | S3: 1554043.5 | T3: 1577828.8 | U3: 1601786.5 | V3: 1625133.1 | W3: 1648849 | X3: 1672897.1 | Y3: 1697269.9 | Z3: 1721962 | AA3: 1744684.3 | AB3: 1767155.7 | AC3: 1789481.3 | AD3: 1811794.2 | AE3: 1834213.2 | AF3: 1856831 | AG3: 1879714.2 | AH3: 1902907.1 | AI3: 1926438 | AJ3: 1950324.5 | AK3: 1974577.5 | AL3: 1998657.4 | AM3: 2022691.7 | AN3: 2046778.6 | AO3: 2071007.2 | AP3: 2095457.2 | AQ3: 2120195.8 | AR3: 2145276.8 | AS3: 2170740.5 | AT3: 2196615.9 | AU3: 2222922.7 | AV3: 2249723.3 | AW3: 2277015.8 | AX3: 2304798.4 | AY3: 2333068.1 | AZ3: 2361822 | BA3: 2391057.7 | BB3: 2420774.5 | BC3: 2450973.2 | BD3: 2481655.9 | BE3: 2512826
A4: pch_2 | B4: 0.99729718 | C4: 1.0128276 | D4: 1.0280114 | E4: 1.0434977 | F4: 1.0596469 | G4: 1.0766401 | H4: 1.094533 | I4: 1.1133551 | J4: 1.1331274 | K4: 1.1538652 | L4: 1.1756308 | M4: 1.1983878 | N4: 1.2221021 | O4: 1.246741 | P4: 1.2722691 | Q4: 1.2986462 | R4: 1.3258276 | S4: 1.3537626 | T4: 1.3824044 | U4: 1.4117105 | V4: 1.4416005 | W4: 1.4720632 | X4: 1.5030821 | Y4: 1.5346403 | Z4: 1.5667234 | AA4: 1.5991958 | AB4: 1.632055 | AC4: 1.6653082 | AD4: 1.6989641 | AE4: 1.7330345 | AF4: 1.7675363 | AG4: 1.8024905 | AH4: 1.8379268 | AI4: 1.8738784 | AJ4: 1.9103804 | AK4: 1.947469 | AL4: 1.9851274 | AM4: 2.0233968 | AN4: 2.0623185 | AO4: 2.1019299 | AP4: 2.1422641 | AQ4: 2.1833473 | AR4: 2.2252127 | AS4: 2.2678919 | AT4: 2.3114147 | AU4: 2.3558097 | AV4: 2.4010882 | AW4: 2.4472931 | AX4: 2.4944611 | AY4: 2.5426225 | AZ4: 2.5918027 | BA4: 2.6420094 | BB4: 2.6932736 | BC4: 2.7456223 | BD4: 2.7990787 | BE4: 2.8536629
A5: pch_0 | B5: 0.99928331 | C5: 1.0179892 | D5: 1.0368376 | E5: 1.0561224 | F5: 1.0760452 | G5: 1.0967217 | H5: 1.118178 | I5: 1.1404204 | J5: 1.1634451 | K5: 1.1872427 | L5: 1.2118535 | M5: 1.2372342 | N5: 1.2633511 | O5: 1.2901752 | P5: 1.3176784 | Q5: 1.345832 | R5: 1.3746072 | S5: 1.4039762 | T5: 1.4339138 | U5: 1.4643979 | V5: 1.4953689 | W5: 1.5268323 | X5: 1.558789 | Y5: 1.5912391 | Z5: 1.6241845 | AA5: 1.657509 | AB5: 1.6912196 | AC5: 1.7253282 | AD5: 1.7598483 | AE5: 1.7947968 | AF5: 1.8301955 | AG5: 1.8660716 | AH5: 1.9024564 | AI5: 1.9393842 | AJ5: 1.9768912 | AK5: 2.0150141 | AL5: 2.0537578 | AM5: 2.0931402 | AN5: 2.1331865 | AO5: 2.1739242 | AP5: 2.2153819 | AQ5: 2.257589 | AR5: 2.3005754 | AS5: 2.3443715 | AT5: 2.3890085 | AU5: 2.4345173 | AV5: 2.480932 | AW5: 2.5282848 | AX5: 2.5766066 | AY5: 2.6259271 | AZ5: 2.6762747 | BA5: 2.7276767 | BB5: 2.7801596 | BC5: 2.8337489 | BD5: 2.88847 | BE5: 2.9443477
A6: ch_cagr_2 | B6: 31449.802 | C6: 31538.548 | D6: 31672.705 | E6: 31878.791 | F6: 32159.297 | G6: 32509.11 | H6: 32905.877 | I6: 33345.191 | J6: 33822.005 | K6: 34331.364 | L6: 34895.059 | M6: 35476.871 | N6: 36074.088 | O6: 36684.093 | P6: 37304.913 | Q6: 37935.146 | R6: 38573.094 | S6: 39217.782 | T6: 39868.633 | U6: 40525.22 | V6: 41167.443 | W6: 41818.448 | X6: 42477.373 | Y6: 43143.848 | Z6: 43817.485 | AA6: 44440.732 | AB6: 45054.476 | AC6: 45661.726 | AD6: 46265.995 | AE6: 46870.429 | AF6: 47477.562 | AG6: 48089.469 | AH6: 48707.553 | AI6: 49332.737 | AJ6: 49965.64 | AK6: 50606.701 | AL6: 51244.047 | AM6: 51880.86 | AN6: 52519.33 | AO6: 53161.416 | AP6: 53808.932 | AQ6: 54463.716 | AR6: 55127.113 | AS6: 55800.064 | AT6: 56483.203 | AU6: 57176.943 | AV6: 57883.622 | AW6: 58603.305 | AX6: 59335.721 | AY6: 60080.532 | AZ6: 60837.437 | BA6: 61606.762 | BB6: 62388.439 | BC6: 63182.266 | BD6: 63988.064 | BE6: 64805.716
A7: ch_cagr_0 | B7: 31662.956 | C7: 31996.188 | D7: 32358.857 | E7: 32768.944 | F7: 33228.484 | G7: 33733.194 | H7: 34262.147 | I7: 34813.311 | J7: 35384.643 | K7: 35974.338 | L7: 36608.029 | M7: 37251.719 | N7: 37904.545 | O7: 38565.103 | P7: 39232.284 | Q7: 39905.382 | R7: 40584.011 | S7: 41267.997 | T7: 41957.286 | U7: 42651.892 | V7: 43331.355 | W7: 44019.975 | X7: 44717.404 | Y7: 45423.726 | Z7: 46138.907 | AA7: 46803.273 | AB7: 47458.643 | AC7: 48108.293 | AD7: 48756.126 | AE7: 49405.636 | AF7: 50059.599 | AG7: 50720.066 | AH7: 51388.474 | AI7: 52065.795 | AJ7: 52752.678 | AK7: 53449.567 | AL7: 54142.403 | AM7: 54833.954 | AN7: 55526.658 | AO7: 56222.909 | AP7: 56924.95 | AQ7: 57634.737 | AR7: 58353.876 | AS7: 59083.613 | AT7: 59824.876 | AU7: 60578.343 | AV7: 61345.842 | AW7: 62127.606 | AX7: 62923.763 | AY7: 63734.149 | AZ7: 64558.589 | BA7: 65397.009 | BB7: 66249.419 | BC7: 67115.889 | BD7: 67996.523 | BE7: 68891.443
A8: pch_cagr_2 | B8: 0.99790586 | C8: 1.0143988 | D8: 1.0306486 | E8: 1.0471913 | F8: 1.0643496 | G8: 1.0822947 | H8: 1.101083 | I8: 1.1207395 | J8: 1.1412773 | K8: 1.1627041 | L8: 1.1850683 | M8: 1.2083405 | N8: 1.2324919 | O8: 1.2574947 | P8: 1.2833193 | Q8: 1.3099332 | R8: 1.337303 | S8: 1.3653883 | T8: 1.3941518 | U8: 1.4235595 | V8: 1.4535458 | W8: 1.484103 | X8: 1.5152207 | Y8: 1.5468883 | Z8: 1.5790977 | AA8: 1.6117388 | AB8: 1.6448101 | AC8: 1.6783217 | AD8: 1.7122865 | AE8: 1.7467206 | AF8: 1.7816433 | AG8: 1.8170756 | AH8: 1.8530455 | AI8: 1.8895835 | AJ8: 1.9267219 | AK8: 1.9644934 | AL8: 2.0028802 | AM8: 2.0419166 | AN8: 2.0816405 | AO8: 2.1220881 | AP8: 2.1632926 | AQ8: 2.2052797 | AR8: 2.2480807 | AS8: 2.2917252 | AT8: 2.3362415 | AU8: 2.3816561 | AV8: 2.4279778 | AW8: 2.4752433 | AX8: 2.5234863 | AY8: 2.5727363 | AZ8: 2.623019 | BA8: 2.6743425 | BB8: 2.7267353 | BC8: 2.7802239 | BD8: 2.8348322 | BE8: 2.8905819
A9: pch_cagr_0 | B9: 0.99950351 | C9: 1.0184615 | D9: 1.0375509 | E9: 1.0570511 | F9: 1.0771576 | G9: 1.0979806 | H9: 1.1195443 | I9: 1.1418505 | J9: 1.1648906 | K9: 1.188652 | L9: 1.2131658 | M9: 1.2383939 | N9: 1.2643083 | O9: 1.2908855 | P9: 1.3181035 | Q9: 1.3459406 | R9: 1.3743759 | S9: 1.403389 | T9: 1.4329619 | U9: 1.4630789 | V9: 1.4936928 | W9: 1.524812 | X9: 1.5564402 | Y9: 1.5885808 | Z9: 1.6212384 | AA9: 1.654317 | AB9: 1.687828 | AC9: 1.7217852 | AD9: 1.7562041 | AE9: 1.7911034 | AF9: 1.8265051 | AG9: 1.8624345 | AH9: 1.89892 | AI9: 1.9359922 | AJ9: 1.9736831 | AK9: 2.0120251 | AL9: 2.0510238 | AM9: 2.0906968 | AN9: 2.1310677 | AO9: 2.1721626 | AP9: 2.2140082 | AQ9: 2.2566321 | AR9: 2.3000617 | AS9: 2.3443251 | AT9: 2.3894501 | AU9: 2.435465 | AV9: 2.4824003 | AW9: 2.5302852 | AX9: 2.5791479 | AY9: 2.6290156 | AZ9: 2.6799145 | BA9: 2.7318701 | BB9: 2.7849075 | BC9: 2.8390511 | BD9: 2.8943252 | BE9: 2.9507538
A10: ch_cfoo_2 | B10: 174038.52 | C10: 174560.87 | D10: 175349.95 | E10: 176549.12 | F10: 178167.61 | G10: 180172.61 | H10: 182436.5 | I10: 184932.04 | J10: 187629.43 | K10: 190500.13 | L10: 193664.53 | M10: 196921.61 | N10: 200256.52 | O10: 203655.24 | P10: 207107.44 | Q10: 210606.16 | R10: 214142.95 | S10: 217713.33 | T10: 221315 | U10: 224946.44 | V10: 228496.95 | W10: 232095.86 | X10: 235739.08 | Y10: 239425.09 | Z10: 243152.16 | AA10: 246601.4 | AB10: 250000.23 | AC10: 253365.82 | AD10: 256717.93 | AE10: 260074.17 | AF10: 263448.61 | AG10: 266852.65 | AH10: 270293.89 | AI10: 273777.26 | AJ10: 277305.94 | AK10: 280882.07 | AL10: 284439.13 | AM10: 287994.53 | AN10: 291560.27 | AO10: 295147.09 | AP10: 298764.94 | AQ10: 302423.81 | AR10: 306131 | AS10: 309891.59 | AT10: 313709 | AU10: 317585.41 | AV10: 321533.52 | AW10: 325553.6 | AX10: 329644.09 | AY10: 333803.07 | AZ10: 338028.87 | BA10: 342323.14 | BB10: 346685.48 | BC10: 351114.8 | BD10: 355610.12 | BE10: 360170.87
A11: ch_cfoo_0 | B11: 175207.58 | C11: 177059.97 | D11: 179079.11 | E11: 181363.83 | F11: 183923.96 | G11: 186734.04 | H11: 189676.51 | I11: 192738.81 | J11: 195908.77 | K11: 199175.98 | L11: 202682.19 | M11: 206239.2 | N11: 209842.54 | O11: 213484.97 | P11: 217160.94 | Q11: 220867.22 | R11: 224602.31 | S11: 228365.88 | T11: 232158.21 | U11: 235979.9 | V11: 239718.27 | W11: 243508.28 | X11: 247348.4 | Y11: 251239.32 | Z11: 255181 | AA11: 258843.62 | AB11: 262458.88 | AC11: 266045.25 | AD11: 269624.47 | AE11: 273215.91 | AF11: 276834.85 | AG11: 280492.52 | AH11: 284196.67 | AI11: 287952.46 | AJ11: 291763.23 | AK11: 295631.16 | AL11: 299478.22 | AM11: 303319.53 | AN11: 307168.43 | AO11: 311038.05 | AP11: 314940.64 | AQ11: 318886.9 | AR11: 322885.6 | AS11: 326943.49 | AT11: 331065.61 | AU11: 335255.57 | AV11: 339523.4 | AW11: 343870.26 | AX11: 348296.75 | AY11: 352801.85 | AZ11: 357384.51 | BA11: 362044.25 | BB11: 366781.07 | BC11: 371595.3 | BD11: 376487.48 | BE11: 381458.28
A12: pch_cfoo_2 | B12: 0.99765474 | C12: 1.013713 | D12: 1.0293615 | E12: 1.0451831 | F12: 1.0615544 | G12: 1.0786944 | H12: 1.0966962 | I12: 1.1156105 | J12: 1.1354674 | K12: 1.1562846 | L12: 1.1781167 | M12: 1.2009352 | N12: 1.2247101 | O12: 1.2494091 | P12: 1.2749966 | Q12: 1.3014326 | R12: 1.3286728 | S12: 1.3566683 | T12: 1.3853726 | U12: 1.4147428 | V12: 1.4447037 | W12: 1.4752379 | X12: 1.5063272 | Y12: 1.5379549 | Z12: 1.5701077 | AA12: 1.6026695 | AB12: 1.6356308 | AC12: 1.6689953 | AD12: 1.7027722 | AE12: 1.7369753 | AF12: 1.7716229 | AG12: 1.8067369 | AH12: 1.8423463 | AI12: 1.8784831 | AJ12: 1.9151818 | AK12: 1.9524783 | AL12: 1.9903644 | AM12: 2.0288744 | AN12: 2.0680464 | AO12: 2.107918 | AP12: 2.148524 | AQ12: 2.1898933 | AR12: 2.2320586 | AS12: 2.2750513 | AT12: 2.3189007 | AU12: 2.363635 | AV12: 2.409268 | AW12: 2.4558365 | AX12: 2.5033743 | AY12: 2.5519114 | AZ12: 2.6014739 | BA12: 2.6520731 | BB12: 2.7037368 | BC12: 2.756491 | BD12: 2.8103588 | BE12: 2.8653614
... A105: pch_cbio_0 | B105: 0.99908602 | C105: 1.0168016 | D105: 1.0341894 | E105: 1.0519779 | F105: 1.0706314 | G105: 1.0903796 | H105: 1.111257 | I105: 1.133194 | J105: 1.1560864 | K105: 1.1798353 | L105: 1.2043996 | M105: 1.2297283 | N105: 1.2557879 | O105: 1.2825623 | P105: 1.31004 | Q105: 1.3382065 | R105: 1.3670414 | S105: 1.3965197 | T105: 1.4266145 | U105: 1.457299 | V105: 1.4885209 | W105: 1.5202651 | X105: 1.5525214 | Y105: 1.5852791 | Z105: 1.618532 | AA105: 1.6521966 | AB105: 1.686261 | AC105: 1.7207266 | AD105: 1.7555919 | AE105: 1.7908585 | AF105: 1.8265365 | AG105: 1.862647 | AH105: 1.8992202 | AI105: 1.9362929 | AJ105: 1.9739056 | AK105: 2.0121003 | AL105: 2.0508953 | AM105: 2.0903153 | AN105: 2.1303885 | AO105: 2.1711418 | AP105: 2.2126007 | AQ105: 2.2547905 | AR105: 2.2977382 | AS105: 2.3414727 | AT105: 2.3860248 | AU105: 2.4314255 | AV105: 2.4777027 | AW105: 2.5248865 | AX105: 2.5730129 | AY105: 2.6221222 | AZ105: 2.6722543 | BA105: 2.7234436 | BB105: 2.7757175 | BC105: 2.829099 | BD105: 2.8836094 | BE105: 2.93927

Sheet Value_Added
A1: _date_ | B1: 42005 | C1: 42370 | D1: 42736 | E1: 43101 | F1: 43466 | G1: 43831 | H1: 44197 | I1: 44562 | J1: 44927 | K1: 45292 | L1: 45658 | M1: 46023 | N1: 46388 | O1: 46753 | P1: 47119 | Q1: 47484 | R1: 47849 | S1: 48214 | T1: 48580 | U1: 48945 | V1: 49310 | W1: 49675 | X1: 50041 | Y1: 50406 | Z1: 50771 | AA1: 51136 | AB1: 51502 | AC1: 51867 | AD1: 52232 | AE1: 52597 | AF1: 52963 | AG1: 53328 | AH1: 53693 | AI1: 54058 | AJ1: 54424 | AK1: 54789 | AL1: 55154 | AM1: 55519 | AN1: 55885 | AO1: 56250 | AP1: 56615 | AQ1: 56980 | AR1: 57346 | AS1: 57711 | AT1: 58076 | AU1: 58441 | AV1: 58807 | AW1: 59172 | AX1: 59537 | AY1: 59902 | AZ1: 60268 | BA1: 60633 | BB1: 60998 | BC1: 61363 | BD1: 61729 | BE1: 62094
A2: va_2 | B2: 1934585.5 | C2: 1951835.4 | D2: 1972160.7 | E2: 1995153.9 | F2: 2020573.1 | G2: 2048090.3 | H2: 2075955.4 | I2: 2105009.8 | J2: 2135094.4 | K2: 2166071.8 | L2: 2200294 | M2: 2233166.1 | N2: 2266489.6 | O2: 2300202.5 | P2: 2334280.9 | Q2: 2368719.9 | R2: 2403375.8 | S2: 2438395.6 | T2: 2473802.8 | U2: 2509625.1 | V2: 2544066.3 | W2: 2580349 | X2: 2617206.9 | Y2: 2654664.1 | Z2: 2692730 | AA2: 2726166.6 | AB2: 2761737.6 | AC2: 2797534.6 | AD2: 2833677.8 | AE2: 2870255 | AF2: 2907332.8 | AG2: 2944993.2 | AH2: 2983238.2 | AI2: 3022084 | AJ2: 3061536.9 | AK2: 3101597.3 | AL2: 3141310.2 | AM2: 3181349.2 | AN2: 3221757.7 | AO2: 3262577.3 | AP2: 3303847.1 | AQ2: 3345651.2 | AR2: 3387978.1 | AS2: 3430847.4 | AT2: 3474271.8 | AU2: 3518259 | AV2: 3563096.7 | AW2: 3608568.2 | AX2: 3654664.4 | AY2: 3701374.1 | AZ2: 3748689.5 | BA2: 3796713.9 | BB2: 3845362.5 | BC2: 3894634.2 | BD2: 3944528.6 | BE2: 3995048.8
A3: va_0 | B3: 1969443.9 | C3: 1994426 | D3: 2022137.4 | E3: 2051600.6 | F3: 2082683.3 | G3: 2115213.8 | H3: 2147570.4 | I3: 2180707.3 | J3: 2214571.2 | K3: 2249123.1 | L3: 2286889 | M3: 2323348.6 | N3: 2360285.3 | O3: 2397668.4 | P3: 2435493.2 | Q3: 2473767.2 | R3: 2512506.4 | S3: 2551732.3 | T3: 2591469.1 | U3: 2631741.4 | V3: 2670666.4 | W3: 2711601.9 | X3: 2753225.2 | Y3: 2795561.6 | Z3: 2838619.2 | AA3: 2876883.2 | AB3: 2917378.8 | AC3: 2958149.4 | AD3: 2999322.6 | AE3: 3040991 | AF3: 3083223.9 | AG3: 3126069.3 | AH3: 3169557.1 | AI3: 3213703.3 | AJ3: 3258514 | AK3: 3303989.2 | AL3: 3348785.4 | AM3: 3393886.6 | AN3: 3439346.1 | AO3: 3485223.5 | AP3: 3531574 | AQ3: 3578445.4 | AR3: 3625876.6 | AS3: 3673897.5 | AT3: 3722530.6 | AU3: 3771792 | AV3: 3821816 | AW3: 3872521.6 | AX3: 3923912.4 | AY3: 3975989 | AZ3: 4028752.8 | BA3: 4082207.5 | BB3: 4136359.2 | BC3: 4191216.2 | BD3: 4246788.7 | BE3: 4303088.6
A4: va_sagr_2 | B4: 30052.108 | C4: 30169.547 | D4: 30349.929 | E4: 30598.707 | F4: 30911.061 | G4: 31277.643 | H4: 31667.731 | I4: 32088.666 | J4: 32534.587 | K4: 33000.701 | L4: 33519.42 | M4: 34022.423 | N4: 34533.615 | O4: 35050.576 | P4: 35572.096 | Q4: 36097.619 | R4: 36623.6 | S4: 37153.228 | T4: 37686.651 | U4: 38224.267 | V4: 38739.847 | W4: 39278.947 | X4: 39825.024 | Y4: 40378.759 | Z4: 40940.437 | AA4: 41433.792 | AB4: 41952.932 | AC4: 42472.905 | AD4: 42996.518 | AE4: 43525.837 | AF4: 44062.38 | AG4: 44607.979 | AH4: 45162.634 | AI4: 45726.747 | AJ4: 46300.478 | AK4: 46883.854 | AL4: 47465.491 | AM4: 48051.563 | AN4: 48643.094 | AO4: 49240.952 | AP4: 49845.953 | AQ4: 50459.925 | AR4: 51082.487 | AS4: 51714.065 | AT4: 52354.883 | AU4: 53005.056 | AV4: 53670.049 | AW4: 54345.545 | AX4: 55031.455 | AY4: 55727.506 | AZ4: 56433.453 | BA4: 57151.517 | BB4: 57879.581 | BC4: 58617.611 | BD4: 59365.512 | BE4: 60123.237
A5: va_sagr_0 | B5: 30845.43 | C5: 31093.508 | D5: 31421.779 | E5: 31804.116 | F5: 32233.049 | G5: 32700.911 | H5: 33179.089 | I5: 33677.367 | J5: 34192.428 | K5: 34721.949 | L5: 35302.542 | M5: 35867.504 | N5: 36440.568 | O5: 37020.245 | P5: 37605.887 | Q5: 38197.316 | R5: 38794.643 | S5: 39398.161 | T5: 40008.259 | U5: 40625.367 | V5: 41221.38 | W5: 41845.11 | X5: 42478.578 | Y5: 43122.581 | Z5: 43777.424 | AA5: 44360.673 | AB5: 44972.903 | AC5: 45587.731 | AD5: 46208.144 | AE5: 46836.358 | AF5: 47473.992 | AG5: 48122.155 | AH5: 48781.551 | AI5: 49452.572 | AJ5: 50135.397 | AK5: 50830.069 | AL5: 51516.522 | AM5: 52208.381 | AN5: 52906.537 | AO5: 53612.179 | AP5: 54326.474 | AQ5: 55050.433 | AR5: 55784.864 | AS5: 56530.373 | AT5: 57287.385 | AU5: 58056.186 | AV5: 58838.806 | AW5: 59634.176 | AX5: 60442.318 | AY5: 61263.068 | AZ5: 62096.278 | BA5: 62941.876 | BB5: 63799.855 | BC5: 64670.253 | BD5: 65553.142 | BE5: 66448.619
A6: va_sfor_2 | B6: 5245.063 | C6: 5223.4965 | D6: 5192.2067 | E6: 5161.9587 | F6: 5136.6185 | G6: 5116.2899 | H6: 5096.8503 | I6: 5078.517 | J6: 5061.2284 | K6: 5045.1843 | L6: 5034.3476 | M6: 5022.1066 | N6: 5010.7044 | O6: 5000.4884 | P6: 4991.5002 | Q6: 4983.6678 | R6: 4976.3732 | S6: 4969.9072 | T6: 4964.2964 | U6: 4959.5293 | V6: 4953.0465 | W6: 4949.1195 | X6: 4946.451 | Y6: 4944.785 | Z6: 4944.0223 | AA6: 4937.0964 | AB6: 4932.7566 | AC6: 4929.4887 | AD6: 4927.1229 | AE6: 4925.6013 | AF6: 4924.9087 | AG6: 4925.1588 | AH6: 4926.2675 | AI6: 4928.209 | AJ6: 4930.9658 | AK6: 4934.5213 | AL6: 4938.3049 | AM6: 4942.6298 | AN6: 4947.5457 | AO6: 4953.0658 | AP6: 4959.1926 | AQ6: 4966.0832 | AR6: 4973.6196 | AS6: 4981.7664 | AT6: 4990.5033 | AU6: 4999.8167 | AV6: 5010.3536 | AW6: 5021.6377 | AX6: 5033.5421 | AY6: 5046.0084 | AZ6: 5059.0096 | BA6: 5072.8551 | BB6: 5087.3095 | BC6: 5102.312 | BD6: 5117.8372 | BE6: 5133.8762
A7: va_sfor_0 | B7: 5291.3592 | C7: 5276.6635 | D7: 5254.8412 | E7: 5233.543 | F7: 5215.0328 | G7: 5202.7318 | H7: 5194.9967 | I7: 5192.4663 | J7: 5194.2032 | K7: 5199.1235 | L7: 5210.2708 | M7: 5220.5106 | N7: 5231.3692 | O7: 5242.955 | P7: 5255.2435 | Q7: 5268.1804 | R7: 5281.7164 | S7: 5295.8163 | T7: 5310.4599 | U7: 5325.6384 | V7: 5338.6393 | W7: 5354.0367 | X7: 5370.4545 | Y7: 5387.6411 | Z7: 5405.4966 | AA7: 5416.3775 | AB7: 5429.5104 | AC7: 5443.4082 | AD7: 5457.9568 | AE7: 5473.1242 | AF7: 5488.9059 | AG7: 5505.304 | AH7: 5522.3193 | AI7: 5539.9494 | AJ7: 5558.1887 | AK7: 5577.0297 | AL7: 5594.7361 | AM7: 5612.4893 | AN7: 5630.567 | AO7: 5649.0928 | AP7: 5668.1279 | AQ7: 5687.7065 | AR7: 5707.8494 | AS7: 5728.5654 | AT7: 5749.8432 | AU7: 5771.6186 | AV7: 5793.7257 | AW7: 5815.9901 | AX7: 5838.4734 | AY7: 5861.3498 | AZ7: 5884.7761 | BA7: 5908.8109 | BB7: 5933.4433 | BC7: 5958.637 | BD7: 5984.3588 | BE7: 6010.5885
A8: va_sfoo_2 | B8: 42740.664 | C8: 43033.975 | D8: 43363.743 | E8: 43774.549 | F8: 44265.702 | G8: 44827.202 | H8: 45416.805 | I8: 46048.919 | J8: 46715.77 | K8: 47411.304 | L8: 48184.914 | M8: 48934.377 | N8: 49698.248 | O8: 50471.833 | P8: 51253.151 | Q8: 52041.299 | R8: 52831.838 | S8: 53628.632 | T8: 54431.528 | U8: 55240.894 | V8: 56017.04 | W8: 56829.435 | X8: 57650.781 | Y8: 58482.778 | Z8: 59325.928 | AA8: 60065.086 | AB8: 60845.086 | AC8: 61623.715 | AD8: 62406.14 | AE8: 63195.667 | AF8: 63994.643 | AG8: 64805.657 | AH8: 65628.95 | AI8: 66465.265 | AJ8: 67314.962 | AK8: 68178.208 | AL8: 69035.811 | AM8: 69899.561 | AN8: 70770.744 | AO8: 71650.663 | AP8: 72540.64 | AQ8: 73443.197 | AR8: 74358.077 | AS8: 75286.046 | AT8: 76227.522 | AU8: 77182.742 | AV8: 78158.9 | AW8: 79150.215 | AX8: 80156.86 | AY8: 81178.526 | AZ8: 82214.918 | BA8: 83268.737 | BB8: 84337.297 | BC8: 85420.686 | BD8: 86518.805 | BE8: 87631.609
A9: va_sfoo_0 | B9: 43732.11 | C9: 44168.302 | D9: 44703.723 | E9: 45303.832 | F9: 45960.539 | G9: 46665.078 | H9: 47377.598 | I9: 48115.741 | J9: 48875.288 | K9: 49653.69 | L9: 50506.011 | M9: 51332.115 | N9: 52170.679 | O9: 53018.459 | P9: 53874.341 | Q9: 54738.051 | R9: 55609.738 | S9: 56489.789 | T9: 57378.711 | U9: 58277.065 | V9: 59142.947 | W9: 60050.019 | X9: 60969.181 | Y9: 61902.454 | Z9: 62850.432 | AA9: 63690.424 | AB9: 64575.389 | AC9: 65461.039 | AD9: 66352.865 | AE9: 67254.389 | AF9: 68168.085 | AG9: 69095.661 | AH9: 70038.23 | AI9: 70996.465 | AJ9: 71970.733 | AK9: 72961.207 | AL9: 73938.142 | AM9: 74922.711 | AN9: 75915.547 | AO9: 76918.329 | AP9: 77932.825 | AQ9: 78960.59 | AR9: 80002.883 | AS9: 81060.656 | AT9: 82134.599 | AU9: 83225.198 | AV9: 84335.54 | AW9: 85464.03 | AX9: 86610.823 | AY9: 87775.695 | AZ9: 88958.462 | BA9: 90159.067 | BB9: 91377.539 | BC9: 92613.961 | BD9: 93868.457 | BE9: 95141.178
A10: va_sveh_2 | B10: 28154.815 | C10: 29061.237 | D10: 29672.454 | E10: 30208.949 | F10: 30707.812 | G10: 31178.595 | H10: 31592.253 | I10: 31997.263 | J10: 32392.745 | K10: 32781.627 | L10: 33225.41 | M10: 33589.09 | N10: 33962.932 | O10: 34338.183 | P10: 34715.108 | Q10: 35094.923 | R10: 35470.752 | S10: 35853.62 | T10: 36242.783 | U10: 36638.783 | V10: 36999.875 | W10: 37419.094 | X10: 37839.862 | Y10: 38268.51 | Z10: 38705.755 | AA10: 39031.428 | AB10: 39454.821 | AC10: 39877.222 | AD10: 40307.924 | AE10: 40747.93 | AF10: 41197.096 | AG10: 41656.893 | AH10: 42124.728 | AI10: 42600.559 | AJ10: 43084.058 | AK10: 43574.919 | AL10: 44060.489 | AM10: 44554.478 | AN10: 45055.381 | AO10: 45562.994 | AP10: 46077.309 | AQ10: 46600.909 | AR10: 47130.708 | AS10: 47667.161 | AT10: 48210.268 | AU10: 48759.996 | AV10: 49327.594 | AW10: 49899.646 | AX10: 50478.126 | AY10: 51063.185 | AZ10: 51654.854 | BA10: 52258.709 | BB10: 52868.365 | BC10: 53484.949 | BD10: 54108.665 | BE10: 54739.655
A11: va_sveh_0 | B11: 29948.865 | C11: 30559.324 | D11: 31210.566 | E11: 31816.153 | F11: 32383.826 | G11: 32924.68 | H11: 33412.831 | I11: 33898.34 | J11: 34381.176 | K11: 34864.577 | L11: 35413.985 | M11: 35893.499 | N11: 36388.441 | O11: 36890.389 | P11: 37399.149 | Q11: 37915.444 | R11: 38440.004 | S11: 38973.466 | T11: 39516.363 | U11: 40069.134 | V11: 40585.66 | W11: 41167.698 | X11: 41753.161 | Y11: 42349.034 | Z11: 42956.063 | AA11: 43440.168 | AB11: 44030.421 | AC11: 44621.462 | AD11: 45223.111 | AE11: 45836.516 | AF11: 46461.581 | AG11: 47097.977 | AH11: 47745.319 | AI11: 48403.224 | AJ11: 49071.343 | AK11: 49749.385 | AL11: 50404.594 | AM11: 51074.995 | AN11: 51755.378 | AO11: 52445.353 | AP11: 53145.014 | AQ11: 53854.42 | AR11: 54573.566 | AS11: 55302.4 | AT11: 56040.851 | AU11: 56788.848 | AV11: 57549.282 | AW11: 58318.645 | AX11: 59097.396 | AY11: 59885.584 | AZ11: 60683.253 | BA11: 61490.486 | BB11: 62307.398 | BC11: 63134.125 | BD11: 63970.818 | BE11: 64817.628
A12: va_sgla_2 | B12: 7734.1322 | C12: 7806.8146 | D12: 7888.8618 | E12: 7981.809 | F12: 8084.2674 | G12: 8194.4004 | H12: 8305.7651 | I12: 8420.9373 | J12: 8539.3898 | K12: 8660.7625 | L12: 8793.2317 | M12: 8921.3735 | N12: 9051.3318 | O12: 9182.9418 | P12: 9316.2373 | Q12: 9451.324 | R12: 9587.5487 | S12: 9725.8234 | T12: 9866.3155 | U12: 10009.222 | V12: 10148.525 | W12: 10294.913 | X12: 10444.463 | Y12: 10597.333 | Z12: 10753.586 | AA12: 10895.469 | AB12: 11044.963 | AC12: 11195.936 | AD12: 11348.823 | AE12: 11503.885 | AF12: 11661.294 | AG12: 11821.34 | AH12: 11983.907 | AI12: 12148.993 | AJ12: 12316.55 | AK12: 12486.507 | AL12: 12656.135 | AM12: 12826.792 | AN12: 12998.572 | AO12: 13171.54 | AP12: 13345.753 | AQ12: 13521.534 | AR12: 13698.709 | AS12: 13877.317 | AT12: 14057.373 | AU12: 14238.882 | AV12: 14423.126 | AW12: 14609.089 | AX12: 14796.757 | AY12: 14986.082 | AZ12: 15177.031 | BA12: 15370.16 | BB12: 15565.011 | BC12: 15761.611 | BD12: 15959.977 | BE12: 16160.141
... A79: va_ser_0 | B79: 1513908.6 | C79: 1533424.8 | D79: 1554985.3 | E79: 1577934.7 | F79: 1602168.7 | G79: 1627543.1 | H79: 1652794.8 | I79: 1678634.3 | J79: 1705033 | K79: 1731961.3 | L79: 1761370.5 | M79: 1789801.2 | N79: 1818562.8 | O79: 1847650.8 | P79: 1877062.3 | Q79: 1906801.4 | R79: 1936879 | S79: 1967310.2 | T79: 1998112.8 | U79: 2029304.9 | V79: 2059429.2 | W79: 2091056 | X79: 2123211.2 | Y79: 2155898.5 | Z79: 2189122.1 | AA79: 2218614.3 | AB79: 2249735.5 | AC79: 2281077.2 | AD79: 2312721.5 | AE79: 2344742.3 | AF79: 2377197.5 | AG79: 2410128.3 | AH79: 2443561.5 | AI79: 2477512.6 | AJ79: 2511989.2 | AK79: 2546994.4 | AL79: 2581490.8 | AM79: 2616224.2 | AN79: 2651253.5 | AO79: 2686630.4 | AP79: 2722401.7 | AQ79: 2758607.3 | AR79: 2795279.7 | AS79: 2832443.8 | AT79: 2870118.2 | AU79: 2908316.4 | AV79: 2947143.2 | AW79: 2986539.7 | AX79: 3026507.9 | AY79: 3067045.5 | AZ79: 3108151.2 | BA79: 3149826.4 | BB79: 3192074.5 | BC79: 3234900.7 | BD79: 3278311.8 | BE79: 3322315.4

Sheet INV
A1: _date_ | B1: 42005 | C1: 42370 | D1: 42736 | E1: 43101 | F1: 43466 | G1: 43831 | H1: 44197 | I1: 44562 | J1: 44927 | K1: 45292 | L1: 45658 | M1: 46023 | N1: 46388 | O1: 46753 | P1: 47119 | Q1: 47484 | R1: 47849 | S1: 48214 | T1: 48580 | U1: 48945 | V1: 49310 | W1: 49675 | X1: 50041 | Y1: 50406 | Z1: 50771 | AA1: 51136 | AB1: 51502 | AC1: 51867 | AD1: 52232 | AE1: 52597 | AF1: 52963 | AG1: 53328 | AH1: 53693 | AI1: 54058 | AJ1: 54424 | AK1: 54789 | AL1: 55154 | AM1: 55519 | AN1: 55885 | AO1: 56250 | AP1: 56615 | AQ1: 56980 | AR1: 57346 | AS1: 57711 | AT1: 58076 | AU1: 58441 | AV1: 58807 | AW1: 59172 | AX1: 59537 | AY1: 59902 | AZ1: 60268 | BA1: 60633 | BB1: 60998 | BC1: 61363 | BD1: 61729 | BE1: 62094
A2: ia_2 | B2: 467598.36 | C2: 470141.5 | D2: 474240.08 | E2: 479286.5 | F2: 484961.96 | G2: 491105.09 | H2: 497438.95 | I2: 503973.31 | J2: 510722.56 | K2: 517693.56 | L2: 525221.06 | M2: 532864.51 | N2: 540651.39 | O2: 548605.27 | P2: 556738.11 | Q2: 565057.18 | R2: 573544.02 | S2: 582214.08 | T2: 591078.48 | U2: 600145.16 | V2: 609173.75 | W2: 618472.61 | X2: 628029.23 | Y2: 637829.98 | Z2: 647867.42 | AA2: 657426 | AB2: 667049.82 | AC2: 676762.07 | AD2: 686568.27 | AE2: 696476.03 | AF2: 706493.04 | AG2: 716630.95 | AH2: 726891.05 | AI2: 737272.84 | AJ2: 747774.26 | AK2: 758392.12 | AL2: 769001.64 | AM2: 779618.61 | AN2: 790255.99 | AO2: 800921.93 | AP2: 811622.89 | AQ2: 822373.15 | AR2: 833175.68 | AS2: 844033.67 | AT2: 854950.2 | AU2: 865927.96 | AV2: 877013.47 | AW2: 888196.56 | AX2: 899470.5 | AY2: 910831.77 | AZ2: 922279.06 | BA2: 933830.95 | BB2: 945483.74 | BC2: 957236.25 | BD2: 969089.38 | BE2: 981045.54
A3: ia_0 | B3: 473222.2 | C3: 479535.72 | D3: 486404.22 | E3: 493756.32 | F3: 501524.7 | G3: 509663.85 | H3: 517948.18 | I3: 526410.66 | J3: 535078.53 | K3: 543968.31 | L3: 553440.24 | M3: 563065.29 | N3: 572866.75 | O3: 582865.14 | P3: 593069.48 | Q3: 603483.73 | R3: 614110.22 | S3: 624950.97 | T3: 636007.83 | U3: 647282.28 | V3: 658510.55 | W3: 670018.11 | X3: 681788.45 | Y3: 693804.72 | Z3: 706056.9 | AA3: 717765.83 | AB3: 729504.46 | AC3: 741298.7 | AD3: 753155.01 | AE3: 765081.61 | AF3: 777086.36 | AG3: 789174.87 | AH3: 801349.8 | AI3: 813611.06 | AJ3: 825956.42 | AK3: 838382.36 | AL3: 850694.97 | AM3: 862930.72 | AN3: 875116.27 | AO3: 887268.73 | AP3: 899400.96 | AQ3: 911523.87 | AR3: 923647.13 | AS3: 935779.37 | AT3: 947928.25 | AU3: 960100.69 | AV3: 972320.43 | AW3: 984590.04 | AX3: 996913.13 | AY3: 1009294.2 | AZ3: 1021738.4 | BA3: 1034252 | BB3: 1046841.9 | BC3: 1059515.9 | BD3: 1072282.8 | BE3: 1085151.5
A4: ia_sagr_2 | B4: 4209.812 | C4: 4211.1329 | D4: 4226.4673 | E4: 4253.1018 | F4: 4289.1863 | G4: 4333.3282 | H4: 4382.5945 | I4: 4436.4605 | J4: 4494.4743 | K4: 4556.1772 | L4: 4624.1778 | M4: 4694.1429 | N4: 4765.9483 | O4: 4839.5375 | P4: 4914.8215 | Q4: 4991.7255 | R4: 5069.8904 | S4: 5149.4537 | T4: 5230.4833 | U4: 5313.0229 | V4: 5394.8551 | W4: 5478.6846 | X4: 5564.5077 | Y4: 5652.2445 | Z4: 5741.8496 | AA4: 5826.7854 | AB4: 5911.7851 | AC4: 5997.2401 | AD4: 6083.3586 | AE4: 6170.3555 | AF4: 6258.4287 | AG4: 6347.8134 | AH4: 6438.5855 | AI4: 6530.7995 | AJ4: 6624.4852 | AK4: 6719.6536 | AL4: 6815.4207 | AM4: 6911.7215 | AN4: 7008.6717 | AO4: 7106.3941 | AP4: 7205.0112 | AQ4: 7304.7567 | AR4: 7405.6843 | AS4: 7507.8594 | AT4: 7611.3384 | AU4: 7716.1646 | AV4: 7822.9162 | AW4: 7931.4084 | AX4: 8041.5496 | AY4: 8153.2838 | AZ4: 8266.5768 | BA4: 8381.6673 | BB4: 8498.4319 | BC4: 8616.8178 | BD4: 8736.7999 | BE4: 8858.3703
A5: ia_sagr_0 | B5: 4277.0312 | C5: 4320.7152 | D5: 4365.7292 | E5: 4416.0705 | F5: 4472.6043 | G5: 4534.9911 | H5: 4600.7215 | I5: 4669.4997 | J5: 4741.0905 | K5: 4815.2656 | L5: 4895.0494 | M5: 4976.3873 | N5: 5059.1779 | O5: 5143.4196 | P5: 5229.0682 | Q5: 5316.0787 | R5: 5404.426 | S5: 5494.1065 | T5: 5585.1314 | U5: 5677.5202 | V5: 5768.8726 | W5: 5862.1044 | X5: 5957.2009 | Y5: 6054.0817 | Z5: 6152.7081 | AA5: 6246.0089 | AB5: 6339.0182 | AC5: 6432.2139 | AD5: 6525.8521 | AE5: 6620.1901 | AF5: 6715.4601 | AG5: 6811.8467 | AH5: 6909.4823 | AI5: 7008.4531 | AJ5: 7108.8104 | AK5: 7210.5816 | AL5: 7312.0553 | AM5: 7413.5568 | AN5: 7515.389 | AO5: 7617.7894 | AP5: 7720.9615 | AQ5: 7825.0843 | AR5: 7930.3119 | AS5: 8036.7717 | AT5: 8144.5655 | AU5: 8253.7726 | AV5: 8364.6139 | AW5: 8477.1143 | AX5: 8591.2912 | AY5: 8707.1504 | AZ5: 8824.6933 | BA5: 8943.9253 | BB5: 9064.8587 | BC5: 9187.5116 | BD5: 9311.906 | BE5: 9438.0671
A6: ia_sfor_2 | B6: 165.28249 | C6: 165.22195 | D6: 164.63047 | E6: 163.82943 | F6: 162.99332 | G6: 162.18475 | H6: 161.34693 | I6: 160.47715 | J6: 159.58509 | K6: 158.6887 | L6: 157.88521 | M6: 157.07602 | N6: 156.28466 | O6: 155.53299 | P6: 154.83439 | Q6: 154.19593 | R6: 153.6063 | S6: 153.07536 | T6: 152.60826 | U6: 152.20797 | V6: 151.8245 | W6: 151.52723 | X6: 151.31456 | Y6: 151.17991 | Z6: 151.11876 | AA6: 150.98622 | AB6: 150.90926 | AC6: 150.89949 | AD6: 150.95541 | AE6: 151.07417 | AF6: 151.25365 | AG6: 151.49589 | AH6: 151.7979 | AI6: 152.15774 | AJ6: 152.57388 | AK6: 153.04504 | AL6: 153.56931 | AM6: 154.13904 | AN6: 154.75385 | AO6: 155.41285 | AP6: 156.11506 | AQ6: 156.86475 | AR6: 157.6585 | AS6: 158.49437 | AT6: 159.37096 | AU6: 160.28726 | AV6: 161.26291 | AW6: 162.28707 | AX6: 163.35387 | AY6: 164.45952 | AZ6: 165.6018 | BA6: 166.7906 | BB6: 168.01919 | BC6: 169.2842 | BD6: 170.58346 | BE6: 171.9157
A7: ia_sfor_0 | B7: 166.98641 | C7: 167.34689 | D7: 166.9176 | E7: 166.16673 | F7: 165.29674 | G7: 164.45417 | H7: 163.66699 | I7: 162.96985 | J7: 162.36646 | K7: 161.84455 | L7: 161.46934 | M7: 161.12375 | N7: 160.80235 | O7: 160.51063 | P7: 160.25292 | Q7: 160.03178 | R7: 159.84878 | S7: 159.705 | T7: 159.60128 | U7: 159.53832 | V7: 159.46302 | W7: 159.44707 | X7: 159.48881 | Y7: 159.58167 | Z7: 159.72114 | AA7: 159.756 | AB7: 159.81245 | AC7: 159.90662 | AD7: 160.03964 | AE7: 160.2104 | AF7: 160.41784 | AG7: 160.66111 | AH7: 160.93946 | AI7: 161.25218 | AJ7: 161.59856 | AK7: 161.97791 | AL7: 162.35631 | AM7: 162.74419 | AN7: 163.15058 | AO7: 163.58061 | AP7: 164.03694 | AQ7: 164.5209 | AR7: 165.0332 | AS7: 165.57412 | AT7: 166.14341 | AU7: 166.73957 | AV7: 167.35854 | AW7: 167.99511 | AX7: 168.64833 | AY7: 169.32103 | AZ7: 170.01715 | BA7: 170.73914 | BB7: 171.48756 | BC7: 172.26181 | BD7: 173.06092 | BE7: 173.88399
A8: ia_sfoo_2 | B8: 6664.4738 | C8: 6683.2027 | D8: 6719.8701 | E8: 6771.4058 | F8: 6835.8594 | G8: 6911.6796 | H8: 6994.7589 | I8: 7084.4554 | J8: 7180.217 | K8: 7281.4489 | L8: 7392.3048 | M8: 7506.4 | N8: 7623.37 | O8: 7743.0364 | P8: 7865.2156 | Q8: 7989.7631 | R8: 8116.2259 | S8: 8244.6913 | T8: 8375.2009 | U8: 8507.7735 | V8: 8638.903 | W8: 8772.625 | X8: 8908.9781 | Y8: 9047.8544 | Z8: 9189.1727 | AA8: 9322.7082 | AB8: 9455.3576 | AC8: 9587.8072 | AD8: 9720.4508 | AE8: 9853.6749 | AF8: 9987.8249 | AG8: 10123.261 | AH8: 10260.152 | AI8: 10398.612 | AJ8: 10538.71 | AK8: 10680.482 | AL8: 10822.263 | AM8: 10964.125 | AN8: 11106.301 | AO8: 11249.034 | AP8: 11392.564 | AQ8: 11537.248 | AR8: 11683.252 | AS8: 11830.726 | AT8: 11979.793 | AU8: 12130.548 | AV8: 12283.719 | AW8: 12439.189 | AX8: 12596.877 | AY8: 12756.731 | AZ8: 12918.722 | BA8: 13083.114 | BB8: 13249.821 | BC8: 13418.798 | BD8: 13590.028 | BE8: 13763.514
A9: ia_sfoo_0 | B9: 6750.3397 | C9: 6827.7393 | D9: 6909.1186 | E9: 6998.4141 | F9: 7096.5154 | G9: 7202.983 | H9: 7314.1518 | I9: 7429.6616 | J9: 7549.27 | K9: 7672.7376 | L9: 7804.841 | M9: 7939.5708 | N9: 8076.682 | O9: 8216.1068 | P9: 8357.7433 | Q9: 8501.5032 | R9: 8647.3337 | S9: 8795.2145 | T9: 8945.1471 | U9: 9097.1438 | V9: 9247.4493 | W9: 9400.4187 | X9: 9556.1029 | Y9: 9714.4207 | Z9: 9875.3224 | AA9: 10027.782 | AB9: 10179.161 | AC9: 10330.24 | AD9: 10481.491 | AE9: 10633.375 | AF9: 10786.297 | AG9: 10940.581 | AH9: 11096.462 | AI9: 11254.099 | AJ9: 11413.594 | AK9: 11575.012 | AL9: 11735.706 | AM9: 11896.09 | AN9: 12056.608 | AO9: 12217.647 | AP9: 12379.557 | AQ9: 12542.657 | AR9: 12707.224 | AS9: 12873.494 | AT9: 13041.657 | AU9: 13211.867 | AV9: 13384.494 | AW9: 13559.614 | AX9: 13737.282 | AY9: 13917.526 | AZ9: 14100.364 | BA9: 14285.82 | BB9: 14473.93 | BC9: 14664.738 | BD9: 14858.295 | BE9: 15054.655
A10: ia_sveh_2 | B10: 35172.373 | C10: 35273.427 | D10: 35747.979 | E10: 36345.265 | F10: 36963.39 | G10: 37566.469 | H10: 38122.386 | I10: 38647.183 | J10: 39152.274 | K10: 39645.137 | L10: 40170.226 | M10: 40663.135 | N10: 41141.388 | O10: 41613.658 | P10: 42084.104 | Q10: 42555.128 | R10: 43022.997 | S10: 43492.496 | T10: 43966.206 | U10: 44445.722 | V10: 44903.732 | W10: 45385.995 | X10: 45884.399 | Y10: 46395.336 | Z10: 46917.597 | AA10: 47369.968 | AB10: 47843.603 | AC10: 48333.423 | AD10: 48836.688 | AE10: 49352.444 | AF10: 49880.288 | AG10: 50421.154 | AH10: 50974.007 | AI10: 51538.222 | AJ10: 52113.344 | AK10: 52698.995 | AL10: 53286.567 | AM10: 53879.978 | AN10: 54481.194 | AO10: 55091.036 | AP10: 55709.828 | AQ10: 56339.418 | AR10: 56978.802 | AS10: 57627.524 | AT10: 58285.343 | AU10: 58952.109 | AV10: 59635.302 | AW10: 60330.475 | AX10: 61035.718 | AY10: 61750.242 | AZ10: 62473.728 | BA10: 63209.781 | BB10: 63956.302 | BC10: 64712.491 | BD10: 65478.1 | BE10: 66253.105
A11: ia_sveh_0 | B11: 36399.484 | C11: 37040.509 | D11: 37801.139 | E11: 38594.48 | F11: 39375.376 | G11: 40130.149 | H11: 40836.401 | I11: 41514.949 | J11: 42179.595 | K11: 42838.946 | L11: 43541.249 | M11: 44222.394 | N11: 44897.277 | O11: 45573.238 | P11: 46253.62 | Q11: 46940.216 | R11: 47634.217 | S11: 48336.566 | T11: 49048.086 | U11: 49769.516 | V11: 50469.468 | W11: 51198.715 | X11: 51947.895 | Y11: 52712.774 | Z11: 53491.808 | AA11: 54191.715 | AB11: 54913.566 | AC11: 55652.967 | AD11: 56407.381 | AE11: 57175.955 | AF11: 57958.321 | AG11: 58754.188 | AH11: 59563.24 | AI11: 60385.128 | AJ11: 61219.5 | AK11: 62066.025 | AL11: 62901.884 | AM11: 63739.398 | AN11: 64584.045 | AO11: 65438.102 | AP11: 66302.561 | AQ11: 67177.858 | AR11: 68064.173 | AS11: 68961.553 | AT11: 69869.98 | AU11: 70789.408 | AV11: 71721.833 | AW11: 72666.079 | AX11: 73621.629 | AY11: 74588.293 | AZ11: 75566.036 | BA11: 76554.914 | BB11: 77555.042 | BC11: 78566.578 | BD11: 79589.708 | BE11: 80624.636
A12: ia_sgla_2 | B12: 1437.014 | C12: 1443.3899 | D12: 1455.3794 | E12: 1470.7927 | F12: 1488.4228 | G12: 1507.6121 | H12: 1527.4517 | I12: 1547.8648 | J12: 1568.845 | K12: 1590.3923 | L12: 1613.4309 | M12: 1636.7616 | N12: 1660.4393 | O12: 1684.539 | P12: 1709.1117 | Q12: 1734.1976 | R12: 1759.7455 | S12: 1785.8305 | T12: 1812.5107 | U12: 1839.8318 | V12: 1867.1494 | W12: 1895.3036 | X12: 1924.3054 | Y12: 1954.1365 | Z12: 1984.7871 | AA12: 2014.2897 | AB12: 2044.0652 | AC12: 2074.218 | AD12: 2104.7743 | AE12: 2135.7554 | AF12: 2167.1792 | AG12: 2199.0771 | AH12: 2231.4431 | AI12: 2264.2653 | AJ12: 2297.527 | AK12: 2331.2073 | AL12: 2364.996 | AM12: 2398.878 | AN12: 2432.8605 | AO12: 2466.9485 | AP12: 2501.1456 | AQ12: 2535.4872 | AR12: 2569.9677 | AS12: 2604.5849 | AT12: 2639.3379 | AU12: 2674.2265 | AV12: 2709.3998 | AW12: 2744.8151 | AX12: 2780.4422 | AY12: 2816.2629 | AZ12: 2852.2679 | BA12: 2888.5225 | BB12: 2925.0077 | BC12: 2961.7156 | BD12: 2998.6466 | BE12: 3035.8077
... A79: ia_ser_0 | B79: 219751.97 | C79: 222616.74 | D79: 225704.59 | E79: 229017.54 | F79: 232539.38 | G79: 236250.16 | H79: 240029.62 | I79: 243893.48 | J79: 247851.33 | K79: 251906.65 | L79: 256240.84 | M79: 260620.41 | N79: 265059.5 | O79: 269568.37 | P79: 274150.21 | Q79: 278805.63 | R79: 283534.8 | S79: 288338.08 | T79: 293216.04 | U79: 298169.31 | V79: 303062.07 | W79: 308069.12 | X79: 313178.67 | Y79: 318381.26 | Z79: 323672.5 | AA79: 328652.71 | AB79: 333638.88 | AC79: 338644.33 | AD79: 343673.95 | AE79: 348735.15 | AF79: 353835.65 | AG79: 358981.93 | AH79: 364178.76 | AI79: 369429.32 | AJ79: 374735.56 | AK79: 380098.62 | AL79: 385421.92 | AM79: 390732.23 | AN79: 396048.08 | AO79: 401381.59 | AP79: 406742.04 | AQ79: 412137.34 | AR79: 417574.29 | AS79: 423058.72 | AT79: 428595.5 | AU79: 434188.67 | AV79: 439850.55 | AW79: 445581.87 | AX79: 451383.82 | AY79: 457257.57 | AZ79: 463204.34 | BA79: 469225.58 | BB79: 475322.99 | BC79: 481498.51 | BD79: 487754.24 | BE79: 494092.39

Sheet Labor
A1: _date_ | B1: 42005 | C1: 42370 | D1: 42736 | E1: 43101 | F1: 43466 | G1: 43831 | H1: 44197 | I1: 44562 | J1: 44927 | K1: 45292 | L1: 45658 | M1: 46023 | N1: 46388 | O1: 46753 | P1: 47119 | Q1: 47484 | R1: 47849 | S1: 48214 | T1: 48580 | U1: 48945 | V1: 49310 | W1: 49675 | X1: 50041 | Y1: 50406 | Z1: 50771 | AA1: 51136 | AB1: 51502 | AC1: 51867 | AD1: 52232 | AE1: 52597 | AF1: 52963 | AG1: 53328 | AH1: 53693 | AI1: 54058 | AJ1: 54424 | AK1: 54789 | AL1: 55154 | AM1: 55519 | AN1: 55885 | AO1: 56250 | AP1: 56615 | AQ1: 56980 | AR1: 57346 | AS1: 57711 | AT1: 58076 | AU1: 58441 | AV1: 58807 | AW1: 59172 | AX1: 59537 | AY1: 59902 | AZ1: 60268 | BA1: 60633 | BB1: 60998 | BC1: 61363 | BD1: 61729 | BE1: 62094
A2: f_l_2 | B2: 27138.753 | C2: 26967.873 | D2: 26850.318 | E2: 26789.162 | F2: 26778.779 | G2: 26810.74 | H2: 26865.675 | I2: 26937.557 | J2: 27021.76 | K2: 27114.48 | L2: 27229.937 | M2: 27344.422 | N2: 27455.648 | O2: 27562.921 | P2: 27666.126 | Q2: 27765.44 | R2: 27860.65 | S2: 27952.297 | T2: 28041.026 | U2: 28127.467 | V2: 28200.759 | W2: 28274.948 | X2: 28350.815 | Y2: 28428.403 | Z2: 28507.597 | AA2: 28557.179 | AB2: 28599.344 | AC2: 28637.618 | AD2: 28674.153 | AE2: 28710.44 | AF2: 28747.509 | AG2: 28786.074 | AH2: 28826.516 | AI2: 28868.964 | AJ2: 28913.379 | AK2: 28959.618 | AL2: 29001.158 | AM2: 29039.217 | AN2: 29074.946 | AO2: 29109.257 | AP2: 29142.833 | AQ2: 29176.185 | AR2: 29209.703 | AS2: 29243.598 | AT2: 29277.963 | AU2: 29312.808 | AV2: 29348.587 | AW2: 29385.332 | AX2: 29422.871 | AY2: 29460.987 | AZ2: 29499.474 | BA2: 29538.1 | BB2: 29576.885 | BC2: 29615.774 | BD2: 29654.703 | BE2: 29693.621
A3: f_l_0 | B3: 27371.847 | C3: 27401.594 | D3: 27439.54 | E3: 27494.808 | F3: 27570.244 | G3: 27664.907 | H3: 27765.327 | I3: 27870.143 | J3: 27978.399 | K3: 28089.186 | L3: 28219.506 | M3: 28347.467 | N3: 28471.836 | O3: 28592.555 | P3: 28709.858 | Q3: 28824.084 | R3: 28935.63 | S3: 29044.92 | T3: 29152.379 | U3: 29258.41 | V3: 29351.548 | W3: 29446.072 | X3: 29542.635 | Y3: 29641.154 | Z3: 29741.393 | AA3: 29810.83 | AB3: 29872.117 | AC3: 29928.772 | AD3: 29982.965 | AE3: 30036.211 | AF3: 30089.559 | AG3: 30143.674 | AH3: 30198.911 | AI3: 30255.389 | AJ3: 30313.061 | AK3: 30371.779 | AL3: 30424.466 | AM3: 30472.143 | AN3: 30516.059 | AO3: 30557.312 | AP3: 30596.785 | AQ3: 30635.157 | AR3: 30672.922 | AS3: 30710.414 | AT3: 30747.841 | AU3: 30785.31 | AV3: 30823.416 | AW3: 30862.065 | AX3: 30901.118 | AY3: 30940.428 | AZ3: 30979.856 | BA3: 31019.296 | BB3: 31058.675 | BC3: 31097.954 | BD3: 31137.122 | BE3: 31176.19
