Workbook

Sheet Données
A1: Scénario 2 | B1: NZ50
A4: Macro | C4: 42005 | D4: 42370 | E4: 42736 | F4: 43101 | G4: 43466 | H4: 43831 | I4: 44197 | J4: 44562 | K4: 44927 | L4: 45292 | M4: 45658 | N4: 46023 | O4: 46388 | P4: 46753 | Q4: 47119 | R4: 47484 | S4: 47849 | T4: 48214 | U4: 48580 | V4: 48945 | W4: 49310 | X4: 49675 | Y4: 50041 | Z4: 50406 | AA4: 50771 | AB4: 51136 | AC4: 51502 | AD4: 51867 | AE4: 52232 | AF4: 52597 | AG4: 52963 | AH4: 53328 | AI4: 53693 | AJ4: 54058 | AK4: 54424 | AL4: 54789 | AM4: 55154 | AN4: 55519 | AO4: 55885 | AP4: 56250 | AQ4: 56615 | AR4: 56980 | AS4: 57346 | AT4: 57711 | AU4: 58076 | AV4: 58441 | AW4: 58807 | AX4: 59172 | AY4: 59537 | AZ4: 59902 | BA4: 60268 | BB4: 60633 | BC4: 60998 | BD4: 61363 | BE4: 61729 | BF4: 62094 | BG4: 62459 | BH4: 62824 | BI4: 63190 | BJ4: 63555 | BK4: 63920 | BL4: 64285 | BM4: 64651 | BN4: 65016 | BO4: 65381 | BP4: 65746 | BQ4: 66112 | BR4: 66477 | BS4: 66842 | BT4: 67207 | BU4: 67573 | BV4: 67938 | BW4: 68303 | BX4: 68668 | BY4: 69034 | BZ4: 69399 | CA4: 69764 | CB4: 70129 | CC4: 70495 | CD4: 70860 | CE4: 71225 | CF4: 71590 | CG4: 71956 | CH4: 72321 | CI4: 72686 | CJ4: 73051
A5: =[1]Results!E1365 -> 100*(GDP_2/GDP_0-1) | B5: PIB | C5: =[1]Results!F1365 -> 0 | D5: =[1]Results!G1365 -> 4.7013424e-05 | E5: =[1]Results!H1365 -> 9.9797017e-05 | F5: =[1]Results!I1365 -> 0.00015668266 | G5: =[1]Results!J1365 -> 0.00021584302 | H5: =[1]Results!K1365 -> 0.00027568373 | I5: =[1]Results!L1365 -> 0.00024921737 | J5: =[1]Results!M1365 -> -0.082360101 | ... CJ5: =[1]Results!CM1365 -> -7.4705744
A6: =[1]Results!E1366 -> 100*((VA_2-VA_spub_2)/(VA_0-VA_spub_0)-1) | B6: =[1]Results!C1366 -> VA du secteur marchand | C6: =[1]Results!F1366 -> 0 | D6: =[1]Results!G1366 -> 6.0803108e-05 | E6: =[1]Results!H1366 -> 0.00012681754 | F6: =[1]Results!I1366 -> 0.00019678698 | G6: =[1]Results!J1366 -> 0.00026874083 | H6: =[1]Results!K1366 -> 0.00034108411 | I6: =[1]Results!L1366 -> 0.00030105937 | J6: =[1]Results!M1366 -> -0.092689585 | ... CJ6: =[1]Results!CM1366 -> -8.9608559
A7: =[1]Results!E1367 -> 100*((CH_2-CH_0)/GDP_0) | B7: Consommation | C7: =[1]Results!F1367 -> 0 | D7: =[1]Results!G1367 -> 9.254611e-06 | E7: =[1]Results!H1367 -> 2.6942445e-05 | F7: =[1]Results!I1367 -> 5.1035076e-05 | G7: =[1]Results!J1367 -> 7.9492858e-05 | H7: =[1]Results!K1367 -> 0.00011034417 | I7: =[1]Results!L1367 -> 0.00012609264 | J7: =[1]Results!M1367 -> -0.084434967 | ... CJ7: =[1]Results!CM1367 -> -5.8921056
A8: =[1]Results!E1368 -> 100*((CH_cveh_2-CH_cveh_0)/GDP_0) | B8: =[1]Results!C1368 -> Consommation des ménages automobile | C8: =[1]Results!F1368 -> 0 | D8: =[1]Results!G1368 -> 8.3939321e-07 | E8: =[1]Results!H1368 -> 2.4042009e-06 | F8: =[1]Results!I1368 -> 4.3418306e-06 | G8: =[1]Results!J1368 -> 6.2990373e-06 | H8: =[1]Results!K1368 -> 8.0690829e-06 | I8: =[1]Results!L1368 -> 7.9609892e-06 | J8: =[1]Results!M1368 -> 0.028779482 | ... CJ8: =[1]Results!CM1368 -> -0.091318039
A9: =[1]Results!E1369 -> 100*((G_2-G_0)/GDP_0) | B9: =[1]Results!C1369 -> Dépenses publiques | C9: =[1]Results!F1369 -> 0 | D9: =[1]Results!G1369 -> 0 | E9: =[1]Results!H1369 -> 0 | F9: =[1]Results!I1369 -> 0 | G9: =[1]Results!J1369 -> 0 | H9: =[1]Results!K1369 -> 0 | I9: =[1]Results!L1369 -> 0 | J9: =[1]Results!M1369 -> 0 | ... CJ9: =[1]Results!CM1369 -> 0
A10: =[1]Results!E1370 -> 100*((I_2-I_0)/GDP_0) | B10: Investissement | C10: =[1]Results!F1370 -> 0 | D10: =[1]Results!G1370 -> 7.1121685e-06 | E10: =[1]Results!H1370 -> 1.8122002e-05 | F10: =[1]Results!I1370 -> 3.1245965e-05 | G10: =[1]Results!J1370 -> 4.5624516e-05 | H10: =[1]Results!K1370 -> 6.07423e-05 | I10: =[1]Results!L1370 -> 6.3426039e-05 | J10: =[1]Results!M1370 -> -0.0074561241 | ... CJ10: =[1]Results!CM1370 -> -2.6033725
A11: =[1]Results!E1371 -> 100*((DS_2-DS_0)/GDP_0) | B11: =[1]Results!C1371 -> Variations de stocks | C11: =[1]Results!F1371 -> 0 | D11: =[1]Results!G1371 -> 0 | E11: =[1]Results!H1371 -> 0 | F11: =[1]Results!I1371 -> 0 | G11: =[1]Results!J1371 -> 0 | H11: =[1]Results!K1371 -> 0 | I11: =[1]Results!L1371 -> 0 | J11: =[1]Results!M1371 -> 0 | ... CJ11: =[1]Results!CM1371 -> 0
A12: =[1]Results!E1372 -> 100*((X_2-X_0)/GDP_0)-100*((M_2-M_0)/GDP_0) | B12: Exportations nettes | C12: =[1]Results!F1372 -> 0 | D12: =[1]Results!G1372 -> 3.0646644e-05 | E12: =[1]Results!H1372 -> 5.477839e-05 | F12: =[1]Results!I1372 -> 7.4392566e-05 | G12: =[1]Results!J1372 -> 9.0716695e-05 | H12: =[1]Results!K1372 -> 0.00010462818 | I12: =[1]Results!L1372 -> 5.9698689e-05 | J12: =[1]Results!M1372 -> 0.0095309983 | ... CJ12: =[1]Results!CM1372 -> 1.0249037
A13: =[1]Results!E1373 -> 100*((CH_2-CH_ccon_2-(CH_0-CH_ccon_0))/GDP_0) | B13: =[1]Results!C1373 -> Consommation des ménages | C13: =[1]Results!F1373 -> 0 | D13: =[1]Results!G1373 -> 9.7589873e-06 | E13: =[1]Results!H1373 -> 2.8303314e-05 | F13: =[1]Results!I1373 -> 5.3270294e-05 | G13: =[1]Results!J1373 -> 8.2432796e-05 | H13: =[1]Results!K1373 -> 0.00011389303 | I13: =[1]Results!L1373 -> 0.00012893442 | J13: =[1]Results!M1373 -> -0.079022591 | ... CJ13: =[1]Results!CM1373 -> -5.900535
A14: =[1]Results!E1374 -> 100*((I_2+CH_ccon_2-(I_0+CH_ccon_0))/GDP_0) | B14: Investissement | C14: =[1]Results!F1374 -> 0 | D14: =[1]Results!G1374 -> 6.6077922e-06 | E14: =[1]Results!H1374 -> 1.6761134e-05 | F14: =[1]Results!I1374 -> 2.9010746e-05 | G14: =[1]Results!J1374 -> 4.2684578e-05 | H14: =[1]Results!K1374 -> 5.719344e-05 | I14: =[1]Results!L1374 -> 6.0584262e-05 | J14: =[1]Results!M1374 -> -0.0128685 | ... CJ14: =[1]Results!CM1374 -> -2.594943
A15: =[1]Results!E1375 -> 100*((I_2-IA_spub_2-(I_0-IA_spub_0))/GDP_0) | B15: =[1]Results!C1375 -> Investissement entreprises | C15: =[1]Results!F1375 -> 0 | D15: =[1]Results!G1375 -> 6.8271265e-06 | E15: =[1]Results!H1375 -> 1.7340304e-05 | F15: =[1]Results!I1375 -> 2.9823141e-05 | G15: =[1]Results!J1375 -> 4.3459823e-05 | H15: =[1]Results!K1375 -> 5.7758413e-05 | I15: =[1]Results!L1375 -> 6.0074916e-05 | J15: =[1]Results!M1375 -> -0.0099703878 | ... CJ15: =[1]Results!CM1375 -> -2.4954148
A16: =[1]Results!E1376 -> 100*((CH_ccon_2-CH_ccon_0)/GDP_0) | B16: =[1]Results!C1376 -> Investissement ménages | C16: =[1]Results!F1376 -> 0 | D16: =[1]Results!G1376 -> -5.043763e-07 | E16: =[1]Results!H1376 -> -1.3608684e-06 | F16: =[1]Results!I1376 -> -2.2352186e-06 | G16: =[1]Results!J1376 -> -2.9399384e-06 | H16: =[1]Results!K1376 -> -3.5488593e-06 | I16: =[1]Results!L1376 -> -2.8417763e-06 | J16: =[1]Results!M1376 -> -0.005412376 | ... CJ16: =[1]Results!CM1376 -> 0.0084294322
A17: =[1]Results!E1377 -> 100*((IA_spub_2-IA_spub_0)/GDP_0) | B17: =[1]Results!C1377 -> Investissement public | C17: =[1]Results!F1377 -> 0 | D17: =[1]Results!G1377 -> 2.8504202e-07 | E17: =[1]Results!H1377 -> 7.8169748e-07 | F17: =[1]Results!I1377 -> 1.4228235e-06 | G17: =[1]Results!J1377 -> 2.164693e-06 | H17: =[1]Results!K1377 -> 2.9838865e-06 | I17: =[1]Results!L1377 -> 3.3511225e-06 | J17: =[1]Results!M1377 -> 0.0025142637 | ... CJ17: =[1]Results!CM1377 -> -0.10795765
A18: =[1]Results!E1378 -> 100*(CH_2/CH_0-1) | B18: =[1]Results!C1378 -> Consommation des ménages | C18: =[1]Results!F1378 -> 0 | D18: =[1]Results!G1378 -> 1.667196e-05 | E18: =[1]Results!H1378 -> 4.8472668e-05 | F18: =[1]Results!I1378 -> 9.1729309e-05 | G18: =[1]Results!J1378 -> 0.0001429503 | H18: =[1]Results!K1378 -> 0.00019872419 | I18: =[1]Results!L1378 -> 0.00022766086 | J18: =[1]Results!M1378 -> -0.15281255 | ... CJ18: =[1]Results!CM1378 -> -10.420639
A19: =[1]Results!E1379 -> 100*(CH_cveh_2/CH_cveh_0-1) | B19: =[1]Results!C1379 -> Consommation des ménages automobile | C19: =[1]Results!F1379 -> 0 | D19: =[1]Results!G1379 -> 2.7803906e-05 | E19: =[1]Results!H1379 -> 7.6078422e-05 | F19: =[1]Results!I1379 -> 0.00013336858 | G19: =[1]Results!J1379 -> 0.00018950595 | H19: =[1]Results!K1379 -> 0.00024021219 | I19: =[1]Results!L1379 -> 0.00023928835 | J19: =[1]Results!M1379 -> 0.88820428 | ... CJ19: =[1]Results!CM1379 -> -5.6892266
A20: =[1]Results!E1380 -> 100*(G_2/G_0-1) | B20: =[1]Results!C1380 -> Dépenses publiques | C20: =[1]Results!F1380 -> 0 | D20: =[1]Results!G1380 -> 0 | E20: =[1]Results!H1380 -> 0 | F20: =[1]Results!I1380 -> 0 | G20: =[1]Results!J1380 -> 0 | H20: =[1]Results!K1380 -> 0 | I20: =[1]Results!L1380 -> 0 | J20: =[1]Results!M1380 -> 0 | ... CJ20: =[1]Results!CM1380 -> 0
A21: =[1]Results!E1381 -> 100*(I_2/I_0-1) | B21: =[1]Results!C1381 -> Investissement | C21: =[1]Results!F1381 -> 0 | D21: =[1]Results!G1381 -> 3.2981357e-05 | E21: =[1]Results!H1381 -> 8.4490632e-05 | F21: =[1]Results!I1381 -> 0.00014610963 | G21: =[1]Results!J1381 -> 0.00021352959 | H21: =[1]Results!K1381 -> 0.0002842929 | I21: =[1]Results!L1381 -> 0.00029679564 | J21: =[1]Results!M1381 -> -0.034908864 | ... CJ21: =[1]Results!CM1381 -> -11.416629
A22: =[1]Results!E1382 -> 100*((I_2-IA_spub_2)/(I_0-IA_spub_0)-1) | B22: =[1]Results!C1382 -> Investissement entreprises | C22: =[1]Results!F1382 -> 0 | D22: =[1]Results!G1382 -> 3.7980434e-05 | E22: =[1]Results!H1382 -> 9.7113709e-05 | F22: =[1]Results!I1382 -> 0.00016767463 | G22: =[1]Results!J1382 -> 0.00024473601 | H22: =[1]Results!K1382 -> 0.0003254536 | I22: =[1]Results!L1382 -> 0.00033859662 | J22: =[1]Results!M1382 -> -0.056235943 | ... CJ22: =[1]Results!CM1382 -> -13.130746
A23: =[1]Results!E1383 -> 100*(X_2/X_0-1) | B23: Exports | C23: =[1]Results!F1383 -> 0 | D23: =[1]Results!G1383 -> 0.00016316138 | E23: =[1]Results!H1383 -> 0.00031624936 | F23: =[1]Results!I1383 -> 0.00045931137 | G23: =[1]Results!J1383 -> 0.00059293092 | H23: =[1]Results!K1383 -> 0.00071788859 | I23: =[1]Results!L1383 -> 0.00054175819 | J23: =[1]Results!M1383 -> 0.22568633 | ... CJ23: =[1]Results!CM1383 -> -1.5521656
A24: =[1]Results!E1384 -> 100*(M_2/M_0-1) | B24: Imports | C24: =[1]Results!F1384 -> 0 | D24: =[1]Results!G1384 -> 5.1103827e-05 | E24: =[1]Results!H1384 -> 0.00011548695 | F24: =[1]Results!I1384 -> 0.0001859978 | G24: =[1]Results!J1384 -> 0.00025950378 | H24: =[1]Results!K1384 -> 0.0003339943 | I24: =[1]Results!L1384 -> 0.00031683749 | J24: =[1]Results!M1384 -> 0.18271424 | ... CJ24: =[1]Results!CM1384 -> -4.9593841
A25: =[1]Results!E1385 -> 100*((CH_2-CH_ccon_2)/(CH_0-CH_ccon_0)-1) | B25: =[1]Results!C1385 -> Consommation des ménages | C25: =[1]Results!F1385 -> 0 | D25: =[1]Results!G1385 -> 1.8135687e-05 | E25: =[1]Results!H1385 -> 5.325649e-05 | F25: =[1]Results!I1385 -> 0.00010066716 | G25: =[1]Results!J1385 -> 0.0001559056 | H25: =[1]Results!K1385 -> 0.00021537263 | I25: =[1]Results!L1385 -> 0.00024394257 | J25: =[1]Results!M1385 -> -0.1495991 | ... CJ25: =[1]Results!CM1385 -> -10.565111
A26: =[1]Results!E1386 -> 100*((I_2+CH_ccon_2)/(I_0+CH_ccon_0)-1) | B26: =[1]Results!C1386 -> Investissement | C26: =[1]Results!F1386 -> 0 | D26: =[1]Results!G1386 -> 2.8404383e-05 | E26: =[1]Results!H1386 -> 7.0171355e-05 | F26: =[1]Results!I1386 -> 0.00012035335 | G26: =[1]Results!J1386 -> 0.0001770994 | H26: =[1]Results!K1386 -> 0.0002382014 | I26: =[1]Results!L1386 -> 0.00025346908 | J26: =[1]Results!M1386 -> -0.054092351 | ... CJ26: =[1]Results!CM1386 -> -11.043842
A27: =[1]Results!E1387 -> 100*((CH_ccon_2)/(CH_ccon_0)-1) | B27: =[1]Results!C1387 -> Investissement ménages | C27: =[1]Results!F1387 -> 0 | D27: =[1]Results!G1387 -> -2.9685339e-05 | E27: =[1]Results!H1387 -> -5.5831163e-05 | F27: =[1]Results!I1387 -> -8.2196618e-05 | G27: =[1]Results!J1387 -> -0.00010748493 | H27: =[1]Results!K1387 -> -0.00013420072 | I27: =[1]Results!L1387 -> -0.0001122451 | J27: =[1]Results!M1387 -> -0.22263599 | ... CJ27: =[1]Results!CM1387 -> 1.2156574
A28: =[1]Results!E1388 -> 100*((IA_spub_2)/(IA_spub_0)-1) | B28: =[1]Results!C1388 -> Investissement public | C28: =[1]Results!F1388 -> 0 | D28: =[1]Results!G1388 -> 7.9424759e-06 | E28: =[1]Results!H1388 -> 2.1756953e-05 | F28: =[1]Results!I1388 -> 3.9534183e-05 | G28: =[1]Results!J1388 -> 5.998045e-05 | H28: =[1]Results!K1388 -> 8.244949e-05 | I28: =[1]Results!L1388 -> 9.236967e-05 | J28: =[1]Results!M1388 -> 0.069277523 | ... CJ28: =[1]Results!CM1388 -> -2.8417592
A29: =[1]Results!E1389 -> 100*(DISPINC_AT_VAL_2/DISPINC_AT_VAL_0-1) | B29: =[1]Results!C1389 -> Revenu disponible des ménages | C29: =[1]Results!F1389 -> 0 | D29: =[1]Results!G1389 -> 2.1614482e-05 | E29: =[1]Results!H1389 -> 5.9297036e-05 | F29: =[1]Results!I1389 -> 0.00010825505 | G29: =[1]Results!J1389 -> 0.00016488343 | H29: =[1]Results!K1389 -> 0.00022617948 | I29: =[1]Results!L1389 -> 0.00025096914 | J29: =[1]Results!M1389 -> -0.84718849 | ... CJ29: =[1]Results!CM1389 -> -12.831545
A30: =[1]Results!E1390 -> 100*(DISPINC_AT_VAL_2/DISPINC_AT_VAL_0-1)-100*(PCH_2/PCH_0-1) | B30: =[1]Results!C1390 -> Revenu disponible réel des ménages | C30: =[1]Results!F1390 -> 0 | D30: =[1]Results!G1390 -> 1.8544169e-05 | E30: =[1]Results!H1390 -> 5.1355397e-05 | F30: =[1]Results!I1390 -> 9.3019723e-05 | G30: =[1]Results!J1390 -> 0.00013967688 | H30: =[1]Results!K1390 -> 0.00018908502 | I30: =[1]Results!L1390 -> 0.0002065904 | J30: =[1]Results!M1390 -> -0.21716967 | ... CJ30: =[1]Results!CM1390 -> -9.3562568
A31: =[1]Results!E1391 -> 100*(DISPINC_AT_VAL_2/DISPINC_AT_VAL_0-1)-100*((F_L_2/F_L_0)-1) | B31: =[1]Results!C1391 -> Revenu disponible par emploi en valeur | C31: =[1]Results!F1391 -> 0 | D31: =[1]Results!G1391 -> 1.7431558e-06 | E31: =[1]Results!H1391 -> 4.7545025e-06 | F31: =[1]Results!I1391 -> 9.840929e-06 | G31: =[1]Results!J1391 -> 1.7720869e-05 | H31: =[1]Results!K1391 -> 2.8433113e-05 | I31: =[1]Results!L1391 -> 3.8069382e-05 | J31: =[1]Results!M1391 -> -0.77044258 | ... CJ31: =[1]Results!CM1391 -> -7.7673007
A32: =[1]Results!E1392 -> 100*(DISPINC_AT_VAL_2/DISPINC_AT_VAL_0-1)-100*((F_L_2/F_L_0)-1)-100*(PCH_2/PCH_0-1) | B32: =[1]Results!C1392 -> Revenu disponible réel par emploi | C32: =[1]Results!F1392 -> 0 | D32: =[1]Results!G1392 -> -1.3271576e-06 | E32: =[1]Results!H1392 -> -3.1871372e-06 | F32: =[1]Results!I1392 -> -5.3943986e-06 | G32: =[1]Results!J1392 -> -7.4856826e-06 | H32: =[1]Results!K1392 -> -8.6613523e-06 | I32: =[1]Results!L1392 -> -6.3093623e-06 | J32: =[1]Results!M1392 -> -0.14042377 | ... CJ32: =[1]Results!CM1392 -> -4.2920125
A33: =[1]Results!E1393 -> 100*(MPS_n_2-MPS_n_0) | B33: =[1]Results!C1393 -> Taux d'épargne | C33: =[1]Results!F1393 -> 0 | D33: =[1]Results!G1393 -> 0 | E33: =[1]Results!H1393 -> 0 | F33: =[1]Results!I1393 -> 0 | G33: =[1]Results!J1393 -> 0 | H33: =[1]Results!K1393 -> 0 | I33: =[1]Results!L1393 -> 0 | J33: =[1]Results!M1393 -> 0 | ... CJ33: =[1]Results!CM1393 -> 0
A34: =[1]Results!E1394 -> 100*(PCH_2/PCH_0-1) | B34: =[1]Results!C1394 -> Prix à la consommation des ménages | C34: =[1]Results!F1394 -> 0 | D34: =[1]Results!G1394 -> 1.8544169e-05 | E34: =[1]Results!H1394 -> 5.1355397e-05 | F34: =[1]Results!I1394 -> 9.3019723e-05 | G34: =[1]Results!J1394 -> 0.00013967688 | H34: =[1]Results!K1394 -> 0.00018908502 | I34: =[1]Results!L1394 -> 0.0002065904 | J34: =[1]Results!M1394 -> -0.21716967 | ... CJ34: =[1]Results!CM1394 -> -9.3562568
A35: =[1]Results!E1395 -> 100*(PY_2/PY_0-1) | B35: =[1]Results!C1395 -> Prix à la production marchande | C35: =[1]Results!F1395 -> 0 | D35: =[1]Results!G1395 -> 4.0622903e-06 | E35: =[1]Results!H1395 -> 1.2459618e-05 | F35: =[1]Results!I1395 -> 2.546611e-05 | G35: =[1]Results!J1395 -> 4.2399638e-05 | H35: =[1]Results!K1395 -> 6.2187075e-05 | I35: =[1]Results!L1395 -> 7.6459675e-05 | J35: =[1]Results!M1395 -> -0.26701343 | ... CJ35: =[1]Results!CM1395 -> -5.6479257
A36: =[1]Results!E1396 -> 100*(PX_2/PX_0-1) | B36: =[1]Results!C1396 -> Prix des exportations | C36: =[1]Results!F1396 -> 0 | D36: =[1]Results!G1396 -> 5.1519673e-06 | E36: =[1]Results!H1396 -> 1.4218898e-05 | F36: =[1]Results!I1396 -> 2.6503143e-05 | G36: =[1]Results!J1396 -> 4.1164026e-05 | H36: =[1]Results!K1396 -> 5.7359497e-05 | I36: =[1]Results!L1396 -> 6.506256e-05 | J36: =[1]Results!M1396 -> -0.32599982 | ... CJ36: =[1]Results!CM1396 -> -2.1237319
... A55: =[1]Results!E1415 -> DEBT_G_VAL_2 | B55: =[1]Results!C1415 -> Dette publique | C55: =[1]Results!F1415 -> 2111098.1 | D55: =[1]Results!G1415 -> 2203198.7 | E55: =[1]Results!H1415 -> 2301624.7 | F55: =[1]Results!I1415 -> 2405582.3 | G55: =[1]Results!J1415 -> 2515115.8 | H55: =[1]Results!K1415 -> 2629448.7 | I55: =[1]Results!L1415 -> 2750556.4 | J55: =[1]Results!M1415 -> 2881178.4 | ... CJ55: =[1]Results!CM1415 -> 59407436
B56: Emissions de CO2 énergétiques (MtCO2) | C56: =C73-C67 -> 0 | D56: =D73-D67 -> 0.0001238 | E56: =E73-E67 -> 0.000285 | F56: =F73-F67 -> 0.00046 | G56: =G73-G67 -> 0.0006415 | H56: =H73-H67 -> 0.0008235 | I56: =I73-I67 -> 0.0007749 | J56: =J73-J67 -> 8.702276 | ... CJ56: =CJ73-CJ67 -> 320.33068
A58: Consommation | B58: Baseline | C58: =[1]Results!F1731 -> 1196741.2 | D58: =[1]Results!G1731 -> 1199619 | E58: =[1]Results!H1731 -> 1213054.7 | F58: =[1]Results!I1731 -> 1228614.9 | G58: =[1]Results!J1731 -> 1243089.4 | H58: =[1]Results!K1731 -> 1257018.6 | I58: =[1]Results!L1731 -> 1268992.8 | J58: =[1]Results!M1731 -> 1281894.7 | ... CJ58: =[1]Results!CM1731 -> 3232059.9
B59: NZ50 | C59: =[1]Results!F1702 -> 1196741.2 | D59: =[1]Results!G1702 -> 1199619.2 | E59: =[1]Results!H1702 -> 1213055.3 | F59: =[1]Results!I1702 -> 1228616.1 | G59: =[1]Results!J1702 -> 1243091.2 | H59: =[1]Results!K1702 -> 1257021.1 | I59: =[1]Results!L1702 -> 1268995.7 | J59: =[1]Results!M1702 -> 1279935.8 | ... CJ59: =[1]Results!CM1702 -> 2895258.6
H60: =H58/G58-1 -> 0.011205299 | I60: =I58/H58-1 -> 0.0095259012 | J60: =J58/I58-1 -> 0.01016704 | K60: =K58/J58-1 -> 0.010912174 | L60: =L58/K58-1 -> 0.012088701 | M60: =M58/L58-1 -> 0.013229824 | N60: =N58/M58-1 -> 0.014086765 | O60: =O58/N58-1 -> 0.015135816 | ... CJ60: =CJ58/CI58-1 -> 0.0095210496
A61: IPC | B61: Baseline | C61: =[1]Results!F1789 -> 0.99804945 | D61: =[1]Results!G1789 -> 1.0096689 | E61: =[1]Results!H1789 -> 1.0199405 | F61: =[1]Results!I1789 -> 1.0304997 | G61: =[1]Results!J1789 -> 1.0394123 | H61: =[1]Results!K1789 -> 1.048674 | I61: =[1]Results!L1789 -> 1.0613189 | J61: =[1]Results!M1789 -> 1.0824302 | ... CJ61: =[1]Results!CM1789 -> 4.536156
B62: NZ50 | C62: =[1]Results!F1760 -> 0.99804945 | D62: =[1]Results!G1760 -> 1.0096689 | E62: =[1]Results!H1760 -> 1.0199406 | F62: =[1]Results!I1760 -> 1.0304998 | G62: =[1]Results!J1760 -> 1.0394126 | H62: =[1]Results!K1760 -> 1.0486744 | I62: =[1]Results!L1760 -> 1.0613194 | J62: =[1]Results!M1760 -> 1.0756107 | ... CJ62: =[1]Results!CM1760 -> 4.3785115
A64: Inflation | B64: =B61 -> Baseline | D64: =(D61/C61-1)*100 -> 1.1642174 | E64: =(E61/D61-1)*100 -> 1.0173235 | F64: =(F61/E61-1)*100 -> 1.0352719 | G64: =(G61/F61-1)*100 -> 0.86488586 | H64: =(H61/G61-1)*100 -> 0.89104678 | I64: =(I61/H61-1)*100 -> 1.2058025 | J64: =(J61/I61-1)*100 -> 1.9891571 | K64: =(K61/J61-1)*100 -> 2.0031947 | ... CJ64: =(CJ61/CI61-1)*100 -> 1.8734487
B65: =B62 -> NZ50 | D65: =(D62/C62-1)*100 -> 1.1642205 | E65: =(E62/D62-1)*100 -> 1.0173284 | F65: =(F62/E62-1)*100 -> 1.0352793 | G65: =(G62/F62-1)*100 -> 0.86489592 | H65: =(H62/G62-1)*100 -> 0.89105877 | I65: =(I62/H62-1)*100 -> 1.2058099 | J65: =(J62/I62-1)*100 -> 1.3465612 | K65: =(K62/J62-1)*100 -> 1.499739 | ... CJ65: =(CJ62/CI62-1)*100 -> 1.9546279
A67: Emissions | B67: =B64 -> Baseline | C67: =[1]Emissions!B820 -> 345.90436 | D67: =[1]Emissions!C820 -> 344.36746 | E67: =[1]Emissions!D820 -> 343.1496 | F67: =[1]Emissions!E820 -> 341.67319 | G67: =[1]Emissions!F820 -> 341.14439 | H67: =[1]Emissions!G820 -> 341.53634 | I67: =[1]Emissions!H820 -> 341.99583 | J67: =[1]Emissions!I820 -> 333.79015 | ... CJ67: =[1]Emissions!CI820 -> 159.15354
B68: Ménages | C68: =[1]Emissions!B824 -> 115.31193 | D68: =[1]Emissions!C824 -> 114.58552 | E68: =[1]Emissions!D824 -> 113.4387 | F68: =[1]Emissions!E824 -> 112.27297 | G68: =[1]Emissions!F824 -> 111.43338 | H68: =[1]Emissions!G824 -> 110.83983 | I68: =[1]Emissions!H824 -> 110.18008 | J68: =[1]Emissions!I824 -> 106.00457 | ... CJ68: =[1]Emissions!CI824 -> 4.2333276
B69: Entreprises | C69: =SUM(C70:C72) -> 230.59244 | D69: =SUM(D70:D72) -> 229.78194 | E69: =SUM(E70:E72) -> 229.7109 | F69: =SUM(F70:F72) -> 229.40023 | G69: =SUM(G70:G72) -> 229.71101 | H69: =SUM(H70:H72) -> 230.6965 | I69: =SUM(I70:I72) -> 231.81575 | J69: =SUM(J70:J72) -> 227.78558 | ... CJ69: =SUM(CJ70:CJ72) -> 154.92022
B70: CI | C70: =[1]Emissions!B821 -> 180.02321 | D70: =[1]Emissions!C821 -> 178.70446 | E70: =[1]Emissions!D821 -> 177.85555 | F70: =[1]Emissions!E821 -> 176.85944 | G70: =[1]Emissions!F821 -> 176.57545 | H70: =[1]Emissions!G821 -> 176.98299 | I70: =[1]Emissions!H821 -> 177.5555 | J70: =[1]Emissions!I821 -> 172.43666 | ... CJ70: =[1]Emissions!CI821 -> 54.298154
B71: Y | C71: =[1]Emissions!B822 -> 2.6960155 | D71: =[1]Emissions!C822 -> 2.675495 | E71: =[1]Emissions!D822 -> 2.6712091 | F71: =[1]Emissions!E822 -> 2.68488 | G71: =[1]Emissions!F822 -> 2.712273 | H71: =[1]Emissions!G822 -> 2.7493615 | I71: =[1]Emissions!H822 -> 2.7902186 | J71: =[1]Emissions!I822 -> 2.8329119 | ... CJ71: =[1]Emissions!CI822 -> 3.7140915
B72: MAT | C72: =[1]Emissions!B823 -> 47.873206 | D72: =[1]Emissions!C823 -> 48.401987 | E72: =[1]Emissions!D823 -> 49.184138 | F72: =[1]Emissions!E823 -> 49.855907 | G72: =[1]Emissions!F823 -> 50.423281 | H72: =[1]Emissions!G823 -> 50.96415 | I72: =[1]Emissions!H823 -> 51.47003 | J72: =[1]Emissions!I823 -> 52.516002 | ... CJ72: =[1]Emissions!CI823 -> 96.907972
B73: =B65 -> NZ50 | C73: =[1]Emissions!B825 -> 345.90436 | D73: =[1]Emissions!C825 -> 344.36759 | E73: =[1]Emissions!D825 -> 343.14988 | F73: =[1]Emissions!E825 -> 341.67365 | G73: =[1]Emissions!F825 -> 341.14503 | H73: =[1]Emissions!G825 -> 341.53716 | I73: =[1]Emissions!H825 -> 341.9966 | J73: =[1]Emissions!I825 -> 342.49242 | ... CJ73: =[1]Emissions!CI825 -> 479.48422
B74: Ménages | C74: =[1]Emissions!B829 -> 115.31193 | D74: =[1]Emissions!C829 -> 114.58555 | E74: =[1]Emissions!D829 -> 113.43876 | F74: =[1]Emissions!E829 -> 112.27307 | G74: =[1]Emissions!F829 -> 111.43353 | H74: =[1]Emissions!G829 -> 110.84002 | I74: =[1]Emissions!H829 -> 110.18026 | J74: =[1]Emissions!I829 -> 109.43995 | ... CJ74: =[1]Emissions!CI829 -> 30.116683
B75: Entreprises | C75: =SUM(C76:C78) -> 230.59244 | D75: =SUM(D76:D78) -> 229.78204 | E75: =SUM(E76:E78) -> 229.71112 | F75: =SUM(F76:F78) -> 229.40059 | G75: =SUM(G76:G78) -> 229.7115 | H75: =SUM(H76:H78) -> 230.69714 | I75: =SUM(I76:I78) -> 231.81634 | J75: =SUM(J76:J78) -> 233.05247 | ... CJ75: =SUM(CJ76:CJ78) -> 449.36754
B76: CI | C76: =[1]Emissions!B826 -> 180.02321 | D76: =[1]Emissions!C826 -> 178.70453 | E76: =[1]Emissions!D826 -> 177.85571 | F76: =[1]Emissions!E826 -> 176.85969 | G76: =[1]Emissions!F826 -> 176.5758 | H76: =[1]Emissions!G826 -> 176.98344 | I76: =[1]Emissions!H826 -> 177.55592 | J76: =[1]Emissions!I826 -> 178.2485 | ... CJ76: =[1]Emissions!CI826 -> 335.83927
B77: Y | C77: =[1]Emissions!B827 -> 2.6960155 | D77: =[1]Emissions!C827 -> 2.6754961 | E77: =[1]Emissions!D827 -> 2.6712113 | F77: =[1]Emissions!E827 -> 2.6848837 | G77: =[1]Emissions!F827 -> 2.7122781 | H77: =[1]Emissions!G827 -> 2.7493682 | I77: =[1]Emissions!H827 -> 2.7902246 | J77: =[1]Emissions!I827 -> 2.8306558 | ... CJ77: =[1]Emissions!CI827 -> 3.4132379
B78: MAT | C78: =[1]Emissions!B828 -> 47.873206 | D78: =[1]Emissions!C828 -> 48.402018 | E78: =[1]Emissions!D828 -> 49.184205 | F78: =[1]Emissions!E828 -> 49.856012 | G78: =[1]Emissions!F828 -> 50.423426 | H78: =[1]Emissions!G828 -> 50.964333 | I78: =[1]Emissions!H828 -> 51.470191 | J78: =[1]Emissions!I828 -> 51.973314 | ... CJ78: =[1]Emissions!CI828 -> 110.11503
B79: VA | C79: =[1]Results!F1551 -> 1918841.7 | D79: =[1]Results!G1551 -> 1927191.9 | E79: =[1]Results!H1551 -> 1945247.7 | F79: =[1]Results!I1551 -> 1967916.6 | G79: =[1]Results!J1551 -> 1992260.4 | H79: =[1]Results!K1551 -> 2018011.4 | I79: =[1]Results!L1551 -> 2043036.8 | J79: =[1]Results!M1551 -> 2069540.1 | ... CJ79: =[1]Results!CM1551 -> 5112422.7
B81: Baseline | C81: =C82+C83 -> 295.33514 | D81: =D82+D83 -> 293.28998 | E81: =E82+E83 -> 291.29425 | F81: =F82+F83 -> 289.13241 | G81: =G82+G83 -> 288.00883 | H81: =H82+H83 -> 287.82283 | I81: =I82+I83 -> 287.73558 | J81: =J82+J83 -> 278.44123 | ... CJ81: =CJ82+CJ83 -> 58.531481
B82: Ménages | C82: =C68 -> 115.31193 | D82: =D68 -> 114.58552 | E82: =E68 -> 113.4387 | F82: =F68 -> 112.27297 | G82: =G68 -> 111.43338 | H82: =H68 -> 110.83983 | I82: =I68 -> 110.18008 | J82: =J68 -> 106.00457 | ... CJ82: =CJ68 -> 4.2333276
B83: Entreprises | C83: =C70 -> 180.02321 | D83: =D70 -> 178.70446 | E83: =E70 -> 177.85555 | F83: =F70 -> 176.85944 | G83: =G70 -> 176.57545 | H83: =H70 -> 176.98299 | I83: =I70 -> 177.5555 | J83: =J70 -> 172.43666 | ... CJ83: =CJ70 -> 54.298154
B84: NZ50 | C84: =C85+C86 -> 295.33514 | D84: =D85+D86 -> 293.29007 | E84: =E85+E86 -> 291.29447 | F84: =F85+F86 -> 289.13276 | G84: =G85+G86 -> 288.00932 | H84: =H85+H86 -> 287.82346 | I84: =I85+I86 -> 287.73619 | J84: =J85+J86 -> 287.68845 | ... CJ84: =CJ85+CJ86 -> 365.95595
B85: Ménages | C85: =C74 -> 115.31193 | D85: =D74 -> 114.58555 | E85: =E74 -> 113.43876 | F85: =F74 -> 112.27307 | G85: =G74 -> 111.43353 | H85: =H74 -> 110.84002 | I85: =I74 -> 110.18026 | J85: =J74 -> 109.43995 | ... CJ85: =CJ74 -> 30.116683
B86: Entreprises | C86: =C76 -> 180.02321 | D86: =D76 -> 178.70453 | E86: =E76 -> 177.85571 | F86: =F76 -> 176.85969 | G86: =G76 -> 176.5758 | H86: =H76 -> 176.98344 | I86: =I76 -> 177.55592 | J86: =J76 -> 178.2485 | ... CJ86: =CJ76 -> 335.83927
A89: Valeur ajoutée sectorielle | B89: VA | C89: =[1]Results!F1551 -> 1918841.7 | D89: =[1]Results!G1551 -> 1927191.9 | E89: =[1]Results!H1551 -> 1945247.7 | F89: =[1]Results!I1551 -> 1967916.6 | G89: =[1]Results!J1551 -> 1992260.4 | H89: =[1]Results!K1551 -> 2018011.4 | I89: =[1]Results!L1551 -> 2043036.8 | J89: =[1]Results!M1551 -> 2069540.1 | ... CJ89: =[1]Results!CM1551 -> 5112422.7
A90: baseline | B90: Agriculture | C90: =[1]Results!F1552 -> 34095.189 | D90: =[1]Results!G1552 -> 33672.129 | E90: =[1]Results!H1552 -> 33530.526 | F90: =[1]Results!I1552 -> 33622.073 | G90: =[1]Results!J1552 -> 33876.473 | H90: =[1]Results!K1552 -> 34240.251 | I90: =[1]Results!L1552 -> 34642.788 | J90: =[1]Results!M1552 -> 35091.783 | ... CJ90: =[1]Results!CM1552 -> 39793.56
B91: Construction | C91: =[1]Results!F1565 -> 106422.84 | D91: =[1]Results!G1565 -> 114436.37 | E91: =[1]Results!H1565 -> 121030.31 | F91: =[1]Results!I1565 -> 124101.92 | G91: =[1]Results!J1565 -> 125522.59 | H91: =[1]Results!K1565 -> 126404.97 | I91: =[1]Results!L1565 -> 127121.16 | J91: =[1]Results!M1565 -> 127932.77 | ... CJ91: =[1]Results!CM1565 -> 304457.99
B92: Electricité | C92: =[1]Results!F1580 -> 12959.483 | D92: =[1]Results!G1580 -> 12931.464 | E92: =[1]Results!H1580 -> 12907.517 | F92: =[1]Results!I1580 -> 12910.167 | G92: =[1]Results!J1580 -> 12902.091 | H92: =[1]Results!K1580 -> 12908.14 | I92: =[1]Results!L1580 -> 12930.876 | J92: =[1]Results!M1580 -> 12933.713 | ... CJ92: =[1]Results!CM1580 -> 17650.391
B93: Industrie | C93: =[1]Results!F1555-[1]Results!F1565 -> 218286.98 | D93: =[1]Results!G1555-[1]Results!G1565 -> 219402.61 | E93: =[1]Results!H1555-[1]Results!H1565 -> 220850.65 | F93: =[1]Results!I1555-[1]Results!I1565 -> 222569.47 | G93: =[1]Results!J1555-[1]Results!J1565 -> 224536.8 | H93: =[1]Results!K1555-[1]Results!K1565 -> 226765.13 | I93: =[1]Results!L1555-[1]Results!L1565 -> 228883.13 | J93: =[1]Results!M1555-[1]Results!M1565 -> 231328.59 | ... CJ93: =[1]Results!CM1555-[1]Results!CM1565 -> 465058.32
B94: Oil & Gas | C94: =[1]Results!F1575 -> 3660.3299 | D94: =[1]Results!G1575 -> 3982.5262 | E94: =[1]Results!H1575 -> 4046.4212 | F94: =[1]Results!I1575 -> 4084.3356 | G94: =[1]Results!J1575 -> 4139.816 | H94: =[1]Results!K1575 -> 4198.2145 | I94: =[1]Results!L1575 -> 4236.1607 | J94: =[1]Results!M1575 -> 4038.1718 | ... CJ94: =[1]Results!CM1575 -> 7233.1114
B95: Services | C95: =[1]Results!F1572 -> 1492749.6 | D95: =[1]Results!G1572 -> 1492245.6 | E95: =[1]Results!H1572 -> 1502347.3 | F95: =[1]Results!I1572 -> 1519910.4 | G95: =[1]Results!J1572 -> 1540263.7 | H95: =[1]Results!K1572 -> 1562082.5 | I95: =[1]Results!L1572 -> 1583409.7 | J95: =[1]Results!M1572 -> 1605938.9 | ... CJ95: =[1]Results!CM1572 -> 4163031.1
B96: Transports | C96: =[1]Results!F1567 -> 50667.301 | D96: =[1]Results!G1567 -> 50521.165 | E96: =[1]Results!H1567 -> 50534.968 | F96: =[1]Results!I1567 -> 50718.217 | G96: =[1]Results!J1567 -> 51018.885 | H96: =[1]Results!K1567 -> 51412.261 | I96: =[1]Results!L1567 -> 51813.01 | J96: =[1]Results!M1567 -> 52276.174 | ... CJ96: =[1]Results!CM1567 -> 115198.16
A98: shock | B98: VA | C98: =[1]Results!F1512 -> 1918841.7 | D98: =[1]Results!G1512 -> 1927192.9 | E98: =[1]Results!H1512 -> 1945249.7 | F98: =[1]Results!I1512 -> 1967919.7 | G98: =[1]Results!J1512 -> 1992264.7 | H98: =[1]Results!K1512 -> 2018017 | I98: =[1]Results!L1512 -> 2043041.9 | J98: =[1]Results!M1512 -> 2067777.4 | ... CJ98: =[1]Results!CM1512 -> 4735397.1
B99: Agriculture | C99: =[1]Results!F1513 -> 34095.189 | D99: =[1]Results!G1513 -> 33672.173 | E99: =[1]Results!H1513 -> 33530.618 | F99: =[1]Results!I1513 -> 33622.215 | G99: =[1]Results!J1513 -> 33876.666 | H99: =[1]Results!K1513 -> 34240.497 | I99: =[1]Results!L1513 -> 34642.996 | J99: =[1]Results!M1513 -> 35038.721 | ... CJ99: =[1]Results!CM1513 -> 27255.339
B100: Construction | C100: =[1]Results!F1526 -> 106422.84 | D100: =[1]Results!G1526 -> 114436.4 | E100: =[1]Results!H1526 -> 121030.38 | F100: =[1]Results!I1526 -> 124102.03 | G100: =[1]Results!J1526 -> 125522.76 | H100: =[1]Results!K1526 -> 126405.2 | I100: =[1]Results!L1526 -> 127121.41 | J100: =[1]Results!M1526 -> 127849.35 | ... CJ100: =[1]Results!CM1526 -> 273076.81
B101: Electricité | C101: =[1]Results!F1541 -> 12959.483 | D101: =[1]Results!G1541 -> 12931.492 | E101: =[1]Results!H1541 -> 12907.576 | F101: =[1]Results!I1541 -> 12910.259 | G101: =[1]Results!J1541 -> 12902.217 | H101: =[1]Results!K1541 -> 12908.299 | I101: =[1]Results!L1541 -> 12931.012 | J101: =[1]Results!M1541 -> 12964.727 | ... CJ101: =[1]Results!CM1541 -> 17224.068
B102: Industrie | C102: =[1]Results!F1516-[1]Results!F1526 -> 218286.98 | D102: =[1]Results!G1516-[1]Results!G1526 -> 219402.83 | E102: =[1]Results!H1516-[1]Results!H1526 -> 220851.06 | F102: =[1]Results!I1516-[1]Results!I1526 -> 222570.08 | G102: =[1]Results!J1516-[1]Results!J1526 -> 224537.6 | H102: =[1]Results!K1516-[1]Results!K1526 -> 226766.13 | I102: =[1]Results!L1516-[1]Results!L1526 -> 228883.89 | J102: =[1]Results!M1516-[1]Results!M1526 -> 231108.97 | ... CJ102: =[1]Results!CM1516-[1]Results!CM1526 -> 430378.33
B103: Oil & Gas | C103: =[1]Results!F1536 -> 3660.3299 | D103: =[1]Results!G1536 -> 3982.5318 | E103: =[1]Results!H1536 -> 4046.429 | F103: =[1]Results!I1536 -> 4084.3451 | G103: =[1]Results!J1536 -> 4139.8276 | H103: =[1]Results!K1536 -> 4198.2282 | I103: =[1]Results!L1536 -> 4236.1659 | J103: =[1]Results!M1536 -> 4269.7451 | ... CJ103: =[1]Results!CM1536 -> 7352.7899
B104: Services | C104: =[1]Results!F1533 -> 1492749.6 | D104: =[1]Results!G1533 -> 1492246.2 | E104: =[1]Results!H1533 -> 1502348.6 | F104: =[1]Results!I1533 -> 1519912.5 | G104: =[1]Results!J1533 -> 1540266.6 | H104: =[1]Results!K1533 -> 1562086.3 | I104: =[1]Results!L1533 -> 1583413.2 | J104: =[1]Results!M1533 -> 1604307.7 | ... CJ104: =[1]Results!CM1533 -> 3873796.6
B105: Transports | C105: =[1]Results!F1528 -> 50667.301 | D105: =[1]Results!G1528 -> 50521.198 | E105: =[1]Results!H1528 -> 50535.034 | F105: =[1]Results!I1528 -> 50718.317 | G105: =[1]Results!J1528 -> 51019.019 | H105: =[1]Results!K1528 -> 51412.43 | I105: =[1]Results!L1528 -> 51813.148 | J105: =[1]Results!M1528 -> 52238.184 | ... CJ105: =[1]Results!CM1528 -> 106313.17
A107: VA graphique | B107: Année | C107: 2030 | D107: 2040 | E107: 2050 | F107: 2100
A108: %deviation | B108: Total | C108: =(R98-R89)/R89 -> -0.013772328 | D108: =(AB98-AB89)/AB89 -> -0.019739866 | E108: =(AL98-AL89)/AL89 -> -0.02732026 | F108: =(CJ98-CJ89)/CJ89 -> -0.073746943 | H108: 2020 | I108: 2100
B109: Agriculture | C109: =(R99-R90)/R90 -> -0.0064799535 | D109: =(AB99-AB90)/AB90 -> -0.020184183 | E109: =(AL99-AL90)/AL90 -> -0.047907691 | F109: =(CJ99-CJ90)/CJ90 -> -0.31508165 | H109: =H99/$H$98 -> 0.016967397 | I109: =CI99/$CI$98 -> 0.0058610297
B110: Construction | C110: =(R100-R91)/R91 -> -0.026533268 | D110: =(AB100-AB91)/AB91 -> -0.03563316 | E110: =(AL100-AL91)/AL91 -> -0.045177024 | F110: =(CJ100-CJ91)/CJ91 -> -0.10307226 | H110: =H100/$H$98 -> 0.062638322 | I110: =CI100/$CI$98 -> 0.057728201
B111: Electricité | C111: =(R101-R92)/R92 -> 0.095447274 | D111: =(AB101-AB92)/AB92 -> 0.2305714 | E111: =(AL101-AL92)/AL92 -> 0.40816386 | F111: =(CJ101-CJ92)/CJ92 -> -0.024153757 | H111: =H101/$H$98 -> 0.006396526 | I111: =CI101/$CI$98 -> 0.0036928135
B112: Industrie | C112: =(R102-R93)/R93 -> -0.014078035 | D112: =(AB102-AB93)/AB93 -> -0.014038056 | E112: =(AL102-AL93)/AL93 -> -0.023974868 | F112: =(CJ102-CJ93)/CJ93 -> -0.074571257 | H112: =H102/$H$98 -> 0.11237077 | I112: =CI102/$CI$98 -> 0.091090726
B113: Oil & Gas | C113: =(R103-R94)/R94 -> 0.38634307 | D113: =(AB103-AB94)/AB94 -> 0.5908604 | E113: =(AL103-AL94)/AL94 -> -0.22848792 | F113: =(CJ103-CJ94)/CJ94 -> 0.016545926 | H113: =H103/$H$98 -> 0.002080373 | I113: =CI103/$CI$98 -> 0.0015487495
B114: Services | C114: =(R104-R95)/R95 -> -0.014285037 | D114: =(AB104-AB95)/AB95 -> -0.021539285 | E114: =(AL104-AL95)/AL95 -> -0.027247182 | F114: =(CJ104-CJ95)/CJ95 -> -0.069476909 | H114: =H104/$H$98 -> 0.7740699 | I114: =CI104/$CI$98 -> 0.81761282
B115: Transports | C115: =(R105-R96)/R96 -> -0.015121308 | D115: =(AB105-AB96)/AB96 -> -0.021451125 | E115: =(AL105-AL96)/AL96 -> -0.045801966 | F115: =(CJ105-CJ96)/CJ96 -> -0.077127873 | H115: =H105/$H$98 -> 0.025476707 | I115: =CI105/$CI$98 -> 0.022465662
A117: VA graphique | B117: Année | C117: 2030 | D117: 2040 | E117: 2050 | F117: 2100
A118: %deviation contrib | B118: Total | C118: =C108 -> -0.013772328 | D118: =D108 -> -0.019739866 | E118: =E108 -> -0.02732026 | F118: =F108 -> -0.073746943 | G118: =R89 -> 2305265.8 | H118: =AB89 -> 2630202.1 | I118: =AL89 -> 2986754.1 | J118: =CJ89 -> 5112422.7
B119: Agriculture | C119: =C109*G119/G$118 -> -0.00010160036 | D119: =D109*H119/H$118 -> -0.00027816014 | E119: =E109*I119/I$118 -> -0.00058914561 | F119: =F109*J119/J$118 -> -0.0024525007 | G119: =R90 -> 36144.679 | H119: =AB90 -> 36247.065 | I119: =AL90 -> 36729.657 | J119: =CJ90 -> 39793.56
B120: Construction | C120: =C110*G120/G$118 -> -0.0016203249 | D120: =D110*H120/H$118 -> -0.0021653228 | E120: =E110*I120/I$118 -> -0.0027182441 | F120: =F110*J120/J$118 -> -0.0061382194 | G120: =R91 -> 140777.22 | H120: =AB91 -> 159829.68 | I120: =AL91 -> 179709.2 | J120: =CJ91 -> 304457.99
B121: Electricité | C121: =C111*G121/G$118 -> 0.00051623908 | D121: =D111*H121/H$118 -> 0.0010992793 | E121: =E111*I121/I$118 -> 0.0016644025 | F121: =F111*J121/J$118 -> -8.3389672e-05 | G121: =R92 -> 12468.332 | H121: =AB92 -> 12539.832 | I121: =AL92 -> 12179.327 | J121: =CJ92 -> 17650.391
B122: Industrie | C122: =C112*G122/G$118 -> -0.0015401089 | D122: =D112*H122/H$118 -> -0.0014644611 | E122: =E112*I122/I$118 -> -0.0024385287 | F122: =F112*J122/J$118 -> -0.0067834734 | G122: =R93 -> 252191.48 | H122: =AB93 -> 274384.76 | I122: =AL93 -> 303788.36 | J122: =CJ93 -> 465058.32
B123: Oil & Gas | C123: =C113*G123/G$118 -> 0.00052340832 | D123: =D113*H123/H$118 -> 0.00062769001 | E123: =E113*I123/I$118 -> -0.00045848906 | F123: =F113*J123/J$118 -> 2.3409357e-05 | G123: =R94 -> 3123.1188 | H123: =AB94 -> 2794.1484 | I123: =AL94 -> 5993.2887 | J123: =CJ94 -> 7233.1114
B124: Services | C124: =C114*G124/G$118 -> -0.011177351 | D124: =D114*H124/H$118 -> -0.017045323 | E124: =E114*I124/I$118 -> -0.021682478 | F124: =F114*J124/J$118 -> -0.056574848 | G124: =R95 -> 1803759.1 | H124: =AB95 -> 2081436.1 | I124: =AL95 -> 2376768 | J124: =CJ95 -> 4163031.1
B125: Transports | C125: =C115*G125/G$118 -> -0.00037259017 | D125: =D115*H125/H$118 -> -0.00051356855 | E125: =E115*I125/I$118 -> -0.0010977779 | F125: =F115*J125/J$118 -> -0.0017379215 | G125: =R96 -> 56801.924 | H125: =AB96 -> 62970.549 | I125: =AL96 -> 71586.283 | J125: =CJ96 -> 115198.16
A127: VA graphique | B127: Année | C127: 2030 | D127: 2040 | E127: 2050 | F127: 2100
A128: share evolution | B128: Agriculture | C128: =R99/R$98-R90/R$89 -> 0.00011593516 | D128: =AB99/AB$98-AB90/AB$89 -> -6.2464728e-06 | E128: =AL99/AL$98-AL90/AL$89 -> -0.00026028532 | F128: =CJ99/CJ$98-CJ90/CJ$89 -> -0.0020280384
B129: Construction | C129: =R100/R$98-R91/R$89 -> -0.00079016329 | D129: =AB100/AB$98-AB91/AB$89 -> -0.00098523737 | E129: =AL100/AL$98-AL91/AL$89 -> -0.0011045967 | F129: =CJ100/CJ$98-CJ91/CJ$89 -> -0.001885444
B130: Electricité | C130: =R101/R$98-R92/R$89 -> 0.00059897784 | D130: =AB101/AB$98-AB92/AB$89 -> 0.0012174234 | E130: =AL101/AL$98-AL92/AL$89 -> 0.0018256868 | F130: =CJ101/CJ$98-CJ92/CJ$89 -> 0.00018485021
...

Sheet Impact macro
A1: Scénario d'inaction (par rapport au scénario de transition ordonnée), en % d'écart | B1: 2030 | C1: 2050 | D1: 2100
A2: =Données!B5 -> PIB | B2: =Données!R5 -> -1.456527 | C2: =Données!AL5 -> -2.8145324 | D2: =Données!CJ5 -> -7.4705744
A3: =Données!B6 -> VA du secteur marchand | B3: =Données!R6 -> -1.595913 | C3: =Données!AL6 -> -3.2775856 | D3: =Données!CJ6 -> -8.9608559
A4: =Données!B18 -> Consommation des ménages | B4: =Données!R18 -> -2.9241921 | C4: =Données!AL18 -> -4.3407085 | D4: =Données!CJ18 -> -10.420639
A5: =Données!B21 -> Investissement | B5: =Données!R21 -> -2.2009279 | C5: =Données!AL21 -> -6.58725 | D5: =Données!CJ21 -> -11.416629
A6: =Données!B23 -> Exports | B6: =Données!R23 -> 2.0473731 | C6: =Données!AL23 -> 3.0643475 | D6: =Données!CJ23 -> -1.5521656
A7: =Données!B24 -> Imports | B7: =Données!R24 -> -0.19723562 | C7: =Données!AL24 -> -1.0315948 | D7: =Données!CJ24 -> -4.9593841
A8: =Données!B30 -> Revenu disponible réel des ménages | B8: =Données!R30 -> -2.8074534 | C8: =Données!AL30 -> -4.0060088 | D8: =Données!CJ30 -> -9.3562568
A9: =Données!B34 -> Prix à la consommation des ménages | B9: =Données!R34 -> -2.8074534 | C9: =Données!AL34 -> -4.0060088 | D9: =Données!CJ34 -> -9.3562568
A10: =Données!B35 -> Prix à la production marchande | B10: =Données!R35 -> -3.1744036 | C10: =Données!AL35 -> -4.747243 | D10: =Données!CJ35 -> -5.6479257
A11: =Données!B36 -> Prix des exportations | B11: =Données!R36 -> -2.7233117 | C11: =Données!AL36 -> -3.6131435 | D11: =Données!CJ36 -> -2.1237319
A12: =Données!B37 -> Prix des importations | B12: =Données!R37 -> 0.31883632 | C12: =Données!AL37 -> -0.74639129 | D12: =Données!CJ37 -> 1.2881515
A13: Salaire net réel | B13: =Données!R39 -> -0.2731383 | C13: =Données!AL39 -> -1.8689531 | D13: =Données!CJ39 -> -3.737534
A14: Coût réel du travail | B14: =Données!R41 -> -0.57653081 | C14: =Données!AL41 -> -1.0366523 | D14: =Données!CJ41 -> -2.9632148
A15: Emploi (en milliers) | B15: =Données!R43 -> -398.78935 | C15: =Données!AL43 -> -653.88165 | D15: =Données!CJ43 -> -1555.2091
A16: Taux de chômage (en points) | B16: =Données!R44 -> 0.92483096 | C16: =Données!AL44 -> 1.4181936 | D16: =Données!CJ44 -> 3.2791174
A17: Balance commerciale (en pts de PIB) | B17: =Données!R45 -> -0.39017979 | C17: =Données!AL45 -> 0.18109684 | D17: =Données!CJ45 -> -0.15643273
A18: Facture énergétique (en pts de PIB) | B18: =Données!R46 -> 1.1839658 | C18: =Données!AL46 -> 1.1696125 | D18: =Données!CJ46 -> 0.66986288
A19: Solde public primaire (en pts de PIB) | B19: =Données!R47 -> 0.83293849 | C19: =Données!AL47 -> 1.3404487 | D19: =Données!CJ47 -> 2.8845707
