Workbook
Name formatResults: [1]ResultsEXR10!$A$50

Sheet List_Sectors
A1: Acronym in ThreeME | B1: Name UK
A2: S1 | B2: Housing | G2: sagr
A3: S2 | B3: Services
A4: S3 | B4: Agriculture
A5: S4 | B5: Basic metals (Steel, Aluminum, Zinc)
A6: S5 | B6: Chemical products (Nitric Acid, Urea, Chlorine, other)
A7: S6 | B7: Rubber and Plastic (Ethylene, Propylene, other HVC)
A8: S7 | B8: non-metallic mineral products (Glass, Ceramic)
A9: S8 | B9: Paper and board products
A10: S9 | B10: Food products
A11: S10 | B11: Coke and refined petroleum products
A12: S11 | B12: Other non-ETS products
A13: S12 | B13: Sewerage and Waste
A14: S13 | B14: Land Transport (LDV, HDV, Buses, Rail, Other)
... A19: S18 | B19: Electricity, gas, steam and air conditioning

Sheet Tab-macro
C1: en écart au scénario de référence (%)
C2: ThreeME
C3: 2021 | D3: 2022 | E3: 2023 | F3: 2024 | G3: 2025 | H3: 2030 | I3: 2040 | J3: 2050
A4: GDP in volume | B4: =Shock_dev!A2 -> 100*(gdp_2/gdp_0-1) | C4: =VLOOKUP($B4,Shock_dev!$A$1:$CI$100,MATCH(DATE(C$3,1,1),Shock_dev!$A$1:$CI$1,0),FALSE) -> 0.0014626161 | D4: =VLOOKUP($B4,Shock_dev!$A$1:$CI$100,MATCH(DATE(D$3,1,1),Shock_dev!$A$1:$CI$1,0),FALSE) -> 0.001683267 | E4: =VLOOKUP($B4,Shock_dev!$A$1:$CI$100,MATCH(DATE(E$3,1,1),Shock_dev!$A$1:$CI$1,0),FALSE) -> 0.0015073164 | F4: =VLOOKUP($B4,Shock_dev!$A$1:$CI$100,MATCH(DATE(F$3,1,1),Shock_dev!$A$1:$CI$1,0),FALSE) -> 0.00077487238 | G4: =VLOOKUP($B4,Shock_dev!$A$1:$CI$100,MATCH(DATE(G$3,1,1),Shock_dev!$A$1:$CI$1,0),FALSE) -> -0.00062909206 | H4: =VLOOKUP($B4,Shock_dev!$A$1:$CI$100,MATCH(DATE(H$3,1,1),Shock_dev!$A$1:$CI$1,0),FALSE) -> -0.019847013 | I4: =VLOOKUP($B4,Shock_dev!$A$1:$CI$100,MATCH(DATE(I$3,1,1),Shock_dev!$A$1:$CI$1,0),FALSE) -> -0.13651108 | J4: =VLOOKUP($B4,Shock_dev!$A$1:$CI$100,MATCH(DATE(J$3,1,1),Shock_dev!$A$1:$CI$1,0),FALSE) -> -0.3939661
A5: Household consumption | B5: =Shock_dev!A3 -> 100*(ch_2/ch_0-1) | C5: =VLOOKUP($B5,Shock_dev!$A$1:$CI$100,MATCH(DATE(C$3,1,1),Shock_dev!$A$1:$CI$1,0),FALSE) -> 0.0018098904 | D5: =VLOOKUP($B5,Shock_dev!$A$1:$CI$100,MATCH(DATE(D$3,1,1),Shock_dev!$A$1:$CI$1,0),FALSE) -> 0.0016528893 | E5: =VLOOKUP($B5,Shock_dev!$A$1:$CI$100,MATCH(DATE(E$3,1,1),Shock_dev!$A$1:$CI$1,0),FALSE) -> 0.00075887252 | F5: =VLOOKUP($B5,Shock_dev!$A$1:$CI$100,MATCH(DATE(F$3,1,1),Shock_dev!$A$1:$CI$1,0),FALSE) -> -0.00096424107 | G5: =VLOOKUP($B5,Shock_dev!$A$1:$CI$100,MATCH(DATE(G$3,1,1),Shock_dev!$A$1:$CI$1,0),FALSE) -> -0.0034765459 | H5: =VLOOKUP($B5,Shock_dev!$A$1:$CI$100,MATCH(DATE(H$3,1,1),Shock_dev!$A$1:$CI$1,0),FALSE) -> -0.022970473 | I5: =VLOOKUP($B5,Shock_dev!$A$1:$CI$100,MATCH(DATE(I$3,1,1),Shock_dev!$A$1:$CI$1,0),FALSE) -> -0.07129756 | J5: =VLOOKUP($B5,Shock_dev!$A$1:$CI$100,MATCH(DATE(J$3,1,1),Shock_dev!$A$1:$CI$1,0),FALSE) -> -0.14907989
A6: Investment | B6: =Shock_dev!A4 -> 100*(i_2/i_0-1) | C6: =VLOOKUP($B6,Shock_dev!$A$1:$CI$100,MATCH(DATE(C$3,1,1),Shock_dev!$A$1:$CI$1,0),FALSE) -> 0.0022873322 | D6: =VLOOKUP($B6,Shock_dev!$A$1:$CI$100,MATCH(DATE(D$3,1,1),Shock_dev!$A$1:$CI$1,0),FALSE) -> 0.0027163516 | E6: =VLOOKUP($B6,Shock_dev!$A$1:$CI$100,MATCH(DATE(E$3,1,1),Shock_dev!$A$1:$CI$1,0),FALSE) -> 0.0025303607 | F6: =VLOOKUP($B6,Shock_dev!$A$1:$CI$100,MATCH(DATE(F$3,1,1),Shock_dev!$A$1:$CI$1,0),FALSE) -> 0.001437433 | G6: =VLOOKUP($B6,Shock_dev!$A$1:$CI$100,MATCH(DATE(G$3,1,1),Shock_dev!$A$1:$CI$1,0),FALSE) -> -0.00077346481 | H6: =VLOOKUP($B6,Shock_dev!$A$1:$CI$100,MATCH(DATE(H$3,1,1),Shock_dev!$A$1:$CI$1,0),FALSE) -> -0.031424629 | I6: =VLOOKUP($B6,Shock_dev!$A$1:$CI$100,MATCH(DATE(I$3,1,1),Shock_dev!$A$1:$CI$1,0),FALSE) -> -0.19825501 | J6: =VLOOKUP($B6,Shock_dev!$A$1:$CI$100,MATCH(DATE(J$3,1,1),Shock_dev!$A$1:$CI$1,0),FALSE) -> -0.53374594
A7: Exports | B7: =Shock_dev!A5 -> 100*(x_2/x_0-1) | C7: =VLOOKUP($B7,Shock_dev!$A$1:$CI$100,MATCH(DATE(C$3,1,1),Shock_dev!$A$1:$CI$1,0),FALSE) -> 0.00080793683 | D7: =VLOOKUP($B7,Shock_dev!$A$1:$CI$100,MATCH(DATE(D$3,1,1),Shock_dev!$A$1:$CI$1,0),FALSE) -> 0.0011081675 | E7: =VLOOKUP($B7,Shock_dev!$A$1:$CI$100,MATCH(DATE(E$3,1,1),Shock_dev!$A$1:$CI$1,0),FALSE) -> 0.0012940637 | F7: =VLOOKUP($B7,Shock_dev!$A$1:$CI$100,MATCH(DATE(F$3,1,1),Shock_dev!$A$1:$CI$1,0),FALSE) -> 0.0012354916 | G7: =VLOOKUP($B7,Shock_dev!$A$1:$CI$100,MATCH(DATE(G$3,1,1),Shock_dev!$A$1:$CI$1,0),FALSE) -> 0.00079422462 | H7: =VLOOKUP($B7,Shock_dev!$A$1:$CI$100,MATCH(DATE(H$3,1,1),Shock_dev!$A$1:$CI$1,0),FALSE) -> -0.0115758 | I7: =VLOOKUP($B7,Shock_dev!$A$1:$CI$100,MATCH(DATE(I$3,1,1),Shock_dev!$A$1:$CI$1,0),FALSE) -> -0.11911393 | J7: =VLOOKUP($B7,Shock_dev!$A$1:$CI$100,MATCH(DATE(J$3,1,1),Shock_dev!$A$1:$CI$1,0),FALSE) -> -0.37444426
A8: Imports | B8: =Shock_dev!A6 -> 100*(m_2/m_0-1) | C8: =VLOOKUP($B8,Shock_dev!$A$1:$CI$100,MATCH(DATE(C$3,1,1),Shock_dev!$A$1:$CI$1,0),FALSE) -> 0.00069396636 | D8: =VLOOKUP($B8,Shock_dev!$A$1:$CI$100,MATCH(DATE(D$3,1,1),Shock_dev!$A$1:$CI$1,0),FALSE) -> 0.00075900347 | E8: =VLOOKUP($B8,Shock_dev!$A$1:$CI$100,MATCH(DATE(E$3,1,1),Shock_dev!$A$1:$CI$1,0),FALSE) -> 0.00060320139 | F8: =VLOOKUP($B8,Shock_dev!$A$1:$CI$100,MATCH(DATE(F$3,1,1),Shock_dev!$A$1:$CI$1,0),FALSE) -> 0.00015635031 | G8: =VLOOKUP($B8,Shock_dev!$A$1:$CI$100,MATCH(DATE(G$3,1,1),Shock_dev!$A$1:$CI$1,0),FALSE) -> -0.00061711627 | H8: =VLOOKUP($B8,Shock_dev!$A$1:$CI$100,MATCH(DATE(H$3,1,1),Shock_dev!$A$1:$CI$1,0),FALSE) -> -0.0092417337 | I8: =VLOOKUP($B8,Shock_dev!$A$1:$CI$100,MATCH(DATE(I$3,1,1),Shock_dev!$A$1:$CI$1,0),FALSE) -> -0.049015249 | J8: =VLOOKUP($B8,Shock_dev!$A$1:$CI$100,MATCH(DATE(J$3,1,1),Shock_dev!$A$1:$CI$1,0),FALSE) -> -0.1292846
A9: Household disposable income (real) | B9: =Shock_dev!A7 -> 100*((dispinc_at_val_2/pch_2)/(dispinc_at_val_0/pch_0)-1) | C9: =VLOOKUP($B9,Shock_dev!$A$1:$CI$100,MATCH(DATE(C$3,1,1),Shock_dev!$A$1:$CI$1,0),FALSE) -> 0.0018347614 | D9: =VLOOKUP($B9,Shock_dev!$A$1:$CI$100,MATCH(DATE(D$3,1,1),Shock_dev!$A$1:$CI$1,0),FALSE) -> 0.0014349103 | E9: =VLOOKUP($B9,Shock_dev!$A$1:$CI$100,MATCH(DATE(E$3,1,1),Shock_dev!$A$1:$CI$1,0),FALSE) -> 0.00025187778 | F9: =VLOOKUP($B9,Shock_dev!$A$1:$CI$100,MATCH(DATE(F$3,1,1),Shock_dev!$A$1:$CI$1,0),FALSE) -> -0.0017272387 | G9: =VLOOKUP($B9,Shock_dev!$A$1:$CI$100,MATCH(DATE(G$3,1,1),Shock_dev!$A$1:$CI$1,0),FALSE) -> -0.0044094594 | H9: =VLOOKUP($B9,Shock_dev!$A$1:$CI$100,MATCH(DATE(H$3,1,1),Shock_dev!$A$1:$CI$1,0),FALSE) -> -0.023596583 | I9: =VLOOKUP($B9,Shock_dev!$A$1:$CI$100,MATCH(DATE(I$3,1,1),Shock_dev!$A$1:$CI$1,0),FALSE) -> -0.071813114 | J9: =VLOOKUP($B9,Shock_dev!$A$1:$CI$100,MATCH(DATE(J$3,1,1),Shock_dev!$A$1:$CI$1,0),FALSE) -> -0.15035773
A10: Saving rate (in points) | B10: =Shock_dev!A8 -> 100*(rsav_h_val_2-rsav_h_val_0) | C10: =VLOOKUP($B10,Shock_dev!$A$1:$CI$100,MATCH(DATE(C$3,1,1),Shock_dev!$A$1:$CI$1,0),FALSE) -> 1.766e-05 | D10: =VLOOKUP($B10,Shock_dev!$A$1:$CI$100,MATCH(DATE(D$3,1,1),Shock_dev!$A$1:$CI$1,0),FALSE) -> -0.00015472 | E10: =VLOOKUP($B10,Shock_dev!$A$1:$CI$100,MATCH(DATE(E$3,1,1),Shock_dev!$A$1:$CI$1,0),FALSE) -> -0.00035976 | F10: =VLOOKUP($B10,Shock_dev!$A$1:$CI$100,MATCH(DATE(F$3,1,1),Shock_dev!$A$1:$CI$1,0),FALSE) -> -0.00054142 | G10: =VLOOKUP($B10,Shock_dev!$A$1:$CI$100,MATCH(DATE(G$3,1,1),Shock_dev!$A$1:$CI$1,0),FALSE) -> -0.00066203 | H10: =VLOOKUP($B10,Shock_dev!$A$1:$CI$100,MATCH(DATE(H$3,1,1),Shock_dev!$A$1:$CI$1,0),FALSE) -> -0.0004444 | I10: =VLOOKUP($B10,Shock_dev!$A$1:$CI$100,MATCH(DATE(I$3,1,1),Shock_dev!$A$1:$CI$1,0),FALSE) -> -0.00036605 | J10: =VLOOKUP($B10,Shock_dev!$A$1:$CI$100,MATCH(DATE(J$3,1,1),Shock_dev!$A$1:$CI$1,0),FALSE) -> -0.00090815
A11: Household consumption price index | B11: =Shock_dev!A9 -> 100*(pch_2/pch_0-1) | C11: =VLOOKUP($B11,Shock_dev!$A$1:$CI$100,MATCH(DATE(C$3,1,1),Shock_dev!$A$1:$CI$1,0),FALSE) -> -0.0046793428 | D11: =VLOOKUP($B11,Shock_dev!$A$1:$CI$100,MATCH(DATE(D$3,1,1),Shock_dev!$A$1:$CI$1,0),FALSE) -> -0.0052204882 | E11: =VLOOKUP($B11,Shock_dev!$A$1:$CI$100,MATCH(DATE(E$3,1,1),Shock_dev!$A$1:$CI$1,0),FALSE) -> -0.0044904689 | F11: =VLOOKUP($B11,Shock_dev!$A$1:$CI$100,MATCH(DATE(F$3,1,1),Shock_dev!$A$1:$CI$1,0),FALSE) -> -0.0020251151 | G11: =VLOOKUP($B11,Shock_dev!$A$1:$CI$100,MATCH(DATE(G$3,1,1),Shock_dev!$A$1:$CI$1,0),FALSE) -> 0.0025375014 | H11: =VLOOKUP($B11,Shock_dev!$A$1:$CI$100,MATCH(DATE(H$3,1,1),Shock_dev!$A$1:$CI$1,0),FALSE) -> 0.064833459 | I11: =VLOOKUP($B11,Shock_dev!$A$1:$CI$100,MATCH(DATE(I$3,1,1),Shock_dev!$A$1:$CI$1,0),FALSE) -> 0.43509752 | J11: =VLOOKUP($B11,Shock_dev!$A$1:$CI$100,MATCH(DATE(J$3,1,1),Shock_dev!$A$1:$CI$1,0),FALSE) -> 1.2122639
A12: Production price index | B12: =Shock_dev!A10 -> 100*(py_2/py_0-1) | C12: =VLOOKUP($B12,Shock_dev!$A$1:$CI$100,MATCH(DATE(C$3,1,1),Shock_dev!$A$1:$CI$1,0),FALSE) -> -0.0048447719 | D12: =VLOOKUP($B12,Shock_dev!$A$1:$CI$100,MATCH(DATE(D$3,1,1),Shock_dev!$A$1:$CI$1,0),FALSE) -> -0.0055926527 | E12: =VLOOKUP($B12,Shock_dev!$A$1:$CI$100,MATCH(DATE(E$3,1,1),Shock_dev!$A$1:$CI$1,0),FALSE) -> -0.0051118099 | F12: =VLOOKUP($B12,Shock_dev!$A$1:$CI$100,MATCH(DATE(F$3,1,1),Shock_dev!$A$1:$CI$1,0),FALSE) -> -0.0028694848 | G12: =VLOOKUP($B12,Shock_dev!$A$1:$CI$100,MATCH(DATE(G$3,1,1),Shock_dev!$A$1:$CI$1,0),FALSE) -> 0.0015822878 | H12: =VLOOKUP($B12,Shock_dev!$A$1:$CI$100,MATCH(DATE(H$3,1,1),Shock_dev!$A$1:$CI$1,0),FALSE) -> 0.067854111 | I12: =VLOOKUP($B12,Shock_dev!$A$1:$CI$100,MATCH(DATE(I$3,1,1),Shock_dev!$A$1:$CI$1,0),FALSE) -> 0.48790679 | J12: =VLOOKUP($B12,Shock_dev!$A$1:$CI$100,MATCH(DATE(J$3,1,1),Shock_dev!$A$1:$CI$1,0),FALSE) -> 1.406838
A13: Added value price index | B13: =Shock_dev!A11 -> 100*(pva_2/pva_0-1) | C13: =VLOOKUP($B13,Shock_dev!$A$1:$CI$100,MATCH(DATE(C$3,1,1),Shock_dev!$A$1:$CI$1,0),FALSE) -> -0.0053331561 | D13: =VLOOKUP($B13,Shock_dev!$A$1:$CI$100,MATCH(DATE(D$3,1,1),Shock_dev!$A$1:$CI$1,0),FALSE) -> -0.0063043356 | E13: =VLOOKUP($B13,Shock_dev!$A$1:$CI$100,MATCH(DATE(E$3,1,1),Shock_dev!$A$1:$CI$1,0),FALSE) -> -0.0059873203 | F13: =VLOOKUP($B13,Shock_dev!$A$1:$CI$100,MATCH(DATE(F$3,1,1),Shock_dev!$A$1:$CI$1,0),FALSE) -> -0.0037575332 | G13: =VLOOKUP($B13,Shock_dev!$A$1:$CI$100,MATCH(DATE(G$3,1,1),Shock_dev!$A$1:$CI$1,0),FALSE) -> 0.00092781393 | H13: =VLOOKUP($B13,Shock_dev!$A$1:$CI$100,MATCH(DATE(H$3,1,1),Shock_dev!$A$1:$CI$1,0),FALSE) -> 0.07483793 | I13: =VLOOKUP($B13,Shock_dev!$A$1:$CI$100,MATCH(DATE(I$3,1,1),Shock_dev!$A$1:$CI$1,0),FALSE) -> 0.55750449 | J13: =VLOOKUP($B13,Shock_dev!$A$1:$CI$100,MATCH(DATE(J$3,1,1),Shock_dev!$A$1:$CI$1,0),FALSE) -> 1.6093293
A14: Intermediate consumption price index | B14: =Shock_dev!A12 -> 100*(pci_2/pci_0-1) | C14: =VLOOKUP($B14,Shock_dev!$A$1:$CI$100,MATCH(DATE(C$3,1,1),Shock_dev!$A$1:$CI$1,0),FALSE) -> -0.0044225415 | D14: =VLOOKUP($B14,Shock_dev!$A$1:$CI$100,MATCH(DATE(D$3,1,1),Shock_dev!$A$1:$CI$1,0),FALSE) -> -0.0049771667 | E14: =VLOOKUP($B14,Shock_dev!$A$1:$CI$100,MATCH(DATE(E$3,1,1),Shock_dev!$A$1:$CI$1,0),FALSE) -> -0.0043547639 | F14: =VLOOKUP($B14,Shock_dev!$A$1:$CI$100,MATCH(DATE(F$3,1,1),Shock_dev!$A$1:$CI$1,0),FALSE) -> -0.0021016782 | G14: =VLOOKUP($B14,Shock_dev!$A$1:$CI$100,MATCH(DATE(G$3,1,1),Shock_dev!$A$1:$CI$1,0),FALSE) -> 0.0021482461 | H14: =VLOOKUP($B14,Shock_dev!$A$1:$CI$100,MATCH(DATE(H$3,1,1),Shock_dev!$A$1:$CI$1,0),FALSE) -> 0.061815482 | I14: =VLOOKUP($B14,Shock_dev!$A$1:$CI$100,MATCH(DATE(I$3,1,1),Shock_dev!$A$1:$CI$1,0),FALSE) -> 0.4277225 | J14: =VLOOKUP($B14,Shock_dev!$A$1:$CI$100,MATCH(DATE(J$3,1,1),Shock_dev!$A$1:$CI$1,0),FALSE) -> 1.2316926
A15: Export price index | B15: =Shock_dev!A13 -> 100*(px_2/px_0-1) | C15: =VLOOKUP($B15,Shock_dev!$A$1:$CI$100,MATCH(DATE(C$3,1,1),Shock_dev!$A$1:$CI$1,0),FALSE) -> -0.0025382662 | D15: =VLOOKUP($B15,Shock_dev!$A$1:$CI$100,MATCH(DATE(D$3,1,1),Shock_dev!$A$1:$CI$1,0),FALSE) -> -0.0030142276 | E15: =VLOOKUP($B15,Shock_dev!$A$1:$CI$100,MATCH(DATE(E$3,1,1),Shock_dev!$A$1:$CI$1,0),FALSE) -> -0.0028795058 | F15: =VLOOKUP($B15,Shock_dev!$A$1:$CI$100,MATCH(DATE(F$3,1,1),Shock_dev!$A$1:$CI$1,0),FALSE) -> -0.0018314899 | G15: =VLOOKUP($B15,Shock_dev!$A$1:$CI$100,MATCH(DATE(G$3,1,1),Shock_dev!$A$1:$CI$1,0),FALSE) -> 0.0003926187 | H15: =VLOOKUP($B15,Shock_dev!$A$1:$CI$100,MATCH(DATE(H$3,1,1),Shock_dev!$A$1:$CI$1,0),FALSE) -> 0.035663593 | I15: =VLOOKUP($B15,Shock_dev!$A$1:$CI$100,MATCH(DATE(I$3,1,1),Shock_dev!$A$1:$CI$1,0),FALSE) -> 0.26554353 | J15: =VLOOKUP($B15,Shock_dev!$A$1:$CI$100,MATCH(DATE(J$3,1,1),Shock_dev!$A$1:$CI$1,0),FALSE) -> 0.76674579
... A23: Public debt (in points of GDP) | B23: =Shock_dev!A21 -> 100*(rdebt_g_val_2-rdebt_g_val_0) | C23: =VLOOKUP($B23,Shock_dev!$A$1:$CI$100,MATCH(DATE(C$3,1,1),Shock_dev!$A$1:$CI$1,0),FALSE) -> 0.00328952 | D23: =VLOOKUP($B23,Shock_dev!$A$1:$CI$100,MATCH(DATE(D$3,1,1),Shock_dev!$A$1:$CI$1,0),FALSE) -> 0.00441664 | E23: =VLOOKUP($B23,Shock_dev!$A$1:$CI$100,MATCH(DATE(E$3,1,1),Shock_dev!$A$1:$CI$1,0),FALSE) -> 0.00522445 | F23: =VLOOKUP($B23,Shock_dev!$A$1:$CI$100,MATCH(DATE(F$3,1,1),Shock_dev!$A$1:$CI$1,0),FALSE) -> 0.00532517 | G23: =VLOOKUP($B23,Shock_dev!$A$1:$CI$100,MATCH(DATE(G$3,1,1),Shock_dev!$A$1:$CI$1,0),FALSE) -> 0.00422063 | H23: =VLOOKUP($B23,Shock_dev!$A$1:$CI$100,MATCH(DATE(H$3,1,1),Shock_dev!$A$1:$CI$1,0),FALSE) -> -0.0435568 | I23: =VLOOKUP($B23,Shock_dev!$A$1:$CI$100,MATCH(DATE(I$3,1,1),Shock_dev!$A$1:$CI$1,0),FALSE) -> -0.68435193 | J23: =VLOOKUP($B23,Shock_dev!$A$1:$CI$100,MATCH(DATE(J$3,1,1),Shock_dev!$A$1:$CI$1,0),FALSE) -> -2.7567188

Sheet Tab-GDP
C1: 2021 | D1: =C1+1 -> 2022 | E1: =D1+1 -> 2023 | F1: =E1+1 -> 2024 | G1: =F1+1 -> 2025 | H1: =G1+1 -> 2026 | I1: =H1+1 -> 2027 | J1: =I1+1 -> 2028 | K1: =J1+1 -> 2029 | ... AF1: =AE1+1 -> 2050 | AH1: 2021-25 | AI1: 2026-30 | AJ1: 2031-35 | AK1: 2036-40 | AL1: 2041-45 | AM1: 2046-50 | AO1: 2021-30 | AP1: 2031-40 | AQ1: 2041-50
B26: 100*i_0/gdp_0*(i_2/i_0-1) | C26: =VLOOKUP($B26,Shock_dev!$A$1:$CI$100,MATCH(DATE(C$1,1,1),Shock_dev!$A$1:$CI$1,0),FALSE) -> 0.0005056371 | D26: =VLOOKUP($B26,Shock_dev!$A$1:$CI$100,MATCH(DATE(D$1,1,1),Shock_dev!$A$1:$CI$1,0),FALSE) -> 0.00060047602 | E26: =VLOOKUP($B26,Shock_dev!$A$1:$CI$100,MATCH(DATE(E$1,1,1),Shock_dev!$A$1:$CI$1,0),FALSE) -> 0.00055936093 | F26: =VLOOKUP($B26,Shock_dev!$A$1:$CI$100,MATCH(DATE(F$1,1,1),Shock_dev!$A$1:$CI$1,0),FALSE) -> 0.0003177586 | G26: =VLOOKUP($B26,Shock_dev!$A$1:$CI$100,MATCH(DATE(G$1,1,1),Shock_dev!$A$1:$CI$1,0),FALSE) -> -0.00017098194 | H26: =VLOOKUP($B26,Shock_dev!$A$1:$CI$100,MATCH(DATE(H$1,1,1),Shock_dev!$A$1:$CI$1,0),FALSE) -> -0.00093557835 | I26: =VLOOKUP($B26,Shock_dev!$A$1:$CI$100,MATCH(DATE(I$1,1,1),Shock_dev!$A$1:$CI$1,0),FALSE) -> -0.0019909054 | J26: =VLOOKUP($B26,Shock_dev!$A$1:$CI$100,MATCH(DATE(J$1,1,1),Shock_dev!$A$1:$CI$1,0),FALSE) -> -0.0033432879 | ... AF26: =VLOOKUP($B26,Shock_dev!$A$1:$CI$100,MATCH(DATE(AF$1,1,1),Shock_dev!$A$1:$CI$1,0),FALSE) -> -0.11798975 | AH26: =AVERAGE(C26:G26) -> 0.00036245014 | AI26: =AVERAGE(H26:L26) -> -0.0036422838 | AJ26: =AVERAGE(M26:Q26) -> -0.014935462 | AK26: =AVERAGE(R26:V26) -> -0.0341225 | AL26: =AVERAGE(W26:AA26) -> -0.062100184 | AM26: =AVERAGE(AB26:AF26) -> -0.10012029 | AO26: =AVERAGE(AH26:AI26) -> -0.0016399168 | AP26: =AVERAGE(AJ26:AK26) -> -0.024528981 | AQ26: =AVERAGE(AL26:AM26) -> -0.081110235
B27: 100*ds_0/gdp_0*(ds_2/ds_0-1) | C27: =VLOOKUP($B27,Shock_dev!$A$1:$CI$100,MATCH(DATE(C$1,1,1),Shock_dev!$A$1:$CI$1,0),FALSE) -> 0 | D27: =VLOOKUP($B27,Shock_dev!$A$1:$CI$100,MATCH(DATE(D$1,1,1),Shock_dev!$A$1:$CI$1,0),FALSE) -> 0 | E27: =VLOOKUP($B27,Shock_dev!$A$1:$CI$100,MATCH(DATE(E$1,1,1),Shock_dev!$A$1:$CI$1,0),FALSE) -> 0 | F27: =VLOOKUP($B27,Shock_dev!$A$1:$CI$100,MATCH(DATE(F$1,1,1),Shock_dev!$A$1:$CI$1,0),FALSE) -> 0 | G27: =VLOOKUP($B27,Shock_dev!$A$1:$CI$100,MATCH(DATE(G$1,1,1),Shock_dev!$A$1:$CI$1,0),FALSE) -> 0 | H27: =VLOOKUP($B27,Shock_dev!$A$1:$CI$100,MATCH(DATE(H$1,1,1),Shock_dev!$A$1:$CI$1,0),FALSE) -> 0 | I27: =VLOOKUP($B27,Shock_dev!$A$1:$CI$100,MATCH(DATE(I$1,1,1),Shock_dev!$A$1:$CI$1,0),FALSE) -> 0 | J27: =VLOOKUP($B27,Shock_dev!$A$1:$CI$100,MATCH(DATE(J$1,1,1),Shock_dev!$A$1:$CI$1,0),FALSE) -> 0 | ... AF27: =VLOOKUP($B27,Shock_dev!$A$1:$CI$100,MATCH(DATE(AF$1,1,1),Shock_dev!$A$1:$CI$1,0),FALSE) -> 0 | AH27: =AVERAGE(C27:G27) -> 0 | AI27: =AVERAGE(H27:L27) -> 0 | AJ27: =AVERAGE(M27:Q27) -> 0 | AK27: =AVERAGE(R27:V27) -> 0 | AL27: =AVERAGE(W27:AA27) -> 0 | AM27: =AVERAGE(AB27:AF27) -> 0 | AO27: =AVERAGE(AH27:AI27) -> 0 | AP27: =AVERAGE(AJ27:AK27) -> 0 | AQ27: =AVERAGE(AL27:AM27) -> 0
B28: 100*(gdp_2/gdp_0-1) | C28: =VLOOKUP($B28,Shock_dev!$A$1:$CI$100,MATCH(DATE(C$1,1,1),Shock_dev!$A$1:$CI$1,0),FALSE) -> 0.0014626161 | D28: =VLOOKUP($B28,Shock_dev!$A$1:$CI$100,MATCH(DATE(D$1,1,1),Shock_dev!$A$1:$CI$1,0),FALSE) -> 0.001683267 | E28: =VLOOKUP($B28,Shock_dev!$A$1:$CI$100,MATCH(DATE(E$1,1,1),Shock_dev!$A$1:$CI$1,0),FALSE) -> 0.0015073164 | F28: =VLOOKUP($B28,Shock_dev!$A$1:$CI$100,MATCH(DATE(F$1,1,1),Shock_dev!$A$1:$CI$1,0),FALSE) -> 0.00077487238 | G28: =VLOOKUP($B28,Shock_dev!$A$1:$CI$100,MATCH(DATE(G$1,1,1),Shock_dev!$A$1:$CI$1,0),FALSE) -> -0.00062909206 | H28: =VLOOKUP($B28,Shock_dev!$A$1:$CI$100,MATCH(DATE(H$1,1,1),Shock_dev!$A$1:$CI$1,0),FALSE) -> -0.0027823956 | I28: =VLOOKUP($B28,Shock_dev!$A$1:$CI$100,MATCH(DATE(I$1,1,1),Shock_dev!$A$1:$CI$1,0),FALSE) -> -0.0057393703 | J28: =VLOOKUP($B28,Shock_dev!$A$1:$CI$100,MATCH(DATE(J$1,1,1),Shock_dev!$A$1:$CI$1,0),FALSE) -> -0.0095427768 | ... AF28: =VLOOKUP($B28,Shock_dev!$A$1:$CI$100,MATCH(DATE(AF$1,1,1),Shock_dev!$A$1:$CI$1,0),FALSE) -> -0.3939661 | AH28: =AVERAGE(C28:G28) -> 0.00095979596 | AI28: =AVERAGE(H28:L28) -> -0.010428714 | AJ28: =AVERAGE(M28:Q28) -> -0.043775445 | AK28: =AVERAGE(R28:V28) -> -0.10464347 | AL28: =AVERAGE(W28:AA28) -> -0.1984417 | AM28: =AVERAGE(AB28:AF28) -> -0.33073905 | AO28: =AVERAGE(AH28:AI28) -> -0.0047344588 | AP28: =AVERAGE(AJ28:AK28) -> -0.074209457 | AQ28: =AVERAGE(AL28:AM28) -> -0.26459038
A29: Consumption | B29: 100*(ch_0+g_0)/gdp_0*((ch_2+g_2)/(ch_0+g_0)-1) | C29: =VLOOKUP($B29,Shock_dev!$A$1:$CI$100,MATCH(DATE(C$1,1,1),Shock_dev!$A$1:$CI$1,0),FALSE) -> 0.00081047787 | D29: =VLOOKUP($B29,Shock_dev!$A$1:$CI$100,MATCH(DATE(D$1,1,1),Shock_dev!$A$1:$CI$1,0),FALSE) -> 0.000740172 | E29: =VLOOKUP($B29,Shock_dev!$A$1:$CI$100,MATCH(DATE(E$1,1,1),Shock_dev!$A$1:$CI$1,0),FALSE) -> 0.00033982687 | F29: =VLOOKUP($B29,Shock_dev!$A$1:$CI$100,MATCH(DATE(F$1,1,1),Shock_dev!$A$1:$CI$1,0),FALSE) -> -0.00043179193 | G29: =VLOOKUP($B29,Shock_dev!$A$1:$CI$100,MATCH(DATE(G$1,1,1),Shock_dev!$A$1:$CI$1,0),FALSE) -> -0.0015568145 | H29: =VLOOKUP($B29,Shock_dev!$A$1:$CI$100,MATCH(DATE(H$1,1,1),Shock_dev!$A$1:$CI$1,0),FALSE) -> -0.0029790273 | I29: =VLOOKUP($B29,Shock_dev!$A$1:$CI$100,MATCH(DATE(I$1,1,1),Shock_dev!$A$1:$CI$1,0),FALSE) -> -0.004626752 | J29: =VLOOKUP($B29,Shock_dev!$A$1:$CI$100,MATCH(DATE(J$1,1,1),Shock_dev!$A$1:$CI$1,0),FALSE) -> -0.006430002 | ... AF29: =VLOOKUP($B29,Shock_dev!$A$1:$CI$100,MATCH(DATE(AF$1,1,1),Shock_dev!$A$1:$CI$1,0),FALSE) -> -0.066758713 | AH29: =AVERAGE(C29:G29) -> -1.9625933e-05 | AI29: =AVERAGE(H29:L29) -> -0.0065305366 | AJ29: =AVERAGE(M29:Q29) -> -0.016311448 | AK29: =AVERAGE(R29:V29) -> -0.027119246 | AL29: =AVERAGE(W29:AA29) -> -0.040577864 | AM29: =AVERAGE(AB29:AF29) -> -0.058405729 | AO29: =AVERAGE(AH29:AI29) -> -0.0032750812 | AP29: =AVERAGE(AJ29:AK29) -> -0.021715347 | AQ29: =AVERAGE(AL29:AM29) -> -0.049491797
A30: Investment | C30: =SUM(C26:C27) -> 0.0005056371 | D30: =SUM(D26:D27) -> 0.00060047602 | E30: =SUM(E26:E27) -> 0.00055936093 | F30: =SUM(F26:F27) -> 0.0003177586 | G30: =SUM(G26:G27) -> -0.00017098194 | H30: =SUM(H26:H27) -> -0.00093557835 | I30: =SUM(I26:I27) -> -0.0019909054 | J30: =SUM(J26:J27) -> -0.0033432879 | ... AF30: =SUM(AF26:AF27) -> -0.11798975 | AH30: =AVERAGE(C30:G30) -> 0.00036245014 | AI30: =AVERAGE(H30:L30) -> -0.0036422838 | AJ30: =AVERAGE(M30:Q30) -> -0.014935462 | AK30: =AVERAGE(R30:V30) -> -0.0341225 | AL30: =AVERAGE(W30:AA30) -> -0.062100184 | AM30: =AVERAGE(AB30:AF30) -> -0.10012029 | AO30: =AVERAGE(AH30:AI30) -> -0.0016399168 | AP30: =AVERAGE(AJ30:AK30) -> -0.024528981 | AQ30: =AVERAGE(AL30:AM30) -> -0.081110235
A31: Trade balance | B31: 100*(x_0-m_0)/gdp_0*((x_2-m_2)/(x_0-m_0)-1) | C31: =VLOOKUP($B31,Shock_dev!$A$1:$CI$100,MATCH(DATE(C$1,1,1),Shock_dev!$A$1:$CI$1,0),FALSE) -> 0.00014648755 | D31: =VLOOKUP($B31,Shock_dev!$A$1:$CI$100,MATCH(DATE(D$1,1,1),Shock_dev!$A$1:$CI$1,0),FALSE) -> 0.00034261897 | E31: =VLOOKUP($B31,Shock_dev!$A$1:$CI$100,MATCH(DATE(E$1,1,1),Shock_dev!$A$1:$CI$1,0),FALSE) -> 0.00060812864 | F31: =VLOOKUP($B31,Shock_dev!$A$1:$CI$100,MATCH(DATE(F$1,1,1),Shock_dev!$A$1:$CI$1,0),FALSE) -> 0.00088887957 | G31: =VLOOKUP($B31,Shock_dev!$A$1:$CI$100,MATCH(DATE(G$1,1,1),Shock_dev!$A$1:$CI$1,0),FALSE) -> 0.0010987044 | H31: =VLOOKUP($B31,Shock_dev!$A$1:$CI$100,MATCH(DATE(H$1,1,1),Shock_dev!$A$1:$CI$1,0),FALSE) -> 0.0011321972 | I31: =VLOOKUP($B31,Shock_dev!$A$1:$CI$100,MATCH(DATE(I$1,1,1),Shock_dev!$A$1:$CI$1,0),FALSE) -> 0.00087827449 | J31: =VLOOKUP($B31,Shock_dev!$A$1:$CI$100,MATCH(DATE(J$1,1,1),Shock_dev!$A$1:$CI$1,0),FALSE) -> 0.00023051302 | ... AF31: =VLOOKUP($B31,Shock_dev!$A$1:$CI$100,MATCH(DATE(AF$1,1,1),Shock_dev!$A$1:$CI$1,0),FALSE) -> -0.20921771 | AH31: =AVERAGE(C31:G31) -> 0.00061696382 | AI31: =AVERAGE(H31:L31) -> -0.00025589827 | AJ31: =AVERAGE(M31:Q31) -> -0.012528541 | AK31: =AVERAGE(R31:V31) -> -0.043401718 | AL31: =AVERAGE(W31:AA31) -> -0.095763659 | AM31: =AVERAGE(AB31:AF31) -> -0.17221306 | AO31: =AVERAGE(AH31:AI31) -> 0.00018053278 | AP31: =AVERAGE(AJ31:AK31) -> -0.027965129 | AQ31: =AVERAGE(AL31:AM31) -> -0.13398836
A32: VERIF | C32: =IF(ROUND(C28-SUM(C29:C31),4)=0,"","ERROR") | D32: =IF(ROUND(D28-SUM(D29:D31),4)=0,"","ERROR") | E32: =IF(ROUND(E28-SUM(E29:E31),4)=0,"","ERROR") | F32: =IF(ROUND(F28-SUM(F29:F31),4)=0,"","ERROR") | G32: =IF(ROUND(G28-SUM(G29:G31),4)=0,"","ERROR") | H32: =IF(ROUND(H28-SUM(H29:H31),4)=0,"","ERROR") | I32: =IF(ROUND(I28-SUM(I29:I31),4)=0,"","ERROR") | J32: =IF(ROUND(J28-SUM(J29:J31),4)=0,"","ERROR") | ... AQ32: =IF(ROUND(AQ28-SUM(AQ29:AQ31),4)=0,"","ERROR")

Sheet Baseline
A1: @date | B1: 42005 | C1: 42370 | D1: 42736 | E1: 43101 | F1: 43466 | G1: 43831 | H1: 44197 | I1: 44562 | J1: 44927 | K1: 45292 | L1: 45658 | M1: 46023 | N1: 46388 | O1: 46753 | P1: 47119 | Q1: 47484 | R1: 47849 | S1: 48214 | T1: 48580 | U1: 48945 | V1: 49310 | W1: 49675 | X1: 50041 | Y1: 50406 | Z1: 50771 | AA1: 51136 | AB1: 51502 | AC1: 51867 | AD1: 52232 | AE1: 52597 | AF1: 52963 | AG1: 53328 | AH1: 53693 | AI1: 54058 | AJ1: 54424 | AK1: 54789
A2: @pch(gdp_0) | B2: 0.0115225 | C2: 0.0115225 | D2: 0.0115225 | E2: 0.0115225 | F2: 0.0115225 | G2: 0.0115225 | H2: 0.0115225 | I2: 0.0115225 | J2: 0.0115225 | K2: 0.0115225 | L2: 0.0115225 | M2: 0.0115225 | N2: 0.0115225 | O2: 0.0115225 | P2: 0.0115225 | Q2: 0.0115225 | R2: 0.0115225 | S2: 0.0115225 | T2: 0.0115225 | U2: 0.0115225 | V2: 0.0115225 | W2: 0.0115225 | X2: 0.0115225 | Y2: 0.0115225 | Z2: 0.0115225 | AA2: 0.0115225 | AB2: 0.0115225 | AC2: 0.0115225 | AD2: 0.0115225 | AE2: 0.0115225 | AF2: 0.0115225 | AG2: 0.0115225 | AH2: 0.0115225 | AI2: 0.0115225 | AJ2: 0.0115225 | AK2: 0.0115225
A3: @pch(pch_0) | B3: 0.02 | C3: 0.02 | D3: 0.02 | E3: 0.02 | F3: 0.02 | G3: 0.02 | H3: 0.02 | I3: 0.020000001 | J3: 0.02 | K3: 0.02 | L3: 0.02 | M3: 0.02 | N3: 0.020000001 | O3: 0.019999999 | P3: 0.02 | Q3: 0.02 | R3: 0.02 | S3: 0.02 | T3: 0.02 | U3: 0.02 | V3: 0.02 | W3: 0.02 | X3: 0.02 | Y3: 0.02 | Z3: 0.02 | AA3: 0.019999999 | AB3: 0.02 | AC3: 0.02 | AD3: 0.02 | AE3: 0.02 | AF3: 0.02 | AG3: 0.02 | AH3: 0.02 | AI3: 0.02 | AJ3: 0.02 | AK3: 0.02
A4: unr_0 | B4: 0.069 | C4: 0.069 | D4: 0.069 | E4: 0.069 | F4: 0.069 | G4: 0.069 | H4: 0.069 | I4: 0.069 | J4: 0.069 | K4: 0.069 | L4: 0.069 | M4: 0.069 | N4: 0.069 | O4: 0.069 | P4: 0.069 | Q4: 0.069 | R4: 0.069 | S4: 0.069 | T4: 0.069 | U4: 0.069 | V4: 0.069 | W4: 0.069 | X4: 0.069 | Y4: 0.069 | Z4: 0.069 | AA4: 0.069 | AB4: 0.069 | AC4: 0.069 | AD4: 0.069 | AE4: 0.069 | AF4: 0.069 | AG4: 0.069 | AH4: 0.069 | AI4: 0.069 | AJ4: 0.069 | AK4: 0.069
A5: rdebt_g_val_0 | B5: 0.647 | C5: 0.647 | D5: 0.647 | E5: 0.647 | F5: 0.647 | G5: 0.647 | H5: 0.647 | I5: 0.647 | J5: 0.647 | K5: 0.647 | L5: 0.647 | M5: 0.647 | N5: 0.647 | O5: 0.647 | P5: 0.647 | Q5: 0.647 | R5: 0.647 | S5: 0.647 | T5: 0.647 | U5: 0.647 | V5: 0.647 | W5: 0.647 | X5: 0.647 | Y5: 0.647 | Z5: 0.647 | AA5: 0.647 | AB5: 0.647 | AC5: 0.647 | AD5: 0.647 | AE5: 0.647 | AF5: 0.647 | AG5: 0.647 | AH5: 0.647 | AI5: 0.647 | AJ5: 0.647 | AK5: 0.647
A6: rbal_g_prim_val_0 | B6: -0.006270881 | C6: -0.006270881 | D6: -0.006270881 | E6: -0.006270881 | F6: -0.006270881 | G6: -0.006270881 | H6: -0.006270881 | I6: -0.006270881 | J6: -0.006270881 | K6: -0.006270881 | L6: -0.006270881 | M6: -0.006270881 | N6: -0.006270881 | O6: -0.006270881 | P6: -0.006270881 | Q6: -0.006270881 | R6: -0.006270881 | S6: -0.006270881 | T6: -0.006270881 | U6: -0.006270881 | V6: -0.006270881 | W6: -0.006270881 | X6: -0.006270881 | Y6: -0.006270881 | Z6: -0.006270881 | AA6: -0.006270881 | AB6: -0.006270881 | AC6: -0.006270881 | AD6: -0.006270881 | AE6: -0.006270881 | AF6: -0.006270881 | AG6: -0.006270881 | AH6: -0.006270881 | AI6: -0.006270881 | AJ6: -0.006270881 | AK6: -0.006270881
A7: rbal_trade_val_0 | B7: 0.077659969 | C7: 0.077659969 | D7: 0.077659969 | E7: 0.077659969 | F7: 0.077659969 | G7: 0.077659969 | H7: 0.077659969 | I7: 0.077659969 | J7: 0.077659969 | K7: 0.077659969 | L7: 0.077659969 | M7: 0.077659969 | N7: 0.077659969 | O7: 0.077659969 | P7: 0.077659969 | Q7: 0.077659969 | R7: 0.077659969 | S7: 0.077659969 | T7: 0.077659969 | U7: 0.077659969 | V7: 0.077659969 | W7: 0.077659969 | X7: 0.077659969 | Y7: 0.077659969 | Z7: 0.077659969 | AA7: 0.077659969 | AB7: 0.077659969 | AC7: 0.077659969 | AD7: 0.077659969 | AE7: 0.077659969 | AF7: 0.077659969 | AG7: 0.077659969 | AH7: 0.077659969 | AI7: 0.077659969 | AJ7: 0.077659969 | AK7: 0.077659969
A8: pop | B8: 16900.726 | C8: 16942.978 | D8: 16985.335 | E8: 17027.799 | F8: 17070.368 | G8: 17113.044 | H8: 17155.827 | I8: 17198.716 | J8: 17241.713 | K8: 17284.817 | L8: 17328.029 | M8: 17371.349 | N8: 17414.778 | O8: 17458.315 | P8: 17501.96 | Q8: 17545.715 | R8: 17589.58 | S8: 17633.554 | T8: 17677.638 | U8: 17721.832 | V8: 17766.136 | W8: 17810.552 | X8: 17855.078 | Y8: 17899.716 | Z8: 17944.465 | AA8: 17989.326 | AB8: 18034.299 | AC8: 18079.385 | AD8: 18124.584 | AE8: 18169.895 | AF8: 18215.32 | AG8: 18260.858 | AH8: 18306.51 | AI8: 18352.276 | AJ8: 18398.157 | AK8: 18444.153
A9: gdp_0 | B9: 690008 | C9: 697958.62 | D9: 706000.85 | E9: 714135.74 | F9: 722364.37 | G9: 730687.81 | H9: 739107.16 | I9: 747623.53 | J9: 756238.02 | K9: 764951.77 | L9: 773765.93 | M9: 782681.64 | N9: 791700.09 | O9: 800822.46 | P9: 810049.93 | Q9: 819383.74 | R9: 828825.08 | S9: 838375.22 | T9: 848035.4 | U9: 857806.89 | V9: 867690.97 | W9: 877688.94 | X9: 887802.11 | Y9: 898031.81 | Z9: 908379.38 | AA9: 918846.18 | AB9: 929433.59 | AC9: 940142.98 | AD9: 950975.78 | AE9: 961933.4 | AF9: 973017.28 | AG9: 984228.87 | AH9: 995569.65 | AI9: 1007041.1 | AJ9: 1018644.7 | AK9: 1030382.1
A10: pch_0 | B10: 1 | C10: 1.02 | D10: 1.0404 | E10: 1.061208 | F10: 1.0824322 | G10: 1.1040808 | H10: 1.1261624 | I10: 1.1486857 | J10: 1.1716594 | K10: 1.1950926 | L10: 1.2189944 | M10: 1.2433743 | N10: 1.2682418 | O10: 1.2936066 | P10: 1.3194788 | Q10: 1.3458683 | R10: 1.3727857 | S10: 1.4002414 | T10: 1.4282462 | U10: 1.4568112 | V10: 1.4859474 | W10: 1.5156663 | X10: 1.5459797 | Y10: 1.5768993 | Z10: 1.6084372 | AA10: 1.640606 | AB10: 1.6734181 | AC10: 1.7068865 | AD10: 1.7410242 | AE10: 1.7758447 | AF10: 1.8113616 | AG10: 1.8475888 | AH10: 1.8845406 | AI10: 1.9222314 | AJ10: 1.960676 | AK10: 1.9998896
A11: va_s1_0 | B11: 59446 | C11: 60130.967 | D11: 60823.826 | E11: 61524.668 | F11: 62233.586 | G11: 62950.673 | H11: 63676.022 | I11: 64409.729 | J11: 65151.89 | K11: 65902.602 | L11: 66661.965 | M11: 67430.078 | N11: 68207.041 | O11: 68992.956 | P11: 69787.928 | Q11: 70592.059 | R11: 71405.456 | S11: 72228.225 | T11: 73060.475 | U11: 73902.315 | V11: 74753.854 | W11: 75615.205 | X11: 76486.481 | Y11: 77367.797 | Z11: 78259.267 | AA11: 79161.01 | AB11: 80073.143 | AC11: 80995.785 | AD11: 81929.059 | AE11: 82873.087 | AF11: 83827.992 | AG11: 84793.9 | AH11: 85770.938 | AI11: 86759.233 | AJ11: 87758.917 | AK11: 88770.119
A12: va_s2_0 | B12: 375834 | C12: 380164.55 | D12: 384544.99 | E12: 388975.91 | F12: 393457.89 | G12: 397991.51 | H12: 402577.36 | I12: 407216.06 | J12: 411908.21 | K12: 416654.42 | L12: 421455.32 | M12: 426311.54 | N12: 431223.71 | O12: 436192.49 | P12: 441218.52 | Q12: 446302.46 | R12: 451444.98 | S12: 456646.75 | T12: 461908.47 | U12: 467230.81 | V12: 472614.47 | W12: 478060.17 | X12: 483568.62 | Y12: 489140.54 | Z12: 494776.66 | AA12: 500477.73 | AB12: 506244.48 | AC12: 512077.68 | AD12: 517978.1 | AE12: 523946.5 | AF12: 529983.67 | AG12: 536090.41 | AH12: 542267.51 | AI12: 548515.79 | AJ12: 554836.06 | AK12: 561229.16
... A28: va_s18_0 | B28: 7817 | C28: 7907.0714 | D28: 7998.1806 | E28: 8090.3396 | F28: 8183.5606 | G28: 8277.8557 | H28: 8373.2373 | I28: 8469.7179 | J28: 8567.3102 | K28: 8666.027 | L28: 8765.8813 | M28: 8866.8862 | N28: 8969.0549 | O28: 9072.4008 | P28: 9176.9376 | Q28: 9282.6788 | R28: 9389.6385 | S28: 9497.8306 | T28: 9607.2694 | U28: 9717.9691 | V28: 9829.9444 | W28: 9943.21 | X28: 10057.781 | Y28: 10173.671 | Z28: 10290.897 | AA28: 10409.474 | AB28: 10529.418 | AC28: 10650.743 | AD28: 10773.466 | AE28: 10897.603 | AF28: 11023.171 | AG28: 11150.185 | AH28: 11278.663 | AI28: 11408.622 | AJ28: 11540.078 | AK28: 11673.048

Sheet Shock
A1: @date | B1: 42005 | C1: 42370 | D1: 42736 | E1: 43101 | F1: 43466 | G1: 43831 | H1: 44197 | I1: 44562 | J1: 44927 | K1: 45292 | L1: 45658 | M1: 46023 | N1: 46388 | O1: 46753 | P1: 47119 | Q1: 47484 | R1: 47849 | S1: 48214 | T1: 48580 | U1: 48945 | V1: 49310 | W1: 49675 | X1: 50041 | Y1: 50406 | Z1: 50771 | AA1: 51136 | AB1: 51502 | AC1: 51867 | AD1: 52232 | AE1: 52597 | AF1: 52963 | AG1: 53328 | AH1: 53693 | AI1: 54058 | AJ1: 54424 | AK1: 54789

Sheet Shock_dev
A1: _date_ | B1: 42005 | C1: 42370 | D1: 42736 | E1: 43101 | F1: 43466 | G1: 43831 | H1: 44197 | I1: 44562 | J1: 44927 | K1: 45292 | L1: 45658 | M1: 46023 | N1: 46388 | O1: 46753 | P1: 47119 | Q1: 47484 | R1: 47849 | S1: 48214 | T1: 48580 | U1: 48945 | V1: 49310 | W1: 49675 | X1: 50041 | Y1: 50406 | Z1: 50771 | AA1: 51136 | AB1: 51502 | AC1: 51867 | AD1: 52232 | AE1: 52597 | AF1: 52963 | AG1: 53328 | AH1: 53693 | AI1: 54058 | AJ1: 54424 | AK1: 54789
A2: 100*(gdp_2/gdp_0-1) | B2: 0 | C2: 1.5717264e-05 | D2: 9.0382328e-05 | E2: 0.00027714619 | F2: 0.00060437643 | G2: 0.0010398969 | H2: 0.0014626161 | I2: 0.001683267 | J2: 0.0015073164 | K2: 0.00077487238 | L2: -0.00062909206 | M2: -0.0027823956 | N2: -0.0057393703 | O2: -0.0095427768 | P2: -0.014232012 | Q2: -0.019847013 | R2: -0.026429762 | S2: -0.034023942 | T2: -0.042674327 | U2: -0.052425891 | V2: -0.063323305 | W2: -0.075410498 | X2: -0.08873063 | Y2: -0.10332614 | Z2: -0.119239 | AA2: -0.13651108 | AB2: -0.15518448 | AC2: -0.17530202 | AD2: -0.19690762 | AE2: -0.22004689 | AF2: -0.24476751 | AG2: -0.27111973 | AH2: -0.29915684 | AI2: -0.32893563 | AJ2: -0.36051696 | AK2: -0.3939661
A3: 100*(ch_2/ch_0-1) | B3: 0 | C3: 2.85075e-05 | D3: 0.00015698211 | E3: 0.00045582537 | F3: 0.00092927396 | G3: 0.0014644614 | H3: 0.0018098904 | I3: 0.0016528893 | J3: 0.00075887252 | K3: -0.00096424107 | L3: -0.0034765459 | M3: -0.0066525109 | N3: -0.01033207 | O3: -0.014358935 | P3: -0.018603211 | Q3: -0.022970473 | R3: -0.027401902 | S3: -0.031870057 | T3: -0.036372398 | U3: -0.040925111 | V3: -0.045557232 | W3: -0.05030582 | X3: -0.055212168 | Y3: -0.060318878 | Z3: -0.065667563 | AA3: -0.07129756 | AB3: -0.077244778 | AC3: -0.083541194 | AD3: -0.090214746 | AE3: -0.09728933 | AF3: -0.10478515 | AG3: -0.11271895 | AH3: -0.1211047 | AI3: -0.12995388 | AJ3: -0.13927616 | AK3: -0.14907989
A4: 100*(i_2/i_0-1) | B4: 0 | C4: 2.0675276e-05 | D4: 0.00012398412 | E4: 0.00039489019 | F4: 0.00089037408 | G4: 0.001579006 | H4: 0.0022873322 | I4: 0.0027163516 | J4: 0.0025303607 | K4: 0.001437433 | L4: -0.00077346481 | M4: -0.0042322418 | N4: -0.0090061866 | O4: -0.01512391 | P4: -0.022595368 | Q4: -0.031424629 | R4: -0.04161792 | S4: -0.053186401 | T4: -0.066147179 | U4: -0.080522888 | V4: -0.096340651 | W4: -0.11363182 | X4: -0.13243063 | Y4: -0.15277423 | Z4: -0.17470189 | AA4: -0.19825501 | AB4: -0.22347688 | AC4: -0.25041282 | AD4: -0.27910974 | AE4: -0.30961684 | AF4: -0.34198546 | AG4: -0.37626944 | AH4: -0.41252555 | AI4: -0.45081375 | AJ4: -0.49119786 | AK4: -0.53374594
A5: 100*(x_2/x_0-1) | B5: 0 | C5: 4.9907469e-06 | D5: 3.1556014e-05 | E5: 0.00010701624 | F5: 0.00025957712 | G5: 0.00050141508 | H5: 0.00080793683 | I5: 0.0011081675 | J5: 0.0012940637 | K5: 0.0012354916 | L5: 0.00079422462 | M5: -0.00016608434 | N5: -0.0017734213 | O5: -0.0041441082 | P5: -0.0073814703 | Q5: -0.0115758 | R5: -0.016805176 | S5: -0.023136645 | T5: -0.030627825 | U5: -0.039328355 | V5: -0.049281682 | W5: -0.060526599 | X5: -0.073098706 | Y5: -0.087031792 | Z5: -0.10235897 | AA5: -0.11911393 | AB5: -0.13733165 | AC5: -0.15704936 | AD5: -0.17830718 | AE5: -0.20114861 | AF5: -0.2256212 | AG5: -0.25177682 | AH5: -0.27967221 | AI5: -0.30936929 | AJ5: -0.3409355 | AK5: -0.37444426
A6: 100*(m_2/m_0-1) | B6: 0 | C6: 7.741116e-06 | D6: 4.4838103e-05 | E6: 0.00013774636 | F6: 0.00029869316 | G6: 0.00050671015 | H6: 0.00069396636 | I6: 0.00075900347 | J6: 0.00060320139 | K6: 0.00015635031 | L6: -0.00061711627 | M6: -0.0017245039 | N6: -0.003156146 | O6: -0.0048958222 | P6: -0.00692796 | Q6: -0.0092417337 | R6: -0.011832369 | S6: -0.014701181 | T6: -0.017854541 | U6: -0.02130277 | V6: -0.025059058 | W6: -0.029138458 | X6: -0.03355707 | Y6: -0.038331592 | Z6: -0.043478767 | AA6: -0.049015249 | AB6: -0.054957359 | AC6: -0.061321096 | AD6: -0.068122123 | AE6: -0.075375945 | AF6: -0.083097891 | AG6: -0.091303442 | AH6: -0.1000083 | AI6: -0.1092287 | AJ6: -0.11898151 | AK6: -0.1292846
A7: 100*((dispinc_at_val_2/pch_2)/(dispinc_at_val_0/pch_0)-1) | B7: 0 | C7: 4.1972962e-05 | D7: 0.00021384278 | E7: 0.00057787684 | F7: 0.0011011324 | G7: 0.001619767 | H7: 0.0018347614 | I7: 0.0014349103 | J7: 0.00025187778 | K7: -0.0017272387 | L7: -0.0044094594 | M7: -0.007652381 | N7: -0.011307134 | O7: -0.015244116 | P7: -0.01936327 | Q7: -0.023596583 | R7: -0.027904747 | S7: -0.032272484 | T7: -0.036703447 | U7: -0.041215334 | V7: -0.045835569 | W7: -0.05059784 | X7: -0.055539089 | Y7: -0.060697537 | Z7: -0.066110331 | AA7: -0.071813114 | AB7: -0.077838247 | AC7: -0.084215272 | AD7: -0.090970222 | AE7: -0.098125321 | AF7: -0.10569983 | AG7: -0.11371026 | AH7: -0.12217027 | AI7: -0.13109181 | AJ7: -0.14048463 | AK7: -0.15035773
A8: 100*(rsav_h_val_2-rsav_h_val_0) | B8: 0 | C8: 9.52e-06 | D8: 4.036e-05 | E8: 8.657e-05 | F8: 0.00012193 | G8: 0.00011021 | H8: 1.766e-05 | I8: -0.00015472 | J8: -0.00035976 | K8: -0.00054142 | L8: -0.00066203 | M8: -0.00070954 | N8: -0.000692 | O8: -0.00062821 | P8: -0.00053944 | Q8: -0.0004444 | R8: -0.0003569 | S8: -0.00028566 | T8: -0.00023501 | U8: -0.00020603 | V8: -0.0001976 | W8: -0.00020731 | X8: -0.00023213 | Y8: -0.00026885 | Z8: -0.0003144 | AA8: -0.00036605 | AB8: -0.00042147 | AC8: -0.00047877 | AD8: -0.00053653 | AE8: -0.00059373 | AF8: -0.00064973 | AG8: -0.0007042 | AH8: -0.00075707 | AI8: -0.00080847 | AJ8: -0.00085869 | AK8: -0.00090815
A9: 100*(pch_2/pch_0-1) | B9: 0 | C9: -6.1960784e-05 | D9: -0.00033631296 | E9: -0.0009822768 | F9: -0.0020594362 | G9: -0.0034295497 | H9: -0.0046793428 | I9: -0.0052204882 | J9: -0.0044904689 | K9: -0.0020251151 | L9: 0.0025375014 | M9: 0.0094766314 | N9: 0.019011753 | O9: 0.031321113 | P9: 0.046552928 | Q9: 0.064833459 | R9: 0.086271513 | S9: 0.11096237 | T9: 0.1389913 | U9: 0.17043671 | V9: 0.20537322 | W9: 0.24387445 | X9: 0.28601553 | Y9: 0.33187561 | Z9: 0.38153898 | AA9: 0.43509752 | AB9: 0.49265106 | AC9: 0.55430921 | AD9: 0.62019195 | AE9: 0.69043014 | AF9: 0.76516683 | AG9: 0.84455761 | AH9: 0.92877166 | AI9: 1.0179923 | AJ9: 1.1124181 | AK9: 1.2122639
A10: 100*(py_2/py_0-1) | B10: 0 | C10: -5.872549e-05 | D10: -0.00032304883 | E10: -0.00095796489 | F10: -0.0020423451 | G10: -0.0034665941 | H10: -0.0048447719 | I10: -0.0055926527 | J10: -0.0051118099 | K10: -0.0028694848 | L10: 0.0015822878 | M10: 0.0086124508 | N10: 0.018523912 | O10: 0.031567479 | P10: 0.047952041 | Q10: 0.067854111 | R10: 0.091424247 | S10: 0.11879416 | T10: 0.15008133 | U10: 0.18539506 | V10: 0.2248404 | W10: 0.26852256 | X10: 0.31655009 | Y10: 0.36903848 | Z10: 0.42611205 | AA10: 0.48790679 | AB10: 0.55457186 | AC10: 0.62627141 | AD10: 0.70318615 | AE10: 0.78551419 | AF10: 0.87347292 | AG10: 0.96730007 | AH10: 1.0672551 | AI10: 1.1736204 | AJ10: 1.2867033 | AK10: 1.406838
A11: 100*(pva_2/pva_0-1) | B11: 0 | C11: -5.9607843e-05 | D11: -0.00033333333 | E11: -0.0010039502 | F11: -0.002173254 | G11: -0.0037472801 | H11: -0.0053331561 | I11: -0.0063043356 | J11: -0.0059873203 | K11: -0.0037575332 | L11: 0.00092781393 | M11: 0.0085272793 | N11: 0.019424135 | O11: 0.033938215 | P11: 0.052335515 | Q11: 0.07483793 | R11: 0.10163094 | S11: 0.13287159 | T11: 0.16869549 | U11: 0.20922368 | V11: 0.25456857 | W11: 0.30483945 | X11: 0.3601471 | Y11: 0.42060829 | Z11: 0.48634822 | AA11: 0.55750449 | AB11: 0.63422805 | AC11: 0.71668633 | AD11: 0.80506428 | AE11: 0.89956588 | AF11: 1.0004154 | AG11: 1.107859 | AH11: 1.2221657 | AI11: 1.3436287 | AJ11: 1.4725675 | AK11: 1.6093293
A12: 100*(pci_2/pci_0-1) | B12: 0 | C12: -5.7941176e-05 | D12: -0.00031420607 | E12: -0.00091819888 | F12: -0.001929174 | G12: -0.0032239488 | H12: -0.0044225415 | I12: -0.0049771667 | J12: -0.0043547639 | K12: -0.0021016782 | L12: 0.0021482461 | M12: 0.0086861213 | N12: 0.017745512 | O12: 0.029517551 | P12: 0.044161832 | Q12: 0.061815482 | R12: 0.082599054 | S12: 0.10662183 | T12: 0.13398614 | U12: 0.16479088 | V12: 0.19913484 | W12: 0.23711947 | X12: 0.27885147 | Y12: 0.32444508 | Z12: 0.37402385 | AA12: 0.4277225 | AB12: 0.48568836 | AC12: 0.54808273 | AD12: 0.61508249 | AE12: 0.68688079 | AF12: 0.76368888 | AG12: 0.8457372 | AH12: 0.93327658 | AI12: 1.0265801 | AJ12: 1.1259447 | AK12: 1.2316926
... A25: 100*ds_0/gdp_0*(ds_2/ds_0-1) | B25: 0 | C25: 0 | D25: 0 | E25: 0 | F25: 0 | G25: 0 | H25: 0 | I25: 0 | J25: 0 | K25: 0 | L25: 0 | M25: 0 | N25: 0 | O25: 0 | P25: 0 | Q25: 0 | R25: 0 | S25: 0 | T25: 0 | U25: 0 | V25: 0 | W25: 0 | X25: 0 | Y25: 0 | Z25: 0 | AA25: 0 | AB25: 0 | AC25: 0 | AD25: 0 | AE25: 0 | AF25: 0 | AG25: 0 | AH25: 0 | AI25: 0 | AJ25: 0 | AK25: 0
