Workbook

Sheet template
A1: Model | B1: Scenario | C1: Region | D1: Variable | E1: Sector | F1: Type of variable | G1: Unit | H1: 44197 | I1: 44562 | J1: 44927 | K1: 45292 | L1: 45658 | M1: 46023 | N1: 46388 | O1: 46753 | P1: 47119 | Q1: 47484 | R1: 47849 | S1: 48214 | T1: 48580 | U1: 48945 | V1: 49310 | W1: 49675 | X1: 50041 | Y1: 50406 | Z1: 50771 | AA1: 51136 | AB1: 51502 | AC1: 51867 | AD1: 52232 | AE1: 52597 | AF1: 52963 | AG1: 53328 | AH1: 53693 | AI1: 54058 | AJ1: 54424 | AK1: 54789
A2: Three-ME | B2: Baseline | C2: France | D2: GDP | E2: Macro | F2: Volume | G2: Index (base: 2021) | H2: =base!H2/base!$H2*100 -> 100 | I2: =base!I2/base!$H2*100 -> 101.73226 | J2: =base!J2/base!$H2*100 -> 103.48099 | K2: =base!K2/base!$H2*100 -> 105.25508 | L2: =base!L2/base!$H2*100 -> 107.13135 | M2: =base!M2/base!$H2*100 -> 109.00319 | N2: =base!N2/base!$H2*100 -> 110.88445 | O2: =base!O2/base!$H2*100 -> 112.70971 | ... AK2: =base!AK2/base!$H2*100 -> 181.44477
A3: Three-ME | B3: Baseline | C3: France | D3: Investment | E3: Macro | F3: Volume | G3: Index (base: 2021) | H3: =base!H3/base!$H3*100 -> 100 | I3: =base!I3/base!$H3*100 -> 102.06437 | J3: =base!J3/base!$H3*100 -> 104.16792 | K3: =base!K3/base!$H3*100 -> 106.32098 | L3: =base!L3/base!$H3*100 -> 108.57172 | M3: =base!M3/base!$H3*100 -> 110.8963 | N3: =base!N3/base!$H3*100 -> 113.28523 | O3: =base!O3/base!$H3*100 -> 115.69089 | ... AK3: =base!AK3/base!$H3*100 -> 210.29322
A4: Three-ME | B4: Baseline | C4: France | D4: Consumption | E4: Macro | F4: Volume | G4: Index (base: 2021) | H4: =base!H4/base!$H4*100 -> 100 | I4: =base!I4/base!$H4*100 -> 101.74308 | J4: =base!J4/base!$H4*100 -> 103.47191 | K4: =base!K4/base!$H4*100 -> 105.21222 | L4: =base!L4/base!$H4*100 -> 107.04674 | M4: =base!M4/base!$H4*100 -> 108.90535 | N4: =base!N4/base!$H4*100 -> 110.79802 | O4: =base!O4/base!$H4*100 -> 112.69632 | ... AK4: =base!AK4/base!$H4*100 -> 173.81573
A5: Three-ME | B5: Baseline | C5: France | D5: Exports | E5: Macro | F5: Volume | G5: Index (base: 2021) | H5: =base!H5/base!$H5*100 -> 100 | I5: =base!I5/base!$H5*100 -> 102.0279 | J5: =base!J5/base!$H5*100 -> 104.06896 | K5: =base!K5/base!$H5*100 -> 106.12641 | L5: =base!L5/base!$H5*100 -> 108.20656 | M5: =base!M5/base!$H5*100 -> 110.30617 | N5: =base!N5/base!$H5*100 -> 112.31688 | O5: =base!O5/base!$H5*100 -> 114.01927 | ... AK5: =base!AK5/base!$H5*100 -> 205.5912
A6: Three-ME | B6: Baseline | C6: France | D6: Imports | E6: Macro | F6: Volume | G6: Index (base: 2021) | H6: =base!H6/base!$H6*100 -> 100 | I6: =base!I6/base!$H6*100 -> 101.89677 | J6: =base!J6/base!$H6*100 -> 103.81433 | K6: =base!K6/base!$H6*100 -> 105.774 | L6: =base!L6/base!$H6*100 -> 107.8377 | M6: =base!M6/base!$H6*100 -> 109.94956 | N6: =base!N6/base!$H6*100 -> 112.09449 | O6: =base!O6/base!$H6*100 -> 114.187 | ... AK6: =base!AK6/base!$H6*100 -> 193.49794
A7: Three-ME | B7: Baseline | C7: France | D7: Public surplus | E7: Macro | F7: Value | G7: Euro | H7: =base!H7/(base!H$2*base!H$14) -> -0.017059773 | I7: =base!I7/(base!I$2*base!I$14) -> -0.014458075 | J7: =base!J7/(base!J$2*base!J$14) -> -0.012104855 | K7: =base!K7/(base!K$2*base!K$14) -> -0.0097878892 | L7: =base!L7/(base!L$2*base!L$14) -> -0.0079707217 | M7: =base!M7/(base!M$2*base!M$14) -> -0.005320899 | N7: =base!N7/(base!N$2*base!N$14) -> -0.0026919127 | O7: =base!O7/(base!O$2*base!O$14) -> -0.00035473458 | ... AK7: =base!AK7/(base!AK$2*base!AK$14) -> 0.086218259
A8: Three-ME | B8: Baseline | C8: France | D8: Public debt | E8: Macro | F8: Value | G8: Euro | H8: =base!H8/(base!H$2*base!H$14) -> 0.90067846 | I8: =base!I8/(base!I$2*base!I$14) -> 0.88266612 | J8: =base!J8/(base!J$2*base!J$14) -> 0.86265177 | K8: =base!K8/(base!K$2*base!K$14) -> 0.84088707 | L8: =base!L8/(base!L$2*base!L$14) -> 0.8175116 | M8: =base!M8/(base!M$2*base!M$14) -> 0.79268949 | N8: =base!N8/(base!N$2*base!N$14) -> 0.76654865 | O8: =base!O8/(base!O$2*base!O$14) -> 0.74009614 | ... AK8: =base!AK8/(base!AK$2*base!AK$14) -> -0.24372015
A9: Three-ME | B9: Baseline | C9: France | D9: Primary public surplus | E9: Macro | F9: Value | G9: Euro | H9: =base!H9/(base!H$2*base!H$14) -> 0.00024634369 | I9: =base!I9/(base!I$2*base!I$14) -> 0.0026588286 | J9: =base!J9/(base!J$2*base!J$14) -> 0.0049478458 | K9: =base!K9/(base!K$2*base!K$14) -> 0.0071516912 | L9: =base!L9/(base!L$2*base!L$14) -> 0.0087255598 | M9: =base!M9/(base!M$2*base!M$14) -> 0.011021242 | N9: =base!N9/(base!N$2*base!N$14) -> 0.01313751 | O9: =base!O9/(base!O$2*base!O$14) -> 0.014801491 | ... AK9: =base!AK9/(base!AK$2*base!AK$14) -> 0.082314554
A10: Three-ME | B10: Baseline | C10: France | D10: Energy bill | E10: Macro | F10: Value | G10: Euro | H10: =base!H10/(base!H$2*base!H$14) -> 0.012332001 | I10: =base!I10/(base!I$2*base!I$14) -> 0.012909544 | J10: =base!J10/(base!J$2*base!J$14) -> 0.013407687 | K10: =base!K10/(base!K$2*base!K$14) -> 0.013851872 | L10: =base!L10/(base!L$2*base!L$14) -> 0.0142569 | M10: =base!M10/(base!M$2*base!M$14) -> 0.014628682 | N10: =base!N10/(base!N$2*base!N$14) -> 0.014967865 | O10: =base!O10/(base!O$2*base!O$14) -> 0.015286233 | ... AK10: =base!AK10/(base!AK$2*base!AK$14) -> 0.013689193
A11: Three-ME | B11: Baseline | C11: France | D11: Trade balance | E11: Macro | F11: Value | G11: Euro | H11: =base!H11/(base!H$2*base!H$14) -> 0.0038523426 | I11: =base!I11/(base!I$2*base!I$14) -> 0.0051382561 | J11: =base!J11/(base!J$2*base!J$14) -> 0.0065536224 | K11: =base!K11/(base!K$2*base!K$14) -> 0.0079791662 | L11: =base!L11/(base!L$2*base!L$14) -> 0.0092102944 | M11: =base!M11/(base!M$2*base!M$14) -> 0.010483146 | N11: =base!N11/(base!N$2*base!N$14) -> 0.011555301 | O11: =base!O11/(base!O$2*base!O$14) -> 0.012010948 | ... AK11: =base!AK11/(base!AK$2*base!AK$14) -> 0.053407928
A12: Three-ME | B12: Baseline | C12: France | D12: Unemployment rate | E12: Macro | F12: Rate | G12: Share of total population | H12: =base!H12 -> 0.13674745 | I12: =base!I12 -> 0.13471467 | J12: =base!J12 -> 0.1328859 | K12: =base!K12 -> 0.13122862 | L12: =base!L12 -> 0.13056274 | M12: =base!M12 -> 0.12881535 | N12: =base!N12 -> 0.12735848 | O12: =base!O12 -> 0.12643905 | ... AK12: =base!AK12 -> 0.047327205
A13: Three-ME | B13: Baseline | C13: France | D13: Consumption deflator | E13: Macro | F13: Price | G13: Index (base: 2021) | H13: =base!H13/base!$H13*100 -> 100 | I13: =base!I13/base!$H13*100 -> 101.863 | J13: =base!J13/base!$H13*100 -> 103.79455 | K13: =base!K13/base!$H13*100 -> 105.77845 | L13: =base!L13/base!$H13*100 -> 107.80236 | M13: =base!M13/base!$H13*100 -> 109.84389 | N13: =base!N13/base!$H13*100 -> 111.87612 | O13: =base!O13/base!$H13*100 -> 113.86681 | ... AK13: =base!AK13/base!$H13*100 -> 160.74456
A14: Three-ME | B14: Baseline | C14: France | D14: GDP deflator | E14: Macro | F14: Price | G14: Index (base: 2021) | H14: =base!H14/base!$H14*100 -> 100 | I14: =base!I14/base!$H14*100 -> 101.97349 | J14: =base!J14/base!$H14*100 -> 104.03598 | K14: =base!K14/base!$H14*100 -> 106.16558 | L14: =base!L14/base!$H14*100 -> 108.34506 | M14: =base!M14/base!$H14*100 -> 110.5611 | N14: =base!N14/base!$H14*100 -> 112.78779 | O14: =base!O14/base!$H14*100 -> 114.98235 | ... AK14: =base!AK14/base!$H14*100 -> 167.56184
A15: Three-ME | B15: Baseline | C15: France | D15: Production deflator | E15: Macro | F15: Price | G15: Index (base: 2021) | H15: =base!H15/base!$H15*100 -> 100 | I15: =base!I15/base!$H15*100 -> 101.96647 | J15: =base!J15/base!$H15*100 -> 104.01015 | K15: =base!K15/base!$H15*100 -> 106.11419 | L15: =base!L15/base!$H15*100 -> 108.26415 | M15: =base!M15/base!$H15*100 -> 110.44216 | N15: =base!N15/base!$H15*100 -> 112.62174 | O15: =base!O15/base!$H15*100 -> 114.76469 | ... AK15: =base!AK15/base!$H15*100 -> 165.22657
A16: Three-ME | B16: Baseline | C16: France | D16: Deflator of imports | E16: Macro | F16: Price | G16: Index (base: 2021) | H16: =base!H16/base!$H16*100 -> 100 | I16: =base!I16/base!$H16*100 -> 101.59796 | J16: =base!J16/base!$H16*100 -> 103.20926 | K16: =base!K16/base!$H16*100 -> 104.83374 | L16: =base!L16/base!$H16*100 -> 106.471 | M16: =base!M16/base!$H16*100 -> 108.06445 | N16: =base!N16/base!$H16*100 -> 109.57958 | O16: =base!O16/base!$H16*100 -> 111.00945 | ... AK16: =base!AK16/base!$H16*100 -> 145.2737
A17: Three-ME | B17: Baseline | C17: France | D17: Deflator of investment | E17: Macro | F17: Price | G17: Index (base: 2021) | H17: =base!H17/base!$H17*100 -> 100 | I17: =base!I17/base!$H17*100 -> 101.91092 | J17: =base!J17/base!$H17*100 -> 103.90329 | K17: =base!K17/base!$H17*100 -> 105.94716 | L17: =base!L17/base!$H17*100 -> 108.02127 | M17: =base!M17/base!$H17*100 -> 110.09562 | N17: =base!N17/base!$H17*100 -> 112.13605 | O17: =base!O17/base!$H17*100 -> 114.10277 | ... AK17: =base!AK17/base!$H17*100 -> 164.66812
A18: Three-ME | B18: Baseline | C18: France | D18: Deflator of exports | E18: Macro | F18: Price | G18: Index (base: 2021) | H18: =base!H18/base!$H18*100 -> 100 | I18: =base!I18/base!$H18*100 -> 101.91738 | J18: =base!J18/base!$H18*100 -> 103.91903 | K18: =base!K18/base!$H18*100 -> 105.98257 | L18: =base!L18/base!$H18*100 -> 108.08923 | M18: =base!M18/base!$H18*100 -> 110.21335 | N18: =base!N18/base!$H18*100 -> 112.3226 | O18: =base!O18/base!$H18*100 -> 114.37743 | ... AK18: =base!AK18/base!$H18*100 -> 161.94193
A19: Three-ME | B19: Baseline | C19: France | D19: Unit cost of production | E19: Macro | F19: Price | G19: Index (base: 2021) | H19: =base!H19/base!$H19*100 -> 100 | I19: =base!I19/base!$H19*100 -> 101.97602 | J19: =base!J19/base!$H19*100 -> 104.01913 | K19: =base!K19/base!$H19*100 -> 106.11079 | L19: =base!L19/base!$H19*100 -> 108.21293 | M19: =base!M19/base!$H19*100 -> 110.35757 | N19: =base!N19/base!$H19*100 -> 112.50187 | O19: =base!O19/base!$H19*100 -> 114.62575 | ... AK19: =base!AK19/base!$H19*100 -> 165.68315
A20: Three-ME | B20: Baseline | C20: France | D20: Employment | E20: Macro | F20: Thousands of people | G20: Number | H20: =base!H20 -> 28279.679 | I20: =base!I20 -> 28464.796 | J20: =base!J20 -> 28643.926 | K20: =base!K20 -> 28817.205 | L20: =base!L20 -> 28997.285 | M20: =base!M20 -> 29172.28 | N20: =base!N20 -> 29338.304 | O20: =base!O20 -> 29483.766 | ... AK20: =base!AK20 -> 35122.491
A21: Three-ME | B21: Baseline | C21: France | D21: Firms' capital | E21: Macro | F21: Volume | G21: Value | H21: =base!H21/base!$H21*100 -> 100 | I21: =base!I21/base!$H21*100 -> 101.52555 | J21: =base!J21/base!$H21*100 -> 103.12538 | K21: =base!K21/base!$H21*100 -> 104.79817 | L21: =base!L21/base!$H21*100 -> 106.54719 | M21: =base!M21/base!$H21*100 -> 108.37324 | N21: =base!N21/base!$H21*100 -> 110.27616 | O21: =base!O21/base!$H21*100 -> 112.25137 | ... AK21: =base!AK21/base!$H21*100 -> 185.67194
A22: Three-ME | B22: Baseline | C22: France | D22: Firms' energy consumption | E22: Macro | F22: Volume | H22: =base!H22/base!$H22*100 -> 100 | I22: =base!I22/base!$H22*100 -> 101.19988 | J22: =base!J22/base!$H22*100 -> 102.39717 | K22: =base!K22/base!$H22*100 -> 103.5847 | L22: =base!L22/base!$H22*100 -> 104.80002 | M22: =base!M22/base!$H22*100 -> 105.99895 | N22: =base!N22/base!$H22*100 -> 107.1543 | O22: =base!O22/base!$H22*100 -> 108.18717 | ... AK22: =base!AK22/base!$H22*100 -> 167.84115
A23: Three-ME | B23: Baseline | C23: France | D23: Material consumption | E23: Macro | F23: Volume | H23: =base!H23/base!$H23*100 -> 100 | I23: =base!I23/base!$H23*100 -> 101.79193 | J23: =base!J23/base!$H23*100 -> 103.59454 | K23: =base!K23/base!$H23*100 -> 105.41719 | L23: =base!L23/base!$H23*100 -> 107.31747 | M23: =base!M23/base!$H23*100 -> 109.23699 | N23: =base!N23/base!$H23*100 -> 111.15829 | O23: =base!O23/base!$H23*100 -> 113.00664 | ... AK23: =base!AK23/base!$H23*100 -> 186.71125
A24: Three-ME | B24: Baseline | C24: France | D24: Wage | E24: Macro | F24: Value | G24: Index (base: 2021) | H24: =base!H24 -> 49.398758 | I24: =base!I24 -> 50.90364 | J24: =base!J24 -> 52.467274 | K24: =base!K24 -> 54.096553 | L24: =base!L24 -> 55.782829 | M24: =base!M24 -> 57.544746 | N24: =base!N24 -> 59.373827 | O24: =base!O24 -> 61.254823 | ... AK24: =base!AK24 -> 120.17709
A25: Three-ME | B25: Baseline | C25: France | D25: Labor cost | E25: Macro | F25: Value | G25: Unit cost | H25: =base!H25 -> 62.913273 | I25: =base!I25 -> 64.829861 | J25: =base!J25 -> 66.821275 | K25: =base!K25 -> 68.896292 | L25: =base!L25 -> 71.0439 | M25: =base!M25 -> 73.287841 | N25: =base!N25 -> 75.617323 | O25: =base!O25 -> 78.012922 | ... AK25: =base!AK25 -> 153.05514
A26: Three-ME | B26: Baseline | C26: France | D26: Capital cost | E26: Macro | F26: Value | G26: Unit cost | H26: =base!H26 -> 0.093613883 | I26: =base!I26 -> 0.095758072 | J26: =base!J26 -> 0.097959031 | K26: =base!K26 -> 0.10012844 | L26: =base!L26 -> 0.1022399 | M26: =base!M26 -> 0.10422871 | N26: =base!N26 -> 0.10603624 | O26: =base!O26 -> 0.10760077 | ... AK26: =base!AK26 -> 0.16458273
A27: Three-ME | B27: Baseline | C27: France | D27: Energy cost | E27: Macro | F27: Value | G27: Unit cost | H27: =base!H27 -> 1.2338385 | I27: =base!I27 -> 1.2869446 | J27: =base!J27 -> 1.3437479 | K27: =base!K27 -> 1.402716 | L27: =base!L27 -> 1.4631574 | M27: =base!M27 -> 1.5242745 | N27: =base!N27 -> 1.5854229 | O27: =base!O27 -> 1.646138 | ... AK27: =base!AK27 -> 2.4674337
A28: Three-ME | B28: Baseline | C28: France | D28: Material cost | E28: Macro | F28: Value | G28: Unit cost | H28: =base!H28 -> 1.1110215 | I28: =base!I28 -> 1.1309432 | J28: =base!J28 -> 1.1515104 | K28: =base!K28 -> 1.172613 | L28: =base!L28 -> 1.1941428 | M28: =base!M28 -> 1.2158519 | N28: =base!N28 -> 1.2374427 | O28: =base!O28 -> 1.2585563 | ... AK28: =base!AK28 -> 1.7747975
A29: Three-ME | B29: Baseline | C29: France | D29: Value added | E29: Agriculture | F29: Volume | G29: Index (base: 2021) | H29: =base!H30/base!$H30*100 -> 100 | I29: =base!I30/base!$H30*100 -> 101.7519 | J29: =base!J30/base!$H30*100 -> 103.52415 | K29: =base!K30/base!$H30*100 -> 105.32054 | L29: =base!L30/base!$H30*100 -> 107.1926 | M29: =base!M30/base!$H30*100 -> 109.08246 | N29: =base!N30/base!$H30*100 -> 110.95802 | O29: =base!O30/base!$H30*100 -> 112.72312 | ... AK29: =base!AK30/base!$H30*100 -> 184.72539
A30: Three-ME | B30: Baseline | C30: France | D30: Value added | E30: Forestry | F30: Volume | G30: Index (base: 2021) | H30: =base!H31/base!$H31*100 -> 100 | I30: =base!I31/base!$H31*100 -> 100.076 | J30: =base!J31/base!$H31*100 -> 100.2264 | K30: =base!K31/base!$H31*100 -> 100.42857 | L30: =base!L31/base!$H31*100 -> 100.71365 | M30: =base!M31/base!$H31*100 -> 100.99122 | N30: =base!N31/base!$H31*100 -> 101.24665 | O30: =base!O31/base!$H31*100 -> 101.4463 | ... AK30: =base!AK31/base!$H31*100 -> 120.42202
A31: Three-ME | B31: Baseline | C31: France | D31: Value added | E31: Food | F31: Volume | G31: Index (base: 2021) | H31: =base!H33/base!$H33*100 -> 100 | I31: =base!I33/base!$H33*100 -> 101.81589 | J31: =base!J33/base!$H33*100 -> 103.65101 | K31: =base!K33/base!$H33*100 -> 105.51076 | L31: =base!L33/base!$H33*100 -> 107.46054 | M31: =base!M33/base!$H33*100 -> 109.41639 | N31: =base!N33/base!$H33*100 -> 111.36644 | O31: =base!O33/base!$H33*100 -> 113.22708 | ... AK31: =base!AK33/base!$H33*100 -> 183.84562
A32: Three-ME | B32: Baseline | C32: France | D32: Value added | E32: Vehicles | F32: Volume | G32: Index (base: 2021) | H32: =base!H34/base!$H34*100 -> 100 | I32: =base!I34/base!$H34*100 -> 101.91781 | J32: =base!J34/base!$H34*100 -> 103.82673 | K32: =base!K34/base!$H34*100 -> 105.76301 | L32: =base!L34/base!$H34*100 -> 107.76951 | M32: =base!M34/base!$H34*100 -> 109.80732 | N32: =base!N34/base!$H34*100 -> 111.7846 | O32: =base!O34/base!$H34*100 -> 113.49741 | ... AK32: =base!AK34/base!$H34*100 -> 197.65678
A33: Three-ME | B33: Baseline | C33: France | D33: Value added | E33: Glass | F33: Volume | G33: Index (base: 2021) | H33: =base!H35/base!$H35*100 -> 100 | I33: =base!I35/base!$H35*100 -> 101.84774 | J33: =base!J35/base!$H35*100 -> 103.73212 | K33: =base!K35/base!$H35*100 -> 105.65673 | L33: =base!L35/base!$H35*100 -> 107.66839 | M33: =base!M35/base!$H35*100 -> 109.71887 | N33: =base!N35/base!$H35*100 -> 111.78221 | O33: =base!O35/base!$H35*100 -> 113.77681 | ... AK33: =base!AK35/base!$H35*100 -> 198.12511
A34: Three-ME | B34: Baseline | C34: France | D34: Value added | E34: Paper | F34: Volume | G34: Index (base: 2021) | H34: =base!H36/base!$H36*100 -> 100 | I34: =base!I36/base!$H36*100 -> 101.73081 | J34: =base!J36/base!$H36*100 -> 103.46254 | K34: =base!K36/base!$H36*100 -> 105.20178 | L34: =base!L36/base!$H36*100 -> 106.99815 | M34: =base!M36/base!$H36*100 -> 108.78699 | N34: =base!N36/base!$H36*100 -> 110.52157 | O34: =base!O36/base!$H36*100 -> 112.0705 | ... AK34: =base!AK36/base!$H36*100 -> 185.92311
A35: Three-ME | B35: Baseline | C35: France | D35: Value added | E35: Chemicals | F35: Volume | G35: Index (base: 2021) | H35: =base!H37/base!$H37*100 -> 100 | I35: =base!I37/base!$H37*100 -> 101.75131 | J35: =base!J37/base!$H37*100 -> 103.48913 | K35: =base!K37/base!$H37*100 -> 105.21617 | L35: =base!L37/base!$H37*100 -> 106.97002 | M35: =base!M37/base!$H37*100 -> 108.7031 | N35: =base!N37/base!$H37*100 -> 110.35014 | O35: =base!O37/base!$H37*100 -> 111.74718 | ... AK35: =base!AK37/base!$H37*100 -> 189.73009
A36: Three-ME | B36: Baseline | C36: France | D36: Value added | E36: Plastics | F36: Volume | G36: Index (base: 2021) | H36: =base!H38/base!$H38*100 -> 100 | I36: =base!I38/base!$H38*100 -> 101.78816 | J36: =base!J38/base!$H38*100 -> 103.58753 | K36: =base!K38/base!$H38*100 -> 105.40395 | L36: =base!L38/base!$H38*100 -> 107.26989 | M36: =base!M38/base!$H38*100 -> 109.14884 | N36: =base!N38/base!$H38*100 -> 110.97123 | O36: =base!O38/base!$H38*100 -> 112.58747 | ... AK36: =base!AK38/base!$H38*100 -> 192.60679
A37: Three-ME | B37: Baseline | C37: France | D37: Value added | E37: Metallurgy | F37: Volume | G37: Index (base: 2021) | H37: =base!H39/base!$H39*100 -> 100 | I37: =base!I39/base!$H39*100 -> 101.80462 | J37: =base!J39/base!$H39*100 -> 103.62821 | K37: =base!K39/base!$H39*100 -> 105.47671 | L37: =base!L39/base!$H39*100 -> 107.38119 | M37: =base!M39/base!$H39*100 -> 109.30618 | N37: =base!N39/base!$H39*100 -> 111.18016 | O37: =base!O39/base!$H39*100 -> 112.85108 | ... AK37: =base!AK39/base!$H39*100 -> 196.32402
A38: Three-ME | B38: Baseline | C38: France | D38: Value added | E38: Industry goods | F38: Volume | G38: Index (base: 2021) | H38: =base!H40/base!$H40*100 -> 100 | I38: =base!I40/base!$H40*100 -> 101.98466 | J38: =base!J40/base!$H40*100 -> 103.98469 | K38: =base!K40/base!$H40*100 -> 106.007 | L38: =base!L40/base!$H40*100 -> 108.07109 | M38: =base!M40/base!$H40*100 -> 110.15847 | N38: =base!N40/base!$H40*100 -> 112.16875 | O38: =base!O40/base!$H40*100 -> 113.90366 | ... AK38: =base!AK40/base!$H40*100 -> 202.23499
A39: Three-ME | B39: Baseline | C39: France | D39: Value added | E39: Consumer goods | F39: Volume | G39: Index (base: 2021) | H39: =base!H41/base!$H41*100 -> 100 | I39: =base!I41/base!$H41*100 -> 101.8146 | J39: =base!J41/base!$H41*100 -> 103.6511 | K39: =base!K41/base!$H41*100 -> 105.51883 | L39: =base!L41/base!$H41*100 -> 107.46743 | M39: =base!M41/base!$H41*100 -> 109.44188 | N39: =base!N41/base!$H41*100 -> 111.40622 | O39: =base!O41/base!$H41*100 -> 113.25055 | ... AK39: =base!AK41/base!$H41*100 -> 191.88955
A40: Three-ME | B40: Baseline | C40: France | D40: Value added | E40: Construction | F40: Volume | G40: Index (base: 2021) | H40: =base!H42/base!$H42*100 -> 100 | I40: =base!I42/base!$H42*100 -> 102.07582 | J40: =base!J42/base!$H42*100 -> 104.20169 | K40: =base!K42/base!$H42*100 -> 106.38877 | L40: =base!L42/base!$H42*100 -> 108.69541 | M40: =base!M42/base!$H42*100 -> 111.08026 | N40: =base!N42/base!$H42*100 -> 113.55113 | O40: =base!O42/base!$H42*100 -> 116.0805 | ... AK40: =base!AK42/base!$H42*100 -> 213.17769
A41: Three-ME | B41: Baseline | C41: France | D41: Value added | E41: Energy transformation | F41: Volume | G41: Index (base: 2021) | H41: =base!H43/base!$H43*100 -> 100 | I41: =base!I43/base!$H43*100 -> 101.47385 | J41: =base!J43/base!$H43*100 -> 102.94433 | K41: =base!K43/base!$H43*100 -> 104.41884 | L41: =base!L43/base!$H43*100 -> 105.94463 | M41: =base!M43/base!$H43*100 -> 107.47313 | N41: =base!N43/base!$H43*100 -> 108.96772 | O41: =base!O43/base!$H43*100 -> 110.32831 | ... AK41: =base!AK43/base!$H43*100 -> 178.34861
A42: Three-ME | B42: Baseline | C42: France | D42: Value added | E42: Rail transport | F42: Volume | G42: Index (base: 2021) | H42: =base!H45/base!$H45*100 -> 100 | I42: =base!I45/base!$H45*100 -> 101.47085 | J42: =base!J45/base!$H45*100 -> 102.94333 | K42: =base!K45/base!$H45*100 -> 104.4255 | L42: =base!L45/base!$H45*100 -> 105.97675 | M42: =base!M45/base!$H45*100 -> 107.51619 | N42: =base!N45/base!$H45*100 -> 109.0378 | O42: =base!O45/base!$H45*100 -> 110.4605 | ... AK42: =base!AK45/base!$H45*100 -> 169.71824
A43: Three-ME | B43: Baseline | C43: France | D43: Value added | E43: Road transport | F43: Volume | G43: Index (base: 2021) | H43: =base!H46/base!$H46*100 -> 100 | I43: =base!I46/base!$H46*100 -> 101.46006 | J43: =base!J46/base!$H46*100 -> 102.91916 | K43: =base!K46/base!$H46*100 -> 104.38475 | L43: =base!L46/base!$H46*100 -> 105.91444 | M43: =base!M46/base!$H46*100 -> 107.43303 | N43: =base!N46/base!$H46*100 -> 108.93214 | O43: =base!O46/base!$H46*100 -> 110.33292 | ... AK43: =base!AK46/base!$H46*100 -> 169.47451
A44: Three-ME | B44: Baseline | C44: France | D44: Value added | E44: Water transport | F44: Volume | G44: Index (base: 2021) | H44: =base!H47/base!$H47*100 -> 100 | I44: =base!I47/base!$H47*100 -> 102.05271 | J44: =base!J47/base!$H47*100 -> 104.12137 | K44: =base!K47/base!$H47*100 -> 106.21779 | L44: =base!L47/base!$H47*100 -> 108.35312 | M44: =base!M47/base!$H47*100 -> 110.51818 | N44: =base!N47/base!$H47*100 -> 112.54959 | O44: =base!O47/base!$H47*100 -> 114.18335 | ... AK44: =base!AK47/base!$H47*100 -> 204.76467
A45: Three-ME | B45: Baseline | C45: France | D45: Value added | E45: Air transport | F45: Volume | G45: Index (base: 2021) | H45: =base!H48/base!$H48*100 -> 100 | I45: =base!I48/base!$H48*100 -> 102.0372 | J45: =base!J48/base!$H48*100 -> 104.13179 | K45: =base!K48/base!$H48*100 -> 106.27865 | L45: =base!L48/base!$H48*100 -> 108.52378 | M45: =base!M48/base!$H48*100 -> 110.79904 | N45: =base!N48/base!$H48*100 -> 113.04761 | O45: =base!O48/base!$H48*100 -> 115.1248 | ... AK45: =base!AK48/base!$H48*100 -> 206.81955
A46: Three-ME | B46: Baseline | C46: France | D46: Value added | E46: Private services | F46: Volume | G46: Index (base: 2021) | H46: =base!H50/base!$H50*100 -> 100 | I46: =base!I50/base!$H50*100 -> 101.78963 | J46: =base!J50/base!$H50*100 -> 103.59207 | K46: =base!K50/base!$H50*100 -> 105.41704 | L46: =base!L50/base!$H50*100 -> 107.33018 | M46: =base!M50/base!$H50*100 -> 109.25394 | N46: =base!N50/base!$H50*100 -> 111.18123 | O46: =base!O50/base!$H50*100 -> 113.0386 | ... AK46: =base!AK50/base!$H50*100 -> 183.92383
A47: Three-ME | B47: Baseline | C47: France | D47: Value added | E47: Public services | F47: Volume | G47: Index (base: 2021) | H47: =base!H51/base!$H51*100 -> 100 | I47: =base!I51/base!$H51*100 -> 101.53904 | J47: =base!J51/base!$H51*100 -> 103.1095 | K47: =base!K51/base!$H51*100 -> 104.71239 | L47: =base!L51/base!$H51*100 -> 106.49401 | M47: =base!M51/base!$H51*100 -> 108.17273 | N47: =base!N51/base!$H51*100 -> 109.88601 | O47: =base!O51/base!$H51*100 -> 111.61735 | ... AK47: =base!AK51/base!$H51*100 -> 164.77248
A48: Three-ME | B48: Baseline | C48: France | D48: Value added | E48: Oil | F48: Volume | G48: Index (base: 2021) | H48: =base!H53/base!$H53*100 -> 100 | I48: =base!I53/base!$H53*100 -> 101.13188 | J48: =base!J53/base!$H53*100 -> 102.31952 | K48: =base!K53/base!$H53*100 -> 103.50236 | L48: =base!L53/base!$H53*100 -> 104.66154 | M48: =base!M53/base!$H53*100 -> 105.85294 | N48: =base!N53/base!$H53*100 -> 107.05469 | O48: =base!O53/base!$H53*100 -> 108.25417 | ... AK48: =base!AK53/base!$H53*100 -> 157.184
A49: Three-ME | B49: Baseline | C49: France | D49: Value added | E49: Biofuel | F49: Volume | G49: Index (base: 2021) | H49: =base!H54/base!$H54*100 -> 100 | I49: =base!I54/base!$H54*100 -> 100.94706 | J49: =base!J54/base!$H54*100 -> 101.94498 | K49: =base!K54/base!$H54*100 -> 102.94877 | L49: =base!L54/base!$H54*100 -> 103.95138 | M49: =base!M54/base!$H54*100 -> 104.95727 | N49: =base!N54/base!$H54*100 -> 105.95306 | O49: =base!O54/base!$H54*100 -> 106.91882 | ... AK49: =base!AK54/base!$H54*100 -> 143.13704
A50: Three-ME | B50: Baseline | C50: France | D50: Value added | E50: Natural gas | F50: Volume | G50: Index (base: 2021) | H50: =base!H55/base!$H55*100 -> 100 | I50: =base!I55/base!$H55*100 -> 100.3058 | J50: =base!J55/base!$H55*100 -> 100.52961 | K50: =base!K55/base!$H55*100 -> 100.71965 | L50: =base!L55/base!$H55*100 -> 100.94506 | M50: =base!M55/base!$H55*100 -> 101.16184 | N50: =base!N55/base!$H55*100 -> 101.3624 | O50: =base!O55/base!$H55*100 -> 101.48804 | ... AK50: =base!AK55/base!$H55*100 -> 144.12399
A51: Three-ME | B51: Baseline | C51: France | D51: Value added | E51: Biogas | F51: Volume | G51: Index (base: 2021) | H51: =base!H56/base!$H56*100 -> 100 | I51: =base!I56/base!$H56*100 -> 100.31725 | J51: =base!J56/base!$H56*100 -> 100.54396 | K51: =base!K56/base!$H56*100 -> 100.73214 | L51: =base!L56/base!$H56*100 -> 100.9515 | M51: =base!M56/base!$H56*100 -> 101.16567 | N51: =base!N56/base!$H56*100 -> 101.36522 | O51: =base!O56/base!$H56*100 -> 101.49369 | ... AK51: =base!AK56/base!$H56*100 -> 144.12355
A52: Three-ME | B52: Baseline | C52: France | D52: Value added | E52: Electricity | F52: Volume | G52: Index (base: 2021) | H52: =base!H57/base!$H57*100 -> 100 | I52: =base!I57/base!$H57*100 -> 100.9446 | J52: =base!J57/base!$H57*100 -> 101.93217 | K52: =base!K57/base!$H57*100 -> 102.94508 | L52: =base!L57/base!$H57*100 -> 104.02268 | M52: =base!M57/base!$H57*100 -> 105.08008 | N52: =base!N57/base!$H57*100 -> 106.09814 | O52: =base!O57/base!$H57*100 -> 107.01565 | ... AK52: =base!AK57/base!$H57*100 -> 153.0902
A53: Three-ME | B53: Baseline | C53: France | D53: CO2 Emissions | E53: Macro | F53: Physical | G53: MtCO2 | H53: =base!H67 -> 347.92632 | I53: =base!I67 -> 349.72034 | J53: =base!J67 -> 351.50164 | K53: =base!K67 -> 353.28982 | L53: =base!L67 -> 355.24888 | M53: =base!M67 -> 357.20531 | N53: =base!N67 -> 359.11797 | O53: =base!O67 -> 360.8094 | ... AK53: =base!AK67 -> 511.73421
A54: Three-ME | B54: Baseline | C54: France | D54: CO2 Emissions | E54: Firms | F54: Physical | G54: MtCO2 | H54: =base!H68+base!H69+base!H70 -> 232.98661 | I54: =base!I68+base!I69+base!I70 -> 235.0184 | J54: =base!J68+base!J69+base!J70 -> 237.02761 | K54: =base!K68+base!K69+base!K70 -> 239.02066 | L54: =base!L68+base!L69+base!L70 -> 241.11776 | M54: =base!M68+base!M69+base!M70 -> 243.20697 | N54: =base!N68+base!N69+base!N70 -> 245.24071 | O54: =base!O68+base!O69+base!O70 -> 247.03888 | ... AK54: =base!AK68+base!AK69+base!AK70 -> 392.57714
A55: Three-ME | B55: Baseline | C55: France | D55: CO2 Emissions | E55: Housholds | F55: Physical | G55: MtCO2 | H55: =base!H71 -> 114.93971 | I55: =base!I71 -> 114.70194 | J55: =base!J71 -> 114.47403 | K55: =base!K71 -> 114.26917 | L55: =base!L71 -> 114.13111 | M55: =base!M71 -> 113.99834 | N55: =base!N71 -> 113.87726 | O55: =base!O71 -> 113.77052 | ... AK55: =base!AK71 -> 119.15707
A56: Three-ME | B56: Baseline | C56: France | D56: Production | E56: Macro | F56: Volume | G56: Index (base: 2021) | H56: =base!H72/base!$H72*100 -> 100 | I56: =base!I72/base!$H72*100 -> 101.74567 | J56: =base!J72/base!$H72*100 -> 103.50619 | K56: =base!K72/base!$H72*100 -> 105.2894 | L56: =base!L72/base!$H72*100 -> 107.16246 | M56: =base!M72/base!$H72*100 -> 109.03968 | N56: =base!N72/base!$H72*100 -> 110.92018 | O56: =base!O72/base!$H72*100 -> 112.73244 | ... AK56: =base!AK72/base!$H72*100 -> 183.70156
A57: Three-ME | B57: Baseline | C57: France | D57: Production | E57: Agriculture | F57: Volume | G57: Index (base: 2021) | H57: =base!H73/base!$H73*100 -> 100 | I57: =base!I73/base!$H73*100 -> 101.72346 | J57: =base!J73/base!$H73*100 -> 103.46416 | K57: =base!K73/base!$H73*100 -> 105.22335 | L57: =base!L73/base!$H73*100 -> 107.04686 | M57: =base!M73/base!$H73*100 -> 108.89043 | N57: =base!N73/base!$H73*100 -> 110.71995 | O57: =base!O73/base!$H73*100 -> 112.4451 | ... AK57: =base!AK73/base!$H73*100 -> 184.2687
A58: Three-ME | B58: Baseline | C58: France | D58: Production | E58: Forestry | F58: Volume | G58: Index (base: 2021) | H58: =base!H74/base!$H74*100 -> 100 | I58: =base!I74/base!$H74*100 -> 100.06449 | J58: =base!J74/base!$H74*100 -> 100.20458 | K58: =base!K74/base!$H74*100 -> 100.3965 | L58: =base!L74/base!$H74*100 -> 100.67018 | M58: =base!M74/base!$H74*100 -> 100.93762 | N58: =base!N74/base!$H74*100 -> 101.18274 | O58: =base!O74/base!$H74*100 -> 101.37214 | ... AK58: =base!AK74/base!$H74*100 -> 120.30851
A59: Three-ME | B59: Baseline | C59: France | D59: Production | E59: Food | F59: Volume | G59: Index (base: 2021) | H59: =base!H75/base!$H75*100 -> 100 | I59: =base!I75/base!$H75*100 -> 101.78434 | J59: =base!J75/base!$H75*100 -> 103.57996 | K59: =base!K75/base!$H75*100 -> 105.39185 | L59: =base!L75/base!$H75*100 -> 107.27621 | M59: =base!M75/base!$H75*100 -> 109.17604 | N59: =base!N75/base!$H75*100 -> 111.07048 | O59: =base!O75/base!$H75*100 -> 112.88507 | ... AK59: =base!AK75/base!$H75*100 -> 183.07799
A60: Three-ME | B60: Baseline | C60: France | D60: Production | E60: Vehicles | F60: Volume | G60: Index (base: 2021) | H60: =base!H76/base!$H76*100 -> 100 | I60: =base!I76/base!$H76*100 -> 101.85845 | J60: =base!J76/base!$H76*100 -> 103.68034 | K60: =base!K76/base!$H76*100 -> 105.50878 | L60: =base!L76/base!$H76*100 -> 107.38993 | M60: =base!M76/base!$H76*100 -> 109.30433 | N60: =base!N76/base!$H76*100 -> 111.17389 | O60: =base!O76/base!$H76*100 -> 112.81631 | ... AK60: =base!AK76/base!$H76*100 -> 195.72123
A61: Three-ME | B61: Baseline | C61: France | D61: Production | E61: Glass | F61: Volume | G61: Index (base: 2021) | H61: =base!H77/base!$H77*100 -> 100 | I61: =base!I77/base!$H77*100 -> 101.77897 | J61: =base!J77/base!$H77*100 -> 103.59105 | K61: =base!K77/base!$H77*100 -> 105.43789 | L61: =base!L77/base!$H77*100 -> 107.36131 | M61: =base!M77/base!$H77*100 -> 109.32614 | N61: =base!N77/base!$H77*100 -> 111.30495 | O61: =base!O77/base!$H77*100 -> 113.2218 | ... AK61: =base!AK77/base!$H77*100 -> 196.91492
A62: Three-ME | B62: Baseline | C62: France | D62: Production | E62: Paper | F62: Volume | G62: Index (base: 2021) | H62: =base!H78/base!$H78*100 -> 100 | I62: =base!I78/base!$H78*100 -> 101.71525 | J62: =base!J78/base!$H78*100 -> 103.43329 | K62: =base!K78/base!$H78*100 -> 105.15952 | L62: =base!L78/base!$H78*100 -> 106.936 | M62: =base!M78/base!$H78*100 -> 108.71931 | N62: =base!N78/base!$H78*100 -> 110.46167 | O62: =base!O78/base!$H78*100 -> 112.04375 | ... AK62: =base!AK78/base!$H78*100 -> 186.04899
A63: Three-ME | B63: Baseline | C63: France | D63: Production | E63: Chemicals | F63: Volume | G63: Index (base: 2021) | H63: =base!H79/base!$H79*100 -> 100 | I63: =base!I79/base!$H79*100 -> 101.70614 | J63: =base!J79/base!$H79*100 -> 103.37967 | K63: =base!K79/base!$H79*100 -> 105.02509 | L63: =base!L79/base!$H79*100 -> 106.67919 | M63: =base!M79/base!$H79*100 -> 108.31272 | N63: =base!N79/base!$H79*100 -> 109.86833 | O63: =base!O79/base!$H79*100 -> 111.19871 | ... AK63: =base!AK79/base!$H79*100 -> 188.2422
A64: Three-ME | B64: Baseline | C64: France | D64: Production | E64: Plastics | F64: Volume | G64: Index (base: 2021) | H64: =base!H80/base!$H80*100 -> 100 | I64: =base!I80/base!$H80*100 -> 101.77714 | J64: =base!J80/base!$H80*100 -> 103.56287 | K64: =base!K80/base!$H80*100 -> 105.36191 | L64: =base!L80/base!$H80*100 -> 107.20388 | M64: =base!M80/base!$H80*100 -> 109.06086 | N64: =base!N80/base!$H80*100 -> 110.86774 | O64: =base!O80/base!$H80*100 -> 112.48286 | ... AK64: =base!AK80/base!$H80*100 -> 192.33886
A65: Three-ME | B65: Baseline | C65: France | D65: Production | E65: Metallurgy | F65: Volume | G65: Index (base: 2021) | H65: =base!H81/base!$H81*100 -> 100 | I65: =base!I81/base!$H81*100 -> 101.77656 | J65: =base!J81/base!$H81*100 -> 103.56813 | K65: =base!K81/base!$H81*100 -> 105.37947 | L65: =base!L81/base!$H81*100 -> 107.23884 | M65: =base!M81/base!$H81*100 -> 109.12264 | N65: =base!N81/base!$H81*100 -> 110.96705 | O65: =base!O81/base!$H81*100 -> 112.63175 | ... AK65: =base!AK81/base!$H81*100 -> 195.7986
A66: Three-ME | B66: Baseline | C66: France | D66: Production | E66: Industry goods | F66: Volume | G66: Index (base: 2021) | H66: =base!H82/base!$H82*100 -> 100 | I66: =base!I82/base!$H82*100 -> 101.97008 | J66: =base!J82/base!$H82*100 -> 103.95067 | K66: =base!K82/base!$H82*100 -> 105.94835 | L66: =base!L82/base!$H82*100 -> 107.98162 | M66: =base!M82/base!$H82*100 -> 110.03712 | N66: =base!N82/base!$H82*100 -> 112.02462 | O66: =base!O82/base!$H82*100 -> 113.75626 | ... AK66: =base!AK82/base!$H82*100 -> 201.78347
A67: Three-ME | B67: Baseline | C67: France | D67: Production | E67: Consumer goods | F67: Volume | G67: Index (base: 2021) | H67: =base!H83/base!$H83*100 -> 100 | I67: =base!I83/base!$H83*100 -> 101.80899 | J67: =base!J83/base!$H83*100 -> 103.6368 | K67: =base!K83/base!$H83*100 -> 105.49198 | L67: =base!L83/base!$H83*100 -> 107.42026 | M67: =base!M83/base!$H83*100 -> 109.37834 | N67: =base!N83/base!$H83*100 -> 111.32874 | O67: =base!O83/base!$H83*100 -> 113.16778 | ... AK67: =base!AK83/base!$H83*100 -> 191.68648
A68: Three-ME | B68: Baseline | C68: France | D68: Production | E68: Construction | F68: Volume | G68: Index (base: 2021) | H68: =base!H84/base!$H84*100 -> 100 | I68: =base!I84/base!$H84*100 -> 102.05889 | J68: =base!J84/base!$H84*100 -> 104.16713 | K68: =base!K84/base!$H84*100 -> 106.33323 | L68: =base!L84/base!$H84*100 -> 108.61035 | M68: =base!M84/base!$H84*100 -> 110.96831 | N68: =base!N84/base!$H84*100 -> 113.41044 | O68: =base!O84/base!$H84*100 -> 115.91186 | ... AK68: =base!AK84/base!$H84*100 -> 212.98468
A69: Three-ME | B69: Baseline | C69: France | D69: Production | E69: Rail transport | F69: Volume | G69: Index (base: 2021) | H69: =base!H86/base!$H86*100 -> 100 | I69: =base!I86/base!$H86*100 -> 101.45688 | J69: =base!J86/base!$H86*100 -> 102.91026 | K69: =base!K86/base!$H86*100 -> 104.36691 | L69: =base!L86/base!$H86*100 -> 105.88027 | M69: =base!M86/base!$H86*100 -> 107.3883 | N69: =base!N86/base!$H86*100 -> 108.87683 | O69: =base!O86/base!$H86*100 -> 110.27212 | ... AK69: =base!AK86/base!$H86*100 -> 169.36042
A70: Three-ME | B70: Baseline | C70: France | D70: Production | E70: Road transport | F70: Volume | G70: Index (base: 2021) | H70: =base!H87/base!$H87*100 -> 100 | I70: =base!I87/base!$H87*100 -> 101.9165 | J70: =base!J87/base!$H87*100 -> 103.80645 | K70: =base!K87/base!$H87*100 -> 105.67258 | L70: =base!L87/base!$H87*100 -> 107.52795 | M70: =base!M87/base!$H87*100 -> 109.37734 | N70: =base!N87/base!$H87*100 -> 111.12197 | O70: =base!O87/base!$H87*100 -> 112.55327 | ... AK70: =base!AK87/base!$H87*100 -> 200.15584
A71: Three-ME | B71: Baseline | C71: France | D71: Production | E71: Water transport | F71: Volume | G71: Index (base: 2021) | H71: =base!H88/base!$H88*100 -> 100 | I71: =base!I88/base!$H88*100 -> 102.02997 | J71: =base!J88/base!$H88*100 -> 104.12373 | K71: =base!K88/base!$H88*100 -> 106.27266 | L71: =base!L88/base!$H88*100 -> 108.51693 | M71: =base!M88/base!$H88*100 -> 110.79749 | N71: =base!N88/base!$H88*100 -> 113.05596 | O71: =base!O88/base!$H88*100 -> 115.15283 | ... AK71: =base!AK88/base!$H88*100 -> 207.09463
A72: Three-ME | B72: Baseline | C72: France | D72: Production | E72: Air transport | F72: Volume | G72: Index (base: 2021) | H72: =base!H89/base!$H89*100 -> 100 | I72: =base!I89/base!$H89*100 -> 101.78986 | J72: =base!J89/base!$H89*100 -> 103.59088 | K72: =base!K89/base!$H89*100 -> 105.41259 | L72: =base!L89/base!$H89*100 -> 107.31746 | M72: =base!M89/base!$H89*100 -> 109.23731 | N72: =base!N89/base!$H89*100 -> 111.16061 | O72: =base!O89/base!$H89*100 -> 113.01702 | ... AK72: =base!AK89/base!$H89*100 -> 183.88138
A73: Three-ME | B73: Baseline | C73: France | D73: Production | E73: Private services | F73: Volume | G73: Index (base: 2021) | H73: =base!H90/base!$H90*100 -> 100 | I73: =base!I90/base!$H90*100 -> 101.53536 | J73: =base!J90/base!$H90*100 -> 103.10194 | K73: =base!K90/base!$H90*100 -> 104.70089 | L73: =base!L90/base!$H90*100 -> 106.47425 | M73: =base!M90/base!$H90*100 -> 108.1534 | N73: =base!N90/base!$H90*100 -> 109.86258 | O73: =base!O90/base!$H90*100 -> 111.58943 | ... AK73: =base!AK90/base!$H90*100 -> 164.72981
A74: Three-ME | B74: Baseline | C74: France | D74: Production | E74: Public services | F74: Volume | G74: Index (base: 2021) | H74: =base!H91/base!$H91*100 -> 100 | I74: =base!I91/base!$H91*100 -> 101.47181 | J74: =base!J91/base!$H91*100 -> 102.93893 | K74: =base!K91/base!$H91*100 -> 104.40611 | L74: =base!L91/base!$H91*100 -> 105.91626 | M74: =base!M91/base!$H91*100 -> 107.43231 | N74: =base!N91/base!$H91*100 -> 108.91717 | O74: =base!O91/base!$H91*100 -> 110.27655 | ... AK74: =base!AK91/base!$H91*100 -> 178.22079
A75: Three-ME | B75: Baseline | C75: France | D75: Production | E75: Energy transformation | F75: Volume | G75: Index (base: 2021) | H75: =base!H92/base!$H92*100 -> 100 | I75: =base!I92/base!$H92*100 -> 101.02181 | J75: =base!J92/base!$H92*100 -> 102.0398 | K75: =base!K92/base!$H92*100 -> 103.05009 | L75: =base!L92/base!$H92*100 -> 104.07871 | M75: =base!M92/base!$H92*100 -> 105.10519 | N75: =base!N92/base!$H92*100 -> 106.10835 | O75: =base!O92/base!$H92*100 -> 107.0267 | ... AK75: =base!AK92/base!$H92*100 -> 154.03211
A76: Three-ME | B76: Baseline | C76: France | D76: Production | E76: Oil | F76: Volume | G76: Index (base: 2021) | H76: =base!H93/base!$H93*100 -> 100 | I76: =base!I93/base!$H93*100 -> 100.93188 | J76: =base!J93/base!$H93*100 -> 101.88492 | K76: =base!K93/base!$H93*100 -> 102.84296 | L76: =base!L93/base!$H93*100 -> 103.81898 | M76: =base!M93/base!$H93*100 -> 104.79627 | N76: =base!N93/base!$H93*100 -> 105.76387 | O76: =base!O93/base!$H93*100 -> 106.68946 | ... AK76: =base!AK93/base!$H93*100 -> 142.85658
A77: Three-ME | B77: Baseline | C77: France | D77: Production | E77: Biofuel | F77: Volume | G77: Index (base: 2021) | H77: =base!H94/base!$H94*100 -> 100 | I77: =base!I94/base!$H94*100 -> 100.31924 | J77: =base!J94/base!$H94*100 -> 100.54645 | K77: =base!K94/base!$H94*100 -> 100.73431 | L77: =base!L94/base!$H94*100 -> 100.95262 | M77: =base!M94/base!$H94*100 -> 101.16634 | N77: =base!N94/base!$H94*100 -> 101.36571 | O77: =base!O94/base!$H94*100 -> 101.49467 | ... AK77: =base!AK94/base!$H94*100 -> 144.12348
A78: Three-ME | B78: Baseline | C78: France | D78: Production | E78: Natural gas | F78: Volume | G78: Index (base: 2021) | H78: =base!H95/base!$H95*100 -> 100 | I78: =base!I95/base!$H95*100 -> 100.31924 | J78: =base!J95/base!$H95*100 -> 100.54645 | K78: =base!K95/base!$H95*100 -> 100.73431 | L78: =base!L95/base!$H95*100 -> 100.95262 | M78: =base!M95/base!$H95*100 -> 101.16634 | N78: =base!N95/base!$H95*100 -> 101.36571 | O78: =base!O95/base!$H95*100 -> 101.49467 | ... AK78: =base!AK95/base!$H95*100 -> 144.12348
A79: Three-ME | B79: Baseline | C79: France | D79: Production | E79: Biogas | F79: Volume | G79: Index (base: 2021) | H79: =base!H96/base!$H96*100 -> 100 | I79: =base!I96/base!$H96*100 -> 100.96589 | J79: =base!J96/base!$H96*100 -> 101.98667 | K79: =base!K96/base!$H96*100 -> 103.04061 | L79: =base!L96/base!$H96*100 -> 104.15473 | M79: =base!M96/base!$H96*100 -> 105.2585 | N79: =base!N96/base!$H96*100 -> 106.32392 | O79: =base!O96/base!$H96*100 -> 107.2865 | ... AK79: =base!AK96/base!$H96*100 -> 154.83197
A80: Three-ME | B80: Baseline | C80: France | D80: Production | E80: Electricity | F80: Volume | G80: Index (base: 2021) | H80: =SUM(base!H96:H104)/SUM(base!$H96:$H104)*100 -> 100 | I80: =SUM(base!I96:I104)/SUM(base!$H96:$H104)*100 -> 100.94594 | J80: =SUM(base!J96:J104)/SUM(base!$H96:$H104)*100 -> 101.93758 | K80: =SUM(base!K96:K104)/SUM(base!$H96:$H104)*100 -> 102.95672 | L80: =SUM(base!L96:L104)/SUM(base!$H96:$H104)*100 -> 104.03932 | M80: =SUM(base!M96:M104)/SUM(base!$H96:$H104)*100 -> 105.10656 | N80: =SUM(base!N96:N104)/SUM(base!$H96:$H104)*100 -> 106.1354 | O80: =SUM(base!O96:O104)/SUM(base!$H96:$H104)*100 -> 107.06605 | ... AK80: =SUM(base!AK96:AK104)/SUM(base!$H96:$H104)*100 -> 153.16606
A81: Three-ME | B81: Baseline | C81: France | D81: Auto | E81: Hybrid | F81: Physical | G81: Number | H81: =base!H105 -> 32173.16 | I81: =base!I105 -> 32399.008 | J81: =base!J105 -> 32634.391 | K81: =base!K105 -> 32877.538 | L81: =base!L105 -> 33133.714 | M81: =base!M105 -> 33397.411 | N81: =base!N105 -> 33668.683 | O81: =base!O105 -> 33944.056 | ... AK81: =base!AK105 -> 42106.337
A82: Three-ME | B82: Baseline | C82: France | D82: Auto | E82: Fuel | F82: Physical | G82: Number | H82: =base!H106 -> 31994.923 | I82: =base!I106 -> 32194.829 | J82: =base!J106 -> 32403.053 | K82: =base!K106 -> 32617.374 | L82: =base!L106 -> 32842.463 | M82: =base!M106 -> 33072.342 | N82: =base!N106 -> 33306.522 | O82: =base!O106 -> 33541.054 | ... AK82: =base!AK106 -> 39079.453
A83: Three-ME | B83: Baseline | C83: France | D83: Auto | E83: Electric | F83: Physical | G83: Number | H83: =base!H107 -> 175.86538 | I83: =base!I107 -> 201.72995 | J83: =base!J107 -> 228.81361 | K83: =base!K107 -> 257.56694 | L83: =base!L107 -> 288.58453 | M83: =base!M107 -> 322.3347 | N83: =base!N107 -> 359.36258 | O83: =base!O107 -> 400.14024 | ... AK83: =base!AK107 -> 3023.0184
A84: Three-ME | B84: Baseline | C84: France | D84: Auto | E84: Gas | F84: Physical | G84: Number | H84: =base!H108 -> 2.3718638 | I84: =base!I108 -> 2.4495936 | J84: =base!J108 -> 2.5244712 | K84: =base!K108 -> 2.5965424 | L84: =base!L108 -> 2.666415 | M84: =base!M108 -> 2.7337946 | N84: =base!N108 -> 2.7988271 | O84: =base!O108 -> 2.8613558 | ... AK84: =base!AK108 -> 3.8659259
A85: Three-ME | B85: Baseline | C85: France | D85: Auto | E85: Class A | F85: Physical | G85: Number | H85: =base!H109 -> 7942.5645 | I85: =base!I109 -> 8136.9553 | J85: =base!J109 -> 8331.0613 | K85: =base!K109 -> 8524.8687 | L85: =base!L109 -> 8720.3414 | M85: =base!M109 -> 8915.9839 | N85: =base!N109 -> 9111.8129 | O85: =base!O109 -> 9306.6128 | ... AK85: =base!AK109 -> 13865.747
A86: Three-ME | B86: Baseline | C86: France | D86: Auto | E86: Class B | F86: Physical | G86: Number | H86: =base!H110 -> 8490.6138 | I86: =base!I110 -> 8600.6588 | J86: =base!J110 -> 8714.5076 | K86: =base!K110 -> 8831.6515 | L86: =base!L110 -> 8953.5289 | M86: =base!M110 -> 9078.4019 | N86: =base!N110 -> 9206.0422 | O86: =base!O110 -> 9335.1374 | ... AK86: =base!AK110 -> 12735.052
A87: Three-ME | B87: Baseline | C87: France | D87: Auto | E87: Class C | F87: Physical | G87: Number | H87: =base!H111 -> 6519.4906 | I87: =base!I111 -> 6539.4074 | J87: =base!J111 -> 6565.0787 | K87: =base!K111 -> 6595.7962 | L87: =base!L111 -> 6632.2349 | M87: =base!M111 -> 6672.9698 | N87: =base!N111 -> 6717.6612 | O87: =base!O111 -> 6765.2849 | ... AK87: =base!AK111 -> 8452.2874
A88: Three-ME | B88: Baseline | C88: France | D88: Auto | E88: Class D | F88: Physical | G88: Number | H88: =base!H112 -> 3829.4916 | I88: =base!I112 -> 3809.3829 | J88: =base!J112 -> 3792.1558 | K88: =base!K112 -> 3777.3104 | L88: =base!L112 -> 3765.1057 | M88: =base!M112 -> 3754.7819 | N88: =base!N112 -> 3746.2047 | O88: =base!O112 -> 3738.9514 | ... AK88: =base!AK112 -> 3844.272
A89: Three-ME | B89: Baseline | C89: France | D89: Auto | E89: Class E | F89: Physical | G89: Number | H89: =base!H113 -> 2304.3963 | I89: =base!I113 -> 2288.4627 | J89: =base!J113 -> 2273.22 | K89: =base!K113 -> 2258.4032 | L89: =base!L113 -> 2244.204 | M89: =base!M113 -> 2230.255 | N89: =base!N113 -> 2216.5764 | O89: =base!O113 -> 2203.0471 | ... AK89: =base!AK113 -> 1979.4773
A90: Three-ME | B90: Baseline | C90: France | D90: Auto | E90: Class F | F90: Physical | G90: Number | H90: =base!H114 -> 1107.3792 | I90: =base!I114 -> 1088.6846 | J90: =base!J114 -> 1069.3418 | K90: =base!K114 -> 1049.3282 | L90: =base!L114 -> 1028.8176 | M90: =base!M114 -> 1007.7968 | N90: =base!N114 -> 986.42589 | O90: =base!O114 -> 964.82963 | ... AK90: =base!AK114 -> 549.42749
A91: Three-ME | B91: Baseline | C91: France | D91: Auto | E91: Class G | F91: Physical | G91: Number | H91: =base!H115 -> 1979.224 | I91: =base!I115 -> 1935.4566 | J91: =base!J115 -> 1889.0258 | K91: =base!K115 -> 1840.1798 | L91: =base!L115 -> 1789.4813 | M91: =base!M115 -> 1737.2214 | N91: =base!N115 -> 1683.9599 | O91: =base!O115 -> 1630.1925 | ... AK91: =base!AK115 -> 680.07399
A92: Three-ME | B92: Baseline | C92: France | D92: Building | E92: Hybrid | F92: Physical | G92: Number | H92: =base!H116 -> 2517.7068 | I92: =base!I116 -> 2526.3058 | J92: =base!J116 -> 2534.9343 | K92: =base!K116 -> 2543.5922 | L92: =base!L116 -> 2556.2719 | M92: =base!M116 -> 2565.0027 | N92: =base!N116 -> 2573.7633 | O92: =base!O116 -> 2582.5538 | ... AK92: =base!AK116 -> 2738.7438
... A101: Three-ME | B101: Baseline | C101: France | D101: Final energy | E101: Hybrid | F101: Energy | G101: toe | H101: =base!H125 -> 165.3825 | I101: =base!I125 -> 164.86224 | J101: =base!J125 -> 164.06499 | K101: =base!K125 -> 163.69381 | L101: =base!L125 -> 163.48425 | M101: =base!M125 -> 163.54713 | N101: =base!N125 -> 163.79613 | O101: =base!O125 -> 164.13652 | ... AK101: =base!AK125 -> 236.28394
A102: Three-ME | B102: Net Zero 2050 | C102: France | D102: GDP | E102: Macro | F102: Volume | G102: Index (base: 2021) | H102: =Orderly!H2/Orderly!$H2*100 -> 100 | I102: =Orderly!I2/Orderly!$H2*100 -> 101.54705 | J102: =Orderly!J2/Orderly!$H2*100 -> 103.12065 | K102: =Orderly!K2/Orderly!$H2*100 -> 105.09655 | L102: =Orderly!L2/Orderly!$H2*100 -> 107.20863 | M102: =Orderly!M2/Orderly!$H2*100 -> 109.30709 | N102: =Orderly!N2/Orderly!$H2*100 -> 111.393 | O102: =Orderly!O2/Orderly!$H2*100 -> 113.40984 | ... AK102: =Orderly!AK2/Orderly!$H2*100 -> 185.99243
A103: Three-ME | B103: Net Zero 2050 | C103: France | D103: Investment | E103: Macro | F103: Volume | G103: Index (base: 2021) | H103: =Orderly!H3/Orderly!$H3*100 -> 100 | I103: =Orderly!I3/Orderly!$H3*100 -> 101.8507 | J103: =Orderly!J3/Orderly!$H3*100 -> 103.68127 | K103: =Orderly!K3/Orderly!$H3*100 -> 105.82498 | L103: =Orderly!L3/Orderly!$H3*100 -> 108.22004 | M103: =Orderly!M3/Orderly!$H3*100 -> 110.7929 | N103: =Orderly!N3/Orderly!$H3*100 -> 113.48807 | O103: =Orderly!O3/Orderly!$H3*100 -> 116.24415 | ... AK103: =Orderly!AK3/Orderly!$H3*100 -> 242.3167
A104: Three-ME | B104: Net Zero 2050 | C104: France | D104: Consumption | E104: Macro | F104: Volume | G104: Index (base: 2021) | H104: =Orderly!H4/Orderly!$H4*100 -> 100 | I104: =Orderly!I4/Orderly!$H4*100 -> 101.78255 | J104: =Orderly!J4/Orderly!$H4*100 -> 103.52937 | K104: =Orderly!K4/Orderly!$H4*100 -> 105.4372 | L104: =Orderly!L4/Orderly!$H4*100 -> 107.60526 | M104: =Orderly!M4/Orderly!$H4*100 -> 109.91621 | N104: =Orderly!N4/Orderly!$H4*100 -> 112.35553 | O104: =Orderly!O4/Orderly!$H4*100 -> 114.83579 | ... AK104: =Orderly!AK4/Orderly!$H4*100 -> 180.77909
A105: Three-ME | B105: Net Zero 2050 | C105: France | D105: Exports | E105: Macro | F105: Volume | G105: Index (base: 2021) | H105: =Orderly!H5/Orderly!$H5*100 -> 100 | I105: =Orderly!I5/Orderly!$H5*100 -> 101.00637 | J105: =Orderly!J5/Orderly!$H5*100 -> 102.14745 | K105: =Orderly!K5/Orderly!$H5*100 -> 104.63112 | L105: =Orderly!L5/Orderly!$H5*100 -> 106.99036 | M105: =Orderly!M5/Orderly!$H5*100 -> 109.14893 | N105: =Orderly!N5/Orderly!$H5*100 -> 110.96522 | O105: =Orderly!O5/Orderly!$H5*100 -> 112.34758 | ... AK105: =Orderly!AK5/Orderly!$H5*100 -> 195.13332
A106: Three-ME | B106: Net Zero 2050 | C106: France | D106: Imports | E106: Macro | F106: Volume | G106: Index (base: 2021) | H106: =Orderly!H6/Orderly!$H6*100 -> 100 | I106: =Orderly!I6/Orderly!$H6*100 -> 101.42806 | J106: =Orderly!J6/Orderly!$H6*100 -> 102.88047 | K106: =Orderly!K6/Orderly!$H6*100 -> 104.88703 | L106: =Orderly!L6/Orderly!$H6*100 -> 107.15501 | M106: =Orderly!M6/Orderly!$H6*100 -> 109.57825 | N106: =Orderly!N6/Orderly!$H6*100 -> 112.07351 | O106: =Orderly!O6/Orderly!$H6*100 -> 114.53307 | ... AK106: =Orderly!AK6/Orderly!$H6*100 -> 203.98525
A107: Three-ME | B107: Net Zero 2050 | C107: France | D107: Public surplus | E107: Macro | F107: Value | G107: Euro | H107: =Orderly!H7/(Orderly!H$2*Orderly!H$14) -> -0.016974432 | I107: =Orderly!I7/(Orderly!I$2*Orderly!I$14) -> -0.015292785 | J107: =Orderly!J7/(Orderly!J$2*Orderly!J$14) -> -0.01720368 | K107: =Orderly!K7/(Orderly!K$2*Orderly!K$14) -> -0.015090857 | L107: =Orderly!L7/(Orderly!L$2*Orderly!L$14) -> -0.012412688 | M107: =Orderly!M7/(Orderly!M$2*Orderly!M$14) -> -0.0082627305 | N107: =Orderly!N7/(Orderly!N$2*Orderly!N$14) -> -0.0030160273 | O107: =Orderly!O7/(Orderly!O$2*Orderly!O$14) -> 0.0018107874 | ... AK107: =Orderly!AK7/(Orderly!AK$2*Orderly!AK$14) -> 0.10929489
A108: Three-ME | B108: Net Zero 2050 | C108: France | D108: Public debt | E108: Macro | F108: Value | G108: Euro | H108: =Orderly!H8/(Orderly!H$2*Orderly!H$14) -> 0.90046965 | I108: =Orderly!I8/(Orderly!I$2*Orderly!I$14) -> 0.87921826 | J108: =Orderly!J8/(Orderly!J$2*Orderly!J$14) -> 0.86045484 | K108: =Orderly!K8/(Orderly!K$2*Orderly!K$14) -> 0.83601344 | L108: =Orderly!L8/(Orderly!L$2*Orderly!L$14) -> 0.80794088 | M108: =Orderly!M8/(Orderly!M$2*Orderly!M$14) -> 0.7781152 | N108: =Orderly!N8/(Orderly!N$2*Orderly!N$14) -> 0.74511204 | O108: =Orderly!O8/(Orderly!O$2*Orderly!O$14) -> 0.71023323 | ... AK108: =Orderly!AK8/(Orderly!AK$2*Orderly!AK$14) -> -0.48555383
...

Sheet base
B1: 42005 | C1: 42370 | D1: 42736 | E1: 43101 | F1: 43466 | G1: 43831 | H1: 44197 | I1: 44562 | J1: 44927 | K1: 45292 | L1: 45658 | M1: 46023 | N1: 46388 | O1: 46753 | P1: 47119 | Q1: 47484 | R1: 47849 | S1: 48214 | T1: 48580 | U1: 48945 | V1: 49310 | W1: 49675 | X1: 50041 | Y1: 50406 | Z1: 50771 | AA1: 51136 | AB1: 51502 | AC1: 51867 | AD1: 52232 | AE1: 52597 | AF1: 52963 | AG1: 53328 | AH1: 53693 | AI1: 54058 | AJ1: 54424 | AK1: 54789
A2: =[1]Macro!A99 -> gdp_0 | B2: =[1]Macro!B99 -> 2197953 | C2: =[1]Macro!C99 -> 2230476.4 | D2: =[1]Macro!D99 -> 2266147.4 | E2: =[1]Macro!E99 -> 2304476.7 | F2: =[1]Macro!F99 -> 2344700.1 | G2: =[1]Macro!G99 -> 2386655 | H2: =[1]Macro!H99 -> 2428465.8 | ... AK2: =[1]Macro!AK99 -> 4406324
A3: =[1]Results!E1639 -> IA_0 | B3: =[1]Results!F1639 -> 472737.8 | C3: =[1]Results!G1639 -> 479640.45 | D3: =[1]Results!H1639 -> 487700.59 | E3: =[1]Results!I1639 -> 496636.8 | F3: =[1]Results!J1639 -> 506358.69 | G3: =[1]Results!K1639 -> 516731.29 | H3: =[1]Results!L1639 -> 527414.47 | ... AK3: =[1]Results!AO1639 -> 1109116.9
A4: =[1]Results!E1731 -> CH_0 | B4: =[1]Results!F1731 -> 1202789 | C4: =[1]Results!G1731 -> 1220397.5 | D4: =[1]Results!H1731 -> 1240919.3 | E4: =[1]Results!I1731 -> 1263569.8 | F4: =[1]Results!J1731 -> 1287361.8 | G4: =[1]Results!K1731 -> 1311977.1 | H4: =[1]Results!L1731 -> 1335837.5 | ... AK4: =[1]Results!AO1731 -> 2321895.8
A5: =[1]Export!A3 -> x_0 | B5: =[1]Export!B3 -> 631198.05 | C5: =[1]Export!C3 -> 645659.12 | D5: =[1]Export!D3 -> 659829.13 | E5: =[1]Export!E3 -> 673817.85 | F5: =[1]Export!F3 -> 687886.09 | G5: =[1]Export!G3 -> 702162.43 | H5: =[1]Export!H3 -> 716590.17 | ... AK5: =[1]Export!AK3 -> 1473246.3
A6: =[1]Import!A3 -> m_0 | B6: =[1]Import!B3 -> 655146.23 | C6: =[1]Import!C3 -> 664463.74 | D6: =[1]Import!D3 -> 675963.41 | E6: =[1]Import!E3 -> 688489.73 | F6: =[1]Import!F3 -> 701879.78 | G6: =[1]Import!G3 -> 715851.24 | H6: =[1]Import!H3 -> 729712.43 | ... AK6: =[1]Import!AK3 -> 1411978.5
A7: =[1]Macro!A72 -> bal_g_tot_val_0 | B7: =[1]Macro!B72 -> -65724.458 | C7: =[1]Macro!C72 -> -68542.988 | D7: =[1]Macro!D72 -> -66434.788 | E7: =[1]Macro!E72 -> -63456.443 | F7: =[1]Macro!F72 -> -60105.648 | G7: =[1]Macro!G72 -> -53781.563 | H7: =[1]Macro!H72 -> -46675.665 | ... AK7: =[1]Macro!AK72 -> 717193.04
A8: =[1]Macro!A73 -> debt_g_val_0 | B8: =[1]Macro!B73 -> 2105265.8 | C8: =[1]Macro!C73 -> 2173808.8 | D8: =[1]Macro!D73 -> 2240243.6 | E8: =[1]Macro!E73 -> 2303700 | F8: =[1]Macro!F73 -> 2363805.7 | G8: =[1]Macro!G73 -> 2417587.2 | H8: =[1]Macro!H73 -> 2464262.9 | ... AK8: =[1]Macro!AK73 -> -2027347.8
A9: =[1]Macro!A95 -> bal_g_prim_val_0 | B9: =[1]Macro!B95 -> -21358.417 | C9: =[1]Macro!C95 -> -20676.422 | D9: =[1]Macro!D95 -> -19223.797 | E9: =[1]Macro!E95 -> -16334.445 | F9: =[1]Macro!F95 -> -11655.009 | G9: =[1]Macro!G95 -> -6167.4624 | H9: =[1]Macro!H95 -> 673.99816 | ... AK9: =[1]Macro!AK95 -> 684720.68
A10: =[1]Macro!A96 -> ener_bill_0 | B10: =[1]Macro!B96 -> 28684.77 | C10: =[1]Macro!C96 -> 29034.892 | D10: =[1]Macro!D96 -> 29339.235 | E10: =[1]Macro!E96 -> 29587.102 | F10: =[1]Macro!F96 -> 30059.54 | G10: =[1]Macro!G96 -> 30716.5 | H10: =[1]Macro!H96 -> 33740.446 | ... AK10: =[1]Macro!AK96 -> 113871.4
A11: =[1]Macro!A97 -> bal_trade_val_0 | B11: =[1]Macro!B97 -> -23361.949 | C11: =[1]Macro!C97 -> -14334.785 | D11: =[1]Macro!D97 -> -7730.366 | E11: =[1]Macro!E97 -> -1774.1393 | F11: =[1]Macro!F97 -> 3079.9967 | G11: =[1]Macro!G97 -> 7509.9023 | H11: =[1]Macro!H97 -> 10540.038 | ... AK11: =[1]Macro!AK97 -> 444265.46
A12: =[1]Macro!A98 -> unr_0 | B12: =[1]Macro!B98 -> 0.14242623 | C12: =[1]Macro!C98 -> 0.14261844 | D12: =[1]Macro!D98 -> 0.14265441 | E12: =[1]Macro!E98 -> 0.14186411 | F12: =[1]Macro!F98 -> 0.14058843 | G12: =[1]Macro!G98 -> 0.1389887 | H12: =[1]Macro!H98 -> 0.13674745 | ... AK12: =[1]Macro!AK98 -> 0.047327205
A13: =[1]Macro!A74 -> pch_0 | B13: =[1]Macro!B74 -> 1.0019287 | C13: =[1]Macro!C74 -> 1.0209119 | D13: =[1]Macro!D74 -> 1.0398984 | E13: =[1]Macro!E74 -> 1.0599435 | F13: =[1]Macro!F74 -> 1.078494 | G13: =[1]Macro!G74 -> 1.0971251 | H13: =[1]Macro!H74 -> 1.1169742 | ... AK13: =[1]Macro!AK74 -> 1.7954752
A14: =[1]Macro!A75 -> pgdp_0 | B14: =[1]Macro!B75 -> 1.0015748 | C14: =[1]Macro!C75 -> 1.0222259 | D14: =[1]Macro!D75 -> 1.0427743 | E14: =[1]Macro!E75 -> 1.06443 | F14: =[1]Macro!F75 -> 1.0850099 | G14: =[1]Macro!G75 -> 1.1056596 | H14: =[1]Macro!H75 -> 1.1266403 | ... AK14: =[1]Macro!AK75 -> 1.8878191
A15: =[1]Macro!A76 -> py_0 | B15: =[1]Macro!B76 -> 1.0006765 | C15: =[1]Macro!C76 -> 1.0200906 | D15: =[1]Macro!D76 -> 1.0394175 | E15: =[1]Macro!E76 -> 1.0594942 | F15: =[1]Macro!F76 -> 1.079276 | G15: =[1]Macro!G76 -> 1.0991176 | H15: =[1]Macro!H76 -> 1.1200898 | ... AK15: =[1]Macro!AK76 -> 1.8506859
A16: =[1]Macro!A77 -> pm_0 | B16: =[1]Macro!B77 -> 1 | C16: =[1]Macro!C77 -> 1.0126187 | D16: =[1]Macro!D77 -> 1.0253847 | E16: =[1]Macro!E77 -> 1.038296 | F16: =[1]Macro!F77 -> 1.0513623 | G16: =[1]Macro!G77 -> 1.0645895 | H16: =[1]Macro!H77 -> 1.0817288 | ... AK16: =[1]Macro!AK77 -> 1.5714675
A17: =[1]Macro!A78 -> pi_0 | B17: =[1]Macro!B78 -> 1.0011136 | C17: =[1]Macro!C78 -> 1.0191048 | D17: =[1]Macro!D78 -> 1.0367895 | E17: =[1]Macro!E78 -> 1.0555264 | F17: =[1]Macro!F78 -> 1.0738987 | G17: =[1]Macro!G78 -> 1.0925687 | H17: =[1]Macro!H78 -> 1.1125794 | ... AK17: =[1]Macro!AK78 -> 1.8320636
A18: =[1]Macro!A79 -> px_0 | B18: =[1]Macro!B79 -> 1.0009288 | C18: =[1]Macro!C79 -> 1.0199092 | D18: =[1]Macro!D79 -> 1.038742 | E18: =[1]Macro!E79 -> 1.0582712 | F18: =[1]Macro!F79 -> 1.0772277 | G18: =[1]Macro!G79 -> 1.0960393 | H18: =[1]Macro!H79 -> 1.1162461 | ... AK18: =[1]Macro!AK79 -> 1.8076704
A19: =[1]Macro!A80 -> cu_0 | B19: =[1]Macro!B80 -> 0.99335227 | C19: =[1]Macro!C80 -> 1.0104374 | D19: =[1]Macro!D80 -> 1.0279936 | E19: =[1]Macro!E80 -> 1.046912 | F19: =[1]Macro!F80 -> 1.0647773 | G19: =[1]Macro!G80 -> 1.083175 | H19: =[1]Macro!H80 -> 1.1039332 | ... AK19: =[1]Macro!AK80 -> 1.8290313
A20: =[1]Macro!A81 -> f_l_0 | B20: =[1]Macro!B81 -> 27379.148 | C20: =[1]Macro!C81 -> 27463.028 | D20: =[1]Macro!D81 -> 27580.776 | E20: =[1]Macro!E81 -> 27730.779 | F20: =[1]Macro!F81 -> 27902.628 | G20: =[1]Macro!G81 -> 28090.563 | H20: =[1]Macro!H81 -> 28279.679 | ... AK20: =[1]Macro!AK81 -> 35122.491
A21: =[1]Macro!A82 -> f_k_0 | B21: =[1]Macro!B82 -> 5223867.2 | C21: =[1]Macro!C82 -> 5285598.3 | D21: =[1]Macro!D82 -> 5350451 | E21: =[1]Macro!E82 -> 5419051.7 | F21: =[1]Macro!F82 -> 5491886.3 | G21: =[1]Macro!G82 -> 5569266.7 | H21: =[1]Macro!H82 -> 5651139.8 | ... AK21: =[1]Macro!AK82 -> 10492581
A22: =[1]Macro!A83 -> f_e_0 | B22: =[1]Macro!B83 -> 128715.09 | C22: =[1]Macro!C83 -> 129845.11 | D22: =[1]Macro!D83 -> 130908.4 | E22: =[1]Macro!E83 -> 131946.02 | F22: =[1]Macro!F83 -> 133196.59 | G22: =[1]Macro!G83 -> 134698.61 | H22: =[1]Macro!H83 -> 136301.1 | ... AK22: =[1]Macro!AK83 -> 228769.33
A23: =[1]Macro!A84 -> f_mat_0 | B23: =[1]Macro!B84 -> 1758477.5 | C23: =[1]Macro!C84 -> 1784507.9 | D23: =[1]Macro!D84 -> 1813592.5 | E23: =[1]Macro!E84 -> 1844865 | F23: =[1]Macro!F84 -> 1877854 | G23: =[1]Macro!G84 -> 1912361.4 | H23: =[1]Macro!H84 -> 1947120 | ... AK23: =[1]Macro!AK84 -> 3635492.1
A24: =[1]Macro!A85 -> w_0 | B24: =[1]Macro!B85 -> 41.206115 | C24: =[1]Macro!C85 -> 42.474185 | D24: =[1]Macro!D85 -> 43.782653 | E24: =[1]Macro!E85 -> 45.126543 | F24: =[1]Macro!F85 -> 46.518731 | G24: =[1]Macro!G85 -> 47.94126 | H24: =[1]Macro!H85 -> 49.398758 | ... AK24: =[1]Macro!AK85 -> 120.17709
... A28: =[1]Macro!A89 -> c_mat_0 | B28: =[1]Macro!B89 -> 1.0004669 | C28: =[1]Macro!C89 -> 1.0184736 | D28: =[1]Macro!D89 -> 1.0364266 | E28: =[1]Macro!E89 -> 1.0549734 | F28: =[1]Macro!F89 -> 1.0733596 | G28: =[1]Macro!G89 -> 1.0918361 | H28: =[1]Macro!H89 -> 1.1110215 | ... AK28: =[1]Macro!AK89 -> 1.7747975
A29: =[1]Results!E1552 -> VA_agrf_0 | B29: =[1]Results!F1552 -> 36098.159 | C29: =[1]Results!G1552 -> 36421.501 | D29: =[1]Results!H1552 -> 36813.129 | E29: =[1]Results!I1552 -> 37266.283 | F29: =[1]Results!J1552 -> 37780.952 | G29: =[1]Results!K1552 -> 38345.706 | H29: =[1]Results!L1552 -> 38928.936 | ... AK29: =[1]Results!AO1552 -> 68631.967
A30: =[1]Results!E1553 -> VA_sagr_0 | B30: =[1]Results!F1553 -> 30808.957 | C30: =[1]Results!G1553 -> 31184.966 | D30: =[1]Results!H1553 -> 31625.026 | E30: =[1]Results!I1553 -> 32127.895 | F30: =[1]Results!J1553 -> 32667.725 | G30: =[1]Results!K1553 -> 33243.213 | H30: =[1]Results!L1553 -> 33828.64 | ... AK30: =[1]Results!AO1553 -> 62490.087
A31: =[1]Results!E1554 -> VA_sfor_0 | B31: =[1]Results!F1554 -> 5289.202 | C31: =[1]Results!G1554 -> 5236.5354 | D31: =[1]Results!H1554 -> 5188.1023 | E31: =[1]Results!I1554 -> 5138.3884 | F31: =[1]Results!J1554 -> 5113.2264 | G31: =[1]Results!K1554 -> 5102.4936 | H31: =[1]Results!L1554 -> 5100.2965 | ... AK31: =[1]Results!AO1554 -> 6141.8799
A32: =[1]Results!E1555 -> VA_ind_0 | B32: =[1]Results!F1555 -> 331692.74 | C32: =[1]Results!G1555 -> 337438.2 | D32: =[1]Results!H1555 -> 343505.96 | E32: =[1]Results!I1555 -> 349929.82 | F32: =[1]Results!J1555 -> 356653.64 | G32: =[1]Results!K1555 -> 363647.64 | H32: =[1]Results!L1555 -> 370695.93 | ... AK32: =[1]Results!AO1555 -> 739765
A33: =[1]Results!E1556 -> VA_sfoo_0 | B33: =[1]Results!F1556 -> 43690.453 | C33: =[1]Results!G1556 -> 44313.022 | D33: =[1]Results!H1556 -> 45008.475 | E33: =[1]Results!I1556 -> 45790.966 | F33: =[1]Results!J1556 -> 46614.025 | G33: =[1]Results!K1556 -> 47479.998 | H33: =[1]Results!L1556 -> 48350.105 | ... AK33: =[1]Results!AO1556 -> 88889.55
A34: =[1]Results!E1557 -> VA_sveh_0 | B34: =[1]Results!F1557 -> 29848.047 | C34: =[1]Results!G1557 -> 30681.863 | D34: =[1]Results!H1557 -> 31486.643 | E34: =[1]Results!I1557 -> 32239.342 | F34: =[1]Results!J1557 -> 32983.67 | G34: =[1]Results!K1557 -> 33705.808 | H34: =[1]Results!L1557 -> 34386.97 | ... AK34: =[1]Results!AO1557 -> 67968.18
A35: =[1]Results!E1558 -> VA_sgla_0 | B35: =[1]Results!F1558 -> 7904.2817 | C35: =[1]Results!G1558 -> 8022.9587 | D35: =[1]Results!H1558 -> 8150.4235 | E35: =[1]Results!I1558 -> 8285.942 | F35: =[1]Results!J1558 -> 8429.9887 | G35: =[1]Results!K1558 -> 8583.1305 | H35: =[1]Results!L1558 -> 8741.0302 | ... AK35: =[1]Results!AO1558 -> 17318.176
A36: =[1]Results!E1559 -> VA_spap_0 | B36: =[1]Results!F1559 -> 4277.9101 | C36: =[1]Results!G1559 -> 4348.1288 | D36: =[1]Results!H1559 -> 4420.0588 | E36: =[1]Results!I1559 -> 4496.2852 | F36: =[1]Results!J1559 -> 4575.3695 | G36: =[1]Results!K1559 -> 4657.5485 | H36: =[1]Results!L1559 -> 4739.6266 | ... AK36: =[1]Results!AO1559 -> 8812.0612
A37: =[1]Results!E1560 -> VA_sche_0 | B37: =[1]Results!F1560 -> 26174.001 | C37: =[1]Results!G1560 -> 26647.117 | D37: =[1]Results!H1560 -> 27106.822 | E37: =[1]Results!I1560 -> 27579.385 | F37: =[1]Results!J1560 -> 28069.008 | G37: =[1]Results!K1560 -> 28578.174 | H37: =[1]Results!L1560 -> 29089.267 | ... AK37: =[1]Results!AO1560 -> 55191.091
A38: =[1]Results!E1561 -> VA_spla_0 | B38: =[1]Results!F1561 -> 11103.246 | C38: =[1]Results!G1561 -> 11296.887 | D38: =[1]Results!H1561 -> 11493.862 | E38: =[1]Results!I1561 -> 11697.826 | F38: =[1]Results!J1561 -> 11908.623 | G38: =[1]Results!K1561 -> 12126.487 | H38: =[1]Results!L1561 -> 12346.113 | ... AK38: =[1]Results!AO1561 -> 23779.451
A39: =[1]Results!E1562 -> VA_smet_0 | B39: =[1]Results!F1562 -> 24632.932 | C39: =[1]Results!G1562 -> 25066.115 | D39: =[1]Results!H1562 -> 25507.094 | E39: =[1]Results!I1562 -> 25959.82 | F39: =[1]Results!J1562 -> 26427.307 | G39: =[1]Results!K1562 -> 26911.267 | H39: =[1]Results!L1562 -> 27401.084 | ... AK39: =[1]Results!AO1562 -> 53794.91
A40: =[1]Results!E1563 -> VA_sigo_0 | B40: =[1]Results!F1563 -> 30238.345 | C40: =[1]Results!G1563 -> 30922.967 | D40: =[1]Results!H1563 -> 31563.983 | E40: =[1]Results!I1563 -> 32207.175 | F40: =[1]Results!J1563 -> 32862.536 | G40: =[1]Results!K1563 -> 33531.396 | H40: =[1]Results!L1563 -> 34205.98 | ... AK40: =[1]Results!AO1563 -> 69176.458
... A66: =[1]Results!E1589 -> VA_seot_0 | B66: =[1]Results!F1589 -> -1482.5662 | C66: =[1]Results!G1589 -> -1500.0569 | D66: =[1]Results!H1589 -> -1514.9428 | E66: =[1]Results!I1589 -> -1530.5361 | F66: =[1]Results!J1589 -> -1543.7595 | G66: =[1]Results!K1589 -> -1556.626 | H66: =[1]Results!L1589 -> -1570.5321 | ... AK66: =[1]Results!AO1589 -> -2434.9585
A67: =[1]Emissions!A820 -> ems_co2_0 | B67: =[1]Emissions!B820 -> 348.01864 | C67: =[1]Emissions!C820 -> 347.12999 | D67: =[1]Emissions!D820 -> 345.9606 | E67: =[1]Emissions!E820 -> 344.35911 | F67: =[1]Emissions!F820 -> 344.57747 | G67: =[1]Emissions!G820 -> 346.16873 | H67: =[1]Emissions!H820 -> 347.92632 | ... AK67: =[1]Emissions!AK820 -> 511.73421
A68: =[1]Emissions!A821 -> ems_ci_co2_0 | B68: =[1]Emissions!B821 -> 213.27374 | C68: =[1]Emissions!C821 -> 213.29498 | D68: =[1]Emissions!D821 -> 213.13965 | E68: =[1]Emissions!E821 -> 212.5091 | F68: =[1]Emissions!F821 -> 213.04677 | G68: =[1]Emissions!G821 -> 214.54738 | H68: =[1]Emissions!H821 -> 216.2543 | ... AK68: =[1]Emissions!AK821 -> 361.1347
A69: =[1]Emissions!A822 -> ems_y_co2_0 | B69: =[1]Emissions!B822 -> 0.027534944 | C69: =[1]Emissions!C822 -> 0.027853944 | D69: =[1]Emissions!D822 -> 0.028219876 | E69: =[1]Emissions!E822 -> 0.028637518 | F69: =[1]Emissions!F822 -> 0.029095659 | G69: =[1]Emissions!G822 -> 0.029591995 | H69: =[1]Emissions!H822 -> 0.030103176 | ... AK69: =[1]Emissions!AK822 -> 0.055470729
A70: =[1]Emissions!A823 -> ems_mat_co2_0 | B70: =[1]Emissions!B823 -> 15.226879 | C70: =[1]Emissions!C823 -> 15.432255 | D70: =[1]Emissions!D823 -> 15.657793 | E70: =[1]Emissions!E823 -> 15.895768 | F70: =[1]Emissions!F823 -> 16.150067 | G70: =[1]Emissions!G823 -> 16.42237 | H70: =[1]Emissions!H823 -> 16.702208 | ... AK70: =[1]Emissions!AK823 -> 31.386973
A71: =[1]Emissions!A824 -> ems_ch_co2_0 | B71: =[1]Emissions!B824 -> 119.49049 | C71: =[1]Emissions!C824 -> 118.3749 | D71: =[1]Emissions!D824 -> 117.13493 | E71: =[1]Emissions!E824 -> 115.9256 | F71: =[1]Emissions!F824 -> 115.35154 | G71: =[1]Emissions!G824 -> 115.16939 | H71: =[1]Emissions!H824 -> 114.93971 | ... AK71: =[1]Emissions!AK824 -> 119.15707
A72: =[1]Production!A3 -> y_0 | B72: =[1]Production!B3 -> 3854147.4 | C72: =[1]Production!C3 -> 3910661.1 | D72: =[1]Production!D3 -> 3972850.3 | E72: =[1]Production!E3 -> 4039546.5 | F72: =[1]Production!F3 -> 4109788.5 | G72: =[1]Production!G3 -> 4183314.3 | H72: =[1]Production!H3 -> 4257127.2 | ... AK72: =[1]Production!AK3 -> 7820409
A73: =[1]Production!A5 -> y_sagr_0 | B73: =[1]Production!B5 -> 81750.877 | C73: =[1]Production!C5 -> 82697.982 | D73: =[1]Production!D5 -> 83784.429 | E73: =[1]Production!E5 -> 85024.403 | F73: =[1]Production!F5 -> 86384.617 | G73: =[1]Production!G5 -> 87858.233 | H73: =[1]Production!H5 -> 89375.921 | ... AK73: =[1]Production!AK5 -> 164691.84
A74: =[1]Production!A7 -> y_sfor_0 | B74: =[1]Production!B7 -> 6533.6203 | C74: =[1]Production!C7 -> 6469.9469 | D74: =[1]Production!D7 -> 6408.2174 | E74: =[1]Production!E7 -> 6344.6002 | F74: =[1]Production!F7 -> 6311.2776 | G74: =[1]Production!G7 -> 6296.6029 | H74: =[1]Production!H7 -> 6292.9679 | ... AK74: =[1]Production!AK7 -> 7570.9756
A75: =[1]Production!A9 -> y_sfoo_0 | B75: =[1]Production!B9 -> 157700.04 | C75: =[1]Production!C9 -> 159810.09 | D75: =[1]Production!D9 -> 162170.83 | E75: =[1]Production!E9 -> 164824.62 | F75: =[1]Production!F9 -> 167674.97 | G75: =[1]Production!G9 -> 170710.62 | H75: =[1]Production!H9 -> 173789.79 | ... AK75: =[1]Production!AK9 -> 318170.84
A76: =[1]Production!A11 -> y_sveh_0 | B76: =[1]Production!B11 -> 125571.2 | C76: =[1]Production!C11 -> 128565.38 | D76: =[1]Production!D11 -> 131819.14 | E76: =[1]Production!E11 -> 134958.35 | F76: =[1]Production!F11 -> 138028.96 | G76: =[1]Production!G11 -> 141004.01 | H76: =[1]Production!H11 -> 143803.66 | ... AK76: =[1]Production!AK11 -> 281454.3
A77: =[1]Production!A13 -> y_sgla_0 | B77: =[1]Production!B13 -> 22090.315 | C77: =[1]Production!C13 -> 22389.103 | D77: =[1]Production!D13 -> 22713.53 | E77: =[1]Production!E13 -> 23056.031 | F77: =[1]Production!F13 -> 23427.732 | G77: =[1]Production!G13 -> 23831.661 | H77: =[1]Production!H13 -> 24252.537 | ... AK77: =[1]Production!AK13 -> 47756.863
A78: =[1]Production!A15 -> y_spap_0 | B78: =[1]Production!B15 -> 16306.072 | C78: =[1]Production!C15 -> 16549.579 | D78: =[1]Production!D15 -> 16809.246 | E78: =[1]Production!E15 -> 17083.983 | F78: =[1]Production!F15 -> 17373.21 | G78: =[1]Production!G15 -> 17677.329 | H78: =[1]Production!H15 -> 17984.904 | ... AK78: =[1]Production!AK15 -> 33460.732
A79: =[1]Production!A17 -> y_sche_0 | B79: =[1]Production!B17 -> 86967.448 | C79: =[1]Production!C17 -> 88425.816 | D79: =[1]Production!D17 -> 89928.191 | E79: =[1]Production!E17 -> 91470.253 | F79: =[1]Production!F17 -> 93067.146 | G79: =[1]Production!G17 -> 94730.857 | H79: =[1]Production!H17 -> 96397.359 | ... AK79: =[1]Production!AK17 -> 181460.51
A80: =[1]Production!A19 -> y_spla_0 | B80: =[1]Production!B19 -> 29077.376 | C80: =[1]Production!C19 -> 29556.579 | D80: =[1]Production!D19 -> 30061.866 | E80: =[1]Production!E19 -> 30585.494 | F80: =[1]Production!F19 -> 31128.331 | G80: =[1]Production!G19 -> 31691.427 | H80: =[1]Production!H19 -> 32261.576 | ... AK80: =[1]Production!AK19 -> 62051.549
A81: =[1]Production!A21 -> y_smet_0 | B81: =[1]Production!B21 -> 80205.786 | C81: =[1]Production!C21 -> 81478.597 | D81: =[1]Production!D21 -> 82835.665 | E81: =[1]Production!E21 -> 84232.809 | F81: =[1]Production!F21 -> 85692.454 | G81: =[1]Production!G21 -> 87221.803 | H81: =[1]Production!H21 -> 88782.593 | ... AK81: =[1]Production!AK21 -> 173835.07
A82: =[1]Production!A23 -> y_sigo_0 | B82: =[1]Production!B23 -> 81062.007 | C82: =[1]Production!C23 -> 82774.904 | D82: =[1]Production!D23 -> 84492.299 | E82: =[1]Production!E23 -> 86215.622 | F82: =[1]Production!F23 -> 87963.547 | G82: =[1]Production!G23 -> 89744.779 | H82: =[1]Production!H23 -> 91539.989 | ... AK82: =[1]Production!AK23 -> 184712.57
A83: =[1]Production!A25 -> y_scgo_0 | B83: =[1]Production!B25 -> 104630.73 | C83: =[1]Production!C25 -> 106133.22 | D83: =[1]Production!D25 -> 107824.58 | E83: =[1]Production!E25 -> 109658.88 | F83: =[1]Production!F25 -> 111606.26 | G83: =[1]Production!G25 -> 113651.99 | H83: =[1]Production!H25 -> 115726.81 | ... AK83: =[1]Production!AK25 -> 221832.65
A84: =[1]Production!A27 -> y_scon_0 | B84: =[1]Production!B27 -> 271138.58 | C84: =[1]Production!C27 -> 274967.02 | D84: =[1]Production!D27 -> 279382.17 | E84: =[1]Production!E27 -> 284317.64 | F84: =[1]Production!F27 -> 289733.67 | G84: =[1]Production!G27 -> 295571.53 | H84: =[1]Production!H27 -> 301626.21 | ... AK84: =[1]Production!AK27 -> 642417.62
A85: =[1]Production!A29 -> y_srai_0 | B85: =[1]Production!B29 -> 6786.9645 | C85: =[1]Production!C29 -> 6873.2953 | D85: =[1]Production!D29 -> 6964.7379 | E85: =[1]Production!E29 -> 7061.1511 | F85: =[1]Production!F29 -> 7163.1549 | G85: =[1]Production!G29 -> 7270.5885 | H85: =[1]Production!H29 -> 7378.3279 | ... AK85: =[1]Production!AK29 -> 12495.967
A86: =[1]Production!A31 -> y_sroa_0 | B86: =[1]Production!B31 -> 78079.916 | C86: =[1]Production!C31 -> 79073.099 | D86: =[1]Production!D31 -> 80125.091 | E86: =[1]Production!E31 -> 81234.266 | F86: =[1]Production!F31 -> 82407.758 | G86: =[1]Production!G31 -> 83643.716 | H86: =[1]Production!H31 -> 84883.193 | ... AK86: =[1]Production!AK31 -> 143758.53
A87: =[1]Production!A33 -> y_swat_0 | B87: =[1]Production!B33 -> 15431.507 | C87: =[1]Production!C33 -> 15775.112 | D87: =[1]Production!D33 -> 16107.435 | E87: =[1]Production!E33 -> 16430.096 | F87: =[1]Production!F33 -> 16755.655 | G87: =[1]Production!G33 -> 17089.178 | H87: =[1]Production!H33 -> 17425.474 | ... AK87: =[1]Production!AK33 -> 34878.104
A88: =[1]Production!A35 -> y_sair_0 | B88: =[1]Production!B35 -> 20625.001 | C88: =[1]Production!C35 -> 20975.099 | D88: =[1]Production!D35 -> 21335.75 | E88: =[1]Production!E35 -> 21687.633 | F88: =[1]Production!F35 -> 22066.981 | G88: =[1]Production!G35 -> 22487.226 | H88: =[1]Production!H35 -> 22933.473 | ... AK88: =[1]Production!AK35 -> 47493.99
A89: =[1]Production!A37 -> y_spri_0 | B89: =[1]Production!B37 -> 2017586.2 | C89: =[1]Production!C37 -> 2046965.7 | D89: =[1]Production!D37 -> 2079754.8 | E89: =[1]Production!E37 -> 2115507.3 | F89: =[1]Production!F37 -> 2153350.3 | G89: =[1]Production!G37 -> 2193016.8 | H89: =[1]Production!H37 -> 2232848.9 | ... AK89: =[1]Production!AK37 -> 4105793.4
A90: =[1]Production!A39 -> y_spub_0 | B90: =[1]Production!B39 -> 540249.27 | C90: =[1]Production!C39 -> 547803.88 | D90: =[1]Production!D39 -> 556077.52 | E90: =[1]Production!E39 -> 564672.23 | F90: =[1]Production!F39 -> 573546.03 | G90: =[1]Production!G39 -> 582683.37 | H90: =[1]Production!H39 -> 591582.26 | ... AK90: =[1]Production!AK39 -> 974512.32
A91: =[1]Production!A41 -> y_smin_0 | B91: =[1]Production!B41 -> 4213.3121 | C91: =[1]Production!C41 -> 4259.8401 | D91: =[1]Production!D41 -> 4309.8684 | E91: =[1]Production!E41 -> 4362.0533 | F91: =[1]Production!F41 -> 4420.7809 | G91: =[1]Production!G41 -> 4485.6903 | H91: =[1]Production!H41 -> 4552.4336 | ... AK91: =[1]Production!AK41 -> 8113.3829
A92: =[1]Production!A43 -> y_soil_0 | B92: =[1]Production!B43 -> 35350.668 | C92: =[1]Production!C43 -> 35534.063 | D92: =[1]Production!D43 -> 35690.151 | E92: =[1]Production!E43 -> 35849.205 | F92: =[1]Production!F43 -> 36100.041 | G92: =[1]Production!G43 -> 36432.024 | H92: =[1]Production!H43 -> 36798.855 | ... AK92: =[1]Production!AK43 -> 56682.054
A93: =[1]Production!A45 -> y_sbfu_0 | B93: =[1]Production!B45 -> 3918.7917 | C93: =[1]Production!C45 -> 3928.3545 | D93: =[1]Production!D45 -> 3933.7011 | E93: =[1]Production!E45 -> 3941.5806 | F93: =[1]Production!F45 -> 3960.5454 | G93: =[1]Production!G45 -> 3989.4071 | H93: =[1]Production!H45 -> 4024.2794 | ... AK93: =[1]Production!AK45 -> 5748.948
A94: =[1]Production!A47 -> y_sgas_0 | B94: =[1]Production!B47 -> 398.3488 | C94: =[1]Production!C47 -> 399.2601 | D94: =[1]Production!D47 -> 400.14934 | E94: =[1]Production!E47 -> 400.5384 | F94: =[1]Production!F47 -> 402.56905 | G94: =[1]Production!G47 -> 405.70842 | H94: =[1]Production!H47 -> 407.68985 | ... AK94: =[1]Production!AK47 -> 587.57678
A95: =[1]Production!A49 -> y_sbga_0 | B95: =[1]Production!B49 -> 559.21765 | C95: =[1]Production!C49 -> 560.49697 | D95: =[1]Production!D49 -> 561.74532 | E95: =[1]Production!E49 -> 562.29151 | F95: =[1]Production!F49 -> 565.14221 | G95: =[1]Production!G49 -> 569.54937 | H95: =[1]Production!H49 -> 572.33098 | ... AK95: =[1]Production!AK49 -> 824.8633
A96: =[1]Production!A51 -> y_senu_0 | B96: =[1]Production!B51 -> 46402.332 | C96: =[1]Production!C51 -> 46941.155 | D96: =[1]Production!D51 -> 47396.593 | E96: =[1]Production!E51 -> 47883.634 | F96: =[1]Production!F51 -> 48288.074 | G96: =[1]Production!G51 -> 48690.218 | H96: =[1]Production!H51 -> 49128.137 | ... AK96: =[1]Production!AK51 -> 76066.061
A97: =[1]Production!A53 -> y_seoi_0 | B97: =[1]Production!B53 -> 924.79196 | C97: =[1]Production!C53 -> 935.53064 | D97: =[1]Production!D53 -> 944.60744 | E97: =[1]Production!E53 -> 954.3141 | F97: =[1]Production!F53 -> 962.37454 | G97: =[1]Production!G53 -> 970.38922 | H97: =[1]Production!H53 -> 979.11686 | ... AK97: =[1]Production!AK53 -> 1515.9859
A98: =[1]Production!A55 -> y_sega_0 | B98: =[1]Production!B55 -> 1343.8781 | C98: =[1]Production!C55 -> 1359.4832 | D98: =[1]Production!D55 -> 1372.6733 | E98: =[1]Production!E55 -> 1386.7787 | F98: =[1]Production!F55 -> 1398.4919 | G98: =[1]Production!G55 -> 1410.1385 | H98: =[1]Production!H55 -> 1422.8213 | ... AK98: =[1]Production!AK55 -> 2202.9822
A99: =[1]Production!A57 -> y_seco_0 | B99: =[1]Production!B57 -> 1220.9208 | C99: =[1]Production!C57 -> 1235.0982 | D99: =[1]Production!D57 -> 1247.0815 | E99: =[1]Production!E57 -> 1259.8963 | F99: =[1]Production!F57 -> 1270.5378 | G99: =[1]Production!G57 -> 1281.1189 | H99: =[1]Production!H57 -> 1292.6412 | ... AK99: =[1]Production!AK57 -> 2001.4218
A100: =[1]Production!A59 -> y_sewi_0 | B100: =[1]Production!B59 -> 2402.7509 | C100: =[1]Production!C59 -> 2430.6479 | D100: =[1]Production!D59 -> 2454.2308 | E100: =[1]Production!E59 -> 2479.4501 | F100: =[1]Production!F59 -> 2500.3923 | G100: =[1]Production!G59 -> 2521.2157 | H100: =[1]Production!H59 -> 2543.8914 | ... AK100: =[1]Production!AK59 -> 3938.7571
A101: =[1]Production!A61 -> y_seso_0 | B101: =[1]Production!B61 -> 873.49172 | C101: =[1]Production!C61 -> 883.63471 | D101: =[1]Production!D61 -> 892.208 | E101: =[1]Production!E61 -> 901.37621 | F101: =[1]Production!F61 -> 908.98952 | G101: =[1]Production!G61 -> 916.55961 | H101: =[1]Production!H61 -> 924.80311 | ... AK101: =[1]Production!AK61 -> 1431.8909
A102: =[1]Production!A63 -> y_sehy_0 | B102: =[1]Production!B63 -> 6724.2714 | C102: =[1]Production!C63 -> 6802.3537 | D102: =[1]Production!D63 -> 6868.3522 | E102: =[1]Production!E63 -> 6938.9305 | F102: =[1]Production!F63 -> 6997.5388 | G102: =[1]Production!G63 -> 7055.8145 | H102: =[1]Production!H63 -> 7119.2743 | ... AK102: =[1]Production!AK63 -> 11022.913
A103: =[1]Production!A65 -> y_sech_0 | B103: =[1]Production!B65 -> 7911.8534 | C103: =[1]Production!C65 -> 7995.6778 | D103: =[1]Production!D65 -> 8071.2286 | E103: =[1]Production!E65 -> 8147.802 | F103: =[1]Production!F65 -> 8216.621 | G103: =[1]Production!G65 -> 8289.4713 | H103: =[1]Production!H65 -> 8358.6275 | ... AK103: =[1]Production!AK65 -> 11744.282
A104: =[1]Production!A67 -> y_seot_0 | B104: =[1]Production!B67 -> 109.8413 | C104: =[1]Production!C67 -> 111.11678 | D104: =[1]Production!D67 -> 112.19487 | E104: =[1]Production!E67 -> 113.34777 | F104: =[1]Production!F67 -> 114.30514 | G104: =[1]Production!G67 -> 115.25707 | H104: =[1]Production!H67 -> 116.29369 | ... AK104: =[1]Production!AK67 -> 180.05981
A105: =[1]Results!E28 -> AUTO_0 | B105: =[1]Results!F28 -> 32317.941 | C105: =[1]Results!G28 -> 31911.217 | D105: =[1]Results!H28 -> 31732.935 | E105: =[1]Results!I28 -> 31702.286 | F105: =[1]Results!J28 -> 31792.126 | G105: =[1]Results!K28 -> 31964.155 | H105: =[1]Results!L28 -> 32173.16 | ... AK105: =[1]Results!AO28 -> 42106.337
A106: =[1]Results!E29 -> AUTO_cfut_0 | B106: =[1]Results!F29 -> 32271.24 | C106: =[1]Results!G29 -> 31846.407 | D106: =[1]Results!H29 -> 31648.242 | E106: =[1]Results!I29 -> 31596.228 | F106: =[1]Results!J29 -> 31663.113 | G106: =[1]Results!K29 -> 31810.955 | H106: =[1]Results!L29 -> 31994.923 | ... AK106: =[1]Results!AO29 -> 39079.453
A107: =[1]Results!E37 -> AUTO_cele_0 | B107: =[1]Results!F37 -> 44.765 | C107: =[1]Results!G37 -> 62.819188 | D107: =[1]Results!H37 -> 82.635226 | E107: =[1]Results!I37 -> 103.92645 | F107: =[1]Results!J37 -> 126.8031 | G107: =[1]Results!K37 -> 150.90795 | H107: =[1]Results!L37 -> 175.86538 | ... AK107: =[1]Results!AO37 -> 3023.0184
A108: =[1]Results!E45 -> AUTO_cgas_0 | B108: =[1]Results!F45 -> 1.936 | C108: =[1]Results!G45 -> 1.990293 | D108: =[1]Results!H45 -> 2.0574577 | E108: =[1]Results!I45 -> 2.1314073 | F108: =[1]Results!J45 -> 2.2103839 | G108: =[1]Results!K45 -> 2.2916631 | H108: =[1]Results!L45 -> 2.3718638 | ... AK108: =[1]Results!AO45 -> 3.8659259
A109: =[2]Données!B362 -> AUTO_CA_0 | B109: =[2]Données!C362 -> 7105.969 | C109: =[2]Données!D362 -> 7152.3093 | D109: =[2]Données!E362 -> 7255.4507 | E109: =[2]Données!F362 -> 7394.3019 | F109: =[2]Données!G362 -> 7562.4358 | G109: =[2]Données!H362 -> 7749.3584 | H109: =[2]Données!I362 -> 7942.5645 | ... AK109: =[2]Données!AL362 -> 13865.747
A110: =[2]Données!B363 -> AUTO_CB_0 | B110: =[2]Données!C363 -> 8263.1971 | C110: =[2]Données!D363 -> 8194.9442 | D110: =[2]Données!E363 -> 8188.9422 | E110: =[2]Données!F363 -> 8224.0385 | F110: =[2]Données!G363 -> 8293.3352 | G110: =[2]Données!H363 -> 8386.3478 | H110: =[2]Données!I363 -> 8490.6138 | ... AK110: =[2]Données!AL363 -> 12735.052
A111: =[2]Données!B364 -> AUTO_CC_0 | B111: =[2]Données!C364 -> 6787.4106 | C111: =[2]Données!D364 -> 6656.6716 | D111: =[2]Données!E364 -> 6574.7958 | E111: =[2]Données!F364 -> 6526.4877 | F111: =[2]Données!G364 -> 6506.4446 | G111: =[2]Données!H364 -> 6507.1004 | H111: =[2]Données!I364 -> 6519.4906 | ... AK111: =[2]Données!AL364 -> 8452.2874
A112: =[2]Données!B365 -> AUTO_CD_0 | B112: =[2]Données!C365 -> 4165.6835 | C112: =[2]Données!D365 -> 4060.838 | D112: =[2]Données!E365 -> 3984.0057 | E112: =[2]Données!F365 -> 3926.2141 | F112: =[2]Données!G365 -> 3884.1704 | G112: =[2]Données!H365 -> 3853.5994 | H112: =[2]Données!I365 -> 3829.4916 | ... AK112: =[2]Données!AL365 -> 3844.272
A113: =[2]Données!B366 -> AUTO_CE_0 | B113: =[2]Données!C366 -> 2507.3525 | C113: =[2]Données!D366 -> 2446.6033 | D113: =[2]Données!E366 -> 2401.9268 | E113: =[2]Données!F366 -> 2367.677 | F113: =[2]Données!G366 -> 2341.7745 | G113: =[2]Données!H366 -> 2321.6754 | H113: =[2]Données!I366 -> 2304.3963 | ... AK113: =[2]Données!AL366 -> 1979.4773
A114: =[2]Données!B367 -> AUTO_CF_0 | B114: =[2]Données!C367 -> 1245.4666 | C114: =[2]Données!D367 -> 1212.6424 | D114: =[2]Données!E367 -> 1186.4603 | E114: =[2]Données!F367 -> 1163.9737 | F114: =[2]Données!G367 -> 1144.0787 | G114: =[2]Données!H367 -> 1125.642 | H114: =[2]Données!I367 -> 1107.3792 | ... AK114: =[2]Données!AL367 -> 549.42749
A115: =[2]Données!B368 -> AUTO_CG_0 | B115: =[2]Données!C368 -> 2242.8617 | C115: =[2]Données!D368 -> 2187.2078 | D115: =[2]Données!E368 -> 2141.3531 | E115: =[2]Données!F368 -> 2099.5926 | F115: =[2]Données!G368 -> 2059.8869 | G115: =[2]Données!H368 -> 2020.4312 | H115: =[2]Données!I368 -> 1979.224 | ... AK115: =[2]Données!AL368 -> 680.07399
A116: =[1]Results!E111 -> BUIL_0 | B116: =[1]Results!F111 -> 2457.4699 | C116: =[1]Results!G111 -> 2465.7264 | D116: =[1]Results!H111 -> 2476.5081 | E116: =[1]Results!I111 -> 2487.337 | F116: =[1]Results!J111 -> 2498.2132 | G116: =[1]Results!K111 -> 2509.137 | H116: =[1]Results!L111 -> 2517.7068 | ... AK116: =[1]Results!AO111 -> 2738.7438
A117: =[1]Results!E112 -> BUIL_ca_0 | B117: =[1]Results!F112 -> 3.4765421 | C117: =[1]Results!G112 -> 8.5373482 | D117: =[1]Results!H112 -> 14.692051 | E117: =[1]Results!I112 -> 21.391993 | F117: =[1]Results!J112 -> 28.503845 | G117: =[1]Results!K112 -> 35.432174 | H117: =[1]Results!L112 -> 42.026715 | ... AK117: =[1]Results!AO112 -> 209.32763
A118: =[1]Results!E113 -> BUIL_cb_0 | B118: =[1]Results!F113 -> 68.804763 | C118: =[1]Results!G113 -> 75.130067 | D118: =[1]Results!H113 -> 80.746061 | E118: =[1]Results!I113 -> 85.701618 | F118: =[1]Results!J113 -> 90.337252 | G118: =[1]Results!K113 -> 94.778736 | H118: =[1]Results!L113 -> 98.504765 | ... AK118: =[1]Results!AO113 -> 197.93084
A119: =[1]Results!E114 -> BUIL_cc_0 | B119: =[1]Results!F114 -> 408.2804 | C119: =[1]Results!G114 -> 422.13434 | D119: =[1]Results!H114 -> 435.39237 | E119: =[1]Results!I114 -> 447.44191 | F119: =[1]Results!J114 -> 458.88957 | G119: =[1]Results!K114 -> 469.9427 | H119: =[1]Results!L114 -> 479.05933 | ... AK119: =[1]Results!AO114 -> 715.59327
A120: =[1]Results!E115 -> BUIL_cd_0 | B120: =[1]Results!F115 -> 954.38156 | C120: =[1]Results!G115 -> 951.24267 | D120: =[1]Results!H115 -> 950.15263 | E120: =[1]Results!I115 -> 950.18991 | F120: =[1]Results!J115 -> 950.96815 | G120: =[1]Results!K115 -> 951.42001 | H120: =[1]Results!L115 -> 951.28783 | ... AK120: =[1]Results!AO115 -> 877.47906
A121: =[1]Results!E116 -> BUIL_ce_0 | B121: =[1]Results!F116 -> 878.8 | C121: =[1]Results!G116 -> 866.98909 | D121: =[1]Results!H116 -> 855.83698 | E121: =[1]Results!I116 -> 844.89794 | F121: =[1]Results!J116 -> 833.74053 | G121: =[1]Results!K116 -> 823.70474 | H121: =[1]Results!L116 -> 814.85593 | ... AK121: =[1]Results!AO116 -> 648.79755
A122: =[1]Results!E117 -> BUIL_cf_0 | B122: =[1]Results!F117 -> 139.85209 | C122: =[1]Results!G117 -> 137.9677 | D122: =[1]Results!H117 -> 136.10652 | E122: =[1]Results!I117 -> 134.27017 | F122: =[1]Results!J117 -> 132.46281 | G122: =[1]Results!K117 -> 130.67505 | H122: =[1]Results!L117 -> 128.91107 | ... AK122: =[1]Results!AO117 -> 88.559021
A123: =[1]Results!E118 -> BUIL_cg_0 | B123: =[1]Results!F118 -> 3.8745671 | C123: =[1]Results!G118 -> 3.7251598 | D123: =[1]Results!H118 -> 3.5815059 | E123: =[1]Results!I118 -> 3.4434436 | F123: =[1]Results!J118 -> 3.3110557 | G123: =[1]Results!K118 -> 3.1835898 | H123: =[1]Results!L118 -> 3.0611505 | ... AK123: =[1]Results!AO118 -> 1.0564346
A124: =[1]Results!E241 -> YG_toe_0 | B124: =[1]Results!F241 -> 148.56082 | C124: =[1]Results!G241 -> 149.66963 | D124: =[1]Results!H241 -> 150.66914 | E124: =[1]Results!I241 -> 151.72016 | F124: =[1]Results!J241 -> 152.92185 | G124: =[1]Results!K241 -> 154.31153 | H124: =[1]Results!L241 -> 155.81162 | ... AK124: =[1]Results!AO241 -> 238.10205
A125: =[1]Results!E281 -> CF_toe_2 | B125: =[1]Results!F281 -> 161.69428 | C125: =[1]Results!G281 -> 162.00032 | D125: =[1]Results!H281 -> 162.18906 | E125: =[1]Results!I281 -> 162.30169 | F125: =[1]Results!J281 -> 162.93754 | G125: =[1]Results!K281 -> 164.00585 | H125: =[1]Results!L281 -> 165.3825 | ... AK125: =[1]Results!AO281 -> 236.28394

Sheet Orderly
B1: 42005 | C1: 42370 | D1: 42736 | E1: 43101 | F1: 43466 | G1: 43831 | H1: 44197 | I1: 44562 | J1: 44927 | K1: 45292 | L1: 45658 | M1: 46023 | N1: 46388 | O1: 46753 | P1: 47119 | Q1: 47484 | R1: 47849 | S1: 48214 | T1: 48580 | U1: 48945 | V1: 49310 | W1: 49675 | X1: 50041 | Y1: 50406 | Z1: 50771 | AA1: 51136 | AB1: 51502 | AC1: 51867 | AD1: 52232 | AE1: 52597 | AF1: 52963 | AG1: 53328 | AH1: 53693 | AI1: 54058 | AJ1: 54424 | AK1: 54789
A2: =[1]Macro!A47 -> gdp_2 | B2: =[1]Macro!B47 -> 2197953 | C2: =[1]Macro!C47 -> 2230476.4 | D2: =[1]Macro!D47 -> 2266147.4 | E2: =[1]Macro!E47 -> 2304476.7 | F2: =[1]Macro!F47 -> 2344700.1 | G2: =[1]Macro!G47 -> 2386655 | H2: =[1]Macro!H47 -> 2429108.1 | ... AK2: =[1]Macro!AK47 -> 4517957.1
A3: =[1]Results!E1600 -> IA_2 | B3: =[1]Results!F1600 -> 472737.8 | C3: =[1]Results!G1600 -> 479640.45 | D3: =[1]Results!H1600 -> 487700.59 | E3: =[1]Results!I1600 -> 496636.8 | F3: =[1]Results!J1600 -> 506358.69 | G3: =[1]Results!K1600 -> 516731.29 | H3: =[1]Results!L1600 -> 527542.26 | ... AK3: =[1]Results!AO1600 -> 1278323
A4: =[1]Results!E1702 -> CH_2 | B4: =[1]Results!F1702 -> 1202789 | C4: =[1]Results!G1702 -> 1220397.5 | D4: =[1]Results!H1702 -> 1240919.3 | E4: =[1]Results!I1702 -> 1263569.8 | F4: =[1]Results!J1702 -> 1287361.8 | G4: =[1]Results!K1702 -> 1311977.1 | H4: =[1]Results!L1702 -> 1336547.3 | ... AK4: =[1]Results!AO1702 -> 2416198
A5: =[1]Export!A2 -> x_2 | B5: =[1]Export!B2 -> 631198.05 | C5: =[1]Export!C2 -> 645659.12 | D5: =[1]Export!D2 -> 659829.13 | E5: =[1]Export!E2 -> 673817.85 | F5: =[1]Export!F2 -> 687886.09 | G5: =[1]Export!G2 -> 702162.43 | H5: =[1]Export!H2 -> 716701.79 | ... AK5: =[1]Export!AK2 -> 1398524
A6: =[1]Import!A2 -> m_2 | B6: =[1]Import!B2 -> 655146.23 | C6: =[1]Import!C2 -> 664463.74 | D6: =[1]Import!D2 -> 675963.41 | E6: =[1]Import!E2 -> 688489.73 | F6: =[1]Import!F2 -> 701879.78 | G6: =[1]Import!G2 -> 715851.24 | H6: =[1]Import!H2 -> 730019.19 | ... AK6: =[1]Import!AK2 -> 1489131.4
A7: =[1]Macro!A51 -> bal_g_tot_val_2 | B7: =[1]Macro!B51 -> -65724.458 | C7: =[1]Macro!C51 -> -68542.988 | D7: =[1]Macro!D51 -> -66434.789 | E7: =[1]Macro!E51 -> -63456.443 | F7: =[1]Macro!F51 -> -60105.648 | G7: =[1]Macro!G51 -> -53781.563 | H7: =[1]Macro!H51 -> -46448.662 | ... AK7: =[1]Macro!AK51 -> 1063387.2
A8: =[1]Macro!A52 -> debt_g_val_2 | B8: =[1]Macro!B52 -> 2105265.8 | C8: =[1]Macro!C52 -> 2173808.8 | D8: =[1]Macro!D52 -> 2240243.6 | E8: =[1]Macro!E52 -> 2303700 | F8: =[1]Macro!F52 -> 2363805.7 | G8: =[1]Macro!G52 -> 2417587.2 | H8: =[1]Macro!H52 -> 2464035.9 | ... AK8: =[1]Macro!AK52 -> -4724207.2
A9: =[1]Macro!A91 -> bal_g_prim_val_2 | B9: =[1]Macro!B91 -> -21358.417 | C9: =[1]Macro!C91 -> -20676.422 | D9: =[1]Macro!D91 -> -19223.797 | E9: =[1]Macro!E91 -> -16334.445 | F9: =[1]Macro!F91 -> -11655.008 | G9: =[1]Macro!G91 -> -6167.4622 | H9: =[1]Macro!H91 -> 901.00115 | ... AK9: =[1]Macro!AK91 -> 975742.2
A10: =[1]Macro!A92 -> ener_bill_2 | B10: =[1]Macro!B92 -> 28684.77 | C10: =[1]Macro!C92 -> 29034.892 | D10: =[1]Macro!D92 -> 29339.235 | E10: =[1]Macro!E92 -> 29587.101 | F10: =[1]Macro!F92 -> 30059.54 | G10: =[1]Macro!G92 -> 30716.5 | H10: =[1]Macro!H92 -> 31824.967 | ... AK10: =[1]Macro!AK92 -> 26311.515
A11: =[1]Macro!A93 -> bal_trade_val_2 | B11: =[1]Macro!B93 -> -23361.949 | C11: =[1]Macro!C93 -> -14334.785 | D11: =[1]Macro!D93 -> -7730.3659 | E11: =[1]Macro!E93 -> -1774.1391 | F11: =[1]Macro!F93 -> 3079.9969 | G11: =[1]Macro!G93 -> 7509.9025 | H11: =[1]Macro!H93 -> 11845.058 | ... AK11: =[1]Macro!AK93 -> 398488.97
A12: =[1]Macro!A94 -> unr_2 | B12: =[1]Macro!B94 -> 0.14242623 | C12: =[1]Macro!C94 -> 0.14261844 | D12: =[1]Macro!D94 -> 0.14265441 | E12: =[1]Macro!E94 -> 0.14186411 | F12: =[1]Macro!F94 -> 0.14058843 | G12: =[1]Macro!G94 -> 0.1389887 | H12: =[1]Macro!H94 -> 0.13668008 | ... AK12: =[1]Macro!AK94 -> 0.013801406
A13: =[1]Macro!A53 -> pch_2 | B13: =[1]Macro!B53 -> 1.0019287 | C13: =[1]Macro!C53 -> 1.0209119 | D13: =[1]Macro!D53 -> 1.0398984 | E13: =[1]Macro!E53 -> 1.0599435 | F13: =[1]Macro!F53 -> 1.078494 | G13: =[1]Macro!G53 -> 1.0971251 | H13: =[1]Macro!H53 -> 1.1160388 | ... AK13: =[1]Macro!AK53 -> 1.9819788
A14: =[1]Macro!A54 -> pgdp_2 | B14: =[1]Macro!B54 -> 1.0015748 | C14: =[1]Macro!C54 -> 1.0222259 | D14: =[1]Macro!D54 -> 1.0427743 | E14: =[1]Macro!E54 -> 1.06443 | F14: =[1]Macro!F54 -> 1.0850099 | G14: =[1]Macro!G54 -> 1.1056596 | H14: =[1]Macro!H54 -> 1.1264998 | ... AK14: =[1]Macro!AK54 -> 2.1535227
A15: =[1]Macro!A55 -> py_2 | B15: =[1]Macro!B55 -> 1.0006765 | C15: =[1]Macro!C55 -> 1.0200906 | D15: =[1]Macro!D55 -> 1.0394175 | E15: =[1]Macro!E55 -> 1.0594942 | F15: =[1]Macro!F55 -> 1.079276 | G15: =[1]Macro!G55 -> 1.0991176 | H15: =[1]Macro!H55 -> 1.1192759 | ... AK15: =[1]Macro!AK55 -> 2.0871764
A16: =[1]Macro!A56 -> pm_2 | B16: =[1]Macro!B56 -> 1 | C16: =[1]Macro!C56 -> 1.0126187 | D16: =[1]Macro!D56 -> 1.0253847 | E16: =[1]Macro!E56 -> 1.038296 | F16: =[1]Macro!F56 -> 1.0513623 | G16: =[1]Macro!G56 -> 1.0645895 | H16: =[1]Macro!H56 -> 1.078541 | ... AK16: =[1]Macro!AK56 -> 1.6169305
A17: =[1]Macro!A57 -> pi_2 | B17: =[1]Macro!B57 -> 1.0011136 | C17: =[1]Macro!C57 -> 1.0191048 | D17: =[1]Macro!D57 -> 1.0367895 | E17: =[1]Macro!E57 -> 1.0555264 | F17: =[1]Macro!F57 -> 1.0738987 | G17: =[1]Macro!G57 -> 1.0925687 | H17: =[1]Macro!H57 -> 1.1118314 | ... AK17: =[1]Macro!AK57 -> 2.0877229
A18: =[1]Macro!A58 -> px_2 | B18: =[1]Macro!B58 -> 1.0009288 | C18: =[1]Macro!C58 -> 1.0199092 | D18: =[1]Macro!D58 -> 1.038742 | E18: =[1]Macro!E58 -> 1.0582712 | F18: =[1]Macro!F58 -> 1.0772277 | G18: =[1]Macro!G58 -> 1.0960393 | H18: =[1]Macro!H58 -> 1.1151091 | ... AK18: =[1]Macro!AK58 -> 2.0066234
A19: =[1]Macro!A59 -> cu_2 | B19: =[1]Macro!B59 -> 0.99335227 | C19: =[1]Macro!C59 -> 1.0104374 | D19: =[1]Macro!D59 -> 1.0279936 | E19: =[1]Macro!E59 -> 1.046912 | F19: =[1]Macro!F59 -> 1.0647773 | G19: =[1]Macro!G59 -> 1.083175 | H19: =[1]Macro!H59 -> 1.102419 | ... AK19: =[1]Macro!AK59 -> 2.1028333
A20: =[1]Macro!A60 -> f_l_2 | B20: =[1]Macro!B60 -> 27379.148 | C20: =[1]Macro!C60 -> 27463.028 | D20: =[1]Macro!D60 -> 27580.776 | E20: =[1]Macro!E60 -> 27730.779 | F20: =[1]Macro!F60 -> 27902.628 | G20: =[1]Macro!G60 -> 28090.563 | H20: =[1]Macro!H60 -> 28282.274 | ... AK20: =[1]Macro!AK60 -> 36776.975
A21: =[1]Macro!A61 -> f_k_2 | B21: =[1]Macro!B61 -> 5223867.2 | C21: =[1]Macro!C61 -> 5285598.3 | D21: =[1]Macro!D61 -> 5350451 | E21: =[1]Macro!E61 -> 5419051.7 | F21: =[1]Macro!F61 -> 5491886.3 | G21: =[1]Macro!G61 -> 5569266.7 | H21: =[1]Macro!H61 -> 5651267.6 | ... AK21: =[1]Macro!AK61 -> 11308943
A22: =[1]Macro!A62 -> f_e_2 | B22: =[1]Macro!B62 -> 128715.09 | C22: =[1]Macro!C62 -> 129845.11 | D22: =[1]Macro!D62 -> 130908.4 | E22: =[1]Macro!E62 -> 131946.02 | F22: =[1]Macro!F62 -> 133196.59 | G22: =[1]Macro!G62 -> 134698.61 | H22: =[1]Macro!H62 -> 136399.87 | ... AK22: =[1]Macro!AK62 -> 705067.95
A23: =[1]Macro!A63 -> f_mat_2 | B23: =[1]Macro!B63 -> 1758477.5 | C23: =[1]Macro!C63 -> 1784507.9 | D23: =[1]Macro!D63 -> 1813592.5 | E23: =[1]Macro!E63 -> 1844865 | F23: =[1]Macro!F63 -> 1877854 | G23: =[1]Macro!G63 -> 1912361.4 | H23: =[1]Macro!H63 -> 1947622.2 | ... AK23: =[1]Macro!AK63 -> 3834440.5
A24: =[1]Macro!A64 -> w_2 | B24: =[1]Macro!B64 -> 41.206115 | C24: =[1]Macro!C64 -> 42.474185 | D24: =[1]Macro!D64 -> 43.782653 | E24: =[1]Macro!E64 -> 45.126543 | F24: =[1]Macro!F64 -> 46.518731 | G24: =[1]Macro!G64 -> 47.94126 | H24: =[1]Macro!H64 -> 49.399442 | ... AK24: =[1]Macro!AK64 -> 137.17285
... A28: =[1]Macro!A68 -> c_mat_2 | B28: =[1]Macro!B68 -> 1.0004669 | C28: =[1]Macro!C68 -> 1.0184736 | D28: =[1]Macro!D68 -> 1.0364266 | E28: =[1]Macro!E68 -> 1.0549734 | F28: =[1]Macro!F68 -> 1.0733596 | G28: =[1]Macro!G68 -> 1.0918361 | H28: =[1]Macro!H68 -> 1.1105362 | ... AK28: =[1]Macro!AK68 -> 1.975243
A29: =[1]Results!E1513 -> VA_agrf_2 | B29: =[1]Results!F1513 -> 36098.159 | C29: =[1]Results!G1513 -> 36421.501 | D29: =[1]Results!H1513 -> 36813.129 | E29: =[1]Results!I1513 -> 37266.283 | F29: =[1]Results!J1513 -> 37780.952 | G29: =[1]Results!K1513 -> 38345.706 | H29: =[1]Results!L1513 -> 38939.771 | ... AK29: =[1]Results!AO1513 -> 68235.331
A30: =[1]Results!E1514 -> VA_sagr_2 | B30: =[1]Results!F1514 -> 30808.957 | C30: =[1]Results!G1514 -> 31184.966 | D30: =[1]Results!H1514 -> 31625.026 | E30: =[1]Results!I1514 -> 32127.895 | F30: =[1]Results!J1514 -> 32667.725 | G30: =[1]Results!K1514 -> 33243.213 | H30: =[1]Results!L1514 -> 33839.747 | ... AK30: =[1]Results!AO1514 -> 62585.006
A31: =[1]Results!E1515 -> VA_sfor_2 | B31: =[1]Results!F1515 -> 5289.202 | C31: =[1]Results!G1515 -> 5236.5354 | D31: =[1]Results!H1515 -> 5188.1023 | E31: =[1]Results!I1515 -> 5138.3884 | F31: =[1]Results!J1515 -> 5113.2264 | G31: =[1]Results!K1515 -> 5102.4936 | H31: =[1]Results!L1515 -> 5100.0235 | ... AK31: =[1]Results!AO1515 -> 5650.3249
A32: =[1]Results!E1516 -> VA_ind_2 | B32: =[1]Results!F1516 -> 331692.74 | C32: =[1]Results!G1516 -> 337438.2 | D32: =[1]Results!H1516 -> 343505.96 | E32: =[1]Results!I1516 -> 349929.82 | F32: =[1]Results!J1516 -> 356653.64 | G32: =[1]Results!K1516 -> 363647.64 | H32: =[1]Results!L1516 -> 370795.68 | ... AK32: =[1]Results!AO1516 -> 796063.71
A33: =[1]Results!E1517 -> VA_sfoo_2 | B33: =[1]Results!F1517 -> 43690.453 | C33: =[1]Results!G1517 -> 44313.022 | D33: =[1]Results!H1517 -> 45008.475 | E33: =[1]Results!I1517 -> 45790.966 | F33: =[1]Results!J1517 -> 46614.025 | G33: =[1]Results!K1517 -> 47479.998 | H33: =[1]Results!L1517 -> 48363.635 | ... AK33: =[1]Results!AO1517 -> 89705.323
A34: =[1]Results!E1518 -> VA_sveh_2 | B34: =[1]Results!F1518 -> 29848.047 | C34: =[1]Results!G1518 -> 30681.863 | D34: =[1]Results!H1518 -> 31486.643 | E34: =[1]Results!I1518 -> 32239.342 | F34: =[1]Results!J1518 -> 32983.67 | G34: =[1]Results!K1518 -> 33705.808 | H34: =[1]Results!L1518 -> 34399.173 | ... AK34: =[1]Results!AO1518 -> 64898.172
A35: =[1]Results!E1519 -> VA_sgla_2 | B35: =[1]Results!F1519 -> 7904.2817 | C35: =[1]Results!G1519 -> 8022.9587 | D35: =[1]Results!H1519 -> 8150.4235 | E35: =[1]Results!I1519 -> 8285.942 | F35: =[1]Results!J1519 -> 8429.9887 | G35: =[1]Results!K1519 -> 8583.1305 | H35: =[1]Results!L1519 -> 8742.7436 | ... AK35: =[1]Results!AO1519 -> 17833.69
A36: =[1]Results!E1520 -> VA_spap_2 | B36: =[1]Results!F1520 -> 4277.9101 | C36: =[1]Results!G1520 -> 4348.1288 | D36: =[1]Results!H1520 -> 4420.0588 | E36: =[1]Results!I1520 -> 4496.2852 | F36: =[1]Results!J1520 -> 4575.3695 | G36: =[1]Results!K1520 -> 4657.5485 | H36: =[1]Results!L1520 -> 4741.3756 | ... AK36: =[1]Results!AO1520 -> 8860.573
A37: =[1]Results!E1521 -> VA_sche_2 | B37: =[1]Results!F1521 -> 26174.001 | C37: =[1]Results!G1521 -> 26647.117 | D37: =[1]Results!H1521 -> 27106.822 | E37: =[1]Results!I1521 -> 27579.385 | F37: =[1]Results!J1521 -> 28069.008 | G37: =[1]Results!K1521 -> 28578.174 | H37: =[1]Results!L1521 -> 29100.407 | ... AK37: =[1]Results!AO1521 -> 53287.483
A38: =[1]Results!E1522 -> VA_spla_2 | B38: =[1]Results!F1522 -> 11103.246 | C38: =[1]Results!G1522 -> 11296.887 | D38: =[1]Results!H1522 -> 11493.862 | E38: =[1]Results!I1522 -> 11697.826 | F38: =[1]Results!J1522 -> 11908.623 | G38: =[1]Results!K1522 -> 12126.487 | H38: =[1]Results!L1522 -> 12349.12 | ... AK38: =[1]Results!AO1522 -> 23826.608
A39: =[1]Results!E1523 -> VA_smet_2 | B39: =[1]Results!F1523 -> 24632.932 | C39: =[1]Results!G1523 -> 25066.115 | D39: =[1]Results!H1523 -> 25507.094 | E39: =[1]Results!I1523 -> 25959.82 | F39: =[1]Results!J1523 -> 26427.307 | G39: =[1]Results!K1523 -> 26911.267 | H39: =[1]Results!L1523 -> 27407.709 | ... AK39: =[1]Results!AO1523 -> 52035.279
A40: =[1]Results!E1524 -> VA_sigo_2 | B40: =[1]Results!F1524 -> 30238.345 | C40: =[1]Results!G1524 -> 30922.967 | D40: =[1]Results!H1524 -> 31563.983 | E40: =[1]Results!I1524 -> 32207.175 | F40: =[1]Results!J1524 -> 32862.536 | G40: =[1]Results!K1524 -> 33531.396 | H40: =[1]Results!L1524 -> 34210.86 | ... AK40: =[1]Results!AO1524 -> 70053.389
... A66: =[1]Results!E1550 -> VA_seot_2 | B66: =[1]Results!F1550 -> -1482.5662 | C66: =[1]Results!G1550 -> -1500.0569 | D66: =[1]Results!H1550 -> -1514.9428 | E66: =[1]Results!I1550 -> -1530.5361 | F66: =[1]Results!J1550 -> -1543.7595 | G66: =[1]Results!K1550 -> -1556.626 | H66: =[1]Results!L1550 -> -1570.0078 | ... AK66: =[1]Results!AO1550 -> -3742.7262
A67: =[1]Emissions!A825 -> ems_co2_2 | B67: =[1]Emissions!B825 -> 348.01866 | C67: =[1]Emissions!C825 -> 347.13002 | D67: =[1]Emissions!D825 -> 345.96062 | E67: =[1]Emissions!E825 -> 344.35913 | F67: =[1]Emissions!F825 -> 344.57749 | G67: =[1]Emissions!G825 -> 346.16875 | H67: =[1]Emissions!H825 -> 348.70131 | ... AK67: =[1]Emissions!AK825 -> 143.5138
A68: =[1]Emissions!A826 -> ems_ci_co2_2 | B68: =[1]Emissions!B826 -> 213.27376 | C68: =[1]Emissions!C826 -> 213.295 | D68: =[1]Emissions!D826 -> 213.13966 | E68: =[1]Emissions!E826 -> 212.50912 | F68: =[1]Emissions!F826 -> 213.04679 | G68: =[1]Emissions!G826 -> 214.54739 | H68: =[1]Emissions!H826 -> 216.75806 | ... AK68: =[1]Emissions!AK826 -> 97.303405
A69: =[1]Emissions!A827 -> ems_y_co2_2 | B69: =[1]Emissions!B827 -> 0.027534944 | C69: =[1]Emissions!C827 -> 0.027853944 | D69: =[1]Emissions!D827 -> 0.028219876 | E69: =[1]Emissions!E827 -> 0.028637518 | F69: =[1]Emissions!F827 -> 0.029095659 | G69: =[1]Emissions!G827 -> 0.029591995 | H69: =[1]Emissions!H827 -> 0.030113441 | ... AK69: =[1]Emissions!AK827 -> 0.055493663
A70: =[1]Emissions!A828 -> ems_mat_co2_2 | B70: =[1]Emissions!B828 -> 15.226879 | C70: =[1]Emissions!C828 -> 15.432255 | D70: =[1]Emissions!D828 -> 15.657793 | E70: =[1]Emissions!E828 -> 15.895768 | F70: =[1]Emissions!F828 -> 16.150067 | G70: =[1]Emissions!G828 -> 16.42237 | H70: =[1]Emissions!H828 -> 16.706308 | ... AK70: =[1]Emissions!AK828 -> 31.554238
A71: =[1]Emissions!A829 -> ems_ch_co2_2 | B71: =[1]Emissions!B829 -> 119.49049 | C71: =[1]Emissions!C829 -> 118.37491 | D71: =[1]Emissions!D829 -> 117.13494 | E71: =[1]Emissions!E829 -> 115.92561 | F71: =[1]Emissions!F829 -> 115.35154 | G71: =[1]Emissions!G829 -> 115.1694 | H71: =[1]Emissions!H829 -> 115.20683 | ... AK71: =[1]Emissions!AK829 -> 14.600668
A72: =[1]Production!A2 -> y_2 | B72: =[1]Production!B2 -> 3854147.4 | C72: =[1]Production!C2 -> 3910661.1 | D72: =[1]Production!D2 -> 3972850.3 | E72: =[1]Production!E2 -> 4039546.5 | F72: =[1]Production!F2 -> 4109788.5 | G72: =[1]Production!G2 -> 4183314.3 | H72: =[1]Production!H2 -> 4258224.3 | ... AK72: =[1]Production!AK2 -> 8559645.5
A73: =[1]Production!A4 -> y_sagr_2 | B73: =[1]Production!B4 -> 81750.877 | C73: =[1]Production!C4 -> 82697.982 | D73: =[1]Production!D4 -> 83784.429 | E73: =[1]Production!E4 -> 85024.403 | F73: =[1]Production!F4 -> 86384.617 | G73: =[1]Production!G4 -> 87858.233 | H73: =[1]Production!H4 -> 89406.399 | ... AK73: =[1]Production!AK4 -> 164759.93
A74: =[1]Production!A6 -> y_sfor_2 | B74: =[1]Production!B6 -> 6533.6203 | C74: =[1]Production!C6 -> 6469.9469 | D74: =[1]Production!D6 -> 6408.2174 | E74: =[1]Production!E6 -> 6344.6002 | F74: =[1]Production!F6 -> 6311.2776 | G74: =[1]Production!G6 -> 6296.6029 | H74: =[1]Production!H6 -> 6292.7253 | ... AK74: =[1]Production!AK6 -> 6951.0511
A75: =[1]Production!A8 -> y_sfoo_2 | B75: =[1]Production!B8 -> 157700.04 | C75: =[1]Production!C8 -> 159810.09 | D75: =[1]Production!D8 -> 162170.83 | E75: =[1]Production!E8 -> 164824.62 | F75: =[1]Production!F8 -> 167674.97 | G75: =[1]Production!G8 -> 170710.62 | H75: =[1]Production!H8 -> 173851.1 | ... AK75: =[1]Production!AK8 -> 319427.34
A76: =[1]Production!A10 -> y_sveh_2 | B76: =[1]Production!B10 -> 125571.2 | C76: =[1]Production!C10 -> 128565.38 | D76: =[1]Production!D10 -> 131819.14 | E76: =[1]Production!E10 -> 134958.35 | F76: =[1]Production!F10 -> 138028.96 | G76: =[1]Production!G10 -> 141004.01 | H76: =[1]Production!H10 -> 143868.31 | ... AK76: =[1]Production!AK10 -> 267710.5
A77: =[1]Production!A12 -> y_sgla_2 | B77: =[1]Production!B12 -> 22090.315 | C77: =[1]Production!C12 -> 22389.103 | D77: =[1]Production!D12 -> 22713.53 | E77: =[1]Production!E12 -> 23056.031 | F77: =[1]Production!F12 -> 23427.732 | G77: =[1]Production!G12 -> 23831.661 | H77: =[1]Production!H12 -> 24260.914 | ... AK77: =[1]Production!AK12 -> 47945.779
A78: =[1]Production!A14 -> y_spap_2 | B78: =[1]Production!B14 -> 16306.072 | C78: =[1]Production!C14 -> 16549.579 | D78: =[1]Production!D14 -> 16809.246 | E78: =[1]Production!E14 -> 17083.983 | F78: =[1]Production!F14 -> 17373.21 | G78: =[1]Production!G14 -> 17677.329 | H78: =[1]Production!H14 -> 17991.604 | ... AK78: =[1]Production!AK14 -> 32961.558
A79: =[1]Production!A16 -> y_sche_2 | B79: =[1]Production!B16 -> 86967.448 | C79: =[1]Production!C16 -> 88425.816 | D79: =[1]Production!D16 -> 89928.191 | E79: =[1]Production!E16 -> 91470.253 | F79: =[1]Production!F16 -> 93067.146 | G79: =[1]Production!G16 -> 94730.857 | H79: =[1]Production!H16 -> 96444.025 | ... AK79: =[1]Production!AK16 -> 174463.72
A80: =[1]Production!A18 -> y_spla_2 | B80: =[1]Production!B18 -> 29077.376 | C80: =[1]Production!C18 -> 29556.579 | D80: =[1]Production!D18 -> 30061.866 | E80: =[1]Production!E18 -> 30585.494 | F80: =[1]Production!F18 -> 31128.331 | G80: =[1]Production!G18 -> 31691.427 | H80: =[1]Production!H18 -> 32269.634 | ... AK80: =[1]Production!AK18 -> 61996.734
A81: =[1]Production!A20 -> y_smet_2 | B81: =[1]Production!B20 -> 80205.786 | C81: =[1]Production!C20 -> 81478.597 | D81: =[1]Production!D20 -> 82835.665 | E81: =[1]Production!E20 -> 84232.809 | F81: =[1]Production!F20 -> 85692.454 | G81: =[1]Production!G20 -> 87221.803 | H81: =[1]Production!H20 -> 88807.281 | ... AK81: =[1]Production!AK20 -> 170436.04
A82: =[1]Production!A22 -> y_sigo_2 | B82: =[1]Production!B22 -> 81062.007 | C82: =[1]Production!C22 -> 82774.904 | D82: =[1]Production!D22 -> 84492.299 | E82: =[1]Production!E22 -> 86215.622 | F82: =[1]Production!F22 -> 87963.547 | G82: =[1]Production!G22 -> 89744.779 | H82: =[1]Production!H22 -> 91556.133 | ... AK82: =[1]Production!AK22 -> 186895.21
A83: =[1]Production!A24 -> y_scgo_2 | B83: =[1]Production!B24 -> 104630.73 | C83: =[1]Production!C24 -> 106133.22 | D83: =[1]Production!D24 -> 107824.58 | E83: =[1]Production!E24 -> 109658.88 | F83: =[1]Production!F24 -> 111606.26 | G83: =[1]Production!G24 -> 113651.99 | H83: =[1]Production!H24 -> 115755.51 | ... AK83: =[1]Production!AK24 -> 224955.91
A84: =[1]Production!A26 -> y_scon_2 | B84: =[1]Production!B26 -> 271138.58 | C84: =[1]Production!C26 -> 274967.02 | D84: =[1]Production!D26 -> 279382.17 | E84: =[1]Production!E26 -> 284317.64 | F84: =[1]Production!F26 -> 289733.67 | G84: =[1]Production!G26 -> 295571.53 | H84: =[1]Production!H26 -> 301703.52 | ... AK84: =[1]Production!AK26 -> 786277.91
A85: =[1]Production!A28 -> y_srai_2 | B85: =[1]Production!B28 -> 6786.9645 | C85: =[1]Production!C28 -> 6873.2953 | D85: =[1]Production!D28 -> 6964.7379 | E85: =[1]Production!E28 -> 7061.1511 | F85: =[1]Production!F28 -> 7163.1549 | G85: =[1]Production!G28 -> 7270.5885 | H85: =[1]Production!H28 -> 7380.4635 | ... AK85: =[1]Production!AK28 -> 12594.859
A86: =[1]Production!A30 -> y_sroa_2 | B86: =[1]Production!B30 -> 78079.916 | C86: =[1]Production!C30 -> 79073.099 | D86: =[1]Production!D30 -> 80125.091 | E86: =[1]Production!E30 -> 81234.266 | F86: =[1]Production!F30 -> 82407.758 | G86: =[1]Production!G30 -> 83643.716 | H86: =[1]Production!H30 -> 84907.762 | ... AK86: =[1]Production!AK30 -> 144896.23
A87: =[1]Production!A32 -> y_swat_2 | B87: =[1]Production!B32 -> 15431.507 | C87: =[1]Production!C32 -> 15775.112 | D87: =[1]Production!D32 -> 16107.435 | E87: =[1]Production!E32 -> 16430.096 | F87: =[1]Production!F32 -> 16755.655 | G87: =[1]Production!G32 -> 17089.178 | H87: =[1]Production!H32 -> 17430.601 | ... AK87: =[1]Production!AK32 -> 42415.221
A88: =[1]Production!A34 -> y_sair_2 | B88: =[1]Production!B34 -> 20625.001 | C88: =[1]Production!C34 -> 20975.099 | D88: =[1]Production!D34 -> 21335.75 | E88: =[1]Production!E34 -> 21687.633 | F88: =[1]Production!F34 -> 22066.981 | G88: =[1]Production!G34 -> 22487.226 | H88: =[1]Production!H34 -> 22939.954 | ... AK88: =[1]Production!AK34 -> 50039.387
A89: =[1]Production!A36 -> y_spri_2 | B89: =[1]Production!B36 -> 2017586.2 | C89: =[1]Production!C36 -> 2046965.7 | D89: =[1]Production!D36 -> 2079754.8 | E89: =[1]Production!E36 -> 2115507.3 | F89: =[1]Production!F36 -> 2153350.3 | G89: =[1]Production!G36 -> 2193016.8 | H89: =[1]Production!H36 -> 2233483.5 | ... AK89: =[1]Production!AK36 -> 4242197.5
A90: =[1]Production!A38 -> y_spub_2 | B90: =[1]Production!B38 -> 540249.27 | C90: =[1]Production!C38 -> 547803.88 | D90: =[1]Production!D38 -> 556077.52 | E90: =[1]Production!E38 -> 564672.23 | F90: =[1]Production!F38 -> 573546.03 | G90: =[1]Production!G38 -> 582683.37 | H90: =[1]Production!H38 -> 591620.96 | ... AK90: =[1]Production!AK38 -> 985733.25
A91: =[1]Production!A40 -> y_smin_2 | B91: =[1]Production!B40 -> 4213.3121 | C91: =[1]Production!C40 -> 4259.8401 | D91: =[1]Production!D40 -> 4309.8684 | E91: =[1]Production!E40 -> 4362.0533 | F91: =[1]Production!F40 -> 4420.7809 | G91: =[1]Production!G40 -> 4485.6903 | H91: =[1]Production!H40 -> 4554.6078 | ... AK91: =[1]Production!AK40 -> 7507.8716
A92: =[1]Production!A42 -> y_soil_2 | B92: =[1]Production!B42 -> 35350.668 | C92: =[1]Production!C42 -> 35534.063 | D92: =[1]Production!D42 -> 35690.151 | E92: =[1]Production!E42 -> 35849.205 | F92: =[1]Production!F42 -> 36100.041 | G92: =[1]Production!G42 -> 36432.024 | H92: =[1]Production!H42 -> 36819.469 | ... AK92: =[1]Production!AK42 -> 24103.212
A93: =[1]Production!A44 -> y_sbfu_2 | B93: =[1]Production!B44 -> 3918.7917 | C93: =[1]Production!C44 -> 3928.3545 | D93: =[1]Production!D44 -> 3933.7011 | E93: =[1]Production!E44 -> 3941.5806 | F93: =[1]Production!F44 -> 3960.5454 | G93: =[1]Production!G44 -> 3989.4071 | H93: =[1]Production!H44 -> 4025.0942 | ... AK93: =[1]Production!AK44 -> 58816.201
A94: =[1]Production!A46 -> y_sgas_2 | B94: =[1]Production!B46 -> 398.34882 | C94: =[1]Production!C46 -> 399.26012 | D94: =[1]Production!D46 -> 400.14936 | E94: =[1]Production!E46 -> 400.53842 | F94: =[1]Production!F46 -> 402.56907 | G94: =[1]Production!G46 -> 405.70843 | H94: =[1]Production!H46 -> 409.80558 | ... AK94: =[1]Production!AK46 -> 33.564906
A95: =[1]Production!A48 -> y_sbga_2 | B95: =[1]Production!B48 -> 559.21752 | C95: =[1]Production!C48 -> 560.49684 | D95: =[1]Production!D48 -> 561.7452 | E95: =[1]Production!E48 -> 562.29138 | F95: =[1]Production!F48 -> 565.14208 | G95: =[1]Production!G48 -> 569.54924 | H95: =[1]Production!H48 -> 575.30097 | ... AK95: =[1]Production!AK48 -> 4393.4448
A96: =[1]Production!A50 -> y_senu_2 | B96: =[1]Production!B50 -> 46402.332 | C96: =[1]Production!C50 -> 46941.155 | D96: =[1]Production!D50 -> 47396.593 | E96: =[1]Production!E50 -> 47883.634 | F96: =[1]Production!F50 -> 48288.074 | G96: =[1]Production!G50 -> 48690.218 | H96: =[1]Production!H50 -> 49110.87 | ... AK96: =[1]Production!AK50 -> 158939.89
A97: =[1]Production!A52 -> y_seoi_2 | B97: =[1]Production!B52 -> 924.79196 | C97: =[1]Production!C52 -> 935.53064 | D97: =[1]Production!D52 -> 944.60744 | E97: =[1]Production!E52 -> 954.3141 | F97: =[1]Production!F52 -> 962.37454 | G97: =[1]Production!G52 -> 970.38922 | H97: =[1]Production!H52 -> 978.77274 | ... AK97: =[1]Production!AK52 -> 536.12889
A98: =[1]Production!A54 -> y_sega_2 | B98: =[1]Production!B54 -> 1343.8781 | C98: =[1]Production!C54 -> 1359.4832 | D98: =[1]Production!D54 -> 1372.6733 | E98: =[1]Production!E54 -> 1386.7787 | F98: =[1]Production!F54 -> 1398.4919 | G98: =[1]Production!G54 -> 1410.1385 | H98: =[1]Production!H54 -> 1422.3212 | ... AK98: =[1]Production!AK54 -> 268.06445
A99: =[1]Production!A56 -> y_seco_2 | B99: =[1]Production!B56 -> 1220.9208 | C99: =[1]Production!C56 -> 1235.0982 | D99: =[1]Production!D56 -> 1247.0815 | E99: =[1]Production!E56 -> 1259.8963 | F99: =[1]Production!F56 -> 1270.5378 | G99: =[1]Production!G56 -> 1281.1189 | H99: =[1]Production!H56 -> 1292.1869 | ... AK99: =[1]Production!AK56 -> 268.06445
A100: =[1]Production!A58 -> y_sewi_2 | B100: =[1]Production!B58 -> 2402.7509 | C100: =[1]Production!C58 -> 2430.6479 | D100: =[1]Production!D58 -> 2454.2308 | E100: =[1]Production!E58 -> 2479.4501 | F100: =[1]Production!F58 -> 2500.3923 | G100: =[1]Production!G58 -> 2521.2157 | H100: =[1]Production!H58 -> 2542.9973 | ... AK100: =[1]Production!AK58 -> 144754.8
A101: =[1]Production!A60 -> y_seso_2 | B101: =[1]Production!B60 -> 873.49172 | C101: =[1]Production!C60 -> 883.63471 | D101: =[1]Production!D60 -> 892.208 | E101: =[1]Production!E60 -> 901.37621 | F101: =[1]Production!F60 -> 908.98952 | G101: =[1]Production!G60 -> 916.55961 | H101: =[1]Production!H60 -> 924.47808 | ... AK101: =[1]Production!AK60 -> 145402.08
A102: =[1]Production!A62 -> y_sehy_2 | B102: =[1]Production!B62 -> 6724.2714 | C102: =[1]Production!C62 -> 6802.3537 | D102: =[1]Production!D62 -> 6868.3522 | E102: =[1]Production!E62 -> 6938.9305 | F102: =[1]Production!F62 -> 6997.5388 | G102: =[1]Production!G62 -> 7055.8145 | H102: =[1]Production!H62 -> 7116.7721 | ... AK102: =[1]Production!AK62 -> 52711.405
A103: =[1]Production!A64 -> y_sech_2 | B103: =[1]Production!B64 -> 7911.8534 | C103: =[1]Production!C64 -> 7995.6778 | D103: =[1]Production!D64 -> 8071.2286 | E103: =[1]Production!E64 -> 8147.802 | F103: =[1]Production!F64 -> 8216.621 | G103: =[1]Production!G64 -> 8289.4713 | H103: =[1]Production!H64 -> 8364.9224 | ... AK103: =[1]Production!AK64 -> 38984.616
A104: =[1]Production!A66 -> y_seot_2 | B104: =[1]Production!B66 -> 109.8413 | C104: =[1]Production!C66 -> 111.11678 | D104: =[1]Production!D66 -> 112.19487 | E104: =[1]Production!E66 -> 113.34777 | F104: =[1]Production!F66 -> 114.30514 | G104: =[1]Production!G66 -> 115.25707 | H104: =[1]Production!H66 -> 116.25282 | ... AK104: =[1]Production!AK66 -> 268.06445
A105: =[1]Results!E3 -> AUTO_2 | B105: =[1]Results!F3 -> 32317.941 | C105: =[1]Results!G3 -> 31911.217 | D105: =[1]Results!H3 -> 31732.935 | E105: =[1]Results!I3 -> 31702.286 | F105: =[1]Results!J3 -> 31792.126 | G105: =[1]Results!K3 -> 31964.155 | H105: =[1]Results!L3 -> 32183.571 | ... AK105: =[1]Results!AO3 -> 43625.428
A106: =[1]Results!E4 -> AUTO_cfut_2 | B106: =[1]Results!F4 -> 32271.24 | C106: =[1]Results!G4 -> 31846.407 | D106: =[1]Results!H4 -> 31648.242 | E106: =[1]Results!I4 -> 31596.228 | F106: =[1]Results!J4 -> 31663.113 | G106: =[1]Results!K4 -> 31810.955 | H106: =[1]Results!L4 -> 32005.277 | ... AK106: =[1]Results!AO4 -> 35733.333
A107: =[1]Results!E12 -> AUTO_cele_2 | B107: =[1]Results!F12 -> 44.765 | C107: =[1]Results!G12 -> 62.819188 | D107: =[1]Results!H12 -> 82.635226 | E107: =[1]Results!I12 -> 103.92645 | F107: =[1]Results!J12 -> 126.8031 | G107: =[1]Results!K12 -> 150.90795 | H107: =[1]Results!L12 -> 175.92151 | ... AK107: =[1]Results!AO12 -> 7888.5377
A108: =[1]Results!E20 -> AUTO_cgas_2 | B108: =[1]Results!F20 -> 1.936 | C108: =[1]Results!G20 -> 1.990293 | D108: =[1]Results!H20 -> 2.0574577 | E108: =[1]Results!I20 -> 2.1314073 | F108: =[1]Results!J20 -> 2.2103839 | G108: =[1]Results!K20 -> 2.2916631 | H108: =[1]Results!L20 -> 2.3727336 | ... AK108: =[1]Results!AO20 -> 3.5575264
A109: AUTO_CA_2 | B109: =[2]Données!C332 -> 8263.1971 | C109: =[2]Données!D332 -> 8194.9442 | D109: =[2]Données!E332 -> 8188.9422 | E109: =[2]Données!F332 -> 8224.0385 | F109: =[2]Données!G332 -> 8293.3352 | G109: =[2]Données!H332 -> 8386.3478 | H109: =[2]Données!I332 -> 8493.4775 | I109: =[2]Données!J332 -> 8582.164 | ... AK109: =[2]Données!AL332 -> 13320.719
A110: AUTO_CB_2 | B110: =[2]Données!C333 -> 6787.4106 | C110: =[2]Données!D333 -> 6656.6716 | D110: =[2]Données!E333 -> 6574.7958 | E110: =[2]Données!F333 -> 6526.4877 | F110: =[2]Données!G333 -> 6506.4446 | G110: =[2]Données!H333 -> 6507.1004 | H110: =[2]Données!I333 -> 6521.4842 | I110: =[2]Données!J333 -> 6526.5067 | ... AK110: =[2]Données!AL333 -> 8760.3935
A111: AUTO_CC_2 | B111: =[2]Données!C334 -> 4165.6835 | C111: =[2]Données!D334 -> 4060.838 | D111: =[2]Données!E334 -> 3984.0057 | E111: =[2]Données!F334 -> 3926.2141 | F111: =[2]Données!G334 -> 3884.1704 | G111: =[2]Données!H334 -> 3853.5994 | H111: =[2]Données!I334 -> 3830.5837 | I111: =[2]Données!J334 -> 3802.3696 | ... AK111: =[2]Données!AL334 -> 3868.2859
A112: AUTO_CD_2 | B112: =[2]Données!C335 -> 2507.3525 | C112: =[2]Données!D335 -> 2446.6033 | D112: =[2]Données!E335 -> 2401.9268 | E112: =[2]Données!F335 -> 2367.677 | F112: =[2]Données!G335 -> 2341.7745 | G112: =[2]Données!H335 -> 2321.6754 | H112: =[2]Données!I335 -> 2305.0613 | I112: =[2]Données!J335 -> 2284.2222 | ... AK112: =[2]Données!AL335 -> 1937.3995
A113: AUTO_CE_2 | B113: =[2]Données!C336 -> 1245.4666 | C113: =[2]Données!D336 -> 1212.6424 | D113: =[2]Données!E336 -> 1186.4603 | E113: =[2]Données!F336 -> 1163.9737 | F113: =[2]Données!G336 -> 1144.0787 | G113: =[2]Données!H336 -> 1125.642 | H113: =[2]Données!I336 -> 1107.6801 | I113: =[2]Données!J336 -> 1086.8322 | ... AK113: =[2]Données!AL336 -> 499.9062
A114: AUTO_CF_2 | B114: =[2]Données!C337 -> 2242.8617 | C114: =[2]Données!D337 -> 2187.2078 | D114: =[2]Données!E337 -> 2141.3531 | E114: =[2]Données!F337 -> 2099.5926 | F114: =[2]Données!G337 -> 2059.8869 | G114: =[2]Données!H337 -> 2020.4312 | H114: =[2]Données!I337 -> 1979.7546 | I114: =[2]Données!J337 -> 1932.2908 | ... AK114: =[2]Données!AL337 -> 594.15754
A115: AUTO_CG_2 | B115: =[2]Données!C338 -> 0 | C115: =[2]Données!D338 -> 0 | D115: =[2]Données!E338 -> 0 | E115: =[2]Données!F338 -> 0 | F115: =[2]Données!G338 -> 0 | G115: =[2]Données!H338 -> 0 | H115: =[2]Données!I338 -> 0 | I115: =[2]Données!J338 -> 0 | ... AK115: =[2]Données!AL338 -> 0
A116: =[1]Results!E103 -> BUIL_2 | B116: =[1]Results!F103 -> 2457.4699 | C116: =[1]Results!G103 -> 2465.7264 | D116: =[1]Results!H103 -> 2476.5081 | E116: =[1]Results!I103 -> 2487.337 | F116: =[1]Results!J103 -> 2498.2132 | G116: =[1]Results!K103 -> 2509.137 | H116: =[1]Results!L103 -> 2517.7068 | ... AK116: =[1]Results!AO103 -> 2738.7438
A117: =[1]Results!E104 -> BUIL_ca_2 | B117: =[1]Results!F104 -> 3.4765421 | C117: =[1]Results!G104 -> 8.5373484 | D117: =[1]Results!H104 -> 14.692051 | E117: =[1]Results!I104 -> 21.391994 | F117: =[1]Results!J104 -> 28.503846 | G117: =[1]Results!K104 -> 35.432174 | H117: =[1]Results!L104 -> 41.982732 | ... AK117: =[1]Results!AO104 -> 631.91073
A118: =[1]Results!E105 -> BUIL_cb_2 | B118: =[1]Results!F105 -> 68.804763 | C118: =[1]Results!G105 -> 75.130067 | D118: =[1]Results!H105 -> 80.746061 | E118: =[1]Results!I105 -> 85.701618 | F118: =[1]Results!J105 -> 90.337253 | G118: =[1]Results!K105 -> 94.778736 | H118: =[1]Results!L105 -> 98.501494 | ... AK118: =[1]Results!AO105 -> 213.78586
A119: =[1]Results!E106 -> BUIL_cc_2 | B119: =[1]Results!F106 -> 408.2804 | C119: =[1]Results!G106 -> 422.13434 | D119: =[1]Results!H106 -> 435.39237 | E119: =[1]Results!I106 -> 447.44191 | F119: =[1]Results!J106 -> 458.88957 | G119: =[1]Results!K106 -> 469.9427 | H119: =[1]Results!L106 -> 479.0531 | ... AK119: =[1]Results!AO106 -> 676.33415
A120: =[1]Results!E107 -> BUIL_cd_2 | B120: =[1]Results!F107 -> 954.38156 | C120: =[1]Results!G107 -> 951.24267 | D120: =[1]Results!H107 -> 950.15263 | E120: =[1]Results!I107 -> 950.18991 | F120: =[1]Results!J107 -> 950.96815 | G120: =[1]Results!K107 -> 951.42001 | H120: =[1]Results!L107 -> 951.35751 | ... AK120: =[1]Results!AO107 -> 1096.5925
A121: =[1]Results!E108 -> BUIL_ce_2 | B121: =[1]Results!F108 -> 878.8 | C121: =[1]Results!G108 -> 866.98909 | D121: =[1]Results!H108 -> 855.83698 | E121: =[1]Results!I108 -> 844.89794 | F121: =[1]Results!J108 -> 833.74053 | G121: =[1]Results!K108 -> 823.70474 | H121: =[1]Results!L108 -> 814.84197 | ... AK121: =[1]Results!AO108 -> 35.880311
A122: =[1]Results!E109 -> BUIL_cf_2 | B122: =[1]Results!F109 -> 139.85209 | C122: =[1]Results!G109 -> 137.9677 | D122: =[1]Results!H109 -> 136.10652 | E122: =[1]Results!I109 -> 134.27017 | F122: =[1]Results!J109 -> 132.46281 | G122: =[1]Results!K109 -> 130.67505 | H122: =[1]Results!L109 -> 128.90885 | ... AK122: =[1]Results!AO109 -> 83.246599
A123: =[1]Results!E110 -> BUIL_cg_2 | B123: =[1]Results!F110 -> 3.8745671 | C123: =[1]Results!G110 -> 3.7251598 | D123: =[1]Results!H110 -> 3.5815059 | E123: =[1]Results!I110 -> 3.4434436 | F123: =[1]Results!J110 -> 3.3110557 | G123: =[1]Results!K110 -> 3.1835898 | H123: =[1]Results!L110 -> 3.0611305 | ... AK123: =[1]Results!AO110 -> 0.99365589
A124: =[1]Results!E205 -> YG_toe_2 | B124: =[1]Results!F205 -> 148.56083 | C124: =[1]Results!G205 -> 149.66963 | D124: =[1]Results!H205 -> 150.66914 | E124: =[1]Results!I205 -> 151.72017 | F124: =[1]Results!J205 -> 152.92185 | G124: =[1]Results!K205 -> 154.31153 | H124: =[1]Results!L205 -> 155.83472 | ... AK124: =[1]Results!AO205 -> 527.58747
A125: =[1]Results!E281 -> CF_toe_2 | B125: =[1]Results!F281 -> 161.69428 | C125: =[1]Results!G281 -> 162.00032 | D125: =[1]Results!H281 -> 162.18906 | E125: =[1]Results!I281 -> 162.30169 | F125: =[1]Results!J281 -> 162.93754 | G125: =[1]Results!K281 -> 164.00585 | H125: =[1]Results!L281 -> 165.3825 | ... AK125: =[1]Results!AO281 -> 236.28394
